Workbook
Name A_ALL_ANF: #REF!
Name E_ALL_ANF: #REF!
Name L_ALL_ANF: #REF!
Name V_ALL_ANF: #REF!

Sheet Cover
F3: Abercrombie & Fitch (ANF)
F4: COMPANY MODEL
B9: Sources: Company data, Goldman Sachs Global Investment Research
B11: Date: September 08, 2026
B13: Jon Keypour
B14: Vice President
B15: tel: 212-934-0334
B16: jon.keypour@gs.com
B18: Kareem Elbadrawi
B19: Analyst
B20: tel: 212-902-7320
B21: kareem.elbadrawi@gs.com

Sheet Rev Driver
A1: ANF Rev. Driver
A3: Period | B3: FY15 | C3: FY16 | D3: FY17 | E3: FY18 | F3: FY19 | G3: 1Q20 | H3: 2Q20 | I3: 3Q20 | J3: 4Q20 | K3: FY20 | L3: 1Q21 | M3: 2Q21 | N3: 3Q21 | O3: 4Q21 | P3: FY21 | Q3: 1Q22 | R3: 2Q22 | S3: 3Q22 | T3: 4Q22 | U3: FY22 | V3: 1Q23 | W3: 2Q23 | X3: 3Q23 | Y3: 4Q23 | Z3: FY23 | AA3: 1Q24 | AB3: 2Q24 | AC3: 3Q24 | AD3: 4Q24 | AE3: FY24 | AF3: 1Q25 | AG3: 2Q25 | AH3: 3Q25 | AI3: 4Q25 | AJ3: FY25 | AK3: 1Q26 | AL3: 2Q26 | AM3: 3Q26E | AN3: 4Q26E | AO3: FY26E | AP3: 1Q27E | AQ3: 2Q27E | AR3: 3Q27E | AS3: 4Q27E | AT3: FY27E | AU3: 1Q28E | AV3: 2Q28E | AW3: 3Q28E | AX3: 4Q28E | AY3: FY28E
A4: End Date | B4: 42399 | C4: 42763 | D4: 43134 | E4: 43498 | F4: 43862 | G4: 43953 | H4: 44044 | I4: 44135 | J4: 44226 | K4: =J4 -> 44226 | L4: 44317 | M4: 44408 | N4: 44500 | O4: 44590 | P4: =O4 -> 44590 | Q4: 44681 | R4: 44772 | S4: 44863 | T4: 44954 | U4: =T4 -> 44954 | V4: 45045 | W4: 45136 | X4: 45227 | Y4: 45325 | Z4: =Y4 -> 45325 | AA4: 45416 | AB4: 45507 | AC4: 45598 | AD4: 45689 | AE4: =AD4 -> 45689 | AF4: 45780 | AG4: =AF4+AG5*7 -> 45871 | AH4: =AH5*7+AG4 -> 45962 | AI4: =AI5*7+AH4 -> 46053 | AJ4: =AI4 -> 46053 | AK4: =AK5*7+AJ4 -> 46144 | AL4: =AL5*7+AK4 -> 46235 | AM4: =AM5*7+AL4 -> 46326 | AN4: =AN5*7+AM4 -> 46417 | AO4: =AN4 -> 46417 | AP4: =AP5*7+AO4 -> 46508 | AQ4: =AQ5*7+AP4 -> 46599 | AR4: =AR5*7+AQ4 -> 46690 | AS4: =AS5*7+AR4 -> 46781 | AT4: =AS4 -> 46781 | AU4: =AU5*7+AT4 -> 46872 | AV4: =AV5*7+AU4 -> 46963 | AW4: =AW5*7+AV4 -> 47054 | AX4: =AX5*7+AW4 -> 47145 | AY4: =AX4 -> 47145
A5: Wks. In Q | B5: 52 | C5: 52 | D5: 53 | E5: 52 | F5: 52 | G5: 13 | H5: 13 | I5: 13 | J5: 13 | K5: =SUM(G5:J5) -> 52 | L5: 13 | M5: 13 | N5: 13 | O5: 13 | P5: =SUM(L5:O5) -> 52 | Q5: 13 | R5: 13 | S5: 13 | T5: 13 | U5: =SUM(Q5:T5) -> 52 | V5: 13 | W5: 13 | X5: 13 | Y5: 14 | Z5: =SUM(V5:Y5) -> 53 | AA5: 13 | AB5: 13 | AC5: 13 | AD5: 13 | AE5: =SUM(AA5:AD5) -> 52 | AF5: 13 | AG5: 13 | AH5: 13 | AI5: 13 | AJ5: =SUM(AF5:AI5) -> 52 | AK5: 13 | AL5: 13 | AM5: 13 | AN5: 13 | AO5: =SUM(AK5:AN5) -> 52 | AP5: 13 | AQ5: 13 | AR5: 13 | AS5: 13 | AT5: =SUM(AP5:AS5) -> 52 | AU5: 13 | AV5: 13 | AW5: 13 | AX5: 13 | AY5: =SUM(AU5:AX5) -> 52
A6: Segments by Brand | AT6: x | AY6: x
A7: Abercrombie | B7: 1640992 | C7: 1487024 | D7: 1454092 | E7: 1437571 | F7: 1464559 | G7: 212347 | H7: 269080 | I7: 342988 | J7: 466620 | K7: =SUM(G7:J7) -> 1291035 | L7: 338997 | M7: 350367 | N7: 382849 | O7: 492576 | P7: =SUM(L7:O7) -> 1564789 | Q7: 383928 | R7: 368157 | S7: 422332 | T7: 560438 | U7: =SUM(Q7:T7) -> 1734855 | V7: 436044 | W7: 462711 | X7: 547728 | Y7: 755203 | Z7: =SUM(V7:Y7) -> 2201686 | AA7: 571513 | AB7: 582416 | AC7: 629835 | AD7: 772670 | AE7: =SUM(AA7:AD7) -> 2556434 | AF7: 547947 | AG7: 551868 | AH7: 617345 | AI7: 806502 | AJ7: =SUM(AF7:AI7) -> 2523662 | AK7: 564719 | AL7: 596808 | AM7: =AH7*(1+AM14) -> 666732.6 | AN7: =AI7*(1+AN14) -> 862957.14 | AO7: =SUM(AK7:AN7) -> 2691216.7 | AP7: =AK7*(1+AP14) -> 592954.95 | AQ7: =AL7*(1+AQ14) -> 620680.32 | AR7: =AM7*(1+AR14) -> 693401.9 | AS7: =AN7*(1+AS14) -> 897475.43 | AT7: =SUM(AP7:AS7) -> 2804512.6 | AU7: =AP7*(1+AU14) -> 607778.82 | AV7: =AQ7*(1+AV14) -> 636197.33 | AW7: =AR7*(1+AW14) -> 710736.95 | AX7: =AS7*(1+AX14) -> 919912.31 | AY7: =SUM(AU7:AX7) -> 2874625.4
A8: Hollister | B8: 1877688 | C8: 1839716 | D8: 2038598 | E8: 2152538 | F8: 2158514 | G8: 273012 | H8: 429248 | I8: 476665 | J8: 655424 | K8: =SUM(G8:J8) -> 1834349 | L8: 442408 | M8: 514483 | N8: 522311 | O8: 668777 | P8: =SUM(L8:O8) -> 2147979 | Q8: 428834 | R8: 436934 | S8: 457752 | T8: 639376 | U8: =SUM(Q8:T8) -> 1962896 | V8: 399950 | W8: 472634 | X8: 508703 | Y8: 697704 | Z8: =SUM(V8:Y8) -> 2078991 | AA8: 449217 | AB8: 551558 | AC8: 579131 | AD8: 812247 | AE8: =SUM(AA8:AD8) -> 2392153 | AF8: 549364 | AG8: 656692 | AH8: 673274 | AI8: 863300 | AJ8: =SUM(AF8:AI8) -> 2742630 | AK8: 549102 | AL8: 669881 | AM8: =AH8*(1+AM15) -> 700204.96 | AN8: =AI8*(1+AN15) -> 923731 | AO8: =SUM(AK8:AN8) -> 2842919 | AP8: =AK8*(1+AP15) -> 571066.08 | AQ8: =AL8*(1+AQ15) -> 696676.24 | AR8: =AM8*(1+AR15) -> 721211.11 | AS8: =AN8*(1+AS15) -> 951442.93 | AT8: =SUM(AP8:AS8) -> 2940396.4 | AU8: =AP8*(1+AU15) -> 588198.06 | AV8: =AQ8*(1+AV15) -> 717576.53 | AW8: =AR8*(1+AW15) -> 746453.5 | AX8: =AS8*(1+AX15) -> 984743.43 | AY8: =SUM(AU8:AX8) -> 3036971.5
A9: Total | B9: =SUM(B7:B8) -> 3518680 | C9: =SUM(C7:C8) -> 3326740 | D9: =SUM(D7:D8) -> 3492690 | E9: =SUM(E7:E8) -> 3590109 | F9: =SUM(F7:F8) -> 3623073 | G9: =SUM(G7:G8) -> 485359 | H9: =SUM(H7:H8) -> 698328 | I9: =SUM(I7:I8) -> 819653 | J9: =SUM(J7:J8) -> 1122044 | K9: =IF(SUM(K7:K8)=SUM(G9:J9),SUM(K7:K8),"ERR") -> 3125384 | L9: =SUM(L7:L8) -> 781405 | M9: =SUM(M7:M8) -> 864850 | N9: =SUM(N7:N8) -> 905160 | O9: =SUM(O7:O8) -> 1161353 | P9: =IF(SUM(P7:P8)=SUM(L9:O9),SUM(P7:P8),"ERR") -> 3712768 | Q9: =SUM(Q7:Q8) -> 812762 | R9: =SUM(R7:R8) -> 805091 | S9: =SUM(S7:S8) -> 880084 | T9: =SUM(T7:T8) -> 1199814 | U9: =IF(SUM(U7:U8)=SUM(Q9:T9),SUM(U7:U8),"ERR") -> 3697751 | V9: =SUM(V7:V8) -> 835994 | W9: =SUM(W7:W8) -> 935345 | X9: =SUM(X7:X8) -> 1056431 | Y9: =SUM(Y7:Y8) -> 1452907 | Z9: =IF(SUM(Z7:Z8)=SUM(V9:Y9),SUM(Z7:Z8),"ERR") -> 4280677 | AA9: =SUM(AA7:AA8) -> 1020730 | AB9: =SUM(AB7:AB8) -> 1133974 | AC9: =SUM(AC7:AC8) -> 1208966 | AD9: =SUM(AD7:AD8) -> 1584917 | AE9: =IF(SUM(AE7:AE8)=SUM(AA9:AD9),SUM(AE7:AE8),"ERR") -> 4948587 | AF9: =SUM(AF7:AF8) -> 1097311 | AG9: =SUM(AG7:AG8) -> 1208560 | AH9: =SUM(AH7:AH8) -> 1290619 | AI9: =SUM(AI7:AI8) -> 1669802 | AJ9: =IF(SUM(AJ7:AJ8)=SUM(AF9:AI9),SUM(AJ7:AJ8),"ERR") -> 5266292 | AK9: =SUM(AK7:AK8) -> 1113821 | AL9: =SUM(AL7:AL8) -> 1266689 | AM9: =SUM(AM7:AM8) -> 1366937.6 | AN9: =SUM(AN7:AN8) -> 1786688.1 | AO9: =IF(SUM(AO7:AO8)=SUM(AK9:AN9),SUM(AO7:AO8),"ERR") -> 5534135.7 | AP9: =SUM(AP7:AP8) -> 1164021 | AQ9: =SUM(AQ7:AQ8) -> 1317356.6 | AR9: =SUM(AR7:AR8) -> 1414613 | AS9: =SUM(AS7:AS8) -> 1848918.4 | AT9: =IF(SUM(AT7:AT8)=SUM(AP9:AS9),SUM(AT7:AT8),"ERR") -> 5744909 | AU9: =SUM(AU7:AU8) -> 1195976.9 | AV9: =SUM(AV7:AV8) -> 1353773.9 | AW9: =SUM(AW7:AW8) -> 1457190.4 | AX9: =SUM(AX7:AX8) -> 1904655.7 | AY9: =IF(SUM(AY7:AY8)=SUM(AU9:AX9),SUM(AY7:AY8),"ERR") -> 5911596.9
A10: Check | G10: =G9-G52 -> 0 | H10: =H9-H52 -> 0 | I10: =I9-I52 -> 0 | J10: =J9-J52 -> 0 | K10: =K9-K52 -> 0 | L10: =L9-L52 -> 0 | M10: =M9-M52 -> 0 | N10: =N9-N52 -> 0 | ... AH10: =AH9-AH52 -> 0
A12: Sales Drivers
A13: Net Sales
A14: Abercrombie | C14: =C7/B7-1 -> -0.093826173 | D14: =D7/C7-1 -> -0.022146246 | E14: =E7/D7-1 -> -0.01136173 | F14: =F7/E7-1 -> 0.018773334 | K14: =K7/F7-1 -> -0.11848208 | L14: =L7/G7-1 -> 0.59642943 | M14: =M7/H7-1 -> 0.30209231 | N14: =N7/I7-1 -> 0.11621689 | O14: =O7/J7-1 -> 0.055625563 | P14: =P7/K7-1 -> 0.21204228 | Q14: =Q7/L7-1 -> 0.132541 | R14: =R7/M7-1 -> 0.05077533 | ... AH14: =AH7/AC7-1 -> -0.019830591 | AI14: =AI19+AI29+AI34 -> 0.043522564 | AJ14: =AJ7/AE7-1 -> -0.01281942 | AK14: =AK7/AF7-1 -> 0.0306088 | AL14: =AL7/AG7-1 -> 0.081432516 | AM14: =AM19+AM29+AM34 -> 0.08 | AN14: =AN19+AN29+AN34 -> 0.07 | AO14: =AO7/AJ7-1 -> 0.066393495 | AP14: =AP19+AP29+AP34 -> 0.05 | AQ14: =AQ19+AQ29+AQ34 -> 0.04 | AR14: =AR19+AR29+AR34 -> 0.04 | AS14: =AS19+AS29+AS34 -> 0.04 | AT14: =AT7/AO7-1 -> 0.042098378 | AU14: =AU19+AU29+AU34 -> 0.025 | AV14: =AV19+AV29+AV34 -> 0.025 | AW14: =AW19+AW29+AW34 -> 0.025 | AX14: =AX19+AX29+AX34 -> 0.025 | AY14: =AY7/AT7-1 -> 0.025
A15: Hollister | C15: =C8/B8-1 -> -0.020222742 | D15: =D8/C8-1 -> 0.10810473 | E15: =E8/D8-1 -> 0.055891353 | F15: =F8/E8-1 -> 0.0027762576 | K15: =K8/F8-1 -> -0.15017971 | L15: =L8/G8-1 -> 0.6204709 | M15: =M8/H8-1 -> 0.19856819 | N15: =N8/I8-1 -> 0.095761174 | O15: =O8/J8-1 -> 0.020373071 | P15: =P8/K8-1 -> 0.17097619 | Q15: =Q8/L8-1 -> -0.030682085 | R15: =R8/M8-1 -> -0.1507319 | ... AH15: =AH8/AC8-1 -> 0.16255908 | AI15: =AI20+AI30+AI35 -> 0.062185869 | AJ15: =AJ8/AE8-1 -> 0.14651111 | AK15: =AK8/AF8-1 -> -0.00047691512 | AL15: =AL8/AG8-1 -> 0.020083997 | AM15: =AM20+AM30+AM35 -> 0.04 | AN15: =AN20+AN30+AN35 -> 0.07 | AO15: =AO8/AJ8-1 -> 0.036566712 | AP15: =AP20+AP30+AP35 -> 0.04 | AQ15: =AQ20+AQ30+AQ35 -> 0.04 | AR15: =AR20+AR30+AR35 -> 0.03 | AS15: =AS20+AS30+AS35 -> 0.03 | AT15: =AT8/AO8-1 -> 0.034287787 | AU15: =AU20+AU30+AU35 -> 0.03 | AV15: =AV20+AV30+AV35 -> 0.03 | AW15: =AW20+AW30+AW35 -> 0.035 | AX15: =AX20+AX30+AX35 -> 0.035 | AY15: =AY8/AT8-1 -> 0.032844266
A16: Total ANF | C16: =C9/B9-1 -> -0.054548865 | D16: =D9/C9-1 -> 0.04988367 | E16: =E9/D9-1 -> 0.027892255 | F16: =F9/E9-1 -> 0.0091818939 | K16: =K9/F9-1 -> -0.13736654 | L16: =L9/G9-1 -> 0.60995263 | M16: =M9/H9-1 -> 0.23845815 | N16: =N9/I9-1 -> 0.10432097 | O16: =O9/J9-1 -> 0.035033386 | P16: =P9/K9-1 -> 0.18793979 | Q16: =Q9/L9-1 -> 0.040128998 | R16: =R9/M9-1 -> -0.069097531 | ... AY16: =AY9/AT9-1 -> 0.029014903
A18: Comparable Sales
A19: Abercrombie | B19: -0.06 | C19: -0.11 | D19: 0.08 | E19: 0.01 | F19: 0.03 | V19: 0.14 | W19: 0.23 | X19: 0.26 | Y19: 0.28 | Z19: 0.23 | AA19: 0.29 | AB19: 0.21 | AC19: 0.11 | AD19: 0.05 | AE19: 0.15 | AF19: -0.1 | AG19: -0.11 | AH19: -0.07 | AI19: -0.01 | AJ19: -0.07 | AK19: 0 | AL19: 0.04 | AM19: 0.02 | AN19: 0.02 | AO19: =SUMPRODUCT(AK19:AN19,AF$43:AI$43) -> 0.020031074 | AP19: 0.02 | AQ19: 0.02 | AR19: 0.02 | AS19: 0.02 | AT19: =SUMPRODUCT(AP19:AS19,AK$43:AN$43) -> 0.02 | AU19: 0.015 | AV19: 0.015 | AW19: 0.015 | AX19: 0.015 | AY19: =SUMPRODUCT(AU19:AX19,AP$43:AS$43) -> 0.015
A20: Hollister | B20: 0 | C20: 0 | D20: -0.02 | E20: 0.05 | F20: -0.01 | V20: -0.06 | W20: 0.05 | X20: 0.07 | Y20: 0.06 | Z20: 0.04 | AA20: 0.13 | AB20: 0.15 | AC20: 0.21 | AD20: 0.24 | AE20: 0.19 | AF20: 0.23 | AG20: 0.19 | AH20: 0.15 | AI20: 0.03 | AJ20: 0.13 | AK20: -0.02 | AL20: -0.03 | AM20: -0.01 | AN20: 0.03 | AO20: =SUMPRODUCT(AK20:AN20,AF$44:AI$44) -> -0.0042009969 | AP20: 0.03 | AQ20: 0.03 | AR20: 0.02 | AS20: 0.02 | AT20: =SUMPRODUCT(AP20:AS20,AK$44:AN$44) -> 0.024287787 | AU20: 0.02 | AV20: 0.02 | AW20: 0.025 | AX20: 0.025 | AY20: =SUMPRODUCT(AU20:AX20,AP$44:AS$44) -> 0.022844266
A21: Total ANF | B21: -0.03 | C21: -0.05 | D21: 0.03 | E21: 0.03 | F21: 0.01 | V21: 0.03 | W21: 0.13 | X21: 0.16 | Y21: 0.16 | Z21: 0.13 | AA21: 0.21 | AB21: 0.18 | AC21: 0.16 | AD21: 0.14 | AE21: 0.17 | AF21: 0.04 | AG21: 0.03 | AH21: 0.03 | AI21: 0.01 | AJ21: 0.03 | AK21: -0.01 | AL21: 0 | AM21: =AM19*AH$39+AM20*AH$40 -> 0.0043499747 | AN21: =AN19*AI$39+AN20*AI$40 -> 0.025170074 | AO21: =SUMPRODUCT(AK21:AN21,AF$45:AI$45) -> 0.0069631707 | AP21: =AP19*AK$39+AP20*AK$40 -> 0.024929894 | AQ21: =AQ19*AL$39+AQ20*AL$40 -> 0.025288441 | AR21: =AR19*AM$39+AR20*AM$40 -> 0.02 | AS21: =AS19*AN$39+AS20*AN$40 -> 0.02 | AT21: =SUMPRODUCT(AP21:AS21,AK$45:AN$45) -> 0.022202662 | AU21: =AU19*AP$39+AU20*AP$40 -> 0.017452989 | AV21: =AV19*AQ$39+AV20*AQ$40 -> 0.01764422 | AW21: =AW19*AR$39+AW20*AR$40 -> 0.020098293 | AX21: =AX19*AS$39+AX20*AS$40 -> 0.020145943 | AY21: =SUMPRODUCT(AU21:AX21,AP$45:AS$45) -> 0.019014903
A23: FX $ Impact | AF23: Assumed | AG23: Assumed | AH23: Assumed | AI23: Assumed | AK23: Assumed | AL23: Assumed
A24: Abercrombie | S24: -8120 | T24: -7715 | U24: -24948 | V24: -3414 | W24: -71 | X24: 1393 | Y24: 843 | Z24: =SUM(V24:Y24) -> -1249 | AA24: -572 | AB24: -1125 | AC24: 1643 | AD24: -2370 | AE24: =SUM(AA24:AD24) -> -2424 | AF24: =1/3*AF26 -> -69.333333 | AG24: =AG26*1/3 -> 3569 | AH24: =AH26*1/3 -> 1944.6667 | AI24: =AI26*1/3 -> 5609.6667 | AJ24: =SUM(AF24:AI24) -> 11054 | AK24: =1/3*AK26 -> 3673 | AL24: =AL26*1/3 -> 74.333333 | AM24: =AM29*AH7 -> 0 | AN24: =AN29*AI7 -> 0 | AO24: =SUM(AK24:AN24) -> 3747.3333 | AP24: =AP29*AK7 -> 0 | AQ24: =AQ29*AL7 -> 0 | AR24: =AR29*AM7 -> 0 | AS24: =AS29*AN7 -> 0 | AT24: =SUM(AP24:AS24) -> 0 | AU24: =AU29*AP7 -> 0 | AV24: =AV29*AQ7 -> 0 | AW24: =AW29*AR7 -> 0 | AX24: =AX29*AS7 -> 0 | AY24: =SUM(AU24:AX24) -> 0
A25: Hollister | S25: -18740 | T25: -15575 | U25: -56855 | V25: -5183 | W25: 2944 | X25: 5544 | Y25: 4444 | Z25: =SUM(V25:Y25) -> 7749 | AA25: 21 | AB25: -1245 | AC25: 3646 | AD25: -3768 | AE25: =SUM(AA25:AD25) -> -1346 | AF25: =AF26-AF24 -> -138.66667 | AG25: =AG26-AG24 -> 7138 | AH25: =AH26-AH24 -> 3889.3333 | AI25: =AI26-AI24 -> 11219.333 | AJ25: =SUM(AF25:AI25) -> 22108 | AK25: =AK26-AK24 -> 7346 | AL25: =AL26-AL24 -> 148.66667 | AM25: =AM30*AH8 -> 0 | AN25: =AN30*AI8 -> 4316.5 | AO25: =SUM(AK25:AN25) -> 11811.167 | AP25: =AP30*AK8 -> 0 | AQ25: =AQ30*AL8 -> 0 | AR25: =AR30*AM8 -> 0 | AS25: =AS30*AN8 -> 0 | AT25: =SUM(AP25:AS25) -> 0 | AU25: =AU30*AP8 -> 0 | AV25: =AV30*AQ8 -> 0 | AW25: =AW30*AR8 -> 0 | AX25: =AX30*AS8 -> 0 | AY25: =SUM(AU25:AX25) -> 0
A26: Total ANF | C26: 20000 | E26: -37000 | R26: -23124 | S26: =SUM(S24:S25) -> -26860 | T26: =SUM(T24:T25) -> -23290 | U26: =SUM(U24:U25) -> -81803 | V26: =SUM(V24:V25) -> -8597 | W26: =SUM(W24:W25) -> 2873 | X26: =SUM(X24:X25) -> 6937 | Y26: =SUM(Y24:Y25) -> 5287 | Z26: =SUM(V26:Y26) -> 6500 | AA26: =SUM(AA24:AA25) -> -551 | AB26: =SUM(AB24:AB25) -> -2370 | AC26: =SUM(AC24:AC25) -> 5289 | AD26: =SUM(AD24:AD25) -> -6138 | AE26: =SUM(AA26:AD26) -> -3770 | AF26: -208 | AG26: 10707 | AH26: 5834 | AI26: 16829 | AJ26: =SUM(AF26:AI26) -> 33162 | AK26: 11019 | AL26: 223 | AM26: =SUM(AM24:AM25) -> 0 | AN26: =SUM(AN24:AN25) -> 4316.5 | AO26: =SUM(AK26:AN26) -> 15558.5 | AP26: =SUM(AP24:AP25) -> 0 | AQ26: =SUM(AQ24:AQ25) -> 0 | AR26: =SUM(AR24:AR25) -> 0 | AS26: =SUM(AS24:AS25) -> 0 | AT26: =SUM(AP26:AS26) -> 0 | AU26: =SUM(AU24:AU25) -> 0 | AV26: =SUM(AV24:AV25) -> 0 | AW26: =SUM(AW24:AW25) -> 0 | AX26: =SUM(AX24:AX25) -> 0 | AY26: =SUM(AU26:AX26) -> 0
A28: FX % Impact
A29: Abercrombie | S29: =S24/N7 -> -0.021209406 | T29: =T24/O7 -> -0.015662558 | U29: =U24/P7 -> -0.015943364 | V29: =V24/Q7 -> -0.0088922923 | W29: =W24/R7 -> -0.00019285251 | X29: =X24/S7 -> 0.003298353 | Y29: =Y24/T7 -> 0.0015041807 | Z29: =Z24/U7 -> -0.00071994489 | ... AL29: =AL24/AG7 -> 0.00013469405 | AM29: 0 | AN29: 0 | AO29: =SUMPRODUCT(AK29:AN29,AF$43:AI$43) -> 0.0014848792 | AP29: 0 | AQ29: 0 | AR29: 0 | AS29: 0 | AT29: =SUMPRODUCT(AP29:AS29,AK$43:AN$43) -> 0 | AU29: 0 | AV29: 0 | AW29: 0 | AX29: 0 | AY29: =SUMPRODUCT(AU29:AX29,AP$43:AS$43) -> 0
A30: Hollister | S30: =S25/N8 -> -0.035879007 | T30: =T25/O8 -> -0.023288779 | U30: =U25/P8 -> -0.026469067 | V30: =V25/Q8 -> -0.012086262 | W30: =W25/R8 -> 0.0067378597 | X30: =X25/S8 -> 0.012111362 | Y30: =Y25/T8 -> 0.0069505268 | Z30: =Z25/U8 -> 0.0039477384 | ... AL30: =AL25/AG8 -> 0.00022638721 | AM30: 0 | AN30: 0.005 | AO30: =SUMPRODUCT(AK30:AN30,AF$44:AI$44) -> 0.0043065111 | AP30: 0 | AQ30: 0 | AR30: 0 | AS30: 0 | AT30: =SUMPRODUCT(AP30:AS30,AK$44:AN$44) -> 0 | AU30: 0 | AV30: 0 | AW30: 0 | AX30: 0 | AY30: =SUMPRODUCT(AU30:AX30,AP$44:AS$44) -> 0
A31: Total ANF | C31: =B26/B9 -> 0 | D31: =C26/C9 -> 0.0060118915 | E31: =E26/D9 -> -0.010593554 | F31: =F26/E9 -> 0 | R31: =R26/M9 -> -0.026737585 | S31: =S26/N9 -> -0.029674312 | T31: =T26/O9 -> -0.020054195 | U31: =U26/P9 -> -0.022032888 | V31: =V26/Q9 -> -0.010577512 | W31: =W26/R9 -> 0.0035685407 | X31: =X26/S9 -> 0.0078822022 | Y31: =Y26/T9 -> 0.0044065163 | ... AH31: =AH26/AC9 -> 0.0048256113 | AI31: =AI29*AD$39+AI30*AD$40 -> 0.010618222 | AJ31: =AJ26/AE9 -> 0.0067013069 | AK31: =AK26/AF9 -> 0.01004182 | AL31: =AL26/AG9 -> 0.00018451711 | AM31: =AM29*AH$39+AM30*AH$40 -> 0 | AN31: =AN29*AI$39+AN30*AI$40 -> 0.002585037 | AO31: =SUMPRODUCT(AK31:AN31,AF$45:AI$45) -> 0.0029543557 | AP31: =AP29*AK$39+AP30*AK$40 -> 0 | AQ31: =AQ29*AL$39+AQ30*AL$40 -> 0 | AR31: =AR29*AM$39+AR30*AM$40 -> 0 | AS31: =AS29*AN$39+AS30*AN$40 -> 0 | AT31: =SUMPRODUCT(AP31:AS31,AK$45:AN$45) -> 0 | AU31: =AU29*AP$39+AU30*AP$40 -> 0 | AV31: =AV29*AQ$39+AV30*AQ$40 -> 0 | AW31: =AW29*AR$39+AW30*AR$40 -> 0 | AX31: =AX29*AS$39+AX30*AS$40 -> 0 | AY31: =SUMPRODUCT(AU31:AX31,AP$45:AS$45) -> 0
A33: Non-Comp/Other Impact
A34: Abercrombie | V34: =V7/(Q7+V24)-1-V19 -> 0.0059341838 | W34: =W7/(R7+W24)-1-W19 -> 0.027073075 | X34: =X7/(S7+X24)-1-X19 -> 0.032649714 | Y34: =Y7/(T7+Y24)-1-Y19 -> 0.065498957 | Z34: =Z7/(U7+Z24)-1-Z19 -> 0.04000368 | AA34: =AA7/(V7+AA24)-1-AA19 -> 0.02239896 | AB34: =AB7/(W7+AB24)-1-AB19 -> 0.051771371 | AC34: =AC7/(X7+AC24)-1-AC19 -> 0.036465685 | ... AL34: =AL7/(AG7+AL24)-1-AL19 -> 0.041286874 | AM34: 0.06 | AN34: 0.05 | AO34: =SUMPRODUCT(AK34:AN34,AF$43:AI$43) -> 0.044840586 | AP34: 0.03 | AQ34: 0.02 | AR34: 0.02 | AS34: 0.02 | AT34: =SUMPRODUCT(AP34:AS34,AK$43:AN$43) -> 0.022098378 | AU34: 0.01 | AV34: 0.01 | AW34: 0.01 | AX34: 0.01 | AY34: =SUMPRODUCT(AU34:AX34,AP$43:AS$43) -> 0.01
A35: Hollister | V35: =V8/(Q8+V25)-1-V20 -> 0.0040553663 | W35: =W8/(R8+W25)-1-W20 -> 0.024466102 | X35: =X8/(S8+X25)-1-X20 -> 0.028008617 | Y35: =Y8/(T8+Y25)-1-Y20 -> 0.0236942 | Z35: =Z8/(U8+Z25)-1-Z20 -> 0.014979968 | AA35: =AA8/(V8+AA25)-1-AA20 -> -0.0068760735 | AB35: =AB8/(W8+AB25)-1-AB20 -> 0.02006973 | AC35: =AC8/(X8+AC25)-1-AC20 -> -0.079655255 | ... AL35: =AL8/(AG8+AL25)-1-AL20 -> 0.049853115 | AM35: 0.05 | AN35: 0.035 | AO35: =SUMPRODUCT(AK35:AN35,AF$44:AI$44) -> 0.036496725 | AP35: 0.01 | AQ35: 0.01 | AR35: 0.01 | AS35: 0.01 | AT35: =SUMPRODUCT(AP35:AS35,AK$44:AN$44) -> 0.01 | AU35: 0.01 | AV35: 0.01 | AW35: 0.01 | AX35: 0.01 | AY35: =SUMPRODUCT(AU35:AX35,AP$44:AS$44) -> 0.01
A36: Total ANF | D36: =D9/(C9+C26)-1-D21 -> 0.013609602 | F36: =F9/(E9+F26)-1-F21 -> -0.00081810608 | V36: =V9/(Q9+V26)-1-V21 -> 0.0095801857 | W36: =W9/(R9+W26)-1-W21 -> 0.027656777 | X36: =X9/(S9+X26)-1-X21 -> 0.030987587 | Y36: =Y9/(T9+Y26)-1-Y21 -> 0.045630897 | Z36: =Z9/(U9+Z26)-1-Z21 -> 0.025612025 | AA36: =AA9/(V9+AA26)-1-AA21 -> 0.011782934 | AB36: =AB9/(W9+AB26)-1-AB21 -> 0.035438785 | AC36: =AC9/(X9+AC26)-1-AC21 -> -0.021313717 | ... AL36: =AL9/(AG9+AL26)-1-AL21 -> 0.04790438 | AM36: =AM34*AH$39+AM35*AH$40 -> 0.054783325 | AN36: =AN34*AI$39+AN35*AI$40 -> 0.042244889 | AO36: =SUMPRODUCT(AK36:AN36,AF$45:AI$45) -> 0.040930096 | AP36: =AP34*AK$39+AP35*AK$40 -> 0.020140211 | AQ36: =AQ34*AL$39+AQ35*AL$40 -> 0.014711559 | AR36: =AR34*AM$39+AR35*AM$40 -> 0.014877564 | AS36: =AS34*AN$39+AS35*AN$40 -> 0.014829926 | AT36: =SUMPRODUCT(AP36:AS36,AK$45:AN$45) -> 0.015883368 | AU36: =AU34*AP$39+AU35*AP$40 -> 0.01 | AV36: =AV34*AQ$39+AV35*AQ$40 -> 0.01 | AW36: =AW34*AR$39+AW35*AR$40 -> 0.01 | AX36: =AX34*AS$39+AX35*AS$40 -> 0.01 | AY36: =SUMPRODUCT(AU36:AX36,AP$45:AS$45) -> 0.01
A38: Sales Weights
A39: Abercrombie | B39: =B7/B$9 -> 0.4663658 | C39: =C7/C$9 -> 0.44699135 | D39: =D7/D$9 -> 0.41632438 | E39: =E7/E$9 -> 0.40042545 | F39: =F7/F$9 -> 0.40423116 | G39: =G7/G$9 -> 0.43750502 | H39: =H7/H$9 -> 0.38532037 | I39: =I7/I$9 -> 0.41845513 | ... AY39: =AY7/AY$9 -> 0.48626885
A40: Hollister | B40: =B8/B$9 -> 0.5336342 | C40: =C8/C$9 -> 0.55300865 | D40: =D8/D$9 -> 0.58367562 | E40: =E8/E$9 -> 0.59957455 | F40: =F8/F$9 -> 0.59576884 | G40: =G8/G$9 -> 0.56249498 | H40: =H8/H$9 -> 0.61467963 | I40: =I8/I$9 -> 0.58154487 | ... AY40: =AY8/AY$9 -> 0.51373115
A42: Seasonality
A43: Abercrombie | G43: =G7/K7 -> 0.16447811 | H43: =H7/K7 -> 0.20842193 | I43: =I7/K7 -> 0.26566902 | J43: =J7/K7 -> 0.36143094 | K43: =SUM(G43:J43) -> 1 | L43: =L7/P7 -> 0.21664071 | M43: =M7/P7 -> 0.22390687 | N43: =N7/P7 -> 0.24466494 | O43: =O7/P7 -> 0.31478749 | P43: =SUM(L43:O43) -> 1 | Q43: =Q7/U7 -> 0.22130264 | R43: =R7/U7 -> 0.21221197 | S43: =S7/U7 -> 0.24343937 | T43: =T7/U7 -> 0.32304602 | U43: =SUM(Q43:T43) -> 1 | V43: =V7/Z7 -> 0.19805004 | W43: =W7/Z7 -> 0.21016212 | X43: =X7/Z7 -> 0.24877662 | Y43: =Y7/Z7 -> 0.34301122 | Z43: =SUM(V43:Y43) -> 1 | AA43: =AA7/AE7 -> 0.22355868 | AB43: =AB7/AE7 -> 0.2278236 | AC43: =AC7/AE7 -> 0.24637249 | AD43: =AD7/AE7 -> 0.30224524 | AE43: =SUM(AA43:AD43) -> 1 | AF43: =AF7/AJ7 -> 0.21712377 | AG43: =AG7/AJ7 -> 0.21867746 | AH43: =AH7/AJ7 -> 0.2446227 | AI43: =AI7/AJ7 -> 0.31957608 | AJ43: =SUM(AF43:AI43) -> 1 | AK43: =AK7/$AO7 -> 0.2098378 | AL43: =AL7/$AO7 -> 0.2217614 | AM43: =AM7/$AO7 -> 0.24774393 | AN43: =AN7/$AO7 -> 0.32065687 | AO43: =SUM(AK43:AN43) -> 1 | AP43: =AP7/$AT7 -> 0.21142888 | AQ43: =AQ7/$AT7 -> 0.22131486 | AR43: =AR7/$AT7 -> 0.24724507 | AS43: =AS7/$AT7 -> 0.32001119 | AT43: =SUM(AP43:AS43) -> 1 | AU43: =AU7/$AT7 -> 0.2167146 | AV43: =AV7/$AT7 -> 0.22684773 | AW43: =AW7/$AT7 -> 0.25342619 | AX43: =AX7/$AT7 -> 0.32801147 | AY43: =SUM(AU43:AX43) -> 1.025
A44: Hollister | G44: =G8/K8 -> 0.14883318 | H44: =H8/K8 -> 0.23400563 | I44: =I8/K8 -> 0.25985513 | J44: =J8/K8 -> 0.35730605 | K44: =SUM(G44:J44) -> 1 | L44: =L8/P8 -> 0.20596477 | M44: =M8/P8 -> 0.23951957 | N44: =N8/P8 -> 0.24316392 | O44: =O8/P8 -> 0.31135174 | P44: =SUM(L44:O44) -> 1 | Q44: =Q8/U8 -> 0.21847006 | R44: =R8/U8 -> 0.22259661 | S44: =S8/U8 -> 0.23320237 | T44: =T8/U8 -> 0.32573096 | U44: =SUM(Q44:T44) -> 1 | V44: =V8/Z8 -> 0.19237698 | W44: =W8/Z8 -> 0.22733817 | X44: =X8/Z8 -> 0.24468745 | Y44: =Y8/Z8 -> 0.33559741 | Z44: =SUM(V44:Y44) -> 1 | AA44: =AA8/AE8 -> 0.18778774 | AB44: =AB8/AE8 -> 0.2305697 | AC44: =AC8/AE8 -> 0.24209614 | AD44: =AD8/AE8 -> 0.33954643 | AE44: =SUM(AA44:AD44) -> 1 | AF44: =AF8/AJ8 -> 0.20030555 | AG44: =AG8/AJ8 -> 0.23943879 | AH44: =AH8/AJ8 -> 0.24548481 | AI44: =AI8/AJ8 -> 0.31477086 | AJ44: =SUM(AF44:AI44) -> 1 | AK44: =AK8/$AO8 -> 0.19314726 | AL44: =AL8/$AO8 -> 0.23563141 | AM44: =AM8/$AO8 -> 0.2462979 | AN44: =AN8/$AO8 -> 0.32492344 | AO44: =SUM(AK44:AN44) -> 1 | AP44: =AP8/$AT8 -> 0.19421398 | AQ44: =AQ8/$AT8 -> 0.23693277 | AR44: =AR8/$AT8 -> 0.24527683 | AS44: =AS8/$AT8 -> 0.32357642 | AT44: =SUM(AP44:AS44) -> 1 | AU44: =AU8/$AT8 -> 0.2000404 | AV44: =AV8/$AT8 -> 0.24404075 | AW44: =AW8/$AT8 -> 0.25386152 | AX44: =AX8/$AT8 -> 0.3349016 | AY44: =SUM(AU44:AX44) -> 1.0328443
A45: Total | G45: =G9/K9 -> 0.1552958 | H45: =H9/K9 -> 0.2234375 | I45: =I9/K9 -> 0.26225673 | J45: =J9/K9 -> 0.35900996 | K45: =SUM(G45:J45) -> 1 | L45: =L9/P9 -> 0.21046427 | M45: =M9/P9 -> 0.23293941 | N45: =N9/P9 -> 0.24379654 | O45: =O9/P9 -> 0.31279978 | P45: =SUM(L45:O45) -> 1 | Q45: =Q9/U9 -> 0.21979901 | R45: =R9/U9 -> 0.2177245 | S45: =S9/U9 -> 0.23800521 | T45: =T9/U9 -> 0.32447128 | U45: =SUM(Q45:T45) -> 1 | V45: =V9/Z9 -> 0.19529481 | W45: =W9/Z9 -> 0.21850399 | X45: =X9/Z9 -> 0.24679064 | Y45: =Y9/Z9 -> 0.33941057 | Z45: =SUM(V45:Y45) -> 1 | AA45: =AA9/AE9 -> 0.20626696 | AB45: =AB9/AE9 -> 0.22915107 | AC45: =AC9/AE9 -> 0.24430529 | AD45: =AD9/AE9 -> 0.32027668 | AE45: =SUM(AA45:AD45) -> 1 | AF45: =AF9/AJ9 -> 0.20836501 | AG45: =AG9/AJ9 -> 0.22948974 | AH45: =AH9/AJ9 -> 0.24507167 | AI45: =AI9/AJ9 -> 0.31707357 | AJ45: =SUM(AF45:AI45) -> 1 | AK45: =AK9/$AO9 -> 0.20126377 | AL45: =AL9/$AO9 -> 0.22888651 | AM45: =AM9/$AO9 -> 0.24700109 | AN45: =AN9/$AO9 -> 0.32284863 | AO45: =SUM(AK45:AN45) -> 1 | AP45: =AP9/$AT9 -> 0.20261784 | AQ45: =AQ9/$AT9 -> 0.22930852 | AR45: =AR9/$AT9 -> 0.24623767 | AS45: =AS9/$AT9 -> 0.32183597 | AT45: =SUM(AP45:AS45) -> 1 | AU45: =AU9/$AT9 -> 0.2081803 | AV45: =AV9/$AT9 -> 0.23564757 | AW45: =AW9/$AT9 -> 0.25364901 | AX45: =AX9/$AT9 -> 0.33153802 | AY45: =SUM(AU45:AX45) -> 1.0290149
A48: Segments by Geography (NON-DRIVER)
A49: Americas | G49: =322862+17508 -> 340370 | H49: =458671+26546 -> 485217 | I49: =557814+28007 -> 585821 | J49: =788056+39834 -> 827890 | K49: =SUM(G49:J49) -> 2239298 | L49: =553846+22511 -> 576357 | M49: =601767+31015 -> 632782 | N49: =654858+32931 -> 687789 | O49: =841687+47380 -> 889067 | P49: =SUM(L49:O49) -> 2785995 | Q49: =585106+33790 -> 618896 | R49: 613244 | S49: 713860 | T49: 971091 | U49: =SUM(Q49:T49) -> 2917091 | V49: 665423 | W49: 731427 | X49: 867566 | Y49: 1191259 | Z49: =SUM(V49:Y49) -> 3455675 | AA49: 820121 | AB49: 901224 | AC49: 986449 | AD49: 1319720 | AE49: =SUM(AA49:AD49) -> 4027514 | AF49: 874804 | AG49: 974200 | AH49: 1057448 | AI49: 1383943 | AJ49: =SUM(AF49:AI49) -> 4290395 | AK49: 899944 | AL49: 1020537 | AM49: =(1+AM65)*AH49 -> 1119060.2 | AN49: =(1+AN65)*AI49 -> 1496734.4 | AO49: =SUM(AK49:AN49) -> 4536275.6 | AP49: =(1+AP65)*AK49 -> 936301.74 | AQ49: =(1+AQ65)*AL49 -> 1056562 | AR49: =(1+AR65)*AM49 -> 1158563 | AS49: =(1+AS65)*AN49 -> 1549569.1 | AT49: =SUM(AP49:AS49) -> 4700995.8 | AU49: =(1+AU65)*AP49 -> 964578.05 | AV49: =(1+AV65)*AQ49 -> 1088470.1 | AW49: =(1+AW65)*AR49 -> 1193551.6 | AX49: =(1+AX65)*AS49 -> 1596366.1 | AY49: =SUM(AU49:AX49) -> 4842965.9
A50: EMEA | G50: 112654 | H50: 171297 | I50: 190214 | J50: 235286 | K50: =SUM(G50:J50) -> 709451 | L50: 159002 | M50: 190840 | N50: 179156 | O50: 226074 | P50: =SUM(L50:O50) -> 755072 | Q50: 163969 | R50: 164827 | S50: 138840 | T50: 193400 | U50: =SUM(Q50:T50) -> 661036 | V50: 138106 | W50: 171962 | X50: 157976 | Y50: 219050 | Z50: =SUM(V50:Y50) -> 687094 | AA50: 164778 | AB50: 199682 | AC50: 181592 | AD50: 224467 | AE50: =SUM(AA50:AD50) -> 770519 | AF50: 185036 | AG50: 197210 | AH50: 194510 | AI50: 241384 | AJ50: =SUM(AF50:AI50) -> 818140 | AK50: 167373 | AL50: 201990 | AM50: =(1+AM71)*AH50 -> 199995.18 | AN50: =(1+AN71)*AI50 -> 231825.19 | AO50: =SUM(AK50:AN50) -> 801183.38 | AP50: =(1+AP71)*AK50 -> 177499.07 | AQ50: =(1+AQ71)*AL50 -> 214210.39 | AR50: =(1+AR71)*AM50 -> 204015.09 | AS50: =(1+AS71)*AN50 -> 236484.88 | AT50: =SUM(AP50:AS50) -> 832209.43 | AU50: =(1+AU71)*AP50 -> 181066.8 | AV50: =(1+AV71)*AQ50 -> 218516.02 | AW50: =(1+AW71)*AR50 -> 208115.79 | AX50: =(1+AX71)*AS50 -> 241238.23 | AY50: =SUM(AU50:AX50) -> 848936.84
A51: APAC | G51: 32335 | H51: 41814 | I51: 43618 | J51: 58868 | K51: =SUM(G51:J51) -> 176635 | L51: 46046 | M51: 41228 | N51: 38215 | O51: 46212 | P51: =SUM(L51:O51) -> 171701 | Q51: 29897 | R51: 27020 | S51: 27384 | T51: 35323 | U51: =SUM(Q51:T51) -> 119624 | V51: 32465 | W51: 31956 | X51: 30889 | Y51: 42598 | Z51: =SUM(V51:Y51) -> 137908 | AA51: 35831 | AB51: 33068 | AC51: 40925 | AD51: 40730 | AE51: =SUM(AA51:AD51) -> 150554 | AF51: 37471 | AG51: 37150 | AH51: 38661 | AI51: 44475 | AJ51: =SUM(AF51:AI51) -> 157757 | AK51: 46504 | AL51: 44162 | AM51: =AM52-SUM(AM49:AM50) -> 47882.17 | AN51: =AN52-SUM(AN49:AN50) -> 58128.592 | AO51: =SUM(AK51:AN51) -> 196676.76 | AP51: =AP52-SUM(AP49:AP50) -> 50220.226 | AQ51: =AQ52-SUM(AQ49:AQ50) -> 46584.209 | AR51: =AR52-SUM(AR49:AR50) -> 52034.895 | AS51: =AS52-SUM(AS49:AS50) -> 62864.398 | AT51: =SUM(AP51:AS51) -> 211703.73 | AU51: =AU52-SUM(AU49:AU50) -> 50332.038 | AV51: =AV52-SUM(AV49:AV50) -> 46787.704 | AW51: =AW52-SUM(AW49:AW50) -> 55523.024 | AX51: =AX52-SUM(AX49:AX50) -> 67051.454 | AY51: =SUM(AU51:AX51) -> 219694.22
A52: Total | G52: =SUM(G49:G51) -> 485359 | H52: =SUM(H49:H51) -> 698328 | I52: =SUM(I49:I51) -> 819653 | J52: =SUM(J49:J51) -> 1122044 | K52: =IF(SUM(K49:K51)=SUM(G52:J52),SUM(K49:K51),"ERR") -> 3125384 | L52: =SUM(L49:L51) -> 781405 | M52: =SUM(M49:M51) -> 864850 | N52: =SUM(N49:N51) -> 905160 | O52: =SUM(O49:O51) -> 1161353 | P52: =IF(SUM(P49:P51)=SUM(L52:O52),SUM(P49:P51),"ERR") -> 3712768 | Q52: =SUM(Q49:Q51) -> 812762 | R52: =SUM(R49:R51) -> 805091 | S52: =SUM(S49:S51) -> 880084 | T52: =SUM(T49:T51) -> 1199814 | U52: =IF(SUM(U49:U51)=SUM(Q52:T52),SUM(U49:U51),"ERR") -> 3697751 | V52: =SUM(V49:V51) -> 835994 | W52: =SUM(W49:W51) -> 935345 | X52: =SUM(X49:X51) -> 1056431 | Y52: =SUM(Y49:Y51) -> 1452907 | Z52: =IF(SUM(Z49:Z51)=SUM(V52:Y52),SUM(Z49:Z51),"ERR") -> 4280677 | AA52: =SUM(AA49:AA51) -> 1020730 | AB52: =SUM(AB49:AB51) -> 1133974 | AC52: =SUM(AC49:AC51) -> 1208966 | AD52: =SUM(AD49:AD51) -> 1584917 | AE52: =IF(SUM(AE49:AE51)=SUM(AA52:AD52),SUM(AE49:AE51),"ERR") -> 4948587 | AF52: =SUM(AF49:AF51) -> 1097311 | AG52: =SUM(AG49:AG51) -> 1208560 | AH52: =SUM(AH49:AH51) -> 1290619 | AI52: =SUM(AI49:AI51) -> 1669802 | AJ52: =IF(SUM(AJ49:AJ51)=SUM(AF52:AI52),SUM(AJ49:AJ51),"ERR") -> 5266292 | AK52: =SUM(AK49:AK51) -> 1113821 | AL52: =AL9 -> 1266689 | AM52: =AM9 -> 1366937.6 | AN52: =AN9 -> 1786688.1 | AO52: =IF(SUM(AO49:AO51)=SUM(AK52:AN52),SUM(AO49:AO51),"ERR") -> 5534135.7 | AP52: =AP9 -> 1164021 | AQ52: =AQ9 -> 1317356.6 | AR52: =AR9 -> 1414613 | AS52: =AS9 -> 1848918.4 | AT52: =IF(SUM(AT49:AT51)=SUM(AP52:AS52),SUM(AT49:AT51),"ERR") -> 5744909 | AU52: =AU9 -> 1195976.9 | AV52: =AV9 -> 1353773.9 | AW52: =AW9 -> 1457190.4 | AX52: =AX9 -> 1904655.7 | AY52: =IF(SUM(AY49:AY51)=SUM(AU52:AX52),SUM(AY49:AY51),"ERR") -> 5911596.9
A54: Comparable Sales
A55: Total ANF
A56: Comparable Sales | S56: N/A | T56: N/A | V56: N/A | W56: 0.13 | X56: 0.16 | Y56: 0.16 | Z56: 0.13 | AA56: 0.21 | AB56: 0.18 | AC56: 0.16 | AD56: 0.14 | AE56: 0.17 | AF56: 0.04 | AG56: 0.03 | AH56: 0.03 | AI56: 0.01 | AJ56: =SUMPRODUCT(AF56:AI56,AA95:AD95) -> 0.025657136 | AK56: -0.01 | AL56: 0 | AM56: =AM62*AH$87+AM68*AH$88+AM74*AH$89 -> 0.0043499747 | AN56: =AN62*AI$87+AN68*AI$88+AN74*AI$89 -> 0.025170074 | AO56: =SUMPRODUCT(AK56:AN56,AF95:AI95) -> 0.0069631707 | AP56: =AP62*AK$87+AP68*AK$88+AP74*AK$89 -> 0.024929894 | AQ56: =AQ62*AL$87+AQ68*AL$88+AQ74*AL$89 -> 0.025288441 | AR56: =AR62*AM$87+AR68*AM$88+AR74*AM$89 -> 0.02 | AS56: =AS62*AN$87+AS68*AN$88+AS74*AN$89 -> 0.02 | AT56: =SUMPRODUCT(AP56:AS56,AK95:AN95) -> 0.022202662 | AU56: =AU62*AP$87+AU68*AP$88+AU74*AP$89 -> 0.017452989 | AV56: =AV62*AQ$87+AV68*AQ$88+AV74*AQ$89 -> 0.01764422 | AW56: =AW62*AR$87+AW68*AR$88+AW74*AR$89 -> 0.020098293 | AX56: =AX62*AS$87+AX68*AS$88+AX74*AS$89 -> 0.020145943 | AY56: =SUMPRODUCT(AU56:AX56,AP95:AS95) -> 0.019014903
A57: Non-Comp/Other | S57: =S59-S58 -> 0.0020311966 | T57: =T59-T58 -> 0.054259738 | V57: =V59-V58 -> 0.039580186 | W57: =W59-W56-W58 -> 0.027656777 | X57: =X59-X56-X58 -> 0.030987587 | Y57: =Y59-Y56-Y58 -> 0.045630897 | Z57: =Z59-Z56-Z58 -> 0.025612025 | AA57: =AA59-AA56-AA58 -> 0.011782934 | AB57: =AB59-AB56-AB58 -> 0.035438785 | AC57: =AC59-AC56-AC58 -> -0.021313717 | AD57: =AD59-AD56-AD58 -> -0.044512745 | ... AY57: =AY59-AY56-AY58 -> 0.01
A58: FX | S58: =S59-(S52/(N52+S84)-1) -> -0.029734586 | T58: =T59-(T52/(O52+T84)-1) -> -0.021142331 | V58: =V59-(V52/(Q52+V84)-1) -> -0.010996172 | W58: =W59-(W52/(R52+W84)-1) -> 0.0041311453 | X58: =X59-(X52/(S52+X84)-1) -> 0.0093876049 | Y58: =Y59-(Y52/(T52+Y84)-1) -> 0.0053126323 | Z58: =Z59-(Z52/(U52+Z84)-1) -> 0.002031364 | AA58: =AA59-(AA52/(V52+AA84)-1) -> -0.0008052718 | AB58: =AB59-(AB52/(W52+AB84)-1) -> -0.0030797085 | AC58: =AC59-(AC52/(X52+AC84)-1) -> 0.0057008094 | ... AY58: =AY59-(AY52/(AT52+AY84)-1) -> 0
A59: Net Sales | L59: =L52/G52-1 -> 0.60995263 | M59: =M52/H52-1 -> 0.23845815 | N59: =N52/I52-1 -> 0.10432097 | O59: =O52/J52-1 -> 0.035033386 | P59: =P52/K52-1 -> 0.18793979 | Q59: =Q52/L52-1 -> 0.040128998 | R59: =R52/M52-1 -> -0.069097531 | S59: =S52/N52-1 -> -0.027703389 | T59: =T52/O52-1 -> 0.033117407 | V59: =V52/Q52-1 -> 0.028584014 | W59: =W52/R52-1 -> 0.16178792 | X59: =X52/S52-1 -> 0.20037519 | Y59: =Y52/T52-1 -> 0.21094353 | Z59: =Z52/U52-1 -> 0.15764339 | AA59: =AA52/V52-1 -> 0.22097766 | AB59: =AB52/W52-1 -> 0.21235908 | AC59: =AC52/X52-1 -> 0.14438709 | ... AY59: =AY52/AT52-1 -> 0.029014903
A61: Americas
A62: Comparable Sales | S62: N/A | T62: N/A | V62: N/A | W62: 0.14 | X62: 0.16 | Y62: 0.17 | Z62: 0.13 | AA62: 0.21 | AB62: 0.18 | AC62: 0.16 | AD62: 0.15 | AE62: 0.17 | AF62: 0.04 | AG62: 0.05 | AH62: 0.04 | AI62: 0.02 | AJ62: 0.04 | AK62: 0.01 | AL62: 0.01 | AM62: 0.005 | AN62: 0.03 | AO62: =SUMPRODUCT(AK62:AN62,AF92:AI92) -> 0.015219011 | AP62: 0.02 | AQ62: 0.02 | AR62: 0.02 | AS62: 0.02 | AT62: =SUMPRODUCT(AP62:AS62,AK92:AN92) -> 0.02 | AU62: 0.02 | AV62: 0.02 | AW62: 0.02 | AX62: 0.02 | AY62: =SUMPRODUCT(AU62:AX62,AP92:AS92) -> 0.02
A63: Non-Comp/Other | S63: =S65-S64 -> 0.040542471 | T63: =T65-T64 -> 0.095772362 | V63: =V65-V64 -> 0.078922023 | W63: =W65-W62-W64 -> 0.055005473 | X63: =X65-X62-X64 -> 0.056245277 | Y63: =Y65-Y62-Y64 -> 0.056795588 | Z63: =Z65-Z62-Z64 -> 0.0562266 | AA63: =AA65-AA62-AA64 -> 0.022595538 | AB63: =AB65-AB62-AB64 -> 0.053549687 | AC63: =AC65-AC62-AC64 -> -0.022620777 | AD63: =AD65-AD62-AD64 -> -0.039966448 | ... AL63: =AL65-AL62-AL64 -> 0.037564155 | AM63: 0.053 | AN63: 0.05 | AO63: =AO65-AO62-AO64 -> 0.042090528 | AP63: 0.02 | AQ63: 0.015 | AR63: 0.015 | AS63: 0.015 | AT63: =AT65-AT62-AT64 -> 0.01631178 | AU63: 0.01 | AV63: 0.01 | AW63: 0.01 | AX63: 0.01 | AY63: =AY65-AY62-AY64 -> 0.0102
A64: FX | S64: =S65-(S49/(N49+S81)-1) -> -0.0026369505 | T64: =T65-(T49/(O49+T81)-1) -> -0.0035138488 | V64: =V65-(V49/(Q49+V81)-1) -> -0.0037446106 | W64: =W65-(W49/(R49+W81)-1) -> -0.0022877296 | X64: =X65-(X49/(S49+X81)-1) -> -0.00092854856 | Y64: =Y65-(Y49/(T49+Y81)-1) -> -7.3272375e-05 | Z64: =Z65-(Z49/(U49+Z81)-1) -> -0.0015960899 | AA64: =AA65-(AA49/(V49+AA81)-1) -> -0.00011484563 | AB64: =AB65-(AB49/(W49+AB81)-1) -> -0.0014048523 | AC64: =AC65-(AC49/(X49+AC81)-1) -> -0.00034872606 | ... AE64: =AE65-(AE49/(Z49+AE81)-1) -> -0.0011880454 | AJ64: =AJ65-(AJ49/(AE49+AJ81)-1) -> 0 | AM64: 0 | AN64: 0 | AO64: =AO65-(AO49/(AJ49+AO81)-1) -> 0 | AP64: 0 | AQ64: 0 | AR64: 0 | AS64: 0 | AT64: =AT65-(AT49/(AO49+AT81)-1) -> 0 | AU64: 0 | AV64: 0 | AW64: 0 | AX64: 0 | AY64: =AY65-(AY49/(AT49+AY81)-1) -> 0
A65: Net Sales | L65: =L49/G49-1 -> 0.69332491 | M65: =M49/H49-1 -> 0.30412166 | N65: =N49/I49-1 -> 0.17405999 | O65: =O49/J49-1 -> 0.073895083 | P65: =P49/K49-1 -> 0.24413767 | Q65: =Q49/L49-1 -> 0.073806686 | R65: =R49/M49-1 -> -0.030876352 | S65: =S49/N49-1 -> 0.03790552 | T65: =T49/O49-1 -> 0.092258514 | V65: =V49/Q49-1 -> 0.075177413 | W65: =W49/R49-1 -> 0.19271774 | X65: =X49/S49-1 -> 0.21531673 | Y65: =Y49/T49-1 -> 0.22672232 | Z65: =Z49/U49-1 -> 0.18463051 | AA65: =AA49/V49-1 -> 0.23248069 | AB65: =AB49/W49-1 -> 0.23214483 | AC65: =AC49/X49-1 -> 0.1370305 | ... AL65: =AL49/AG49-1 -> 0.047564155 | AM65: =(1+AM62)*(1+AM64)*(1+AM63)-1 -> 0.058265 | AN65: =(1+AN62)*(1+AN64)*(1+AN63)-1 -> 0.0815 | AO65: =AO49/AJ49-1 -> 0.05730954 | AP65: =(1+AP62)*(1+AP64)*(1+AP63)-1 -> 0.0404 | AQ65: =(1+AQ62)*(1+AQ64)*(1+AQ63)-1 -> 0.0353 | AR65: =(1+AR62)*(1+AR64)*(1+AR63)-1 -> 0.0353 | AS65: =(1+AS62)*(1+AS64)*(1+AS63)-1 -> 0.0353 | AT65: =AT49/AO49-1 -> 0.03631178 | AU65: =(1+AU62)*(1+AU64)*(1+AU63)-1 -> 0.0302 | AV65: =(1+AV62)*(1+AV64)*(1+AV63)-1 -> 0.0302 | AW65: =(1+AW62)*(1+AW64)*(1+AW63)-1 -> 0.0302 | AX65: =(1+AX62)*(1+AX64)*(1+AX63)-1 -> 0.0302 | AY65: =AY49/AT49-1 -> 0.0302
A67: EMEA
A68: Comparable Sales | S68: N/A | T68: N/A | V68: N/A | W68: 0.06 | X68: 0.15 | Y68: 0.1 | Z68: 0.07 | AA68: 0.23 | AB68: 0.17 | AC68: 0.13 | AD68: 0.12 | AE68: 0.16 | AF68: 0.06 | AG68: -0.05 | AH68: 0.02 | AI68: -0.03 | AJ68: 0 | AK68: -0.11 | AL68: -0.04 | AM68: -0.03 | AN68: -0.02 | AO68: =SUMPRODUCT(AK68:AN68,AF93:AI93) -> -0.047553402 | AP68: 0.05 | AQ68: 0.05 | AR68: 0.01 | AS68: 0.01 | AT68: =SUMPRODUCT(AP68:AS68,AK93:AN93) -> 0.028440872 | AU68: 0.01 | AV68: 0.01 | AW68: 0.01 | AX68: 0.01 | AY68: =SUMPRODUCT(AU68:AX68,AP93:AS93) -> 0.01
A69: Non-Comp/Other | S69: =S71-S70 -> -0.11830825 | T69: =T71-T70 -> -0.080077057 | V69: =V71-V70 -> -0.13381669 | W69: =W71-W68-W70 -> -0.049249587 | X69: =X71-X68-X70 -> -0.076684105 | Y69: =Y71-Y68-Y70 -> -0.0035109674 | Z69: =Z71-Z68-Z70 -> -0.054391028 | AA69: =AA71-AA68-AA70 -> -0.046649551 | AB69: =AB71-AB68-AB70 -> -0.0060060391 | AC69: =AC71-AC68-AC70 -> -0.016150487 | AD69: =AD71-AD68-AD70 -> -0.080723943 | ... AL69: =AL71-AL68-AL70 -> 0.064238122 | AM69: 0.06 | AN69: -0.02 | AO69: =AO71-AO68-AO70 -> 0.026827579 | AP69: 0.01 | AQ69: 0.01 | AR69: 0.01 | AS69: 0.01 | AT69: =AT71-AT68-AT70 -> 0.010284409 | AU69: 0.01 | AV69: 0.01 | AW69: 0.01 | AX69: 0.01 | AY69: =AY71-AY68-AY70 -> 0.0101
A70: FX | S70: =S71-(S50/(N50+S82)-1) -> -0.10672468 | T70: =T71-(T50/(O50+T82)-1) -> -0.064450841 | V70: =V71-(V50/(Q50+V82)-1) -> -0.023914349 | W70: =W71-(W50/(R50+W82)-1) -> 0.032537398 | X70: =X71-(X50/(S50+X82)-1) -> 0.06451182 | Y70: =Y71-(Y50/(T50+Y82)-1) -> 0.036137648 | Z70: =Z71-(Z50/(U50+Z82)-1) -> 0.023810969 | AA70: =AA71-(AA50/(V50+AA82)-1) -> 0.0097765692 | AB70: =AB71-(AB50/(W50+AB82)-1) -> -0.0027955566 | AC70: =AC71-(AC50/(X50+AC82)-1) -> 0.035641549 | ... AE70: =AE71-(AE50/(Z50+AE82)-1) -> 0.0044169931 | AJ70: =AJ71-(AJ50/(AE50+AJ82)-1) -> 0 | AM70: 0 | AN70: 0 | AO70: =AO71-(AO50/(AJ50+AO82)-1) -> 0 | AP70: 0 | AQ70: 0 | AR70: 0 | AS70: 0 | AT70: =AT71-(AT50/(AO50+AT82)-1) -> 0 | AU70: 0 | AV70: 0 | AW70: 0 | AX70: 0 | AY70: =AY71-(AY50/(AT50+AY82)-1) -> 0
A71: Net Sales | L71: =L50/G50-1 -> 0.41141904 | M71: =M50/H50-1 -> 0.1140884 | N71: =N50/I50-1 -> -0.058134522 | O71: =O50/J50-1 -> -0.039152351 | P71: =P50/K50-1 -> 0.064304652 | Q71: =Q50/L50-1 -> 0.031238601 | R71: =R50/M50-1 -> -0.1363079 | S71: =S50/N50-1 -> -0.22503293 | T71: =T50/O50-1 -> -0.1445279 | V71: =V50/Q50-1 -> -0.15773103 | W71: =W50/R50-1 -> 0.043287811 | X71: =X50/S50-1 -> 0.13782772 | Y71: =Y50/T50-1 -> 0.13262668 | Z71: =Z50/U50-1 -> 0.039419941 | AA71: =AA50/V50-1 -> 0.19312702 | AB71: =AB50/W50-1 -> 0.1611984 | AC71: =AC50/X50-1 -> 0.14949106 | ... AL71: =AL50/AG50-1 -> 0.024238122 | AM71: =(1+AM68)*(1+AM70)*(1+AM69)-1 -> 0.0282 | AN71: =(1+AN68)*(1+AN70)*(1+AN69)-1 -> -0.0396 | AO71: =AO50/AJ50-1 -> -0.020725822 | AP71: =(1+AP68)*(1+AP70)*(1+AP69)-1 -> 0.0605 | AQ71: =(1+AQ68)*(1+AQ70)*(1+AQ69)-1 -> 0.0605 | AR71: =(1+AR68)*(1+AR70)*(1+AR69)-1 -> 0.0201 | AS71: =(1+AS68)*(1+AS70)*(1+AS69)-1 -> 0.0201 | AT71: =AT50/AO50-1 -> 0.038725281 | AU71: =(1+AU68)*(1+AU70)*(1+AU69)-1 -> 0.0201 | AV71: =(1+AV68)*(1+AV70)*(1+AV69)-1 -> 0.0201 | AW71: =(1+AW68)*(1+AW70)*(1+AW69)-1 -> 0.0201 | AX71: =(1+AX68)*(1+AX70)*(1+AX69)-1 -> 0.0201 | AY71: =AY50/AT50-1 -> 0.0201
A73: APAC
A74: Comparable Sales | S74: N/A | T74: N/A | V74: N/A | W74: 0.26 | X74: 0.32 | Y74: 0.21 | Z74: 0.26 | AA74: 0.22 | AB74: 0.21 | AC74: 0.16 | AD74: 0.17 | AE74: 0.19 | AF74: 0.02 | AG74: 0.01 | AH74: -0.12 | AI74: 0 | AJ74: -0.03 | AK74: 0.15 | AL74: 0.13 | AM74: =(AM21-AM62*AH87-AM68*AH88)/AH89 -> 0.15939112 | AN74: =(AN21-AN62*AI87-AN68*AI88)/AI89 -> 0.12003215 | AO74: =SUMPRODUCT(AK74:AN74,AF94:AI94) -> 0.13914311 | AP74: =(AP21-AP62*AK87-AP68*AK88)/AK89 -> 0.030103002 | AQ74: =(AQ21-AQ62*AL87-AQ68*AL88)/AL89 -> 0.034471944 | AR74: =(AR21-AR62*AM87-AR68*AM88)/AM89 -> 0.061768195 | AS74: =(AS21-AS62*AN87-AS68*AN88)/AN89 -> 0.05988144 | AT74: =SUMPRODUCT(AP74:AS74,AK94:AN94) -> 0.04759423 | AU74: =(AU21-AU62*AP87-AU68*AP88)/AP89 -> -0.0036913328 | AV74: =(AV21-AV62*AQ87-AV68*AQ88)/AQ89 -> -0.00063569765 | AW74: =(AW21-AW62*AR87-AW68*AR88)/AR89 -> 0.061879529 | AX74: =(AX21-AX62*AS87-AX68*AS88)/AS89 -> 0.061910627 | AY74: =SUMPRODUCT(AU74:AX74,AP94:AS94) -> 0.032577962
A75: Non-Comp/Other | S75: =S77-S76 -> -0.21274149 | T75: =T77-T76 -> -0.15113429 | V75: =V77-V76 -> 0.16050045 | W75: =W77-W74-W76 -> -0.019520205 | X75: =X77-X74-X76 -> -0.15530033 | Y75: =Y77-Y74-Y76 -> 0.032141482 | Z75: =Z77-Z74-Z76 -> -0.056099554 | AA75: =AA77-AA74-AA76 -> -0.057976326 | AB75: =AB77-AB74-AB76 -> -0.13747794 | AC75: =AC77-AC74-AC76 -> 0.14380069 | AD75: =AD77-AD74-AD76 -> -0.19755229 | ... AY75: =AY77-AY74-AY76 -> 0.0051657908
A76: FX | S76: =S77-(S51/(N51+S83)-1) -> -0.070681249 | T76: =T77-(T51/(O51+T83)-1) -> -0.08449715 | V76: =V77-(V51/(Q51+V83)-1) -> -0.074605541 | W76: =W77-(W51/(R51+W83)-1) -> -0.057800298 | X76: =X77-(X51/(S51+X83)-1) -> -0.036705223 | Y76: =Y77-(Y51/(T51+Y83)-1) -> -0.036185024 | Z76: =Z77-(Z51/(U51+Z83)-1) -> -0.051054863 | AA76: =AA77-(AA51/(V51+AA83)-1) -> -0.058342787 | AB76: =AB77-(AB51/(W51+AB83)-1) -> -0.037724208 | AC76: =AC77-(AC51/(X51+AC83)-1) -> 0.021104612 | ... AE76: =AE77-(AE51/(Z51+AE83)-1) -> -0.024011873 | AJ76: =AJ77-(AJ51/(AE51+AJ83)-1) -> 0.18914291 | AM76: =AM77-(AM51/(AH51+AM83)-1) -> 0 | AN76: =AN77-(AN51/(AI51+AN83)-1) -> 0.11562758 | AO76: =AO77-(AO51/(AJ51+AO83)-1) -> 0.11191666 | AP76: =AP77-(AP51/(AK51+AP83)-1) -> 0 | AQ76: =AQ77-(AQ51/(AL51+AQ83)-1) -> 0 | AR76: =AR77-(AR51/(AM51+AR83)-1) -> 0 | AS76: =AS77-(AS51/(AN51+AS83)-1) -> 0 | AT76: =AT77-(AT51/(AO51+AT83)-1) -> 0 | ... AY76: =AY77-(AY51/(AT51+AY83)-1) -> 0
A77: Net Sales | L77: =L51/G51-1 -> 0.42402969 | M77: =M51/H51-1 -> -0.014014445 | N77: =N51/I51-1 -> -0.12387088 | O77: =O51/J51-1 -> -0.21498947 | P77: =P51/K51-1 -> -0.027933309 | Q77: =Q51/L51-1 -> -0.3507145 | R77: =R51/M51-1 -> -0.34462016 | S77: =S51/N51-1 -> -0.28342274 | T77: =T51/O51-1 -> -0.23563144 | V77: =V51/Q51-1 -> 0.085894906 | W77: =W51/R51-1 -> 0.1826795 | X77: =X51/S51-1 -> 0.12799445 | Y77: =Y51/T51-1 -> 0.20595646 | Z77: =Z51/U51-1 -> 0.15284558 | AA77: =AA51/V51-1 -> 0.10368089 | AB77: =AB51/W51-1 -> 0.034797847 | AC77: =AC51/X51-1 -> 0.32490531 | ... AY77: =AY51/AT51-1 -> 0.037743753
A80: FX $ Impact
A81: Americas | S81: -1743 | T81: -2851 | U81: -6601 | V81: =Z81-SUM(W81:Y81) -> -2148 | W81: -1174 | X81: -545 | Y81: -58 | Z81: -3925 | AA81: -62 | AB81: -833 | AC81: -266 | AD81: -2358 | AE81: =SUM(AA81:AD81) -> -3519 | AJ81: =SUM(AF81:AI81) -> 0 | AM81: =AM64*AH49 -> 0 | AN81: =AN64*AI49 -> 0 | AO81: =SUM(AK81:AN81) -> 0 | AP81: =AP64*AK49 -> 0 | AQ81: =AQ64*AL49 -> 0 | AR81: =AR64*AM49 -> 0 | AS81: =AS64*AN49 -> 0 | AT81: =SUM(AP81:AS81) -> 0 | AU81: =AU64*AP49 -> 0 | AV81: =AV64*AQ49 -> 0 | AW81: =AW64*AR49 -> 0 | AX81: =AX64*AS49 -> 0 | AY81: =SUM(AU81:AX81) -> 0
A82: EMEA | S82: -21686 | T82: -15839 | U82: -61083 | V82: =Z82-SUM(W82:Y82) -> -4527 | W82: 5306 | X82: 8345 | Y82: 6374 | Z82: 15498 | AA82: 1141 | AB82: -413 | AC82: 5055 | AD82: -3066 | AE82: =SUM(AA82:AD82) -> 2717 | AJ82: =SUM(AF82:AI82) -> 0 | AM82: =AM70*AH50 -> 0 | AN82: =AN70*AI50 -> 0 | AO82: =SUM(AK82:AN82) -> 0 | AP82: =AP70*AK50 -> 0 | AQ82: =AQ70*AL50 -> 0 | AR82: =AR70*AM50 -> 0 | AS82: =AS70*AN50 -> 0 | AT82: =SUM(AP82:AS82) -> 0 | AU82: =AU70*AP50 -> 0 | AV82: =AV70*AQ50 -> 0 | AW82: =AW70*AR50 -> 0 | AX82: =AX70*AS50 -> 0 | AY82: =SUM(AU82:AX82) -> 0
A83: APAC | S83: -3431 | T83: -4600 | U83: -14119 | V83: =Z83-SUM(W83:Y83) -> -1922 | W83: -1259 | X83: -863 | Y83: -1029 | Z83: -5073 | AA83: -1630 | AB83: -1124 | AC83: 500 | AD83: -714 | AE83: =SUM(AA83:AD83) -> -2968 | AF83: =AF84-SUM(AF81:AF82) -> -208 | AG83: =AG84-SUM(AG81:AG82) -> 10707 | AH83: =AH84-SUM(AH81:AH82) -> 5834 | AI83: =AI84-SUM(AI81:AI82) -> 16829 | AJ83: =SUM(AF83:AI83) -> 33162 | AK83: =AK84-SUM(AK81:AK82) -> 11019 | AL83: =AL84-SUM(AL81:AL82) -> 223 | AM83: =AM84-SUM(AM81:AM82) -> 0 | AN83: =AN84-SUM(AN81:AN82) -> 4316.5 | AO83: =SUM(AK83:AN83) -> 15558.5 | AP83: =AP84-SUM(AP81:AP82) -> 0 | AQ83: =AQ84-SUM(AQ81:AQ82) -> 0 | AR83: =AR84-SUM(AR81:AR82) -> 0 | AS83: =AS84-SUM(AS81:AS82) -> 0 | AT83: =SUM(AP83:AS83) -> 0 | AU83: =AU84-SUM(AU81:AU82) -> 0 | AV83: =AV84-SUM(AV81:AV82) -> 0 | AW83: =AW84-SUM(AW81:AW82) -> 0 | AX83: =AX84-SUM(AX81:AX82) -> 0 | AY83: =SUM(AU83:AX83) -> 0
A84: Total | S84: =SUM(S81:S83) -> -26860 | T84: =SUM(T81:T83) -> -23290 | U84: =SUM(U81:U83) -> -81803 | V84: =Z84-SUM(W84:Y84) -> -8597 | W84: =SUM(W81:W83) -> 2873 | X84: =SUM(X81:X83) -> 6937 | Y84: =SUM(Y81:Y83) -> 5287 | Z84: =SUM(Z81:Z83) -> 6500 | AA84: =SUM(AA81:AA83) -> -551 | AB84: =SUM(AB81:AB83) -> -2370 | AC84: =SUM(AC81:AC83) -> 5289 | AD84: =SUM(AD81:AD83) -> -6138 | AE84: =SUM(AE81:AE83) -> -3770 | AF84: -208 | AG84: 10707 | AH84: 5834 | AI84: =AI26 -> 16829 | AJ84: =SUM(AJ81:AJ83) -> 33162 | AK84: 11019 | AL84: =AL26 -> 223 | AM84: =AM26 -> 0 | AN84: =AN26 -> 4316.5 | AO84: =SUM(AO81:AO83) -> 15558.5 | AP84: =AP26 -> 0 | AQ84: =AQ26 -> 0 | AR84: =AR26 -> 0 | AS84: =AS26 -> 0 | AT84: =SUM(AT81:AT83) -> 0 | AU84: =AU26 -> 0 | AV84: =AV26 -> 0 | AW84: =AW26 -> 0 | AX84: =AX26 -> 0 | AY84: =SUM(AY81:AY83) -> 0
A86: Sales Weights
A87: Americas | G87: =G49/G$52 -> 0.70127473 | H87: =H49/H$52 -> 0.69482679 | I87: =I49/I$52 -> 0.7147183 | J87: =J49/J$52 -> 0.73784094 | K87: =K49/K$52 -> 0.71648732 | L87: =L49/L$52 -> 0.73759062 | M87: =M49/M$52 -> 0.73166676 | N87: =N49/N$52 -> 0.75985351 | ... AY87: =AY49/AY$52 -> 0.81923141
A88: EMEA | G88: =G50/G$52 -> 0.23210448 | H88: =H50/H$52 -> 0.24529591 | I88: =I50/I$52 -> 0.2320665 | J88: =J50/J$52 -> 0.20969409 | K88: =K50/K$52 -> 0.22699643 | L88: =L50/L$52 -> 0.20348219 | M88: =M50/M$52 -> 0.22066254 | N88: =N50/N$52 -> 0.19792744 | ... AY88: =AY50/AY$52 -> 0.14360533
A89: APAC | G89: =G51/G$52 -> 0.06662079 | H89: =H51/H$52 -> 0.059877307 | I89: =I51/I$52 -> 0.053215202 | J89: =J51/J$52 -> 0.052464966 | K89: =K51/K$52 -> 0.056516255 | L89: =L51/L$52 -> 0.058927189 | M89: =M51/M$52 -> 0.047670694 | N89: =N51/N$52 -> 0.042219055 | ... AY89: =AY51/AY$52 -> 0.037163261
A91: Seasonality
A92: Americas | G92: =G49/K49 -> 0.15199853 | H92: =H49/K49 -> 0.21668264 | I92: =I49/K49 -> 0.26160922 | J92: =J49/K49 -> 0.36970961 | K92: =SUM(G92:J92) -> 1 | L92: =L49/P49 -> 0.20687654 | M92: =M49/P49 -> 0.22712963 | N92: =N49/P49 -> 0.24687374 | O92: =O49/P49 -> 0.3191201 | P92: =SUM(L92:O92) -> 1 | Q92: =Q49/U49 -> 0.21216205 | R92: =R49/U49 -> 0.2102245 | S92: =S49/U49 -> 0.2447164 | T92: =T49/U49 -> 0.33289705 | U92: =SUM(Q92:T92) -> 1 | V92: =V49/Z49 -> 0.19255949 | W92: =W49/Z49 -> 0.21165966 | X92: =X49/Z49 -> 0.25105544 | Y92: =Y49/Z49 -> 0.34472542 | Z92: =SUM(V92:Y92) -> 1 | AA92: =AA49/AE49 -> 0.20362958 | AB92: =AB49/AE49 -> 0.22376682 | AC92: =AC49/AE49 -> 0.24492752 | AD92: =AD49/AE49 -> 0.32767608 | AE92: =SUM(AA92:AD92) -> 1 | AF92: =AF49/AJ49 -> 0.20389824 | AG92: =AG49/AJ49 -> 0.22706534 | AH92: =AH49/AJ49 -> 0.24646868 | AI92: =AI49/AJ49 -> 0.32256774 | AJ92: =SUM(AF92:AI92) -> 1 | AK92: =AK49/AO49 -> 0.1983883 | AL92: =AL49/AO49 -> 0.22497244 | AM92: =AM49/AO49 -> 0.24669141 | AN92: =AN49/AO49 -> 0.32994785 | AO92: =SUM(AK92:AN92) -> 1 | AP92: =AP49/AT49 -> 0.19917094 | AQ92: =AQ49/AT49 -> 0.2247528 | AR92: =AR49/AT49 -> 0.24645056 | AS92: =AS49/AT49 -> 0.32962571 | AT92: =SUM(AP92:AS92) -> 1 | AU92: =AU49/AY49 -> 0.19917094 | AV92: =AV49/AY49 -> 0.2247528 | AW92: =AW49/AY49 -> 0.24645056 | AX92: =AX49/AY49 -> 0.32962571 | AY92: =SUM(AU92:AX92) -> 1
A93: EMEA | G93: =G50/K50 -> 0.15879039 | H93: =H50/K50 -> 0.24145008 | I93: =I50/K50 -> 0.26811436 | J93: =J50/K50 -> 0.33164517 | K93: =SUM(G93:J93) -> 1 | L93: =L50/P50 -> 0.21057859 | M93: =M50/P50 -> 0.25274411 | N93: =N50/P50 -> 0.23727009 | O93: =O50/P50 -> 0.29940721 | P93: =SUM(L93:O93) -> 1 | Q93: =Q50/U50 -> 0.24804852 | R93: =R50/U50 -> 0.24934648 | S93: =S50/U50 -> 0.21003395 | T93: =T50/U50 -> 0.29257106 | U93: =SUM(Q93:T93) -> 1 | V93: =V50/Z50 -> 0.20100015 | W93: =W50/Z50 -> 0.25027434 | X93: =X50/Z50 -> 0.22991905 | Y93: =Y50/Z50 -> 0.31880645 | Z93: =SUM(V93:Y93) -> 1 | AA93: =AA50/AE50 -> 0.21385326 | AB93: =AB50/AE50 -> 0.2591526 | AC93: =AC50/AE50 -> 0.23567492 | AD93: =AD50/AE50 -> 0.29131923 | AE93: =SUM(AA93:AD93) -> 1 | AF93: =AF50/AJ50 -> 0.22616667 | AG93: =AG50/AJ50 -> 0.24104676 | AH93: =AH50/AJ50 -> 0.2377466 | AI93: =AI50/AJ50 -> 0.29503997 | AJ93: =SUM(AF93:AI93) -> 1 | AK93: =AK50/AO50 -> 0.20890723 | AL93: =AL50/AO50 -> 0.25211457 | AM93: =AM50/AO50 -> 0.24962473 | AN93: =AN50/AO50 -> 0.28935347 | AO93: =SUM(AK93:AN93) -> 1 | AP93: =AP50/AT50 -> 0.21328654 | AQ93: =AQ50/AT50 -> 0.25739963 | AR93: =AR50/AT50 -> 0.24514873 | AS93: =AS50/AT50 -> 0.28416511 | AT93: =SUM(AP93:AS93) -> 1 | AU93: =AU50/AY50 -> 0.21328654 | AV93: =AV50/AY50 -> 0.25739963 | AW93: =AW50/AY50 -> 0.24514873 | AX93: =AX50/AY50 -> 0.28416511 | AY93: =SUM(AU93:AX93) -> 1
A94: APAC | G94: =G51/K51 -> 0.18306111 | H94: =H51/K51 -> 0.23672545 | I94: =I51/K51 -> 0.2469386 | J94: =J51/K51 -> 0.33327483 | K94: =SUM(G94:J94) -> 1 | L94: =L51/P51 -> 0.26817549 | M94: =M51/P51 -> 0.24011508 | N94: =N51/P51 -> 0.22256714 | O94: =O51/P51 -> 0.26914229 | P94: =SUM(L94:O94) -> 1 | Q94: =Q51/U51 -> 0.24992476 | R94: =R51/U51 -> 0.22587441 | S94: =S51/U51 -> 0.22891727 | T94: =T51/U51 -> 0.29528356 | U94: =SUM(Q94:T94) -> 1 | V94: =V51/Z51 -> 0.23541056 | W94: =W51/Z51 -> 0.2317197 | X94: =X51/Z51 -> 0.22398266 | Y94: =Y51/Z51 -> 0.30888708 | Z94: =SUM(V94:Y94) -> 1 | AA94: =AA51/AE51 -> 0.23799434 | AB94: =AB51/AE51 -> 0.21964212 | AC94: =AC51/AE51 -> 0.27182938 | AD94: =AD51/AE51 -> 0.27053416 | AE94: =SUM(AA94:AD94) -> 1 | AF94: =AF51/AJ51 -> 0.23752353 | AG94: =AG51/AJ51 -> 0.23548876 | AH94: =AH51/AJ51 -> 0.24506678 | AI94: =AI51/AJ51 -> 0.28192093 | AJ94: =SUM(AF94:AI94) -> 1 | AK94: =AK51/AO51 -> 0.23644888 | AL94: =AL51/AO51 -> 0.22454102 | AM94: =AM51/AO51 -> 0.24345617 | AN94: =AN51/AO51 -> 0.29555394 | AO94: =SUM(AK94:AN94) -> 1 | AP94: =AP51/AT51 -> 0.23721937 | AQ94: =AQ51/AT51 -> 0.22004435 | AR94: =AR51/AT51 -> 0.24579111 | AS94: =AS51/AT51 -> 0.29694517 | AT94: =SUM(AP94:AS94) -> 1 | AU94: =AU51/AY51 -> 0.22910042 | AV94: =AV51/AY51 -> 0.21296739 | AW94: =AW51/AY51 -> 0.25272865 | AX94: =AX51/AY51 -> 0.30520354 | AY94: =SUM(AU94:AX94) -> 1
A95: Total | G95: =G52/K52 -> 0.1552958 | H95: =H52/K52 -> 0.2234375 | I95: =I52/K52 -> 0.26225673 | J95: =J52/K52 -> 0.35900996 | K95: =SUM(G95:J95) -> 1 | L95: =L52/P52 -> 0.21046427 | M95: =M52/P52 -> 0.23293941 | N95: =N52/P52 -> 0.24379654 | O95: =O52/P52 -> 0.31279978 | P95: =SUM(L95:O95) -> 1 | Q95: =Q52/U52 -> 0.21979901 | R95: =R52/U52 -> 0.2177245 | S95: =S52/U52 -> 0.23800521 | T95: =T52/U52 -> 0.32447128 | U95: =SUM(Q95:T95) -> 1 | V95: =V52/Z52 -> 0.19529481 | W95: =W52/Z52 -> 0.21850399 | X95: =X52/Z52 -> 0.24679064 | Y95: =Y52/Z52 -> 0.33941057 | Z95: =SUM(V95:Y95) -> 1 | AA95: =AA52/AE52 -> 0.20626696 | AB95: =AB52/AE52 -> 0.22915107 | AC95: =AC52/AE52 -> 0.24430529 | AD95: =AD52/AE52 -> 0.32027668 | AE95: =SUM(AA95:AD95) -> 1 | AF95: =AF52/AJ52 -> 0.20836501 | AG95: =AG52/AJ52 -> 0.22948974 | AH95: =AH52/AJ52 -> 0.24507167 | AI95: =AI52/AJ52 -> 0.31707357 | AJ95: =SUM(AF95:AI95) -> 1 | AK95: =AK52/AO52 -> 0.20126377 | AL95: =AL52/AO52 -> 0.22888651 | AM95: =AM52/AO52 -> 0.24700109 | AN95: =AN52/AO52 -> 0.32284863 | AO95: =SUM(AK95:AN95) -> 1 | AP95: =AP52/AT52 -> 0.20261784 | AQ95: =AQ52/AT52 -> 0.22930852 | AR95: =AR52/AT52 -> 0.24623767 | AS95: =AS52/AT52 -> 0.32183597 | AT95: =SUM(AP95:AS95) -> 1 | AU95: =AU52/AY52 -> 0.20231029 | AV95: =AV52/AY52 -> 0.22900307 | AW95: =AW52/AY52 -> 0.24649692 | AX95: =AX52/AY52 -> 0.32218972 | AY95: =SUM(AU95:AX95) -> 1
A97: Operating Income & Margin
A98: Operating Income
A99: Americas | P99: 637308 | Q99: =297826-SUM(R99:S99) -> 86264 | R99: 85836 | S99: 125726 | T99: =U99-SUM(Q99:S99) -> 185619 | U99: 483445 | V99: 156445 | W99: 177063 | X99: 257440 | Y99: =Z99-SUM(V99:X99) -> 349344 | Z99: 940292 | AA99: 252347 | AB99: 275120 | AC99: 304542 | AD99: =AE99-SUM(AA99:AC99) -> 378484 | AE99: 1210493 | AF99: 226960 | AG99: =319829-38574 -> 281255 | AH99: 288586 | AI99: =AJ99-SUM(AF99:AH99) -> 351878 | AJ99: =1187253-38574 -> 1148679 | AK99: 230929 | AL99: =382599-100000 -> 282599 | AM99: =AM106*AM49 -> 310995.76 | AN99: =AN106*AN49 -> 388039.73 | AO99: =SUM(AK99:AN99) -> 1212563.5 | AP99: =AP106*AP49 -> 222468.8 | AQ99: =AQ106*AQ49 -> 272500.07 | AR99: =AR106*AR49 -> 299961.22 | AS99: =AS106*AS49 -> 372295.72 | AT99: =SUM(AP99:AS99) -> 1167225.8 | AU99: =AU106*AU49 -> 210860.37 | AV99: =AV106*AV49 -> 260048.64 | AW99: =AW106*AW49 -> 286342.56 | AX99: =AX106*AX49 -> 353208.09 | AY99: =SUM(AU99:AX99) -> 1110459.7
A100: EMEA | P100: 118235 | Q100: =30107-SUM(R100:S100) -> 9107 | R100: 17545 | S100: 3455 | T100: =U100-SUM(Q100:S100) -> 15078 | U100: 45185 | V100: -1485 | W100: 29860 | X100: 20795 | Y100: =Z100-SUM(V100:X100) -> 32046 | Z100: 81216 | AA100: 24501 | AB100: 38040 | AC100: 21708 | AD100: =AE100-SUM(AA100:AC100) -> 25572 | AE100: 109821 | AF100: 16034 | AG100: 24530 | AH100: 21484 | AI100: =AJ100-SUM(AF100:AH100) -> 29466 | AJ100: 91514 | AK100: 3404 | AL100: 27244 | AM100: =AM107*AM50 -> 20089.897 | AN100: =AN107*AN50 -> 25980.894 | AO100: =SUM(AK100:AN100) -> 76718.791 | AP100: =AP107*AP50 -> 1834.9513 | AQ100: =AQ107*AQ50 -> 26750.158 | AR100: =AR107*AR50 -> 18453.553 | AS100: =AS107*AS50 -> 24138.262 | AT100: =SUM(AP100:AS100) -> 71176.924 | AU100: =AU107*AU50 -> 61.165879 | AV100: =AV107*AV50 -> 25102.676 | AW100: =AW107*AW50 -> 16743.312 | AX100: =AX107*AX50 -> 22211.058 | AY100: =SUM(AU100:AX100) -> 64118.212
A101: APAC | P101: -20240 | Q101: =-21128-SUM(R101:S101) -> -9105 | R101: -6380 | S101: -5643 | T101: =U101-SUM(Q101:S101) -> -7979 | U101: -29107 | V101: -2547 | W101: -464 | X101: -3261 | Y101: =Z101-SUM(V101:X101) -> -4286 | Z101: -10558 | AA101: -322 | AB101: -3245 | AC101: -4181 | AD101: =AE101-SUM(AA101:AC101) -> -4263 | AE101: -12011 | AF101: -4410 | AG101: -5967 | AH101: -6306 | AI101: =AJ101-SUM(AF101:AH101) -> -10914 | AJ101: -27597 | AK101: -885 | AL101: -3396 | AM101: =AM108*AM51 -> -7762.1839 | AN101: =AN108*AN51 -> -14206.412 | AO101: =SUM(AK101:AN101) -> -26249.596 | AP101: =AP108*AP51 -> -3215.6323 | AQ101: =AQ108*AQ51 -> -5678.5541 | AR101: =AR108*AR51 -> -10776.953 | AS101: =AS108*AS51 -> -18192.724 | AT101: =SUM(AP101:AS101) -> -37863.863 | AU101: =AU108*AU51 -> -5487.7334 | AV101: =AV108*AV51 -> -7808.8066 | AW101: =AW108*AW51 -> -13997.916 | AX101: =AX108*AX51 -> -22421.758 | AY101: =SUM(AU101:AX101) -> -49716.213
A102: Not attributable | P102: =-5880-403622+17283+12100 -> -380119 | Q102: =-5972-299108+3901-SUM(R102:S102) -> -95992 | R102: =-2825-95388-979 -> -99192 | S102: =-1254-105747+1006 -> -105995 | T102: =U102-SUM(Q102:S102) -> -91665 | U102: =-9051-400508+2684+14031 -> -392844 | V102: =-1889-119405+2889+4436 -> -113969 | W102: =-3114-116198+2695 -> -116617 | X102: =-3202-132496-1256 -> -136954 | Y102: =Z102-SUM(V102:X102) -> -154303 | Z102: =-526279+4436 -> -521843 | AA102: -146677 | AB102: =-5002-129355+67 -> -134290 | AC102: =-4671-139691+1575 -> -142787 | AD102: =AE102-SUM(AA102:AC102) -> -143729 | AE102: -567483 | AF102: -137051 | AG102: =-131734 -> -131734 | AH102: -148743 | AI102: =AJ102-SUM(AF102:AH102) -> -134499 | AJ102: -552027 | AK102: -144651 | AL102: -153747 | AM102: =AM103-SUM(AM99:AM101) -> -154000.26 | AN102: =AN103-SUM(AN99:AN101) -> -111848.14 | AO102: =SUM(AK102:AN102) -> -564246.39 | AP102: =AP103-SUM(AP99:AP101) -> -117372.32 | AQ102: =AQ103-SUM(AQ99:AQ101) -> -132112.8 | AR102: =AR103-SUM(AR99:AR101) -> -133599.79 | AS102: =AS103-SUM(AS99:AS101) -> -81870.386 | AT102: =SUM(AP102:AS102) -> -464955.3 | AU102: =AU103-SUM(AU99:AU101) -> -96506.204 | AV102: =AV103-SUM(AV99:AV101) -> -111447.87 | AW102: =AW103-SUM(AW99:AW101) -> -109841.78 | AX102: =AX103-SUM(AX99:AX101) -> -43912.979 | AY102: =SUM(AU102:AX102) -> -361708.84
A103: Total | P103: =SUM(P99:P102) -> 355184 | Q103: =SUM(Q99:Q102) -> -9726 | R103: =SUM(R99:R102) -> -2191 | S103: =SUM(S99:S102) -> 17543 | T103: =SUM(T99:T102) -> 101053 | U103: =SUM(U99:U102) -> 106679 | V103: =SUM(V99:V102) -> 38444 | W103: =SUM(W99:W102) -> 89842 | ... AL103: =SUM(AL99:AL102) -> 152700 | AM103: =IS!AM12 -> 169323.22 | AN103: =IS!AN12 -> 287966.07 | AO103: =SUM(AK103:AN103) -> 698786.29 | AP103: =IS!AP12 -> 103715.79 | AQ103: =IS!AQ12 -> 161458.87 | AR103: =IS!AR12 -> 174038.03 | AS103: =IS!AS12 -> 296370.87 | AT103: =SUM(AP103:AS103) -> 735583.57 | AU103: =IS!AU12 -> 108927.6 | AV103: =IS!AV12 -> 165894.63 | AW103: =IS!AW12 -> 179246.18 | AX103: =IS!AX12 -> 309084.42 | AY103: =SUM(AU103:AX103) -> 763152.83
P104: =IF(P103-IS!P12=0,"-",P103-IS!P12) -> - | U104: =IF(U103-IS!U12=0,"-",U103-IS!U12) -> - | V104: =IF(V103-IS!V12=0,"-",V103-IS!V12) -> - | W104: =IF(W103-IS!W12=0,"-",W103-IS!W12) -> - | X104: =IF(X103-IS!X12=0,"-",X103-IS!X12) -> - | Y104: =IF(Y103-IS!Y12=0,"-",Y103-IS!Y12) -> - | Z104: =IF(Z103-IS!Z12=0,"-",Z103-IS!Z12) -> - | AA104: =IF(AA103-IS!AA12=0,"-",AA103-IS!AA12) -> - | AB104: =IF(AB103-IS!AB12=0,"-",AB103-IS!AB12) -> - | ... AL104: =IF(AL103-IS!AL12=0,"-",AL103-IS!AL12) -> -
A105: Operating Margin
A106: Americas | P106: =P99/P49 -> 0.22875418 | Q106: =Q99/Q49 -> 0.13938368 | R106: =R99/R49 -> 0.13997039 | S106: =S99/S49 -> 0.17612137 | T106: =T99/T49 -> 0.19114481 | U106: =U99/U49 -> 0.16572846 | V106: =V99/V49 -> 0.23510609 | W106: =W99/W49 -> 0.24207884 | ... AL106: =AL99/AL49 -> 0.27691206 | AM106: =AH106+AM112/10^4 -> 0.27790798 | AN106: =AI106+AN112/10^4 -> 0.25925758 | AO106: =AO99/AO49 -> 0.26730376 | AP106: =AK106+AP112/10^4 -> 0.23760374 | AQ106: =AL106+AQ112/10^4 -> 0.25791206 | AR106: =AM106+AR112/10^4 -> 0.25890798 | AS106: =AN106+AS112/10^4 -> 0.24025758 | AT106: =AT99/AT49 -> 0.24829331 | AU106: =AP106+AU112/10^4 -> 0.21860374 | AV106: =AQ106+AV112/10^4 -> 0.23891206 | AW106: =AR106+AW112/10^4 -> 0.23990798 | AX106: =AS106+AX112/10^4 -> 0.22125758 | AY106: =AY99/AY49 -> 0.22929331
A107: EMEA | P107: =P100/P50 -> 0.15658772 | Q107: =Q100/Q50 -> 0.055540986 | R107: =R100/R50 -> 0.10644494 | S107: =S100/S50 -> 0.024884759 | T107: =T100/T50 -> 0.077962771 | U107: =U100/U50 -> 0.068354825 | V107: =V100/V50 -> -0.01075261 | W107: =W100/W50 -> 0.17364301 | ... AL107: =AL100/AL50 -> 0.13487796 | AM107: =AH107+AM113/10^4 -> 0.1004519 | AN107: =AI107+AN113/10^4 -> 0.11207106 | AO107: =AO100/AO50 -> 0.095756844 | AP107: =AK107+AP113/10^4 -> 0.010337808 | AQ107: =AL107+AQ113/10^4 -> 0.12487796 | AR107: =AM107+AR113/10^4 -> 0.090451905 | AS107: =AN107+AS113/10^4 -> 0.10207106 | AT107: =AT100/AT50 -> 0.085527659 | AU107: =AP107+AU113/10^4 -> 0.00033780837 | AV107: =AQ107+AV113/10^4 -> 0.11487796 | AW107: =AR107+AW113/10^4 -> 0.080451905 | AX107: =AS107+AX113/10^4 -> 0.092071057 | AY107: =AY100/AY50 -> 0.075527659
A108: APAC | P108: =P101/P51 -> -0.11787934 | Q108: =Q101/Q51 -> -0.30454561 | R108: =R101/R51 -> -0.23612139 | S108: =S101/S51 -> -0.20606924 | T108: =T101/T51 -> -0.22588682 | U108: =U101/U51 -> -0.24332074 | V108: =V101/V51 -> -0.078453719 | W108: =W101/W51 -> -0.014519965 | ... AL108: =AL101/AL51 -> -0.076898691 | AM108: =AH108+AM114/10^4 -> -0.16211011 | AN108: =AI108+AN114/10^4 -> -0.24439629 | AO108: =AO101/AO51 -> -0.13346567 | AP108: =AK108+AP114/10^4 -> -0.064030621 | AQ108: =AL108+AQ114/10^4 -> -0.12189869 | AR108: =AM108+AR114/10^4 -> -0.20711011 | AS108: =AN108+AS114/10^4 -> -0.28939629 | AT108: =AT101/AT51 -> -0.17885308 | AU108: =AP108+AU114/10^4 -> -0.10903062 | AV108: =AQ108+AV114/10^4 -> -0.16689869 | AW108: =AR108+AW114/10^4 -> -0.25211011 | AX108: =AS108+AX114/10^4 -> -0.33439629 | AY108: =AY101/AY51 -> -0.22629732
A109: Total | P109: =P103/P52 -> 0.095665552 | Q109: =Q103/Q52 -> -0.011966603 | R109: =R103/R52 -> -0.0027214315 | S109: =S103/S52 -> 0.019933325 | T109: =T103/T52 -> 0.084223888 | U109: =U103/U52 -> 0.028849698 | V109: =V103/V52 -> 0.045985976 | W109: =W103/W52 -> 0.096052259 | ... AY109: =AY103/AY52 -> 0.12909419
A111: Margin Bps. Chg. YoY
A112: Americas | U112: =(ROUND(U106,3)-ROUND(P106,3))*10^4 -> -630 | V112: =(ROUND(V106,3)-ROUND(Q106,3))*10^4 -> 960 | W112: =(ROUND(W106,3)-ROUND(R106,3))*10^4 -> 1020 | X112: =(ROUND(X106,3)-ROUND(S106,3))*10^4 -> 1210 | Y112: =(ROUND(Y106,3)-ROUND(T106,3))*10^4 -> 1020 | Z112: =(ROUND(Z106,3)-ROUND(U106,3))*10^4 -> 1060 | AA112: =(ROUND(AA106,3)-ROUND(V106,3))*10^4 -> 730 | AB112: =(ROUND(AB106,3)-ROUND(W106,3))*10^4 -> 630 | ... AL112: =(ROUND(AL106,3)-ROUND(AG106,3))*10^4 -> -120 | AM112: 50 | AN112: 50 | AO112: =(ROUND(AO106,3)-ROUND(AJ106,3))*10^4 -> -10 | AP112: -190 | AQ112: -190 | AR112: -190 | AS112: -190 | AT112: =(ROUND(AT106,3)-ROUND(AO106,3))*10^4 -> -190 | AU112: -190 | AV112: -190 | AW112: -190 | AX112: -190 | AY112: =(ROUND(AY106,3)-ROUND(AT106,3))*10^4 -> -190
A113: EMEA | U113: =(ROUND(U107,3)-ROUND(P107,3))*10^4 -> -890 | V113: =(ROUND(V107,3)-ROUND(Q107,3))*10^4 -> -670 | W113: =(ROUND(W107,3)-ROUND(R107,3))*10^4 -> 680 | X113: =(ROUND(X107,3)-ROUND(S107,3))*10^4 -> 1070 | Y113: =(ROUND(Y107,3)-ROUND(T107,3))*10^4 -> 680 | Z113: =(ROUND(Z107,3)-ROUND(U107,3))*10^4 -> 500 | AA113: =(ROUND(AA107,3)-ROUND(V107,3))*10^4 -> 1600 | AB113: =(ROUND(AB107,3)-ROUND(W107,3))*10^4 -> 170 | ... AL113: =(ROUND(AL107,3)-ROUND(AG107,3))*10^4 -> 110 | AM113: -100 | AN113: -100 | AO113: =(ROUND(AO107,3)-ROUND(AJ107,3))*10^4 -> -160 | AP113: -100 | AQ113: -100 | AR113: -100 | AS113: -100 | AT113: =(ROUND(AT107,3)-ROUND(AO107,3))*10^4 -> -100 | AU113: -100 | AV113: -100 | AW113: -100 | AX113: -100 | AY113: =(ROUND(AY107,3)-ROUND(AT107,3))*10^4 -> -100
A114: APAC | U114: =(ROUND(U108,3)-ROUND(P108,3))*10^4 -> -1250 | V114: =(ROUND(V108,3)-ROUND(Q108,3))*10^4 -> 2270 | W114: =(ROUND(W108,3)-ROUND(R108,3))*10^4 -> 2210 | X114: =(ROUND(X108,3)-ROUND(S108,3))*10^4 -> 1000 | Y114: =(ROUND(Y108,3)-ROUND(T108,3))*10^4 -> 1250 | Z114: =(ROUND(Z108,3)-ROUND(U108,3))*10^4 -> 1660 | AA114: =(ROUND(AA108,3)-ROUND(V108,3))*10^4 -> 690 | AB114: =(ROUND(AB108,3)-ROUND(W108,3))*10^4 -> -830 | ... AL114: =(ROUND(AL108,3)-ROUND(AG108,3))*10^4 -> 840 | AM114: 10 | AN114: 10 | AO114: =(ROUND(AO108,3)-ROUND(AJ108,3))*10^4 -> 420 | AP114: -450 | AQ114: -450 | AR114: -450 | AS114: -450 | AT114: =(ROUND(AT108,3)-ROUND(AO108,3))*10^4 -> -460 | AU114: -450 | AV114: -450 | AW114: -450 | AX114: -450 | AY114: =(ROUND(AY108,3)-ROUND(AT108,3))*10^4 -> -470
A115: Total | U115: =(ROUND(U109,3)-ROUND(P109,3))*10^4 -> -670 | V115: =(ROUND(V109,3)-ROUND(Q109,3))*10^4 -> 580 | W115: =(ROUND(W109,3)-ROUND(R109,3))*10^4 -> 990 | X115: =(ROUND(X109,3)-ROUND(S109,3))*10^4 -> 1110 | Y115: =(ROUND(Y109,3)-ROUND(T109,3))*10^4 -> 690 | Z115: =(ROUND(Z109,3)-ROUND(U109,3))*10^4 -> 850 | AA115: =(ROUND(AA109,3)-ROUND(V109,3))*10^4 -> 810 | AB115: =(ROUND(AB109,3)-ROUND(W109,3))*10^4 -> 590 | ... AY115: =(ROUND(AY109,3)-ROUND(AT109,3))*10^4 -> 10
A117: OI % Chg. YoY
A118: Americas | U118: =(U99-P99)/ABS(P99) -> -0.24142644 | V118: =(V99-Q99)/ABS(Q99) -> 0.8135607 | W118: =(W99-R99)/ABS(R99) -> 1.0628058 | X118: =(X99-S99)/ABS(S99) -> 1.0476274 | Y118: =(Y99-T99)/ABS(T99) -> 0.88204871 | Z118: =(Z99-U99)/ABS(U99) -> 0.94498237 | AA118: =(AA99-V99)/ABS(V99) -> 0.61300777 | AB118: =(AB99-W99)/ABS(W99) -> 0.55379724 | ... AY118: =(AY99-AT99)/ABS(AT99) -> -0.048633377
A119: EMEA | U119: =(U100-P100)/ABS(P100) -> -0.61783736 | V119: =(V100-Q100)/ABS(Q100) -> -1.1630614 | W119: =(W100-R100)/ABS(R100) -> 0.70190938 | X119: =(X100-S100)/ABS(S100) -> 5.0188133 | Y119: =(Y100-T100)/ABS(T100) -> 1.1253482 | Z119: =(Z100-U100)/ABS(U100) -> 0.79741065 | AA119: =(AA100-V100)/ABS(V100) -> 17.49899 | AB119: =(AB100-W100)/ABS(W100) -> 0.27394508 | ... AY119: =(AY100-AT100)/ABS(AT100) -> -0.099171358
A120: APAC | U120: =(U101-P101)/ABS(P101) -> -0.43809289 | V120: =(V101-Q101)/ABS(Q101) -> 0.72026359 | W120: =(W101-R101)/ABS(R101) -> 0.92727273 | X120: =(X101-S101)/ABS(S101) -> 0.4221159 | Y120: =(Y101-T101)/ABS(T101) -> 0.46283995 | Z120: =(Z101-U101)/ABS(U101) -> 0.63726939 | AA120: =(AA101-V101)/ABS(V101) -> 0.87357676 | AB120: =(AB101-W101)/ABS(W101) -> -5.9935345 | ... AY120: =(AY101-AT101)/ABS(AT101) -> -0.31302539
A121: Not attributable | U121: =(U102-P102)/ABS(P102) -> -0.033476359 | V121: =(V102-Q102)/ABS(Q102) -> -0.18727602 | W121: =(W102-R102)/ABS(R102) -> -0.17566941 | X121: =(X102-S102)/ABS(S102) -> -0.29207982 | Y121: =(Y102-T102)/ABS(T102) -> -0.68333606 | Z121: =(Z102-U102)/ABS(U102) -> -0.32837208 | AA121: =(AA102-V102)/ABS(V102) -> -0.28699032 | AB121: =(AB102-W102)/ABS(W102) -> -0.15154737 | ... AY121: =(AY102-AT102)/ABS(AT102) -> 0.22205674
...

Sheet IS
A1: ANF P&L | AE1: 0.44
U2: Old Opex <-| | V2: |-> New Opex
A3: Period | B3: ='Rev Driver'!B3 -> FY15 | C3: ='Rev Driver'!C3 -> FY16 | D3: ='Rev Driver'!D3 -> FY17 | E3: ='Rev Driver'!E3 -> FY18 | F3: ='Rev Driver'!F3 -> FY19 | G3: ='Rev Driver'!G3 -> 1Q20 | H3: ='Rev Driver'!H3 -> 2Q20 | I3: ='Rev Driver'!I3 -> 3Q20 | ... AY3: ='Rev Driver'!AY3 -> FY28E
A4: Date end | B4: ='Rev Driver'!B4 -> 42399 | C4: ='Rev Driver'!C4 -> 42763 | D4: ='Rev Driver'!D4 -> 43134 | E4: ='Rev Driver'!E4 -> 43498 | F4: ='Rev Driver'!F4 -> 43862 | G4: ='Rev Driver'!G4 -> 43953 | H4: ='Rev Driver'!H4 -> 44044 | I4: 44135 | J4: ='Rev Driver'!J4 -> 44226 | K4: ='Rev Driver'!K4 -> 44226 | L4: ='Rev Driver'!L4 -> 44317 | M4: ='Rev Driver'!M4 -> 44408 | N4: ='Rev Driver'!N4 -> 44500 | O4: ='Rev Driver'!O4 -> 44590 | P4: ='Rev Driver'!P4 -> 44590 | Q4: ='Rev Driver'!Q4 -> 44681 | ... AY4: ='Rev Driver'!AY4 -> 47145
A5: # Weeks | B5: ='Rev Driver'!B5 -> 52 | C5: ='Rev Driver'!C5 -> 52 | D5: ='Rev Driver'!D5 -> 53 | E5: ='Rev Driver'!E5 -> 52 | F5: ='Rev Driver'!F5 -> 52 | G5: ='Rev Driver'!G5 -> 13 | H5: ='Rev Driver'!H5 -> 13 | I5: ='Rev Driver'!I5 -> 13 | ... AY5: ='Rev Driver'!AY5 -> 52
A6: Net Sales | B6: ='Rev Driver'!B9 -> 3518680 | C6: ='Rev Driver'!C9 -> 3326740 | D6: ='Rev Driver'!D9 -> 3492690 | E6: ='Rev Driver'!E9 -> 3590109 | F6: ='Rev Driver'!F9 -> 3623073 | G6: ='Rev Driver'!G9 -> 485359 | H6: ='Rev Driver'!H9 -> 698328 | I6: ='Rev Driver'!I9 -> 819653 | ... AY6: ='Rev Driver'!AY9 -> 5911596.9
A7: COGS | B7: =1361137-20647 -> 1340490 | C7: 1298172 | D7: 1408848 | E7: 1430193 | F7: 1472155 | G7: 221214 | H7: 274720 | I7: 295220 | J7: 443025 | K7: =SUM(G7:J7) -> 1234179 | L7: 286271 | M7: 301365 | N7: 328916 | O7: 484221 | P7: =SUM(L7:O7) -> 1400773 | Q7: 363216 | R7: 339200 | S7: 359268 | T7: 531529 | U7: =SUM(Q7:T7) -> 1593213 | V7: 326200 | W7: 350965 | X7: 370762 | Y7: 539338 | Z7: =SUM(V7:Y7) -> 1587265 | AA7: 343273 | AB7: 397712 | AC7: 422034 | AD7: 610907 | AE7: =SUM(AA7:AD7) -> 1773926 | AF7: 417133 | AG7: =451590 -> 451590 | AH7: 483670 | AI7: 676491 | AJ7: =SUM(AF7:AI7) -> 2028884 | AK7: 413838 | AL7: =366109+100000 -> 466109 | AM7: =AM6-AM8 -> 494500.81 | AN7: =AN6-AN8 -> 693471.67 | AO7: =SUM(AK7:AN7) -> 2067919.5 | AP7: =AP6-AP8 -> 431325.7 | AQ7: =AQ6-AQ8 -> 483436 | AR7: =AR6-AR8 -> 510333.19 | AS7: =AS6-AS8 -> 715776.32 | AT7: =SUM(AP7:AS7) -> 2140871.2 | AU7: =AU6-AU8 -> 440774.93 | AV7: =AV6-AV8 -> 496800.21 | AW7: =AW6-AW8 -> 525693.34 | AX7: =AX6-AX8 -> 733544.76 | AY7: =SUM(AU7:AX7) -> 2196813.2
A8: Adj. Gross Profit | B8: =B6-B7 -> 2178190 | C8: =C6-C7 -> 2028568 | D8: =D6-D7 -> 2083842 | E8: =E6-E7 -> 2159916 | F8: =F6-F7 -> 2150918 | G8: =G6-G7 -> 264145 | H8: =H6-H7 -> 423608 | I8: =I6-I7 -> 524433 | ... AL8: =AL6-AL7 -> 800580 | AM8: =AM$6*AM26 -> 872436.75 | AN8: =AN$6*AN26 -> 1093216.5 | AO8: =AO6-AO7 -> 3466216.2 | AP8: =AP$6*AP26 -> 732695.33 | AQ8: =AQ$6*AQ26 -> 833920.56 | AR8: =AR$6*AR26 -> 904279.83 | AS8: =AS$6*AS26 -> 1133142 | AT8: =AT6-AT7 -> 3604037.7 | AU8: =AU$6*AU26 -> 755201.96 | AV8: =AV$6*AV26 -> 856973.64 | AW8: =AW$6*AW26 -> 931497.11 | AX8: =AX$6*AX26 -> 1171111 | AY8: =AY6-AY7 -> 3714783.7
A9: Selling Exp. | B9: =1604214-6665 -> 1597549 | C9: 1578460 | D9: 1542425 | E9: 1542022 | F9: 1551243 | G9: 322124 | H9: 310370 | I9: 346263 | J9: 412827 | K9: =SUM(G9:J9) -> 1391584 | L9: 316608 | M9: 325847 | N9: 351815 | O9: 435153 | P9: =SUM(L9:O9) -> 1429423 | Q9: 337543 | R9: 340791 | S9: 367333 | T9: 437264 | U9: =SUM(Q9:T9) -> 1482931 | V9: =324251-4436 -> 319815 | W9: 338296 | X9: 371969 | Y9: 498922 | Z9: =SUM(V9:Y9) -> 1529002 | AA9: 360018 | AB9: 382557 | AC9: 420990 | AD9: 526423 | AE9: =SUM(AA9:AD9) -> 1689988 | AF9: 399937 | AG9: =375356+42874 -> 418230 | AH9: 459548 | AI9: 574792 | AJ9: =SUM(AF9:AI9) -> 1852507 | AK9: 431195 | AL9: 444042 | AM9: =AM$6*AM29 -> 493557.28 | AN9: =AN$6*AN29 -> 609667.38 | AO9: =SUM(AK9:AN9) -> 1978461.7 | AP9: =AP$6*AP29 -> 442480.86 | AQ9: =AQ$6*AQ29 -> 464438.39 | AR9: =AR$6*AR29 -> 513600.58 | AS9: =AS$6*AS29 -> 634599.88 | AT9: =SUM(AP9:AS9) -> 2055119.7 | AU9: =AU$6*AU29 -> 455824.26 | AV9: =AV$6*AV29 -> 478631.2 | AW9: =AW$6*AW29 -> 530516.27 | AX9: =AX$6*AX29 -> 655635.15 | AY9: =SUM(AU9:AX9) -> 2120606.9
A10: G&A Exp. | B10: =470321-17523 -> 452798 | C10: =453202+6000 -> 459202 | D10: =471914-15070 -> 456844 | E10: =484863-2595 -> 482268 | F10: 464615 | G10: 108257 | H10: 97252 | I10: 121000 | J10: 137334 | K10: =SUM(G10:J10) -> 463843 | L10: 120947 | M10: 123913 | N10: 146269 | O10: 145686 | P10: =SUM(L10:O10) -> 536815 | Q10: 122149 | R10: 124168 | S10: 133201 | T10: 138084 | U10: =SUM(Q10:T10) -> 517602 | V10: =154429 -> 154429 | W10: 158936 | X10: 174424 | Y10: 193387 | Z10: =SUM(V10:Y10) -> 681176 | AA10: 189548 | AB10: 178147 | AC10: 188246 | AD10: 194544 | AE10: =SUM(AA10:AD10) -> 750485 | AF10: 174925 | AG10: =175325-4300 -> 171025 | AH10: 193402 | AI10: 181819 | AJ10: =SUM(AF10:AI10) -> 721171 | AK10: 182754 | AL10: 204784 | AM10: =AM$6*AM36 -> 210306.25 | AN10: =AN$6*AN36 -> 196333.02 | AO10: =SUM(AK10:AN10) -> 794177.27 | AP10: =AP$6*AP36 -> 187498.68 | AQ10: =AQ$6*AQ36 -> 209023.29 | AR10: =AR$6*AR36 -> 217641.22 | AS10: =AS$6*AS36 -> 203171.28 | AT10: =SUM(AP10:AS10) -> 817334.47 | AU10: =AU$6*AU36 -> 191450.1 | AV10: =AV$6*AV36 -> 213447.8 | AW10: =AW$6*AW36 -> 222734.66 | AX10: =AX$6*AX36 -> 207391.42 | AY10: =SUM(AU10:AX10) -> 835023.98
A11: Other Loss/(Inc.) | B11: =-6441-2211 -> -8652 | C11: =(-26212+12282)+1574 -> -12356 | D11: =-16938+(14391-13661) -> -16208 | E11: =-5915+(11580-8671) -> -3006 | F11: =-1400+(19135-12752)+47257 -> 52240 | G11: =-543+506 -> -37 | H11: =-3884-2356 -> -6240 | I11: =-8063+288 -> -7775 | J11: =854-3492 -> -2638 | K11: =SUM(G11:J11) -> -16690 | L11: =-1418-1100 -> -2518 | M11: -1848 | N11: -1320 | O11: -3741 | P11: =SUM(L11:O11) -> -9427 | Q11: -3842 | R11: 953 | S11: -1005 | T11: 1220 | U11: =SUM(Q11:T11) -> -2674 | V11: -2894 | W11: -2694 | X11: 1256 | Y11: -1541 | Z11: =SUM(V11:Y11) -> -5873 | AA11: -1958 | AB11: -67 | AC11: -1586 | AD11: -3021 | AE11: =SUM(AA11:AD11) -> -6632 | AF11: 3783 | AG11: =-369 -> -369 | AH11: -1022 | AI11: 769 | AJ11: =SUM(AF11:AI11) -> 3161 | AK11: -2763 | AL11: -946 | AM11: -750 | AN11: -750 | AO11: =SUM(AK11:AN11) -> -5209 | AP11: -1000 | AQ11: -1000 | AR11: -1000 | AS11: -1000 | AT11: =SUM(AP11:AS11) -> -4000 | AU11: -1000 | AV11: -1000 | AW11: -1000 | AX11: -1000 | AY11: =SUM(AU11:AX11) -> -4000
A12: Adj. Operating Income | B12: =B6-B7-B9-B10-B11 -> 136495 | C12: =C6-C7-C9-C10-C11 -> 3262 | D12: =D6-D7-D9-D10-D11 -> 100781 | E12: =E6-E7-E9-E10-E11 -> 138632 | F12: =F6-F7-F9-F10-F11 -> 82820 | G12: =G6-G7-G9-G10-G11 -> -166199 | H12: =H6-H7-H9-H10-H11 -> 22226 | I12: =I6-I7-I9-I10-I11 -> 64945 | ... AY12: =AY6-AY7-AY9-AY10-AY11 -> 763152.83
A13: Interest Exp. Net | B13: 18248 | C13: 18666 | D13: 16889 | E13: 10999 | F13: 7737 | G13: 3371 | H13: 7098 | I13: 8808 | J13: 8997 | K13: =SUM(G13:J13) -> 28274 | L13: 8606 | M13: 11275 | N13: 7270 | O13: 6959 | P13: =SUM(L13:O13) -> 34110 | Q13: 7307 | R13: 6917 | S13: 7295 | T13: 4113 | U13: =SUM(Q13:T13) -> 25632 | V13: =7458-4015 -> 3443 | W13: =7635-6538 -> 1097 | X13: =8568-7897 -> 671 | Y13: =6691-11530 -> -4839 | Z13: =SUM(V13:Y13) -> 372 | AA13: =-10803+5780 -> -5023 | AB13: =-10392+5189 -> -5203 | AC13: =-9302+569 -> -8733 | AD13: =-9437+539 -> -8898 | AE13: =SUM(AA13:AD13) -> -27857 | AF13: =-7444+661 -> -6783 | AG13: =620-3094 -> -2474 | AH13: =-6491+550 -> -5941 | AI13: =544-6975 -> -6431 | AJ13: =SUM(AF13:AI13) -> -21629 | AK13: =450-5737 -> -5287 | AL13: =561-8152+3084 -> -4507 | AM13: -4500 | AN13: -5500 | AO13: =SUM(AK13:AN13) -> -19794 | AP13: -4500 | AQ13: -4500 | AR13: -4500 | AS13: -5000 | AT13: =SUM(AP13:AS13) -> -18500 | AU13: -4500 | AV13: -4500 | AW13: -4500 | AX13: -5000 | AY13: =SUM(AU13:AX13) -> -18500
A14: Adj. Pre-Tax Income | B14: =B12-B13 -> 118247 | C14: =C12-C13 -> -15404 | D14: =D12-D13 -> 83892 | E14: =E12-E13 -> 127633 | F14: =F12-F13 -> 75083 | G14: =G12-G13 -> -169570 | H14: =H12-H13 -> 15128 | I14: =I12-I13 -> 56137 | ... AY14: =AY12-AY13 -> 781652.83
A15: Tax | B15: =16031+21186 -> 37217 | C15: =-11196-3900 -> -15096 | D15: =44636-9180 -> 35456 | E15: =37559+6018 -> 43577 | F15: =17371+4013 -> 21384 | G15: 35965 | H15: 87 | I15: 6148 | J15: 22310 | K15: =SUM(G15:J15) -> 64510 | L15: =6121+449 -> 6570 | M15: =-6944+224 -> -6720 | N15: 17758 | O15: 23721 | P15: =SUM(L15:O15) -> 41329 | Q15: =-2187--918 -> -1269 | R15: =4976-Q15 -> 6245 | S15: =-SUM(Q15:R15)+16918 -> 11942 | T15: 43515 | U15: =SUM(Q15:T15) -> 60433 | V15: 13905 | W15: =-V15+43939 -> 30034 | X15: =-SUM(V15:W15)+83556 -> 39617 | Y15: =-SUM(V15:X15)+150117 -> 66561 | Z15: =SUM(V15:Y15) -> 150117 | AA15: 19794 | AB15: 45449 | AC15: 54151 | AD15: 75267 | AE15: =SUM(AA15:AD15) -> 194661 | AF15: 26577 | AG15: =65744-9692 -> 56052 | AH15: 45862 | AI15: 67594 | AJ15: =SUM(AF15:AI15) -> 196085 | AK15: 25965 | AL15: =74752-(100000+3084-AL21) -> 48757.25 | AM15: =AM$14*AM45 -> 50408.734 | AN15: =AN$14*AN45 -> 82170.501 | AO15: =SUM(AK15:AN15) -> 207301.48 | AP15: =AP$14*AP45 -> 32464.738 | AQ15: =AQ$14*AQ45 -> 49787.662 | AR15: =AR$14*AR45 -> 53561.409 | AS15: =AS$14*AS45 -> 90411.261 | AT15: =SUM(AP15:AS15) -> 226225.07 | AU15: =AU$14*AU45 -> 34028.281 | AV15: =AV$14*AV45 -> 51118.39 | AW15: =AW$14*AW45 -> 55123.854 | AX15: =AX$14*AX45 -> 94225.325 | AY15: =SUM(AU15:AX15) -> 234495.85
A16: NCI | B16: 2983 | C16: 3762 | D16: 3431 | E16: 4267 | F16: 5602 | G16: 117 | H16: 328 | I16: 1758 | J16: 2864 | K16: =SUM(G16:J16) -> 5067 | L16: 938 | M16: 1956 | N16: 1845 | O16: 2317 | P16: =SUM(L16:O16) -> 7056 | Q16: 1623 | R16: 2092 | S16: 1496 | T16: 2358 | U16: =SUM(Q16:T16) -> 7569 | V16: 1276 | W16: =-V16+3113 -> 1837 | X16: 1521 | Y16: 2656 | Z16: =SUM(V16:Y16) -> 7290 | AA16: 1228 | AB16: 2211 | AC16: 1885 | AD16: 2469 | AE16: =SUM(AA16:AD16) -> 7793 | AF16: 1326 | AG16: =2005 -> 2005 | AH16: 2105 | AI16: 2638 | AJ16: =SUM(AF16:AI16) -> 8074 | AK16: 985 | AL16: 1819 | AM16: =AM$14*AM46 -> 1738.2322 | AN16: =AN$14*AN46 -> 2934.6607 | AO16: =SUM(AK16:AN16) -> 7476.8929 | AP16: =AP$14*AP46 -> 1082.1579 | AQ16: =AQ$14*AQ46 -> 1825.5476 | AR16: =AR$14*AR46 -> 1963.9183 | AS16: =AS$14*AS46 -> 3013.7087 | AT16: =SUM(AP16:AS16) -> 7885.3326 | AU16: =AU$14*AU46 -> 1247.7036 | AV16: =AV$14*AV46 -> 1874.341 | AW16: =AW$14*AW46 -> 2021.208 | AX16: =AX$14*AX46 -> 3140.8442 | AY16: =SUM(AU16:AX16) -> 8284.0967
A17: Adj. Net Income | B17: =B14-B15-B16 -> 78047 | C17: =C14-C15-C16 -> -4070 | D17: =D14-D15-D16 -> 45005 | E17: =E14-E15-E16 -> 79789 | F17: =F14-F15-F16 -> 48097 | G17: =G14-G15-G16 -> -205652 | H17: =H14-H15-H16 -> 14713 | I17: =I14-I15-I16 -> 48231 | ... AY17: =AY14-AY15-AY16 -> 538872.88
A18: Diluted EPS | B18: =B17/B19 -> 1.1243211 | C18: =C17/C19 -> -0.059960517 | D18: =D17/D19 -> 0.648459 | E18: =E17/E19 -> 1.1540709 | F18: =F17/F19 -> 0.73120192 | G18: =G17/G19 -> -3.2882749 | H18: =H17/H19 -> 0.23248428 | I18: =I17/I19 -> 0.75506051 | ... AY18: =AY17/AY19 -> 13.448709
A19: Diluted Shares Out | B19: 69417 | C19: 67878 | D19: 69403 | E19: 69137 | F19: 65778 | G19: 62541 | H19: 63286 | I19: 63877 | J19: 64788 | K19: 62636 | L19: 65305 | M19: 64136 | N19: 61465 | O19: 58700 | P19: 62636 | Q19: 52077 | R19: 50441 | S19: 49486 | T19: 51217 | U19: 52327 | V19: 51467 | W19: 51548 | X19: 52624 | Y19: 53399 | Z19: 52726 | AA19: 53276 | AB19: 53279 | AC19: 52869 | AD19: 52461 | AE19: 52971 | AF19: 50634 | AG19: 48551 | AH19: 47881 | AI19: 46837 | AJ19: 48476 | AK19: 45677 | AL19: 44051 | AM19: =SCF!AM61 -> 43434.333 | AN19: =SCF!AN61 -> 42826.743 | AO19: =AVERAGE(AK19:AN19) -> 43997.269 | AP19: =SCF!AP61 -> 42398.212 | AQ19: =SCF!AQ61 -> 41976.152 | AR19: =SCF!AR61 -> 41560.498 | AS19: =SCF!AS61 -> 41151.188 | AT19: =AVERAGE(AP19:AS19) -> 41771.512 | AU19: =SCF!AU61 -> 40712.409 | AV19: =SCF!AV61 -> 40279.461 | AW19: =SCF!AW61 -> 39852.284 | AX19: =SCF!AX61 -> 39430.821 | AY19: =AVERAGE(AU19:AX19) -> 40068.744
A21: Adj. to Net Income | B21: -42471 | C21: 8026 | D21: -37911 | E21: -5248 | F21: -8739 | G21: -38496 | H21: -9249 | I21: -5960 | J21: -14933 | K21: =SUM(G21:J21) -> -68638 | L21: -2215 | M21: -562 | N21: -5374 | O21: -1528 | P21: =SUM(L21:O21) -> -9679 | Q21: -2504 | R21: =-16834-R17 -> -1559 | S21: =-2214-S17 -> -2768 | T21: -3398 | U21: =SUM(Q21:T21) -> -10229 | V21: -3249 | W21: =-V21-3229 -> 20 | X21: =-SUM(V21:W21)-3229 -> 0 | Y21: =-SUM(V21:X21)-3205 -> 24 | Z21: =SUM(V21:Y21) -> -3205 | AA21: 0 | AB21: 0 | AC21: 0 | AD21: 0 | AE21: =SUM(AA21:AD21) -> 0 | AF21: 0 | AG21: 28882 | AH21: 0 | AI21: 0 | AJ21: =SUM(AF21:AI21) -> 28882 | AK21: 0 | AL21: =1.75*AL19 -> 77089.25 | AM21: =0.35*AM19 -> 15202.017 | AN21: 0 | AO21: =SUM(AK21:AN21) -> 92291.267 | AP21: 0 | AQ21: 0 | AR21: 0 | AS21: 0 | AT21: =SUM(AP21:AS21) -> 0 | AU21: 0 | AV21: 0 | AW21: 0 | AX21: 0 | AY21: =SUM(AU21:AX21) -> 0
A22: GAAP Net Income | B22: =B21+B17 -> 35576 | C22: =C21+C17 -> 3956 | D22: =D21+D17 -> 7094 | E22: =E21+E17 -> 74541 | F22: =F21+F17 -> 39358 | G22: =G21+G17 -> -244148 | H22: =H21+H17 -> 5464 | I22: =I21+I17 -> 42271 | ... AY22: =AY21+AY17 -> 538872.88
A23: GAAP EPS | B23: =B22/B19 -> 0.51249694 | C23: =C22/68284 -> 0.057934509 | D23: =D22/D19 -> 0.1022146 | E23: =E22/E19 -> 1.0781636 | F23: =F22/F19 -> 0.59834595 | G23: =G22/G19 -> -3.9038071 | H23: =H22/H19 -> 0.086338211 | I23: =I22/I19 -> 0.66175619 | J23: =J22/J19 -> 1.271717 | K23: =K22/K19 -> -1.8203749 | ... AY23: =AY22/AY19 -> 13.448709
A25: Margin Analysis
A26: Gross Margin | B26: =B7/B6 -> 0.38096388 | C26: =C7/C6 -> 0.39022346 | D26: =D7/D6 -> 0.40337047 | E26: =E7/E6 -> 0.39837036 | F26: =F7/F6 -> 0.40632772 | G26: =G7/G6 -> 0.45577397 | H26: =H7/H6 -> 0.3933968 | I26: =I7/I6 -> 0.36017681 | ... P26: =P7/P6 -> 0.37728536 | Q26: =Q8/Q$6 -> 0.55310903 | R26: =R8/R$6 -> 0.57868117 | S26: =S8/S$6 -> 0.59177988 | T26: =T8/T$6 -> 0.5569905 | U26: =U8/U$6 -> 0.56914 | V26: =V8/V$6 -> 0.60980581 | W26: =W8/W$6 -> 0.62477482 | X26: =X8/X$6 -> 0.64904286 | ... AL26: =AL8/AL$6 -> 0.6320257 | AM26: =AH26+AM27/10^4 -> 0.63824184 | AN26: =AI26+AN27/10^4 -> 0.61186754 | AO26: =AO8/AO$6 -> 0.62633379 | AP26: =AK26+AP27/10^4 -> 0.62945197 | AQ26: =AL26+AQ27/10^4 -> 0.6330257 | AR26: =AM26+AR27/10^4 -> 0.63924184 | AS26: =AN26+AS27/10^4 -> 0.61286754 | AT26: =AT8/AT$6 -> 0.62734462 | AU26: =AP26+AU27/10^4 -> 0.63145197 | AV26: =AQ26+AV27/10^4 -> 0.6330257 | AW26: =AR26+AW27/10^4 -> 0.63924184 | AX26: =AS26+AX27/10^4 -> 0.61486754 | AY26: =AY8/AY$6 -> 0.6283892
A27: YoY Chg. | C27: =(ROUND(C26,3)-ROUND(B26,3))*10^4 -> 90 | D27: =(ROUND(D26,3)-ROUND(C26,3))*10^4 -> 130 | E27: =(ROUND(E26,3)-ROUND(D26,3))*10^4 -> -50 | F27: =(ROUND(F26,3)-ROUND(E26,3))*10^4 -> 80 | K27: =(ROUND(K26,3)-ROUND(F26,3))*10^4 -> -110 | L27: =(ROUND(L26,3)-ROUND(G26,3))*10^4 -> -900 | M27: =(ROUND(M26,3)-ROUND(H26,3))*10^4 -> -450 | N27: =(ROUND(N26,3)-ROUND(I26,3))*10^4 -> 30 | O27: =(ROUND(O26,3)-ROUND(J26,3))*10^4 -> 220 | P27: =(ROUND(P26,3)-ROUND(K26,3))*10^4 -> -180 | Q27: =(ROUND(Q26,3)-ROUND(L26,3))*10^4 -> 1870 | R27: =(ROUND(R26,3)-ROUND(M26,3))*10^4 -> 2310 | ... AL27: =(ROUND(AL26,3)-ROUND(AG26,3))*10^4 -> 60 | AM27: 130 | AN27: 170 | AO27: =(ROUND(AO26,3)-ROUND(AJ26,3))*10^4 -> 110 | AP27: 10 | AQ27: 10 | AR27: 10 | AS27: 10 | AT27: =(ROUND(AT26,3)-ROUND(AO26,3))*10^4 -> 10 | AU27: 20 | AV27: 0 | AW27: 0 | AX27: 20 | AY27: =(ROUND(AY26,3)-ROUND(AT26,3))*10^4 -> 10
A29: Selling Margin | B29: =B9/B$6 -> 0.45401941 | C29: =C9/C$6 -> 0.47447651 | D29: =D9/D$6 -> 0.4416152 | E29: =E9/E$6 -> 0.42951955 | F29: =F9/F$6 -> 0.42815671 | G29: =G9/G$6 -> 0.66368193 | H29: =H9/H$6 -> 0.44444731 | I29: =I9/I$6 -> 0.42245072 | ... AL29: =AL9/AL$6 -> 0.35055329 | AM29: =AH29+AM34/10^4 -> 0.3610679 | AN29: =AI29+AN34/10^4 -> 0.34122764 | AO29: =AO9/AO$6 -> 0.35750147 | AP29: =AK29+AP34/10^4 -> 0.38013133 | AQ29: =AL29+AQ34/10^4 -> 0.35255329 | AR29: =AM29+AR34/10^4 -> 0.3630679 | AS29: =AN29+AS34/10^4 -> 0.34322764 | AT29: =AT9/AT$6 -> 0.35772886 | AU29: =AP29+AU34/10^4 -> 0.38113133 | AV29: =AQ29+AV34/10^4 -> 0.35355329 | AW29: =AR29+AW34/10^4 -> 0.3640679 | AX29: =AS29+AX34/10^4 -> 0.34422764 | AY29: =AY9/AY$6 -> 0.3587198
A30: Marketing | AF30: 50 | AG30: 0 | AH30: 100 | AK30: 50 | AL30: 0
A31: Store Expense | AF31: 40 | AG31: 90 | AH31: 40 | AK31: 40 | AL31: 0
A32: Fulfillment | AF32: 30 | AG32: 0 | AH32: -80 | AK32: 30 | AL32: 80
A33: Other | AF33: =AF34-SUM(AF30:AF32) -> -10 | AG33: =AG34-SUM(AG30:AG32) -> -4.6895821e-13 | AH33: =AH34-SUM(AH30:AH32) -> 20 | AK33: =AK34-SUM(AK30:AK32) -> 110 | AL33: =AL34-SUM(AL30:AL32) -> -30
A34: YoY Chg. | C34: =(ROUND(C29,3)-ROUND(B29,3))*10^4 -> 200 | D34: =(ROUND(D29,3)-ROUND(C29,3))*10^4 -> -320 | E34: =(ROUND(E29,3)-ROUND(D29,3))*10^4 -> -120 | F34: =(ROUND(F29,3)-ROUND(E29,3))*10^4 -> -20 | K34: =(ROUND(K29,3)-ROUND(F29,3))*10^4 -> 170 | L34: =(ROUND(L29,3)-ROUND(G29,3))*10^4 -> -2590 | M34: =(ROUND(M29,3)-ROUND(H29,3))*10^4 -> -670 | N34: =(ROUND(N29,3)-ROUND(I29,3))*10^4 -> -330 | O34: =(ROUND(O29,3)-ROUND(J29,3))*10^4 -> 70 | P34: =(ROUND(P29,3)-ROUND(K29,3))*10^4 -> -600 | Q34: =(ROUND(Q29,3)-ROUND(L29,3))*10^4 -> 100 | R34: =(ROUND(R29,3)-ROUND(M29,3))*10^4 -> 460 | ... U34: =(ROUND(U29,3)-ROUND(P29,3))*10^4 -> 160 | V34: N/A | W34: N/A | X34: N/A | Y34: N/A | Z34: N/A | AA34: =(ROUND(AA29,3)-ROUND(V29,3))*10^4 -> -300 | AB34: =(ROUND(AB29,3)-ROUND(W29,3))*10^4 -> -250 | AC34: =(ROUND(AC29,3)-ROUND(X29,3))*10^4 -> -40 | AD34: =(ROUND(AD29,3)-ROUND(Y29,3))*10^4 -> -110 | AE34: =(ROUND(AE29,3)-ROUND(Z29,3))*10^4 -> -150 | AF34: =(ROUND(AF29,3)-ROUND(AA29,3))*10^4 -> 110 | AG34: =(ROUND(AG29,3)-ROUND(AB29,3))*10^4 -> 90 | AH34: =(ROUND(AH29,3)-ROUND(AC29,3))*10^4 -> 80 | ... AL34: =(ROUND(AL29,3)-ROUND(AG29,3))*10^4 -> 50 | AM34: 50 | AN34: -30 | AO34: =(ROUND(AO29,3)-ROUND(AJ29,3))*10^4 -> 60 | AP34: -70 | AQ34: 20 | AR34: 20 | AS34: 20 | AT34: =(ROUND(AT29,3)-ROUND(AO29,3))*10^4 -> 0 | AU34: 10 | AV34: 10 | AW34: 10 | AX34: 10 | AY34: =(ROUND(AY29,3)-ROUND(AT29,3))*10^4 -> 10
A36: G&A Margin | B36: =B10/B$6 -> 0.12868405 | C36: =C10/C$6 -> 0.13803363 | D36: =D10/D$6 -> 0.13080004 | E36: =E10/E$6 -> 0.13433241 | F36: =F10/F$6 -> 0.12823782 | G36: =G10/G$6 -> 0.22304521 | H36: =H10/H$6 -> 0.13926407 | I36: =I10/I$6 -> 0.14762345 | ... AL36: =AL10/AL$6 -> 0.16166873 | AM36: =AH36+AM40/10^4 -> 0.15385213 | AN36: =AI36+AN40/10^4 -> 0.10988656 | AO36: =AO10/AO$6 -> 0.1435052 | AP36: =AK36+AP40/10^4 -> 0.16107843 | AQ36: =AL36+AQ40/10^4 -> 0.15866873 | AR36: =AM36+AR40/10^4 -> 0.15385213 | AS36: =AN36+AS40/10^4 -> 0.10988656 | AT36: =AT10/AT$6 -> 0.14227109 | AU36: =AP36+AU40/10^4 -> 0.16007843 | AV36: =AQ36+AV40/10^4 -> 0.15766873 | AW36: =AR36+AW40/10^4 -> 0.15285213 | AX36: =AS36+AX40/10^4 -> 0.10888656 | AY36: =AY10/AY$6 -> 0.14125185
A37: Employee comp | AF37: -210 | AG37: -150 | AH37: -110 | AK37: -210 | AL37: 120
A38: Outside services | AF38: -60 | AG38: 0 | AH38: 40 | AK38: -60 | AL38: 70
A39: Other | AF39: =AF40-SUM(AF37:AF38) -> 0 | AG39: =AG40-SUM(AG37:AG38) -> 0 | AH39: =AH40-SUM(AH37:AH38) -> 10 | AK39: =AK40-SUM(AK37:AK38) -> 320 | AL39: =AL40-SUM(AL37:AL38) -> 10
A40: YoY Chg. | C40: =(ROUND(C36,3)-ROUND(B36,3))*10^4 -> 90 | D40: =(ROUND(D36,3)-ROUND(C36,3))*10^4 -> -70 | E40: =(ROUND(E36,3)-ROUND(D36,3))*10^4 -> 30 | F40: =(ROUND(F36,3)-ROUND(E36,3))*10^4 -> -60 | K40: =(ROUND(K36,3)-ROUND(F36,3))*10^4 -> 200 | L40: =(ROUND(L36,3)-ROUND(G36,3))*10^4 -> -680 | M40: =(ROUND(M36,3)-ROUND(H36,3))*10^4 -> 40 | N40: =(ROUND(N36,3)-ROUND(I36,3))*10^4 -> 140 | O40: =(ROUND(O36,3)-ROUND(J36,3))*10^4 -> 30 | P40: =(ROUND(P36,3)-ROUND(K36,3))*10^4 -> -30 | Q40: =(ROUND(Q36,3)-ROUND(L36,3))*10^4 -> -50 | R40: =(ROUND(R36,3)-ROUND(M36,3))*10^4 -> 110 | ... U40: =(ROUND(U36,3)-ROUND(P36,3))*10^4 -> -50 | V40: N/A | W40: N/A | X40: N/A | Y40: N/A | Z40: N/A | AA40: =(ROUND(AA36,3)-ROUND(V36,3))*10^4 -> 10 | AB40: =(ROUND(AB36,3)-ROUND(W36,3))*10^4 -> -130 | AC40: =(ROUND(AC36,3)-ROUND(X36,3))*10^4 -> -90 | AD40: =(ROUND(AD36,3)-ROUND(Y36,3))*10^4 -> -100 | AE40: =(ROUND(AE36,3)-ROUND(Z36,3))*10^4 -> -70 | AF40: =(ROUND(AF36,3)-ROUND(AA36,3))*10^4 -> -270 | AG40: =(ROUND(AG36,3)-ROUND(AB36,3))*10^4 -> -150 | AH40: =(ROUND(AH36,3)-ROUND(AC36,3))*10^4 -> -60 | ... AL40: =(ROUND(AL36,3)-ROUND(AG36,3))*10^4 -> 200 | AM40: 40 | AN40: 10 | AO40: =(ROUND(AO36,3)-ROUND(AJ36,3))*10^4 -> 70 | AP40: -30 | AQ40: -30 | AR40: 0 | AS40: 0 | AT40: =(ROUND(AT36,3)-ROUND(AO36,3))*10^4 -> -20 | AU40: -10 | AV40: -10 | AW40: -10 | AX40: -10 | AY40: =(ROUND(AY36,3)-ROUND(AT36,3))*10^4 -> -10
A42: Operating Margin | B42: =B12/B$6 -> 0.038791535 | C42: =C12/C$6 -> 0.00098053951 | D42: =D12/D$6 -> 0.028854837 | E42: =E12/E$6 -> 0.038614984 | F42: =F12/F$6 -> 0.022859048 | G42: =G12/G$6 -> -0.34242489 | H42: =H12/H$6 -> 0.031827451 | I42: =I12/I$6 -> 0.079234749 | ... AY42: =AY12/AY$6 -> 0.12909419
A43: YoY Chg. | C43: =(ROUND(C42,3)-ROUND(B42,3))*10^4 -> -380 | D43: =(ROUND(D42,3)-ROUND(C42,3))*10^4 -> 280 | E43: =(ROUND(E42,3)-ROUND(D42,3))*10^4 -> 100 | F43: =(ROUND(F42,3)-ROUND(E42,3))*10^4 -> -160 | K43: =(ROUND(K42,3)-ROUND(J42,3))*10^4 -> -1000 | L43: =(ROUND(L42,3)-ROUND(G42,3))*10^4 -> 4190 | M43: =(ROUND(M42,3)-ROUND(H42,3))*10^4 -> 1020 | N43: =(ROUND(N42,3)-ROUND(I42,3))*10^4 -> 90 | O43: =(ROUND(O42,3)-ROUND(J42,3))*10^4 -> -310 | P43: =(ROUND(P42,3)-ROUND(O42,3))*10^4 -> 100 | Q43: =(ROUND(Q42,3)-ROUND(L42,3))*10^4 -> -850 | R43: =(ROUND(R42,3)-ROUND(M42,3))*10^4 -> -1340 | S43: =(ROUND(S42,3)-ROUND(N42,3))*10^4 -> -640 | T43: =(ROUND(T42,3)-ROUND(O42,3))*10^4 -> -100 | U43: =(ROUND(U42,3)-ROUND(P42,3))*10^4 -> -670 | V43: =(ROUND(V42,3)-ROUND(Q42,3))*10^4 -> 540 | W43: =(ROUND(W42,3)-ROUND(R42,3))*10^4 -> 960 | X43: =(ROUND(X42,3)-ROUND(S42,3))*10^4 -> 1070 | ... AY43: =(ROUND(AY42,3)-ROUND(AT42,3))*10^4 -> 10
A45: Tax Rate | B45: =B15/B$14 -> 0.31473949 | C45: =C15/C$14 -> 0.98000519 | D45: =D15/D$14 -> 0.42263863 | E45: =E15/E$14 -> 0.34142424 | F45: =F15/F$14 -> 0.28480482 | G45: =G15/G$14 -> -0.2120953 | H45: =H15/H$14 -> 0.0057509254 | I45: =I15/I$14 -> 0.10951779 | ... AL45: =AL15/AL$14 -> 0.31014681 | AM45: 0.29 | AN45: 0.28 | AO45: =AO15/AO$14 -> 0.28848757 | AP45: 0.3 | AQ45: 0.3 | AR45: 0.3 | AS45: 0.3 | AT45: =AT15/AT$14 -> 0.3 | AU45: 0.3 | AV45: 0.3 | AW45: 0.3 | AX45: 0.3 | AY45: =AY15/AY$14 -> 0.3
A46: NCI % of Pretax | B46: =B16/B$14 -> 0.025226856 | C46: =C16/C$14 -> -0.24422228 | D46: =D16/D$14 -> 0.040897821 | E46: =E16/E$14 -> 0.033431793 | F46: =F16/F$14 -> 0.074610764 | G46: =G16/G$14 -> -0.00068998054 | H46: =H16/H$14 -> 0.02168165 | I46: =I16/I$14 -> 0.031316244 | ... AL46: =AL16/AL$14 -> 0.011570732 | AM46: 0.01 | AN46: 0.01 | AO46: =AO16/AO$14 -> 0.01040509 | AP46: 0.01 | AQ46: 0.011 | AR46: 0.011 | AS46: 0.01 | AT46: =AT16/AT$14 -> 0.010456842 | AU46: 0.011 | AV46: 0.011 | AW46: 0.011 | AX46: 0.01 | AY46: =AY16/AY$14 -> 0.010598179
A48: YoY Chg.
A49: Net Sales | C49: =C6/B6-1 -> -0.054548865 | D49: =D6/C6-1 -> 0.04988367 | E49: =E6/D6-1 -> 0.027892255 | F49: =F6/E6-1 -> 0.0091818939 | K49: =K6/F6-1 -> -0.13736654 | L49: =L6/G6-1 -> 0.60995263 | M49: =M6/H6-1 -> 0.23845815 | N49: =N6/I6-1 -> 0.10432097 | O49: =O6/J6-1 -> 0.035033386 | P49: =P6/K6-1 -> 0.18793979 | Q49: =Q6/L6-1 -> 0.040128998 | R49: =R6/M6-1 -> -0.069097531 | ... AY49: =AY6/AT6-1 -> 0.029014903
A50: COGS | C50: =C7/B7-1 -> -0.031569053 | D50: =D7/C7-1 -> 0.085255267 | E50: =E7/D7-1 -> 0.015150676 | F50: =F7/E7-1 -> 0.029340096 | K50: =K7/F7-1 -> -0.16165146 | L50: =L7/G7-1 -> 0.29409079 | M50: =M7/H7-1 -> 0.096989662 | N50: =N7/I7-1 -> 0.11413861 | O50: =O7/J7-1 -> 0.09298798 | P50: =P7/K7-1 -> 0.13498366 | Q50: =Q7/L7-1 -> 0.26878377 | R50: =R7/M7-1 -> 0.12554543 | ... AY50: =AY7/AT7-1 -> 0.0261305
A51: Gross Profit | C51: =C8/B8-1 -> -0.068690977 | D51: =D8/C8-1 -> 0.027247793 | E51: =E8/D8-1 -> 0.036506607 | F51: =F8/E8-1 -> -0.0041659027 | K51: =K8/F8-1 -> -0.12074519 | L51: =L8/G8-1 -> 0.87447803 | M51: =M8/H8-1 -> 0.33020387 | N51: =N8/I8-1 -> 0.098794317 | O51: =O8/J8-1 -> -0.0027790091 | P51: =P8/K8-1 -> 0.22249835 | Q51: =Q8/L8-1 -> -0.092072045 | R51: =R8/M8-1 -> -0.17319716 | ... AY51: =AY8/AT8-1 -> 0.030728296
A52: Selling Exp. | C52: =C9/B9-1 -> -0.011948929 | D52: =D9/C9-1 -> -0.022829213 | E52: =E9/D9-1 -> -0.00026127689 | F52: =F9/E9-1 -> 0.0059798109 | K52: =K9/F9-1 -> -0.10292327 | L52: =L9/G9-1 -> -0.017123841 | M52: =M9/H9-1 -> 0.049866289 | N52: =N9/I9-1 -> 0.016034055 | O52: =O9/J9-1 -> 0.054080765 | P52: =P9/K9-1 -> 0.027191316 | Q52: =Q9/L9-1 -> 0.066122776 | R52: =R9/M9-1 -> 0.045862015 | ... AY52: =AY9/AT9-1 -> 0.031865379
A53: G&A | C53: =C10/B10-1 -> 0.014143172 | D53: =D10/C10-1 -> -0.0051349951 | E53: =E10/D10-1 -> 0.055651382 | F53: =F10/E10-1 -> -0.036604129 | K53: =K10/F10-1 -> -0.0016615908 | L53: =L10/G10-1 -> 0.11722106 | M53: =M10/H10-1 -> 0.27414346 | N53: =N10/I10-1 -> 0.20883471 | O53: =O10/J10-1 -> 0.060815239 | P53: =P10/K10-1 -> 0.15732047 | Q53: =Q10/L10-1 -> 0.0099382374 | R53: =R10/M10-1 -> 0.0020578955 | ... AY53: =AY10/AT10-1 -> 0.021642923
A54: Operating Income | C54: =C12/B12-1 -> -0.97610169 | D54: =D12/C12-1 -> 29.895463 | E54: =E12/D12-1 -> 0.37557675 | F54: =F12/E12-1 -> -0.40259103 | K54: =K12/F12-1 -> -0.36648153 | L54: =L12/G12-1 -> -1.3615966 | M54: =M12/H12-1 -> 4.199901 | N54: =N12/I12-1 -> 0.22380476 | O54: =O12/J12-1 -> -0.23926203 | P54: =P12/K12-1 -> 5.7695357 | Q54: =Q12/L12-1 -> -1.1048971 | R54: =R12/M12-1 -> -1.0001817 | ... U54: =U12/P12-1 -> -0.69965145 | V54: =ABS(V12/Q12)-1 -> 5.0983503 | W54: =ABS(W12/R12)-1 -> 4277.1905 | X54: =X12/S12-1 -> 5.4837694 | Y54: =Y12/T12-1 -> 1.4292225 | Z54: =Z12/U12-1 -> 3.584848 | AA54: =AA12/V12-1 -> 2.3776142 | AB54: =AB12/W12-1 -> 0.95482069 | AC54: =AC12/X12-1 -> 0.29895667 | AD54: =AD12/Y12-1 -> 0.14929466 | AE54: =AE12/Z12-1 -> 0.5146379 | ... AY54: =AY12/AT12-1 -> 0.037479445
A55: Pre-Tax Income | C55: =C14/B14-1 -> -1.1302697 | D55: =D14/C14-1 -> -6.4461179 | E55: =E14/D14-1 -> 0.52139656 | F55: =F14/E14-1 -> -0.41172737 | K55: =K14/F14-1 -> -0.67776993 | L55: =L14/G14-1 -> -1.3036563 | M55: =M14/H14-1 -> 5.8943681 | N55: =N14/I14-1 -> 0.2863174 | O55: =O14/J14-1 -> -0.24019788 | P55: =P14/K14-1 -> 12.270811 | Q55: =Q14/L14-1 -> -1.2643375 | R55: =R14/M14-1 -> -1.0665209 | ... U55: =U14/P14-1 -> -0.74757533 | V55: =ABS(V14/Q14)-1 -> 1.571523 | W55: =ABS(W14/R14)-1 -> 11.79115 | X55: =X14/S14-1 -> 8.8162521 | Y55: =Y14/T14-1 -> 1.5985115 | Z55: =Z14/U14-1 -> 5.0302664 | AA55: =AA14/V14-1 -> 2.8533756 | AB55: =AB14/W14-1 -> 1.0376134 | AC55: =AC14/X14-1 -> 0.3688851 | AD55: =AD14/Y14-1 -> 0.16395185 | AE55: =AE14/Z14-1 -> 0.57278893 | ... AY55: =AY14/AT14-1 -> 0.036559959
A56: Net Income | C56: =C17/B17-1 -> -1.0521481 | D56: =D17/C17-1 -> -12.05774 | E56: =E17/D17-1 -> 0.7728919 | F56: =F17/E17-1 -> -0.39719761 | K56: =K17/F17-1 -> -1.9435724 | L56: =L17/G17-1 -> -1.213871 | M56: =M17/H17-1 -> 6.4126283 | N56: =N17/I17-1 -> 0.090730028 | O56: =O17/J17-1 -> -0.31120473 | P56: =P17/K17-1 -> -7.0086156 | Q56: =Q17/L17-1 -> -1.317509 | R56: =R17/M17-1 -> -1.1400579 | ... U56: =U17/P17-1 -> -0.95216162 | V56: =ABS(V17/Q17)-1 -> 0.41926244 | W56: =ABS(W17/R17)-1 -> 2.7233388 | X56: =X17/S17-1 -> 172.66606 | Y56: =Y17/T17-1 -> 2.7962905 | Z56: =Z17/U17-1 -> 24.39885 | AA56: =AA17/V17-1 -> 4.7441978 | AB56: =AB17/W17-1 -> 1.3414566 | AC56: =AC17/X17-1 -> 0.37176622 | AD56: =AD17/Y17-1 -> 0.18181072 | AE56: =AE17/Z17-1 -> 0.70895004 | ... AY56: =AY17/AT17-1 -> 0.036347493
A57: EPS | C57: =(C18-B18)/ABS(B18) -> -1.0533304 | D57: =(D18-C18)/ABS(C18) -> 11.814767 | E57: =(E18-D18)/ABS(D18) -> 0.77971298 | F57: =(F18-E18)/ABS(E18) -> -0.36641508 | K57: =(K18-F18)/ABS(F18) -> -1.9909046 | L57: =(L18-G18)/ABS(G18) -> 1.204819 | M57: =(M18-H18)/ABS(H18) -> 6.3143881 | N57: =(N18-I18)/ABS(I18) -> 0.13353229 | O57: =(O18-J18)/ABS(J18) -> -0.23976715 | P57: =(P18-K18)/ABS(K18) -> 7.0086156 | Q57: =(Q18-L18)/ABS(L18) -> -1.398159 | R57: =(R18-M18)/ABS(M18) -> -1.1780844 | ... AY57: =(AY18-AT18)/ABS(AT18) -> 0.080388304
A59: EBITDA/R
A60: D&A | B60: =SCF!B7 -> 213680 | C60: =SCF!C7 -> 195414 | D60: =SCF!D7 -> 194549 | E60: =SCF!E7 -> 178030 | F60: =SCF!F7 -> 173625 | G60: 44037 | H60: 38716 | I60: 44495 | J60: 39033 | K60: =SUM(G60:J60) -> 166281 | L60: 37856 | M60: =-L60+72249 -> 34393 | N60: =-SUM(L60:M60)+107787 -> 35538 | O60: =-SUM(L60:N60)+144035 -> 36248 | P60: =SUM(L60:O60) -> 144035 | Q60: 33888 | R60: =-Q60+65543 -> 31655 | S60: =-SUM(Q60:R60)+98393 -> 32850 | T60: =-SUM(Q60:S60)+132243 -> 33850 | U60: =SUM(Q60:T60) -> 132243 | V60: 36028 | W60: 36383 | X60: =-SUM(V60:W60)+105547 -> 33136 | Y60: =-SUM(V60:X60)+141104 -> 35557 | Z60: =SUM(V60:Y60) -> 141104 | AA60: 37689 | AB60: 39355 | AC60: 39566 | AD60: 37163 | AE60: =SUM(AA60:AD60) -> 153773 | AF60: 38576 | AG60: =-AF60+76000 -> 37424 | AH60: 38566 | AI60: 40455 | AJ60: =SUM(AF60:AI60) -> 155021 | AK60: 42304 | AL60: 43279 | AM60: =SCF!AM7 -> 43337.996 | AN60: =SCF!AN7 -> 44273.086 | AO60: =SUM(AK60:AN60) -> 173194.08 | AP60: =SCF!AP7 -> 44674.686 | AQ60: =SCF!AQ7 -> 45080.026 | AR60: =SCF!AR7 -> 45461.43 | AS60: =SCF!AS7 -> 45959.272 | AT60: =SUM(AP60:AS60) -> 181175.41 | AU60: =SCF!AU7 -> 46214.919 | AV60: =SCF!AV7 -> 46506.257 | AW60: =SCF!AW7 -> 46846.876 | AX60: =SCF!AX7 -> 47292.775 | AY60: =SUM(AU60:AX60) -> 186860.83
A61: Adj. EBITDA | B61: =B60+B12 -> 350175 | C61: =C60+C12 -> 198676 | D61: =D60+D12 -> 295330 | E61: =E60+E12 -> 316662 | F61: =F60+F12 -> 256445 | G61: =G60+G12 -> -122162 | H61: =H60+H12 -> 60942 | I61: =I60+I12 -> 109440 | J61: =J60+J12 -> 170529 | K61: =SUM(G61:J61) -> 218749 | L61: =L60+L12 -> 97953 | M61: =M60+M12 -> 149966 | N61: =N60+N12 -> 115018 | O61: =O60+O12 -> 136282 | P61: =SUM(L61:O61) -> 499219 | Q61: =Q60+Q12 -> 27584 | R61: =R60+R12 -> 31634 | S61: =S60+S12 -> 54137 | T61: =T60+T12 -> 125567 | U61: =SUM(Q61:T61) -> 238922 | V61: =V60+V12 -> 74472 | W61: =W60+W12 -> 126225 | X61: =X60+X12 -> 171156 | Y61: =Y60+Y12 -> 258358 | Z61: =SUM(V61:Y61) -> 630211 | AA61: =AA60+AA12 -> 167538 | AB61: =AB60+AB12 -> 214980 | AC61: =AC60+AC12 -> 218848 | AD61: =AD60+AD12 -> 293227 | AE61: =SUM(AA61:AD61) -> 894593 | AF61: =AF60+AF12 -> 140109 | AG61: =AG60+AG12 -> 205508 | AH61: =AH60+AH12 -> 193587 | AI61: =AI60+AI12 -> 276386 | AJ61: =SUM(AF61:AI61) -> 815590 | AK61: =AK60+AK12 -> 131101 | AL61: =AL60+AL12 -> 195979 | AM61: =AM60+AM12 -> 212661.22 | AN61: =AN60+AN12 -> 332239.16 | AO61: =SUM(AK61:AN61) -> 871980.38 | AP61: =AP60+AP12 -> 148390.48 | AQ61: =AQ60+AQ12 -> 206538.9 | AR61: =AR60+AR12 -> 219499.46 | AS61: =AS60+AS12 -> 342330.14 | AT61: =SUM(AP61:AS61) -> 916758.98 | AU61: =AU60+AU12 -> 155142.52 | AV61: =AV60+AV12 -> 212400.89 | AW61: =AW60+AW12 -> 226093.06 | AX61: =AX60+AX12 -> 356377.19 | AY61: =SUM(AU61:AX61) -> 950013.66
A62: Margin | B62: =B61/B$6 -> 0.099518854 | C62: =C61/C$6 -> 0.059720928 | D62: =D61/D$6 -> 0.084556603 | E62: =E61/E$6 -> 0.088204007 | F62: =F61/F$6 -> 0.070781075 | G62: =G61/G$6 -> -0.25169411 | H62: =H61/H$6 -> 0.087268447 | I62: =I61/I$6 -> 0.13351992 | ... AY62: =AY61/AY$6 -> 0.16070339
A63: Chg. YoY | L63: =(ROUND(L62,3)-ROUND(G62,3))*10^4 -> 3770 | M63: =(ROUND(M62,3)-ROUND(H62,3))*10^4 -> 860 | N63: =(ROUND(N62,3)-ROUND(I62,3))*10^4 -> -70 | O63: =(ROUND(O62,3)-ROUND(J62,3))*10^4 -> -350 | P63: =(ROUND(P62,3)-ROUND(K62,3))*10^4 -> 640 | Q63: =(ROUND(Q62,3)-ROUND(L62,3))*10^4 -> -910 | R63: =(ROUND(R62,3)-ROUND(M62,3))*10^4 -> -1340 | S63: =(ROUND(S62,3)-ROUND(N62,3))*10^4 -> -650 | ... AY63: =(ROUND(AY62,3)-ROUND(AT62,3))*10^4 -> 10
A65: EBITDAR | B65: =B61+B69 -> 740402 | C65: =C61+C69 -> 600156 | D65: =D61+D69 -> 671142 | E65: =E61+E69 -> 687560 | F65: =F61+F69 -> 827899 | G65: =G61+G69 -> -769 | H65: =H61+H69 -> 168073 | I65: =I61+I69 -> 207611 | ... AY65: =AY61+AY69 -> 1473936.4
A66: Margin | B66: =B65/B$6 -> 0.21042038 | C66: =C65/C$6 -> 0.18040364 | D66: =D65/D$6 -> 0.19215619 | E66: =E65/E$6 -> 0.19151508 | F66: =F65/F$6 -> 0.2285074 | G66: =G65/G$6 -> -0.0015843942 | H66: =H65/H$6 -> 0.24067917 | I66: =I65/I$6 -> 0.25329133 | ... AY66: =AY65/AY$6 -> 0.24932966
A67: Chg. YoY | AF67: =(ROUND(AF66,3)-ROUND(AA66,3))*10^4 -> -320 | AH67: =(ROUND(AH66,3)-ROUND(AC66,3))*10^4 -> -270 | AI67: =(ROUND(AI66,3)-ROUND(AD66,3))*10^4 -> -170 | AJ67: =(ROUND(AJ66,3)-ROUND(AE66,3))*10^4 -> -220 | AK67: =(ROUND(AK66,3)-ROUND(AF66,3))*10^4 -> -20 | AL67: =(ROUND(AL66,3)-ROUND(AG66,3))*10^4 -> -130 | AM67: =(ROUND(AM66,3)-ROUND(AH66,3))*10^4 -> -120 | AN67: =(ROUND(AN66,3)-ROUND(AI66,3))*10^4 -> 220 | AO67: =(ROUND(AO66,3)-ROUND(AJ66,3))*10^4 -> 10 | ... AY67: =(ROUND(AY66,3)-ROUND(AT66,3))*10^4 -> 10
A69: Operating Lease (excl. impairment) | B69: 390227 | C69: 401480 | D69: 375812 | E69: 370898 | F69: =427982+143472 -> 571454 | G69: =156401-35008 -> 121393 | H69: =112541-5410 -> 107131 | I69: =102150-3979 -> 98171 | J69: =K69-SUM(G69:I69) -> 244759 | K69: =587266-15812 -> 571454 | L69: =94289-2464+1093 -> 92918 | M69: =88770-240 -> 88530 | N69: =97822-5512 -> 92310 | O69: =P69-SUM(L69:N69) -> 105085 | P69: =388352-9509 -> 378843 | Q69: 91644 | R69: =95094-1573 -> 93521 | S69: 104241 | T69: =U69-SUM(Q69:S69) -> 104501 | U69: =400155-6248 -> 393907 | V69: =94465-1414 -> 93051 | W69: 113441 | X69: =94530 -> 94530 | Y69: =Z69-SUM(V69:X69) -> 112477 | Z69: =414939-1440 -> 413499 | AA69: =105504-339 -> 105165 | AB69: =108846-472 -> 108374 | AC69: =114112-233 -> 113879 | AD69: =AE69-SUM(AA69:AC69) -> 120243 | AE69: =453131-5470 -> 447661 | AF69: =117883-449 -> 117434 | AG69: 122239 | AH69: =128320-1331 -> 126989 | AI69: =AJ69-SUM(AF69:AH69) -> 131520 | AJ69: =503137-4955 -> 498182 | AK69: =129372-668 -> 128704 | AL69: 131296 | AM69: =AM71*AM6 -> 109355 | AN69: =AN71*AN6 -> 142935.05 | AO69: =SUM(AK69:AN69) -> 512290.06 | AP69: =AP71*AP6 -> 116402.1 | AQ69: =AQ71*AQ6 -> 131735.66 | AR69: =AR71*AR6 -> 113169.04 | AS69: =AS71*AS6 -> 147913.47 | AT69: =SUM(AP69:AS69) -> 509220.27 | AU69: =AU71*AU6 -> 119597.69 | AV69: =AV71*AV6 -> 135377.39 | AW69: =AW71*AW6 -> 116575.24 | AX69: =AX71*AX6 -> 152372.46 | AY69: =SUM(AU69:AX69) -> 523922.77
A70: YoY Chg. | L70: =L69/G69-1 -> -0.23456871 | M70: =M69/H69-1 -> -0.17362855 | N70: =N69/I69-1 -> -0.059701949 | O70: =O69/J69-1 -> -0.5706593 | P70: =P69/K69-1 -> -0.33705425 | Q70: =Q69/L69-1 -> -0.013711014 | R70: =R69/M69-1 -> 0.05637637 | S70: =S69/N69-1 -> 0.12924927 | ... AY70: =AY69/AT69-1 -> 0.028872576
A71: Op. Lease Margin | B71: =B69/B6 -> 0.11090153 | C71: =C69/C6 -> 0.12068271 | D71: =D69/D6 -> 0.10759959 | E71: =E69/E6 -> 0.10331107 | F71: =F69/F6 -> 0.15772633 | G71: =G69/G6 -> 0.25010971 | H71: =H69/H6 -> 0.15341072 | I71: =I69/I6 -> 0.11977142 | ... AL71: =AL69/AL6 -> 0.10365291 | AM71: 0.08 | AN71: 0.08 | AO71: =AO69/AO6 -> 0.092569117 | AP71: 0.1 | AQ71: 0.1 | AR71: 0.08 | AS71: 0.08 | AT71: =AT69/AT6 -> 0.088638527 | AU71: 0.1 | AV71: 0.1 | AW71: 0.08 | AX71: 0.08 | AY71: =AY69/AY6 -> 0.088626267
A72: Chg. YoY | L72: =(ROUND(L71,3)-ROUND(G71,3))*10^4 -> -1310 | M72: =(ROUND(M71,3)-ROUND(H71,3))*10^4 -> -510 | N72: =(ROUND(N71,3)-ROUND(I71,3))*10^4 -> -180 | O72: =(ROUND(O71,3)-ROUND(J71,3))*10^4 -> -1280 | P72: =(ROUND(P71,3)-ROUND(K71,3))*10^4 -> -810 | Q72: =(ROUND(Q71,3)-ROUND(L71,3))*10^4 -> -60 | R72: =(ROUND(R71,3)-ROUND(M71,3))*10^4 -> 140 | S72: =(ROUND(S71,3)-ROUND(N71,3))*10^4 -> 160 | ... AY72: =(ROUND(AY71,3)-ROUND(AT71,3))*10^4 -> 0
A74: Est. Tariff $ Impact ($mil) | AG74: 5 | AH74: 25 | AI74: 60 | AJ74: =SUM(AF74:AI74) -> 90 | AK74: 20 | AL74: 15 | AM74: -5 | AN74: -40 | AO74: =SUM(AK74:AN74) -> -10
A75: Bps impact (benefit) to GM | AG75: =ROUND(AG74/(AB6/1000),3)*10^4 -> 40 | AH75: =ROUND(AH74/(AC6/1000),3)*10^4 -> 210 | AI75: =ROUND(AI74/(AD6/1000),3)*10^4 -> 380 | AJ75: =ROUND(AJ74/(AE6/1000),3)*10^4 -> 180 | AK75: =ROUND(AK74/(AF6/1000),3)*10^4 -> 180 | AL75: =ROUND(AL74/(AG6/1000),3)*10^4 -> 120 | AM75: =ROUND(AM74/(AH6/1000),3)*10^4 -> -40 | AN75: =ROUND(AN74/(AI6/1000),3)*10^4 -> -240 | AO75: =ROUND(AO74/(AJ6/1000),3)*10^4 -> -20
A78: Interest expense, net | C78: 3
A79: Interest expense | B79: 22601 | C79: 23078 | D79: 22973 | E79: 22788 | F79: 19908 | G79: 5073 | H79: 7761 | I79: 9408 | J79: =K79-SUM(G79:I79) -> 9484 | K79: 31726 | L79: 9143 | M79: 13560 | N79: 7802 | O79: =P79-SUM(L79:N79) -> 7453 | P79: 37958 | Q79: 7809 | R79: 7660 | S79: 7586 | T79: =U79-SUM(Q79:S79) -> 7181 | U79: 30236 | V79: 7458 | W79: 7635 | X79: 8568 | Y79: =Z79-SUM(V79:X79) -> 6691 | Z79: 30352 | AA79: 5780 | AB79: 5189 | AC79: 569 | AD79: =AE79-SUM(AA79:AC79) -> 539 | AE79: 12077 | AF79: 661 | AG79: 620 | AH79: 550 | AI79: 544 | AJ79: =SUM(AF79:AI79) -> 2375 | AK79: 450 | AL79: 561
A80: Interest income | B80: 4353 | C80: 4412 | D80: 6084 | E80: 11789 | F80: 12171 | G80: 1702 | H80: 663 | I80: 600 | J80: =K80-SUM(G80:I80) -> 487 | K80: 3452 | L80: 537 | M80: 2285 | N80: 532 | O80: =P80-SUM(L80:N80) -> 494 | P80: 3848 | Q80: 502 | R80: 743 | S80: 291 | T80: =U80-SUM(Q80:S80) -> 3068 | U80: 4604 | V80: 4015 | W80: 6538 | X80: 7897 | Y80: =Z80-SUM(V80:X80) -> 11530 | Z80: 29980 | AA80: 10803 | AB80: 10392 | AC80: 9302 | AD80: =AE80-SUM(AA80:AC80) -> 9437 | AE80: 39934 | AF80: 7444 | AG80: 3094 | AH80: 6491 | AI80: 6975 | AJ80: =SUM(AF80:AI80) -> 24004 | AK80: 5737 | AL80: =8152-3084 -> 5068
A81: Interest expense (income), net | B81: =+B79-B80 -> 18248 | C81: =+C79-C80 -> 18666 | D81: =+D79-D80 -> 16889 | E81: =+E79-E80 -> 10999 | F81: =+F79-F80 -> 7737 | G81: =+G79-G80 -> 3371 | H81: =+H79-H80 -> 7098 | I81: =+I79-I80 -> 8808 | ... AL81: =+AL79-AL80 -> -4507
A82: Check | B82: =B81-B13 -> 0 | C82: =C81-C13 -> 0 | D82: =D81-D13 -> 0 | E82: =E81-E13 -> 0 | F82: =F81-F13 -> 0 | G82: =G81-G13 -> 0 | H82: =H81-H13 -> 0 | I82: =I81-I13 -> 0 | ... AL82: =AL81-AL13 -> 0
A84: Consensus | AM84: =AM3 -> 3Q26E | AN84: =AN3 -> 4Q26E | AO84: =AO3 -> FY26E | AP84: =AP3 -> 1Q27E | AQ84: =AQ3 -> 2Q27E | AR84: =AR3 -> 3Q27E | AS84: =AS3 -> 4Q27E | AT84: =AT3 -> FY27E | ... AY84: =AY3 -> FY28E
A85: GSe
A86: Net Sales | AM86: =AM6/10^3 -> 1366.9376 | AN86: =AN6/10^3 -> 1786.6881 | AO86: =AO6/10^3 -> 5534.1357 | AP86: =AP6/10^3 -> 1164.021 | AQ86: =AQ6/10^3 -> 1317.3566 | AR86: =AR6/10^3 -> 1414.613 | AS86: =AS6/10^3 -> 1848.9184 | AT86: =AT6/10^3 -> 5744.909 | ... AY86: =AY6/10^3 -> 5911.5969
A87: Gross Margin | AM87: =AM26 -> 0.63824184 | AN87: =AN26 -> 0.61186754 | AO87: =AO26 -> 0.62633379 | AP87: =AP26 -> 0.62945197 | AQ87: =AQ26 -> 0.6330257 | AR87: =AR26 -> 0.63924184 | AS87: =AS26 -> 0.61286754 | AT87: =AT26 -> 0.62734462 | ... AY87: =AY26 -> 0.6283892
A88: EBIT | AM88: =AM12/10^3 -> 169.32322 | AN88: =AN12/10^3 -> 287.96607 | AO88: =AO12/10^3 -> 698.78629 | AP88: =AP12/10^3 -> 103.71579 | AQ88: =AQ12/10^3 -> 161.45887 | AR88: =AR12/10^3 -> 174.03803 | AS88: =AS12/10^3 -> 296.37087 | AT88: =AT12/10^3 -> 735.58357 | ... AY88: =AY12/10^3 -> 763.15283
A89: Margin | AM89: =AM88/AM86 -> 0.12387049 | AN89: =AN88/AN86 -> 0.1611731 | AO89: =AO88/AO86 -> 0.12626837 | AP89: =AP88/AP86 -> 0.089101305 | AQ89: =AQ88/AQ86 -> 0.12256277 | AR89: =AR88/AR86 -> 0.12302872 | AS89: =AS88/AS86 -> 0.16029419 | AT89: =AT88/AT86 -> 0.12804094 | ... AY89: =AY88/AY86 -> 0.12909419
A90: EBITDA | AM90: =AM61/10^3 -> 212.66122 | AN90: =AN61/10^3 -> 332.23916 | AO90: =AO61/10^3 -> 871.98038 | AP90: =AP61/10^3 -> 148.39048 | AQ90: =AQ61/10^3 -> 206.5389 | AR90: =AR61/10^3 -> 219.49946 | AS90: =AS61/10^3 -> 342.33014 | AT90: =AT61/10^3 -> 916.75898 | ... AY90: =AY61/10^3 -> 950.01366
A91: Margin | AM91: =AM62 -> 0.15557493 | AN91: =AN62 -> 0.18595252 | AO91: =AO62 -> 0.15756397 | AP91: =AP62 -> 0.12748093 | AQ91: =AQ62 -> 0.15678284 | AR91: =AR62 -> 0.15516573 | AS91: =AS62 -> 0.18515157 | AT91: =AT62 -> 0.15957763 | ... AY91: =AY62 -> 0.16070339
A92: EPS | AM92: =AM18 -> 2.8013842 | AN92: =AN18 -> 4.8652057 | AO92: =AO18 -> 11.450754 | AP92: =AP18 -> 1.7611332 | AQ92: =AQ18 -> 2.7240626 | AR92: =AR18 -> 2.9598467 | AS92: =AS18 -> 5.0532175 | AT92: =AT18 -> 12.448033 | ... AY92: =AY18 -> 13.448709
A94: VAe | AM94: 3Q27 | AN94: 4Q27 | AO94: FY27 | AP94: 1Q28 | AQ94: 2Q28 | AR94: 3Q28 | AS94: 4Q28 | AT94: FY28 | AU94: 1Q29 | AV94: 2Q29 | AW94: 3Q29 | AX94: 4Q29 | AY94: FY29
A95: Net Sales | AM95: 1365.2358 | AN95: 1782.8669 | AO95: 5528.6127 | AP95: 1169.8711 | AQ95: 1321.3099 | AR95: 1420.3419 | AS95: 1854.9283 | AT95: 5762.1451 | AU95: 1208.947 | AV95: 1363.7654 | AW95: 1465.8547 | AX95: 1918.3644 | AY95: 5953.5569
A96: Gross Margin | AM96: 0.64141087 | AN96: 0.60640007 | AO96: 0.63741802 | AP96: 0.62982088 | AQ96: 0.63334957 | AR96: 0.63636857 | AS96: 0.6076291 | AT96: 0.62474768 | AU96: 0.63066866 | AV96: 0.63296685 | AW96: 0.63617986 | AX96: 0.60905185 | AY96: 0.62478874
A97: EBIT | AM97: 182.65209 | AN97: 289.44718 | AO97: 776.09626 | AP97: 97.32105 | AQ97: 162.78256 | AR97: 179.73591 | AS97: 297.63015 | AT97: 740.99616 | AU97: 103.46671 | AV97: 166.93351 | AW97: 186.88272 | AX97: 312.32275 | AY97: 762.46132
A98: Margin | AM98: =AM97/AM95 -> 0.13378794 | AN98: =AN97/AN95 -> 0.1623493 | AO98: =AO97/AO95 -> 0.14037812 | AP98: =AP97/AP95 -> 0.083189547 | AQ98: =AQ97/AQ95 -> 0.12319787 | AR98: =AR97/AR95 -> 0.12654411 | AS98: =AS97/AS95 -> 0.16045372 | AT98: =AT97/AT95 -> 0.12859728 | ... AY98: =AY97/AY95 -> 0.1280682
A99: EBITDA | AM99: 224.73845 | AN99: 334.5156 | AO99: 950.49087 | AP99: 145.25447 | AQ99: 211.47672 | AR99: 224.89149 | AS99: 344.98724 | AT99: 919.82437 | AU99: 152.10282 | AV99: 216.73494 | AW99: 233.4485 | AX99: 367.88228 | AY99: 930.36245
A100: Margin | AM100: =AM99/AM95 -> 0.16461511 | AN100: =AN99/AN95 -> 0.18762792 | AO100: =AO99/AO95 -> 0.17192213 | AP100: =AP99/AP95 -> 0.1241628 | AQ100: =AQ99/AQ95 -> 0.16005081 | AR100: =AR99/AR95 -> 0.15833616 | AS100: =AS99/AS95 -> 0.18598414 | AT100: =AT99/AT95 -> 0.15963228 | ... AY100: =AY99/AY95 -> 0.15627002
A101: EPS | AM101: 3.0263139 | AN101: 4.8564578 | AO101: 12.752606 | AP101: 1.6749796 | AQ101: 2.7632325 | AR101: 3.0733753 | AS101: 5.093323 | AT101: 12.716074 | AU101: 1.7993902 | AV101: 2.8590619 | AW101: 3.2557334 | AX101: 5.4599796 | AY101: 13.67202
AT102: =AT101/AO101-1 -> -0.0028646498 | AY102: =AY101/AT101-1 -> 0.075176214
A103: GSe vs VAe
A104: Net Sales | AM104: =AM$86/AM95-1 -> 0.0012464805 | AN104: =AN$86/AN95-1 -> 0.0021433345 | AO104: =AO$86/AO95-1 -> 0.00099898841 | AP104: =AP$86/AP95-1 -> -0.0050006477 | AQ104: =AQ$86/AQ95-1 -> -0.002992001 | AR104: =AR$86/AR95-1 -> -0.0040334827 | AS104: =AS$86/AS95-1 -> -0.0032399839 | AT104: =AT$86/AT95-1 -> -0.0029912666 | ... AY104: =AY$86/AY95-1 -> -0.0070478761
A105: Gross Margin | AM105: =ROUND(AM$87-AM96,3)*10^4 -> -30 | AN105: =ROUND(AN$87-AN96,3)*10^4 -> 50 | AO105: =ROUND(AO$87-AO96,3)*10^4 -> -110 | AP105: =ROUND(AP$87-AP96,3)*10^4 -> 0 | AQ105: =ROUND(AQ$87-AQ96,3)*10^4 -> 0 | AR105: =ROUND(AR$87-AR96,3)*10^4 -> 30 | AS105: =ROUND(AS$87-AS96,3)*10^4 -> 50 | AT105: =ROUND(AT$87-AT96,3)*10^4 -> 30 | ... AY105: =ROUND(AY$87-AY96,3)*10^4 -> 40
A106: EBIT | AM106: =AM$88/AM97-1 -> -0.072974069 | AN106: =AN$88/AN97-1 -> -0.0051170109 | AO106: =AO$88/AO97-1 -> -0.099613893 | AP106: =AP$88/AP97-1 -> 0.065707705 | AQ106: =AQ$88/AQ97-1 -> -0.0081316482 | AR106: =AR$88/AR97-1 -> -0.031701389 | AS106: =AS$88/AS97-1 -> -0.0042310177 | AT106: =AT$88/AT97-1 -> -0.0073044872 | ... AY106: =AY$88/AY97-1 -> 0.00090694766
A107: Margin | AM107: =ROUND(AM$89-AM98,3)*10^4 -> -100 | AN107: =ROUND(AN$89-AN98,3)*10^4 -> -10 | AO107: =ROUND(AO$89-AO98,3)*10^4 -> -140 | AP107: =ROUND(AP$89-AP98,3)*10^4 -> 60 | AQ107: =ROUND(AQ$89-AQ98,3)*10^4 -> -10 | AR107: =ROUND(AR$89-AR98,3)*10^4 -> -40 | AS107: =ROUND(AS$89-AS98,3)*10^4 -> 0 | AT107: =ROUND(AT$89-AT98,3)*10^4 -> -10 | ... AY107: =ROUND(AY$89-AY98,3)*10^4 -> 10
A108: EBITDA | AM108: =AM$90/AM99-1 -> -0.053739057 | AN108: =AN$90/AN99-1 -> -0.006805188 | AO108: =AO$90/AO99-1 -> -0.082599946 | AP108: =AP$90/AP99-1 -> 0.021589747 | AQ108: =AQ$90/AQ99-1 -> -0.023349247 | AR108: =AR$90/AR99-1 -> -0.023976152 | AS108: =AS$90/AS99-1 -> -0.0077020134 | AT108: =AT$90/AT99-1 -> -0.0033325807 | ... AY108: =AY$90/AY99-1 -> 0.021122104
A109: Margin | AM109: =ROUND(AM$91-AM100,3)*10^4 -> -90 | AN109: =ROUND(AN$91-AN100,3)*10^4 -> -20 | AO109: =ROUND(AO$91-AO100,3)*10^4 -> -140 | AP109: =ROUND(AP$91-AP100,3)*10^4 -> 30 | AQ109: =ROUND(AQ$91-AQ100,3)*10^4 -> -30 | AR109: =ROUND(AR$91-AR100,3)*10^4 -> -30 | AS109: =ROUND(AS$91-AS100,3)*10^4 -> -10 | AT109: =ROUND(AT$91-AT100,3)*10^4 -> 0 | ... AY109: =ROUND(AY$91-AY100,3)*10^4 -> 40
A110: EPS | AM110: =ROUND(AM$92,2)-ROUND(AM101,2) -> -0.23 | AN110: =ROUND(AN$92,2)-ROUND(AN101,2) -> 0.01 | AO110: =ROUND(AO$92,2)-ROUND(AO101,2) -> -1.3 | AP110: =ROUND(AP$92,2)-ROUND(AP101,2) -> 0.09 | AQ110: =ROUND(AQ$92,2)-ROUND(AQ101,2) -> -0.04 | AR110: =ROUND(AR$92,2)-ROUND(AR101,2) -> -0.11 | AS110: =ROUND(AS$92,2)-ROUND(AS101,2) -> -0.04 | AT110: =ROUND(AT$92,2)-ROUND(AT101,2) -> -0.27 | ... AY110: =ROUND(AY$92,2)-ROUND(AY101,2) -> -0.22
AO111: =AO92/AO101-1 -> -0.10208514 | AT111: =AT92/AT101-1 -> -0.021078924 | AY111: =AY92/AY101-1 -> -0.016333447
A112: Prior GSe
A113: Net Sales | AM113: 1366.9376 | AN113: 1786.6881 | AO113: 5534.1357 | AP113: 1164.021 | AQ113: 1317.3566 | AR113: 1414.613 | AS113: 1848.9184 | AT113: 5744.909 | AU113: 1195.9769 | AV113: 1353.7739 | AW113: 1457.1904 | AX113: 1904.6557 | AY113: 5911.5969
A114: Gross Margin | AM114: 0.63824184 | AN114: 0.61186754 | AO114: 0.62633379 | AP114: 0.62945197 | AQ114: 0.6330257 | AR114: 0.63924184 | AS114: 0.61286754 | AT114: 0.62734462 | AU114: 0.63145197 | AV114: 0.6330257 | AW114: 0.63924184 | AX114: 0.61486754 | AY114: 0.6283892
A115: EBIT | AM115: 169.32322 | AN115: 287.96607 | AO115: 698.78629 | AP115: 103.71579 | AQ115: 161.45887 | AR115: 174.03803 | AS115: 296.37087 | AT115: 735.58357 | AU115: 108.9276 | AV115: 165.89463 | AW115: 179.24618 | AX115: 309.08442 | AY115: 763.15283
...

Sheet BS
A1: ANF Balance Sheet
A3: Period | B3: ='Rev Driver'!B3 -> FY15 | C3: ='Rev Driver'!C3 -> FY16 | D3: ='Rev Driver'!D3 -> FY17 | E3: ='Rev Driver'!E3 -> FY18 | F3: ='Rev Driver'!F3 -> FY19 | G3: ='Rev Driver'!G3 -> 1Q20 | H3: ='Rev Driver'!H3 -> 2Q20 | I3: ='Rev Driver'!I3 -> 3Q20 | ... AY3: ='Rev Driver'!AY3 -> FY28E
A4: Date end | B4: ='Rev Driver'!B4 -> 42399 | C4: ='Rev Driver'!C4 -> 42763 | D4: ='Rev Driver'!D4 -> 43134 | E4: ='Rev Driver'!E4 -> 43498 | F4: ='Rev Driver'!F4 -> 43862 | G4: ='Rev Driver'!G4 -> 43953 | H4: ='Rev Driver'!H4 -> 44044 | I4: ='Rev Driver'!I4 -> 44135 | ... AY4: ='Rev Driver'!AY4 -> 47145
A5: # Weeks | B5: ='Rev Driver'!B5 -> 52 | C5: ='Rev Driver'!C5 -> 52 | D5: ='Rev Driver'!D5 -> 53 | E5: ='Rev Driver'!E5 -> 52 | F5: ='Rev Driver'!F5 -> 52 | G5: ='Rev Driver'!G5 -> 13 | H5: ='Rev Driver'!H5 -> 13 | I5: ='Rev Driver'!I5 -> 13 | ... AY5: ='Rev Driver'!AY5 -> 52
A6: Cash & Equiv. | B6: =SCF!B36 -> 588578 | C6: =SCF!C36 -> 547189 | D6: =SCF!D36 -> 675558 | E6: =SCF!E36 -> 723135 | F6: =SCF!F36 -> 671267 | G6: =SCF!G36 -> 703989 | H6: =SCF!H36 -> 766721 | I6: =SCF!I36 -> 812881 | ... AI6: =SCF!AI36 -> 759540 | AJ6: 759540 | AK6: =SCF!AK36 -> 594080 | AL6: =SCF!AL36 -> 627716 | AM6: =SCF!AM36 -> 676349.14 | AN6: =SCF!AN36 -> 768594.75 | AO6: =SCF!AO36 -> 768594.75 | AP6: =SCF!AP36 -> 828807.84 | AQ6: =SCF!AQ36 -> 956277.54 | AR6: =SCF!AR36 -> 850766.04 | ... AY6: =SCF!AY36 -> 1107375.1
A7: Marketable Securities | G7: 0 | H7: 0 | I7: 0 | J7: 0 | K7: =J7 -> 0 | L7: 0 | M7: 0 | N7: 0 | O7: 0 | P7: =O7 -> 0 | Q7: 0 | R7: 0 | S7: 0 | T7: 0 | U7: =T7 -> 0 | V7: 0 | W7: 0 | X7: 0 | Y7: 0 | Z7: =Y7 -> 0 | AA7: 0 | AB7: 0 | AC7: 0 | AD7: 116221 | AE7: =AD7 -> 116221 | AF7: 97006 | AG7: 30795 | AH7: 25255 | AI7: 25036 | AJ7: =AI7 -> 25036 | AK7: 25144 | AL7: 10283 | AM7: =AL7 -> 10283 | AN7: =AM7 -> 10283 | AO7: =AN7 -> 10283 | AP7: =AO7 -> 10283 | AQ7: =AP7 -> 10283 | AR7: =AQ7 -> 10283 | AS7: =AR7 -> 10283 | AT7: =AS7 -> 10283 | ... AY7: =AX7 -> 10283
A8: Receivables | B8: 56868 | C8: 93384 | D8: 79724 | E8: 73112 | F8: 80251 | G8: 88639 | H8: 88323 | I8: 89074 | J8: 83857 | K8: =J8 -> 83857 | L8: 107821 | M8: 87151 | N8: 83447 | O8: 69102 | P8: =O8 -> 69102 | Q8: 88807 | R8: 79820 | S8: 108468 | T8: 104506 | U8: =T8 -> 104506 | V8: 106149 | W8: 112597 | X8: 96762 | Y8: 78346 | Z8: =Y8 -> 78346 | AA8: 93605 | AB8: 115077 | AC8: 111583 | AD8: 105324 | AE8: =AD8 -> 105324 | AF8: 113311 | AG8: 174000 | AH8: 131741 | AI8: 146757 | AJ8: =AI8 -> 146757 | AK8: 146042 | AL8: 190347 | AM8: =AM50*2-AH8 -> 119114.57 | AN8: =AN50*2-AI8 -> 160710.43 | AO8: =AN8 -> 160710.43 | AP8: =AP50*2-AK8 -> 108507.65 | AQ8: =AQ50*2-AL8 -> 119448.94 | AR8: =AR50*2-AM8 -> 162875.32 | AS8: =AS50*2-AN8 -> 153402.51 | AT8: =AS8 -> 153402.51 | AU8: =AU50*2-AP8 -> 158287.19 | AV8: =AV50*2-AQ8 -> 139404.52 | AW8: =AW50*2-AR8 -> 175000.71 | AX8: =AX50*2-AS8 -> 164737.79 | AY8: =AX8 -> 164737.79
A9: Inventories | B9: 436701 | C9: 399795 | D9: 424393 | E9: 437879 | F9: 434326 | G9: 426594 | H9: 453239 | I9: 545548 | J9: 404053 | K9: =J9 -> 404053 | L9: 388633 | M9: 415604 | N9: 543713 | O9: 525864 | P9: =O9 -> 525864 | Q9: 562510 | R9: 708024 | S9: 741963 | T9: 505621 | U9: =T9 -> 505621 | V9: 447806 | W9: 493479 | X9: 595067 | Y9: 469466 | Z9: =Y9 -> 469466 | AA9: 449267 | AB9: 539759 | AC9: 692596 | AD9: 575005 | AE9: =AD9 -> 575005 | AF9: 542059 | AG9: 592966 | AH9: 730453 | AI9: 601218 | AJ9: =AI9 -> 601218 | AK9: 532691 | AL9: 591662 | AM9: =AM44*2-AH9 -> 748702.18 | AN9: =AN44*2-AI9 -> 646268.95 | AO9: =AN9 -> 646268.95 | AP9: =AP44*2-AK9 -> 567900.51 | AQ9: =AQ44*2-AL9 -> 688115.29 | AR9: =AR44*2-AM9 -> 765473.2 | AS9: =AS44*2-AN9 -> 692468.74 | AT9: =AS9 -> 692468.74 | AU9: =AU44*2-AP9 -> 519990.13 | AV9: =AV44*2-AQ9 -> 694190.36 | AW9: =AW44*2-AR9 -> 758459.81 | AX9: =AX44*2-AS9 -> 760111.11 | AY9: =AX9 -> 760111.11
A10: Other CA | B10: 96833 | C10: 98932 | D10: 84863 | E10: 101824 | F10: 78905 | G10: 67412 | H10: 75160 | I10: 73776 | J10: 68857 | K10: =J10 -> 68857 | L10: 78727 | M10: 77392 | N10: 111423 | O10: 89654 | P10: =O10 -> 89654 | Q10: 93179 | R10: 104887 | S10: 112602 | T10: 100289 | U10: =T10 -> 100289 | V10: 107684 | W10: 87850 | X10: 100085 | Y10: 88569 | Z10: =Y10 -> 88569 | AA10: 102516 | AB10: 123415 | AC10: 168499 | AD10: 104154 | AE10: =AD10 -> 104154 | AF10: 111231 | AG10: 118624 | AH10: 116303 | AI10: 117913 | AJ10: =AI10 -> 117913 | AK10: 117202 | AL10: 125670 | AM10: =AL10+(SCF!AM35-SCF!AL35)-SCF!AM17 -> 125670 | AN10: =AM10+(SCF!AN35-SCF!AM35)-SCF!AN17 -> 125670 | AO10: =AN10 -> 125670 | AP10: =AO10+(SCF!AP35-SCF!AO35)-SCF!AP17 -> 125670 | AQ10: =AP10+(SCF!AQ35-SCF!AP35)-SCF!AQ17 -> 125670 | AR10: =AQ10+(SCF!AR35-SCF!AQ35)-SCF!AR17 -> 125670 | AS10: =AR10+(SCF!AS35-SCF!AR35)-SCF!AS17 -> 125670 | AT10: =AS10 -> 125670 | AU10: =AT10+(SCF!AU35-SCF!AT35)-SCF!AU17 -> 125670 | AV10: =AU10+(SCF!AV35-SCF!AU35)-SCF!AV17 -> 125670 | AW10: =AV10+(SCF!AW35-SCF!AV35)-SCF!AW17 -> 125670 | AX10: =AW10+(SCF!AX35-SCF!AW35)-SCF!AX17 -> 125670 | AY10: =AX10 -> 125670
A11: Total CA | B11: =SUM(B6:B10) -> 1178980 | C11: =SUM(C6:C10) -> 1139300 | D11: =SUM(D6:D10) -> 1264538 | E11: =SUM(E6:E10) -> 1335950 | F11: =SUM(F6:F10) -> 1264749 | G11: =SUM(G6:G10) -> 1286634 | H11: =SUM(H6:H10) -> 1383443 | I11: =SUM(I6:I10) -> 1521279 | J11: =SUM(J6:J10) -> 1661629 | K11: =J11 -> 1661629 | L11: =SUM(L6:L10) -> 1484189 | M11: =SUM(M6:M10) -> 1501651 | N11: =SUM(N6:N10) -> 1604205 | O11: =SUM(O6:O10) -> 1507759 | P11: =O11 -> 1507759 | Q11: =SUM(Q6:Q10) -> 1212874 | R11: =SUM(R6:R10) -> 1262688 | S11: =SUM(S6:S10) -> 1220365 | T11: =SUM(T6:T10) -> 1228018 | U11: =T11 -> 1228018 | V11: =SUM(V6:V10) -> 1108591 | W11: =SUM(W6:W10) -> 1311265 | X11: =SUM(X6:X10) -> 1441403 | Y11: =SUM(Y6:Y10) -> 1537265 | Z11: =Y11 -> 1537265 | AA11: =SUM(AA6:AA10) -> 1509583 | AB11: =SUM(AB6:AB10) -> 1516653 | AC11: =SUM(AC6:AC10) -> 1655767 | AD11: =SUM(AD6:AD10) -> 1673431 | AE11: =AD11 -> 1673431 | AF11: =SUM(AF6:AF10) -> 1374170 | AG11: =SUM(AG6:AG10) -> 1489115 | AH11: =SUM(AH6:AH10) -> 1609535 | AI11: =SUM(AI6:AI10) -> 1650464 | AJ11: =AI11 -> 1650464 | AK11: =SUM(AK6:AK10) -> 1415159 | AL11: =SUM(AL6:AL10) -> 1545678 | AM11: =SUM(AM6:AM10) -> 1680118.9 | AN11: =SUM(AN6:AN10) -> 1711527.1 | AO11: =AN11 -> 1711527.1 | AP11: =SUM(AP6:AP10) -> 1641169 | AQ11: =SUM(AQ6:AQ10) -> 1899794.8 | AR11: =SUM(AR6:AR10) -> 1915067.6 | AS11: =SUM(AS6:AS10) -> 1910909.4 | AT11: =AS11 -> 1910909.4 | AU11: =SUM(AU6:AU10) -> 1778760.8 | AV11: =SUM(AV6:AV10) -> 2020367.8 | AW11: =SUM(AW6:AW10) -> 2170336.9 | AX11: =SUM(AX6:AX10) -> 2168177 | AY11: =AX11 -> 2168177
A12: PP&E | B12: 894178 | C12: 824738 | D12: 738182 | E12: 694855 | F12: 665290 | G12: 654784 | H12: 635703 | I12: 593932 | J12: 550587 | K12: =J12 -> 550587 | L12: 533773 | M12: 532795 | N12: 516176 | O12: 508336 | P12: =O12 -> 508336 | Q12: 497976 | R12: 511181 | S12: 542138 | T12: 551585 | U12: =T12 -> 551585 | V12: 550810 | W12: 553680 | X12: 546935 | Y12: 538033 | Z12: =Y12 -> 538033 | AA12: 540697 | AB12: 552453 | AC12: 570440 | AD12: 575773 | AE12: =AD12 -> 575773 | AF12: 606060 | AG12: 638590 | AH12: 661646 | AI12: 674079 | AJ12: =AI12 -> 674079 | AK12: 686576 | AL12: 708576 | AM12: =AL12-SCF!AM23-SCF!AM7-SCF!AM8 -> 730245 | AN12: =AM12-SCF!AN23-SCF!AN7-SCF!AN8 -> 741313.27 | AO12: =AN12 -> 741313.27 | AP12: =AO12-SCF!AP23-SCF!AP7-SCF!AP8 -> 752481.94 | AQ12: =AP12-SCF!AQ23-SCF!AQ7-SCF!AQ8 -> 763751.95 | AR12: =AQ12-SCF!AR23-SCF!AR7-SCF!AR8 -> 775117.31 | AS12: =AR12-SCF!AS23-SCF!AS7-SCF!AS8 -> 786607.12 | AT12: =AS12 -> 786607.12 | AU12: =AT12-SCF!AU23-SCF!AU7-SCF!AU8 -> 798160.85 | AV12: =AU12-SCF!AV23-SCF!AV7-SCF!AV8 -> 809787.42 | AW12: =AV12-SCF!AW23-SCF!AW7-SCF!AW8 -> 821499.14 | AX12: =AW12-SCF!AX23-SCF!AX7-SCF!AX8 -> 833322.33 | AY12: =AX12 -> 833322.33
A13: Op. Lease ROU | F13: 1230954 | G13: 1133618 | H13: 1073464 | I13: 955781 | J13: 893989 | K13: =J13 -> 893989 | L13: 839003 | M13: 791036 | N13: 762641 | O13: 698231 | P13: =O13 -> 698231 | Q13: 671991 | R13: 740627 | S13: 713166 | T13: 723550 | U13: =T13 -> 723550 | V13: 692699 | W13: 714977 | X13: 682559 | Y13: 678256 | Z13: =Y13 -> 678256 | AA13: 699471 | AB13: 746788 | AC13: 798290 | AD13: 803121 | AE13: =AD13 -> 803121 | AF13: 868130 | AG13: 933559 | AH13: 965919 | AI13: 997399 | AJ13: =AI13 -> 997399 | AK13: 1115832 | AL13: 1107421 | AM13: =AL13*(1+AM65) -> 1162792.1 | AN13: =AM13*(1+AN65) -> 1220931.7 | AO13: =AN13 -> 1220931.7 | AP13: =AO13*(1+AP65) -> 1281978.2 | AQ13: =AP13*(1+AQ65) -> 1346077.1 | AR13: =AQ13*(1+AR65) -> 1413381 | AS13: =AR13*(1+AS65) -> 1484050.1 | AT13: =AS13 -> 1484050.1 | AU13: =AT13*(1+AU65) -> 1558252.6 | AV13: =AU13*(1+AV65) -> 1636165.2 | AW13: =AV13*(1+AW65) -> 1717973.4 | AX13: =AW13*(1+AX65) -> 1803872.1 | AY13: =AX13 -> 1803872.1
A14: Other NCA | B14: 359881 | C14: 331719 | D14: 322972 | E14: 354788 | F14: 388672 | G14: 216795 | H14: 216204 | I14: 205970 | J14: 208697 | K14: =J14 -> 208697 | L14: 213585 | M14: 229911 | N14: 229512 | O14: 225165 | P14: =O14 -> 225165 | Q14: 224462 | R14: 219598 | S14: 218325 | T14: 209947 | U14: =T14 -> 209947 | V14: 205978 | W14: 216792 | X14: 226749 | Y14: 220679 | Z14: =Y14 -> 220679 | AA14: 220334 | AB14: 233664 | AC14: 245375 | AD14: 247562 | AE14: =AD14 -> 247562 | AF14: 247816 | AG14: 240677 | AH14: 242818 | AI14: 219932 | AJ14: =AI14 -> 219932 | AK14: 235397 | AL14: 233181 | AM14: =AL14 -> 233181 | AN14: =AM14 -> 233181 | AO14: =AN14 -> 233181 | AP14: =AO14 -> 233181 | AQ14: =AP14 -> 233181 | AR14: =AQ14 -> 233181 | AS14: =AR14 -> 233181 | AT14: =AS14 -> 233181 | ... AY14: =AX14 -> 233181
A15: Total Assets | B15: =SUM(B12:B14,B11) -> 2433039 | C15: =SUM(C12:C14,C11) -> 2295757 | D15: =SUM(D12:D14,D11) -> 2325692 | E15: =SUM(E12:E14,E11) -> 2385593 | F15: =SUM(F12:F14,F11) -> 3549665 | G15: =SUM(G12:G14,G11) -> 3291831 | H15: =SUM(H12:H14,H11) -> 3308814 | I15: =SUM(I12:I14,I11) -> 3276962 | J15: =SUM(J12:J14,J11) -> 3314902 | K15: =J15 -> 3314902 | L15: =SUM(L12:L14,L11) -> 3070550 | M15: =SUM(M12:M14,M11) -> 3055393 | N15: =SUM(N12:N14,N11) -> 3112534 | O15: =SUM(O12:O14,O11) -> 2939491 | P15: =O15 -> 2939491 | Q15: =SUM(Q12:Q14,Q11) -> 2607303 | R15: =SUM(R12:R14,R11) -> 2734094 | S15: =SUM(S12:S14,S11) -> 2693994 | T15: =SUM(T12:T14,T11) -> 2713100 | U15: =T15 -> 2713100 | V15: =SUM(V12:V14,V11) -> 2558078 | W15: =SUM(W12:W14,W11) -> 2796714 | X15: =SUM(X12:X14,X11) -> 2897646 | Y15: =SUM(Y12:Y14,Y11) -> 2974233 | Z15: =Y15 -> 2974233 | AA15: =SUM(AA12:AA14,AA11) -> 2970085 | AB15: =SUM(AB12:AB14,AB11) -> 3049558 | AC15: =SUM(AC12:AC14,AC11) -> 3269872 | AD15: =SUM(AD12:AD14,AD11) -> 3299887 | AE15: =AD15 -> 3299887 | AF15: =SUM(AF12:AF14,AF11) -> 3096176 | AG15: =SUM(AG12:AG14,AG11) -> 3301941 | AH15: =SUM(AH12:AH14,AH11) -> 3479918 | AI15: =SUM(AI12:AI14,AI11) -> 3541874 | AJ15: =AI15 -> 3541874 | AK15: =SUM(AK12:AK14,AK11) -> 3452964 | AL15: =SUM(AL12:AL14,AL11) -> 3594856 | AM15: =SUM(AM12:AM14,AM11) -> 3806336.9 | AN15: =SUM(AN12:AN14,AN11) -> 3906953.1 | AO15: =AN15 -> 3906953.1 | AP15: =SUM(AP12:AP14,AP11) -> 3908810.2 | AQ15: =SUM(AQ12:AQ14,AQ11) -> 4242804.9 | AR15: =SUM(AR12:AR14,AR11) -> 4336746.9 | AS15: =SUM(AS12:AS14,AS11) -> 4414747.6 | AT15: =AS15 -> 4414747.6 | AU15: =SUM(AU12:AU14,AU11) -> 4368355.3 | AV15: =SUM(AV12:AV14,AV11) -> 4699501.4 | AW15: =SUM(AW12:AW14,AW11) -> 4942990.5 | AX15: =SUM(AX12:AX14,AX11) -> 5038552.5 | AY15: =AX15 -> 5038552.5
A17: Acc. Payable | B17: 184175 | C17: 187017 | D17: 168868 | E17: 226878 | F17: 219919 | G17: 162747 | H17: 284221 | I17: 334775 | J17: 289396 | K17: =J17 -> 289396 | L17: 236667 | M17: 289475 | N17: 424560 | O17: 374829 | P17: =O17 -> 374829 | Q17: 311352 | R17: 408297 | S17: 322128 | T17: 258895 | U17: =T17 -> 258895 | V17: 221587 | W17: 323197 | X17: 373930 | Y17: 296976 | Z17: =Y17 -> 296976 | AA17: 266925 | AB17: 406756 | AC17: 466303 | AD17: 364532 | AE17: =AD17 -> 364532 | AF17: 296738 | AG17: 368051 | AH17: 461528 | AI17: 377465 | AJ17: =AI17 -> 377465 | AK17: 257945 | AL17: 354209 | AM17: =AM56*2-AH17 -> 473132.88 | AN17: =AN56*2-AI17 -> 405929.37 | AO17: =AN17 -> 405929.37 | AP17: =AP56*2-AK17 -> 341171.14 | AQ17: =AQ56*2-AL17 -> 565913.15 | AR17: =AR56*2-AM17 -> 537438.99 | AS17: =AS56*2-AN17 -> 403448.47 | AT17: =AS17 -> 403448.47 | AU17: =AU56*2-AP17 -> 266226.4 | AV17: =AV56*2-AQ17 -> 463718.94 | AW17: =AW56*2-AR17 -> 559007.13 | AX17: =AX56*2-AS17 -> 410705.61 | AY17: =AX17 -> 410705.61
A18: Accrued Exp. | B18: 321237 | C18: 273044 | D18: 308601 | E18: 293579 | F18: 302214 | G18: 285799 | H18: 351849 | I18: 356370 | J18: 396365 | K18: =J18 -> 396365 | L18: 321906 | M18: 351991 | N18: 355149 | O18: 395815 | P18: =O18 -> 395815 | Q18: 320681 | R18: 342690 | S18: 378366 | T18: 413303 | U18: =T18 -> 413303 | V18: 340331 | W18: 375544 | X18: 402572 | Y18: 436655 | Z18: =Y18 -> 436655 | AA18: 402786 | AB18: 422484 | AC18: 469148 | AD18: 504922 | AE18: =AD18 -> 504922 | AF18: 433682 | AG18: 429616 | AH18: 458075 | AI18: 465549 | AJ18: =AI18 -> 465549 | AK18: 425149 | AL18: 443364 | AM18: =AL18 -> 443364 | AN18: =AM18 -> 443364 | AO18: =AN18 -> 443364 | AP18: =AO18 -> 443364 | AQ18: =AP18 -> 443364 | AR18: =AQ18 -> 443364 | AS18: =AR18 -> 443364 | AT18: =AS18 -> 443364 | ... AY18: =AX18 -> 443364
A19: ST of Op. Lease Liabilities | F19: 282829 | G19: 307173 | H19: 278495 | I19: 255775 | J19: 248846 | K19: =J19 -> 248846 | L19: 231750 | M19: 219453 | N19: 209812 | O19: 222823 | P19: =O19 -> 222823 | Q19: 195599 | R19: 202699 | S19: 211304 | T19: 213979 | U19: =T19 -> 213979 | V19: 188520 | W19: 191700 | X19: 195025 | Y19: 179625 | Z19: =Y19 -> 179625 | AA19: 188851 | AB19: 202840 | AC19: 210335 | AD19: 211600 | AE19: =AD19 -> 211600 | AF19: 215511 | AG19: 223020 | AH19: 225847 | AI19: 241265 | AJ19: =AI19 -> 241265 | AK19: 262316 | AL19: 262354 | AM19: =(AL19+AL24)*(1+AM66)*AM67 -> 275471.7 | AN19: =(AM19+AM24)*(1+AN66)*AN67 -> 289245.28 | AO19: =AN19 -> 289245.28 | AP19: =(AO19+AO24)*(1+AP66)*AP67 -> 303707.55 | AQ19: =(AP19+AP24)*(1+AQ66)*AQ67 -> 318892.93 | AR19: =(AQ19+AQ24)*(1+AR66)*AR67 -> 334837.57 | AS19: =(AR19+AR24)*(1+AS66)*AS67 -> 351579.45 | AT19: =AS19 -> 351579.45 | AU19: =(AT19+AT24)*(1+AU66)*AU67 -> 369158.42 | AV19: =(AU19+AU24)*(1+AV66)*AV67 -> 387616.35 | AW19: =(AV19+AV24)*(1+AW66)*AW67 -> 406997.16 | AX19: =(AW19+AW24)*(1+AX66)*AX67 -> 427347.02 | AY19: =AX19 -> 427347.02
A20: ST of deferred lease credits | B20: 23303 | C20: 20076 | D20: 19751 | E20: 19558
A21: ST of borrowings | G21: 210000 | H21: 0 | I21: 0
A22: Taxes Payable | B22: 5988 | C22: 5863 | D22: 10326 | E22: 18902 | F22: 10392 | G22: 8232 | H22: 6425 | I22: 6663 | J22: 24792 | K22: =J22 -> 24792 | L22: 26672 | M22: 26260 | N22: 39900 | O22: 21773 | P22: =O22 -> 21773 | Q22: 25400 | R22: 5582 | S22: 23694 | T22: 16023 | U22: =T22 -> 16023 | V22: 19023 | W22: 46039 | X22: 55615 | Y22: 53564 | Z22: =Y22 -> 53564 | AA22: 61137 | AB22: 19576 | AC22: 36303 | AD22: 45890 | AE22: =AD22 -> 45890 | AF22: 52939 | AG22: 17354 | AH22: 17557 | AI22: 21721 | AJ22: =AI22 -> 21721 | AK22: 31708 | AL22: 38871 | AM22: =AL22+SCF!AM16 -> 38871 | AN22: =AM22+SCF!AN16 -> 38871 | AO22: =AN22 -> 38871 | AP22: =AO22+SCF!AP16 -> 38871 | AQ22: =AP22+SCF!AQ16 -> 38871 | AR22: =AQ22+SCF!AR16 -> 38871 | AS22: =AR22+SCF!AS16 -> 38871 | AT22: =AS22 -> 38871 | AU22: =AT22+SCF!AU16 -> 38871 | AV22: =AU22+SCF!AV16 -> 38871 | AW22: =AV22+SCF!AW16 -> 38871 | AX22: =AW22+SCF!AX16 -> 38871 | AY22: =AX22 -> 38871
A23: Total CL | B23: =SUM(B17:B22) -> 534703 | C23: =SUM(C17:C22) -> 486000 | D23: =SUM(D17:D22) -> 507546 | E23: =SUM(E17:E22) -> 558917 | F23: =SUM(F17:F22) -> 815354 | G23: =SUM(G17:G22) -> 973951 | H23: =SUM(H17:H22) -> 920990 | I23: =SUM(I17:I22) -> 953583 | J23: =SUM(J17:J22) -> 959399 | K23: =J23 -> 959399 | L23: =SUM(L17:L22) -> 816995 | M23: =SUM(M17:M22) -> 887179 | N23: =SUM(N17:N22) -> 1029421 | O23: =SUM(O17:O22) -> 1015240 | P23: =O23 -> 1015240 | Q23: =SUM(Q17:Q22) -> 853032 | R23: =SUM(R17:R22) -> 959268 | S23: =SUM(S17:S22) -> 935492 | T23: =SUM(T17:T22) -> 902200 | U23: =T23 -> 902200 | V23: =SUM(V17:V22) -> 769461 | W23: =SUM(W17:W22) -> 936480 | X23: =SUM(X17:X22) -> 1027142 | Y23: =SUM(Y17:Y22) -> 966820 | Z23: =Y23 -> 966820 | AA23: =SUM(AA17:AA22) -> 919699 | AB23: =SUM(AB17:AB22) -> 1051656 | AC23: =SUM(AC17:AC22) -> 1182089 | AD23: =SUM(AD17:AD22) -> 1126944 | AE23: =AD23 -> 1126944 | AF23: =SUM(AF17:AF22) -> 998870 | AG23: =SUM(AG17:AG22) -> 1038041 | AH23: =SUM(AH17:AH22) -> 1163007 | AI23: =SUM(AI17:AI22) -> 1106000 | AJ23: =AI23 -> 1106000 | AK23: =SUM(AK17:AK22) -> 977118 | AL23: =SUM(AL17:AL22) -> 1098798 | AM23: =SUM(AM17:AM22) -> 1230839.6 | AN23: =SUM(AN17:AN22) -> 1177409.7 | AO23: =AN23 -> 1177409.7 | AP23: =SUM(AP17:AP22) -> 1127113.7 | AQ23: =SUM(AQ17:AQ22) -> 1367041.1 | AR23: =SUM(AR17:AR22) -> 1354511.6 | AS23: =SUM(AS17:AS22) -> 1237262.9 | AT23: =AS23 -> 1237262.9 | AU23: =SUM(AU17:AU22) -> 1117619.8 | AV23: =SUM(AV17:AV22) -> 1333570.3 | AW23: =SUM(AW17:AW22) -> 1448239.3 | AX23: =SUM(AX17:AX22) -> 1320287.6 | AY23: =AX23 -> 1320287.6
A24: LT of Op. Lease Liabilities | F24: 1252634 | G24: 1184448 | H24: 1122853 | I24: 1010051 | J24: 957588 | K24: =J24 -> 957588 | L24: 844401 | M24: 791793 | N24: 764346 | O24: 697264 | P24: =O24 -> 697264 | Q24: 662322 | R24: 714265 | S24: 708512 | T24: 713361 | U24: =T24 -> 713361 | V24: 682996 | W24: 692046 | X24: 658923 | Y24: 646624 | Z24: =Y24 -> 646624 | AA24: 656862 | AB24: 688006 | AC24: 734918 | AD24: 740013 | AE24: =AD24 -> 740013 | AF24: 810391 | AG24: 876461 | AH24: 905041 | AI24: 926830 | AJ24: =AI24 -> 926830 | AK24: 1030161 | AL24: 1025086 | AM24: =(AL19+AL24)*(1+AM66)*(1-AM67) -> 1076340.3 | AN24: =(AM19+AM24)*(1+AN66)*(1-AN67) -> 1130157.3 | AO24: =AN24 -> 1130157.3 | AP24: =(AO19+AO24)*(1+AP66)*(1-AP67) -> 1186665.2 | AQ24: =(AP19+AP24)*(1+AQ66)*(1-AQ67) -> 1245998.4 | AR24: =(AQ19+AQ24)*(1+AR66)*(1-AR67) -> 1308298.4 | AS24: =(AR19+AR24)*(1+AS66)*(1-AS67) -> 1373713.3 | AT24: =AS24 -> 1373713.3 | AU24: =(AT19+AT24)*(1+AU66)*(1-AU67) -> 1442398.9 | AV24: =(AU19+AU24)*(1+AV66)*(1-AV67) -> 1514518.9 | AW24: =(AV19+AV24)*(1+AW66)*(1-AW67) -> 1590244.8 | AX24: =(AW19+AW24)*(1+AX66)*(1-AX67) -> 1669757.1 | AY24: =AX24 -> 1669757.1
A25: LT borrowings, net | B25: 286235 | C25: 262992 | D25: 249686 | E25: 250439 | F25: 231963 | G25: 232178 | H25: 343250 | I25: 343559 | J25: 343910 | K25: =J25 -> 343910 | L25: 344278 | M25: 303015 | N25: 303247 | O25: 303574 | P25: =O25 -> 303574 | Q25: 303901 | R25: 304219 | S25: 296532 | T25: 296852 | U25: =T25 -> 296852 | V25: 297172 | W25: 297385 | X25: 248033 | Y25: 222119 | Z25: =Y25 -> 222119 | AA25: 213102 | AB25: 0 | AC25: 0 | AD25: 0 | AE25: =AD25 -> 0 | AF25: 0 | AG25: 0 | AH25: 0 | AI25: 0 | AJ25: =AI25 -> 0 | AK25: 0 | AL25: 0 | AM25: 0 | AN25: 0 | AO25: =AN25 -> 0 | AP25: 0 | AQ25: 0 | AR25: 0 | AS25: 0 | AT25: =AS25 -> 0 | AU25: 0 | AV25: 0 | AW25: 0 | AX25: 0 | AY25: =AX25 -> 0
A26: Other LT liabilities | B26: =89256+47440+179683 -> 316379 | C26: =76321+46397+172008 -> 294726 | D26: =75648+50653+189688 -> 315989 | E26: =76134+46337+235145 -> 357616 | F26: 178536 | G26: 103188 | H26: 108111 | I26: 110965 | J26: 104693 | K26: =J26 -> 104693 | L26: 114926 | M26: 106473 | N26: 97191 | O26: 86089 | P26: =O26 -> 86089 | Q26: 83243 | R26: 83415 | S26: 97393 | T26: 94118 | U26: =T26 -> 94118 | V26: 97476 | W26: 92019 | X26: 87435 | Y26: 88683 | Z26: =Y26 -> 88683 | AA26: 89252 | AB26: 88746 | AC26: 92405 | AD26: 81607 | AE26: =AD26 -> 81607 | AF26: 84321 | AG26: 80235 | AH26: 80460 | AI26: 88633 | AJ26: =AI26 -> 88633 | AK26: 91789 | AL26: 101310 | AM26: =AL26+SCF!AM11+SCF!AM29+SCF!AM9 -> 101310 | AN26: =AM26+SCF!AN11+SCF!AN29+SCF!AN9 -> 101310 | AO26: =AN26 -> 101310 | AP26: =AO26+SCF!AP11+SCF!AP29+SCF!AP9 -> 101310 | AQ26: =AP26+SCF!AQ11+SCF!AQ29+SCF!AQ9 -> 101310 | AR26: =AQ26+SCF!AR11+SCF!AR29+SCF!AR9 -> 101310 | AS26: =AR26+SCF!AS11+SCF!AS29+SCF!AS9 -> 101310 | AT26: =AS26 -> 101310 | AU26: =AT26+SCF!AU11+SCF!AU29+SCF!AU9 -> 101310 | AV26: =AU26+SCF!AV11+SCF!AV29+SCF!AV9 -> 101310 | AW26: =AV26+SCF!AW11+SCF!AW29+SCF!AW9 -> 101310 | AX26: =AW26+SCF!AX11+SCF!AX29+SCF!AX9 -> 101310 | AY26: =AX26 -> 101310
A27: Total Liabilities | B27: =SUM(B23:B26) -> 1137317 | C27: =SUM(C23:C26) -> 1043718 | D27: =SUM(D23:D26) -> 1073221 | E27: =SUM(E23:E26) -> 1166972 | F27: =SUM(F23:F26) -> 2478487 | G27: =SUM(G23:G26) -> 2493765 | H27: =SUM(H23:H26) -> 2495204 | I27: =SUM(I23:I26) -> 2418158 | J27: =SUM(J23:J26) -> 2365590 | K27: =J27 -> 2365590 | L27: =SUM(L23:L26) -> 2120600 | M27: =SUM(M23:M26) -> 2088460 | N27: =SUM(N23:N26) -> 2194205 | O27: =SUM(O23:O26) -> 2102167 | P27: =O27 -> 2102167 | Q27: =SUM(Q23:Q26) -> 1902498 | R27: =SUM(R23:R26) -> 2061167 | S27: =SUM(S23:S26) -> 2037929 | T27: =SUM(T23:T26) -> 2006531 | U27: =T27 -> 2006531 | V27: =SUM(V23:V26) -> 1847105 | W27: =SUM(W23:W26) -> 2017930 | X27: =SUM(X23:X26) -> 2021533 | Y27: =SUM(Y23:Y26) -> 1924246 | Z27: =Y27 -> 1924246 | AA27: =SUM(AA23:AA26) -> 1878915 | AB27: =SUM(AB23:AB26) -> 1828408 | AC27: =SUM(AC23:AC26) -> 2009412 | AD27: =SUM(AD23:AD26) -> 1948564 | AE27: =AD27 -> 1948564 | AF27: =SUM(AF23:AF26) -> 1893582 | AG27: =SUM(AG23:AG26) -> 1994737 | AH27: =SUM(AH23:AH26) -> 2148508 | AI27: =SUM(AI23:AI26) -> 2121463 | AJ27: =AI27 -> 2121463 | AK27: =SUM(AK23:AK26) -> 2099068 | AL27: =SUM(AL23:AL26) -> 2225194 | AM27: =SUM(AM23:AM26) -> 2408489.9 | AN27: =SUM(AN23:AN26) -> 2408877 | AO27: =AN27 -> 2408877 | AP27: =SUM(AP23:AP26) -> 2415088.9 | AQ27: =SUM(AQ23:AQ26) -> 2714349.5 | AR27: =SUM(AR23:AR26) -> 2764119.9 | AS27: =SUM(AS23:AS26) -> 2712286.2 | AT27: =AS27 -> 2712286.2 | AU27: =SUM(AU23:AU26) -> 2661328.8 | AV27: =SUM(AV23:AV26) -> 2949399.2 | AW27: =SUM(AW23:AW26) -> 3139794.1 | AX27: =SUM(AX23:AX26) -> 3091354.7 | AY27: =AX27 -> 3091354.7
A29: Shareholder's Equity | B29: 1295722 | C29: 1252039 | D29: 1252471 | E29: 1218621 | F29: 1071178 | G29: 798066 | H29: 813610 | I29: 858804 | J29: 949312 | K29: =J29 -> 949312 | L29: 949950 | M29: 966933 | N29: 918329 | O29: 837324 | P29: =O29 -> 837324 | Q29: 704805 | R29: 672927 | S29: 656065 | T29: 706569 | U29: =T29 -> 706569 | V29: 710973 | W29: 778784 | X29: 876113 | Y29: 1049987 | Z29: =Y29 -> 1049987 | AA29: 1091170 | AB29: 1221150 | AC29: 1260460 | AD29: 1351323 | AE29: =AD29 -> 1351323 | AF29: 1202594 | AG29: 1307204 | AH29: 1331410 | AI29: 1420411 | AJ29: =AI29 -> 1420411 | AK29: 1353896 | AL29: 1369662 | AM29: =AL29+SCF!AM6+SCF!AM27+SCF!AM28+SCF!AM10+SCF!AM31 -> 1397847.1 | AN29: =AM29+SCF!AN6+SCF!AN27+SCF!AN28+SCF!AN10+SCF!AN31 -> 1498076.1 | AO29: =AN29 -> 1498076.1 | AP29: =AO29+SCF!AP6+SCF!AP27+SCF!AP28+SCF!AP10+SCF!AP31 -> 1493721.3 | AQ29: =AP29+SCF!AQ6+SCF!AQ27+SCF!AQ28+SCF!AQ10+SCF!AQ31 -> 1528455.3 | AR29: =AQ29+SCF!AR6+SCF!AR27+SCF!AR28+SCF!AR10+SCF!AR31 -> 1572626.9 | AS29: =AR29+SCF!AS6+SCF!AS27+SCF!AS28+SCF!AS10+SCF!AS31 -> 1702461.4 | AT29: =AS29 -> 1702461.4 | AU29: =AT29+SCF!AU6+SCF!AU27+SCF!AU28+SCF!AU10+SCF!AU31 -> 1707026.5 | AV29: =AU29+SCF!AV6+SCF!AV27+SCF!AV28+SCF!AV10+SCF!AV31 -> 1750102.3 | AW29: =AV29+SCF!AW6+SCF!AW27+SCF!AW28+SCF!AW10+SCF!AW31 -> 1803196.3 | AX29: =AW29+SCF!AX6+SCF!AX27+SCF!AX28+SCF!AX10+SCF!AX31 -> 1947197.8 | AY29: =AX29 -> 1947197.8
A30: Total Liabilities + SE | B30: =B29+B27 -> 2433039 | C30: =C29+C27 -> 2295757 | D30: =D29+D27 -> 2325692 | E30: =E29+E27 -> 2385593 | F30: =F29+F27 -> 3549665 | G30: =G29+G27 -> 3291831 | H30: =H29+H27 -> 3308814 | I30: =I29+I27 -> 3276962 | J30: =J29+J27 -> 3314902 | K30: =J30 -> 3314902 | L30: =L29+L27 -> 3070550 | M30: =M29+M27 -> 3055393 | N30: =N29+N27 -> 3112534 | O30: =O29+O27 -> 2939491 | P30: =O30 -> 2939491 | Q30: =Q29+Q27 -> 2607303 | R30: =R29+R27 -> 2734094 | S30: =S29+S27 -> 2693994 | T30: =T29+T27 -> 2713100 | U30: =T30 -> 2713100 | V30: =V29+V27 -> 2558078 | W30: =W29+W27 -> 2796714 | X30: =X29+X27 -> 2897646 | Y30: =Y29+Y27 -> 2974233 | Z30: =Y30 -> 2974233 | AA30: =AA29+AA27 -> 2970085 | AB30: =AB29+AB27 -> 3049558 | AC30: =AC29+AC27 -> 3269872 | AD30: =AD29+AD27 -> 3299887 | AE30: =AD30 -> 3299887 | AF30: =AF29+AF27 -> 3096176 | AG30: =AG29+AG27 -> 3301941 | AH30: =AH29+AH27 -> 3479918 | AI30: =AI29+AI27 -> 3541874 | AJ30: =AI30 -> 3541874 | AK30: =AK29+AK27 -> 3452964 | AL30: =AL29+AL27 -> 3594856 | AM30: =AM29+AM27 -> 3806336.9 | AN30: =AN29+AN27 -> 3906953.1 | AO30: =AN30 -> 3906953.1 | AP30: =AP29+AP27 -> 3908810.2 | AQ30: =AQ29+AQ27 -> 4242804.9 | AR30: =AR29+AR27 -> 4336746.9 | AS30: =AS29+AS27 -> 4414747.6 | AT30: =AS30 -> 4414747.6 | AU30: =AU29+AU27 -> 4368355.3 | AV30: =AV29+AV27 -> 4699501.4 | AW30: =AW29+AW27 -> 4942990.5 | AX30: =AX29+AX27 -> 5038552.5 | AY30: =AX30 -> 5038552.5
A31: Check | B31: =(IF(B30=B15,"-",B30-B15)) -> - | C31: =(IF(C30=C15,"-",C30-C15)) -> - | D31: =(IF(D30=D15,"-",D30-D15)) -> - | E31: =(IF(E30=E15,"-",E30-E15)) -> - | F31: =(IF(F30=F15,"-",F30-F15)) -> - | G31: =(IF(G30=G15,"-",G30-G15)) -> - | H31: =(IF(H30=H15,"-",H30-H15)) -> - | I31: =(IF(I30=I15,"-",I30-I15)) -> - | ... AG31: =(IF(AG30=AG15,"-",AG30-AG15)) -> - | AH31: =(IF(MROUND(AH30,1)=MROUND(AH15,1),"-",AH30-AH15)) -> - | AI31: =(IF(MROUND(AI30,1)=MROUND(AI15,1),"-",AI30-AI15)) -> - | AJ31: =(IF(MROUND(AJ30,1)=MROUND(AJ15,1),"-",AJ30-AJ15)) -> - | AK31: =(IF(MROUND(AK30,1)=MROUND(AK15,1),"-",AK30-AK15)) -> - | AL31: =(IF(MROUND(AL30,1)=MROUND(AL15,1),"-",AL30-AL15)) -> - | AM31: =(IF(MROUND(AM30,1)=MROUND(AM15,1),"-",AM30-AM15)) -> - | AN31: =(IF(MROUND(AN30,1)=MROUND(AN15,1),"-",AN30-AN15)) -> - | AO31: =(IF(MROUND(AO30,1)=MROUND(AO15,1),"-",AO30-AO15)) -> - | ... AY31: =(IF(MROUND(AY30,1)=MROUND(AY15,1),"-",AY30-AY15)) -> -
A35: Income Statement items
A36: Sales | B36: =IS!B6 -> 3518680 | C36: =IS!C6 -> 3326740 | D36: =IS!D6 -> 3492690 | E36: =IS!E6 -> 3590109 | F36: =IS!F6 -> 3623073 | G36: =IS!G6 -> 485359 | H36: =IS!H6 -> 698328 | I36: =IS!I6 -> 819653 | ... AY36: =IS!AY6 -> 5911596.9
A37: COGS | B37: =IS!B7 -> 1340490 | C37: =IS!C7 -> 1298172 | D37: =IS!D7 -> 1408848 | E37: =IS!E7 -> 1430193 | F37: =IS!F7 -> 1472155 | G37: =IS!G7 -> 221214 | H37: =IS!H7 -> 274720 | I37: =IS!I7 -> 295220 | ... AY37: =IS!AY7 -> 2196813.2
A38: TTM Sales | B38: =B36 -> 3518680 | C38: =C36 -> 3326740 | D38: =D36 -> 3492690 | E38: =E36 -> 3590109 | F38: =F36 -> 3623073 | J38: =J36+I36+H36+G36 -> 3125384 | K38: =J38 -> 3125384 | L38: =L36+J36+I36+H36 -> 3421430 | M38: =M36+L36+J36+I36 -> 3587952 | N38: =N36+M36+L36+J36 -> 3673459 | O38: =O36+N36+M36+L36 -> 3712768 | P38: =O38 -> 3712768 | Q38: =Q36+O36+N36+M36 -> 3744125 | R38: =R36+Q36+O36+N36 -> 3684366 | S38: =S36+R36+Q36+O36 -> 3659290 | T38: =T36+S36+R36+Q36 -> 3697751 | U38: =T38 -> 3697751 | V38: =V36+T36+S36+R36 -> 3720983 | W38: =W36+V36+T36+S36 -> 3851237 | X38: =X36+W36+V36+T36 -> 4027584 | Y38: =Y36+X36+W36+V36 -> 4280677 | Z38: =Y38 -> 4280677 | AA38: =AA36+Y36+X36+W36 -> 4465413 | AB38: =AB36+AA36+Y36+X36 -> 4664042 | AC38: =AC36+AB36+AA36+Y36 -> 4816577 | AD38: =AD36+AC36+AB36+AA36 -> 4948587 | AE38: =AD38 -> 4948587 | AF38: =AF36+AD36+AC36+AB36 -> 5025168 | AG38: =AG36+AF36+AD36+AC36 -> 5099754 | AH38: =AH36+AG36+AF36+AD36 -> 5181407 | AI38: =AI36+AH36+AG36+AF36 -> 5266292 | AJ38: =AI38 -> 5266292 | AK38: =AK36+AI36+AH36+AG36 -> 5282802 | AL38: =AL36+AK36+AI36+AH36 -> 5340931 | AM38: =AM36+AL36+AK36+AI36 -> 5417249.6 | AN38: =AN36+AM36+AL36+AK36 -> 5534135.7 | AO38: =AN38 -> 5534135.7 | AP38: =AP36+AN36+AM36+AL36 -> 5584335.7 | AQ38: =AQ36+AP36+AN36+AM36 -> 5635003.3 | AR38: =AR36+AQ36+AP36+AN36 -> 5682678.7 | AS38: =AS36+AR36+AQ36+AP36 -> 5744909 | AT38: =AS38 -> 5744909 | AU38: =AU36+AS36+AR36+AQ36 -> 5776864.8 | AV38: =AV36+AU36+AS36+AR36 -> 5813282.1 | AW38: =AW36+AV36+AU36+AS36 -> 5855859.5 | AX38: =AX36+AW36+AV36+AU36 -> 5911596.9 | AY38: =AX38 -> 5911596.9
A39: TTM COGS | B39: =B37 -> 1340490 | C39: =C37 -> 1298172 | D39: =D37 -> 1408848 | E39: =E37 -> 1430193 | F39: =F37 -> 1472155 | J39: =J37+I37+H37+G37 -> 1234179 | K39: =J39 -> 1234179 | L39: =L37+J37+I37+H37 -> 1299236 | M39: =M37+L37+J37+I37 -> 1325881 | N39: =N37+M37+L37+J37 -> 1359577 | O39: =O37+N37+M37+L37 -> 1400773 | P39: =O39 -> 1400773 | Q39: =Q37+O37+N37+M37 -> 1477718 | R39: =R37+Q37+O37+N37 -> 1515553 | S39: =S37+R37+Q37+O37 -> 1545905 | T39: =T37+S37+R37+Q37 -> 1593213 | U39: =T39 -> 1593213 | V39: =V37+T37+S37+R37 -> 1556197 | W39: =W37+V37+T37+S37 -> 1567962 | X39: =X37+W37+V37+T37 -> 1579456 | Y39: =Y37+X37+W37+V37 -> 1587265 | Z39: =Y39 -> 1587265 | AA39: =AA37+Y37+X37+W37 -> 1604338 | AB39: =AB37+AA37+Y37+X37 -> 1651085 | AC39: =AC37+AB37+AA37+Y37 -> 1702357 | AD39: =AD37+AC37+AB37+AA37 -> 1773926 | AE39: =AD39 -> 1773926 | AF39: =AF37+AD37+AC37+AB37 -> 1847786 | AG39: =AG37+AF37+AD37+AC37 -> 1901664 | AH39: =AH37+AG37+AF37+AD37 -> 1963300 | AI39: =AI37+AH37+AG37+AF37 -> 2028884 | AJ39: =AI39 -> 2028884 | AK39: =AK37+AI37+AH37+AG37 -> 2025589 | AL39: =AL37+AK37+AI37+AH37 -> 2040108 | AM39: =AM37+AL37+AK37+AI37 -> 2050938.8 | AN39: =AN37+AM37+AL37+AK37 -> 2067919.5 | AO39: =AN39 -> 2067919.5 | AP39: =AP37+AN37+AM37+AL37 -> 2085407.2 | AQ39: =AQ37+AP37+AN37+AM37 -> 2102734.2 | AR39: =AR37+AQ37+AP37+AN37 -> 2118566.6 | AS39: =AS37+AR37+AQ37+AP37 -> 2140871.2 | AT39: =AS39 -> 2140871.2 | AU39: =AU37+AS37+AR37+AQ37 -> 2150320.4 | AV39: =AV37+AU37+AS37+AR37 -> 2163684.6 | AW39: =AW37+AV37+AU37+AS37 -> 2179044.8 | AX39: =AX37+AW37+AV37+AU37 -> 2196813.2 | AY39: =AX39 -> 2196813.2
A41: Cash Conversion
A42: Inventory Analysis
A43: Inventory Growth YoY | C43: =C9/B9-1 -> -0.084510913 | D43: =D9/C9-1 -> 0.061526532 | E43: =E9/D9-1 -> 0.03177715 | F43: =F9/E9-1 -> -0.0081141137 | K43: =K9/F9-1 -> -0.0697011 | L43: =L9/G9-1 -> -0.088986249 | M43: =M9/H9-1 -> -0.083035661 | N43: =N9/I9-1 -> -0.0033635904 | O43: =O9/J9-1 -> 0.30147283 | P43: =P9/K9-1 -> 0.30147283 | Q43: =Q9/L9-1 -> 0.44740668 | R43: =R9/M9-1 -> 0.70360247 | ... AY43: =AY9/AT9-1 -> 0.097682925
A44: Avg. Inventory YoY | C44: =AVERAGE(B9:C9) -> 418248 | D44: =AVERAGE(C9:D9) -> 412094 | E44: =AVERAGE(D9:E9) -> 431136 | F44: =AVERAGE(E9:F9) -> 436102.5 | K44: =AVERAGE(K9,F9) -> 419189.5 | L44: =AVERAGE(L9,G9) -> 407613.5 | M44: =AVERAGE(M9,H9) -> 434421.5 | N44: =AVERAGE(N9,I9) -> 544630.5 | O44: =AVERAGE(O9,J9) -> 464958.5 | P44: =AVERAGE(P9,K9) -> 464958.5 | Q44: =AVERAGE(Q9,L9) -> 475571.5 | R44: =AVERAGE(R9,M9) -> 561814 | ... AL44: =AVERAGE(AL9,AG9) -> 592314 | AM44: =AM46*(AM37/(AM5*7)) -> 739577.59 | AN44: =AN46*(AN37/(AN5*7)) -> 623743.48 | AO44: =AVERAGE(AO9,AJ9) -> 623743.48 | AP44: =AP46*(AP37/(AP5*7)) -> 550295.76 | AQ44: =AQ46*(AQ37/(AQ5*7)) -> 639888.64 | AR44: =AR46*(AR37/(AR5*7)) -> 757087.69 | AS44: =AS46*(AS37/(AS5*7)) -> 669368.84 | AT44: =AVERAGE(AT9,AO9) -> 669368.84 | AU44: =AU46*(AU37/(AU5*7)) -> 543945.32 | AV44: =AV46*(AV37/(AV5*7)) -> 691152.83 | AW44: =AW46*(AW37/(AW5*7)) -> 761966.51 | AX44: =AX46*(AX37/(AX5*7)) -> 726289.92 | AY44: =AVERAGE(AY9,AT9) -> 726289.92
A45: Inventory Turns | C45: =C39/C44 -> 3.1038331 | D45: =D39/D44 -> 3.418754 | E45: =E39/E44 -> 3.3172665 | F45: =F39/F44 -> 3.3757087 | K45: =K39/K44 -> 2.944203 | L45: =L39/L44 -> 3.1874214 | M45: =M39/M44 -> 3.0520612 | N45: =N39/N44 -> 2.4963292 | O45: =O39/O44 -> 3.0126839 | P45: =P39/P44 -> 3.0126839 | Q45: =Q39/Q44 -> 3.1072468 | R45: =R39/R44 -> 2.6976063 | ... AY45: =AY39/AY44 -> 3.0247057
A46: Days Inventory | C46: =C44/(C37/(C$5*7)) -> 117.27435 | D46: =D44/(D37/(D$5*7)) -> 108.51907 | E46: =E44/(E37/(E$5*7)) -> 109.7289 | F46: =F44/(F37/(F$5*7)) -> 107.82921 | K46: =K44/(K37/(K$5*7)) -> 123.63278 | L46: =L44/(L37/(L$5*7)) -> 129.57243 | M46: =M44/(M37/(M$5*7)) -> 131.17766 | N46: =N44/(N37/(N$5*7)) -> 150.68095 | O46: =O44/(O37/(O$5*7)) -> 87.379985 | P46: =P44/(P37/(P$5*7)) -> 120.8225 | Q46: =Q44/(Q37/(Q$5*7)) -> 119.1495 | R46: =R44/(R37/(R$5*7)) -> 150.72251 | ... AI46: =AI44/(AI37/(AI$5*7)) -> 79.111395 | AJ46: =AJ44/(AJ37/(AJ5*7)) -> 105.51248 | AK46: =AK44/(AK37/(AK$5*7)) -> 118.1649 | AL46: =AL44/(AL37/(AL$5*7)) -> 115.63942 | AM46: 136.1 | AN46: 81.85 | AO46: =AO44/(AO37/(AO5*7)) -> 109.79278 | AP46: 116.1 | AQ46: 120.45 | AR46: 135 | AS46: 85.1 | AT46: =AT44/(AT37/(AT5*7)) -> 113.80893 | AU46: 112.3 | AV46: 126.6 | AW46: 131.9 | AX46: 90.1 | AY46: =AY44/(AY37/(AY5*7)) -> 120.34229
A48: Receivables Analysis
A49: Receivables Growth YoY | C49: =C8/B8-1 -> 0.64211859 | D49: =D8/C8-1 -> -0.14627773 | E49: =E8/D8-1 -> -0.08293613 | F49: =F8/E8-1 -> 0.097644709 | K49: =K8/F8-1 -> 0.04493402 | L49: =L8/G8-1 -> 0.21640587 | M49: =M8/H8-1 -> -0.013269477 | N49: =N8/I8-1 -> -0.063172194 | O49: =O8/J8-1 -> -0.1759543 | P49: =P8/K8-1 -> -0.1759543 | Q49: =Q8/L8-1 -> -0.17634784 | R49: =R8/M8-1 -> -0.084118369 | ... AY49: =AY8/AT8-1 -> 0.073892389
A50: Avg. Receivables YoY | C50: =AVERAGE(B8:C8) -> 75126 | D50: =AVERAGE(C8:D8) -> 86554 | E50: =AVERAGE(D8:E8) -> 76418 | F50: =AVERAGE(E8:F8) -> 76681.5 | K50: =AVERAGE(K8,F8) -> 82054 | L50: =AVERAGE(L8,G8) -> 98230 | M50: =AVERAGE(M8,H8) -> 87737 | N50: =AVERAGE(N8,I8) -> 86260.5 | O50: =AVERAGE(O8,J8) -> 76479.5 | P50: =AVERAGE(P8,K8) -> 76479.5 | Q50: =AVERAGE(Q8,L8) -> 98314 | R50: =AVERAGE(R8,M8) -> 83485.5 | ... AL50: =AVERAGE(AL8,AG8) -> 182173.5 | AM50: =AM52*(AM$36/(AM$5*7)) -> 125427.79 | AN50: =AN52*(AN36/(AN5*7)) -> 153733.72 | AO50: =AVERAGE(AO8,AJ8) -> 153733.72 | AP50: =AP52*(AP$36/(AP$5*7)) -> 127274.83 | AQ50: =AQ52*(AQ36/(AQ5*7)) -> 154897.97 | AR50: =AR52*(AR$36/(AR$5*7)) -> 140994.95 | AS50: =AS52*(AS36/(AS5*7)) -> 157056.47 | AT50: =AVERAGE(AT8,AO8) -> 157056.47 | AU50: =AU52*(AU$36/(AU$5*7)) -> 133397.42 | AV50: =AV52*(AV36/(AV5*7)) -> 129426.73 | AW50: =AW52*(AW$36/(AW$5*7)) -> 168938.01 | AX50: =AX52*(AX36/(AX5*7)) -> 159070.15 | AY50: =AVERAGE(AY8,AT8) -> 159070.15
A51: Receivables Turns | C51: =C38/C50 -> 44.282139 | D51: =D38/D50 -> 40.352728 | E51: =E38/E50 -> 46.979887 | F51: =F38/F50 -> 47.248332 | K51: =K38/K50 -> 38.089356 | L51: =L38/L50 -> 34.830805 | M51: =M38/M50 -> 40.8944 | N51: =N38/N50 -> 42.585645 | O51: =O38/O50 -> 48.545924 | P51: =P38/P50 -> 48.545924 | Q51: =Q38/Q50 -> 38.083335 | R51: =R38/R50 -> 44.131807 | ... AL51: =AL38/AL50 -> 29.317826 | AM51: =AM$38/AM50 -> 43.190187 | AN51: =AN38/AN50 -> 35.998191 | AO51: =AO38/AO50 -> 35.998191 | AP51: =AP$38/AP50 -> 43.8762 | AQ51: =AQ38/AQ50 -> 36.378807 | AR51: =AR$38/AR50 -> 40.304131 | AS51: =AS38/AS50 -> 36.57862 | AT51: =AT38/AT50 -> 36.57862 | AU51: =AU$38/AU50 -> 43.305671 | AV51: =AV38/AV50 -> 44.915622 | AW51: =AW$38/AW50 -> 34.66277 | AX51: =AX38/AX50 -> 37.163459 | AY51: =AY38/AY50 -> 37.163459
A52: Days Receivable | C52: =C50/(C36/(C$5*7)) -> 8.2200184 | D52: =D50/(D36/(D$5*7)) -> 9.1939262 | E52: =E50/(E36/(E$5*7)) -> 7.7479965 | F52: =F50/(F36/(F$5*7)) -> 7.7039756 | K52: =K50/(K36/(K$5*7)) -> 9.5564756 | L52: =L50/(L36/(L$5*7)) -> 11.439561 | M52: =M50/(M36/(M$5*7)) -> 9.2317361 | N52: =N50/(N36/(N$5*7)) -> 8.6721745 | O52: =O50/(O36/(O$5*7)) -> 5.9926952 | P52: =P50/(P36/(P$5*7)) -> 7.4980548 | Q52: =Q50/(Q36/(Q$5*7)) -> 11.007618 | R52: =R50/(R36/(R$5*7)) -> 9.4364246 | ... AI52: =AI50/(AI36/(AI$5*7)) -> 6.8688895 | AJ52: =AJ50/(AJ36/(AJ5*7)) -> 8.7117733 | AK52: =AK50/(AK36/(AK$5*7)) -> 10.594666 | AL52: =AL50/(AL36/(AL$5*7)) -> 13.087497 | AM52: 8.35 | AN52: 7.83 | AO52: =AO50/(AO36/(AO5*7)) -> 10.111619 | AP52: 9.95 | AQ52: 10.7 | AR52: 9.07 | AS52: 7.73 | AT52: =AT50/(AT36/(AT5*7)) -> 9.9511682 | AU52: 10.15 | AV52: 8.7 | AW52: 10.55 | AX52: 7.6 | AY52: =AY50/(AY36/(AY5*7)) -> 9.7945674
A54: Payables Analysis
A55: Payables Growth YoY | C55: =C17/B17-1 -> 0.015430976 | D55: =D17/C17-1 -> -0.097044654 | E55: =E17/D17-1 -> 0.34352275 | F55: =F17/E17-1 -> -0.030672873 | K55: =K17/F17-1 -> 0.31592086 | L55: =L17/G17-1 -> 0.45420192 | M55: =M17/H17-1 -> 0.018485615 | N55: =N17/I17-1 -> 0.26819506 | O55: =O17/J17-1 -> 0.29521141 | P55: =P17/K17-1 -> 0.29521141 | Q55: =Q17/L17-1 -> 0.31556998 | R55: =R17/M17-1 -> 0.41047413 | ... AY55: =AY17/AT17-1 -> 0.017987778
A56: Avg. Payables YoY | C56: =AVERAGE(B17:C17) -> 185596 | D56: =AVERAGE(C17:D17) -> 177942.5 | E56: =AVERAGE(D17:E17) -> 197873 | F56: =AVERAGE(E17:F17) -> 223398.5 | K56: =AVERAGE(K17,F17) -> 254657.5 | L56: =AVERAGE(L17,G17) -> 199707 | M56: =AVERAGE(M17,H17) -> 286848 | N56: =AVERAGE(N17,I17) -> 379667.5 | O56: =AVERAGE(O17,J17) -> 332112.5 | P56: =AVERAGE(P17,K17) -> 332112.5 | Q56: =AVERAGE(Q17,L17) -> 274009.5 | R56: =AVERAGE(R17,M17) -> 348886 | ... AL56: =AVERAGE(AL17,AG17) -> 361130 | AM56: =AM58*(AM$37/(AM$5*7)) -> 467330.44 | AN56: =AN58*(AN$37/(AN$5*7)) -> 391697.19 | AO56: =AVERAGE(AO17,AJ17) -> 391697.19 | AP56: =AP58*(AP$37/(AP$5*7)) -> 299558.07 | AQ56: =AQ58*(AQ$37/(AQ$5*7)) -> 460061.08 | AR56: =AR58*(AR$37/(AR$5*7)) -> 505285.93 | AS56: =AS58*(AS$37/(AS$5*7)) -> 404688.92 | AT56: =AVERAGE(AT17,AO17) -> 404688.92 | AU56: =AU58*(AU$37/(AU$5*7)) -> 303698.77 | AV56: =AV58*(AV$37/(AV$5*7)) -> 514816.05 | AW56: =AW58*(AW$37/(AW$5*7)) -> 548223.06 | AX56: =AX58*(AX$37/(AX$5*7)) -> 407077.04 | AY56: =AVERAGE(AY17,AT17) -> 407077.04
A57: Payables Turns | C57: =C39/C56 -> 6.994612 | D57: =D39/D56 -> 7.917434 | E57: =E39/E56 -> 7.227833 | F57: =F39/F56 -> 6.589816 | K57: =K39/K56 -> 4.8464271 | L57: =L39/L56 -> 6.5057109 | M57: =M39/M56 -> 4.6222424 | N57: =N39/N56 -> 3.5809676 | O57: =O39/O56 -> 4.2177666 | P57: =P39/P56 -> 4.2177666 | Q57: =Q39/Q56 -> 5.3929444 | R57: =R39/R56 -> 4.3439777 | ... AY57: =AY39/AY56 -> 5.3965541
A58: Days Payable | C58: =C56/(C37/(C$5*7)) -> 52.040056 | D58: =D56/(D37/(D$5*7)) -> 46.858616 | E58: =E56/(E37/(E$5*7)) -> 50.360876 | F58: =F56/(F37/(F$5*7)) -> 55.236747 | K58: =K56/(K37/(K$5*7)) -> 75.106877 | L58: =L56/(L37/(L$5*7)) -> 63.482983 | M58: =M56/(M37/(M$5*7)) -> 86.616455 | N58: =N56/(N37/(N$5*7)) -> 105.04123 | O58: =O56/(O37/(O$5*7)) -> 62.41414 | P58: =P56/(P37/(P$5*7)) -> 86.301599 | Q58: =Q56/(Q37/(Q$5*7)) -> 68.650237 | R58: =R56/(R37/(R$5*7)) -> 93.598544 | ... AL58: =AL56/(AL37/(AL$5*7)) -> 70.504603 | AM58: 86 | AN58: 51.4 | AO58: =AO56/(AO37/(AO$5*7)) -> 68.94745 | AP58: 63.2 | AQ58: 86.6 | AR58: 90.1 | AS58: 51.45 | AT58: =AT56/(AT37/(AT$5*7)) -> 68.806926 | AU58: 62.7 | AV58: 94.3 | AW58: 94.9 | AX58: 50.5 | AY58: =AY56/(AY37/(AY$5*7)) -> 67.45045
A60: Operating Cashflow | B60: =SCF!B18 -> 309941 | C60: =SCF!C18 -> 184591 | D60: =SCF!D18 -> 287658 | E60: =SCF!E18 -> 352933 | F60: =SCF!F18 -> 300685 | G60: =SCF!G18 -> -90776 | H60: =SCF!H18 -> 187009 | I60: =SCF!I18 -> 62661 | ... AY60: =SCF!AY18 -> 751866.02
A61: Free Cashflow | B61: =SCF!B56 -> 166742 | C61: =SCF!C56 -> 43747 | D61: =SCF!D56 -> 180657 | E61: =SCF!E56 -> 200540 | F61: =SCF!F56 -> 97901 | G61: =SCF!G56 -> -137766 | H61: =SCF!H56 -> 158378 | I61: =SCF!I56 -> 46534 | ... AY61: =SCF!AY56 -> 518289.99
A62: Cash Conversion Cycle | C62: =C46+C52-C58 -> 73.454308 | D62: =D46+D52-D58 -> 70.85438 | E62: =E46+E52-E58 -> 67.11602 | F62: =F46+F52-F58 -> 60.296438 | G62: =G46+G52-G58 -> 0 | H62: =H46+H52-H58 -> 0 | I62: =I46+I52-I58 -> 0 | J62: =J46+J52-J58 -> 0 | ... AY62: =AY46+AY52-AY58 -> 62.686405
A64: Lease Right of Use Items
A65: Asset Seq. chg | H65: =H13/G13-1 -> -0.05306373 | I65: =I13/H13-1 -> -0.1096292 | J65: =J13/I13-1 -> -0.064650793 | L65: =L13/K13-1 -> -0.06150635 | M65: =M13/L13-1 -> -0.057171428 | N65: =N13/M13-1 -> -0.035895964 | O65: =O13/N13-1 -> -0.084456514 | P65: =P13/K13-1 -> -0.21897137 | Q65: =Q13/P13-1 -> -0.037580686 | R65: =R13/Q13-1 -> 0.10213827 | S65: =S13/R13-1 -> -0.037078043 | T65: =T13/S13-1 -> 0.014560425 | U65: =U13/P13-1 -> 0.036261638 | V65: =V13/U13-1 -> -0.04263838 | W65: =W13/V13-1 -> 0.032161155 | X65: =X13/W13-1 -> -0.045341319 | Y65: =Y13/X13-1 -> -0.0063042169 | Z65: =Z13/U13-1 -> -0.062599682 | AA65: =AA13/Z13-1 -> 0.03127875 | AB65: =AB13/AA13-1 -> 0.067646836 | AC65: =AC13/AB13-1 -> 0.068964686 | AD65: =AD13/AC13-1 -> 0.0060516855 | AE65: =AE13/Z13-1 -> 0.18409716 | AF65: =AF13/AE13-1 -> 0.080945462 | AG65: =AG13/AF13-1 -> 0.075367744 | AH65: =AH13/AG13-1 -> 0.034663048 | AI65: =AI13/AH13-1 -> 0.032590724 | AJ65: =AJ13/AE13-1 -> 0.24190377 | AK65: =AK13/AJ13-1 -> 0.11874185 | AL65: =AL13/AK13-1 -> -0.0075378731 | AM65: 0.05 | AN65: 0.05 | AO65: =AO13/AJ13-1 -> 0.22411558 | AP65: 0.05 | AQ65: 0.05 | AR65: 0.05 | AS65: 0.05 | AT65: =AT13/AO13-1 -> 0.21550625 | AU65: 0.05 | AV65: 0.05 | AW65: 0.05 | AX65: 0.05 | AY65: =AY13/AT13-1 -> 0.21550625
A66: Liability Seq. chg | H66: =SUM(H19,H24)/SUM(G19,G24)-1 -> -0.060520065 | I66: =SUM(I19,I24)/SUM(H19,H24)-1 -> -0.096708312 | J66: =SUM(J19,J24)/SUM(I19,I24)-1 -> -0.046919561 | L66: =SUM(L19,L24)/SUM(K19,K24)-1 -> -0.10799016 | M66: =SUM(M19,M24)/SUM(L19,L24)-1 -> -0.060312168 | N66: =SUM(N19,N24)/SUM(M19,M24)-1 -> -0.036675547 | O66: =SUM(O19,O24)/SUM(N19,N24)-1 -> -0.05550537 | P66: =SUM(P19,P24)/SUM(K19,K24)-1 -> -0.23734991 | Q66: =SUM(Q19,Q24)/SUM(P19,P24)-1 -> -0.06756535 | R66: =SUM(R19,R24)/SUM(Q19,Q24)-1 -> 0.068821022 | S66: =SUM(S19,S24)/SUM(R19,R24)-1 -> 0.0031102639 | T66: =SUM(T19,T24)/SUM(S19,S24)-1 -> 0.0081798968 | U66: =SUM(U19,U24)/SUM(P19,P24)-1 -> 0.0078829502 | V66: =SUM(V19,V24)/SUM(U19,U24)-1 -> -0.060197986 | W66: =SUM(W19,W24)/SUM(V19,V24)-1 -> 0.014033018 | X66: =SUM(X19,X24)/SUM(W19,W24)-1 -> -0.033717833 | Y66: =SUM(Y19,Y24)/SUM(X19,X24)-1 -> -0.032436401 | Z66: =SUM(Z19,Z24)/SUM(U19,U24)-1 -> -0.1090118 | AA66: =SUM(AA19,AA24)/SUM(Z19,Z24)-1 -> 0.023557063 | AB66: =SUM(AB19,AB24)/SUM(AA19,AA24)-1 -> 0.053366804 | AC66: =SUM(AC19,AC24)/SUM(AB19,AB24)-1 -> 0.061073407 | AD66: =SUM(AD19,AD24)/SUM(AC19,AC24)-1 -> 0.0067283574 | AE66: =SUM(AE19,AE24)/SUM(Z19,Z24)-1 -> 0.15172666 | AF66: =SUM(AF19,AF24)/SUM(AE19,AE24)-1 -> 0.078066399 | AG66: =SUM(AG19,AG24)/SUM(AF19,AF24)-1 -> 0.071721276 | AH66: =SUM(AH19,AH24)/SUM(AG19,AG24)-1 -> 0.028565296 | AI66: =SUM(AI19,AI24)/SUM(AH19,AH24)-1 -> 0.032900694 | AJ66: =SUM(AJ19,AJ24)/SUM(AE19,AE24)-1 -> 0.22748954 | AK66: =SUM(AK19,AK24)/SUM(AJ19,AJ24)-1 -> 0.10648278 | AL66: =SUM(AL19,AL24)/SUM(AK19,AK24)-1 -> -0.003897168 | AM66: 0.05 | AN66: 0.05 | AO66: =SUM(AO19,AO24)/SUM(AJ19,AJ24)-1 -> 0.21514312 | AP66: 0.05 | AQ66: 0.05 | AR66: 0.05 | AS66: 0.05 | AT66: =SUM(AT19,AT24)/SUM(AO19,AO24)-1 -> 0.21550625 | AU66: 0.05 | AV66: 0.05 | AW66: 0.05 | AX66: 0.05 | AY66: =SUM(AY19,AY24)/SUM(AT19,AT24)-1 -> 0.21550625
A67: ST proportion of Liability | G67: =G19/SUM(G19,G24) -> 0.20593234 | H67: =H19/SUM(H19,H24) -> 0.19873365 | I67: =I19/SUM(I19,I24) -> 0.20206174 | J67: =J19/SUM(J19,J24) -> 0.20626574 | K67: =K19/SUM(K19,K24) -> 0.20626574 | L67: =L19/SUM(L19,L24) -> 0.21535082 | M67: =M19/SUM(M19,M24) -> 0.21701248 | N67: =N19/SUM(N19,N24) -> 0.21537779 | ... AH67: =AH19/SUM(AH19,AH24) -> 0.19970766 | AI67: =AH67 -> 0.19970766 | AJ67: =AJ19/SUM(AJ19,AJ24) -> 0.2065457 | AK67: =AK19/SUM(AK19,AK24) -> 0.20295603 | AL67: =AL19/SUM(AL19,AL24) -> 0.20377959 | AM67: =AL67 -> 0.20377959 | AN67: =AM67 -> 0.20377959 | AO67: =AO19/SUM(AO19,AO24) -> 0.20377959 | AP67: =AO67 -> 0.20377959 | AQ67: =AP67 -> 0.20377959 | AR67: =AQ67 -> 0.20377959 | AS67: =AR67 -> 0.20377959 | AT67: =AT19/SUM(AT19,AT24) -> 0.20377959 | AU67: =AT67 -> 0.20377959 | AV67: =AU67 -> 0.20377959 | AW67: =AV67 -> 0.20377959 | AX67: =AW67 -> 0.20377959 | AY67: =AY19/SUM(AY19,AY24) -> 0.20377959
A69: Ratio Analysis
A70: Cash and Cash Equivalents | B70: =B6 -> 588578 | C70: =C6 -> 547189 | D70: =D6 -> 675558 | E70: =E6 -> 723135 | F70: =F6 -> 671267 | G70: =G6 -> 703989 | H70: =H6 -> 766721 | I70: =I6 -> 812881 | ... AY70: =AY6 -> 1107375.1
A71: Cash as a % of TTM Net Sales | B71: =B70/B38 -> 0.16727239 | C71: =C70/C38 -> 0.16448205 | D71: =D70/D38 -> 0.19342054 | E71: =E70/E38 -> 0.20142425 | F71: =F70/F38 -> 0.18527559 | J71: =J70/J38 -> 0.3535124 | K71: =K70/K38 -> 0.3535124 | L71: =L70/L38 -> 0.26568072 | M71: =M70/M38 -> 0.25683287 | N71: =N70/N38 -> 0.23564221 | O71: =O70/O38 -> 0.22170494 | P71: =P70/P38 -> 0.22170494 | Q71: =Q70/Q38 -> 0.12509678 | ... AY71: =AY70/AY38 -> 0.1873225
A72: Cash Per Share | B72: =B70/IS!B19 -> 8.4788741 | C72: =C70/IS!C19 -> 8.0613601 | D72: =D70/IS!D19 -> 9.7338444 | E72: =E70/IS!E19 -> 10.45945 | F72: =F70/IS!F19 -> 10.205038 | G72: =G70/IS!G19 -> 11.25644 | H72: =H70/IS!H19 -> 12.115176 | I72: =I70/IS!I19 -> 12.725723 | ... AY72: =AY70/IS!AY19 -> 27.636882
A73: Book Value Per Share | B73: =B29/IS!B19 -> 18.665774 | C73: =C29/IS!C19 -> 18.445432 | D73: =D29/IS!D19 -> 18.046352 | E73: =E29/IS!E19 -> 17.626177 | F73: =F29/IS!F19 -> 16.284746 | G73: =G29/IS!G19 -> 12.760685 | H73: =H29/IS!H19 -> 12.856082 | I73: =I29/IS!I19 -> 13.444651 | ... AY73: =AY29/IS!AY19 -> 48.596427
A74: Working Capital | B74: =B11-B23 -> 644277 | C74: =C11-C23 -> 653300 | D74: =D11-D23 -> 756992 | E74: =E11-E23 -> 777033 | F74: =F11-F23 -> 449395 | G74: =G11-G23 -> 312683 | H74: =H11-H23 -> 462453 | I74: =I11-I23 -> 567696 | ... AY74: =AY11-AY23 -> 847889.4
A75: Return on Average Assets (ROA) | C75: =IS!C17/AVERAGE(BS!C15,B15) -> -0.0017213684 | D75: =IS!D17/AVERAGE(BS!D15,C15) -> 0.019476575 | E75: =IS!E17/AVERAGE(BS!E15,D15) -> 0.033871438 | F75: =IS!F17/AVERAGE(BS!F15,E15) -> 0.016207215 | K75: =IS!K17/AVERAGE(BS!K15,BS!F15) -> -0.013222393 | P75: =IS!P17/AVERAGE(BS!P15,BS!K15) -> 0.087199189 | U75: =IS!U17/AVERAGE(BS!U15,BS!P15) -> 0.0046155825 | Z75: =IS!Z17/AVERAGE(BS!Z15,BS!U15) -> 0.11651437 | AE75: =IS!AE17/AVERAGE(BS!AE15,BS!Z15) -> 0.18049479 | AJ75: =IS!AJ17/AVERAGE(BS!AJ15,BS!AE15) -> 0.13974151 | AO75: =IS!AO17/AVERAGE(BS!AO15,BS!AJ15) -> 0.13527013 | AT75: =IS!AT17/AVERAGE(BS!AT15,BS!AO15) -> 0.12496801 | AY75: =IS!AY17/AVERAGE(BS!AY15,BS!AT15) -> 0.11400736
A76: Return on Average Equity (ROE) | C76: =IS!C17/AVERAGE(BS!C29,B29) -> -0.0031949622 | D76: =IS!D17/AVERAGE(BS!D29,C29) -> 0.035939166 | E76: =IS!E17/AVERAGE(BS!E29,D29) -> 0.064577927 | F76: =IS!F17/AVERAGE(BS!F29,E29) -> 0.042009801 | K76: =IS!K17/AVERAGE(BS!K29,BS!F29) -> -0.044922766 | P76: =IS!P17/AVERAGE(BS!P29,BS!K29) -> 0.30525412 | U76: =IS!U17/AVERAGE(BS!U29,BS!P29) -> 0.016898839 | Z76: =IS!Z17/AVERAGE(BS!Z29,BS!U29) -> 0.3772473 | AE76: =IS!AE17/AVERAGE(BS!AE29,BS!Z29) -> 0.47159509 | AJ76: =IS!AJ17/AVERAGE(BS!AJ29,BS!AE29) -> 0.34493858 | AO76: =IS!AO17/AVERAGE(BS!AO29,BS!AJ29) -> 0.34524869 | AT76: =IS!AT17/AVERAGE(BS!AT29,BS!AO29) -> 0.32492866 | AY76: =IS!AY17/AVERAGE(BS!AY29,BS!AT29) -> 0.29530039
A77: Return on Invested Capital (ROIC) | B77: =(IS!B12*(1-IS!B45))/(BS!B85+BS!B29) -> 0.059125902 | C77: =(IS!C12*(1-IS!C45))/(BS!C85+BS!C29) -> 4.3050643e-05 | D77: =(IS!D12*(1-IS!D45))/(BS!D85+BS!D29) -> 0.038735669 | E77: =(IS!E12*(1-IS!E45))/(BS!E85+BS!E29) -> 0.062148363 | F77: =(IS!F12*(1-IS!F45))/(BS!F85+BS!F29) -> 0.045453612 | K77: =(IS!K12*(1-IS!K45))/(BS!K85+BS!K29) -> -0.067606925 | P77: =(IS!P12*(1-IS!P45))/(BS!P85+BS!P29) -> 0.27124627 | U77: =(IS!U12*(1-IS!U45))/(BS!U85+BS!U29) -> 0.027040896 | Z77: =(IS!Z12*(1-IS!Z45))/(BS!Z85+BS!Z29) -> 0.26638955 | AE77: =(IS!AE12*(1-IS!AE45))/(BS!AE85+BS!AE29) -> 0.40938662 | AJ77: =(IS!AJ12*(1-IS!AJ45))/(BS!AJ85+BS!AJ29) -> 0.33138356 | AO77: =(IS!AO12*(1-IS!AO45))/(BS!AO85+BS!AO29) -> 0.33188911 | AT77: =(IS!AT12*(1-IS!AT45))/(BS!AT85+BS!AT29) -> 0.30244945 | AY77: =(IS!AY12*(1-IS!AY45))/(BS!AY85+BS!AY29) -> 0.27434655
A78: Current Ratio | B78: =B11/B23 -> 2.204925 | C78: =C11/C23 -> 2.3442387 | D78: =D11/D23 -> 2.4914747 | E78: =E11/E23 -> 2.3902476 | F78: =F11/F23 -> 1.5511655 | G78: =G11/G23 -> 1.3210459 | H78: =H11/H23 -> 1.502126 | I78: =I11/I23 -> 1.5953294 | ... AY78: =AY11/AY23 -> 1.6422005
A79: Quick Ratio | B79: =(B11-B9-B10)/B23 -> 1.2071112 | C79: =(C11-C9-C10)/C23 -> 1.3180514 | D79: =(D11-D9-D10)/D23 -> 1.4881055 | E79: =(E11-E9-E10)/E23 -> 1.4246248 | F79: =(F11-F9-F10)/F23 -> 0.92170763 | G79: =(G11-G9-G10)/G23 -> 0.81382739 | H79: =(H11-H9-H10)/H23 -> 0.92839662 | I79: =(I11-I9-I10)/I23 -> 0.94585893 | ... AY79: =(AY11-AY9-AY10)/AY23 -> 0.97130041
A80: Interest Coverage | B80: =IS!B12/IS!B13 -> 7.4799978 | C80: =IS!C12/IS!C13 -> 0.17475624 | D80: =IS!D12/IS!D13 -> 5.9672568 | E80: =IS!E12/IS!E13 -> 12.604055 | F80: =IS!F12/IS!F13 -> 10.704407 | G80: =IS!G12/IS!G13 -> -49.302581 | H80: =IS!H12/IS!H13 -> 3.1313046 | I80: =IS!I12/IS!I13 -> 7.3734105 | ... AY80: =IS!AY12/IS!AY13 -> -41.251504
A81: Debt/Equity | B81: =B85/B29 -> 0.22090773 | C81: =C85/C29 -> 0.21005096 | D81: =D85/D29 -> 0.19935472 | E81: =E85/E29 -> 0.20551016 | F81: =F85/F29 -> 0.21654944 | G81: =G85/G29 -> 0.29092581 | H81: =H85/H29 -> 0.42188518 | I81: =I85/I29 -> 0.40004355 | ... AY81: =AY85/AY29 -> 0
A82: Debt/Total Capital | B82: =B85/(B85+B29) -> 0.18093728 | C82: =C85/(C85+C29) -> 0.17358853 | D82: =D85/(D85+D29) -> 0.16621831 | E82: =E85/(E85+E29) -> 0.17047568 | F82: =F85/(F85+F29) -> 0.17800299 | G82: =G85/(G85+G29) -> 0.22536215 | H82: =H85/(H85+H29) -> 0.29670833 | I82: =I85/(I85+I29) -> 0.2857365 | ... AY82: =AY85/(AY85+AY29) -> 0
A84: Leverage Ratios:
A85: Total Debt | B85: =B25 -> 286235 | C85: =C25 -> 262992 | D85: =D25 -> 249686 | E85: =E25 -> 250439 | F85: =F25 -> 231963 | G85: =G25 -> 232178 | H85: =H25 -> 343250 | I85: =I25 -> 343559 | ... AY85: =AY25 -> 0
A86: Cash | B86: =B6 -> 588578 | C86: =C6 -> 547189 | D86: =D6 -> 675558 | E86: =E6 -> 723135 | F86: =F6 -> 671267 | G86: =G6 -> 703989 | H86: =H6 -> 766721 | I86: =I6 -> 812881 | ... AY86: =AY6 -> 1107375.1
A87: Net Debt | B87: =B85-B86 -> -302343 | C87: =C85-C86 -> -284197 | D87: =D85-D86 -> -425872 | E87: =E85-E86 -> -472696 | F87: =F85-F86 -> -439304 | G87: =G85-G86 -> -471811 | H87: =H85-H86 -> -423471 | I87: =I85-I86 -> -469322 | ... AY87: =AY85-AY86 -> -1107375.1
A88: Net Interest Expense. (Income) | B88: =IS!B13 -> 18248 | C88: =IS!C13 -> 18666 | D88: =IS!D13 -> 16889 | E88: =IS!E13 -> 10999 | F88: =IS!F13 -> 7737 | G88: =IS!G13 -> 3371 | H88: =IS!H13 -> 7098 | I88: =IS!I13 -> 8808 | ... AY88: =IS!AY13 -> -18500
A89: Effective Int. Rate | B89: =B88/B87 -> -0.060355292 | C89: =C88/C87 -> -0.065679793 | D89: =D88/D87 -> -0.039657456 | E89: =E88/E87 -> -0.023268655 | F89: =F88/F87 -> -0.01761195 | G89: =G88/G87 -> -0.0071448101 | H89: =H88/H87 -> -0.016761478 | I89: =I88/I87 -> -0.018767499 | ... AY89: =AY88/AY87 -> 0.016706173
A91: Total Adj. Debt (incl. op lease liabilities) | B91: =B85+B19+B24 -> 286235 | C91: =C85+C19+C24 -> 262992 | D91: =D85+D19+D24 -> 249686 | E91: =E85+E19+E24 -> 250439 | F91: =F85+F19+F24 -> 1767426 | G91: =G85+G19+G24 -> 1723799 | H91: =H85+H19+H24 -> 1744598 | I91: =I85+I19+I24 -> 1609385 | ... AY91: =AY85+AY19+AY24 -> 2097104.1
A92: Net Adj. Debt (incl. op lease liabilities) | B92: =B91-B86 -> -302343 | C92: =C91-C86 -> -284197 | D92: =D91-D86 -> -425872 | E92: =E91-E86 -> -472696 | F92: =F91-F86 -> 1096159 | G92: =G91-G86 -> 1019810 | H92: =H91-H86 -> 977877 | I92: =I91-I86 -> 796504 | ... AY92: =AY91-AY86 -> 989728.97
A93: TTM EBITDA | B93: =IS!B61 -> 350175 | C93: =IS!C61 -> 198676 | D93: =IS!D61 -> 295330 | E93: =IS!E61 -> 316662 | F93: =IS!F61 -> 256445 | J93: =IS!J61+IS!I61+IS!H61+IS!G61 -> 218749 | K93: =IS!K61 -> 218749 | L93: =IS!L61+IS!J61+IS!I61+IS!H61 -> 438864 | M93: =IS!M61+IS!L61+IS!J61+IS!I61 -> 527888 | N93: =IS!N61+IS!M61+IS!L61+IS!J61 -> 533466 | O93: =IS!O61+IS!N61+IS!M61+IS!L61 -> 499219 | P93: =IS!P61 -> 499219 | Q93: =IS!Q61+IS!O61+IS!N61+IS!M61 -> 428850 | R93: =IS!R61+IS!Q61+IS!O61+IS!N61 -> 310518 | S93: =IS!S61+IS!R61+IS!Q61+IS!O61 -> 249637 | T93: =IS!T61+IS!S61+IS!R61+IS!Q61 -> 238922 | U93: =IS!U61 -> 238922 | V93: =IS!V61+IS!T61+IS!S61+IS!R61 -> 285810 | W93: =IS!W61+IS!V61+IS!T61+IS!S61 -> 380401 | X93: =IS!X61+IS!W61+IS!V61+IS!T61 -> 497420 | Y93: =IS!Y61+IS!X61+IS!W61+IS!V61 -> 630211 | Z93: =IS!Z61 -> 630211 | AA93: =IS!AA61+IS!Y61+IS!X61+IS!W61 -> 723277 | AB93: =IS!AB61+IS!AA61+IS!Y61+IS!X61 -> 812032 | AC93: =IS!AC61+IS!AB61+IS!AA61+IS!Y61 -> 859724 | AD93: =IS!AD61+IS!AC61+IS!AB61+IS!AA61 -> 894593 | AE93: =IS!AE61 -> 894593 | AF93: =IS!AF61+IS!AD61+IS!AC61+IS!AB61 -> 867164 | AG93: =IS!AG61+IS!AF61+IS!AD61+IS!AC61 -> 857692 | AH93: =IS!AH61+IS!AG61+IS!AF61+IS!AD61 -> 832431 | AI93: =IS!AI61+IS!AH61+IS!AG61+IS!AF61 -> 815590 | AJ93: =IS!AJ61 -> 815590 | AK93: =IS!AK61+IS!AI61+IS!AH61+IS!AG61 -> 806582 | AL93: =IS!AL61+IS!AK61+IS!AI61+IS!AH61 -> 797053 | AM93: =IS!AM61+IS!AL61+IS!AK61+IS!AI61 -> 816127.22 | AN93: =IS!AN61+IS!AM61+IS!AL61+IS!AK61 -> 871980.38 | AO93: =IS!AO61 -> 871980.38 | AP93: =IS!AP61+IS!AN61+IS!AM61+IS!AL61 -> 889269.85 | AQ93: =IS!AQ61+IS!AP61+IS!AN61+IS!AM61 -> 899829.75 | AR93: =IS!AR61+IS!AQ61+IS!AP61+IS!AN61 -> 906668 | AS93: =IS!AS61+IS!AR61+IS!AQ61+IS!AP61 -> 916758.98 | AT93: =IS!AT61 -> 916758.98 | AU93: =IS!AU61+IS!AS61+IS!AR61+IS!AQ61 -> 923511.02 | AV93: =IS!AV61+IS!AU61+IS!AS61+IS!AR61 -> 929373.01 | AW93: =IS!AW61+IS!AV61+IS!AU61+IS!AS61 -> 935966.61 | AX93: =IS!AX61+IS!AW61+IS!AV61+IS!AU61 -> 950013.66 | AY93: =IS!AY61 -> 950013.66
A94: Leverage Ratio (Total Debt/EBITDA) | B94: =B85/B93 -> 0.81740558 | C94: =C85/C93 -> 1.323723 | D94: =D85/D93 -> 0.84544747 | E94: =E85/E93 -> 0.79087165 | F94: =F85/F93 -> 0.90453314 | J94: =J85/J93 -> 1.5721672 | K94: =K85/K93 -> 1.5721672 | L94: =L85/L93 -> 0.78447537 | M94: =M85/M93 -> 0.57401381 | N94: =N85/N93 -> 0.56844672 | O94: =O85/O93 -> 0.60809785 | P94: =P85/P93 -> 0.60809785 | Q94: =Q85/Q93 -> 0.70864172 | ... AY94: =AY85/AY93 -> 0
A95: Net Leverage Ratio (Net Debt / EBITDA) | B95: =B92/B93 -> -0.86340544 | C95: =C92/C93 -> -1.4304546 | D95: =D92/D93 -> -1.4420208 | E95: =E92/E93 -> -1.4927462 | F95: =F92/F93 -> 4.2744409 | J95: =J92/J93 -> 2.0364985 | K95: =K92/K93 -> 2.0364985 | L95: =L92/L93 -> 1.1653291 | M95: =M92/M93 -> 0.74401578 | N95: =N92/N93 -> 0.77190111 | O95: =O92/O93 -> 0.80229719 | P95: =P92/P93 -> 0.80229719 | Q95: =Q92/Q93 -> 1.616985 | ... AY95: =AY92/AY93 -> 1.041805
A102: Inventory Cost Grw | AB102: =AB9/W9-1 -> 0.093783119 | AC102: =AC9/X9-1 -> 0.16389583 | AD102: =AD9/Y9-1 -> 0.22480648 | AF102: =AF9/AA9-1 -> 0.20654088 | AG102: =AG9/AB9-1 -> 0.098575475
A103: Inventory Unity Grw | AC103: 0.08 | AD103: 0.06 | AF103: 0.06 | AG103: 0.07
A104: Unit Cost Grw | AC104: =(1+AC102)/(1+AC103)-1 -> 0.077681324 | AD104: =(1+AD102)/(1+AD103)-1 -> 0.15547781 | AF104: =(1+AF102)/(1+AF103)-1 -> 0.13824611 | AG104: =(1+AG102)/(1+AG103)-1 -> 0.026706052

Sheet SCF
A1: ANF Statement of Cash Flow
A3: Period | B3: ='Rev Driver'!B3 -> FY15 | C3: ='Rev Driver'!C3 -> FY16 | D3: ='Rev Driver'!D3 -> FY17 | E3: ='Rev Driver'!E3 -> FY18 | F3: ='Rev Driver'!F3 -> FY19 | G3: ='Rev Driver'!G3 -> 1Q20 | H3: ='Rev Driver'!H3 -> 2Q20 | I3: ='Rev Driver'!I3 -> 3Q20 | ... AY3: ='Rev Driver'!AY3 -> FY28E
A4: Date end | B4: ='Rev Driver'!B4 -> 42399 | C4: ='Rev Driver'!C4 -> 42763 | D4: ='Rev Driver'!D4 -> 43134 | E4: ='Rev Driver'!E4 -> 43498 | F4: ='Rev Driver'!F4 -> 43862 | G4: ='Rev Driver'!G4 -> 43953 | H4: ='Rev Driver'!H4 -> 44044 | I4: ='Rev Driver'!I4 -> 44135 | ... AY4: ='Rev Driver'!AY4 -> 47145
A5: # Weeks | B5: ='Rev Driver'!B5 -> 52 | C5: ='Rev Driver'!C5 -> 52 | D5: ='Rev Driver'!D5 -> 53 | E5: ='Rev Driver'!E5 -> 52 | F5: ='Rev Driver'!F5 -> 52 | G5: ='Rev Driver'!G5 -> 13 | H5: ='Rev Driver'!H5 -> 13 | I5: ='Rev Driver'!I5 -> 13 | ... AY5: ='Rev Driver'!AY5 -> 52
A6: Net Income | B6: =IS!B22+IS!B16 -> 38559 | C6: =IS!C22+IS!C16 -> 7718 | D6: =IS!D22+IS!D16 -> 10525 | E6: =IS!E22+IS!E16 -> 78808 | F6: =IS!F22+IS!F16 -> 44960 | G6: =IS!G22+IS!G16 -> -244031 | H6: =IS!H22+IS!H16 -> 5792 | I6: =IS!I22+IS!I16 -> 44029 | J6: =K6-SUM(G6:I6) -> 85256 | K6: =IS!K22+IS!K16 -> -108954 | L6: =IS!L22+IS!L16 -> 42706 | M6: =IS!M22+IS!M16 -> 110456 | N6: =IS!N22+IS!N16 -> 49078 | O6: =P6-SUM(L6:N6) -> 67826 | P6: =IS!P22+IS!P16 -> 270066 | Q6: =IS!Q22+IS!Q16 -> -14846 | R6: =IS!R22+IS!R16 -> -14742 | S6: =IS!S22+IS!S16 -> -718 | T6: =U6-SUM(Q6:S6) -> 40691 | U6: =IS!U22+IS!U16 -> 10385 | V6: =IS!V22+IS!V16 -> 17847 | W6: =IS!W22+IS!W16 -> 58731 | X6: =IS!X22+IS!X16 -> 97732 | Y6: =Z6-SUM(V6:X6) -> 161103 | Z6: =IS!Z22+IS!Z16 -> 335413 | AA6: =IS!AA22+IS!AA16 -> 115078 | AB6: =IS!AB22+IS!AB16 -> 135379 | AC6: =IS!AC22+IS!AC16 -> 133864 | AD6: =AE6-SUM(AA6:AC6) -> 189695 | AE6: =IS!AE22+IS!AE16 -> 574016 | AF6: =IS!AF22+IS!AF16 -> 81739 | AG6: =IS!AG22+IS!AG16 -> 143388 | AH6: =IS!AH22+IS!AH16 -> 115100 | AI6: =AJ6-SUM(AF6:AH6) -> 174768 | AJ6: =IS!AJ22+IS!AJ16 -> 514995 | AK6: =IS!AK22+IS!AK16 -> 68119 | AL6: =IS!AL22+IS!AL16 -> 185539 | AM6: =IS!AM22+IS!AM16 -> 138616.5 | AN6: =IS!AN22+IS!AN16 -> 211295.57 | AO6: =SUM(AK6:AN6) -> 603570.08 | AP6: =IS!AP22+IS!AP16 -> 75751.055 | AQ6: =IS!AQ22+IS!AQ16 -> 116171.21 | AR6: =IS!AR22+IS!AR16 -> 124976.62 | AS6: =IS!AS22+IS!AS16 -> 210959.61 | AT6: =SUM(AP6:AS6) -> 527858.5 | AU6: =IS!AU22+IS!AU16 -> 79399.321 | AV6: =IS!AV22+IS!AV16 -> 119276.24 | AW6: =IS!AW22+IS!AW16 -> 128622.33 | AX6: =IS!AX22+IS!AX16 -> 219859.09 | AY6: =SUM(AU6:AX6) -> 547156.98
A7: D&A | B7: 213680 | C7: 195414 | D7: 194549 | E7: 178030 | F7: 173625 | G7: =IS!G60 -> 44037 | H7: =IS!H60 -> 38716 | I7: =IS!I60 -> 44495 | J7: =K7-SUM(G7:I7) -> 39033 | K7: =IS!K60 -> 166281 | L7: =IS!L60 -> 37856 | M7: =IS!M60 -> 34393 | N7: =IS!N60 -> 35538 | O7: =P7-SUM(L7:N7) -> 36248 | P7: =IS!P60 -> 144035 | Q7: =IS!Q60 -> 33888 | R7: =IS!R60 -> 31655 | S7: =IS!S60 -> 32850 | T7: =U7-SUM(Q7:S7) -> 33850 | U7: =IS!U60 -> 132243 | V7: =IS!V60 -> 36028 | W7: =IS!W60 -> 36383 | X7: =IS!X60 -> 33136 | Y7: =Z7-SUM(V7:X7) -> 35557 | Z7: =IS!Z60 -> 141104 | AA7: =IS!AA60 -> 37689 | AB7: =IS!AB60 -> 39355 | AC7: =IS!AC60 -> 39566 | AD7: =AE7-SUM(AA7:AC7) -> 37163 | AE7: =IS!AE60 -> 153773 | AF7: =IS!AF60 -> 38576 | AG7: =IS!AG60 -> 37424 | AH7: =IS!AH60 -> 38566 | AI7: =AJ7-SUM(AF7:AH7) -> 40455 | AJ7: =IS!AJ60 -> 155021 | AK7: =IS!AK60 -> 42304 | AL7: =IS!AL60 -> 43279 | AM7: =AM52*AM48 -> 43337.996 | AN7: =AN52*AN48 -> 44273.086 | AO7: =SUM(AK7:AN7) -> 173194.08 | AP7: =AP52*AP48 -> 44674.686 | AQ7: =AQ52*AQ48 -> 45080.026 | AR7: =AR52*AR48 -> 45461.43 | AS7: =AS52*AS48 -> 45959.272 | AT7: =SUM(AP7:AS7) -> 181175.41 | AU7: =AU52*AU48 -> 46214.919 | AV7: =AV52*AV48 -> 46506.257 | AW7: =AW52*AW48 -> 46846.876 | AX7: =AX52*AX48 -> 47292.775 | AY7: =SUM(AU7:AX7) -> 186860.83
A8: Other amort, impairment, disposal | B8: =18209+11082-28619 -> 672 | C8: =7930+3836-24557 -> -12791 | D8: =14391+7460-22149 -> -298 | E8: =11580+6020-21320 -> -3720 | F8: =22364+6298 -> 28662 | G8: =42928+6283 -> 49211 | H8: =-G8+51011+7617 -> 9417 | I8: =-SUM(G8:H8)+57340+7586 -> 6298 | J8: =K8-SUM(G8:I8) -> 24364 | K8: =72937+16353 -> 89290 | L8: =2664+189 -> 2853 | M8: =-L8+3450+2188 -> 2785 | N8: =-SUM(L8:M8)+10199+3500 -> 8061 | O8: =P8-SUM(L8:N8) -> 3421 | P8: =12100+5020 -> 17120 | Q8: =3422-2798 -> 624 | R8: =-Q8+5592-1083 -> 3885 | S8: =-SUM(Q8:R8)+9336-198 -> 4629 | T8: =U8-SUM(Q8:S8) -> 5445 | U8: =14031+552 -> 14583 | V8: =4436+489 -> 4925 | W8: =-V8+4436+1622 -> 1133 | X8: =-SUM(V8:W8)+4436+5164 -> 3542 | Y8: =Z8-SUM(V8:X8) -> 5097 | Z8: =8289+6408 -> 14697 | AA8: =5418+866+811 -> 7095 | AB8: =-AA8+1567+2170 -> -3358 | AC8: =-SUM(AA8:AB8)+7066+2585 -> 5914 | AD8: =AE8-SUM(AA8:AC8) -> 20957 | AE8: =15572+11596+3440 -> 30608 | AF8: =4724+679+629 -> 6032 | AG8: =-AF8+3452+1380+9660 -> 8460 | AH8: =-SUM(AF8:AG8)+15126+5724+2414 -> 8772 | AI8: =AJ8-SUM(AF8:AH8) -> 10776 | AJ8: =19338+11484+3218 -> 34040 | AK8: =3118+2185+677 -> 5980 | AL8: =-AK8+7546+3639+1196 -> 6401 | AM8: 0 | AN8: 0 | AO8: =SUM(AK8:AN8) -> 12381 | AP8: 0 | AQ8: 0 | AR8: 0 | AS8: 0 | AT8: =SUM(AP8:AS8) -> 0 | AU8: 0 | AV8: 0 | AW8: 0 | AX8: 0 | AY8: =SUM(AU8:AX8) -> 0
A9: Provision for Def. Tax | B9: 7469 | C9: -7866 | D9: 37485 | E9: 5946 | F9: 9150 | G9: 23353 | H9: =-G9+23037 -> -316 | I9: =-SUM(G9:H9)+27432 -> 4395 | J9: =K9-SUM(G9:I9) -> -3446 | K9: 23986 | L9: 4231 | M9: =-L9-21187 -> -25418 | N9: =-SUM(L9:M9)-32931 -> -11744 | O9: =P9-SUM(L9:N9) -> 1009 | P9: -31922 | Q9: -5853 | R9: =-Q9-1629 -> 4224 | S9: =-SUM(Q9:R9)-9585 -> -7956 | T9: =U9-SUM(Q9:S9) -> 21085 | U9: 11500 | V9: 9689 | W9: =-V9-822 -> -10511 | X9: =-SUM(V9:W9)-13620 -> -12798 | Y9: =Z9-SUM(V9:X9) -> 8877 | Z9: -4743 | AA9: 3064 | AB9: =-AA9-4882 -> -7946 | AC9: =-SUM(AA9:AB9)-9881 -> -4999 | AD9: =AE9-SUM(AA9:AC9) -> -2397 | AE9: =-12278 -> -12278 | AF9: 9549 | AG9: =-AF9+19675 -> 10126 | AH9: =-SUM(AF9:AG9)+17245 -> -2430 | AI9: =AJ9-SUM(AF9:AH9) -> 24133 | AJ9: 41378 | AK9: 5116 | AL9: =-AK9+12850 -> 7734 | AM9: 0 | AN9: 0 | AO9: =SUM(AK9:AN9) -> 12850 | AP9: 0 | AQ9: 0 | AR9: 0 | AS9: 0 | AT9: =SUM(AP9:AS9) -> 0 | AU9: 0 | AV9: 0 | AW9: 0 | AX9: 0 | AY9: =SUM(AU9:AX9) -> 0
A10: Share-based Comp | B10: 28359 | C10: 22120 | D10: 22108 | E10: 21755 | F10: 14007 | G10: 5162 | H10: =-G10+8906 -> 3744 | I10: =-SUM(G10:H10)+13575 -> 4669 | J10: =K10-SUM(G10:I10) -> 5107 | K10: 18682 | L10: 8450 | M10: =-L10+14937 -> 6487 | N10: =-SUM(L10:M10)+22269 -> 7332 | O10: =P10-SUM(L10:N10) -> 7035 | P10: 29304 | Q10: 8356 | R10: =-Q10+16116 -> 7760 | S10: =-SUM(Q10:R10)+23426 -> 7310 | T10: =U10-SUM(Q10:S10) -> 5569 | U10: 28995 | V10: 8088 | W10: =-V10+19647 -> 11559 | X10: =-SUM(V10:W10)+29331 -> 9684 | Y10: =Z10-SUM(V10:X10) -> 10791 | Z10: 40122 | AA10: 11363 | AB10: =-AA10+20596 -> 9233 | AC10: =-SUM(AA10:AB10)+30123 -> 9527 | AD10: =AE10-SUM(AA10:AC10) -> 8544 | AE10: 38667 | AF10: 10591 | AG10: =-AF10+20384 -> 9793 | AH10: =-SUM(AF10:AG10)+29491 -> 9107 | AI10: =AJ10-SUM(AF10:AH10) -> 9557 | AJ10: 39048 | AK10: 12075 | AL10: =-AK10+20575 -> 8500 | AM10: =AM54*AM46 -> 9568.5629 | AN10: =AN54*AN46 -> 8933.4407 | AO10: =SUM(AK10:AN10) -> 39077.004 | AP10: =AP54*AP46 -> 9894.1788 | AQ10: =AQ54*AQ46 -> 8562.8176 | AR10: =AR54*AR46 -> 9194.9846 | AS10: =AS54*AS46 -> 8874.8081 | AT10: =SUM(AP10:AS10) -> 36526.789 | AU10: =AU54*AU46 -> 10165.804 | AV10: =AV54*AV46 -> 8799.5301 | AW10: =AW54*AW46 -> 9471.7379 | AX10: =AX54*AX46 -> 9142.3476 | AY10: =SUM(AU10:AX10) -> 37579.419
A11: Loss on ext. of debt | G11: 0 | H11: 0 | I11: 0 | J11: =K11-SUM(G11:I11) -> 0 | K11: 0 | L11: 0 | M11: =-L11+5347 -> 5347 | N11: =-SUM(L11:M11)+5347 -> 0 | O11: =P11-SUM(L11:N11) -> 0 | P11: 5347 | Q11: 0 | R11: 0 | S11: =-SUM(Q11:R11)-52 -> -52 | T11: =U11-SUM(Q11:S11) -> 0 | U11: -52 | V11: 0 | W11: 0 | X11: 1276 | Y11: =Z11-SUM(V11:X11) -> 699 | Z11: 1975 | AA11: 168 | AB11: =-AA11+1114 -> 946 | AC11: =-SUM(AA11:AB11)+1114 -> 0 | AD11: =AE11-SUM(AA11:AC11) -> 0 | AE11: 1114 | AF11: 0 | AG11: 0 | AH11: 0 | AI11: =AJ11-SUM(AF11:AH11) -> 0 | AJ11: 0 | AK11: 0 | AL11: 0 | AM11: 0 | AN11: 0 | AO11: =SUM(AK11:AN11) -> 0 | AP11: 0 | AQ11: 0 | AR11: 0 | AS11: 0 | AT11: =SUM(AP11:AS11) -> 0 | AU11: 0 | AV11: 0 | AW11: 0 | AX11: 0 | AY11: =SUM(AU11:AX11) -> 0
A12: Working Capital | B12: =SUM(B13:B16) -> 27276 | C12: =SUM(C13:C16) -> -16723 | D12: =SUM(D13:D16) -> 9022 | E12: =SUM(E13:E16) -> 44744 | F12: =SUM(F13:F16) -> 7618 | G12: =SUM(G13:G16) -> -50166 | H12: =SUM(H13:H16) -> 126147 | I12: =SUM(I13:I16) -> -47984 | ... AN12: =SUM(AN13:AN16) -> 3084.8636 | AO12: =SUM(AK12:AN12) -> 41109.936 | AP12: =SUM(AP13:AP16) -> 75736.53 | AQ12: =SUM(AQ13:AQ16) -> 104005.68 | AR12: =SUM(AR13:AR16) -> -138317.74 | AS12: =SUM(AS13:AS16) -> -40025.504 | AT12: =SUM(AP12:AS12) -> 1398.9606 | AU12: =SUM(AU13:AU16) -> 42433.993 | AV12: =SUM(AV13:AV16) -> 54840.215 | AW12: =SUM(AW13:AW16) -> 8721.0576 | AX12: =SUM(AX13:AX16) -> -125726.47 | AY12: =SUM(AU12:AX12) -> -19731.204
A13: Inventories | B13: 21253 | C13: 24452 | D13: -18298 | E13: -23820 | F13: 2270 | G13: 6320 | H13: =-G13-18378 -> -24698 | I13: =-SUM(G13:H13)-109665 -> -91287 | J13: =K13-SUM(G13:I13) -> 142977 | K13: 33312 | L13: 15186 | M13: =-L13-11849 -> -27035 | N13: =-SUM(L13:M13)-140393 -> -128544 | O13: =P13-SUM(L13:N13) -> 17172 | P13: -123221 | Q13: -38475 | R13: =-Q13-184657 -> -146182 | S13: =-SUM(Q13:R13)-221414 -> -36757 | T13: =U13-SUM(Q13:S13) -> 239919 | U13: 18505 | V13: 57662 | W13: =-V13+11909 -> -45753 | X13: =-SUM(V13:W13)-91817 -> -103726 | Y13: =Z13-SUM(V13:X13) -> 126860 | Z13: 35043 | AA13: 19854 | AB13: =-AA13-70053 -> -89907 | AC13: =-SUM(AA13:AB13)-222929 -> -152876 | AD13: =AE13-SUM(AA13:AC13) -> 116055 | AE13: -106874 | AF13: 35511 | AG13: =-AF13-15164 -> -50675 | AH13: =-SUM(AF13:AG13)-153051 -> -137887 | AI13: =AJ13-SUM(AF13:AH13) -> 130993 | AJ13: -22058 | AK13: 68300 | AL13: =-AK13+8881 -> -59419 | AM13: =BS!AL9-BS!AM9 -> -157040.18 | AN13: =BS!AM9-BS!AN9 -> 102433.23 | AO13: =SUM(AK13:AN13) -> -45725.952 | AP13: =BS!AO9-BS!AP9 -> 78368.437 | AQ13: =BS!AP9-BS!AQ9 -> -120214.77 | AR13: =BS!AQ9-BS!AR9 -> -77357.914 | AS13: =BS!AR9-BS!AS9 -> 73004.465 | AT13: =SUM(AP13:AS13) -> -46199.785 | AU13: =BS!AT9-BS!AU9 -> 172478.61 | AV13: =BS!AU9-BS!AV9 -> -174200.24 | AW13: =BS!AV9-BS!AW9 -> -64269.444 | AX13: =BS!AW9-BS!AX9 -> -1651.3003 | AY13: =SUM(AU13:AX13) -> -67642.372
A14: A/P & Accrued Exp. | B14: 51050 | C14: -32647 | D14: 13622 | E14: 63155 | F14: 10821 | G14: -72533 | H14: =-G14+122004 -> 194537 | I14: =-SUM(G14:H14)+186806 -> 64802 | J14: =K14-SUM(G14:I14) -> -59 | K14: 186747 | L14: -133506 | M14: =-L14-63562 -> 69944 | N14: =-SUM(L14:M14)+81793 -> 145355 | O14: =P14-SUM(L14:N14) -> -3883 | P14: 77910 | Q14: -138774 | R14: =-Q14-34013 -> 104761 | S14: =-SUM(Q14:R14)-87463 -> -53450 | T14: =U14-SUM(Q14:S14) -> -27689 | U14: -115152 | V14: -100802 | W14: =-V14+40954 -> 141756 | X14: =-SUM(V14:W14)+126842 -> 85888 | Y14: =Z14-SUM(V14:X14) -> -43917 | Z14: 82925 | AA14: -65715 | AB14: =-AA14+86000 -> 151715 | AC14: =-SUM(AA14:AB14)+184604 -> 98604 | AD14: =AE14-SUM(AA14:AC14) -> -55342 | AE14: 129262 | AF14: -168939 | AG14: =-AF14-102681 -> 66258 | AH14: =-SUM(AF14:AG14)+28717 -> 131398 | AI14: =AJ14-SUM(AF14:AH14) -> -73845 | AJ14: -45128 | AK14: -159339 | AL14: =-AK14-38526 -> 120813 | AM14: =(BS!AM17-BS!AL17)+(BS!AM18-BS!AL18)+(BS!AL8-BS!AM8) -> 190156.31 | AN14: =(BS!AN17-BS!AM17)+(BS!AN18-BS!AM18)+(BS!AM8-BS!AN8) -> -108799.37 | AO14: =SUM(AK14:AN14) -> 42830.94 | AP14: =(BS!AP17-BS!AO17)+(BS!AP18-BS!AO18)+(BS!AO8-BS!AP8) -> -12555.455 | AQ14: =(BS!AQ17-BS!AP17)+(BS!AQ18-BS!AP18)+(BS!AP8-BS!AQ8) -> 213800.73 | AR14: =(BS!AR17-BS!AQ17)+(BS!AR18-BS!AQ18)+(BS!AQ8-BS!AR8) -> -71900.541 | AS14: =(BS!AS17-BS!AR17)+(BS!AS18-BS!AR18)+(BS!AR8-BS!AS8) -> -124517.72 | AT14: =SUM(AP14:AS14) -> 4827.0158 | AU14: =(BS!AU17-BS!AT17)+(BS!AU18-BS!AT18)+(BS!AT8-BS!AU8) -> -142106.75 | AV14: =(BS!AV17-BS!AU17)+(BS!AV18-BS!AU18)+(BS!AU8-BS!AV8) -> 216375.21 | AW14: =(BS!AW17-BS!AV17)+(BS!AW18-BS!AV18)+(BS!AV8-BS!AW8) -> 59691.999 | AX14: =(BS!AX17-BS!AW17)+(BS!AX18-BS!AW18)+(BS!AW8-BS!AX8) -> -138038.6 | AY14: =SUM(AU14:AX14) -> -4078.1366
A15: Op. lease ROU Assets + Liab. | G15: 20029 | H15: =-G15-20266 -> -40295 | I15: =-SUM(G15:H15)-41976 -> -21710 | J15: =K15-SUM(G15:I15) -> -13724 | K15: -55700 | L15: -76379 | M15: =-L15-93040 -> -16661 | N15: =-SUM(L15:M15)-105046 -> -12006 | O15: =P15-SUM(L15:N15) -> 11219 | P15: -93827 | Q15: -32127 | R15: =-Q15-41122 -> -8995 | S15: =-SUM(Q15:R15)-8364 -> 32758 | T15: =U15-SUM(Q15:S15) -> -10131 | U15: -18495 | V15: -26152 | W15: =-V15-36289 -> -10137 | X15: =-SUM(V15:W15)-30956 -> 5333 | Y15: =Z15-SUM(V15:X15) -> -24690 | Z15: -55646 | AA15: -1660 | AB15: =-AA15-5147 -> -3487 | AC15: =-SUM(AA15:AB15)-2194 -> 2953 | AD15: =AE15-SUM(AA15:AC15) -> -1094 | AE15: -3288 | AF15: 5048 | AG15: =-AF15+12210 -> 7162 | AH15: =-SUM(AF15:AG15)+10618 -> -1592 | AI15: =AJ15-SUM(AF15:AH15) -> 1622 | AJ15: 12240 | AK15: 5360 | AL15: =-AK15+8403 -> 3043 | AM15: =(BS!AM24-BS!AL24)+(BS!AM19-BS!AL19)-(BS!AM13-BS!AL13) -> 9000.95 | AN15: =(BS!AN24-BS!AM24)+(BS!AN19-BS!AM19)-(BS!AN13-BS!AM13) -> 9450.9975 | AO15: =SUM(AK15:AN15) -> 26854.948 | AP15: =(BS!AP24-BS!AO24)+(BS!AP19-BS!AO19)-(BS!AP13-BS!AO13) -> 9923.5474 | AQ15: =(BS!AQ24-BS!AP24)+(BS!AQ19-BS!AP19)-(BS!AQ13-BS!AP13) -> 10419.725 | AR15: =(BS!AR24-BS!AQ24)+(BS!AR19-BS!AQ19)-(BS!AR13-BS!AQ13) -> 10940.711 | AS15: =(BS!AS24-BS!AR24)+(BS!AS19-BS!AR19)-(BS!AS13-BS!AR13) -> 11487.747 | AT15: =SUM(AP15:AS15) -> 42771.73 | AU15: =(BS!AU24-BS!AT24)+(BS!AU19-BS!AT19)-(BS!AU13-BS!AT13) -> 12062.134 | AV15: =(BS!AV24-BS!AU24)+(BS!AV19-BS!AU19)-(BS!AV13-BS!AU13) -> 12665.241 | AW15: =(BS!AW24-BS!AV24)+(BS!AW19-BS!AV19)-(BS!AW13-BS!AV13) -> 13298.503 | AX15: =(BS!AX24-BS!AW24)+(BS!AX19-BS!AW19)-(BS!AX13-BS!AW13) -> 13963.428 | AY15: =SUM(AU15:AX15) -> 51989.305
A16: Income taxes | B16: -45027 | C16: -8528 | D16: 13698 | E16: 5409 | F16: -5473 | G16: -3982 | H16: =-G16-7379 -> -3397 | I16: =-SUM(G16:H16)-7168 -> 211 | J16: =K16-SUM(G16:I16) -> 17921 | K16: 10753 | L16: 1751 | M16: =-L16+1379 -> -372 | N16: =-SUM(L16:M16)+15061 -> 13682 | O16: =P16-SUM(L16:N16) -> -18147 | P16: -3086 | Q16: 2664 | R16: =-Q16-17154 -> -19818 | S16: =-SUM(Q16:R16)+281 -> 17435 | T16: =U16-SUM(Q16:S16) -> -7671 | U16: -7390 | V16: 3000 | W16: =-V16+28281 -> 25281 | X16: =-SUM(V16:W16)+37857 -> 9576 | Y16: =Z16-SUM(V16:X16) -> -2051 | Z16: 35806 | AA16: 7573 | AB16: =-AA16-36157 -> -43730 | AC16: =-SUM(AA16:AB16)-19429 -> 16728 | AD16: =AE16-SUM(AA16:AC16) -> 9584 | AE16: -9845 | AF16: 7049 | AG16: =-AF16-28536 -> -35585 | AH16: =-SUM(AF16:AG16)-28333 -> 203 | AI16: =AJ16-SUM(AF16:AH16) -> 4164 | AJ16: -24169 | AK16: 9987 | AL16: =-AK16+17150 -> 7163 | AM16: 0 | AN16: 0 | AO16: =SUM(AK16:AN16) -> 17150 | AP16: 0 | AQ16: 0 | AR16: 0 | AS16: 0 | AT16: =SUM(AP16:AS16) -> 0 | AU16: 0 | AV16: 0 | AW16: 0 | AX16: 0 | AY16: =SUM(AU16:AX16) -> 0
A17: All Other | B17: =11082-1237+9204-25123 -> -6074 | C17: =10288+26649-32291-7927 -> -3281 | D17: =17934-810+8061-10918 -> 14267 | E17: =21776+1292+10234-5932 -> 27370 | F17: =46442-20137-3642 -> 22663 | G17: =32213+50000-555 -> 81658 | H17: =-G17+29940+50000+5227 -> 3509 | I17: =-SUM(G17:H17)+30403+50000+11523 -> 6759 | J17: =K17-SUM(G17:I17) -> -1405 | K17: =38632+1889+50000 -> 90521 | L17: =-34162-336 -> -34498 | M17: =-L17-11575-1554 -> 21369 | N17: =-SUM(L17:M17)-34884-3655 -> -25410 | O17: =P17-SUM(L17:N17) -> 24595 | P17: =396-14340 -> -13944 | Q17: =-33475+231 -> -33244 | R17: =-Q17-38436+698 -> -4494 | S17: =-SUM(Q17:R17)-91432+16184+12000 -> -25510 | T17: =U17-SUM(Q17:S17) -> -2217 | U17: =-86923+9458+12000 -> -65465 | V17: =-10957+112 -> -10845 | W17: =-V17+1115-3514 -> 8446 | X17: =-SUM(V17:W17)+8519-6747 -> 4171 | Y17: =Z17-SUM(V17:X17) -> 24954 | Z17: =33623-6897 -> 26726 | AA17: =-40052+553 -> -39499 | AB17: =-AA17-63060+470 -> -23091 | AC17: =-SUM(AA17:AB17)-70423+1189 -> -6644 | AD17: =AE17-SUM(AA17:AC17) -> -15545 | AE17: =-71361-13418 -> -84779 | AF17: =-27872-1284 -> -29156 | AG17: =-AF17-103606-5008 -> -79458 | AH17: =-SUM(AF17:AG17)-63940-5804 -> 38870 | AI17: =AJ17-SUM(AF17:AH17) -> -16481 | AJ17: =-82349-3876 -> -86225 | AK17: =-8723-4923 -> -13646 | AL17: =-AK17-19607-4197-43750 -> -53908 | AM17: 0 | AN17: 0 | AO17: =SUM(AK17:AN17) -> -67554 | AP17: 0 | AQ17: 0 | AR17: 0 | AS17: 0 | AT17: =SUM(AP17:AS17) -> 0 | AU17: 0 | AV17: 0 | AW17: 0 | AX17: 0 | AY17: =SUM(AU17:AX17) -> 0
A18: Cash from Operations | B18: =SUM(B6:B12,B17) -> 309941 | C18: =SUM(C6:C12,C17) -> 184591 | D18: =SUM(D6:D12,D17) -> 287658 | E18: =SUM(E6:E12,E17) -> 352933 | F18: =SUM(F6:F12,F17) -> 300685 | G18: =SUM(G6:G12,G17) -> -90776 | H18: =SUM(H6:H12,H17) -> 187009 | I18: =SUM(I6:I12,I17) -> 62661 | ... AY18: =SUM(AY6:AY12,AY17) -> 751866.02
A20: Proceeds from maturities | G20: 0 | H20: 0 | I20: 0 | J20: =K20-SUM(G20:I20) -> 0 | K20: 0 | L20: 0 | M20: 0 | N20: 0 | O20: =P20-SUM(L20:N20) -> 0 | P20: 0 | Q20: 0 | R20: 0 | S20: 0 | T20: =U20-SUM(Q20:S20) -> 0 | U20: 0 | V20: 0 | W20: 0 | X20: 0 | Y20: =Z20-SUM(V20:X20) -> 0 | Z20: 0 | AA20: 0 | AB20: =-AA20-15000 -> -15000 | AC20: =-SUM(AA20:AB20)-55000 -> -40000 | AD20: =AE20-SUM(AA20:AC20) -> -59800 | AE20: =-139600+24800 -> -114800 | AF20: 20000 | AG20: =-AF20+85000 -> 65000 | AH20: =-SUM(AF20:AG20)-15000+105000 -> 5000 | AI20: =AJ20-SUM(AF20:AH20) -> 0 | AJ20: =-24800+114800 -> 90000 | AK20: =-9800+9800 -> 0 | AL20: =-AK20-19600+34600 -> 15000 | AM20: =BS!AL7-BS!AM7 -> 0 | AN20: =BS!AM7-BS!AN7 -> 0 | AO20: =SUM(AK20:AN20) -> 15000 | AP20: =BS!AO7-BS!AP7 -> 0 | AQ20: =BS!AP7-BS!AQ7 -> 0 | AR20: =BS!AQ7-BS!AR7 -> 0 | AS20: =BS!AR7-BS!AS7 -> 0 | AT20: =SUM(AP20:AS20) -> 0 | AU20: =BS!AT7-BS!AU7 -> 0 | AV20: =BS!AU7-BS!AV7 -> 0 | AW20: =BS!AV7-BS!AW7 -> 0 | AX20: =BS!AW7-BS!AX7 -> 0 | AY20: =SUM(AU20:AX20) -> 0
A21: Proceeds from sale of property and equipment | B21: 11109 | C21: 4098 | D21: 203 | Q21: 7751 | R21: =-Q21+7972 -> 221 | S21: =-SUM(Q21:R21)+11891 -> 3919 | T21: =U21-SUM(Q21:S21) -> 0 | U21: 11891 | V21: 0 | W21: 0 | X21: 615 | Y21: =Z21-SUM(V21:X21) -> 0 | Z21: 615
A22: Other investing activities | B22: 9523
A23: CAPEX | B23: -143199 | C23: -140844 | D23: -107001 | E23: -152393 | F23: -202784 | G23: -46990 | H23: =-G23-75621 -> -28631 | I23: =-SUM(G23:H23)-91748 -> -16127 | J23: =K23-SUM(G23:I23) -> -10162 | K23: -101910 | L23: -14404 | M23: =-L23-35269 -> -20865 | N23: =-SUM(L23:M23)-62223 -> -26954 | O23: =P23-SUM(L23:N23) -> -34756 | P23: -96979 | Q23: -26292 | R23: =-Q23-59582 -> -33290 | S23: =-SUM(Q23:R23)-120282 -> -60700 | T23: =U23-SUM(Q23:S23) -> -44284 | U23: -164566 | V23: -46391 | W23: =-V23-89780 -> -43389 | X23: =-SUM(V23:W23)-128601 -> -38821 | Y23: =Z23-SUM(V23:X23) -> -29196 | Z23: -157797 | AA23: -38886 | AB23: =-AA23-81649 -> -42763 | AC23: =-SUM(AA23:AB23)-132040 -> -50391 | AD23: =AE23-SUM(AA23:AC23) -> -50863 | AE23: -182903 | AF23: -50764 | AG23: =-AF23-116943 -> -66179 | AH23: =-SUM(AF23:AG23)-185212 -> -68269 | AI23: =AJ23-SUM(AF23:AH23) -> -55562 | AJ23: -240774 | AK23: -61341 | AL23: =-AK23-129357 -> -68016 | AM23: =-AM53*AM48 -> -65006.995 | AN23: =-AN53*AN48 -> -55341.357 | AO23: =SUM(AK23:AN23) -> -249705.35 | AP23: =-AP53*AP48 -> -55843.357 | AQ23: =-AQ53*AQ48 -> -56350.033 | AR23: =-AR53*AR48 -> -56826.787 | AS23: =-AS53*AS48 -> -57449.09 | AT23: =SUM(AP23:AS23) -> -226469.27 | AU23: =-AU53*AU48 -> -57768.648 | AV23: =-AV53*AV48 -> -58132.821 | AW23: =-AW53*AW48 -> -58558.595 | AX23: =-AX53*AX48 -> -59115.969 | AY23: =SUM(AU23:AX23) -> -233576.03
A24: Cash from Investing | B24: =SUM(B20:B23) -> -122567 | C24: =SUM(C20:C23) -> -136746 | D24: =SUM(D20:D23) -> -106798 | E24: =SUM(E20:E23) -> -152393 | F24: =SUM(F20:F23) -> -202784 | G24: =SUM(G20:G23) -> -46990 | H24: =SUM(H20:H23) -> -28631 | I24: =SUM(I20:I23) -> -16127 | ... AY24: =SUM(AY20:AY23) -> -233576.03
A26: Debt | B26: -6000 | C26: -25000 | D26: -15000 | F26: -20000 | G26: 210000 | H26: =-G26+350000+210000-233250-210000-6558 -> -99808 | I26: =-SUM(G26:H26)+350000+210000-233250-210000-7151 -> -593 | J26: =K26-SUM(G26:I26) -> -167 | K26: =350000+210000-233250-210000-7318 -> 109432 | L26: -1490 | M26: =-L26-46969-1837 -> -47316 | N26: =-SUM(L26:M26)-46969-2016 -> -179 | O26: =P26-SUM(L26:N26) -> 0 | P26: =-46969-2016 -> -48985 | Q26: 0 | R26: 0 | S26: =-SUM(Q26:R26)-7862-181 -> -8043 | T26: =U26-SUM(Q26:S26) -> 0 | U26: =-7862-181 -> -8043 | V26: 0 | W26: -17 | X26: =-SUM(V26:W26)-50933-180 -> -51096 | Y26: =Z26-SUM(V26:X26) -> -27039 | Z26: =-77972-180 -> -78152 | AA26: -9425 | AB26: =-AA26-223331-2716 -> -216622 | AC26: =-SUM(AA26:AB26)-223331-3273 -> -557 | AD26: =AE26-SUM(AA26:AC26) -> -18 | AE26: =-223331-3291 -> -226622 | AF26: 0 | AG26: =-AF26 -> 0 | AH26: =BS!AH25-BS!AG25 -> 0 | AI26: =AJ26-SUM(AF26:AH26) -> 0 | AJ26: 0 | AK26: =BS!AK25-BS!AJ25 -> 0 | AL26: =BS!AL25-BS!AK25 -> 0 | AM26: =BS!AM25-BS!AL25 -> 0 | AN26: =BS!AN25-BS!AM25 -> 0 | AO26: =SUM(AK26:AN26) -> 0 | AP26: =BS!AP25-BS!AO25 -> 0 | AQ26: =BS!AQ25-BS!AP25 -> 0 | AR26: =BS!AR25-BS!AQ25 -> 0 | AS26: =BS!AS25-BS!AR25 -> 0 | AT26: =SUM(AP26:AS26) -> 0 | AU26: =BS!AU25-BS!AT25 -> 0 | AV26: =BS!AV25-BS!AU25 -> 0 | AW26: =BS!AW25-BS!AV25 -> 0 | AX26: =BS!AX25-BS!AW25 -> 0 | AY26: =SUM(AU26:AX26) -> 0
A27: Stock Repurchase | B27: -50033 | E27: -68670 | F27: -63542 | G27: -15172 | H27: =-G27-15172 -> 0 | I27: =-SUM(G27:H27)-15172 -> 0 | J27: =K27-SUM(G27:I27) -> 0 | K27: -15172 | L27: -35249 | M27: =-L27-135249 -> -100000 | N27: =-SUM(L27:M27)-235249 -> -100000 | O27: =P27-SUM(L27:N27) -> -142041 | P27: =-377290 -> -377290 | Q27: -100000 | R27: =-Q27-117775 -> -17775 | S27: =-SUM(Q27:R27)-125775 -> -8000 | T27: =U27-SUM(Q27:S27) -> 0 | U27: -125775 | V27: 0 | W27: 0 | X27: 0 | Y27: =Z27-SUM(V27:X27) -> 0 | Z27: 0 | AA27: -15000 | AB27: =-AA27-30000 -> -15000 | AC27: =-SUM(AA27:AB27)-129807 -> -99807 | AD27: =AE27-SUM(AA27:AC27) -> -100000 | AE27: -229807 | AF27: -200000 | AG27: =-AF27-251223 -> -51223 | AH27: =-SUM(AF27:AG27)-351224 -> -100001 | AI27: =AJ27-SUM(AF27:AH27) -> -100000 | AJ27: -451224 | AK27: -105018 | AL27: =-AK27-286446 -> -181428 | AM27: -110000 | AN27: -110000 | AO27: =SUM(AK27:AN27) -> -506446 | AP27: -80000 | AQ27: -80000 | AR27: -80000 | AS27: -80000 | AT27: =SUM(AP27:AS27) -> -320000 | AU27: -75000 | AV27: -75000 | AW27: -75000 | AX27: -75000 | AY27: =SUM(AU27:AX27) -> -300000
A28: for Tax Withholding | G28: 0 | H28: 0 | I28: 0 | J28: =K28-SUM(G28:I28) -> 0 | K28: 0 | L28: 0 | M28: 0 | N28: 0 | O28: =P28-SUM(L28:N28) -> 0 | P28: 0 | Q28: 0 | R28: 0 | S28: 0 | T28: =U28-SUM(Q28:S28) -> 0 | U28: 0 | V28: 0 | W28: 0 | X28: 0 | Y28: =Z28-SUM(V28:X28) -> 0 | Z28: 0 | AA28: -65173 | AB28: =-AA28-67225 -> -2052 | AC28: =-SUM(AA28:AB28)-69613 -> -2388 | AD28: =AE28-SUM(AA28:AC28) -> -595 | AE28: -70208 | AF28: -34062 | AG28: =-AF28-34830 -> -768 | AH28: =-SUM(AF28:AG28)-36181 -> -1351 | AI28: =AJ28-SUM(AF28:AH28) -> -504 | AJ28: -36685 | AK28: -38433 | AL28: =-AK28-38573 -> -140 | AM28: -10000 | AN28: -10000 | AO28: =SUM(AK28:AN28) -> -58573 | AP28: -10000 | AQ28: -10000 | AR28: -10000 | AS28: -10000 | AT28: =SUM(AP28:AS28) -> -40000 | AU28: -10000 | AV28: -10000 | AW28: -10000 | AX28: -10000 | AY28: =SUM(AU28:AX28) -> -40000
A29: Other Financing | B29: =-55145+4303 -> -50842 | C29: =-54066-4727 -> -58793 | D29: =-54392-5421 -> -59813 | E29: =-53714-9307 -> -63021 | F29: =-51510-12821 -> -64331 | G29: =-12556-10604 -> -23160 | H29: =-G29-12556-11135 -> -531 | I29: =-SUM(G29:H29)-12556-11742 -> -607 | J29: =K29-SUM(G29:I29) -> -245 | K29: =-12556+-11987 -> -24543 | L29: -16452 | M29: =-L29-16192 -> 260 | N29: =-SUM(L29:M29)-20124 -> -3932 | O29: =P29-SUM(L29:N29) -> -499 | P29: -20623 | Q29: -16945 | R29: =-Q29-17649 -> -704 | S29: =-SUM(Q29:R29)-21088 -> -3439 | T29: =U29-SUM(Q29:S29) -> -423 | U29: -21511 | V29: -21956 | W29: =-V29-23325 -> -1369 | X29: =-SUM(V29:W29)-35993 -> -12668 | Y29: =Z29-SUM(V29:X29) -> 2944 | Z29: -33049 | AA29: -3353 | AB29: =-AA29-3689 -> -336 | AC29: =-SUM(AA29:AB29)-6546 -> -2857 | AD29: =AE29-SUM(AA29:AC29) -> -1694 | AE29: -8240 | AF29: -451 | AG29: =-AF29-4660 -> -4209 | AH29: =-SUM(AF29:AG29)-7149 -> -2489 | AI29: =AJ29-SUM(AF29:AH29) -> -329 | AJ29: -7478 | AK29: -4177 | AL29: =-AK29-4797 -> -620 | AM29: 0 | AN29: 0 | AO29: =SUM(AK29:AN29) -> -4797 | AP29: 0 | AQ29: 0 | AR29: 0 | AS29: 0 | AT29: =SUM(AP29:AS29) -> 0 | AU29: 0 | AV29: 0 | AW29: 0 | AX29: 0 | AY29: =SUM(AU29:AX29) -> 0
A30: Cash from Financing | B30: =SUM(B26:B29) -> -106875 | C30: =SUM(C26:C29) -> -83793 | D30: =SUM(D26:D29) -> -74813 | E30: =SUM(E26:E29) -> -131691 | F30: =SUM(F26:F29) -> -147873 | G30: =SUM(G26:G29) -> 171668 | H30: =SUM(H26:H29) -> -100339 | I30: =SUM(I26:I29) -> -1200 | ... AY30: =SUM(AY26:AY29) -> -340000
A31: FX: | B31: -12629 | C31: -5441 | D31: 24276 | E31: -20975 | F31: -3593 | G31: -3891 | H31: =-G31+1785 -> 5676 | I31: =-SUM(G31:H31)+2269 -> 484 | J31: =K31-SUM(G31:I31) -> 6899 | K31: 9168 | L31: -1021 | M31: =-L31-2547 -> -1526 | N31: =-SUM(L31:M31)-8560 -> -6013 | O31: =P31-SUM(L31:N31) -> -15134 | P31: -23694 | Q31: -2617 | R31: =-Q31-7567 -> -4950 | S31: =-SUM(Q31:R31)-14871 -> -7304 | T31: =U31-SUM(Q31:S31) -> 6419 | U31: -8452 | V31: -1998 | W31: =-V31-3672 -> -1674 | X31: =-SUM(V31:W31)-4491 -> -819 | Y31: =Z31-SUM(V31:X31) -> 1568 | Z31: -2923 | AA31: -857 | AB31: =-AA31+101 -> 958 | AC31: =-SUM(AA31:AB31)-1834 -> -1935 | AD31: =AE31-SUM(AA31:AC31) -> -5252 | AE31: -7086 | AF31: 7407 | AG31: =-AF31+9700 -> 2293 | AH31: =-SUM(AF31:AG31)+8930 -> -770 | AI31: =AJ31-SUM(AF31:AH31) -> 4610 | AJ31: 13540 | AK31: -787 | AL31: =-AK31-1159 -> -372 | AM31: 0 | AN31: 0 | AO31: =SUM(AK31:AN31) -> -1159 | AP31: 0 | AQ31: 0 | AR31: 0 | AS31: 0 | AT31: =SUM(AP31:AS31) -> 0 | AU31: 0 | AV31: 0 | AW31: 0 | AX31: 0 | AY31: =SUM(AU31:AX31) -> 0
A32: Net Chg. In Cash | B32: =B31+B30+B24+B18 -> 67870 | C32: =C31+C30+C24+C18 -> -41389 | D32: =D31+D30+D24+D18 -> 130323 | E32: =E31+E30+E24+E18 -> 47874 | F32: =F31+F30+F24+F18 -> -53565 | G32: =G31+G30+G24+G18 -> 30011 | H32: =H31+H30+H24+H18 -> 63715 | I32: =I31+I30+I24+I18 -> 45818 | ... AY32: =AY31+AY30+AY24+AY18 -> 178289.99
A33: Starting Cash | B33: 520708 | C33: =B34 -> 588578 | D33: 567632 | E33: =D34 -> 697955 | F33: =E34 -> 745829 | G33: 692264 | H33: =G34 -> 722275 | I33: =H34 -> 785990 | J33: =I34 -> 831808 | K33: =G33 -> 692264 | L33: =K34 -> 1124157 | M33: =L34 -> 924191 | N33: =M34 -> 936039 | O33: =N34 -> 880303 | P33: =L33 -> 1124157 | Q33: =P34 -> 834368 | R33: =Q34 -> 478478 | S33: =R34 -> 380034 | T33: =S34 -> 267006 | U33: =Q33 -> 834368 | V33: =U34 -> 527569 | W33: =V34 -> 456664 | X33: =W34 -> 627103 | Y33: =X34 -> 658128 | Z33: =V33 -> 527569 | AA33: 909685 | AB33: =AA34 -> 872001 | AC33: =AB34 -> 746295 | AD33: =AC34 -> 690997 | AE33: =AA33 -> 909685 | AF33: =AE34 -> 780395 | AG33: =AF34 -> 518525 | AH33: =AG34 -> 580332 | AI33: =AH34 -> 612559 | AJ33: =AF33 -> 780395 | AK33: =AJ34 -> 766916 | AL33: =AK34 -> 601416 | AM33: =AL34 -> 634985 | AN33: =AM34 -> 683618.14 | AO33: =AK33 -> 766916 | AP33: =AO34 -> 775863.75 | AQ33: =AP34 -> 836076.84 | AR33: =AQ34 -> 963546.54 | AS33: =AR34 -> 858035.04 | AT33: =AP33 -> 775863.75 | AU33: =AT34 -> 936354.14 | AV33: =AU34 -> 971799.53 | AW33: =AV34 -> 1058089 | AX33: =AW34 -> 1108192.4 | AY33: =AU33 -> 936354.14
A34: Ending Cash | B34: =B32+B33 -> 588578 | C34: =C32+C33 -> 547189 | D34: =D32+D33 -> 697955 | E34: =E32+E33 -> 745829 | F34: =F32+F33 -> 692264 | G34: =G32+G33 -> 722275 | H34: =H32+H33 -> 785990 | I34: =I32+I33 -> 831808 | ... AY34: =AY32+AY33 -> 1114644.1
A35: -Less Restricted Cash | D35: 22397 | E35: 22694 | F35: 20997 | G35: 18286 | H35: 19269 | I35: =14633+4294 -> 18927 | J35: 19295 | K35: =J35 -> 19295 | L35: =14712+471 -> 15183 | M35: =14268+267 -> 14535 | N35: =11401+3280 -> 14681 | O35: 11229 | P35: =O35 -> 11229 | Q35: 10100 | R35: 10077 | S35: 9674 | T35: 9967 | U35: =T35 -> 9967 | V35: 9712 | W35: 9764 | X35: 8639 | Y35: 8801 | Z35: =Y35 -> 8801 | AA35: 7806 | AB35: 7893 | AC35: 7908 | AD35: 7668 | AE35: =AD35 -> 7668 | AF35: 7962 | AG35: =AG34-572730 -> 7602 | AH35: =AH34-605783 -> 6776 | AI35: 7376 | AJ35: =AI35 -> 7376 | AK35: 7336 | AL35: 7269 | AM35: =AL35 -> 7269 | AN35: =AM35 -> 7269 | AO35: =AN35 -> 7269 | AP35: =AO35 -> 7269 | AQ35: =AP35 -> 7269 | AR35: =AQ35 -> 7269 | AS35: =AR35 -> 7269 | AT35: =AS35 -> 7269 | ... AY35: =AX35 -> 7269
A36: Cash on Balance Sheet | B36: =B34-B35 -> 588578 | C36: =C34-C35 -> 547189 | D36: =D34-D35 -> 675558 | E36: =E34-E35 -> 723135 | F36: =F34-F35 -> 671267 | G36: =G34-G35 -> 703989 | H36: =H34-H35 -> 766721 | I36: =I34-I35 -> 812881 | ... AY36: =AY34-AY35 -> 1107375.1
A38: PP&E accrued in A/P | G38: 46174 | H38: 34865 | I38: 26554 | J38: 16250 | K38: =J38 -> 16250 | L38: 22597 | M38: 35789 | N38: 31561 | O38: 29932 | P38: =O38 -> 29932 | Q38: 33035 | R38: 50133 | S38: 64477 | T38: 57313 | U38: =T38 -> 57313 | V38: 48006 | W38: 45506 | X38: 38787 | Y38: 35568 | Z38: =Y38 -> 35568 | AA38: 63113 | AB38: 46909 | AC38: 57005 | AD38: 48856 | AE38: =AD38 -> 48856 | AF38: 40998 | AG38: 67376 | AH38: 60460 | AI38: 56620 | AJ38: =AI38 -> 56620 | AK38: 58350 | AL38: 51422
A39: Op. lease ROU asset additions, net | G39: 35182 | H39: 23119 | I39: -41305 | J39: -38279 | K39: =J39 -> -38279 | L39: 4856 | M39: 17159 | N39: 26473 | O39: 29241 | P39: =O39 -> 29241 | Q39: 35521 | R39: 139751 | S39: 196003 | T39: 269430 | U39: =T39 -> 269430 | V39: 17857 | W39: 91007 | X39: 117959 | Y39: 155184 | Z39: =Y39 -> 155184 | AA39: 113827 | AB39: 174597 | AC39: 291289 | AD39: 365813 | AE39: =AD39 -> 365813 | AF39: 73686 | AG39: 248528 | AH39: 345947 | AI39: 438776 | AJ39: =AI39 -> 438776 | AK39: 192539 | AL39: 257320
A45: Income Statement items
A46: Sales | B46: =IS!B6 -> 3518680 | C46: =IS!C6 -> 3326740 | D46: =IS!D6 -> 3492690 | E46: =IS!E6 -> 3590109 | F46: =IS!F6 -> 3623073 | G46: =IS!G6 -> 485359 | H46: =IS!H6 -> 698328 | I46: =IS!I6 -> 819653 | ... AY46: =IS!AY6 -> 5911596.9
A47: COGS | B47: =IS!B7 -> 1340490 | C47: =IS!C7 -> 1298172 | D47: =IS!D7 -> 1408848 | E47: =IS!E7 -> 1430193 | F47: =IS!F7 -> 1472155 | G47: =IS!G7 -> 221214 | H47: =IS!H7 -> 274720 | I47: =IS!I7 -> 295220 | ... AY47: =IS!AY7 -> 2196813.2
A48: TTM Sales | J48: =J46+I46+H46+G46 -> 3125384 | K48: =J48 -> 3125384 | L48: =L46+J46+I46+H46 -> 3421430 | M48: =M46+L46+J46+I46 -> 3587952 | N48: =N46+M46+L46+J46 -> 3673459 | O48: =O46+N46+M46+L46 -> 3712768 | P48: =O48 -> 3712768 | Q48: =Q46+O46+N46+M46 -> 3744125 | R48: =R46+Q46+O46+N46 -> 3684366 | S48: =S46+R46+Q46+O46 -> 3659290 | T48: =T46+S46+R46+Q46 -> 3697751 | U48: =T48 -> 3697751 | V48: =V46+T46+S46+R46 -> 3720983 | W48: =W46+V46+T46+S46 -> 3851237 | X48: =X46+W46+V46+T46 -> 4027584 | Y48: =Y46+X46+W46+V46 -> 4280677 | Z48: =Y48 -> 4280677 | AA48: =AA46+Y46+X46+W46 -> 4465413 | AB48: =AB46+AA46+Y46+X46 -> 4664042 | AC48: =AC46+AB46+AA46+Y46 -> 4816577 | AD48: =AD46+AC46+AB46+AA46 -> 4948587 | AE48: =AD48 -> 4948587 | AF48: =AF46+AD46+AC46+AB46 -> 5025168 | AG48: =AG46+AF46+AD46+AC46 -> 5099754 | AH48: =AH46+AG46+AF46+AD46 -> 5181407 | AI48: =AI46+AH46+AG46+AF46 -> 5266292 | AJ48: =AI48 -> 5266292 | AK48: =AK46+AI46+AH46+AG46 -> 5282802 | AL48: =AL46+AK46+AI46+AH46 -> 5340931 | AM48: =AM46+AL46+AK46+AI46 -> 5417249.6 | AN48: =AN46+AM46+AL46+AK46 -> 5534135.7 | AO48: =AN48 -> 5534135.7 | AP48: =AP46+AN46+AM46+AL46 -> 5584335.7 | AQ48: =AQ46+AP46+AN46+AM46 -> 5635003.3 | AR48: =AR46+AQ46+AP46+AN46 -> 5682678.7 | AS48: =AS46+AR46+AQ46+AP46 -> 5744909 | AT48: =AS48 -> 5744909 | AU48: =AU46+AS46+AR46+AQ46 -> 5776864.8 | AV48: =AV46+AU46+AS46+AR46 -> 5813282.1 | AW48: =AW46+AV46+AU46+AS46 -> 5855859.5 | AX48: =AX46+AW46+AV46+AU46 -> 5911596.9 | AY48: =AX48 -> 5911596.9
A49: TTM COGS | J49: =J47+I47+H47+G47 -> 1234179 | K49: =J49 -> 1234179 | L49: =L47+J47+I47+H47 -> 1299236 | M49: =M47+L47+J47+I47 -> 1325881 | N49: =N47+M47+L47+J47 -> 1359577 | O49: =O47+N47+M47+L47 -> 1400773 | P49: =O49 -> 1400773 | Q49: =Q47+O47+N47+M47 -> 1477718 | R49: =R47+Q47+O47+N47 -> 1515553 | S49: =S47+R47+Q47+O47 -> 1545905 | T49: =T47+S47+R47+Q47 -> 1593213 | U49: =T49 -> 1593213 | V49: =V47+T47+S47+R47 -> 1556197 | W49: =W47+V47+T47+S47 -> 1567962 | X49: =X47+W47+V47+T47 -> 1579456 | Y49: =Y47+X47+W47+V47 -> 1587265 | Z49: =Y49 -> 1587265 | AA49: =AA47+Y47+X47+W47 -> 1604338 | AB49: =AB47+AA47+Y47+X47 -> 1651085 | AC49: =AC47+AB47+AA47+Y47 -> 1702357 | AD49: =AD47+AC47+AB47+AA47 -> 1773926 | AE49: =AD49 -> 1773926 | AF49: =AF47+AD47+AC47+AB47 -> 1847786 | AG49: =AG47+AF47+AD47+AC47 -> 1901664 | AH49: =AH47+AG47+AF47+AD47 -> 1963300 | AI49: =AI47+AH47+AG47+AF47 -> 2028884 | AJ49: =AI49 -> 2028884 | AK49: =AK47+AI47+AH47+AG47 -> 2025589 | AL49: =AL47+AK47+AI47+AH47 -> 2040108 | AM49: =AM47+AL47+AK47+AI47 -> 2050938.8 | AN49: =AN47+AM47+AL47+AK47 -> 2067919.5 | AO49: =AN49 -> 2067919.5 | AP49: =AP47+AN47+AM47+AL47 -> 2085407.2 | AQ49: =AQ47+AP47+AN47+AM47 -> 2102734.2 | AR49: =AR47+AQ47+AP47+AN47 -> 2118566.6 | AS49: =AS47+AR47+AQ47+AP47 -> 2140871.2 | AT49: =AS49 -> 2140871.2 | AU49: =AU47+AS47+AR47+AQ47 -> 2150320.4 | AV49: =AV47+AU47+AS47+AR47 -> 2163684.6 | AW49: =AW47+AV47+AU47+AS47 -> 2179044.8 | AX49: =AX47+AW47+AV47+AU47 -> 2196813.2 | AY49: =AX49 -> 2196813.2
A51: Free Cashflow
A52: D&A to TTM Sales | B52: =B7/B46 -> 0.060727318 | C52: =C7/C46 -> 0.058740388 | D52: =D7/D46 -> 0.055701766 | E52: =E7/E46 -> 0.049589024 | F52: =F7/F46 -> 0.047922026 | J52: =J7/J48 -> 0.012489025 | K52: =K7/K$48 -> 0.053203382 | L52: =L7/L48 -> 0.01106438 | M52: =M7/M48 -> 0.0095856912 | N52: =N7/N48 -> 0.0096742607 | O52: =O7/O48 -> 0.0097630663 | P52: =P7/P$48 -> 0.038794506 | Q52: =Q7/Q48 -> 0.0090509799 | R52: =R7/R48 -> 0.0085917089 | S52: =S7/S48 -> 0.0089771513 | T52: =T7/T48 -> 0.0091542129 | U52: =U7/U$48 -> 0.03576309 | V52: =V7/V48 -> 0.0096823877 | W52: =W7/W48 -> 0.0094470945 | X52: =X7/X48 -> 0.0082272648 | Y52: =Y7/Y48 -> 0.0083063964 | Z52: =Z7/Z$48 -> 0.03296301 | AA52: =AA7/AA$48 -> 0.0084402047 | AB52: =AB7/AB$48 -> 0.00843796 | AC52: =AC7/AC$48 -> 0.0082145474 | AD52: =AD7/AD$48 -> 0.0075098205 | AE52: =AE7/AE$48 -> 0.031074123 | AF52: =AF7/AF$48 -> 0.0076765593 | AG52: =AG7/AG$48 -> 0.0073383932 | ... AL52: =AL7/AL$48 -> 0.0081032689 | AM52: 0.008 | AN52: 0.008 | AO52: =AO7/AO$48 -> 0.031295597 | AP52: 0.008 | AQ52: 0.008 | AR52: 0.008 | AS52: 0.008 | AT52: =AT7/AT$48 -> 0.03153669 | AU52: 0.008 | AV52: 0.008 | AW52: 0.008 | AX52: 0.008 | AY52: =AY7/AY$48 -> 0.031609196
A53: CAPEX to TTM Sales | B53: =B23/B46 -> -0.040696795 | C53: =C23/C46 -> -0.042336942 | D53: =D23/D46 -> -0.030635699 | E53: =E23/E46 -> -0.042448015 | F53: =F23/F46 -> -0.055970167 | J53: =J23/J48 -> -0.0032514405 | K53: =-K23/K$48 -> 0.032607193 | L53: =L23/L48 -> -0.0042099356 | M53: =M23/M48 -> -0.0058152952 | N53: =N23/N48 -> -0.0073374985 | O53: =O23/O48 -> -0.0093612097 | P53: =-P23/P$48 -> 0.026120404 | Q53: =Q23/Q48 -> -0.0070222014 | R53: =R23/R48 -> -0.0090354758 | S53: =S23/S48 -> -0.016587917 | T53: =T23/T48 -> -0.011975928 | U53: =-U23/U$48 -> 0.044504349 | V53: =V23/V48 -> -0.012467404 | W53: =W23/W48 -> -0.01126625 | X53: =X23/X48 -> -0.009638781 | Y53: =Y23/Y48 -> -0.0068204165 | Z53: =-Z23/Z$48 -> 0.036862627 | AA53: =-AA23/AA$48 -> 0.0087082651 | AB53: =-AB23/AB$48 -> 0.0091686567 | AC53: =-AC23/AC$48 -> 0.010461994 | AD53: =-AD23/AD$48 -> 0.010278288 | AE53: =-AE23/AE$48 -> 0.036960652 | AF53: =-AF23/AF$48 -> 0.010101951 | AG53: =-AG23/AG$48 -> 0.0129769 | ... AL53: =-AL23/AL$48 -> 0.012734858 | AM53: 0.012 | AN53: 0.01 | AO53: =-AO23/AO$48 -> 0.04512093 | AP53: 0.01 | AQ53: 0.01 | AR53: 0.01 | AS53: 0.01 | AT53: =-AT23/AT$48 -> 0.039420863 | AU53: 0.01 | AV53: 0.01 | AW53: 0.01 | AX53: 0.01 | AY53: =-AY23/AY$48 -> 0.039511495
A54: SBC to Sales (Q) | B54: =B10/B46 -> 0.0080595564 | C54: =C10/C46 -> 0.006649152 | D54: =D10/D46 -> 0.0063297917 | E54: =E10/E46 -> 0.0060597046 | F54: =F10/F46 -> 0.0038660551 | G54: =G10/G46 -> 0.010635427 | H54: =H10/H46 -> 0.0053613775 | I54: =I10/I46 -> 0.005696313 | ... AI54: =AI10/AI46 -> 0.0057234331 | AJ54: =AJ10/AJ$46 -> 0.0074147047 | AK54: =AK10/AK46 -> 0.01084106 | AL54: =AL10/AL46 -> 0.006710408 | AM54: 0.007 | AN54: 0.005 | AO54: =AO10/AO$46 -> 0.0070610852 | AP54: 0.0085 | AQ54: 0.0065 | AR54: 0.0065 | AS54: 0.0048 | AT54: =AT10/AT$46 -> 0.0063581145 | AU54: 0.0085 | AV54: 0.0065 | AW54: 0.0065 | AX54: 0.0048 | AY54: =AY10/AY$46 -> 0.0063568981
A56: FCF | B56: =B18+B23 -> 166742 | C56: =C18+C23 -> 43747 | D56: =D18+D23 -> 180657 | E56: =E18+E23 -> 200540 | F56: =F18+F23 -> 97901 | G56: =G18+G23 -> -137766 | H56: =H18+H23 -> 158378 | I56: =I18+I23 -> 46534 | ... AY56: =AY18+AY23 -> 518289.99
