Workbook

Sheet 周涨跌
A1: 周涨跌幅
A2: Ticker | B2: 251201-1207 | C2: 251208-1214 | D2: 251215-1221 | E2: 251222-1228 | F2: 251229-0104 | G2: 260105-0111 | H2: 260112-0118 | I2: 260119-0125 | J2: 260126-0201 | K2: 260202-0208 | L2: 260209-0215 | M2: 260216-0222 | N2: 260223-0301 | O2: 260302-0308 | P2: 260309-0315 | Q2: 260316-0322 | R2: 260323-0329 | S2: 260330-0405 | T2: 260406-0412 | U2: 260413-0419 | V2: 260420-0426 | W2: 260427-0503 | X2: 260504-0510 | Y2: 260511-0517 | Z2: 260518-0524 | AA2: 260525-0531 | AB2: 260601-0607 | AC2: 260608-0614 | AD2: 260615-0621 | AE2: 260622-0628 | AF2: 260629-0705 | AG2: 260706-0712 | AH2: 260713-0719 | AI2: 260720-0726 | AJ2: 260727-0802 | AK2: 260803-0809 | AL2: 260810-0816 | AM2: 260817-0823 | AN2: 260824-0830 | AO2: 260831-0906 | AP2: 260907-0913 | AQ2: 260914-0920 | AR2: 260921-0927 | AS2: 260928-0930 | AT2: 261001-1004 | AU2: 261005-1011
A3: 运动服饰
A4: NKE.N | B4: 0.0072 | C4: 0.0244 | D4: -0.1298 | E4: 0.0378 | F4: 0.0386 | G4: 0.0417 | H4: -0.0234 | I4: 0.0103 | J4: -0.0497 | K4: 0.0341 | L4: -0.0124 | M4: 0.036 | N4: -0.0492 | O4: -0.0831 | P4: -0.0531 | Q4: -0.0298 | R4: -0.0191 | S4: -0.1398 | T4: -0.0355 | U4: 0.08 | V4: -0.0291 | W4: -0.0065 | X4: -0.0059 | Y4: -0.0512 | Z4: 0.0666 | AA4: 0.0349 | AB4: -0.0703 | AC4: 0.0454 | AD4: 0.006 | AE4: -0.0985 | AF4: 0.082 | AG4: 0.0064 | AH4: -0.0137 | AI4: -0.0471 | AJ4: 0.0002 | AK4: -0.0002 | AL4: -0.0233 | AM4: 0.0007 | AN4: -0.0285 | AO4: -0.0303 | AP4: -0.0417 | AQ4: -0.0351 | AR4: 0.0166 | AS4: -0.0151 | AT4: -0.0432 | AU4: 0.0248
A5: ADDY | B5: 0.0195 | C5: 0.0195 | D5: -0.0143 | E5: -0.0042 | F5: 0.0182 | G5: -0.0045 | H5: -0.0408 | I5: -0.1007 | J5: 0.0376 | K5: 0.0248 | L5: 0.0137 | M5: 0.0242 | N5: -0.0032 | O5: -0.098 | P5: -0.0266 | Q5: -0.0389 | R5: -0.0109 | S5: 0.0216 | T5: 0.0215 | U5: 0.0624 | V5: -0.0693 | W5: 0.0818 | X5: -0.0037 | Y5: -0.0078 | Z5: 0.0604 | AA5: 0.0783 | AB5: -0.0309 | AC5: 0.0923 | AD5: -0.0082 | AE5: 0.0389 | AF5: 0.0198 | AG5: -0.0186 | AH5: -0.0041 | AI5: -0.0414 | AJ5: -0.0818 | AK5: 0.0292 | AL5: -0.0396 | AM5: -0.0197 | AN5: -0.0016 | AO5: -0.0327 | AP5: -0.0429 | AQ5: -0.0035 | AR5: 0 | AS5: -0.0142 | AT5: -0.0086 | AU5: 0.0403
A6: WWW.N | B6: 0.0229 | C6: 0.0408 | D6: 0.0099 | E6: -0.0197 | F6: 0.0151 | G6: 0.045 | H6: 0.0142 | I6: -0.0663 | J6: -0.0166 | K6: 0.0491 | L6: -0.0527 | M6: 0.0312 | N6: -0.027 | O6: -0.0713 | P6: -0.0262 | Q6: -0.0056 | R6: -0.0069 | S6: 0.0108 | T6: 0.0652 | U6: 0.0624 | V6: -0.0172 | W6: -0.0231 | X6: -0.0364 | Y6: -0.0808 | Z6: 0.0691 | AA6: 0.0695 | AB6: -0.094 | AC6: 0.1333 | AD6: -0.0233 | AE6: -0.0261 | AF6: -0.0356 | AG6: 0.0714 | AH6: 0.0373 | AI6: 0.0229 | AJ6: 0.0474 | AK6: -0.0381 | AL6: 0.1109 | AM6: -0.0033 | AN6: -0.0296 | AO6: 0.0206 | AP6: -0.04 | AQ6: -0.0502 | AR6: 0.0291 | AS6: 0.0058 | AT6: 0.0047 | AU6: 0.012
A7: VSCO.N | B7: 0.1117 | C7: 0.1109 | D7: 0.0406 | E7: -0.051 | F7: -0.0084 | G7: 0.235 | H7: -0.0917 | I7: -0.0018 | J7: -0.0877 | K7: 0.1455 | L7: -0.0625 | M7: 0.0996 | N7: -0.0259 | O7: -0.2547 | P7: -0.04 | Q7: 0 | R7: -0.0533 | S7: 0.0831 | T7: 0.095 | U7: 0.0864 | V7: -0.0355 | W7: -0.008 | X7: -0.0825 | Y7: -0.0433 | Z7: 0.1412 | AA7: 0.0486 | AB7: 0.4556 | AC7: 0 | AD7: 0 | AE7: 0 | AF7: 0 | AG7: 0 | AH7: 0 | AI7: 0 | AJ7: 0 | AK7: 0 | AL7: 0 | AM7: 0 | AN7: 0 | AO7: 0 | AP7: 0 | AQ7: 0 | AR7: 0 | AS7: 0
A8: UAA.N | B8: -0.0066 | C8: -0.0484 | D8: 0.0462 | E8: 0.0265 | F8: 0.1376 | G8: 0.0662 | H8: 0.0248 | I8: 0.0986 | J8: -0.0283 | K8: 0.2253 | L8: -0.0489 | M8: 0.1321 | N8: -0.0885 | O8: -0.1119 | P8: -0.0152 | Q8: -0.0986 | R8: -0.0188 | S8: -0.0209 | T8: 0.089 | U8: 0.0605 | V8: -0.0447 | W8: 0.0145 | X8: 0.0223 | Y8: -0.2037 | Z8: 0.0742 | AA8: 0.0673 | AB8: -0.0528 | AC8: 0.0881 | AD8: 0.0017 | AE8: 0.0396 | AF8: 0.0524 | AG8: 0.0241 | AH8: 0.0943 | AI8: -0.0538 | AJ8: -0.0541 | AK8: -0.0812 | AL8: -0.1227 | AM8: 0.0056 | AN8: -0.0575 | AO8: 0.0335 | AP8: -0.0267 | AQ8: -0.045 | AR8: -0.0225 | AS8: -0.0023 | AT8: 0.0561 | AU8: 0.0467
A9: SKX.N
A10: SHOO.O | B10: 0.0221 | C10: -0.0062 | D10: -0.0128 | E10: -0.0002 | F10: -0.0195 | G10: 0.0675 | H10: 0.0122 | I10: -0.0024 | J10: -0.0354 | K10: -0.1862 | L10: 0.0975 | M10: 0.0179 | N10: -0.095 | O10: -0.0615 | P10: -0.0741 | Q10: 0.0147 | R10: 0.0402 | S10: 0.0266 | T10: 0.1168 | U10: 0.0485 | V10: -0.0307 | W10: -0.028 | X10: 0.0829 | Y10: -0.0448 | Z10: 0.0809 | AA10: 0.036 | AB10: 0.0136 | AC10: 0.0481 | AD10: -0.0425 | AE10: -0.022 | AF10: -0.0764 | AG10: 0.0524 | AH10: 0.0336 | AI10: -0.0154 | AJ10: 0.0779 | AK10: 0.0543 | AL10: -0.0296 | AM10: -0.0225 | AN10: -0.0399 | AO10: -0.0127 | AP10: -0.0172 | AQ10: -0.0191 | AR10: 0.0171 | AS10: 0.0053 | AT10: 0.0268 | AU10: -0.0363
A11: RL.N | B11: 0.0069 | C11: 0.0049 | D11: -0.0208 | E11: -0.0122 | F11: 0.0123 | G11: 0.0201 | H11: -0.0183 | I11: 0.0119 | J11: -0.038 | K11: -0.0298 | L11: 0.0767 | M11: 0.0429 | N11: -0.0583 | O11: -0.0669 | P11: -0.0225 | Q11: -0.0026 | R11: -0.0062 | S11: 0.0616 | T11: 0.0915 | U11: 0.0185 | V11: -0.0404 | W11: -0.0243 | X11: -0.0104 | Y11: -0.0883 | Z11: 0.156 | AA11: -0.0367 | AB11: 0.0073 | AC11: 0.1021 | AD11: 0.0224 | AE11: -0.0045 | AF11: -0.0315 | AG11: -0.0083 | AH11: -0.0366 | AI11: -0.0181 | AJ11: 0.0181 | AK11: 0.0399 | AL11: -0.0167 | AM11: -0.042 | AN11: -0.0498 | AO11: -0.008 | AP11: -0.0345 | AQ11: -0.0118 | AR11: 0.0141 | AS11: -0.0035 | AT11: 0.0234 | AU11: 0.0218
A12: PUM.DF | B12: 0.0183 | C12: 0.0313 | D12: 0.0308 | E12: -0.0388 | F12: 0.0394 | G12: 0.0692 | H12: -0.0852 | I12: -0.1556 | J12: 0.1697 | K12: 0.049 | L12: 0.033 | M12: -0.0085 | N12: 0.0219 | O12: -0.0572 | P12: -0.0353 | Q12: -0.0717 | R12: 0.0703 | S12: 0.027 | T12: 0.1224 | U12: 0.0428 | V12: -0.0314 | W12: 0.0392 | X12: -0.0312 | Y12: 0.0532 | Z12: 0.0856 | AA12: 0.0101 | AB12: -0.0802 | AC12: 0.049 | AD12: 0.0064 | AE12: -0.0507 | AF12: 0.0034 | AG12: 0.048 | AH12: 0.0177 | AI12: -0.0241 | AJ12: -0.0175 | AK12: -0.0142 | AL12: -0.0214 | AM12: -0.0569 | AN12: 0.0244 | AO12: -0.0702 | AP12: -0.0898 | AQ12: 0.0138 | AR12: 0 | AS12: -0.0149 | AT12: -0.0281 | AU12: 0.037
A13: ONON.N | B13: 0.0774 | C13: 0.0129 | D13: -0.0039 | E13: -0.0369 | F13: 0.0036 | G13: 0.0462 | H13: -0.0829 | I13: 0.0202 | J13: -0.0154 | K13: -0.0393 | L13: 0.0419 | M13: 0.0912 | N13: -0.0595 | O13: -0.108 | P13: -0.0837 | Q13: -0.0087 | R13: -0.1399 | S13: 0.0198 | T13: 0.0157 | U13: 0.1013 | V13: -0.0189 | W13: -0.0472 | X13: 0.0203 | Y13: 0.0573 | Z13: 0.0684 | AA13: 0.0254 | AB13: -0.0916 | AC13: 0.0405 | AD13: 0.0078 | AE13: -0.0466 | AF13: -0.0065 | AG13: 0.0464 | AH13: -0.0348 | AI13: -0.0371 | AJ13: 0.0117 | AK13: 0.0361 | AL13: -0.1419 | AM13: -0.0683 | AN13: -0.039 | AO13: -0.0298 | AP13: -0.0207 | AQ13: -0.0055 | AR13: 0.0022 | AS13: -0.015 | AT13: 0.0419 | AU13: 0.1374
A14: NWL.O | B14: -0.0236 | C14: 0.0242 | D14: -0.0236 | E14: 0.0188 | F14: -0.0185 | G14: 0.1317 | H14: 0.0024 | I14: 0.0237 | J14: -0.0162 | K14: 0.0894 | L14: 0.0151 | M14: 0.0383 | N14: -0.0676 | O14: -0.0681 | P14: -0.0472 | Q14: -0.1683 | R14: 0.0119 | S14: -0.0029 | T14: 0.1475 | U14: 0.1131 | V14: -0.0231 | W14: 0.0757 | X14: -0.0022 | Y14: -0.1542 | Z14: -0.0521 | AA14: -0.0659 | AB14: 0.0941 | AC14: 0.3226 | AD14: 0 | AE14: 0.1829 | AF14: 0.0017 | AG14: -0.1132 | AH14: 0.0116 | AI14: -0.0287 | AJ14: 0.1024 | AK14: 0.0732 | AL14: 0.0383 | AM14: -0.024 | AN14: 0.0131 | AO14: -0.0097 | AP14: -0.0426 | AQ14: -0.0632 | AR14: 0.0219 | AS14: -0.0221 | AT14: 0.0227 | AU14: 0.0444
A15: LULU.O | B15: 0.0417 | C15: 0.0787 | D15: 0.0219 | E15: -0.0023 | F15: 0.0088 | G15: -0.0328 | H15: -0.01 | I15: -0.0535 | J15: -0.0867 | K15: -0.0095 | L15: 0.0207 | M15: 0.0617 | N15: -0.0114 | O15: -0.0812 | P15: -0.0726 | Q15: 0.0319 | R15: -0.1042 | S15: 0.0677 | T15: 0.0523 | U15: 0.0209 | V15: -0.1404 | W15: -0.0711 | X15: -0.018 | Y15: -0.0918 | Z15: 0.0675 | AA15: 0.0315 | AB15: -0.1292 | AC15: 0.0397 | AD15: -0.0589 | AE15: 0.0519 | AF15: 0.0073 | AG15: 0.007 | AH15: -0.0246 | AI15: -0.0176 | AJ15: 0.0402 | AK15: 0.0817 | AL15: -0.0702 | AM15: 0.0127 | AN15: -0.0021 | AO15: -0.1672 | AP15: -0.0163 | AQ15: -0.0092 | AR15: 0.033 | AS15: -0.0369 | AT15: -0.018 | AU15: 0.0004
A16: LEVI.N | B16: -0.0009 | C16: -0.0346 | D16: 0.0098 | E16: -0.0276 | F16: -0.0137 | G16: 0.0447 | H16: 0.0005 | I16: -0.0239 | J16: -0.064 | K16: 0.0337 | L16: 0.0662 | M16: 0.0443 | N16: -0.0315 | O16: -0.1155 | P16: -0.0862 | Q16: 0.0011 | R16: 0.0184 | S16: 0.035 | T16: 0.2037 | U16: 0.0066 | V16: -0.0258 | W16: -0.0013 | X16: 0.0175 | Y16: -0.0745 | Z16: 0.0496 | AA16: 0.0536 | AB16: -0.0289 | AC16: 0.0657 | AD16: -0.0129 | AE16: 0.0354 | AF16: -0.0053 | AG16: -0.0041 | AH16: 0.0021 | AI16: 0.0074 | AJ16: -0.0008 | AK16: -0.0045 | AL16: -0.0762 | AM16: -0.047 | AN16: -0.0093 | AO16: -0.0108 | AP16: -0.0427 | AQ16: -0.0169 | AR16: 0 | AS16: -0.003 | AT16: 0.0086 | AU16: -0.0589
A17: KTB.N | B17: 0.0138 | C17: -0.1268 | D17: -0.0365 | E17: -0.0189 | F17: -0.0223 | G17: 0.0054 | H17: -0.039 | I17: -0.0268 | J17: 0.0329 | K17: 0.1222 | L17: 0.0064 | M17: 0.0334 | N17: -0.0646 | O17: 0.1696 | P17: -0.1151 | Q17: -0.0074 | R17: -0.0084 | S17: 0.0388 | T17: 0.0422 | U17: 0.0747 | V17: -0.0593 | W17: -0.007 | X17: 0.0201 | Y17: -0.1614 | Z17: 0.132 | AA17: 0.0266 | AB17: -0.0237 | AC17: 0.1276 | AD17: -0.0106 | AE17: 0.0655 | AF17: 0.0205 | AG17: 0.0078 | AH17: -0.0011 | AI17: -0.0237 | AJ17: 0.0024 | AK17: -0.0799 | AL17: 0.1019 | AM17: -0.034 | AN17: -0.0612 | AO17: -0.0442 | AP17: -0.0947 | AQ17: -0.0039 | AR17: 0.0008 | AS17: -0.0099 | AT17: 0.0267 | AU17: 0.0141
A18: HBI.N
A19: GIL.N | B19: 0.0207 | C19: 0.0294 | D19: 0.0474 | E19: 0.0025 | F19: -0.0098 | G19: 0.0083 | H19: -0.0036 | I19: 0.0584 | J19: -0.0288 | K19: 0.0962 | L19: 0.019 | M19: -0.0141 | N19: -0.0485 | O19: -0.0831 | P19: -0.0604 | Q19: -0.0455 | R19: -0.0279 | S19: 0.0004 | T19: 0.0623 | U19: 0.0353 | V19: -0.0219 | W19: 0.0502 | X19: -0.0366 | Y19: -0.0467 | Z19: 0.0299 | AA19: 0.0481 | AB19: -0.0553 | AC19: 0.055 | AD19: -0.1463 | AE19: 0.0179 | AF19: -0.025 | AG19: 0.0194 | AH19: 0.0301 | AI19: -0.0764 | AJ19: 0.1087 | AK19: 0.0383 | AL19: -0.0136 | AM19: -0.0097 | AN19: -0.0543 | AO19: 0.0053 | AP19: -0.0927 | AQ19: -0.0326 | AR19: -0.0151 | AS19: 0.004 | AT19: -0.0382 | AU19: 0.0237
A20: GAP.N | B20: -0.0342 | C20: -0.0083 | D20: 0.0638 | E20: -0.0657 | F20: -0.0378 | G20: 0.1243 | H20: -0.0561 | I20: 0.0138 | J20: 0.0325 | K20: 0.0411 | L20: -0.0501 | M20: 0.0398 | N20: -0.0254 | O20: -0.1698 | P20: -0.0017 | Q20: 0.0288 | R20: 0.0347 | S20: -0.0053 | T20: 0.0687 | U20: 0.0274 | V20: -0.0751 | W20: -0.0124 | X20: -0.0531 | Y20: -0.0993 | Z20: 0.1112 | AA20: -0.0958 | AB20: 0.0194 | AC20: 0.0153 | AD20: -0.0338 | AE20: -0.0444 | AF20: -0.0475 | AG20: 0.0109 | AH20: 0.0457 | AI20: -0.0658 | AJ20: 0.0568 | AK20: 0.0189 | AL20: 0.0064 | AM20: -0.0388 | AN20: 0.1859 | AO20: -0.0447 | AP20: -0.041 | AQ20: -0.0451 | AR20: 0.0346 | AS20: 0.0257 | AT20: -0.0144 | AU20: 0.032
A21: DECK.N | B21: 0.0835 | C21: 0.0148 | D21: -0.0169 | E21: 0.0364 | F21: 0.0359 | G21: -0.0284 | H21: -0.0296 | I21: -0.0071 | J21: 0.1936 | K21: -0.0326 | L21: 0.0024 | M21: 0.0256 | N21: -0.012 | O21: -0.111 | P21: -0.0333 | Q21: -0.0035 | R21: -0.0635 | S21: 0.0453 | T21: 0.0971 | U21: 0.043 | V21: -0.0353 | W21: -0.0705 | X21: -0.0046 | Y21: -0.0683 | Z21: 0.1401 | AA21: 0.0673 | AB21: -0.0502 | AC21: 0.0527 | AD21: -0.0415 | AE21: -0.0417 | AF21: 0.0012 | AG21: 0.0124 | AH21: 0.0047 | AI21: -0.0981 | AJ21: 0.0087 | AK21: 0.006 | AL21: -0.0448 | AM21: -0.0151 | AN21: -0.0428 | AO21: -0.0222 | AP21: -0.0529 | AQ21: -0.0349 | AR21: 0.023 | AS21: -0.0087 | AT21: 0.0125 | AU21: 0.0476
A22: CROX.O | B22: 0.0354 | C22: 0.0023 | D22: -0.0067 | E22: 0.026 | F22: -0.0511 | G22: -0.0101 | H22: -0.0349 | I22: 0.0332 | J22: -0.0223 | K22: 0.0225 | L22: 0.129 | M22: 0.0326 | N22: -0.0933 | O22: -0.0519 | P22: -0.0936 | Q22: -0.0278 | R22: 0.0496 | S22: 0.0518 | T22: 0.1924 | U22: 0.0612 | V22: -0.0335 | W22: 0.0152 | X22: -0.0024 | Y22: -0.0839 | Z22: 0.1633 | AA22: 0.0745 | AB22: 0.0057 | AC22: 0.0449 | AD22: 0.0027 | AE22: 0.0217 | AF22: -0.0194 | AG22: 0.0599 | AH22: 0.0328 | AI22: -0.0176 | AJ22: -0.0498 | AK22: 0.0673 | AL22: -0.0359 | AM22: -0.073 | AN22: 0.001 | AO22: -0.0385 | AP22: -0.043 | AQ22: 0.0868 | AR22: 0.0119 | AS22: 0.0022 | AT22: 0.0066 | AU22: -0.0263
A23: COLM.O | B23: -0.004 | C23: 0.0376 | D23: -0.0343 | E23: 0.0065 | F23: 0.0081 | G23: -0.0007 | H23: -0.0368 | I23: -0.0193 | J23: 0.0452 | K23: 0.1409 | L23: 0.0035 | M23: 0.0149 | N23: -0.0357 | O23: -0.0584 | P23: -0.0526 | Q23: -0.0004 | R23: -0.0112 | S23: -0.0029 | T23: 0.0516 | U23: 0.0616 | V23: -0.0087 | W23: 0.0347 | X23: 0.0111 | Y23: -0.0839 | Z23: 0.0977 | AA23: 0.044 | AB23: -0.0296 | AC23: 0.0431 | AD23: -0.0079 | AE23: -0.0293 | AF23: -0.0184 | AG23: -0.0055 | AH23: 0.0084 | AI23: -0.0186 | AJ23: -0.0472 | AK23: -0.034 | AL23: 0.001 | AM23: 0.0507 | AN23: -0.0385 | AO23: -0.005 | AP23: -0.0139 | AQ23: -0.0014 | AR23: -0.0019 | AS23: -0.006 | AT23: -0.0024 | AU23: -0.004
A24: BZUN.O | B24: 0.0554 | C24: -0.0951 | D24: -0.0109 | E24: -0.011 | F24: 0.0407 | G24: 0.0178 | H24: -0.0245 | I24: 0.0036 | J24: -0.0429 | K24: 0 | L24: 0 | M24: 0.0299 | N24: -0.0906 | O24: -0.0518 | P24: 0.0084 | Q24: -0.1 | R24: -0.0301 | S24: 0.2029 | T24: -0.0397 | U24: 0.2975 | V24: -0.1115 | W24: -0.0179 | X24: 0.0036 | Y24: -0.1055 | Z24: 0.0163 | AA24: 0.036 | AB24: 0.0232 | AC24: 0.0377 | AD24: 0.0145 | AE24: -0.0072 | AF24: 0.0036 | AG24: 0.0216 | AH24: -0.1162 | AI24: -0.012 | AJ24: 0.1573 | AK24: 0.0314 | AL24: -0.0439 | AM24: 0.0035 | AN24: 0.0634 | AO24: -0.0497 | AP24: -0.0488 | AQ24: 0.044 | AR24: 0.0298 | AS24: -0.0129 | AT24: 0.0327 | AU24: 0.0475
A25: AS.N | B25: -0.0329 | C25: 0.0712 | D25: -0.0039 | E25: 0.0042 | F25: -0.0227 | G25: 0.0275 | H25: -0.0389 | I25: 0.0186 | J25: -0.0289 | K25: 0.024 | L25: 0.0613 | M25: 0.054 | N25: -0.0949 | O25: -0.1053 | P25: -0.0483 | Q25: -0.0495 | R25: 0.0224 | S25: 0.0627 | T25: 0.0545 | U25: 0.0537 | V25: -0.0342 | W25: -0.0165 | X25: 0.0221 | Y25: -0.0885 | Z25: 0.0737 | AA25: 0.0091 | AB25: -0.0416 | AC25: 0.0399 | AD25: 0.0386 | AE25: -0.0722 | AF25: 0.0258 | AG25: -0.0071 | AH25: 0.0471 | AI25: -0.0692 | AJ25: 0.0469 | AK25: 0.0375 | AL25: -0.1078 | AM25: -0.0073 | AN25: -0.0484 | AO25: -0.049 | AP25: -0.0494 | AQ25: -0.0477 | AR25: 0.0269 | AS25: -0.0138 | AT25: -0.0044 | AU25: 0.0357
A26: ANF.N | B26: -0.069 | C26: 0.1815 | D26: 0.08 | E26: 0.0477 | F26: -0.0244 | G26: 0.0091 | H26: -0.1661 | I26: -0.0752 | J26: 0.0138 | K26: 0.0003 | L26: -0.0405 | M26: 0.0289 | N26: 0.0144 | O26: -0.1309 | P26: -0.0369 | Q26: 0.0748 | R26: 0.0131 | S26: 0.035 | T26: 0.0666 | U26: -0.041 | V26: -0.0769 | W26: -0.0294 | X26: -0.0775 | Y26: -0.0951 | Z26: 0.0948 | AA26: -0.0005 | AB26: -0.0243 | AC26: 0.2022 | AD26: -0.0368 | AE26: 0.0489 | AF26: 0.0099 | AG26: 0.007 | AH26: 0.0233 | AI26: -0.015 | AJ26: 0.0611 | AK26: 0.1314 | AL26: -0.0399 | AM26: 0.0081 | AN26: 0.3615 | AO26: 0.0084 | AP26: -0.0297 | AQ26: -0.0652 | AR26: 0.0074 | AS26: -0.0044 | AT26: 0.0091 | AU26: 0.0491
A27: 9983.T | B27: 0.0141 | C27: 0.0067 | D27: -0.0135 | E27: 0.0163 | F27: -0.0058 | G27: 0.102 | H27: -0.0016 | I27: -0.0343 | J27: -0.0281 | K27: 0.0799 | L27: 0.089 | M27: -0.0317 | N27: 0.0309 | O27: -0.0522 | P27: -0.0066 | Q27: -0.0242 | R27: -0.026 | S27: 0.0408 | T27: 0.1748 | U27: -0.0197 | V27: -0.0535 | W27: 0.0399 | X27: 0.0289 | Y27: -0.0449 | Z27: 0.0542 | AA27: 0.0903 | AB27: -0.0441 | AC27: 0.0233 | AD27: 0.0319 | AE27: 0.0117 | AF27: 0.0051 | AG27: -0.0283 | AH27: -0.0398 | AI27: -0.0332 | AJ27: 0.0258 | AK27: 0.0143 | AL27: -0.0276 | AM27: -0.0468 | AN27: -0.0306 | AO27: -0.0303 | AP27: -0.0379 | AQ27: 0.0181 | AR27: 0 | AS27: 0.0255 | AT27: 0.0128 | AU27: 0.0001
A28: 8111.T | B28: -0.0019 | C28: -0.0086 | D28: -0.0567 | E28: -0.054 | F28: -0.0226 | G28: 0.0367 | H28: 0.0161 | I28: -0.0216 | J28: -0.0037 | K28: -0.0444 | L28: -0.0071 | M28: -0.0102 | N28: 0.0194 | O28: -0.0436 | P28: -0.0125 | Q28: 0.0015 | R28: -0.0219 | S28: -0.0388 | T28: 0.0203 | U28: 0.0161 | V28: -0.0415 | W28: 0.0147 | X28: 0.0016 | Y28: -0.0079 | Z28: -0.0184 | AA28: -0.022 | AB28: -0.0088 | AC28: 0.038 | AD28: 0.0088 | AE28: -0.0199 | AF28: 0.0424 | AG28: 0.0018 | AH28: 0.0109 | AI28: 0.0154 | AJ28: -0.0041 | AK28: -0.0945 | AL28: 0.0282 | AM28: 0.0026 | AN28: 0.0238 | AO28: -0.0352 | AP28: -0.0109 | AQ28: 0.0175 | AR28: 0 | AS28: -0.0377 | AT28: -0.008 | AU28: 0.0309
A29: 7936.T | B29: 0.0016 | C29: 0.0528 | D29: -0.0205 | E29: 0.0146 | F29: -0.0327 | G29: 0.1031 | H29: 0.0036 | I29: -0.0404 | J29: -0.0687 | K29: 0.0086 | L29: 0.1732 | M29: 0.0942 | N29: -0.0033 | O29: -0.039 | P29: -0.0319 | Q29: -0.0126 | R29: -0.0223 | S29: 0 | T29: 0.0606 | U29: 0.0061 | V29: -0.0394 | W29: -0.0165 | X29: 0.0689 | Y29: -0.0289 | Z29: 0.0087 | AA29: 0.0656 | AB29: -0.0865 | AC29: 0.0059 | AD29: -0.0196 | AE29: 0.0213 | AF29: 0.0377 | AG29: -0.0097 | AH29: 0.069 | AI29: -0.0208 | AJ29: -0.0081 | AK29: 0.0469 | AL29: 0.0611 | AM29: -0.1121 | AN29: -0.0188 | AO29: -0.0728 | AP29: -0.0649 | AQ29: 0.0193 | AR29: 0 | AS29: 0.0024 | AT29: -0.0187 | AU29: 0.0804
A30: 3998.HK | B30: -0.014 | C30: -0.0344 | D30: -0.0356 | E30: 0 | F30: -0.0174 | G30: -0.0088 | H30: 0.0089 | I30: 0.0243 | J30: 0.0302 | K30: 0.0398 | L30: -0.0282 | M30: -0.0124 | N30: 0.021 | O30: -0.037 | P30: -0.1346 | Q30: 0.0123 | R30: -0.0244 | S30: 0.035 | T30: 0.0386 | U30: -0.0302 | V30: 0.036 | W30: -0.0139 | X30: 0.0305 | Y30: -0.0251 | Z30: -0.0257 | AA30: 0.0192 | AB30: 0.0024 | AC30: 0.0023 | AD30: -0.0913 | AE30: 0.018 | AF30: 0.1367 | AG30: 0.0579 | AH30: 0.0042 | AI30: -0.0042 | AJ30: 0.04 | AK30: -0.0425 | AL30: -0.0095 | AM30: -0.0075 | AN30: -0.0505 | AO30: -0.0159 | AP30: 0.0046 | AQ30: -0.0607 | AR30: -0.05 | AS30: -0.0309 | AT30: -0.01 | AU30: 0.1108
... A36: 002832.SZ | B36: -0.0146 | C36: -0.0078 | D36: -0.0065 | E36: -0.0072 | F36: -0.0119 | G36: 0.0167 | H36: 0 | I36: 0.0099 | J36: -0.0176 | K36: 0.0252 | L36: -0.0291 | M36: 0 | N36: 0.034 | O36: 0.065 | P36: 0.0193 | Q36: -0.0142 | R36: 0.0445 | S36: -0.0127 | T36: 0.0158 | U36: 0.0224 | V36: 0.0135 | W36: 0.122 | X36: -0.0321 | Y36: 0.0791 | Z36: -0.0459 | AA36: -0.0283 | AB36: 0.0194 | AC36: 0.0696 | AD36: -0.0267 | AE36: -0.0385 | AF36: 0.046 | AG36: -0.011 | AH36: 0.0155 | AI36: 0.0857 | AJ36: 0.1394 | AK36: -0.0527 | AL36: 0.0593 | AM36: -0.0686 | AN36: 0.0074 | AO36: 0.087 | AP36: -0.0579 | AQ36: 0.0227 | AR36: 0.0078 | AS36: 0.0244 | AT36: 0 | AU36: 0.0698
AG37: =AVERAGE(AG4:AG36) | AH37: =AVERAGE(AH4:AH36) | AI37: =AVERAGE(AI4:AI36) | AJ37: =AVERAGE(AJ4:AJ36) | AK37: =AVERAGE(AK4:AK36) | AL37: =AVERAGE(AL4:AL36) | AM37: =AVERAGE(AM4:AM36) | AN37: =AVERAGE(AN4:AN36) | ... AS37: =AVERAGE(AS4:AS36)
A38: 奢侈品
A39: VFC | B39: 0.0502 | C39: 0.032 | D39: -0.0529 | E39: -0.0064 | F39: -0.0184 | G39: 0.0936 | H39: -0.0524 | I39: 0.0489 | J39: -0.0076 | K39: 0.0383 | L39: -0.002 | M39: 0.0458 | N39: -0.0853 | O39: -0.1081 | P39: -0.0785 | Q39: 0.0201 | R39: 0.0074 | S39: 0.0287 | T39: 0.0806 | U39: 0.1519 | V39: -0.0576 | W39: -0.0394 | X39: -0.0016 | Y39: -0.1212 | Z39: 0.0012 | AA39: 0.0287 | AB39: -0.0343 | AC39: 0.0633 | AD39: -0.0176 | AE39: 0.0023 | AF39: -0.0616 | AG39: 0.0288 | AH39: 0.0125 | AI39: 0.0029 | AJ39: -0.1591 | AK39: 0.0468 | AL39: -0.008 | AM39: -0.0336 | AN39: -0.0487 | AO39: -0.0161 | AP39: -0.0208 | AQ39: -0.0289 | AR39: 0.0203 | AS39: 0.0055 | AT39: 0.0192 | AU39: 0.0468
A40: CFR | B40: -0.0009 | C40: -0.0409 | D40: 0.0117 | E40: 0.0104 | F40: 0.0118 | G40: 0.0256 | H40: -0.0856 | I40: -0.0421 | J40: -0.0324 | K40: 0.0395 | L40: 0.0206 | M40: 0.023 | N40: -0.0311 | O40: -0.0925 | P40: -0.0322 | Q40: -0.0558 | R40: 0.0587 | S40: 0.0351 | T40: 0.0731 | U40: 0.0434 | V40: -0.0606 | W40: -0.012 | X40: 0.0667 | Y40: -0.0177 | Z40: 0.001 | AA40: 0.0844 | AB40: -0.0252 | AC40: 0.0865 | AD40: 0.0266 | AE40: 0.0172 | AF40: -0.0139 | AG40: -0.0109 | AH40: 0.0659 | AI40: -0.0059 | AJ40: -0.0111 | AK40: 0.0238 | AL40: -0.0153 | AM40: -0.0348 | AN40: 0.0474 | AO40: -0.0468 | AP40: -0.0563 | AQ40: -0.0351 | AR40: 0 | AS40: 0.025 | AT40: -0.0349 | AU40: -0.0148
A41: 1913.HK | B41: -0.04 | C41: 0.0314 | D41: 0.0239 | E41: -0.0327 | F41: -0.0189 | G41: -0.0336 | H41: -0.0231 | I41: -0.0104 | J41: -0.0412 | K41: 0.011 | L41: 0.0346 | M41: 0.0076 | N41: 0.0545 | O41: -0.0813 | P41: -0.044 | Q41: -0.0573 | R41: 0.0071 | S41: -0.0016 | T41: 0.0508 | U41: -0.0504 | V41: 0.0152 | W41: -0.0752 | X41: 0.1084 | Y41: -0.0718 | Z41: 0.0275 | AA41: 0 | AB41: 0.0016 | AC41: 0.1045 | AD41: -0.0054 | AE41: -0.0525 | AF41: 0.0115 | AG41: 0.0222 | AH41: 0.041 | AI41: -0.0598 | AJ41: 0.1178 | AK41: 0.0194 | AL41: -0.0553 | AM41: -0.0134 | AN41: 0.0131 | AO41: -0.0552 | AP41: -0.0214 | AQ41: 0.0166 | AR41: -0.0445 | AS41: -0.0344 | AT41: -0.0229 | AU41: 0.0164
A42: MONC | B42: -0.0014 | C42: -0.0355 | D42: 0.0096 | E42: -0.0106 | F42: -0.0215 | G42: -0.011 | H42: -0.0576 | I42: -0.0271 | J42: -0.0123 | K42: -0.0133 | L42: 0.048 | M42: 0.1247 | N42: 0.0253 | O42: -0.0589 | P42: -0.0444 | Q42: -0.0088 | R42: -0.0376 | S42: 0.0602 | T42: 0.0229 | U42: 0.0445 | V42: -0.0475 | W42: -0.0529 | X42: 0.0636 | Y42: -0.0879 | Z42: 0.0364 | AA42: 0.0842 | AB42: -0.0301 | AC42: -0.0059 | AD42: -0.0189 | AE42: -0.0288 | AF42: -0.0035 | AG42: -0.0235 | AH42: 0.014 | AI42: -0.0533 | AJ42: 0.0242 | AK42: 0.0318 | AL42: -0.034 | AM42: -0.0376 | AN42: 0.0132 | AO42: -0.0394 | AP42: -0.0251 | AQ42: -0.0322 | AR42: 0 | AS42: -0.0045 | AT42: -0.0211 | AU42: -0.0041
A43: KER | B43: -0.0134 | C43: 0.0024 | D43: 0.0214 | E43: 0.0035 | F43: 0.0033 | G43: 0.042 | H43: -0.0904 | I43: -0.0476 | J43: -0.0393 | K43: -0.0231 | L43: 0.1019 | M43: -0.0223 | N43: 0.0284 | O43: -0.0997 | P43: -0.0338 | Q43: -0.0585 | R43: 0.0604 | S43: 0.0683 | T43: 0.0422 | U43: -0.0827 | V43: -0.0534 | W43: -0.0308 | X43: 0.057 | Y43: -0.0368 | Z43: 0.0217 | AA43: 0.0552 | AB43: -0.0231 | AC43: 0.0758 | AD43: 0.0134 | AE43: -0.018 | AF43: -0.0696 | AG43: 0.0002 | AH43: 0.0153 | AI43: -0.0396 | AJ43: 0.1729 | AK43: 0.0086 | AL43: -0.0631 | AM43: -0.0531 | AN43: -0.0004 | AO43: -0.0354 | AP43: -0.0269 | AQ43: -0.0235 | AR43: 0 | AS43: -0.0204 | AT43: -0.0586 | AU43: 0.0052
A44: SFER | B44: -0.0087 | C44: -0.0006 | D44: 0.0256 | E44: -0.0165 | F44: 0.0347 | G44: -0.0503 | H44: -0.0833 | I44: -0.0323 | J44: -0.059 | K44: 0.0113 | L44: 0.0045 | M44: 0.0372 | N44: -0.0316 | O44: -0.1007 | P44: 0.1252 | Q44: -0.0783 | R44: 0.0167 | S44: 0.0984 | T44: 0.0861 | U44: 0.0648 | V44: -0.0547 | W44: -0.0371 | X44: 0.1743 | Y44: -0.2394 | Z44: 0.1649 | AA44: 0.2273 | AB44: -0.0265 | AC44: 0.0359 | AD44: 0.0126 | AE44: 0.1202 | AF44: -0.0305 | AG44: -0.0363 | AH44: 0.0337 | AI44: -0.0421 | AJ44: 0.018 | AK44: -0.0079 | AL44: -0.049 | AM44: -0.0349 | AN44: 0.0243 | AO44: -0.0405 | AP44: -0.0582 | AQ44: -0.1136 | AR44: 0 | AS44: -0.0145 | AT44: -0.0409 | AU44: -0.0284
A45: RACE | B45: 0.0162 | C45: -0.0663 | D45: 0.0304 | E45: -0.0004 | F45: -0.0165 | G45: 0.0116 | H45: -0.0823 | I45: -0.0194 | J45: -0.0158 | K45: 0.0019 | L45: 0.1357 | M45: -0.032 | N45: 0.0353 | O45: -0.0785 | P45: -0.052 | Q45: -0.0519 | R45: 0.0088 | S45: 0.0712 | T45: 0.035 | U45: 0.0596 | V45: -0.0561 | W45: -0.0304 | X45: -0.0046 | Y45: -0.0544 | Z45: 0.0842 | AA45: -0.023 | AB45: 0.0199 | AC45: 0.0228 | AD45: 0.0203 | AE45: 0.0171 | AF45: 0.0451 | AG45: -0.0216 | AH45: 0.0005 | AI45: -0.0443 | AJ45: 0.0937 | AK45: 0.0467 | AL45: 0.0063 | AM45: 0.0523 | AN45: -0.0367 | AO45: -0.0252 | AP45: 0.0093 | AQ45: -0.0171 | AR45: 0.0232 | AS45: 0.0102 | AT45: -0.0115 | AU45: 0.0041
A46: RMS | B46: 0.0084 | C46: -0.0143 | D46: -0.015 | E46: -0.0033 | F46: 0.0043 | G46: 0.0537 | H46: -0.0122 | I46: -0.0274 | J46: -0.0474 | K46: 0.0128 | L46: 0.0448 | M46: -0.0163 | N46: -0.0298 | O46: -0.07 | P46: -0.0171 | Q46: -0.1159 | R46: -0.0208 | S46: 0.0284 | T46: 0.054 | U46: -0.0094 | V46: -0.0534 | W46: -0.0149 | X46: 0.0231 | Y46: -0.0515 | Z46: 0.0187 | AA46: 0.0093 | AB46: -0.0006 | AC46: 0.0482 | AD46: 0.0144 | AE46: -0.0555 | AF46: 0.0092 | AG46: 0.0003 | AH46: 0.0241 | AI46: -0.0226 | AJ46: -0.0679 | AK46: 0.0679 | AL46: -0.0364 | AM46: -0.0019 | AN46: 0.0159 | AO46: -0.0882 | AP46: -0.0395 | AQ46: -0.0486 | AR46: 0 | AS46: -0.021 | AT46: -0.0277 | AU46: -0.0127
A47: MC | B47: -0.0227 | C47: -0.0057 | D47: 0.0115 | E47: 0.0006 | F47: 0.0153 | G47: 0.016 | H47: -0.0658 | I47: -0.0292 | J47: -0.0752 | K47: -0.0196 | L47: -0.041 | M47: 0.0788 | N47: -0.0191 | O47: -0.077 | P47: -0.0568 | Q47: -0.0332 | R47: -0.0048 | S47: 0.0336 | T47: 0.026 | U47: 0.0333 | V47: -0.0556 | W47: -0.0429 | X47: 0.0472 | Y47: -0.0362 | Z47: 0.0373 | AA47: 0.001 | AB47: 0.0127 | AC47: 0.0659 | AD47: -0.0222 | AE47: -0.007 | AF47: -0.0001 | AG47: -0.0117 | AH47: 0.0106 | AI47: -0.0675 | AJ47: 0.0291 | AK47: 0.0102 | AL47: -0.045 | AM47: -0.0129 | AN47: 0.0125 | AO47: -0.0634 | AP47: -0.0322 | AQ47: -0.0301 | AR47: 0 | AS47: -0.0105 | AT47: -0.0294 | AU47: 0.0038
A48: BRBY | B48: 0.0553 | C48: 0.0341 | D48: 0.0083 | E48: -0.0238 | F48: 0.0511 | G48: 0.0141 | H48: -0.0472 | I48: -0.0601 | J48: -0.0807 | K48: 0.0737 | L48: 0.0131 | M48: 0.0151 | N48: -0.0416 | O48: -0.0563 | P48: -0.062 | Q48: -0.0146 | R48: 0.0118 | S48: 0.0628 | T48: 0.0609 | U48: 0.0213 | V48: -0.0291 | W48: 0.0239 | X48: 0.0376 | Y48: -0.1293 | Z48: 0.0589 | AA48: 0.0489 | AB48: -0.0619 | AC48: 0.0628 | AD48: -0.0349 | AE48: -0.0229 | AF48: -0.0262 | AG48: -0.0093 | AH48: -0.0192 | AI48: 0.0181 | AJ48: 0.1119 | AK48: -0.0194 | AL48: -0.073 | AM48: -0.0093 | AN48: 0.0136 | AO48: 0.018 | AP48: -0.0775 | AQ48: -0.0216 | AR48: 0 | AS48: 0.0049 | AT48: -0.0093 | AU48: 0.0139
A49: CPRI | B49: 0.073 | C49: -0.0374 | D49: -0.03 | E49: -0.0103 | F49: -0.024 | G49: 0.0709 | H49: -0.049 | I49: -0.0068 | J49: -0.0851 | K49: -0.1059 | L49: 0.0119 | M49: 0.0847 | N49: -0.074 | O49: -0.1248 | P49: 0.0351 | Q49: -0.0264 | R49: -0.0453 | S49: 0.04 | T49: 0.1069 | U49: 0.0513 | V49: -0.0129 | W49: -0.0485 | X49: -0.056 | Y49: -0.0685 | Z49: 0.0707 | AA49: 0.0016 | AB49: 0.0194 | AC49: 0.1304 | AD49: -0.0474 | AE49: -0.0463 | AF49: -0.0217 | AG49: -0.0485 | AH49: -0.092 | AI49: -0.0574 | AJ49: 0.0317 | AK49: -0.0389 | AL49: 0.002 | AM49: -0.1102 | AN49: -0.011 | AO49: 0.0044 | AP49: 0.0243 | AQ49: 0.0619 | AR49: -0.0298 | AS49: -0.0088 | AT49: 0.0227 | AU49: 0.0353
A50: PVH | B50: -0.0793 | C50: -0.041 | D50: -0.062 | E50: -0.0276 | F50: -0.0121 | G50: -0.0233 | H50: -0.0243 | I50: -0.0508 | J50: 0.0165 | K50: 0.0603 | L50: 0.0392 | M50: 0.0504 | N50: -0.0495 | O50: -0.0538 | P50: -0.0622 | Q50: 0.0394 | R50: 0.0495 | S50: 0.1613 | T50: 0.1768 | U50: 0.0378 | V50: -0.0056 | W50: -0.0214 | X50: -0.0236 | Y50: -0.1121 | Z50: 0.1192 | AA50: 0.049 | AB50: -0.166 | AC50: 0.0535 | AD50: -0.0597 | AE50: -0.0349 | AF50: 0.0114 | AG50: 0.055 | AH50: -0.0154 | AI50: 0.0289 | AJ50: 0.0777 | AK50: 0.0106 | AL50: -0.0583 | AM50: -0.0481 | AN50: -0.0345 | AO50: -0.0193 | AP50: -0.0496 | AQ50: 0.0384 | AR50: 0.0007 | AS50: 0.0001 | AT50: 0.02 | AU50: 0.0771
... A53: ZGN | B53: 0.0085 | C53: -0.0169 | D53: 0.0153 | E53: -0.0141 | F53: -0.0038 | G53: 0.0393 | H53: -0.1181 | I53: 0.0063 | J53: -0.0967 | K53: 0.1956 | L53: 0.0626 | M53: 0.0371 | N53: -0.0157 | O53: -0.071 | P53: -0.0735 | Q53: -0.0021 | R53: 0.0083 | S53: 0.0809 | T53: 0.091 | U53: 0.0556 | V53: -0.0156 | W53: 0.0401 | X53: 0.0579 | Y53: -0.0441 | Z53: 0.0572 | AA53: 0.1053 | AB53: -0.0034 | AC53: 0.0034 | AD53: -0.0565 | AE53: -0.0519 | AF53: 0.0015 | AG53: 0.0205 | AH53: 0.0342 | AI53: 0.0302 | AJ53: 0.0272 | AK53: 0.0136 | AL53: -0.0771 | AM53: 0.0102 | AN53: -0.0122 | AO53: -0.0852 | AP53: -0.0756 | AQ53: 0.0586 | AR53: 0.0106 | AS53: -0.0016 | AT53: 0.0016 | AU53: 0.0128
A55: 宏观指标 | AG55: =AVERAGE(AG39:AG53) | AH55: =AVERAGE(AH39:AH53) | AI55: =AVERAGE(AI39:AI53) | AJ55: =AVERAGE(AJ39:AJ53) | AK55: =AVERAGE(AK39:AK53) | AL55: =AVERAGE(AL39:AL53) | AM55: =AVERAGE(AM39:AM53) | AN55: =AVERAGE(AN39:AN53) | ... AS55: =AVERAGE(AS39:AS53)
B56: 251201-1207 | C56: 251208-1214 | D56: 251215-1221 | E56: 251222-1228 | F56: 251229-0104 | G56: 260105-0111 | H56: 260112-0118 | I56: 260119-0125 | J56: 260126-0201 | K56: 260202-0208 | L56: 260209-0215 | M56: 260216-0222 | N56: 260223-0301 | O56: 260302-0308 | P56: 260309-0315 | Q56: 260316-0322 | R56: 260323-0329 | S56: 260330-0405 | T56: 260406-0412 | U56: 260413-0419 | V56: 260420-0426 | W56: 260427-0503 | X56: 260504-0510 | Y56: 260511-0517 | Z56: 260518-0524 | AA56: 260525-0531 | AB56: 260601-0607 | AC56: 260608-0614 | AD56: 260615-0621 | AE56: 260622-0628 | AF56: 260629-0705 | AG56: 260706-0712 | AH56: 260713-0719 | AI56: 260720-0726 | AJ56: 260727-0802 | AK56: 260803-0809 | AL56: 260810-0816 | AM56: 260817-0823 | AN56: 260824-0830 | AO56: 260831-0906 | AP56: 260907-0913 | AQ56: 260914-0920 | AR56: 260921-0927 | AS56: 260928-0930
A57: Brent($/bbl) | B57: 63.75 | C57: 61.12 | D57: 60.47 | E57: 60.64 | F57: 60.75 | G57: 63.34 | H57: 64.13 | I57: 65.88 | J57: 70.69 | K57: 68.05 | L57: 67.75 | M57: 71.76 | N57: 72.48 | O57: 92.69 | P57: 103.14 | Q57: 112.19 | R57: 112.57 | S57: 109.03 | T57: 95.2 | U57: 90.38 | V57: 105.33 | W57: 108.17 | X57: 101.29 | Y57: 109.26 | Z57: 103.54 | AA57: 92.05 | AB57: 93.09 | AC57: 87.33 | AD57: 79.85 | AE57: 71.99 | AF57: 71.8 | AG57: 76.01 | AH57: 88.1 | AI57: 96.78 | AJ57: 90.12 | AK57: 83.55 | AL57: 88.52 | AM57: 94.39 | AN57: 89.31 | AO57: 96.28 | AP57: 104.61 | AQ57: 103.87 | AR57: 97.21 | AS57: 98.03 | AT57: 102.25 | AU57: 104.72
A58: WTI($/bbl) | B58: 60.08 | C58: 57.44 | D58: 56.66 | E58: 56.74 | F58: 57.32 | G58: 59.12 | H58: 59.44 | I58: 61.07 | J58: 65.21 | K58: 63.55 | L58: 62.89 | M58: 66.39 | N58: 67.02 | O58: 90.9 | P58: 98.71 | Q58: 98.32 | R58: 99.64 | S58: 111.54 | T58: 96.57 | U58: 83.85 | V58: 94.4 | W58: 101.94 | X58: 95.42 | Y58: 105.42 | Z58: 96.6 | AA58: 87.36 | AB58: 90.54 | AC58: 84.88 | AD58: 76.6 | AE58: 69.23 | AF58: 68.69 | AG58: 71.41 | AH58: 82.49 | AI58: 89.31 | AJ58: 84.67 | AK58: 78.18 | AL58: 82.4 | AM58: 87.06 | AN58: 83.4 | AO58: 91.48 | AP58: 100.05 | AQ58: 100.3 | AR58: 93.11 | AS58: 90.42 | AT58: 91.11 | AU58: 91.85
A59: 汽油($/gal) | B59: 2.98 | C59: 2.94 | D59: 2.9 | E59: 2.84 | F59: 2.81 | G59: 2.8 | H59: 2.78 | I59: 2.81 | J59: 2.85 | K59: 2.87 | L59: 2.9 | M59: 2.92 | N59: 2.94 | O59: 3.02 | P59: 3.5 | Q59: 3.72 | R59: 3.96 | S59: 3.99 | T59: 4.12 | U59: 4.12 | V59: 4.04 | W59: 4.12 | X59: 4.45 | Y59: 4.5 | Z59: 4.49 | AA59: 4.47 | AB59: 4.3 | AC59: 4.15 | AD59: 4.05 | AE59: 3.91 | AF59: 3.83 | AG59: 3.78 | AH59: 3.85 | AI59: 4 | AJ59: 4.1 | AK59: 4.08 | AL59: 4.01 | AM59: 4.05 | AN59: 4.08 | AO59: 4.07 | AP59: 4.16 | AQ59: 4.16 | AR59: 4.16
A60: Brent周涨跌 | C60: -0.0413 | D60: -0.0106 | E60: 0.0028 | F60: 0.0018 | G60: 0.0426 | H60: 0.0125 | I60: 0.0273 | J60: 0.073 | K60: -0.0373 | L60: -0.0044 | M60: 0.0592 | N60: 0.01 | O60: 0.2788 | P60: 0.1127 | Q60: 0.0877 | R60: 0.0034 | S60: -0.0314 | T60: -0.1268 | U60: -0.0506 | V60: 0.1654 | W60: 0.027 | X60: -0.0636 | Y60: 0.0787 | Z60: -0.0524 | AA60: -0.111 | AB60: 0.0113 | AC60: -0.0619 | AD60: -0.0857 | AE60: -0.0984 | AF60: -0.0026 | AG60: 0.0586 | AH60: 0.1591 | AI60: 0.0985 | AJ60: -0.0688 | AK60: -0.0729 | AL60: 0.0595 | AM60: 0.0663 | AN60: -0.0538 | AO60: 0.078 | AP60: 0.0865 | AQ60: -0.0071 | AR60: -0.0641 | AS60: 0.82 | AT60: 4.22 | AU60: 2.47
A61: WTI周涨跌 | C61: -0.0439 | D61: -0.0136 | E61: 0.0014 | F61: 0.0102 | G61: 0.0314 | H61: 0.0054 | I61: 0.0274 | J61: 0.0678 | K61: -0.0255 | L61: -0.0104 | M61: 0.0557 | N61: 0.0095 | O61: 0.3563 | P61: 0.0859 | Q61: -0.004 | R61: 0.0134 | S61: 0.1194 | T61: -0.1342 | U61: -0.1317 | V61: 0.1258 | W61: 0.0799 | X61: -0.064 | Y61: 0.1048 | Z61: -0.0837 | AA61: -0.0957 | AB61: 0.0364 | AC61: -0.0625 | AD61: -0.0975 | AE61: -0.0962 | AF61: -0.0078 | AG61: 0.0396 | AH61: 0.1552 | AI61: 0.0827 | AJ61: -0.052 | AK61: -0.0767 | AL61: 0.054 | AM61: 0.0566 | AN61: -0.042 | AO61: 0.0969 | AP61: 0.0937 | AQ61: 0.0025 | AR61: -0.0717 | AS61: -2.69 | AT61: 0.69 | AU61: 0.74
A62: 汽油周涨跌 | C62: -0.0134 | D62: -0.0136 | E62: -0.0207 | F62: -0.0106 | G62: -0.0036 | H62: -0.0071 | I62: 0.0108 | J62: 0.0142 | K62: 0.007 | L62: 0.0105 | M62: 0.0069 | N62: 0.0068 | O62: 0.0272 | P62: 0.1589 | Q62: 0.0629 | R62: 0.0645 | S62: 0.0076 | T62: 0.0326 | U62: 0 | V62: -0.0194 | W62: 0.0198 | X62: 0.0801 | Y62: 0.0112 | Z62: -0.0022 | AA62: -0.0045 | AB62: -0.038 | AC62: -0.0349 | AD62: -0.0241 | AE62: -0.0346 | AF62: -0.0205 | AG62: -0.0131 | AH62: 0.0185 | AI62: 0.039 | AJ62: 0.025 | AK62: -0.0049 | AL62: -0.0172 | AM62: 0.01 | AN62: 0.0074 | AO62: -0.0025 | AP62: 0.0221 | AQ62: 0 | AR62: 0
B64: 251201-1207 | C64: 251208-1214 | D64: 251215-1221 | E64: 251222-1228 | F64: 251229-0104 | G64: 260105-0111 | H64: 260112-0118 | I64: 260119-0125 | J64: 260126-0201 | K64: 260202-0208 | L64: 260209-0215 | M64: 260216-0222 | N64: 260223-0301 | O64: 260302-0308 | P64: 260309-0315 | Q64: 260316-0322 | R64: 260323-0329 | S64: 260330-0405 | T64: 260406-0412 | U64: 260413-0419 | V64: 260420-0426 | W64: 260427-0503 | X64: 260504-0510 | Y64: 260511-0517 | Z64: 260518-0524 | AA64: 260525-0531 | AB64: 260601-0607 | AC64: 260608-0614 | AD64: 260615-0621 | AE64: 260622-0628 | AF64: 260629-0705 | AG64: 260706-0712 | AH64: 260713-0719 | AI64: 260720-0726 | AJ64: 260727-0802 | AK64: 260803-0809 | AL64: 260810-0816 | AM64: 260817-0823 | AN64: 260824-0830 | AO64: 260831-0906 | AP64: 260907-0913 | AQ64: 260914-0920 | AR64: 260921-0927 | AS64: 260928-0930
A65: 2Y收益率(%) | B65: 3.56 | C65: 3.52 | D65: 3.48 | E65: 3.46 | F65: 3.47 | G65: 3.54 | H65: 3.59 | I65: 3.6 | J65: 3.52 | K65: 3.5 | L65: 3.4 | M65: 3.48 | N65: 3.38 | O65: 3.56 | P65: 3.73 | Q65: 3.88 | R65: 3.88 | S65: 3.84 | T65: 3.81 | U65: 3.71 | V65: 3.78 | W65: 3.88 | X65: 3.9 | Y65: 4.09 | Z65: 4.13 | AA65: 3.98 | AB65: 4.17 | AC65: 4.09 | AD65: 4.19 | AE65: 4.07 | AF65: 4.14 | AG65: 4.21 | AH65: 4.18 | AI65: 4.33 | AJ65: 4.28 | AK65: 4.19 | AL65: 4.17 | AM65: 4.24 | AN65: 4.34 | AO65: 4.37 | AP65: 4.63 | AQ65: 4.76 | AR65: 4.76
A66: 10Y收益率(%) | B66: 4.14 | C66: 4.19 | D66: 4.15 | E66: 4.14 | F66: 4.19 | G66: 4.17 | H66: 4.23 | I66: 4.24 | J66: 4.24 | K66: 4.21 | L66: 4.06 | M66: 4.09 | N66: 3.96 | O66: 4.13 | P66: 4.28 | Q66: 4.39 | R66: 4.44 | S66: 4.31 | T66: 4.32 | U66: 4.25 | V66: 4.31 | W66: 4.38 | X66: 4.36 | Y66: 4.59 | Z66: 4.56 | AA66: 4.45 | AB66: 4.54 | AC66: 4.49 | AD66: 4.45 | AE66: 4.37 | AF66: 4.49 | AG66: 4.57 | AH66: 4.54 | AI66: 4.68 | AJ66: 4.74 | AK66: 4.66 | AL66: 4.7 | AM66: 4.74 | AN66: 4.72 | AO66: 4.78 | AP66: 4.97 | AQ66: 5 | AR66: 4.96 | AS66: 5.29 | AT66: 5.28 | AU66: 5.24
A67: 30Y收益率(%) | B67: 4.79 | C67: 4.86 | D67: 4.83 | E67: 4.82 | F67: 4.86 | G67: 4.82 | H67: 4.84 | I67: 4.83 | J67: 4.87 | K67: 4.86 | L67: 4.7 | M67: 4.72 | N67: 4.63 | O67: 4.76 | P67: 4.91 | Q67: 4.96 | R67: 4.98 | S67: 4.89 | T67: 4.91 | U67: 4.89 | V67: 4.92 | W67: 4.97 | X67: 4.95 | Y67: 5.13 | Z67: 5.06 | AA67: 4.99 | AB67: 5 | AC67: 4.97 | AD67: 4.9 | AE67: 4.86 | AF67: 4.99 | AG67: 5.07 | AH67: 5.06 | AI67: 5.16 | AJ67: 5.28 | AK67: 5.21 | AL67: 5.26 | AM67: 5.28 | AN67: 5.21 | AO67: 5.25 | AP67: 5.35 | AQ67: 5.33 | AR67: 5.3 | AS67: 5.64 | AT67: 5.63 | AU67: 5.6
A68: 2Y收益率周变动(bps) | C68: -4 | D68: -4 | E68: -2 | F68: 1 | G68: 7 | H68: 5 | I68: 1 | J68: -8 | K68: -2 | L68: -10 | M68: 8 | N68: -10 | O68: 18 | P68: 17 | Q68: 15 | R68: 0 | S68: -4 | T68: -3 | U68: -10 | V68: 7 | W68: 10 | X68: 2 | Y68: 19 | Z68: 4 | AA68: -15 | AB68: 19 | AC68: -8 | AD68: 10 | AE68: -12 | AF68: 7 | AG68: 7 | AH68: -3 | AI68: 15 | AJ68: -5 | AK68: -9 | AL68: -2 | AM68: 7 | AN68: 10 | AO68: 3 | AP68: 26 | AQ68: 13 | AR68: 0
A69: 10Y收益率周变动(bps) | C69: 5 | D69: -4 | E69: -1 | F69: 5 | G69: -2 | H69: 6 | I69: 1 | J69: 0 | K69: -3 | L69: -15 | M69: 3 | N69: -13 | O69: 17 | P69: 15 | Q69: 11 | R69: 5 | S69: -13 | T69: 1 | U69: -7 | V69: 6 | W69: 7 | X69: -2 | Y69: 23 | Z69: -3 | AA69: -11 | AB69: 9 | AC69: -5 | AD69: -4 | AE69: -8 | AF69: 12 | AG69: 8 | AH69: -3 | AI69: 14 | AJ69: 6 | AK69: -8 | AL69: 4 | AM69: 4 | AN69: -2 | AO69: 6 | AP69: 19 | AQ69: 3 | AR69: -4 | AS69: 33 | AT69: -1 | AU69: -4
A70: 30Y收益率周变动(bps) | C70: 7 | D70: -3 | E70: -1 | F70: 4 | G70: -4 | H70: 2 | I70: -1 | J70: 4 | K70: -1 | L70: -16 | M70: 2 | N70: -9 | O70: 13 | P70: 15 | Q70: 5 | R70: 2 | S70: -9 | T70: 2 | U70: -2 | V70: 3 | W70: 5 | X70: -2 | Y70: 18 | Z70: -7 | AA70: -7 | AB70: 1 | AC70: -3 | AD70: -7 | AE70: -4 | AF70: 13 | AG70: 8 | AH70: -1 | AI70: 10 | AJ70: 12 | AK70: -7 | AL70: 5 | AM70: 2 | AN70: -7 | AO70: 4 | AP70: 10 | AQ70: -2 | AR70: -3 | AS70: 34 | AT70: -1 | AU70: -3
A72: 初请失业金(千人) | B72: 235 | C72: 224 | D72: 215 | E72: 203 | F72: 207 | G72: 201 | H72: 210 | I72: 211 | J72: 0 | K72: 230 | L72: 208 | M72: 211 | N72: 0 | O72: 213 | P72: 205 | Q72: 211 | R72: 203 | S72: 218 | T72: 208 | U72: 215 | V72: 190 | W72: 199 | X72: 212 | Y72: 210 | Z72: 212 | AA72: 225 | AB72: 230 | AC72: 227 | AD72: 216 | AE72: 217 | AF72: 217 | AG72: 209 | AH72: 189 | AI72: 198 | AJ72: 0 | AK72: 212 | AL72: 207 | AM72: 204 | AN72: 207 | AO72: 206 | AP72: 196 | AQ72: 196 | AR72: 196

Sheet 日度收盘价
A1: 日度收盘价（本地货币）
A2: Date | B2: NKE.N | C2: ADDY | D2: ZGN.N | E2: WWW.N | F2: UAA.N | G2: SHOO.O | H2: RL.N | I2: PUM.DF | J2: ONON.N | K2: NWL.O | L2: LULU.O | M2: LEVI.N | N2: KTB.N | O2: GIL.N | P2: GAP.N | Q2: DECK.N | R2: CROX.O | S2: COLM.O | T2: BZUN.O | U2: AS.N | V2: ANF.N | W2: 9983.T | X2: 8111.T | Y2: 7936.T | Z2: 3998.HK | AA2: 2331.HK | AB2: 2020.HK | AC2: 1836.HK | AD2: 1368.HK | AE2: 1361.HK | AF2: 002832.SZ | AG2: | | AH2: VFC | AI2: CFR | AJ2: 1913.HK | AK2: MONC | AL2: KER | AM2: SFER | AN2: RACE | AO2: RMS | AP2: MC | AQ2: BRBY | AR2: CPRI | AS2: PVH | AT2: TPR | AU2: GOOS | AV2: ZGN
A3: 46295 | W3: 69580 | X3: 2091 | Y3: 4178 | Z3: 3.925 | AA3: 12.38 | AB3: 73.3 | AC3: 12.01 | AD3: 3.495 | AE3: 4.515 | AF3: 25.58 | AJ3: 37.56
A4: 46294 | B4: 35.84 | C4: 145.75 | D4: 12.62 | E4: 19.24 | F4: 4.27 | G4: 45.14 | H4: 355.92 | I4: 22.53 | J4: 29.55 | K4: 5.32 | L4: 96.87 | M4: 19.75 | N4: 64.29 | O4: 42.79 | P4: 23.54 | Q4: 77.68 | R4: 122.63 | S4: 58.34 | T4: 3.05 | U4: 27.24 | V4: 133.59 | W4: 68710 | X4: 2099 | Y4: 4101 | Z4: 4.01 | AA4: 12.53 | AB4: 73.5 | AC4: 12.1 | AD4: 3.48 | AE4: 4.53 | AF4: 25.28 | AH4: 14.5 | AI4: 176.55 | AJ4: 38.04 | AK4: 44.5 | AL4: 223.55 | AM4: 7.48 | AN4: 402.05 | AO4: 1352.5 | AP4: 394.6 | AQ4: 1028.5 | AR4: 14.66 | AS4: 75.74 | AT4: 114.12 | AU4: 10.92 | AV4: 12.62
A5: 46293 | B5: 36.39 | C5: 147.85 | D5: 12.64 | E5: 19.13 | F5: 4.28 | G5: 44.9 | H5: 357.16 | I5: 22.87 | J5: 30 | K5: 5.44 | L5: 100.58 | M5: 19.81 | N5: 64.93 | O5: 42.62 | P5: 22.95 | Q5: 78.36 | R5: 122.36 | S5: 58.69 | T5: 3.09 | U5: 27.62 | V5: 134.18 | W5: 67850 | X5: 2173 | Y5: 4168 | Z5: 4.05 | AA5: 12.45 | AB5: 72 | AC5: 12.03 | AD5: 3.48 | AE5: 4.49 | AF5: 24.97 | AH5: 14.42 | AI5: 172.25 | AJ5: 38.9 | AK5: 44.7 | AL5: 228.2 | AM5: 7.59 | AN5: 398 | AO5: 1381.5 | AP5: 398.8 | AQ5: 1023.5 | AR5: 14.79 | AS5: 75.73 | AT5: 113.45 | AU5: 10.87 | AV5: 12.64
A6: 46290 | B6: 35.75 | C6: 146.5 | D6: 12.73 | E6: 19.07 | F6: 4.43 | G6: 45.06 | H6: 357.1 | I6: 22.36 | J6: 29.96 | K6: 5.43 | L6: 101.3 | M6: 19.73 | N6: 65.37 | O6: 40.98 | P6: 21.82 | Q6: 78.67 | R6: 126.14 | S6: 57.6 | T6: 2.94 | U6: 27.77 | V6: 135.71 | W6: 68620 | X6: 2182 | Y6: 4144 | Z6: 3.97 | AA6: 12.24 | AB6: 71.2 | AC6: 11.85 | AD6: 3.41 | AE6: 4.42 | AH6: 14.15 | AI6: 171.4 | AJ6: 38.68 | AK6: 43.56 | AL6: 223.35 | AM6: 7.41 | AN6: 411.33 | AO6: 1347.5 | AP6: 396.85 | AQ6: 1017 | AR6: 15.1 | AS6: 75.99 | AT6: 113.88 | AU6: 10.75 | AV6: 12.73
A7: 46289 | B7: 35.99 | C7: 142.25 | D7: 12.47 | E7: 19.3 | F7: 4.5 | G7: 44.23 | H7: 351.86 | I7: 22.14 | J7: 30.46 | K7: 5.59 | L7: 101.64 | M7: 19.72 | N7: 64.41 | O7: 40.63 | P7: 21.69 | Q7: 78.68 | R7: 123.44 | S7: 56.97 | T7: 2.94 | U7: 26.77 | V7: 134.3 | W7: 67920 | X7: 2164 | Y7: 4110 | Z7: 4.01 | AA7: 12.3 | AB7: 71.95 | AC7: 11.77 | AD7: 3.46 | AE7: 4.45 | AF7: 25.15 | AH7: 13.69 | AI7: 170.6 | AJ7: 38.22 | AK7: 43.61 | AL7: 225.75 | AM7: 7.62 | AN7: 411.82 | AO7: 1354.5 | AP7: 397.1 | AQ7: 1024.5 | AR7: 15.19 | AS7: 75.79 | AT7: 112.12 | AU7: 10.72 | AV7: 12.47
A8: 46288 | B8: 36.05 | C8: 144.45 | D8: 12.44 | E8: 19.11 | F8: 4.53 | G8: 43.4 | H8: 337.47 | I8: 22.3 | J8: 30.16 | K8: 5.68 | L8: 102.28 | M8: 19.63 | N8: 65.69 | O8: 46.19 | P8: 21.28 | Q8: 78.59 | R8: 124.62 | S8: 56.78 | T8: 3 | U8: 26.9 | V8: 132.25 | Z8: 4.01 | AA8: 12.38 | AB8: 71.8 | AC8: 11.7 | AD8: 3.48 | AE8: 4.5 | AF8: 25.45 | AH8: 13.52 | AI8: 170.4 | AJ8: 38.14 | AK8: 44.32 | AL8: 227.3 | AM8: 7.7 | AN8: 413.05 | AO8: 1349.5 | AP8: 396.9 | AQ8: 1035.5 | AR8: 15.43 | AS8: 75.39 | AT8: 110.51 | AU8: 10.61 | AV8: 12.44
A9: 46287 | B9: 36.1 | C9: 146.85 | D9: 12.51 | E9: 19.87 | F9: 4.74 | G9: 44.45 | H9: 346.06 | I9: 22.75 | J9: 29.39 | K9: 5.77 | L9: 103.73 | M9: 20.06 | N9: 67.82 | O9: 47.01 | P9: 21.46 | Q9: 79.83 | R9: 124.58 | S9: 58.43 | T9: 2.99 | U9: 27.65 | V9: 136.21 | Z9: 3.94 | AA9: 12.36 | AB9: 71.9 | AC9: 11.62 | AD9: 3.52 | AE9: 4.46 | AF9: 25.65 | AH9: 13.55 | AI9: 169.75 | AJ9: 37.38 | AK9: 43.81 | AL9: 232 | AM9: 7.62 | AN9: 413.32 | AO9: 1355 | AP9: 401.95 | AQ9: 1024 | AR9: 15.19 | AS9: 75.89 | AT9: 112.59 | AU9: 10.71 | AV9: 12.51
A10: 46286 | B10: 36.1 | C10: 143.15 | D10: 12.42 | E10: 19.48 | F10: 4.77 | G10: 42.83 | H10: 339.82 | I10: 22.31 | J10: 27.32 | K10: 5.6 | L10: 101.3 | M10: 19.82 | N10: 66.41 | O10: 46.16 | P10: 21.25 | Q10: 80.23 | R10: 123.69 | S10: 56.73 | T10: 2.94 | U10: 27.45 | V10: 136.76 | Z10: 4.06 | AA10: 12.81 | AB10: 72 | AC10: 11.6 | AD10: 3.6 | AE10: 4.45 | AF10: 25.82 | AH10: 13.05 | AI10: 169.15 | AJ10: 37.34 | AK10: 43.48 | AL10: 228.65 | AM10: 7.46 | AN10: 416.13 | AO10: 1344 | AP10: 405.5 | AQ10: 1025.5 | AR10: 14.31 | AS10: 73.4 | AT10: 113.07 | AU10: 10.53 | AV10: 12.42
A11: 46283 | B11: 35.51 | C11: 142.25 | D11: 12.29 | E11: 18.93 | F11: 4.88 | G11: 42.11 | H11: 335.1 | I11: 21.99 | J11: 27.26 | K11: 5.48 | L11: 98.06 | M11: 19.82 | N11: 66.36 | O11: 46.87 | P11: 20.54 | Q11: 78.43 | R11: 122.24 | S11: 56.84 | T11: 2.85 | U11: 26.73 | V11: 135.76 | W11: 67680 | X11: 2126.5 | Y11: 4066 | Z11: 4.1 | AA11: 12.57 | AB11: 71.7 | AC11: 11.49 | AD11: 3.5 | AE11: 4.33 | AF11: 25.63 | AH11: 12.79 | AI11: 168.85 | AJ11: 39.14 | AK11: 43.25 | AL11: 233 | AM11: 7.61 | AN11: 406.69 | AO11: 1331.5 | AP11: 402.8 | AQ11: 996 | AR11: 14.75 | AS11: 73.35 | AT11: 115 | AU11: 10.43 | AV11: 12.29
A12: 46282 | B12: 36.36 | C12: 142.4 | D12: 12.36 | E12: 19.34 | F12: 4.97 | G12: 41.8 | H12: 333.08 | I12: 22 | J12: 27.33 | K12: 5.61 | L12: 99.39 | M12: 19.85 | N12: 65.53 | O12: 46.27 | P12: 20.87 | Q12: 79.71 | R12: 123 | S12: 57.05 | T12: 2.78 | U12: 26.27 | V12: 138.6 | W12: 67700 | X12: 2169.5 | Y12: 4097 | Z12: 4.08 | AA12: 12.58 | AB12: 72 | AC12: 11.3 | AD12: 3.5 | AE12: 4.39 | AF12: 25.36 | AH12: 12.93 | AI12: 171.55 | AJ12: 39.02 | AK12: 43.99 | AL12: 239.6 | AM12: 8 | AN12: 414 | AO12: 1375 | AP12: 412.3 | AQ12: 1013.5 | AR12: 14.95 | AS12: 73.54 | AT12: 116.04 | AU12: 10.44 | AV12: 12.36
A13: 46281 | B13: 35.78 | C13: 144.65 | D13: 11.8 | E13: 19.29 | F13: 5 | G13: 41.51 | H13: 338.36 | I13: 22.36 | J13: 27.15 | K13: 5.69 | L13: 95.98 | M13: 19.65 | N13: 68.37 | O13: 46.32 | P13: 20.17 | Q13: 77.96 | R13: 115.4 | S13: 57.09 | T13: 2.76 | U13: 27.13 | V13: 139.89 | W13: 67030 | X13: 2129.5 | Y13: 4013 | Z13: 4.22 | AA13: 12.65 | AB13: 72.35 | AC13: 11.44 | AD13: 3.53 | AE13: 4.43 | AF13: 25 | AH13: 12.73 | AI13: 170.75 | AJ13: 38.72 | AK13: 43.75 | AL13: 238 | AM13: 8.33 | AN13: 412.34 | AO13: 1383 | AP13: 410.95 | AQ13: 1009 | AR13: 14.73 | AS13: 71.7 | AT13: 117.94 | AU13: 10.39 | AV13: 11.8
A14: 46280 | B14: 36.22 | C14: 141.9 | D14: 11.6 | E14: 19.12 | F14: 4.96 | G14: 40.46 | H14: 335.23 | I14: 21.81 | J14: 26.76 | K14: 5.64 | L14: 98.37 | M14: 19.82 | N14: 67 | O14: 45.89 | P14: 20.43 | Q14: 77.51 | R14: 111.48 | S14: 56.49 | T14: 2.73 | U14: 26.62 | V14: 135.17 | W14: 66620 | X14: 2141 | Y14: 4115 | Z14: 4.31 | AA14: 12.8 | AB14: 73.25 | AC14: 11.28 | AD14: 3.5 | AE14: 4.38 | AF14: 25.55 | AH14: 12.71 | AI14: 169.85 | AJ14: 39.14 | AK14: 43.46 | AL14: 234.35 | AM14: 8.05 | AN14: 406.92 | AO14: 1375 | AP14: 406.45 | AQ14: 977.6 | AR14: 14.05 | AS14: 71.61 | AT14: 117.11 | AU14: 10.32 | AV14: 11.6
A15: 46279 | B15: 37.05 | C15: 143.9 | D15: 11.63 | E15: 19.53 | F15: 5.03 | G15: 42.34 | H15: 341.43 | I15: 21.71 | J15: 27.47 | K15: 5.77 | L15: 100.3 | M15: 20.23 | N15: 67.42 | O15: 47.44 | P15: 20.92 | Q15: 80.54 | R15: 111.49 | S15: 57.67 | T15: 2.72 | U15: 27.55 | V15: 140.62 | W15: 66760 | X15: 2139 | Y15: 4071 | Z15: 4.37 | AA15: 12.93 | AB15: 73.65 | AC15: 11.35 | AD15: 3.42 | AE15: 4.4 | AF15: 25.35 | AH15: 13.07 | AI15: 173.05 | AJ15: 39.08 | AK15: 44.34 | AL15: 238 | AM15: 8.42 | AN15: 409.08 | AO15: 1414 | AP15: 417.45 | AQ15: 997.6 | AR15: 14.16 | AS15: 73.01 | AT15: 117.91 | AU15: 10.89 | AV15: 11.63
A16: 46276 | B16: 36.8 | C16: 142.75 | D16: 11.61 | E16: 19.93 | F16: 5.11 | G16: 42.93 | H16: 339.09 | I16: 21.69 | J16: 27.41 | K16: 5.85 | L16: 98.97 | M16: 20.16 | N16: 66.62 | O16: 48.45 | P16: 21.51 | Q16: 81.27 | R16: 112.48 | S16: 56.92 | T16: 2.73 | U16: 28.07 | V16: 145.23 | W16: 66480 | X16: 2090 | Y16: 3989 | Z16: 4.37 | AA16: 13.01 | AB16: 72.45 | AC16: 11.59 | AD16: 3.29 | AE16: 4.38 | AF16: 25.06 | AH16: 13.17 | AI16: 175 | AJ16: 38.5 | AK16: 44.69 | AL16: 238.6 | AM16: 8.58 | AN16: 413.78 | AO16: 1399.5 | AP16: 415.3 | AQ16: 1018 | AR16: 13.89 | AS16: 70.64 | AT16: 118.49 | AU16: 10.99 | AV16: 11.61
A17: 46275 | B17: 36.62 | C17: 142.7 | D17: 11.63 | E17: 19.29 | F17: 4.97 | G17: 41.56 | H17: 336.67 | I17: 22.22 | J17: 26.85 | K17: 5.87 | L17: 96.88 | M17: 20.12 | N17: 66.16 | O17: 48.93 | P17: 20.91 | Q17: 79.88 | R17: 108.83 | S17: 56.42 | T17: 2.74 | U17: 27.41 | V17: 142.93 | W17: 66810 | X17: 2081.5 | Y17: 4020 | Z17: 4.36 | AA17: 13.06 | AB17: 72.05 | AC17: 11.7 | AD17: 3.37 | AE17: 4.43 | AF17: 25.67 | AH17: 12.62 | AI17: 172.9 | AJ17: 38.5 | AK17: 43.6 | AL17: 234.15 | AM17: 8.57 | AN17: 408.64 | AO17: 1409 | AP17: 406.5 | AQ17: 1029.5 | AR17: 12.88 | AS17: 69.35 | AT17: 115.87 | AU17: 10.54 | AV17: 11.63
A18: 46274 | B18: 37.35 | C18: 146.45 | D18: 11.7 | E18: 19.59 | F18: 4.9 | G18: 43.46 | H18: 335.61 | I18: 22.75 | J18: 26.84 | K18: 6 | L18: 99.72 | M18: 20.35 | N18: 67.16 | O18: 50.45 | P18: 21.36 | Q18: 80.23 | R18: 111.09 | S18: 56.06 | T18: 2.75 | U18: 27.77 | V18: 152.08 | W18: 66860 | X18: 2095 | Y18: 4100 | Z18: 4.31 | AA18: 13.37 | AB18: 73.5 | AC18: 11.77 | AD18: 3.47 | AE18: 4.5 | AF18: 26.09 | AH18: 12.91 | AI18: 175.1 | AJ18: 39.68 | AK18: 45.16 | AL18: 232.25 | AM18: 8.74 | AN18: 402.33 | AO18: 1409 | AP18: 411.25 | AQ18: 1035 | AR18: 12.71 | AS18: 68.51 | AT18: 113.71 | AU18: 10.51 | AV18: 11.7
A19: 46273 | B19: 38.1 | C19: 147.85 | D19: 12.03 | E19: 20.05 | F19: 5.06 | G19: 43.16 | H19: 347.23 | I19: 23.13 | J19: 27.27 | K19: 6.34 | L19: 103.19 | M19: 20.85 | N19: 70.73 | O19: 51.55 | P19: 22.38 | Q19: 82.6 | R19: 114.35 | S19: 57.71 | T19: 2.81 | U19: 28.69 | V19: 151.43 | W19: 68730 | X19: 2107.5 | Y19: 4049 | Z19: 4.48 | AA19: 14.23 | AB19: 75.95 | AC19: 11.7 | AD19: 3.53 | AE19: 4.55 | AF19: 26.56 | AH19: 13.2 | AI19: 183.65 | AJ19: 40.1 | AK19: 45.96 | AL19: 244.4 | AM19: 9.05 | AN19: 405.94 | AO19: 1442.5 | AP19: 426.55 | AQ19: 1078 | AR19: 13.1 | AS19: 71.26 | AT19: 117.58 | AU19: 10.66 | AV19: 12.03
A20: 46272 | C20: 147.6 | I20: 23.53 | W20: 69160 | X20: 2104 | Y20: 4164 | Z20: 4.39 | AA20: 13.75 | AB20: 75.85 | AC20: 11.8 | AD20: 3.5 | AE20: 4.51 | AF20: 26.21 | AI20: 185.4 | AJ20: 39.96 | AK20: 46.18 | AL20: 241.4 | AM20: 9.09 | AO20: 1475 | AP20: 431.2 | AQ20: 1102
A21: 46269 | B21: 38.4 | C21: 149.15 | D21: 12.56 | E21: 20.76 | F21: 5.25 | G21: 43.68 | H21: 351.2 | I21: 23.83 | J21: 27.99 | K21: 6.11 | L21: 100.61 | M21: 21.06 | N21: 73.59 | O21: 53.4 | P21: 22.43 | Q21: 85.81 | R21: 117.53 | S21: 57.72 | T21: 2.87 | U21: 29.53 | V21: 149.67 | W21: 69100 | X21: 2113 | Y21: 4266 | Z21: 4.35 | AA21: 13.53 | AB21: 76.1 | AC21: 11.84 | AD21: 3.43 | AE21: 4.45 | AF21: 26.6 | AH21: 13.45 | AI21: 185.45 | AJ21: 39.34 | AK21: 45.84 | AL21: 245.2 | AM21: 9.11 | AN21: 409.95 | AO21: 1457 | AP21: 429.1 | AQ21: 1103.5 | AR21: 13.56 | AS21: 74.33 | AT21: 122.14 | AU21: 11.28 | AV21: 12.56
A22: 46268 | B22: 38.77 | C22: 148.7 | D22: 12.65 | E22: 19.55 | F22: 5.19 | G22: 42.3 | H22: 344.2 | I22: 24.26 | J22: 28.36 | K22: 6.07 | L22: 121.77 | M22: 20.7 | N22: 73.67 | O22: 53.68 | P22: 22.32 | Q22: 84.5 | R22: 116.01 | S22: 57.79 | T22: 2.79 | U22: 28.51 | V22: 143.54 | W22: 68000 | X22: 2098.5 | Y22: 4195 | Z22: 4.3 | AA22: 13.24 | AB22: 75.85 | AC22: 11.73 | AD22: 3.62 | AE22: 4.41 | AF22: 25.94 | AH22: 13.14 | AI22: 183.65 | AJ22: 39.56 | AK22: 46.17 | AL22: 244.6 | AM22: 9.09 | AN22: 417.93 | AO22: 1481.5 | AP22: 431.05 | AQ22: 1097 | AR22: 13.24 | AS22: 72.46 | AT22: 122.6 | AU22: 11.25 | AV22: 12.65
A23: 46267 | B23: 38.24 | C23: 149.55 | D23: 12.56 | E23: 19.28 | F23: 5.15 | G23: 41.99 | H23: 336.5 | I23: 24.62 | J23: 27.8 | K23: 5.98 | L23: 120.07 | M23: 20.46 | N23: 72.49 | O23: 51.46 | P23: 22.06 | Q23: 83.76 | R23: 115.79 | S23: 56.86 | T23: 2.82 | U23: 28.56 | V23: 136.6 | W23: 70400 | X23: 2091.5 | Y23: 4213 | Z23: 4.25 | AA23: 13.24 | AB23: 76.4 | AC23: 11.69 | AD23: 3.67 | AE23: 4.42 | AF23: 25.3 | AH23: 13.22 | AI23: 189.55 | AJ23: 40 | AK23: 46.56 | AL23: 249.65 | AM23: 9.32 | AN23: 413.23 | AO23: 1532 | AP23: 439 | AQ23: 1075.5 | AR23: 12.71 | AS23: 72.29 | AT23: 123.14 | AU23: 11.26 | AV23: 12.56
A24: 46266 | B24: 38.12 | C24: 147.95 | D24: 13.04 | E24: 19.33 | F24: 4.92 | G24: 41.44 | H24: 340.82 | I24: 24.52 | J24: 27.73 | K24: 5.94 | L24: 118 | M24: 20.36 | N24: 74.64 | O24: 50.27 | P24: 22 | Q24: 84.58 | R24: 115.28 | S24: 56.81 | T24: 2.74 | U24: 29.46 | V24: 140.68 | W24: 71260 | X24: 2127 | Y24: 4371 | Z24: 4.3 | AA24: 13.39 | AB24: 78.35 | AC24: 12.31 | AD24: 3.76 | AE24: 4.5 | AF24: 25.11 | AH24: 13.09 | AI24: 188.75 | AJ24: 40.32 | AK24: 46.15 | AL24: 247.2 | AM24: 9.41 | AN24: 410.21 | AO24: 1542.5 | AP24: 445 | AQ24: 1070 | AR24: 12.79 | AS24: 72.87 | AT24: 122.14 | AU24: 11.25 | AV24: 13.04
A25: 46265 | B25: 39.06 | C25: 151.4 | D25: 13.58 | E25: 19.73 | F25: 5.04 | G25: 43.18 | H25: 346.9 | I25: 25.42 | J25: 28.5 | K25: 6.25 | L25: 120.26 | M25: 20.76 | N25: 75.41 | O25: 52.13 | P25: 22.31 | Q25: 87.08 | R25: 120.38 | S25: 57.4 | T25: 2.84 | U25: 30.55 | V25: 143.08 | W25: 72450 | X25: 2149 | Y25: 4500 | Z25: 4.27 | AA25: 13.63 | AB25: 77.7 | AC25: 12.39 | AD25: 3.67 | AE25: 4.51 | AF25: 25.38 | AH25: 13.44 | AI25: 192.15 | AJ25: 41.02 | AK25: 47.11 | AL25: 254.05 | AM25: 9.57 | AN25: 422.6 | AO25: 1581 | AP25: 453.3 | AR25: 13.25 | AS25: 74.16 | AT25: 123.39 | AU25: 11.45 | AV25: 13.58
A26: 46262 | B26: 39.6 | C26: 154.2 | D26: 13.73 | E26: 20.34 | F26: 5.08 | G26: 44.24 | H26: 354.04 | I26: 25.63 | J26: 28.85 | K26: 6.17 | L26: 120.81 | M26: 21.29 | N26: 76.99 | O26: 53.12 | P26: 23.48 | Q26: 87.76 | R26: 122.23 | S26: 58.01 | T26: 3.02 | U26: 31.05 | V26: 148.42 | W26: 71260 | X26: 2190 | Y26: 4601 | Z26: 4.42 | AA26: 13.65 | AB26: 77.4 | AC26: 12.48 | AD26: 3.78 | AE26: 4.57 | AF26: 24.47 | AH26: 13.67 | AI26: 194.55 | AJ26: 41.64 | AK26: 47.72 | AL26: 254.2 | AM26: 9.49 | AN26: 420.54 | AO26: 1598 | AP26: 458.15 | AQ26: 1084 | AR26: 13.5 | AS26: 75.79 | AT26: 125.49 | AU26: 11.46 | AV26: 13.73
A27: 46261 | B27: 38.44 | C27: 153.1 | D27: 13.64 | E27: 19.76 | F27: 5.07 | G27: 44.69 | H27: 351.9 | I27: 26.02 | J27: 28.95 | K27: 5.88 | L27: 115 | M27: 21.05 | N27: 76.48 | O27: 53.23 | P27: 20.79 | Q27: 86.33 | R27: 121.69 | S27: 56.84 | T27: 3.02 | U27: 30.52 | V27: 145.75 | W27: 71540 | X27: 2170 | Y27: 4467 | Z27: 4.42 | AA27: 13.68 | AB27: 77.8 | AC27: 12.49 | AD27: 3.66 | AE27: 4.73 | AF27: 24.03 | AH27: 13.64 | AI27: 191.05 | AJ27: 40.96 | AK27: 47.1 | AL27: 250.55 | AM27: 9.25 | AN27: 414.04 | AO27: 1563 | AP27: 447.4 | AQ27: 1072 | AR27: 13.18 | AS27: 76.16 | AT27: 123.24 | AU27: 11.23 | AV27: 13.64
A28: 46260 | B28: 38.59 | C28: 150.7 | D28: 13.73 | E28: 20.1 | F28: 5.15 | G28: 45.11 | H28: 362.32 | I28: 25 | J28: 29.23 | K28: 5.96 | L28: 116.35 | M28: 21.43 | N28: 77.18 | O28: 53.58 | P28: 21.15 | Q28: 89.47 | R28: 123.64 | S28: 58.16 | T28: 2.82 | U28: 31.08 | V28: 147.75 | W28: 72120 | X28: 2166.5 | Y28: 4536 | Z28: 4.46 | AA28: 13.57 | AB28: 78.75 | AC28: 12.64 | AD28: 3.75 | AE28: 4.76 | AF28: 24.14 | AH28: 13.89 | AI28: 191 | AJ28: 40.86 | AK28: 47.59 | AL28: 252.75 | AM28: 9.52 | AN28: 412.83 | AO28: 1547.5 | AP28: 453.8 | AQ28: 1088 | AR28: 13.6 | AS28: 78.51 | AT28: 130.25 | AU28: 11.28 | AV28: 13.73
A29: 46259 | B29: 39.48 | C29: 152.6 | D29: 13.65 | E29: 20.47 | F29: 5.12 | G29: 45.5 | H29: 362.6 | I29: 25 | J29: 28.83 | K29: 5.93 | L29: 118.33 | M29: 21.1 | N29: 80.01 | O29: 54.59 | P29: 20.15 | Q29: 88.74 | R29: 122.89 | S29: 58.94 | T29: 2.83 | U29: 31.59 | V29: 108.9 | W29: 72530 | X29: 2185 | Y29: 4695 | Z29: 4.48 | AA29: 13.57 | AB29: 71.9 | AC29: 12.77 | AD29: 3.79 | AE29: 4.76 | AF29: 24.03 | AH29: 13.85 | AI29: 187.05 | AJ29: 40.9 | AK29: 47.18 | AL29: 247.2 | AM29: 9.37 | AN29: 421.85 | AO29: 1556.5 | AP29: 450.7 | AQ29: 1080 | AR29: 13.3 | AS29: 74.52 | AT29: 130.12 | AU29: 11.37 | AV29: 13.65
A30: 46258 | B30: 40.75 | C30: 155.25 | D30: 13.86 | E30: 20.87 | F30: 5.37 | G30: 45.91 | H30: 370.82 | I30: 25.29 | J30: 29.51 | K30: 6.07 | L30: 122.78 | M30: 21.72 | N30: 83.23 | O30: 54.95 | P30: 20.36 | Q30: 92.08 | R30: 125.84 | S30: 60.08 | T30: 2.82 | U30: 31.24 | V30: 112.36 | W30: 72840 | X30: 2172 | Y30: 4766 | Z30: 4.44 | AA30: 13.66 | AB30: 72.7 | AC30: 12.71 | AD30: 3.57 | AE30: 4.74 | AF30: 24.17 | AH30: 14.31 | AI30: 188.2 | AJ30: 40.78 | AK30: 48.25 | AL30: 255.75 | AM30: 9.32 | AN30: 424.44 | AO30: 1580.5 | AP30: 459.35 | AQ30: 1078 | AR30: 13.68 | AS30: 77.03 | AT30: 132.16 | AU30: 11.4 | AV30: 13.86
A31: 46255 | B31: 40.76 | C31: 154.45 | D31: 13.9 | E31: 20.96 | F31: 5.39 | G31: 46.08 | H31: 372.59 | I31: 25.02 | J31: 30.02 | K31: 6.09 | L31: 121.07 | M31: 21.49 | N31: 82.01 | O31: 56.17 | P31: 19.8 | Q31: 91.68 | R31: 122.11 | S31: 60.33 | T31: 2.84 | U31: 32.63 | V31: 109.01 | W31: 73510 | X31: 2139 | Y31: 4689 | Z31: 4.65 | AA31: 14.25 | AB31: 74.1 | AC31: 13.15 | AD31: 3.51 | AE31: 4.91 | AF31: 24.29 | AH31: 14.37 | AI31: 185.75 | AJ31: 41.1 | AK31: 47.1 | AL31: 254.3 | AM31: 9.27 | AN31: 436.54 | AO31: 1573 | AP31: 452.5 | AQ31: 1069.5 | AR31: 13.65 | AS31: 78.5 | AT31: 130.17 | AU31: 12.02 | AV31: 13.9
A32: 46254 | B32: 40.21 | C32: 151 | D32: 13.63 | E32: 20.45 | F32: 5.3 | G32: 45.71 | H32: 372.52 | I32: 25.06 | J32: 29.9 | K32: 5.79 | L32: 115.69 | M32: 21.23 | N32: 78.99 | O32: 55.45 | P32: 19.65 | Q32: 88.86 | R32: 123.09 | S32: 59.44 | T32: 2.8 | U32: 32.53 | V32: 105.02 | W32: 76280 | X32: 2138.5 | Y32: 4917 | Z32: 4.64 | AA32: 14.46 | AB32: 74.9 | AC32: 14.15 | AD32: 3.57 | AE32: 4.83 | AF32: 24.97 | AH32: 13.95 | AI32: 182.95 | AJ32: 41.24 | AK32: 46.94 | AL32: 250.6 | AM32: 9.12 | AN32: 428.37 | AO32: 1549.5 | AP32: 443.1 | AQ32: 1056.5 | AR32: 13.77 | AS32: 76.09 | AT32: 129.82 | AU32: 11.78 | AV32: 13.63
A33: 46253 | B33: 41.05 | C33: 155.9 | D33: 13.77 | E33: 20.85 | F33: 5.25 | G33: 47.34 | H33: 377.96 | I33: 25.53 | J33: 31.26 | K33: 6.16 | L33: 119.45 | M33: 22 | N33: 82.17 | O33: 57.03 | P33: 20.1 | Q33: 91.57 | R33: 125.73 | S33: 60.32 | T33: 2.82 | U33: 34.02 | V33: 105.45 | W33: 74940 | X33: 2100 | Y33: 4853 | Z33: 4.69 | AA33: 14.21 | AB33: 73.65 | AC33: 14.15 | AD33: 3.52 | AE33: 4.93 | AF33: 25.2 | AH33: 14.37 | AI33: 185.45 | AJ33: 40.9 | AK33: 47.67 | AL33: 260.05 | AM33: 9.34 | AN33: 425.18 | AO33: 1582.5 | AP33: 456 | AQ33: 1083 | AR33: 14.4 | AS33: 78.99 | AT33: 131.72 | AU33: 12.08 | AV33: 13.77
A34: 46252 | B34: 40.06 | C34: 154.7 | D34: 13.47 | E34: 19.99 | F34: 5.07 | G34: 46.75 | H34: 378.25 | I34: 25.83 | J34: 31.03 | K34: 5.93 | L34: 119.01 | M34: 22.01 | N34: 82.3 | O34: 55.76 | P34: 20.08 | Q34: 89.51 | R34: 128.66 | S34: 57.89 | T34: 2.73 | U34: 33.62 | V34: 103.38 | W34: 75010 | X34: 2119 | Y34: 4897 | Z34: 4.61 | AA34: 14.25 | AB34: 72.1 | AC34: 14.1 | AD34: 3.52 | AE34: 4.81 | AF34: 26.37 | AH34: 14.31 | AI34: 187.05 | AJ34: 41.54 | AK34: 47.17 | AL34: 255.7 | AM34: 9.48 | AN34: 412.44 | AO34: 1560.5 | AP34: 447.75 | AQ34: 1074.5 | AR34: 14.42 | AS34: 78.73 | AT34: 132.26 | AU34: 11.82 | AV34: 13.47
A35: 46251 | B35: 39.09 | C35: 152.6 | D35: 13.37 | E35: 19.83 | F35: 5.29 | G35: 46.6 | H35: 379.31 | I35: 25.63 | J35: 31.31 | K35: 6.04 | L35: 115.74 | M35: 22.57 | N35: 81.77 | O35: 55.89 | P35: 20.18 | Q35: 90.11 | R35: 129.97 | S35: 57.09 | T35: 2.78 | U35: 32.57 | V35: 105.16 | W35: 76820 | X35: 2098 | Y35: 5148 | Z35: 4.59 | AA35: 14.45 | AB35: 72.15 | AC35: 14.26 | AD35: 3.58 | AE35: 4.67 | AF35: 26.42 | AH35: 14.48 | AI35: 186.4 | AJ35: 41.28 | AK35: 47.06 | AL35: 257.1 | AM35: 9.39 | AN35: 417.1 | AO35: 1550 | AP35: 446 | AQ35: 1050 | AR35: 14.67 | AS35: 78.18 | AT35: 129.02 | AU35: 11.77 | AV35: 13.37

Sheet 运动服饰 Prices
A1: 运动服饰 收盘价（本地货币）
A2: Date | B2: NKE.N | C2: ADDY | D2: ZGN.N | E2: WWW.N | F2: VSCO.N | G2: UAA.N | H2: SKX.N | I2: SHOO.O | J2: RL.N | K2: PUM.DF | L2: ONON.N | M2: NWL.O | N2: LULU.O | O2: LEVI.N | P2: KTB.N | Q2: HBI.N | R2: GIL.N | S2: GAP.N | T2: DECK.N | U2: CROX.O | V2: COLM.O | W2: BZUN.O | X2: AS.N | Y2: ANF.N | Z2: 9983.T | AA2: 8111.T | AB2: 7936.T | AC2: 3998.HK | AD2: 2331.HK | AE2: 2020.HK | AF2: 1836.HK | AG2: 1368.HK | AH2: 1361.HK | AI2: 002832.SZ
A3: 45257 | B3: 106.19985 | C3: 188.34645 | D3: 11.330142 | E3: 8.4159317 | G3: 8.6000004 | I3: 36.319511 | J3: 128.09523 | K3: 57.084995 | L3: 30.26 | M3: 7.0632625 | N3: 466.60999 | O3: 14.565889 | P3: 49.593102 | R3: 35.420803 | S3: 19.247845 | T3: 114.17667 | U3: 106.56 | V3: 75.909065 | W3: 2.8099999 | Y3: 77.879997 | Z3: 35938.934 | AA3: 3566.5745 | AB3: 1273.1725 | AC3: 2.6982057 | AD3: 19.263432 | AE3: 72.140068 | AF3: 7.1965842 | AG3: 3.5060871 | AH3: 2.8189254 | AI3: 29.6479
A4: 45264 | B4: 108.47395 | C4: 187.49316 | D4: 11.43612 | E4: 8.2770538 | G4: 8.46 | I4: 36.693356 | J4: 126.30268 | K4: 53.636909 | L4: 28.629999 | M4: 7.3332529 | N4: 489.64001 | O4: 13.93541 | P4: 50.027584 | R4: 34.82951 | S4: 19.852201 | T4: 115.89667 | U4: 103.74 | V4: 76.251625 | W4: 2.9300001 | Y4: 78.650002 | Z4: 34049.961 | AA4: 3444.2302 | AB4: 1153.5847 | AC4: 2.7886946 | AD4: 18.909163 | AE4: 67.111305 | AF4: 7.3169036 | AG4: 3.5688367 | AH4: 2.7863364 | AI4: 29.39883
A5: 45271 | B5: 113.75213 | C5: 186.67865 | D5: 11.2627 | E5: 8.3140879 | G5: 8.6000004 | I5: 39.663448 | J5: 135.2079 | K5: 50.62941 | L5: 30.879999 | M5: 7.6206603 | N5: 491.45999 | O5: 14.278464 | P5: 54.265808 | R5: 32.883938 | S5: 19.513395 | T5: 117.135 | U5: 107.11 | V5: 77.564842 | W5: 2.97 | Y5: 84.169998 | Z5: 34466.504 | AA5: 3458.1682 | AB5: 1100.5966 | AC5: 2.8304417 | AD5: 16.827827 | AE5: 68.482788 | AF5: 7.4146628 | AG5: 3.4747128 | AH5: 2.7456007 | AI5: 29.238714
A6: 45278 | B6: 101.10883 | C6: 178.5529 | D6: 11.147086 | E6: 8.4437056 | G6: 8.9700003 | I6: 40.518341 | J6: 139.44481 | K6: 47.794319 | L6: 28.030001 | M6: 7.4551821 | N6: 510 | O6: 15.233454 | P6: 57.802273 | R6: 31.195871 | S6: 19.385199 | T6: 115.615 | U6: 98.18 | V6: 76.308723 | W6: 2.8199999 | Y6: 92.580002 | Z6: 34495.562 | AA6: 3119.0107 | AB6: 1089.4156 | AC6: 2.8805377 | AD6: 17.536366 | AE6: 67.614182 | AF6: 7.098825 | AG6: 3.4668696 | AH6: 2.6559815 | AI6: 28.020067
A7: 45285 | B7: 101.60485 | C7: 178.5723 | D7: 11.147086 | E7: 8.322217 | G7: 8.79 | I7: 39.456768 | J7: 138.94298 | K7: 48.388157 | L7: 26.969999 | M7: 7.5596943 | N7: 511.29001 | O7: 15.335443 | P7: 57.63607 | R7: 31.529673 | S7: 19.14712 | T7: 111.405 | U7: 93.410004 | V7: 75.690186 | W7: 2.74 | Y7: 88.220001 | Z7: 33894.969 | AA7: 3139.1431 | AB7: 1083.4667 | AC7: 2.930634 | AD7: 18.510609 | AE7: 69.259949 | AF7: 6.9258666 | AG7: 3.4590259 | AH7: 2.8270724 | AI7: 28.197969
A8: 45292 | B8: 95.531204 | C8: 168.21634 | D8: 10.53048 | E8: 7.2363014 | G8: 7.9000001 | I8: 38.460957 | J8: 137.70964 | K8: 44.987961 | L8: 26.57 | M8: 7.324542 | N8: 491.10001 | O8: 14.918216 | P8: 52.816128 | R8: 30.33753 | S8: 19.174788 | T8: 108.715 | U8: 86.459999 | V8: 71.722023 | W8: 2.4000001 | Y8: 90.540001 | Z8: 33420.301 | AA8: 2937.8169 | AB8: 1032.4572 | AC8: 2.8972366 | AD8: 16.686117 | AE8: 64.13974 | AF8: 7.3093834 | AG8: 2.9648793 | AH8: 2.7863364 | AI8: 27.993378
A9: 45299 | B9: 98.320007 | C9: 172.15315 | D9: 10.453404 | E9: 8.3690224 | G9: 7.9200001 | I9: 39.419186 | J9: 132.98831 | K9: 45.409393 | L9: 28.02 | M9: 7.3942175 | N9: 479.94 | O9: 14.742052 | P9: 53.120842 | R9: 29.994198 | S9: 18.667517 | T9: 117.78 | U9: 103.39 | V9: 73.644249 | W9: 2.24 | Y9: 96.790001 | Z9: 37721.352 | AA9: 3194.8953 | AB9: 1092.5408 | AC9: 2.930634 | AD9: 15.942149 | AE9: 67.522743 | AF9: 7.5199423 | AG9: 3.4119642 | AH9: 2.9411333 | AI9: 26.899263
A10: 45306 | B10: 95.250443 | C10: 159.68333 | D10: 9.9235086 | E10: 7.7137284 | G10: 7.5100002 | I10: 38.987045 | J10: 133.05573 | K10: 40.275574 | L10: 27.959999 | M10: 7.0981011 | N10: 484.01999 | O10: 14.463901 | P10: 54.108833 | R10: 30.614107 | S10: 17.468517 | T10: 124.875 | U10: 101.35 | V10: 74.605362 | W10: 2.0699999 | Y10: 101.11 | Z10: 37624.477 | AA10: 3119.0107 | AB10: 1143.3052 | AC10: 2.8805377 | AD10: 14.330223 | AE10: 60.116734 | AF10: 7.7004204 | AG10: 3.1452825 | AH10: 2.9085445 | AI10: 27.593094
A11: 45313 | B11: 96.158211 | C11: 172.46346 | D11: 10.925494 | E11: 8.0413761 | G11: 7.6799998 | I11: 40.27409 | J11: 138.8466 | K11: 36.51141 | L11: 26.25 | M11: 7.5684037 | N11: 478.03 | O11: 14.788411 | P11: 55.872444 | R11: 31.815783 | S11: 18.206364 | T11: 127.965 | U11: 102.96 | V11: 76.57518 | W11: 2.3599999 | Y11: 103.8 | Z11: 37653.539 | AA11: 3066.356 | AB11: 1107.0099 | AC11: 3.014128 | AD11: 15.162757 | AE11: 64.002609 | AF11: 7.8808985 | AG11: 3.1217513 | AH11: 2.981869 | AI11: 26.552347
A12: 45320 | B12: 94.249084 | C12: 169.70961 | D12: 12.640429 | E12: 8.0226526 | G12: 7.75 | I12: 39.823151 | J12: 142.38286 | K12: 36.837063 | L12: 27.700001 | M12: 7.2461596 | N12: 462.39999 | O12: 15.038747 | P12: 53.868767 | R12: 32.130512 | S12: 18.270924 | T12: 147.00999 | U12: 98.18 | V12: 77.422096 | W12: 2.1400001 | X12: 14.95 | Y12: 109.47 | Z12: 37605.105 | AA12: 3027.3296 | AB12: 1126.629 | AC12: 2.9723809 | AD12: 15.69416 | AE12: 60.893898 | AF12: 7.5124216 | AG12: 3.0433154 | AH12: 2.8270724 | AI12: 25.3248
A13: 45327 | B13: 97.795944 | C13: 166.52913 | D13: 12.052727 | E13: 8.2286034 | G13: 8.0900002 | I13: 39.221912 | J13: 168.62975 | K13: 38.838867 | L13: 29.5 | M13: 5.965889 | N13: 470.23999 | O13: 16.597235 | P13: 57.368294 | R13: 32.645512 | S13: 18.501505 | T13: 140.87 | U13: 107.54 | V13: 76.175499 | W13: 2.3499999 | X13: 14.94 | Y13: 110.11 | Z13: 38467.25 | AA13: 2808.6582 | AB13: 1172.2434 | AC13: 3.0809231 | AD13: 16.508982 | AE13: 64.596909 | AF13: 7.6703405 | AG13: 3.0433154 | AH13: 2.9981635 | AI13: 29.105288
A14: 45334 | B14: 96.869461 | C14: 170.89262 | D14: 12.495914 | E14: 8.6592236 | G14: 8.0699997 | I14: 41.20414 | J14: 174.25687 | K14: 40.428818 | L14: 31.74 | M14: 6.6800532 | N14: 449.60001 | O14: 16.681295 | P14: 58.199314 | R14: 32.941162 | S14: 18.224812 | T14: 143.83 | U14: 118.98 | V14: 77.165161 | W14: 2.5 | X14: 15.97 | Y14: 120.9 | Z14: 40763.082 | AA14: 2767.4636 | AB14: 1447.6471 | AC14: 3.2228625 | AD14: 18.820597 | AE14: 71.68293 | AF14: 8.0914574 | AG14: 3.3805897 | AH14: 3.1040766
A15: 45341 | B15: 98.853455 | C15: 183.05212 | D15: 13.680953 | E15: 9.2489882 | G15: 8.4300003 | I15: 41.711437 | J15: 181.57016 | K15: 40.524601 | L15: 32.200001 | M15: 6.3142619 | N15: 457.89001 | O15: 16.980177 | P15: 58.587132 | R15: 33.818573 | S15: 17.938894 | T15: 146.74667 | U15: 118.31 | V15: 78.725792 | W15: 2.4100001 | X15: 15.54 | Y15: 122.82 | Z15: 41915.84 | AA15: 2724.7205 | AB15: 1539.1213 | AC15: 3.2562604 | AD15: 18.510609 | AE15: 72.551514 | AF15: 7.8808985 | AG15: 3.3727465 | AH15: 3.3810813 | AI15: 27.2017
A16: 45348 | B16: 95.684669 | C16: 181.32613 | D16: 14.01816 | E16: 9.5017405 | G16: 8.8900003 | I16: 40.123768 | J16: 178.24593 | K16: 40.084011 | L16: 34.650002 | M16: 6.6386814 | N16: 458.5 | O16: 17.036215 | P16: 54.552048 | R16: 33.007919 | S16: 17.579193 | T16: 150.54834 | U16: 124.81 | V16: 77.269844 | W16: 2.3599999 | X16: 17.66 | Y16: 131.37 | Z16: 43154.984 | AA16: 2757.2424 | AB16: 1567.5691 | AC16: 3.3147056 | AD16: 17.757786 | AE16: 69.625687 | AF16: 8.0463381 | AG16: 3.4511824 | AH16: 3.4462581 | AI16: 27.441874
A17: 45355 | B17: 93.130089 | C17: 183.40118 | D17: 13.921815 | E17: 9.3613214 | G17: 8.4399996 | I17: 39.645504 | J17: 169.61255 | K17: 39.720047 | L17: 33.09 | M17: 6.9112625 | N17: 460.39001 | O17: 17.017536 | P17: 57.144482 | R17: 32.492916 | S17: 19.294689 | T17: 152.03334 | U17: 125.04 | V17: 77.072098 | W17: 2.4400001 | X17: 15.49 | Y17: 118.64 | Z17: 42240.727 | AA17: 2999.144 | AB17: 1560.7024 | AC17: 3.3481035 | AD17: 17.022673 | AE17: 68.437065 | AF17: 8.1816969 | AG17: 3.2786233 | AH17: 3.4951415 | AI17: 27.397398
A18: 45362 | B18: 93.580879 | C18: 198.77997 | D18: 14.201214 | E18: 9.5017405 | G18: 7.1500001 | I18: 39.305607 | J18: 174.97951 | K18: 40.026543 | L18: 33.23 | M18: 7.1926374 | N18: 464.94 | O18: 16.989517 | P18: 54.938023 | R18: 32.786671 | S18: 21.75725 | T18: 151.63333 | U18: 128.17 | V18: 76.155106 | W18: 2.8299999 | X18: 15.13 | Y18: 125.89 | Z18: 42814.57 | AA18: 3031.9758 | AB18: 1585.7167 | AC18: 3.4232476 | AD18: 18.333473 | AE18: 71.591476 | AF18: 8.9186506 | AG18: 3.710021 | AH18: 3.6417906 | AI18: 27.851055
A19: 45369 | B19: 88.152359 | C19: 194.1741 | D19: 14.085601 | E19: 9.8387489 | G19: 7.1500001 | I19: 38.842964 | J19: 180.76077 | K19: 37.545837 | L19: 34.709999 | M19: 6.7354035 | N19: 403.19 | O19: 17.428497 | P19: 53.383259 | R19: 35.9147 | S19: 25.898415 | T19: 153.74001 | U19: 141.62 | V19: 74.053741 | W19: 2.3 | X19: 16.27 | Y19: 134.97 | Z19: 46111.742 | AA19: 3097.3293 | AB19: 1712.5055 | AC19: 3.3731515 | AD19: 18.112053 | AE19: 72.688667 | AF19: 9.324728 | AG19: 3.8198311 | AH19: 3.6580846 | AI19: 26.481186
A20: 45376 | B20: 88.265076 | C20: 200.7193 | D20: 14.114504 | E20: 10.587907 | G20: 7.3800001 | I20: 39.919312 | J20: 181.6599 | K20: 40.246838 | L20: 35.380001 | M20: 7.0607419 | N20: 390.64999 | O20: 18.670719 | P20: 56.092449 | R20: 35.626846 | S20: 25.40959 | T20: 156.87666 | U20: 143.8 | V20: 77.540108 | W20: 2.3 | X20: 16.299999 | Y20: 125.33 | Z20: 45654.609 | AA20: 3103.0408 | AB20: 1790.2463 | AC20: 3.2646096 | AD20: 18.422041 | AE20: 76.071663 | AF20: 9.3848877 | AG20: 3.8041441 | AH20: 3.7477038 | AI20: 25.965261
A21: 45383 | B21: 83.437645 | C21: 195.48314 | D21: 11.522831 | E21: 9.152257 | G21: 6.8200002 | I21: 38.673012 | J21: 166.36353 | K21: 40.361774 | L21: 31.98 | M21: 6.357306 | N21: 356.87 | O21: 19.193766 | P21: 52.48951 | R21: 34.715305 | S21: 22.365973 | T21: 146.64833 | U21: 134.09 | V21: 72.086143 | W21: 2.3299999 | X21: 15.34 | Y21: 120.79 | Z21: 42950.738 | AA21: 3020.4646 | AB21: 1719.8625 | AC21: 3.3481035 | AD21: 18.377758 | AE21: 81.191879 | AF21: 9.8210449 | AG21: 3.764926 | AH21: 3.7395573 | AI21: 26.498976
A22: 45390 | B22: 86.405495 | C22: 190.44092 | D22: 10.89659 | E22: 8.6138887 | G22: 6.5599999 | I22: 36.907425 | J22: 155.08237 | K22: 38.685619 | L22: 32.869999 | M22: 6.2605834 | N22: 336.13 | O22: 17.96088 | P22: 50.236496 | R22: 34.149193 | S22: 20.885359 | T22: 135.72833 | U22: 125.54 | V22: 71.446167 | W22: 2.3699999 | X22: 14.19 | Y22: 111.83 | Z22: 41005.504 | AA22: 2935.6907 | AB22: 1757.8748 | AC22: 3.2980072 | AD22: 16.827827 | AE22: 77.854591 | AF22: 10.24216 | AG22: 3.7257082 | AH22: 3.7802927 | AI22: 25.867413
A23: 45397 | B23: 88.781624 | C23: 217.78528 | D23: 11.089279 | E23: 9.2372646 | G23: 6.73 | I23: 36.935745 | J23: 153.31183 | K23: 40.764053 | L23: 31.58 | M23: 6.0495524 | N23: 352.47 | O23: 19.193766 | P23: 52.554676 | R23: 33.774975 | S23: 19.270224 | T23: 133.39667 | U23: 120.54 | V23: 73.117699 | W23: 2.3199999 | X23: 13.77 | Y23: 110.36 | Z23: 39410.418 | AA23: 2822.6587 | AB23: 1626.917 | AC23: 3.6069348 | AD23: 14.8262 | AE23: 76.620262 | AF23: 10.512878 | AG23: 3.5688367 | AH23: 3.6336436 | AI23: 26.383337
A24: 45404 | B24: 88.396568 | C24: 223.89412 | D24: 11.590271 | E24: 10.295111 | G24: 6.8000002 | I24: 38.219814 | J24: 161.07127 | K24: 41.86552 | L24: 32.790001 | M24: 6.8497114 | N24: 364.70001 | O24: 19.735485 | P24: 57.907898 | R24: 33.870926 | S24: 19.817886 | T24: 138.91 | U24: 125.4 | V24: 76.413017 | W24: 2.75 | X24: 15.04 | Y24: 122.08 | Z24: 40256.586 | AA24: 2985.927 | AB24: 1645.3098 | AC24: 3.7906206 | AD24: 18.687746 | AE24: 82.289047 | AF24: 10.42264 | AG24: 3.9688594 | AH24: 3.8699117 | AI24: 26.418921
A25: 45411 | B25: 86.546364 | C25: 218.17316 | D25: 12.245417 | E25: 10.153434 | G25: 6.7399998 | I25: 37.379509 | J25: 161.22604 | K25: 42.880795 | L25: 33.27 | M25: 6.7354035 | N25: 355.14999 | O25: 20.548067 | P25: 61.119831 | R25: 31.759993 | S25: 20.040663 | T25: 140.39 | U25: 124.28 | V25: 77.377724 | W25: 2.75 | X25: 14.48 | Y25: 128.75999 | Z25: 39702.199 | AA25: 2936.0046 | AB25: 1658.0623 | AC25: 3.8741145 | AD25: 19.440567 | AE25: 85.534904 | AF25: 10.693357 | AG25: 4.133575 | AH25: 3.9781785 | AI25: 26.552347
A26: 45418 | B26: 85.409943 | C26: 217.59135 | D26: 11.869672 | E26: 12.741379 | G26: 6.71 | I26: 39.060123 | J26: 161.71944 | K26: 48.675495 | L26: 30.4 | M26: 7.1135006 | N26: 352.95999 | O26: 21.241714 | P26: 63.484554 | R26: 32.230156 | S26: 21.126701 | T26: 143.66499 | U26: 143.27 | V26: 80.300522 | W26: 2.74 | X26: 14.81 | Y26: 129.71001 | Z26: 39604.938 | AA26: 2923.7598 | AB26: 1777.9841 | AC26: 3.8240182 | AD26: 19.750553 | AE26: 84.300575 | AF26: 11.129514 | AG26: 4.3264098 | AH26: 3.9949646 | AI26: 26.410023
... A55: 45621 | B55: 74.60038 | C55: 216.99034 | D55: 7.8824754 | E55: 22.193701 | G55: 9.71 | I55: 43.445805 | J55: 225.88026 | K55: 43.141705 | L55: 58.330002 | M55: 8.6587152 | N55: 320.66 | O55: 16.638758 | P55: 86.633171 | R55: 48.317692 | S55: 22.82135 | T55: 195.96001 | U55: 105.6 | V55: 84.247803 | W55: 2.55 | X55: 26.33 | Y55: 149.69 | Z55: 49953.699 | AA55: 2805.0349 | AB55: 2957.7275 | AC55: 3.5580809 | AD55: 14.717245 | AE55: 72.329933 | AF55: 11.66186 | AG55: 4.7529244 | AH55: 3.500314 | AI55: 18.133163
A56: 45628 | B56: 79.09 | C56: 230.2 | D56: 8.2 | E56: 23.53 | F56: 41.92 | G56: 10.16 | I56: 46.18 | J56: 233.41 | K56: 43.16 | L56: 58.53 | M56: 9.76 | N56: 334.4 | O56: 18.18 | P56: 94.19 | R56: 50.11 | S56: 25.81 | T56: 201.9 | U56: 109.68 | V56: 88.1 | W56: 2.77 | X56: 26.13 | Y56: 157.31 | Z56: 50430 | AA56: 2945 | AB56: 3134 | AC56: 4.13 | AD56: 16.32 | AE56: 78.2 | AF56: 14.02 | AG56: 5.32 | AH56: 3.94 | AI56: 19.61
A57: 45635 | B57: 77.64 | C57: 238.6 | D57: 8.49 | E57: 22.59 | F57: 47.2 | G57: 10.18 | I57: 43.84 | J57: 228.13 | K57: 46.29 | L57: 55.02 | M57: 11.51 | N57: 404.79 | O57: 17.55 | P57: 87.87 | R57: 47.84 | S57: 25.41 | T57: 201.55 | U57: 110.59 | V57: 90.65 | W57: 2.9 | X57: 25.79 | Y57: 140.07 | Z57: 53670 | AA57: 2866.33 | AB57: 3053 | AC57: 4.02 | AD57: 17.44 | AE57: 83.75 | AF57: 14.8 | AG57: 5.59 | AH57: 4.26 | AI57: 19.15
A58: 45642 | B58: 77.2 | C58: 243 | D58: 8.87 | E58: 23.36 | F58: 45.89 | G58: 8.32 | I58: 43.82 | J58: 231.66 | K58: 45.14 | L58: 57.88 | M58: 10.84 | N58: 389.74 | O58: 17.11 | P58: 89.95 | R58: 48.64 | S58: 24.84 | T58: 211.12 | U58: 108.96 | V58: 89.85 | W58: 3.7 | X58: 27.65 | Y58: 146.85 | Z58: 52780 | AA58: 2749.33 | AB58: 3029 | AC58: 4 | AD58: 16.72 | AE58: 81.35 | AF58: 14.7 | AG58: 5.83 | AH58: 4.25 | AI58: 22.41
A59: 45649 | B59: 76.76 | C59: 234.9 | D59: 8.51 | E59: 22.72 | F59: 42.18 | G59: 8.43 | I59: 42.47 | J59: 230.41 | K59: 45.13 | L59: 56.65 | M59: 10.05 | N59: 383.49 | O59: 17.32 | P59: 86.57 | R59: 46.75 | S59: 24.01 | T59: 207.65 | U59: 113.27 | V59: 87.23 | W59: 3.06 | X59: 28.56 | Y59: 152.96 | Z59: 53180 | AA59: 2839 | AB59: 3100 | AC59: 4.13 | AD59: 16.56 | AE59: 80 | AF59: 15.96 | AG59: 5.69 | AH59: 4.23 | AI59: 20.55
A60: 45656 | B60: 74.65 | C60: 236.8 | D60: 8.25 | E60: 22.05 | F60: 41.89 | G60: 8.21 | I60: 42.23 | J60: 232.22 | K60: 44.36 | L60: 55.19 | M60: 10 | N60: 384.05 | O60: 17.34 | P60: 85.21 | R60: 46.28 | S60: 23.55 | T60: 205.76 | U60: 108.71 | V60: 83.47 | W60: 2.76 | X60: 28.4 | Y60: 154.65 | Z60: 53820 | AA60: 2948.33 | AB60: 3110 | AC60: 4.03 | AD60: 16.3 | AE60: 78 | AF60: 16.3 | AG60: 5.76 | AH60: 4.22 | AI60: 20.56
A61: 45663 | B61: 72 | C61: 239.5 | D61: 8 | E61: 22.35 | F61: 39.72 | G61: 8.47 | I61: 42.15 | J61: 242.96 | K61: 44.71 | L61: 54.62 | M61: 10.17 | N61: 395.31 | O61: 17.84 | P61: 86.8 | R61: 47.1 | S61: 24.08 | T61: 208.47 | U61: 112.07 | V61: 83.1 | W61: 2.97 | X61: 29.86 | Y61: 156.22 | Z61: 51550 | AA61: 2874.67 | AB61: 3059 | AC61: 3.64 | AD61: 15.8 | AE61: 75.15 | AF61: 16.08 | AG61: 5.49 | AH61: 4.08 | AI61: 19.58
A62: 45670 | B62: 72.08 | C62: 238.8 | D62: 7.63 | E62: 22.67 | F62: 35.82 | G62: 8.3 | I62: 40.26 | J62: 236.5 | K62: 41.52 | L62: 55.38 | M62: 9.71 | N62: 398.86 | O62: 17.42 | P62: 84.3 | R62: 47.97 | S62: 23.06 | T62: 204.59 | U62: 105.77 | V62: 83.2 | W62: 2.71 | X62: 29.1 | Y62: 135.72 | Z62: 48700 | AA62: 2845 | AB62: 3251 | AC62: 3.58 | AD62: 14.66 | AE62: 78 | AF62: 17.42 | AG62: 5.51 | AH62: 3.87 | AI62: 18.33
A63: 45677 | B63: 70.84 | C63: 243.3 | D63: 8.31 | E63: 22.79 | F63: 37.1 | G63: 8.2 | I63: 41.12 | J63: 240.46 | K63: 40.44 | L63: 57.98 | M63: 10.12 | N63: 373.7 | O63: 17.37 | P63: 85.98 | R63: 49.75 | S63: 23.46 | T63: 209.91 | U63: 99.97 | V63: 83.62 | W63: 2.88 | X63: 29.76 | Y63: 130.35 | Z63: 48500 | AA63: 2730.67 | AB63: 3300 | AC63: 3.68 | AD63: 15.56 | AE63: 81.05 | AF63: 17.48 | AG63: 5.74 | AH63: 4.05 | AI63: 19.34
A64: 45684 | B64: 75.58 | C64: 255.1 | D64: 9.52 | E64: 23.22 | F64: 37.34 | G64: 8.26 | I64: 41.23 | J64: 247.71 | K64: 31.75 | L64: 59.91 | M64: 10.59 | N64: 402.9 | O64: 18.24 | P64: 91.59 | R64: 51.14 | S64: 24.21 | T64: 211.9 | U64: 102.42 | V64: 89.58 | W64: 3.06 | X64: 30.44 | Y64: 119.53 | Z64: 50000 | AA64: 2701.33 | AB64: 3551 | AC64: 3.71 | AD64: 15.78 | AE64: 82.15 | AF64: 17.8 | AG64: 5.96 | AH64: 4.14 | AI64: 19.02
A65: 45691 | B65: 76.59 | C65: 253.5 | D65: 8.84 | E65: 21.89 | F65: 34.91 | G65: 8.25 | I65: 38.32 | J65: 246 | K65: 29.52 | L65: 58.52 | M65: 9.59 | N65: 410.29 | O65: 18.66 | P65: 86.51 | R65: 51.09 | S65: 23.11 | T65: 170.63 | U65: 96.74 | V65: 85.19 | W65: 3.1 | X65: 30.94 | Y65: 115.55 | Z65: 49200 | AA65: 2678 | AB65: 3371 | AC65: 3.69 | AD65: 15.56 | AE65: 82.35 | AF65: 18.06 | AG65: 5.95 | AH65: 4.1 | AI65: 19.02
A66: 45698 | B66: 70.94 | C66: 257.3 | D66: 8.78 | E66: 20.8 | F66: 32.8 | G66: 7.28 | I66: 37.73 | J66: 268.55 | K66: 29.15 | L66: 55.71 | M66: 7.01 | N66: 399.71 | O66: 18.21 | P66: 84.33 | R66: 50.69 | S66: 22.6 | T66: 161.65 | U66: 90.76 | V66: 78 | W66: 3.52 | X66: 30.61 | Y66: 113.19 | Z66: 48280 | AA66: 2593.67 | AB66: 3295 | AC66: 3.87 | AD66: 16.06 | AE66: 86.7 | AF66: 17.2 | AG66: 5.54 | AH66: 4.05 | AI66: 19.02
A67: 45705 | B67: 73.04 | C67: 259.8 | D67: 8.92 | E67: 18.53 | F67: 32.83 | G67: 7.1 | I67: 39.63 | J67: 282.63 | K67: 29.72 | L67: 52.03 | M67: 7.06 | N67: 366.68 | O67: 18.27 | P67: 83.73 | R67: 50.95 | S67: 22.78 | T67: 155.07 | U67: 108.43 | V67: 84.58 | W67: 3.75 | X67: 30.99 | Y67: 112.07 | Z67: 49800 | AA67: 2448 | AB67: 3803 | AC67: 3.85 | AD67: 16.42 | AE67: 85.15 | AF67: 17.46 | AG67: 5.45 | AH67: 3.97 | AI67: 18.73
... A151: 46290 | B151: 36.099998 | C151: 142.25 | D151: 12.42 | E151: 19.48 | F151: 80.06 | G151: 4.77 | I151: 42.830002 | J151: 339.82001 | K151: 21.99 | L151: 27.32 | M151: 5.5999999 | N151: 101.3 | O151: 19.82 | P151: 66.410004 | R151: 46.16 | S151: 21.25 | T151: 80.230003 | U151: 123.69 | V151: 56.73 | W151: 2.9349999 | X151: 27.450001 | Y151: 136.75999 | Z151: 67680 | AA151: 2126.5 | AB151: 4066 | AC151: 3.895 | AD151: 12.61 | AE151: 71.5 | AF151: 11.55 | AG151: 3.5599999 | AH151: 4.3899999 | AI151: 25.83
A152: 46297 | B152: 33.869999 | C152: 144.05 | D152: 12.52 | E152: 19.200001 | G152: 4.71 | I152: 45.970001 | J152: 363.37 | K152: 22.16 | L152: 30.85 | M152: 5.4000001 | N152: 94.459999 | O152: 19.870001 | P152: 64.709999 | R152: 41 | S152: 22.51 | T152: 79.120003 | U152: 118.09 | V152: 57.27 | W152: 3.155 | X152: 27.17 | Y152: 135.91 | Z152: 71770 | AA152: 2102 | AB152: 4141 | AC152: 3.97 | AD152: 12.28 | AE152: 74.150002 | AF152: 12.03 | AG152: 3.4649999 | AH152: 4.3699999 | AI152: 25.93
A153: 46304 | B153: 34.709999 | C153: 149.85001 | D153: 12.68 | E153: 19.43 | G153: 4.9299998 | I153: 44.299999 | J153: 371.28 | K153: 22.98 | L153: 35.09 | M153: 5.6399999 | N153: 94.5 | O153: 18.700001 | P153: 65.620003 | R153: 41.970001 | S153: 23.23 | T153: 82.889999 | U153: 114.98 | V153: 57.040001 | W153: 3.3099999 | X153: 28.139999 | Y153: 142.58 | Z153: 71780 | AA153: 2167 | AB153: 4474 | AC153: 4.4050002 | AD153: 12.76 | AE153: 72.650002 | AF153: 12.25 | AG153: 3.53 | AH153: 4.5599999 | AI153: 27.74
A154: 46311 | B154: 34.709999 | C154: 150.95 | D154: 12.68 | E154: 19.43 | G154: 4.9299998 | I154: 44.299999 | J154: 371.28 | K154: 23.040001 | L154: 35.09 | M154: 5.6399999 | N154: 94.5 | O154: 18.700001 | P154: 65.620003 | R154: 41.970001 | S154: 23.23 | T154: 82.889999 | U154: 114.98 | V154: 57.040001 | W154: 3.3099999 | X154: 28.139999 | Y154: 142.58 | Z154: 71780 | AA154: 2167 | AB154: 4474 | AC154: 4.3049998 | AD154: 12.65 | AE154: 71.449997 | AF154: 12.33 | AG154: 3.5450001 | AH154: 4.5799999 | AI154: 26.76

Sheet 运动服饰 Normalized
A1: 运动服饰 归一化（2025-12-01 = 1）
A2: Date | B2: NKE.N | C2: ADDY | D2: ZGN.N | E2: WWW.N | F2: VSCO.N | G2: UAA.N | H2: SKX.N | I2: SHOO.O | J2: RL.N | K2: PUM.DF | L2: ONON.N | M2: NWL.O | N2: LULU.O | O2: LEVI.N | P2: KTB.N | Q2: HBI.N | R2: GIL.N | S2: GAP.N | T2: DECK.N | U2: CROX.O | V2: COLM.O | W2: BZUN.O | X2: AS.N | Y2: ANF.N | Z2: 9983.T | AA2: 8111.T | AB2: 7936.T | AC2: 3998.HK | AD2: 2331.HK | AE2: 2020.HK | AF2: 1836.HK | AG2: 1368.HK | AH2: 1361.HK | AI2: 002832.SZ
A3: 45628 | B3: 1.209512 | C3: 1.428483 | D3: 0.777251 | E3: 1.382491 | G3: 2.218341 | I3: 1.075705 | J3: 0.637941 | K3: 2.084017 | L3: 1.309982 | M3: 2.56168 | N3: 1.833233 | O3: 0.815612 | P3: 1.253193 | R3: 0.869965 | S3: 0.938545 | T3: 2.194088 | U3: 1.266074 | V3: 1.592265 | W3: 0.958477 | X3: 0.705644 | Y3: 1.543768 | Z3: 0.90134 | AA3: 1.012898 | AB3: 0.846112 | AC3: 0.824351 | AD3: 0.933638 | AE3: 0.929845 | AF3: 0.853317 | AG3: 0.95 | AH3: 0.659967 | AI3: 1.249045
A4: 45635 | B4: 1.187338 | C4: 1.480608 | D4: 0.804739 | E4: 1.327262 | G4: 2.222707 | I4: 1.021197 | J4: 0.62351 | K4: 2.235152 | L4: 1.231423 | M4: 3.020997 | N4: 2.219122 | O4: 0.787349 | P4: 1.169106 | R4: 0.830556 | S4: 0.924 | T4: 2.190285 | U4: 1.276579 | V4: 1.638352 | W4: 1.00346 | X4: 0.696462 | Y4: 1.374583 | Z4: 0.959249 | AA4: 0.98584 | AB4: 0.824244 | AC4: 0.802395 | AD4: 0.997712 | AE4: 0.995838 | AF4: 0.900791 | AG4: 0.998214 | AH4: 0.713568 | AI4: 1.219745
A5: 45642 | B5: 1.180609 | C5: 1.507912 | D5: 0.840758 | E5: 1.372503 | G5: 1.816594 | I5: 1.020731 | J5: 0.633158 | K5: 2.179623 | L5: 1.295434 | M5: 2.845144 | N5: 2.136615 | O5: 0.767609 | P5: 1.19678 | R5: 0.844444 | S5: 0.903273 | T5: 2.294284 | U5: 1.257763 | V5: 1.623893 | W5: 1.280277 | X5: 0.746692 | Y5: 1.441119 | Z5: 0.943342 | AA5: 0.945599 | AB5: 0.817765 | AC5: 0.798403 | AD5: 0.956522 | AE5: 0.967301 | AF5: 0.894705 | AG5: 1.041071 | AH5: 0.711893 | AI5: 1.427389
A6: 45649 | B6: 1.17388 | C6: 1.457648 | D6: 0.806635 | E6: 1.3349 | G6: 1.840611 | I6: 0.989285 | J6: 0.629742 | K6: 2.179141 | L6: 1.267905 | M6: 2.637795 | N6: 2.102352 | O6: 0.77703 | P6: 1.151809 | R6: 0.811632 | S6: 0.873091 | T6: 2.256575 | U6: 1.307515 | V6: 1.576541 | W6: 1.058823 | X6: 0.771267 | Y6: 1.501079 | Z6: 0.950492 | AA6: 0.97644 | AB6: 0.836933 | AC6: 0.824351 | AD6: 0.947368 | AE6: 0.951249 | AF6: 0.971394 | AG6: 1.016071 | AH6: 0.708543 | AI6: 1.308917
A7: 45656 | B7: 1.141612 | C7: 1.469438 | D7: 0.781991 | E7: 1.295535 | G7: 1.792576 | I7: 0.983694 | J7: 0.634689 | K7: 2.141961 | L7: 1.235228 | M7: 2.624672 | N7: 2.105422 | O7: 0.777927 | P7: 1.133715 | R7: 0.803472 | S7: 0.856364 | T7: 2.236036 | U7: 1.254877 | V7: 1.508585 | W7: 0.955017 | X7: 0.766946 | Y7: 1.517664 | Z7: 0.96193 | AA7: 1.014043 | AB7: 0.839633 | AC7: 0.804391 | AD7: 0.932494 | AE7: 0.927467 | AF7: 0.992088 | AG7: 1.028571 | AH7: 0.706868 | AI7: 1.309554
A8: 45663 | B8: 1.101086 | C8: 1.486193 | D8: 0.758294 | E8: 1.313161 | G8: 1.849345 | I8: 0.981831 | J8: 0.664043 | K8: 2.158861 | L8: 1.222471 | M8: 2.669291 | N8: 2.167151 | O8: 0.800359 | P8: 1.15487 | R8: 0.817708 | S8: 0.875636 | T8: 2.265486 | U8: 1.293663 | V8: 1.501898 | W8: 1.027682 | X8: 0.806373 | Y8: 1.533072 | Z8: 0.921358 | AA8: 0.988709 | AB8: 0.825864 | AC8: 0.726547 | AD8: 0.90389 | AE8: 0.893579 | AF8: 0.978697 | AG8: 0.980357 | AH8: 0.683417 | AI8: 1.247134
A9: 45670 | B9: 1.102309 | C9: 1.481849 | D9: 0.723223 | E9: 1.331962 | G9: 1.812227 | I9: 0.937806 | J9: 0.646387 | K9: 2.004829 | L9: 1.239481 | M9: 2.548556 | N9: 2.186613 | O9: 0.781516 | P9: 1.121607 | R9: 0.832813 | S9: 0.838545 | T9: 2.223321 | U9: 1.22094 | V9: 1.503705 | W9: 0.937716 | X9: 0.785849 | Y9: 1.331894 | Z9: 0.87042 | AA9: 0.978504 | AB9: 0.8777 | AC9: 0.714571 | AD9: 0.838673 | AE9: 0.927467 | AF9: 1.060256 | AG9: 0.983929 | AH9: 0.648241 | AI9: 1.167516
A10: 45677 | B10: 1.083346 | C10: 1.509774 | D10: 0.787678 | E10: 1.339013 | G10: 1.790393 | I10: 0.957838 | J10: 0.65721 | K10: 1.95268 | L10: 1.297672 | M10: 2.656168 | N10: 2.048682 | O10: 0.779273 | P10: 1.143959 | R10: 0.863715 | S10: 0.853091 | T10: 2.281135 | U10: 1.153988 | V10: 1.511296 | W10: 0.99654 | X10: 0.803673 | Y10: 1.279195 | Z10: 0.866845 | AA10: 0.939181 | AB10: 0.890929 | AC10: 0.734531 | AD10: 0.89016 | AE10: 0.963734 | AF10: 1.063907 | AG10: 1.025 | AH10: 0.678392 | AI10: 1.231847
A11: 45684 | B11: 1.155834 | C11: 1.582997 | D11: 0.90237 | E11: 1.364277 | G11: 1.803493 | I11: 0.960401 | J11: 0.677025 | K11: 1.533076 | L11: 1.340868 | M11: 2.779528 | N11: 2.20876 | O11: 0.818304 | P11: 1.2186 | R11: 0.887847 | S11: 0.880364 | T11: 2.30276 | U11: 1.182269 | V11: 1.619013 | W11: 1.058823 | X11: 0.822036 | Y11: 1.173013 | Z11: 0.893655 | AA11: 0.92909 | AB11: 0.958693 | AC11: 0.740519 | AD11: 0.902746 | AE11: 0.976813 | AF11: 1.083384 | AG11: 1.064286 | AH11: 0.693467 | AI11: 1.211465
A12: 45691 | B12: 1.17128 | C12: 1.573069 | D12: 0.837915 | E12: 1.286134 | G12: 1.80131 | I12: 0.892616 | J12: 0.672352 | K12: 1.425398 | L12: 1.309758 | M12: 2.51706 | N12: 2.249274 | O12: 0.837147 | P12: 1.151011 | R12: 0.886979 | S12: 0.840364 | T12: 1.854271 | U12: 1.116703 | V12: 1.539671 | W12: 1.072664 | X12: 0.835539 | Y12: 1.133955 | Z12: 0.879357 | AA12: 0.921066 | AB12: 0.910097 | AC12: 0.736527 | AD12: 0.89016 | AE12: 0.979191 | AF12: 1.099209 | AG12: 1.0625 | AH12: 0.686767 | AI12: 1.211465
A13: 45698 | B13: 1.084875 | C13: 1.596649 | D13: 0.832227 | E13: 1.222092 | G13: 1.58952 | I13: 0.878873 | J13: 0.733984 | K13: 1.407533 | L13: 1.246867 | M13: 1.839895 | N13: 2.191272 | O13: 0.816958 | P13: 1.122006 | R13: 0.880035 | S13: 0.821818 | T13: 1.756683 | U13: 1.047674 | V13: 1.409723 | W13: 1.217993 | X13: 0.826627 | Y13: 1.110795 | Z13: 0.862913 | AA13: 0.892062 | AB13: 0.889579 | AC13: 0.772455 | AD13: 0.918764 | AE13: 1.030916 | AF13: 1.046865 | AG13: 0.989286 | AH13: 0.678392 | AI13: 1.211465
A14: 45705 | B14: 1.11699 | C14: 1.612163 | D14: 0.845498 | E14: 1.088719 | G14: 1.550218 | I14: 0.923131 | J14: 0.772466 | K14: 1.435056 | L14: 1.164503 | M14: 1.853018 | N14: 2.010197 | O14: 0.81965 | P14: 1.114023 | R14: 0.884549 | S14: 0.828364 | T14: 1.685177 | U14: 1.251645 | V14: 1.528646 | W14: 1.297578 | X14: 0.836889 | Y14: 1.099804 | Z14: 0.89008 | AA14: 0.84196 | AB14: 1.026728 | AC14: 0.768463 | AD14: 0.939359 | AE14: 1.012485 | AF14: 1.06269 | AG14: 0.973214 | AH14: 0.664992 | AI14: 1.192994
... A54: 45985 | B54: 0.947087 | C54: 0.945393 | D54: 0.978199 | E54: 0.905993 | G54: 0.960699 | I54: 0.94689 | J54: 0.956543 | K54: 0.751811 | L54: 0.912936 | M54: 0.908136 | N54: 0.930157 | O54: 0.930911 | P54: 0.939329 | R54: 0.9875 | S54: 0.9 | T54: 0.903391 | U54: 0.927277 | V54: 0.945418 | W54: 1.010381 | X54: 0.973535 | Y54: 0.643867 | Z54: 0.979446 | AA54: 0.983835 | AB54: 1.010799 | AC54: 1.01996 | AD54: 1.013158 | AE54: 0.994055 | AF54: 0.978697 | AG54: 0.998214 | AH54: 0.998325 | AI54: 0.995541
A55: 45992 | B55: =IF(OR('运动服饰 Prices'!B3="",'运动服饰 Prices'!B$3=""),"",'运动服饰 Prices'!B3/'运动服饰 Prices'!B$3) | C55: =IF(OR('运动服饰 Prices'!C3="",'运动服饰 Prices'!C$3=""),"",'运动服饰 Prices'!C3/'运动服饰 Prices'!C$3) | D55: =IF(OR('运动服饰 Prices'!D3="",'运动服饰 Prices'!D$3=""),"",'运动服饰 Prices'!D3/'运动服饰 Prices'!D$3) | E55: =IF(OR('运动服饰 Prices'!E3="",'运动服饰 Prices'!E$3=""),"",'运动服饰 Prices'!E3/'运动服饰 Prices'!E$3) | F55: =IF(OR('运动服饰 Prices'!F3="",'运动服饰 Prices'!F$3=""),"",'运动服饰 Prices'!F3/'运动服饰 Prices'!F$3) | G55: =IF(OR('运动服饰 Prices'!G3="",'运动服饰 Prices'!G$3=""),"",'运动服饰 Prices'!G3/'运动服饰 Prices'!G$3) | H55: =IF(OR('运动服饰 Prices'!H3="",'运动服饰 Prices'!H$3=""),"",'运动服饰 Prices'!H3/'运动服饰 Prices'!H$3) | I55: =IF(OR('运动服饰 Prices'!I3="",'运动服饰 Prices'!I$3=""),"",'运动服饰 Prices'!I3/'运动服饰 Prices'!I$3) | ... AI55: =IF(OR('运动服饰 Prices'!AI3="",'运动服饰 Prices'!AI$3=""),"",'运动服饰 Prices'!AI3/'运动服饰 Prices'!AI$3)
A56: 45996 | B56: =IF(OR('运动服饰 Prices'!B4="",'运动服饰 Prices'!B$3=""),"",'运动服饰 Prices'!B4/'运动服饰 Prices'!B$3) | C56: =IF(OR('运动服饰 Prices'!C4="",'运动服饰 Prices'!C$3=""),"",'运动服饰 Prices'!C4/'运动服饰 Prices'!C$3) | D56: =IF(OR('运动服饰 Prices'!D4="",'运动服饰 Prices'!D$3=""),"",'运动服饰 Prices'!D4/'运动服饰 Prices'!D$3) | E56: =IF(OR('运动服饰 Prices'!E4="",'运动服饰 Prices'!E$3=""),"",'运动服饰 Prices'!E4/'运动服饰 Prices'!E$3) | F56: =IF(OR('运动服饰 Prices'!F4="",'运动服饰 Prices'!F$3=""),"",'运动服饰 Prices'!F4/'运动服饰 Prices'!F$3) | G56: =IF(OR('运动服饰 Prices'!G4="",'运动服饰 Prices'!G$3=""),"",'运动服饰 Prices'!G4/'运动服饰 Prices'!G$3) | H56: =IF(OR('运动服饰 Prices'!H4="",'运动服饰 Prices'!H$3=""),"",'运动服饰 Prices'!H4/'运动服饰 Prices'!H$3) | I56: =IF(OR('运动服饰 Prices'!I4="",'运动服饰 Prices'!I$3=""),"",'运动服饰 Prices'!I4/'运动服饰 Prices'!I$3) | ... AI56: =IF(OR('运动服饰 Prices'!AI4="",'运动服饰 Prices'!AI$3=""),"",'运动服饰 Prices'!AI4/'运动服饰 Prices'!AI$3)
A57: 46003 | B57: =IF(OR('运动服饰 Prices'!B5="",'运动服饰 Prices'!B$3=""),"",'运动服饰 Prices'!B5/'运动服饰 Prices'!B$3) | C57: =IF(OR('运动服饰 Prices'!C5="",'运动服饰 Prices'!C$3=""),"",'运动服饰 Prices'!C5/'运动服饰 Prices'!C$3) | D57: =IF(OR('运动服饰 Prices'!D5="",'运动服饰 Prices'!D$3=""),"",'运动服饰 Prices'!D5/'运动服饰 Prices'!D$3) | E57: =IF(OR('运动服饰 Prices'!E5="",'运动服饰 Prices'!E$3=""),"",'运动服饰 Prices'!E5/'运动服饰 Prices'!E$3) | F57: =IF(OR('运动服饰 Prices'!F5="",'运动服饰 Prices'!F$3=""),"",'运动服饰 Prices'!F5/'运动服饰 Prices'!F$3) | G57: =IF(OR('运动服饰 Prices'!G5="",'运动服饰 Prices'!G$3=""),"",'运动服饰 Prices'!G5/'运动服饰 Prices'!G$3) | H57: =IF(OR('运动服饰 Prices'!H5="",'运动服饰 Prices'!H$3=""),"",'运动服饰 Prices'!H5/'运动服饰 Prices'!H$3) | I57: =IF(OR('运动服饰 Prices'!I5="",'运动服饰 Prices'!I$3=""),"",'运动服饰 Prices'!I5/'运动服饰 Prices'!I$3) | ... AI57: =IF(OR('运动服饰 Prices'!AI5="",'运动服饰 Prices'!AI$3=""),"",'运动服饰 Prices'!AI5/'运动服饰 Prices'!AI$3)
A58: 46010 | B58: =IF(OR('运动服饰 Prices'!B6="",'运动服饰 Prices'!B$3=""),"",'运动服饰 Prices'!B6/'运动服饰 Prices'!B$3) | C58: =IF(OR('运动服饰 Prices'!C6="",'运动服饰 Prices'!C$3=""),"",'运动服饰 Prices'!C6/'运动服饰 Prices'!C$3) | D58: =IF(OR('运动服饰 Prices'!D6="",'运动服饰 Prices'!D$3=""),"",'运动服饰 Prices'!D6/'运动服饰 Prices'!D$3) | E58: =IF(OR('运动服饰 Prices'!E6="",'运动服饰 Prices'!E$3=""),"",'运动服饰 Prices'!E6/'运动服饰 Prices'!E$3) | F58: =IF(OR('运动服饰 Prices'!F6="",'运动服饰 Prices'!F$3=""),"",'运动服饰 Prices'!F6/'运动服饰 Prices'!F$3) | G58: =IF(OR('运动服饰 Prices'!G6="",'运动服饰 Prices'!G$3=""),"",'运动服饰 Prices'!G6/'运动服饰 Prices'!G$3) | H58: =IF(OR('运动服饰 Prices'!H6="",'运动服饰 Prices'!H$3=""),"",'运动服饰 Prices'!H6/'运动服饰 Prices'!H$3) | I58: =IF(OR('运动服饰 Prices'!I6="",'运动服饰 Prices'!I$3=""),"",'运动服饰 Prices'!I6/'运动服饰 Prices'!I$3) | ... AI58: =IF(OR('运动服饰 Prices'!AI6="",'运动服饰 Prices'!AI$3=""),"",'运动服饰 Prices'!AI6/'运动服饰 Prices'!AI$3)
A59: 46017 | B59: =IF(OR('运动服饰 Prices'!B7="",'运动服饰 Prices'!B$3=""),"",'运动服饰 Prices'!B7/'运动服饰 Prices'!B$3) | C59: =IF(OR('运动服饰 Prices'!C7="",'运动服饰 Prices'!C$3=""),"",'运动服饰 Prices'!C7/'运动服饰 Prices'!C$3) | D59: =IF(OR('运动服饰 Prices'!D7="",'运动服饰 Prices'!D$3=""),"",'运动服饰 Prices'!D7/'运动服饰 Prices'!D$3) | E59: =IF(OR('运动服饰 Prices'!E7="",'运动服饰 Prices'!E$3=""),"",'运动服饰 Prices'!E7/'运动服饰 Prices'!E$3) | F59: =IF(OR('运动服饰 Prices'!F7="",'运动服饰 Prices'!F$3=""),"",'运动服饰 Prices'!F7/'运动服饰 Prices'!F$3) | G59: =IF(OR('运动服饰 Prices'!G7="",'运动服饰 Prices'!G$3=""),"",'运动服饰 Prices'!G7/'运动服饰 Prices'!G$3) | H59: =IF(OR('运动服饰 Prices'!H7="",'运动服饰 Prices'!H$3=""),"",'运动服饰 Prices'!H7/'运动服饰 Prices'!H$3) | I59: =IF(OR('运动服饰 Prices'!I7="",'运动服饰 Prices'!I$3=""),"",'运动服饰 Prices'!I7/'运动服饰 Prices'!I$3) | ... AI59: =IF(OR('运动服饰 Prices'!AI7="",'运动服饰 Prices'!AI$3=""),"",'运动服饰 Prices'!AI7/'运动服饰 Prices'!AI$3)
A60: 46024 | B60: =IF(OR('运动服饰 Prices'!B8="",'运动服饰 Prices'!B$3=""),"",'运动服饰 Prices'!B8/'运动服饰 Prices'!B$3) | C60: =IF(OR('运动服饰 Prices'!C8="",'运动服饰 Prices'!C$3=""),"",'运动服饰 Prices'!C8/'运动服饰 Prices'!C$3) | D60: =IF(OR('运动服饰 Prices'!D8="",'运动服饰 Prices'!D$3=""),"",'运动服饰 Prices'!D8/'运动服饰 Prices'!D$3) | E60: =IF(OR('运动服饰 Prices'!E8="",'运动服饰 Prices'!E$3=""),"",'运动服饰 Prices'!E8/'运动服饰 Prices'!E$3) | F60: =IF(OR('运动服饰 Prices'!F8="",'运动服饰 Prices'!F$3=""),"",'运动服饰 Prices'!F8/'运动服饰 Prices'!F$3) | G60: =IF(OR('运动服饰 Prices'!G8="",'运动服饰 Prices'!G$3=""),"",'运动服饰 Prices'!G8/'运动服饰 Prices'!G$3) | H60: =IF(OR('运动服饰 Prices'!H8="",'运动服饰 Prices'!H$3=""),"",'运动服饰 Prices'!H8/'运动服饰 Prices'!H$3) | I60: =IF(OR('运动服饰 Prices'!I8="",'运动服饰 Prices'!I$3=""),"",'运动服饰 Prices'!I8/'运动服饰 Prices'!I$3) | ... AI60: =IF(OR('运动服饰 Prices'!AI8="",'运动服饰 Prices'!AI$3=""),"",'运动服饰 Prices'!AI8/'运动服饰 Prices'!AI$3)
A61: 46031 | B61: =IF(OR('运动服饰 Prices'!B9="",'运动服饰 Prices'!B$3=""),"",'运动服饰 Prices'!B9/'运动服饰 Prices'!B$3) | C61: =IF(OR('运动服饰 Prices'!C9="",'运动服饰 Prices'!C$3=""),"",'运动服饰 Prices'!C9/'运动服饰 Prices'!C$3) | D61: =IF(OR('运动服饰 Prices'!D9="",'运动服饰 Prices'!D$3=""),"",'运动服饰 Prices'!D9/'运动服饰 Prices'!D$3) | E61: =IF(OR('运动服饰 Prices'!E9="",'运动服饰 Prices'!E$3=""),"",'运动服饰 Prices'!E9/'运动服饰 Prices'!E$3) | F61: =IF(OR('运动服饰 Prices'!F9="",'运动服饰 Prices'!F$3=""),"",'运动服饰 Prices'!F9/'运动服饰 Prices'!F$3) | G61: =IF(OR('运动服饰 Prices'!G9="",'运动服饰 Prices'!G$3=""),"",'运动服饰 Prices'!G9/'运动服饰 Prices'!G$3) | H61: =IF(OR('运动服饰 Prices'!H9="",'运动服饰 Prices'!H$3=""),"",'运动服饰 Prices'!H9/'运动服饰 Prices'!H$3) | I61: =IF(OR('运动服饰 Prices'!I9="",'运动服饰 Prices'!I$3=""),"",'运动服饰 Prices'!I9/'运动服饰 Prices'!I$3) | ... AI61: =IF(OR('运动服饰 Prices'!AI9="",'运动服饰 Prices'!AI$3=""),"",'运动服饰 Prices'!AI9/'运动服饰 Prices'!AI$3)
A62: 46038 | B62: =IF(OR('运动服饰 Prices'!B10="",'运动服饰 Prices'!B$3=""),"",'运动服饰 Prices'!B10/'运动服饰 Prices'!B$3) | C62: =IF(OR('运动服饰 Prices'!C10="",'运动服饰 Prices'!C$3=""),"",'运动服饰 Prices'!C10/'运动服饰 Prices'!C$3) | D62: =IF(OR('运动服饰 Prices'!D10="",'运动服饰 Prices'!D$3=""),"",'运动服饰 Prices'!D10/'运动服饰 Prices'!D$3) | E62: =IF(OR('运动服饰 Prices'!E10="",'运动服饰 Prices'!E$3=""),"",'运动服饰 Prices'!E10/'运动服饰 Prices'!E$3) | F62: =IF(OR('运动服饰 Prices'!F10="",'运动服饰 Prices'!F$3=""),"",'运动服饰 Prices'!F10/'运动服饰 Prices'!F$3) | G62: =IF(OR('运动服饰 Prices'!G10="",'运动服饰 Prices'!G$3=""),"",'运动服饰 Prices'!G10/'运动服饰 Prices'!G$3) | H62: =IF(OR('运动服饰 Prices'!H10="",'运动服饰 Prices'!H$3=""),"",'运动服饰 Prices'!H10/'运动服饰 Prices'!H$3) | I62: =IF(OR('运动服饰 Prices'!I10="",'运动服饰 Prices'!I$3=""),"",'运动服饰 Prices'!I10/'运动服饰 Prices'!I$3) | ... AI62: =IF(OR('运动服饰 Prices'!AI10="",'运动服饰 Prices'!AI$3=""),"",'运动服饰 Prices'!AI10/'运动服饰 Prices'!AI$3)
A63: 46045 | B63: =IF(OR('运动服饰 Prices'!B11="",'运动服饰 Prices'!B$3=""),"",'运动服饰 Prices'!B11/'运动服饰 Prices'!B$3) | C63: =IF(OR('运动服饰 Prices'!C11="",'运动服饰 Prices'!C$3=""),"",'运动服饰 Prices'!C11/'运动服饰 Prices'!C$3) | D63: =IF(OR('运动服饰 Prices'!D11="",'运动服饰 Prices'!D$3=""),"",'运动服饰 Prices'!D11/'运动服饰 Prices'!D$3) | E63: =IF(OR('运动服饰 Prices'!E11="",'运动服饰 Prices'!E$3=""),"",'运动服饰 Prices'!E11/'运动服饰 Prices'!E$3) | F63: =IF(OR('运动服饰 Prices'!F11="",'运动服饰 Prices'!F$3=""),"",'运动服饰 Prices'!F11/'运动服饰 Prices'!F$3) | G63: =IF(OR('运动服饰 Prices'!G11="",'运动服饰 Prices'!G$3=""),"",'运动服饰 Prices'!G11/'运动服饰 Prices'!G$3) | H63: =IF(OR('运动服饰 Prices'!H11="",'运动服饰 Prices'!H$3=""),"",'运动服饰 Prices'!H11/'运动服饰 Prices'!H$3) | I63: =IF(OR('运动服饰 Prices'!I11="",'运动服饰 Prices'!I$3=""),"",'运动服饰 Prices'!I11/'运动服饰 Prices'!I$3) | ... AI63: =IF(OR('运动服饰 Prices'!AI11="",'运动服饰 Prices'!AI$3=""),"",'运动服饰 Prices'!AI11/'运动服饰 Prices'!AI$3)
A64: 46052 | B64: =IF(OR('运动服饰 Prices'!B12="",'运动服饰 Prices'!B$3=""),"",'运动服饰 Prices'!B12/'运动服饰 Prices'!B$3) | C64: =IF(OR('运动服饰 Prices'!C12="",'运动服饰 Prices'!C$3=""),"",'运动服饰 Prices'!C12/'运动服饰 Prices'!C$3) | D64: =IF(OR('运动服饰 Prices'!D12="",'运动服饰 Prices'!D$3=""),"",'运动服饰 Prices'!D12/'运动服饰 Prices'!D$3) | E64: =IF(OR('运动服饰 Prices'!E12="",'运动服饰 Prices'!E$3=""),"",'运动服饰 Prices'!E12/'运动服饰 Prices'!E$3) | F64: =IF(OR('运动服饰 Prices'!F12="",'运动服饰 Prices'!F$3=""),"",'运动服饰 Prices'!F12/'运动服饰 Prices'!F$3) | G64: =IF(OR('运动服饰 Prices'!G12="",'运动服饰 Prices'!G$3=""),"",'运动服饰 Prices'!G12/'运动服饰 Prices'!G$3) | H64: =IF(OR('运动服饰 Prices'!H12="",'运动服饰 Prices'!H$3=""),"",'运动服饰 Prices'!H12/'运动服饰 Prices'!H$3) | I64: =IF(OR('运动服饰 Prices'!I12="",'运动服饰 Prices'!I$3=""),"",'运动服饰 Prices'!I12/'运动服饰 Prices'!I$3) | ... AI64: =IF(OR('运动服饰 Prices'!AI12="",'运动服饰 Prices'!AI$3=""),"",'运动服饰 Prices'!AI12/'运动服饰 Prices'!AI$3)
A65: 46059 | B65: =IF(OR('运动服饰 Prices'!B13="",'运动服饰 Prices'!B$3=""),"",'运动服饰 Prices'!B13/'运动服饰 Prices'!B$3) | C65: =IF(OR('运动服饰 Prices'!C13="",'运动服饰 Prices'!C$3=""),"",'运动服饰 Prices'!C13/'运动服饰 Prices'!C$3) | D65: =IF(OR('运动服饰 Prices'!D13="",'运动服饰 Prices'!D$3=""),"",'运动服饰 Prices'!D13/'运动服饰 Prices'!D$3) | E65: =IF(OR('运动服饰 Prices'!E13="",'运动服饰 Prices'!E$3=""),"",'运动服饰 Prices'!E13/'运动服饰 Prices'!E$3) | F65: =IF(OR('运动服饰 Prices'!F13="",'运动服饰 Prices'!F$3=""),"",'运动服饰 Prices'!F13/'运动服饰 Prices'!F$3) | G65: =IF(OR('运动服饰 Prices'!G13="",'运动服饰 Prices'!G$3=""),"",'运动服饰 Prices'!G13/'运动服饰 Prices'!G$3) | H65: =IF(OR('运动服饰 Prices'!H13="",'运动服饰 Prices'!H$3=""),"",'运动服饰 Prices'!H13/'运动服饰 Prices'!H$3) | I65: =IF(OR('运动服饰 Prices'!I13="",'运动服饰 Prices'!I$3=""),"",'运动服饰 Prices'!I13/'运动服饰 Prices'!I$3) | ... AI65: =IF(OR('运动服饰 Prices'!AI13="",'运动服饰 Prices'!AI$3=""),"",'运动服饰 Prices'!AI13/'运动服饰 Prices'!AI$3)
A66: 46066 | B66: =IF(OR('运动服饰 Prices'!B14="",'运动服饰 Prices'!B$3=""),"",'运动服饰 Prices'!B14/'运动服饰 Prices'!B$3) | C66: =IF(OR('运动服饰 Prices'!C14="",'运动服饰 Prices'!C$3=""),"",'运动服饰 Prices'!C14/'运动服饰 Prices'!C$3) | D66: =IF(OR('运动服饰 Prices'!D14="",'运动服饰 Prices'!D$3=""),"",'运动服饰 Prices'!D14/'运动服饰 Prices'!D$3) | E66: =IF(OR('运动服饰 Prices'!E14="",'运动服饰 Prices'!E$3=""),"",'运动服饰 Prices'!E14/'运动服饰 Prices'!E$3) | F66: =IF(OR('运动服饰 Prices'!F14="",'运动服饰 Prices'!F$3=""),"",'运动服饰 Prices'!F14/'运动服饰 Prices'!F$3) | G66: =IF(OR('运动服饰 Prices'!G14="",'运动服饰 Prices'!G$3=""),"",'运动服饰 Prices'!G14/'运动服饰 Prices'!G$3) | H66: =IF(OR('运动服饰 Prices'!H14="",'运动服饰 Prices'!H$3=""),"",'运动服饰 Prices'!H14/'运动服饰 Prices'!H$3) | I66: =IF(OR('运动服饰 Prices'!I14="",'运动服饰 Prices'!I$3=""),"",'运动服饰 Prices'!I14/'运动服饰 Prices'!I$3) | ... AI66: =IF(OR('运动服饰 Prices'!AI14="",'运动服饰 Prices'!AI$3=""),"",'运动服饰 Prices'!AI14/'运动服饰 Prices'!AI$3)
... A98: 46290 | B98: =IF(OR('运动服饰 Prices'!B46="",'运动服饰 Prices'!B$3=""),"",'运动服饰 Prices'!B46/'运动服饰 Prices'!B$3) | C98: =IF(OR('运动服饰 Prices'!C46="",'运动服饰 Prices'!C$3=""),"",'运动服饰 Prices'!C46/'运动服饰 Prices'!C$3) | D98: =IF(OR('运动服饰 Prices'!D46="",'运动服饰 Prices'!D$3=""),"",'运动服饰 Prices'!D46/'运动服饰 Prices'!D$3) | E98: =IF(OR('运动服饰 Prices'!E46="",'运动服饰 Prices'!E$3=""),"",'运动服饰 Prices'!E46/'运动服饰 Prices'!E$3) | F98: =IF(OR('运动服饰 Prices'!F46="",'运动服饰 Prices'!F$3=""),"",'运动服饰 Prices'!F46/'运动服饰 Prices'!F$3) | G98: =IF(OR('运动服饰 Prices'!G46="",'运动服饰 Prices'!G$3=""),"",'运动服饰 Prices'!G46/'运动服饰 Prices'!G$3) | H98: =IF(OR('运动服饰 Prices'!H46="",'运动服饰 Prices'!H$3=""),"",'运动服饰 Prices'!H46/'运动服饰 Prices'!H$3) | I98: =IF(OR('运动服饰 Prices'!I46="",'运动服饰 Prices'!I$3=""),"",'运动服饰 Prices'!I46/'运动服饰 Prices'!I$3) | ... AI98: =IF(OR('运动服饰 Prices'!AI46="",'运动服饰 Prices'!AI$3=""),"",'运动服饰 Prices'!AI46/'运动服饰 Prices'!AI$3)
A99: 46297 | B99: =IF(OR('运动服饰 Prices'!B99="",'运动服饰 Prices'!B$3=""),"",'运动服饰 Prices'!B99/'运动服饰 Prices'!B$3) | C99: =IF(OR('运动服饰 Prices'!C99="",'运动服饰 Prices'!C$3=""),"",'运动服饰 Prices'!C99/'运动服饰 Prices'!C$3) | D99: =IF(OR('运动服饰 Prices'!D99="",'运动服饰 Prices'!D$3=""),"",'运动服饰 Prices'!D99/'运动服饰 Prices'!D$3) | E99: =IF(OR('运动服饰 Prices'!E99="",'运动服饰 Prices'!E$3=""),"",'运动服饰 Prices'!E99/'运动服饰 Prices'!E$3) | F99: =IF(OR('运动服饰 Prices'!F99="",'运动服饰 Prices'!F$3=""),"",'运动服饰 Prices'!F99/'运动服饰 Prices'!F$3) | G99: =IF(OR('运动服饰 Prices'!G99="",'运动服饰 Prices'!G$3=""),"",'运动服饰 Prices'!G99/'运动服饰 Prices'!G$3) | H99: =IF(OR('运动服饰 Prices'!H99="",'运动服饰 Prices'!H$3=""),"",'运动服饰 Prices'!H99/'运动服饰 Prices'!H$3) | I99: =IF(OR('运动服饰 Prices'!I99="",'运动服饰 Prices'!I$3=""),"",'运动服饰 Prices'!I99/'运动服饰 Prices'!I$3) | ... AI99: =IF(OR('运动服饰 Prices'!AI99="",'运动服饰 Prices'!AI$3=""),"",'运动服饰 Prices'!AI99/'运动服饰 Prices'!AI$3)
A100: 46304 | B100: =IF(OR('运动服饰 Prices'!B100="",'运动服饰 Prices'!B$3=""),"",'运动服饰 Prices'!B100/'运动服饰 Prices'!B$3) | C100: =IF(OR('运动服饰 Prices'!C100="",'运动服饰 Prices'!C$3=""),"",'运动服饰 Prices'!C100/'运动服饰 Prices'!C$3) | D100: =IF(OR('运动服饰 Prices'!D100="",'运动服饰 Prices'!D$3=""),"",'运动服饰 Prices'!D100/'运动服饰 Prices'!D$3) | E100: =IF(OR('运动服饰 Prices'!E100="",'运动服饰 Prices'!E$3=""),"",'运动服饰 Prices'!E100/'运动服饰 Prices'!E$3) | F100: =IF(OR('运动服饰 Prices'!F100="",'运动服饰 Prices'!F$3=""),"",'运动服饰 Prices'!F100/'运动服饰 Prices'!F$3) | G100: =IF(OR('运动服饰 Prices'!G100="",'运动服饰 Prices'!G$3=""),"",'运动服饰 Prices'!G100/'运动服饰 Prices'!G$3) | H100: =IF(OR('运动服饰 Prices'!H100="",'运动服饰 Prices'!H$3=""),"",'运动服饰 Prices'!H100/'运动服饰 Prices'!H$3) | I100: =IF(OR('运动服饰 Prices'!I100="",'运动服饰 Prices'!I$3=""),"",'运动服饰 Prices'!I100/'运动服饰 Prices'!I$3) | ... AI100: =IF(OR('运动服饰 Prices'!AI100="",'运动服饰 Prices'!AI$3=""),"",'运动服饰 Prices'!AI100/'运动服饰 Prices'!AI$3)
A101: 46311 | B101: =IF(OR('运动服饰 Prices'!B101="",'运动服饰 Prices'!B$3=""),"",'运动服饰 Prices'!B101/'运动服饰 Prices'!B$3) | C101: =IF(OR('运动服饰 Prices'!C101="",'运动服饰 Prices'!C$3=""),"",'运动服饰 Prices'!C101/'运动服饰 Prices'!C$3) | D101: =IF(OR('运动服饰 Prices'!D101="",'运动服饰 Prices'!D$3=""),"",'运动服饰 Prices'!D101/'运动服饰 Prices'!D$3) | E101: =IF(OR('运动服饰 Prices'!E101="",'运动服饰 Prices'!E$3=""),"",'运动服饰 Prices'!E101/'运动服饰 Prices'!E$3) | F101: =IF(OR('运动服饰 Prices'!F101="",'运动服饰 Prices'!F$3=""),"",'运动服饰 Prices'!F101/'运动服饰 Prices'!F$3) | G101: =IF(OR('运动服饰 Prices'!G101="",'运动服饰 Prices'!G$3=""),"",'运动服饰 Prices'!G101/'运动服饰 Prices'!G$3) | H101: =IF(OR('运动服饰 Prices'!H101="",'运动服饰 Prices'!H$3=""),"",'运动服饰 Prices'!H101/'运动服饰 Prices'!H$3) | I101: =IF(OR('运动服饰 Prices'!I101="",'运动服饰 Prices'!I$3=""),"",'运动服饰 Prices'!I101/'运动服饰 Prices'!I$3) | ... AI101: =IF(OR('运动服饰 Prices'!AI101="",'运动服饰 Prices'!AI$3=""),"",'运动服饰 Prices'!AI101/'运动服饰 Prices'!AI$3)

Sheet 运动服饰 Tickers
A1: 代码 | B1: Yahoo | C1: Bloomberg | D1: 区域 | E1: 状态 | F1: 备注
A2: NKE.N | B2: NKE | C2: NKE US | D2: US/EU | E2: OK | F2: Nike
A3: ADDY | B3: ADS.DE | C3: ADS GY | D3: US/EU | E3: OK | F3: Adidas 德国本地股 EUR
A4: ZGN.N | B4: ZGN | C4: ZGN US | D4: US/EU | E4: OK | F4: Zegna
A5: WWW.N | B5: WWW | C5: WWW US | D5: US/EU | E5: OK | F5: Wolverine
A6: VSCO.N | B6: VSCO | C6: - | D6: US/EU | E6: 无数据 | F6: 疑似退市
A7: UAA.N | B7: UAA | C7: UAA US | D7: US/EU | E7: OK | F7: Under Armour
A8: SKX.N | B8: - | C8: - | D8: US/EU | E8: 无数据 | F8: 私有化退市
A9: SHOO.O | B9: SHOO | C9: SHOO US | D9: US/EU | E9: OK | F9: Steven Madden
A10: RL.N | B10: RL | C10: RL US | D10: US/EU | E10: OK | F10: Ralph Lauren
A11: PUM.DF | B11: PUM.DE | C11: PUM GY | D11: US/EU | E11: OK | F11: Puma EUR
A12: ONON.N | B12: ONON | C12: ONON US | D12: US/EU | E12: OK | F12: On Holding
... A35: 002832.SZ | B35: 002832.SZ | C35: 002832 CH | D35: China/HK | E35: OK | F35: 比音勒芬

Sheet 奢侈品 Prices
A1: 奢侈品 收盘价（本地货币）
A2: Date | B2: VFC | C2: CFR | D2: 1913.HK | E2: MONC | F2: KER | G2: SFER | H2: RACE | I2: RMS | J2: MC | K2: BRBY | L2: CPRI | M2: PVH | N2: TPR | O2: GOOS | P2: ZGN
A3: 45257 | B3: 16.923746 | C3: 102.59559 | D3: 38.812771 | E3: 47.296864 | F3: 360.00696 | G3: 11.579132 | H3: 347.89508 | I3: 1855.4807 | J3: 654.18011 | K3: 1497.6511 | L3: 48.419998 | M3: 99.089859 | N3: 30.620216 | O3: 15.81 | P3: 11.330142
A4: 45264 | B4: 17.054863 | C4: 108.00764 | D4: 40.367111 | E4: 50.07793 | F4: 379.15726 | G4: 11.955207 | H4: 357.40643 | I4: 1920.5854 | J4: 696.99371 | K4: 1517.6399 | L4: 48.439999 | M4: 107.74878 | N4: 31.739126 | O4: 15.93 | P4: 11.43612
A5: 45271 | B5: 18.718977 | C5: 113.74628 | D5: 41.51001 | E5: 52.187065 | F5: 382.86826 | G5: 12.509422 | H5: 345.46851 | I5: 1960.4037 | J5: 705.76385 | K5: 1522.8236 | L5: 49.279999 | M5: 117.94042 | N5: 34.152924 | O5: 16.969999 | P5: 11.2627
A6: 45278 | B6: 17.477942 | C6: 108.19426 | D6: 40.0471 | E6: 52.261726 | F6: 364.49677 | G6: 12.143245 | H6: 326.095 | I6: 1880.6702 | J6: 695.67346 | K6: 1419.8694 | L6: 50.080002 | M6: 120.40872 | N6: 35.071125 | O6: 15.99 | P6: 11.147086
A7: 45285 | B7: 17.675377 | C7: 108.00764 | D7: 40.824272 | E7: 51.981747 | F7: 365.59631 | G7: 12.083864 | H7: 329.80792 | I7: 1858.9685 | J7: 691.80701 | K7: 1415.3713 | L7: 50.240002 | M7: 121.54333 | N7: 34.843937 | O7: 15.74 | P7: 11.147086
A8: 45292 | B8: 15.889034 | C8: 104.60178 | D8: 37.989887 | E8: 48.640736 | F8: 346.72092 | G8: 11.519753 | H8: 326.39709 | I8: 1763.0557 | J8: 649.65356 | K8: 1377.3883 | L8: 50.689999 | M8: 116.44751 | N8: 35.336166 | O8: 15.25 | P8: 10.53048
A9: 45299 | B9: 15.240314 | C9: 102.87553 | D9: 37.761307 | E9: 50.152592 | F9: 336.0004 | G9: 11.222852 | H9: 342.35004 | I9: 1779.5255 | J9: 631.73602 | K9: 1284.9293 | L9: 50.66 | M9: 119.39352 | N9: 34.399044 | O9: 15.8 | P9: 10.453404
A10: 45306 | B10: 14.770224 | C10: 108.61416 | D10: 41.784306 | E10: 48.006126 | F10: 325.1467 | G10: 10.45091 | H10: 340.50821 | I10: 1775.6503 | J10: 621.83417 | K10: 1231.9529 | L10: 50.220001 | M10: 120.20966 | N10: 34.683025 | O10: 15.4 | P10: 9.9235086
A11: 45313 | B11: 16.312119 | C11: 119.90482 | D11: 43.795803 | E11: 53.064312 | F11: 356.96561 | G11: 11.618719 | H11: 331.50363 | I11: 1904.8905 | J11: 729.0567 | K11: 1340.9044 | L11: 48.709999 | M11: 122.77749 | N11: 36.888577 | O11: 16.200001 | P11: 10.925494
A12: 45320 | B12: 15.672797 | C12: 119.99812 | D12: 43.704369 | E12: 53.885571 | F12: 349.3588 | G12: 11.549442 | H12: 369.58798 | I12: 1959.9193 | J12: 733.77179 | K12: 1281.9307 | L12: 47.57 | M12: 120.80682 | N12: 37.873024 | O12: 16.75 | P12: 12.640429
A13: 45327 | B13: 14.384752 | C13: 125.2702 | D13: 46.675903 | E13: 55.584076 | F13: 383.21857 | G13: 11.94531 | H13: 382.5589 | I13: 2106.6953 | J13: 761.49695 | K13: 1270.4358 | L13: 46.830002 | M13: 127.15671 | N13: 39.756741 | O13: 16.440001 | P13: 12.052727
A14: 45334 | B14: 15.653993 | C14: 127.88292 | D14: 48.45882 | E14: 58.346481 | F14: 397.13358 | G14: 12.707355 | H14: 379.31372 | I14: 2133.8486 | J14: 769.3241 | K14: 1337.9058 | L14: 47.32 | M14: 131.0383 | N14: 43.457893 | O14: 17.639999 | P14: 12.495914
... A154: 46311 | B154: 15 | C154: 170.39999 | D154: 36.900002 | E154: 43.650002 | F154: 214.7 | G154: 6.9299998 | H154: 389.91 | I154: 1309 | J154: 384.29999 | K154: 1036.5 | L154: 14.95 | M154: 81.349998 | N154: 116.24 | O154: 11.27 | P154: 12.68

Sheet 奢侈品 Normalized
A1: 奢侈品 归一化（2025-12-01 = 1）
A2: Date | B2: VFC | C2: CFR | D2: 1913.HK | E2: MONC | F2: KER | G2: SFER | H2: RACE | I2: RMS | J2: MC | K2: BRBY | L2: CPRI | M2: PVH | N2: TPR | O2: GOOS | P2: ZGN
A3: 45628 | B3: 1.150496 | C3: 0.724942 | D3: 1.20749 | E3: 0.801789 | F3: 0.743406 | G3: 0.708798 | H3: 1.130437 | I3: 1.007452 | J3: 0.943053 | K3: 0.782847 | L3: 0.927778 | M3: 1.304047 | N3: 0.576093 | O3: 0.672302 | P3: 0.777251
A4: 45635 | B4: 1.176406 | C4: 0.771889 | D4: 1.310805 | E4: 0.890571 | F4: 0.823038 | G4: 0.83891 | H4: 1.159073 | I4: 1.061015 | J4: 1.015404 | K4: 0.831904 | L4: 0.884921 | M4: 1.267683 | N4: 0.555486 | O4: 0.699652 | P4: 0.804739
A5: 45642 | B5: 1.191841 | C5: 0.780242 | D5: 1.335557 | E5: 0.884377 | F5: 0.800167 | G5: 0.845105 | H5: 1.1293 | I5: 1.056823 | J5: 0.982107 | K5: 0.817153 | L5: 0.878968 | M5: 1.293138 | N5: 0.572703 | O5: 0.710094 | P5: 0.840758
A6: 45649 | B6: 1.214443 | C6: 0.783986 | D6: 1.371072 | E6: 0.858741 | F6: 0.786644 | G6: 0.827757 | H6: 1.1117 | I6: 1.072194 | J6: 0.978995 | K6: 0.832075 | L6: 0.847222 | M6: 1.260293 | N6: 0.577431 | O6: 0.721034 | P6: 0.806635
A7: 45656 | B7: 1.180265 | C7: 0.794355 | D7: 1.366767 | E7: 0.877151 | F7: 0.791653 | G7: 0.83891 | H7: 1.102964 | I7: 1.073591 | J7: 0.97915 | K7: 0.825386 | L7: 0.814286 | M7: 1.24 | N7: 0.587154 | O7: 0.704127 | P7: 0.781991
A8: 45663 | B8: 1.186329 | C8: 0.800979 | D8: 1.304348 | E8: 0.883689 | F8: 0.767446 | G8: 0.83767 | H8: 1.102964 | I8: 1.088961 | J8: 0.987397 | K8: 0.817839 | L8: 0.868651 | M8: 1.264282 | N8: 0.603568 | O8: 0.743411 | P8: 0.758294
A9: 45670 | B9: 1.268468 | C9: 0.797523 | D9: 1.322643 | E9: 0.919133 | F9: 0.759265 | G9: 0.842627 | H9: 1.081255 | I9: 1.095948 | J9: 1.005757 | K9: 0.830189 | L9: 0.943651 | M9: 1.144985 | N9: 0.59545 | O9: 0.706614 | P9: 0.723223
A10: 45677 | B10: 1.304851 | C10: 0.944988 | D10: 1.338786 | E10: 0.991053 | F10: 0.826544 | G10: 0.827757 | H10: 1.126483 | I10: 1.163484 | J10: 1.06286 | K10: 0.834305 | L10: 0.945238 | M10: 1.088328 | N10: 0.636842 | O10: 0.740428 | P10: 0.787678
A11: 45684 | B11: 1.432745 | C11: 0.9928 | D11: 1.371072 | E11: 1.057467 | F11: 0.876628 | G11: 0.89715 | H11: 1.117308 | I11: 1.23987 | J11: 1.17442 | K11: 0.971698 | L11: 1.005556 | M11: 1.060293 | N11: 0.646833 | O11: 0.770761 | P11: 0.90237
A12: 45691 | B12: 1.357222 | C12: 1.012385 | D12: 1.332329 | E12: 1.049553 | F12: 0.814524 | G12: 0.947955 | H12: 1.108573 | I12: 1.266884 | J12: 1.073751 | K12: 1.021441 | L12: 0.950397 | M12: 0.977361 | N12: 0.655932 | O12: 0.757832 | P12: 0.837915
A13: 45698 | B13: 1.304851 | C13: 1.013249 | D13: 1.373224 | E13: 1.047832 | F13: 0.815359 | G13: 0.877323 | H13: 1.190913 | I13: 1.280857 | J13: 1.066283 | K13: 1.015866 | L13: 0.872222 | M13: 0.907918 | N13: 0.705174 | O13: 0.700646 | P13: 0.832227
A14: 45705 | B14: 1.410695 | C14: 1.053571 | D14: 1.485149 | E14: 1.129732 | F14: 0.935225 | G14: 0.986369 | H14: 1.302148 | I14: 1.308337 | J14: 1.091489 | K14: 0.990566 | L14: 0.89127 | M14: 0.911554 | N14: 0.782337 | O14: 0.711089 | P14: 0.845498
... A54: 45985 | B54: 0.902426 | C54: 0.959101 | D54: 0.96427 | E54: 0.970406 | F54: 0.987145 | G54: 0.947955 | H54: 0.986173 | I54: 0.982767 | J54: 0.967325 | K54: 0.957118 | L54: 0.952381 | M54: 0.913314 | N54: 0.942819 | O54: 0.903531 | P54: 0.978199
A55: 45992 | B55: =IF(OR('奢侈品 Prices'!B3="",'奢侈品 Prices'!B$3=""),"",'奢侈品 Prices'!B3/'奢侈品 Prices'!B$3) | C55: =IF(OR('奢侈品 Prices'!C3="",'奢侈品 Prices'!C$3=""),"",'奢侈品 Prices'!C3/'奢侈品 Prices'!C$3) | D55: =IF(OR('奢侈品 Prices'!D3="",'奢侈品 Prices'!D$3=""),"",'奢侈品 Prices'!D3/'奢侈品 Prices'!D$3) | E55: =IF(OR('奢侈品 Prices'!E3="",'奢侈品 Prices'!E$3=""),"",'奢侈品 Prices'!E3/'奢侈品 Prices'!E$3) | F55: =IF(OR('奢侈品 Prices'!F3="",'奢侈品 Prices'!F$3=""),"",'奢侈品 Prices'!F3/'奢侈品 Prices'!F$3) | G55: =IF(OR('奢侈品 Prices'!G3="",'奢侈品 Prices'!G$3=""),"",'奢侈品 Prices'!G3/'奢侈品 Prices'!G$3) | H55: =IF(OR('奢侈品 Prices'!H3="",'奢侈品 Prices'!H$3=""),"",'奢侈品 Prices'!H3/'奢侈品 Prices'!H$3) | I55: =IF(OR('奢侈品 Prices'!I3="",'奢侈品 Prices'!I$3=""),"",'奢侈品 Prices'!I3/'奢侈品 Prices'!I$3) | ... P55: =IF(OR('奢侈品 Prices'!P3="",'奢侈品 Prices'!P$3=""),"",'奢侈品 Prices'!P3/'奢侈品 Prices'!P$3)
A56: 45996 | B56: =IF(OR('奢侈品 Prices'!B4="",'奢侈品 Prices'!B$3=""),"",'奢侈品 Prices'!B4/'奢侈品 Prices'!B$3) | C56: =IF(OR('奢侈品 Prices'!C4="",'奢侈品 Prices'!C$3=""),"",'奢侈品 Prices'!C4/'奢侈品 Prices'!C$3) | D56: =IF(OR('奢侈品 Prices'!D4="",'奢侈品 Prices'!D$3=""),"",'奢侈品 Prices'!D4/'奢侈品 Prices'!D$3) | E56: =IF(OR('奢侈品 Prices'!E4="",'奢侈品 Prices'!E$3=""),"",'奢侈品 Prices'!E4/'奢侈品 Prices'!E$3) | F56: =IF(OR('奢侈品 Prices'!F4="",'奢侈品 Prices'!F$3=""),"",'奢侈品 Prices'!F4/'奢侈品 Prices'!F$3) | G56: =IF(OR('奢侈品 Prices'!G4="",'奢侈品 Prices'!G$3=""),"",'奢侈品 Prices'!G4/'奢侈品 Prices'!G$3) | H56: =IF(OR('奢侈品 Prices'!H4="",'奢侈品 Prices'!H$3=""),"",'奢侈品 Prices'!H4/'奢侈品 Prices'!H$3) | I56: =IF(OR('奢侈品 Prices'!I4="",'奢侈品 Prices'!I$3=""),"",'奢侈品 Prices'!I4/'奢侈品 Prices'!I$3) | ... P56: =IF(OR('奢侈品 Prices'!P4="",'奢侈品 Prices'!P$3=""),"",'奢侈品 Prices'!P4/'奢侈品 Prices'!P$3)
A57: 46003 | B57: =IF(OR('奢侈品 Prices'!B5="",'奢侈品 Prices'!B$3=""),"",'奢侈品 Prices'!B5/'奢侈品 Prices'!B$3) | C57: =IF(OR('奢侈品 Prices'!C5="",'奢侈品 Prices'!C$3=""),"",'奢侈品 Prices'!C5/'奢侈品 Prices'!C$3) | D57: =IF(OR('奢侈品 Prices'!D5="",'奢侈品 Prices'!D$3=""),"",'奢侈品 Prices'!D5/'奢侈品 Prices'!D$3) | E57: =IF(OR('奢侈品 Prices'!E5="",'奢侈品 Prices'!E$3=""),"",'奢侈品 Prices'!E5/'奢侈品 Prices'!E$3) | F57: =IF(OR('奢侈品 Prices'!F5="",'奢侈品 Prices'!F$3=""),"",'奢侈品 Prices'!F5/'奢侈品 Prices'!F$3) | G57: =IF(OR('奢侈品 Prices'!G5="",'奢侈品 Prices'!G$3=""),"",'奢侈品 Prices'!G5/'奢侈品 Prices'!G$3) | H57: =IF(OR('奢侈品 Prices'!H5="",'奢侈品 Prices'!H$3=""),"",'奢侈品 Prices'!H5/'奢侈品 Prices'!H$3) | I57: =IF(OR('奢侈品 Prices'!I5="",'奢侈品 Prices'!I$3=""),"",'奢侈品 Prices'!I5/'奢侈品 Prices'!I$3) | ... P57: =IF(OR('奢侈品 Prices'!P5="",'奢侈品 Prices'!P$3=""),"",'奢侈品 Prices'!P5/'奢侈品 Prices'!P$3)
A58: 46010 | B58: =IF(OR('奢侈品 Prices'!B6="",'奢侈品 Prices'!B$3=""),"",'奢侈品 Prices'!B6/'奢侈品 Prices'!B$3) | C58: =IF(OR('奢侈品 Prices'!C6="",'奢侈品 Prices'!C$3=""),"",'奢侈品 Prices'!C6/'奢侈品 Prices'!C$3) | D58: =IF(OR('奢侈品 Prices'!D6="",'奢侈品 Prices'!D$3=""),"",'奢侈品 Prices'!D6/'奢侈品 Prices'!D$3) | E58: =IF(OR('奢侈品 Prices'!E6="",'奢侈品 Prices'!E$3=""),"",'奢侈品 Prices'!E6/'奢侈品 Prices'!E$3) | F58: =IF(OR('奢侈品 Prices'!F6="",'奢侈品 Prices'!F$3=""),"",'奢侈品 Prices'!F6/'奢侈品 Prices'!F$3) | G58: =IF(OR('奢侈品 Prices'!G6="",'奢侈品 Prices'!G$3=""),"",'奢侈品 Prices'!G6/'奢侈品 Prices'!G$3) | H58: =IF(OR('奢侈品 Prices'!H6="",'奢侈品 Prices'!H$3=""),"",'奢侈品 Prices'!H6/'奢侈品 Prices'!H$3) | I58: =IF(OR('奢侈品 Prices'!I6="",'奢侈品 Prices'!I$3=""),"",'奢侈品 Prices'!I6/'奢侈品 Prices'!I$3) | ... P58: =IF(OR('奢侈品 Prices'!P6="",'奢侈品 Prices'!P$3=""),"",'奢侈品 Prices'!P6/'奢侈品 Prices'!P$3)
A59: 46017 | B59: =IF(OR('奢侈品 Prices'!B7="",'奢侈品 Prices'!B$3=""),"",'奢侈品 Prices'!B7/'奢侈品 Prices'!B$3) | C59: =IF(OR('奢侈品 Prices'!C7="",'奢侈品 Prices'!C$3=""),"",'奢侈品 Prices'!C7/'奢侈品 Prices'!C$3) | D59: =IF(OR('奢侈品 Prices'!D7="",'奢侈品 Prices'!D$3=""),"",'奢侈品 Prices'!D7/'奢侈品 Prices'!D$3) | E59: =IF(OR('奢侈品 Prices'!E7="",'奢侈品 Prices'!E$3=""),"",'奢侈品 Prices'!E7/'奢侈品 Prices'!E$3) | F59: =IF(OR('奢侈品 Prices'!F7="",'奢侈品 Prices'!F$3=""),"",'奢侈品 Prices'!F7/'奢侈品 Prices'!F$3) | G59: =IF(OR('奢侈品 Prices'!G7="",'奢侈品 Prices'!G$3=""),"",'奢侈品 Prices'!G7/'奢侈品 Prices'!G$3) | H59: =IF(OR('奢侈品 Prices'!H7="",'奢侈品 Prices'!H$3=""),"",'奢侈品 Prices'!H7/'奢侈品 Prices'!H$3) | I59: =IF(OR('奢侈品 Prices'!I7="",'奢侈品 Prices'!I$3=""),"",'奢侈品 Prices'!I7/'奢侈品 Prices'!I$3) | ... P59: =IF(OR('奢侈品 Prices'!P7="",'奢侈品 Prices'!P$3=""),"",'奢侈品 Prices'!P7/'奢侈品 Prices'!P$3)
A60: 46024 | B60: =IF(OR('奢侈品 Prices'!B8="",'奢侈品 Prices'!B$3=""),"",'奢侈品 Prices'!B8/'奢侈品 Prices'!B$3) | C60: =IF(OR('奢侈品 Prices'!C8="",'奢侈品 Prices'!C$3=""),"",'奢侈品 Prices'!C8/'奢侈品 Prices'!C$3) | D60: =IF(OR('奢侈品 Prices'!D8="",'奢侈品 Prices'!D$3=""),"",'奢侈品 Prices'!D8/'奢侈品 Prices'!D$3) | E60: =IF(OR('奢侈品 Prices'!E8="",'奢侈品 Prices'!E$3=""),"",'奢侈品 Prices'!E8/'奢侈品 Prices'!E$3) | F60: =IF(OR('奢侈品 Prices'!F8="",'奢侈品 Prices'!F$3=""),"",'奢侈品 Prices'!F8/'奢侈品 Prices'!F$3) | G60: =IF(OR('奢侈品 Prices'!G8="",'奢侈品 Prices'!G$3=""),"",'奢侈品 Prices'!G8/'奢侈品 Prices'!G$3) | H60: =IF(OR('奢侈品 Prices'!H8="",'奢侈品 Prices'!H$3=""),"",'奢侈品 Prices'!H8/'奢侈品 Prices'!H$3) | I60: =IF(OR('奢侈品 Prices'!I8="",'奢侈品 Prices'!I$3=""),"",'奢侈品 Prices'!I8/'奢侈品 Prices'!I$3) | ... P60: =IF(OR('奢侈品 Prices'!P8="",'奢侈品 Prices'!P$3=""),"",'奢侈品 Prices'!P8/'奢侈品 Prices'!P$3)
A61: 46031 | B61: =IF(OR('奢侈品 Prices'!B9="",'奢侈品 Prices'!B$3=""),"",'奢侈品 Prices'!B9/'奢侈品 Prices'!B$3) | C61: =IF(OR('奢侈品 Prices'!C9="",'奢侈品 Prices'!C$3=""),"",'奢侈品 Prices'!C9/'奢侈品 Prices'!C$3) | D61: =IF(OR('奢侈品 Prices'!D9="",'奢侈品 Prices'!D$3=""),"",'奢侈品 Prices'!D9/'奢侈品 Prices'!D$3) | E61: =IF(OR('奢侈品 Prices'!E9="",'奢侈品 Prices'!E$3=""),"",'奢侈品 Prices'!E9/'奢侈品 Prices'!E$3) | F61: =IF(OR('奢侈品 Prices'!F9="",'奢侈品 Prices'!F$3=""),"",'奢侈品 Prices'!F9/'奢侈品 Prices'!F$3) | G61: =IF(OR('奢侈品 Prices'!G9="",'奢侈品 Prices'!G$3=""),"",'奢侈品 Prices'!G9/'奢侈品 Prices'!G$3) | H61: =IF(OR('奢侈品 Prices'!H9="",'奢侈品 Prices'!H$3=""),"",'奢侈品 Prices'!H9/'奢侈品 Prices'!H$3) | I61: =IF(OR('奢侈品 Prices'!I9="",'奢侈品 Prices'!I$3=""),"",'奢侈品 Prices'!I9/'奢侈品 Prices'!I$3) | ... P61: =IF(OR('奢侈品 Prices'!P9="",'奢侈品 Prices'!P$3=""),"",'奢侈品 Prices'!P9/'奢侈品 Prices'!P$3)
A62: 46038 | B62: =IF(OR('奢侈品 Prices'!B10="",'奢侈品 Prices'!B$3=""),"",'奢侈品 Prices'!B10/'奢侈品 Prices'!B$3) | C62: =IF(OR('奢侈品 Prices'!C10="",'奢侈品 Prices'!C$3=""),"",'奢侈品 Prices'!C10/'奢侈品 Prices'!C$3) | D62: =IF(OR('奢侈品 Prices'!D10="",'奢侈品 Prices'!D$3=""),"",'奢侈品 Prices'!D10/'奢侈品 Prices'!D$3) | E62: =IF(OR('奢侈品 Prices'!E10="",'奢侈品 Prices'!E$3=""),"",'奢侈品 Prices'!E10/'奢侈品 Prices'!E$3) | F62: =IF(OR('奢侈品 Prices'!F10="",'奢侈品 Prices'!F$3=""),"",'奢侈品 Prices'!F10/'奢侈品 Prices'!F$3) | G62: =IF(OR('奢侈品 Prices'!G10="",'奢侈品 Prices'!G$3=""),"",'奢侈品 Prices'!G10/'奢侈品 Prices'!G$3) | H62: =IF(OR('奢侈品 Prices'!H10="",'奢侈品 Prices'!H$3=""),"",'奢侈品 Prices'!H10/'奢侈品 Prices'!H$3) | I62: =IF(OR('奢侈品 Prices'!I10="",'奢侈品 Prices'!I$3=""),"",'奢侈品 Prices'!I10/'奢侈品 Prices'!I$3) | ... P62: =IF(OR('奢侈品 Prices'!P10="",'奢侈品 Prices'!P$3=""),"",'奢侈品 Prices'!P10/'奢侈品 Prices'!P$3)
A63: 46045 | B63: =IF(OR('奢侈品 Prices'!B11="",'奢侈品 Prices'!B$3=""),"",'奢侈品 Prices'!B11/'奢侈品 Prices'!B$3) | C63: =IF(OR('奢侈品 Prices'!C11="",'奢侈品 Prices'!C$3=""),"",'奢侈品 Prices'!C11/'奢侈品 Prices'!C$3) | D63: =IF(OR('奢侈品 Prices'!D11="",'奢侈品 Prices'!D$3=""),"",'奢侈品 Prices'!D11/'奢侈品 Prices'!D$3) | E63: =IF(OR('奢侈品 Prices'!E11="",'奢侈品 Prices'!E$3=""),"",'奢侈品 Prices'!E11/'奢侈品 Prices'!E$3) | F63: =IF(OR('奢侈品 Prices'!F11="",'奢侈品 Prices'!F$3=""),"",'奢侈品 Prices'!F11/'奢侈品 Prices'!F$3) | G63: =IF(OR('奢侈品 Prices'!G11="",'奢侈品 Prices'!G$3=""),"",'奢侈品 Prices'!G11/'奢侈品 Prices'!G$3) | H63: =IF(OR('奢侈品 Prices'!H11="",'奢侈品 Prices'!H$3=""),"",'奢侈品 Prices'!H11/'奢侈品 Prices'!H$3) | I63: =IF(OR('奢侈品 Prices'!I11="",'奢侈品 Prices'!I$3=""),"",'奢侈品 Prices'!I11/'奢侈品 Prices'!I$3) | ... P63: =IF(OR('奢侈品 Prices'!P11="",'奢侈品 Prices'!P$3=""),"",'奢侈品 Prices'!P11/'奢侈品 Prices'!P$3)
A64: 46052 | B64: =IF(OR('奢侈品 Prices'!B12="",'奢侈品 Prices'!B$3=""),"",'奢侈品 Prices'!B12/'奢侈品 Prices'!B$3) | C64: =IF(OR('奢侈品 Prices'!C12="",'奢侈品 Prices'!C$3=""),"",'奢侈品 Prices'!C12/'奢侈品 Prices'!C$3) | D64: =IF(OR('奢侈品 Prices'!D12="",'奢侈品 Prices'!D$3=""),"",'奢侈品 Prices'!D12/'奢侈品 Prices'!D$3) | E64: =IF(OR('奢侈品 Prices'!E12="",'奢侈品 Prices'!E$3=""),"",'奢侈品 Prices'!E12/'奢侈品 Prices'!E$3) | F64: =IF(OR('奢侈品 Prices'!F12="",'奢侈品 Prices'!F$3=""),"",'奢侈品 Prices'!F12/'奢侈品 Prices'!F$3) | G64: =IF(OR('奢侈品 Prices'!G12="",'奢侈品 Prices'!G$3=""),"",'奢侈品 Prices'!G12/'奢侈品 Prices'!G$3) | H64: =IF(OR('奢侈品 Prices'!H12="",'奢侈品 Prices'!H$3=""),"",'奢侈品 Prices'!H12/'奢侈品 Prices'!H$3) | I64: =IF(OR('奢侈品 Prices'!I12="",'奢侈品 Prices'!I$3=""),"",'奢侈品 Prices'!I12/'奢侈品 Prices'!I$3) | ... P64: =IF(OR('奢侈品 Prices'!P12="",'奢侈品 Prices'!P$3=""),"",'奢侈品 Prices'!P12/'奢侈品 Prices'!P$3)
A65: 46059 | B65: =IF(OR('奢侈品 Prices'!B13="",'奢侈品 Prices'!B$3=""),"",'奢侈品 Prices'!B13/'奢侈品 Prices'!B$3) | C65: =IF(OR('奢侈品 Prices'!C13="",'奢侈品 Prices'!C$3=""),"",'奢侈品 Prices'!C13/'奢侈品 Prices'!C$3) | D65: =IF(OR('奢侈品 Prices'!D13="",'奢侈品 Prices'!D$3=""),"",'奢侈品 Prices'!D13/'奢侈品 Prices'!D$3) | E65: =IF(OR('奢侈品 Prices'!E13="",'奢侈品 Prices'!E$3=""),"",'奢侈品 Prices'!E13/'奢侈品 Prices'!E$3) | F65: =IF(OR('奢侈品 Prices'!F13="",'奢侈品 Prices'!F$3=""),"",'奢侈品 Prices'!F13/'奢侈品 Prices'!F$3) | G65: =IF(OR('奢侈品 Prices'!G13="",'奢侈品 Prices'!G$3=""),"",'奢侈品 Prices'!G13/'奢侈品 Prices'!G$3) | H65: =IF(OR('奢侈品 Prices'!H13="",'奢侈品 Prices'!H$3=""),"",'奢侈品 Prices'!H13/'奢侈品 Prices'!H$3) | I65: =IF(OR('奢侈品 Prices'!I13="",'奢侈品 Prices'!I$3=""),"",'奢侈品 Prices'!I13/'奢侈品 Prices'!I$3) | ... P65: =IF(OR('奢侈品 Prices'!P13="",'奢侈品 Prices'!P$3=""),"",'奢侈品 Prices'!P13/'奢侈品 Prices'!P$3)
A66: 46066 | B66: =IF(OR('奢侈品 Prices'!B14="",'奢侈品 Prices'!B$3=""),"",'奢侈品 Prices'!B14/'奢侈品 Prices'!B$3) | C66: =IF(OR('奢侈品 Prices'!C14="",'奢侈品 Prices'!C$3=""),"",'奢侈品 Prices'!C14/'奢侈品 Prices'!C$3) | D66: =IF(OR('奢侈品 Prices'!D14="",'奢侈品 Prices'!D$3=""),"",'奢侈品 Prices'!D14/'奢侈品 Prices'!D$3) | E66: =IF(OR('奢侈品 Prices'!E14="",'奢侈品 Prices'!E$3=""),"",'奢侈品 Prices'!E14/'奢侈品 Prices'!E$3) | F66: =IF(OR('奢侈品 Prices'!F14="",'奢侈品 Prices'!F$3=""),"",'奢侈品 Prices'!F14/'奢侈品 Prices'!F$3) | G66: =IF(OR('奢侈品 Prices'!G14="",'奢侈品 Prices'!G$3=""),"",'奢侈品 Prices'!G14/'奢侈品 Prices'!G$3) | H66: =IF(OR('奢侈品 Prices'!H14="",'奢侈品 Prices'!H$3=""),"",'奢侈品 Prices'!H14/'奢侈品 Prices'!H$3) | I66: =IF(OR('奢侈品 Prices'!I14="",'奢侈品 Prices'!I$3=""),"",'奢侈品 Prices'!I14/'奢侈品 Prices'!I$3) | ... P66: =IF(OR('奢侈品 Prices'!P14="",'奢侈品 Prices'!P$3=""),"",'奢侈品 Prices'!P14/'奢侈品 Prices'!P$3)
... A98: 46290 | B98: =IF(OR('奢侈品 Prices'!B46="",'奢侈品 Prices'!B$3=""),"",'奢侈品 Prices'!B46/'奢侈品 Prices'!B$3) | C98: =IF(OR('奢侈品 Prices'!C46="",'奢侈品 Prices'!C$3=""),"",'奢侈品 Prices'!C46/'奢侈品 Prices'!C$3) | D98: =IF(OR('奢侈品 Prices'!D46="",'奢侈品 Prices'!D$3=""),"",'奢侈品 Prices'!D46/'奢侈品 Prices'!D$3) | E98: =IF(OR('奢侈品 Prices'!E46="",'奢侈品 Prices'!E$3=""),"",'奢侈品 Prices'!E46/'奢侈品 Prices'!E$3) | F98: =IF(OR('奢侈品 Prices'!F46="",'奢侈品 Prices'!F$3=""),"",'奢侈品 Prices'!F46/'奢侈品 Prices'!F$3) | G98: =IF(OR('奢侈品 Prices'!G46="",'奢侈品 Prices'!G$3=""),"",'奢侈品 Prices'!G46/'奢侈品 Prices'!G$3) | H98: =IF(OR('奢侈品 Prices'!H46="",'奢侈品 Prices'!H$3=""),"",'奢侈品 Prices'!H46/'奢侈品 Prices'!H$3) | I98: =IF(OR('奢侈品 Prices'!I46="",'奢侈品 Prices'!I$3=""),"",'奢侈品 Prices'!I46/'奢侈品 Prices'!I$3) | ... P98: =IF(OR('奢侈品 Prices'!P46="",'奢侈品 Prices'!P$3=""),"",'奢侈品 Prices'!P46/'奢侈品 Prices'!P$3)
A99: 46297 | B99: =IF(OR('奢侈品 Prices'!B99="",'奢侈品 Prices'!B$3=""),"",'奢侈品 Prices'!B99/'奢侈品 Prices'!B$3) | C99: =IF(OR('奢侈品 Prices'!C99="",'奢侈品 Prices'!C$3=""),"",'奢侈品 Prices'!C99/'奢侈品 Prices'!C$3) | D99: =IF(OR('奢侈品 Prices'!D99="",'奢侈品 Prices'!D$3=""),"",'奢侈品 Prices'!D99/'奢侈品 Prices'!D$3) | E99: =IF(OR('奢侈品 Prices'!E99="",'奢侈品 Prices'!E$3=""),"",'奢侈品 Prices'!E99/'奢侈品 Prices'!E$3) | F99: =IF(OR('奢侈品 Prices'!F99="",'奢侈品 Prices'!F$3=""),"",'奢侈品 Prices'!F99/'奢侈品 Prices'!F$3) | G99: =IF(OR('奢侈品 Prices'!G99="",'奢侈品 Prices'!G$3=""),"",'奢侈品 Prices'!G99/'奢侈品 Prices'!G$3) | H99: =IF(OR('奢侈品 Prices'!H99="",'奢侈品 Prices'!H$3=""),"",'奢侈品 Prices'!H99/'奢侈品 Prices'!H$3) | I99: =IF(OR('奢侈品 Prices'!I99="",'奢侈品 Prices'!I$3=""),"",'奢侈品 Prices'!I99/'奢侈品 Prices'!I$3) | ... P99: =IF(OR('奢侈品 Prices'!P99="",'奢侈品 Prices'!P$3=""),"",'奢侈品 Prices'!P99/'奢侈品 Prices'!P$3)
A100: 46304 | B100: =IF(OR('奢侈品 Prices'!B100="",'奢侈品 Prices'!B$3=""),"",'奢侈品 Prices'!B100/'奢侈品 Prices'!B$3) | C100: =IF(OR('奢侈品 Prices'!C100="",'奢侈品 Prices'!C$3=""),"",'奢侈品 Prices'!C100/'奢侈品 Prices'!C$3) | D100: =IF(OR('奢侈品 Prices'!D100="",'奢侈品 Prices'!D$3=""),"",'奢侈品 Prices'!D100/'奢侈品 Prices'!D$3) | E100: =IF(OR('奢侈品 Prices'!E100="",'奢侈品 Prices'!E$3=""),"",'奢侈品 Prices'!E100/'奢侈品 Prices'!E$3) | F100: =IF(OR('奢侈品 Prices'!F100="",'奢侈品 Prices'!F$3=""),"",'奢侈品 Prices'!F100/'奢侈品 Prices'!F$3) | G100: =IF(OR('奢侈品 Prices'!G100="",'奢侈品 Prices'!G$3=""),"",'奢侈品 Prices'!G100/'奢侈品 Prices'!G$3) | H100: =IF(OR('奢侈品 Prices'!H100="",'奢侈品 Prices'!H$3=""),"",'奢侈品 Prices'!H100/'奢侈品 Prices'!H$3) | I100: =IF(OR('奢侈品 Prices'!I100="",'奢侈品 Prices'!I$3=""),"",'奢侈品 Prices'!I100/'奢侈品 Prices'!I$3) | ... P100: =IF(OR('奢侈品 Prices'!P100="",'奢侈品 Prices'!P$3=""),"",'奢侈品 Prices'!P100/'奢侈品 Prices'!P$3)
A101: 46311 | B101: =IF(OR('奢侈品 Prices'!B101="",'奢侈品 Prices'!B$3=""),"",'奢侈品 Prices'!B101/'奢侈品 Prices'!B$3) | C101: =IF(OR('奢侈品 Prices'!C101="",'奢侈品 Prices'!C$3=""),"",'奢侈品 Prices'!C101/'奢侈品 Prices'!C$3) | D101: =IF(OR('奢侈品 Prices'!D101="",'奢侈品 Prices'!D$3=""),"",'奢侈品 Prices'!D101/'奢侈品 Prices'!D$3) | E101: =IF(OR('奢侈品 Prices'!E101="",'奢侈品 Prices'!E$3=""),"",'奢侈品 Prices'!E101/'奢侈品 Prices'!E$3) | F101: =IF(OR('奢侈品 Prices'!F101="",'奢侈品 Prices'!F$3=""),"",'奢侈品 Prices'!F101/'奢侈品 Prices'!F$3) | G101: =IF(OR('奢侈品 Prices'!G101="",'奢侈品 Prices'!G$3=""),"",'奢侈品 Prices'!G101/'奢侈品 Prices'!G$3) | H101: =IF(OR('奢侈品 Prices'!H101="",'奢侈品 Prices'!H$3=""),"",'奢侈品 Prices'!H101/'奢侈品 Prices'!H$3) | I101: =IF(OR('奢侈品 Prices'!I101="",'奢侈品 Prices'!I$3=""),"",'奢侈品 Prices'!I101/'奢侈品 Prices'!I$3) | ... P101: =IF(OR('奢侈品 Prices'!P101="",'奢侈品 Prices'!P$3=""),"",'奢侈品 Prices'!P101/'奢侈品 Prices'!P$3)

Sheet 奢侈品 Tickers
A1: 代码 | B1: Yahoo | C1: Bloomberg | D1: 区域 | E1: 状态 | F1: 备注
A2: VFC | B2: VFC | C2: VFC US | D2: US | E2: OK | F2: V.F. Corporation
A3: CFR | B3: CFR.SW | C3: CFR SW | D3: Europe | E3: OK | F3: Richemont 瑞士
A4: 1913.HK | B4: 1913.HK | C4: 1913 HK | D4: Asia | E4: OK | F4: Prada
A5: MONC | B5: MONC.MI | C5: MONC IM | D5: Europe | E5: OK | F5: Moncler 米兰
A6: KER | B6: KER.PA | C6: KER FP | D6: Europe | E6: OK | F6: Kering 巴黎
A7: SFER | B7: SFER.MI | C7: SFER IM | D7: Europe | E7: OK | F7: Ferragamo 米兰
A8: RACE | B8: RACE | C8: RACE US | D8: US | E8: OK | F8: Ferrari
A9: RMS | B9: RMS.PA | C9: RMS FP | D9: Europe | E9: OK | F9: Hermès 巴黎
A10: MC | B10: MC.PA | C10: MC FP | D10: Europe | E10: OK | F10: LVMH 巴黎
A11: BRBY | B11: BRBY.L | C11: BRBY LN | D11: Europe | E11: OK | F11: Burberry 伦敦
A12: CPRI | B12: CPRI | C12: CPRI US | D12: US | E12: OK | F12: Capri Holdings
... A16: ZGN | B16: ZGN | C16: ZGN US | D16: US | E16: OK | F16: Zegna

Sheet 行业指数
A1: 行业等权指数（归一化简单平均，基期 = 1）
A2: Date | B2: 运动服饰等权指数 | C2: 奢侈品等权指数
A3: 45628 | B3: 1.2199 | C3: 0.8972
A4: 45635 | B4: 1.2472 | C4: 0.9394
A5: 45642 | B5: 1.248 | C5: 0.9412
A6: 45649 | B6: 1.2257 | C6: 0.9367
A7: 45656 | B7: 1.2108 | C7: 0.9305
A8: 45663 | B8: 1.2128 | C8: 0.9344
A9: 45670 | B9: 1.1826 | C9: 0.9358
A10: 45677 | B10: 1.1945 | C10: 0.9746
A11: 45684 | B11: 1.217 | C11: 1.0345
A12: 45691 | B12: 1.1736 | C12: 1.0109
A13: 45698 | B13: 1.1267 | C13: 1.0003
A14: 45705 | B14: 1.132 | C14: 1.0557
... A98: 46290 | B98: 0.9452 | C98: 0.8184
A100: 说明：等权指数 = 板块内所有有数据个股归一化值的简单平均。退市/无数据的公司不参与计算。
A101: 46297 | B101: 0.95 | C101: 0.8137
A102: 46304 | B102: 0.9769 | C102: 0.8221
A103: 46311 | B103: 0.9743 | C103: 0.8254

Sheet 可选消费ETFs
A1: 可选消费 ETF 周度价格（2025-01-01 起）
A2: Date | B2: XLY | C2: RSPD | D2: XRT | E2: XLY Norm | F2: RSPD Norm | G2: XRT Norm
A3: 45658 | B3: 110.7 | C3: 52.959999 | D3: 79.360001 | E3: 1 | F3: 1 | G3: 1
A4: 45660 | B4: 112.94 | C4: 53.34 | D4: 79.68 | E4: 1.0202 | F4: 1.0072 | G4: 1.004
A5: 45667 | B5: 110.41 | C5: 52.41 | D5: 79.050003 | E5: 0.9974 | F5: 0.9896 | G5: 0.9961
A6: 45674 | B6: 114.61 | C6: 53.990002 | D6: 78.43 | E6: 1.0353 | F6: 1.0194 | G6: 0.9883
A7: 45681 | B7: 115.005 | C7: 54.360001 | D7: 80.330002 | E7: 1.0389 | F7: 1.0264 | G7: 1.0122
A8: 45688 | B8: 116.085 | C8: 54.810001 | D8: 80.25 | E8: 1.0486 | F8: 1.0349 | G8: 1.0112
A9: 45695 | B9: 112.79 | C9: 54.389999 | D9: 78.269997 | E9: 1.0189 | F9: 1.027 | G9: 0.9863
A10: 45702 | B10: 113.5 | C10: 55.549999 | D10: 79.360001 | E10: 1.0253 | F10: 1.0489 | G10: 1
A11: 45709 | B11: 109.195 | C11: 54.009998 | D11: 75.290001 | E11: 0.9864 | F11: 1.0198 | G11: 0.9487
A12: 45716 | B12: 107.98 | C12: 54.380001 | D12: 74.139999 | E12: 0.9754 | F12: 1.0268 | G12: 0.9342
A13: 45723 | B13: 102.835 | C13: 52.59 | D13: 71.739998 | E13: 0.929 | F13: 0.993 | G13: 0.904
A14: 45730 | B14: 98.349998 | C14: 49.970001 | D14: 67.529999 | E14: 0.8884 | F14: 0.9435 | G14: 0.8509
... A96: 46304 | B96: 112.85 | C96: 52.650002 | D96: 84.089996 | E96: 1.0194 | F96: 0.9941 | G96: 1.0596
A97: ETF 说明
A98: XLY | B98: 可选消费 ETF 市值加权 | D98: 被亚马逊、特斯拉主导
A99: RSPD | B99: 标普500可选消费等权 ETF | D99: 去掉巨头集中度
A100: XRT | B100: 标普零售精选 ETF 等权 | D100: 零售属性强，含服装零售
A102: 关键统计
A103: ETF | B103: 基期价 | C103: 当前价 | D103: 累计涨跌 | E103: 峰值 | F103: 峰值日期 | G103: 谷值 | H103: 谷值日期 | I103: 最大回撤 | J103: 回撤谷底日期
A104: XLY | B104: 110.7 | C104: 112.23 | D104: +1.4% | E104: 1.124 | F104: 2026-01-09 | G104: 0.826 | H104: 2025-04-04 | I104: -21.3% | J104: 2025-04-04
A105: RSPD | B105: 52.96 | C105: 52.73 | D105: -0.4% | E105: 1.129 | F105: 2026-01-09 | G105: 0.872 | H105: 2025-04-04 | I105: -16.9% | J105: 2025-04-04
A106: XRT | B106: 79.36 | C106: 82.56 | D106: +4.0% | E106: 1.144 | F106: 2026-08-07 | G106: 0.818 | H106: 2025-04-04 | I106: -19.2% | J106: 2025-04-04
A108: 趋势阶段注释（zigzag ≥5%）
A109: XLY
A110: 起始 | B110: 结束 | C110: 阶段 | D110: 幅度 | E110: 起始值 | F110: 结束值
A111: 2025-01-01 | B111: 2025-04-04 | C111: 下跌 | D111: -17.4% | E111: 110.70 | F111: 91.39
A112: 2025-04-04 | B112: 2025-09-19 | C112: 上涨 | D112: +32.1% | E112: 91.39 | F112: 120.69
A113: 2025-09-19 | B113: 2025-11-21 | C113: 下跌 | D113: -6.6% | E113: 120.69 | F113: 112.75
A114: 2025-11-21 | B114: 2026-01-09 | C114: 上涨 | D114: +10.3% | E114: 112.75 | F114: 124.41
A115: 2026-01-09 | B115: 2026-03-27 | C115: 下跌 | D115: -15.1% | E115: 124.41 | F115: 105.68
A116: 2026-03-27 | B116: 2026-05-29 | C116: 上涨 | D116: +14.4% | E116: 105.68 | F116: 120.87
A117: 2026-05-29 | B117: 2026-07-24 | C117: 下跌 | D117: -9.5% | E117: 120.87 | F117: 109.41
A118: 2026-07-24 | B118: 2026-08-07 | C118: 上涨 | D118: +9.6% | E118: 109.41 | F118: 119.86
A119: 2026-08-07 | B119: 2026-09-25 | C119: 下跌 | D119: -6.4% | E119: 119.86 | F119: 112.23
A121: RSPD
A122: 起始 | B122: 结束 | C122: 阶段 | D122: 幅度 | E122: 起始值 | F122: 结束值
A123: 2025-01-01 | B123: 2025-04-04 | C123: 下跌 | D123: -12.8% | E123: 52.96 | F123: 46.17
A124: 2025-04-04 | B124: 2025-09-05 | C124: 上涨 | D124: +27.6% | E124: 46.17 | F124: 58.92
A125: 2025-09-05 | B125: 2025-11-21 | C125: 下跌 | D125: -7.4% | E125: 58.92 | F125: 54.57
A126: 2025-11-21 | B126: 2026-01-09 | C126: 上涨 | D126: +9.6% | E126: 54.57 | F126: 59.80
A127: 2026-01-09 | B127: 2026-03-27 | C127: 下跌 | D127: -12.9% | E127: 59.80 | F127: 52.06
A128: 2026-03-27 | B128: 2026-04-17 | C128: 上涨 | D128: +11.5% | E128: 52.06 | F128: 58.07
A129: 2026-04-17 | B129: 2026-05-15 | C129: 下跌 | D129: -10.9% | E129: 58.07 | F129: 51.76
A130: 2026-05-15 | B130: 2026-08-07 | C130: 上涨 | D130: +13.3% | E130: 51.76 | F130: 58.65
A131: 2026-08-07 | B131: 2026-09-25 | C131: 下跌 | D131: -10.1% | E131: 58.65 | F131: 52.73
A133: XRT
A134: 起始 | B134: 结束 | C134: 阶段 | D134: 幅度 | E134: 起始值 | F134: 结束值
A135: 2025-01-01 | B135: 2025-04-04 | C135: 下跌 | D135: -18.2% | E135: 79.36 | F135: 64.89
A136: 2025-04-04 | B136: 2025-09-05 | C136: 上涨 | D136: +34.6% | E136: 64.89 | F136: 87.35
A137: 2025-09-05 | B137: 2025-11-07 | C137: 下跌 | D137: -8.5% | E137: 87.35 | F137: 79.90
A138: 2025-11-07 | B138: 2026-01-16 | C138: 上涨 | D138: +13.2% | E138: 79.90 | F138: 90.42
A139: 2026-01-16 | B139: 2026-03-27 | C139: 下跌 | D139: -13.1% | E139: 90.42 | F139: 78.58
A140: 2026-03-27 | B140: 2026-04-17 | C140: 上涨 | D140: +10.7% | E140: 78.58 | F140: 86.95
A141: 2026-04-17 | B141: 2026-05-15 | C141: 下跌 | D141: -9.0% | E141: 86.95 | F141: 79.09
A142: 2026-05-15 | B142: 2026-08-07 | C142: 上涨 | D142: +14.8% | E142: 79.09 | F142: 90.82
A143: 2026-08-07 | B143: 2026-09-25 | C143: 下跌 | D143: -9.1% | E143: 90.82 | F143: 82.56

Sheet 地缘政治
A1: 重要地缘政治事件
A2: 时间点/时间段
A3: 详情
A5: （由 /track-prices skill 搜索填充，每列一个事件，向右追加）

Sheet 油价汽油
A1: 油价 & 汽油价格（周度，2025-01-01 起）
A2: Date | B2: Brent($/bbl) | C2: WTI($/bbl) | D2: 全美汽油均价($/gal)
A3: 45658 | B3: 75.93 | C3: 73.13
A4: 45660 | B4: 76.51 | C4: 73.96
A5: 45667 | B5: 79.76 | C5: 76.57 | D5: 3.05
A6: 45674 | B6: 80.79 | C6: 77.88 | D6: 3.04
A7: 45681 | B7: 78.5 | C7: 74.66 | D7: 3.11
A8: 45688 | B8: 76.76 | C8: 72.53 | D8: 3.1
A9: 45695 | B9: 74.66 | C9: 71 | D9: 3.08
A10: 45702 | B10: 74.74 | C10: 70.74 | D10: 3.13
A11: 45709 | B11: 74.43 | C11: 70.4 | D11: 3.15
A12: 45716 | B12: 73.18 | C12: 69.76 | D12: 3.12
A13: 45723 | B13: 70.36 | C13: 67.04 | D13: 3.08
A14: 45730 | B14: 70.58 | C14: 67.18 | D14: 3.07
A15: 45737 | B15: 72.16 | C15: 68.28 | D15: 3.06
A16: 45744 | B16: 73.63 | C16: 69.36 | D16: 3.12
... A97: 46311 | B97: 103.85 | C97: 90.95 | D97: 4.35

Sheet 美债收益率
A1: 美债收益率 2Y/10Y/30Y（周度，2025-01-01 起）
A2: Date | B2: 2Y(%) | C2: 10Y(%) | D2: 30Y(%)
A3: 45658 | B3: 4.25 | C3: 4.57 | D3: 4.8
A4: 45660 | B4: 4.28 | C4: 4.6 | D4: 4.81
A5: 45667 | B5: 4.4 | C5: 4.78 | D5: 4.97
A6: 45674 | B6: 4.27 | C6: 4.61 | D6: 4.84
A7: 45681 | B7: 4.27 | C7: 4.63 | D7: 4.85
A8: 45688 | B8: 4.22 | C8: 4.57 | D8: 4.81
A9: 45695 | B9: 4.29 | C9: 4.49 | D9: 4.69
A10: 45702 | B10: 4.26 | C10: 4.47 | D10: 4.69
A11: 45709 | B11: 4.19 | C11: 4.42 | D11: 4.67
A12: 45716 | B12: 3.99 | C12: 4.23 | D12: 4.52
A13: 45723 | B13: 3.99 | C13: 4.32 | D13: 4.62
A14: 45730 | B14: 4.02 | C14: 4.31 | D14: 4.61
... A96: 46304 | B96: 4.75 | C96: 5.24 | D96: 5.6
A99: 加息/降息重要变化

Sheet 宏观高频数据
A1: 美国宏观高频数据
A3: 一、周度数据（初请失业金）
A4: Date | B4: 初请失业金(千人)
A5: 45661 | B5: 206000
A6: 45668 | B6: 219000
A7: 45675 | B7: 223000
A8: 45682 | B8: 212000
A9: 45689 | B9: 220000
A10: 45696 | B10: 216000
A11: 45703 | B11: 223000
A12: 45710 | B12: 241000
A13: 45717 | B13: 224000
A14: 45724 | B14: 222000
A15: 45731 | B15: 225000
A16: 45738 | B16: 224000
... A96: 46298 | B96: 197000
A99: 二、月度数据
A100: Date | B100: CPI YoY% | C100: 核心CPI YoY% | D100: PPI YoY% | E100: PCE YoY% | F100: 核心PCE YoY% | G100: 非农delta(千人) | H100: 失业率(%) | I100: 零售销售MoM% | J100: 消费者信心 | K100: 信用卡余额YoY%
A101: 45658 | B101: 3 | C101: 3.3 | D101: 2.4 | E101: 2.6 | F101: 2.8 | G101: -48 | H101: 4 | I101: -0.7 | J101: 71.7 | K101: -0.5
A102: 45689 | B102: 2.8 | C102: 3.1 | D102: 1.8 | E102: 2.6 | F102: 2.8 | G102: 42 | H102: 4.2 | I102: -0.5 | J102: 64.7 | K102: -1.2
A103: 45717 | B103: 2.4 | C103: 2.8 | D103: 1.3 | E103: 2.3 | F103: 2.6 | G103: 67 | H103: 4.2 | I103: 1.6 | J103: 57 | K103: -2.1
A104: 45748 | B104: 2.3 | C104: 2.8 | D104: 0.6 | E104: 2.3 | F104: 2.7 | G104: 108 | H104: 4.2 | I104: 0.1 | J104: 52.2 | K104: -1.8
A105: 45778 | B105: 2.4 | C105: 2.8 | D105: 1.3 | E105: 2.5 | F105: 2.8 | G105: 13 | H105: 4.3 | I105: -1.4 | J105: 52.2 | K105: -2.3
A106: 45809 | B106: 2.7 | C106: 2.9 | D106: 1.8 | E106: 2.6 | F106: 2.8 | G106: -20 | H106: 4.1 | I106: 0.9 | J106: 60.7 | K106: -2.2
A107: 45839 | B107: 2.7 | C107: 3.1 | D107: 2 | E107: 2.6 | F107: 2.8 | G107: 64 | H107: 4.3 | I107: 0.9 | J107: 61.7 | K107: -2
A108: 45870 | B108: 2.9 | C108: 3.1 | D108: 2.6 | E108: 2.7 | F108: 2.9 | G108: -70 | H108: 4.3 | I108: 0.3 | J108: 58.2 | K108: -2.4
A109: 45901 | B109: 3 | C109: 3 | D109: 3.7 | E109: 2.8 | F109: 2.8 | G109: 76 | H109: 4.4 | I109: 0.2 | J109: 55.1 | K109: -2.2
A110: 45931 | D110: 3 | E110: 2.7 | F110: 2.7 | G110: -140 | I110: -0.1 | J110: 53.6 | K110: -2.6
A111: 45962 | B111: 3 | C111: 2.9 | D111: 3.4 | E111: 2.7 | F111: 2.7 | G111: 41 | H111: 4.5 | I111: 0.7 | J111: 51 | K111: -1.9
A112: 45992 | B112: 3 | C112: 2.8 | D112: 3.1 | E112: 2.8 | F112: 2.9 | G112: -17 | H112: 4.4 | I112: 0.1 | J112: 52.9 | K112: 2.1
A113: 46023 | B113: 2.8 | C113: 2.9 | D113: 2.4 | E113: 2.7 | F113: 2.9 | G113: 160 | H113: 4.3 | I113: -0.6 | J113: 56.4 | K113: 1.9
A114: 46054 | B114: 2.7 | C114: 2.7 | D114: 3.9 | E114: 2.8 | F114: 3 | G114: -156 | H114: 4.4 | I114: 0.9 | J114: 56.6 | K114: 1.8
A115: 46082 | B115: 3.3 | C115: 2.7 | D115: 6.8 | E115: 3.4 | F115: 3.1 | G115: 214 | H115: 4.3 | I115: 1.7 | J115: 53.3 | K115: 3.5
A116: 46113 | B116: 3.9 | C116: 3 | D116: 9.4 | E116: 3.6 | F116: 3.1 | G116: 148 | H116: 4.3 | I116: 0.6 | J116: 49.8 | K116: 3.9
A117: 46143 | B117: 4.3 | C117: 3 | D117: 12.2 | E117: 3.8 | F117: 3.2 | G117: 63 | H117: 4.3 | I117: 1 | J117: 44.8 | K117: 3.7
A118: 46174 | B118: 3.7 | C118: 2.8 | D118: 9.8 | E118: 3.5 | F118: 3 | G118: 31 | H118: 4.2 | I118: 0.2 | J118: 49.5 | K118: 4
A119: 46204 | B119: 3.5 | C119: 2.8 | D119: 8.7 | E119: 3.4 | F119: 3 | G119: -10 | H119: 4.1 | I119: -0.5 | J119: 55.2 | K119: 3.6
A120: 46235 | B120: 3.7 | C120: 2.8 | D120: 9.9 | E120: 3.4 | F120: 3 | G120: 133 | H120: 4.1 | I120: 1.1 | J120: 51.7 | K120: 3.4
A121: 46266 | G121: 29 | H121: 4.2
A124: 说明：CPI/PPI/PCE/信用卡余额为同比%；零售销售为环比%；非农为环比变化千人。来源 FRED，日期为统计期非发布日。信用卡余额(REVOLSL)=循环信贷总额，反映消费者信用卡支出趋势。

Sheet Charts

Sheet 运动服饰走势
T1: 共 34 只，基期 2025-12-01 = 1

Sheet 奢侈品走势
T1: 共 15 只，基期 2025-12-01 = 1

Sheet 股价分位数
A1: 运动服饰 — 股价历史分位数
A2: 截至 2026-10-16，数据起点 2023-11-27
A3: Ticker | B3: 当前价 | C3: 历史最低 | D3: 历史最高 | E3: 分位数 | F3: 数据周数
A4: LULU.O | B4: 94.5 | C4: 94.46 | D4: 511.29 | E4: 0 | F4: 152
A5: NKE.N | B5: 34.71 | C5: 33.87 | D5: 113.75 | E5: 0.011 | F5: 152
A6: DECK.N | B6: 82.89 | C6: 78.43 | D6: 211.9 | E6: 0.033 | F6: 152
A7: 8111.T | B7: 2167 | C7: 2075 | D7: 3566.57 | E7: 0.062 | F7: 152
A8: 2331.HK | B8: 12.65 | C8: 11.73 | D8: 23 | E8: 0.082 | F8: 152
A9: UAA.N | B9: 4.93 | C9: 4.26 | D9: 10.18 | E9: 0.113 | F9: 152
A10: ADDY | B10: 150.95 | C10: 132.05 | D10: 259.8 | E10: 0.148 | F10: 152
A11: 1368.HK | B11: 3.55 | C11: 2.96 | D11: 6.65 | E11: 0.157 | F11: 152
A12: COLM.O | B12: 57.04 | C12: 49.42 | D12: 92.08 | E12: 0.179 | F12: 152
A13: PUM.DF | B13: 23.04 | C13: 15.57 | D13: 57.08 | E13: 0.18 | F13: 152
A14: 2020.HK | B14: 71.45 | C14: 60.12 | D14: 104.4 | E14: 0.256 | F14: 152
A15: ONON.N | B15: 35.09 | C15: 26.25 | D15: 59.99 | E15: 0.262 | F15: 152
... A35: VSCO.N | B35: 80.06 | C35: 16.28 | D35: 80.06 | E35: 1 | F35: 96
A36: SKX.N | F36: 0
A37: HBI.N | F37: 0
A39: 奢侈品 — 股价历史分位数
A40: 截至 2026-10-16，数据起点 2023-11-27
A41: Ticker | B41: 当前价 | C41: 历史最低 | D41: 历史最高 | E41: 分位数 | F41: 数据周数
A42: MC | B42: 384.3 | C42: 378.55 | D42: 813.18 | E42: 0.013 | F42: 152
A43: MONC | B43: 43.65 | C43: 43.25 | D43: 66.24 | E43: 0.017 | F43: 152
A44: RMS | B44: 1309 | C44: 1283 | D44: 2809 | E44: 0.017 | F44: 152
A45: CPRI | B45: 14.95 | C45: 13.5 | D45: 50.69 | E45: 0.039 | F45: 152
A46: 1913.HK | B46: 36.9 | C46: 34.7 | D46: 69 | E46: 0.064 | F46: 152
A47: GOOS | B47: 11.27 | C47: 10.41 | D47: 20.85 | E47: 0.082 | F47: 152
A48: KER | B48: 214.7 | C48: 164.12 | D48: 397.13 | E48: 0.217 | F48: 152
A49: PVH | B49: 81.35 | C49: 60.87 | D49: 139.98 | E49: 0.259 | F49: 152
A50: VFC | B50: 15 | C50: 10.47 | D50: 25.99 | E50: 0.292 | F50: 152
A51: SFER | B51: 6.93 | C51: 4.44 | D51: 12.71 | E51: 0.301 | F51: 152
A52: RACE | B52: 389.91 | C52: 314.63 | D52: 507.34 | E52: 0.391 | F52: 152
A53: BRBY | B53: 1036.5 | C53: 592.4 | D53: 1522.82 | E53: 0.477 | F53: 152
... A56: ZGN | B56: 12.68 | C56: 6.48 | D56: 14.91 | E56: 0.735 | F56: 152
