Workbook

Sheet Summary
A2: Sportswear
A3: Forward PE | C3: FY-2 | D3: FY-1 | E3: FY | F3: FY+1E | G3: FY+2E
B4: NKE.N | C4: =IF(ISBLANK(NKE.N!C18),"",NKE.N!C18) -> 9.0112281 | D4: =IF(ISBLANK(NKE.N!D18),"",NKE.N!D18) -> 15.956508 | E4: =IF(ISBLANK(NKE.N!E18),"",NKE.N!E18) -> 16.526384 | F4: =IF(ISBLANK(NKE.N!F18),"",NKE.N!F18) -> 27.119324 | G4: =IF(ISBLANK(NKE.N!G18),"",NKE.N!G18) -> 22.940598
B5: ADDY | C5: =IF(ISBLANK(ADDY!C18),"",ADDY!C18) | D5: =IF(ISBLANK(ADDY!D18),"",ADDY!D18) -> 34.577225 | E5: =IF(ISBLANK(ADDY!E18),"",ADDY!E18) -> 19.714179 | F5: =IF(ISBLANK(ADDY!F18),"",ADDY!F18) -> 16.428483 | G5: =IF(ISBLANK(ADDY!G18),"",ADDY!G18) -> 13.077723
B6: ZGN.N | C6: =IF(ISBLANK(ZGN.N!C18),"",ZGN.N!C18) -> 24.885246 | D6: =IF(ISBLANK(ZGN.N!D18),"",ZGN.N!D18) -> 39.428571 | E6: =IF(ISBLANK(ZGN.N!E18),"",ZGN.N!E18) -> 31.957895 | F6: =IF(ISBLANK(ZGN.N!F18),"",ZGN.N!F18) -> 28.914286 | G6: =IF(ISBLANK(ZGN.N!G18),"",ZGN.N!G18) -> 21.380282
B7: WWW.N | C7: =IF(ISBLANK(WWW.N!C18),"",WWW.N!C18) | D7: =IF(ISBLANK(WWW.N!D18),"",WWW.N!D18) -> 33.1875 | E7: =IF(ISBLANK(WWW.N!E18),"",WWW.N!E18) -> 16.59375 | F7: =IF(ISBLANK(WWW.N!F18),"",WWW.N!F18) -> 11.8 | G7: =IF(ISBLANK(WWW.N!G18),"",WWW.N!G18) -> 10.480263
B8: UAA.N | C8: =IF(ISBLANK(UAA.N!C18),"",UAA.N!C18) -> 9.0646552 | D8: =IF(ISBLANK(UAA.N!D18),"",UAA.N!D18) | E8: =IF(ISBLANK(UAA.N!E18),"",UAA.N!E18) | F8: =IF(ISBLANK(UAA.N!F18),"",UAA.N!F18) -> 45.717391 | G8: =IF(ISBLANK(UAA.N!G18),"",UAA.N!G18) -> 25.962963
B9: SHOO.O | C9: =IF(ISBLANK(SHOO.O!C18),"",SHOO.O!C18) -> 18.825581 | D9: =IF(ISBLANK(SHOO.O!D18),"",SHOO.O!D18) -> 19.159763 | E9: =IF(ISBLANK(SHOO.O!E18),"",SHOO.O!E18) -> 71.955556 | F9: =IF(ISBLANK(SHOO.O!F18),"",SHOO.O!F18) -> 20.111801 | G9: =IF(ISBLANK(SHOO.O!G18),"",SHOO.O!G18) -> 16.029703
B10: RL.N | C10: =IF(ISBLANK(RL.N!C18),"",RL.N!C18) -> 35.058824 | D10: =IF(ISBLANK(RL.N!D18),"",RL.N!D18) -> 30.48183 | E10: =IF(ISBLANK(RL.N!E18),"",RL.N!E18) -> 24.068013 | F10: =IF(ISBLANK(RL.N!F18),"",RL.N!F18) -> 19.62565 | G10: =IF(ISBLANK(RL.N!G18),"",RL.N!G18) -> 17.679938
B11: PUM.DF | C11: =IF(ISBLANK(PUM.DF!C18),"",PUM.DF!C18) -> 11.095082 | D11: =IF(ISBLANK(PUM.DF!D18),"",PUM.DF!D18) -> 12 | E11: =IF(ISBLANK(PUM.DF!E18),"",PUM.DF!E18) | F11: =IF(ISBLANK(PUM.DF!F18),"",PUM.DF!F18) | G11: =IF(ISBLANK(PUM.DF!G18),"",PUM.DF!G18) -> 91.459459
B12: ONON.N | C12: =IF(ISBLANK(ONON.N!C18),"",ONON.N!C18) -> 121.5875 | D12: =IF(ISBLANK(ONON.N!D18),"",ONON.N!D18) -> 40.194215 | E12: =IF(ISBLANK(ONON.N!E18),"",ONON.N!E18) -> 47.681373 | F12: =IF(ISBLANK(ONON.N!F18),"",ONON.N!F18) -> 20.349372 | G12: =IF(ISBLANK(ONON.N!G18),"",ONON.N!G18) -> 17.246454
B13: NWL.O | C13: =IF(ISBLANK(NWL.O!C18),"",NWL.O!C18) | D13: =IF(ISBLANK(NWL.O!D18),"",NWL.O!D18) | E13: =IF(ISBLANK(NWL.O!E18),"",NWL.O!E18) | F13: =IF(ISBLANK(NWL.O!F18),"",NWL.O!F18) -> 7.4210526 | G13: =IF(ISBLANK(NWL.O!G18),"",NWL.O!G18) -> 8.2371134
B14: LULU.O | C14: =IF(ISBLANK(LULU.O!C18),"",LULU.O!C18) -> 6.9232258 | D14: =IF(ISBLANK(LULU.O!D18),"",LULU.O!D18) -> 5.9123967 | E14: =IF(ISBLANK(LULU.O!E18),"",LULU.O!E18) -> 6.7960735 | F14: =IF(ISBLANK(LULU.O!F18),"",LULU.O!F18) -> 9.8630515 | G14: =IF(ISBLANK(LULU.O!G18),"",LULU.O!G18) -> 11.224895
B15: LEVI.N | C15: =IF(ISBLANK(LEVI.N!C18),"",LEVI.N!C18) -> 29.268 | D15: =IF(ISBLANK(LEVI.N!D18),"",LEVI.N!D18) -> 34.677725 | E15: =IF(ISBLANK(LEVI.N!E18),"",LEVI.N!E18) -> 12.65917 | F15: =IF(ISBLANK(LEVI.N!F18),"",LEVI.N!F18) -> 11.955882 | G15: =IF(ISBLANK(LEVI.N!G18),"",LEVI.N!G18) -> 11.188073
B16: KTB.N | C16: =IF(ISBLANK(KTB.N!C18),"",KTB.N!C18) -> 15.701299 | D16: =IF(ISBLANK(KTB.N!D18),"",KTB.N!D18) -> 14.743902 | E16: =IF(ISBLANK(KTB.N!E18),"",KTB.N!E18) -> 15.977974 | F16: =IF(ISBLANK(KTB.N!F18),"",KTB.N!F18) -> 12.421233 | G16: =IF(ISBLANK(KTB.N!G18),"",KTB.N!G18) -> 9.9642857
B17: GIL.N | C17: =IF(ISBLANK(GIL.N!C18),"",GIL.N!C18) -> 12.026217 | D17: =IF(ISBLANK(GIL.N!D18),"",GIL.N!D18) -> 16.014963 | E17: =IF(ISBLANK(GIL.N!E18),"",GIL.N!E18) -> 15.817734 | F17: =IF(ISBLANK(GIL.N!F18),"",GIL.N!F18) -> 9.0834512 | G17: =IF(ISBLANK(GIL.N!G18),"",GIL.N!G18) -> 7.691018
B18: GAP.N | C18: =IF(ISBLANK(GAP.N!C18),"",GAP.N!C18) -> 16.657371 | D18: =IF(ISBLANK(GAP.N!D18),"",GAP.N!D18) -> 9.9075829 | E18: =IF(ISBLANK(GAP.N!E18),"",GAP.N!E18) -> 10.247549 | F18: =IF(ISBLANK(GAP.N!F18),"",GAP.N!F18) -> 9.644752 | G18: =IF(ISBLANK(GAP.N!G18),"",GAP.N!G18) -> 8.7836134
B19: DECK.N | C19: =IF(ISBLANK(DECK.N!C18),"",DECK.N!C18) -> 14.852632 | D19: =IF(ISBLANK(DECK.N!D18),"",DECK.N!D18) -> 11.6853 | E19: =IF(ISBLANK(DECK.N!E18),"",DECK.N!E18) -> 11.023438 | F19: =IF(ISBLANK(DECK.N!F18),"",DECK.N!F18) -> 11.001949 | G19: =IF(ISBLANK(DECK.N!G18),"",DECK.N!G18) -> 9.9366197
B20: CROX.O | C20: =IF(ISBLANK(CROX.O!C18),"",CROX.O!C18) -> 6.9520807 | D20: =IF(ISBLANK(CROX.O!D18),"",CROX.O!D18) -> 5.8031579 | E20: =IF(ISBLANK(CROX.O!E18),"",CROX.O!E18) | F20: =IF(ISBLANK(CROX.O!F18),"",CROX.O!F18) -> 8.2406577 | G20: =IF(ISBLANK(CROX.O!G18),"",CROX.O!G18) -> 7.6889819
B21: COLM.O | C21: =IF(ISBLANK(COLM.O!C18),"",COLM.O!C18) -> 11.621514 | D21: =IF(ISBLANK(COLM.O!D18),"",COLM.O!D18) -> 13.080717 | E21: =IF(ISBLANK(COLM.O!E18),"",COLM.O!E18) -> 16.480226 | F21: =IF(ISBLANK(COLM.O!F18),"",COLM.O!F18) -> 12.519313 | G21: =IF(ISBLANK(COLM.O!G18),"",COLM.O!G18) -> 13.630841
B22: BZUN.O | C22: =IF(ISBLANK(BZUN.O!C18),"",BZUN.O!C18) | D22: =IF(ISBLANK(BZUN.O!D18),"",BZUN.O!D18) | E22: =IF(ISBLANK(BZUN.O!E18),"",BZUN.O!E18) | F22: =IF(ISBLANK(BZUN.O!F18),"",BZUN.O!F18) -> 6.8510638 | G22: =IF(ISBLANK(BZUN.O!G18),"",BZUN.O!G18) -> 3.8795181
B23: AS.N | C23: =IF(ISBLANK(AS.N!C18),"",AS.N!C18) | D23: =IF(ISBLANK(AS.N!D18),"",AS.N!D18) -> 222.91781 | E23: =IF(ISBLANK(AS.N!E18),"",AS.N!E18) -> 38.11007 | F23: =IF(ISBLANK(AS.N!F18),"",AS.N!F18) -> 21.697333 | G23: =IF(ISBLANK(AS.N!G18),"",AS.N!G18) -> 17.201903
B24: ANF.N | C24: =IF(ISBLANK(ANF.N!C18),"",ANF.N!C18) -> 19.317073 | D24: =IF(ISBLANK(ANF.N!D18),"",ANF.N!D18) -> 11.194346 | E24: =IF(ISBLANK(ANF.N!E18),"",ANF.N!E18) -> 12.497041 | F24: =IF(ISBLANK(ANF.N!F18),"",ANF.N!F18) -> 11.076923 | G24: =IF(ISBLANK(ANF.N!G18),"",ANF.N!G18) -> 11.01913
B25: VSCO.N | C25: =IF(ISBLANK(VSCO.N!C18),"",VSCO.N!C18) -> 66.678899 | D25: =IF(ISBLANK(VSCO.N!D18),"",VSCO.N!D18) -> 44.048485 | E25: =IF(ISBLANK(VSCO.N!E18),"",VSCO.N!E18) -> 45.142857 | F25: =IF(ISBLANK(VSCO.N!F18),"",VSCO.N!F18) -> 19.590296 | G25: =IF(ISBLANK(VSCO.N!G18),"",VSCO.N!G18) -> 16.332584
B26: 9983.T | C26: =IF(ISBLANK('9983.T'!C18),"",'9983.T'!C18) -> 59.20921 | D26: =IF(ISBLANK('9983.T'!D18),"",'9983.T'!D18) -> 50.866765 | E26: =IF(ISBLANK('9983.T'!E18),"",'9983.T'!E18) -> 40.59922 | F26: =IF(ISBLANK('9983.T'!F18),"",'9983.T'!F18) -> 38.196341 | G26: =IF(ISBLANK('9983.T'!G18),"",'9983.T'!G18) -> 33.862977
B27: 8111.T | C27: =IF(ISBLANK('8111.T'!C18),"",'8111.T'!C18) -> 12.206211 | D27: =IF(ISBLANK('8111.T'!D18),"",'8111.T'!D18) -> 12.124816 | E27: =IF(ISBLANK('8111.T'!E18),"",'8111.T'!E18) -> 12.300946 | F27: =IF(ISBLANK('8111.T'!F18),"",'8111.T'!F18) -> 12.452899 | G27: =IF(ISBLANK('8111.T'!G18),"",'8111.T'!G18) -> 11.643253
B28: 7936.T | C28: =IF(ISBLANK('7936.T'!C18),"",'7936.T'!C18) -> 89.920362 | D28: =IF(ISBLANK('7936.T'!D18),"",'7936.T'!D18) -> 49.708037 | E28: =IF(ISBLANK('7936.T'!E18),"",'7936.T'!E18) -> 32.127948 | F28: =IF(ISBLANK('7936.T'!F18),"",'7936.T'!F18) -> 24.925898 | G28: =IF(ISBLANK('7936.T'!G18),"",'7936.T'!G18) -> 21.156039
B29: 3998.HK | C29: =IF(ISBLANK('3998.HK'!C18),"",'3998.HK'!C18) -> 13.900781 | D29: =IF(ISBLANK('3998.HK'!D18),"",'3998.HK'!D18) -> 12.160216 | E29: =IF(ISBLANK('3998.HK'!E18),"",'3998.HK'!E18) -> 11.087442 | F29: =IF(ISBLANK('3998.HK'!F18),"",'3998.HK'!F18) -> 9.6306063 | G29: =IF(ISBLANK('3998.HK'!G18),"",'3998.HK'!G18) -> 9.0321285
B30: 2331.HK | C30: =IF(ISBLANK('2331.HK'!C18),"",'2331.HK'!C18) -> 8.7188579 | D30: =IF(ISBLANK('2331.HK'!D18),"",'2331.HK'!D18) -> 9.2223697 | E30: =IF(ISBLANK('2331.HK'!E18),"",'2331.HK'!E18) -> 9.4642371 | F30: =IF(ISBLANK('2331.HK'!F18),"",'2331.HK'!F18) -> 10.987347 | G30: =IF(ISBLANK('2331.HK'!G18),"",'2331.HK'!G18) -> 9.5982729
B31: 2020.HK | C31: =IF(ISBLANK('2020.HK'!C18),"",'2020.HK'!C18) -> 16.383841 | D31: =IF(ISBLANK('2020.HK'!D18),"",'2020.HK'!D18) -> 10.753078 | E31: =IF(ISBLANK('2020.HK'!E18),"",'2020.HK'!E18) -> 12.34214 | F31: =IF(ISBLANK('2020.HK'!F18),"",'2020.HK'!F18) -> 10.524978 | G31: =IF(ISBLANK('2020.HK'!G18),"",'2020.HK'!G18) -> 9.9563643
B32: 1836.HK | C32: =IF(ISBLANK('1836.HK'!C18),"",'1836.HK'!C18) -> 9.3758865 | D32: =IF(ISBLANK('1836.HK'!D18),"",'1836.HK'!D18) -> 7.7309942 | E32: =IF(ISBLANK('1836.HK'!E18),"",'1836.HK'!E18) -> 9.5797101 | F32: =IF(ISBLANK('1836.HK'!F18),"",'1836.HK'!F18) -> 10.66129 | G32: =IF(ISBLANK('1836.HK'!G18),"",'1836.HK'!G18) -> 9.3758865
B33: 1368.HK | C33: =IF(ISBLANK('1368.HK'!C18),"",'1368.HK'!C18) -> 7.9912621 | D33: =IF(ISBLANK('1368.HK'!D18),"",'1368.HK'!D18) -> 6.6486268 | E33: =IF(ISBLANK('1368.HK'!E18),"",'1368.HK'!E18) -> 5.9992711 | F33: =IF(ISBLANK('1368.HK'!F18),"",'1368.HK'!F18) -> 6.8307054 | G33: =IF(ISBLANK('1368.HK'!G18),"",'1368.HK'!G18) -> 6.0388848
B34: 1361.HK | C34: =IF(ISBLANK('1361.HK'!C18),"",'1361.HK'!C18) -> 8.8137357 | D34: =IF(ISBLANK('1361.HK'!D18),"",'1361.HK'!D18) -> 7.3716275 | E34: =IF(ISBLANK('1361.HK'!E18),"",'1361.HK'!E18) -> 6.4705882 | F34: =IF(ISBLANK('1361.HK'!F18),"",'1361.HK'!F18) -> 5.4857513 | G34: =IF(ISBLANK('1361.HK'!G18),"",'1361.HK'!G18) -> 4.9619215
B35: 002832.SZ | C35: =IF(ISBLANK('002832.SZ'!C18),"",'002832.SZ'!C18) -> 16.763996 | D35: =IF(ISBLANK('002832.SZ'!D18),"",'002832.SZ'!D18) -> 19.554417 | E35: =IF(ISBLANK('002832.SZ'!E18),"",'002832.SZ'!E18) -> 27.716878 | F35: =IF(ISBLANK('002832.SZ'!F18),"",'002832.SZ'!F18) -> 20.417112 | G35: =IF(ISBLANK('002832.SZ'!G18),"",'002832.SZ'!G18) -> 16.528139
A37: Forward PS | C37: FY-2 | D37: FY-1 | E37: FY | F37: FY+1E | G37: FY+2E
B38: NKE.N | C38: =IF(ISBLANK(NKE.N!C19),"",NKE.N!C19) -> 1.0000389 | D38: =IF(ISBLANK(NKE.N!D19),"",NKE.N!D19) -> 1.109158 | E38: =IF(ISBLANK(NKE.N!E19),"",NKE.N!E19) -> 1.1070305 | F38: =IF(ISBLANK(NKE.N!F19),"",NKE.N!F19) -> 1.1966824 | G38: =IF(ISBLANK(NKE.N!G19),"",NKE.N!G19) -> 1.191519
B39: ADDY | C39: =IF(ISBLANK(ADDY!C19),"",ADDY!C19) -> 1.2328837 | D39: =IF(ISBLANK(ADDY!D19),"",ADDY!D19) -> 1.1154415 | E39: =IF(ISBLANK(ADDY!E19),"",ADDY!E19) -> 1.0647294 | F39: =IF(ISBLANK(ADDY!F19),"",ADDY!F19) -> 0.98062289 | G39: =IF(ISBLANK(ADDY!G19),"",ADDY!G19) -> 0.91452607
B40: ZGN.N | C40: =IF(ISBLANK(ZGN.N!C19),"",ZGN.N!C19) -> 1.5937008 | D40: =IF(ISBLANK(ZGN.N!D19),"",ZGN.N!D19) -> 1.559322 | E40: =IF(ISBLANK(ZGN.N!E19),"",ZGN.N!E19) -> 1.6491037 | F40: =IF(ISBLANK(ZGN.N!F19),"",ZGN.N!F19) -> 1.5134596 | G40: =IF(ISBLANK(ZGN.N!G19),"",ZGN.N!G19) -> 1.3952206
B41: WWW.N | C41: =IF(ISBLANK(WWW.N!C19),"",WWW.N!C19) -> 0.71020954 | D41: =IF(ISBLANK(WWW.N!D19),"",WWW.N!D19) -> 0.90769231 | E41: =IF(ISBLANK(WWW.N!E19),"",WWW.N!E19) -> 0.85005336 | F41: =IF(ISBLANK(WWW.N!F19),"",WWW.N!F19) -> 0.79610195 | G41: =IF(ISBLANK(WWW.N!G19),"",WWW.N!G19) -> 0.75354778
B42: UAA.N | C42: =IF(ISBLANK(UAA.N!C19),"",UAA.N!C19) -> 0.36881796 | D42: =IF(ISBLANK(UAA.N!D19),"",UAA.N!D19) -> 0.40708479 | E42: =IF(ISBLANK(UAA.N!E19),"",UAA.N!E19) -> 0.42347966 | F42: =IF(ISBLANK(UAA.N!F19),"",UAA.N!F19) -> 0.44479695 | G42: =IF(ISBLANK(UAA.N!G19),"",UAA.N!G19) -> 0.43666944
B43: SHOO.O | C43: =IF(ISBLANK(SHOO.O!C19),"",SHOO.O!C19) -> 1.6337033 | D43: =IF(ISBLANK(SHOO.O!D19),"",SHOO.O!D19) -> 1.4183092 | E43: =IF(ISBLANK(SHOO.O!E19),"",SHOO.O!E19) -> 1.2839017 | F43: =IF(ISBLANK(SHOO.O!F19),"",SHOO.O!F19) -> 1.1266527 | G43: =IF(ISBLANK(SHOO.O!G19),"",SHOO.O!G19) -> 1.0475574
B44: RL.N | C44: =IF(ISBLANK(RL.N!C19),"",RL.N!C19) -> 3.4154728 | D44: =IF(ISBLANK(RL.N!D19),"",RL.N!D19) -> 3.1993219 | E44: =IF(ISBLANK(RL.N!E19),"",RL.N!E19) -> 2.791225 | F44: =IF(ISBLANK(RL.N!F19),"",RL.N!F19) -> 2.6071141 | G44: =IF(ISBLANK(RL.N!G19),"",RL.N!G19) -> 2.4760031
B45: PUM.DF | C45: =IF(ISBLANK(PUM.DF!C19),"",PUM.DF!C19) -> 0.39339688 | D45: =IF(ISBLANK(PUM.DF!D19),"",PUM.DF!D19) -> 0.38380401 | E45: =IF(ISBLANK(PUM.DF!E19),"",PUM.DF!E19) -> 0.46381579 | F45: =IF(ISBLANK(PUM.DF!F19),"",PUM.DF!F19) -> 0.48965417 | G45: =IF(ISBLANK(PUM.DF!G19),"",PUM.DF!G19) -> 0.46528255
B46: ONON.N | C46: =IF(ISBLANK(ONON.N!C19),"",ONON.N!C19) -> 5.4280134 | D46: =IF(ISBLANK(ONON.N!D19),"",ONON.N!D19) -> 4.1962899 | E46: =IF(ISBLANK(ONON.N!E19),"",ONON.N!E19) -> 3.2272727 | F46: =IF(ISBLANK(ONON.N!F19),"",ONON.N!F19) -> 2.7688585 | G46: =IF(ISBLANK(ONON.N!G19),"",ONON.N!G19) -> 2.3270335
B47: NWL.O | C47: =IF(ISBLANK(NWL.O!C19),"",NWL.O!C19) -> 0.29472519 | D47: =IF(ISBLANK(NWL.O!D19),"",NWL.O!D19) -> 0.3161435 | E47: =IF(ISBLANK(NWL.O!E19),"",NWL.O!E19) -> 0.33273182 | F47: =IF(ISBLANK(NWL.O!F19),"",NWL.O!F19) -> 0.32701228 | G47: =IF(ISBLANK(NWL.O!G19),"",NWL.O!G19) -> 0.32226405
B48: LULU.O | C48: =IF(ISBLANK(LULU.O!C19),"",LULU.O!C19) -> 1.1156045 | D48: =IF(ISBLANK(LULU.O!D19),"",LULU.O!D19) -> 1.0135059 | E48: =IF(ISBLANK(LULU.O!E19),"",LULU.O!E19) -> 0.96649554 | F48: =IF(ISBLANK(LULU.O!F19),"",LULU.O!F19) -> 1.0256141 | G48: =IF(ISBLANK(LULU.O!G19),"",LULU.O!G19) -> 1.0411371
B49: LEVI.N | C49: =IF(ISBLANK(LEVI.N!C19),"",LEVI.N!C19) -> 1.1841722 | D49: =IF(ISBLANK(LEVI.N!D19),"",LEVI.N!D19) -> 1.1513769 | E49: =IF(ISBLANK(LEVI.N!E19),"",LEVI.N!E19) -> 1.1647564 | F49: =IF(ISBLANK(LEVI.N!F19),"",LEVI.N!F19) -> 1.0856083 | G49: =IF(ISBLANK(LEVI.N!G19),"",LEVI.N!G19) -> 1.039199
B50: KTB.N | C50: =IF(ISBLANK(KTB.N!C19),"",KTB.N!C19) -> 1.3912543 | D50: =IF(ISBLANK(KTB.N!D19),"",KTB.N!D19) -> 1.3907209 | E50: =IF(ISBLANK(KTB.N!E19),"",KTB.N!E19) -> 1.1499683 | F50: =IF(ISBLANK(KTB.N!F19),"",KTB.N!F19) -> 1.342836 | G50: =IF(ISBLANK(KTB.N!G19),"",KTB.N!G19) -> 1.2879972
B51: GIL.N | C51: =IF(ISBLANK(GIL.N!C19),"",GIL.N!C19) -> 2.0093867 | D51: =IF(ISBLANK(GIL.N!D19),"",GIL.N!D19) -> 1.963314 | E51: =IF(ISBLANK(GIL.N!E19),"",GIL.N!E19) -> 1.745583 | F51: =IF(ISBLANK(GIL.N!F19),"",GIL.N!F19) -> 1.0724783 | G51: =IF(ISBLANK(GIL.N!G19),"",GIL.N!G19) -> 1.0376474
B52: GAP.N | C52: =IF(ISBLANK(GAP.N!C19),"",GAP.N!C19) -> 0.56162267 | D52: =IF(ISBLANK(GAP.N!D19),"",GAP.N!D19) -> 0.55428874 | E52: =IF(ISBLANK(GAP.N!E19),"",GAP.N!E19) -> 0.54418847 | F52: =IF(ISBLANK(GAP.N!F19),"",GAP.N!F19) -> 0.53809524 | G52: =IF(ISBLANK(GAP.N!G19),"",GAP.N!G19) -> 0.52259234
B53: DECK.N | C53: =IF(ISBLANK(DECK.N!C19),"",DECK.N!C19) -> 2.6324627 | D53: =IF(ISBLANK(DECK.N!D19),"",DECK.N!D19) -> 2.263939 | E53: =IF(ISBLANK(DECK.N!E19),"",DECK.N!E19) -> 2.0628655 | F53: =IF(ISBLANK(DECK.N!F19),"",DECK.N!F19) -> 1.9187489 | G53: =IF(ISBLANK(DECK.N!G19),"",DECK.N!G19) -> 1.7880564
B54: CROX.O | C54: =IF(ISBLANK(CROX.O!C19),"",CROX.O!C19) -> 1.391469 | D54: =IF(ISBLANK(CROX.O!D19),"",CROX.O!D19) -> 1.3439785 | E54: =IF(ISBLANK(CROX.O!E19),"",CROX.O!E19) -> 1.3642663 | F54: =IF(ISBLANK(CROX.O!F19),"",CROX.O!F19) -> 1.3446341 | G54: =IF(ISBLANK(CROX.O!G19),"",CROX.O!G19) -> 1.312619
B55: COLM.O | C55: =IF(ISBLANK(COLM.O!C19),"",COLM.O!C19) -> 0.8365357 | D55: =IF(ISBLANK(COLM.O!D19),"",COLM.O!D19) -> 0.86583556 | E55: =IF(ISBLANK(COLM.O!E19),"",COLM.O!E19) -> 0.85869885 | F55: =IF(ISBLANK(COLM.O!F19),"",COLM.O!F19) -> 0.84233324 | G55: =IF(ISBLANK(COLM.O!G19),"",COLM.O!G19) -> 0.81640078
B56: BZUN.O | C56: =IF(ISBLANK(BZUN.O!C19),"",BZUN.O!C19) -> 0.14616432 | D56: =IF(ISBLANK(BZUN.O!D19),"",BZUN.O!D19) -> 0.13670134 | E56: =IF(ISBLANK(BZUN.O!E19),"",BZUN.O!E19) -> 0.12951232 | F56: =IF(ISBLANK(BZUN.O!F19),"",BZUN.O!F19) -> 0.11995902 | G56: =IF(ISBLANK(BZUN.O!G19),"",BZUN.O!G19) -> 0.11200974
B57: AS.N | C57: =IF(ISBLANK(AS.N!C19),"",AS.N!C19) -> 3.6984091 | D57: =IF(ISBLANK(AS.N!D19),"",AS.N!D19) -> 3.1396874 | E57: =IF(ISBLANK(AS.N!E19),"",AS.N!E19) -> 2.4783734 | F57: =IF(ISBLANK(AS.N!F19),"",AS.N!F19) -> 1.9864502 | G57: =IF(ISBLANK(AS.N!G19),"",AS.N!G19) -> 1.7142105
B58: ANF.N | C58: =IF(ISBLANK(ANF.N!C19),"",ANF.N!C19) -> 1.480028 | D58: =IF(ISBLANK(ANF.N!D19),"",ANF.N!D19) -> 1.2802586 | E58: =IF(ISBLANK(ANF.N!E19),"",ANF.N!E19) -> 1.2031903 | F58: =IF(ISBLANK(ANF.N!F19),"",ANF.N!F19) -> 1.1459577 | G58: =IF(ISBLANK(ANF.N!G19),"",ANF.N!G19) -> 1.0982839
B59: VSCO.N | C59: =IF(ISBLANK(VSCO.N!C19),"",VSCO.N!C19) -> 1.1756713 | D59: =IF(ISBLANK(VSCO.N!D19),"",VSCO.N!D19) -> 1.1666132 | E59: =IF(ISBLANK(VSCO.N!E19),"",VSCO.N!E19) -> 1.1091103 | F59: =IF(ISBLANK(VSCO.N!F19),"",VSCO.N!F19) -> 1.0176421 | G59: =IF(ISBLANK(VSCO.N!G19),"",VSCO.N!G19) -> 0.97321907
B60: 9983.T | C60: =IF(ISBLANK('9983.T'!C19),"",'9983.T'!C19) -> 7.096305 | D60: =IF(ISBLANK('9983.T'!D19),"",'9983.T'!D19) -> 6.4771399 | E60: =IF(ISBLANK('9983.T'!E19),"",'9983.T'!E19) -> 5.5573064 | F60: =IF(ISBLANK('9983.T'!F19),"",'9983.T'!F19) -> 4.9666254 | G60: =IF(ISBLANK('9983.T'!G19),"",'9983.T'!G19) -> 4.4840859
B61: 8111.T | C61: =IF(ISBLANK('8111.T'!C19),"",'8111.T'!C19) -> 2.3354031 | D61: =IF(ISBLANK('8111.T'!D19),"",'8111.T'!D19) -> 2.2401194 | E61: =IF(ISBLANK('8111.T'!E19),"",'8111.T'!E19) -> 2.1552328 | F61: =IF(ISBLANK('8111.T'!F19),"",'8111.T'!F19) -> 2.1064306 | G61: =IF(ISBLANK('8111.T'!G19),"",'8111.T'!G19) -> 1.9900691
B62: 7936.T | C62: =IF(ISBLANK('7936.T'!C19),"",'7936.T'!C19) -> 5.559819 | D62: =IF(ISBLANK('7936.T'!D19),"",'7936.T'!D19) -> 4.6743544 | E62: =IF(ISBLANK('7936.T'!E19),"",'7936.T'!E19) -> 3.9112202 | F62: =IF(ISBLANK('7936.T'!F19),"",'7936.T'!F19) -> 3.0473073 | G62: =IF(ISBLANK('7936.T'!G19),"",'7936.T'!G19) -> 2.714979
B63: 3998.HK | C63: =IF(ISBLANK('3998.HK'!C19),"",'3998.HK'!C19) -> 1.8407427 | D63: =IF(ISBLANK('3998.HK'!D19),"",'3998.HK'!D19) -> 1.6497182 | E63: =IF(ISBLANK('3998.HK'!E19),"",'3998.HK'!E19) -> 1.6192732 | F63: =IF(ISBLANK('3998.HK'!F19),"",'3998.HK'!F19) -> 1.4266017 | G63: =IF(ISBLANK('3998.HK'!G19),"",'3998.HK'!G19) -> 1.3450957
B64: 2331.HK | C64: =IF(ISBLANK('2331.HK'!C19),"",'2331.HK'!C19) -> 1.0068483 | D64: =IF(ISBLANK('2331.HK'!D19),"",'2331.HK'!D19) -> 0.96899847 | E64: =IF(ISBLANK('2331.HK'!E19),"",'2331.HK'!E19) -> 0.93881343 | F64: =IF(ISBLANK('2331.HK'!F19),"",'2331.HK'!F19) -> 0.87043824 | G64: =IF(ISBLANK('2331.HK'!G19),"",'2331.HK'!G19) -> 0.82790573
B65: 2020.HK | C65: =IF(ISBLANK('2020.HK'!C19),"",'2020.HK'!C19) -> 2.6894766 | D65: =IF(ISBLANK('2020.HK'!D19),"",'2020.HK'!D19) -> 2.3678451 | E65: =IF(ISBLANK('2020.HK'!E19),"",'2020.HK'!E19) -> 2.0905895 | F65: =IF(ISBLANK('2020.HK'!F19),"",'2020.HK'!F19) -> 1.8099159 | G65: =IF(ISBLANK('2020.HK'!G19),"",'2020.HK'!G19) -> 1.665293
B66: 1836.HK | C66: =IF(ISBLANK('1836.HK'!C19),"",'1836.HK'!C19) -> 0.88546551 | D66: =IF(ISBLANK('1836.HK'!D19),"",'1836.HK'!D19) -> 0.85566343 | E66: =IF(ISBLANK('1836.HK'!E19),"",'1836.HK'!E19) -> 0.84203822 | F66: =IF(ISBLANK('1836.HK'!F19),"",'1836.HK'!F19) -> 0.83301827 | G66: =IF(ISBLANK('1836.HK'!G19),"",'1836.HK'!G19) -> 0.79399399
B67: 1368.HK | C67: =IF(ISBLANK('1368.HK'!C19),"",'1368.HK'!C19) -> 0.57374878 | D67: =IF(ISBLANK('1368.HK'!D19),"",'1368.HK'!D19) -> 0.60624586 | E67: =IF(ISBLANK('1368.HK'!E19),"",'1368.HK'!E19) -> 0.58165501 | F67: =IF(ISBLANK('1368.HK'!F19),"",'1368.HK'!F19) -> 0.56222678 | G67: =IF(ISBLANK('1368.HK'!G19),"",'1368.HK'!G19) -> 0.53580263
B68: 1361.HK | C68: =IF(ISBLANK('1361.HK'!C19),"",'1361.HK'!C19) -> 1.00558 | D68: =IF(ISBLANK('1361.HK'!D19),"",'1361.HK'!D19) -> 0.84077824 | E68: =IF(ISBLANK('1361.HK'!E19),"",'1361.HK'!E19) -> 0.75991387 | F68: =IF(ISBLANK('1361.HK'!F19),"",'1361.HK'!F19) -> 0.66337719 | G68: =IF(ISBLANK('1361.HK'!G19),"",'1361.HK'!G19) -> 0.60957179
B69: 002832.SZ | C69: =IF(ISBLANK('002832.SZ'!C19),"",'002832.SZ'!C19) -> 4.3190045 | D69: =IF(ISBLANK('002832.SZ'!D19),"",'002832.SZ'!D19) -> 3.8141858 | E69: =IF(ISBLANK('002832.SZ'!E19),"",'002832.SZ'!E19) -> 3.540102 | F69: =IF(ISBLANK('002832.SZ'!F19),"",'002832.SZ'!F19) -> 2.9273529 | G69: =IF(ISBLANK('002832.SZ'!G19),"",'002832.SZ'!G19) -> 2.5436376
A72: Luxury
A73: Forward PE | C73: FY-2 | D73: FY-1 | E73: FY | F73: FY+1E | G73: FY+2E
B74: VFC | C74: =IF(ISBLANK(VFC!C18),"",VFC!C18) | D74: =IF(ISBLANK(VFC!D18),"",VFC!D18) | E74: =IF(ISBLANK(VFC!E18),"",VFC!E18) -> 23.12549 | F74: =IF(ISBLANK(VFC!F18),"",VFC!F18) -> 14.007126 | G74: =IF(ISBLANK(VFC!G18),"",VFC!G18) -> 11.318618
B75: CFR | C75: =IF(ISBLANK(CFR!C18),"",CFR!C18) -> 45.618967 | D75: =IF(ISBLANK(CFR!D18),"",CFR!D18) -> 39.168302 | E75: =IF(ISBLANK(CFR!E18),"",CFR!E18) -> 30.927669 | F75: =IF(ISBLANK(CFR!F18),"",CFR!F18) -> 24.30679 | G75: =IF(ISBLANK(CFR!G18),"",CFR!G18) -> 21.156882
B76: 1913.HK | C76: =IF(ISBLANK('1913.HK'!C18),"",'1913.HK'!C18) -> 16.104322 | D76: =IF(ISBLANK('1913.HK'!D18),"",'1913.HK'!D18) -> 12.879619 | E76: =IF(ISBLANK('1913.HK'!E18),"",'1913.HK'!E18) -> 12.683099 | F76: =IF(ISBLANK('1913.HK'!F18),"",'1913.HK'!F18) -> 14.762295 | G76: =IF(ISBLANK('1913.HK'!G18),"",'1913.HK'!G18) -> 13.423602
B77: MONC | C77: =IF(ISBLANK(MONC!C18),"",MONC!C18) -> 19.408497 | D77: =IF(ISBLANK(MONC!D18),"",MONC!D18) -> 18.559375 | E77: =IF(ISBLANK(MONC!E18),"",MONC!E18) -> 18.944179 | F77: =IF(ISBLANK(MONC!F18),"",MONC!F18) -> 18.559375 | G77: =IF(ISBLANK(MONC!G18),"",MONC!G18) -> 17.139971
B78: KER | C78: =IF(ISBLANK(KER!C18),"",KER!C18) -> 8.8293664 | D78: =IF(ISBLANK(KER!D18),"",KER!D18) -> 23.246249 | E78: =IF(ISBLANK(KER!E18),"",KER!E18) -> 365.80556 | F78: =IF(ISBLANK(KER!F18),"",KER!F18) -> 33.723431 | G78: =IF(ISBLANK(KER!G18),"",KER!G18) -> 21.893599
B79: SFER | C79: =IF(ISBLANK(SFER!C18),"",SFER!C18) -> 44.461538 | D79: =IF(ISBLANK(SFER!D18),"",SFER!D18) | E79: =IF(ISBLANK(SFER!E18),"",SFER!E18) | F79: =IF(ISBLANK(SFER!F18),"",SFER!F18) -> 165.14286 | G79: =IF(ISBLANK(SFER!G18),"",SFER!G18) -> 48.166667
B80: RACE | C80: =IF(ISBLANK(RACE!C18),"",RACE!C18) -> 48.890575 | D80: =IF(ISBLANK(RACE!D18),"",RACE!D18) -> 40.217477 | E80: =IF(ISBLANK(RACE!E18),"",RACE!E18) -> 38.328741 | F80: =IF(ISBLANK(RACE!F18),"",RACE!F18) -> 35.567112 | G80: =IF(ISBLANK(RACE!G18),"",RACE!G18) -> 31.76492
B81: RMS | C81: =IF(ISBLANK(RMS!C18),"",RMS!C18) -> 31.646022 | D81: =IF(ISBLANK(RMS!D18),"",RMS!D18) -> 29.638497 | E81: =IF(ISBLANK(RMS!E18),"",RMS!E18) -> 30.156057 | F81: =IF(ISBLANK(RMS!F18),"",RMS!F18) -> 29.446579 | G81: =IF(ISBLANK(RMS!G18),"",RMS!G18) -> 26.650908
B82: MC | C82: =IF(ISBLANK(MC!C18),"",MC!C18) -> 12.50949 | D82: =IF(ISBLANK(MC!D18),"",MC!D18) -> 15.12502 | E82: =IF(ISBLANK(MC!E18),"",MC!E18) -> 17.449807 | F82: =IF(ISBLANK(MC!F18),"",MC!F18) -> 17.349328 | G82: =IF(ISBLANK(MC!G18),"",MC!G18) -> 15.822206
B83: BRBY | C83: =IF(ISBLANK(BRBY!C18),"",BRBY!C18) -> 0.13703704 | D83: =IF(ISBLANK(BRBY!D18),"",BRBY!D18) | E83: =IF(ISBLANK(BRBY!E18),"",BRBY!E18) -> 1.7619048 | F83: =IF(ISBLANK(BRBY!F18),"",BRBY!F18) -> 37 | G83: =IF(ISBLANK(BRBY!G18),"",BRBY!G18) -> 18.5
B84: CPRI | C84: =IF(ISBLANK(CPRI!C18),"",CPRI!C18) | D84: =IF(ISBLANK(CPRI!D18),"",CPRI!D18) | E84: =IF(ISBLANK(CPRI!E18),"",CPRI!E18) -> 18.652174 | F84: =IF(ISBLANK(CPRI!F18),"",CPRI!F18) -> 7.0327869 | G84: =IF(ISBLANK(CPRI!G18),"",CPRI!G18) -> 5.9377163
B85: PVH | C85: =IF(ISBLANK(PVH!C18),"",PVH!C18) -> 5.6490964 | D85: =IF(ISBLANK(PVH!D18),"",PVH!D18) -> 6.2725753 | E85: =IF(ISBLANK(PVH!E18),"",PVH!E18) -> 150.04 | F85: =IF(ISBLANK(PVH!F18),"",PVH!F18) -> 6.7222222 | G85: =IF(ISBLANK(PVH!G18),"",PVH!G18) -> 6.5234783
B86: TPR | C86: =IF(ISBLANK(TPR!C18),"",TPR!C18) -> 28.781863 | D86: =IF(ISBLANK(TPR!D18),"",TPR!D18) -> 128.3388 | E86: =IF(ISBLANK(TPR!E18),"",TPR!E18) -> 15.370419 | F86: =IF(ISBLANK(TPR!F18),"",TPR!F18) -> 14.560446 | G86: =IF(ISBLANK(TPR!G18),"",TPR!G18) -> 13.026068
B87: GOOS | C87: =IF(ISBLANK(GOOS!C18),"",GOOS!C18) -> 18.87931 | D87: =IF(ISBLANK(GOOS!D18),"",GOOS!D18) -> 11.526316 | E87: =IF(ISBLANK(GOOS!E18),"",GOOS!E18) -> 49.772727 | F87: =IF(ISBLANK(GOOS!F18),"",GOOS!F18) -> 10.841584 | G87: =IF(ISBLANK(GOOS!G18),"",GOOS!G18) -> 9.7767857
A89: Forward PS | C89: FY-2 | D89: FY-1 | E89: FY | F89: FY+1E | G89: FY+2E
B90: VFC | C90: =IF(ISBLANK(VFC!C19),"",VFC!C19) -> 0.59469544 | D90: =IF(ISBLANK(VFC!D19),"",VFC!D19) -> 0.62041031 | E90: =IF(ISBLANK(VFC!E19),"",VFC!E19) -> 0.61395107 | F90: =IF(ISBLANK(VFC!F19),"",VFC!F19) -> 0.62132547 | G90: =IF(ISBLANK(VFC!G19),"",VFC!G19) -> 0.60259554
B91: CFR | C91: =IF(ISBLANK(CFR!C19),"",CFR!C19) -> 5.2266201 | D91: =IF(ISBLANK(CFR!D19),"",CFR!D19) -> 5.0353755 | E91: =IF(ISBLANK(CFR!E19),"",CFR!E19) -> 4.806066 | F91: =IF(ISBLANK(CFR!F19),"",CFR!F19) -> 4.2288854 | G91: =IF(ISBLANK(CFR!G19),"",CFR!G19) -> 3.9266791
B92: 1913.HK | C92: =IF(ISBLANK('1913.HK'!C19),"",'1913.HK'!C19) -> 2.2865002 | D92: =IF(ISBLANK('1913.HK'!D19),"",'1913.HK'!D19) -> 1.9893225 | E92: =IF(ISBLANK('1913.HK'!E19),"",'1913.HK'!E19) -> 1.8898216 | F92: =IF(ISBLANK('1913.HK'!F19),"",'1913.HK'!F19) -> 1.7590754 | G92: =IF(ISBLANK('1913.HK'!G19),"",'1913.HK'!G19) -> 1.6795151
B93: MONC | C93: =IF(ISBLANK(MONC!C19),"",MONC!C19) -> 3.980563 | D93: =IF(ISBLANK(MONC!D19),"",MONC!D19) -> 3.8205211 | E93: =IF(ISBLANK(MONC!E19),"",MONC!E19) -> 3.7924649 | F93: =IF(ISBLANK(MONC!F19),"",MONC!F19) -> 3.673987 | G93: =IF(ISBLANK(MONC!G19),"",MONC!G19) -> 3.4379161
B94: KER | C94: =IF(ISBLANK(KER!C19),"",KER!C19) -> 1.3461106 | D94: =IF(ISBLANK(KER!D19),"",KER!D19) -> 1.5318134 | E94: =IF(ISBLANK(KER!E19),"",KER!E19) -> 1.794753 | F94: =IF(ISBLANK(KER!F19),"",KER!F19) -> 1.8015048 | G94: =IF(ISBLANK(KER!G19),"",KER!G19) -> 1.7066027
B95: SFER | C95: =IF(ISBLANK(SFER!C19),"",SFER!C19) -> 1 | D95: =IF(ISBLANK(SFER!D19),"",SFER!D19) -> 1.1169082 | E95: =IF(ISBLANK(SFER!E19),"",SFER!E19) -> 1.1832139 | F95: =IF(ISBLANK(SFER!F19),"",SFER!F19) -> 1.1991701 | G95: =IF(ISBLANK(SFER!G19),"",SFER!G19) -> 1.1502488
B96: RACE | C96: =IF(ISBLANK(RACE!C19),"",RACE!C19) -> 10.253099 | D96: =IF(ISBLANK(RACE!D19),"",RACE!D19) -> 9.1674405 | E96: =IF(ISBLANK(RACE!E19),"",RACE!E19) -> 8.5657711 | F96: =IF(ISBLANK(RACE!F19),"",RACE!F19) -> 8.0700066 | G96: =IF(ISBLANK(RACE!G19),"",RACE!G19) -> 7.4447823
B97: RMS | C97: =IF(ISBLANK(RMS!C19),"",RMS!C19) -> 10.160572 | D97: =IF(ISBLANK(RMS!D19),"",RMS!D19) -> 8.9931444 | E97: =IF(ISBLANK(RMS!E19),"",RMS!E19) -> 8.5255593 | F97: =IF(ISBLANK(RMS!F19),"",RMS!F19) -> 8.1623788 | G97: =IF(ISBLANK(RMS!G19),"",RMS!G19) -> 7.5792222
B98: MC | C98: =IF(ISBLANK(MC!C19),"",MC!C19) -> 2.2032779 | D98: =IF(ISBLANK(MC!D19),"",MC!D19) -> 2.2415243 | E98: =IF(ISBLANK(MC!E19),"",MC!E19) -> 2.3490415 | F98: =IF(ISBLANK(MC!F19),"",MC!F19) -> 2.3617847 | G98: =IF(ISBLANK(MC!G19),"",MC!G19) -> 2.2629828
B99: BRBY | C99: =IF(ISBLANK(BRBY!C19),"",BRBY!C19) -> 0.012466307 | D99: =IF(ISBLANK(BRBY!D19),"",BRBY!D19) -> 0.015034539 | E99: =IF(ISBLANK(BRBY!E19),"",BRBY!E19) -> 0.015289256 | F99: =IF(ISBLANK(BRBY!F19),"",BRBY!F19) -> 0.014584155 | G99: =IF(ISBLANK(BRBY!G19),"",BRBY!G19) -> 0.01380597
B100: CPRI | C100: =IF(ISBLANK(CPRI!C19),"",CPRI!C19) -> 0.38631247 | D100: =IF(ISBLANK(CPRI!D19),"",CPRI!D19) -> 0.38631247 | E100: =IF(ISBLANK(CPRI!E19),"",CPRI!E19) -> 0.49395509 | F100: =IF(ISBLANK(CPRI!F19),"",CPRI!F19) -> 0.50440917 | G100: =IF(ISBLANK(CPRI!G19),"",CPRI!G19) -> 0.49197248
B101: PVH | C101: =IF(ISBLANK(PVH!C19),"",PVH!C19) -> 0.40692124 | D101: =IF(ISBLANK(PVH!D19),"",PVH!D19) -> 0.43349127 | E101: =IF(ISBLANK(PVH!E19),"",PVH!E19) -> 0.41910615 | F101: =IF(ISBLANK(PVH!F19),"",PVH!F19) -> 0.42141332 | G101: =IF(ISBLANK(PVH!G19),"",PVH!G19) -> 0.41442934
B102: TPR | C102: =IF(ISBLANK(TPR!C19),"",TPR!C19) -> 3.5206116 | D102: =IF(ISBLANK(TPR!D19),"",TPR!D19) -> 3.3498788 | E102: =IF(ISBLANK(TPR!E19),"",TPR!E19) -> 2.9342829 | F102: =IF(ISBLANK(TPR!F19),"",TPR!F19) -> 2.7456161 | G102: =IF(ISBLANK(TPR!G19),"",TPR!G19) -> 2.60637
B103: GOOS | C103: =IF(ISBLANK(GOOS!C19),"",GOOS!C19) -> 0.82083958 | D103: =IF(ISBLANK(GOOS!D19),"",GOOS!D19) -> 0.81231454 | E103: =IF(ISBLANK(GOOS!E19),"",GOOS!E19) -> 0.71662304 | F103: =IF(ISBLANK(GOOS!F19),"",GOOS!F19) -> 0.69391635 | G103: =IF(ISBLANK(GOOS!G19),"",GOOS!G19) -> 0.66686967

Sheet template
B3: 公司ticker，名字
B4: End in | F4: 46752 | G4: 47118 | H4: 47483 | N4: xxx | O4: xxx
B5: Fisical year | C5: 2024 | D5: 2025 | E5: 2026 | F5: 2027E | G5: 2028E | H5: 2029E | J5: 26Q1 | K5: 26Q2 | L5: 26Q3 | M5: 26Q4 | N5: 27Q1 | O5: 27Q2
B6: Revenue
B7: yoy
B8: GM
B9: OPM (EBIT margin)
B10: Net Profit (GAAP)
B11: EPS
B14: Date | C14: 46283
B15: Share price ($) | C15: 35.51
B16: Market Cap | C16: =C15*#REF! -> #REF!
B17: Forward PE
B18: Forward PS | C18: =IF(N(C6)=0,"",#REF!/C6) | D18: =IF(N(D6)=0,"",#REF!/D6) | E18: =IF(N(E6)=0,"",#REF!/E6) | F18: =IF(N(F6)=0,"",#REF!/F6) | G18: =IF(N(G6)=0,"",#REF!/G6) | H18: =IF(N(H6)=0,"",#REF!/H6)

Sheet Sportswear>>

Sheet Luxury>>

Sheet NKE.N
B3: NKE.N, NIKE, Inc.
B4: End in | F4: 46535 | G4: 46901 | N4: 46356 | O4: 46446
B5: Fiscal year | C5: 2024 | D5: 2025 | E5: 2026 | F5: 2027E | G5: 2028E | J5: 25Q4 | K5: 26Q1 | L5: 26Q2 | M5: 26Q3 | N5: 26Q4 | O5: 27Q1
B6: Revenue | C6: 51362 | D6: 46309 | E6: 46398 | F6: 42922 | G6: 43108 | J6: 12427 | K6: 11279 | L6: 10972 | M6: 11213
B7: yoy | C7: 0.0028310912 | D7: -0.098380125 | E7: 0.0019218726 | F7: -0.074917973 | G7: 0.0043435696
B8: GM | C8: 0.44560181 | D8: 0.42734674 | E8: 0.42913488 | J8: 0.40597087 | K8: 0.40163135 | L8: 0.49152388 | M8: 0.42789619
B9: OPM (EBIT margin) | C9: 0.12287294 | D9: 0.079941264 | E9: 0.081900082 | J9: 0.080952764 | K9: 0.049029169 | L9: 0.11975939 | M9: 0.079193793
B10: Net Profit (GAAP) | C10: 5700 | D10: 3219 | E10: 3108 | F10: 1894 | G10: 2239 | J10: 792 | K10: 520 | L10: 1069 | M10: 712
B11: NPM | C11: 0.11097699 | D11: 0.069511326 | E11: 0.066985646 | F11: 0.044116844 | G11: 0.051936414 | J11: 0.063732196 | K11: 0.046103378 | L11: 0.097429821 | M11: 0.063497726
B12: EPS (diluted) | C12: 3.76 | D12: 2.17 | E12: 2.1 | F12: 1.27961 | G12: 1.51296 | J12: 0.54 | K12: 0.35 | L12: 0.72 | M12: 0.48
B13: Shares Out (mm) | C13: 3 | D13: 3 | E13: 14865 | F13: 1479.8 | G13: 1479.8 | J13: 3 | K13: 3 | L13: 14865 | M13: 3 | N13: 1479.8 | O13: 1479.8
B15: Date | C15: 46307
B16: Share price (USD) | C16: 34.71
B17: Market Cap (USD mm) | C17: 51364
B18: Forward PE | C18: =IF(OR(C10="",C10<=0),"",C$17/C10) -> 9.0112281 | D18: =IF(OR(D10="",D10<=0),"",C$17/D10) -> 15.956508 | E18: =IF(OR(E10="",E10<=0),"",C$17/E10) -> 16.526384 | F18: =IF(OR(F10="",F10<=0),"",C$17/F10) -> 27.119324 | G18: =IF(OR(G10="",G10<=0),"",C$17/G10) -> 22.940598
B19: Forward PS | C19: =IF(OR(C6="",C6=0),"",C$17/C6) -> 1.0000389 | D19: =IF(OR(D6="",D6=0),"",C$17/D6) -> 1.109158 | E19: =IF(OR(E6="",E6=0),"",C$17/E6) -> 1.1070305 | F19: =IF(OR(F6="",F6=0),"",C$17/F6) -> 1.1966824 | G19: =IF(OR(G6="",G6=0),"",C$17/G6) -> 1.191519
B21: # Analysts (rev) | F21: 28 | G21: 30

Sheet ADDY
B3: ADDY, adidas AG
B4: End in | F4: 46384 | G4: 46749 | N4: 46295 | O4: 46386
B5: Fiscal year | C5: 2023 | D5: 2024 | E5: 2025 | F5: 2026E | G5: 2027E | J5: 25Q3 | K5: 25Q4 | L5: 26Q1 | M5: 26Q2 | N5: 26Q3 | O5: 26Q4
B6: Revenue | C6: 21427 | D6: 23683 | E6: 24811 | F6: 26939 | G6: 28886 | J6: 6630 | K6: 6076 | L6: 6592 | M6: 6743
B7: yoy | C7: -0.048154236 | D7: 0.10528772 | E7: 0.047629101 | F7: 0.085756506 | G7: 0.072289504
B8: GM | C8: 0.47524152 | D8: 0.50774817 | E8: 0.47116198 | J8: 0.51809955 | K8: 0.5082291 | L8: 0.51107403 | M8: 0.52498888
B9: OPM (EBIT margin) | C9: 0.012507584 | D9: 0.056453997 | E9: 0.079440571 | J9: 0.11101056 | K9: 0.023699803 | L9: 0.10709951 | M9: 0.085125315
B10: Net Profit (GAAP) | C10: -75 | D10: 764 | E10: 1340 | F10: 1608 | G10: 2020 | J10: 461 | K10: 81 | L10: 482 | M10: 355
B11: NPM | C11: -0.0035002567 | D11: 0.032259427 | E11: 0.054008303 | F11: 0.059703991 | G11: 0.069916632 | J11: 0.069532428 | K11: 0.013331139 | L11: 0.073118932 | M11: 0.05264719
B12: EPS (diluted) | C12: -0.42 | D12: 4.28 | E12: 7.5 | F12: 9.18726 | G12: 11.53653 | J12: 2.58 | K12: 0.45 | L12: 2.7 | M12: 2.02
B13: Shares Out (mm) | C13: 179 | D13: 179 | E13: 179 | F13: 175.1 | G13: 175.1 | J13: 179 | K13: 179 | L13: 175 | M13: 175 | N13: 175.1 | O13: 175.1
B15: Date | C15: 46307
B16: Share price (EUR) | C16: 150.9
B17: Market Cap (EUR mm) | C17: 26417
B18: Forward PE | C18: =IF(OR(C10="",C10<=0),"",C$17/C10) | D18: =IF(OR(D10="",D10<=0),"",C$17/D10) -> 34.577225 | E18: =IF(OR(E10="",E10<=0),"",C$17/E10) -> 19.714179 | F18: =IF(OR(F10="",F10<=0),"",C$17/F10) -> 16.428483 | G18: =IF(OR(G10="",G10<=0),"",C$17/G10) -> 13.077723
B19: Forward PS | C19: =IF(OR(C6="",C6=0),"",C$17/C6) -> 1.2328837 | D19: =IF(OR(D6="",D6=0),"",C$17/D6) -> 1.1154415 | E19: =IF(OR(E6="",E6=0),"",C$17/E6) -> 1.0647294 | F19: =IF(OR(F6="",F6=0),"",C$17/F6) -> 0.98062289 | G19: =IF(OR(G6="",G6=0),"",C$17/G6) -> 0.91452607
B21: # Analysts (rev) | F21: 28 | G21: 28

Sheet ZGN.N
B3: ZGN.N, Ermenegildo Zegna N.V.
B4: End in | F4: 46384 | G4: 46749 | N4: 46295 | O4: 46386
B5: Fiscal year | C5: 2023 | D5: 2024 | E5: 2025 | F5: 2026E | G5: 2027E | J5: 24Q4 | K5: 25Q2 | L5: 25Q4 | M5: 26Q2 | N5: 26Q3 | O5: 26Q4
B6: Revenue | C6: 1905 | D6: 1947 | E6: 1841 | F6: 2006 | G6: 2176 | J6: 987 | K6: 928 | L6: 982 | M6: 1001
B7: yoy | C7: 0.2757891 | D7: 0.022103921 | E7: -0.054122157 | F7: 0.089443777 | G7: 0.084829115
B8: GM | C8: 0.6428367 | D8: 0.66604782 | E8: 0.55624699 | J8: 0.6681189 | K8: 0.67482888 | L8: 0.56013756 | M8: 0.56018495
B9: OPM (EBIT margin) | C9: 0.10928992 | D9: 0.08571251 | E9: 0.085010175 | J9: 0.095051823 | K9: 0.066127694 | L9: 0.095313957 | M9: 0.075413505
B10: Net Profit (GAAP) | C10: 122 | D10: 77 | E10: 95 | F10: 105 | G10: 142 | J10: 52 | K10: 43 | L10: 55 | M10: 23
B11: NPM | C11: 0.063809857 | D11: 0.039597832 | E11: 0.051426565 | F11: 0.052452385 | G11: 0.065301666 | J11: 0.052708244 | K11: 0.04644116 | L11: 0.056101699 | M11: 0.023460178
B12: EPS (diluted) | C12: 0.48 | D12: 0.31 | E12: 0.37 | F12: 0.39215 | G12: 0.52963 | J12: 0.2 | K12: 0.17 | L12: 0.2 | M12: 0.0869
B13: Shares Out (mm) | C13: 9.2 | D13: 9.2 | E13: 9.2 | F13: 268.3 | G13: 268.3 | J13: 9.2 | K13: 9.2 | L13: 9.2 | M13: 9.2 | N13: 268.3 | O13: 268.3
B15: Date | C15: 46307
B16: Share price (USD) | C16: 12.68
B17: Market Cap (EUR mm) | C17: 3036
B18: Forward PE | C18: =IF(OR(C10="",C10<=0),"",C$17/C10) -> 24.885246 | D18: =IF(OR(D10="",D10<=0),"",C$17/D10) -> 39.428571 | E18: =IF(OR(E10="",E10<=0),"",C$17/E10) -> 31.957895 | F18: =IF(OR(F10="",F10<=0),"",C$17/F10) -> 28.914286 | G18: =IF(OR(G10="",G10<=0),"",C$17/G10) -> 21.380282
B19: Forward PS | C19: =IF(OR(C6="",C6=0),"",C$17/C6) -> 1.5937008 | D19: =IF(OR(D6="",D6=0),"",C$17/D6) -> 1.559322 | E19: =IF(OR(E6="",E6=0),"",C$17/E6) -> 1.6491037 | F19: =IF(OR(F6="",F6=0),"",C$17/F6) -> 1.5134596 | G19: =IF(OR(G6="",G6=0),"",C$17/G6) -> 1.3952206
B21: # Analysts (rev) | F21: 7 | G21: 9

Sheet WWW.N
B3: WWW.N, Wolverine World Wide, Inc.
B4: End in | F4: 46390 | G4: 46755 | N4: 46299 | O4: 46391
B5: Fiscal year | C5: 2023 | D5: 2024 | E5: 2026 | F5: 2027E | G5: 2028E | J5: 25Q3 | K5: 26Q1 | L5: 26Q2 | M5: 26Q3 | N5: 26Q4 | O5: 27Q1
B6: Revenue | C6: 2243 | D6: 1755 | E6: 1874 | F6: 2001 | G6: 2114 | J6: 470 | K6: 518 | L6: 458 | M6: 506
B7: yoy | C7: -0.16459327 | D7: -0.21753088 | E7: 0.067977208 | F7: 0.067586027 | G7: 0.056300222
B8: GM | C8: 0.38900531 | D8: 0.44529915 | E8: 0.46956197 | J8: 0.47352754 | K8: 0.46628019 | L8: 0.47596154 | M8: 0.46465245
B9: OPM (EBIT margin) | C9: -0.030407062 | D9: 0.057549858 | E9: 0.080136584 | J9: 0.084201573 | K9: 0.094492754 | L9: 0.074082168 | M9: 0.093404423
B10: Net Profit (GAAP) | C10: -40 | D10: 48 | E10: 96 | F10: 135 | G10: 152 | J10: 25 | K10: 32 | L10: 20 | M10: 31
B11: NPM | C11: -0.017655714 | D11: 0.027293447 | E11: 0.051112415 | F11: 0.067438693 | G11: 0.071774253 | J11: 0.053370189 | K11: 0.061449275 | L11: 0.044143357 | M11: 0.061611374
B12: EPS (diluted) | C12: -0.51 | D12: 0.58 | E12: 1.14 | F12: 1.64586 | G12: 1.85029 | J12: 0.3 | K12: 0.39 | L12: 0.24 | M12: 0.37
B13: Shares Out (mm) | C13: 113 | D13: 113.7 | E13: 115.5 | F13: 82 | G13: 82 | J13: 115.3 | K13: 115.5 | L13: 116.3 | M13: 116.3 | N13: 82 | O13: 82
B15: Date | C15: 46307
B16: Share price (USD) | C16: 19.43
B17: Market Cap (USD mm) | C17: 1593
B18: Forward PE | C18: =IF(OR(C10="",C10<=0),"",C$17/C10) | D18: =IF(OR(D10="",D10<=0),"",C$17/D10) -> 33.1875 | E18: =IF(OR(E10="",E10<=0),"",C$17/E10) -> 16.59375 | F18: =IF(OR(F10="",F10<=0),"",C$17/F10) -> 11.8 | G18: =IF(OR(G10="",G10<=0),"",C$17/G10) -> 10.480263
B19: Forward PS | C19: =IF(OR(C6="",C6=0),"",C$17/C6) -> 0.71020954 | D19: =IF(OR(D6="",D6=0),"",C$17/D6) -> 0.90769231 | E19: =IF(OR(E6="",E6=0),"",C$17/E6) -> 0.85005336 | F19: =IF(OR(F6="",F6=0),"",C$17/F6) -> 0.79610195 | G19: =IF(OR(G6="",G6=0),"",C$17/G6) -> 0.75354778
B21: # Analysts (rev) | F21: 8 | G21: 8

Sheet UAA.N
B3: UAA.N, Under Armour, Inc.
B4: End in | F4: 46474 | G4: 46840 | N4: 46295 | O4: 46386
B5: Fiscal year | C5: 2024 | D5: 2025 | E5: 2026 | F5: 2027E | G5: 2028E | J5: 25Q3 | K5: 25Q4 | L5: 26Q1 | M5: 26Q2 | N5: 26Q3 | O5: 26Q4
B6: Revenue | C6: 5702 | D6: 5166 | E6: 4966 | F6: 4728 | G6: 4816 | J6: 1342 | K6: 1334 | L6: 1171 | M6: 1098
B7: yoy | C7: -0.03409798 | D7: -0.094041806 | E7: -0.038580519 | F7: -0.047964277 | G7: 0.018596873
B8: GM | C8: 0.46129583 | D8: 0.47883021 | E8: 0.45483079 | J8: 0.47866918 | K8: 0.44712477 | L8: 0.4201284 | M8: 0.54086656
B9: OPM (EBIT margin) | C9: 0.04029391 | D9: 0.033119653 | E9: -0.0071265331 | J9: 0.045595877 | K9: -0.050739168 | L9: -0.021940621 | M9: 0.042570226
B10: Net Profit (GAAP) | C10: 232 | D10: -201 | E10: -496 | F10: 46 | G10: 81 | J10: -19 | K10: -431 | L10: -43 | M10: 1
B11: NPM | C11: 0.040695708 | D11: -0.038962464 | E11: -0.099799854 | F11: 0.0098154026 | G11: 0.016775437 | J11: -0.014014946 | K11: -0.32295901 | L11: -0.037048706 | M11: 0.00049639002
B12: EPS (diluted) | C12: 0.53 | D12: -0.47 | E12: -1.16 | F12: 0.10879 | G12: 0.18939 | J12: -0.0439 | K12: -1.01 | L12: -0.1 | M12: 0.0013
B13: Shares Out (mm) | C13: 0.1 | D13: 0.1 | E13: 0.1 | F13: 426.6 | G13: 426.6 | J13: 0.1 | K13: 0.1 | L13: 0.1 | M13: 0.1 | N13: 426.6 | O13: 426.6
B15: Date | C15: 46307
B16: Share price (USD) | C16: 4.93
B17: Market Cap (USD mm) | C17: 2103
B18: Forward PE | C18: =IF(OR(C10="",C10<=0),"",C$17/C10) -> 9.0646552 | D18: =IF(OR(D10="",D10<=0),"",C$17/D10) | E18: =IF(OR(E10="",E10<=0),"",C$17/E10) | F18: =IF(OR(F10="",F10<=0),"",C$17/F10) -> 45.717391 | G18: =IF(OR(G10="",G10<=0),"",C$17/G10) -> 25.962963
B19: Forward PS | C19: =IF(OR(C6="",C6=0),"",C$17/C6) -> 0.36881796 | D19: =IF(OR(D6="",D6=0),"",C$17/D6) -> 0.40708479 | E19: =IF(OR(E6="",E6=0),"",C$17/E6) -> 0.42347966 | F19: =IF(OR(F6="",F6=0),"",C$17/F6) -> 0.44479695 | G19: =IF(OR(G6="",G6=0),"",C$17/G6) -> 0.43666944
B21: # Analysts (rev) | F21: 19 | G21: 19

Sheet SHOO.O
B3: SHOO.O, Steven Madden, Ltd.
B4: End in | F4: 46384 | G4: 46749 | N4: 46295 | O4: 46386
B5: Fiscal year | C5: 2023 | D5: 2024 | E5: 2025 | F5: 2026E | G5: 2027E | J5: 25Q3 | K5: 25Q4 | L5: 26Q1 | M5: 26Q2 | N5: 26Q3 | O5: 26Q4
B6: Revenue | C6: 1982 | D6: 2283 | E6: 2522 | F6: 2874 | G6: 3091 | J6: 668 | K6: 754 | L6: 650 | M6: 666
B7: yoy | C7: -0.066176439 | D7: 0.15207294 | E7: 0.10451101 | F7: 0.13965877 | G7: 0.075695338
B8: GM | C8: 0.42007548 | D8: 0.41040822 | E8: 0.41121182 | J8: 0.41530975 | K8: 0.42430675 | L8: 0.54487578 | M8: 0.46504772
B9: OPM (EBIT margin) | C9: 0.10760191 | D9: 0.098530965 | E9: 0.02732481 | J9: 0.0469519 | K9: 0.04799257 | L9: 0.14729397 | M9: 0.059049507
B10: Net Profit (GAAP) | C10: 172 | D10: 169 | E10: 45 | F10: 161 | G10: 202 | J10: 21 | K10: 23 | L10: 72 | M10: 28
B11: NPM | C11: 0.086574262 | D11: 0.074198606 | E11: 0.01771195 | F11: 0.056132702 | G11: 0.065247661 | J11: 0.03073629 | K11: 0.03076423 | L11: 0.11055321 | M11: 0.041640573
B12: EPS (diluted) | C12: 2.34 | D12: 2.38 | E12: 0.63 | F12: 2.2071 | G12: 2.75969 | J12: 0.29 | K12: 0.33 | L12: 1.01 | M12: 0.39
B13: Shares Out (mm) | C13: 0 | D13: 0 | E13: 0 | F13: 73.1 | G13: 73.1 | J13: 0 | K13: 0 | L13: 0 | M13: 0 | N13: 73.1 | O13: 73.1
B15: Date | C15: 46307
B16: Share price (USD) | C16: 44.3
B17: Market Cap (USD mm) | C17: 3238
B18: Forward PE | C18: =IF(OR(C10="",C10<=0),"",C$17/C10) -> 18.825581 | D18: =IF(OR(D10="",D10<=0),"",C$17/D10) -> 19.159763 | E18: =IF(OR(E10="",E10<=0),"",C$17/E10) -> 71.955556 | F18: =IF(OR(F10="",F10<=0),"",C$17/F10) -> 20.111801 | G18: =IF(OR(G10="",G10<=0),"",C$17/G10) -> 16.029703
B19: Forward PS | C19: =IF(OR(C6="",C6=0),"",C$17/C6) -> 1.6337033 | D19: =IF(OR(D6="",D6=0),"",C$17/D6) -> 1.4183092 | E19: =IF(OR(E6="",E6=0),"",C$17/E6) -> 1.2839017 | F19: =IF(OR(F6="",F6=0),"",C$17/F6) -> 1.1266527 | G19: =IF(OR(G6="",G6=0),"",C$17/G6) -> 1.0475574
B21: # Analysts (rev) | F21: 6 | G21: 6

Sheet RL.N
B3: RL.N, Ralph Lauren Corporation
B4: End in | F4: 46474 | G4: 46840 | N4: 46292 | O4: 46383
B5: Fiscal year | C5: 2024 | D5: 2025 | E5: 2026 | F5: 2027E | G5: 2028E | J5: 25Q3 | K5: 25Q4 | L5: 26Q1 | M5: 26Q2 | N5: 26Q3 | O5: 26Q4
B6: Revenue | C6: 6631 | D6: 7079 | E6: 8114 | F6: 8687 | G6: 9147 | J6: 2011 | K6: 2406 | L6: 1979 | M6: 1960
B7: yoy | C7: 0.029145198 | D7: 0.067497059 | E7: 0.14627772 | F7: 0.070537026 | G7: 0.053003545
B8: GM | C8: 0.66830534 | D8: 0.68553468 | E8: 0.69865056 | J8: 0.67956433 | K8: 0.69896093 | L8: 0.69682115 | M8: 0.73691193
B9: OPM (EBIT margin) | C9: 0.1140634 | D9: 0.13167114 | E9: 0.14532011 | J9: 0.12219625 | K9: 0.20910224 | L9: 0.079243948 | M9: 0.17471171
B10: Net Profit (GAAP) | C10: 646 | D10: 743 | E10: 941 | F10: 1154 | G10: 1281 | J10: 208 | K10: 362 | L10: 152 | M10: 262
B11: NPM | C11: 0.097460566 | D11: 0.1049442 | E11: 0.11597757 | F11: 0.13286687 | G11: 0.14005638 | J11: 0.10319789 | K11: 0.15029094 | L11: 0.07661596 | M11: 0.13378916
B12: EPS (diluted) | C12: 9.91 | D12: 11.86 | E12: 15.42 | F12: 18.92133 | G12: 21.00234 | J12: 3.32 | K12: 5.92 | L12: 2.49 | M12: 4.36
B13: Shares Out (mm) | C13: 1.3 | D13: 1.3 | E13: 0 | F13: 61 | G13: 61 | J13: 1.3 | K13: 1.3 | L13: 0 | M13: 1.3 | N13: 61 | O13: 61
B15: Date | C15: 46307
B16: Share price (USD) | C16: 371.28
B17: Market Cap (USD mm) | C17: 22648
B18: Forward PE | C18: =IF(OR(C10="",C10<=0),"",C$17/C10) -> 35.058824 | D18: =IF(OR(D10="",D10<=0),"",C$17/D10) -> 30.48183 | E18: =IF(OR(E10="",E10<=0),"",C$17/E10) -> 24.068013 | F18: =IF(OR(F10="",F10<=0),"",C$17/F10) -> 19.62565 | G18: =IF(OR(G10="",G10<=0),"",C$17/G10) -> 17.679938
B19: Forward PS | C19: =IF(OR(C6="",C6=0),"",C$17/C6) -> 3.4154728 | D19: =IF(OR(D6="",D6=0),"",C$17/D6) -> 3.1993219 | E19: =IF(OR(E6="",E6=0),"",C$17/E6) -> 2.791225 | F19: =IF(OR(F6="",F6=0),"",C$17/F6) -> 2.6071141 | G19: =IF(OR(G6="",G6=0),"",C$17/G6) -> 2.4760031
B21: # Analysts (rev) | F21: 13 | G21: 13

Sheet PUM.DF
B3: PUM.DF, PUMA Se
B4: End in | F4: 46384 | G4: 46749 | N4: 46295 | O4: 46386
B5: Fiscal year | C5: 2023 | D5: 2024 | E5: 2025 | F5: 2026E | G5: 2027E | J5: 25Q3 | K5: 25Q4 | L5: 26Q1 | M5: 26Q2 | N5: 26Q3 | O5: 26Q4
B6: Revenue | C6: 8602 | D6: 8817 | E6: 7296 | F6: 6911 | G6: 7273 | J6: 2042 | K6: 1322 | L6: 1864 | M6: 1691
B7: yoy | C7: 0.016136844 | D7: 0.025053187 | E7: -0.17250374 | F7: -0.05285872 | G7: 0.052521248
B8: GM | C8: 0.46346652 | D8: 0.47384657 | E8: 0.44949426 | J8: 0.45144228 | K8: 0.39703547 | L8: 0.47698251 | M8: 0.4804803
B9: OPM (EBIT margin) | C9: 0.072264785 | D9: 0.070543937 | E9: -0.048956991 | J9: 0.021401636 | K9: -0.26204341 | L9: 0.027846335 | M9: -0.03566781
B10: Net Profit (GAAP) | C10: 305 | D10: 282 | E10: -646 | F10: -228 | G10: 37 | J10: -62 | K10: -337 | L10: 26 | M10: -73
B11: NPM | C11: 0.035446482 | D11: 0.031937577 | E11: -0.088470711 | F11: -0.032925194 | G11: 0.0050994522 | J11: -0.030559773 | K11: -0.25455645 | L11: 0.014218264 | M11: -0.043061635
B12: EPS (diluted) | C12: 2.03 | D12: 1.89 | E12: -4.37 | F12: -1.54563 | G12: 0.25196 | J12: -0.4334 | K12: -2.27 | L12: 0.18 | M12: -0.49
B13: Shares Out (mm) | C13: 150.8 | D13: 149.7 | E13: 148 | F13: 147.2 | G13: 147.2 | J13: 0 | K13: 148 | L13: 0 | M13: 148 | N13: 147.2 | O13: 147.2
B15: Date | C15: 46307
B16: Share price (EUR) | C16: 22.99
B17: Market Cap (EUR mm) | C17: 3384
B18: Forward PE | C18: =IF(OR(C10="",C10<=0),"",C$17/C10) -> 11.095082 | D18: =IF(OR(D10="",D10<=0),"",C$17/D10) -> 12 | E18: =IF(OR(E10="",E10<=0),"",C$17/E10) | F18: =IF(OR(F10="",F10<=0),"",C$17/F10) | G18: =IF(OR(G10="",G10<=0),"",C$17/G10) -> 91.459459
B19: Forward PS | C19: =IF(OR(C6="",C6=0),"",C$17/C6) -> 0.39339688 | D19: =IF(OR(D6="",D6=0),"",C$17/D6) -> 0.38380401 | E19: =IF(OR(E6="",E6=0),"",C$17/E6) -> 0.46381579 | F19: =IF(OR(F6="",F6=0),"",C$17/F6) -> 0.48965417 | G19: =IF(OR(G6="",G6=0),"",C$17/G6) -> 0.46528255
B21: # Analysts (rev) | F21: 19 | G21: 19

Sheet ONON.N
B3: ONON.N, On Holding AG
B4: End in | F4: 46384 | G4: 46749 | N4: 46295 | O4: 46386
B5: Fiscal year | C5: 2023 | D5: 2024 | E5: 2025 | F5: 2026E | G5: 2027E | J5: 25Q3 | K5: 25Q4 | L5: 26Q1 | M5: 26Q2 | N5: 26Q3 | O5: 26Q4
B6: Revenue | C6: 1792 | D6: 2318 | E6: 3014 | F6: 3513 | G6: 4180 | J6: 794 | K6: 744 | L6: 850 | M6: 850
B7: yoy | C7: 0.46641028 | D7: 0.29362201 | E7: 0.30009058 | F7: 0.16564826 | G7: 0.18986973
B8: GM | C8: 0.59555828 | D8: 0.60634948 | E8: 0.62826808 | J8: 0.65735146 | K8: 0.63901586 | L8: 0.64226469 | M8: 0.65353405
B9: OPM (EBIT margin) | C9: 0.10055242 | D9: 0.091273778 | E9: 0.12508295 | J9: 0.15697382 | K9: 0.11091691 | L9: 0.14112273 | M9: 0.14042103
B10: Net Profit (GAAP) | C10: 80 | D10: 242 | E10: 204 | F10: 478 | G10: 564 | J10: 119 | K10: 69 | L10: 106 | M10: 105
B11: NPM | C11: 0.044417164 | D11: 0.10451624 | E11: 0.067584605 | F11: 0.1360923 | G11: 0.134929 | J11: 0.14967271 | K11: 0.092901318 | L11: 0.12417358 | M11: 0.12348583
B12: EPS (diluted) | C12: 0.25 | D12: 0.71 | E12: 0.62 | F12: 1.4344 | G12: 1.69216 | J12: 0.36 | K12: 0.21 | L12: 0.32 | M12: 0.31
B13: Shares Out (mm) | C13: 33.5 | D13: 33.7 | E13: 34.1 | F13: 333.3 | G13: 333.3 | J13: 34 | K13: 34.1 | L13: 34 | M13: 34.1 | N13: 333.3 | O13: 333.3
B15: Date | C15: 46307
B16: Share price (USD) | C16: 35.09
B17: Market Cap (CHF mm) | C17: 9727
B18: Forward PE | C18: =IF(OR(C10="",C10<=0),"",C$17/C10) -> 121.5875 | D18: =IF(OR(D10="",D10<=0),"",C$17/D10) -> 40.194215 | E18: =IF(OR(E10="",E10<=0),"",C$17/E10) -> 47.681373 | F18: =IF(OR(F10="",F10<=0),"",C$17/F10) -> 20.349372 | G18: =IF(OR(G10="",G10<=0),"",C$17/G10) -> 17.246454
B19: Forward PS | C19: =IF(OR(C6="",C6=0),"",C$17/C6) -> 5.4280134 | D19: =IF(OR(D6="",D6=0),"",C$17/D6) -> 4.1962899 | E19: =IF(OR(E6="",E6=0),"",C$17/E6) -> 3.2272727 | F19: =IF(OR(F6="",F6=0),"",C$17/F6) -> 2.7688585 | G19: =IF(OR(G6="",G6=0),"",C$17/G6) -> 2.3270335
B21: # Analysts (rev) | F21: 22 | G21: 23

Sheet NWL.O
B3: NWL.O, Newell Brands Inc.
B4: End in | F4: 46384 | G4: 46749 | N4: 46295 | O4: 46386
B5: Fiscal year | C5: 2023 | D5: 2024 | E5: 2025 | F5: 2026E | G5: 2027E | J5: 25Q3 | K5: 25Q4 | L5: 26Q1 | M5: 26Q2 | N5: 26Q3 | O5: 26Q4
B6: Revenue | C6: 8133 | D6: 7582 | E6: 7204 | F6: 7330 | G6: 7438 | J6: 1806 | K6: 1897 | L6: 1549 | M6: 1994
B7: yoy | C7: -0.14018395 | D7: -0.067748678 | E7: -0.04985492 | F7: 0.017450118 | G7: 0.014795199
B8: GM | C8: 0.29988934 | D8: 0.33605909 | E8: 0.33759023 | J8: 0.34108527 | K8: 0.33104902 | L8: 0.33118141 | M8: 0.40722166
B9: OPM (EBIT margin) | C9: -0.010451248 | D9: 0.0088367185 | E9: 0.062048862 | J9: 0.065891473 | K9: 0.071692145 | L9: 0.03227889 | M9: 0.14192578
B10: Net Profit (GAAP) | C10: -388 | D10: -216 | E10: -285 | F10: 323 | G10: 291 | J10: 21 | K10: -315 | L10: -33 | M10: 106
B11: NPM | C11: -0.047706873 | D11: -0.028488525 | E11: -0.039561355 | F11: 0.044086402 | G11: 0.039162464 | J11: 0.011627907 | K11: -0.16605166 | L11: -0.021304067 | M11: 0.053159478
B12: EPS (diluted) | C12: -0.94 | D12: -0.52 | E12: -0.68 | F12: 0.76046 | G12: 0.68552 | J12: 0.0501 | K12: -0.75 | L12: -0.0783 | M12: 0.25
B13: Shares Out (mm) | C13: 440 | D13: 442 | E13: 447 | F13: 424.9 | G13: 424.9 | J13: 447 | K13: 447 | L13: 457 | M13: 457 | N13: 424.9 | O13: 424.9
B15: Date | C15: 46307
B16: Share price (USD) | C16: 5.64
B17: Market Cap (USD mm) | C17: 2397
B18: Forward PE | C18: =IF(OR(C10="",C10<=0),"",C$17/C10) | D18: =IF(OR(D10="",D10<=0),"",C$17/D10) | E18: =IF(OR(E10="",E10<=0),"",C$17/E10) | F18: =IF(OR(F10="",F10<=0),"",C$17/F10) -> 7.4210526 | G18: =IF(OR(G10="",G10<=0),"",C$17/G10) -> 8.2371134
B19: Forward PS | C19: =IF(OR(C6="",C6=0),"",C$17/C6) -> 0.29472519 | D19: =IF(OR(D6="",D6=0),"",C$17/D6) -> 0.3161435 | E19: =IF(OR(E6="",E6=0),"",C$17/E6) -> 0.33273182 | F19: =IF(OR(F6="",F6=0),"",C$17/F6) -> 0.32701228 | G19: =IF(OR(G6="",G6=0),"",C$17/G6) -> 0.32226405
B21: # Analysts (rev) | F21: 7 | G21: 7

Sheet LULU.O
B3: LULU.O, Lululemon Athletica Inc.
B4: End in | F4: 46419 | G4: 46784 | N4: 46328 | O4: 46420
B5: Fiscal year | C5: 2024 | D5: 2025 | E5: 2026 | F5: 2027E | G5: 2028E | J5: 25Q4 | K5: 26Q1 | L5: 26Q2 | M5: 26Q3 | N5: 26Q4 | O5: 27Q1
B6: Revenue | C6: 9619 | D6: 10588 | E6: 11103 | F6: 10463 | G6: 10307 | J6: 2566 | K6: 3641 | L6: 2472 | M6: 2416
B7: yoy | C7: 0.18602511 | D7: 0.10071941 | E7: 0.048589713 | F7: -0.057582507 | G7: -0.014908929
B8: GM | C8: 0.583142 | D8: 0.59224937 | E8: 0.56600544 | J8: 0.55571335 | K8: 0.54874957 | L8: 0.54168004 | M8: 0.60517438
B9: OPM (EBIT margin) | C9: 0.22170853 | D9: 0.2366516 | E9: 0.19910787 | J9: 0.16987513 | K9: 0.22068852 | L9: 0.11205117 | M9: 0.18779896
B10: Net Profit (GAAP) | C10: 1550 | D10: 1815 | E10: 1579 | F10: 1088 | G10: 956 | J10: 307 | K10: 587 | L10: 195 | M10: 329
B11: NPM | C11: 0.16115451 | D11: 0.17138217 | E11: 0.14223542 | F11: 0.10399467 | G11: 0.092772399 | J11: 0.11958089 | K11: 0.16119283 | L11: 0.078915586 | M11: 0.13628861
B12: EPS (diluted) | C12: 12.23 | D12: 14.67 | E12: 13.27 | F12: 9.58246 | G12: 8.42095 | J12: 2.59 | K12: 4.97 | L12: 1.69 | M12: 2.92
B13: Shares Out (mm) | C13: 0.6 | D13: 0.6 | E13: 0.6 | F13: 113.6 | G13: 113.6 | J13: 0.6 | K13: 0.6 | L13: 0.5 | M13: 0.5 | N13: 113.6 | O13: 113.6
B15: Date | C15: 46307
B16: Share price (USD) | C16: 94.5
B17: Market Cap (USD mm) | C17: 10731
B18: Forward PE | C18: =IF(OR(C10="",C10<=0),"",C$17/C10) -> 6.9232258 | D18: =IF(OR(D10="",D10<=0),"",C$17/D10) -> 5.9123967 | E18: =IF(OR(E10="",E10<=0),"",C$17/E10) -> 6.7960735 | F18: =IF(OR(F10="",F10<=0),"",C$17/F10) -> 9.8630515 | G18: =IF(OR(G10="",G10<=0),"",C$17/G10) -> 11.224895
B19: Forward PS | C19: =IF(OR(C6="",C6=0),"",C$17/C6) -> 1.1156045 | D19: =IF(OR(D6="",D6=0),"",C$17/D6) -> 1.0135059 | E19: =IF(OR(E6="",E6=0),"",C$17/E6) -> 0.96649554 | F19: =IF(OR(F6="",F6=0),"",C$17/F6) -> 1.0256141 | G19: =IF(OR(G6="",G6=0),"",C$17/G6) -> 1.0411371
B21: # Analysts (rev) | F21: 24 | G21: 25

Sheet LEVI.N
B3: LEVI.N, Levi Strauss & Co.
B4: End in | F4: 46354 | G4: 46719 | N4: 46356 | O4: 46446
B5: Fiscal year | C5: 2023 | D5: 2024 | E5: 2025 | F5: 2026E | G5: 2027E | J5: 25Q4 | K5: 26Q1 | L5: 26Q2 | M5: 26Q3 | N5: 26Q4 | O5: 27Q1
B6: Revenue | C6: 6179 | D6: 6355 | E6: 6282 | F6: 6740 | G6: 7041 | J6: 1766 | K6: 1742 | L6: 1562 | M6: 1610
B7: yoy | C7: 0.0016859579 | D7: 0.028532125 | E7: -0.011533681 | F7: 0.072968403 | G7: 0.044608752
B8: GM | C8: 0.56897556 | D8: 0.60042799 | E8: 0.61728749 | J8: 0.60754332 | K8: 0.61882353 | L8: 0.62682458 | M8: 0.66211095
B9: OPM (EBIT margin) | C9: 0.057177537 | D9: 0.041555867 | E9: 0.10786374 | J9: 0.11926606 | K9: 0.11403156 | L9: 0.15288092 | M9: 0.13810027
B10: Net Profit (GAAP) | C10: 250 | D10: 211 | E10: 578 | F10: 612 | G10: 654 | J10: 158 | K10: 176 | L10: 87 | M10: 169
B11: NPM | C11: 0.040394886 | D11: 0.033137696 | E11: 0.092024833 | F11: 0.090751714 | G11: 0.092847849 | J11: 0.089477857 | K11: 0.10088953 | L11: 0.055889885 | M11: 0.10474001
B12: EPS (diluted) | C12: 0.63 | D12: 0.53 | E12: 1.46 | F12: 1.56336 | G12: 1.67082 | J12: 0.4 | K12: 0.45 | L12: 0.23 | M12: 0.44
B13: Shares Out (mm) | C13: 0.4 | D13: 0.4 | E13: 0.4 | F13: 391.3 | G13: 391.3 | J13: 0.4 | K13: 0.4 | L13: 0.4 | M13: 0.4 | N13: 391.3 | O13: 391.3
B15: Date | C15: 46307
B16: Share price (USD) | C16: 18.7
B17: Market Cap (USD mm) | C17: 7317
B18: Forward PE | C18: =IF(OR(C10="",C10<=0),"",C$17/C10) -> 29.268 | D18: =IF(OR(D10="",D10<=0),"",C$17/D10) -> 34.677725 | E18: =IF(OR(E10="",E10<=0),"",C$17/E10) -> 12.65917 | F18: =IF(OR(F10="",F10<=0),"",C$17/F10) -> 11.955882 | G18: =IF(OR(G10="",G10<=0),"",C$17/G10) -> 11.188073
B19: Forward PS | C19: =IF(OR(C6="",C6=0),"",C$17/C6) -> 1.1841722 | D19: =IF(OR(D6="",D6=0),"",C$17/D6) -> 1.1513769 | E19: =IF(OR(E6="",E6=0),"",C$17/E6) -> 1.1647564 | F19: =IF(OR(F6="",F6=0),"",C$17/F6) -> 1.0856083 | G19: =IF(OR(G6="",G6=0),"",C$17/G6) -> 1.039199
B21: # Analysts (rev) | F21: 10 | G21: 10

Sheet KTB.N
B3: KTB.N, Kontoor Brands, Inc.
B4: End in | F4: 46390 | G4: 46755 | N4: 46299 | O4: 46391
B5: Fiscal year | C5: 2023 | D5: 2024 | E5: 2026 | F5: 2027E | G5: 2028E | J5: 25Q3 | K5: 26Q1 | L5: 26Q2 | M5: 26Q3 | N5: 26Q4 | O5: 27Q1
B6: Revenue | C6: 2607 | D6: 2608 | E6: 3154 | F6: 2701 | G6: 2816 | J6: 853 | K6: 1019 | L6: 613 | M6: 584
B7: yoy | C7: -0.0091098272 | D7: 4.0652402e-05 | E7: 0.20959373 | F7: -0.14367151 | G7: 0.042426232
B8: GM | C8: 0.41719988 | D8: 0.44545935 | E8: 0.46704649 | J8: 0.4577627 | K8: 0.46901025 | L8: 0.53703275 | M8: 0.56181541
B9: OPM (EBIT margin) | C9: 0.12244388 | D9: 0.13126702 | E9: 0.14140693 | J9: 0.07483694 | K9: 0.14160165 | L9: 0.14691304 | M9: 0.15493387
B10: Net Profit (GAAP) | C10: 231 | D10: 246 | E10: 227 | F10: 292 | G10: 364 | J10: 37 | K10: 74 | L10: 92 | M10: 65
B11: NPM | C11: 0.088589254 | D11: 0.094264486 | E11: 0.072112894 | F11: 0.10817325 | G11: 0.12917494 | J11: 0.043299754 | K11: 0.072393327 | L11: 0.15071855 | M11: 0.11090763
B12: EPS (diluted) | C12: 4.13 | D12: 4.42 | E12: 4.1 | F12: 5.28602 | G12: 6.5801 | J12: 0.66 | K12: 1.33 | L12: 1.67 | M12: 1.18
B13: Shares Out (mm) | C13: 0 | D13: 0 | E13: 0 | F13: 55.3 | G13: 55.3 | J13: 0 | K13: 0 | L13: 0 | M13: 0 | N13: 55.3 | O13: 55.3
B15: Date | C15: 46307
B16: Share price (USD) | C16: 65.62
B17: Market Cap (USD mm) | C17: 3627
B18: Forward PE | C18: =IF(OR(C10="",C10<=0),"",C$17/C10) -> 15.701299 | D18: =IF(OR(D10="",D10<=0),"",C$17/D10) -> 14.743902 | E18: =IF(OR(E10="",E10<=0),"",C$17/E10) -> 15.977974 | F18: =IF(OR(F10="",F10<=0),"",C$17/F10) -> 12.421233 | G18: =IF(OR(G10="",G10<=0),"",C$17/G10) -> 9.9642857
B19: Forward PS | C19: =IF(OR(C6="",C6=0),"",C$17/C6) -> 1.3912543 | D19: =IF(OR(D6="",D6=0),"",C$17/D6) -> 1.3907209 | E19: =IF(OR(E6="",E6=0),"",C$17/E6) -> 1.1499683 | F19: =IF(OR(F6="",F6=0),"",C$17/F6) -> 1.342836 | G19: =IF(OR(G6="",G6=0),"",C$17/G6) -> 1.2879972
B21: # Analysts (rev) | F21: 6 | G21: 6

Sheet GIL.N
B3: GIL.N, Gildan Activewear Inc.
B4: End in | F4: 46384 | G4: 46749 | N4: 46295 | O4: 46386
B5: Fiscal year | C5: 2023 | D5: 2024 | E5: 2025 | F5: 2026E | G5: 2027E | J5: 25Q3 | K5: 25Q4 | L5: 26Q1 | M5: 26Q2 | N5: 26Q3 | O5: 26Q4
B6: Revenue | C6: 3196 | D6: 3271 | E6: 3679 | F6: 5988 | G6: 6189 | J6: 911 | K6: 1094 | L6: 1166 | M6: 1542
B7: yoy | C7: -0.013754435 | D7: 0.023367046 | E7: 0.12497642 | F7: 0.6275544 | G7: 0.033528634
B8: GM | C8: 0.27536874 | D8: 0.3068801 | E8: 0.30177576 | J8: 0.33670998 | K8: 0.28190159 | L8: 0.23873702 | M8: 0.2813863
B9: OPM (EBIT margin) | C9: 0.20146149 | D9: 0.18902981 | E9: 0.19844714 | J9: 0.21097294 | K9: 0.17238538 | L9: 0.051203145 | M9: 0.16806484
B10: Net Profit (GAAP) | C10: 534 | D10: 401 | E10: 406 | F10: 707 | G10: 835 | J10: 120 | K10: 57 | L10: -66 | M10: -49
B11: NPM | C11: 0.16695709 | D11: 0.12256657 | E11: 0.11030836 | F11: 0.1181359 | G11: 0.1348784 | J11: 0.13195624 | K11: 0.052072052 | L11: -0.056425523 | M11: -0.031563377
B12: EPS (diluted) | C12: 3.03 | D12: 2.46 | E12: 2.65 | F12: 4.62354 | G12: 5.45579 | J12: 0.8 | K12: 0.36 | L12: -0.36 | M12: -0.26
B13: Shares Out (mm) | C13: 269.8 | D13: 268.6 | E13: 2295.3 | F13: 153 | G13: 153 | J13: 286.8 | K13: 2295.3 | L13: 2314 | M13: 2311.7 | N13: 153 | O13: 153
B15: Date | C15: 46307
B16: Share price (USD) | C16: 41.97
B17: Market Cap (USD mm) | C17: 6422
B18: Forward PE | C18: =IF(OR(C10="",C10<=0),"",C$17/C10) -> 12.026217 | D18: =IF(OR(D10="",D10<=0),"",C$17/D10) -> 16.014963 | E18: =IF(OR(E10="",E10<=0),"",C$17/E10) -> 15.817734 | F18: =IF(OR(F10="",F10<=0),"",C$17/F10) -> 9.0834512 | G18: =IF(OR(G10="",G10<=0),"",C$17/G10) -> 7.691018
B19: Forward PS | C19: =IF(OR(C6="",C6=0),"",C$17/C6) -> 2.0093867 | D19: =IF(OR(D6="",D6=0),"",C$17/D6) -> 1.963314 | E19: =IF(OR(E6="",E6=0),"",C$17/E6) -> 1.745583 | F19: =IF(OR(F6="",F6=0),"",C$17/F6) -> 1.0724783 | G19: =IF(OR(G6="",G6=0),"",C$17/G6) -> 1.0376474
B21: # Analysts (rev) | F21: 9 | G21: 9

Sheet GAP.N
B3: GAP.N, The Gap, Inc.
B4: End in | F4: 46415 | G4: 46780 | N4: 46327 | O4: 46419
B5: Fiscal year | C5: 2024 | D5: 2025 | E5: 2026 | F5: 2027E | G5: 2028E | J5: 25Q4 | K5: 26Q1 | L5: 26Q2 | M5: 26Q3 | N5: 26Q4 | O5: 27Q1
B6: Revenue | C6: 14889 | D6: 15086 | E6: 15366 | F6: 15540 | G6: 16001 | J6: 3942 | K6: 4236 | L6: 3497 | M6: 3651
B7: yoy | C7: -0.046554816 | D7: 0.013231245 | E7: 0.018560255 | F7: 0.0113258 | G7: 0.029666885
B8: GM | C8: 0.38787024 | D8: 0.4127668 | E8: 0.40791358 | J8: 0.42364282 | K8: 0.38101983 | L8: 0.40520446 | M8: 0.5283484
B9: OPM (EBIT margin) | C9: 0.03761166 | D9: 0.073710725 | E9: 0.072562801 | J9: 0.084728564 | K9: 0.054060434 | L9: 0.12725193 | M9: 0.18515475
B10: Net Profit (GAAP) | C10: 502 | D10: 844 | E10: 816 | F10: 867 | G10: 952 | J10: 236 | K10: 171 | L10: 339 | M10: 501
B11: NPM | C11: 0.033716166 | D11: 0.05594591 | E11: 0.053104256 | F11: 0.055770916 | G11: 0.05949295 | J11: 0.059868087 | K11: 0.040368272 | L11: 0.096940234 | M11: 0.13722268
B12: EPS (diluted) | C12: 1.36 | D12: 2.24 | E12: 2.18 | F12: 2.40759 | G12: 2.64446 | J12: 0.63 | K12: 0.46 | L12: 0.92 | M12: 1.41
B13: Shares Out (mm) | C13: 19 | D13: 19 | E13: 19 | F13: 360 | G13: 360 | J13: 19 | K13: 19 | L13: 18 | M13: 18 | N13: 360 | O13: 360
B15: Date | C15: 46307
B16: Share price (USD) | C16: 23.23
B17: Market Cap (USD mm) | C17: 8362
B18: Forward PE | C18: =IF(OR(C10="",C10<=0),"",C$17/C10) -> 16.657371 | D18: =IF(OR(D10="",D10<=0),"",C$17/D10) -> 9.9075829 | E18: =IF(OR(E10="",E10<=0),"",C$17/E10) -> 10.247549 | F18: =IF(OR(F10="",F10<=0),"",C$17/F10) -> 9.644752 | G18: =IF(OR(G10="",G10<=0),"",C$17/G10) -> 8.7836134
B19: Forward PS | C19: =IF(OR(C6="",C6=0),"",C$17/C6) -> 0.56162267 | D19: =IF(OR(D6="",D6=0),"",C$17/D6) -> 0.55428874 | E19: =IF(OR(E6="",E6=0),"",C$17/E6) -> 0.54418847 | F19: =IF(OR(F6="",F6=0),"",C$17/F6) -> 0.53809524 | G19: =IF(OR(G6="",G6=0),"",C$17/G6) -> 0.52259234
B21: # Analysts (rev) | F21: 14 | G21: 14

Sheet DECK.N
B3: DECK.N, Deckers Outdoor Corporation
B4: End in | F4: 46474 | G4: 46840 | N4: 46295 | O4: 46386
B5: Fiscal year | C5: 2024 | D5: 2025 | E5: 2026 | F5: 2027E | G5: 2028E | J5: 25Q3 | K5: 25Q4 | L5: 26Q1 | M5: 26Q2 | N5: 26Q3 | O5: 26Q4
B6: Revenue | C6: 4288 | D6: 4986 | E6: 5472 | F6: 5883 | G6: 6313 | J6: 1431 | K6: 1958 | L6: 1119 | M6: 1020
B7: yoy | C7: 0.18208572 | D7: 0.16275363 | E7: 0.097617705 | F7: 0.075110385 | G7: 0.073093793
B8: GM | C8: 0.55634791 | D8: 0.57879815 | E8: 0.5770386 | J8: 0.56178329 | K8: 0.59838093 | L8: 0.5758941 | M8: 0.56414469
B9: OPM (EBIT margin) | C9: 0.21631653 | D9: 0.23649895 | E9: 0.23078119 | J9: 0.22820231 | K9: 0.31384451 | L9: 0.14001549 | M9: 0.15232592
B10: Net Profit (GAAP) | C10: 760 | D10: 966 | E10: 1024 | F10: 1026 | G10: 1136 | J10: 268 | K10: 481 | L10: 136 | M10: 130
B11: NPM | C11: 0.17714668 | D11: 0.19377581 | E11: 0.18713736 | F11: 0.17437447 | G11: 0.17989353 | J11: 0.18740879 | K11: 0.24578951 | L11: 0.12111377 | M11: 0.12748215
B12: EPS (diluted) | C12: 4.89 | D12: 6.36 | E12: 7.04 | F12: 7.53331 | G12: 8.33981 | J12: 1.82 | K12: 3.34 | L12: 0.96 | M12: 0.94
B13: Shares Out (mm) | C13: 1.5 | D13: 1.5 | E13: 1.4 | F13: 136.2 | G13: 136.2 | J13: 1.5 | K13: 1.4 | L13: 1.4 | M13: 1.4 | N13: 136.2 | O13: 136.2
B15: Date | C15: 46307
B16: Share price (USD) | C16: 82.89
B17: Market Cap (USD mm) | C17: 11288
B18: Forward PE | C18: =IF(OR(C10="",C10<=0),"",C$17/C10) -> 14.852632 | D18: =IF(OR(D10="",D10<=0),"",C$17/D10) -> 11.6853 | E18: =IF(OR(E10="",E10<=0),"",C$17/E10) -> 11.023438 | F18: =IF(OR(F10="",F10<=0),"",C$17/F10) -> 11.001949 | G18: =IF(OR(G10="",G10<=0),"",C$17/G10) -> 9.9366197
B19: Forward PS | C19: =IF(OR(C6="",C6=0),"",C$17/C6) -> 2.6324627 | D19: =IF(OR(D6="",D6=0),"",C$17/D6) -> 2.263939 | E19: =IF(OR(E6="",E6=0),"",C$17/E6) -> 2.0628655 | F19: =IF(OR(F6="",F6=0),"",C$17/F6) -> 1.9187489 | G19: =IF(OR(G6="",G6=0),"",C$17/G6) -> 1.7880564
B21: # Analysts (rev) | F21: 19 | G21: 19

Sheet CROX.O
B3: CROX.O, Crocs, Inc.
B4: End in | F4: 46384 | G4: 46749 | N4: 46295 | O4: 46386
B5: Fiscal year | C5: 2023 | D5: 2024 | E5: 2025 | F5: 2026E | G5: 2027E | J5: 25Q3 | K5: 25Q4 | L5: 26Q1 | M5: 26Q2 | N5: 26Q3 | O5: 26Q4
B6: Revenue | C6: 3962 | D6: 4102 | E6: 4041 | F6: 4100 | G6: 4200 | J6: 996 | K6: 958 | L6: 921 | M6: 1179
B7: yoy | C7: 0.11458895 | D7: 0.035272277 | E7: -0.014982784 | F7: 0.01464708 | G7: 0.02438524
B8: GM | C8: 0.54957201 | D8: 0.58756571 | E8: 0.58333604 | J8: 0.58517255 | K8: 0.54682553 | L8: 0.5675197 | M8: 0.59408733
B9: OPM (EBIT margin) | C9: 0.26410357 | D9: 0.2491185 | E9: 0.037002737 | J9: 0.20843099 | K9: 0.15287269 | L9: 0.21796351 | M9: 0.2422092
B10: Net Profit (GAAP) | C10: 793 | D10: 950 | E10: -81 | F10: 669 | G10: 717 | J10: 146 | K10: 105 | L10: 138 | M10: 205
B11: NPM | C11: 0.20002438 | D11: 0.23160555 | E11: -0.020095297 | F11: 0.16316497 | G11: 0.17075089 | J11: 0.14635738 | K11: 0.10981684 | L11: 0.14928098 | M11: 0.17371137
B12: EPS (diluted) | C12: 12.91 | D12: 16 | E12: -1.5 | F12: 13.95239 | G12: 14.95712 | J12: 2.72 | K12: 2.05 | L12: 2.74 | M12: 4.15
B13: Shares Out (mm) | C13: 0.1 | D13: 0.1 | E13: 0.1 | F13: 47.9 | G13: 47.9 | J13: 0.1 | K13: 0.1 | L13: 0.1 | M13: 0.1 | N13: 47.9 | O13: 47.9
B15: Date | C15: 46307
B16: Share price (USD) | C16: 114.98
B17: Market Cap (USD mm) | C17: 5513
B18: Forward PE | C18: =IF(OR(C10="",C10<=0),"",C$17/C10) -> 6.9520807 | D18: =IF(OR(D10="",D10<=0),"",C$17/D10) -> 5.8031579 | E18: =IF(OR(E10="",E10<=0),"",C$17/E10) | F18: =IF(OR(F10="",F10<=0),"",C$17/F10) -> 8.2406577 | G18: =IF(OR(G10="",G10<=0),"",C$17/G10) -> 7.6889819
B19: Forward PS | C19: =IF(OR(C6="",C6=0),"",C$17/C6) -> 1.391469 | D19: =IF(OR(D6="",D6=0),"",C$17/D6) -> 1.3439785 | E19: =IF(OR(E6="",E6=0),"",C$17/E6) -> 1.3642663 | F19: =IF(OR(F6="",F6=0),"",C$17/F6) -> 1.3446341 | G19: =IF(OR(G6="",G6=0),"",C$17/G6) -> 1.312619
B21: # Analysts (rev) | F21: 10 | G21: 10

Sheet COLM.O
B3: COLM.O, Columbia Sportswear Company
B4: End in | F4: 46384 | G4: 46749 | N4: 46295 | O4: 46386
B5: Fiscal year | C5: 2023 | D5: 2024 | E5: 2025 | F5: 2026E | G5: 2027E | J5: 25Q3 | K5: 25Q4 | L5: 26Q1 | M5: 26Q2 | N5: 26Q3 | O5: 26Q4
B6: Revenue | C6: 3487 | D6: 3369 | E6: 3397 | F6: 3463 | G6: 3573 | J6: 943 | K6: 1070 | L6: 779 | M6: 614
B7: yoy | C7: 0.0066541537 | D7: -0.034016087 | E7: 0.008441831 | F7: 0.019296276 | G7: 0.031766434
B8: GM | C8: 0.4960801 | D8: 0.50201687 | E8: 0.50238489 | J8: 0.49673865 | K8: 0.51429175 | L8: 0.50700309 | M8: 0.5834215
B9: OPM (EBIT margin) | C9: 0.0889779 | D9: 0.080372394 | E9: 0.060083561 | J9: 0.092895433 | K9: 0.10153477 | L9: 0.048555031 | M9: 0.050270036
B10: Net Profit (GAAP) | C10: 251 | D10: 223 | E10: 177 | F10: 233 | G10: 214 | J10: 52 | K10: 93 | L10: 34 | M10: 27
B11: NPM | C11: 0.072092161 | D11: 0.066281005 | E11: 0.052170447 | F11: 0.067301728 | G11: 0.059990226 | J11: 0.055138639 | K11: 0.087098581 | L11: 0.044040343 | M11: 0.043220447
B12: EPS (diluted) | C12: 4.11 | D12: 3.83 | E12: 3.24 | F12: 4.55677 | G12: 4.19076 | J12: 0.95 | K12: 1.74 | L12: 0.65 | M12: 0.52
B13: Shares Out (mm) | C13: 0 | D13: 0 | E13: 0 | F13: 51.1 | G13: 51.1 | J13: 0 | K13: 0 | L13: 0 | M13: 8.2 | N13: 51.1 | O13: 51.1
B15: Date | C15: 46307
B16: Share price (USD) | C16: 57.04
B17: Market Cap (USD mm) | C17: 2917
B18: Forward PE | C18: =IF(OR(C10="",C10<=0),"",C$17/C10) -> 11.621514 | D18: =IF(OR(D10="",D10<=0),"",C$17/D10) -> 13.080717 | E18: =IF(OR(E10="",E10<=0),"",C$17/E10) -> 16.480226 | F18: =IF(OR(F10="",F10<=0),"",C$17/F10) -> 12.519313 | G18: =IF(OR(G10="",G10<=0),"",C$17/G10) -> 13.630841
B19: Forward PS | C19: =IF(OR(C6="",C6=0),"",C$17/C6) -> 0.8365357 | D19: =IF(OR(D6="",D6=0),"",C$17/D6) -> 0.86583556 | E19: =IF(OR(E6="",E6=0),"",C$17/E6) -> 0.85869885 | F19: =IF(OR(F6="",F6=0),"",C$17/F6) -> 0.84233324 | G19: =IF(OR(G6="",G6=0),"",C$17/G6) -> 0.81640078
B21: # Analysts (rev) | F21: 7 | G21: 7

Sheet BZUN.O
B3: BZUN.O, Baozun Inc.
B4: End in | F4: 46384 | G4: 46749 | N4: 46295 | O4: 46386
B5: Fiscal year | C5: 2023 | D5: 2024 | E5: 2025 | F5: 2026E | G5: 2027E | J5: 25Q3 | K5: 25Q4 | L5: 26Q1 | M5: 26Q2 | N5: 26Q3 | O5: 26Q4
B6: Revenue | C6: 8812 | D6: 9422 | E6: 9945 | F6: 10737 | G6: 11499 | J6: 2156 | K6: 3172 | L6: 2381 | M6: 2735
B7: yoy | C7: 0.048970369 | D7: 0.069248196 | E7: 0.055533993 | F7: 0.079580882 | G7: 0.070930252
B8: GM | C8: 0.44207799 | D8: 0.47619666 | E8: 0.50874513 | J8: 0.52376876 | K8: 0.53668494 | L8: 0.49014241 | M8: 0.74856807
B9: OPM (EBIT margin) | C9: -0.023420301 | D9: -0.012186607 | E9: 0.0075360845 | J9: -0.011880436 | K9: 0.061135265 | L9: 0.0001049953 | M9: 0.016142338
B10: Net Profit (GAAP) | C10: -278 | D10: -185 | E10: -242 | F10: 188 | G10: 332 | J10: -107 | K10: -38 | L10: -7 | M10: 17
B11: NPM | C11: -0.031595732 | D11: -0.019655434 | E11: -0.024342709 | F11: 0.017533832 | G11: 0.028880706 | J11: -0.049672253 | K11: -0.011965407 | L11: -0.0031326397 | M11: 0.006204945
B12: EPS (diluted) | C12: -4.68 | D12: -3.09 | E12: -4.05 | F12: 3.23799 | G12: 5.71173 | J12: -1.86 | K12: -0.66 | L12: -0.13 | M12: 0.29
B13: Shares Out (mm) | C13: 0.1 | D13: 0.1 | E13: 0.1 | F13: 58.1 | G13: 58.1 | J13: 0.1 | K13: 0.1 | L13: 0.1 | M13: 0.1 | N13: 58.1 | O13: 58.1
B15: Date | C15: 46307
B16: Share price (USD) | C16: 3.31
B17: Market Cap (CNY mm) | C17: 1288
B18: Forward PE | C18: =IF(OR(C10="",C10<=0),"",C$17/C10) | D18: =IF(OR(D10="",D10<=0),"",C$17/D10) | E18: =IF(OR(E10="",E10<=0),"",C$17/E10) | F18: =IF(OR(F10="",F10<=0),"",C$17/F10) -> 6.8510638 | G18: =IF(OR(G10="",G10<=0),"",C$17/G10) -> 3.8795181
B19: Forward PS | C19: =IF(OR(C6="",C6=0),"",C$17/C6) -> 0.14616432 | D19: =IF(OR(D6="",D6=0),"",C$17/D6) -> 0.13670134 | E19: =IF(OR(E6="",E6=0),"",C$17/E6) -> 0.12951232 | F19: =IF(OR(F6="",F6=0),"",C$17/F6) -> 0.11995902 | G19: =IF(OR(G6="",G6=0),"",C$17/G6) -> 0.11200974
B21: # Analysts (rev) | F21: 5 | G21: 5

Sheet AS.N
B3: AS.N, Amer Sports, Inc.
B4: End in | F4: 46384 | G4: 46749 | N4: 46295 | O4: 46386
B5: Fiscal year | C5: 2023 | D5: 2024 | E5: 2025 | F5: 2026E | G5: 2027E | J5: 25Q3 | K5: 25Q4 | L5: 26Q1 | M5: 26Q2 | N5: 26Q3 | O5: 26Q4
B6: Revenue | C6: 4400 | D6: 5183 | E6: 6566 | F6: 8192 | G6: 9493 | J6: 1756 | K6: 2101 | L6: 1946 | M6: 1633
B7: yoy | C7: 0.23219086 | D7: 0.17791564 | E7: 0.26679914 | F7: 0.24765096 | G7: 0.15881361
B8: GM | C8: 0.5245205 | D8: 0.55404858 | E8: 0.5763303 | J8: 0.56835393 | K8: 0.5768883 | L8: 0.59902339 | M8: 0.65637633
B9: OPM (EBIT margin) | C9: 0.068743751 | D9: 0.090830166 | E9: 0.10351497 | J9: 0.12292888 | K9: 0.10651563 | L9: 0.16103829 | M9: 0.10400588
B10: Net Profit (GAAP) | C10: -209 | D10: 73 | E10: 427 | F10: 750 | G10: 946 | J10: 143 | K10: 132 | L10: 165 | M10: 107
B11: NPM | C11: -0.047404781 | D11: 0.014006521 | E11: 0.06509092 | F11: 0.091593002 | G11: 0.099617401 | J11: 0.081478107 | K11: 0.062586264 | L11: 0.0846055 | M11: 0.065662134
B12: EPS (diluted) | C12: -0.43 | D12: 0.15 | E12: 0.77 | F12: 1.29759 | G12: 1.6354 | J12: 0.26 | K12: 0.24 | L12: 0.29 | M12: 0.18
B13: Shares Out (mm) | C13: 642.2 | D13: 18.4 | E13: 18.6 | F13: 578.3 | G13: 578.3 | J13: 18.5 | K13: 18.6 | L13: 19.4 | M13: 19.5 | N13: 578.3 | O13: 578.3
B15: Date | C15: 46307
B16: Share price (USD) | C16: 28.14
B17: Market Cap (USD mm) | C17: 16273
B18: Forward PE | C18: =IF(OR(C10="",C10<=0),"",C$17/C10) | D18: =IF(OR(D10="",D10<=0),"",C$17/D10) -> 222.91781 | E18: =IF(OR(E10="",E10<=0),"",C$17/E10) -> 38.11007 | F18: =IF(OR(F10="",F10<=0),"",C$17/F10) -> 21.697333 | G18: =IF(OR(G10="",G10<=0),"",C$17/G10) -> 17.201903
B19: Forward PS | C19: =IF(OR(C6="",C6=0),"",C$17/C6) -> 3.6984091 | D19: =IF(OR(D6="",D6=0),"",C$17/D6) -> 3.1396874 | E19: =IF(OR(E6="",E6=0),"",C$17/E6) -> 2.4783734 | F19: =IF(OR(F6="",F6=0),"",C$17/F6) -> 1.9864502 | G19: =IF(OR(G6="",G6=0),"",C$17/G6) -> 1.7142105
B21: # Analysts (rev) | F21: 13 | G21: 14

Sheet ANF.N
B3: ANF.N, Abercrombie & Fitch Co.
B4: End in | F4: 46415 | G4: 46780 | N4: 46327 | O4: 46419
B5: Fiscal year | C5: 2024 | D5: 2025 | E5: 2026 | F5: 2027E | G5: 2028E | J5: 25Q4 | K5: 26Q1 | L5: 26Q2 | M5: 26Q3 | N5: 26Q4 | O5: 27Q1
B6: Revenue | C6: 4281 | D6: 4949 | E6: 5266 | F6: 5529 | G6: 5769 | J6: 1291 | K6: 1670 | L6: 1114 | M6: 1267
B7: yoy | C7: 0.15764339 | D7: 0.15602906 | E7: 0.064201155 | F7: 0.049866655 | G7: 0.043493017
B8: GM | C8: 0.62920234 | D8: 0.64152878 | E8: 0.61474145 | J8: 0.62524184 | K8: 0.59486754 | L8: 0.590471 | M8: 0.71097167
B9: OPM (EBIT margin) | C9: 0.11322298 | D9: 0.14970334 | E9: 0.13275812 | J9: 0.12011368 | K9: 0.1412928 | L9: 0.077242214 | M9: 0.19949648
B10: Net Profit (GAAP) | C10: 328 | D10: 566 | E10: 507 | F10: 572 | G10: 575 | J10: 113 | K10: 172 | L10: 67 | M10: 184
B11: NPM | C11: 0.076652128 | D11: 0.11442115 | E11: 0.09625767 | F11: 0.10352888 | G11: 0.099637885 | J11: 0.087551012 | K11: 0.10308408 | L11: 0.060273599 | M11: 0.14503955
B12: EPS (diluted) | C12: 6.53 | D12: 11.14 | E12: 10.71 | F12: 12.88272 | G12: 12.93779 | J12: 2.41 | K12: 3.77 | L12: 1.49 | M12: 4.2
B13: Shares Out (mm) | C13: 1 | D13: 1 | E13: 1 | F13: 44.4 | G13: 44.4 | J13: 1 | K13: 1 | L13: 1 | M13: 1 | N13: 44.4 | O13: 44.4
B15: Date | C15: 46307
B16: Share price (USD) | C16: 142.6
B17: Market Cap (USD mm) | C17: 6336
B18: Forward PE | C18: =IF(OR(C10="",C10<=0),"",C$17/C10) -> 19.317073 | D18: =IF(OR(D10="",D10<=0),"",C$17/D10) -> 11.194346 | E18: =IF(OR(E10="",E10<=0),"",C$17/E10) -> 12.497041 | F18: =IF(OR(F10="",F10<=0),"",C$17/F10) -> 11.076923 | G18: =IF(OR(G10="",G10<=0),"",C$17/G10) -> 11.01913
B19: Forward PS | C19: =IF(OR(C6="",C6=0),"",C$17/C6) -> 1.480028 | D19: =IF(OR(D6="",D6=0),"",C$17/D6) -> 1.2802586 | E19: =IF(OR(E6="",E6=0),"",C$17/E6) -> 1.2031903 | F19: =IF(OR(F6="",F6=0),"",C$17/F6) -> 1.1459577 | G19: =IF(OR(G6="",G6=0),"",C$17/G6) -> 1.0982839
B21: # Analysts (rev) | F21: 9 | G21: 9

Sheet VSCO.N
B3: VSCO.N, Victoria's Secret & Co.
B4: End in | F4: 46415 | G4: 46780 | N4: 46327 | O4: 46419
B5: Fiscal year | C5: 2024 | D5: 2025 | E5: 2026 | F5: 2027E | G5: 2028E | J5: 25Q4 | K5: 26Q1 | L5: 26Q2 | M5: 26Q3 | N5: 26Q4 | O5: 27Q1
B6: Revenue | C6: 6182 | D6: 6230 | E6: 6553 | F6: 7142 | G6: 7468 | J6: 1472 | K6: 2270 | L6: 1560 | M6: 1611
B7: yoy | C7: -0.025535939 | D7: 0.0077644775 | E7: 0.051911557 | F7: 0.089743 | G7: 0.045662962
B8: GM | C8: 0.3626658 | D8: 0.36661316 | E8: 0.364311 | J8: 0.36413043 | K8: 0.3766823 | L8: 0.37634739 | M8: 0.47113594
B9: OPM (EBIT margin) | C9: 0.039792947 | D9: 0.04975923 | E9: 0.045303139 | J9: -0.012907609 | K9: 0.10087655 | L9: 0.052631106 | M9: 0.15952824
B10: Net Profit (GAAP) | C10: 109 | D10: 165 | E10: 161 | F10: 371 | G10: 445 | J10: -37 | K10: 184 | L10: 48 | M10: 183
B11: NPM | C11: 0.017631834 | D11: 0.026484751 | E11: 0.024545698 | F11: 0.051908112 | G11: 0.05959269 | J11: -0.02513587 | K11: 0.080903021 | L11: 0.030579171 | M11: 0.11359404
B12: EPS (diluted) | C12: 1.4 | D12: 2.09 | E12: 1.93 | F12: 4.6673 | G12: 5.60293 | J12: -0.46 | K12: 2.14 | L12: 0.56 | M12: 0
B13: Shares Out (mm) | C13: 1 | D13: 1 | E13: 1 | F13: 79.4 | G13: 79.4 | J13: 1 | K13: 1 | L13: 1 | M13: 1 | N13: 79.4 | O13: 79.4
B15: Date | C15: 46307
B16: Share price (USD) | C16: 91.51
B17: Market Cap (USD mm) | C17: 7268
B18: Forward PE | C18: =IF(OR(C10="",C10<=0),"",C$17/C10) -> 66.678899 | D18: =IF(OR(D10="",D10<=0),"",C$17/D10) -> 44.048485 | E18: =IF(OR(E10="",E10<=0),"",C$17/E10) -> 45.142857 | F18: =IF(OR(F10="",F10<=0),"",C$17/F10) -> 19.590296 | G18: =IF(OR(G10="",G10<=0),"",C$17/G10) -> 16.332584
B19: Forward PS | C19: =IF(OR(C6="",C6=0),"",C$17/C6) -> 1.1756713 | D19: =IF(OR(D6="",D6=0),"",C$17/D6) -> 1.1666132 | E19: =IF(OR(E6="",E6=0),"",C$17/E6) -> 1.1091103 | F19: =IF(OR(F6="",F6=0),"",C$17/F6) -> 1.0176421 | G19: =IF(OR(G6="",G6=0),"",C$17/G6) -> 0.97321907
B21: # Analysts (rev) | F21: 6 | G21: 6

Sheet 9983.T
B3: 9983.T, Fast Retailing Co., Ltd.
B4: End in | F4: 46627 | G4: 46993 | N4: 46356 | O4: 46446
B5: Fiscal year | C5: 2024 | D5: 2025 | E5: 2026 | F5: 2027E | G5: 2028E | J5: 25Q4 | K5: 26Q1 | L5: 26Q2 | M5: 26Q3 | N5: 26Q4 | O5: 27Q1
B6: Revenue | C6: 3103836 | D6: 3400539 | E6: 3963389 | F6: 4434755 | G6: 4911986 | J6: 1027745 | K6: 1027482 | L6: 1009955 | M6: 898207
B7: yoy | C7: 0.1219129 | D7: 0.095592357 | E7: 0.16551788 | F7: 0.11892998 | G7: 0.10761153
B8: GM | C8: 0.53903363 | D8: 0.53781415 | E8: 0.49298567 | J8: 0.49740548 | K8: 0.47206958 | L8: 0.508086 | M8: 0.4948759
B9: OPM (EBIT margin) | C9: 0.1563736 | D9: 0.16593399 | E9: 0.18128425 | J9: 0.20009633 | K9: 0.17646635 | L9: 0.20372393 | M9: 0.14003899
B10: Net Profit (GAAP) | C10: 371999 | D10: 433009 | E10: 542517 | F10: 576646 | G10: 650438 | J10: 147446 | K10: 131845 | L10: 146787 | M10: 116439
B11: NPM | C11: 0.11985137 | D11: 0.1273354 | E11: 0.1368821 | F11: 0.13002891 | G11: 0.13241861 | J11: 0.14346555 | K11: 0.12831855 | L11: 0.14534014 | M11: 0.12963493
B12: EPS (diluted) | C12: 1213.19 | D12: 1411.43 | E12: 1768.07 | F12: 1879.2387 | G12: 2119.7201 | J12: 480.55 | K12: 429.69 | L12: 478.37 | M12: 379.46
B13: Shares Out (mm) | C13: 10273 | D13: 10273 | E13: 10273 | F13: 306.9 | G13: 306.9 | J13: 10273 | K13: 10273 | L13: 10273 | M13: 10273 | N13: 306.9 | O13: 306.9
B15: Date | C15: 46307
B16: Share price (JPY) | C16: 71780
B17: Market Cap (JPY mm) | C17: 22025767
B18: Forward PE | C18: =IF(OR(C10="",C10<=0),"",C$17/C10) -> 59.20921 | D18: =IF(OR(D10="",D10<=0),"",C$17/D10) -> 50.866765 | E18: =IF(OR(E10="",E10<=0),"",C$17/E10) -> 40.59922 | F18: =IF(OR(F10="",F10<=0),"",C$17/F10) -> 38.196341 | G18: =IF(OR(G10="",G10<=0),"",C$17/G10) -> 33.862977
B19: Forward PS | C19: =IF(OR(C6="",C6=0),"",C$17/C6) -> 7.096305 | D19: =IF(OR(D6="",D6=0),"",C$17/D6) -> 6.4771399 | E19: =IF(OR(E6="",E6=0),"",C$17/E6) -> 5.5573064 | F19: =IF(OR(F6="",F6=0),"",C$17/F6) -> 4.9666254 | G19: =IF(OR(G6="",G6=0),"",C$17/G6) -> 4.4840859
B21: # Analysts (rev) | F21: 14 | G21: 16

Sheet 8111.T
B3: 8111.T, Goldwin Inc.
B4: End in | F4: 46474 | G4: 46840 | N4: 46295 | O4: 46386
B5: Fiscal year | C5: 2024 | D5: 2025 | E5: 2026 | F5: 2027E | G5: 2028E | J5: 25Q3 | K5: 25Q4 | L5: 26Q1 | M5: 26Q2 | N5: 26Q3 | O5: 26Q4
B6: Revenue | C6: 126907 | D6: 132305 | E6: 137516 | F6: 140702 | G6: 148929 | J6: 31711 | K6: 43883 | L6: 38044 | M6: 23592
B7: yoy | C7: 0.10304036 | D7: 0.042535085 | E7: 0.039386267 | F7: 0.023164577 | G7: 0.058476041
B8: GM | C8: 0.52930886 | D8: 0.52096293 | E8: 0.53046191 | J8: 0.50162404 | K8: 0.56188045 | L8: 0.51876774 | M8: 0.54026789
B9: OPM (EBIT margin) | C9: 0.18790926 | D9: 0.16557197 | E9: 0.18805084 | J9: 0.15388982 | K9: 0.26793975 | L9: 0.18773 | M9: 0.015768057
B10: Net Profit (GAAP) | C10: 24281 | D10: 24444 | E10: 24094 | F10: 23800 | G10: 25455 | J10: 3610 | K10: 8453 | L10: 8842 | M10: 2249
B11: NPM | C11: 0.19132908 | D11: 0.18475492 | E11: 0.1752087 | F11: 0.16915345 | G11: 0.17091747 | J11: 0.11384062 | K11: 0.19262585 | L11: 0.2324151 | M11: 0.095328925
B12: EPS (diluted) | C12: 179.7 | D12: 181.99 | E12: 175.75 | F12: 174.01667 | G12: 186.11333 | J12: 26.23 | K12: 61.61 | L12: 64.59 | M12: 16.44
B13: Shares Out (mm) | C13: 7079 | D13: 7079 | E13: 7079 | F13: 136.8 | G13: 136.8 | J13: 7079 | K13: 7079 | L13: 7079 | M13: 7079 | N13: 136.8 | O13: 136.8
B15: Date | C15: 46307
B16: Share price (JPY) | C16: 2167
B17: Market Cap (JPY mm) | C17: 296379
B18: Forward PE | C18: =IF(OR(C10="",C10<=0),"",C$17/C10) -> 12.206211 | D18: =IF(OR(D10="",D10<=0),"",C$17/D10) -> 12.124816 | E18: =IF(OR(E10="",E10<=0),"",C$17/E10) -> 12.300946 | F18: =IF(OR(F10="",F10<=0),"",C$17/F10) -> 12.452899 | G18: =IF(OR(G10="",G10<=0),"",C$17/G10) -> 11.643253
B19: Forward PS | C19: =IF(OR(C6="",C6=0),"",C$17/C6) -> 2.3354031 | D19: =IF(OR(D6="",D6=0),"",C$17/D6) -> 2.2401194 | E19: =IF(OR(E6="",E6=0),"",C$17/E6) -> 2.1552328 | F19: =IF(OR(F6="",F6=0),"",C$17/F6) -> 2.1064306 | G19: =IF(OR(G6="",G6=0),"",C$17/G6) -> 1.9900691
B21: # Analysts (rev) | F21: 6 | G21: 6

Sheet 7936.T
B3: 7936.T, ASICS Corporation
B4: End in | F4: 46384 | G4: 46749 | N4: 46295 | O4: 46386
B5: Fiscal year | C5: 2023 | D5: 2024 | E5: 2025 | F5: 2026E | G5: 2027E | J5: 25Q3 | K5: 25Q4 | L5: 26Q1 | M5: 26Q2 | N5: 26Q3 | O5: 26Q4
B6: Revenue | C6: 570463 | D6: 678526 | E6: 810916 | F6: 1040811 | G6: 1168212 | J6: 222257 | K6: 185861 | L6: 270265 | M6: 264218
B7: yoy | C7: 0.17718081 | D7: 0.18943034 | E7: 0.19511412 | F7: 0.28349998 | G7: 0.12240548
B8: GM | C8: 0.52044918 | D8: 0.55838391 | E8: 0.53728623 | J8: 0.53207323 | K8: 0.53811181 | L8: 0.5179324 | M8: 0.57050617
B9: OPM (EBIT margin) | C9: 0.095036838 | D9: 0.14754188 | E9: 0.1757531 | J9: 0.20910478 | K9: 0.080242762 | L9: 0.22483118 | M9: 0.22603683
B10: Net Profit (GAAP) | C10: 35272 | D10: 63806 | E10: 98720 | F10: 127244 | G10: 149918 | J10: 32709 | K10: 12405 | L10: 46570 | M10: 35601
B11: NPM | C11: 0.061830478 | D11: 0.09403619 | E11: 0.12173887 | F11: 0.12225487 | G11: 0.128331 | J11: 0.14716747 | K11: 0.066743427 | L11: 0.17231236 | M11: 0.13474101
B12: EPS (diluted) | C12: 48.13 | D12: 88.3 | E12: 138.13 | F12: 179.49227 | G12: 211.47593 | J12: 45.64 | K12: 17.47 | L12: 65.71 | M12: 50.22
B13: Shares Out (mm) | C13: 23972 | D13: 23972 | E13: 23972 | F13: 708.9 | G13: 708.9 | J13: 23972 | K13: 23972 | L13: 23972 | M13: 23972 | N13: 708.9 | O13: 708.9
B15: Date | C15: 46307
B16: Share price (JPY) | C16: 4474
B17: Market Cap (JPY mm) | C17: 3171671
B18: Forward PE | C18: =IF(OR(C10="",C10<=0),"",C$17/C10) -> 89.920362 | D18: =IF(OR(D10="",D10<=0),"",C$17/D10) -> 49.708037 | E18: =IF(OR(E10="",E10<=0),"",C$17/E10) -> 32.127948 | F18: =IF(OR(F10="",F10<=0),"",C$17/F10) -> 24.925898 | G18: =IF(OR(G10="",G10<=0),"",C$17/G10) -> 21.156039
B19: Forward PS | C19: =IF(OR(C6="",C6=0),"",C$17/C6) -> 5.559819 | D19: =IF(OR(D6="",D6=0),"",C$17/D6) -> 4.6743544 | E19: =IF(OR(E6="",E6=0),"",C$17/E6) -> 3.9112202 | F19: =IF(OR(F6="",F6=0),"",C$17/F6) -> 3.0473073 | G19: =IF(OR(G6="",G6=0),"",C$17/G6) -> 2.714979
B21: # Analysts (rev) | F21: 13 | G21: 13

Sheet 3998.HK
B3: 3998.HK, Bosideng International Holdings Limited
B4: End in | F4: 46474 | G4: 46840 | N4: 46203 | O4: 46295
B5: Fiscal year | C5: 2024 | D5: 2025 | E5: 2026 | F5: 2027E | G5: 2028E | J5: 24Q3 | K5: 25Q1 | L5: 25Q3 | M5: 26Q1 | N5: 26Q2 | O5: 26Q3
B6: Revenue | C6: 23214 | D6: 25902 | E6: 26389 | F6: 29953 | G6: 31768 | J6: 8804 | K6: 17098 | L6: 8928 | M6: 17994
B7: yoy | C7: 0.38391132 | D7: 0.11577824 | E7: 0.018817134 | F7: 0.13504358 | G7: 0.06059143
B8: GM | C8: 0.59591283 | D8: 0.57292952 | E8: 0.56993095 | J8: 0.49877966 | K8: 0.6111118 | L8: 0.50032304 | M8: 0.60520956
B9: OPM (EBIT margin) | C9: 0.18943524 | D9: 0.19175886 | E9: 0.18029737 | J9: 0.16717215 | K9: 0.2044194 | L9: 0.16990395 | M9: 0.19362321
B10: Net Profit (GAAP) | C10: 3074 | D10: 3514 | E10: 3854 | F10: 4437 | G10: 4731 | J10: 1130 | K10: 2384 | L10: 1189 | M10: 2740
B11: NPM | C11: 0.132423 | D11: 0.13566334 | E11: 0.14604684 | F11: 0.14812392 | G11: 0.14892362 | J11: 0.12831458 | K11: 0.13944747 | L11: 0.13322281 | M11: 0.15226147
B12: EPS (diluted) | C12: 0.28 | D12: 0.32 | E12: 0.33 | F12: 0.3818 | G12: 0.40712 | J12: 0.1 | K12: 0.22 | L12: 0.1 | M12: 0.24
B13: Shares Out (mm) | C13: 0.8 | D13: 0.9 | E13: 0.9 | F13: 11620.5 | G13: 11620.5 | J13: 0.8 | K13: 0.9 | L13: 0.9 | M13: 0.9 | N13: 11620.5 | O13: 11620.5
B15: Date | C15: 46307
B16: Share price (HKD) | C16: 4.31
B17: Market Cap (CNY mm) | C17: 42731
B18: Forward PE | C18: =IF(OR(C10="",C10<=0),"",C$17/C10) -> 13.900781 | D18: =IF(OR(D10="",D10<=0),"",C$17/D10) -> 12.160216 | E18: =IF(OR(E10="",E10<=0),"",C$17/E10) -> 11.087442 | F18: =IF(OR(F10="",F10<=0),"",C$17/F10) -> 9.6306063 | G18: =IF(OR(G10="",G10<=0),"",C$17/G10) -> 9.0321285
B19: Forward PS | C19: =IF(OR(C6="",C6=0),"",C$17/C6) -> 1.8407427 | D19: =IF(OR(D6="",D6=0),"",C$17/D6) -> 1.6497182 | E19: =IF(OR(E6="",E6=0),"",C$17/E6) -> 1.6192732 | F19: =IF(OR(F6="",F6=0),"",C$17/F6) -> 1.4266017 | G19: =IF(OR(G6="",G6=0),"",C$17/G6) -> 1.3450957
B21: # Analysts (rev) | F21: 19 | G21: 19

Sheet 2331.HK
B3: 2331.HK, Li Ning Company Limited
B4: End in | F4: 46384 | G4: 46749 | N4: 46295 | O4: 46386
B5: Fiscal year | C5: 2023 | D5: 2024 | E5: 2025 | F5: 2026E | G5: 2027E | J5: 24Q4 | K5: 25Q2 | L5: 25Q4 | M5: 26Q2 | N5: 26Q3 | O5: 26Q4
B6: Revenue | C6: 27598 | D6: 28676 | E6: 29598 | F6: 31923 | G6: 33563 | J6: 14330 | K6: 14817 | L6: 14782 | M6: 15025
B7: yoy | C7: 0.069568707 | D7: 0.03902938 | E7: 0.032179714 | F7: 0.078541547 | G7: 0.051373809
B8: GM | C8: 0.48379656 | D8: 0.49366297 | E8: 0.48951392 | J8: 0.482926 | K8: 0.50043339 | L8: 0.4785685 | M8: 0.50873645
B9: OPM (EBIT margin) | C9: 0.12895948 | D9: 0.12826935 | E9: 0.13170326 | J9: 0.08906346 | K9: 0.1645761 | L9: 0.098752345 | M9: 0.15631086
B10: Net Profit (GAAP) | C10: 3187 | D10: 3013 | E10: 2936 | F10: 2529 | G10: 2895 | J10: 1061 | K10: 1737 | L10: 1198 | M10: 1791
B11: NPM | C11: 0.11547407 | D11: 0.10506889 | E11: 0.099185811 | F11: 0.079233033 | G11: 0.086264982 | J11: 0.074030685 | K11: 0.11726056 | L11: 0.081068127 | M11: 0.1192094
B12: EPS (diluted) | C12: 1.23 | D12: 1.17 | E12: 1.14 | F12: 0.97855 | G12: 1.12013 | J12: 0.41 | K12: 0.67 | L12: 0.46 | M12: 0.69
B13: Shares Out (mm) | C13: 239.5 | D13: 235.9 | E13: 236 | F13: 2584.8 | G13: 2584.8 | J13: 235.9 | K13: 235.9 | L13: 236 | M13: 235.8 | N13: 2584.8 | O13: 2584.8
B15: Date | C15: 46307
B16: Share price (HKD) | C16: 12.6
B17: Market Cap (CNY mm) | C17: 27787
B18: Forward PE | C18: =IF(OR(C10="",C10<=0),"",C$17/C10) -> 8.7188579 | D18: =IF(OR(D10="",D10<=0),"",C$17/D10) -> 9.2223697 | E18: =IF(OR(E10="",E10<=0),"",C$17/E10) -> 9.4642371 | F18: =IF(OR(F10="",F10<=0),"",C$17/F10) -> 10.987347 | G18: =IF(OR(G10="",G10<=0),"",C$17/G10) -> 9.5982729
B19: Forward PS | C19: =IF(OR(C6="",C6=0),"",C$17/C6) -> 1.0068483 | D19: =IF(OR(D6="",D6=0),"",C$17/D6) -> 0.96899847 | E19: =IF(OR(E6="",E6=0),"",C$17/E6) -> 0.93881343 | F19: =IF(OR(F6="",F6=0),"",C$17/F6) -> 0.87043824 | G19: =IF(OR(G6="",G6=0),"",C$17/G6) -> 0.82790573
B21: # Analysts (rev) | F21: 29 | G21: 30

Sheet 2020.HK
B3: 2020.HK, ANTA Sports Products Limited
B4: End in | F4: 46384 | G4: 46749 | N4: 46295 | O4: 46386
B5: Fiscal year | C5: 2023 | D5: 2024 | E5: 2025 | F5: 2026E | G5: 2027E | J5: 24Q4 | K5: 25Q2 | L5: 25Q4 | M5: 26Q2 | N5: 26Q3 | O5: 26Q4
B6: Revenue | C6: 62356 | D6: 70826 | E6: 80219 | F6: 92659 | G6: 100706 | J6: 37091 | K6: 38544 | L6: 41675 | M6: 43507
B7: yoy | C7: 0.16225233 | D7: 0.13583296 | E7: 0.13262079 | F7: 0.15507351 | G7: 0.086847091
B8: GM | C8: 0.62589005 | D8: 0.6216926 | E8: 0.61997781 | J8: 0.60429754 | K8: 0.63369137 | L8: 0.60729454 | M8: 0.63879376
B9: OPM (EBIT margin) | C9: 0.2464398 | D9: 0.23430661 | E9: 0.23798601 | J9: 0.2139333 | K9: 0.26284247 | L9: 0.214997 | M9: 0.27030133
B10: Net Profit (GAAP) | C10: 10236 | D10: 15596 | E10: 13588 | F10: 15934 | G10: 16844 | J10: 7875 | K10: 7031 | L10: 6557 | M10: 9487
B11: NPM | C11: 0.16415421 | D11: 0.22020162 | E11: 0.1693863 | F11: 0.17196059 | G11: 0.16726109 | J11: 0.21231566 | K11: 0.1824149 | L11: 0.15733653 | M11: 0.21805686
B12: EPS (diluted) | C12: 3.69 | D12: 5.55 | E12: 4.89 | F12: 5.75119 | G12: 6.07984 | J12: 2.77 | K12: 2.53 | L12: 2.32 | M12: 3.37
B13: Shares Out (mm) | C13: 272 | D13: 271 | E13: 269.1 | F13: 2770.5 | G13: 2770.5 | J13: 271 | K13: 270 | L13: 269.1 | M13: 269 | N13: 2770.5 | O13: 2770.5
B15: Date | C15: 46307
B16: Share price (HKD) | C16: 70.95
B17: Market Cap (CNY mm) | C17: 167705
B18: Forward PE | C18: =IF(OR(C10="",C10<=0),"",C$17/C10) -> 16.383841 | D18: =IF(OR(D10="",D10<=0),"",C$17/D10) -> 10.753078 | E18: =IF(OR(E10="",E10<=0),"",C$17/E10) -> 12.34214 | F18: =IF(OR(F10="",F10<=0),"",C$17/F10) -> 10.524978 | G18: =IF(OR(G10="",G10<=0),"",C$17/G10) -> 9.9563643
B19: Forward PS | C19: =IF(OR(C6="",C6=0),"",C$17/C6) -> 2.6894766 | D19: =IF(OR(D6="",D6=0),"",C$17/D6) -> 2.3678451 | E19: =IF(OR(E6="",E6=0),"",C$17/E6) -> 2.0905895 | F19: =IF(OR(F6="",F6=0),"",C$17/F6) -> 1.8099159 | G19: =IF(OR(G6="",G6=0),"",C$17/G6) -> 1.665293
B21: # Analysts (rev) | F21: 32 | G21: 32

Sheet 1836.HK
B3: 1836.HK, Stella International Holdings Limited
B4: End in | F4: 46384 | G4: 46749 | N4: 46295 | O4: 46386
B5: Fiscal year | C5: 2023 | D5: 2024 | E5: 2025 | F5: 2026E | G5: 2027E | J5: 24Q4 | K5: 25Q2 | L5: 25Q4 | M5: 26Q2 | N5: 26Q3 | O5: 26Q4
B6: Revenue | C6: 1493 | D6: 1545 | E6: 1570 | F6: 1587 | G6: 1665 | J6: 775 | K6: 388 | L6: 795 | M6: 785
B7: yoy | C7: -0.084696135 | D7: 0.035147533 | E7: 0.016259642 | F7: 0.0105512 | G7: 0.049445027
B8: GM | C8: 0.24568905 | D8: 0.24849752 | E8: 0.21801168 | J8: 0.23877343 | K8: 0.22598874 | L8: 0.21023614 | M8: 0.2031571
B9: OPM (EBIT margin) | C9: 0.10675838 | D9: 0.11871487 | E9: 0.095051893 | J9: 0.11062401 | K9: 0.10959341 | L9: 0.080877757 | M9: 0.078079555
B10: Net Profit (GAAP) | C10: 141 | D10: 171 | E10: 138 | F10: 124 | G10: 141 | J10: 79 | K10: 39 | L10: 59 | M10: 64
B11: NPM | C11: 0.094511041 | D11: 0.11070316 | E11: 0.087876543 | F11: 0.078388518 | G11: 0.084904112 | J11: 0.1020574 | K11: 0.10145225 | L11: 0.074643815 | M11: 0.081406227
B12: EPS (diluted) | C12: 0.18 | D12: 0.21 | E12: 0.17 | F12: 0.14787 | G12: 0.16808 | J12: 0.0968 | K12: 0.0465 | L12: 0.0709 | M12: 0.0778
B13: Shares Out (mm) | C13: 10.2 | D13: 10.5 | E13: 10.7 | F13: 841.2 | G13: 841.2 | J13: 10.5 | K13: 10.7 | L13: 10.7 | M13: 10.8 | N13: 841.2 | O13: 841.2
B15: Date | C15: 46307
B16: Share price (HKD) | C16: 12.33
B17: Market Cap (USD mm) | C17: 1322
B18: Forward PE | C18: =IF(OR(C10="",C10<=0),"",C$17/C10) -> 9.3758865 | D18: =IF(OR(D10="",D10<=0),"",C$17/D10) -> 7.7309942 | E18: =IF(OR(E10="",E10<=0),"",C$17/E10) -> 9.5797101 | F18: =IF(OR(F10="",F10<=0),"",C$17/F10) -> 10.66129 | G18: =IF(OR(G10="",G10<=0),"",C$17/G10) -> 9.3758865
B19: Forward PS | C19: =IF(OR(C6="",C6=0),"",C$17/C6) -> 0.88546551 | D19: =IF(OR(D6="",D6=0),"",C$17/D6) -> 0.85566343 | E19: =IF(OR(E6="",E6=0),"",C$17/E6) -> 0.84203822 | F19: =IF(OR(F6="",F6=0),"",C$17/F6) -> 0.83301827 | G19: =IF(OR(G6="",G6=0),"",C$17/G6) -> 0.79399399
B21: # Analysts (rev) | F21: 7 | G21: 7

Sheet 1368.HK
B3: 1368.HK, Xtep International Holdings Limited
B4: End in | F4: 46384 | G4: 46749 | N4: 46295 | O4: 46386
B5: Fiscal year | C5: 2023 | D5: 2024 | E5: 2025 | F5: 2026E | G5: 2027E | J5: 24Q4 | K5: 25Q2 | L5: 25Q4 | M5: 26Q2 | N5: 26Q3 | O5: 26Q4
B6: Revenue | C6: 14346 | D6: 13577 | E6: 14151 | F6: 14640 | G6: 15362 | J6: 6374 | K6: 3419 | L6: 7313 | M6: 6795
B7: yoy | C7: 0.10944168 | D7: -0.053555859 | E7: 0.042266673 | F7: 0.034584275 | G7: 0.049284372
B8: GM | C8: 0.42171215 | D8: 0.43200325 | E8: 0.42845065 | J8: 0.40023147 | K8: 0.44953158 | L8: 0.40874122 | M8: 0.46425571
B9: OPM (EBIT margin) | C9: 0.11013218 | D9: 0.14476739 | E9: 0.14266071 | J9: 0.13671733 | K9: 0.19083201 | L9: 0.097623363 | M9: 0.17084594
B10: Net Profit (GAAP) | C10: 1030 | D10: 1238 | E10: 1372 | F10: 1205 | G10: 1363 | J10: 486 | K10: 457 | L10: 458 | M10: 818
B11: NPM | C11: 0.071800106 | D11: 0.091211737 | E11: 0.096923374 | F11: 0.082293154 | G11: 0.088705722 | J11: 0.076299359 | K11: 0.13360863 | L11: 0.062624804 | M11: 0.12036762
B12: EPS (diluted) | C12: 0.48 | D12: 0.51 | E12: 0.5 | F12: 0.44083 | G12: 0.4986 | J12: 0.22 | K12: 0.17 | L12: 0.17 | M12: 0.3
B13: Shares Out (mm) | C13: 23.2 | D13: 23.6 | E13: 24.7 | F13: 2733.1 | G13: 2733.1 | J13: 23.6 | K13: 24.5 | L13: 24.7 | M13: 24.8 | N13: 2733.1 | O13: 2733.1
B15: Date | C15: 46307
B16: Share price (HKD) | C16: 3.53
B17: Market Cap (CNY mm) | C17: 8231
B18: Forward PE | C18: =IF(OR(C10="",C10<=0),"",C$17/C10) -> 7.9912621 | D18: =IF(OR(D10="",D10<=0),"",C$17/D10) -> 6.6486268 | E18: =IF(OR(E10="",E10<=0),"",C$17/E10) -> 5.9992711 | F18: =IF(OR(F10="",F10<=0),"",C$17/F10) -> 6.8307054 | G18: =IF(OR(G10="",G10<=0),"",C$17/G10) -> 6.0388848
B19: Forward PS | C19: =IF(OR(C6="",C6=0),"",C$17/C6) -> 0.57374878 | D19: =IF(OR(D6="",D6=0),"",C$17/D6) -> 0.60624586 | E19: =IF(OR(E6="",E6=0),"",C$17/E6) -> 0.58165501 | F19: =IF(OR(F6="",F6=0),"",C$17/F6) -> 0.56222678 | G19: =IF(OR(G6="",G6=0),"",C$17/G6) -> 0.53580263
B21: # Analysts (rev) | F21: 16 | G21: 17

Sheet 1361.HK
B3: 1361.HK, 361 Degrees International Limited
B4: End in | F4: 46384 | G4: 46749 | N4: 46295 | O4: 46386
B5: Fiscal year | C5: 2023 | D5: 2024 | E5: 2025 | F5: 2026E | G5: 2027E | J5: 24Q4 | K5: 25Q2 | L5: 25Q4 | M5: 26Q2 | N5: 26Q3 | O5: 26Q4
B6: Revenue | C6: 8423 | D6: 10074 | E6: 11146 | F6: 12768 | G6: 13895 | J6: 4932 | K6: 5705 | L6: 5441 | M6: 6075
B7: yoy | C7: 0.21009446 | D7: 0.19591626 | E7: 0.10644939 | F7: 0.14553024 | G7: 0.088279188
B8: GM | C8: 0.41102331 | D8: 0.4152765 | E8: 0.41527068 | J8: 0.41731563 | K8: 0.41481517 | L8: 0.41574828 | M8: 0.41769164
B9: OPM (EBIT margin) | C9: 0.16425345 | D9: 0.15647376 | E9: 0.15854541 | J9: 0.10457651 | K9: 0.1993488 | L9: 0.11576348 | M9: 0.17630416
B10: Net Profit (GAAP) | C10: 961 | D10: 1149 | E10: 1309 | F10: 1544 | G10: 1707 | J10: 359 | K10: 858 | L10: 451 | M10: 913
B11: NPM | C11: 0.11413958 | D11: 0.11402331 | E11: 0.11743263 | F11: 0.12092633 | G11: 0.12287972 | J11: 0.072768766 | K11: 0.15034453 | L11: 0.082924845 | M11: 0.15031995
B12: EPS (diluted) | C12: 0.46 | D12: 0.56 | E12: 0.63 | F12: 0.71227 | G12: 0.78767 | J12: 0.17 | K12: 0.41 | L12: 0.22 | M12: 0.44
B13: Shares Out (mm) | C13: 182.3 | D13: 182.3 | E13: 182.3 | F13: 2167.7 | G13: 2167.7 | J13: 182.3 | K13: 182.3 | L13: 182.3 | M13: 191 | N13: 2167.7 | O13: 2167.7
B15: Date | C15: 46307
B16: Share price (HKD) | C16: 4.58
B17: Market Cap (CNY mm) | C17: 8470
B18: Forward PE | C18: =IF(OR(C10="",C10<=0),"",C$17/C10) -> 8.8137357 | D18: =IF(OR(D10="",D10<=0),"",C$17/D10) -> 7.3716275 | E18: =IF(OR(E10="",E10<=0),"",C$17/E10) -> 6.4705882 | F18: =IF(OR(F10="",F10<=0),"",C$17/F10) -> 5.4857513 | G18: =IF(OR(G10="",G10<=0),"",C$17/G10) -> 4.9619215
B19: Forward PS | C19: =IF(OR(C6="",C6=0),"",C$17/C6) -> 1.00558 | D19: =IF(OR(D6="",D6=0),"",C$17/D6) -> 0.84077824 | E19: =IF(OR(E6="",E6=0),"",C$17/E6) -> 0.75991387 | F19: =IF(OR(F6="",F6=0),"",C$17/F6) -> 0.66337719 | G19: =IF(OR(G6="",G6=0),"",C$17/G6) -> 0.60957179
B21: # Analysts (rev) | F21: 10 | G21: 10

Sheet 002832.SZ
B3: 002832.SZ, BIEM.L.FDLKK Garment Co.,Ltd.
B4: End in | F4: 46384 | G4: 46749 | N4: 46295 | O4: 46386
B5: Fiscal year | C5: 2023 | D5: 2024 | E5: 2025 | F5: 2026E | G5: 2027E | J5: 25Q3 | K5: 25Q4 | L5: 26Q1 | M5: 26Q2 | N5: 26Q3 | O5: 26Q4
B6: Revenue | C6: 3536 | D6: 4004 | E6: 4314 | F6: 5217 | G6: 6004 | J6: 1098 | K6: 1112 | L6: 1522 | M6: 1079
B7: yoy | C7: 0.22576315 | D7: 0.13244147 | E7: 0.077275682 | F7: 0.20936683 | G7: 0.15079448
B8: GM | C8: 0.76892545 | D8: 0.75604583 | E8: 0.7508751 | J8: 0.75081579 | K8: 0.73520173 | L8: 0.75271654 | M8: 0.75205258
B9: OPM (EBIT margin) | C9: 0.30046977 | D9: 0.23542861 | E9: 0.15155537 | J9: 0.20093832 | K9: -0.078055385 | L9: 0.30707602 | M9: 0.10311934
B10: Net Profit (GAAP) | C10: 911 | D10: 781 | E10: 551 | F10: 748 | G10: 924 | J10: 205 | K10: -69 | L10: 386 | M10: 104
B11: NPM | C11: 0.25755651 | D11: 0.19495498 | E11: 0.12765505 | F11: 0.14330302 | G11: 0.15391421 | J11: 0.18702741 | K11: -0.061950285 | L11: 0.25373647 | M11: 0.096659754
B12: EPS (diluted) | C12: 1.6 | D12: 1.37 | E12: 0.96 | F12: 1.31 | G12: 1.61917 | J12: 0.36 | K12: -0.12 | L12: 0.68 | M12: 0.18
B13: Shares Out (mm) | C13: 570.7 | D13: 570.7 | E13: 570.7 | F13: 570.7 | G13: 570.7 | J13: 570.7 | K13: 570.7 | L13: 570.7 | M13: 570.7 | N13: 570.7 | O13: 570.7
B15: Date | C15: 46307
B16: Share price (CNY) | C16: 26.76
B17: Market Cap (CNY mm) | C17: 15272
B18: Forward PE | C18: =IF(OR(C10="",C10<=0),"",C$17/C10) -> 16.763996 | D18: =IF(OR(D10="",D10<=0),"",C$17/D10) -> 19.554417 | E18: =IF(OR(E10="",E10<=0),"",C$17/E10) -> 27.716878 | F18: =IF(OR(F10="",F10<=0),"",C$17/F10) -> 20.417112 | G18: =IF(OR(G10="",G10<=0),"",C$17/G10) -> 16.528139
B19: Forward PS | C19: =IF(OR(C6="",C6=0),"",C$17/C6) -> 4.3190045 | D19: =IF(OR(D6="",D6=0),"",C$17/D6) -> 3.8141858 | E19: =IF(OR(E6="",E6=0),"",C$17/E6) -> 3.540102 | F19: =IF(OR(F6="",F6=0),"",C$17/F6) -> 2.9273529 | G19: =IF(OR(G6="",G6=0),"",C$17/G6) -> 2.5436376
B21: # Analysts (rev) | F21: 5 | G21: 5

Sheet VFC
B3: VFC, V.F. Corporation
B4: End in | F4: 46474 | G4: 46840 | N4: 46292 | O4: 46383
B5: Fiscal year | C5: 2024 | D5: 2025 | E5: 2026 | F5: 2027E | G5: 2028E | J5: 25Q3 | K5: 25Q4 | L5: 26Q1 | M5: 26Q2 | N5: 26Q3 | O5: 26Q4
B6: Revenue | C6: 9916 | D6: 9505 | E6: 9605 | F6: 9491 | G6: 9786 | J6: 2803 | K6: 2876 | L6: 2166 | M6: 1669
B7: yoy | C7: -0.10583849 | D7: -0.0414482 | E7: 0.01057541 | F7: -0.011921481 | G7: 0.0311218
B8: GM | C8: 0.51603229 | D8: 0.53507389 | E8: 0.54779819 | J8: 0.52179715 | K8: 0.55554087 | L8: 0.5641315 | M8: 0.54933242
B9: OPM (EBIT margin) | C9: -0.014515901 | D9: 0.031960324 | E9: 0.063224561 | J9: 0.1115422 | K9: 0.10051252 | L9: 0.028394753 | M9: -0.049762217
B10: Net Profit (GAAP) | C10: -969 | D10: -190 | E10: 255 | F10: 421 | G10: 521 | J10: 190 | K10: 301 | L10: -119 | M10: -97
B11: NPM | C11: -0.097712128 | D11: -0.019960249 | E11: 0.026539772 | F11: 0.044390697 | G11: 0.053259209 | J11: 0.06770778 | K11: 0.10461259 | L11: -0.055069311 | M11: -0.058196491
B12: EPS (diluted) | C12: -2.49 | D12: -0.49 | E12: 0.65 | F12: 1.07164 | G12: 1.32575 | J12: 0.49 | K12: 0.76 | L12: -0.3 | M12: -0.25
B13: Shares Out (mm) | C13: 97.2 | D13: 97.4 | E13: 97.9 | F13: 393.1 | G13: 393.1 | J13: 97.7 | K13: 97.8 | L13: 97.9 | M13: 98.3 | N13: 393.1 | O13: 393.1
B15: Date | C15: 46307
B16: Share price (USD) | C16: 15
B17: Market Cap (USD mm) | C17: 5897
B18: Forward PE | C18: =IF(OR(C10="",C10<=0),"",C$17/C10) | D18: =IF(OR(D10="",D10<=0),"",C$17/D10) | E18: =IF(OR(E10="",E10<=0),"",C$17/E10) -> 23.12549 | F18: =IF(OR(F10="",F10<=0),"",C$17/F10) -> 14.007126 | G18: =IF(OR(G10="",G10<=0),"",C$17/G10) -> 11.318618
B19: Forward PS | C19: =IF(OR(C6="",C6=0),"",C$17/C6) -> 0.59469544 | D19: =IF(OR(D6="",D6=0),"",C$17/D6) -> 0.62041031 | E19: =IF(OR(E6="",E6=0),"",C$17/E6) -> 0.61395107 | F19: =IF(OR(F6="",F6=0),"",C$17/F6) -> 0.62132547 | G19: =IF(OR(G6="",G6=0),"",C$17/G6) -> 0.60259554
B21: # Analysts (rev) | F21: 17 | G21: 17

Sheet CFR
B3: CFR, Compagnie Financière Richemont S.A.
B4: End in | F4: 46474 | G4: 46840 | N4: 46203 | O4: 46295
B5: Fiscal year | C5: 2024 | D5: 2025 | E5: 2026 | F5: 2027E | G5: 2028E | J5: 24Q3 | K5: 25Q1 | L5: 25Q3 | M5: 26Q1 | N5: 26Q2 | O5: 26Q3
B6: Revenue | C6: 20616 | D6: 21399 | E6: 22420 | F6: 25480 | G6: 27441 | J6: 10077 | K6: 11322 | L6: 10645 | M6: 11818
B7: yoy | C7: 0.033228086 | D7: 0.03798021 | E7: 0.04771251 | F7: 0.1364978 | G7: 0.076931556
B8: GM | C8: 0.68083042 | D8: 0.66914342 | E8: 0.64397859 | J8: 0.67192617 | K8: 0.66657834 | L8: 0.65138563 | M8: 0.63545462
B9: OPM (EBIT margin) | C9: 0.23253783 | D9: 0.20874807 | E9: 0.20673506 | J9: 0.21891436 | K9: 0.1996997 | L9: 0.22104274 | M9: 0.18056831
B10: Net Profit (GAAP) | C10: 2362 | D10: 2751 | E10: 3484 | F10: 4433 | G10: 5093 | J10: 458 | K10: 2293 | L10: 1817 | M10: 1673
B11: NPM | C11: 0.11457121 | D11: 0.12855741 | E11: 0.15539697 | F11: 0.17397604 | G11: 0.18561165 | J11: 0.045450035 | K11: 0.20252606 | L11: 0.17069047 | M11: 0.14159817
B12: EPS (diluted) | C12: 4.1 | D12: 4.69 | E12: 5.89 | F12: 7.53981 | G12: 8.66292 | J12: 0.79 | K12: 3.45 | L12: 3.09 | M12: 2.84
B13: Shares Out (mm) | C13: 352 | D13: 352 | E13: 353.3 | F13: 587.9 | G13: 587.9 | J13: 352 | K13: 352 | L13: 352 | M13: 353.3 | N13: 587.9 | O13: 587.9
B15: Date | C15: 46307
B16: Share price (CHF) | C16: 170.75
B17: Market Cap (EUR mm) | C17: 107752
B18: Forward PE | C18: =IF(OR(C10="",C10<=0),"",C$17/C10) -> 45.618967 | D18: =IF(OR(D10="",D10<=0),"",C$17/D10) -> 39.168302 | E18: =IF(OR(E10="",E10<=0),"",C$17/E10) -> 30.927669 | F18: =IF(OR(F10="",F10<=0),"",C$17/F10) -> 24.30679 | G18: =IF(OR(G10="",G10<=0),"",C$17/G10) -> 21.156882
B19: Forward PS | C19: =IF(OR(C6="",C6=0),"",C$17/C6) -> 5.2266201 | D19: =IF(OR(D6="",D6=0),"",C$17/D6) -> 5.0353755 | E19: =IF(OR(E6="",E6=0),"",C$17/E6) -> 4.806066 | F19: =IF(OR(F6="",F6=0),"",C$17/F6) -> 4.2288854 | G19: =IF(OR(G6="",G6=0),"",C$17/G6) -> 3.9266791
B21: # Analysts (rev) | F21: 26 | G21: 26

Sheet 1913.HK
B3: 1913.HK, Prada S.p.A.
B4: End in | F4: 46384 | G4: 46749 | N4: 46295 | O4: 46386
B5: Fiscal year | C5: 2023 | D5: 2024 | E5: 2025 | F5: 2026E | G5: 2027E | J5: 24Q4 | K5: 25Q2 | L5: 25Q4 | M5: 26Q2 | N5: 26Q3 | O5: 26Q4
B6: Revenue | C6: 4726 | D6: 5432 | E6: 5718 | F6: 6143 | G6: 6434 | J6: 2883 | K6: 2740 | L6: 2977 | M6: 3101
B7: yoy | C7: 0.12515539 | D7: 0.1491927 | E7: 0.052648624 | F7: 0.074461101 | G7: 0.047349143
B8: GM | C8: 0.80436742 | D8: 0.7984252 | E8: 0.80315875 | J8: 0.7987487 | K8: 0.8009321 | L8: 0.80520782 | M8: 0.78336779
B9: OPM (EBIT margin) | C9: 0.22462964 | D9: 0.23557702 | E9: 0.22720336 | J9: 0.2443461 | K9: 0.22163731 | L9: 0.23232553 | M9: 0.17393358
B10: Net Profit (GAAP) | C10: 671 | D10: 839 | E10: 852 | F10: 732 | G10: 805 | J10: 455 | K10: 386 | L10: 466 | M10: 333
B11: NPM | C11: 0.14197369 | D11: 0.15445056 | E11: 0.14900444 | F11: 0.11912639 | G11: 0.12505529 | J11: 0.15796745 | K11: 0.14083141 | L11: 0.15652567 | M11: 0.10723606
B12: EPS (diluted) | C12: 0.26 | D12: 0.33 | E12: 0.33 | F12: 0.286 | G12: 0.31445 | J12: 0.18 | K12: 0.15 | L12: 0.18 | M12: 0.13
B13: Shares Out (mm) | C13: 255.9 | D13: 255.9 | E13: 255.8 | F13: 2558.8 | G13: 2558.8 | J13: 255.9 | K13: 255.9 | L13: 255.8 | M13: 255.7 | N13: 2558.8 | O13: 2558.8
B15: Date | C15: 46307
B16: Share price (HKD) | C16: 37.12
B17: Market Cap (EUR mm) | C17: 10806
B18: Forward PE | C18: =IF(OR(C10="",C10<=0),"",C$17/C10) -> 16.104322 | D18: =IF(OR(D10="",D10<=0),"",C$17/D10) -> 12.879619 | E18: =IF(OR(E10="",E10<=0),"",C$17/E10) -> 12.683099 | F18: =IF(OR(F10="",F10<=0),"",C$17/F10) -> 14.762295 | G18: =IF(OR(G10="",G10<=0),"",C$17/G10) -> 13.423602
B19: Forward PS | C19: =IF(OR(C6="",C6=0),"",C$17/C6) -> 2.2865002 | D19: =IF(OR(D6="",D6=0),"",C$17/D6) -> 1.9893225 | E19: =IF(OR(E6="",E6=0),"",C$17/E6) -> 1.8898216 | F19: =IF(OR(F6="",F6=0),"",C$17/F6) -> 1.7590754 | G19: =IF(OR(G6="",G6=0),"",C$17/G6) -> 1.6795151
B21: # Analysts (rev) | F21: 17 | G21: 18

Sheet MONC
B3: MONC, Moncler S.p.A.
B4: End in | F4: 46384 | G4: 46749 | N4: 46295 | O4: 46386
B5: Fiscal year | C5: 2023 | D5: 2024 | E5: 2025 | F5: 2026E | G5: 2027E | J5: 24Q4 | K5: 25Q2 | L5: 25Q4 | M5: 26Q2 | N5: 26Q3 | O5: 26Q4
B6: Revenue | C6: 2984 | D6: 3109 | E6: 3132 | F6: 3233 | G6: 3455 | J6: 1879 | K6: 1226 | L6: 1906 | M6: 1290
B7: yoy | C7: 0.14650139 | D7: 0.041788851 | E7: 0.0074636755 | F7: 0.032275021 | G7: 0.068685696
B8: GM | C8: 0.77099956 | D8: 0.78051345 | E8: 0.78100161 | J8: 0.78960176 | K8: 0.68913365 | L8: 0.78902659 | M8: 0.77152395
B9: OPM (EBIT margin) | C9: 0.29952212 | D9: 0.29473992 | E9: 0.29160877 | J9: 0.35005464 | K9: 0.18337066 | L9: 0.36119505 | M9: 0.19023391
B10: Net Profit (GAAP) | C10: 612 | D10: 640 | E10: 627 | F10: 640 | G10: 693 | J10: 459 | K10: 153 | L10: 473 | M10: 165
B11: NPM | C11: 0.2050558 | D11: 0.20572906 | E11: 0.20007803 | F11: 0.19788971 | G11: 0.2005445 | J11: 0.24423277 | K11: 0.1252055 | L11: 0.24821358 | M11: 0.12769243
B12: EPS (diluted) | C12: 2.27 | D12: 2.36 | E12: 2.31 | F12: 2.35237 | G12: 2.54767 | J12: 1.7 | K12: 0.57 | L12: 1.71 | M12: 0.6
B13: Shares Out (mm) | C13: 54.9 | D13: 55 | E13: 55 | F13: 272 | G13: 272 | J13: 55 | K13: 55 | L13: 55 | M13: 55 | N13: 272 | O13: 272
B15: Date | C15: 46307
B16: Share price (EUR) | C16: 43.67
B17: Market Cap (EUR mm) | C17: 11878
B18: Forward PE | C18: =IF(OR(C10="",C10<=0),"",C$17/C10) -> 19.408497 | D18: =IF(OR(D10="",D10<=0),"",C$17/D10) -> 18.559375 | E18: =IF(OR(E10="",E10<=0),"",C$17/E10) -> 18.944179 | F18: =IF(OR(F10="",F10<=0),"",C$17/F10) -> 18.559375 | G18: =IF(OR(G10="",G10<=0),"",C$17/G10) -> 17.139971
B19: Forward PS | C19: =IF(OR(C6="",C6=0),"",C$17/C6) -> 3.980563 | D19: =IF(OR(D6="",D6=0),"",C$17/D6) -> 3.8205211 | E19: =IF(OR(E6="",E6=0),"",C$17/E6) -> 3.7924649 | F19: =IF(OR(F6="",F6=0),"",C$17/F6) -> 3.673987 | G19: =IF(OR(G6="",G6=0),"",C$17/G6) -> 3.4379161
B21: # Analysts (rev) | F21: 24 | G21: 24

Sheet KER
B3: KER, Kering S.A.
B4: End in | F4: 46384 | G4: 46749 | N4: 46295 | O4: 46386
B5: Fiscal year | C5: 2023 | D5: 2024 | E5: 2025 | F5: 2026E | G5: 2027E | J5: 24Q4 | K5: 25Q2 | L5: 25Q4 | M5: 26Q2 | N5: 26Q3 | O5: 26Q4
B6: Revenue | C6: 19566 | D6: 17194 | E6: 14675 | F6: 14620 | G6: 15433 | J6: 8176 | K6: 7587 | L6: 7088 | M6: 7220
B7: yoy | C7: -0.038573043 | D7: -0.12123071 | E7: -0.14650459 | F7: -0.0037302724 | G7: 0.055557831
B8: GM | C8: 0.76290504 | D8: 0.73752472 | E8: 0.53717206 | J8: 0.73055284 | K8: 0.73006458 | L8: 0.72248871 | M8: 0.71606648
B9: OPM (EBIT margin) | C9: 0.24256363 | D9: 0.13446551 | E9: 0.1111414 | J9: 0.090875734 | K9: 0.12771847 | L9: 0.093397291 | M9: 0.12756233
B10: Net Profit (GAAP) | C10: 2983 | D10: 1133 | E10: 72 | F10: 781 | G10: 1203 | J10: 255 | K10: 474 | L10: -402 | M10: 189
B11: NPM | C11: 0.15245835 | D11: 0.06589508 | E11: 0.0049063032 | F11: 0.053394413 | G11: 0.07793585 | J11: 0.031188845 | K11: 0.062475287 | L11: -0.056715576 | M11: 0.026177285
B12: EPS (diluted) | C12: 24.37 | D12: 9.24 | E12: 0.59 | F12: 6.36641 | G12: 9.80885 | J12: 2.08 | K12: 3.87 | L12: -3.27 | M12: 1.54
B13: Shares Out (mm) | C13: 493 | D13: 493 | E13: 493 | F13: 122.6 | G13: 122.6 | J13: 493 | K13: 493 | L13: 493 | M13: 493 | N13: 122.6 | O13: 122.6
B15: Date | C15: 46307
B16: Share price (EUR) | C16: 214.8
B17: Market Cap (EUR mm) | C17: 26338
B18: Forward PE | C18: =IF(OR(C10="",C10<=0),"",C$17/C10) -> 8.8293664 | D18: =IF(OR(D10="",D10<=0),"",C$17/D10) -> 23.246249 | E18: =IF(OR(E10="",E10<=0),"",C$17/E10) -> 365.80556 | F18: =IF(OR(F10="",F10<=0),"",C$17/F10) -> 33.723431 | G18: =IF(OR(G10="",G10<=0),"",C$17/G10) -> 21.893599
B19: Forward PS | C19: =IF(OR(C6="",C6=0),"",C$17/C6) -> 1.3461106 | D19: =IF(OR(D6="",D6=0),"",C$17/D6) -> 1.5318134 | E19: =IF(OR(E6="",E6=0),"",C$17/E6) -> 1.794753 | F19: =IF(OR(F6="",F6=0),"",C$17/F6) -> 1.8015048 | G19: =IF(OR(G6="",G6=0),"",C$17/G6) -> 1.7066027
B21: # Analysts (rev) | F21: 23 | G21: 24

Sheet SFER
B3: SFER, Salvatore Ferragamo S.p.A.
B4: End in | F4: 46384 | G4: 46749 | N4: 46295 | O4: 46386
B5: Fiscal year | C5: 2023 | D5: 2024 | E5: 2025 | F5: 2026E | G5: 2027E | J5: 25Q3 | K5: 25Q4 | L5: 26Q1 | M5: 26Q2 | N5: 26Q3 | O5: 26Q4
B6: Revenue | C6: 1156 | D6: 1035 | E6: 977 | F6: 964 | G6: 1005 | J6: 251 | K6: 251 | L6: 234 | M6: 234
B7: yoy | C7: -0.076319212 | D7: -0.10478945 | E7: -0.056588407 | F7: -0.012975834 | G7: 0.042342513
B8: GM | C8: 0.72598206 | D8: 0.71491036 | E8: 0.70666164 | J8: 0.68476554 | K8: 0.68476554 | L8: 0.69232266 | M8: 0.69232266
B9: OPM (EBIT margin) | C9: 0.062288166 | D9: -0.047339113 | E9: 0.01128382 | J9: 0.045199775 | K9: 0.045199775 | L9: 0.04471735 | M9: 0.04471735
B10: Net Profit (GAAP) | C10: 26 | D10: -68 | E10: -49 | F10: 7 | G10: 24 | J10: 4 | K10: 4 | L10: 1 | M10: 1
B11: NPM | C11: 0.022537969 | D11: -0.065777804 | E11: -0.050618977 | F11: 0.0071887339 | G11: 0.023787729 | J11: 0.016468655 | K11: 0.016468655 | L11: 0.0030354528 | M11: 0.0030354528
B12: EPS (diluted) | C12: 0.16 | D12: -0.41 | E12: -0.3 | F12: 0.041822 | G12: 0.14425 | J12: 0.025 | K12: 0.025 | L12: 0.0043 | M12: 0.0043
B13: Shares Out (mm) | C13: 16.9 | D13: 16.9 | E13: 16.9 | F13: 165.7 | G13: 165.7 | J13: 16.9 | K13: 16.9 | L13: 16.9 | M13: 16.9 | N13: 165.7 | O13: 165.7
B15: Date | C15: 46307
B16: Share price (EUR) | C16: 6.98
B17: Market Cap (EUR mm) | C17: 1156
B18: Forward PE | C18: =IF(OR(C10="",C10<=0),"",C$17/C10) -> 44.461538 | D18: =IF(OR(D10="",D10<=0),"",C$17/D10) | E18: =IF(OR(E10="",E10<=0),"",C$17/E10) | F18: =IF(OR(F10="",F10<=0),"",C$17/F10) -> 165.14286 | G18: =IF(OR(G10="",G10<=0),"",C$17/G10) -> 48.166667
B19: Forward PS | C19: =IF(OR(C6="",C6=0),"",C$17/C6) -> 1 | D19: =IF(OR(D6="",D6=0),"",C$17/D6) -> 1.1169082 | E19: =IF(OR(E6="",E6=0),"",C$17/E6) -> 1.1832139 | F19: =IF(OR(F6="",F6=0),"",C$17/F6) -> 1.1991701 | G19: =IF(OR(G6="",G6=0),"",C$17/G6) -> 1.1502488
B21: # Analysts (rev) | F21: 14 | G21: 15

Sheet RACE
B3: RACE, Ferrari N.V.
B4: End in | F4: 46384 | G4: 46749 | N4: 46295 | O4: 46386
B5: Fiscal year | C5: 2023 | D5: 2024 | E5: 2025 | F5: 2026E | G5: 2027E | J5: 25Q3 | K5: 25Q4 | L5: 26Q1 | M5: 26Q2 | N5: 26Q3 | O5: 26Q4
B6: Revenue | C6: 5970 | D6: 6677 | E6: 7146 | F6: 7585 | G6: 8222 | J6: 1766 | K6: 1801 | L6: 1848 | M6: 1935
B7: yoy | C7: 0.17170724 | D7: 0.1183425 | E7: 0.070259597 | F7: 0.061468405 | G7: 0.083939793
B8: GM | C8: 0.49819033 | D8: 0.50132566 | E8: 0.51678098 | J8: 0.50050845 | K8: 0.51884435 | L8: 0.51833963 | M8: 0.52592543
B9: OPM (EBIT margin) | C9: 0.27304692 | D9: 0.28336724 | E9: 0.29348056 | J9: 0.28393415 | K9: 0.28238353 | L9: 0.29878133 | M9: 0.31662649
B10: Net Profit (GAAP) | C10: 1252 | D10: 1522 | E10: 1597 | F10: 1721 | G10: 1927 | J10: 381 | K10: 380 | L10: 413 | M10: 462
B11: NPM | C11: 0.20971815 | D11: 0.2279396 | E11: 0.22347759 | F11: 0.22691245 | G11: 0.23441297 | J11: 0.21590618 | K11: 0.21078338 | L11: 0.22340177 | M11: 0.23854391
B12: EPS (diluted) | C12: 6.91 | D12: 8.47 | E12: 8.96 | F12: 9.78383 | G12: 10.95563 | J12: 2.14 | K12: 2.14 | L12: 2.35 | M12: 2.62
B13: Shares Out (mm) | C13: 2.6 | D13: 2.6 | E13: 2.6 | F13: 175.9 | G13: 175.9 | J13: 2.6 | K13: 2.6 | L13: 2.6 | M13: 2.6 | N13: 175.9 | O13: 175.9
B15: Date | C15: 46307
B16: Share price (USD) | C16: 389.91
B17: Market Cap (EUR mm) | C17: 61211
B18: Forward PE | C18: =IF(OR(C10="",C10<=0),"",C$17/C10) -> 48.890575 | D18: =IF(OR(D10="",D10<=0),"",C$17/D10) -> 40.217477 | E18: =IF(OR(E10="",E10<=0),"",C$17/E10) -> 38.328741 | F18: =IF(OR(F10="",F10<=0),"",C$17/F10) -> 35.567112 | G18: =IF(OR(G10="",G10<=0),"",C$17/G10) -> 31.76492
B19: Forward PS | C19: =IF(OR(C6="",C6=0),"",C$17/C6) -> 10.253099 | D19: =IF(OR(D6="",D6=0),"",C$17/D6) -> 9.1674405 | E19: =IF(OR(E6="",E6=0),"",C$17/E6) -> 8.5657711 | F19: =IF(OR(F6="",F6=0),"",C$17/F6) -> 8.0700066 | G19: =IF(OR(G6="",G6=0),"",C$17/G6) -> 7.4447823
B21: # Analysts (rev) | F21: 15 | G21: 15

Sheet RMS
B3: RMS, Hermès International Société en commandite par actions
B4: End in | F4: 46384 | G4: 46749 | N4: 46295 | O4: 46386
B5: Fiscal year | C5: 2023 | D5: 2024 | E5: 2025 | F5: 2026E | G5: 2027E | J5: 24Q4 | K5: 25Q2 | L5: 25Q4 | M5: 26Q2 | N5: 26Q3 | O5: 26Q4
B6: Revenue | C6: 13427 | D6: 15170 | E6: 16002 | F6: 16714 | G6: 18000 | J6: 7666 | K6: 8034 | L6: 7968 | M6: 8163
B7: yoy | C7: 0.15730047 | D7: 0.12981306 | E7: 0.054845089 | F7: 0.044488356 | G7: 0.076934107
B8: GM | C8: 0.7229463 | D8: 0.70263678 | E8: 0.71109861 | J8: 0.69932168 | K8: 0.66268359 | L8: 0.71548695 | M8: 0.66421659
B9: OPM (EBIT margin) | C9: 0.42079392 | D9: 0.40540541 | E9: 0.4183852 | J9: 0.39159927 | K9: 0.41859597 | L9: 0.49447791 | M9: 0.41724856
B10: Net Profit (GAAP) | C10: 4311 | D10: 4603 | E10: 4524 | F10: 4633 | G10: 5119 | J10: 2235 | K10: 2246 | L10: 2277 | M10: 2238
B11: NPM | C11: 0.32106949 | D11: 0.30342782 | E11: 0.28271466 | F11: 0.27720581 | G11: 0.28441721 | J11: 0.29154709 | K11: 0.27956186 | L11: 0.28576807 | M11: 0.27416391
B12: EPS (diluted) | C12: 41.2 | D12: 43.93 | E12: 43.15 | F12: 44.23435 | G12: 48.87675 | J12: 21.32 | K12: 21.42 | L12: 21.73 | M12: 21.36
B13: Shares Out (mm) | C13: 54 | D13: 54 | E13: 54 | F13: 104.7 | G13: 104.7 | J13: 54 | K13: 54 | L13: 54 | M13: 54 | N13: 104.7 | O13: 104.7
B15: Date | C15: 46307
B16: Share price (EUR) | C16: 1302.5
B17: Market Cap (EUR mm) | C17: 136426
B18: Forward PE | C18: =IF(OR(C10="",C10<=0),"",C$17/C10) -> 31.646022 | D18: =IF(OR(D10="",D10<=0),"",C$17/D10) -> 29.638497 | E18: =IF(OR(E10="",E10<=0),"",C$17/E10) -> 30.156057 | F18: =IF(OR(F10="",F10<=0),"",C$17/F10) -> 29.446579 | G18: =IF(OR(G10="",G10<=0),"",C$17/G10) -> 26.650908
B19: Forward PS | C19: =IF(OR(C6="",C6=0),"",C$17/C6) -> 10.160572 | D19: =IF(OR(D6="",D6=0),"",C$17/D6) -> 8.9931444 | E19: =IF(OR(E6="",E6=0),"",C$17/E6) -> 8.5255593 | F19: =IF(OR(F6="",F6=0),"",C$17/F6) -> 8.1623788 | G19: =IF(OR(G6="",G6=0),"",C$17/G6) -> 7.5792222
B21: # Analysts (rev) | F21: 21 | G21: 21

Sheet MC
B3: MC, LVMH Moët Hennessy - Louis Vuitton, Société Européenne
B4: End in | F4: 46384 | G4: 46749 | N4: 46295 | O4: 46386
B5: Fiscal year | C5: 2023 | D5: 2024 | E5: 2025 | F5: 2026E | G5: 2027E | J5: 24Q4 | K5: 25Q2 | L5: 25Q4 | M5: 26Q2 | N5: 26Q3 | O5: 26Q4
B6: Revenue | C6: 86153 | D6: 84683 | E6: 80807 | F6: 80371 | G6: 83880 | J6: 43006 | K6: 39810 | L6: 40997 | M6: 38644
B7: yoy | C7: 0.088010204 | D7: -0.017062668 | E7: -0.045770698 | F7: -0.0053988835 | G7: 0.043667918
B8: GM | C8: 0.68804336 | D8: 0.67032344 | E8: 0.66241786 | J8: 0.65274613 | K8: 0.66842502 | L8: 0.65658463 | M8: 0.67115205
B9: OPM (EBIT margin) | C9: 0.26185971 | D9: 0.22326795 | E9: 0.21879293 | J9: 0.19260103 | K9: 0.22579754 | L9: 0.21199112 | M9: 0.2243039
B10: Net Profit (GAAP) | C10: 15174 | D10: 12550 | E10: 10878 | F10: 10941 | G10: 11997 | J10: 5283 | K10: 5698 | L10: 5180 | M10: 5697
B11: NPM | C11: 0.17612852 | D11: 0.14819976 | E11: 0.13461705 | F11: 0.13613501 | G11: 0.14302327 | J11: 0.12284332 | K11: 0.14312987 | L11: 0.12635071 | M11: 0.14742263
B12: EPS (diluted) | C12: 30.34 | D12: 25.13 | E12: 21.86 | F12: 22.18878 | G12: 24.32947 | J12: 10.58 | K12: 11.43 | L12: 10.43 | M12: 11.52
B13: Shares Out (mm) | C13: 151 | D13: 150 | E13: 149 | F13: 493.1 | G13: 493.1 | J13: 150 | K13: 150 | L13: 149 | M13: 149 | N13: 493.1 | O13: 493.1
B15: Date | C15: 46307
B16: Share price (EUR) | C16: 384.95
B17: Market Cap (EUR mm) | C17: 189819
B18: Forward PE | C18: =IF(OR(C10="",C10<=0),"",C$17/C10) -> 12.50949 | D18: =IF(OR(D10="",D10<=0),"",C$17/D10) -> 15.12502 | E18: =IF(OR(E10="",E10<=0),"",C$17/E10) -> 17.449807 | F18: =IF(OR(F10="",F10<=0),"",C$17/F10) -> 17.349328 | G18: =IF(OR(G10="",G10<=0),"",C$17/G10) -> 15.822206
B19: Forward PS | C19: =IF(OR(C6="",C6=0),"",C$17/C6) -> 2.2032779 | D19: =IF(OR(D6="",D6=0),"",C$17/D6) -> 2.2415243 | E19: =IF(OR(E6="",E6=0),"",C$17/E6) -> 2.3490415 | F19: =IF(OR(F6="",F6=0),"",C$17/F6) -> 2.3617847 | G19: =IF(OR(G6="",G6=0),"",C$17/G6) -> 2.2629828
B21: # Analysts (rev) | F21: 24 | G21: 24

Sheet BRBY
B3: BRBY, Burberry Group plc
B4: End in | F4: 46474 | G4: 46840 | N4: 46203 | O4: 46295
B5: Fiscal year | C5: 2024 | D5: 2025 | E5: 2026 | F5: 2027E | G5: 2028E | J5: 24Q3 | K5: 25Q1 | L5: 25Q3 | M5: 26Q1 | N5: 26Q2 | O5: 26Q3
B6: Revenue | C6: 2968 | D6: 2461 | E6: 2420 | F6: 2537 | G6: 2680 | J6: 1086 | K6: 1375 | L6: 1032 | M6: 1388
B7: yoy | C7: -0.040723982 | D7: -0.1708221 | E7: -0.016659894 | F7: 0.04854824 | G7: 0.056196654
B8: GM | C8: 0.67688679 | D8: 0.62494921 | E8: 0.52520661 | J8: 0.63443831 | K8: 0.61745455 | L8: 0.55135659 | M8: 0.54394813
B9: OPM (EBIT margin) | C9: 0.14083558 | D9: -0.0012190167 | E9: 0.06322314 | J9: -0.048802947 | K9: 0.036363636 | L9: 0.018410853 | M9: 0.10158501
B10: Net Profit (GAAP) | C10: 270 | D10: -75 | E10: 21 | F10: 1 | G10: 2 | J10: -74 | K10: -1 | L10: -26 | M10: 47
B11: NPM | C11: 0.09097035 | D11: -0.030475416 | E11: 0.008677686 | F11: 0.00053614056 | G11: 0.00073584631 | J11: -0.068139963 | K11: -0.00072727273 | L11: -0.025193798 | M11: 0.033861671
B12: EPS (diluted) | C12: 0.74 | D12: -0.21 | E12: 0.0586 | F12: 0.37979 | G12: 0.55055 | J12: -0.21 | K12: -0.0028 | L12: -0.0726 | M12: 0.13
B13: Shares Out (mm) | C13: 0 | D13: 0 | E13: 0 | F13: 3.6 | G13: 3.6 | J13: 0 | K13: 0 | L13: 0 | M13: 0 | N13: 3.6 | O13: 3.6
B15: Date | C15: 46307
B16: Share price (GBp) | C16: 1030.5
B17: Market Cap (GBP mm) | C17: 37
B18: Forward PE | C18: =IF(OR(C10="",C10<=0),"",C$17/C10) -> 0.13703704 | D18: =IF(OR(D10="",D10<=0),"",C$17/D10) | E18: =IF(OR(E10="",E10<=0),"",C$17/E10) -> 1.7619048 | F18: =IF(OR(F10="",F10<=0),"",C$17/F10) -> 37 | G18: =IF(OR(G10="",G10<=0),"",C$17/G10) -> 18.5
B19: Forward PS | C19: =IF(OR(C6="",C6=0),"",C$17/C6) -> 0.012466307 | D19: =IF(OR(D6="",D6=0),"",C$17/D6) -> 0.015034539 | E19: =IF(OR(E6="",E6=0),"",C$17/E6) -> 0.015289256 | F19: =IF(OR(F6="",F6=0),"",C$17/F6) -> 0.014584155 | G19: =IF(OR(G6="",G6=0),"",C$17/G6) -> 0.01380597
B21: # Analysts (rev) | F21: 19 | G21: 17

Sheet CPRI
B3: CPRI, Capri Holdings Limited
B4: End in | F4: 46474 | G4: 46840 | N4: 46292 | O4: 46383
B5: Fiscal year | C5: 2024 | D5: 2025 | E5: 2026 | F5: 2027E | G5: 2028E | J5: 25Q3 | K5: 25Q4 | L5: 26Q1 | M5: 26Q2 | N5: 26Q3 | O5: 26Q4
B6: Revenue | C6: 4442 | D6: 4442 | E6: 3474 | F6: 3402 | G6: 3488 | J6: 856 | K6: 1025 | L6: 796 | M6: 769
B7: yoy | C7: -0.20946788 | D7: 0 | E7: -0.21791986 | F7: -0.020806377 | G7: 0.025467838
B8: GM | C8: 0.63619991 | D8: 0.63619991 | E8: 0.58894646 | J8: 0.57476636 | K8: 0.60780488 | L8: 0.61055276 | M8: 0.65019506
B9: OPM (EBIT margin) | C9: -0.16929311 | D9: -0.16929311 | E9: 0.023603915 | J9: 0.011682243 | K9: 0.044878049 | L9: -0.0087939698 | M9: 0.022106632
B10: Net Profit (GAAP) | C10: -1182 | D10: -1182 | E10: 92 | F10: 244 | G10: 289 | J10: -28 | K10: 116 | L10: -4 | M10: 69
B11: NPM | C11: -0.26609635 | D11: -0.26609635 | E11: 0.026482441 | F11: 0.071703218 | G11: 0.082789299 | J11: -0.03271028 | K11: 0.11317073 | L11: -0.0050251256 | M11: 0.089726918
B12: EPS (diluted) | C12: -10 | D12: -10 | E12: 0.77 | F12: 2.12476 | G12: 2.51575 | J12: -0.28 | K12: 0.97 | L12: -0.0337 | M12: 0.6
B13: Shares Out (mm) | C13: 0 | D13: 0 | E13: 0 | F13: 114.8 | G13: 114.8 | J13: 0 | K13: 0 | L13: 0 | M13: 0 | N13: 114.8 | O13: 114.8
B15: Date | C15: 46307
B16: Share price (USD) | C16: 14.95
B17: Market Cap (USD mm) | C17: 1716
B18: Forward PE | C18: =IF(OR(C10="",C10<=0),"",C$17/C10) | D18: =IF(OR(D10="",D10<=0),"",C$17/D10) | E18: =IF(OR(E10="",E10<=0),"",C$17/E10) -> 18.652174 | F18: =IF(OR(F10="",F10<=0),"",C$17/F10) -> 7.0327869 | G18: =IF(OR(G10="",G10<=0),"",C$17/G10) -> 5.9377163
B19: Forward PS | C19: =IF(OR(C6="",C6=0),"",C$17/C6) -> 0.38631247 | D19: =IF(OR(D6="",D6=0),"",C$17/D6) -> 0.38631247 | E19: =IF(OR(E6="",E6=0),"",C$17/E6) -> 0.49395509 | F19: =IF(OR(F6="",F6=0),"",C$17/F6) -> 0.50440917 | G19: =IF(OR(G6="",G6=0),"",C$17/G6) -> 0.49197248
B21: # Analysts (rev) | F21: 11 | G21: 11

Sheet PVH
B3: PVH, PVH Corp.
B4: End in | F4: 46419 | G4: 46784 | N4: 46328 | O4: 46420
B5: Fiscal year | C5: 2024 | D5: 2025 | E5: 2026 | F5: 2027E | G5: 2028E | J5: 25Q4 | K5: 26Q1 | L5: 26Q2 | M5: 26Q3 | N5: 26Q4 | O5: 27Q1
B6: Revenue | C6: 9218 | D6: 8653 | E6: 8950 | F6: 8901 | G6: 9051 | J6: 2294 | K6: 2505 | L6: 2025 | M6: 2097
B7: yoy | C7: 0.021442344 | D7: -0.06127342 | E7: 0.034358423 | F7: -0.0054874882 | G7: 0.016827273
B8: GM | C8: 0.58017727 | D8: 0.59111974 | E8: 0.57524972 | J8: 0.56047596 | K8: 0.58464732 | L8: 0.58574885 | M8: 0.63032904
B9: OPM (EBIT margin) | C9: 0.10279137 | D9: 0.079233552 | E9: 0.073350316 | J9: 0.070522599 | K9: 0.089856692 | L9: 0.058614389 | M9: -0.091034812
B10: Net Profit (GAAP) | C10: 664 | D10: 598 | E10: 25 | F10: 558 | G10: 575 | J10: 4 | K10: -158 | L10: 88 | M10: -103
B11: NPM | C11: 0.071991929 | D11: 0.069167562 | E11: 0.0028267525 | F11: 0.062636273 | G11: 0.063498782 | J11: 0.0018306237 | K11: -0.06319109 | L11: 0.043454644 | M11: -0.0490701
B12: EPS (diluted) | C12: 10.88 | D12: 10.69 | E12: 0.53 | F12: 12.09182 | G12: 12.4646 | J12: 0.0888 | K12: -3.34 | L12: 1.92 | M12: -2.23
B13: Shares Out (mm) | C13: 88.6 | D13: 89.1 | E13: 89.6 | F13: 46.1 | G13: 46.1 | J13: 89.6 | K13: 89.6 | L13: 90 | M13: 90.1 | N13: 46.1 | O13: 46.1
B15: Date | C15: 46307
B16: Share price (USD) | C16: 81.35
B17: Market Cap (USD mm) | C17: 3751
B18: Forward PE | C18: =IF(OR(C10="",C10<=0),"",C$17/C10) -> 5.6490964 | D18: =IF(OR(D10="",D10<=0),"",C$17/D10) -> 6.2725753 | E18: =IF(OR(E10="",E10<=0),"",C$17/E10) -> 150.04 | F18: =IF(OR(F10="",F10<=0),"",C$17/F10) -> 6.7222222 | G18: =IF(OR(G10="",G10<=0),"",C$17/G10) -> 6.5234783
B19: Forward PS | C19: =IF(OR(C6="",C6=0),"",C$17/C6) -> 0.40692124 | D19: =IF(OR(D6="",D6=0),"",C$17/D6) -> 0.43349127 | E19: =IF(OR(E6="",E6=0),"",C$17/E6) -> 0.41910615 | F19: =IF(OR(F6="",F6=0),"",C$17/F6) -> 0.42141332 | G19: =IF(OR(G6="",G6=0),"",C$17/G6) -> 0.41442934
B21: # Analysts (rev) | F21: 9 | G21: 9

Sheet TPR
B3: TPR, Tapestry, Inc.
B4: End in | F4: 46565 | G4: 46931 | N4: 46292 | O4: 46383
B5: Fiscal year | C5: 2024 | D5: 2025 | E5: 2026 | F5: 2027E | G5: 2028E | J5: 25Q3 | K5: 25Q4 | L5: 26Q1 | M5: 26Q2 | N5: 26Q3 | O5: 26Q4
B6: Revenue | C6: 6671 | D6: 7011 | E6: 8004 | F6: 8554 | G6: 9011 | J6: 1705 | K6: 2502 | L6: 1921 | M6: 1877
B7: yoy | C7: 0.0015463376 | D7: 0.050890395 | E7: 0.14171195 | F7: 0.068699026 | G7: 0.053465411
B8: GM | C8: 0.73292661 | D8: 0.75440398 | E8: 0.77821644 | J8: 0.76293559 | K8: 0.75463555 | L8: 0.76877018 | M8: 0.83320899
B9: OPM (EBIT margin) | C9: 0.17089879 | D9: 0.05919523 | E9: 0.23917443 | J9: 0.19253784 | K9: 0.28628517 | L9: 0.22258669 | M9: 0.23569221
B10: Net Profit (GAAP) | C10: 816 | D10: 183 | E10: 1528 | F10: 1613 | G10: 1803 | J10: 275 | K10: 561 | L10: 344 | M10: 348
B11: NPM | C11: 0.12231682 | D11: 0.026131485 | E11: 0.1908623 | F11: 0.1885841 | G11: 0.20005182 | J11: 0.16121084 | K11: 0.22430467 | L11: 0.17900656 | M11: 0.18533518
B12: EPS (diluted) | C12: 3.56 | D12: 0.85 | E12: 7.49 | F12: 7.98418 | G12: 8.92253 | J12: 1.32 | K12: 2.75 | L12: 1.7 | M12: 1.72
B13: Shares Out (mm) | C13: 2.3 | D13: 2.1 | E13: 2 | F13: 202 | G13: 202 | J13: 2.1 | K13: 2 | L13: 2 | M13: 2 | N13: 202 | O13: 202
B15: Date | C15: 46307
B16: Share price (USD) | C16: 116.24
B17: Market Cap (USD mm) | C17: 23486
B18: Forward PE | C18: =IF(OR(C10="",C10<=0),"",C$17/C10) -> 28.781863 | D18: =IF(OR(D10="",D10<=0),"",C$17/D10) -> 128.3388 | E18: =IF(OR(E10="",E10<=0),"",C$17/E10) -> 15.370419 | F18: =IF(OR(F10="",F10<=0),"",C$17/F10) -> 14.560446 | G18: =IF(OR(G10="",G10<=0),"",C$17/G10) -> 13.026068
B19: Forward PS | C19: =IF(OR(C6="",C6=0),"",C$17/C6) -> 3.5206116 | D19: =IF(OR(D6="",D6=0),"",C$17/D6) -> 3.3498788 | E19: =IF(OR(E6="",E6=0),"",C$17/E6) -> 2.9342829 | F19: =IF(OR(F6="",F6=0),"",C$17/F6) -> 2.7456161 | G19: =IF(OR(G6="",G6=0),"",C$17/G6) -> 2.60637
B21: # Analysts (rev) | F21: 15 | G21: 15

Sheet GOOS
B3: GOOS, Canada Goose Holdings Inc.
B4: End in | F4: 46474 | G4: 46840 | N4: 46295 | O4: 46386
B5: Fiscal year | C5: 2024 | D5: 2025 | E5: 2026 | F5: 2027E | G5: 2028E | J5: 25Q3 | K5: 25Q4 | L5: 26Q1 | M5: 26Q2 | N5: 26Q3 | O5: 26Q4
B6: Revenue | C6: 1334 | D6: 1348 | E6: 1528 | F6: 1578 | G6: 1642 | J6: 273 | K6: 694 | L6: 453 | M6: 119
B7: yoy | C7: 0.095973706 | D7: 0.010946169 | E7: 0.13334322 | F7: 0.032616154 | G7: 0.040505089
B8: GM | C8: 0.68780927 | D8: 0.69942154 | E8: 0.61117655 | J8: 0.6239912 | K8: 0.69618431 | L8: 0.61769248 | M8: 0.34650967
B9: OPM (EBIT margin) | C9: 0.09334233 | D9: 0.12169979 | E9: 0.058107578 | J9: -0.064563463 | K9: 0.2899928 | L9: 0.14317229 | M9: -0.88645921
B10: Net Profit (GAAP) | C10: 58 | D10: 95 | E10: 22 | F10: 101 | G10: 112 | J10: -15 | K10: 135 | L10: 28 | M10: -91
B11: NPM | C11: 0.043784675 | D11: 0.070305547 | E11: 0.014723204 | F11: 0.063779675 | G11: 0.068161642 | J11: -0.055759354 | K11: 0.19409647 | L11: 0.061989852 | M11: -0.76366695
B12: EPS (diluted) | C12: 0.58 | D12: 0.98 | E12: 0.23 | F12: 1.03596 | G12: 1.15198 | J12: -0.16 | K12: 1.39 | L12: 0.29 | M12: -0.93
B13: Shares Out (mm) | C13: 104.9 | D13: 109.6 | E13: 114.1 | F13: 97.2 | G13: 97.2 | J13: 109.5 | K13: 113.8 | L13: 114.1 | M13: 124.7 | N13: 97.2 | O13: 97.2
B15: Date | C15: 46307
B16: Share price (CAD) | C16: 11.27
B17: Market Cap (CAD mm) | C17: 1095
B18: Forward PE | C18: =IF(OR(C10="",C10<=0),"",C$17/C10) -> 18.87931 | D18: =IF(OR(D10="",D10<=0),"",C$17/D10) -> 11.526316 | E18: =IF(OR(E10="",E10<=0),"",C$17/E10) -> 49.772727 | F18: =IF(OR(F10="",F10<=0),"",C$17/F10) -> 10.841584 | G18: =IF(OR(G10="",G10<=0),"",C$17/G10) -> 9.7767857
B19: Forward PS | C19: =IF(OR(C6="",C6=0),"",C$17/C6) -> 0.82083958 | D19: =IF(OR(D6="",D6=0),"",C$17/D6) -> 0.81231454 | E19: =IF(OR(E6="",E6=0),"",C$17/E6) -> 0.71662304 | F19: =IF(OR(F6="",F6=0),"",C$17/F6) -> 0.69391635 | G19: =IF(OR(G6="",G6=0),"",C$17/G6) -> 0.66686967
B21: # Analysts (rev) | F21: 11 | G21: 10
