Workbook
Name ___OR2: #REF!
Name ___OR3: #REF!
Name ___OR4: #REF!
Name __ANI01: #REF!
Name __ANI02: #REF!
Name __ANI03: #REF!
Name __ANI04: #REF!
Name __ANI05: #REF!
Name __ANI06: #REF!
Name __ANI07: #REF!
Name __ANI87: #REF!
Name __ANI88: #REF!
Name __ANI89: #REF!
Name __ANI90: #REF!
Name __ANI91: #REF!
Name __ANI92: #REF!
Name __ANI93: #REF!
Name __ANI94: #REF!
Name __ANI95: #REF!
Name __ANI96: #REF!
Name __ANI97: #REF!
Name __ANI98: #REF!
Name __ANI99: #REF!
Name __DPS01: #REF!
Name __DPS04: #REF!
Name __DPS98: #REF!
Name __DPS99: #REF!
Name __FEE01: #REF!
Name __FEE02: #REF!
Name __FEE03: #REF!
Name __FEE04: #REF!
Name __FEE05: #REF!
Name __FEE06: #REF!
Name __FEE07: #REF!
Name __FEE87: #REF!
Name __FEE88: #REF!
Name __FEE89: #REF!
Name __FEE90: #REF!
Name __FEE91: #REF!
Name __FEE92: #REF!
Name __FEE93: #REF!
Name __FEE94: #REF!
Name __FEE95: #REF!
Name __FEE96: #REF!
Name __FEE97: #REF!
Name __FEE98: #REF!
Name __FEE99: #REF!
Name __GBP01: #REF!
Name __GBP98: #REF!
Name __GBP99: #REF!
Name __GOI01: #REF!
Name __GOI02: #REF!
Name __GOI03: #REF!
Name __GOI04: #REF!
Name __GOI05: #REF!
Name __GOI06: #REF!
Name __GOI07: #REF!
Name __GOI87: #REF!
Name __GOI88: #REF!
Name __GOI89: #REF!

Sheet 1. Cover
F3: Amer Sports, Inc.
F4: COMPANY MODEL
B9: Sources: Company data, Goldman Sachs Global Investment Research
B11: Date: September 21st, 2026
B13: Brooke Roach, CFA
B14: Managing Director
B15: tel: 212-357-2421
B16: brooke.roach@gs.com
B18: Mentesnot Adamu
B19: Analyst
B20: tel: 801-744-0630
B21: mentesnot.adamu@gs.com
B23: Carly Chasen
B24: Analyst
... B26: carly.chasen@gs.com

Sheet 2. Consolidated
B1: Amer Sports, Inc.
B2: Annual Consolidated Financial Statements
B3: $ millions, FY ending Saturday closest to December 31
C5: 44196 | D5: 44286 | E5: 44377 | F5: 44469 | G5: 44561 | H5: 44561 | I5: =DATE(YEAR(D5)+1,MONTH(D5),DAY(D5)) -> 44651 | J5: =DATE(YEAR(E5)+1,MONTH(E5),DAY(E5)) -> 44742 | K5: =DATE(YEAR(F5)+1,MONTH(F5),DAY(F5)) -> 44834 | L5: =DATE(YEAR(G5)+1,MONTH(G5),DAY(G5)) -> 44926 | M5: =DATE(YEAR(H5)+1,MONTH(H5),DAY(H5)) -> 44926 | N5: =DATE(YEAR(I5)+1,MONTH(I5),DAY(I5)) -> 45016 | O5: =DATE(YEAR(J5)+1,MONTH(J5),DAY(J5)) -> 45107 | P5: =DATE(YEAR(K5)+1,MONTH(K5),DAY(K5)) -> 45199 | ... R5: =DATE(YEAR(M5)+1,MONTH(M5),DAY(M5)) -> 45291 | S5: =H5 -> 44561 | T5: =M5 -> 44926 | U5: =N5 -> 45016 | V5: =O5 -> 45107 | W5: =P5 -> 45199 | X5: =Q5 -> 45291 | Y5: =R5 -> 45291 | Z5: =DATE(YEAR(N5)+1,MONTH(N5),DAY(N5)) -> 45382 | AA5: =DATE(YEAR(O5)+1,MONTH(O5),DAY(O5)) -> 45473 | AB5: =DATE(YEAR(P5)+1,MONTH(P5),DAY(P5)) -> 45565 | AC5: =DATE(YEAR(Q5)+1,MONTH(Q5),DAY(Q5)) -> 45657 | AD5: =DATE(YEAR(R5)+1,MONTH(R5),DAY(R5)) -> 45657 | AE5: =DATE(YEAR(Z5)+1,MONTH(Z5),DAY(Z5)) -> 45747 | AF5: =DATE(YEAR(AA5)+1,MONTH(AA5),DAY(AA5)) -> 45838 | AG5: =DATE(YEAR(AB5)+1,MONTH(AB5),DAY(AB5)) -> 45930 | AH5: =DATE(YEAR(AC5)+1,MONTH(AC5),DAY(AC5)) -> 46022 | AI5: =DATE(YEAR(AD5)+1,MONTH(AD5),DAY(AD5)) -> 46022 | AJ5: =DATE(YEAR(AE5)+1,MONTH(AE5),DAY(AE5)) -> 46112 | AK5: =DATE(YEAR(AF5)+1,MONTH(AF5),DAY(AF5)) -> 46203 | AL5: =DATE(YEAR(AG5)+1,MONTH(AG5),DAY(AG5)) -> 46295 | ... AX5: =DATE(YEAR(AS5)+1,MONTH(AS5),DAY(AS5)) -> 47118
C6: FY20 | D6: Q1'21 | E6: Q2'21 | F6: Q3'21 | G6: Q4'21 | H6: FY21 | I6: Q1'22 | J6: Q2'22 | K6: Q3'22 | L6: Q4'22 | M6: FY22 | N6: Q1'23 | O6: Q2'23 | P6: Q3'23 | Q6: Q4'23 | R6: FY23 | S6: =H6&"R" -> FY21R | T6: =M6&"R" -> FY22R | U6: =N6&"R" -> Q1'23R | V6: =O6&"R" -> Q2'23R | W6: =P6&"R" -> Q3'23R | X6: =Q6&"R" -> Q4'23R | Y6: =R6&"R" -> FY23R | Z6: Q1'24 | AA6: Q2'24 | AB6: Q3'24 | AC6: Q4'24 | AD6: FY24 | AE6: Q1'25 | AF6: Q2'25 | AG6: Q3'25 | AH6: Q4'25 | AI6: FY25 | AJ6: Q1'26 | AK6: Q2'26 | AL6: Q3'26E | AM6: Q4'26E | AN6: FY26E | AO6: Q1'27E | AP6: Q2'27E | AQ6: Q3'27E | AR6: Q4'27E | AS6: FY27E | AT6: Q1'28E | AU6: Q2'28E | AV6: Q3'28E | AW6: Q4'28E | AX6: FY28E
B7: Income Statement ($M, except where noted)
B8: Net Sales | C8: ='3. Segment Build'!C12 -> 2446.2 | D8: ='3. Segment Build'!D12 -> 663.49 | E8: ='3. Segment Build'!E12 -> 597.81 | F8: ='3. Segment Build'!F12 -> 806.13 | G8: ='3. Segment Build'!G12 -> 999 | H8: =D8+E8+F8+G8 -> 3066.43 | I8: ='3. Segment Build'!I12 -> 809.15761 | J8: ='3. Segment Build'!J12 -> 693.42159 | K8: ='3. Segment Build'!K12 -> 847.18302 | L8: ='3. Segment Build'!L12 -> 1198.7114 | M8: =I8+J8+K8+L8 -> 3548.4736 | N8: ='3. Segment Build'!N12 -> 1050.3 | O8: ='3. Segment Build'!O12 -> 856.8 | P8: ='3. Segment Build'!P12 -> 1146.3 | Q8: 1315 | R8: =N8+O8+P8+Q8 -> 4368.4 | S8: =H8+19.3 -> 3085.73 | T8: =M8+22.4 -> 3570.8736 | U8: =N8+6.7 -> 1057 | V8: =O8+6 -> 862.8 | W8: =P8+6.8 -> 1153.1 | X8: =Q8+12.5 -> 1327.5 | Y8: =U8+V8+W8+X8 -> 4400.4 | Z8: =1182.9+9.5 -> 1192.4 | AA8: =993.8+7.6 -> 1001.4 | AB8: 1353.8 | AC8: 1635.5 | AD8: =Z8+AA8+AB8+AC8 -> 5183.1 | AE8: 1472.5 | AF8: 1236.3 | AG8: 1756.3 | AH8: 2101.1 | AI8: =AE8+AF8+AG8+AH8 -> 6566.2 | AJ8: 1945.5 | AK8: 1632.6 | AL8: ='3. Segment Build'!AL12 -> 2145.3634 | AM8: ='3. Segment Build'!AM12 -> 2480.2939 | AN8: =AJ8+AK8+AL8+AM8 -> 8203.7573 | AO8: ='3. Segment Build'!AO12 -> 2257.3358 | AP8: ='3. Segment Build'!AP12 -> 1893.2688 | AQ8: ='3. Segment Build'!AQ12 -> 2451.3328 | AR8: ='3. Segment Build'!AR12 -> 2853.541 | AS8: =AO8+AP8+AQ8+AR8 -> 9455.4784 | AT8: ='3. Segment Build'!AT12 -> 2564.9111 | AU8: ='3. Segment Build'!AU12 -> 2152.926 | AV8: ='3. Segment Build'!AV12 -> 2774.1745 | AW8: ='3. Segment Build'!AW12 -> 3255.7219 | AX8: =AT8+AU8+AV8+AW8 -> 10747.734
B9: % chg. y/y | C9: -- | D9: -- | E9: -- | F9: -- | G9: -- | H9: =H8/C8-1 -> 0.25354836 | I9: =I8/D8-1 -> 0.21954756 | J9: =J8/E8-1 -> 0.15993641 | K9: =K8/F8-1 -> 0.05092606 | L9: =L8/G8-1 -> 0.19991127 | M9: =M8/H8-1 -> 0.15720026 | N9: =N8/I8-1 -> 0.29801658 | O9: =O8/J8-1 -> 0.23561195 | ... R9: =R8/M8-1 -> 0.23106454 | S9: -- | T9: =T8/S8-1 -> 0.15722166 | U9: -- | V9: -- | W9: -- | X9: -- | Y9: =Y8/T8-1 -> 0.2323035 | Z9: =Z8/U8-1 -> 0.12809839 | AA9: =AA8/V8-1 -> 0.16063978 | AB9: =AB8/W8-1 -> 0.17405255 | AC9: =AC8/X8-1 -> 0.23201507 | AD9: =AD8/Y8-1 -> 0.17787019 | AE9: =AE8/Z8-1 -> 0.23490439 | AF9: =AF8/AA8-1 -> 0.2345716 | ... AX9: =AX8/AS8-1 -> 0.13666734
B11: COGS | C11: -1297.4 | D11: -336.34878 | E11: -323.56518 | F11: -404.04946 | G11: -496.93783 | H11: =D11+E11+F11+G11 -> -1560.9012 | I11: -408.6 | J11: -364.7 | K11: -415.25413 | L11: -596.68189 | M11: =I11+J11+K11+L11 -> -1785.236 | N11: -495.4 | O11: -400.2 | P11: -564.9 | Q11: =-631.8 -> -631.8 | R11: =N11+O11+P11+Q11 -> -2092.3 | S11: =H11 -> -1560.9012 | T11: =M11 -> -1785.236 | U11: =N11 -> -495.4 | V11: =O11 -> -400.2 | W11: =P11 -> -564.9 | X11: =Q11 -> -631.8 | Y11: =U11+V11+W11+X11 -> -2092.3 | Z11: =-544.4 -> -544.4 | AA11: -442.5 | AB11: -606.5 | AC11: -718 | AD11: =Z11+AA11+AB11+AC11 -> -2311.4 | AE11: -621.4 | AF11: -513.4 | AG11: -758.1 | AH11: =-889 -> -889 | AI11: =AE11+AF11+AG11+AH11 -> -2781.9 | AJ11: -780.1 | AK11: -561 | AL11: =AL12-AL8 -> -883.90696 | AM11: =AM12-AM8 -> -994.02944 | AN11: =AJ11+AK11+AL11+AM11 -> -3219.0364 | AO11: =AO12-AO8 -> -888.66006 | AP11: =AP12-AP8 -> -702.25912 | AQ11: =AQ12-AQ8 -> -991.05612 | AR11: =AR12-AR8 -> -1124.5112 | AS11: =AO11+AP11+AQ11+AR11 -> -3706.4865 | AT11: =AT12-AT8 -> -990.00425 | AU11: =AU12-AU8 -> -781.91786 | AV11: =AV12-AV8 -> -1100.2851 | AW11: =AW12-AW8 -> -1261.3172 | AX11: =AT11+AU11+AV11+AW11 -> -4133.5244
B12: Gross Profit | C12: =C8+C11 -> 1148.8 | D12: =D8+D11 -> 327.14122 | E12: =E8+E11 -> 274.24482 | F12: =F8+F11 -> 402.08054 | G12: =G8+G11 -> 502.06217 | H12: =H8+H11 -> 1505.5288 | I12: =I8+I11 -> 400.55761 | J12: =J8+J11 -> 328.72159 | ... AK12: =AK8+AK11 -> 1071.6 | AL12: =AL17-AL16 -> 1261.4565 | AM12: =AM17-AM16 -> 1486.2645 | AN12: =AN8+AN11 -> 4984.7209 | AO12: =AO17-AO16 -> 1368.6758 | AP12: =AP17-AP16 -> 1191.0096 | AQ12: =AQ17-AQ16 -> 1460.2767 | AR12: =AR17-AR16 -> 1729.0298 | AS12: =AS8+AS11 -> 5748.992 | AT12: =AT17-AT16 -> 1574.9069 | AU12: =AU17-AU16 -> 1371.0081 | AV12: =AV17-AV16 -> 1673.8894 | AW12: =AW17-AW16 -> 1994.4047 | AX12: =AX8+AX11 -> 6614.2091
B13: % margin | C13: =C12/C8 -> 0.46962636 | D13: =D12/D8 -> 0.49306127 | E13: =E12/E8 -> 0.45874914 | F13: =F12/F8 -> 0.49877879 | G13: =G12/G8 -> 0.50256473 | H13: =H12/H8 -> 0.49097118 | I13: =I12/I8 -> 0.49503039 | J13: =J12/J8 -> 0.47405733 | ... AX13: =AX12/AX8 -> 0.61540502
B14: bps chg. y/y | C14: -- | D14: -- | E14: -- | F14: -- | G14: -- | H14: =(H13-C13)*100*100 -> 213.44821 | I14: =(I13-D13)*100*100 -> 19.691244 | J14: =(J13-E13)*100*100 -> 153.0819 | K14: =(K13-F13)*100*100 -> 110.62514 | L14: =(L13-G13)*100*100 -> -3.3418044 | M14: =(M13-H13)*100*100 -> 59.291121 | N14: =(N13-I13)*100*100 -> 332.94846 | O14: =(O13-J13)*100*100 -> 588.55835 | ... R14: =(R13-M13)*100*100 -> 241.37158 | S14: -- | T14: =(T13-S13)*100*100 -> 59.012733 | U14: -- | V14: -- | W14: -- | X14: -- | Y14: =(Y13-T13)*100*100 -> 244.64274 | Z14: =(Z13-U13)*100*100 -> 121.26755 | AA14: =(AA13-V13)*100*100 -> 219.57299 | AB14: =(AB13-W13)*100*100 -> 418.98573 | AC14: =(AC13-X13)*100*100 -> 369.22726 | AD14: =(AD13-Y13)*100*100 -> 295.30167 | AE14: =(AE13-Z13)*100*100 -> 345.54806 | AF14: =(AF13-AA13)*100*100 -> 266.09992 | ... AX14: =(AX13-AS13)*100*100 -> 73.985572
B16: PPA and Other Adjustments | I16: 3.5 | J16: 3.75 | K16: 3.75 | L16: 3 | M16: =I16+J16+K16+L16 -> 14 | N16: 3.8 | O16: 4.4 | P16: =3.7+1 -> 4.7 | Q16: 3.7 | R16: =N16+O16+P16+Q16 -> 16.6 | T16: =M16 -> 14 | U16: =N16 -> 3.8 | V16: =O16 -> 4.4 | W16: =P16 -> 4.7 | X16: =Q16 -> 3.7 | Y16: =U16+V16+W16+X16 -> 16.6 | Z16: 3.7 | AA16: 3.7 | AB16: 3.7 | AC16: =3.7+1.8 -> 5.5 | AD16: =Z16+AA16+AB16+AC16 -> 16.6 | AE16: =3.6-0.8 -> 2.8 | AF16: =-1.3+3.8 -> 2.5 | AG16: =17.5+0.7 -> 18.2 | AH16: 2.8 | AI16: =AE16+AF16+AG16+AH16 -> 26.3 | AJ16: 2.8 | AK16: 2.7 | AL16: 3.7 | AM16: 3.7 | AN16: =AJ16+AK16+AL16+AM16 -> 12.9 | AO16: 3.7 | AP16: 3.7 | AQ16: 3.7 | AR16: 3.7 | AS16: =AO16+AP16+AQ16+AR16 -> 14.8 | AT16: 3.7 | AU16: 3.7 | AV16: 3.7 | AW16: 3.7 | AX16: =AT16+AU16+AV16+AW16 -> 14.8
B17: Adj. Gross Profit | I17: =I12+I16 -> 404.05761 | J17: =J12+J16 -> 332.47159 | K17: =K12+K16 -> 435.67889 | L17: =L12+L16 -> 605.02947 | M17: =I17+J17+K17+L17 -> 1777.2376 | N17: =N12+N16 -> 558.7 | O17: =O12+O16 -> 461 | P17: =P12+P16 -> 586.1 | Q17: =Q12+Q16 -> 686.9 | R17: =N17+O17+P17+Q17 -> 2292.7 | T17: =T12+T16 -> 1799.6376 | U17: =U12+U16 -> 565.4 | V17: =V12+V16 -> 467 | W17: =W12+W16 -> 592.9 | X17: =X12+X16 -> 699.4 | Y17: =Y12+Y16 -> 2324.7 | Z17: =Z12+Z16 -> 651.7 | AA17: =AA12+AA16 -> 562.6 | ... AC17: =AC12+AC16 -> 923 | AD17: =Z17+AA17+AB17+AC17 -> 2888.3 | AE17: =AE12+AE16 -> 853.9 | AF17: =AF12+AF16 -> 725.4 | AG17: =AG12+AG16 -> 1016.4 | AH17: =AH12+AH16 -> 1214.9 | AI17: =AE17+AF17+AG17+AH17 -> 3810.6 | AJ17: =AJ12+AJ16 -> 1168.2 | AK17: =AK12+AK16 -> 1074.3 | AL17: =(AG18+AL19/100/100)*AL8 -> 1265.1565 | AM17: =(AH18+AM19/100/100)*AM8 -> 1489.9645 | AN17: =AJ17+AK17+AL17+AM17 -> 4997.6209 | AO17: =(AJ18+AO19/100/100)*AO8 -> 1372.3758 | AP17: =(AK18+AP19/100/100)*AP8 -> 1194.7096 | AQ17: =(AL18+AQ19/100/100)*AQ8 -> 1463.9767 | AR17: =(AM18+AR19/100/100)*AR8 -> 1732.7298 | AS17: =AO17+AP17+AQ17+AR17 -> 5763.792 | AT17: =(AO18+AT19/100/100)*AT8 -> 1578.6069 | AU17: =(AP18+AU19/100/100)*AU8 -> 1374.7081 | AV17: =(AQ18+AV19/100/100)*AV8 -> 1677.5894 | AW17: =(AR18+AW19/100/100)*AW8 -> 1998.1047 | AX17: =AT17+AU17+AV17+AW17 -> 6629.0091
B18: % margin | I18: =I17/I8 -> 0.49935588 | J18: =J17/J8 -> 0.4794653 | K18: =K17/K8 -> 0.51426773 | L18: =L17/L8 -> 0.50473324 | M18: =M17/M8 -> 0.50084565 | N18: =N17/N8 -> 0.53194325 | O18: =O17/O8 -> 0.53804855 | P18: =P17/P8 -> 0.51129722 | ... R18: =R17/R8 -> 0.52483747 | T18: =T17/T8 -> 0.50397683 | U18: =U17/U8 -> 0.53491012 | V18: =V17/V8 -> 0.54126101 | W18: =W17/W8 -> 0.51417917 | X18: =X17/X8 -> 0.52685499 | Y18: =Y17/Y8 -> 0.52829288 | Z18: =Z17/Z8 -> 0.54654478 | AA18: =AA17/AA8 -> 0.56181346 | ... AX18: =AX17/AX8 -> 0.61678205
B19: bps chg. y/y | I19: -- | J19: -- | K19: -- | L19: -- | M19: -- | N19: =(N18-I18)*100*100 -> 325.87374 | O19: =(O18-J18)*100*100 -> 585.83257 | P19: =(P18-K18)*100*100 -> -29.705172 | Q19: =(Q18-L18)*100*100 -> 176.24175 | R19: =(R18-M18)*100*100 -> 239.91818 | T19: -- | U19: -- | V19: -- | W19: -- | X19: -- | Y19: =(Y18-T18)*100*100 -> 243.16049 | Z19: =(Z18-U18)*100*100 -> 116.34661 | AA19: =(AA18-V18)*100*100 -> 205.5245 | AB19: =(AB18-W18)*100*100 -> 405.55651 | AC19: =(AC18-X18)*100*100 -> 374.98418 | AD19: =(AD18-Y18)*100*100 -> 289.60499 | AE19: =(AE18-Z18)*100*100 -> 333.53349 | AF19: =(AF18-AA18)*100*100 -> 249.37327 | ... AK19: =(AK18-AF18)*100*100 -> 712.79347 | AL19: =75-20+30+45-20 -> 110 | AM19: 225 | AN19: =(AN18-AI18)*100*100 -> 288.51173 | AO19: =65+10 -> 75 | AP19: =65+10-345 -> -270 | AQ19: =65+10 -> 75 | AR19: =65 -> 65 | AS19: =(AS18-AN18)*100*100 -> 3.8485743 | AT19: =65+10 -> 75 | AU19: =65+10 -> 75 | AV19: =65+10 -> 75 | AW19: =65 -> 65 | AX19: =(AX18-AS18)*100*100 -> 72.103616
B21: Selling and marketing expenses | C21: -733.2 | D21: -210.69895 | E21: -222.11811 | F21: -231.97091 | G21: -297.75899 | H21: =D21+E21+F21+G21 -> -962.54696 | I21: -249.1 | J21: -241.6 | K21: -263.6581 | L21: -353.46842 | M21: =I21+J21+K21+L21 -> -1107.8265 | N21: -303.8 | O21: -318.8 | P21: -334.2 | Q21: -424.9 | R21: =N21+O21+P21+Q21 -> -1381.7
B22: % chg. y/y | C22: -- | D22: -- | E22: -- | F22: -- | G22: -- | H22: =H21/C21-1 -> 0.31280273 | I22: =I21/D21-1 -> 0.18225552 | J22: =J21/E21-1 -> 0.08770961 | K22: =K21/F21-1 -> 0.13659984 | L22: =L21/G21-1 -> 0.18709571 | M22: =M21/H21-1 -> 0.15093244 | N22: =N21/I21-1 -> 0.21959053 | O22: =O21/J21-1 -> 0.31953642 | ... R22: =R21/M21-1 -> 0.24721694
B23: % of sales | C23: =-C21/C8 -> 0.29973019 | D23: =-D21/D8 -> 0.31756161 | E23: =-E21/E8 -> 0.37155301 | F23: =-F21/F8 -> 0.28775869 | G23: =-G21/G8 -> 0.29805704 | H23: =-H21/H8 -> 0.31389823 | I23: =-I21/I8 -> 0.30785102 | J23: =-J21/J8 -> 0.34841719 | ... R23: =-R21/R8 -> 0.3162943
B24: bps chg. y/y | C24: -- | D24: -- | E24: -- | F24: -- | G24: -- | H24: =(H23-C23)*100*100 -> 141.6804 | I24: =(I23-D23)*100*100 -> -97.105857 | J24: =(J23-E23)*100*100 -> -231.35825 | K24: =(K23-F23)*100*100 -> 234.58715 | L24: =(L23-G23)*100*100 -> -31.833751 | M24: =(M23-H23)*100*100 -> -17.001873 | N24: =(N23-I23)*100*100 -> -186.00334 | O24: =(O23-J23)*100*100 -> 236.64977 | ... R24: =(R23-M23)*100*100 -> 40.962487
B26: Administrative and other expenses | C26: =C30-C94-C96-C97-C98-'3. Segment Build'!C95 -> -277.11276 | D26: =D30-D94-D96-D97-D98-'3. Segment Build'!D95 -> -80.620206 | E26: =E30-E94-E96-E97-E98-'3. Segment Build'!E95 -> -96.846539 | F26: =F30-F94-F96-F97-F98-'3. Segment Build'!F95 -> -73.023541 | G26: =G30-G94-G96-G97-G98-'3. Segment Build'!G95 -> -113.7455 | H26: =D26+E26+F26+G26 -> -364.23579 | I26: =I30-I94-I96-I97-I98-'3. Segment Build'!I95+I16 -> -99.660163 | J26: =J30-J94-J96-J97-J98-'3. Segment Build'!J95+J16 -> -99.04881 | K26: =K30-K94-K96-K97-K98-'3. Segment Build'!K95+K16 -> -100.09062 | L26: =L30-L94-L96-L97-L98-'3. Segment Build'!L95+L16 -> -115.12819 | M26: =I26+J26+K26+L26 -> -413.92779 | N26: =N30-N94-N96-N97-N98-'3. Segment Build'!N95+N16 -> -118.6 | O26: =O30-O94-O96-O97-O98-'3. Segment Build'!O95+O16 -> -126.54467 | P26: =P30-P94-P96-P97-P98-'3. Segment Build'!P95+P16 -> -147.14467 | Q26: =Q30-Q94-Q96-Q97-Q98-'3. Segment Build'!Q95+Q16 -> -208.31067 | R26: =N26+O26+P26+Q26 -> -600.6
B27: % chg. y/y | C27: -- | D27: -- | E27: -- | F27: -- | G27: -- | H27: =H26/C26-1 -> 0.31439558 | I27: =I26/D26-1 -> 0.23616855 | J27: =J26/E26-1 -> 0.022739804 | L27: =L26/G26-1 -> 0.012156018 | M27: =M26/H26-1 -> 0.13642812 | N27: =N26/I26-1 -> 0.19004421 | O27: =O26/J26-1 -> 0.27759906 | P27: =P26/K26-1 -> 0.4701144 | Q27: =Q26/L26-1 -> 0.80938014 | R27: =R26/M26-1 -> 0.45097772
B28: % of sales | C28: =-C26/C8 -> 0.11328295 | D28: =-D26/D8 -> 0.1215093 | E28: =-E26/E8 -> 0.16200221 | F28: =-F26/F8 -> 0.090585316 | G28: =-G26/G8 -> 0.11385936 | H28: =-H26/H8 -> 0.11878171 | I28: =-I26/I8 -> 0.12316533 | J28: =-J26/J8 -> 0.14284068 | ... R28: =-R26/R8 -> 0.13748741
B29: bps chg. y/y | C29: -- | D29: -- | E29: -- | F29: -- | G29: -- | H29: =(H28-C28)*100*100 -> 54.987532 | I29: =(I28-D28)*100*100 -> 16.560279 | J29: =(J28-E28)*100*100 -> -191.61527 | K29: =(K28-F28)*100*100 -> 275.59902 | L29: =(L28-G28)*100*100 -> -178.16061 | M29: =(M28-H28)*100*100 -> -21.321718 | N29: =(N28-I28)*100*100 -> -102.45211 | O29: =(O28-J28)*100*100 -> 48.538432 | ... R29: =(R28-M28)*100*100 -> 208.37875
B30: Adjusted administrative and other expenses | C30: =C55-C12-C21-C46-C48 -> -222.7 | D30: =D55-D12-D21-D46-D48 -> -66.670405 | E30: =E55-E12-E21-E46-E48 -> -51.596871 | F30: =F55-F12-F21-F46-F48 -> -59.078287 | G30: =G55-G12-G21-G46-G48 -> -103.27301 | H30: =D30+E30+F30+G30 -> -280.61857 | I30: =I55-I17-I21-I46-I48 -> -85.519038 | J30: =J55-J17-J21-J46-J48 -> -88.823434 | K30: =K55-K17-K21-K46-K48 -> -93.840442 | L30: =L55-L17-L21-L46-L48 -> -107.49647 | M30: =I30+J30+K30+L30 -> -375.67938 | N30: =N55-N17-N21-N46-N48 -> -111.6 | O30: =O55-O17-O21-O46-O48 -> -117.5 | P30: =P55-P17-P21-P46-P48 -> -123 | Q30: =Q55-Q17-Q21-Q46-Q48 -> -135.1 | R30: =N30+O30+P30+Q30 -> -487.2
B31: % chg. y/y | C31: -- | D31: -- | E31: -- | F31: -- | G31: -- | H31: =H30/C30-1 -> 0.26007442 | I31: =I30/D30-1 -> 0.28271363 | J31: =J30/E30-1 -> 0.72148878 | K31: =K30/F30-1 -> 0.58840831 | L31: =L30/G30-1 -> 0.040896069 | M31: =M30/H30-1 -> 0.33875452 | N31: =N30/I30-1 -> 0.30497259 | O31: =O30/J30-1 -> 0.32284911 | ... R31: =R30/M30-1 -> 0.29685051
B32: % of sales | C32: =-C30/C8 -> 0.091039163 | D32: =-D30/D8 -> 0.10048442 | E32: =-E30/E8 -> 0.086309815 | F32: =-F30/F8 -> 0.073286302 | G32: =-G30/G8 -> 0.10337639 | H32: =-H30/H8 -> 0.091513119 | I32: =-I30/I8 -> 0.10568897 | J32: =-J30/J8 -> 0.12809442 | ... R32: =-R30/R8 -> 0.11152825
B33: bps chg. y/y | C33: -- | D33: -- | E33: -- | F33: -- | G33: -- | H33: =(H32-C32)*100*100 -> 4.7395632 | I33: =(I32-D32)*100*100 -> 52.045579 | J33: =(J32-E32)*100*100 -> 417.84602 | K33: =(K32-F32)*100*100 -> 374.81311 | L33: =(L32-G32)*100*100 -> -136.99694 | M33: =(M32-H32)*100*100 -> 143.57582 | N33: =(N32-I32)*100*100 -> 5.663818 | O33: =(O32-J32)*100*100 -> 90.437714 | ... R33: =(R32-M32)*100*100 -> 56.575475
B35: Total SG&A (IFRS) | C35: =C21+C26 -> -1010.3128 | D35: =D21+D26 -> -291.31916 | E35: =E21+E26 -> -318.96465 | F35: =F21+F26 -> -304.99445 | G35: =G21+G26 -> -411.50449 | H35: =D35+E35+F35+G35 -> -1326.7827 | I35: =I21+I26 -> -348.76016 | J35: =J21+J26 -> -340.64881 | K35: =K21+K26 -> -363.74873 | L35: =L21+L26 -> -468.59661 | M35: =I35+J35+K35+L35 -> -1521.7543 | N35: =N21+N26 -> -422.4 | O35: =O21+O26 -> -445.34467 | P35: =P21+P26 -> -481.34467 | Q35: =Q21+Q26 -> -633.21067 | R35: =N35+O35+P35+Q35 -> -1982.3 | S35: =H35-19.3 -> -1346.0827 | T35: =M35-22.4 -> -1544.1543 | U35: =N35-6.7 -> -429.1 | V35: =O35-6 -> -451.34467 | W35: =P35-6.8 -> -488.14467 | X35: =Q35-12.5 -> -645.71067 | Y35: =U35+V35+W35+X35 -> -2014.3 | Z35: =-534.2-9.5 -> -543.7 | AA35: =-560.2-7.6 -> -567.8 | AB35: -586.5 | AC35: -732.3 | AD35: =Z35+AA35+AB35+AC35 -> -2430.3 | AE35: -641.9 | AF35: -697.8 | AG35: -776.6 | AH35: =-988.3 -> -988.3 | AI35: =AE35+AF35+AG35+AH35 -> -3104.6 | AJ35: -856.2 | AK35: =-909.2 -> -909.2 | AL35: =AL40-AL96-AL97-AL98-AL94-'3. Segment Build'!AL95+AL16 -> -971.63478 | AM35: =AM40-AM96-AM97-AM98-AM94-'3. Segment Build'!AM95+AM16 -> -1158.5977 | AN35: =AJ35+AK35+AL35+AM35 -> -3895.6324 | AO35: =AO40-AO96-AO97-AO98-AO94-'3. Segment Build'!AO95+AO16 -> -982.64528 | AP35: =AP40-AP96-AP97-AP98-AP94-'3. Segment Build'!AP95+AP16 -> -1030.8629 | AQ35: =AQ40-AQ96-AQ97-AQ98-AQ94-'3. Segment Build'!AQ95+AQ16 -> -1106.7345 | AR35: =AR40-AR96-AR97-AR98-AR94-'3. Segment Build'!AR95+AR16 -> -1330.0011 | AS35: =AO35+AP35+AQ35+AR35 -> -4450.2437 | AT35: =AT40-AT96-AT97-AT98-AT94-'3. Segment Build'!AT95+AT16 -> -1116.8501 | AU35: =AU40-AU96-AU97-AU98-AU94-'3. Segment Build'!AU95+AU16 -> -1171.9096 | AV35: =AV40-AV96-AV97-AV98-AV94-'3. Segment Build'!AV95+AV16 -> -1255.946 | AW35: =AW40-AW96-AW97-AW98-AW94-'3. Segment Build'!AW95+AW16 -> -1516.7376 | AX35: =AT35+AU35+AV35+AW35 -> -5061.4433
B36: % chg. y/y | C36: -- | D36: -- | E36: -- | F36: -- | G36: -- | H36: =H35/C35-1 -> 0.31323962 | I36: =I35/D35-1 -> 0.19717551 | J36: =J35/E35-1 -> 0.06798297 | K36: =K35/F35-1 -> 0.19264046 | L36: =L35/G35-1 -> 0.13873997 | M36: =M35/H35-1 -> 0.14695063 | N36: =N35/I35-1 -> 0.2111475 | O36: =O35/J35-1 -> 0.3073425 | ... R36: =R35/M35-1 -> 0.30264129 | S36: -- | T36: =T35/S35-1 -> 0.14714665 | U36: -- | V36: -- | W36: -- | X36: -- | Y36: =Y35/T35-1 -> 0.30446808 | Z36: =Z35/U35-1 -> 0.26707061 | AA36: =AA35/V35-1 -> 0.25801863 | AB36: =AB35/W35-1 -> 0.20148808 | AC36: =AC35/X35-1 -> 0.13409928 | AD36: =AD35/Y35-1 -> 0.20652336 | AE36: =AE35/Z35-1 -> 0.18061431 | AF36: =AF35/AA35-1 -> 0.22895386 | ... AX36: =AX35/AS35-1 -> 0.1373407
B37: % of sales | C37: =-C35/C8 -> 0.41301315 | D37: =-D35/D8 -> 0.43907091 | E37: =-E35/E8 -> 0.53355522 | F37: =-F35/F8 -> 0.37834401 | G37: =-G35/G8 -> 0.4119164 | H37: =-H35/H8 -> 0.43267994 | I37: =-I35/I8 -> 0.43101635 | J37: =-J35/J8 -> 0.49125787 | ... AX37: =-AX35/AX8 -> 0.47093123
B38: bps chg. y/y | C38: -- | D38: -- | E38: -- | F38: -- | G38: -- | H38: =(H37-C37)*100*100 -> 196.66793 | I38: =(I37-D37)*100*100 -> -80.545578 | J38: =(J37-E37)*100*100 -> -422.97352 | K38: =(K37-F37)*100*100 -> 510.18617 | L38: =(L37-G37)*100*100 -> -209.99436 | M38: =(M37-H37)*100*100 -> -38.323591 | N38: =(N37-I37)*100*100 -> -288.45545 | O38: =(O37-J37)*100*100 -> 285.1882 | ... R38: =(R37-M37)*100*100 -> 249.34124 | S38: -- | T38: =(T37-S37)*100*100 -> -37.978932 | U38: -- | V38: -- | W38: -- | X38: -- | Y38: =(Y37-T37)*100*100 -> 253.23435 | Z38: =(Z37-U37)*100*100 -> 500.10886 | AA38: =(AA37-V37)*100*100 -> 438.89981 | AB38: =(AB37-W37)*100*100 -> 98.925302 | AC38: =(AC37-X37)*100*100 -> -386.58068 | AD38: =(AD37-Y37)*100*100 -> 111.35434 | AE38: =(AE37-Z37)*100*100 -> -200.45854 | AF38: =(AF37-AA37)*100*100 -> -25.800812 | ... AX38: =(AX37-AS37)*100*100 -> 2.7881241
B40: Total Adj. SG&A | C40: =C21+C30 -> -955.9 | D40: =D21+D30 -> -277.36936 | E40: =E21+E30 -> -273.71498 | F40: =F21+F30 -> -291.0492 | G40: =G21+G30 -> -401.032 | H40: =D40+E40+F40+G40 -> -1243.1655 | I40: =I21+I30 -> -334.61904 | J40: =J21+J30 -> -330.42343 | K40: =K21+K30 -> -357.49855 | L40: =L21+L30 -> -460.96489 | M40: =I40+J40+K40+L40 -> -1483.5059 | N40: =N21+N30 -> -415.4 | O40: =O21+O30 -> -436.3 | P40: =P21+P30 -> -457.2 | Q40: =Q21+Q30 -> -560 | R40: =N40+O40+P40+Q40 -> -1868.9 | S40: =H40-19.3 -> -1262.4655 | T40: =M40-22.4 -> -1505.9059 | U40: =N40-6.7 -> -422.1 | V40: =O40-6 -> -442.3 | W40: =P40-6.8 -> -464 | X40: =Q40-12.5 -> -572.5 | Y40: =U40+V40+W40+X40 -> -1900.9 | Z40: =-534.2+0.9+5.8+3.4+7-9.5 -> -526.6 | AA40: =-560.2+8.8+7+12.2+6.1-7.6 -> -533.7 | AB40: =-586.5+6.5+2.5+2.3+1.4+1.3 -> -572.5 | AC40: =-732.3+6.9+10.2+1.8+0.4+4.5 -> -708.5 | AD40: =Z40+AA40+AB40+AC40 -> -2341.3 | AE40: =-641.9+6.9+2.9+0.3+5 -> -626.8 | AF40: =-697.8+7.2+6+2+0.1+5.9 -> -676.6 | AG40: =-776.6+23+5.4+3.9+0.1+1.7 -> -742.5 | AH40: =-988.3+6.3+9.3+9.7+4.6+2.4 -> -956 | AI40: =AE40+AF40+AG40+AH40 -> -3001.9 | AJ40: =-856.2+6.4+4.2-0.1+4.6 -> -841.1 | AK40: =-909.2+6.3+6.8+0.6+0.2-1.7 -> -897 | AL40: =AL55-AL17-AL48-AL46 -> -962.33478 | AM40: =AM55-AM17-AM48-AM46 -> -1149.2977 | AN40: =AJ40+AK40+AL40+AM40 -> -3849.7324 | AO40: =AO55-AO17-AO48-AO46 -> -973.34528 | AP40: =AP55-AP17-AP48-AP46 -> -1021.5629 | AQ40: =AQ55-AQ17-AQ48-AQ46 -> -1097.4345 | AR40: =AR55-AR17-AR48-AR46 -> -1320.7011 | AS40: =AO40+AP40+AQ40+AR40 -> -4413.0437 | AT40: =AT55-AT17-AT48-AT46 -> -1107.5501 | AU40: =AU55-AU17-AU48-AU46 -> -1162.6096 | AV40: =AV55-AV17-AV48-AV46 -> -1246.646 | AW40: =AW55-AW17-AW48-AW46 -> -1507.4376 | AX40: =AT40+AU40+AV40+AW40 -> -5024.2433
B41: % chg. y/y | C41: -- | D41: -- | E41: -- | F41: -- | G41: -- | H41: =H40/C40-1 -> 0.3005184 | I41: =I40/D40-1 -> 0.20640232 | J41: =J40/E40-1 -> 0.20718068 | K41: =K40/F40-1 -> 0.22830966 | L41: =L40/G40-1 -> 0.14944665 | M41: =M40/H40-1 -> 0.19332934 | N41: =N40/I40-1 -> 0.24141173 | O41: =O40/J40-1 -> 0.32042693 | ... R41: =R40/M40-1 -> 0.25978602 | S41: -- | T41: =T40/S40-1 -> 0.19282932 | U41: -- | V41: -- | W41: -- | X41: -- | Y41: =Y40/T40-1 -> 0.26229666 | Z41: =Z40/U40-1 -> 0.24757167 | AA41: =AA40/V40-1 -> 0.20664707 | AB41: =AB40/W40-1 -> 0.23383621 | AC41: =AC40/X40-1 -> 0.23755459 | AD41: =AD40/Y40-1 -> 0.23167973 | AE41: =AE40/Z40-1 -> 0.19027725 | AF41: =AF40/AA40-1 -> 0.26775342 | ... AX41: =AX40/AS40-1 -> 0.13849842
B42: % of sales | C42: =-C40/C8 -> 0.39076936 | D42: =-D40/D8 -> 0.41804603 | E42: =-E40/E8 -> 0.45786283 | F42: =-F40/F8 -> 0.36104499 | G42: =-G40/G8 -> 0.40143343 | H42: =-H40/H8 -> 0.40541135 | I42: =-I40/I8 -> 0.41354 | J42: =-J40/J8 -> 0.47651161 | ... AX42: =-AX40/AX8 -> 0.46747003
B43: bps chg. y/y | C43: -- | D43: -- | E43: -- | F43: -- | G43: -- | H43: =(H42-C42)*100*100 -> 146.41997 | I43: =(I42-D42)*100*100 -> -45.060278 | J43: =(J42-E42)*100*100 -> 186.48777 | K43: =(K42-F42)*100*100 -> 609.40026 | L43: =(L42-G42)*100*100 -> -168.83069 | M43: =(M42-H42)*100*100 -> 126.57394 | N43: =(N42-I42)*100*100 -> -180.33953 | O43: =(O42-J42)*100*100 -> 327.08748 | ... R43: =(R42-M42)*100*100 -> 97.537962 | S43: -- | T43: =(T42-S42)*100*100 -> 125.88922 | U43: -- | V43: -- | W43: -- | X43: -- | Y43: =(Y42-T42)*100*100 -> 102.64268 | Z43: =(Z42-U42)*100*100 -> 422.92577 | AA43: =(AA42-V42)*100*100 -> 203.20578 | AB43: =(AB42-W42)*100*100 -> 204.90187 | AC43: =(AC42-X42)*100*100 -> 19.390858 | AD43: =(AD42-Y42)*100*100 -> 197.34628 | AE43: =(AE42-Z42)*100*100 -> -159.59697 | AF43: =(AF42-AA42)*100*100 -> 143.24304 | ... AX43: =(AX42-AS42)*100*100 -> 7.518447
B45: Impairment losses | C45: -20.5 | D45: 7.2024204 | E45: -6.7777385 | F45: 5.0349079 | G45: -6.2019981 | H45: =D45+E45+F45+G45 -> -0.74240835 | I45: -2.8 | J45: -1.2 | K45: 2.641505 | L45: -200.78907 | M45: =I45+J45+K45+L45 -> -202.14757 | N45: -2.8 | O45: -4.7 | P45: 2.9 | Q45: 2.2 | R45: =N45+O45+P45+Q45 -> -2.4 | S45: =H45 -> -0.74240835 | T45: =M45 -> -202.14757 | U45: =N45 -> -2.8 | V45: =O45 -> -4.7 | W45: =P45 -> 2.9 | X45: =Q45 -> 2.2 | Y45: =U45+V45+W45+X45 -> -2.4 | Z45: -1.3 | AA45: -1.2 | AB45: 0 | AC45: 0.6 | AD45: =Z45+AA45+AB45+AC45 -> -1.9 | AE45: -0.3 | AF45: -2.6 | AG45: -10.2 | AH45: -0.9 | AI45: =AE45+AF45+AG45+AH45 -> -14 | AJ45: -0.7 | AK45: -2.3 | AL45: 0 | AM45: 0 | AN45: =AJ45+AK45+AL45+AM45 -> -3 | AO45: 0 | AP45: 0 | AQ45: 0 | AR45: 0 | AS45: =AO45+AP45+AQ45+AR45 -> 0 | AT45: 0 | AU45: 0 | AV45: 0 | AW45: 0 | AX45: =AT45+AU45+AV45+AW45 -> 0
B46: Adjusted impairment losses | C46: =C45+C95 -> -20.5 | D46: =D45+D95 -> 7.2024204 | E46: =E45+E95 -> -6.7777385 | F46: =F45+F95 -> 5.0349079 | G46: =G45+G95 -> -6.2019981 | H46: =D46+E46+F46+G46 -> -0.74240835 | I46: =I45+I95 -> -2.8 | J46: =J45+J95 -> -1.2 | K46: =K45+K95 -> 2.641505 | L46: =L45+L95 -> -2.689075 | M46: =I46+J46+K46+L46 -> -4.04757 | N46: =N45+N95 -> -2.8 | O46: =O45+O95 -> -4.7 | P46: =P45+P95 -> 2.9 | Q46: =Q45+Q95 -> 2.2 | R46: =N46+O46+P46+Q46 -> -2.4 | S46: =H46 -> -0.74240835 | T46: =M46 -> -4.04757 | U46: =N46 -> -2.8 | V46: =O46 -> -4.7 | W46: =P46 -> 2.9 | X46: =Q46 -> 2.2 | Y46: =U46+V46+W46+X46 -> -2.4 | Z46: =Z45+Z95 -> -1.3 | AA46: =AA45+AA95 -> -1.2 | AB46: =AB45+AB95 -> 0 | AC46: =AC45+AC95 -> 0.6 | AD46: =Z46+AA46+AB46+AC46 -> -1.9 | AE46: =AE45+AE95 -> -0.3 | AF46: =AF45+AF95 -> -2.6 | AG46: =AG45+AG95 -> -3.5 | AH46: =AH45+AH95 -> -0.9 | AI46: =AE46+AF46+AG46+AH46 -> -7.3 | AJ46: =AJ45+AJ95 -> -0.7 | AK46: =AK45+AK95 -> -0.5 | AL46: =AL45+AL95 -> 0 | AM46: =AM45+AM95 -> 0 | AN46: =AJ46+AK46+AL46+AM46 -> -1.2 | AO46: =AO45+AO95 -> 0 | AP46: =AP45+AP95 -> 0 | AQ46: =AQ45+AQ95 -> 0 | AR46: =AR45+AR95 -> 0 | AS46: =AO46+AP46+AQ46+AR46 -> 0 | AT46: =AT45+AT95 -> 0 | AU46: =AU45+AU95 -> 0 | AV46: =AV45+AV95 -> 0 | AW46: =AW45+AW95 -> 0 | AX46: =AT46+AU46+AV46+AW46 -> 0
B48: Other operating income | C48: 7.2 | D48: 0.81671535 | E48: 0.8258933 | F48: 0.44675039 | G48: 6.8978288 | H48: =D48+E48+F48+G48 -> 8.9871878 | I48: 0.5 | J48: 2.2 | K48: -0.621854 | L48: 9.224496 | M48: =I48+J48+K48+L48 -> 11.302642 | N48: 0.7 | O48: 0.9 | P48: 1.7 | Q48: 7.9 | R48: =N48+O48+P48+Q48 -> 11.2 | S48: =H48 -> 8.9871878 | T48: =M48 -> 11.302642 | U48: =N48 -> 0.7 | V48: =O48 -> 0.9 | W48: =P48 -> 1.7 | X48: =Q48 -> 7.9 | Y48: =U48+V48+W48+X48 -> 11.2 | Z48: 6 | AA48: 1.6 | AB48: 15.9 | AC48: 7.8 | AD48: =Z48+AA48+AB48+AC48 -> 31.3 | AE48: 5.3 | AF48: 21.2 | AG48: 4.5 | AH48: 5.1 | AI48: =AE48+AF48+AG48+AH48 -> 36.1 | AJ48: 12.6 | AK48: 31.6 | AL48: 0 | AM48: 0 | AN48: =AJ48+AK48+AL48+AM48 -> 44.2 | AO48: =AJ48 -> 12.6 | AP48: =AK48 -> 31.6 | AQ48: =AL48 -> 0 | AR48: =AM48 -> 0 | AS48: =AO48+AP48+AQ48+AR48 -> 44.2 | AT48: =AO48 -> 12.6 | AU48: =AP48 -> 31.6 | AV48: =AQ48 -> 0 | AW48: =AR48 -> 0 | AX48: =AT48+AU48+AV48+AW48 -> 44.2
B50: Operating profit (IFRS) | C50: =C12+C21+C26+C45+C48 -> 125.18724 | D50: =D12+D21+D26+D45+D48 -> 43.841199 | E50: =E12+E21+E26+E45+E48 -> -50.671668 | F50: =F12+F21+F26+F45+F48 -> 102.56775 | G50: =G12+G21+G26+G45+G48 -> 91.25351 | H50: =H12+H21+H26+H45+H48 -> 186.99079 | I50: =I12+I21+I26+I45+I48 -> 49.497449 | J50: =J12+J21+J26+J45+J48 -> -10.927225 | ... R50: =R12+R21+R26+R45+R48 -> 302.6 | S50: =S12+S35+S45+S48 -> 186.99079 | T50: =T12+T35+T45+T48 -> 50.638321 | U50: =U12+U35+U45+U48 -> 130.4 | V50: =V12+V35+V45+V48 -> 7.4553333 | W50: =W12+W35+W45+W48 -> 104.65533 | X50: =X12+X35+X45+X48 -> 60.089333 | Y50: =Y12+Y35+Y45+Y48 -> 302.6 | Z50: =Z12+Z35+Z45+Z48 -> 109 | ... AX50: =AX12+AX35+AX45+AX48 -> 1596.9658
B51: % chg. y/y | C51: -- | D51: -- | E51: -- | F51: -- | G51: -- | H51: =H50/C50-1 -> 0.49368886 | I51: =I50/D50-1 -> 0.12901677 | J51: =J50/E50-1 -> -0.78435238 | K51: =K50/F50-1 -> -0.31557608 | L51: =L50/G50-1 -> -1.6370355 | M51: =M50/H50-1 -> -0.7291935 | N51: =N50/I50-1 -> 1.6344792 | O51: =O50/J50-1 -> -1.6822714 | ... R51: =R50/M50-1 -> 4.9757116 | S51: -- | T51: =T50/S50-1 -> -0.7291935 | U51: -- | V51: -- | W51: -- | X51: -- | Y51: =Y50/T50-1 -> 4.9757116 | Z51: =Z50/U50-1 -> -0.16411043 | AA51: =AA50/V50-1 -> -2.1401234 | AB51: =AB50/W50-1 -> 0.68839938 | AC51: =AC50/X50-1 -> 2.2218697 | AD51: =AD50/Y50-1 -> 0.55584931 | AE51: =AE50/Z50-1 -> 0.96513761 | AF51: =AF50/AA50-1 -> -6.1411765 | ... AX51: =AX50/AS50-1 -> 0.1891492
B52: % margin | C52: =C50/C8 -> 0.051176208 | D52: =D50/D8 -> 0.066076654 | E52: =E50/E8 -> -0.084762162 | F52: =F50/F8 -> 0.12723475 | G52: =G50/G8 -> 0.091344855 | H52: =H50/H8 -> 0.060979963 | I52: =I50/I8 -> 0.061171579 | J52: =J50/J8 -> -0.015758415 | ... AX52: =AX50/AX8 -> 0.14858628
B53: bps chg. y/y | C53: -- | D53: -- | E53: -- | F53: -- | G53: -- | H53: =(H52-C52)*100*100 -> 98.037543 | I53: =(I52-D52)*100*100 -> -49.050749 | J53: =(J52-E52)*100*100 -> 690.03747 | K53: =(K52-F52)*100*100 -> -443.7211 | L53: =(L52-G52)*100*100 -> -1398.4003 | M53: =(M52-H52)*100*100 -> -467.09511 | N53: =(N52-I52)*100*100 -> 629.83424 | O53: =(O52-J52)*100*100 -> 244.59784 | ... R53: =(R52-M52)*100*100 -> 549.99762 | S53: -- | T53: =(T52-S52)*100*100 -> -464.17624 | U53: -- | V53: -- | W53: -- | X53: -- | Y53: =(Y52-T52)*100*100 -> 545.85542 | Z53: =(Z52-U52)*100*100 -> -319.55745 | AA53: =(AA52-V52)*100*100 -> -171.28976 | AB53: =(AB52-W52)*100*100 -> 397.61515 | AC53: =(AC52-X52)*100*100 -> 731.08551 | AD53: =(AD52-Y52)*100*100 -> 220.67195 | AE53: =(AE52-Z52)*100*100 -> 540.54615 | AF53: =(AF52-AA52)*100*100 -> 438.35524 | ... AX53: =(AX52-AS52)*100*100 -> 65.577011
B55: Adjusted Operating Profit | C55: ='3. Segment Build'!C65 -> 179.6 | D55: ='3. Segment Build'!D65 -> 57.791 | E55: ='3. Segment Build'!E65 -> -5.422 | F55: ='3. Segment Build'!F65 -> 116.513 | G55: ='3. Segment Build'!G65 -> 101.726 | H55: ='3. Segment Build'!H65 -> 270.608 | I55: ='3. Segment Build'!I65 -> 67.138574 | J55: ='3. Segment Build'!J65 -> 3.0481514 | ... R55: ='3. Segment Build'!R65 -> 432.6 | T55: =T17+T40+T46+T48 -> 300.98673 | U55: =U17+U40+U46+U48 -> 141.2 | V55: =V17+V40+V46+V48 -> 20.9 | W55: =W17+W40+W46+W48 -> 133.5 | X55: =X17+X40+X46+X48 -> 137 | Y55: =Y17+Y40+Y46+Y48 -> 432.6 | Z55: ='3. Segment Build'!Z65 -> 129.8 | AA55: ='3. Segment Build'!AA65 -> 29.3 | AB55: ='3. Segment Build'!AB65 -> 195 | AC55: ='3. Segment Build'!AC65 -> 222.9 | AD55: ='3. Segment Build'!AD65 -> 577 | AE55: ='3. Segment Build'!AE65 -> 232.2 | AF55: ='3. Segment Build'!AF65 -> 67.4 | AG55: ='3. Segment Build'!AG65 -> 274.9 | ... AX55: ='3. Segment Build'!AX65 -> 1648.9658
B56: % chg. y/y | C56: -- | D56: -- | E56: -- | F56: -- | G56: -- | H56: =H55/C55-1 -> 0.50672606 | I56: =I55/D55-1 -> 0.16174793 | J56: =J55/E55-1 -> -1.5621821 | K56: =K55/F55-1 -> -0.31166479 | L56: =L55/G55-1 -> 0.48044748 | M56: =M55/H55-1 -> 0.112261 | N56: =N55/I55-1 -> 1.1031129 | O56: =O55/J55-1 -> 5.8566148 | ... R56: =R55/M55-1 -> 0.43727269 | T56: -- | U56: -- | V56: -- | W56: -- | X56: -- | Y56: =Y55/T55-1 -> 0.43727269 | Z56: =Z55/U55-1 -> -0.080736544 | AA56: =AA55/V55-1 -> 0.40191388 | AB56: =AB55/W55-1 -> 0.46067416 | AC56: =AC55/X55-1 -> 0.6270073 | AD56: =AD55/Y55-1 -> 0.33379565 | AE56: =AE55/Z55-1 -> 0.78890601 | AF56: =AF55/AA55-1 -> 1.3003413 | ... AX56: =AX55/AS55-1 -> 0.18209822
B57: % margin | C57: =C55/C8 -> 0.073419998 | D57: =D55/D8 -> 0.087101539 | E57: =E55/E8 -> -0.0090697713 | F57: =F55/F8 -> 0.14453376 | G57: =G55/G8 -> 0.10182783 | H57: =H55/H8 -> 0.08824855 | I57: =I55/I8 -> 0.08297342 | J57: =J55/J8 -> 0.0043958127 | ... R57: =R55/R8 -> 0.099029393 | T57: =T55/T8 -> 0.084289382 | U57: =U55/U8 -> 0.13358562 | V57: =V55/V8 -> 0.024223459 | W57: =W55/W8 -> 0.11577487 | X57: =X55/X8 -> 0.10320151 | Y57: =Y55/Y8 -> 0.098309245 | Z57: =Z55/Z8 -> 0.10885609 | AA57: =AA55/AA8 -> 0.029259037 | ... AX57: =AX55/AX8 -> 0.15342451
B58: bps chg. y/y | C58: -- | D58: -- | E58: -- | F58: -- | G58: -- | H58: =(H57-C57)*100*100 -> 148.28551 | I58: =(I57-D57)*100*100 -> -41.281188 | J58: =(J57-E57)*100*100 -> 134.65584 | K58: =(K57-F57)*100*100 -> -498.67085 | L58: =(L57-G57)*100*100 -> 238.07088 | M58: =(M57-H57)*100*100 -> -34.270851 | N58: =(N57-I57)*100*100 -> 514.6436 | O58: =(O57-J57)*100*100 -> 199.97278 | ... R58: =(R57-M57)*100*100 -> 142.07928 | T58: -- | U58: -- | V58: -- | W58: -- | X58: -- | Y58: =(Y57-T57)*100*100 -> 140.19863 | Z58: =(Z57-U57)*100*100 -> -247.29531 | AA58: =(AA57-V57)*100*100 -> 50.355788 | AB58: =(AB57-W57)*100*100 -> 282.64134 | AC58: =(AC57-X57)*100*100 -> 330.8709 | AD58: =(AD57-Y57)*100*100 -> 130.14095 | AE58: =(AE57-Z57)*100*100 -> 488.34913 | AF58: =(AF57-AA57)*100*100 -> 252.58475 | ... AX58: =(AX57-AS57)*100*100 -> 58.964731
B60: Finance income | C60: 1.6 | D60: 0.74292038 | E60: 0.5140625 | F60: 0.42702973 | G60: 0.61808322 | H60: =D60+E60+F60+G60 -> 2.3020958 | I60: 0.6 | J60: 0.9 | K60: 0.545469 | L60: 1.255912 | M60: =I60+J60+K60+L60 -> 3.301381 | N60: 1.3 | O60: 1.8 | P60: 1.4 | Q60: 1.9 | R60: =N60+O60+P60+Q60 -> 6.4 | S60: =H60 -> 2.3020958 | T60: =M60 -> 3.301381 | U60: =N60 -> 1.3 | V60: =O60 -> 1.8 | W60: =P60 -> 1.4 | X60: =Q60 -> 1.9 | Y60: =U60+V60+W60+X60 -> 6.4 | Z60: 2.7 | AA60: 2.5 | AB60: 1.1 | AC60: 2.5 | AD60: =Z60+AA60+AB60+AC60 -> 8.8 | AE60: =1.5+3.9 -> 5.4 | AF60: =6.7+1.4 -> 8.1 | AG60: =5.9+1.5 -> 7.4 | AH60: 2 | AI60: =AE60+AF60+AG60+AH60 -> 22.9 | AJ60: 2.7 | AK60: =5.4 -> 5.4 | AL60: =AL339 -> 4.4380057 | AM60: =AM339 -> 5.5641574 | AN60: =AJ60+AK60+AL60+AM60 -> 18.102163 | AO60: =AO339 -> 6.7598608 | AP60: =AP339 -> 8.0090615 | AQ60: =AQ339 -> 6.6554671 | AR60: =AR339 -> 7.8876501 | AS60: =AO60+AP60+AQ60+AR60 -> 29.312039 | AT60: =AT339 -> 11.989115 | AU60: =AU339 -> 13.761625 | AV60: =AV339 -> 12.559193 | AW60: =AW339 -> 14.21666 | AX60: =AT60+AU60+AV60+AW60 -> 52.526593
B61: Finance cost | C61: -274.1 | D61: -75.465903 | E61: -78.675649 | F61: -67.632504 | G61: -57.24426 | H61: =D61+E61+F61+G61 -> -279.01832 | I61: -57.6 | J61: -55.3 | K61: -55.515802 | L61: -68.022794 | M61: =I61+J61+K61+L61 -> -236.4386 | N61: -86.1 | O61: -101.1 | P61: -109.4 | Q61: -116.8 | R61: =N61+O61+P61+Q61 -> -413.4 | S61: =H61 -> -279.01832 | T61: =M61 -> -236.4386 | U61: =N61 -> -86.1 | V61: =O61 -> -101.1 | W61: =P61 -> -109.4 | X61: =Q61 -> -116.8 | Y61: =U61+V61+W61+X61 -> -413.4 | Z61: =-82.3-14.3 -> -96.6 | AA61: -47.7 | AB61: -48.9 | AC61: =-64.1-43.6-17.5 -> -125.2 | AD61: =Z61+AA61+AB61+AC61 -> -318.4 | AE61: -22 | AF61: -30 | AG61: -25.6 | AH61: =-20.1-2.5 -> -22.6 | AI61: =AE61+AF61+AG61+AH61 -> -100.2 | AJ61: =-24.9-7.8-50.5 -> -83.2 | AK61: =-20-16.3 -> -36.3 | AL61: =AL335 -> -22.11 | AM61: =AM335 -> -22.11 | AN61: =AJ61+AK61+AL61+AM61 -> -163.72 | AO61: =AO335 -> -14.74 | AP61: =AP335 -> -14.74 | AQ61: =AQ335 -> -14.74 | AR61: =AR335 -> -14.74 | AS61: =AO61+AP61+AQ61+AR61 -> -58.96 | AT61: =AT335 -> -14.74 | AU61: =AU335 -> -14.74 | AV61: =AV335 -> -14.74 | AW61: =AW335 -> -14.74 | AX61: =AT61+AU61+AV61+AW61 -> -58.96
B62: Net finance cost | C62: =C60+C61 -> -272.5 | D62: =D60+D61 -> -74.722983 | E62: =E60+E61 -> -78.161587 | F62: =F60+F61 -> -67.205474 | G62: =G60+G61 -> -56.626177 | H62: =H60+H61 -> -276.71622 | I62: =I60+I61 -> -57 | J62: =J60+J61 -> -54.4 | ... AK62: =AK60+AK61 -> -30.9 | AL62: =AL343 -> -17.671839 | AM62: =AM343 -> -16.545272 | AN62: =AN60+AN61 -> -145.61784 | AO62: =AO343 -> -7.979497 | AP62: =AP343 -> -6.7299097 | AQ62: =AQ343 -> -8.082723 | AR62: =AR343 -> -6.8493607 | AS62: =AS60+AS61 -> -29.647961 | AT62: =AT343 -> -2.7465891 | AU62: =AU343 -> -0.97272047 | AV62: =AV343 -> -2.1734128 | AW62: =AW343 -> -0.5137862 | AX62: =AX60+AX61 -> -6.4334069
B63: Adj. Net Finance Cost | Z63: =Z62+Z118+18.1 -> -61.5 | AA63: =AA62+AA118 -> -45.2 | AB63: =AB62+AB118 -> -45.6 | AC63: =AC62+AC118+11.4+29.6 -> -64.2 | AD63: =Z63+AA63+AB63+AC63 -> -216.5 | AE63: -16.6 | AF63: =-30+6.7+1.4 -> -21.9 | AG63: -18.2 | AH63: -20.6 | AI63: =AE63+AF63+AG63+AH63 -> -77.3 | AJ63: -30 | AK63: =-20-16.3+5.4+9.6 -> -21.3 | AL63: =AL62+AL118 -> -17.671839 | AM63: =AM62+AM118 -> -16.545272 | AN63: =AJ63+AK63+AL63+AM63 -> -85.517111 | AO63: =AO62+AO118 -> -7.979497 | AP63: =AP62+AP118 -> -6.7299097 | AQ63: =AQ62+AQ118 -> -8.082723 | AR63: =AR62+AR118 -> -6.8493607 | AS63: =AO63+AP63+AQ63+AR63 -> -29.64149 | AT63: =AT62+AT118 -> -2.7465891 | AU63: =AU62+AU118 -> -0.97272047 | AV63: =AV62+AV118 -> -2.1734128 | AW63: =AW62+AW118 -> -0.5137862 | AX63: =AT63+AU63+AV63+AW63 -> -6.4065086
B65: Income/Loss before tax - IFRS | C65: =C50+C62 -> -147.31276 | D65: =D50+D62 -> -30.881783 | E65: =E50+E62 -> -128.83326 | F65: =F50+F62 -> 35.362272 | G65: =G50+G62 -> 34.627333 | H65: =H50+H62 -> -89.725433 | I65: =I50+I62 -> -7.5025511 | J65: =J50+J62 -> -65.327225 | ... AX65: =AX50+AX62 -> 1590.5324
B66: Income tax expense - IFRS | C66: -26.2 | D66: 2.4504146 | E66: -3.0535727 | F66: -13.156717 | G66: -21.011529 | H66: =D66+E66+F66+G66 -> -34.771404 | I66: -11.7 | J66: 3.8 | K66: -17.011148 | L66: -23.527994 | M66: =I66+J66+K66+L66 -> -48.439142 | N66: -26.6 | O66: -5.2 | P66: -32.6 | Q66: =-39.8 -> -39.8 | R66: =N66+O66+P66+Q66 -> -104.2 | S66: =H66 -> -34.771404 | T66: =M66 -> -48.439142 | U66: =N66 -> -26.6 | V66: =O66 -> -5.2 | W66: =P66 -> -32.6 | X66: =Q66 -> -39.8 | Y66: =U66+V66+W66+X66 -> -104.2 | Z66: =-8.2 -> -8.2 | AA66: 51.9 | AB66: -72.7 | AC66: -53.8 | AD66: =Z66+AA66+AB66+AC66 -> -82.8 | AE66: -59.5 | AF66: 0.6 | AG66: -51.3 | AH66: =-73.9 -> -73.9 | AI66: =AE66+AF66+AG66+AH66 -> -184.1 | AJ66: =-70.5 -> -70.5 | AK66: =-43 -> -43 | AL66: =-AL67*AL65 -> -76.201958 | AM66: =-AM67*AM65 -> -86.336228 | AN66: =AJ66+AK66+AL66+AM66 -> -276.03819 | AO66: =-AO67*AO65 -> -107.42903 | AP66: =-AP67*AP65 -> -50.879637 | AQ66: =-AQ67*AQ65 -> -95.001364 | AR66: =-AR67*AR65 -> -107.84932 | AS66: =AO66+AP66+AQ66+AR66 -> -361.15935 | AT66: =-AT67*AT65 -> -126.33575 | AU66: =-AU67*AU65 -> -62.025967 | AV66: =-AV67*AV65 -> -112.2579 | AW66: =-AW67*AW65 -> -128.8314 | AX66: =AT66+AU66+AV66+AW66 -> -429.45101
B67: Tax rate | C67: =-C66/C65 -> -0.17785289 | D67: =-D66/D65 -> 0.079348221 | E67: =-E66/E65 -> -0.023701743 | F67: =-F66/F65 -> 0.3720552 | G67: =-G66/G65 -> 0.60679027 | H67: =-H66/H65 -> -0.38753119 | I67: =-I66/I65 -> -1.5594696 | J67: =-J66/J65 -> 0.058168704 | ... AK67: =-AK66/AK65 -> 0.26741294 | AL67: 0.28 | AM67: 0.2775 | AN67: =-AN66/AN65 -> 0.28033554 | AO67: 0.275 | AP67: 0.275 | AQ67: 0.275 | AR67: 0.275 | AS67: =-AS66/AS65 -> 0.27500135 | AT67: 0.27 | AU67: 0.27 | AV67: 0.27 | AW67: 0.27 | AX67: =-AX66/AX65 -> 0.27000457
B68: Income/Loss from continuing operations | C68: =C65+C66 -> -173.51276 | D68: =D65+D66 -> -28.431369 | E68: =E65+E66 -> -131.88683 | F68: =F65+F66 -> 22.205555 | G68: =G65+G66 -> 13.615805 | H68: =H65+H66 -> -124.49684 | I68: =I65+I66 -> -19.202551 | J68: =J65+J66 -> -61.527225 | ... AX68: =AX65+AX66 -> 1161.0814
B69: Loss from discontinued operations / NCI, net of tax | C69: -63.6 | D69: -27.9 | E69: 29.8 | F69: -1.2 | G69: -2.4673115 | H69: =D69+E69+F69+G69 -> -1.7673115 | I69: -9.8 | J69: -11.5 | K69: -0.519801 | L69: 0.01781 | M69: =I69+J69+K69+L69 -> -21.801991 | N69: 0 | O69: 0 | P69: 0 | Q69: 1.9 | R69: =N69+O69+P69+Q69 -> 1.9 | S69: =H69 -> -1.7673115 | T69: =M69 -> -21.801991 | U69: =N69 -> 0 | V69: =O69 -> 0 | W69: =P69 -> 0 | X69: =Q69 -> 1.9 | Y69: =U69+V69+W69+X69 -> 1.9 | Z69: -1.8 | AA69: -1.9 | AB69: -0.4 | AC69: -1.7 | AD69: =Z69+AA69+AB69+AC69 -> -5.8 | AE69: -3.5 | AF69: -4.2 | AG69: -3.3 | AH69: -2 | AI69: =AE69+AF69+AG69+AH69 -> -13 | AJ69: -5.5 | AK69: -10.6 | AL69: -6.75 | AM69: -6.75 | AN69: =AJ69+AK69+AL69+AM69 -> -29.6 | AO69: 0 | AP69: 0 | AQ69: 0 | AR69: 0 | AS69: =AO69+AP69+AQ69+AR69 -> 0 | AT69: 0 | AU69: 0 | AV69: 0 | AW69: 0 | AX69: =AT69+AU69+AV69+AW69 -> 0
B70: Net income/loss (IFRS) | C70: =C68+C69 -> -237.11276 | D70: =D68+D69 -> -56.331369 | E70: =E68+E69 -> -102.08683 | F70: =F68+F69 -> 21.005555 | G70: =G68+G69 -> 11.148493 | H70: =H68+H69 -> -126.26415 | I70: =I68+I69 -> -29.002551 | J70: =J68+J69 -> -73.027225 | ... AX70: =AX68+AX69 -> 1161.0814
B72: Income/Loss Before Tax - Adjusted | Z72: =Z55+Z63 -> 68.3 | AA72: =AA55+AA63 -> -15.9 | AB72: =AB55+AB63 -> 149.4 | AC72: =AC55+AC63 -> 158.7 | AD72: =AD55+AD63 -> 360.5 | AE72: =AE55+AE63 -> 215.6 | AF72: =AF55+AF63 -> 45.5 | AG72: =AG55+AG63 -> 256.7 | ... AX72: =AX55+AX63 -> 1642.5593
B73: Income tax expense - Adjusted | Z73: =Z66+Z119 -> -16.3 | AA73: =AA66+AA119 -> 42.5 | AB73: =AB66+AB119 -> -77.9 | AC73: =AC66+AC119 -> -66.8 | AD73: =Z73+AA73+AB73+AC73 -> -118.5 | AE73: =AE66+AE119 -> -64 | AF73: =AF66+AF119 -> -5.3 | AG73: =AG66+AG119 -> -68 | AH73: =AH66+AH119 -> -65 | AI73: =AE73+AF73+AG73+AH73 -> -202.3 | AJ73: =AJ66+AJ119 -> -85.5 | AK73: =AK66+AK119 -> -49.7 | AL73: =AL66+AL119 -> -79.841958 | AM73: =AM66+AM119 -> -89.943728 | AN73: =AJ73+AK73+AL73+AM73 -> -304.98569 | AO73: =AO66+AO119 -> -111.00403 | AP73: =AP66+AP119 -> -54.454637 | AQ73: =AQ66+AQ119 -> -98.576364 | AR73: =AR66+AR119 -> -111.42432 | AS73: =AO73+AP73+AQ73+AR73 -> -375.45935 | AT73: =AT66+AT119 -> -129.84575 | AU73: =AU66+AU119 -> -65.535967 | AV73: =AV66+AV119 -> -115.7679 | AW73: =AW66+AW119 -> -132.3414 | AX73: =AT73+AU73+AV73+AW73 -> -443.49101
B74: Tax rate | Z74: =-Z73/Z72 -> 0.238653 | AA74: =-AA73/AA72 -> 2.672956 | AB74: =-AB73/AB72 -> 0.52141901 | AC74: =-AC73/AC72 -> 0.42091997 | AD74: =-AD73/AD72 -> 0.32871012 | AE74: =-AE73/AE72 -> 0.29684601 | AF74: =-AF73/AF72 -> 0.11648352 | AG74: =-AG73/AG72 -> 0.26490066 | ... AX74: =-AX73/AX72 -> 0.27
B75: Income/Loss from continuing operations - Adjusted | Z75: =Z72+Z73 -> 52 | AA75: =AA72+AA73 -> 26.6 | AB75: =AB72+AB73 -> 71.5 | AC75: =AC72+AC73 -> 91.9 | AD75: =AD72+AD73 -> 242 | AE75: =AE72+AE73 -> 151.6 | AF75: =AF72+AF73 -> 40.2 | AG75: =AG72+AG73 -> 188.7 | ... AX75: =AX72+AX73 -> 1199.0683
B76: Loss from discontinued operations / NCI, net of tax | Z76: =Z69 -> -1.8 | AA76: =AA69 -> -1.9 | AB76: =AB69 -> -0.4 | AC76: -1.7 | AD76: =AD69 -> -5.8 | AE76: -3.5 | AF76: -4.2 | AG76: -3.3 | AH76: -2 | AI76: =AI69 -> -13 | AJ76: -5.5 | AK76: -10.6 | AL76: =AL69 -> -6.75 | AM76: =AM69 -> -6.75 | AN76: =AN69 -> -29.6 | AO76: =AO69 -> 0 | AP76: =AP69 -> 0 | AQ76: =AQ69 -> 0 | AR76: =AR69 -> 0 | AS76: =AS69 -> 0 | ... AX76: =AX69 -> 0
B77: Net income/loss (IFRS) - Adjusted | Z77: =Z75+Z76 -> 50.2 | AA77: =AA75+AA76 -> 24.7 | AB77: =AB75+AB76 -> 71.1 | AC77: =AC75+AC76 -> 90.2 | AD77: =AD75+AD76 -> 236.2 | AE77: =AE75+AE76 -> 148.1 | AF77: =AF75+AF76 -> 36 | AG77: =AG75+AG76 -> 185.4 | ... AX77: =AX75+AX76 -> 1199.0683
B79: Period-end shares | C79: =D79 -> 384.49961 | D79: =E79 -> 384.49961 | E79: =F79 -> 384.49961 | F79: =G79 -> 384.49961 | G79: =H79 -> 384.49961 | H79: =I79 -> 384.49961 | I79: =J79 -> 384.49961 | J79: =K79 -> 384.49961 | ... M79: =N79 -> 384.49961 | N79: 384.49961 | O79: 384.49961 | P79: 384.49961 | Q79: 384.49961 | R79: =Q79 -> 384.49961 | S79: =H79 -> 384.49961 | T79: =M79 -> 384.49961 | U79: =N79 -> 384.49961 | V79: =O79 -> 384.49961 | W79: =P79 -> 384.49961 | X79: =Q79 -> 384.49961 | Y79: =R79 -> 384.49961 | Z79: 505.24961 | AA79: 505.24961 | AB79: 505.55967 | AC79: 553.6312 | AD79: =AC79 -> 553.6312 | AE79: 554.23842 | AF79: 554.6943 | AG79: 555.07612 | AH79: =555.450449300015+2.3 -> 557.75045 | AI79: =AH79 -> 557.75045 | AJ79: 578.74775 | AK79: 579.11677 | AL79: =AL361 -> 579.50148 | AM79: =AM361 -> 579.87865 | AN79: =AM79 -> 579.87865 | AO79: =AO361 -> 580.24843 | AP79: =AP361 -> 580.61095 | AQ79: =AQ361 -> 580.96637 | AR79: =AR361 -> 581.31482 | AS79: =AR79 -> 581.31482 | AT79: =AT361 -> 581.65643 | AU79: =AU361 -> 581.99135 | AV79: =AV361 -> 582.3197 | AW79: =AW361 -> 582.64161 | AX79: =AW79 -> 582.64161
B80: Weighted average basic shares outstanding | C80: =D80 -> 384.49961 | D80: =E80 -> 384.49961 | E80: =F80 -> 384.49961 | F80: =G80 -> 384.49961 | G80: =H80 -> 384.49961 | H80: =I80 -> 384.49961 | I80: =J80 -> 384.49961 | J80: =K80 -> 384.49961 | ... M80: =N80 -> 384.49961 | N80: 384.49961 | O80: 384.49961 | P80: 384.49961 | Q80: 384.49961 | R80: =AVERAGE(N80:Q80) -> 384.49961 | S80: =H80 -> 384.49961 | T80: =M80 -> 384.49961 | U80: =N80 -> 384.49961 | V80: =O80 -> 384.49961 | W80: =P80 -> 384.49961 | X80: =Q80 -> 384.49961 | Y80: =R80 -> 384.49961 | Z80: 463.42268 | AA80: 505.24961 | AB80: 505.41269 | AC80: 519.04642 | AD80: =AVERAGE(Z80:AC80) -> 498.28285 | AE80: 553.98616 | AF80: 555.40092 | AG80: 556.1994 | AH80: 556.80299 | AI80: =AVERAGE(AE80:AH80) -> 555.59737 | AJ80: 564.90233 | AK80: 582.57714 | AL80: =AL362 -> 579.30912 | AM80: =AM362 -> 579.69007 | AN80: =AVERAGE(AJ80:AM80) -> 576.61966 | AO80: =AO362 -> 580.06354 | AP80: =AP362 -> 580.42969 | AQ80: =AQ362 -> 580.78866 | AR80: =AR362 -> 581.14059 | AS80: =AVERAGE(AO80:AR80) -> 580.60562 | AT80: =AT362 -> 581.48563 | AU80: =AU362 -> 581.82389 | AV80: =AV362 -> 582.15553 | AW80: =AW362 -> 582.48066 | AX80: =AVERAGE(AT80:AW80) -> 581.98642
B81: Weighted average diluted shares outstanding | C81: =D81 -> 384.49961 | D81: =E81 -> 384.49961 | E81: =F81 -> 384.49961 | F81: =G81 -> 384.49961 | G81: =H81 -> 384.49961 | H81: =I81 -> 384.49961 | I81: =J81 -> 384.49961 | J81: =K81 -> 384.49961 | ... M81: =N81 -> 384.49961 | N81: 384.49961 | O81: 384.49961 | P81: 384.49961 | Q81: 384.49961 | R81: =AVERAGE(N81:Q81) -> 384.49961 | S81: =H81 -> 384.49961 | T81: =M81 -> 384.49961 | U81: =N81 -> 384.49961 | V81: =O81 -> 384.49961 | W81: =P81 -> 384.49961 | X81: =Q81 -> 384.49961 | Y81: =R81 -> 384.49961 | Z81: 466.34578 | AA81: 508.3197 | AB81: 507.71679 | AC81: 524.56492 | AD81: =AVERAGE(Z81:AC81) -> 501.7368 | AE81: 557.56756 | AF81: 560.79898 | AG81: 563.53252 | AH81: 563.68948 | AI81: =AVERAGE(AE81:AH81) -> 561.39713 | AJ81: 572.23825 | AK81: 589.08686 | AL81: =AL364 -> 590.02104 | AM81: =AM364 -> 589.79979 | AN81: =AVERAGE(AJ81:AM81) -> 585.28649 | AO81: =AO364 -> 588.17111 | AP81: =AP364 -> 588.53515 | AQ81: =AQ364 -> 588.89206 | AR81: =AR364 -> 589.24196 | AS81: =AVERAGE(AO81:AR81) -> 588.71007 | AT81: =AT364 -> 589.585 | AU81: =AU364 -> 589.92132 | AV81: =AV364 -> 590.25105 | AW81: =AW364 -> 590.5743 | AX81: =AVERAGE(AT81:AW81) -> 590.08292
B82: Comparable EPS | C82: =C120/C81 -> -0.31703543 | D82: =D120/D81 -> -0.038573688 | E82: =E120/E81 -> -0.24658584 | F82: =F120/F81 -> 0.092798037 | G82: =G120/G81 -> 0.063773753 | H82: =H120/H81 -> -0.12858774 | I82: =I120/I81 -> -0.0076241186 | J82: =J120/J81 -> -0.12593115 | ... AX82: =AX120/AX81 -> 2.0320335
B83: One-timers | C83: =C84-C82 -> -0.29964337 | D83: =D84-D82 -> -0.10793197 | E83: =E84-E82 -> -0.018919832 | F83: =F84-F82 -> -0.038167149 | G83: =G84-G82 -> -0.034778943 | H83: =H84-H82 -> -0.1997979 | I83: =I84-I82 -> -0.06780522 | J83: =J84-J82 -> -0.06399681 | ... R83: =R84-R82 -> -0.30143074 | S83: =S82-S84 -> 0.1997979 | T83: =T82-T84 -> 0.68934199 | U83: =U82-U84 -> 0.021066341 | V83: =V82-V84 -> 0.027944545 | W83: =W82-W84 -> 0.086202082 | X83: =X82-X84 -> 0.16127628 | Y83: =Y82-Y84 -> 0.29648925 | Z83: =Z84-Z82 -> -0.096709357 | AA83: =AA84-AA82 -> -0.055870351 | AB83: =AB84-AB82 -> -0.03013491 | AC83: =AC84-AC82 -> -0.14259436 | AD83: =AD84-AD82 -> -0.32606737 | AE83: =AE84-AE82 -> -0.024212313 | AF83: =AF84-AF82 -> -0.031740428 | AG83: =AG84-AG82 -> -0.075062216 | ... AX83: =AX84-AX82 -> -0.064375526
B84: IFRS EPS | C84: =C70/C81 -> -0.61667881 | D84: =D70/D81 -> -0.14650566 | E84: =E70/E81 -> -0.26550568 | F84: =F70/F81 -> 0.054630887 | G84: =G70/G81 -> 0.02899481 | H84: =H70/H81 -> -0.32838564 | I84: =I70/I81 -> -0.075429339 | J84: =J70/J81 -> -0.18992796 | ... P84: =P70/P81 -> -0.093484274 | Q84: =Q68/Q81 -> -0.2460618 | R84: =R68/R81 -> -0.54252331 | S84: =S70/S81 -> -0.32838564 | T84: =T70/T81 -> -0.65732194 | U84: =U70/U81 -> 0.049414875 | V84: =V70/V81 -> -0.25239211 | W84: =W70/W81 -> -0.093484274 | X84: =X70/X81 -> -0.24112032 | Y84: =Y70/Y81 -> -0.53758182 | Z84: =Z70/Z81 -> 0.010936091 | ... AX84: =AX70/AX81 -> 1.967658
B86: Adjusted EBITDA Bridge
B87: Net income/loss | C87: =C70 -> -237.11276 | D87: =D70 -> -56.331369 | E87: =E70 -> -102.08683 | F87: =F70 -> 21.005555 | G87: =G70 -> 11.148493 | H87: =D87+E87+F87+G87 -> -126.26415 | I87: =I70 -> -29.002551 | J87: =J70 -> -73.027225 | K87: =K70 -> -2.3014635 | L87: =L70 -> -148.40879 | M87: =I87+J87+K87+L87 -> -252.74003 | N87: =N70 -> 19 | O87: =O70 -> -97.044667 | P87: =P70 -> -35.944667 | Q87: =Q68 -> -94.610667 | R87: =N87+O87+P87+Q87 -> -208.6 | S87: =S70 -> -126.26415 | T87: =T70 -> -252.74003 | U87: =U70 -> 19 | V87: =V70 -> -97.044667 | W87: =W70 -> -35.944667 | X87: =X68 -> -94.610667 | Y87: =Y68 -> -208.6 | Z87: =Z68 -> 6.9 | AA87: =AA68 -> -1.8 | AB87: =AB68 -> 56.2 | AC87: =AC68 -> 17.1 | AD87: =Z87+AA87+AB87+AC87 -> 78.4 | AE87: =AE68 -> 138.1 | AF87: =AF68 -> 22.4 | AG87: =AG68 -> 146.4 | AH87: =AH68 -> 133.5 | AI87: =AE87+AF87+AG87+AH87 -> 440.4 | AJ87: =AJ68 -> 170.1 | AK87: =AK68 -> 117.8 | AL87: =AL68 -> 195.94789 | AM87: =AM68 -> 224.78531 | AN87: =AJ87+AK87+AL87+AM87 -> 708.6332 | AO87: =AO68 -> 283.22198 | AP87: =AP68 -> 134.13723 | AQ87: =AQ68 -> 250.45814 | AR87: =AR68 -> 284.33003 | AS87: =AO87+AP87+AQ87+AR87 -> 952.14737 | AT87: =AT68 -> 341.57442 | AU87: =AU68 -> 167.69984 | AV87: =AV68 -> 303.51209 | AW87: =AW68 -> 348.32193 | AX87: =AT87+AU87+AV87+AW87 -> 1161.1083
B88: Income tax expense | C88: 14.8 | D88: 0.718 | E88: -8.149 | F88: 12.209 | G88: 27.17 | H88: =D88+E88+F88+G88 -> 31.948 | I88: =-I66 -> 11.7 | J88: =-J66 -> -3.8 | K88: =-K66 -> 17.011148 | L88: =-L66 -> 23.527994 | M88: =I88+J88+K88+L88 -> 48.439142 | N88: =-N66 -> 26.6 | O88: =-O66 -> 5.2 | P88: =-P66 -> 32.6 | Q88: =-Q66 -> 39.8 | R88: =N88+O88+P88+Q88 -> 104.2 | S88: =H88 -> 31.948 | T88: =M88 -> 48.439142 | U88: =N88 -> 26.6 | V88: =O88 -> 5.2 | W88: =P88 -> 32.6 | X88: =Q88 -> 39.8 | Y88: =U88+V88+W88+X88 -> 104.2 | Z88: =-Z66 -> 8.2 | AA88: =-AA66 -> -51.9 | AB88: =-AB66 -> 72.7 | AC88: =-AC66 -> 53.8 | AD88: =Z88+AA88+AB88+AC88 -> 82.8 | AE88: =-AE66 -> 59.5 | AF88: =-AF66 -> -0.6 | AG88: =-AG66 -> 51.3 | AH88: =-AH66 -> 73.9 | AI88: =AE88+AF88+AG88+AH88 -> 184.1 | AJ88: =-AJ66 -> 70.5 | AK88: =-AK66 -> 43 | AL88: =-AL66 -> 76.201958 | AM88: =-AM66 -> 86.336228 | AN88: =AJ88+AK88+AL88+AM88 -> 276.03819 | AO88: =-AO66 -> 107.42903 | AP88: =-AP66 -> 50.879637 | AQ88: =-AQ66 -> 95.001364 | AR88: =-AR66 -> 107.84932 | AS88: =AO88+AP88+AQ88+AR88 -> 361.15935 | AT88: =-AT66 -> 126.33575 | AU88: =-AU66 -> 62.025967 | AV88: =-AV66 -> 112.2579 | AW88: =-AW66 -> 128.8314 | AX88: =AT88+AU88+AV88+AW88 -> 429.45101
B89: Finance cost | C89: 275.5 | D89: =-D61 -> 75.465903 | E89: =-E61 -> 78.675649 | F89: =-F61 -> 67.632504 | G89: =-G61 -> 57.24426 | H89: =D89+E89+F89+G89 -> 279.01832 | I89: =-I61 -> 57.6 | J89: =-J61 -> 55.3 | K89: =-K61 -> 55.515802 | L89: =-L61 -> 68.022794 | M89: =I89+J89+K89+L89 -> 236.4386 | N89: =-N61 -> 86.1 | O89: =-O61 -> 101.1 | P89: =-P61 -> 109.4 | Q89: =-Q61 -> 116.8 | R89: =N89+O89+P89+Q89 -> 413.4 | S89: =H89 -> 279.01832 | T89: =M89 -> 236.4386 | U89: =N89 -> 86.1 | V89: =O89 -> 101.1 | W89: =P89 -> 109.4 | X89: =Q89 -> 116.8 | Y89: =U89+V89+W89+X89 -> 413.4 | Z89: =-Z61 -> 96.6 | AA89: =-AA61 -> 47.7 | AB89: =-AB61 -> 48.9 | AC89: =-AC61 -> 125.2 | AD89: =Z89+AA89+AB89+AC89 -> 318.4 | AE89: =-AE61 -> 22 | AF89: =-AF61 -> 30 | AG89: =-AG61 -> 25.6 | AH89: =-AH61 -> 22.6 | AI89: =AE89+AF89+AG89+AH89 -> 100.2 | AJ89: =-AJ61 -> 83.2 | AK89: =-AK61 -> 36.3 | AL89: =-AL61 -> 22.11 | AM89: =-AM61 -> 22.11 | AN89: =AJ89+AK89+AL89+AM89 -> 163.72 | AO89: =-AO61 -> 14.74 | AP89: =-AP61 -> 14.74 | AQ89: =-AQ61 -> 14.74 | AR89: =-AR61 -> 14.74 | AS89: =AO89+AP89+AQ89+AR89 -> 58.96 | AT89: =-AT61 -> 14.74 | AU89: =-AU61 -> 14.74 | AV89: =-AV61 -> 14.74 | AW89: =-AW61 -> 14.74 | AX89: =AT89+AU89+AV89+AW89 -> 58.96
B90: Depreciation and amortization | C90: 230.1 | D90: 55.859 | E90: 54.352 | F90: 46.556 | G90: 49.61 | H90: =D90+E90+F90+G90 -> 206.377 | I90: 49.703821 | J90: 50.392469 | K90: 47.636778 | L90: 49.11213 | M90: =I90+J90+K90+L90 -> 196.8452 | N90: ='3. Segment Build'!N72+'3. Segment Build'!N184+'3. Segment Build'!N288+'3. Segment Build'!N374+'3. Segment Build'!N95 -> 52 | O90: ='3. Segment Build'!O72+'3. Segment Build'!O184+'3. Segment Build'!O288+'3. Segment Build'!O374+'3. Segment Build'!O95 -> 52.4 | P90: ='3. Segment Build'!P72+'3. Segment Build'!P184+'3. Segment Build'!P288+'3. Segment Build'!P374+'3. Segment Build'!P95 -> 54.114667 | Q90: ='3. Segment Build'!Q72+'3. Segment Build'!Q184+'3. Segment Build'!Q288+'3. Segment Build'!Q374+'3. Segment Build'!Q95 -> 62.385333 | R90: =N90+O90+P90+Q90 -> 220.9 | S90: =H90 -> 206.377 | T90: =M90 -> 196.8452 | U90: =N90 -> 52 | V90: =O90 -> 52.4 | W90: =P90 -> 54.114667 | X90: =Q90 -> 62.385333 | Y90: =U90+V90+W90+X90 -> 220.9 | Z90: 62.5 | AA90: 62.8 | AB90: 71.2 | AC90: 77.3 | AD90: =Z90+AA90+AB90+AC90 -> 273.8 | AE90: 77.7 | AF90: 81.4 | AG90: 118.8 | AH90: 106.3 | AI90: =AE90+AF90+AG90+AH90 -> 384.2 | AJ90: 102.6 | AK90: 112.5 | AL90: ='3. Segment Build'!AL76+'3. Segment Build'!AL184+'3. Segment Build'!AL288+'3. Segment Build'!AL374+'3. Segment Build'!AL95 -> 110.9725 | AM90: ='3. Segment Build'!AM76+'3. Segment Build'!AM184+'3. Segment Build'!AM288+'3. Segment Build'!AM374+'3. Segment Build'!AM95 -> 122.3725 | AN90: =AJ90+AK90+AL90+AM90 -> 448.445 | AO90: ='3. Segment Build'!AO76+'3. Segment Build'!AO184+'3. Segment Build'!AO288+'3. Segment Build'!AO374+'3. Segment Build'!AO95 -> 113.22 | AP90: ='3. Segment Build'!AP76+'3. Segment Build'!AP184+'3. Segment Build'!AP288+'3. Segment Build'!AP374+'3. Segment Build'!AP95 -> 122.46 | AQ90: ='3. Segment Build'!AQ76+'3. Segment Build'!AQ184+'3. Segment Build'!AQ288+'3. Segment Build'!AQ374+'3. Segment Build'!AQ95 -> 127.937 | AR90: ='3. Segment Build'!AR76+'3. Segment Build'!AR184+'3. Segment Build'!AR288+'3. Segment Build'!AR374+'3. Segment Build'!AR95 -> 141.617 | AS90: =AO90+AP90+AQ90+AR90 -> 505.234 | AT90: ='3. Segment Build'!AT76+'3. Segment Build'!AT184+'3. Segment Build'!AT288+'3. Segment Build'!AT374+'3. Segment Build'!AT95 -> 130.401 | AU90: ='3. Segment Build'!AU76+'3. Segment Build'!AU184+'3. Segment Build'!AU288+'3. Segment Build'!AU374+'3. Segment Build'!AU95 -> 141.093 | AV90: ='3. Segment Build'!AV76+'3. Segment Build'!AV184+'3. Segment Build'!AV288+'3. Segment Build'!AV374+'3. Segment Build'!AV95 -> 147.9844 | AW90: ='3. Segment Build'!AW76+'3. Segment Build'!AW184+'3. Segment Build'!AW288+'3. Segment Build'!AW374+'3. Segment Build'!AW95 -> 164.4004 | AX90: =AT90+AU90+AV90+AW90 -> 583.8788
B91: Finance income | C91: =-C60 -> -1.6 | D91: =-D60 -> -0.74292038 | E91: =-E60 -> -0.5140625 | F91: =-F60 -> -0.42702973 | G91: =-G60 -> -0.61808322 | H91: =D91+E91+F91+G91 -> -2.3020958 | I91: =-I60 -> -0.6 | J91: =-J60 -> -0.9 | K91: =-K60 -> -0.545469 | L91: =-L60 -> -1.255912 | M91: =I91+J91+K91+L91 -> -3.301381 | N91: =-N60 -> -1.3 | O91: =-O60 -> -1.8 | P91: =-P60 -> -1.4 | Q91: =-Q60 -> -1.9 | R91: =N91+O91+P91+Q91 -> -6.4 | S91: =H91 -> -2.3020958 | T91: =M91 -> -3.301381 | U91: =N91 -> -1.3 | V91: =O91 -> -1.8 | W91: =P91 -> -1.4 | X91: =Q91 -> -1.9 | Y91: =U91+V91+W91+X91 -> -6.4 | Z91: =-Z60 -> -2.7 | AA91: =-AA60 -> -2.5 | AB91: =-AB60 -> -1.1 | AC91: =-AC60 -> -2.5 | AD91: =Z91+AA91+AB91+AC91 -> -8.8 | AE91: =-AE60 -> -5.4 | AF91: =-AF60 -> -8.1 | AG91: =-AG60 -> -7.4 | AH91: =-AH60 -> -2 | AI91: =AE91+AF91+AG91+AH91 -> -22.9 | AJ91: =-AJ60 -> -2.7 | AK91: =-AK60 -> -5.4 | AL91: =-AL60 -> -4.4380057 | AM91: =-AM60 -> -5.5641574 | AN91: =AJ91+AK91+AL91+AM91 -> -18.102163 | AO91: =-AO60 -> -6.7598608 | AP91: =-AP60 -> -8.0090615 | AQ91: =-AQ60 -> -6.6554671 | AR91: =-AR60 -> -7.8876501 | AS91: =AO91+AP91+AQ91+AR91 -> -29.312039 | AT91: =-AT60 -> -11.989115 | AU91: =-AU60 -> -13.761625 | AV91: =-AV60 -> -12.559193 | AW91: =-AW60 -> -14.21666 | AX91: =AT91+AU91+AV91+AW91 -> -52.526593
B92: EBITDA | C92: =C87+C88+C89+C90+C91 -> 281.68724 | D92: =D87+D88+D89+D90+D91 -> 74.968614 | E92: =E87+E88+E89+E90+E91 -> 22.277759 | F92: =F87+F88+F89+F90+F91 -> 146.97603 | G92: =G87+G88+G89+G90+G91 -> 144.55467 | H92: =H87+H88+H89+H90+H91 -> 388.77707 | I92: =I87+I88+I89+I90+I91 -> 89.40127 | J92: =J87+J88+J89+J90+J91 -> 27.965245 | ... AX92: =AX87+AX88+AX89+AX90+AX91 -> 2180.8715
B93: Loss from discontinued operations | C93: 23.4 | D93: 18.26 | E93: -23.7 | F93: 3.94 | G93: -4.63 | H93: =D93+E93+F93+G93 -> -6.13 | I93: 9.4732899 | J93: 8.3305617 | K93: 0.44839744 | L93: 1.1903052 | M93: =I93+J93+K93+L93 -> 19.442554 | N93: 0 | O93: 0 | P93: 0 | Q93: 0 | R93: =N93+O93+P93+Q93 -> 0 | S93: =H93 -> -6.13 | T93: =M93 -> 19.442554 | U93: =N93 -> 0 | V93: =O93 -> 0 | W93: =P93 -> 0 | X93: =Q93 -> 0 | Y93: =U93+V93+W93+X93 -> 0 | Z93: 0 | AA93: 0 | AB93: 0 | AC93: 0 | AD93: =Z93+AA93+AB93+AC93 -> 0 | AE93: 0 | AF93: 0 | AG93: 0 | AH93: 0 | AI93: =AE93+AF93+AG93+AH93 -> 0 | AJ93: 0 | AK93: 0 | AL93: 0 | AM93: 0 | AN93: =AJ93+AK93+AL93+AM93 -> 0 | AO93: 0 | AP93: 0 | AQ93: 0 | AR93: 0 | AS93: =AO93+AP93+AQ93+AR93 -> 0 | AT93: 0 | AU93: 0 | AV93: 0 | AW93: 0 | AX93: =AT93+AU93+AV93+AW93 -> 0
B94: Restructuring expenses | C94: 11 | D94: 1.4 | E94: 32.7 | F94: 1 | G94: -1.6 | H94: =D94+E94+F94+G94 -> 33.5 | I94: 5.7604681 | J94: -0.4 | K94: 0.1 | L94: 0.3 | M94: =I94+J94+K94+L94 -> 5.7604681 | N94: 0 | O94: 0.2 | P94: 2.3 | Q94: =2.3-N94-O94-P94 -> -0.2 | R94: =N94+O94+P94+Q94 -> 2.3 | S94: =H94 -> 33.5 | T94: =M94 -> 5.7604681 | U94: =N94 -> 0 | V94: =O94 -> 0.2 | W94: =P94 -> 2.3 | X94: =Q94 -> -0.2 | Y94: =U94+V94+W94+X94 -> 2.3 | Z94: 0.9 | AA94: 8.8 | AB94: 2.5 | AC94: 10.2 | AD94: =Z94+AA94+AB94+AC94 -> 22.4 | AE94: 2.9 | AF94: 6 | AG94: 5.4 | AH94: 9.3 | AI94: =AE94+AF94+AG94+AH94 -> 23.6 | AJ94: 4.2 | AK94: 6.8 | AL94: 0 | AM94: 0 | AN94: =AJ94+AK94+AL94+AM94 -> 11 | AO94: 0 | AP94: 0 | AQ94: 0 | AR94: 0 | AS94: =AO94+AP94+AQ94+AR94 -> 0 | AT94: 0 | AU94: 0 | AV94: 0 | AW94: 0 | AX94: =AT94+AU94+AV94+AW94 -> 0
B95: Impairment losses on goodwill | C95: 0 | D95: 0 | E95: 0 | F95: 0 | G95: 0 | H95: =D95+E95+F95+G95 -> 0 | I95: 0 | J95: 0 | K95: 0 | L95: 198.1 | M95: =I95+J95+K95+L95 -> 198.1 | N95: 0 | O95: 0 | P95: 0 | Q95: 0 | R95: =N95+O95+P95+Q95 -> 0 | S95: =H95 -> 0 | T95: =M95 -> 198.1 | U95: =N95 -> 0 | V95: =O95 -> 0 | W95: =P95 -> 0 | X95: =Q95 -> 0 | Y95: =U95+V95+W95+X95 -> 0 | Z95: 0 | AA95: 0 | AB95: 0 | AC95: 0 | AD95: =Z95+AA95+AB95+AC95 -> 0 | AE95: 0 | AF95: 0 | AG95: 6.7 | AH95: 0 | AI95: =AE95+AF95+AG95+AH95 -> 6.7 | AJ95: 0 | AK95: 1.8 | AL95: 0 | AM95: 0 | AN95: =AJ95+AK95+AL95+AM95 -> 1.8 | AO95: 0 | AP95: 0 | AQ95: 0 | AR95: 0 | AS95: =AO95+AP95+AQ95+AR95 -> 0 | AT95: 0 | AU95: 0 | AV95: 0 | AW95: 0 | AX95: =AT95+AU95+AV95+AW95 -> 0
B96: Expenses related to deal activities | C96: -4.7 | D96: 0 | E96: 0 | F96: 0.6 | G96: 0 | H96: =D96+E96+F96+G96 -> 0.6 | I96: 0 | J96: 0 | K96: 0 | L96: 0.3 | M96: =I96+J96+K96+L96 -> 0.3 | N96: 0.2 | O96: 2.5 | P96: 15.8 | Q96: =33.9-N96-O96-P96 -> 15.4 | R96: =N96+O96+P96+Q96 -> 33.9 | S96: =H96 -> 0.6 | T96: =M96 -> 0.3 | U96: =N96 -> 0.2 | V96: =O96 -> 2.5 | W96: =P96 -> 15.8 | X96: =Q96 -> 15.4 | Y96: =U96+V96+W96+X96 -> 33.9 | Z96: 5.8 | AA96: 12.2 | AB96: 2.3 | AC96: 1.8 | AD96: =Z96+AA96+AB96+AC96 -> 22.1 | AE96: 0.3 | AF96: 2 | AG96: 3.9 | AH96: 9.7 | AI96: =AE96+AF96+AG96+AH96 -> 15.9 | AJ96: -0.1 | AK96: 0.6 | AL96: 0 | AM96: 0 | AN96: =AJ96+AK96+AL96+AM96 -> 0.5 | AO96: 0 | AP96: 0 | AQ96: 0 | AR96: 0 | AS96: =AO96+AP96+AQ96+AR96 -> 0 | AT96: 0 | AU96: 0 | AV96: 0 | AW96: 0 | AX96: =AT96+AU96+AV96+AW96 -> 0
B97: Expenses related to certain legal proceedings | C97: 0 | D97: 0 | E97: 0 | F97: 0 | G97: 0 | H97: =D97+E97+F97+G97 -> 0 | I97: 0 | J97: 3.9 | K97: 0 | L97: 0 | M97: =I97+J97+K97+L97 -> 3.9 | N97: 0 | O97: 0 | P97: 0 | Q97: =3.3-N97-O97-P97 -> 3.3 | R97: =N97+O97+P97+Q97 -> 3.3 | S97: =H97 -> 0 | T97: =M97 -> 3.9 | U97: =N97 -> 0 | V97: =O97 -> 0 | W97: =P97 -> 0 | X97: =Q97 -> 3.3 | Y97: =U97+V97+W97+X97 -> 3.3 | Z97: 0 | AA97: 0 | AB97: 1.4 | AC97: 2.2 | AD97: =Z97+AA97+AB97+AC97 -> 3.6 | AE97: -0.7 | AF97: -1.2 | AG97: 0.8 | AH97: 4.6 | AI97: =AE97+AF97+AG97+AH97 -> 3.5 | AJ97: 0 | AK97: 0.2 | AL97: 0 | AM97: 0 | AN97: =AJ97+AK97+AL97+AM97 -> 0.2 | AO97: 0 | AP97: 0 | AQ97: 0 | AR97: 0 | AS97: =AO97+AP97+AQ97+AR97 -> 0 | AT97: 0 | AU97: 0 | AV97: 0 | AW97: 0 | AX97: =AT97+AU97+AV97+AW97 -> 0
B98: Share-based payments | C98: 0 | D98: 0 | E98: 0 | F98: 0 | G98: 0 | H98: =D98+E98+F98+G98 -> 0 | I98: 0 | J98: 0 | K98: 0 | L98: 0 | M98: =I98+J98+K98+L98 -> 0 | N98: 0 | O98: 0 | P98: 0 | Q98: =47.9-N98-O98-P98 -> 47.9 | R98: =N98+O98+P98+Q98 -> 47.9 | S98: =H98 -> 0 | T98: =M98 -> 0 | U98: =N98 -> 0 | V98: =O98 -> 0 | W98: =P98 -> 0 | X98: =Q98 -> 47.9 | Y98: =U98+V98+W98+X98 -> 47.9 | Z98: 3.4 | AA98: 6.1 | AB98: 1.3 | AC98: 4.5 | AD98: =Z98+AA98+AB98+AC98 -> 15.3 | AE98: 5 | AF98: 5.9 | AG98: 1.7 | AH98: 2.4 | AI98: =AE98+AF98+AG98+AH98 -> 15 | AJ98: 4.6 | AK98: -1.7 | AL98: 4 | AM98: 4 | AN98: =AJ98+AK98+AL98+AM98 -> 10.9 | AO98: 4 | AP98: 4 | AQ98: 4 | AR98: 4 | AS98: =AO98+AP98+AQ98+AR98 -> 16 | AT98: 4 | AU98: 4 | AV98: 4 | AW98: 4 | AX98: =AT98+AU98+AV98+AW98 -> 16
B99: Adjusted EBITDA | C99: =C92+C93+C94+C95+C96+C97+C98 -> 311.38724 | D99: =D92+D93+D94+D95+D96+D97+D98 -> 94.628614 | E99: =E92+E93+E94+E95+E96+E97+E98 -> 31.277759 | F99: =F92+F93+F94+F95+F96+F97+F98 -> 152.51603 | G99: =G92+G93+G94+G95+G96+G97+G98 -> 138.32467 | H99: =H92+H93+H94+H95+H96+H97+H98 -> 416.74707 | I99: =I92+I93+I94+I95+I96+I97+I98 -> 104.63503 | J99: =J92+J93+J94+J95+J96+J97+J98 -> 39.795806 | ... AX99: =AX92+AX93+AX94+AX95+AX96+AX97+AX98 -> 2196.8715
B100: % margin | C100: =C99/C8 -> 0.12729427 | D100: =D99/D8 -> 0.14262252 | E100: =E99/E8 -> 0.052320569 | F100: =F99/F8 -> 0.18919533 | G100: =G99/G8 -> 0.13846313 | H100: =H99/H8 -> 0.13590627 | I100: =I99/I8 -> 0.12931353 | J100: =J99/J8 -> 0.057390492 | ... AX100: =AX99/AX8 -> 0.20440323
B101: bps chg. y/y | C101: -- | D101: -- | E101: -- | F101: -- | G101: -- | H101: =(H100-C100)*100*100 -> 86.120035 | I101: =(I100-D100)*100*100 -> -133.08986 | J101: =(J100-E100)*100*100 -> 50.699237 | K101: =(K100-F100)*100*100 -> -500.69318 | L101: =(L100-G100)*100*100 -> 207.81645 | M101: =(M100-H100)*100*100 -> -81.937391 | N101: =(N100-I100)*100*100 -> 445.41558 | O101: =(O100-J100)*100*100 -> 156.19934 | ... R101: =(R100-M100)*100*100 -> 121.32719 | S101: -- | T101: =(T100-S100)*100*100 -> -81.448376 | U101: -- | V101: -- | W101: -- | X101: -- | Y101: =(Y100-T100)*100*100 -> 119.16892 | Z101: =(Z100-U100)*100*100 -> -204.55188 | AA101: =(AA100-V100)*100*100 -> 87.83495 | AB101: =(AB100-W100)*100*100 -> 352.67635 | AC101: =(AC100-X100)*100*100 -> 347.92764 | AD101: =(AD100-Y100)*100*100 -> 170.62974 | AE101: =(AE100-Z100)*100*100 -> 510.29787 | AF101: =(AF100-AA100)*100*100 -> 301.7542 | ... AX101: =(AX100-AS100)*100*100 -> 72.488867
B102: IFRS16 depreciation | C102: 69.2 | D102: 18.305 | E102: 18.105 | F102: 17.685 | G102: 21.332 | H102: =D102+E102+F102+G102 -> 75.427 | I102: 19 | J102: 19.4 | K102: 17.605 | L102: 17.3 | M102: =I102+J102+K102+L102 -> 73.305 | N102: 18.8 | O102: 19.344 | P102: 21.296 | Q102: =87.4-N102-O102-P102 -> 27.96 | R102: =N102+O102+P102+Q102 -> 87.4 | S102: =H102 -> 75.427 | T102: =M102 -> 73.305 | U102: =N102 -> 18.8 | V102: =O102 -> 19.344 | W102: =P102 -> 21.296 | X102: =Q102 -> 27.96 | Y102: =U102+V102+W102+X102 -> 87.4 | Z102: 26.5 | AA102: 29.2 | AB102: 32.3 | AC102: 36.7 | AD102: =Z102+AA102+AB102+AC102 -> 124.7 | AE102: 35.9 | AF102: 39.4 | AG102: 42.8 | AH102: 48 | AI102: =AE102+AF102+AG102+AH102 -> 166.1 | AJ102: 49.6 | AK102: 55.2 | AL102: 57.5 | AM102: 57.5 | AN102: =AJ102+AK102+AL102+AM102 -> 219.8 | AO102: 60 | AP102: 60 | AQ102: 60 | AR102: 60 | AS102: =AO102+AP102+AQ102+AR102 -> 240 | AT102: 65 | AU102: 65 | AV102: 65 | AW102: 65 | AX102: =AT102+AU102+AV102+AW102 -> 260
B103: Adjusted EBITDA without IFRS16 | C103: =C99-C102 -> 242.18724 | D103: =D99-D102 -> 76.323614 | E103: =E99-E102 -> 13.172759 | F103: =F99-F102 -> 134.83103 | G103: =G99-G102 -> 116.99267 | H103: =D103+E103+F103+G103 -> 341.32007 | I103: =I99-I102 -> 85.635028 | J103: =J99-J102 -> 20.395806 | K103: =K99-K102 -> 100.26019 | L103: =L99-L102 -> 173.58852 | M103: =I103+J103+K103+L103 -> 379.87955 | N103: =N99-N102 -> 163.8 | O103: =O99-O102 -> 43.211333 | P103: =P99-P102 -> 155.574 | Q103: =Q99-Q102 -> 160.91467 | R103: =N103+O103+P103+Q103 -> 523.5 | S103: =S99-S102 -> 341.32007 | T103: =T99-T102 -> 379.87955 | U103: =U99-U102 -> 163.8 | V103: =V99-V102 -> 43.211333 | W103: =W99-W102 -> 155.574 | X103: =X99-X102 -> 160.91467 | Y103: =Y99-Y102 -> 523.5 | Z103: =Z99-Z102 -> 155.1 | ... AC103: =AC99-AC102 -> 252.9 | AD103: =Z103+AA103+AB103+AC103 -> 683.3 | AE103: =AE99-AE102 -> 263.5 | AF103: =AF99-AF102 -> 98.4 | AG103: =AG99-AG102 -> 310.4 | AH103: =AH99-AH102 -> 312.3 | AI103: =AE103+AF103+AG103+AH103 -> 984.6 | AJ103: =AJ99-AJ102 -> 382.8 | AK103: =AK99-AK102 -> 256.7 | AL103: =AL99-AL102 -> 347.29434 | AM103: =AM99-AM102 -> 396.53988 | AN103: =AJ103+AK103+AL103+AM103 -> 1383.3342 | AO103: =AO99-AO102 -> 455.85114 | AP103: =AP99-AP102 -> 258.2078 | AQ103: =AQ99-AQ102 -> 425.48104 | AR103: =AR99-AR102 -> 484.6487 | AS103: =AO103+AP103+AQ103+AR103 -> 1624.1887 | AT103: =AT99-AT102 -> 540.06205 | AU103: =AU99-AU102 -> 310.79718 | AV103: =AV99-AV102 -> 504.93519 | AW103: =AW99-AW102 -> 581.07706 | AX103: =AT103+AU103+AV103+AW103 -> 1936.8715
B104: % chg. y/y | C104: -- | D104: -- | E104: -- | F104: -- | G104: -- | H104: =H103/C103-1 -> 0.40932309 | I104: =I103/D103-1 -> 0.12199913 | J104: =J103/E103-1 -> 0.54833212 | K104: =K103/F103-1 -> -0.25640119 | L104: =L103/G103-1 -> 0.48375555 | M104: =M103/H103-1 -> 0.11297161 | N104: =N103/I103-1 -> 0.91276869 | O104: =O103/J103-1 -> 1.1186382 | ... R104: =R103/M103-1 -> 0.37806839 | S104: -- | T104: =T103/S103-1 -> 0.11297161 | U104: -- | V104: -- | W104: -- | X104: -- | Y104: =Y103/T103-1 -> 0.37806839 | Z104: =Z103/U103-1 -> -0.053113553 | AA104: =AA103/V103-1 -> 0.20801642 | AB104: =AB103/W103-1 -> 0.43404425 | AC104: =AC103/X103-1 -> 0.57164046 | AD104: =AD103/Y103-1 -> 0.3052531 | AE104: =AE103/Z103-1 -> 0.69890393 | AF104: =AF103/AA103-1 -> 0.88505747 | ... AX104: =AX103/AS103-1 -> 0.19251631
B105: % margin | C105: =C103/C8 -> 0.099005495 | D105: =D103/D8 -> 0.11503356 | E105: =E103/E8 -> 0.022035027 | F105: =F103/F8 -> 0.16725718 | G105: =G103/G8 -> 0.11710978 | H105: =H103/H8 -> 0.11130861 | I105: =I103/I8 -> 0.10583232 | J105: =J103/J8 -> 0.029413284 | ... AX105: =AX103/AX8 -> 0.18021209
B106: bps chg. y/y | C106: -- | D106: -- | E106: -- | F106: -- | G106: -- | H106: =(H105-C105)*100*100 -> 123.03119 | I106: =(I105-D105)*100*100 -> -92.012347 | J106: =(J105-E105)*100*100 -> 73.782578 | K106: =(K105-F105)*100*100 -> -489.11802 | L106: =(L105-G105)*100*100 -> 277.02833 | M106: =(M105-H105)*100*100 -> -42.542583 | N106: =(N105-I105)*100*100 -> 501.2312 | O106: =(O105-J105)*100*100 -> 210.20111 | ... R106: =(R105-M105)*100*100 -> 127.83572 | S106: -- | T106: =(T105-S105)*100*100 -> -42.29617 | U106: -- | V106: -- | W106: -- | X106: -- | Y106: =(Y105-T105)*100*100 -> 125.83652 | Z106: =(Z105-U105)*100*100 -> -248.93087 | AA106: =(AA105-V105)*100*100 -> 20.443456 | AB106: =(AB105-W105)*100*100 -> 298.77344 | AC106: =(AC105-X105)*100*100 -> 334.1529 | AD106: =(AD105-Y105)*100*100 -> 128.65844 | AE106: =(AE105-Z105)*100*100 -> 488.73568 | AF106: =(AF105-AA105)*100*100 -> 274.6531 | ... AX106: =(AX105-AS105)*100*100 -> 84.398505
B107: incremental margin | C107: -- | D107: -- | E107: -- | F107: -- | G107: -- | H107: =(H103-C103)/(H8-C8) -> 0.15983237 | I107: =(I103-D103)/(I8-D8) -> 0.063922337 | J107: =(J103-E103)/(J8-E8) -> 0.07554573 | K107: =(K103-F103)/(K8-F8) -> -0.84210204 | L107: =(L103-G103)/(L8-G8) -> 0.28338826 | M107: =(M103-H103)/(M8-H8) -> 0.079991687 | N107: =(N103-I103)/(N8-I8) -> 0.32414447 | O107: =(O103-J103)/(O8-J8) -> 0.13964836 | ... R107: =(R103-M103)/(R8-M8) -> 0.17516261 | S107: -- | T107: =(T103-S103)/(T8-S8) -> 0.079480551 | U107: -- | V107: -- | W107: -- | X107: -- | Y107: =(Y103-T103)/(Y8-T8) -> 0.17313547 | Z107: =(Z103-U103)/(Z8-U8) -> -0.064254062 | AA107: =(AA103-V103)/(AA8-V8) -> 0.064853295 | AB107: =(AB103-W103)/(AB8-W8) -> 0.33645242 | AC107: =(AC103-X103)/(AC8-X8) -> 0.29865368 | AD107: =(AD103-Y103)/(AD8-Y8) -> 0.20416507 | AE107: =(AE103-Z103)/(AE8-Z8) -> 0.38700464 | AF107: =(AF103-AA103)/(AF8-AA8) -> 0.19667944 | ... AX107: =(AX103-AS103)/(AX8-AS8) -> 0.24196679
B109: Adjusted net income
B110: Net income/loss | C110: =C70 -> -237.11276 | D110: =D70 -> -56.331369 | E110: =E70 -> -102.08683 | F110: =F70 -> 21.005555 | G110: =G70 -> 11.148493 | H110: =D110+E110+F110+G110 -> -126.26415 | I110: =I70 -> -29.002551 | J110: =J70 -> -73.027225 | K110: =K70 -> -2.3014635 | L110: =L70 -> -148.40879 | M110: =I110+J110+K110+L110 -> -252.74003 | N110: =N70 -> 19 | O110: =O70 -> -97.044667 | P110: =P70 -> -35.944667 | Q110: =Q68 -> -94.610667 | R110: =N110+O110+P110+Q110 -> -208.6 | S110: =S70 -> -126.26415 | T110: =T70 -> -252.74003 | U110: =U70 -> 19 | V110: =V70 -> -97.044667 | W110: =W70 -> -35.944667 | X110: =X68 -> -94.610667 | Y110: =Y68 -> -208.6 | Z110: =Z70 -> 5.1 | AA110: =AA70 -> -3.7 | AB110: =AB70 -> 55.8 | AC110: =AC70 -> 15.4 | AD110: =Z110+AA110+AB110+AC110 -> 72.6 | AE110: =AE70 -> 134.6 | AF110: =AF70 -> 18.2 | AG110: =AG70 -> 143.1 | AH110: =AH70 -> 131.5 | AI110: =AE110+AF110+AG110+AH110 -> 427.4 | AJ110: =AJ70 -> 164.6 | AK110: =AK70 -> 107.2 | AL110: =AL70 -> 189.19789 | AM110: =AM70 -> 218.03531 | AN110: =AJ110+AK110+AL110+AM110 -> 679.0332 | AO110: =AO70 -> 283.22198 | AP110: =AP70 -> 134.13723 | AQ110: =AQ70 -> 250.45814 | AR110: =AR70 -> 284.33003 | AS110: =AO110+AP110+AQ110+AR110 -> 952.14737 | AT110: =AT70 -> 341.57442 | AU110: =AU70 -> 167.69984 | AV110: =AV70 -> 303.51209 | AW110: =AW70 -> 348.32193 | AX110: =AT110+AU110+AV110+AW110 -> 1161.1083
B111: Loss from discontinued operations | C111: 75 | D111: 24.7 | E111: -18.6 | F111: 2.1 | G111: -3.7 | H111: =D111+E111+F111+G111 -> 4.5 | I111: 9.879955 | J111: 11.431372 | K111: 0.519801 | L111: -0.01781 | M111: =I111+J111+K111+L111 -> 21.813318 | N111: 0 | O111: 0 | P111: =P93 -> 0 | Q111: =Q93 -> 0 | R111: =N111+O111+P111+Q111 -> 0 | S111: =H111 -> 4.5 | T111: =M111 -> 21.813318 | U111: =N111 -> 0 | V111: =O111 -> 0 | W111: =P111 -> 0 | X111: =Q111 -> 0 | Y111: =U111+V111+W111+X111 -> 0 | Z111: =Z93 -> 0 | AA111: 0 | AB111: =AB93 -> 0 | AC111: =AC93 -> 0 | AD111: =Z111+AA111+AB111+AC111 -> 0 | AE111: =AE93 -> 0 | AF111: 0 | AG111: =AG93 -> 0 | AH111: =AH93 -> 0 | AI111: =AE111+AF111+AG111+AH111 -> 0 | AJ111: =AJ93 -> 0 | AK111: =AK93 -> 0 | AL111: =AL93 -> 0 | AM111: =AM93 -> 0 | AN111: =AJ111+AK111+AL111+AM111 -> 0 | AO111: =AO93 -> 0 | AP111: =AP93 -> 0 | AQ111: =AQ93 -> 0 | AR111: =AR93 -> 0 | AS111: =AO111+AP111+AQ111+AR111 -> 0 | AT111: =AT93 -> 0 | AU111: =AU93 -> 0 | AV111: =AV93 -> 0 | AW111: =AW93 -> 0 | AX111: =AT111+AU111+AV111+AW111 -> 0
B112: Restructuring expenses | C112: 11 | D112: =D94 -> 1.4 | E112: =E94 -> 32.7 | F112: =F94 -> 1 | G112: =G94 -> -1.6 | H112: =D112+E112+F112+G112 -> 33.5 | I112: =I94 -> 5.7604681 | J112: =J94 -> -0.4 | K112: =K94 -> 0.1 | L112: =L94 -> 0.3 | M112: =I112+J112+K112+L112 -> 5.7604681 | N112: =N94 -> 0 | O112: =O94 -> 0.2 | P112: =P94 -> 2.3 | Q112: =Q94 -> -0.2 | R112: =N112+O112+P112+Q112 -> 2.3 | S112: =H112 -> 33.5 | T112: =M112 -> 5.7604681 | U112: =N112 -> 0 | V112: =O112 -> 0.2 | W112: =P112 -> 2.3 | X112: =Q112 -> -0.2 | Y112: =U112+V112+W112+X112 -> 2.3 | Z112: =Z94 -> 0.9 | AA112: =AA94 -> 8.8 | AB112: =AB94 -> 2.5 | AC112: =AC94 -> 10.2 | AD112: =Z112+AA112+AB112+AC112 -> 22.4 | AE112: =AE94 -> 2.9 | AF112: =AF94 -> 6 | AG112: =AG94 -> 5.4 | AH112: =AH94 -> 9.3 | AI112: =AE112+AF112+AG112+AH112 -> 23.6 | AJ112: =AJ94 -> 4.2 | AK112: =AK94 -> 6.8 | AL112: =AL94 -> 0 | AM112: =AM94 -> 0 | AN112: =AJ112+AK112+AL112+AM112 -> 11 | AO112: =AO94 -> 0 | AP112: =AP94 -> 0 | AQ112: =AQ94 -> 0 | AR112: =AR94 -> 0 | AS112: =AO112+AP112+AQ112+AR112 -> 0 | AT112: =AT94 -> 0 | AU112: =AU94 -> 0 | AV112: =AV94 -> 0 | AW112: =AW94 -> 0 | AX112: =AT112+AU112+AV112+AW112 -> 0
B113: Impairment losses on goodwill and intangible assets | C113: 0 | D113: =D95 -> 0 | E113: =E95 -> 0 | F113: =F95 -> 0 | G113: =G95 -> 0 | H113: =D113+E113+F113+G113 -> 0 | I113: =I95 -> 0 | J113: =J95 -> 0 | K113: =K95 -> 0 | L113: =L95 -> 198.1 | M113: =I113+J113+K113+L113 -> 198.1 | N113: =N95 -> 0 | O113: =O95 -> 0 | P113: =P95 -> 0 | Q113: =Q95 -> 0 | R113: =N113+O113+P113+Q113 -> 0 | S113: =H113 -> 0 | T113: =M113 -> 198.1 | U113: =N113 -> 0 | V113: =O113 -> 0 | W113: =P113 -> 0 | X113: =Q113 -> 0 | Y113: =U113+V113+W113+X113 -> 0 | Z113: =Z95 -> 0 | AA113: =AA95 -> 0 | AB113: =AB95 -> 0 | AC113: =AC95 -> 0 | AD113: =Z113+AA113+AB113+AC113 -> 0 | AE113: =AE95 -> 0 | AF113: =AF95 -> 0 | AG113: =AG95 -> 6.7 | AH113: =AH95 -> 0 | AI113: =AE113+AF113+AG113+AH113 -> 6.7 | AJ113: =AJ95 -> 0 | AK113: =AK95 -> 1.8 | AL113: =AL95 -> 0 | AM113: =AM95 -> 0 | AN113: =AJ113+AK113+AL113+AM113 -> 1.8 | AO113: =AO95 -> 0 | AP113: =AP95 -> 0 | AQ113: =AQ95 -> 0 | AR113: =AR95 -> 0 | AS113: =AO113+AP113+AQ113+AR113 -> 0 | AT113: =AT95 -> 0 | AU113: =AU95 -> 0 | AV113: =AV95 -> 0 | AW113: =AW95 -> 0 | AX113: =AT113+AU113+AV113+AW113 -> 0
B114: Expenses related to M&A activities | C114: =C96 -> -4.7 | D114: =D96 -> 0 | E114: =E96 -> 0 | F114: =F96 -> 0.6 | G114: =G96 -> 0 | H114: =D114+E114+F114+G114 -> 0.6 | I114: =I96 -> 0 | J114: =J96 -> 0 | K114: =K96 -> 0 | L114: =L96 -> 0.3 | M114: =I114+J114+K114+L114 -> 0.3 | N114: =N96 -> 0.2 | O114: =O96 -> 2.5 | P114: =P96 -> 15.8 | Q114: =Q96 -> 15.4 | R114: =N114+O114+P114+Q114 -> 33.9 | S114: =H114 -> 0.6 | T114: =M114 -> 0.3 | U114: =N114 -> 0.2 | V114: =O114 -> 2.5 | W114: =P114 -> 15.8 | X114: =Q114 -> 15.4 | Y114: =U114+V114+W114+X114 -> 33.9 | Z114: 23.9 | AA114: 12.2 | AB114: =4.5-2.2 -> 2.3 | AC114: =13.2+29.6 -> 42.8 | AD114: =Z114+AA114+AB114+AC114 -> 81.2 | AE114: 0.3 | AF114: 2 | AG114: 3.9 | AH114: =9.7 -> 9.7 | AI114: =AE114+AF114+AG114+AH114 -> 15.9 | AJ114: -0.1 | AK114: 0.6 | AL114: =AL96 -> 0 | AM114: =AM96 -> 0 | AN114: =AJ114+AK114+AL114+AM114 -> 0.5 | AO114: =AO96 -> 0 | AP114: =AP96 -> 0 | AQ114: =AQ96 -> 0 | AR114: =AR96 -> 0 | AS114: =AO114+AP114+AQ114+AR114 -> 0 | AT114: =AT96 -> 0 | AU114: =AU96 -> 0 | AV114: =AV96 -> 0 | AW114: =AW96 -> 0 | AX114: =AT114+AU114+AV114+AW114 -> 0
B115: PPA | C115: ='3. Segment Build'!C95 -> 48.112759 | D115: ='3. Segment Build'!D95 -> 12.549801 | E115: ='3. Segment Build'!E95 -> 12.549668 | F115: ='3. Segment Build'!F95 -> 12.345254 | G115: ='3. Segment Build'!G95 -> 12.07249 | H115: =D115+E115+F115+G115 -> 49.517213 | I115: ='3. Segment Build'!I95 -> 11.880657 | J115: ='3. Segment Build'!J95 -> 10.475376 | K115: ='3. Segment Build'!K95 -> 9.9001815 | L115: ='3. Segment Build'!L95 -> 10.031722 | M115: =I115+J115+K115+L115 -> 42.287937 | N115: ='3. Segment Build'!N95 -> 10.6 | O115: ='3. Segment Build'!O95 -> 10.744667 | P115: ='3. Segment Build'!P95 -> 10.744667 | Q115: ='3. Segment Build'!Q95 -> 10.510667 | R115: =N115+O115+P115+Q115 -> 42.6 | S115: =H115 -> 49.517213 | T115: =M115 -> 42.287937 | U115: =N115 -> 10.6 | V115: =O115 -> 10.744667 | W115: =P115 -> 10.744667 | X115: =Q115 -> 10.510667 | Y115: =U115+V115+W115+X115 -> 42.6 | Z115: ='3. Segment Build'!Z95 -> 10.7 | AA115: ='3. Segment Build'!AA95 -> 10.7 | AB115: ='3. Segment Build'!AB95 -> 10.8 | AC115: ='3. Segment Build'!AC95 -> 10.6 | AD115: =Z115+AA115+AB115+AC115 -> 42.8 | AE115: ='3. Segment Build'!AE95 -> 10.5 | AF115: ='3. Segment Build'!AF95 -> 11 | AG115: ='3. Segment Build'!AG95 -> 40.5 | AH115: ='3. Segment Build'!AH95 -> 9.2 | AI115: =AE115+AF115+AG115+AH115 -> 71.2 | AJ115: ='3. Segment Build'!AJ95 -> 9.2 | AK115: ='3. Segment Build'!AK95 -> 9 | AL115: ='3. Segment Build'!AL95 -> 9 | AM115: ='3. Segment Build'!AM95 -> 9 | AN115: =AJ115+AK115+AL115+AM115 -> 36.2 | AO115: ='3. Segment Build'!AO95 -> 9 | AP115: ='3. Segment Build'!AP95 -> 9 | AQ115: ='3. Segment Build'!AQ95 -> 9 | AR115: ='3. Segment Build'!AR95 -> 9 | AS115: =AO115+AP115+AQ115+AR115 -> 36 | AT115: ='3. Segment Build'!AT95 -> 9 | AU115: ='3. Segment Build'!AU95 -> 9 | AV115: ='3. Segment Build'!AV95 -> 9 | AW115: ='3. Segment Build'!AW95 -> 9 | AX115: =AT115+AU115+AV115+AW115 -> 36
B116: Expenses related to certain legal proceedings | C116: 0 | D116: =D97 -> 0 | E116: =E97 -> 0 | F116: =F97 -> 0 | G116: =G97 -> 0 | H116: =D116+E116+F116+G116 -> 0 | I116: =I97 -> 0 | J116: =J97 -> 3.9 | K116: =K97 -> 0 | L116: =L97 -> 0 | M116: =I116+J116+K116+L116 -> 3.9 | N116: =N97 -> 0 | O116: =O97 -> 0 | P116: =P97 -> 0 | Q116: =Q97 -> 3.3 | R116: =N116+O116+P116+Q116 -> 3.3 | S116: =H116 -> 0 | T116: =M116 -> 3.9 | U116: =N116 -> 0 | V116: =O116 -> 0 | W116: =P116 -> 0 | X116: =Q116 -> 3.3 | Y116: =U116+V116+W116+X116 -> 3.3 | Z116: =Z97 -> 0 | AA116: =AA97 -> 0 | AB116: =AB97 -> 1.4 | AC116: =AC97 -> 2.2 | AD116: =Z116+AA116+AB116+AC116 -> 3.6 | AE116: =AE97 -> -0.7 | AF116: =AF97 -> -1.2 | AG116: =AG97 -> 0.8 | AH116: =AH97 -> 4.6 | AI116: =AE116+AF116+AG116+AH116 -> 3.5 | AJ116: =AJ97 -> 0 | AK116: =AK97 -> 0.2 | AL116: =AL97 -> 0 | AM116: =AM97 -> 0 | AN116: =AJ116+AK116+AL116+AM116 -> 0.2 | AO116: =AO97 -> 0 | AP116: =AP97 -> 0 | AQ116: =AQ97 -> 0 | AR116: =AR97 -> 0 | AS116: =AO116+AP116+AQ116+AR116 -> 0 | AT116: =AT97 -> 0 | AU116: =AU97 -> 0 | AV116: =AV97 -> 0 | AW116: =AW97 -> 0 | AX116: =AT116+AU116+AV116+AW116 -> 0
B117: Share-based payments | C117: 0 | D117: =D98 -> 0 | E117: =E98 -> 0 | F117: =F98 -> 0 | G117: =G98 -> 0 | H117: =D117+E117+F117+G117 -> 0 | I117: =I98 -> 0 | J117: =J98 -> 0 | K117: =K98 -> 0 | L117: =L98 -> 0 | M117: =I117+J117+K117+L117 -> 0 | N117: =N98 -> 0 | O117: =O98 -> 0 | P117: =P98 -> 0 | Q117: =Q98 -> 47.9 | R117: =N117+O117+P117+Q117 -> 47.9 | S117: =H117 -> 0 | T117: =M117 -> 0 | U117: =N117 -> 0 | V117: =O117 -> 0 | W117: =P117 -> 0 | X117: =Q117 -> 47.9 | Y117: =U117+V117+W117+X117 -> 47.9 | Z117: =Z98 -> 3.4 | AA117: =AA98 -> 6.1 | AB117: =AB98 -> 1.3 | AC117: =AC98 -> 4.5 | AD117: =Z117+AA117+AB117+AC117 -> 15.3 | AE117: =AE98 -> 5 | AF117: =AF98 -> 5.9 | AG117: =AG98 -> 1.7 | AH117: =AH98 -> 2.4 | AI117: =AE117+AF117+AG117+AH117 -> 15 | AJ117: =AJ98 -> 4.6 | AK117: =AK98 -> -1.7 | AL117: =AL98 -> 4 | AM117: =AM98 -> 4 | AN117: =AJ117+AK117+AL117+AM117 -> 10.9 | AO117: =AO98 -> 4 | AP117: =AP98 -> 4 | AQ117: =AQ98 -> 4 | AR117: =AR98 -> 4 | AS117: =AO117+AP117+AQ117+AR117 -> 16 | AT117: =AT98 -> 4 | AU117: =AU98 -> 4 | AV117: =AV98 -> 4 | AW117: =AW98 -> 4 | AX117: =AT117+AU117+AV117+AW117 -> 16
...

Sheet 3. Segment Build
B1: Amer Sports, Inc.
B2: Segment earnings build
B3: $ millions, FY ending Saturday closest to December 31
C5: 44196 | D5: 44286 | E5: 44377 | F5: 44469 | G5: 44561 | H5: 44561 | I5: =DATE(YEAR(D5)+1,MONTH(D5),DAY(D5)) -> 44651 | J5: =DATE(YEAR(E5)+1,MONTH(E5),DAY(E5)) -> 44742 | K5: =DATE(YEAR(F5)+1,MONTH(F5),DAY(F5)) -> 44834 | L5: =DATE(YEAR(G5)+1,MONTH(G5),DAY(G5)) -> 44926 | M5: =DATE(YEAR(H5)+1,MONTH(H5),DAY(H5)) -> 44926 | N5: =DATE(YEAR(I5)+1,MONTH(I5),DAY(I5)) -> 45016 | O5: =DATE(YEAR(J5)+1,MONTH(J5),DAY(J5)) -> 45107 | P5: =DATE(YEAR(K5)+1,MONTH(K5),DAY(K5)) -> 45199 | ... R5: =DATE(YEAR(M5)+1,MONTH(M5),DAY(M5)) -> 45291 | S5: ='2. Consolidated'!S5 -> 44561 | T5: ='2. Consolidated'!T5 -> 44926 | U5: ='2. Consolidated'!U5 -> 45016 | V5: ='2. Consolidated'!V5 -> 45107 | W5: ='2. Consolidated'!W5 -> 45199 | X5: ='2. Consolidated'!X5 -> 45291 | Y5: ='2. Consolidated'!Y5 -> 45291 | Z5: =DATE(YEAR(N5)+1,MONTH(N5),DAY(N5)) -> 45382 | AA5: =DATE(YEAR(O5)+1,MONTH(O5),DAY(O5)) -> 45473 | AB5: =DATE(YEAR(P5)+1,MONTH(P5),DAY(P5)) -> 45565 | AC5: =DATE(YEAR(Q5)+1,MONTH(Q5),DAY(Q5)) -> 45657 | AD5: =DATE(YEAR(R5)+1,MONTH(R5),DAY(R5)) -> 45657 | AE5: =DATE(YEAR(Z5)+1,MONTH(Z5),DAY(Z5)) -> 45747 | AF5: =DATE(YEAR(AA5)+1,MONTH(AA5),DAY(AA5)) -> 45838 | AG5: =DATE(YEAR(AB5)+1,MONTH(AB5),DAY(AB5)) -> 45930 | AH5: =DATE(YEAR(AC5)+1,MONTH(AC5),DAY(AC5)) -> 46022 | AI5: =DATE(YEAR(AD5)+1,MONTH(AD5),DAY(AD5)) -> 46022 | AJ5: =DATE(YEAR(AE5)+1,MONTH(AE5),DAY(AE5)) -> 46112 | AK5: =DATE(YEAR(AF5)+1,MONTH(AF5),DAY(AF5)) -> 46203 | AL5: =DATE(YEAR(AG5)+1,MONTH(AG5),DAY(AG5)) -> 46295 | ... AX5: =DATE(YEAR(AS5)+1,MONTH(AS5),DAY(AS5)) -> 47118
C6: ='2. Consolidated'!C6 -> FY20 | D6: ='2. Consolidated'!D6 -> Q1'21 | E6: ='2. Consolidated'!E6 -> Q2'21 | F6: ='2. Consolidated'!F6 -> Q3'21 | G6: ='2. Consolidated'!G6 -> Q4'21 | H6: ='2. Consolidated'!H6 -> FY21 | I6: ='2. Consolidated'!I6 -> Q1'22 | J6: ='2. Consolidated'!J6 -> Q2'22 | ... AX6: ='2. Consolidated'!AX6 -> FY28E
B7: Revenue Summary
B9: Technical Apparel | C9: =C107 -> 685.4 | D9: =D107 -> 203.17 | E9: =E107 -> 147.84 | F9: =F107 -> 238.58 | G9: =G107 -> 361.12 | H9: =D9+E9+F9+G9 -> 950.71 | I9: =I107 -> 261.32972 | J9: =J107 -> 169.81807 | K9: =K107 -> 227.67329 | L9: =L107 -> 436.69865 | M9: =I9+J9+K9+L9 -> 1095.5197 | N9: =N107 -> 355.2 | O9: =O107 -> 303 | P9: =P107 -> 384.6 | Q9: =Q107 -> 550 | R9: =N9+O9+P9+Q9 -> 1592.8 | S9: =S107 -> 961.51 | T9: =T107 -> 1108.1197 | U9: =U107 -> 359.4 | V9: =V107 -> 306.8 | W9: =W107 -> 388.8 | X9: =X107 -> 559.2 | Y9: =U9+V9+W9+X9 -> 1614.2 | Z9: =Z107 -> 517 | AA9: =AA107 -> 412.1 | AB9: =AB107 -> 520 | AC9: =AC107 -> 745.2 | AD9: =Z9+AA9+AB9+AC9 -> 2194.3 | AE9: =AE107 -> 663.8 | AF9: =AF107 -> 508.9 | AG9: =AG107 -> 683.3 | AH9: =AH107 -> 999.8 | AI9: =AE9+AF9+AG9+AH9 -> 2855.8 | AJ9: =AJ107 -> 885 | AK9: =AK107 -> 674.2 | AL9: =AL107 -> 845.13423 | AM9: =AM107 -> 1203.7695 | AN9: =AJ9+AK9+AL9+AM9 -> 3608.1037 | AO9: =AO107 -> 1033.9418 | AP9: =AP107 -> 786.57171 | AQ9: =AQ107 -> 968.92629 | AR9: =AR107 -> 1396.5097 | AS9: =AO9+AP9+AQ9+AR9 -> 4185.9496 | AT9: =AT107 -> 1180.8667 | AU9: =AU107 -> 900.59705 | AV9: =AV107 -> 1098.7355 | AW9: =AW107 -> 1602.3149 | AX9: =AT9+AU9+AV9+AW9 -> 4782.5141
B10: Outdoor Performance | C10: =C213 -> 1091.6 | D10: =D213 -> 261.81 | E10: =E213 -> 211.6 | F10: =F213 -> 347.5 | G10: =G213 -> 414.7 | H10: =D10+E10+F10+G10 -> 1235.61 | I10: =I213 -> 263.36717 | J10: =J213 -> 246.39547 | K10: =K213 -> 392.71821 | L10: =L213 -> 513.72745 | M10: =I10+J10+K10+L10 -> 1416.2083 | N10: =N213 -> 377.5 | O10: =O213 -> 273.6 | P10: =P213 -> 493.2 | Q10: =Q213 -> 523.4 | R10: =N10+O10+P10+Q10 -> 1667.7 | S10: =S213 -> 1240.61 | T10: =T213 -> 1422.0083 | U10: =U213 -> 379 | V10: =V213 -> 274.9 | W10: =W213 -> 494.5 | X10: =X213 -> 525.6 | Y10: =U10+V10+W10+X10 -> 1674 | Z10: =Z213 -> 401.8 | AA10: =AA213 -> 305.7 | AB10: =AB213 -> 533.6 | AC10: =AC213 -> 594.4 | AD10: =Z10+AA10+AB10+AC10 -> 1835.5 | AE10: =AE213 -> 502.4 | AF10: =AF213 -> 413.7 | AG10: =AG213 -> 723.5 | AH10: =AH213 -> 764.1 | AI10: =AE10+AF10+AG10+AH10 -> 2403.7 | AJ10: =AJ213 -> 713.6 | AK10: =AK213 -> 568.5 | AL10: =AL213 -> 914.1418 | AM10: =AM213 -> 908.42474 | AN10: =AJ10+AK10+AL10+AM10 -> 3104.6665 | AO10: =AO213 -> 844.5097 | AP10: =AP213 -> 680.82402 | AQ10: =AQ213 -> 1061.1429 | AR10: =AR213 -> 1056.0349 | AS10: =AO10+AP10+AQ10+AR10 -> 3642.5115 | AT10: =AT213 -> 980.41311 | AU10: =AU213 -> 798.44732 | AV10: =AV213 -> 1226.3805 | AW10: =AW213 -> 1226.2139 | AX10: =AT10+AU10+AV10+AW10 -> 4231.4549
B11: Ball & Racquet Sports | C11: =C316 -> 669.2 | D11: =D316 -> 198.51 | E11: =E316 -> 238.37 | F11: =F316 -> 220.05 | G11: =G316 -> 223.18 | H11: =D11+E11+F11+G11 -> 880.11 | I11: =I316 -> 284.46072 | J11: =J316 -> 277.20805 | K11: =K316 -> 226.79153 | L11: =L316 -> 248.28526 | M11: =I11+J11+K11+L11 -> 1036.7455 | N11: =N316 -> 317.6 | O11: =O316 -> 280.2 | P11: =P316 -> 268.5 | Q11: =Q316 -> 241.5 | R11: =N11+O11+P11+Q11 -> 1107.8 | S11: =S316 -> 883.61 | T11: =T316 -> 1040.7455 | U11: =U316 -> 318.6 | V11: =V316 -> 281.1 | W11: =W316 -> 269.8 | X11: =X316 -> 242.6 | Y11: =U11+V11+W11+X11 -> 1112.1 | Z11: =Z316 -> 273.6 | AA11: =AA316 -> 283.5 | AB11: =AB316 -> 300.2 | AC11: =AC316 -> 296.2 | AD11: =Z11+AA11+AB11+AC11 -> 1153.5 | AE11: =AE316 -> 306.3 | AF11: =AF316 -> 313.7 | AG11: =AG316 -> 349.5 | AH11: =AH316 -> 337.2 | AI11: =AE11+AF11+AG11+AH11 -> 1306.7 | AJ11: =AJ316 -> 346.9 | AK11: =AK316 -> 389.9 | AL11: =AL316 -> 386.08739 | AM11: =AM316 -> 368.09967 | AN11: =AJ11+AK11+AL11+AM11 -> 1490.9871 | AO11: =AO316 -> 378.88433 | AP11: =AP316 -> 425.87303 | AQ11: =AQ316 -> 421.26367 | AR11: =AR316 -> 400.99638 | AS11: =AO11+AP11+AQ11+AR11 -> 1627.0174 | AT11: =AT316 -> 403.63131 | AU11: =AU316 -> 453.88159 | AV11: =AV316 -> 449.05854 | AW11: =AW316 -> 427.19308 | AX11: =AT11+AU11+AV11+AW11 -> 1733.7645
B12: Total | C12: =SUM(C9:C11) -> 2446.2 | D12: =SUM(D9:D11) -> 663.49 | E12: =SUM(E9:E11) -> 597.81 | F12: =SUM(F9:F11) -> 806.13 | G12: =SUM(G9:G11) -> 999 | H12: =SUM(H9:H11) -> 3066.43 | I12: =SUM(I9:I11) -> 809.15761 | J12: =SUM(J9:J11) -> 693.42159 | ... AX12: =SUM(AX9:AX11) -> 10747.734
B13: % chg. y/y | C13: -- | D13: -- | E13: -- | F13: -- | G13: -- | H13: =H12/C12-1 -> 0.25354836 | I13: =I12/D12-1 -> 0.21954756 | J13: =J12/E12-1 -> 0.15993641 | K13: =K12/F12-1 -> 0.05092606 | L13: =L12/G12-1 -> 0.19991127 | M13: =M12/H12-1 -> 0.15720026 | N13: =N12/I12-1 -> 0.29801658 | O13: =O12/J12-1 -> 0.23561195 | ... R13: =R12/M12-1 -> 0.23103636 | S13: -- | T13: =T12/S12-1 -> 0.15722166 | U13: -- | V13: -- | W13: -- | X13: -- | Y13: =Y12/T12-1 -> 0.23227549 | Z13: =Z12/U12-1 -> 0.12809839 | AA13: =AA12/V12-1 -> 0.16052388 | AB13: =AB12/W12-1 -> 0.17405255 | AC13: =AC12/X12-1 -> 0.23233389 | AD13: =AD12/Y12-1 -> 0.17794241 | AE13: =AE12/Z12-1 -> 0.23490439 | AF13: =AF12/AA12-1 -> 0.2346949 | ... AX13: =AX12/AS12-1 -> 0.13666734
B14: % chg. y/y ex-FX | Z14: =(Z109*U107+Z215*U213+Z318*U316)/U12 -> 0.14293832 | AA14: =(AA109*V107+AA215*V213+AA318*V316)/V12 -> 0.18413363 | AB14: =(AB109*W107+AB215*W213+AB318*W316)/W12 -> 0.16731003 | AC14: =(AC109*X107+AC215*X213+AC318*X316)/X12 -> 0.24044757 | AD14: =SUMPRODUCT(Z14:AC14,U12:X12)/Y12 -> 0.18681717 | AE14: =(AE109*Z107+AE215*Z213+AE318*Z316)/Z12 -> 0.2647682 | AF14: =(AF109*AA107+AF215*AA213+AF318*AA316)/AA12 -> 0.21980725 | AG14: =(AG109*AB107+AG215*AB213+AG318*AB316)/AB12 -> 0.28460437 | AH14: =(AH109*AC107+AH215*AC213+AH318*AC316)/AC12 -> 0.26639186 | AI14: =SUMPRODUCT(AE14:AH14,Z12:AC12)/AD12 -> 0.26177605 | AJ14: =(AJ109*AE107+AJ215*AE213+AJ318*AE316)/AE12 -> 0.26155334 | AK14: =(AK109*AF107+AK215*AF213+AK318*AF316)/AF12 -> 0.29794678
B15: FX impact | Z15: =Z13-Z14 -> -0.014839924 | AA15: =AA13-AA14 -> -0.023609759 | AB15: =AB13-AB14 -> 0.0067425202 | AC15: =AC13-AC14 -> -0.0081136809 | AD15: =SUMPRODUCT(Z15:AC15,U12:X12)/Y12 -> -0.0088747585 | AE15: =AE13-AE14 -> -0.029863804 | AF15: =AF13-AF14 -> 0.014887646 | AG15: =AG13-AG14 -> 0.012706899 | AH15: =AH13-AH14 -> 0.018056119 | AI15: =SUMPRODUCT(AE15:AH15,Z12:AC12)/AD12 -> 0.0050230934 | AJ15: =AJ13-AJ14 -> 0.059669066 | AK15: =AK13-AK14 -> 0.022606487
B17: Technical Apparel % chg. y/y | C17: -- | D17: -- | E17: -- | F17: -- | G17: -- | H17: =H9/C9-1 -> 0.38708783 | I17: =I9/D9-1 -> 0.28626137 | J17: =J9/E9-1 -> 0.14866118 | K17: =K9/F9-1 -> -0.045715096 | L17: =L9/G9-1 -> 0.20928957 | M17: =M9/H9-1 -> 0.15231746 | N17: =N9/I9-1 -> 0.35920245 | O17: =O9/J9-1 -> 0.78426243 | ... R17: =R9/M9-1 -> 0.45392178 | S17: -- | T17: =T9/S9-1 -> 0.15247863 | U17: -- | V17: -- | W17: -- | X17: -- | Y17: =Y9/T9-1 -> 0.45670179 | Z17: =Z9/U9-1 -> 0.43850863 | AA17: =AA9/V9-1 -> 0.34322034 | AB17: =AB9/W9-1 -> 0.33744856 | AC17: =AC9/X9-1 -> 0.33261803 | AD17: =AD9/Y9-1 -> 0.35937306 | AE17: =AE9/Z9-1 -> 0.28394584 | AF17: =AF9/AA9-1 -> 0.23489444 | ... AX17: =AX9/AS9-1 -> 0.14251595
B18: Outdoor Performance % chg. y/y | C18: -- | D18: -- | E18: -- | F18: -- | G18: -- | H18: =H10/C10-1 -> 0.13192561 | I18: =I10/D10-1 -> 0.0059477216 | J18: =J10/E10-1 -> 0.16443983 | K18: =K10/F10-1 -> 0.13012434 | L18: =L10/G10-1 -> 0.23879298 | M18: =M10/H10-1 -> 0.14616125 | N18: =N10/I10-1 -> 0.43336011 | O18: =O10/J10-1 -> 0.11041004 | ... R18: =R10/M10-1 -> 0.17758101 | S18: -- | T18: =T10/S10-1 -> 0.14621702 | U18: -- | V18: -- | W18: -- | X18: -- | Y18: =Y10/T10-1 -> 0.17720832 | Z18: =Z10/U10-1 -> 0.060158311 | AA18: =AA10/V10-1 -> 0.11204074 | AB18: =AB10/W10-1 -> 0.079069767 | AC18: =AC10/X10-1 -> 0.13089802 | AD18: =AD10/Y10-1 -> 0.096475508 | AE18: =AE10/Z10-1 -> 0.25037332 | AF18: =AF10/AA10-1 -> 0.35328754 | ... AX18: =AX10/AS10-1 -> 0.16168608
B19: Ball & Racquet Sports % chg. y/y | C19: -- | D19: -- | E19: -- | F19: -- | G19: -- | H19: =H11/C11-1 -> 0.31516736 | I19: =I11/D11-1 -> 0.43297928 | J19: =J11/E11-1 -> 0.16293179 | K19: =K11/F11-1 -> 0.030636333 | L19: =L11/G11-1 -> 0.11248884 | M19: =M11/H11-1 -> 0.1779727 | N19: =N11/I11-1 -> 0.11649863 | O19: =O11/J11-1 -> 0.010793158 | ... R19: =R11/M11-1 -> 0.068536055 | S19: -- | T19: =T11/S11-1 -> 0.1778336 | U19: -- | V19: -- | W19: -- | X19: -- | Y19: =Y11/T11-1 -> 0.068560898 | Z19: =Z11/U11-1 -> -0.14124294 | AA19: =AA11/V11-1 -> 0.0085378869 | AB19: =AB11/W11-1 -> 0.11267606 | AC19: =AC11/X11-1 -> 0.22093982 | AD19: =AD11/Y11-1 -> 0.037226868 | AE19: =AE11/Z11-1 -> 0.11951754 | AF19: =AF11/AA11-1 -> 0.10652557 | ... AX19: =AX11/AS11-1 -> 0.065609073
B21: Technical Apparel % of total | C21: =C9/C12 -> 0.28018968 | D21: =D9/D12 -> 0.30621411 | E21: =E9/E12 -> 0.24730265 | F21: =F9/F12 -> 0.29595723 | G21: =G9/G12 -> 0.36148148 | H21: =H9/H12 -> 0.31003806 | I21: =I9/I12 -> 0.32296517 | J21: =J9/J12 -> 0.24489873 | ... AX21: =AX9/AX12 -> 0.44497885
B22: Outdoor Performance % of total | C22: =C10/C12 -> 0.44624315 | D22: =D10/D12 -> 0.39459525 | E22: =E10/E12 -> 0.35395862 | F22: =F10/F12 -> 0.43107191 | G22: =G10/G12 -> 0.41511512 | H22: =H10/H12 -> 0.4029474 | I22: =I10/I12 -> 0.32548316 | J22: =J10/J12 -> 0.35533285 | ... AX22: =AX10/AX12 -> 0.39370672
B23: Ball & Racquet Sports % of total | C23: =C11/C12 -> 0.27356717 | D23: =D11/D12 -> 0.29919064 | E23: =E11/E12 -> 0.39873873 | F23: =F11/F12 -> 0.27297086 | G23: =G11/G12 -> 0.2234034 | H23: =H11/H12 -> 0.28701454 | I23: =I11/I12 -> 0.35155168 | J23: =J11/J12 -> 0.39976842 | ... AX23: =AX11/AX12 -> 0.16131443
B25: Americas | C25: 984 | D25: =D143+D244+D341 -> 250.54613 | E25: =E143+E244+E341 -> 256.33191 | F25: =F143+F244+F341 -> 323.40969 | G25: =G143+G244+G341 -> 422.71765 | H25: =D25+E25+F25+G25 -> 1253.0054 | I25: =I143+I244+I341 -> 350.53477 | J25: =J143+J244+J341 -> 321.1189 | K25: =K143+K244+K341 -> 356.04838 | L25: =L143+L244+L341 -> 476.64035 | M25: =I25+J25+K25+L25 -> 1504.3424 | N25: 409.6 | O25: 365.9 | P25: =P143+P244+P341 -> 450.8 | Q25: =1726.8-N25-O25-P25 -> 500.5 | R25: =N25+O25+P25+Q25 -> 1726.8 | W25: 455 | X25: 507.9 | Y25: 1745.6 | Z25: 414.9 | AA25: 371.9 | AB25: 487.8 | AC25: 584.4 | AD25: =Z25+AA25+AB25+AC25 -> 1859 | AE25: 464.7 | AF25: 395.4 | AG25: 574.2 | AH25: 691.3 | AI25: =AE25+AF25+AG25+AH25 -> 2125.6 | AJ25: 548.8 | AK25: 496.7 | AL25: =AG25*(1+AL30) -> 677.556 | AM25: =AH25*(1+AM30) -> 788.082 | AN25: =AJ25+AK25+AL25+AM25 -> 2511.138 | AO25: =AJ25*(1+AO30) -> 620.144 | AP25: =AK25*(1+AP30) -> 561.271 | AQ25: =AL25*(1+AQ30) -> 765.63828 | AR25: =AM25*(1+AR30) -> 890.53266 | AS25: =AO25+AP25+AQ25+AR25 -> 2837.5859 | AT25: =AO25*(1+AT30) -> 688.35984 | AU25: =AP25*(1+AU30) -> 623.01081 | AV25: =AQ25*(1+AV30) -> 849.85849 | AW25: =AR25*(1+AW30) -> 988.49125 | AX25: =AT25+AU25+AV25+AW25 -> 3149.7204
B26: EMEA | C26: 1080.4 | D26: =D145+D246+D343 -> 283.35581 | E26: =E145+E246+E343 -> 224.34001 | F26: =F145+F246+F343 -> 329.44857 | G26: =G145+G246+G343 -> 388.48056 | H26: =D26+E26+F26+G26 -> 1225.6249 | I26: =I145+I246+I343 -> 278.11113 | J26: =J145+J246+J343 -> 239.6025 | K26: =K145+K246+K343 -> 296.69924 | L26: =L145+L246+L343 -> 456.38479 | M26: =I26+J26+K26+L26 -> 1270.7977 | N26: 356.9 | O26: 230.1 | P26: =P145+P246+P343 -> 411.6 | Q26: =1450.3-N26-O26-P26 -> 451.7 | R26: =N26+O26+P26+Q26 -> 1450.3 | W26: 413 | X26: 454.6 | Y26: 1457.6 | Z26: 360.6 | AA26: 233.1 | AB26: 428.5 | AC26: 491.2 | AD26: =Z26+AA26+AB26+AC26 -> 1513.4 | AE26: 404.9 | AF26: 276.2 | AG26: 528.5 | AH26: 596.2 | AI26: =AE26+AF26+AG26+AH26 -> 1805.8 | AJ26: 512.8 | AK26: 332.3 | AL26: =AG26*(1+AL31) -> 602.49 | AM26: =AH26*(1+AM31) -> 667.744 | AN26: =AJ26+AK26+AL26+AM26 -> 2115.334 | AO26: =AJ26*(1+AO31) -> 579.464 | AP26: =AK26*(1+AP31) -> 375.499 | AQ26: =AL26*(1+AQ31) -> 680.8137 | AR26: =AM26*(1+AR31) -> 754.55072 | AS26: =AO26+AP26+AQ26+AR26 -> 2390.3274 | AT26: =AO26*(1+AT31) -> 643.20504 | AU26: =AP26*(1+AU31) -> 416.80389 | AV26: =AQ26*(1+AV31) -> 755.70321 | AW26: =AR26*(1+AW31) -> 837.5513 | AX26: =AT26+AU26+AV26+AW26 -> 2653.2634
B27: Greater China | C27: 202.3 | D27: =D147+D248+D345 -> 81.710141 | E27: =E147+E248+E345 -> 71.554778 | F27: =F147+F248+F345 -> 100.43374 | G27: =G147+G248+G345 -> 119.16376 | H27: =D27+E27+F27+G27 -> 372.86241 | I27: =I147+I248+I345 -> 130.59833 | J27: =J147+J248+J345 -> 83.33387 | K27: =K147+K248+K345 -> 139.85286 | L27: =L147+L248+L345 -> 169.99065 | M27: =I27+J27+K27+L27 -> 523.77571 | N27: 205.6 | O27: 187.6 | P27: =P147+P248+P345 -> 199.9 | Q27: =841.4-N27-O27-P27 -> 248.3 | R27: =N27+O27+P27+Q27 -> 841.4 | W27: 200.5 | X27: 249.5 | Y27: 844.8 | Z27: 311.6 | AA27: 289.6 | AB27: 312.9 | AC27: 383.9 | AD27: =Z27+AA27+AB27+AC27 -> 1298 | AE27: 446 | AF27: 410.2 | AG27: 461.5 | AH27: 544.2 | AI27: =AE27+AF27+AG27+AH27 -> 1861.9 | AJ27: 644.5 | AK27: 556 | AL27: =AG27*(1+AL32) -> 553.8 | AM27: =AH27*(1+AM32) -> 669.366 | AN27: =AJ27+AK27+AL27+AM27 -> 2423.666 | AO27: =AJ27*(1+AO32) -> 754.065 | AP27: =AK27*(1+AP32) -> 650.52 | AQ27: =AL27*(1+AQ32) -> 647.946 | AR27: =AM27*(1+AR32) -> 783.15822 | AS27: =AO27+AP27+AQ27+AR27 -> 2835.6892 | AT27: =AO27*(1+AT32) -> 874.7154 | AU27: =AP27*(1+AU32) -> 754.6032 | AV27: =AQ27*(1+AV32) -> 751.61736 | AW27: =AR27*(1+AW32) -> 908.46354 | AX27: =AT27+AU27+AV27+AW27 -> 3289.3995
B28: APAC | C28: 179.6 | D28: =D149+D250+D347 -> 47.932674 | E28: =E149+E250+E347 -> 45.636748 | F28: =F149+F250+F347 -> 52.881846 | G28: =G149+G250+G347 -> 68.564066 | H28: =D28+E28+F28+G28 -> 215.01533 | I28: =I149+I250+I347 -> 50.625918 | J28: =J149+J250+J347 -> 48.69249 | K28: =K149+K250+K347 -> 54.766539 | L28: =L149+L250+L347 -> 95.794137 | M28: =I28+J28+K28+L28 -> 249.87908 | N28: 78.2 | O28: 73.2 | P28: =P149+P250+P347 -> 84 | Q28: =350-N28-O28-P28 -> 114.6 | R28: =N28+O28+P28+Q28 -> 350 | W28: 84.6 | X28: 115.5 | Y28: 352.4 | Z28: 105.4 | AA28: 106.8 | AB28: 124.6 | AC28: 176 | AD28: =Z28+AA28+AB28+AC28 -> 512.8 | AE28: 156.9 | AF28: 154.5 | AG28: 192.1 | AH28: 269.4 | AI28: =AE28+AF28+AG28+AH28 -> 772.9 | AJ28: 239.4 | AK28: 247.6 | AL28: =AL12-AL25-AL26-AL27 -> 311.51742 | AM28: =AM12-AM25-AM26-AM27 -> 355.10192 | AN28: =AJ28+AK28+AL28+AM28 -> 1153.6193 | AO28: =AO12-AO25-AO26-AO27 -> 303.66284 | AP28: =AP12-AP25-AP26-AP27 -> 305.97876 | AQ28: =AQ12-AQ25-AQ26-AQ27 -> 356.93484 | AR28: =AR12-AR25-AR26-AR27 -> 425.29941 | AS28: =AO28+AP28+AQ28+AR28 -> 1391.8758 | AT28: =AT12-AT25-AT26-AT27 -> 358.63086 | AU28: =AU12-AU25-AU26-AU27 -> 358.50806 | AV28: =AV12-AV25-AV26-AV27 -> 416.99546 | AW28: =AW12-AW25-AW26-AW27 -> 521.21581 | AX28: =AT28+AU28+AV28+AW28 -> 1655.3502
B30: Americas % chg. y/y | C30: -- | D30: -- | E30: -- | F30: -- | G30: -- | H30: =H25/C25-1 -> 0.27337945 | I30: =I25/D25-1 -> 0.39908277 | J30: =J25/E25-1 -> 0.25274649 | K30: =K25/F25-1 -> 0.10092056 | L30: =L25/G25-1 -> 0.12756197 | M30: =M25/H25-1 -> 0.20058734 | N30: =N25/I25-1 -> 0.16850033 | O30: =O25/J25-1 -> 0.13945334 | ... R30: =R25/M25-1 -> 0.14787697 | Z30: =Z25/N25-1 -> 0.012939453 | AA30: =AA25/O25-1 -> 0.016397923 | AB30: =AB25/W25-1 -> 0.072087912 | AC30: =AC25/X25-1 -> 0.1506202 | AD30: =AD25/Y25-1 -> 0.064963336 | AE30: =AE25/Z25-1 -> 0.12002892 | AF30: =AF25/AA25-1 -> 0.063189029 | AG30: =AG25/AB25-1 -> 0.17712177 | AH30: =AH25/AC25-1 -> 0.18292266 | AI30: =AI25/AD25-1 -> 0.14341044 | ... AK30: =AK25/AF25-1 -> 0.25619626 | AL30: 0.18 | AM30: 0.14 | AN30: =AN25/AI25-1 -> 0.18137843 | AO30: 0.13 | AP30: 0.13 | AQ30: 0.13 | AR30: 0.13 | AS30: =AS25/AN25-1 -> 0.13 | AT30: 0.11 | AU30: 0.11 | AV30: 0.11 | AW30: 0.11 | AX30: =AX25/AS25-1 -> 0.11
B31: EMEA % chg. y/y | C31: -- | D31: -- | E31: -- | F31: -- | G31: -- | H31: =H26/C26-1 -> 0.13441776 | I31: =I26/D26-1 -> -0.018509166 | J31: =J26/E26-1 -> 0.068032847 | K31: =K26/F26-1 -> -0.099406509 | L31: =L26/G26-1 -> 0.17479441 | M31: =M26/H26-1 -> 0.036856876 | N31: =N26/I26-1 -> 0.28329997 | O31: =O26/J26-1 -> -0.03965945 | ... R31: =R26/M26-1 -> 0.14125171 | Z31: =Z26/N26-1 -> 0.01036705 | AA31: =AA26/O26-1 -> 0.01303781 | AB31: =AB26/W26-1 -> 0.037530266 | AC31: =AC26/X26-1 -> 0.080510339 | AD31: =AD26/Y26-1 -> 0.038282108 | AE31: =AE26/Z26-1 -> 0.1228508 | AF31: =AF26/AA26-1 -> 0.18489918 | AG31: =AG26/AB26-1 -> 0.23337223 | AH31: =AH26/AC26-1 -> 0.21376221 | AI31: =AI26/AD26-1 -> 0.19320735 | ... AK31: =AK26/AF26-1 -> 0.20311369 | AL31: 0.14 | AM31: 0.12 | AN31: =AN26/AI26-1 -> 0.17141101 | AO31: 0.13 | AP31: 0.13 | AQ31: 0.13 | AR31: 0.13 | AS31: =AS26/AN26-1 -> 0.13 | AT31: 0.11 | AU31: 0.11 | AV31: 0.11 | AW31: 0.11 | AX31: =AX26/AS26-1 -> 0.11
B32: Greater China % chg. y/y | C32: -- | D32: -- | E32: -- | F32: -- | G32: -- | H32: =H27/C27-1 -> 0.84311622 | I32: =I27/D27-1 -> 0.59831241 | J32: =J27/E27-1 -> 0.16461642 | K32: =K27/F27-1 -> 0.39248884 | L32: =L27/G27-1 -> 0.42652979 | M32: =M27/H27-1 -> 0.40474258 | N32: =N27/I27-1 -> 0.5742927 | O32: =O27/J27-1 -> 1.2511855 | ... R32: =R27/M27-1 -> 0.6064128 | Z32: =Z27/N27-1 -> 0.5155642 | AA32: =AA27/O27-1 -> 0.54371002 | AB32: =AB27/W27-1 -> 0.5605985 | AC32: =AC27/X27-1 -> 0.53867735 | AD32: =AD27/Y27-1 -> 0.53645833 | AE32: =AE27/Z27-1 -> 0.43132221 | AF32: =AF27/AA27-1 -> 0.41643646 | AG32: =AG27/AB27-1 -> 0.47491211 | AH32: =AH27/AC27-1 -> 0.41755666 | AI32: =AI27/AD27-1 -> 0.4344376 | ... AK32: =AK27/AF27-1 -> 0.35543637 | AL32: 0.2 | AM32: 0.23 | AN32: =AN27/AI27-1 -> 0.30171653 | AO32: 0.17 | AP32: 0.17 | AQ32: 0.17 | AR32: 0.17 | AS32: =AS27/AN27-1 -> 0.17 | AT32: 0.16 | AU32: 0.16 | AV32: 0.16 | AW32: 0.16 | AX32: =AX27/AS27-1 -> 0.16
B33: APAC (excl. China) % chg. y/y | C33: -- | D33: -- | E33: -- | F33: -- | G33: -- | H33: =H28/C28-1 -> 0.19719006 | I33: =I28/D28-1 -> 0.056188046 | J33: =J28/E28-1 -> 0.066957916 | K33: =K28/F28-1 -> 0.035639696 | L33: =L28/G28-1 -> 0.39714785 | M33: =M28/H28-1 -> 0.16214541 | N33: =N28/I28-1 -> 0.54466335 | O33: =O28/J28-1 -> 0.50331191 | ... R33: =R28/M28-1 -> 0.40067746 | Z33: =Z28/N28-1 -> 0.34782609 | AA33: =AA28/O28-1 -> 0.45901639 | AB33: =AB28/W28-1 -> 0.47281324 | AC33: =AC28/X28-1 -> 0.52380952 | AD33: =AD28/Y28-1 -> 0.45516459 | AE33: =AE28/Z28-1 -> 0.4886148 | AF33: =AF28/AA28-1 -> 0.44662921 | AG33: =AG28/AB28-1 -> 0.54173355 | AH33: =AH28/AC28-1 -> 0.53068182 | AI33: =AI28/AD28-1 -> 0.50721529 | ... AX33: =AX28/AS28-1 -> 0.18929443
B35: Americas % of total | C35: =C25/C$12 -> 0.40225656 | D35: =D25/D$12 -> 0.37761855 | E35: =E25/E$12 -> 0.42878491 | F35: =F25/F$12 -> 0.40118801 | G35: =G25/G$12 -> 0.42314079 | H35: =H25/H$12 -> 0.40862025 | I35: =I25/I$12 -> 0.43320951 | J35: =J25/J$12 -> 0.46309331 | ... R35: =R25/R$12 -> 0.39530252 | Z35: =Z25/Z$12 -> 0.34795371 | AA35: =AA25/AA$12 -> 0.37141716 | AB35: =AB25/AB$12 -> 0.3603191 | AC35: =AC25/AC$12 -> 0.35725639 | AD35: =AD25/AD$12 -> 0.35865182 | AE35: =AE25/AE$12 -> 0.31558574 | AF35: =AF25/AF$12 -> 0.31982529 | AG35: =AG25/AG$12 -> 0.32693731 | ... AX35: =AX25/AX$12 -> 0.29305903
B36: EMEA % of total | C36: =C26/C$12 -> 0.44166462 | D36: =D26/D$12 -> 0.42706869 | E36: =E26/E$12 -> 0.37526976 | F36: =F26/F$12 -> 0.40867921 | G36: =G26/G$12 -> 0.38886943 | H36: =H26/H$12 -> 0.39969116 | I36: =I26/I$12 -> 0.34370452 | J36: =J26/J$12 -> 0.34553655 | ... R36: =R26/R$12 -> 0.33200559 | Z36: =Z26/Z$12 -> 0.3024153 | AA36: =AA26/AA$12 -> 0.23279736 | AB36: =AB26/AB$12 -> 0.31651647 | AC36: =AC26/AC$12 -> 0.30028121 | AD36: =AD26/AD$12 -> 0.29197615 | AE36: =AE26/AE$12 -> 0.27497453 | AF36: =AF26/AF$12 -> 0.22340856 | AG36: =AG26/AG$12 -> 0.3009167 | ... AX36: =AX26/AX$12 -> 0.24686725
B37: Greater China % of total | C37: =C27/C$12 -> 0.082699697 | D37: =D27/D$12 -> 0.12315203 | E37: =E27/E$12 -> 0.11969485 | F37: =F27/F$12 -> 0.12458752 | G37: =G27/G$12 -> 0.11928304 | H37: =H27/H$12 -> 0.12159495 | I37: =I27/I$12 -> 0.16140036 | J37: =J27/J$12 -> 0.12017778 | ... R37: =R27/R$12 -> 0.19261498 | Z37: =Z27/Z$12 -> 0.2613217 | AA37: =AA27/AA$12 -> 0.28922401 | AB37: =AB27/AB$12 -> 0.2311272 | AC37: =AC27/AC$12 -> 0.23468639 | AD37: =AD27/AD$12 -> 0.25041962 | AE37: =AE27/AE$12 -> 0.30288625 | AF37: =AF27/AF$12 -> 0.33179649 | AG37: =AG27/AG$12 -> 0.26276832 | ... AX37: =AX27/AX$12 -> 0.30605518
B38: APAC (excl. China) % of total | C38: =C28/C$12 -> 0.073419998 | D38: =D28/D$12 -> 0.072243251 | E38: =E28/E$12 -> 0.076339888 | F38: =F28/F$12 -> 0.06559965 | G38: =G28/G$12 -> 0.068632698 | H38: =H28/H$12 -> 0.070119107 | I38: =I28/I$12 -> 0.062566201 | J38: =J28/J$12 -> 0.070220614 | ... R38: =R28/R$12 -> 0.080122702 | Z38: =Z28/Z$12 -> 0.088393157 | AA38: =AA28/AA$12 -> 0.10666134 | AB38: =AB28/AB$12 -> 0.092037229 | AC38: =AC28/AC$12 -> 0.10759262 | AD38: =AD28/AD$12 -> 0.098933112 | AE38: =AE28/AE$12 -> 0.10655348 | AF38: =AF28/AF$12 -> 0.12496967 | AG38: =AG28/AG$12 -> 0.10937767 | ... AX38: =AX28/AX$12 -> 0.15401854
B40: Wholesale | C40: =C101+C207+C310 -> 1916.2 | D40: =D101+D207+D310 -> 498.54 | E40: =E101+E207+E310 -> 433.54 | F40: =F101+F207+F310 -> 634.21 | G40: =G101+G207+G310 -> 669.93 | H40: =D40+E40+F40+G40 -> 2236.22 | I40: =I101+I207+I310 -> 566.72195 | J40: =J101+J207+J310 -> 504.54427 | K40: =K101+K207+K310 -> 638.84542 | L40: =L101+L207+L310 -> 792.27256 | M40: =I40+J40+K40+L40 -> 2502.3842 | N40: =N101+N207+N310 -> 702.7 | O40: =O101+O207+O310 -> 535.9 | P40: =P101+P207+P310 -> 812.5 | Q40: =Q101+Q207+Q310 -> 758.5 | R40: =N40+O40+P40+Q40 -> 2809.6 | S40: =S101+S207+S310 -> 2236.22 | T40: =T101+T207+T310 -> 2502.3842 | U40: =U101+U207+U310 -> 702.7 | V40: =V101+V207+V310 -> 535.9 | W40: =W101+W207+W310 -> 812.5 | X40: =X101+X207+X310 -> 758.5 | Y40: =U40+V40+W40+X40 -> 2809.6 | Z40: =Z101+Z207+Z310 -> 694.5 | AA40: =AA101+AA207+AA310 -> 544.5 | AB40: =AB101+AB207+AB310 -> 874 | AC40: =AC101+AC207+AC310 -> 803.3 | AD40: =Z40+AA40+AB40+AC40 -> 2916.3 | AE40: 779.9 | AF40: 595.4 | AG40: 1033.8 | AH40: 948.4 | AI40: =AE40+AF40+AG40+AH40 -> 3357.5 | AJ40: 944 | AK40: 735.8 | AL40: =AL101+AL207+AL310 -> 1165.458 | AM40: =AM101+AM207+AM310 -> 1042.915 | AN40: =AJ40+AK40+AL40+AM40 -> 3888.173 | AO40: =AO101+AO207+AO310 -> 1034.271 | AP40: =AP101+AP207+AP310 -> 804.158 | AQ40: =AQ101+AQ207+AQ310 -> 1280.1745 | AR40: =AR101+AR207+AR310 -> 1146.6177 | AS40: =AO40+AP40+AQ40+AR40 -> 4265.2212 | AT40: =AT101+AT207+AT310 -> 1125.0821 | AU40: =AU101+AU207+AU310 -> 870.9614 | AV40: =AV101+AV207+AV310 -> 1397.606 | AW40: =AW101+AW207+AW310 -> 1252.9057 | AX40: =AT40+AU40+AV40+AW40 -> 4646.5552
B41: DTC | C41: =C104+C210+C313 -> 530 | D41: =D104+D210+D313 -> 164.95 | E41: =E104+E210+E313 -> 164.27 | F41: =F104+F210+F313 -> 171.92 | G41: =G104+G210+G313 -> 329.07 | H41: =D41+E41+F41+G41 -> 830.21 | I41: =I104+I210+I313 -> 242.43566 | J41: =J104+J210+J313 -> 188.87732 | K41: =K104+K210+K313 -> 208.3376 | L41: =L104+L210+L313 -> 406.43879 | M41: =I41+J41+K41+L41 -> 1046.0894 | N41: =N104+N210+N313 -> 347.6 | O41: =O104+O210+O313 -> 320.9 | P41: =P104+P210+P313 -> 333.8 | Q41: =Q104+Q210+Q313 -> 556.4 | R41: =N41+O41+P41+Q41 -> 1558.7 | S41: =S104+S210+S313 -> 849.51 | T41: =T104+T210+T313 -> 1068.4894 | U41: =U104+U210+U313 -> 354.3 | V41: =V104+V210+V313 -> 326.9 | W41: =W104+W210+W313 -> 340.6 | X41: =X104+X210+X313 -> 568.9 | Y41: =U41+V41+W41+X41 -> 1590.7 | Z41: =Z104+Z210+Z313 -> 497.9 | AA41: =AA104+AA210+AA313 -> 456.8 | AB41: =AB104+AB210+AB313 -> 479.8 | AC41: =AC104+AC210+AC313 -> 832.5 | AD41: =Z41+AA41+AB41+AC41 -> 2267 | AE41: 692.6 | AF41: 640.9 | AG41: 722.5 | AH41: 1152.7 | AI41: =AE41+AF41+AG41+AH41 -> 3208.7 | AJ41: 1001.5 | AK41: 896.8 | AL41: =AL104+AL210+AL313 -> 979.90542 | AM41: =AM104+AM210+AM313 -> 1437.3789 | AN41: =AJ41+AK41+AL41+AM41 -> 4315.5843 | AO41: =AO104+AO210+AO313 -> 1223.0648 | AP41: =AP104+AP210+AP313 -> 1089.1108 | AQ41: =AQ104+AQ210+AQ313 -> 1171.1584 | AR41: =AR104+AR210+AR313 -> 1706.9233 | AS41: =AO41+AP41+AQ41+AR41 -> 5190.2572 | AT41: =AT104+AT210+AT313 -> 1439.829 | AU41: =AU104+AU210+AU313 -> 1281.9646 | AV41: =AV104+AV210+AV313 -> 1376.5685 | AW41: =AW104+AW210+AW313 -> 2002.8162 | AX41: =AT41+AU41+AV41+AW41 -> 6101.1783
B42: Ecommerce | C42: 274 | D42: 83.42209 | E42: 83.51704 | F42: 77.091911 | G42: 160.38432 | H42: =D42+E42+F42+G42 -> 404.41536 | I42: 113.2049 | J42: 97.541879 | K42: 92.693385 | L42: 210.31628 | M42: =I42+J42+K42+L42 -> 513.75645 | N42: 154.52854 | O42: 140.47242 | P42: 150.4 | Q42: =718.4-N42-O42-P42 -> 272.99904 | R42: =N42+O42+P42+Q42 -> 718.4
B43: Retail | C43: 257 | D43: 81.535481 | E43: 80.737995 | F43: 94.826903 | G43: 168.68469 | H43: =D43+E43+F43+G43 -> 425.78506 | I43: 129.23075 | J43: 91.335439 | K43: 115.64422 | L43: 196.12251 | M43: =I43+J43+K43+L43 -> 532.33292 | N43: 192.97448 | O43: 180.5436 | P43: 183.4 | Q43: =840.4-N43-O43-P43 -> 283.48193 | R43: =N43+O43+P43+Q43 -> 840.4
B44: Total | C44: =C40+C41 -> 2446.2 | D44: =D40+D41 -> 663.49 | E44: =E40+E41 -> 597.81 | F44: =F40+F41 -> 806.13 | G44: =G40+G41 -> 999 | H44: =H40+H41 -> 3066.43 | I44: =I40+I41 -> 809.15761 | J44: =J40+J41 -> 693.42159 | ... AX44: =AX40+AX41 -> 10747.734
B45: % chg. y/y | C45: -- | D45: -- | E45: -- | F45: -- | G45: -- | H45: =H44/C44-1 -> 0.25354836 | I45: =I44/D44-1 -> 0.21954756 | J45: =J44/E44-1 -> 0.15993641 | K45: =K44/F44-1 -> 0.05092606 | L45: =L44/G44-1 -> 0.19991127 | M45: =M44/H44-1 -> 0.15720026 | N45: =N44/I44-1 -> 0.29801658 | O45: =O44/J44-1 -> 0.23561195 | ... R45: =R44/M44-1 -> 0.23103636 | S45: -- | T45: =T44/S44-1 -> 0.15722166 | U45: -- | V45: -- | W45: -- | X45: -- | Y45: =Y44/T44-1 -> 0.23227549 | Z45: =Z44/U44-1 -> 0.12809839 | AA45: =AA44/V44-1 -> 0.16052388 | AB45: =AB44/W44-1 -> 0.17405255 | AC45: =AC44/X44-1 -> 0.23233389 | AD45: =AD44/Y44-1 -> 0.17794241 | AE45: =AE44/Z44-1 -> 0.23490439 | AF45: =AF44/AA44-1 -> 0.2346949 | ... AX45: =AX44/AS44-1 -> 0.13666734
B47: Wholesale % chg. y/y | C47: -- | D47: -- | E47: -- | F47: -- | G47: -- | H47: =H40/C40-1 -> 0.16700762 | I47: =I40/D40-1 -> 0.13676325 | J47: =J40/E40-1 -> 0.16377789 | K47: =K40/F40-1 -> 0.0073089671 | L47: =L40/G40-1 -> 0.18261992 | M47: =M40/H40-1 -> 0.11902416 | N47: =N40/I40-1 -> 0.23993785 | O47: =O40/J40-1 -> 0.062146644 | ... R47: =R40/M40-1 -> 0.12276924 | S47: -- | T47: =T40/S40-1 -> 0.11902416 | U47: -- | V47: -- | W47: -- | X47: -- | Y47: =Y40/T40-1 -> 0.12276924 | Z47: =Z40/U40-1 -> -0.011669276 | AA47: =AA40/V40-1 -> 0.01604777 | AB47: =AB40/W40-1 -> 0.075692308 | AC47: =AC40/X40-1 -> 0.059063942 | AD47: =AD40/Y40-1 -> 0.037976936 | AE47: =AE40/Z40-1 -> 0.12296616 | AF47: =AF40/AA40-1 -> 0.093480257 | ... AX47: =AX40/AS40-1 -> 0.089405447
B48: DTC % chg. y/y | C48: -- | D48: -- | E48: -- | F48: -- | G48: -- | H48: =H41/C41-1 -> 0.56643396 | I48: =I41/D41-1 -> 0.4697524 | J48: =J41/E41-1 -> 0.149798 | K48: =K41/F41-1 -> 0.21182878 | L48: =L41/G41-1 -> 0.23511348 | M48: =M41/H41-1 -> 0.26002984 | N48: =N41/I41-1 -> 0.43378248 | O48: =O41/J41-1 -> 0.69898643 | ... R48: =R41/M41-1 -> 0.49002565 | S48: -- | T48: =T41/S41-1 -> 0.25777139 | U48: -- | V48: -- | W48: -- | X48: -- | Y48: =Y41/T41-1 -> 0.48873731 | Z48: =Z41/U41-1 -> 0.40530624 | AA48: =AA41/V41-1 -> 0.39736923 | AB48: =AB41/W41-1 -> 0.40869055 | AC48: =AC41/X41-1 -> 0.46335033 | AD48: =AD41/Y41-1 -> 0.42515874 | AE48: =AE41/Z41-1 -> 0.39104238 | AF48: =AF41/AA41-1 -> 0.40302102 | ... AX48: =AX41/AS41-1 -> 0.17550596
B49: Ecommerce % chg. y/y | C49: -- | D49: -- | E49: -- | F49: -- | G49: -- | H49: =H42/C42-1 -> 0.47596847 | I49: =I42/D42-1 -> 0.35701352 | J49: =J42/E42-1 -> 0.16792787 | K49: =K42/F42-1 -> 0.20237499 | L49: =L42/G42-1 -> 0.31132695 | M49: =M42/H42-1 -> 0.27036829 | N49: =N42/I42-1 -> 0.365034 | O49: =O42/J42-1 -> 0.44012419 | ... R49: =R42/M42-1 -> 0.39832794
B50: Retail % chg. y/y | C50: -- | D50: -- | E50: -- | F50: -- | G50: -- | H50: =H43/C43-1 -> 0.65675123 | I50: =I43/D43-1 -> 0.58496341 | J50: =J43/E43-1 -> 0.13125722 | K50: =K43/F43-1 -> 0.21952966 | L50: =L43/G43-1 -> 0.16265746 | M50: =M43/H43-1 -> 0.2502386 | N50: =N43/I43-1 -> 0.49325504 | O50: =O43/J43-1 -> 0.97670912 | ... R50: =R43/M43-1 -> 0.5787113
B52: Wholesale % of total | C52: =C40/C44 -> 0.78333742 | D52: =D40/D44 -> 0.75139038 | E52: =E40/E44 -> 0.7252137 | F52: =F40/F44 -> 0.78673415 | G52: =G40/G44 -> 0.6706006 | H52: =H40/H44 -> 0.72925845 | I52: =I40/I44 -> 0.70038512 | J52: =J40/J44 -> 0.72761546 | ... R52: =R40/R44 -> 0.64317927 | S52: =S40/S12 -> 0.72469724 | T52: =T40/T12 -> 0.70077648 | U52: =U40/U12 -> 0.66480605 | V52: =V40/V12 -> 0.62111729 | W52: =W40/W12 -> 0.70462232 | X52: =X40/X12 -> 0.57141781 | Y52: =Y40/Y12 -> 0.63850192 | Z52: =Z40/Z44 -> 0.58243878 | AA52: =AA40/AA44 -> 0.54379307 | AB52: =AB40/AB44 -> 0.64559019 | AC52: =AC40/AC44 -> 0.4910747 | AD52: =AD40/AD44 -> 0.56263384 | AE52: =AE40/AE44 -> 0.52964346 | AF52: =AF40/AF44 -> 0.48159832 | AG52: =AG40/AG44 -> 0.58862381 | ... AX52: =AX40/AX44 -> 0.43232885
B53: DTC % of total | C53: =C41/C44 -> 0.21666258 | D53: =D41/D44 -> 0.24860962 | E53: =E41/E44 -> 0.2747863 | F53: =F41/F44 -> 0.21326585 | G53: =G41/G44 -> 0.3293994 | H53: =H41/H44 -> 0.27074155 | I53: =I41/I44 -> 0.29961488 | J53: =J41/J44 -> 0.27238454 | ... R53: =R41/R44 -> 0.35682073 | S53: =S41/S12 -> 0.27530276 | T53: =T41/T12 -> 0.29922352 | U53: =U41/U12 -> 0.33519395 | V53: =V41/V12 -> 0.37888271 | W53: =W41/W12 -> 0.29537768 | X53: =X41/X12 -> 0.42858219 | Y53: =Y41/Y12 -> 0.36149808 | Z53: =Z41/Z44 -> 0.41756122 | AA53: =AA41/AA44 -> 0.45620693 | AB53: =AB41/AB44 -> 0.35440981 | AC53: =AC41/AC44 -> 0.5089253 | AD53: =AD41/AD44 -> 0.43736616 | AE53: =AE41/AE44 -> 0.47035654 | AF53: =AF41/AF44 -> 0.51840168 | AG53: =AG41/AG44 -> 0.41137619 | ... AX53: =AX41/AX44 -> 0.56767115
B54: Ecommerce % of total | C54: =C42/C44 -> 0.11201047 | D54: =D42/D44 -> 0.12573225 | E54: =E42/E44 -> 0.13970499 | F54: =F42/F44 -> 0.095632107 | G54: =G42/G44 -> 0.16054487 | H54: =H42/H44 -> 0.13188475 | I54: =I42/I44 -> 0.13990464 | J54: =J42/J44 -> 0.1406675 | ... R54: =R42/R44 -> 0.16445757
B55: Retail % of total | C55: =C43/C44 -> 0.10506091 | D55: =D43/D44 -> 0.12288879 | E55: =E43/E44 -> 0.13505628 | F55: =F43/F44 -> 0.11763227 | G55: =G43/G44 -> 0.16885354 | H55: =H43/H44 -> 0.13885367 | I55: =I43/I44 -> 0.15971024 | J55: =J43/J44 -> 0.13171704 | ... R55: =R43/R44 -> 0.19238605
B57: Arc'teryx | C57: =C164 -> 547.7 | D57: =D164 -> 162.23 | E57: =E164 -> 128.66595 | F57: =F164 -> 195.25699 | G57: =G164 -> 296.9076 | H57: =H164 -> 783.1 | I57: =I164 -> 222.19433 | J57: =J164 -> 147.38778 | ... R57: =R164 -> 1443.5
B58: Peak Performance | C58: =C167 -> 137.7 | D58: =D167 -> 40.950224 | E58: =E167 -> 19.166554 | F58: =F167 -> 43.319646 | G58: =G167 -> 64.212533 | H58: =H167 -> 167.6 | I58: =I167 -> 39.135388 | J58: =J167 -> 22.430293 | ... R58: =R167 -> 149.3
B59: Salomon | C59: =C265 -> 852.1 | D59: =D265 -> 223.09872 | E59: =E265 -> 191.49684 | F59: =F265 -> 259.52016 | G59: =G265 -> 287.5504 | H59: =H265 -> 961.66612 | I59: =I265 -> 203.14905 | J59: =J265 -> 225.4593 | ... R59: =R265 -> 1311.8
B60: Atomic | C60: =C268 -> 194.6 | D60: =D268 -> 27.630845 | E60: =E268 -> 10.814109 | F60: =F268 -> 68.993481 | G60: =G268 -> 110.58081 | H60: =H268 -> 218.01925 | I60: =I268 -> 50.365186 | J60: =J268 -> 10.479888 | ... R60: =R268 -> 305.6
B61: Other (Armada and Enve) | C61: =C271 -> 44.9 | D61: =D271 -> 11.104315 | E61: =E271 -> 9.3068039 | F61: =F271 -> 18.996281 | G61: =G271 -> 16.593951 | H61: =H271 -> 56.00135 | I61: =I271 -> 9.8529354 | J61: =J271 -> 10.56897 | ... R61: =R271 -> 50.4
B62: Ball & Racquet Sports | C62: =C349 -> 669.2 | D62: =D349 -> 198.55475 | E62: =E349 -> 238.44345 | F62: =F349 -> 220.10384 | G62: =G349 -> 223.11604 | H62: =H349 -> 880.21808 | I62: =I349 -> 285.19512 | J62: =J349 -> 276.56567 | ... R62: =R349 -> 1107.8314
B64: Profit Summary
B65: Adjusted EBIT (Consolidated) | C65: =C172+C276+C362+C71 -> 179.6 | D65: =D172+D276+D362+D71 -> 57.791 | E65: =E172+E276+E362+E71 -> -5.422 | F65: =F172+F276+F362+F71 -> 116.513 | G65: =G172+G276+G362+G71 -> 101.726 | H65: =H172+H276+H362+H71 -> 270.608 | I65: =I172+I276+I362+I71 -> 67.138574 | J65: =J172+J276+J362+J71 -> 3.0481514 | ... AI65: =AI172+AI276+AI362+AI71 -> 837.7 | AJ65: =AJ178+AJ282+AJ368+AJ75 -> 339 | AK65: =AK178+AK282+AK368+AK75 -> 208.4 | AL65: =AL178+AL282+AL368+AL75 -> 302.82169 | AM65: =AM178+AM282+AM368+AM75 -> 340.66681 | AN65: =AN178+AN282+AN368+AN75 -> 1190.8885 | AO65: =AO178+AO282+AO368+AO75 -> 411.6305 | AP65: =AP178+AP282+AP368+AP75 -> 204.74677 | AQ65: =AQ178+AQ282+AQ368+AQ75 -> 366.54223 | ... AX65: =AX178+AX282+AX368+AX75 -> 1648.9658
B66: % chg. y/y | C66: -- | D66: -- | E66: -- | F66: -- | G66: -- | H66: =H65/C65-1 -> 0.50672606 | I66: =I65/D65-1 -> 0.16174793 | J66: =J65/E65-1 -> -1.5621821 | K66: =K65/F65-1 -> -0.31166479 | L66: =L65/G65-1 -> 0.48044748 | M66: =M65/H65-1 -> 0.112261 | N66: =N65/I65-1 -> 1.1031129 | O66: =O65/J65-1 -> 5.8566148 | ... R66: =R65/M65-1 -> 0.43727269 | S66: =S65/C65-1 -> 0.50672606 | T66: =T65/S65-1 -> 0.112261 | U66: =U65/I65-1 -> 1.1031129 | V66: =V65/J65-1 -> 5.8566148 | W66: =W65/K65-1 -> 0.66458853 | X66: =X65/L65-1 -> -0.090305445 | Y66: =Y65/T65-1 -> 0.43727269 | Z66: =Z65/U65-1 -> -0.080736544 | AA66: =AA65/V65-1 -> 0.40191388 | AB66: =AB65/W65-1 -> 0.46067416 | AC66: =AC65/X65-1 -> 0.6270073 | AD66: =AD65/Y65-1 -> 0.33379565 | AE66: =AE65/Z65-1 -> 0.78890601 | AF66: =AF65/AA65-1 -> 1.3003413 | ... AX66: =AX65/AS65-1 -> 0.18209822
B67: % margin | C67: =C65/C12 -> 0.073419998 | D67: =D65/D12 -> 0.087101539 | E67: =E65/E12 -> -0.0090697713 | F67: =F65/F12 -> 0.14453376 | G67: =G65/G12 -> 0.10182783 | H67: =H65/H12 -> 0.08824855 | I67: =I65/I12 -> 0.08297342 | J67: =J65/J12 -> 0.0043958127 | ... AX67: =AX65/AX12 -> 0.15342451
B68: bps chg. y/y | C68: -- | D68: -- | E68: -- | F68: -- | G68: -- | H68: =(H67-C67)*100*100 -> 148.28551 | I68: =(I67-D67)*100*100 -> -41.281188 | J68: =(J67-E67)*100*100 -> 134.65584 | K68: =(K67-F67)*100*100 -> -498.67085 | L68: =(L67-G67)*100*100 -> 238.07088 | M68: =(M67-H67)*100*100 -> -34.270851 | N68: =(N67-I67)*100*100 -> 514.6436 | O68: =(O67-J67)*100*100 -> 199.97278 | ... R68: =(R67-M67)*100*100 -> 142.10195 | S68: -- | T68: =(T67-S67)*100*100 -> -34.072088 | U68: -- | V68: -- | W68: -- | X68: -- | Y68: =(Y67-T67)*100*100 -> 140.22097 | Z68: =(Z67-U67)*100*100 -> -247.29531 | AA68: =(AA67-V67)*100*100 -> 50.385009 | AB68: =(AB67-W67)*100*100 -> 282.64134 | AC68: =(AC67-X67)*100*100 -> 330.54321 | AD68: =(AD67-Y67)*100*100 -> 130.07565 | AE68: =(AE67-Z67)*100*100 -> 488.34913 | AF68: =(AF67-AA67)*100*100 -> 252.55552 | ... AX68: =(AX67-AS67)*100*100 -> 58.964731
B69: incremental margin | C69: -- | D69: -- | E69: -- | F69: -- | G69: -- | H69: =(H65-C65)/(H12-C12) -> 0.14673266 | I69: =(I65-D65)/(I12-D12) -> 0.064170575 | J69: =(J65-E65)/(J12-E12) -> 0.088589175 | K69: =(K65-F65)/(K12-F12) -> -0.88453897 | L69: =(L65-G65)/(L12-G12) -> 0.24472319 | M69: =(M65-H65)/(M12-H12) -> 0.063020704 | N69: =(N65-I65)/(N12-I12) -> 0.30712736 | O69: =(O65-J65)/(O12-J12) -> 0.10926687 | ... R69: =(R65-M65)/(R12-M12) -> 0.16053798 | S69: -- | T69: =(T65-S65)/(T12-S12) -> 0.062618011 | U69: -- | V69: -- | W69: -- | X69: -- | Y69: =(Y65-T65)/(Y12-T12) -> 0.15867987 | Z69: =(Z65-U65)/(Z12-U12) -> -0.084194978 | AA69: =(AA65-V65)/(AA12-V12) -> 0.060649819 | AB69: =(AB65-W65)/(AB12-W12) -> 0.3064275 | AC69: =(AC65-X65)/(AC12-X12) -> 0.27853437 | AD69: =(AD65-Y65)/(AD12-Y12) -> 0.1844189 | AE69: =(AE65-Z65)/(AE12-Z12) -> 0.36558372 | AF69: =(AF65-AA65)/(AF12-AA12) -> 0.16212766 | ... AX69: =(AX65-AS65)/(AX12-AS12) -> 0.19656923
B71: Corporate-level expenses | C71: -51.1 | D71: -10.209 | E71: -8.522 | F71: -5.787 | G71: -18.074 | H71: =D71+E71+F71+G71 -> -42.592 | I71: -11.85083 | J71: -9.3091059 | K71: -10.9 | L71: -16.9 | M71: =I71+J71+K71+L71 -> -48.959936 | N71: -18.8 | O71: -10 | P71: -20.5 | Q71: =-63.7-N71-O71-P71 -> -14.4 | R71: =N71+O71+P71+Q71 -> -63.7 | S71: =H71 -> -42.592 | T71: =M71 -> -48.959936 | U71: =N71 -> -18.8 | V71: =O71 -> -10 | W71: =P71 -> -20.5 | X71: =Q71 -> -14.4 | Y71: =U71+V71+W71+X71 -> -63.7 | Z71: -17.7 | AA71: -25.2 | AB71: -23.1 | AC71: -13.5 | AD71: =Z71+AA71+AB71+AC71 -> -79.5 | AE71: -19.6 | AF71: -34.3 | AG71: -38 | AH71: -34.5 | AI71: =AE71+AF71+AG71+AH71 -> -126.4
B72: Corporate level D&A ex-PPA | C72: 5.4 | D72: =D73-D71+D95-D95 -> 1.4576015 | E72: =E73-E71+E95-E95 -> 1.6546236 | F72: =F73-F71+F95-F95 -> 1.4952095 | G72: =G73-G71+G95-G95 -> 1.5288391 | H72: 5.8 | I72: =I73-I71+I95-I95 -> 1.5260617 | J72: =J73-J71+J95-J95 -> 3.2724441 | K72: =K73-K71+K95-K95 -> -0.34245028 | L72: =L73-L71+L95-L95 -> 2.4658317 | M72: =I72+J72+K72+L72 -> 6.9218872 | N72: 1.5 | O72: 1.6 | P72: 1.6 | Q72: =6.4-N72-O72-P72 -> 1.7 | R72: =N72+O72+P72+Q72 -> 6.4 | S72: =H72 -> 5.8 | T72: =M72 -> 6.9218872 | U72: =N72 -> 1.5 | V72: =O72 -> 1.6 | W72: =P72 -> 1.6 | X72: =Q72 -> 1.7 | Y72: =U72+V72+W72+X72 -> 6.4 | Z72: 1.6 | AA72: 1.9 | AB72: 1.2 | AC72: =6.2-Z72-AA72-AB72 -> 1.5 | AD72: =Z72+AA72+AB72+AC72 -> 6.2 | AE72: 1.4 | AF72: 3.3 | AG72: 7.7 | AH72: =16.3-AG72-AF72-AE72 -> 3.9 | AI72: =AE72+AF72+AG72+AH72 -> 16.3
B73: Corporate EBITDA | C73: =C71+C72 -> -45.7 | D73: -8.7513985 | E73: -6.8673764 | F73: -4.2917905 | G73: -16.545161 | H73: =H71+H72 -> -36.792 | I73: -10.324768 | J73: -6.0366618 | K73: -11.24245 | L73: -14.434168 | M73: =M71+M72 -> -42.038049 | N73: =N71+N72 -> -17.3 | O73: =O71+O72 -> -8.4 | P73: =P71+P72 -> -18.9 | Q73: =Q71+Q72 -> -12.7 | R73: =R71+R72 -> -57.3 | S73: =S71+S72 -> -36.792 | T73: =T71+T72 -> -42.038049 | ... AI73: =AI71+AI72 -> -110.1
B75: Corporate-level expenses (new) | AE75: =AE71-7.7 -> -27.3 | AF75: =AF71-10.8 -> -45.1 | AG75: =AG71-6.7 -> -44.7 | AH75: =AH71-12.8 -> -47.3 | AI75: =AE75+AF75+AG75+AH75 -> -164.4 | AJ75: -52 | AK75: -68.3 | AL75: -59.75 | AM75: -59.75 | AN75: =(AJ75+AK75+AL75+AM75) -> -239.8 | AO75: =AJ75-10 -> -62 | AP75: =AK75-10 -> -78.3 | AQ75: =AL75-10 -> -69.75 | AR75: =AM75-10 -> -69.75 | AS75: =AO75+AP75+AQ75+AR75 -> -279.8 | AT75: =AO75-10 -> -72 | AU75: =AP75-10 -> -88.3 | AV75: =AQ75-10 -> -79.75 | AW75: =AR75-10 -> -79.75 | AX75: =AT75+AU75+AV75+AW75 -> -319.8
B76: Corporate level D&A ex-PPA | AE76: =AE72 -> 1.4 | AF76: =AF72 -> 3.3 | AG76: =AG72 -> 7.7 | AH76: =AH72 -> 3.9 | AI76: =AE76+AF76+AG76+AH76 -> 16.3 | AJ76: 5.4 | AK76: 7.5 | AL76: 1.65 | AM76: 1.65 | AN76: =(AJ76+AK76+AL76+AM76) -> 16.2 | AO76: 1.65 | AP76: 1.65 | AQ76: 1.65 | AR76: 1.65 | AS76: =AO76+AP76+AQ76+AR76 -> 6.6 | AT76: 1.65 | AU76: 1.65 | AV76: 1.65 | AW76: 1.65 | AX76: =AT76+AU76+AV76+AW76 -> 6.6
B77: Corporate EBITDA (new) | AE77: =AE75+AE76 -> -25.9 | AF77: =AF75+AF76 -> -41.8 | AG77: =AG75+AG76 -> -37 | AH77: =AH75+AH76 -> -43.4 | AI77: =AI75+AI76 -> -148.1 | AJ77: =AJ75+AJ76 -> -46.6 | AK77: =AK75+AK76 -> -60.8 | AL77: =AL75+AL76 -> -58.1 | ... AX77: =AX75+AX76 -> -313.2
B79: Segment adjusted EBITDA | C79: =C376+C290+C186 -> 357.08724 | D79: =D376+D290+D186 -> 103.3677 | E79: =E376+E290+E186 -> 38.431693 | F79: =F376+F290+F186 -> 156.90959 | G79: =G376+G290+G186 -> 154.76021 | H79: =H376+H290+H186 -> 453.46919 | I79: =I376+I290+I186 -> 114.92349 | J79: =J376+J290+J186 -> 45.541555 | ... L79: =L376+L290+L186 -> 205.5804 | M79: =I79+J79+K79+L79 -> 494.99723 | N79: =N376+N290+N186 -> 199.9 | O79: =O376+O290+O186 -> 70.955333 | P79: =P376+P290+P186 -> 195.77 | Q79: =Q376+Q290+Q186 -> 201.57467 | R79: =N79+O79+P79+Q79 -> 668.2 | S79: =S376+S290+S186 -> 453.46919 | T79: =T376+T290+T186 -> 494.99723 | U79: =U376+U290+U186 -> 199.9 | V79: =V376+V290+V186 -> 70.955333 | W79: =W376+W290+W186 -> 195.77 | X79: =X376+X290+X186 -> 201.57467 | Y79: =U79+V79+W79+X79 -> 668.2 | Z79: =Z376+Z290+Z186 -> 197.7 | AA79: =AA376+AA290+AA186 -> 104.7 | AB79: =AB376+AB290+AB186 -> 277.3 | AC79: =AC376+AC290+AC186 -> 301.6 | AD79: =Z79+AA79+AB79+AC79 -> 881.3 | AE79: =AE376+AE290+AE186 -> 317.6 | AF79: =AF376+AF290+AF186 -> 168.8 | AG79: =AG376+AG290+AG186 -> 383.5 | AH79: =AH376+AH290+AH186 -> 390.9 | AI79: =AE79+AF79+AG79+AH79 -> 1260.8 | AJ79: =AJ389+AJ303+AJ199 -> 479 | AK79: =AK389+AK303+AK199 -> 372.7 | AL79: =AL389+AL303+AL199 -> 462.89419 | AM79: =AM389+AM303+AM199 -> 512.13931 | AN79: =AN389+AN303+AN199 -> 1826.7335 | AO79: =AO389+AO303+AO199 -> 576.2005 | AP79: =AP389+AP303+AP199 -> 394.85677 | AQ79: =AQ389+AQ303+AQ199 -> 553.57923 | ... AX79: =AX389+AX303+AX199 -> 2510.0446
B80: Corporate-level expenses excluding D&A | C80: =C73 -> -45.7 | D80: =D73 -> -8.7513985 | E80: =E73 -> -6.8673764 | F80: =F73 -> -4.2917905 | G80: =G73 -> -16.545161 | H80: =H73 -> -36.792 | I80: =I73 -> -10.324768 | J80: =J73 -> -6.0366618 | ... Q80: =Q73 -> -12.7 | R80: =N80+O80+P80+Q80 -> -57.3 | S80: =S73 -> -36.792 | T80: =T73 -> -42.038049 | U80: =U73 -> -17.3 | V80: =V73 -> -8.4 | W80: =W73 -> -18.9 | X80: =X73 -> -12.7 | Y80: =U80+V80+W80+X80 -> -57.3 | Z80: =Z73 -> -16.1 | AA80: =AA73 -> -23.3 | AB80: =AB73 -> -21.9 | AC80: =AC73 -> -12 | AD80: =Z80+AA80+AB80+AC80 -> -73.3 | AE80: =AE73 -> -18.2 | AF80: =AF73 -> -31 | AG80: =AG73 -> -30.3 | AH80: =AH73 -> -30.6 | AI80: =AE80+AF80+AG80+AH80 -> -110.1 | AJ80: =AJ77 -> -46.6 | AK80: =AK77 -> -60.8 | AL80: =AL77 -> -58.1 | AM80: =AM77 -> -58.1 | AN80: =AJ80+AK80+AL80+AM80 -> -223.6 | AO80: =AO77 -> -60.35 | AP80: =AP77 -> -76.65 | AQ80: =AQ77 -> -68.1 | AR80: =AR77 -> -68.1 | AS80: =AO80+AP80+AQ80+AR80 -> -273.2 | AT80: =AT77 -> -70.35 | AU80: =AU77 -> -86.65 | AV80: =AV77 -> -78.1 | AW80: =AW77 -> -78.1 | AX80: =AT80+AU80+AV80+AW80 -> -313.2
B81: Consolidated Adj. EBITDA (IFRS) | C81: =C79+C80 -> 311.38724 | D81: =D79+D80 -> 94.616299 | E81: =E79+E80 -> 31.564316 | F81: =F79+F80 -> 152.6178 | G81: =G79+G80 -> 138.21505 | H81: =H79+H80 -> 416.67719 | I81: =I79+I80 -> 104.59872 | J81: =J79+J80 -> 39.504893 | ... AX81: =AX79+AX80 -> 2196.8446
B82: % chg. y/y | C82: -- | D82: -- | E82: -- | F82: -- | G82: -- | H82: =H81/C81-1 -> 0.33813187 | I82: =I81/D81-1 -> 0.10550425 | J82: =J81/E81-1 -> 0.25156816 | K82: =K81/F81-1 -> -0.22873134 | L82: =L81/G81-1 -> 0.38296254 | M82: =M81/H81-1 -> 0.087074567 | N82: =N81/I81-1 -> 0.74571924 | O82: =O81/J81-1 -> 0.58348317 | ... R82: =R81/M81-1 -> 0.34868666 | S82: =S81/C81-1 -> 0.33813187 | T82: =T81/S81-1 -> 0.087074567 | U82: =U81/I81-1 -> 0.74571924 | V82: =V81/J81-1 -> 0.58348317 | W82: =W81/K81-1 -> 0.50259972 | X82: =X81/L81-1 -> -0.011883938 | Y82: =Y81/T81-1 -> 0.34868666 | Z82: =Z81/U81-1 -> -0.0054764513 | AA82: =AA81/V81-1 -> 0.30124796 | AB82: =AB81/W81-1 -> 0.44399842 | AC82: =AC81/X81-1 -> 0.53329192 | AD82: =AD81/Y81-1 -> 0.32263873 | AE82: =AE81/Z81-1 -> 0.64867841 | AF82: =AF81/AA81-1 -> 0.69287469 | ... AX82: =AX81/AS81-1 -> 0.1784495
B83: % margin | C83: =C81/C44 -> 0.12729427 | D83: =D81/D44 -> 0.14260396 | E83: =E81/E44 -> 0.052799913 | F83: =F81/F44 -> 0.18932157 | G83: =G81/G44 -> 0.1383534 | H83: =H81/H44 -> 0.13588348 | I83: =I81/I44 -> 0.12926866 | J83: =J81/J44 -> 0.05697096 | ... R83: =R81/R44 -> 0.13984845 | S83: =S81/S12 -> 0.13503359 | T83: =T81/T12 -> 0.12684828 | U83: =U81/U12 -> 0.17275307 | V83: =V81/V12 -> 0.072502704 | W83: =W81/W12 -> 0.15338652 | X83: =X81/X12 -> 0.14228919 | Y83: =Y81/Y12 -> 0.13883144 | Z83: =Z81/Z44 -> 0.15229789 | AA83: =AA81/AA44 -> 0.081294317 | AB83: =AB81/AB44 -> 0.18865416 | AC83: =AC81/AC44 -> 0.17703876 | AD83: =AD81/AD44 -> 0.15588525 | AE83: =AE81/AE44 -> 0.20332767 | AF83: =AF81/AF44 -> 0.11146162 | AG83: =AG81/AG44 -> 0.20110459 | ... AX83: =AX81/AX44 -> 0.20440073
B84: bps chg. y/y | C84: -- | D84: -- | E84: -- | F84: -- | G84: -- | H84: =(H83-C83)*100*100 -> 85.892145 | I84: =(I83-D83)*100*100 -> -133.35296 | J84: =(J83-E83)*100*100 -> 41.710463 | K84: =(K83-F83)*100*100 -> -503.79546 | L84: =(L83-G83)*100*100 -> 211.06366 | M84: =(M83-H83)*100*100 -> -82.344631 | N84: =(N83-I83)*100*100 -> 445.86428 | O84: =(O83-J83)*100*100 -> 160.39467 | ... R84: =(R83-M83)*100*100 -> 121.99433 | S84: -- | T84: =(T83-S83)*100*100 -> -81.853057 | U84: -- | V84: -- | W84: -- | X84: -- | Y84: =(Y83-T83)*100*100 -> 119.83162 | Z84: =(Z83-U83)*100*100 -> -204.55188 | AA84: =(AA83-V83)*100*100 -> 87.91613 | AB84: =(AB83-W83)*100*100 -> 352.67635 | AC84: =(AC83-X83)*100*100 -> 347.49571 | AD84: =(AD83-Y83)*100*100 -> 170.53804 | AE84: =(AE83-Z83)*100*100 -> 510.29787 | AF84: =(AF83-AA83)*100*100 -> 301.67302 | ... AX84: =(AX83-AS83)*100*100 -> 72.470683
B85: incremental margin | C85: -- | D85: -- | E85: -- | F85: -- | G85: -- | H85: =(H81-C81)/(H12-C12) -> 0.16975952 | I85: =(I81-D81)/(I12-D12) -> 0.068528766 | J85: =(J81-E81)/(J12-E12) -> 0.083050364 | K85: =(K81-F81)/(K12-F12) -> -0.85032645 | L85: =(L81-G81)/(L12-G12) -> 0.26503844 | M85: =(M81-H81)/(M12-H12) -> 0.075267024 | N85: =(N81-I81)/(N12-I12) -> 0.32346565 | O85: =(O81-J81)/(O12-J12) -> 0.1410862 | ... R85: =(R81-M81)/(R12-M12) -> 0.19265154 | S85: -- | T85: =(T81-S81)/(T12-S12) -> 0.074786079 | U85: -- | V85: -- | W85: -- | X85: -- | Y85: =(Y81-T81)/(Y12-T12) -> 0.19042174 | Z85: =(Z81-U81)/(Z12-N12) -> -0.0070372977 | AA85: =(AA81-V81)/(AA12-O12) -> 0.13041292 | AB85: =(AB81-W81)/(AB12-P12) -> 0.37845783 | AC85: =(AC81-X81)/(AC12-Q12) -> 0.31388387 | AD85: =(AD81-Y81)/(AD12-R12) -> 0.24184049 | AE85: =(AE81-Z81)/(AE12-Z12) -> 0.42056408 | AF85: =(AF81-AA81)/(AF12-T12) -> -0.024158587 | AG85: =(AG81-AB81)/(AG12-U12) -> 0.13985414 | AH85: =(AH81-AC81)/(AH12-AC12) -> 0.15194498 | AI85: =(AI81-AD81)/(AI12-AD12) -> 0.24781257 | AJ85: =(AJ81-AE81)/(AJ12-AE12) -> 0.28118393 | AK85: =(AK81-AF81)/(AK12-AF12) -> 0.43931365 | AL85: =(AL81-AG81)/(AL12-AG12) -> 0.13261126 | AM85: =(AM81-AH81)/(AM12-AH12) -> 0.2472068 | AN85: =(AN81-AI81)/(AN12-AI12) -> 0.27628559 | AO85: =(AO81-AJ81)/(AO12-AJ12) -> 0.26761036 | ... AX85: =(AX81-AS81)/(AX12-AS12) -> 0.2574278
B87: Corproate ROU Asset Depreciation | C87: ='2. Consolidated'!C102-'3. Segment Build'!C88 -> 1.9 | D87: ='2. Consolidated'!D102-'3. Segment Build'!D88 -> 0.7392718 | E87: ='2. Consolidated'!E102-'3. Segment Build'!E88 -> 0.14168901 | F87: ='2. Consolidated'!F102-'3. Segment Build'!F88 -> -0.54700356 | G87: ='2. Consolidated'!G102-'3. Segment Build'!G88 -> 2.9872827 | H87: =D87+E87+F87+G87 -> 3.32124 | I87: ='2. Consolidated'!I102-'3. Segment Build'!I88 -> 0.48119144 | J87: ='2. Consolidated'!J102-'3. Segment Build'!J88 -> 0.95414556 | K87: ='2. Consolidated'!K102-'3. Segment Build'!K88 -> 0.052553604 | L87: ='2. Consolidated'!L102-'3. Segment Build'!L88 -> 0.47585738 | M87: =I87+J87+K87+L87 -> 1.963748 | N87: ='2. Consolidated'!N102-'3. Segment Build'!N88 -> 0.48465502 | O87: ='2. Consolidated'!O102-'3. Segment Build'!O88 -> 0.48988615 | P87: ='2. Consolidated'!P102-'3. Segment Build'!P88 -> 0.496 | Q87: ='2. Consolidated'!Q102-'3. Segment Build'!Q88 -> 0.96 | R87: =N87+O87+P87+Q87 -> 2.4305412
B88: Segment ROU Asset Depreciation | C88: =C192+C296+C382 -> 67.3 | D88: =D192+D296+D382 -> 17.565728 | E88: =E192+E296+E382 -> 17.963311 | F88: =F192+F296+F382 -> 18.232004 | G88: =G192+G296+G382 -> 18.344717 | H88: =D88+E88+F88+G88 -> 72.10576 | I88: =I192+I296+I382 -> 18.518809 | J88: =J192+J296+J382 -> 18.445854 | K88: =K192+K296+K382 -> 17.552446 | L88: =L192+L296+L382 -> 16.824143 | M88: =I88+J88+K88+L88 -> 71.341252 | N88: =N192+N296+N382 -> 18.315345 | O88: =O192+O296+O382 -> 18.854114 | P88: =P192+P296+P382 -> 20.8 | Q88: =Q192+Q296+Q382 -> 27 | R88: =N88+O88+P88+Q88 -> 84.969459
B89: Consolidated Adj. EBITDA (Adj. for IFRS 16) | C89: =C81-C88-C87 -> 242.18724 | D89: =D81-D88-D87 -> 76.311299 | E89: =E81-E88-E87 -> 13.459316 | F89: =F81-F88-F87 -> 134.9328 | G89: =G81-G88-G87 -> 116.88305 | H89: =H81-H88-H87 -> 341.25019 | I89: =I81-I88-I87 -> 85.598721 | J89: =J81-J88-J87 -> 20.104893 | ... R89: =R81-R88-R87 -> 523.5
B90: % chg. y/y | C90: -- | D90: -- | E90: -- | F90: -- | G90: -- | H90: =H89/C89-1 -> 0.40903455 | I90: =I89/D89-1 -> 0.12170441 | J90: =J89/E89-1 -> 0.49375294 | K90: =K89/F89-1 -> -0.25811718 | L90: =L89/G89-1 -> 0.48735198 | M90: =M89/H89-1 -> 0.11253909 | N90: =N89/I89-1 -> 0.91357999 | O90: =O89/J89-1 -> 1.1492944 | ... R90: =R89/M89-1 -> 0.37888645
B91: % margin | C91: =C89/C44 -> 0.099005495 | D91: =D89/D44 -> 0.115015 | E91: =E89/E44 -> 0.022514371 | F91: =F89/F44 -> 0.16738342 | G91: =G89/G44 -> 0.11700005 | H91: =H89/H44 -> 0.11128582 | I91: =I89/I44 -> 0.10578745 | J91: =J89/J44 -> 0.028993751 | ... R91: =R89/R44 -> 0.11984067
B92: bps chg. y/y | C92: -- | D92: -- | E92: -- | F92: -- | G92: -- | H92: =(H91-C91)*100*100 -> 122.8033 | I92: =(I91-D91)*100*100 -> -92.275447 | J92: =(J91-E91)*100*100 -> 64.793804 | K92: =(K91-F91)*100*100 -> -492.2203 | L92: =(L91-G91)*100*100 -> 280.27554 | M92: =(M91-H91)*100*100 -> -42.949823 | N92: =(N91-I91)*100*100 -> 501.6799 | O92: =(O91-J91)*100*100 -> 214.39644 | ... R92: =(R91-M91)*100*100 -> 128.49828
B93: incremental margin | C93: -- | D93: -- | E93: -- | F93: -- | G93: -- | H93: =(H89-C89)/(H12-C12) -> 0.1597197 | I93: =(I89-D89)/(I12-D12) -> 0.06375763 | J93: =(J89-E89)/(J12-E12) -> 0.06950598 | K93: =(K89-F89)/(K12-F12) -> -0.84837776 | L93: =(L89-G89)/(L12-G12) -> 0.28522758 | M93: =(M89-H89)/(M12-H12) -> 0.079669116 | N93: =(N89-I89)/(N12-I12) -> 0.32429503 | O93: =(O89-J89)/(O12-J12) -> 0.14142897 | ... R93: =(R89-M89)/(R12-M12) -> 0.17545888
B95: Purchase Price Adjustments | C95: =C98+C97+C96 -> 48.112759 | D95: =D98+D97+D96 -> 12.549801 | E95: =E98+E97+E96 -> 12.549668 | F95: =F98+F97+F96 -> 12.345254 | G95: =G98+G97+G96 -> 12.07249 | H95: =H98+H97+H96 -> 49.517213 | I95: =I98+I97+I96 -> 11.880657 | J95: =J98+J97+J96 -> 10.475376 | ... AX95: =AX98+AX97+AX96 -> 36
B96: Technical Apparel | C96: 13.086175 | D96: 3.3022042 | E96: 3.3021974 | F96: 3.2936961 | G96: 3.2809348 | H96: =D96+E96+F96+G96 -> 13.179032 | I96: 3.2665073 | J96: 2.2992268 | K96: 2.1691579 | L96: 2.2024463 | M96: =I96+J96+K96+L96 -> 9.9373382 | N96: 2.4 | O96: 2.3759523 | P96: 2.3759523 | Q96: =9.4-N96-O96-P96 -> 2.2480953 | R96: =N96+O96+P96+Q96 -> 9.4 | S96: =H96 -> 13.179032 | T96: =M96 -> 9.9373382 | U96: =N96 -> 2.4 | V96: =O96 -> 2.3759523 | W96: =P96 -> 2.3759523 | X96: =Q96 -> 2.2480953 | Y96: =U96+V96+W96+X96 -> 9.4 | Z96: 2.4 | AA96: 2.4 | AB96: 2.4 | AC96: =9.5-Z96-AA96-AB96 -> 2.3 | AD96: =Z96+AA96+AB96+AC96 -> 9.5 | AE96: 2.4 | AF96: 2.3 | AG96: 2.1 | AH96: =9.1-AE96-AF96-AG96 -> 2.3 | AI96: =AE96+AF96+AG96+AH96 -> 9.1 | AJ96: 2.3 | AK96: 2.3 | AL96: =AK96 -> 2.3 | AM96: =AL96 -> 2.3 | AN96: =AJ96+AK96+AL96+AM96 -> 9.2 | AO96: =AM96 -> 2.3 | AP96: =AO96 -> 2.3 | AQ96: =AP96 -> 2.3 | AR96: =AQ96 -> 2.3 | AS96: =AO96+AP96+AQ96+AR96 -> 9.2 | AT96: =AR96 -> 2.3 | AU96: =AT96 -> 2.3 | AV96: =AU96 -> 2.3 | AW96: =AV96 -> 2.3 | AX96: =AT96+AU96+AV96+AW96 -> 9.2
B97: Outdoor Performance Sports | C97: 33.747384 | D97: 8.9273992 | E97: 8.9272732 | F97: 8.7313604 | G97: 8.4736046 | H97: =D97+E97+F97+G97 -> 35.059637 | I97: 8.2942344 | J97: 7.8725005 | K97: 7.4440181 | L97: 7.539485 | M97: =I97+J97+K97+L97 -> 31.150238 | N97: 7.9 | O97: 8.0488539 | P97: 8.0488539 | Q97: =31.9-N97-O97-P97 -> 7.9022922 | R97: =N97+O97+P97+Q97 -> 31.9 | S97: =H97 -> 35.059637 | T97: =M97 -> 31.150238 | U97: =N97 -> 7.9 | V97: =O97 -> 8.0488539 | W97: =P97 -> 8.0488539 | X97: =Q97 -> 7.9022922 | Y97: =U97+V97+W97+X97 -> 31.9 | Z97: 8 | AA97: 8 | AB97: 8.1 | AC97: =32-Z97-AA97-AB97 -> 7.9 | AD97: =Z97+AA97+AB97+AC97 -> 32 | AE97: 7.8 | AF97: 8.4 | AG97: 38.1 | AH97: =60.8-AE97-AF97-AG97 -> 6.5 | AI97: =AE97+AF97+AG97+AH97 -> 60.8 | AJ97: 6.6 | AK97: 6.5 | AL97: =AK97 -> 6.5 | AM97: =AL97 -> 6.5 | AN97: =AJ97+AK97+AL97+AM97 -> 26.1 | AO97: =AM97 -> 6.5 | AP97: =AO97 -> 6.5 | AQ97: =AP97 -> 6.5 | AR97: =AQ97 -> 6.5 | AS97: =AO97+AP97+AQ97+AR97 -> 26 | AT97: =AR97 -> 6.5 | AU97: =AT97 -> 6.5 | AV97: =AU97 -> 6.5 | AW97: =AV97 -> 6.5 | AX97: =AT97+AU97+AV97+AW97 -> 26
B98: Ball & Racquet Sports | C98: 1.2792 | D98: 0.3201975 | E98: 0.3201975 | F98: 0.3201975 | G98: 0.3179505 | H98: =D98+E98+F98+G98 -> 1.278543 | I98: 0.31991566 | J98: 0.30364902 | K98: 0.28700557 | L98: 0.28979073 | M98: =I98+J98+K98+L98 -> 1.200361 | N98: 0.3 | O98: 0.31986045 | P98: 0.31986045 | Q98: =1.3-N98-O98-P98 -> 0.3602791 | R98: =N98+O98+P98+Q98 -> 1.3 | S98: =H98 -> 1.278543 | T98: =M98 -> 1.200361 | U98: =N98 -> 0.3 | V98: =O98 -> 0.31986045 | W98: =P98 -> 0.31986045 | X98: =Q98 -> 0.3602791 | Y98: =U98+V98+W98+X98 -> 1.3 | Z98: 0.3 | AA98: 0.3 | AB98: 0.3 | AC98: =1.3-Z98-AA98-AB98 -> 0.4 | AD98: =Z98+AA98+AB98+AC98 -> 1.3 | AE98: 0.3 | AF98: 0.3 | AG98: 0.3 | AH98: =1.3-AE98-AF98-AG98 -> 0.4 | AI98: =AE98+AF98+AG98+AH98 -> 1.3 | AJ98: 0.3 | AK98: 0.2 | AL98: =AK98 -> 0.2 | AM98: =AL98 -> 0.2 | AN98: =AJ98+AK98+AL98+AM98 -> 0.9 | AO98: =AM98 -> 0.2 | AP98: =AO98 -> 0.2 | AQ98: =AP98 -> 0.2 | AR98: =AQ98 -> 0.2 | AS98: =AO98+AP98+AQ98+AR98 -> 0.8 | AT98: =AR98 -> 0.2 | AU98: =AT98 -> 0.2 | AV98: =AU98 -> 0.2 | AW98: =AV98 -> 0.2 | AX98: =AT98+AU98+AV98+AW98 -> 0.8
B100: Technical Apparel
B101: Wholesale | C101: 374.8 | D101: 100.73 | E101: 54.27 | F101: 138.4 | G101: 128.37 | H101: =D101+E101+F101+G101 -> 421.77 | I101: 103.87842 | J101: 60.408413 | K101: 101.77319 | L101: 149.97536 | M101: =I101+J101+K101+L101 -> 416.03538 | N101: 119.4 | O101: 94.6 | P101: 172 | Q101: =528-N101-O101-P101 -> 142 | R101: =N101+O101+P101+Q101 -> 528 | S101: =H101 -> 421.77 | T101: =M101 -> 416.03538 | U101: =N101 -> 119.4 | V101: =O101 -> 94.6 | W101: =P101 -> 172 | X101: =Q101 -> 142 | Y101: =U101+V101+W101+X101 -> 528 | Z101: 166.8 | AA101: 117.1 | AB101: 216.5 | AC101: =643.1-Z101-AA101-AB101 -> 142.7 | AD101: =Z101+AA101+AB101+AC101 -> 643.1 | AE101: 203.2 | AF101: 121.6 | AG101: 241.4 | AH101: =761.1-AE101-AF101-AG101 -> 194.9 | AI101: =AE101+AF101+AG101+AH101 -> 761.1 | AJ101: 236.5 | AK101: 155 | AL101: =AG101*(1+AL102) -> 269.938 | AM101: =AH101*(1+AM102) -> 204.645 | AN101: =AJ101+AK101+AL101+AM101 -> 866.083 | AO101: =AJ101*(1+AO102) -> 253.055 | AP101: =AK101*(1+AP102) -> 165.85 | AQ101: =AL101*(1+AQ102) -> 288.83366 | AR101: =AM101*(1+AR102) -> 218.97015 | AS101: =AO101+AP101+AQ101+AR101 -> 926.70881 | AT101: =AO101*(1+AT102) -> 268.2383 | AU101: =AP101*(1+AU102) -> 175.801 | AV101: =AQ101*(1+AV102) -> 306.16368 | AW101: =AR101*(1+AW102) -> 232.10836 | AX101: =AT101+AU101+AV101+AW101 -> 982.31134
B102: % chg. y/y | C102: -- | D102: -- | E102: -- | F102: -- | G102: -- | H102: =H101/C101-1 -> 0.12532017 | I102: =I101/D101-1 -> 0.031256071 | J102: =J101/E101-1 -> 0.11310877 | K102: =K101/F101-1 -> -0.26464461 | L102: =L101/G101-1 -> 0.16830538 | M102: =M101/H101-1 -> -0.013596548 | N102: =N101/I101-1 -> 0.1494206 | O102: =O101/J101-1 -> 0.56600704 | ... R102: =R101/M101-1 -> 0.26912282 | S102: =S101/C101-1 -> 0.12532017 | T102: =T101/S101-1 -> -0.013596548 | U102: =U101/I101-1 -> 0.1494206 | V102: =V101/J101-1 -> 0.56600704 | W102: =W101/K101-1 -> 0.69003258 | X102: =X101/L101-1 -> -0.053177808 | Y102: =Y101/T101-1 -> 0.26912282 | Z102: =Z101/U101-1 -> 0.39698492 | AA102: =AA101/V101-1 -> 0.23784355 | AB102: =AB101/W101-1 -> 0.25872093 | AC102: =AC101/X101-1 -> 0.0049295775 | AD102: =AD101/Y101-1 -> 0.21799242 | AE102: =AE101/Z101-1 -> 0.21822542 | AF102: =AF101/AA101-1 -> 0.038428693 | ... AK102: =AK101/AF101-1 -> 0.27467105 | AL102: =17%-12.5/AG101 -> 0.11821872 | AM102: 0.05 | AN102: =AN101/AI101-1 -> 0.13793588 | AO102: 0.07 | AP102: 0.07 | AQ102: 0.07 | AR102: 0.07 | AS102: =AS101/AN101-1 -> 0.07 | AT102: 0.06 | AU102: 0.06 | AV102: 0.06 | AW102: 0.06 | AX102: =AX101/AS101-1 -> 0.06
B103: % of sales | C103: =C101/C107 -> 0.54683397 | D103: =D101/D107 -> 0.4957917 | E103: =E101/E107 -> 0.36708604 | F103: =F101/F107 -> 0.58009892 | G103: =G101/G107 -> 0.3554774 | H103: =H101/H107 -> 0.44363686 | I103: =I101/I107 -> 0.39749946 | J103: =J101/J107 -> 0.3557243 | ... R103: =R101/R107 -> 0.33149171 | Z103: =Z101/Z107 -> 0.32263056 | AA103: =AA101/AA107 -> 0.28415433 | AB103: =AB101/AB107 -> 0.41634615 | AC103: =AC101/AC107 -> 0.19149222 | AD103: =AD101/AD107 -> 0.29307752 | AE103: =AE101/AE107 -> 0.3061163 | AF103: =AF101/AF107 -> 0.23894675 | AG103: =AG101/AG107 -> 0.35328553 | ... AX103: =AX101/AX107 -> 0.20539643
B104: DTC | C104: 310.6 | D104: 102.44 | E104: 93.57 | F104: 100.18 | G104: 232.75 | H104: =D104+E104+F104+G104 -> 528.94 | I104: 157.4513 | J104: 109.40966 | K104: 125.90011 | L104: 286.72329 | M104: =I104+J104+K104+L104 -> 679.48435 | N104: 235.8 | O104: 208.4 | P104: 212.6 | Q104: =1064.8-N104-O104-P104 -> 408 | R104: =N104+O104+P104+Q104 -> 1064.8 | S104: =H104+10.8 -> 539.74 | T104: =M104+12.6 -> 692.08435 | U104: =N104+4.2 -> 240 | V104: =O104+3.8 -> 212.2 | W104: =P104+4.2 -> 216.8 | X104: =Q104+9.2 -> 417.2 | Y104: =U104+V104+W104+X104 -> 1086.2 | Z104: =343.5+6.7 -> 350.2 | AA104: =290.2+4.8 -> 295 | AB104: 303.5 | AC104: =1551.2-Z104-AA104-AB104 -> 602.5 | AD104: =Z104+AA104+AB104+AC104 -> 1551.2 | AE104: 460.6 | AF104: 387.3 | AG104: 441.9 | AH104: =2094.7-AG104-AF104-AE104 -> 804.9 | AI104: =AE104+AF104+AG104+AH104 -> 2094.7 | AJ104: 648.5 | AK104: 519.2 | AL104: =AG104*(1+AL136)*(1+AL135*AL133) -> 575.19623 | AM104: =AH104*(1+AM136)*(1+AM135*AM133) -> 999.12451 | AN104: =AJ104+AK104+AL104+AM104 -> 2742.0207 | AO104: =AJ104*(1+AO136)*(1+AO135*AO133) -> 780.8868 | AP104: =AK104*(1+AP136)*(1+AP135*AP133) -> 620.72171 | AQ104: =AL104*(1+AQ136)*(1+AQ135*AQ133) -> 680.09263 | AR104: =AM104*(1+AR136)*(1+AR135*AR133) -> 1177.5396 | AS104: =AO104+AP104+AQ104+AR104 -> 3259.2407 | AT104: =AO104*(1+AT136)*(1+AT135*AT133) -> 912.62841 | AU104: =AP104*(1+AU136)*(1+AU135*AU133) -> 724.79605 | AV104: =AQ104*(1+AV136)*(1+AV135*AV133) -> 792.57179 | AW104: =AR104*(1+AW136)*(1+AW135*AW133) -> 1370.2065 | AX104: =AT104+AU104+AV104+AW104 -> 3800.2028
B105: % chg. y/y | C105: -- | D105: -- | E105: -- | F105: -- | G105: -- | H105: =H104/C104-1 -> 0.70296201 | I105: =I104/D104-1 -> 0.53700994 | J105: =J104/E104-1 -> 0.16928135 | K105: =K104/F104-1 -> 0.25673893 | L105: =L104/G104-1 -> 0.23189382 | M105: =M104/H104-1 -> 0.28461517 | N105: =N104/I104-1 -> 0.49760594 | O105: =O104/J104-1 -> 0.9047679 | ... R105: =R104/M104-1 -> 0.56707068 | S105: -- | T105: =T104/S104-1 -> 0.28225506 | U105: -- | V105: -- | W105: -- | X105: -- | Y105: =Y104/T104-1 -> 0.56946188 | Z105: =Z104/U104-1 -> 0.45916667 | AA105: =AA104/V104-1 -> 0.39019793 | AB105: =AB104/W104-1 -> 0.39990775 | AC105: =AC104/X104-1 -> 0.44415149 | AD105: =AD104/Y104-1 -> 0.42809796 | AE105: =AE104/Z104-1 -> 0.31524843 | AF105: =AF104/AA104-1 -> 0.31288136 | ... AX105: =AX104/AS104-1 -> 0.16597794
B106: % of sales | C106: =C104/C107 -> 0.45316603 | D106: =D104/D107 -> 0.5042083 | E106: =E104/E107 -> 0.63291396 | F106: =F104/F107 -> 0.41990108 | G106: =G104/G107 -> 0.6445226 | H106: =H104/H107 -> 0.55636314 | I106: =I104/I107 -> 0.60250054 | J106: =J104/J107 -> 0.6442757 | ... AX106: =AX104/AX107 -> 0.79460357
B107: Technical Apparel | C107: =C101+C104 -> 685.4 | D107: =D101+D104 -> 203.17 | E107: =E101+E104 -> 147.84 | F107: =F101+F104 -> 238.58 | G107: =G101+G104 -> 361.12 | H107: =H101+H104 -> 950.71 | I107: =I101+I104 -> 261.32972 | J107: =J101+J104 -> 169.81807 | ... Y107: =Y101+Y104 -> 1614.2 | Z107: 517 | AA107: 412.1 | AB107: 520 | AC107: =2194.3-Z107-AA107-AB107 -> 745.2 | AD107: =AD101+AD104 -> 2194.3 | AE107: 663.8 | AF107: 508.9 | AG107: 683.3 | AH107: 999.8 | AI107: =AI101+AI104 -> 2855.8 | AJ107: 885 | AK107: 674.2 | AL107: =AL101+AL104 -> 845.13423 | AM107: =AM101+AM104 -> 1203.7695 | AN107: =AN101+AN104 -> 3608.1037 | AO107: =AO101+AO104 -> 1033.9418 | AP107: =AP101+AP104 -> 786.57171 | AQ107: =AQ101+AQ104 -> 968.92629 | AR107: =AR101+AR104 -> 1396.5097 | AS107: =AS101+AS104 -> 4185.9496 | ... AX107: =AX101+AX104 -> 4782.5141
B108: % chg. y/y | D108: -- | E108: -- | F108: -- | G108: -- | H108: =H107/C107-1 -> 0.38708783 | I108: =I107/D107-1 -> 0.28626137 | J108: =J107/E107-1 -> 0.14866118 | K108: =K107/F107-1 -> -0.045715096 | L108: =L107/G107-1 -> 0.20928957 | M108: =M107/H107-1 -> 0.15231746 | N108: =N107/I107-1 -> 0.35920245 | O108: =O107/J107-1 -> 0.78426243 | ... R108: =R107/M107-1 -> 0.45392178 | S108: -- | T108: =T107/S107-1 -> 0.15247863 | U108: -- | V108: -- | W108: -- | X108: -- | Y108: =Y107/T107-1 -> 0.45670179 | Z108: =Z107/U107-1 -> 0.43850863 | AA108: =AA107/V107-1 -> 0.34322034 | AB108: =AB107/W107-1 -> 0.33744856 | AC108: =AC107/X107-1 -> 0.33261803 | AD108: =AD107/Y107-1 -> 0.35937306 | AE108: =AE107/Z107-1 -> 0.28394584 | AF108: =AF107/AA107-1 -> 0.23489444 | ... AX108: =AX107/AS107-1 -> 0.14251595
B109: % chg. y/y ex-FX | Z109: 0.477 | AA109: 0.384 | AB109: 0.332 | AC109: =(AD109*Y107-Z109*U107-AA109*V107-AB109*W107)/X107 -> 0.3430633 | AD109: 0.378 | AE109: 0.318 | AF109: 0.227 | AG109: 0.319 | AH109: =(AI109*AD107-AE109*Z107-AF109*AA107-AG109*AB107)/AC107 -> 0.34701369 | AI109: 0.311 | AJ109: 0.284 | AK109: 0.302 | AN109: =AN107-105 -> 3503.1037
B110: FX impact | Z110: =Z108-Z109 -> -0.038491375 | AA110: =AA108-AA109 -> -0.040779661 | AB110: =AB108-AB109 -> 0.0054485597 | AC110: =AC108-AC109 -> -0.010445279 | AD110: =SUMPRODUCT(Z110:AC110,U107:X107)/Y107 -> -0.018626936 | AE110: =AE108-AE109 -> -0.034054159 | AF110: =AF108-AF109 -> 0.0078944431 | AG110: =AG108-AG109 -> -0.0049615385 | AH110: =AH108-AH109 -> -0.0053604402 | AI110: =SUMPRODUCT(AE110:AH110,Z107:AC107)/AD107 -> -0.0095371189 | AJ110: =AJ108-AJ109 -> 0.049232901 | AK110: =AK108-AK109 -> 0.022818235
B112: Arc'teryx Regional Mix
B113: Greater China | AD113: 0.45 | AI113: 0.44
B114: Americas | AD114: 0.33 | AI114: 0.32
B115: EMEA | AD115: 0.11 | AI115: 0.1
B116: APAC ex-China | AD116: 0.11 | AI116: 0.14
B118: Women's Revenue Growth | AB118: >50% | AC118: ~40% | AE118: ~38% | AF118: >30% | AG118: ~40% | AH118: ~40% | AJ118: >40%
B119: Footwear Revenue Growth | AA119: triple digits | AD119: >60% | AE119: ~41% | AG119: ~35% | AH119: nearly 40%
B120: Veilance | AH120: strong DD%
...

Sheet 4. Summary Model
B1: Amer Sports, Inc.
B2: Summary Model
B3: $ millions except per share data, FY ending Dec
C5: ='2. Consolidated'!C5 -> 44196 | D5: ='2. Consolidated'!D5 -> 44286 | E5: ='2. Consolidated'!E5 -> 44377 | F5: ='2. Consolidated'!F5 -> 44469 | G5: ='2. Consolidated'!G5 -> 44561 | H5: ='2. Consolidated'!H5 -> 44561 | I5: ='2. Consolidated'!I5 -> 44651 | J5: ='2. Consolidated'!J5 -> 44742 | ... AX5: ='2. Consolidated'!AX5 -> 47118
C6: ='2. Consolidated'!C6 -> FY20 | D6: ='2. Consolidated'!D6 -> Q1'21 | E6: ='2. Consolidated'!E6 -> Q2'21 | F6: ='2. Consolidated'!F6 -> Q3'21 | G6: ='2. Consolidated'!G6 -> Q4'21 | H6: ='2. Consolidated'!H6 -> FY21 | I6: ='2. Consolidated'!I6 -> Q1'22 | J6: ='2. Consolidated'!J6 -> Q2'22 | ... AX6: ='2. Consolidated'!AX6 -> FY28E
B7: Segment Summary:
B8: Technical Apparel
B9: Total Sales | C9: ='3. Segment Build'!C107 -> 685.4 | D9: ='3. Segment Build'!D107 -> 203.17 | E9: ='3. Segment Build'!E107 -> 147.84 | F9: ='3. Segment Build'!F107 -> 238.58 | G9: ='3. Segment Build'!G107 -> 361.12 | H9: ='3. Segment Build'!H107 -> 950.71 | I9: ='3. Segment Build'!I107 -> 261.32972 | J9: ='3. Segment Build'!J107 -> 169.81807 | ... AX9: ='3. Segment Build'!AX107 -> 4782.5141
B10: Wholesale sales | C10: ='3. Segment Build'!C101 -> 374.8 | D10: ='3. Segment Build'!D101 -> 100.73 | E10: ='3. Segment Build'!E101 -> 54.27 | F10: ='3. Segment Build'!F101 -> 138.4 | G10: ='3. Segment Build'!G101 -> 128.37 | H10: ='3. Segment Build'!H101 -> 421.77 | I10: ='3. Segment Build'!I101 -> 103.87842 | J10: ='3. Segment Build'!J101 -> 60.408413 | ... AX10: ='3. Segment Build'!AX101 -> 982.31134
B11: DTC sales | C11: ='3. Segment Build'!C104 -> 310.6 | D11: ='3. Segment Build'!D104 -> 102.44 | E11: ='3. Segment Build'!E104 -> 93.57 | F11: ='3. Segment Build'!F104 -> 100.18 | G11: ='3. Segment Build'!G104 -> 232.75 | H11: ='3. Segment Build'!H104 -> 528.94 | I11: ='3. Segment Build'!I104 -> 157.4513 | J11: ='3. Segment Build'!J104 -> 109.40966 | ... AX11: ='3. Segment Build'!AX104 -> 3800.2028
B12: Store count (end-of-period) | C12: ='3. Segment Build'!C130 -> 153 | D12: ='3. Segment Build'!D130 -> 154 | E12: ='3. Segment Build'!E130 -> 156 | F12: ='3. Segment Build'!F130 -> 160 | G12: ='3. Segment Build'!G130 -> 167 | H12: ='3. Segment Build'!H130 -> 167 | I12: ='3. Segment Build'!I130 -> 161 | J12: ='3. Segment Build'!J130 -> 161 | ... AX12: ='3. Segment Build'!AX130 -> 383
B13: Comp growth (incl. ecommerce) | C13: 0 | D13: ='3. Segment Build'!D136 -> -- | E13: ='3. Segment Build'!E136 -> -- | F13: ='3. Segment Build'!F136 -> -- | G13: ='3. Segment Build'!G136 -> -- | H13: ='3. Segment Build'!H136 -> 0.4895305 | I13: ='3. Segment Build'!I136 -> -- | J13: ='3. Segment Build'!J136 -> -- | K13: ='3. Segment Build'!K136 -> -- | ... AX13: ='3. Segment Build'!AX136 -> 0.1
B14: Adjusted EBIT | C14: ='3. Segment Build'!C172 -> 117.2 | D14: ='3. Segment Build'!D172 -> 38.6 | E14: ='3. Segment Build'!E172 -> -5.8 | F14: ='3. Segment Build'!F172 -> 59.1 | G14: ='3. Segment Build'!G172 -> 72.3 | H14: ='3. Segment Build'!H172 -> 164.2 | I14: ='3. Segment Build'!I172 -> 57.017479 | J14: ='3. Segment Build'!J172 -> -10.703031 | ... AX14: ='3. Segment Build'!AX172 -> 0
B15: Adjusted EBITDA (adj. for IFRS 16) | C15: ='3. Segment Build'!C193 -> 133.91382 | D15: ='3. Segment Build'!D193 -> 44.175514 | E15: ='3. Segment Build'!E193 -> -0.36128795 | F15: ='3. Segment Build'!F193 -> 63.815461 | G15: ='3. Segment Build'!G193 -> 79.670862 | H15: ='3. Segment Build'!H193 -> 187.30055 | I15: ='3. Segment Build'!I193 -> 63.193252 | J15: ='3. Segment Build'!J193 -> -4.3715552 | ... R15: ='3. Segment Build'!R193 -> 354.42499
B17: Outdoor Performance
B18: Total Sales | C18: ='3. Segment Build'!C213 -> 1091.6 | D18: ='3. Segment Build'!D213 -> 261.81 | E18: ='3. Segment Build'!E213 -> 211.6 | F18: ='3. Segment Build'!F213 -> 347.5 | G18: ='3. Segment Build'!G213 -> 414.7 | H18: ='3. Segment Build'!H213 -> 1235.61 | I18: ='3. Segment Build'!I213 -> 263.36717 | J18: ='3. Segment Build'!J213 -> 246.39547 | ... AX18: ='3. Segment Build'!AX213 -> 4231.4549
B19: Wholesale sales | C19: ='3. Segment Build'!C207 -> 928.8 | D19: ='3. Segment Build'!D207 -> 218.54 | E19: ='3. Segment Build'!E207 -> 164.91 | F19: ='3. Segment Build'!F207 -> 298.67 | G19: ='3. Segment Build'!G207 -> 345.76 | H19: ='3. Segment Build'!H207 -> 1027.88 | I19: ='3. Segment Build'!I207 -> 210.1957 | J19: ='3. Segment Build'!J207 -> 197.57856 | ... AX19: ='3. Segment Build'!AX207 -> 2341.1871
B20: DTC sales | C20: ='3. Segment Build'!C210 -> 162.8 | D20: ='3. Segment Build'!D210 -> 43.27 | E20: ='3. Segment Build'!E210 -> 46.69 | F20: ='3. Segment Build'!F210 -> 48.83 | G20: ='3. Segment Build'!G210 -> 68.94 | H20: ='3. Segment Build'!H210 -> 207.73 | I20: ='3. Segment Build'!I210 -> 53.171475 | J20: ='3. Segment Build'!J210 -> 48.816907 | ... AX20: ='3. Segment Build'!AX210 -> 1890.2678
B21: Adjusted EBIT | C21: ='3. Segment Build'!C276 -> 81.8 | D21: ='3. Segment Build'!D276 -> 11.8 | E21: ='3. Segment Build'!E276 -> -12.2 | F21: ='3. Segment Build'!F276 -> 50.8 | G21: ='3. Segment Build'!G276 -> 41.4 | H21: ='3. Segment Build'!H276 -> 91.8 | I21: ='3. Segment Build'!I276 -> -14.221849 | J21: ='3. Segment Build'!J276 -> -6.3892815 | ... AX21: ='3. Segment Build'!AX276 -> 0
B22: Adjusted EBITDA (adj. for IFRS 16) | C22: ='3. Segment Build'!C297 -> 113.55262 | D22: ='3. Segment Build'!D297 -> 21.876346 | E22: ='3. Segment Build'!E297 -> -2.6745564 | F22: ='3. Segment Build'!F297 -> 58.542143 | G22: ='3. Segment Build'!G297 -> 49.578142 | H22: ='3. Segment Build'!H297 -> 127.32207 | I22: ='3. Segment Build'!I297 -> -6.2361895 | J22: ='3. Segment Build'!J297 -> 0.0015147786 | ... R22: ='3. Segment Build'!R297 -> 185.61642
B24: Ball & Racquet Sports
B25: Total Sales | C25: ='3. Segment Build'!C316 -> 669.2 | D25: ='3. Segment Build'!D316 -> 198.51 | E25: ='3. Segment Build'!E316 -> 238.37 | F25: ='3. Segment Build'!F316 -> 220.05 | G25: ='3. Segment Build'!G316 -> 223.18 | H25: ='3. Segment Build'!H316 -> 880.11 | I25: ='3. Segment Build'!I316 -> 284.46072 | J25: ='3. Segment Build'!J316 -> 277.20805 | ... AX25: ='3. Segment Build'!AX316 -> 1733.7645
B26: Wholesale sales | C26: ='3. Segment Build'!C310 -> 612.6 | D26: ='3. Segment Build'!D310 -> 179.27 | E26: ='3. Segment Build'!E310 -> 214.36 | F26: ='3. Segment Build'!F310 -> 197.14 | G26: ='3. Segment Build'!G310 -> 195.8 | H26: ='3. Segment Build'!H310 -> 786.57 | I26: ='3. Segment Build'!I310 -> 252.64783 | J26: ='3. Segment Build'!J310 -> 246.55729 | ... AX26: ='3. Segment Build'!AX310 -> 1323.0568
B27: DTC sales | C27: ='3. Segment Build'!C313 -> 56.6 | D27: ='3. Segment Build'!D313 -> 19.24 | E27: ='3. Segment Build'!E313 -> 24.01 | F27: ='3. Segment Build'!F313 -> 22.91 | G27: ='3. Segment Build'!G313 -> 27.38 | H27: ='3. Segment Build'!H313 -> 93.54 | I27: ='3. Segment Build'!I313 -> 31.812886 | J27: ='3. Segment Build'!J313 -> 30.650756 | ... AX27: ='3. Segment Build'!AX313 -> 410.70771
B28: Adjusted EBIT | C28: ='3. Segment Build'!C362 -> 31.7 | D28: ='3. Segment Build'!D362 -> 17.6 | E28: ='3. Segment Build'!E362 -> 21.1 | F28: ='3. Segment Build'!F362 -> 12.4 | G28: ='3. Segment Build'!G362 -> 6.1 | H28: ='3. Segment Build'!H362 -> 57.2 | I28: ='3. Segment Build'!I362 -> 36.193774 | J28: ='3. Segment Build'!J362 -> 29.44957 | ... AX28: ='3. Segment Build'!AX362 -> 0
B29: Adjusted EBITDA (adj. for IFRS 16) | C29: ='3. Segment Build'!C383 -> 42.3208 | D29: ='3. Segment Build'!D383 -> 19.750109 | E29: ='3. Segment Build'!E383 -> 23.504226 | F29: ='3. Segment Build'!F383 -> 16.319982 | G29: ='3. Segment Build'!G383 -> 7.1664903 | H29: ='3. Segment Build'!H383 -> 66.740807 | I29: ='3. Segment Build'!I383 -> 39.447618 | J29: ='3. Segment Build'!J383 -> 31.465741 | ... R29: ='3. Segment Build'!R383 -> 43.189133
B31: Total Company Sales Summary
B32: ='3. Segment Build'!B25 -> Americas | C32: ='3. Segment Build'!C25 -> 984 | D32: ='3. Segment Build'!D25 -> 250.54613 | E32: ='3. Segment Build'!E25 -> 256.33191 | F32: ='3. Segment Build'!F25 -> 323.40969 | G32: ='3. Segment Build'!G25 -> 422.71765 | H32: ='3. Segment Build'!H25 -> 1253.0054 | I32: ='3. Segment Build'!I25 -> 350.53477 | ... R32: ='3. Segment Build'!R25 -> 1726.8 | S32: -- | T32: -- | U32: -- | V32: -- | W32: ='3. Segment Build'!W25 -> 455 | X32: ='3. Segment Build'!X25 -> 507.9 | Y32: ='3. Segment Build'!Y25 -> 1745.6 | Z32: ='3. Segment Build'!Z25 -> 414.9 | AA32: ='3. Segment Build'!AA25 -> 371.9 | AB32: ='3. Segment Build'!AB25 -> 487.8 | AC32: ='3. Segment Build'!AC25 -> 584.4 | AD32: ='3. Segment Build'!AD25 -> 1859 | ... AX32: ='3. Segment Build'!AX25 -> 3149.7204
B33: ='3. Segment Build'!B26 -> EMEA | C33: ='3. Segment Build'!C26 -> 1080.4 | D33: ='3. Segment Build'!D26 -> 283.35581 | E33: ='3. Segment Build'!E26 -> 224.34001 | F33: ='3. Segment Build'!F26 -> 329.44857 | G33: ='3. Segment Build'!G26 -> 388.48056 | H33: ='3. Segment Build'!H26 -> 1225.6249 | I33: ='3. Segment Build'!I26 -> 278.11113 | ... R33: ='3. Segment Build'!R26 -> 1450.3 | S33: -- | T33: -- | U33: -- | V33: -- | W33: ='3. Segment Build'!W26 -> 413 | X33: ='3. Segment Build'!X26 -> 454.6 | Y33: ='3. Segment Build'!Y26 -> 1457.6 | Z33: ='3. Segment Build'!Z26 -> 360.6 | AA33: ='3. Segment Build'!AA26 -> 233.1 | AB33: ='3. Segment Build'!AB26 -> 428.5 | AC33: ='3. Segment Build'!AC26 -> 491.2 | AD33: ='3. Segment Build'!AD26 -> 1513.4 | ... AX33: ='3. Segment Build'!AX26 -> 2653.2634
B34: ='3. Segment Build'!B27 -> Greater China | C34: ='3. Segment Build'!C27 -> 202.3 | D34: ='3. Segment Build'!D27 -> 81.710141 | E34: ='3. Segment Build'!E27 -> 71.554778 | F34: ='3. Segment Build'!F27 -> 100.43374 | G34: ='3. Segment Build'!G27 -> 119.16376 | H34: ='3. Segment Build'!H27 -> 372.86241 | I34: ='3. Segment Build'!I27 -> 130.59833 | ... R34: ='3. Segment Build'!R27 -> 841.4 | S34: -- | T34: -- | U34: -- | V34: -- | W34: ='3. Segment Build'!W27 -> 200.5 | X34: ='3. Segment Build'!X27 -> 249.5 | Y34: ='3. Segment Build'!Y27 -> 844.8 | Z34: ='3. Segment Build'!Z27 -> 311.6 | AA34: ='3. Segment Build'!AA27 -> 289.6 | AB34: ='3. Segment Build'!AB27 -> 312.9 | AC34: ='3. Segment Build'!AC27 -> 383.9 | AD34: ='3. Segment Build'!AD27 -> 1298 | ... AX34: ='3. Segment Build'!AX27 -> 3289.3995
B35: ='3. Segment Build'!B28 -> APAC | C35: ='3. Segment Build'!C28 -> 179.6 | D35: ='3. Segment Build'!D28 -> 47.932674 | E35: ='3. Segment Build'!E28 -> 45.636748 | F35: ='3. Segment Build'!F28 -> 52.881846 | G35: ='3. Segment Build'!G28 -> 68.564066 | H35: ='3. Segment Build'!H28 -> 215.01533 | I35: ='3. Segment Build'!I28 -> 50.625918 | ... R35: ='3. Segment Build'!R28 -> 350 | S35: -- | T35: -- | U35: -- | V35: -- | W35: ='3. Segment Build'!W28 -> 84.6 | X35: ='3. Segment Build'!X28 -> 115.5 | Y35: ='3. Segment Build'!Y28 -> 352.4 | Z35: ='3. Segment Build'!Z28 -> 105.4 | AA35: ='3. Segment Build'!AA28 -> 106.8 | AB35: ='3. Segment Build'!AB28 -> 124.6 | AC35: ='3. Segment Build'!AC28 -> 176 | AD35: ='3. Segment Build'!AD28 -> 512.8 | ... AX35: ='3. Segment Build'!AX28 -> 1655.3502
B37: ='3. Segment Build'!B40 -> Wholesale | C37: ='3. Segment Build'!C40 -> 1916.2 | D37: ='3. Segment Build'!D40 -> 498.54 | E37: ='3. Segment Build'!E40 -> 433.54 | F37: ='3. Segment Build'!F40 -> 634.21 | G37: ='3. Segment Build'!G40 -> 669.93 | H37: ='3. Segment Build'!H40 -> 2236.22 | I37: ='3. Segment Build'!I40 -> 566.72195 | ... AX37: ='3. Segment Build'!AX40 -> 4646.5552
B38: ='3. Segment Build'!B41 -> DTC | C38: ='3. Segment Build'!C41 -> 530 | D38: ='3. Segment Build'!D41 -> 164.95 | E38: ='3. Segment Build'!E41 -> 164.27 | F38: ='3. Segment Build'!F41 -> 171.92 | G38: ='3. Segment Build'!G41 -> 329.07 | H38: ='3. Segment Build'!H41 -> 830.21 | I38: ='3. Segment Build'!I41 -> 242.43566 | ... AX38: ='3. Segment Build'!AX41 -> 6101.1783
B40: Income Statement:
B41: ='2. Consolidated'!B8 -> Net Sales | C41: ='2. Consolidated'!C8 -> 2446.2 | D41: ='2. Consolidated'!D8 -> 663.49 | E41: ='2. Consolidated'!E8 -> 597.81 | F41: ='2. Consolidated'!F8 -> 806.13 | G41: ='2. Consolidated'!G8 -> 999 | H41: ='2. Consolidated'!H8 -> 3066.43 | I41: ='2. Consolidated'!I8 -> 809.15761 | ... AX41: ='2. Consolidated'!AX8 -> 10747.734
B42: ='2. Consolidated'!B11 -> COGS | C42: ='2. Consolidated'!C11 -> -1297.4 | D42: ='2. Consolidated'!D11 -> -336.34878 | E42: ='2. Consolidated'!E11 -> -323.56518 | F42: ='2. Consolidated'!F11 -> -404.04946 | G42: ='2. Consolidated'!G11 -> -496.93783 | H42: ='2. Consolidated'!H11 -> -1560.9012 | I42: ='2. Consolidated'!I11 -> -408.6 | ... AX42: ='2. Consolidated'!AX11 -> -4133.5244
B43: ='2. Consolidated'!B12 -> Gross Profit | C43: ='2. Consolidated'!C12 -> 1148.8 | D43: ='2. Consolidated'!D12 -> 327.14122 | E43: ='2. Consolidated'!E12 -> 274.24482 | F43: ='2. Consolidated'!F12 -> 402.08054 | G43: ='2. Consolidated'!G12 -> 502.06217 | H43: ='2. Consolidated'!H12 -> 1505.5288 | I43: ='2. Consolidated'!I12 -> 400.55761 | ... AX43: ='2. Consolidated'!AX12 -> 6614.2091
B45: ='2. Consolidated'!B40 -> Total Adj. SG&A | C45: ='2. Consolidated'!C40 -> -955.9 | D45: ='2. Consolidated'!D40 -> -277.36936 | E45: ='2. Consolidated'!E40 -> -273.71498 | F45: ='2. Consolidated'!F40 -> -291.0492 | G45: ='2. Consolidated'!G40 -> -401.032 | H45: ='2. Consolidated'!H40 -> -1243.1655 | I45: ='2. Consolidated'!I40 -> -334.61904 | ... AX45: ='2. Consolidated'!AX40 -> -5024.2433
B46: ='2. Consolidated'!B46 -> Adjusted impairment losses | C46: ='2. Consolidated'!C46 -> -20.5 | D46: ='2. Consolidated'!D46 -> 7.2024204 | E46: ='2. Consolidated'!E46 -> -6.7777385 | F46: ='2. Consolidated'!F46 -> 5.0349079 | G46: ='2. Consolidated'!G46 -> -6.2019981 | H46: ='2. Consolidated'!H46 -> -0.74240835 | I46: ='2. Consolidated'!I46 -> -2.8 | ... AX46: ='2. Consolidated'!AX46 -> 0
B47: ='2. Consolidated'!B48 -> Other operating income | C47: ='2. Consolidated'!C48 -> 7.2 | D47: ='2. Consolidated'!D48 -> 0.81671535 | E47: ='2. Consolidated'!E48 -> 0.8258933 | F47: ='2. Consolidated'!F48 -> 0.44675039 | G47: ='2. Consolidated'!G48 -> 6.8978288 | H47: ='2. Consolidated'!H48 -> 8.9871878 | I47: ='2. Consolidated'!I48 -> 0.5 | ... AX47: ='2. Consolidated'!AX48 -> 44.2
B48: ='2. Consolidated'!B50 -> Operating profit (IFRS) | C48: ='2. Consolidated'!C50 -> 125.18724 | D48: ='2. Consolidated'!D50 -> 43.841199 | E48: ='2. Consolidated'!E50 -> -50.671668 | F48: ='2. Consolidated'!F50 -> 102.56775 | G48: ='2. Consolidated'!G50 -> 91.25351 | H48: ='2. Consolidated'!H50 -> 186.99079 | I48: ='2. Consolidated'!I50 -> 49.497449 | ... AX48: ='2. Consolidated'!AX50 -> 1596.9658
B49: ='2. Consolidated'!B55 -> Adjusted Operating Profit | C49: ='2. Consolidated'!C55 -> 179.6 | D49: ='2. Consolidated'!D55 -> 57.791 | E49: ='2. Consolidated'!E55 -> -5.422 | F49: ='2. Consolidated'!F55 -> 116.513 | G49: ='2. Consolidated'!G55 -> 101.726 | H49: ='2. Consolidated'!H55 -> 270.608 | I49: ='2. Consolidated'!I55 -> 67.138574 | ... AX49: ='2. Consolidated'!AX55 -> 1648.9658
B51: ='2. Consolidated'!B62 -> Net finance cost | C51: ='2. Consolidated'!C62 -> -272.5 | D51: ='2. Consolidated'!D62 -> -74.722983 | E51: ='2. Consolidated'!E62 -> -78.161587 | F51: ='2. Consolidated'!F62 -> -67.205474 | G51: ='2. Consolidated'!G62 -> -56.626177 | H51: ='2. Consolidated'!H62 -> -276.71622 | I51: ='2. Consolidated'!I62 -> -57 | ... AX51: ='2. Consolidated'!AX62 -> -6.4334069
B52: ='2. Consolidated'!B65 -> Income/Loss before tax - IFRS | C52: ='2. Consolidated'!C65 -> -147.31276 | D52: ='2. Consolidated'!D65 -> -30.881783 | E52: ='2. Consolidated'!E65 -> -128.83326 | F52: ='2. Consolidated'!F65 -> 35.362272 | G52: ='2. Consolidated'!G65 -> 34.627333 | H52: ='2. Consolidated'!H65 -> -89.725433 | I52: ='2. Consolidated'!I65 -> -7.5025511 | ... AX52: ='2. Consolidated'!AX65 -> 1590.5324
B53: ='2. Consolidated'!B66 -> Income tax expense - IFRS | C53: ='2. Consolidated'!C66 -> -26.2 | D53: ='2. Consolidated'!D66 -> 2.4504146 | E53: ='2. Consolidated'!E66 -> -3.0535727 | F53: ='2. Consolidated'!F66 -> -13.156717 | G53: ='2. Consolidated'!G66 -> -21.011529 | H53: ='2. Consolidated'!H66 -> -34.771404 | I53: ='2. Consolidated'!I66 -> -11.7 | ... AX53: ='2. Consolidated'!AX66 -> -429.45101
B54: ='2. Consolidated'!B70 -> Net income/loss (IFRS) | C54: ='2. Consolidated'!C70 -> -237.11276 | D54: ='2. Consolidated'!D70 -> -56.331369 | E54: ='2. Consolidated'!E70 -> -102.08683 | F54: ='2. Consolidated'!F70 -> 21.005555 | G54: ='2. Consolidated'!G70 -> 11.148493 | H54: ='2. Consolidated'!H70 -> -126.26415 | I54: ='2. Consolidated'!I70 -> -29.002551 | ... AX54: ='2. Consolidated'!AX70 -> 1161.0814
B55: ='2. Consolidated'!B120 -> Adjusted Net Income | C55: ='2. Consolidated'!C120 -> -121.9 | D55: ='2. Consolidated'!D120 -> -14.831568 | E55: ='2. Consolidated'!E120 -> -94.81216 | F55: ='2. Consolidated'!F120 -> 35.680809 | G55: ='2. Consolidated'!G120 -> 24.520983 | H55: ='2. Consolidated'!H120 -> -49.441936 | I55: ='2. Consolidated'!I120 -> -2.9314706 | ... AX55: ='2. Consolidated'!AX120 -> 1199.0683
B57: ='2. Consolidated'!B99 -> Adjusted EBITDA | C57: ='2. Consolidated'!C99 -> 311.38724 | D57: ='2. Consolidated'!D99 -> 94.628614 | E57: ='2. Consolidated'!E99 -> 31.277759 | F57: ='2. Consolidated'!F99 -> 152.51603 | G57: ='2. Consolidated'!G99 -> 138.32467 | H57: ='2. Consolidated'!H99 -> 416.74707 | I57: ='2. Consolidated'!I99 -> 104.63503 | ... AX57: ='2. Consolidated'!AX99 -> 2196.8715
B58: ='2. Consolidated'!B102 -> IFRS16 depreciation | C58: ='2. Consolidated'!C102 -> 69.2 | D58: ='2. Consolidated'!D102 -> 18.305 | E58: ='2. Consolidated'!E102 -> 18.105 | F58: ='2. Consolidated'!F102 -> 17.685 | G58: ='2. Consolidated'!G102 -> 21.332 | H58: ='2. Consolidated'!H102 -> 75.427 | I58: ='2. Consolidated'!I102 -> 19 | ... AX58: ='2. Consolidated'!AX102 -> 260
B59: ='2. Consolidated'!B103 -> Adjusted EBITDA without IFRS16 | C59: ='2. Consolidated'!C103 -> 242.18724 | D59: ='2. Consolidated'!D103 -> 76.323614 | E59: ='2. Consolidated'!E103 -> 13.172759 | F59: ='2. Consolidated'!F103 -> 134.83103 | G59: ='2. Consolidated'!G103 -> 116.99267 | H59: ='2. Consolidated'!H103 -> 341.32007 | I59: ='2. Consolidated'!I103 -> 85.635028 | ... AX59: ='2. Consolidated'!AX103 -> 1936.8715
B61: Balance Sheet and CF Metrics:
B62: ='2. Consolidated'!B230 -> Cash and cash equivalents | C62: ='2. Consolidated'!C230 -> 389.5 | D62: ='2. Consolidated'!D230 -> 318.35479 | E62: ='2. Consolidated'!E230 -> 469.24115 | F62: ='2. Consolidated'!F230 -> 363.09461 | G62: ='2. Consolidated'!G230 -> 566.7 | H62: ='2. Consolidated'!H230 -> 566.7 | I62: ='2. Consolidated'!I230 -> 478.34063 | ... R62: ='2. Consolidated'!R230 -> 483.4 | S62: =H62 -> 566.7 | T62: =M62 -> 402 | U62: =N62 -> 348.3 | V62: =O62 -> 278.5 | W62: =P62 -> 284.2 | X62: =Q62 -> 483.4 | Y62: =R62 -> 483.4 | Z62: ='2. Consolidated'!Z230 -> 337.3 | AA62: ='2. Consolidated'!AA230 -> 255.9 | AB62: ='2. Consolidated'!AB230 -> 312 | AC62: ='2. Consolidated'!AC230 -> 345.4 | AD62: ='2. Consolidated'!AD230 -> 345.4 | AE62: ='2. Consolidated'!AE230 -> 422.1 | AF62: ='2. Consolidated'!AF230 -> 303.4 | AG62: ='2. Consolidated'!AG230 -> 353.3 | ... AX62: ='2. Consolidated'!AX230 -> 2837.266
B63: ='2. Consolidated'!B232 -> Inventories | C63: ='2. Consolidated'!C232 -> 569.5 | D63: ='2. Consolidated'!D232 -> 545.04697 | E63: ='2. Consolidated'!E232 -> 631.64483 | F63: ='2. Consolidated'!F232 -> 633.6129 | G63: ='2. Consolidated'!G232 -> 582.8 | H63: ='2. Consolidated'!H232 -> 582.8 | I63: ='2. Consolidated'!I232 -> 643.93671 | ... R63: ='2. Consolidated'!R232 -> 1099.6 | S63: =H63 -> 582.8 | T63: =M63 -> 912.5 | U63: =N63 -> 1035.1 | V63: =O63 -> 1219.2 | W63: =P63 -> 1197.5 | X63: =Q63 -> 1099.6 | Y63: =R63 -> 1099.6 | Z63: ='2. Consolidated'!Z232 -> 1100.6 | AA63: ='2. Consolidated'!AA232 -> 1241 | AB63: ='2. Consolidated'!AB232 -> 1338.5 | AC63: ='2. Consolidated'!AC232 -> 1223.3 | AD63: ='2. Consolidated'!AD232 -> 1223.3 | AE63: ='2. Consolidated'!AE232 -> 1267.2 | AF63: ='2. Consolidated'!AF232 -> 1597 | AG63: ='2. Consolidated'!AG232 -> 1710.4 | ... AX63: ='2. Consolidated'!AX232 -> 2327.5491
B64: ='2. Consolidated'!B326 -> Total Debt | C64: ='2. Consolidated'!C326 -> 6724.5 | D64: ='2. Consolidated'!D326 -> 6408.3309 | E64: ='2. Consolidated'!E326 -> 6234.3543 | F64: ='2. Consolidated'!F326 -> 6077.592 | G64: ='2. Consolidated'!G326 -> 6070.8 | H64: ='2. Consolidated'!H326 -> 6070.8 | I64: ='2. Consolidated'!I326 -> 5953.5298 | ... R64: ='2. Consolidated'!R326 -> 6321.4 | S64: =H64 -> 6070.8 | T64: =M64 -> 6039.5 | U64: =N64 -> 6118 | V64: =O64 -> 6213.2 | W64: =P64 -> 6179.6 | X64: =Q64 -> 6321.4 | Y64: =R64 -> 6321.4 | Z64: ='2. Consolidated'!Z326 -> 2027.2 | AA64: ='2. Consolidated'!AA326 -> 2045.5 | AB64: ='2. Consolidated'!AB326 -> 2270.8 | AC64: ='2. Consolidated'!AC326 -> 927.3 | AD64: ='2. Consolidated'!AD326 -> 927.3 | AE64: ='2. Consolidated'!AE326 -> 928.6 | AF64: ='2. Consolidated'!AF326 -> 934.7 | AG64: ='2. Consolidated'!AG326 -> 1145.3 | ... AX64: ='2. Consolidated'!AX326 -> 147.4
B65: ='2. Consolidated'!B327 -> Net Debt | C65: ='2. Consolidated'!C327 -> 6335 | D65: ='2. Consolidated'!D327 -> 6089.9761 | E65: ='2. Consolidated'!E327 -> 5765.1131 | F65: ='2. Consolidated'!F327 -> 5714.4974 | G65: ='2. Consolidated'!G327 -> 5504.1 | H65: ='2. Consolidated'!H327 -> 5504.1 | I65: ='2. Consolidated'!I327 -> 5475.1892 | ... R65: ='2. Consolidated'!R327 -> 5838 | S65: =H65 -> 5504.1 | T65: =M65 -> 5637.5 | U65: =N65 -> 5769.7 | V65: =O65 -> 5934.7 | W65: =P65 -> 5895.4 | X65: =Q65 -> 5838 | Y65: =R65 -> 5838 | Z65: ='2. Consolidated'!Z327 -> 1689.9 | AA65: ='2. Consolidated'!AA327 -> 1789.6 | AB65: ='2. Consolidated'!AB327 -> 1958.8 | AC65: ='2. Consolidated'!AC327 -> 581.9 | AD65: ='2. Consolidated'!AD327 -> 581.9 | AE65: ='2. Consolidated'!AE327 -> 506.5 | AF65: ='2. Consolidated'!AF327 -> 631.3 | AG65: ='2. Consolidated'!AG327 -> 792 | ... AX65: ='2. Consolidated'!AX327 -> -2689.866
B67: ='2. Consolidated'!B144 -> Cash from Operations | C67: ='2. Consolidated'!C144 -> 297.98724 | D67: ='2. Consolidated'!D144 -> 37.527832 | E67: ='2. Consolidated'!E144 -> 36.80708 | F67: ='2. Consolidated'!F144 -> -37.381292 | G67: ='2. Consolidated'!G144 -> 231.05323 | H67: ='2. Consolidated'!H144 -> 268.03585 | I67: ='2. Consolidated'!I144 -> -36.987854 | ... R67: ='2. Consolidated'!R144 -> 199.1 | S67: =H67 -> 268.03585 | T67: =M67 -> -91.740027 | U67: =N67 -> 57.3 | V67: =O67 -> -94.825442 | W67: =P67 -> -68.77422 | X67: =Q67 -> 305.39966 | Y67: =R67 -> 199.1 | Z67: ='2. Consolidated'!Z144 -> 116.5 | AA67: ='2. Consolidated'!AA144 -> -49.7 | AB67: ='2. Consolidated'!AB144 -> -48.9 | AC67: ='2. Consolidated'!AC144 -> 406.8 | AD67: ='2. Consolidated'!AD144 -> 424.7 | AE67: ='2. Consolidated'!AE144 -> 163.7 | AF67: ='2. Consolidated'!AF144 -> -56.2 | AG67: ='2. Consolidated'!AG144 -> -3.1 | ... AX67: ='2. Consolidated'!AX144 -> 1497.5929
B68: ='2. Consolidated'!B152 -> Cash from Investing | C68: ='2. Consolidated'!C152 -> -106.7 | D68: ='2. Consolidated'!D152 -> -26.809903 | E68: ='2. Consolidated'!E152 -> 380.08231 | F68: ='2. Consolidated'!F152 -> -25.907484 | G68: ='2. Consolidated'!G152 -> -31.964924 | H68: ='2. Consolidated'!H152 -> 295.4 | I68: ='2. Consolidated'!I152 -> -23.502722 | ... R68: ='2. Consolidated'!R152 -> -154.8 | S68: =H68 -> 295.4 | T68: =M68 -> -118.6 | U68: =N68 -> -27.8 | V68: =O68 -> -30.649512 | W68: =P68 -> -37.182825 | X68: =Q68 -> -59.167664 | Y68: =R68 -> -154.8 | Z68: ='2. Consolidated'!Z152 -> -67.3 | AA68: ='2. Consolidated'!AA152 -> -47.1 | AB68: ='2. Consolidated'!AB152 -> -64.5 | AC68: ='2. Consolidated'!AC152 -> -89.4 | AD68: ='2. Consolidated'!AD152 -> -268.3 | AE68: ='2. Consolidated'!AE152 -> -69.2 | AF68: ='2. Consolidated'!AF152 -> -66 | AG68: ='2. Consolidated'!AG152 -> -108.1 | ... AX68: ='2. Consolidated'!AX152 -> -400
B69: ='2. Consolidated'!B164 -> Cash from Financing | C69: ='2. Consolidated'!C164 -> -165.3 | D69: ='2. Consolidated'!D164 -> -40.536198 | E69: ='2. Consolidated'!E164 -> -298.03493 | F69: ='2. Consolidated'!F164 -> -35.232365 | G69: ='2. Consolidated'!G164 -> 4.0740266 | H69: ='2. Consolidated'!H164 -> -369.7 | I69: ='2. Consolidated'!I164 -> -19.024699 | ... R69: ='2. Consolidated'!R164 -> 35.1 | S69: =H69 -> -369.7 | T69: =M69 -> 81.1 | U69: =N69 -> -86.8 | V69: =O69 -> 64.15841 | W69: =P69 -> 119.98439 | X69: =Q69 -> -62.242799 | Y69: =R69 -> 35.1 | Z69: ='2. Consolidated'!Z164 -> -184.9 | AA69: ='2. Consolidated'!AA164 -> 19.1 | AB69: ='2. Consolidated'!AB164 -> 151.5 | AC69: ='2. Consolidated'!AC164 -> -251.7 | AD69: ='2. Consolidated'!AD164 -> -266 | AE69: ='2. Consolidated'!AE164 -> -27.4 | AF69: ='2. Consolidated'!AF164 -> -10.9 | AG69: ='2. Consolidated'!AG164 -> 152.6 | ... AX69: ='2. Consolidated'!AX164 -> 0
B70: ='2. Consolidated'!B153 -> Free Cash Flow | C70: ='2. Consolidated'!C153 -> 191.98724 | D70: ='2. Consolidated'!D153 -> 15.077435 | E70: ='2. Consolidated'!E153 -> 18.019235 | F70: ='2. Consolidated'!F153 -> -54.070065 | G70: ='2. Consolidated'!G153 -> 195.28025 | H70: ='2. Consolidated'!H153 -> 174.33585 | I70: ='2. Consolidated'!I153 -> -58.279696 | ... R70: ='2. Consolidated'!R153 -> 62.8 | S70: =H70 -> 174.33585 | T70: =M70 -> -201.54003 | U70: =N70 -> 31.8 | V70: =O70 -> -126.6388 | W70: =P70 -> -101.4447 | X70: =Q70 -> 259.0835 | Y70: =R70 -> 62.8 | Z70: ='2. Consolidated'!Z153 -> 53.3 | AA70: ='2. Consolidated'!AA153 -> -113.7 | AB70: ='2. Consolidated'!AB153 -> -106.6 | AC70: ='2. Consolidated'!AC153 -> 316.3 | AD70: ='2. Consolidated'!AD153 -> 149.3 | AE70: ='2. Consolidated'!AE153 -> 96 | AF70: ='2. Consolidated'!AF153 -> -117.7 | AG70: ='2. Consolidated'!AG153 -> -69.6 | ... AX70: ='2. Consolidated'!AX153 -> 1097.5929
