Workbook
Name \A: #REF!
Name \B: #REF!
Name \C: #REF!
Name \L: #REF!
Name \M: #REF!
Name \O: #REF!
Name \P: #REF!
Name \q: #REF!
Name \R: #REF!
Name \S: #REF!
Name \T: #REF!
Name \X: #REF!
Name \Z: #REF!
Name _: #REF!
Name __DAT1: #REF!
Name __DAT2: #REF!
Name __DAT3: #REF!
Name __DAT4: #REF!
Name __DAT5: #REF!
Name __DAT6: #REF!
Name __DAT7: #REF!
Name __DAT8: #REF!
Name _10_0pf1: #REF!
Name _107_._0Restructuring_char: #REF!
Name _108_._0Restructuring_char: #REF!
Name _116_._0SGA_gro: #REF!
Name _117_._0SGA_gro: #REF!
Name _125_._0Shares_repurchase_liabil: #REF!
Name _126_._0Shares_repurchase_liabil: #REF!
Name _134_0FAMERangeSheet: #REF!
Name _135_0FAMERangeSheet: #REF!
Name _143_0FAMERangeSheet: #REF!
Name _144_0FAMERangeSheet: #REF!
Name _152_0FAMERangeSheet: #REF!
Name _153_0FAMERangeSheet: #REF!
Name _161_0FAMERangeSheet: #REF!
Name _162_0FAMERangeSheet: #REF!
Name _17_0UniqueRang: #REF!
Name _170_0FAMERangeSheet: #REF!
Name _171_0FAMERangeSheet: #REF!
Name _179_0FAMERangeSheet: #REF!
Name _18_0UniqueRang: #REF!
Name _180_0FAMERangeSheet: #REF!
Name _188_0FAMERangeSheet: #REF!
Name _189_0FAMERangeSheet: #REF!
Name _197_0FAMERangeSheet: #REF!
Name _198_0FAMERangeSheet: #REF!
Name _1997BB: #REF!
Name _1997PL: #REF!
Name _1997PLQ: #REF!
Name _1998BB: #REF!
Name _1998PL: #REF!
Name _1998PLQ: #REF!
Name _1999BB: #REF!
Name _1999PL: #REF!
Name _1999PLQ: #REF!
Name _2: #REF!
Name _20_0_0TWX_Annual_Segments_Cha: #REF!
Name _2000BB: #REF!
Name _2000PL: #REF!

Sheet 1. Cover
F3: Lululemon Athetica Inc. (LULU)
F4: COMPANY MODEL
B9: Sources: Company data, Goldman Sachs Global Investment Research
B11: Date: September 4th, 2026
B13: Brooke Roach, CFA
B14: Managing Director
B15: tel: 212-357-2421
B16: brooke.roach@gs.com
B18: Mentesnot Adamu
B19: Analyst
B20: tel: 801-744-0630
B21: mentesnot.adamu@gs.com
B23: Carly Chasen
B24: Analyst
... B26: carly.chasen@gs.com

Sheet 2. Consolidated
B1: Lululemon Athletica Inc. (LULU)
B2: Consolidated
B3: $ millions except per-share data, fiscal year ending January
C5: 38383 | D5: 38472 | E5: 38564 | F5: 38656 | G5: 38748 | H5: =G5 -> 38748 | I5: =DATE(YEAR(D5)+1,MONTH(D5),DAY(D5)) -> 38837 | J5: =DATE(YEAR(E5)+1,MONTH(E5),DAY(E5)) -> 38929 | K5: =DATE(YEAR(F5)+1,MONTH(F5),DAY(F5)) -> 39021 | L5: =DATE(YEAR(G5)+1,MONTH(G5),DAY(G5)) -> 39113 | M5: =DATE(YEAR(H5)+1,MONTH(H5),DAY(H5)) -> 39113 | N5: =DATE(YEAR(I5)+1,MONTH(I5),DAY(I5)) -> 39202 | O5: =DATE(YEAR(J5)+1,MONTH(J5),DAY(J5)) -> 39294 | P5: =DATE(YEAR(K5)+1,MONTH(K5),DAY(K5)) -> 39386 | ... DS5: =DATE(YEAR(DN5)+1,MONTH(DN5),DAY(DN5)) -> 47149
C6: FY04 | D6: 1Q | E6: 2Q | F6: 3Q | G6: 4Q | H6: FY05 | I6: 1Q | J6: 2Q | K6: 3Q | L6: 4Q | M6: FY06 | N6: 1Q | O6: 2Q | P6: 3Q | Q6: 4Q | R6: FY07 | S6: 1Q | T6: 2Q | U6: 3Q | V6: 4Q | W6: FY08* | X6: 1Q | Y6: 2Q | Z6: 3Q | AA6: 4Q | AB6: FY09 | AC6: 1Q | AD6: 2Q | AE6: 3Q | AF6: 4Q | AG6: FY10 | AH6: 1Q | AI6: 2Q | AJ6: 3Q | AK6: 4Q | AL6: FY11 | AM6: 1Q | AN6: 2Q | AO6: 3Q | AP6: 4Q | AQ6: FY12* | AR6: 1Q | AS6: 2Q | AT6: 3Q | AU6: 4Q | AV6: FY13* | AW6: 1Q | AX6: 2Q | AY6: 3Q | AZ6: 4Q | BA6: FY14 | BB6: 1Q | BC6: 2Q | BD6: 3Q | BE6: 4Q | BF6: FY15 | BG6: 1Q | BH6: 2Q | BI6: 3Q | BJ6: 4Q | BK6: FY16 | BL6: 1Q | BM6: 2Q | BN6: 3Q | BO6: 4Q | BP6: FY17 | BQ6: 1Q | BR6: 2Q | BS6: 3Q | BT6: 4Q | BU6: FY18* | BV6: 1Q | BW6: 2Q | BX6: 3Q | BY6: 4Q | BZ6: FY19 | CA6: 1Q | CB6: 2Q | CC6: 3Q | CD6: 4Q | CE6: FY20 | CF6: 1Q | CG6: 2Q | CH6: 3Q | CI6: 4Q | CJ6: FY21 | CK6: 1Q | CL6: 2Q | CM6: 3QE | CN6: 4Q | CO6: FY22 | CP6: 1Q | CQ6: 2Q | CR6: 3Q | CS6: 4Q | CT6: FY23 | CU6: 1Q | CV6: 2Q | CW6: 3Q | CX6: 4Q | CY6: FY24 | CZ6: 1Q | DA6: 2Q | DB6: 3Q | DC6: 4Q | DD6: FY25 | DE6: 1Q | DF6: 2Q | DG6: 3QE | DH6: 4QE | DI6: FY26E | DJ6: 1QE | DK6: 2QE | DL6: 3QE | DM6: 4QE | DN6: FY27E | DO6: 1QE | DP6: 2QE | DQ6: 3QE | DR6: 4QE | DS6: FY28E
B7: DIVISIONAL SUMMARY
B8: Net Sales
B9: Stores | C9: ='3. Earnings Build'!C28 -> 29.906 | D9: ='3. Earnings Build'!D28 -> 11.052 | E9: ='3. Earnings Build'!E28 -> 13.455 | F9: ='3. Earnings Build'!F28 -> 15.62 | G9: ='3. Earnings Build'!G28 -> 25.45 | H9: =SUM(D9:G9) -> 65.577 | I9: ='3. Earnings Build'!I28 -> 22.146 | J9: ='3. Earnings Build'!J28 -> 26.831 | K9: ='3. Earnings Build'!K28 -> 29.145 | L9: ='3. Earnings Build'!L28 -> 42.612 | M9: =SUM(I9:L9) -> 120.734 | N9: ='3. Earnings Build'!N28 -> 38.008 | O9: ='3. Earnings Build'!O28 -> 53.1 | P9: ='3. Earnings Build'!P28 -> 59.9 | Q9: ='3. Earnings Build'!Q28 -> 92.5 | R9: =SUM(N9:Q9) -> 243.508 | S9: ='3. Earnings Build'!S28 -> 70.6 | T9: ='3. Earnings Build'!T28 -> 78.3 | U9: ='3. Earnings Build'!U28 -> 77.6 | V9: ='3. Earnings Build'!V28 -> 89.047803 | W9: =SUM(S9:V9) -> 315.5478 | X9: ='3. Earnings Build'!X28 -> 72.031 | Y9: ='3. Earnings Build'!Y28 -> 85.1 | Z9: ='3. Earnings Build'!Z28 -> 98.1 | AA9: ='3. Earnings Build'!AA28 -> 138.3 | AB9: =SUM(X9:AA9) -> 393.531 | AC9: ='3. Earnings Build'!AC28 -> 115.597 | AD9: ='3. Earnings Build'!AD28 -> 129.4 | AE9: ='3. Earnings Build'!AE28 -> 143.2 | AF9: ='3. Earnings Build'!AF28 -> 202.8 | AG9: =SUM(AC9:AF9) -> 590.997 | AH9: ='3. Earnings Build'!AH28 -> 156.5 | AI9: ='3. Earnings Build'!AI28 -> 178.223 | AJ9: ='3. Earnings Build'!AJ28 -> 190.016 | AK9: ='3. Earnings Build'!AK28 -> 292.47028 | AL9: =SUM(AH9:AK9) -> 817.20928 | AM9: ='3. Earnings Build'!AM28 -> 228.789 | AN9: ='3. Earnings Build'!AN28 -> 231.314 | AO9: ='3. Earnings Build'!AO28 -> 252.046 | AP9: ='3. Earnings Build'!AP28 -> 378.032 | AQ9: =SUM(AM9:AP9) -> 1090.181 | AR9: ='3. Earnings Build'!AR28 -> 269.357 | AS9: ='3. Earnings Build'!AS28 -> 273.768 | AT9: ='3. Earnings Build'!AT28 -> 290.666 | AU9: ='3. Earnings Build'!AU28 -> 395.208 | AV9: =SUM(AR9:AU9) -> 1228.999 | AW9: ='3. Earnings Build'!AW28 -> 288.101 | AX9: ='3. Earnings Build'!AX28 -> 294.04 | AY9: ='3. Earnings Build'!AY28 -> 310.014 | AZ9: ='3. Earnings Build'!AZ28 -> 456.07 | BA9: =SUM(AW9:AZ9) -> 1348.225 | BB9: ='3. Earnings Build'!BB28 -> 314.094 | BC9: ='3. Earnings Build'!BC28 -> 339.779 | BD9: ='3. Earnings Build'!BD28 -> 353.399 | BE9: ='3. Earnings Build'!BE28 -> 509.051 | BF9: =SUM(BB9:BE9) -> 1516.323 | BG9: ='3. Earnings Build'!BG28 -> 358.704 | BH9: ='3. Earnings Build'!BH28 -> 381.389 | BI9: ='3. Earnings Build'!BI28 -> 393.506 | BJ9: ='3. Earnings Build'!BJ28 -> 570.758 | BK9: =SUM(BG9:BJ9) -> 1704.357 | BL9: ='3. Earnings Build'!BL28 -> 379.099 | BM9: ='3. Earnings Build'!BM28 -> 413.944 | BN9: ='3. Earnings Build'!BN28 -> 425.1 | BO9: ='3. Earnings Build'!BO28 -> 618.9 | BP9: =SUM(BL9:BO9) -> 1837.043 | BQ9: ='3. Earnings Build'!BQ28 -> 433.12 | BR9: ='3. Earnings Build'!BR28 -> 486.4 | BS9: ='3. Earnings Build'!BS28 -> 476.877 | BT9: ='3. Earnings Build'!BT28 -> 729.966 | BU9: =SUM(BQ9:BT9) -> 2126.363 | BV9: ='3. Earnings Build'!BV28 -> 506.422 | BW9: ='3. Earnings Build'!BW28 -> 583.756 | BX9: ='3. Earnings Build'!BX28 -> 579.5 | BY9: ='3. Earnings Build'!BY28 -> 831.4 | BZ9: =SUM(BV9:BY9) -> 2501.078 | CA9: ='3. Earnings Build'!CA28 -> 259.97 | CB9: ='3. Earnings Build'!CB28 -> 287.2 | CC9: ='3. Earnings Build'!CC28 -> 511.756 | CD9: ='3. Earnings Build'!CD28 -> 599.881 | CE9: =SUM(CA9:CD9) -> 1658.807 | CF9: ='3. Earnings Build'!CF28 -> 536.584 | CG9: ='3. Earnings Build'!CG28 -> 695.12 | CH9: ='3. Earnings Build'!CH28 -> 707.16 | CI9: ='3. Earnings Build'!CI28 -> 882.633 | CJ9: =SUM(CF9:CI9) -> 2821.497 | CK9: ='3. Earnings Build'!CK28 -> 731.604 | CL9: ='3. Earnings Build'!CL28 -> 903.077 | CM9: ='3. Earnings Build'!CM28 -> 903.06 | CN9: ='3. Earnings Build'!CN28 -> 1110.386 | CO9: =SUM(CK9:CN9) -> 3648.127 | CP9: ='3. Earnings Build'!CP28 -> 958.087 | CQ9: ='3. Earnings Build'!CQ28 -> 1096.939 | CR9: ='3. Earnings Build'!CR28 -> 1073.973 | CS9: ='3. Earnings Build'!CS28 -> 1281.957 | CT9: =SUM(CP9:CS9) -> 4410.956 | CU9: ='3. Earnings Build'!CU28 -> 1070.525 | CV9: ='3. Earnings Build'!CV28 -> 1215.613 | CW9: ='3. Earnings Build'!CW28 -> 1210.523 | CX9: ='3. Earnings Build'!CX28 -> 1511.211 | CY9: =SUM(CU9:CX9) -> 5007.872 | CZ9: ='3. Earnings Build'!CZ28 -> 1153.107 | DA9: ='3. Earnings Build'!DA28 -> 1254.952 | DB9: ='3. Earnings Build'!DB28 -> 1206.558 | DC9: ='3. Earnings Build'!DC28 -> 1435.127 | DD9: =SUM(CZ9:DC9) -> 5049.744 | DE9: ='3. Earnings Build'!DE28 -> 1192.84 | DF9: ='3. Earnings Build'!DF28 -> 1173.747
B10: Direct | C10: ='3. Earnings Build'!C30 -> 0 | D10: ='3. Earnings Build'!D30 -> 0 | E10: ='3. Earnings Build'!E30 -> 0 | F10: ='3. Earnings Build'!F30 -> 0 | G10: ='3. Earnings Build'!G30 -> 0 | H10: =SUM(D10:G10) -> 0 | I10: ='3. Earnings Build'!I30 -> 0 | J10: ='3. Earnings Build'!J30 -> 0 | K10: ='3. Earnings Build'!K30 -> 0 | L10: ='3. Earnings Build'!L30 -> 0 | M10: =SUM(I10:L10) -> 0 | N10: ='3. Earnings Build'!N30 -> 0 | O10: ='3. Earnings Build'!O30 -> 0 | P10: ='3. Earnings Build'!P30 -> 0 | Q10: ='3. Earnings Build'!Q30 -> 0 | R10: =SUM(N10:Q10) -> 0 | S10: ='3. Earnings Build'!S30 -> 0 | T10: ='3. Earnings Build'!T30 -> 0 | U10: ='3. Earnings Build'!U30 -> 0 | V10: ='3. Earnings Build'!V30 -> 0 | W10: =SUM(S10:V10) -> 0 | X10: ='3. Earnings Build'!X30 -> 0.869 | Y10: ='3. Earnings Build'!Y30 -> 2.8 | Z10: ='3. Earnings Build'!Z30 -> 4.2 | AA10: ='3. Earnings Build'!AA30 -> 8.4 | AB10: =SUM(X10:AA10) -> 16.269 | AC10: ='3. Earnings Build'!AC30 -> 9.1278 | AD10: ='3. Earnings Build'!AD30 -> 9.6 | AE10: ='3. Earnings Build'!AE30 -> 13.4 | AF10: ='3. Earnings Build'!AF30 -> 24.6 | AG10: =SUM(AC10:AF10) -> 56.7278 | AH10: ='3. Earnings Build'!AH30 -> 13.82172 | AI10: ='3. Earnings Build'!AI30 -> 18.6 | AJ10: ='3. Earnings Build'!AJ30 -> 23.9 | AK10: ='3. Earnings Build'!AK30 -> 50.1 | AL10: =SUM(AH10:AK10) -> 106.42172 | AM10: ='3. Earnings Build'!AM30 -> 38.447 | AN10: ='3. Earnings Build'!AN30 -> 35.422 | AO10: ='3. Earnings Build'!AO30 -> 45.122 | AP10: ='3. Earnings Build'!AP30 -> 78.3 | AQ10: =SUM(AM10:AP10) -> 197.291 | AR10: ='3. Earnings Build'!AR30 -> 53.967 | AS10: ='3. Earnings Build'!AS30 -> 49.384 | AT10: ='3. Earnings Build'!AT30 -> 61.954 | AU10: ='3. Earnings Build'!AU30 -> 97.778 | AV10: =SUM(AR10:AU10) -> 263.083 | AW10: ='3. Earnings Build'!AW30 -> 65.974 | AX10: ='3. Earnings Build'!AX30 -> 63.5 | AY10: ='3. Earnings Build'!AY30 -> 77.203 | AZ10: ='3. Earnings Build'!AZ30 -> 114.5 | BA10: =SUM(AW10:AZ10) -> 321.177 | BB10: ='3. Earnings Build'!BB30 -> 83.636 | BC10: ='3. Earnings Build'!BC30 -> 82.239 | BD10: ='3. Earnings Build'!BD30 -> 89.33 | BE10: ='3. Earnings Build'!BE30 -> 146.32 | BF10: =SUM(BB10:BE10) -> 401.525 | BG10: ='3. Earnings Build'!BG30 -> 97.566 | BH10: ='3. Earnings Build'!BH30 -> 87.399 | BI10: ='3. Earnings Build'!BI30 -> 104.013 | BJ10: ='3. Earnings Build'!BJ30 -> 164.309 | BK10: =SUM(BG10:BJ10) -> 453.287 | BL10: ='3. Earnings Build'!BL30 -> 97.223 | BM10: ='3. Earnings Build'!BM30 -> 113.049 | BN10: ='3. Earnings Build'!BN30 -> 131.181 | BO10: ='3. Earnings Build'!BO30 -> 236.14 | BP10: =SUM(BL10:BO10) -> 577.593 | BQ10: ='3. Earnings Build'!BQ30 -> 157.82 | BR10: ='3. Earnings Build'!BR30 -> 167.4 | BS10: ='3. Earnings Build'!BS30 -> 189.375 | BT10: ='3. Earnings Build'!BT30 -> 344.261 | BU10: =SUM(BQ10:BT10) -> 858.856 | BV10: ='3. Earnings Build'!BV30 -> 209.844 | BW10: ='3. Earnings Build'!BW30 -> 217.636 | BX10: ='3. Earnings Build'!BX30 -> 246.7 | BY10: ='3. Earnings Build'!BY30 -> 463.6 | BZ10: =SUM(BV10:BY10) -> 1137.78 | CA10: ='3. Earnings Build'!CA30 -> 352.039 | CB10: ='3. Earnings Build'!CB30 -> 554.3 | CC10: ='3. Earnings Build'!CC30 -> 478.263 | CD10: ='3. Earnings Build'!CD30 -> 899.466 | CE10: =SUM(CA10:CD10) -> 2284.068 | CF10: ='3. Earnings Build'!CF30 -> 545.1 | CG10: ='3. Earnings Build'!CG30 -> 597.426 | CH10: ='3. Earnings Build'!CH30 -> 586.525 | CI10: ='3. Earnings Build'!CI30 -> 1048.893 | CJ10: =SUM(CF10:CI10) -> 2777.944 | CK10: ='3. Earnings Build'!CK30 -> 721.253 | CL10: ='3. Earnings Build'!CL30 -> 775.425 | CM10: ='3. Earnings Build'!CM30 -> 767.351 | CN10: ='3. Earnings Build'!CN30 -> 1435.762 | CO10: =SUM(CK10:CN10) -> 3699.791 | CP10: ='3. Earnings Build'!CP30 -> 834.942 | CQ10: ='3. Earnings Build'!CQ30 -> 893.673 | CR10: ='3. Earnings Build'!CR30 -> 908.127 | CS10: ='3. Earnings Build'!CS30 -> 1674.368 | CT10: =SUM(CP10:CS10) -> 4311.11 | CU10: ='3. Earnings Build'!CU30 -> 905.787 | CV10: ='3. Earnings Build'!CV30 -> 910.637 | CW10: ='3. Earnings Build'!CW30 -> 944.777 | CX10: ='3. Earnings Build'!CX30 -> 1809.245 | CY10: =SUM(CU10:CX10) -> 4570.446 | CZ10: ='3. Earnings Build'!CZ30 -> 960.89 | DA10: ='3. Earnings Build'!DA30 -> 993.093 | DB10: ='3. Earnings Build'!DB30 -> 1066.75 | DC10: ='3. Earnings Build'!DC30 -> 1897.964 | DD10: =SUM(CZ10:DC10) -> 4918.697 | DE10: ='3. Earnings Build'!DE30 -> 997.442 | DF10: ='3. Earnings Build'!DF30 -> 934.63
B11: Other | C11: ='3. Earnings Build'!C32 -> 10.843 | D11: ='3. Earnings Build'!D32 -> 4.578 | E11: ='3. Earnings Build'!E32 -> 3.671 | F11: ='3. Earnings Build'!F32 -> 4.364 | G11: ='3. Earnings Build'!G32 -> 5.939093 | H11: =SUM(D11:G11) -> 18.552093 | I11: ='3. Earnings Build'!I32 -> 6.038 | J11: ='3. Earnings Build'!J32 -> 5.686437 | K11: ='3. Earnings Build'!K32 -> 6.822615 | L11: ='3. Earnings Build'!L32 -> 9.603782 | M11: =SUM(I11:L11) -> 28.150834 | N11: ='3. Earnings Build'!N32 -> 6.781456 | O11: ='3. Earnings Build'!O32 -> 5.580944 | P11: ='3. Earnings Build'!P32 -> 6.25028 | Q11: ='3. Earnings Build'!Q32 -> 12.592648 | R11: =SUM(N11:Q11) -> 31.205328 | S11: ='3. Earnings Build'!S32 -> 7.567494 | T11: ='3. Earnings Build'!T32 -> 7.184223 | U11: ='3. Earnings Build'!U32 -> 9.447135 | V11: ='3. Earnings Build'!V32 -> 14.873197 | W11: =SUM(S11:V11) -> 39.072049 | X11: ='3. Earnings Build'!X32 -> 8.78 | Y11: ='3. Earnings Build'!Y32 -> 9.821 | Z11: ='3. Earnings Build'!Z32 -> 10.591 | AA11: ='3. Earnings Build'!AA32 -> 13.906 | AB11: =SUM(X11:AA11) -> 43.098 | AC11: ='3. Earnings Build'!AC32 -> 13.5722 | AD11: ='3. Earnings Build'!AD32 -> 13.208 | AE11: ='3. Earnings Build'!AE32 -> 19.2 | AF11: ='3. Earnings Build'!AF32 -> 17.999 | AG11: =SUM(AC11:AF11) -> 63.9792 | AH11: ='3. Earnings Build'!AH32 -> 16.45828 | AI11: ='3. Earnings Build'!AI32 -> 15.5 | AJ11: ='3. Earnings Build'!AJ32 -> 16.3 | AK11: ='3. Earnings Build'!AK32 -> 28.94972 | AL11: =SUM(AH11:AK11) -> 77.208 | AM11: ='3. Earnings Build'!AM32 -> 18.462 | AN11: ='3. Earnings Build'!AN32 -> 15.898 | AO11: ='3. Earnings Build'!AO32 -> 19.369 | AP11: ='3. Earnings Build'!AP32 -> 29.193 | AQ11: =SUM(AM11:AP11) -> 82.922 | AR11: ='3. Earnings Build'!AR32 -> 22.458 | AS11: ='3. Earnings Build'!AS32 -> 21.361 | AT11: ='3. Earnings Build'!AT32 -> 27.28 | AU11: ='3. Earnings Build'!AU32 -> 28.007 | AV11: =SUM(AR11:AU11) -> 99.106 | AW11: ='3. Earnings Build'!AW32 -> 30.543 | AX11: ='3. Earnings Build'!AX32 -> 33.187 | AY11: ='3. Earnings Build'!AY32 -> 32.179 | AZ11: ='3. Earnings Build'!AZ32 -> 31.899 | BA11: =SUM(AW11:AZ11) -> 127.808 | BB11: ='3. Earnings Build'!BB32 -> 25.814 | BC11: ='3. Earnings Build'!BC32 -> 30.992 | BD11: ='3. Earnings Build'!BD32 -> 36.964 | BE11: ='3. Earnings Build'!BE32 -> 48.905 | BF11: =SUM(BB11:BE11) -> 142.675 | BG11: ='3. Earnings Build'!BG32 -> 39.246 | BH11: ='3. Earnings Build'!BH32 -> 45.732 | BI11: ='3. Earnings Build'!BI32 -> 46.897 | BJ11: ='3. Earnings Build'!BJ32 -> 54.873 | BK11: =SUM(BG11:BJ11) -> 186.748 | BL11: ='3. Earnings Build'!BL32 -> 43.985 | BM11: ='3. Earnings Build'!BM32 -> 54.061 | BN11: ='3. Earnings Build'!BN32 -> 62.753 | BO11: ='3. Earnings Build'!BO32 -> 73.74 | BP11: =SUM(BL11:BO11) -> 234.539 | BQ11: ='3. Earnings Build'!BQ32 -> 58.72 | BR11: ='3. Earnings Build'!BR32 -> 69.7 | BS11: ='3. Earnings Build'!BS32 -> 81.403 | BT11: ='3. Earnings Build'!BT32 -> 93.277 | BU11: =SUM(BQ11:BT11) -> 303.1 | BV11: ='3. Earnings Build'!BV32 -> 66.049 | BW11: ='3. Earnings Build'!BW32 -> 81.96 | BX11: ='3. Earnings Build'!BX32 -> 89.9 | BY11: ='3. Earnings Build'!BY32 -> 102.5 | BZ11: =SUM(BV11:BY11) -> 340.409 | CA11: ='3. Earnings Build'!CA32 -> 39.953 | CB11: ='3. Earnings Build'!CB32 -> 61.439 | CC11: ='3. Earnings Build'!CC32 -> 127.407 | CD11: ='3. Earnings Build'!CD32 -> 230.205 | CE11: =SUM(CA11:CD11) -> 459.004 | CF11: ='3. Earnings Build'!CF32 -> 144.792 | CG11: ='3. Earnings Build'!CG32 -> 158.072 | CH11: ='3. Earnings Build'!CH32 -> 156.736 | CI11: ='3. Earnings Build'!CI32 -> 197.576 | CJ11: =SUM(CF11:CI11) -> 657.176 | CK11: ='3. Earnings Build'!CK32 -> 160.606 | CL11: ='3. Earnings Build'!CL32 -> 189.826 | CM11: ='3. Earnings Build'!CM32 -> 186.478 | CN11: ='3. Earnings Build'!CN32 -> 225.69 | CO11: =SUM(CK11:CN11) -> 762.6 | CP11: ='3. Earnings Build'!CP32 -> 207.763 | CQ11: ='3. Earnings Build'!CQ32 -> 218.553 | CR11: ='3. Earnings Build'!CR32 -> 222.118 | CS11: ='3. Earnings Build'!CS32 -> 248.778 | CT11: =SUM(CP11:CS11) -> 897.212 | CU11: ='3. Earnings Build'!CU32 -> 232.579 | CV11: ='3. Earnings Build'!CV32 -> 244.828 | CW11: ='3. Earnings Build'!CW32 -> 241.36 | CX11: ='3. Earnings Build'!CX32 -> 291.041 | CY11: =SUM(CU11:CX11) -> 1009.808 | CZ11: ='3. Earnings Build'!CZ32 -> 256.663 | DA11: ='3. Earnings Build'!DA32 -> 277.174 | DB11: ='3. Earnings Build'!DB32 -> 292.612 | DC11: ='3. Earnings Build'!DC32 -> 307.71 | DD11: =SUM(CZ11:DC11) -> 1134.159 | DE11: ='3. Earnings Build'!DE32 -> 281.321 | DF11: ='3. Earnings Build'!DF32 -> 307.254
B12: Total | C12: =SUM(C9:C11) -> 40.749 | D12: =SUM(D9:D11) -> 15.63 | E12: =SUM(E9:E11) -> 17.126 | F12: =SUM(F9:F11) -> 19.984 | G12: =SUM(G9:G11) -> 31.389093 | H12: =SUM(H9:H11) -> 84.129093 | I12: =SUM(I9:I11) -> 28.184 | J12: =SUM(J9:J11) -> 32.517437 | ... DF12: =SUM(DF9:DF11) -> 2415.631
B14: Americas | CO14: ='3. Earnings Build'!CO10 -> 6817.454 | CP14: ='3. Earnings Build'!CP10 -> 1567.738 | CQ14: ='3. Earnings Build'!CQ10 -> 1719.773 | CR14: ='3. Earnings Build'!CR10 -> 1732.398 | CS14: ='3. Earnings Build'!CS10 -> 2611.738 | CT14: ='3. Earnings Build'!CT10 -> 7631.647 | CU14: ='3. Earnings Build'!CU10 -> 1622.264 | CV14: ='3. Earnings Build'!CV10 -> 1741.433 | ... DS14: ='3. Earnings Build'!DS10 -> 6312.3848
B15: Mainland China | CO15: ='3. Earnings Build'!CO11 -> 576.503 | CP15: ='3. Earnings Build'!CP11 -> 210.068 | CQ15: ='3. Earnings Build'!CQ11 -> 234.445 | CR15: ='3. Earnings Build'!CR11 -> 228.595 | CS15: ='3. Earnings Build'!CS11 -> 290.652 | CT15: ='3. Earnings Build'!CT11 -> 963.76 | CU15: ='3. Earnings Build'!CU11 -> 303.786 | CV15: ='3. Earnings Build'!CV11 -> 314.189 | ... DS15: ='3. Earnings Build'!DS11 -> 2185.8684
B16: Rest of World | CO16: ='3. Earnings Build'!CO12 -> 716.561 | CP16: ='3. Earnings Build'!CP12 -> 222.986 | CQ16: ='3. Earnings Build'!CQ12 -> 254.947 | CR16: ='3. Earnings Build'!CR12 -> 243.225 | CS16: ='3. Earnings Build'!CS12 -> 302.713 | CT16: ='3. Earnings Build'!CT12 -> 1023.871 | CU16: ='3. Earnings Build'!CU12 -> 282.841 | CV16: ='3. Earnings Build'!CV12 -> 315.456 | ... DS16: ='3. Earnings Build'!DS12 -> 1832.7337
B17: Total | CO17: =CO14+CO15+CO16 -> 8110.518 | CP17: =CP14+CP15+CP16 -> 2000.792 | CQ17: =CQ14+CQ15+CQ16 -> 2209.165 | CR17: =CR14+CR15+CR16 -> 2204.218 | CS17: =CS14+CS15+CS16 -> 3205.103 | CT17: =CT14+CT15+CT16 -> 9619.278 | CU17: =CU14+CU15+CU16 -> 2208.891 | CV17: =CV14+CV15+CV16 -> 2371.078 | ... DS17: =DS14+DS15+DS16 -> 10330.987
B19: Operating Income
B20: Stores | N20: ='3. Earnings Build'!N149 -> 11.891 | O20: ='3. Earnings Build'!O149 -> 16.943 | P20: ='3. Earnings Build'!P149 -> 19.278 | Q20: ='3. Earnings Build'!Q149 -> 31.688 | R20: =SUM(N20:Q20) -> 79.8 | S20: ='3. Earnings Build'!S149 -> 23.217 | T20: ='3. Earnings Build'!T149 -> 23.758 | U20: ='3. Earnings Build'!U149 -> 21.401 | V20: ='3. Earnings Build'!V149 -> 26.524 | W20: =SUM(S20:V20) -> 94.9 | X20: ='3. Earnings Build'!X149 -> 21.687 | Y20: ='3. Earnings Build'!Y149 -> 23.548 | Z20: ='3. Earnings Build'!Z149 -> 30.76 | AA20: ='3. Earnings Build'!AA149 -> 45.619 | AB20: =SUM(X20:AA20) -> 121.614 | AC20: ='3. Earnings Build'!AC149 -> 45.955 | AD20: ='3. Earnings Build'!AD149 -> 44.353 | AE20: ='3. Earnings Build'!AE149 -> 50.787 | AF20: ='3. Earnings Build'!AF149 -> 74.059 | AG20: =SUM(AC20:AF20) -> 215.154 | AH20: ='3. Earnings Build'!AH149 -> 59.137 | AI20: ='3. Earnings Build'!AI149 -> 64.073 | AJ20: ='3. Earnings Build'!AJ149 -> 66.331 | AK20: ='3. Earnings Build'!AK149 -> 109.433 | AL20: =SUM(AH20:AK20) -> 298.974 | AM20: ='3. Earnings Build'!AM149 -> 77.252 | AN20: ='3. Earnings Build'!AN149 -> 77.04 | AO20: ='3. Earnings Build'!AO149 -> 84.699 | AP20: ='3. Earnings Build'!AP149 -> 140.679 | AQ20: =SUM(AM20:AP20) -> 379.67 | AR20: ='3. Earnings Build'!AR149 -> 69.559 | AS20: ='3. Earnings Build'!AS149 -> 83.53 | AT20: ='3. Earnings Build'!AT149 -> 89.676 | AU20: ='3. Earnings Build'!AU149 -> 129.866 | AV20: =SUM(AR20:AU20) -> 372.631 | AW20: ='3. Earnings Build'!AW149 -> 75.697 | AX20: ='3. Earnings Build'!AX149 -> 74.891 | AY20: ='3. Earnings Build'!AY149 -> 73.99 | AZ20: ='3. Earnings Build'!AZ149 -> 132.011 | BA20: =SUM(AW20:AZ20) -> 356.589 | BB20: ='3. Earnings Build'!BB149 -> 69.223 | BC20: ='3. Earnings Build'!BC149 -> 67.441 | BD20: ='3. Earnings Build'!BD149 -> 70.729 | BE20: ='3. Earnings Build'!BE149 -> 139.409 | BF20: =SUM(BB20:BE20) -> 346.802 | BG20: ='3. Earnings Build'!BG149 -> 73.259 | BH20: ='3. Earnings Build'!BH149 -> 80.277 | BI20: ='3. Earnings Build'!BI149 -> 91.497 | BJ20: ='3. Earnings Build'!BJ149 -> 170.602 | BK20: =SUM(BG20:BJ20) -> 415.635 | BL20: ='3. Earnings Build'!BL149 -> 77.499 | BM20: ='3. Earnings Build'!BM149 -> 92.609 | BN20: ='3. Earnings Build'!BN149 -> 97.015 | BO20: ='3. Earnings Build'!BO149 -> 197.198 | BP20: =SUM(BL20:BO20) -> 464.321 | BQ20: ='3. Earnings Build'!BQ149 -> 99.287 | BR20: ='3. Earnings Build'!BR149 -> 125.868 | BS20: ='3. Earnings Build'!BS149 -> 117.804 | BT20: ='3. Earnings Build'!BT149 -> 232.577 | BU20: =SUM(BQ20:BT20) -> 575.536 | BV20: ='3. Earnings Build'!BV149 -> 120.907 | BW20: ='3. Earnings Build'!BW149 -> 154.332 | BX20: ='3. Earnings Build'!BX149 -> 147.734 | BY20: ='3. Earnings Build'!BY149 -> 266.366 | BZ20: =SUM(BV20:BY20) -> 689.339 | CA20: ='3. Earnings Build'!CA149 -> -30.154 | CB20: ='3. Earnings Build'!CB149 -> -5.293 | CC20: ='3. Earnings Build'!CC149 -> 111.78 | CD20: ='3. Earnings Build'!CD149 -> 136.259 | CE20: =SUM(CA20:CD20) -> 212.592 | CF20: ='3. Earnings Build'!CF149 -> 99.148 | CG20: ='3. Earnings Build'!CG149 -> 184.996 | CH20: ='3. Earnings Build'!CH149 -> 180.7 | CI20: ='3. Earnings Build'!CI149 -> 262.891 | CJ20: =SUM(CF20:CI20) -> 727.735 | CK20: ='3. Earnings Build'!CK149 -> 160.706 | CL20: ='3. Earnings Build'!CL149 -> 256.807 | CM20: ='3. Earnings Build'!CM149 -> 242.733 | CN20: ='3. Earnings Build'!CN149 -> 330.821 | CO20: =SUM(CK20:CN20) -> 991.067 | CP20: ='3. Earnings Build'!CP149 -> 259.819 | CQ20: ='3. Earnings Build'!CQ149 -> 339.692 | CR20: ='3. Earnings Build'!CR149 -> 310.51 | CS20: ='3. Earnings Build'!CS149 -> 400 | CT20: =SUM(CP20:CS20) -> 1310.021
B21: Direct | N21: ='3. Earnings Build'!N150 -> 0 | O21: ='3. Earnings Build'!O150 -> 0 | P21: ='3. Earnings Build'!P150 -> 0 | Q21: ='3. Earnings Build'!Q150 -> 0 | R21: =SUM(N21:Q21) -> 0 | S21: ='3. Earnings Build'!S150 -> 0 | T21: ='3. Earnings Build'!T150 -> 0 | U21: ='3. Earnings Build'!U150 -> 0 | V21: ='3. Earnings Build'!V150 -> 0 | W21: =SUM(S21:V21) -> 0 | X21: ='3. Earnings Build'!X150 -> 0.365 | Y21: ='3. Earnings Build'!Y150 -> 1.199 | Z21: ='3. Earnings Build'!Z150 -> 1.811 | AA21: ='3. Earnings Build'!AA150 -> 2.913 | AB21: =SUM(X21:AA21) -> 6.288 | AC21: ='3. Earnings Build'!AC150 -> 3.242 | AD21: ='3. Earnings Build'!AD150 -> 2.817 | AE21: ='3. Earnings Build'!AE150 -> 3.901 | AF21: ='3. Earnings Build'!AF150 -> 6.404 | AG21: =SUM(AC21:AF21) -> 16.364 | AH21: ='3. Earnings Build'!AH150 -> 4.291 | AI21: ='3. Earnings Build'!AI150 -> 8.178 | AJ21: ='3. Earnings Build'!AJ150 -> 9.098 | AK21: ='3. Earnings Build'!AK150 -> 22.601 | AL21: =SUM(AH21:AK21) -> 44.168 | AM21: ='3. Earnings Build'!AM150 -> 17.057 | AN21: ='3. Earnings Build'!AN150 -> 14.085 | AO21: ='3. Earnings Build'!AO150 -> 18.373 | AP21: ='3. Earnings Build'!AP150 -> 33.432 | AQ21: =SUM(AM21:AP21) -> 82.947 | AR21: ='3. Earnings Build'!AR150 -> 21.216 | AS21: ='3. Earnings Build'!AS150 -> 20.633 | AT21: ='3. Earnings Build'!AT150 -> 27.98 | AU21: ='3. Earnings Build'!AU150 -> 39.74 | AV21: =SUM(AR21:AU21) -> 109.569 | AW21: ='3. Earnings Build'!AW150 -> 27.117 | AX21: ='3. Earnings Build'!AX150 -> 24.087 | AY21: ='3. Earnings Build'!AY150 -> 32.292 | AZ21: ='3. Earnings Build'!AZ150 -> 49.381 | BA21: =SUM(AW21:AZ21) -> 132.877 | BB21: ='3. Earnings Build'!BB150 -> 34.871 | BC21: ='3. Earnings Build'!BC150 -> 32.25 | BD21: ='3. Earnings Build'!BD150 -> 37.985 | BE21: ='3. Earnings Build'!BE150 -> 61.312 | BF21: =SUM(BB21:BE21) -> 166.418 | BG21: ='3. Earnings Build'!BG150 -> 38.551 | BH21: ='3. Earnings Build'!BH150 -> 32.644 | BI21: ='3. Earnings Build'!BI150 -> 43.588 | BJ21: ='3. Earnings Build'!BJ150 -> 71.395 | BK21: =SUM(BG21:BJ21) -> 186.178 | BL21: ='3. Earnings Build'!BL150 -> 35.442 | BM21: ='3. Earnings Build'!BM150 -> 40.139 | BN21: ='3. Earnings Build'!BN150 -> 52.201 | BO21: ='3. Earnings Build'!BO150 -> 103.513 | BP21: =SUM(BL21:BO21) -> 231.295 | BQ21: ='3. Earnings Build'!BQ150 -> 62.267 | BR21: ='3. Earnings Build'!BR150 -> 67.033 | BS21: ='3. Earnings Build'!BS150 -> 76.435 | BT21: ='3. Earnings Build'!BT150 -> 148.372 | BU21: =SUM(BQ21:BT21) -> 354.107 | BV21: ='3. Earnings Build'!BV150 -> 78.675 | BW21: ='3. Earnings Build'!BW150 -> 86.081 | BX21: ='3. Earnings Build'!BX150 -> 103.282 | BY21: ='3. Earnings Build'!BY150 -> 214.33 | BZ21: =SUM(BV21:BY21) -> 482.368 | CA21: ='3. Earnings Build'!CA150 -> 156.947 | CB21: ='3. Earnings Build'!CB150 -> 237.595 | CC21: ='3. Earnings Build'!CC150 -> 209.61 | CD21: ='3. Earnings Build'!CD150 -> 424.95 | CE21: =SUM(CA21:CD21) -> 1029.102 | CF21: ='3. Earnings Build'!CF150 -> 236.933 | CG21: ='3. Earnings Build'!CG150 -> 260.248 | CH21: ='3. Earnings Build'!CH150 -> 257.05 | CI21: ='3. Earnings Build'!CI150 -> 462.265 | CJ21: =SUM(CF21:CI21) -> 1216.496 | CK21: ='3. Earnings Build'!CK150 -> 285.107 | CL21: ='3. Earnings Build'!CL150 -> 326.423 | CM21: ='3. Earnings Build'!CM150 -> 321.742 | CN21: ='3. Earnings Build'!CN150 -> 629.266 | CO21: =SUM(CK21:CN21) -> 1562.538 | CP21: ='3. Earnings Build'!CP150 -> 369.453 | CQ21: ='3. Earnings Build'!CQ150 -> 383.87 | CR21: ='3. Earnings Build'!CR150 -> 384.393 | CS21: ='3. Earnings Build'!CS150 -> 750 | CT21: =SUM(CP21:CS21) -> 1887.716
B22: Other | N22: ='3. Earnings Build'!N151 -> 3.157 | O22: ='3. Earnings Build'!O151 -> 2.061 | P22: ='3. Earnings Build'!P151 -> 2.03 | Q22: ='3. Earnings Build'!Q151 -> 7.152 | R22: =SUM(N22:Q22) -> 14.4 | S22: ='3. Earnings Build'!S151 -> 3.875 | T22: ='3. Earnings Build'!T151 -> 2.963 | U22: ='3. Earnings Build'!U151 -> 2.58 | V22: ='3. Earnings Build'!V151 -> 9.982 | W22: =SUM(S22:V22) -> 19.4 | X22: ='3. Earnings Build'!X151 -> 2.198 | Y22: ='3. Earnings Build'!Y151 -> 2.818 | Z22: ='3. Earnings Build'!Z151 -> 2.776 | AA22: ='3. Earnings Build'!AA151 -> 3.053 | AB22: =SUM(X22:AA22) -> 10.845 | AC22: ='3. Earnings Build'!AC151 -> 4.632 | AD22: ='3. Earnings Build'!AD151 -> 3.31 | AE22: ='3. Earnings Build'!AE151 -> 5.543 | AF22: ='3. Earnings Build'!AF151 -> 4.519 | AG22: =SUM(AC22:AF22) -> 18.004 | AH22: ='3. Earnings Build'!AH151 -> 4.993 | AI22: ='3. Earnings Build'!AI151 -> 4.704 | AJ22: ='3. Earnings Build'!AJ151 -> 3.663 | AK22: ='3. Earnings Build'!AK151 -> 7.865 | AL22: =SUM(AH22:AK22) -> 21.225 | AM22: ='3. Earnings Build'!AM151 -> 3.856 | AN22: ='3. Earnings Build'!AN151 -> 3.008 | AO22: ='3. Earnings Build'!AO151 -> 4.049 | AP22: ='3. Earnings Build'!AP151 -> 6.457 | AQ22: =SUM(AM22:AP22) -> 17.37 | AR22: ='3. Earnings Build'!AR151 -> 4.404 | AS22: ='3. Earnings Build'!AS151 -> 3.325 | AT22: ='3. Earnings Build'!AT151 -> 4.597 | AU22: ='3. Earnings Build'!AU151 -> 3.781 | AV22: =SUM(AR22:AU22) -> 16.107 | AW22: ='3. Earnings Build'!AW151 -> 3.276 | AX22: ='3. Earnings Build'!AX151 -> 3.496 | AY22: ='3. Earnings Build'!AY151 -> 3.279 | AZ22: ='3. Earnings Build'!AZ151 -> -0.552 | BA22: =SUM(AW22:AZ22) -> 9.499 | BB22: ='3. Earnings Build'!BB151 -> 0.981 | BC22: ='3. Earnings Build'!BC151 -> 1.82 | BD22: ='3. Earnings Build'!BD151 -> 1.569 | BE22: ='3. Earnings Build'!BE151 -> 1.456 | BF22: =SUM(BB22:BE22) -> 5.826 | BG22: ='3. Earnings Build'!BG151 -> 2.069 | BH22: ='3. Earnings Build'!BH151 -> 4.636 | BI22: ='3. Earnings Build'!BI151 -> 5.709 | BJ22: ='3. Earnings Build'!BJ151 -> 9.898 | BK22: =SUM(BG22:BJ22) -> 22.312 | BL22: ='3. Earnings Build'!BL151 -> 2.836 | BM22: ='3. Earnings Build'!BM151 -> 6.952 | BN22: ='3. Earnings Build'!BN151 -> 9.319 | BO22: ='3. Earnings Build'!BO151 -> 16.473 | BP22: =SUM(BL22:BO22) -> 35.58 | BQ22: ='3. Earnings Build'!BQ151 -> 11.223 | BR22: ='3. Earnings Build'!BR151 -> 13.094 | BS22: ='3. Earnings Build'!BS151 -> 15.019 | BT22: ='3. Earnings Build'!BT151 -> 23.252 | BU22: =SUM(BQ22:BT22) -> 62.588 | BV22: ='3. Earnings Build'!BV151 -> 12.633 | BW22: ='3. Earnings Build'!BW151 -> 16.619 | BX22: ='3. Earnings Build'!BX151 -> 16.944 | BY22: ='3. Earnings Build'!BY151 -> 26.363 | BZ22: =SUM(BV22:BY22) -> 72.559 | CA22: ='3. Earnings Build'!CA151 -> -0.269 | CB22: ='3. Earnings Build'!CB151 -> 2.587 | CC22: ='3. Earnings Build'!CC151 -> 1.304 | CD22: ='3. Earnings Build'!CD151 -> 6.88 | CE22: =SUM(CA22:CD22) -> 10.502 | CF22: ='3. Earnings Build'!CF151 -> 14.506 | CG22: ='3. Earnings Build'!CG151 -> 22.24 | CH22: ='3. Earnings Build'!CH151 -> 27.45 | CI22: ='3. Earnings Build'!CI151 -> 13.087 | CJ22: =SUM(CF22:CI22) -> 77.283 | CK22: ='3. Earnings Build'!CK151 -> 19.527 | CL22: ='3. Earnings Build'!CL151 -> 29.626 | CM22: ='3. Earnings Build'!CM151 -> 24.911 | CN22: ='3. Earnings Build'!CN151 -> 33.019 | CO22: =SUM(CK22:CN22) -> 107.083 | CP22: ='3. Earnings Build'!CP151 -> 44.083 | CQ22: ='3. Earnings Build'!CQ151 -> 48.683 | CR22: ='3. Earnings Build'!CR151 -> 53.527 | CS22: ='3. Earnings Build'!CS151 -> 36.3 | CT22: =SUM(CP22:CS22) -> 182.593
B23: Segment Operating Profit | N23: =SUM(N20:N22) -> 15.048 | O23: =SUM(O20:O22) -> 19.004 | P23: =SUM(P20:P22) -> 21.308 | Q23: =SUM(Q20:Q22) -> 38.84 | R23: =SUM(R20:R22) -> 94.2 | S23: =SUM(S20:S22) -> 27.092 | T23: =SUM(T20:T22) -> 26.721 | U23: =SUM(U20:U22) -> 23.981 | ... CT23: =SUM(CT20:CT22) -> 3380.33
B24: Corporate Expense | N24: ='3. Earnings Build'!N156 -> -8.201 | O24: ='3. Earnings Build'!O156 -> -9.26 | P24: ='3. Earnings Build'!P156 -> -9.461 | Q24: ='3. Earnings Build'!Q156 -> -17.178 | R24: =SUM(N24:Q24) -> -44.1 | S24: ='3. Earnings Build'!S156 -> -15.371 | T24: ='3. Earnings Build'!T156 -> -11.179 | U24: ='3. Earnings Build'!U156 -> -10.926 | V24: ='3. Earnings Build'!V156 -> -16.024 | W24: =SUM(S24:V24) -> -53.5 | X24: ='3. Earnings Build'!X156 -> -14.397 | Y24: ='3. Earnings Build'!Y156 -> -13.233 | Z24: ='3. Earnings Build'!Z156 -> -14.421 | AA24: ='3. Earnings Build'!AA156 -> -9.949 | AB24: =SUM(X24:AA24) -> -52 | AC24: ='3. Earnings Build'!AC156 -> -21.355 | AD24: ='3. Earnings Build'!AD156 -> -16.237 | AE24: ='3. Earnings Build'!AE156 -> -17.855 | AF24: ='3. Earnings Build'!AF156 -> -13.653 | AG24: =SUM(AC24:AF24) -> -69.1 | AH24: ='3. Earnings Build'!AH156 -> -16.734 | AI24: ='3. Earnings Build'!AI156 -> -17.472 | AJ24: ='3. Earnings Build'!AJ156 -> -19.371 | AK24: ='3. Earnings Build'!AK156 -> -23.823 | AL24: =SUM(AH24:AK24) -> -77.4 | AM24: ='3. Earnings Build'!AM156 -> -25.1 | AN24: ='3. Earnings Build'!AN156 -> -23.945 | AO24: ='3. Earnings Build'!AO156 -> -26.51 | AP24: ='3. Earnings Build'!AP156 -> -27.993 | AQ24: =SUM(AM24:AP24) -> -103.548 | AR24: ='3. Earnings Build'!AR156 -> -29.29 | AS24: ='3. Earnings Build'!AS156 -> -28.502 | AT24: ='3. Earnings Build'!AT156 -> -29.917 | AU24: ='3. Earnings Build'!AU156 -> -19.24 | AV24: =SUM(AR24:AU24) -> -106.949 | AW24: ='3. Earnings Build'!AW156 -> -36.289 | AX24: ='3. Earnings Build'!AX156 -> -34.586 | AY24: ='3. Earnings Build'!AY156 -> -28.405 | AZ24: ='3. Earnings Build'!AZ156 -> -23.652 | BA24: =SUM(AW24:AZ24) -> -122.932 | BB24: ='3. Earnings Build'!BB156 -> -37.039 | BC24: ='3. Earnings Build'!BC156 -> -34.932 | BD24: ='3. Earnings Build'!BD156 -> -42.105 | BE24: ='3. Earnings Build'!BE156 -> -35.894 | BF24: =SUM(BB24:BE24) -> -149.97 | BG24: ='3. Earnings Build'!BG156 -> -56.29 | BH24: ='3. Earnings Build'!BH156 -> -43.598 | BI24: ='3. Earnings Build'!BI156 -> -47.819 | BJ24: ='3. Earnings Build'!BJ156 -> -55.266 | BK24: =SUM(BG24:BJ24) -> -202.973 | BL24: ='3. Earnings Build'!BL156 -> -52.604 | BM24: ='3. Earnings Build'!BM156 -> -65.558 | BN24: ='3. Earnings Build'!BN156 -> -50.762 | BO24: ='3. Earnings Build'!BO156 -> -59.048 | BP24: =SUM(BL24:BO24) -> -227.972 | BQ24: ='3. Earnings Build'!BQ156 -> -68.472 | BR24: ='3. Earnings Build'!BR156 -> -71.787 | BS24: ='3. Earnings Build'!BS156 -> -73.355 | BT24: ='3. Earnings Build'!BT156 -> -72.751 | BU24: =SUM(BQ24:BT24) -> -286.365 | BV24: ='3. Earnings Build'!BV156 -> -83.403 | BW24: ='3. Earnings Build'!BW156 -> -89.05 | BX24: ='3. Earnings Build'!BX156 -> -92.131 | BY24: ='3. Earnings Build'!BY156 -> -90.572 | BZ24: =SUM(BV24:BY24) -> -355.156 | CA24: ='3. Earnings Build'!CA156 -> -93.773 | CB24: ='3. Earnings Build'!CB156 -> -99.016 | CC24: ='3. Earnings Build'!CC156 -> -107.002 | CD24: ='3. Earnings Build'!CD156 -> -100.186 | CE24: =SUM(CA24:CD24) -> -399.977 | CF24: ='3. Earnings Build'!CF156 -> -146.907 | CG24: ='3. Earnings Build'!CG156 -> -166.115 | CH24: ='3. Earnings Build'!CH156 -> -180.931 | CI24: ='3. Earnings Build'!CI156 -> -144.03 | CJ24: =SUM(CF24:CI24) -> -637.983 | CK24: ='3. Earnings Build'!CK156 -> -202.798 | CL24: ='3. Earnings Build'!CL156 -> -219.633 | CM24: ='3. Earnings Build'!CM156 -> -234.77 | CN24: ='3. Earnings Build'!CN156 -> -205.666 | CO24: =SUM(CK24:CN24) -> -862.867 | CP24: ='3. Earnings Build'!CP156 -> -270.063 | CQ24: ='3. Earnings Build'!CQ156 -> -291.109 | CR24: ='3. Earnings Build'!CR156 -> -310.852 | CS24: ='3. Earnings Build'!CS156 -> -272.41 | CT24: =SUM(CP24:CS24) -> -1144.434
B25: Amortization of Intangible Assets & Other | BV25: ='3. Earnings Build'!BV157 -> 0 | BW25: ='3. Earnings Build'!BW157 -> 0 | BX25: ='3. Earnings Build'!BX157 -> -0.007 | BY25: ='3. Earnings Build'!BY157 -> 0 | BZ25: =SUM(BV25:BY25) -> -0.007 | CA25: ='3. Earnings Build'!CA157 -> 0 | CB25: ='3. Earnings Build'!CB157 -> 0 | CC25: ='3. Earnings Build'!CC157 -> -2.241 | CD25: ='3. Earnings Build'!CD157 -> -2.195 | CE25: =SUM(CA25:CD25) -> -4.436 | CF25: ='3. Earnings Build'!CF157 -> -2.195 | CG25: ='3. Earnings Build'!CG157 -> -2.195 | CH25: ='3. Earnings Build'!CH157 -> -2.195 | CI25: ='3. Earnings Build'!CI157 -> -2.197 | CJ25: =SUM(CF25:CI25) -> -8.782 | CK25: ='3. Earnings Build'!CK157 -> -2.195 | CL25: ='3. Earnings Build'!CL157 -> -2.195 | CM25: ='3. Earnings Build'!CM157 -> -2.189 | CN25: ='3. Earnings Build'!CN157 -> -2.173 | CO25: =SUM(CK25:CN25) -> -8.752 | CP25: ='3. Earnings Build'!CP157 -> -1.878 | CQ25: ='3. Earnings Build'!CQ157 -> -1.879 | CR25: ='3. Earnings Build'!CR157 -> -1.253 | CS25: ='3. Earnings Build'!CS157 -> 0 | CT25: =SUM(CP25:CS25) -> -5.01
B26: Total | C26: ='3. Earnings Build'!C158 -> 10.46 | H26: ='3. Earnings Build'!H158 -> 16.534374 | M26: ='3. Earnings Build'!M158 -> 23.441724 | N26: =N23+N24 -> 6.847 | O26: =O23+O24 -> 9.744 | P26: =P23+P24 -> 11.847 | Q26: =Q23+Q24 -> 21.662 | R26: =R23+R24 -> 50.1 | S26: =S23+S24 -> 11.721 | T26: =T23+T24 -> 15.542 | U26: =U23+U24 -> 13.055 | ... BU26: =BU23+BU24 -> 705.866 | BV26: =BV23+BV24+BV25 -> 128.812 | BW26: =BW23+BW24+BW25 -> 167.982 | BX26: =BX23+BX24+BX25 -> 175.822 | BY26: =BY23+BY24+BY25 -> 416.487 | BZ26: =BZ23+BZ24+BZ25 -> 889.103 | CA26: =CA23+CA24+CA25 -> 32.751 | CB26: =CB23+CB24+CB25 -> 135.873 | CC26: =CC23+CC24+CC25 -> 213.451 | ... CT26: =CT23+CT24+CT25 -> 2230.886
B28: Americas | CO28: ='3. Earnings Build'!CO213 -> 2503.74 | CP28: ='3. Earnings Build'!CP213 -> 581.222 | CQ28: ='3. Earnings Build'!CQ213 -> 660.57 | CR28: ='3. Earnings Build'!CR213 -> 636.714 | CS28: ='3. Earnings Build'!CS213 -> 1058.678 | CT28: ='3. Earnings Build'!CT213 -> 2937.184 | CU28: ='3. Earnings Build'!CU213 -> 564.84 | CV28: ='3. Earnings Build'!CV213 -> 669.427 | ... DF28: ='3. Earnings Build'!DF213 -> 594.413
B29: Mainland China | CO29: ='3. Earnings Build'!CO272 -> 196.865 | CP29: ='3. Earnings Build'!CP272 -> 73.885 | CQ29: ='3. Earnings Build'!CQ272 -> 83.481 | CR29: ='3. Earnings Build'!CR272 -> 76.792 | CS29: ='3. Earnings Build'!CS272 -> 103.158 | CT29: ='3. Earnings Build'!CT272 -> 337.316 | CU29: ='3. Earnings Build'!CU272 -> 119.778 | CV29: ='3. Earnings Build'!CV272 -> 119.085 | ... DF29: ='3. Earnings Build'!DF272 -> 151.27
B30: Rest of World | CO30: ='3. Earnings Build'!CO351 -> 103.204 | CP30: ='3. Earnings Build'!CP351 -> 43.794 | CQ30: ='3. Earnings Build'!CQ351 -> 51.292 | CR30: ='3. Earnings Build'!CR351 -> 45.552 | CS30: ='3. Earnings Build'!CS351 -> 61.194 | CT30: ='3. Earnings Build'!CT351 -> 201.832 | CU30: ='3. Earnings Build'!CU351 -> 66.681 | CV30: ='3. Earnings Build'!CV351 -> 74 | ... DF30: ='3. Earnings Build'!DF351 -> 74.973
B31: Segment EBIT | CO31: =CO28+CO29+CO30 -> 2803.809 | CP31: =CP28+CP29+CP30 -> 698.901 | CQ31: =CQ28+CQ29+CQ30 -> 795.343 | CR31: =CR28+CR29+CR30 -> 759.058 | CS31: =CS28+CS29+CS30 -> 1223.03 | CT31: =CT28+CT29+CT30 -> 3476.332 | CU31: =CU28+CU29+CU30 -> 751.299 | CV31: =CV28+CV29+CV30 -> 862.512 | ... DF31: =DF28+DF29+DF30 -> 820.656
B32: Corporate | CO32: ='3. Earnings Build'!CO373 -> -1014.74 | CP32: ='3. Earnings Build'!CP373 -> -297.487 | CQ32: ='3. Earnings Build'!CQ373 -> -316.086 | CR32: ='3. Earnings Build'!CR373 -> -322.733 | CS32: ='3. Earnings Build'!CS373 -> -309.14 | CT32: ='3. Earnings Build'!CT373 -> -1245.446 | CU32: ='3. Earnings Build'!CU373 -> -318.657 | CV32: ='3. Earnings Build'!CV373 -> -322.286 | ... DF32: ='3. Earnings Build'!DF373 -> -367.003
B33: Total EBIT | CO33: =CO31+CO32 -> 1789.069 | CP33: =CP31+CP32 -> 401.414 | CQ33: =CQ31+CQ32 -> 479.257 | CR33: =CR31+CR32 -> 436.325 | CS33: =CS31+CS32 -> 913.89 | CT33: =CT31+CT32 -> 2230.886 | CU33: =CU31+CU32 -> 432.642 | CV33: =CV31+CV32 -> 540.226 | ... DF33: =DF31+DF32 -> 453.653
B35: CONSOLIDATED INCOME STATEMENT
B37: Net Sales | C37: =C12 -> 40.749 | D37: =D12 -> 15.63 | E37: =E12 -> 17.126 | F37: =F12 -> 19.984 | G37: =G12 -> 31.389093 | H37: =SUM(D37:G37) -> 84.129093 | I37: =I12 -> 28.184 | J37: =J12 -> 32.517437 | K37: =K12 -> 35.967615 | L37: =L12 -> 52.215782 | M37: =SUM(I37:L37) -> 148.88483 | N37: =N12 -> 44.789456 | O37: =O12 -> 58.680944 | P37: =P12 -> 66.15028 | Q37: =Q12 -> 105.09265 | R37: =SUM(N37:Q37) -> 274.71333 | S37: =S12 -> 78.167494 | T37: =T12 -> 85.484223 | U37: =U12 -> 87.047135 | V37: =V12 -> 103.921 | W37: =SUM(S37:V37) -> 354.61985 | X37: =X12 -> 81.68 | Y37: =Y12 -> 97.721 | Z37: =Z12 -> 112.891 | AA37: =AA12 -> 160.606 | AB37: =SUM(X37:AA37) -> 452.898 | AC37: =AC12 -> 138.297 | AD37: =AD12 -> 152.208 | AE37: =AE12 -> 175.8 | AF37: =AF12 -> 245.399 | AG37: =SUM(AC37:AF37) -> 711.704 | AH37: =AH12 -> 186.78 | AI37: =AI12 -> 212.323 | AJ37: =AJ12 -> 230.216 | AK37: =AK12 -> 371.52 | AL37: =SUM(AH37:AK37) -> 1000.839 | AM37: =AM12 -> 285.698 | AN37: =AN12 -> 282.634 | AO37: =AO12 -> 316.537 | AP37: 485.489 | AQ37: 1370.358 | AR37: =AR12 -> 345.782 | AS37: =AS12 -> 344.513 | AT37: =AT12 -> 379.9 | AU37: =AU12 -> 520.993 | AV37: =SUM(AR37:AU37) -> 1591.188 | AW37: =AW12 -> 384.618 | AX37: =AX12 -> 390.727 | AY37: =AY12 -> 419.396 | AZ37: 602.491 | BA37: 1797.213 | BB37: =BB12 -> 423.544 | BC37: =BC12 -> 453.01 | BD37: =BD12 -> 479.693 | BE37: =BE12 -> 704.276 | BF37: =SUM(BB37:BE37) -> 2060.523 | BG37: =BG12 -> 495.516 | BH37: =BH12 -> 514.52 | BI37: =BI12 -> 544.416 | BJ37: =BJ12 -> 789.94 | BK37: =SUM(BG37:BJ37) -> 2344.392 | BL37: =BL12 -> 520.307 | BM37: =BM12 -> 581.054 | BN37: =BN12 -> 619.034 | BO37: 928.802 | BP37: 2649.181 | BQ37: 649.706 | BR37: 723.5 | BS37: 747.655 | BT37: 1167.458 | BU37: =SUM(BQ37:BT37) -> 3288.319 | BV37: 782.315 | BW37: 883.352 | BX37: 916.138 | BY37: 1397.491 | BZ37: =SUM(BV37:BY37) -> 3979.296 | CA37: 651.962 | CB37: 902.942 | CC37: 1117.426 | CD37: 1729.55 | CE37: =SUM(CA37:CD37) -> 4401.88 | CF37: 1226.465 | CG37: 1450.618 | CH37: 1450.421 | CI37: 2129.113 | CJ37: =SUM(CF37:CI37) -> 6256.617 | CK37: 1613.463 | CL37: 1868.328 | CM37: 1856.889 | CN37: 2771.838 | CO37: =SUM(CK37:CN37) -> 8110.518 | CP37: 2000.792 | CQ37: 2209.165 | CR37: 2204.218 | CS37: 3205.103 | CT37: =SUM(CP37:CS37) -> 9619.278 | CU37: 2208.891 | CV37: 2371.078 | CW37: 2396.66 | CX37: 3611.497 | CY37: =SUM(CU37:CX37) -> 10588.126 | CZ37: 2370.66 | DA37: 2525.219 | DB37: 2565.92 | DC37: 3640.801 | DD37: ='3. Earnings Build'!DD13 -> 11102.6 | DE37: 2471.603 | DF37: 2415.631 | DG37: ='3. Earnings Build'!DG13 -> 2315.5913 | DH37: ='3. Earnings Build'!DH13 -> 3263.7773 | DI37: ='3. Earnings Build'!DI13 -> 10466.603 | DJ37: ='3. Earnings Build'!DJ13 -> 2361.0562 | DK37: ='3. Earnings Build'!DK13 -> 2329.698 | DL37: ='3. Earnings Build'!DL13 -> 2305.1486 | DM37: ='3. Earnings Build'!DM13 -> 3221.0211 | DN37: ='3. Earnings Build'!DN13 -> 10216.924 | ... DS37: ='3. Earnings Build'!DS13 -> 10330.987
B38: % chg. Y/Y | H38: =H37/C37-1 -> 1.0645683 | I38: =I37/D37-1 -> 0.80319898 | J38: =J37/E37-1 -> 0.89871756 | K38: =K37/F37-1 -> 0.79982061 | L38: =L37/G37-1 -> 0.66350082 | M38: =M37/H37-1 -> 0.76971876 | N38: =N37/I37-1 -> 0.58918024 | O38: =O37/J37-1 -> 0.8045993 | ... DS38: =DS37/DN37-1 -> 0.011164122
B40: Total COGS | C40: ='3. Earnings Build'!C134 -> -19.448 | D40: ='3. Earnings Build'!D134 -> -8.207 | E40: ='3. Earnings Build'!E134 -> -7.94 | F40: ='3. Earnings Build'!F134 -> -9.613 | G40: ='3. Earnings Build'!G134 -> -15.416981 | H40: =SUM(D40:G40) -> -41.176981 | I40: ='3. Earnings Build'!I134 -> -13.664 | J40: ='3. Earnings Build'!J134 -> -16.614142 | K40: ='3. Earnings Build'!K134 -> -17.227413 | L40: ='3. Earnings Build'!L134 -> -25.397557 | M40: =SUM(I40:L40) -> -72.903112 | N40: ='3. Earnings Build'!N134 -> -22.178568 | O40: ='3. Earnings Build'!O134 -> -27.434066 | P40: ='3. Earnings Build'!P134 -> -30.26986 | Q40: ='3. Earnings Build'!Q134 -> -48.528681 | R40: =SUM(N40:Q40) -> -128.41117 | S40: ='3. Earnings Build'!S134 -> -36.645025 | T40: ='3. Earnings Build'!T134 -> -41.107858 | U40: ='3. Earnings Build'!U134 -> -45.153576 | V40: ='3. Earnings Build'!V134 -> -52.261 | W40: =SUM(S40:V40) -> -175.16746 | X40: ='3. Earnings Build'!X134 -> -46.731 | Y40: ='3. Earnings Build'!Y134 -> -52.557 | Z40: ='3. Earnings Build'!Z134 -> -56.553 | AA40: ='3. Earnings Build'!AA134 -> -74.046 | AB40: =SUM(X40:AA40) -> -229.887 | AC40: ='3. Earnings Build'!AC134 -> -63.94 | AD40: ='3. Earnings Build'!AD134 -> -71.91 | AE40: ='3. Earnings Build'!AE134 -> -78.968 | AF40: ='3. Earnings Build'!AF134 -> -101.939 | AG40: =SUM(AC40:AF40) -> -316.757 | AH40: ='3. Earnings Build'!AH134 -> -77.053 | AI40: ='3. Earnings Build'!AI134 -> -90.256 | AJ40: ='3. Earnings Build'!AJ134 -> -101.703 | AK40: ='3. Earnings Build'!AK134 -> -162.502 | AL40: =SUM(AH40:AK40) -> -431.514 | AM40: ='3. Earnings Build'!AM134 -> -128.434 | AN40: ='3. Earnings Build'!AN134 -> -126.879 | AO40: ='3. Earnings Build'!AO134 -> -141.237 | AP40: ='3. Earnings Build'!AP134 -> -210.982 | AQ40: =SUM(AM40:AP40) -> -607.532 | AR40: ='3. Earnings Build'!AR134 -> -175.057 | AS40: ='3. Earnings Build'!AS134 -> -158.558 | AT40: ='3. Earnings Build'!AT134 -> -175.294 | AU40: ='3. Earnings Build'!AU134 -> -242.203 | AV40: =SUM(AR40:AU40) -> -751.112 | AW40: ='3. Earnings Build'!AW134 -> -188.874 | AX40: ='3. Earnings Build'!AX134 -> -193.401 | AY40: ='3. Earnings Build'!AY134 -> -208.308 | AZ40: ='3. Earnings Build'!AZ134 -> -292.45 | BA40: =SUM(AW40:AZ40) -> -883.033 | BB40: ='3. Earnings Build'!BB134 -> -217.667 | BC40: ='3. Earnings Build'!BC134 -> -240.985 | BD40: ='3. Earnings Build'!BD134 -> -254.896 | BE40: ='3. Earnings Build'!BE134 -> -349.809 | BF40: =SUM(BB40:BE40) -> -1063.357 | BG40: ='3. Earnings Build'!BG134 -> -256.385 | BH40: ='3. Earnings Build'!BH134 -> -260.359 | BI40: ='3. Earnings Build'!BI134 -> -265.99 | BJ40: ='3. Earnings Build'!BJ134 -> -362.041 | BK40: =SUM(BG40:BJ40) -> -1144.775 | BL40: ='3. Earnings Build'!BL134 -> -257.993 | BM40: ='3. Earnings Build'!BM134 -> -281.388 | BN40: ='3. Earnings Build'!BN134 -> -295.878 | BO40: ='3. Earnings Build'!BO134 -> -406.434 | BP40: =SUM(BL40:BO40) -> -1241.693 | BQ40: -304.973 | BR40: -327.306 | BS40: -340.878 | BT40: -498.875 | BU40: =SUM(BQ40:BT40) -> -1472.032 | BV40: -360.595 | BW40: =-397.556 -> -397.556 | BX40: -411.094 | BY40: -586.665 | BZ40: =SUM(BV40:BY40) -> -1755.91 | CA40: -317.56 | CB40: -413.441 | CC40: -490.072 | CD40: -716.816 | CE40: =SUM(CA40:CD40) -> -1937.889 | CF40: -526.151 | CG40: -607.932 | CH40: -621.028 | CI40: -892.941 | CJ40: =SUM(CF40:CI40) -> -2648.052 | CK40: -743.07 | CL40: -812.852 | CM40: -818.037 | CN40: =-1244.219+62.928 -> -1181.291 | CO40: =SUM(CK40:CN40) -> -3555.25 | CP40: -849.987 | CQ40: -910.654 | CR40: =-947.554+23.709 -> -923.845 | CS40: =-1301.678 -> -1301.678 | CT40: =SUM(CP40:CS40) -> -3986.164 | CU40: -933.823 | CV40: -958.893 | CW40: -995.054 | CX40: -1429.545 | CY40: =SUM(CU40:CX40) -> -4317.315 | CZ40: -987.534 | DA40: -1048.017 | DB40: -1140.004 | DC40: =-1642.913 -> -1642.913 | DD40: =SUM(CZ40:DC40) -> -4818.468 | DE40: -1132.785 | DF40: =-953.753 -> -953.753 | DG40: =DG42-DG37 -> -1086.6761 | DH40: =DH42-DH37 -> -1472.7809 | DI40: =SUM(DE40:DH40) -> -4645.995 | DJ40: =DJ42-DJ37 -> -1075.036 | DK40: =DK42-DK37 -> -1040.9688 | DL40: =DL42-DL37 -> -1085.2332 | DM40: =DM42-DM37 -> -1458.3187 | DN40: =SUM(DJ40:DM40) -> -4659.5566 | DO40: =DO42-DO37 -> -1091.5165 | DP40: =DP42-DP37 -> -1055.1835 | DQ40: =DQ42-DQ37 -> -1104.7285 | DR40: =DR42-DR37 -> -1470.6806 | DS40: =SUM(DO40:DR40) -> -4722.1091
B42: Gross Profit | C42: =C37+C40 -> 21.301 | D42: =D37+D40 -> 7.423 | E42: =E37+E40 -> 9.186 | F42: =F37+F40 -> 10.371 | G42: =G37+G40 -> 15.972112 | H42: =H37+H40 -> 42.952112 | I42: =I37+I40 -> 14.52 | J42: =J37+J40 -> 15.903295 | ... DF42: =DF37+DF40 -> 1461.878 | DG42: =DG37*(DB44+DG45/10000) -> 1228.9152 | DH42: =DH37*(DC44+DH45/10000) -> 1790.9964 | DI42: =DI37+DI40 -> 5820.6076 | DJ42: =DJ37*(DE44+DJ45/10000) -> 1286.0202 | DK42: =DK37*(DF44+DK45/10000) -> 1288.7293 | DL42: =DL37*(DG44+DL45/10000) -> 1219.9154 | DM42: =DM37*(DH44+DM45/10000) -> 1762.7024 | DN42: =DN37+DN40 -> 5557.3673 | DO42: =DO37*(DJ44+DO45/10000) -> 1300.4816 | DP42: =DP37*(DK44+DP45/10000) -> 1301.0539 | DQ42: =DQ37*(DL44+DQ45/10000) -> 1236.8564 | DR42: =DR37*(DM44+DR45/10000) -> 1770.4858 | DS42: =DS37+DS40 -> 5608.8778
B43: % chg. Y/Y | H43: =H42/C42-1 -> 1.0164364 | I43: =I42/D42-1 -> 0.95608245 | J43: =J42/E42-1 -> 0.73125354 | K43: =K42/F42-1 -> 0.8069812 | L43: =L42/G42-1 -> 0.67906567 | M43: =M42/H42-1 -> 0.76898687 | N43: =N42/I42-1 -> 0.55722369 | O43: =O42/J42-1 -> 0.96480528 | ... DS43: =DS42/DN42-1 -> 0.0092688661
B44: % sales | C44: =C42/C$37 -> 0.52273675 | D44: =D42/D$37 -> 0.47492003 | E44: =E42/E$37 -> 0.53637744 | F44: =F42/F$37 -> 0.51896517 | G44: =G42/G$37 -> 0.50884274 | H44: =H42/H$37 -> 0.51055004 | I44: =I42/I$37 -> 0.51518592 | J44: =J42/J$37 -> 0.48906976 | ... DS44: =DS42/DS$37 -> 0.54291791
B45: Margin chg. Y/Y bps | H45: =(H44-C44)*100*100 -> -121.86712 | I45: =(I44-D44)*100*100 -> 402.65895 | J45: =(J44-E44)*100*100 -> -473.07681 | K45: =(K44-F44)*100*100 -> 20.647043 | L45: =(L44-G44)*100*100 -> 47.610809 | M45: =(M44-H44)*100*100 -> -2.1114518 | N45: =(N44-I44)*100*100 -> -103.59785 | O45: =(O44-J44)*100*100 -> 434.17894 | ... DF45: =(DF44-DA44)*100*100 -> 201.94625 | DG45: -250 | DH45: 0 | DI45: =(DI44-DD44)*100*100 -> -98.930278 | DJ45: 30 | DK45: =30-550 -> -520 | DL45: -15 | DM45: -15 | DN45: =(DN44-DI44)*100*100 -> -121.74988 | DO45: -10 | DP45: -10 | DQ45: -10 | DR45: -10 | DS45: =(DS44-DN44)*100*100 -> -10.195185
B47: Total SG&A | C47: -10.841 | D47: -3.574 | E47: -4.473 | F47: -5.338 | G47: -13.032738 | H47: =SUM(D47:G47) -> -26.417738 | I47: -8.406 | J47: -12.667215 | K47: -14.045858 | L47: -17.420925 | M47: =SUM(I47:L47) -> -52.539998 | N47: -15.762698 | O47: -21.477352 | P47: -24.050692 | Q47: -34.886606 | R47: =SUM(N47:Q47) -> -96.177348 | S47: -29.80172 | T47: -28.832643 | U47: -28.838165 | V47: -31.214 | W47: =SUM(S47:V47) -> -118.68653 | X47: -25.096 | Y47: -30.832 | Z47: -35.412 | AA47: -44.929 | AB47: =SUM(X47:AA47) -> -136.269 | AC47: -41.883 | AD47: -46.055 | AE47: -54.456 | AF47: =-71.483-0.679 -> -72.162 | AG47: =SUM(AC47:AF47) -> -214.556 | AH47: -58.04 | AI47: -62.584 | AJ47: -68.792 | AK47: -92.951 | AL47: =SUM(AH47:AK47) -> -282.367 | AM47: -84.199 | AN47: -85.567 | AO47: -94.689 | AP47: -121.932 | AQ47: =SUM(AM47:AP47) -> -386.387 | AR47: -104.836 | AS47: -106.969 | AT47: -112.27 | AU47: -124.643 | AV47: =SUM(AR47:AU47) -> -448.718 | AW47: -125.943 | AX47: -129.419 | AY47: -129.932 | AZ47: -152.853 | BA47: =SUM(AW47:AZ47) -> -538.147 | BB47: -137.841 | BC47: -145.446 | BD47: -156.619 | BE47: -188.184 | BF47: =SUM(BB47:BE47) -> -628.09 | BG47: -181.542 | BH47: -180.202 | BI47: -185.451 | BJ47: -231.27 | BK47: =SUM(BG47:BJ47) -> -778.465 | BL47: -199.141 | BM47: =-225.524-3.186+2.244+3.186-2.244 -> -225.524 | BN47: =-215.367-21.007+21.007 -> -215.367 | BO47: =-264.232-2.001+2.001 -> -264.232 | BP47: =SUM(BL47:BO47) -> -904.264 | BQ47: -240.428 | BR47: -261.986 | BS47: -270.874 | BT47: -337.163 | BU47: =SUM(BQ47:BT47) -> -1110.451 | BV47: -292.908 | BW47: -317.814 | BX47: -329.208 | BY47: -394.339 | BZ47: =SUM(BV47:BY47) -> -1334.269 | CA47: =-301.651 -> -301.651 | CB47: =-352.904-0.724-11.464+7.201+5.045-0.782 -> -353.628 | CC47: =-411.662-8.531+1.017+7.514 -> -411.662 | CD47: =-544.831-7.802+0.285+7.517 -> -544.831 | CE47: =SUM(CA47:CD47) -> -1611.772 | CF47: =-496.634-7.664+7.168+0.496 -> -496.634 | CG47: -541.317 | CH47: -545.124 | CI47: -641.959 | CJ47: =SUM(CF47:CI47) -> -2225.034 | CK47: -607.851 | CL47: =-662.253+10.18-10.18 -> -662.253 | CM47: -684.236 | CN47: -803.107 | CO47: =SUM(CK47:CN47) -> -2757.447 | CP47: -747.513 | CQ47: -817.375 | CR47: -842.795 | CS47: -989.535 | CT47: =SUM(CP47:CS47) -> -3397.218 | CU47: -842.426 | CV47: -871.959 | CW47: -909.827 | CX47: -1138.167 | CY47: =SUM(CU47:CX47) -> -3762.379 | CZ47: -942.871 | DA47: -951.658 | DB47: -988.254 | DC47: =-1183.773 -> -1183.773 | DD47: =SUM(CZ47:DC47) -> -4066.556 | DE47: -1059.988 | DF47: -1006.332 | DG47: =-DG37*(DB49+DG50/10000) -> -1077.0882 | DH47: =-DH37*(DC49+DH50/10000) -> -1159.1005 | DI47: =SUM(DE47:DH47) -> -4302.5087 | DJ47: =-DJ37*(DE49+DJ50/10000) -> -1047.994 | DK47: =-DK37*(DF49+DK50/10000) -> -1005.4785 | DL47: =-DL37*(DG49+DL50/10000) -> -1089.5194 | DM47: =-DM37*(DH49+DM50/10000) -> -1168.0737 | DN47: =SUM(DJ47:DM47) -> -4311.0656 | DO47: =-DO37*(DJ49+DO50/10000) -> -1073.6881 | DP47: =-DP37*(DK49+DP50/10000) -> -1028.7139 | DQ47: =-DQ37*(DL49+DQ50/10000) -> -1118.4488 | DR47: =-DR37*(DM49+DR50/10000) -> -1191.585 | DS47: =SUM(DO47:DR47) -> -4412.4359
B48: % chg. Y/Y | H48: =H47/C47-1 -> 1.4368359 | I48: =I47/D47-1 -> 1.3519866 | J48: =J47/E47-1 -> 1.8319282 | K48: =K47/F47-1 -> 1.631296 | L48: =L47/G47-1 -> 0.33670492 | M48: =M47/H47-1 -> 0.98881517 | N48: =N47/I47-1 -> 0.87517226 | O48: =O47/J47-1 -> 0.69550702 | ... DS48: =DS47/DN47-1 -> 0.023513958
B49: % of sales | H49: =-H47/H37 -> 0.3140143 | I49: =-I47/I37 -> 0.29825433 | J49: =-J47/J37 -> 0.38955146 | K49: =-K47/K37 -> 0.39051402 | L49: =-L47/L37 -> 0.33363333 | M49: =-M47/M37 -> 0.35289019 | N49: =-N47/N37 -> 0.35192877 | O49: =-O47/O37 -> 0.36600216 | ... DS49: =-DS47/DS37 -> 0.42710691
B50: Margin chg. Y/Y bps | H50: =(H49-C49)*100*100 -> 3140.143 | I50: =(I49-D49)*100*100 -> 2982.5433 | J50: =(J49-E49)*100*100 -> 3895.5146 | K50: =(K49-F49)*100*100 -> 3905.1402 | L50: =(L49-G49)*100*100 -> 3336.3333 | M50: =(M49-H49)*100*100 -> 388.75897 | N50: =(N49-I49)*100*100 -> 536.74438 | O50: =(O49-J49)*100*100 -> -235.49303 | ... DF50: =(DF49-DA49)*100*100 -> 397.30201 | DG50: 800 | DH50: 300 | DI50: =(DI49-DD49)*100*100 -> 447.99625 | DJ50: 150 | DK50: 150 | DL50: 75 | DM50: 75 | DN50: =(DN49-DI49)*100*100 -> 108.83158 | DO50: 50 | DP50: 50 | DQ50: 50 | DR50: 50 | DS50: =(DS49-DN49)*100*100 -> 51.535206
B52: Amortization of Intangible Assets & Other | BV52: 0 | BW52: 0 | BX52: -0.007 | BY52: 0 | BZ52: =SUM(BV52:BY52) -> -0.007 | CA52: 0 | CB52: 0 | CC52: -2.241 | CD52: -2.195 | CE52: =SUM(CA52:CD52) -> -4.436 | CF52: -2.195 | CG52: =-2.195-8.143+1.035+7.108 -> -2.195 | CH52: =-2.195-24.127+23.799+0.328 -> -2.195 | CI52: =-2.197-1.46+1.13+0.33 -> -2.197 | CJ52: =SUM(CF52:CI52) -> -8.782 | CK52: -2.195 | CL52: -2.195 | CM52: -2.189 | CN52: =-2.173-407.913+362.492+40.585+4.836 -> -2.173 | CO52: =SUM(CK52:CN52) -> -8.752 | CP52: -1.878 | CQ52: -1.879 | CR52: =-1.253-74.501+44.186+30.315 -> -1.253 | CS52: 0 | CT52: =SUM(CP52:CS52) -> -5.01 | CU52: 0 | CV52: 0 | CW52: -1.118 | CX52: -1.617 | CY52: =SUM(CU52:CX52) -> -2.735 | CZ52: -1.63 | DA52: -1.73 | DB52: -1.776 | DC52: =-1.825 -> -1.825 | DD52: =SUM(CZ52:DC52) -> -6.961 | DE52: -1.884 | DF52: -1.893 | DG52: -1.5 | DH52: -1.5 | DI52: =SUM(DE52:DH52) -> -6.777 | DJ52: -1 | DK52: -1 | DL52: -1 | DM52: -1 | DN52: =SUM(DJ52:DM52) -> -4 | DO52: -1 | DP52: -1 | DQ52: -1 | DR52: -1 | DS52: =SUM(DO52:DR52) -> -4
B53: % chg. Y/Y | CF53: =IFERROR(CF52/CA52-1,"--") -> -- | CG53: =IFERROR(CG52/CB52-1,"--") -> -- | CH53: =IFERROR(CH52/CC52-1,"--") -> -0.020526551 | CI53: =IFERROR(CI52/CD52-1,"--") -> 0.00091116173 | CJ53: =IFERROR(CJ52/CE52-1,"--") -> 0.97971145 | CK53: =IFERROR(CK52/CF52-1,"--") -> 0 | CL53: =IFERROR(CL52/CG52-1,"--") -> -5.5511151e-16 | CM53: =IFERROR(CM52/CH52-1,"--") -> -0.0027334852 | ... DS53: =IFERROR(DS52/DN52-1,"--") -> 0
B55: EBIT | C55: =C42+C47 -> 10.46 | D55: =D42+D47 -> 3.849 | E55: =E42+E47 -> 4.713 | F55: =F42+F47 -> 5.033 | G55: =G42+G47 -> 2.939374 | H55: =H42+H47 -> 16.534374 | I55: =I42+I47 -> 6.114 | J55: =J42+J47 -> 3.23608 | ... BU55: =BU42+BU47 -> 705.836 | BV55: =BV42+BV47+BV52 -> 128.812 | BW55: =BW42+BW47+BW52 -> 167.982 | BX55: =BX42+BX47+BX52 -> 175.829 | BY55: =BY42+BY47+BY52 -> 416.487 | BZ55: =BZ42+BZ47+BZ52 -> 889.11 | CA55: =CA42+CA47+CA52 -> 32.751 | CB55: =CB42+CB47+CB52 -> 135.873 | CC55: =CC42+CC47+CC52 -> 213.451 | CD55: =CD42+CD47+CD52 -> 465.708 | CE55: =CE26 -> 847.783 | CF55: =CF42+CF47+CF52 -> 201.485 | CG55: =CG42+CG47+CG52 -> 299.174 | CH55: =CH42+CH47+CH52 -> 282.074 | CI55: =CI42+CI47+CI52 -> 592.016 | CJ55: =CJ26 -> 1374.749 | CK55: =CK42+CK47+CK52 -> 260.347 | CL55: =CL42+CL47+CL52 -> 391.028 | CM55: =CM42+CM47+CM52 -> 352.427 | CN55: =CN42+CN47+CN52 -> 785.267 | CO55: =CO26 -> 1789.069 | CP55: =CP42+CP47+CP52 -> 401.414 | CQ55: =CQ42+CQ47+CQ52 -> 479.257 | CR55: =CR42+CR47+CR52 -> 436.325 | CS55: =CS42+CS47+CS52 -> 913.89 | CT55: =CT26 -> 2230.886 | CU55: =CU42+CU47+CU52 -> 432.642 | CV55: =CV42+CV47+CV52 -> 540.226 | CW55: =CW42+CW47+CW52 -> 490.661 | CX55: =CX42+CX47+CX52 -> 1042.168 | CY55: =CY42+CY47+CY52 -> 2505.697 | CZ55: =CZ42+CZ47+CZ52 -> 438.625 | DA55: =DA42+DA47+DA52 -> 523.814 | DB55: =DB42+DB47+DB52 -> 435.886 | ... DS55: =DS42+DS47+DS52 -> 1192.4419
B56: % chg. Y/Y | H56: =H55/C55-1 -> 0.58072409 | I56: =I55/D55-1 -> 0.58846454 | J56: =J55/E55-1 -> -0.31337153 | K56: =K55/F55-1 -> -0.067287105 | L56: =L55/G55-1 -> 2.1970413 | M56: =M55/H55-1 -> 0.41775697 | N56: =N55/I55-1 -> 0.12008342 | O56: =O55/J55-1 -> 2.0189383 | ... DS56: =DS55/DN55-1 -> -0.040134957
B57: % sales | C57: =C55/C$37 -> 0.25669342 | D57: =D55/D$37 -> 0.2462572 | E57: =E55/E$37 -> 0.27519561 | F57: =F55/F$37 -> 0.25185148 | G57: =G55/G$37 -> 0.093643165 | H57: =H55/H$37 -> 0.19653575 | I57: =I55/I$37 -> 0.21693159 | J57: =J55/J$37 -> 0.099518298 | ... DS57: =DS55/DS$37 -> 0.11542381
B58: Margin chg. Y/Y bps | H58: =(H57-C57)*100*100 -> -601.5767 | I58: =(I57-D57)*100*100 -> -293.25605 | J58: =(J57-E57)*100*100 -> -1756.7731 | K58: =(K57-F57)*100*100 -> -1213.3563 | L58: =(L57-G57)*100*100 -> 863.27328 | M58: =(M57-H57)*100*100 -> -390.87042 | N58: =(N57-I57)*100*100 -> -640.34223 | O58: =(O57-J57)*100*100 -> 669.67196 | ... DS58: =(DS57-DN57)*100*100 -> -61.687166
B60: Net Interest / Other | C60: =0.01-0.046 -> -0.036 | H60: =0.057729999999985-0.052 -> 0.00573 | M60: =0.141071-0.046683+0.111865 -> 0.206253 | R60: =0.854088+0.334220000000007 -> 1.188308 | W60: =1.019322-1.138365 -> -0.119043 | AB60: 0.164 | AG60: 2.886 | AH60: 0.904 | AI60: 0.597 | AJ60: 0.619 | AK60: 0.38 | AL60: =SUM(AH60:AK60) -> 2.5 | AM60: 0.91 | AN60: 1.166 | AO60: 1.424 | AP60: 1.457 | AQ60: =SUM(AM60:AP60) -> 4.957 | AR60: 1.501 | AS60: 1.295 | AT60: 1.453 | AU60: 1.519 | AV60: =SUM(AR60:AU60) -> 5.768 | AW60: 1.643 | AX60: 1.89 | AY60: 1.814 | AZ60: 1.755 | BA60: =SUM(AW60:AZ60) -> 7.102 | BB60: 0.529 | BC60: 0.842 | BD60: =-2.89+3.606 -> 0.716 | BE60: 0.938 | BF60: =SUM(BB60:BE60) -> 3.025 | BG60: =-0.486+1.2 -> 0.714 | BH60: =0.578+0.3 -> 0.878 | BI60: =0.628+0.2 -> 0.828 | BJ60: 0.857 | BK60: =SUM(BG60:BJ60) -> 3.277 | BL60: 0.907 | BM60: 0.812 | BN60: 1.052 | BO60: 1.226 | BP60: =SUM(BL60:BO60) -> 3.997 | BQ60: 2.918 | BR60: 1.591 | BS60: 2.044 | BT60: 2.861 | BU60: =SUM(BQ60:BT60) -> 9.414 | BV60: 2.379 | BW60: 1.85 | BX60: 1.925 | BY60: 2.129 | BZ60: =SUM(BV60:BY60) -> 8.283 | CA60: 1.174 | CB60: -0.344 | CC60: -0.58 | CD60: -0.886 | CE60: =SUM(CA60:CD60) -> -0.636 | CF60: 0.227 | CG60: 0.096 | CH60: 0.015 | CI60: 0.176 | CJ60: =SUM(CF60:CI60) -> 0.514 | CK60: -0.022 | CL60: 0.145 | CM60: 0.331 | CN60: 3.709 | CO60: =SUM(CK60:CN60) -> 4.163 | CP60: 8.025 | CQ60: 7.362 | CR60: 9.842 | CS60: 17.83 | CT60: =SUM(CP60:CS60) -> 43.059 | CU60: 23.283 | CV60: 17.994 | CW60: 13.743 | CX60: 15.36 | CY60: =SUM(CU60:CX60) -> 70.38 | CZ60: 11.786 | DA60: 9.737 | DB60: 5.854 | DC60: 0.975 | DD60: =SUM(CZ60:DC60) -> 28.352 | DE60: 9.131 | DF60: =13.698 -> 13.698 | DG60: =DG315 -> 4.8622312 | DH60: =DH315 -> 4.4682344 | DI60: =SUM(DE60:DH60) -> 32.159466 | DJ60: =DJ315 -> 5.5902576 | DK60: =DK315 -> 5.8895438 | DL60: =DL315 -> 4.823189 | DM60: =DM315 -> 5.0143034 | DN60: =SUM(DJ60:DM60) -> 21.317294 | DO60: =DO315 -> 6.5410124 | DP60: =DP315 -> 6.8735693 | DQ60: =DQ315 -> 5.8516212 | DR60: =DR315 -> 6.0028679 | DS60: =SUM(DO60:DR60) -> 25.269071
B61: Pre-Tax | C61: =C55+C60 -> 10.424 | H61: =H55+H60 -> 16.540104 | M61: =M55+M60 -> 23.647977 | R61: =R55+R60 -> 51.313113 | W61: =W55+W60 -> 60.646822 | AB61: =AB55+AB60 -> 86.906 | AG61: 183.277 | AH61: =AH55+AH60 -> 52.591 | AI61: =AI55+AI60 -> 60.08 | AJ61: =AJ55+AJ60 -> 60.34 | AK61: =AK55+AK60 -> 116.447 | AL61: =AL55+AL60 -> 289.458 | AM61: =AM55+AM60 -> 73.975 | AN61: =AN55+AN60 -> 71.354 | AO61: =AO55+AO60 -> 82.035 | ... DS61: =DS55+DS60 -> 1217.711
B62: Taxes | C62: -0.999312 | H62: -1.220217 | M62: =-12.633186 -> -12.633186 | R62: -20.470674 | W62: -18.525128 | AB62: -28.490544 | AG62: -61.08 | AH62: -19.075 | AI62: -21.462 | AJ62: -21.399 | AK62: -42.558 | AL62: =SUM(AH62:AK62) -> -104.494 | AM62: -27.001 | AN62: -13.652 | AO62: -24.655 | AP62: -44.657 | AQ62: =SUM(AM62:AP62) -> -109.965 | AR62: -20.111 | AS62: -23.816 | AT62: -27.678 | AU62: -45.974 | AV62: =SUM(AR62:AU62) -> -117.579 | AW62: =-52.463+33.7 -> -18.763 | AX62: =-21.03 -> -21.03 | AY62: -22.519 | AZ62: -48.09 | BA62: =SUM(AW62:AZ62) -> -110.402 | BB62: -20.755 | BC62: -19.753 | BD62: =-12.135-7.713 -> -19.848 | BE62: =-49.805 -> -49.805 | BF62: =SUM(BB62:BE62) -> -110.161 | BG62: =-11.767-5.6 -> -17.367 | BH62: =-20.912-1.9 -> -22.812 | BI62: =-25.318-4 -> -29.318 | BJ62: =BJ61*-0.306 -> -60.430716 | BK62: =SUM(BG62:BJ62) -> -129.92772 | BL62: =-15.084-4.684 -> -19.768 | BM62: =-20.813-1.39 -> -22.203 | BN62: =-27.696-5.813 -> -33.509 | BO62: =-137.743-0.855+59.294 -> -79.304 | BP62: =SUM(BL62:BO62) -> -154.784 | BQ62: -32.07 | BR62: -40.029 | BS62: =-43.534+5.163 -> -38.371 | BT62: =-115.816+23.714+2.301 -> -89.801 | BU62: =SUM(BQ62:BT62) -> -200.271 | BV62: -34.588 | BW62: -44.842 | BX62: -51.772 | BY62: -120.595 | BZ62: =SUM(BV62:BY62) -> -251.797 | CA62: -5.293 | CB62: =-37.264-1.967 -> -39.231 | CC62: =-60.697-0.896 -> -61.593 | CD62: =-127.181-0.27 -> -127.451 | CE62: =SUM(CA62:CD62) -> -233.568 | CF62: =-49.092-0.372 -> -49.464 | CG62: =-83.053-0.434 -> -83.487 | CH62: =-70.174-0.611 -> -70.785 | CI62: -156.228 | CJ62: =SUM(CF62:CI62) -> -359.964 | CK62: -70.327 | CL62: =-111.832+1.661 -> -110.171 | CM62: -97.288 | CN62: =-198.324-28.171 -> -226.495 | CO62: =SUM(CK62:CN62) -> -504.281 | CP62: -119.034 | CQ62: -145.016 | CR62: =-99.243-26.085 -> -125.328 | CS62: -262.252 | CT62: =SUM(CP62:CS62) -> -651.63 | CU62: -134.504 | CV62: -165.298 | CW62: -152.534 | CX62: -309.125 | CY62: =SUM(CU62:CX62) -> -761.461 | CZ62: -135.839 | DA62: -162.646 | DB62: -134.905 | DC62: =-226.394 -> -226.394 | DD62: =SUM(CZ62:DC62) -> -659.784 | DE62: -91.029 | DF62: =-138.128 -> -138.128 | DG62: =-DG63*DG61 -> -46.556778 | DH62: =-DH63*DH61 -> -187.91978 | DI62: =SUM(DE62:DH62) -> -463.63356 | DJ62: =-DJ63*DJ61 -> -72.784925 | DK62: =-DK63*DK61 -> -86.442093 | DL62: =-DL63*DL61 -> -40.265755 | DM62: =-DM63*DM61 -> -179.5929 | DN62: =SUM(DJ62:DM62) -> -379.08568 | DO62: =-DO63*DO61 -> -69.700365 | DP62: =-DP63*DP61 -> -83.464092 | DQ62: =-DQ63*DQ61 -> -36.977762 | DR62: =-DR63*DR61 -> -175.17107 | DS62: =SUM(DO62:DR62) -> -365.31329
B63: Effective Tax Rate | C63: =-C62/C61 -> 0.095866462 | H63: =-H62/H61 -> 0.073773236 | M63: =-M62/M61 -> 0.53421847 | R63: =-R62/R61 -> 0.39893651 | W63: =-W62/W61 -> 0.30545917 | AB63: =-AB62/AB61 -> 0.32783173 | AG63: =-AG62/AG61 -> 0.33326604 | AH63: =-AH62/AH61 -> 0.36270465 | AI63: =-AI62/AI61 -> 0.3572237 | AJ63: =-AJ62/AJ61 -> 0.35464037 | AK63: =-AK62/AK61 -> 0.36547099 | AL63: =-AL62/AL61 -> 0.36099883 | AM63: =-AM62/AM61 -> 0.36500169 | AN63: =-AN62/AN61 -> 0.19132775 | ... DF63: =-DF62/DF61 -> 0.29555516 | DG63: 0.3 | DH63: 0.296 | DI63: =-DI62/DI61 -> 0.3003817 | DJ63: 0.3 | DK63: 0.3 | DL63: 0.3 | DM63: 0.3 | DN63: =-DN62/DN61 -> 0.3 | DO63: 0.3 | DP63: 0.3 | DQ63: 0.3 | DR63: 0.3 | DS63: =-DS62/DS61 -> 0.3
B64: Consolidated Net Income | C64: =SUM(C61:C62) -> 9.424688 | H64: =SUM(H61:H62) -> 15.319887 | M64: =SUM(M61:M62) -> 11.014791 | R64: =SUM(R61:R62) -> 30.842439 | W64: =SUM(W61:W62) -> 42.121694 | AB64: =SUM(AB61:AB62) -> 58.415456 | AG64: =SUM(AG61:AG62) -> 122.197 | AH64: =AH61+AH62 -> 33.516 | AI64: =AI61+AI62 -> 38.618 | AJ64: =AJ61+AJ62 -> 38.941 | AK64: =AK61+AK62 -> 73.889 | AL64: =SUM(AL61:AL62) -> 184.964 | AM64: =AM61+AM62 -> 46.974 | AN64: =AN61+AN62 -> 57.702 | AO64: =AO61+AO62 -> 57.38 | AP64: =AP61+AP62 -> 109.375 | AQ64: =SUM(AQ61:AQ62) -> 271.431 | AR64: =AR61+AR62 -> 47.279 | AS64: =AS61+AS62 -> 56.465 | AT64: =AT61+AT62 -> 66.111 | AU64: =AU61+AU62 -> 109.692 | AV64: =SUM(AV61:AV62) -> 279.547 | AW64: =AW61+AW62 -> 52.681 | AX64: =AX61+AX62 -> 48.767 | AY64: =AY61+AY62 -> 60.451 | AZ64: =AZ61+AZ62 -> 110.853 | BA64: =SUM(BA61:BA62) -> 272.733 | BB64: =BB61+BB62 -> 47.81 | BC64: =BC61+BC62 -> 47.668 | BD64: =BD61+BD62 -> 49.046 | BE64: =BE61+BE62 -> 117.416 | BF64: =SUM(BF61:BF62) -> 261.94 | BG64: =BG61+BG62 -> 40.936 | BH64: =BH61+BH62 -> 52.025 | BI64: =BI61+BI62 -> 64.485 | BJ64: =BJ61+BJ62 -> 137.05528 | BK64: =SUM(BK61:BK62) -> 294.50128 | BL64: =BL61+BL62 -> 44.312 | BM64: =BM61+BM62 -> 52.751 | BN64: =BN61+BN62 -> 75.332 | BO64: =BO61+BO62 -> 180.058 | BP64: =BP61+BP62 -> 352.437 | BQ64: =BQ61+BQ62 -> 75.153 | BR64: =BR61+BR62 -> 95.77 | BS64: =BS61+BS62 -> 99.576 | ... DS64: =DS61+DS62 -> 852.39768
B65: Minority Interest | C65: 0 | H65: 0 | M65: 0 | R65: 0 | W65: 0 | AB65: 0 | AG65: -0.35 | AH65: -0.144 | AI65: -0.239 | AJ65: -0.147 | AK65: -0.371 | AL65: =SUM(AH65:AK65) -> -0.901 | AM65: -0.331 | AN65: -0.48 | AO65: -0.064 | AP65: 0 | AQ65: =SUM(AM65:AP65) -> -0.875 | AR65: 0 | AS65: 0 | AT65: 0 | AU65: 0 | AV65: =SUM(AR65:AU65) -> 0 | AW65: =AV65 -> 0 | AX65: 0 | AY65: 0 | AZ65: 0 | BA65: =SUM(AW65:AZ65) -> 0 | BB65: =BA65 -> 0 | BC65: 0 | BD65: 0 | BE65: 0 | BF65: =SUM(BB65:BE65) -> 0 | BG65: =BF65 -> 0 | BH65: 0 | BI65: 0 | BJ65: 0 | BK65: =SUM(BG65:BJ65) -> 0 | BL65: =BK65 -> 0 | BM65: 0 | BN65: 0 | BO65: 0 | BP65: =SUM(BL65:BO65) -> 0 | BQ65: 0 | BR65: 0 | BS65: 0 | BT65: 0 | BU65: =SUM(BQ65:BT65) -> 0 | BV65: 0 | BW65: 0 | BX65: 0 | BY65: 0 | BZ65: =SUM(BV65:BY65) -> 0 | CA65: 0 | CB65: 0 | CC65: 0 | CD65: 0 | CE65: =SUM(CA65:CD65) -> 0 | CF65: 0 | CG65: 0 | CH65: 0 | CI65: 0 | CJ65: =SUM(CF65:CI65) -> 0 | CK65: 0 | CL65: 0 | CM65: 0 | CN65: 0 | CO65: =SUM(CK65:CN65) -> 0 | CP65: 0 | CQ65: 0 | CR65: 0 | CS65: 0 | CT65: =SUM(CP65:CS65) -> 0 | CU65: 0 | CV65: 0 | CW65: 0 | CX65: 0 | CY65: =SUM(CU65:CX65) -> 0 | CZ65: 0 | DA65: 0 | DB65: 0 | DC65: 0 | DD65: =SUM(CZ65:DC65) -> 0 | DE65: 0 | DF65: 0 | DG65: 0 | DH65: 0 | DI65: =SUM(DE65:DH65) -> 0 | DJ65: 0 | DK65: 0 | DL65: 0 | DM65: 0 | DN65: =SUM(DJ65:DM65) -> 0 | DO65: 0 | DP65: 0 | DQ65: 0 | DR65: 0 | DS65: =SUM(DO65:DR65) -> 0
B66: Net to Majority | C66: =C64+C65 -> 9.424688 | H66: =H64+H65 -> 15.319887 | M66: =M64+M65 -> 11.014791 | R66: =R64+R65 -> 30.842439 | W66: =W64+W65 -> 42.121694 | AB66: =AB64+AB65 -> 58.415456 | AG66: =AG64+AG65 -> 121.847 | AH66: =AH64+AH65 -> 33.372 | AI66: =AI64+AI65 -> 38.379 | AJ66: =AJ64+AJ65 -> 38.794 | AK66: =AK64+AK65 -> 73.518 | AL66: =AL64+AL65 -> 184.063 | AM66: =AM64+AM65 -> 46.643 | AN66: =AN64+AN65 -> 57.222 | ... DS66: =DS64+DS65 -> 852.39768
B68: Period-End Shares | M68: =M69 -> 135.03346 | R68: 135.054 | W68: 136.414 | AB68: 140.8 | AG68: 142.392 | AH68: =2*(54.026+17.508) -> 143.068 | AI68: =108.773+34.525 -> 143.298 | AJ68: =109.359+34.125 -> 143.484 | AK68: =AL68 -> 143.547 | AL68: 143.547 | AM68: =111.517+32.402 -> 143.919 | AN68: =111.633+32.379 -> 144.012 | AO68: =111.777+32.379 -> 144.156 | AP68: =112.371+32.065 -> 144.436 | AQ68: 144.436 | AR68: =112.517+32.033 -> 144.55 | AS68: =115.006+30.033 -> 145.039 | AT68: =115.223+29.983 -> 145.206 | AU68: =115.342+29.955 -> 145.297 | AV68: 145.297 | AW68: =115.503+29.955 -> 145.458 | AX68: =114.185+29.938 -> 144.123 | AY68: =132.478+9.833 -> 142.311 | AZ68: =132.112+9.833 -> 141.945 | BA68: 141.945 | BB68: =131.978+9.833 -> 141.811 | BC68: =131.104+9.833 -> 140.937 | BD68: =129.581+9.804 -> 139.385 | BE68: =127.494121+9.803819 -> 137.29794 | BF68: 144.298 | BG68: =127.181155+9.803819 -> 136.98497 | BH68: =127.262705+9.784239 -> 137.04694 | BI68: =9.784239+127.29592 -> 137.08016 | BJ68: =127.272795+9.780927 -> 137.05372 | BK68: 137.11174 | BL68: =127.131+9.781 -> 136.912 | BM68: =9.781+125.697 -> 135.478 | BN68: =125.592+9.781 -> 135.373 | BO68: =125.679588+9.776421 -> 135.45601 | BP68: =BO68 -> 135.45601 | BQ68: =125.914467+9.776421 -> 135.69089 | BR68: =122.594553+9.776421 -> 132.37097 | BS68: =122.627574+9.776421 -> 132.404 | BT68: =123.2814+7.669716 -> 130.95112 | BU68: =BT68 -> 130.95112 | BV68: =122.894703+7.38086 -> 130.27556 | BW68: =123.140731+7.134901 -> 130.27563 | BX68: =123.334595+6.960312 -> 130.29491 | BY68: =124.115144+6.049939 -> 130.16508 | BZ68: =BZ381 -> 130.16508 | CA68: =124.814503+5.392512 -> 130.20702 | CB68: =124.920793+5.392512 -> 130.31331 | CC68: =125.122533+5.215512 -> 130.33804 | CD68: =125.164616+5.203012 -> 130.36763 | CE68: =CE381 -> 130.36763 | CF68: =124.952259+5.203012 -> 130.15527 | CG68: =124.644+5.203012 -> 129.84701 | CH68: =124.135+5.203012 -> 129.33801 | CI68: =123.297+5.203012 -> 128.50001 | CJ68: =CJ381 -> 128.50001 | CK68: =122.439795+5.203012 -> 127.64281 | CL68: =122.303352+5.203012 -> 127.50636 | CM68: =5.203+122.318 -> 127.521 | CN68: =122.04868+5.115961 -> 127.16464 | CO68: =CO381 -> 127.16464 | CP68: =122.099+5.116 -> 127.215 | CQ68: =121.613+5.116 -> 126.729 | CR68: =121.122+5.116 -> 126.238 | CS68: =121.106+5.116 -> 126.222 | CT68: =CT381 -> 126.222 | CU68: =120.47+5.116 -> 125.586 | CV68: =118.61+5.116 -> 123.726 | CW68: =117.046+5.116 -> 122.162 | CX68: =116.166+5.116 -> 121.282 | CY68: =CY381 -> 121.282 | CZ68: =114.909+5.116 -> 120.025 | DA68: =5.116+113.828 -> 118.944 | DB68: =5.116+112.789 -> 117.905 | DC68: =110.482671+5.115961 -> 115.59863 | DD68: =DD381 -> 115.59863 | DE68: =5.116+109.308 -> 114.424 | DF68: =106.566+5.116 -> 111.682 | DG68: =DG381 -> 109.20712 | DH68: =DH381 -> 106.95722 | DI68: =DI381 -> 106.95722 | DJ68: =DJ381 -> 105.75407 | DK68: =DK381 -> 104.57451 | DL68: =DL381 -> 103.41808 | DM68: =DM381 -> 102.28432 | DN68: =DN381 -> 102.28432 | ... DS68: =DS381 -> 97.967281
B69: Basic Average Shares | C69: 132.86 | H69: 132.86 | M69: 135.03346 | R69: 132.86 | W69: 137.5 | AB69: 137.5 | AG69: 141.72 | AH69: 142.76 | AI69: 143.163 | AJ69: 143.37 | AK69: 143.196 | AL69: 143.196 | AM69: 143.678 | AN69: 143.972 | AO69: 144.057 | AP69: 144.285 | AQ69: 143.998 | AR69: 144.482 | AS69: 144.818 | AT69: 145.12 | AU69: 145.235 | AV69: 144.91375 | AW69: 145.383 | AX69: 145.18 | AY69: 143.18 | AZ69: 141.999 | BA69: 143.935 | BB69: 141.967 | BC69: 141.372 | BD69: 140.282 | BE69: 138.076 | BF69: 140.42425 | BG69: 137.263 | BH69: 136.987 | BI69: 137.033 | BJ69: 137.059 | BK69: 137.0855 | BL69: 137.037 | BM69: 136.171 | BN69: 135.364 | BO69: 135.381 | BP69: 135.988 | BQ69: 135.502 | BR69: 133.986 | BS69: 132.406 | BT69: 131.878 | BU69: 133.413 | BV69: 130.694 | BW69: 130.285 | BX69: 130.282 | BY69: 130.311 | BZ69: =BZ382 -> 130.393 | CA69: 130.251 | CB69: 130.245 | CC69: 130.318 | CD69: 130.34 | CE69: =CE382 -> 130.2885 | CF69: 130.358 | CG69: 130.007 | CH69: 129.684 | CI69: 129.015 | CJ69: =CJ382 -> 129.766 | CK69: 128.077 | CL69: 127.619 | CM69: 127.511 | CN69: 127.456 | CO69: =CO382 -> 127.66575 | CP69: 127.246 | CQ69: 126.969 | CR69: 126.46 | CS69: 126.228 | CT69: =CT382 -> 126.72575 | CU69: 125.989 | CV69: 124.721 | CW69: 122.697 | CX69: 121.683 | CY69: =CY382 -> 123.7725 | CZ69: 120.632 | DA69: 119.6 | DB69: 118.535 | DC69: 117.155 | DD69: =DD382 -> 118.9805 | DE69: 115.414 | DF69: 112.898 | DG69: =DG382 -> 110.44456 | DH69: =DH382 -> 108.08217 | DI69: =DI382 -> 111.70968 | DJ69: =DJ382 -> 106.35565 | DK69: =DK382 -> 105.16429 | DL69: =DL382 -> 103.99629 | DM69: =DM382 -> 102.8512 | DN69: =DN382 -> 104.59186 | ... DS69: =DS382 -> 100.09909
B70: Diluted Average Shares | C70: 138.594 | H70: 138.594 | M70: 143.97901 | R70: 138.594 | W70: 142 | AB70: 142 | AG70: 143.858 | AH70: 144.91 | AI70: 145.228 | AJ70: 145.349 | AK70: 145.278 | AL70: 145.278 | AM70: 145.637 | AN70: 145.678 | AO70: 145.748 | AP70: 145.846 | AQ70: 145.72725 | AR70: 145.849 | AS70: 145.916 | AT70: 146.014 | AU70: 146.035 | AV70: 145.9535 | AW70: 145.861 | AX70: 145.544 | AY70: 143.441 | AZ70: 142.346 | BA70: 144.298 | BB70: 142.337 | BC70: 141.644 | BD70: 140.457 | BE70: 138.24 | BF70: 140.6695 | BG70: 137.495 | BH70: 137.229 | BI70: 137.237 | BJ70: 137.245 | BK70: 137.30175 | BL70: 137.2 | BM70: 136.303 | BN70: 135.578 | BO70: 135.723 | BP70: 136.198 | BQ70: 135.931 | BR70: 134.53 | BS70: 133.077 | BT70: 132.465 | BU70: 133.971 | BV70: 131.337 | BW70: 130.783 | BX70: 130.805 | BY70: 130.896 | BZ70: =BZ384 -> 130.95525 | CA70: 130.803 | CB70: 130.799 | CC70: 130.924 | CD70: 130.956 | CE70: =CE384 -> 130.8705 | CF70: 130.984 | CG70: 130.49 | CH70: 130.189 | CI70: 129.508 | CJ70: =CJ384 -> 130.29275 | CK70: 128.541 | CL70: 127.906 | CM70: 127.82 | CN70: 127.802 | CO70: =CO384 -> 128.01725 | CP70: 127.621 | CQ70: 127.263 | CR70: 126.77 | CS70: 126.584 | CT70: =CT384 -> 127.0595 | CU70: 126.336 | CV70: 124.857 | CW70: 122.803 | CX70: 121.895 | CY70: =CY384 -> 123.97275 | CZ70: 120.843 | DA70: 119.68 | DB70: 118.552 | DC70: 117.196 | DD70: =DD384 -> 119.06775 | DE70: 115.482 | DF70: 112.919 | DG70: =DG384 -> 110.94456 | DH70: =DH384 -> 108.58217 | DI70: =DI384 -> 111.98193 | DJ70: =DJ384 -> 107.35565 | DK70: =DK384 -> 106.16429 | DL70: =DL384 -> 104.99629 | DM70: =DM384 -> 103.8512 | DN70: =DN384 -> 105.59186 | ... DS70: =DS384 -> 101.09909
B72: Comparable EPS | C72: =C66/C70 -> 0.068002136 | H72: =H66/H70 -> 0.11053788 | M72: =M66/M70 -> 0.076502754 | R72: =R66/R70 -> 0.22253805 | W72: =W66/W70 -> 0.29663165 | AB72: =AB66/AB70 -> 0.41137645 | AG72: =AG66/AG70 -> 0.84699495 | AH72: =AH66/AH70 -> 0.23029467 | AI72: =AI66/AI70 -> 0.26426722 | AJ72: =AJ66/AJ70 -> 0.26690242 | AK72: =AK66/AK70 -> 0.50605047 | AL72: =AL66/AL70 -> 1.2669709 | AM72: =AM66/AM70 -> 0.32026889 | AN72: =AN66/AN70 -> 0.39279781 | ... AU72: =AU66/AU70 -> 0.751135 | AV72: =AV64/AV70 -> 1.9153155 | AW72: =AW66/AW70 -> 0.36117262 | AX72: =AX66/AX70 -> 0.33506706 | AY72: =AY66/AY70 -> 0.4214346 | AZ72: =AZ66/AZ70 -> 0.77875739 | BA72: =BA64/BA70 -> 1.8900678 | BB72: =BB66/BB70 -> 0.33589299 | BC72: =BC66/BC70 -> 0.33653385 | BD72: =BD66/BD70 -> 0.34918872 | BE72: =BE66/BE70 -> 0.84936343 | BF72: =BF64/BF70 -> 1.8620952 | BG72: =BG66/BG70 -> 0.29772719 | BH72: =BH66/BH70 -> 0.37911083 | BI72: =BI66/BI70 -> 0.46988057 | BJ72: =BJ66/BJ70 -> 0.99861768 | BK72: =BK64/BK70 -> 2.1449201 | BL72: =BL66/BL70 -> 0.32297376 | BM72: =BM66/BM70 -> 0.38701276 | BN72: =BN66/BN70 -> 0.55563587 | BO72: =BO66/BO70 -> 1.326658 | BP72: =BP64/BP70 -> 2.5876812 | BQ72: =BQ66/BQ70 -> 0.55287609 | BR72: =BR66/BR70 -> 0.71188582 | BS72: =BS66/BS70 -> 0.74825853 | BT72: =BT66/BT70 -> 1.8456196 | BU72: =BU64/BU70 -> 3.8439588 | BV72: =BV66/BV70 -> 0.7355353 | BW72: =BW66/BW70 -> 0.95570525 | BX72: =BX66/BX70 -> 0.96312832 | BY72: =BY66/BY70 -> 2.276777 | BZ72: =BZ64/BZ70 -> 4.9298978 | CA72: =CA66/CA70 -> 0.21889406 | CB72: =CB66/CB70 -> 0.73622887 | CC72: =CC66/CC70 -> 1.1554642 | CD72: =CD66/CD70 -> 2.5762164 | CE72: =CE64/CE70 -> 4.6884439 | CF72: =CF66/CF70 -> 1.1623404 | CG72: =CG66/CG70 -> 1.6536363 | CH72: =CH66/CH70 -> 1.6230557 | CI72: =CI66/CI70 -> 3.3663094 | CJ72: =CJ64/CJ70 -> 7.7924443 | CK72: =CK66/CK70 -> 1.478112 | CL72: =CL66/CL70 -> 2.1969415 | CM72: =CM66/CM70 -> 1.99867 | CN72: =CN66/CN70 -> 4.4011909 | CO72: =CO64/CO70 -> 10.068573 | CP72: =CP66/CP70 -> 2.2755268 | CQ72: =CQ66/CQ70 -> 2.6842287 | CR72: =CR66/CR70 -> 2.5308748 | CS72: =CS66/CS70 -> 5.2887253 | CT72: =CT64/CT70 -> 12.768152 | CU72: =CU66/CU70 -> 2.5441758 | CV72: =CV66/CV70 -> 3.1469761 | CW72: =CW66/CW70 -> 2.8653209 | CX72: =CX66/CX70 -> 6.139735 | CY72: =CY64/CY70 -> 14.637217 | CZ72: =CZ66/CZ70 -> 2.6031462 | DA72: =DA66/DA70 -> 3.0991394 | DB72: =DB66/DB70 -> 2.5881891 | DC72: =DC66/DC70 -> 5.0076026 | DD72: =DD64/DD70 -> 13.262894 | DE72: =DE66/DE70 -> 1.6889905 | DF72: =DF66/DF70 -> 2.9155678 | DG72: =DG66/DG70 -> 0.97916009 | DH72: =DH66/DH70 -> 4.1161854 | DI72: =DI64/DI70 -> 9.643054 | DJ72: =DJ66/DJ70 -> 1.5819521 | DK72: =DK66/DK70 -> 1.8998688 | DL72: =DL66/DL70 -> 0.89482614 | DM72: =DM66/DM70 -> 4.0351013 | DN72: =DN64/DN70 -> 8.3769078 | DO72: =DO66/DO70 -> 1.5831448 | DP72: =DP66/DP70 -> 1.9162995 | DQ72: =DQ66/DQ70 -> 0.85810449 | DR72: =DR66/DR70 -> 4.1082364 | DS72: =DS64/DS70 -> 8.4313093
B73: One-Time Items | C73: =-10.837688/C70 -> -0.078197382 | H73: =-13.925783/H70 -> -0.10047897 | M73: =-3.34846000000002/M70 -> -0.023256584 | R73: 0 | W73: =-2.7311/W70 -> -0.019233099 | AB73: =-0.134456/AB70 -> -0.00094687324 | AG73: 0 | AH73: 0 | AI73: 0 | AJ73: 0 | AK73: 0 | AL73: 0 | AM73: 0 | AN73: 0 | AO73: 0 | AP73: 0 | AQ73: 0 | AR73: 0 | AS73: 0 | AT73: 0 | AU73: 0 | AV73: 0 | AW73: =-33.7/AW70 -> -0.23104188 | AX73: 0 | AY73: 0 | AZ73: 0 | BA73: =-33.7/BA70 -> -0.23354447 | BB73: 0 | BC73: 0 | BD73: =(-3.6+7.7)/BD70 -> 0.029190428 | BE73: 0 | BF73: =(-3.6+7.7)/BF70 -> 0.029146332 | BG73: =+(45.336-BG66)/BG70 -> 0.032001164 | BH73: =1.6/BH70 -> 0.011659343 | BI73: =3.8/BI70 -> 0.027689326 | BJ73: =-0.922/BJ70 -> -0.0067179132 | BK73: 0.066047349 | BL73: =-13.066/BL70 -> -0.095233236 | BM73: =-4.04/BM70 -> -0.029639847 | BN73: =-(22.185-5.813)/BN70 -> -0.12075705 | BO73: =-(1.858-0.855+59.294)/BO70 -> -0.44426516 | BP73: =-(47.223-12.741+59.294)/BP70 -> -0.688527 | BQ73: 0 | BR73: 0 | BS73: =-5.163/BS70 -> -0.038797087 | BT73: =-(23.714+2.301)/BT70 -> -0.1963915 | BU73: =(BQ73*BQ70+BR73*BR70+BS73*BS70+BT73*BT70)/BU70 -> -0.23272201 | BV73: 0 | BW73: 0 | BX73: 0 | BY73: 0 | BZ73: =(BV73*BV70+BW73*BW70+BX73*BX70+BY73*BY70)/BZ70 -> 0 | CA73: 0 | CB73: =-(7.201-0.782+5.045-1.967)/CB70 -> -0.072607589 | CC73: =-(1.017+7.514-0.896)/CC70 -> -0.058316275 | CD73: =-(0.285+7.517-0.27)/CD70 -> -0.057515501 | CE73: =(CA73*CA70+CB73*CB70+CC73*CC70+CD73*CD70)/CE70 -> -0.18846111 | CF73: =-(0.496+7.168-0.372)/CF70 -> -0.055670922 | CG73: =-(1.035+7.108-0.434)/CG70 -> -0.059077324 | CH73: =-(0.328+23.799-0.611)/CH70 -> -0.1806297 | CI73: =-(1.13+0.33)/CI70 -> -0.011273435 | CJ73: =(CF73*CF70+CG73*CG70+CH73*CH70+CI73*CI70)/CJ70 -> -0.30682444 | CK73: 0 | CL73: =+(10.18-1.661)/CL70 -> 0.0666036 | CM73: 0 | CN73: =-(470.841-28.171)/CN70 -> -3.4637173 | CO73: =(CK73*CK70+CL73*CL70+CM73*CM70+CN73*CN70)/CO70 -> -3.3913477 | CP73: 0 | CQ73: 0 | CR73: =-(23.709+44.186+30.315-26.085)/CR70 -> -0.56894376 | CS73: 0 | CT73: =(CP73*CP70+CQ73*CQ70+CR73*CR70+CS73*CS70)/CT70 -> -0.56764744 | CU73: 0 | CV73: 0 | CW73: 0 | CX73: 0 | CY73: =(CU73*CU70+CV73*CV70+CW73*CW70+CX73*CX70)/CY70 -> 0 | CZ73: 0 | DA73: 0 | DB73: 0 | DC73: 0 | DD73: =(CZ73*CZ70+DA73*DA70+DB73*DB70+DC73*DC70)/DD70 -> 0 | DE73: 0 | DF73: 0 | DG73: 0 | DH73: 0 | DI73: =(DE73*DE70+DF73*DF70+DG73*DG70+DH73*DH70)/DI70 -> 0 | DJ73: 0 | DK73: 0 | DL73: 0 | DM73: 0 | DN73: =(DJ73*DJ70+DK73*DK70+DL73*DL70+DM73*DM70)/DN70 -> 0 | DO73: 0 | DP73: 0 | DQ73: 0 | DR73: 0 | DS73: =(DO73*DO70+DP73*DP70+DQ73*DQ70+DR73*DR70)/DS70 -> 0
B74: % chg. in adjusted EPS | H74: =H72/C72-1 -> 0.62550601 | M74: =M72/H72-1 -> -0.30790464 | R74: =R72/M72-1 -> 1.9088894 | W74: =W72/R72-1 -> 0.33294797 | AB74: =AB72/W72-1 -> 0.3868259 | AG74: =AG72/AB72-1 -> 1.0589291 | AL74: =AL72/AG72-1 -> 0.49584234 | AM74: =AM72/AH72-1 -> 0.39069173 | AN74: =AN72/AI72-1 -> 0.48636601 | AO74: =AO72/AJ72-1 -> 0.47340031 | AP74: =AP72/AK72-1 -> 0.4819369 | AQ74: =AQ72/AL72-1 -> 0.4653783 | AR74: =AR72/AM72-1 -> 0.012162108 | AS74: =AS72/AN72-1 -> -0.014838675 | ... DS74: =DS72/DN72-1 -> 0.0064942266
B76: GAAP EPS | C76: =SUM(C72:C73) -> -0.010195247 | H76: =SUM(H72:H73) -> 0.010058906 | M76: =SUM(M72:M73) -> 0.05324617 | R76: =SUM(R72:R73) -> 0.22253805 | W76: =SUM(W72:W73) -> 0.27739855 | AB76: =SUM(AB72:AB73) -> 0.41042958 | AG76: =SUM(AG72:AG73) -> 0.84699495 | AH76: =AH72+AH73 -> 0.23029467 | AI76: =AI72+AI73 -> 0.26426722 | AJ76: =AJ72+AJ73 -> 0.26690242 | AK76: =AK72+AK73 -> 0.50605047 | AL76: =SUM(AL72:AL73) -> 1.2669709 | AM76: =AM72+AM73 -> 0.32026889 | AN76: =AN72+AN73 -> 0.39279781 | AO76: =AO72+AO73 -> 0.39325411 | AP76: =AP72+AP73 -> 0.74993486 | AQ76: =SUM(AQ72:AQ73) -> 1.8565917 | AR76: =AR72+AR73 -> 0.32416403 | AS76: =AS72+AS73 -> 0.38696922 | AT76: =AT72+AT73 -> 0.45277165 | AU76: =AU72+AU73 -> 0.751135 | AV76: =SUM(AV72:AV73) -> 1.9153155 | AW76: =AW72+AW73 -> 0.13013074 | AX76: =AX72+AX73 -> 0.33506706 | AY76: =AY72+AY73 -> 0.4214346 | AZ76: =AZ72+AZ73 -> 0.77875739 | BA76: =SUM(BA72:BA73) -> 1.6565233 | BB76: =BB72+BB73 -> 0.33589299 | BC76: =BC72+BC73 -> 0.33653385 | BD76: =BD72+BD73 -> 0.37837915 | BE76: =BE72+BE73 -> 0.84936343 | BF76: =SUM(BF72:BF73) -> 1.8912415 | BG76: =BG72+BG73 -> 0.32972835 | BH76: =BH72+BH73 -> 0.39077017 | BI76: =BI72+BI73 -> 0.4975699 | BJ76: =BJ72+BJ73 -> 0.99189977 | BK76: =SUM(BK72:BK73) -> 2.2109675 | BL76: =BL72+BL73 -> 0.22774052 | BM76: =BM72+BM73 -> 0.35737291 | BN76: =BN72+BN73 -> 0.43487882 | BO76: =BO72+BO73 -> 0.88239281 | BP76: =SUM(BP72:BP73) -> 1.8991542 | BQ76: =BQ72+BQ73 -> 0.55287609 | BR76: =BR72+BR73 -> 0.71188582 | BS76: =BS72+BS73 -> 0.70946144 | BT76: =BT72+BT73 -> 1.6492281 | BU76: =SUM(BU72:BU73) -> 3.6112368 | BV76: =BV72+BV73 -> 0.7355353 | BW76: =BW72+BW73 -> 0.95570525 | BX76: =BX72+BX73 -> 0.96312832 | BY76: =BY72+BY73 -> 2.276777 | BZ76: =SUM(BZ72:BZ73) -> 4.9298978 | CA76: =CA72+CA73 -> 0.21889406 | CB76: =CB72+CB73 -> 0.66362128 | CC76: =CC72+CC73 -> 1.097148 | CD76: =CD72+CD73 -> 2.5187009 | CE76: =SUM(CE72:CE73) -> 4.4999828 | CF76: =CF72+CF73 -> 1.1066695 | CG76: =CG72+CG73 -> 1.594559 | CH76: =CH72+CH73 -> 1.442426 | CI76: =CI72+CI73 -> 3.355036 | CJ76: =SUM(CJ72:CJ73) -> 7.4856199 | CK76: =CK72+CK73 -> 1.478112 | CL76: =CL72+CL73 -> 2.2635451 | CM76: =CM72+CM73 -> 1.99867 | CN76: =CN72+CN73 -> 0.93747359 | CO76: =SUM(CO72:CO73) -> 6.6772251 | CP76: =CP72+CP73 -> 2.2755268 | CQ76: =CQ72+CQ73 -> 2.6842287 | CR76: =CR72+CR73 -> 1.9619311 | CS76: =CS72+CS73 -> 5.2887253 | CT76: =SUM(CT72:CT73) -> 12.200504 | CU76: =CU72+CU73 -> 2.5441758 | CV76: =CV72+CV73 -> 3.1469761 | CW76: =CW72+CW73 -> 2.8653209 | CX76: =CX72+CX73 -> 6.139735 | CY76: =SUM(CY72:CY73) -> 14.637217 | CZ76: =CZ72+CZ73 -> 2.6031462 | DA76: =DA72+DA73 -> 3.0991394 | DB76: =DB72+DB73 -> 2.5881891 | DC76: =DC72+DC73 -> 5.0076026 | DD76: =SUM(DD72:DD73) -> 13.262894 | DE76: =DE72+DE73 -> 1.6889905 | DF76: =DF72+DF73 -> 2.9155678 | DG76: =DG72+DG73 -> 0.97916009 | DH76: =DH72+DH73 -> 4.1161854 | DI76: =SUM(DI72:DI73) -> 9.643054 | DJ76: =DJ72+DJ73 -> 1.5819521 | DK76: =DK72+DK73 -> 1.8998688 | DL76: =DL72+DL73 -> 0.89482614 | DM76: =DM72+DM73 -> 4.0351013 | DN76: =SUM(DN72:DN73) -> 8.3769078 | DO76: =DO72+DO73 -> 1.5831448 | DP76: =DP72+DP73 -> 1.9162995 | DQ76: =DQ72+DQ73 -> 0.85810449 | DR76: =DR72+DR73 -> 4.1082364 | DS76: =SUM(DS72:DS73) -> 8.4313093
B78: EBITDA | M78: =M55+M90 -> 28.02837 | R78: =R55+R90 -> 58.416059 | W78: =W55+W90 -> 76.588815 | AB78: =AB55+AB90 -> 107.574 | AG78: =AG55+AG90 -> 205.005 | AH78: =AH55+AH90 -> 57.728 | AI78: =AI55+AI90 -> 67.003 | AJ78: =AJ55+AJ90 -> 67.048 | AK78: =AK55+AK90 -> 125.438 | AL78: =AL55+AL90 -> 317.217 | AM78: =AM55+AM90 -> 82.863 | AN78: =AN55+AN90 -> 79.869 | ... DS78: =DS55+DS90 -> 2009.5135
B79: Rent | M79: ='3. Earnings Build'!M97 -> -9.2 | R79: ='3. Earnings Build'!R97 -> -19.006214 | W79: ='3. Earnings Build'!W97 -> -32.701379 | AB79: ='3. Earnings Build'!AB97 -> -41.639 | AG79: ='3. Earnings Build'!AG97 -> -53.071 | AH79: ='3. Earnings Build'!AH97 -> -14.949859 | AI79: ='3. Earnings Build'!AI97 -> -15.776036 | AJ79: ='3. Earnings Build'!AJ97 -> -17.428389 | AK79: ='3. Earnings Build'!AK97 -> -18.962716 | AL79: ='3. Earnings Build'!AL97 -> -67.117 | AM79: ='3. Earnings Build'!AM97 -> -19.056958 | AN79: ='3. Earnings Build'!AN97 -> -19.89379 | ... DS79: ='3. Earnings Build'!DS97 -> -921.99245
B80: EBITDAR | M80: =M78-M79 -> 37.22837 | R80: =R78-R79 -> 77.422273 | W80: =W78-W79 -> 109.29019 | AB80: =AB78-AB79 -> 149.213 | AG80: =AG78-AG79 -> 258.076 | AH80: =AH78-AH79 -> 72.677859 | AI80: =AI78-AI79 -> 82.779036 | AJ80: =AJ78-AJ79 -> 84.476389 | AK80: =AK78-AK79 -> 144.40072 | AL80: =AL78-AL79 -> 384.334 | AM80: =AM78-AM79 -> 101.91996 | AN80: =AN78-AN79 -> 99.76279 | ... DS80: =DS78-DS79 -> 2931.506
B81: FCF per Share | M81: =M126/M70 -> 0.085999368 | R81: =R126/R70 -> 0.053064851 | W81: =W126/W70 -> 0.035967007 | AB81: =AB126/AB70 -> 0.72157042 | AG81: =AG126/AG70 -> 1.0401785 | AH81: =AH126/AH70 -> -0.47737216 | AI81: =AI126/AI70 -> 0.0095091856 | AJ81: =AJ126/AJ70 -> 0.14189296 | AK81: =AK126/AK70 -> 0.92325748 | AL81: =AL126/AL70 -> 0.59856276 | AM81: =AM126/AM70 -> 0.022356956 | AN81: =AN126/AN70 -> 0.14565 | ... DS81: =DS126/DS70 -> 7.9976534
B82: FCF Conversion | M82: =M81/M72 -> 1.1241343 | R82: =R81/R72 -> 0.23845293 | W82: =W81/W72 -> 0.12125142 | AB82: =AB81/AB72 -> 1.7540392 | AG82: =AG81/AG72 -> 1.2280811 | AH82: =AH81/AH72 -> -2.0728755 | AI82: =AI81/AI72 -> 0.03598322 | AJ82: =AJ81/AJ72 -> 0.5316286 | AK82: =AK81/AK72 -> 1.8244376 | AL82: =AL81/AL72 -> 0.47243607 | AM82: =AM81/AM72 -> 0.069806831 | AN82: =AN81/AN72 -> 0.37080144 | ... DS82: =DS81/DS72 -> 0.94856601
B84: CASH FLOW STATEMENT
B85: Quarterly
B86: Net Income (Comparable) | M86: =M129 -> 11.014791 | R86: =R129 -> 30.842439 | W86: =W129 -> 42.121694 | AB86: =AB129 -> 58.415456 | AG86: =AG64 -> 122.197 | AH86: =AH64 -> 33.516 | AI86: =AI64 -> 38.618 | AJ86: =AJ64 -> 38.941 | AK86: =AK64 -> 73.889 | AL86: =AL129 -> 184.964 | AM86: =AM64 -> 46.974 | AN86: =AN64 -> 57.702 | AO86: =AO64 -> 57.38 | AP86: =AP64 -> 109.375 | AQ86: =AQ129 -> 271.431 | AR86: =AR64 -> 47.279 | AS86: =AS64 -> 56.465 | AT86: =AT64 -> 66.111 | AU86: =AU64 -> 109.692 | AV86: =AV129 -> 279.547 | AW86: =AW64 -> 52.681 | AX86: =AX64 -> 48.767 | AY86: =AY64 -> 60.451 | AZ86: =AZ64 -> 110.853 | BA86: =BA129 -> 272.733 | BB86: =BB64 -> 47.81 | BC86: =BC64 -> 47.668 | BD86: =BD64 -> 49.046 | BE86: =BE64 -> 117.416 | BF86: =BF129 -> 261.94 | BG86: =BG64 -> 40.936 | BH86: =BH64 -> 52.025 | BI86: =BI64 -> 64.485 | BJ86: =BJ64 -> 137.05528 | BK86: =BK129 -> 294.50128 | BL86: =BL64 -> 44.312 | BM86: =BM64 -> 52.751 | BN86: =BN64 -> 75.332 | BO86: =BO64 -> 180.058 | BP86: =BP64 -> 352.437 | BQ86: =BQ64 -> 75.153 | BR86: =BR64 -> 95.77 | BS86: =BS64 -> 99.576 | ... DS86: =DS64 -> 852.39768
B87: One-Timers | M87: =M130 -> -3.34846 | R87: =R130 -> 1.273442 | W87: =W130 -> -1.620102 | AB87: =AB130 -> -0.134456 | AG87: =AG130 -> 0 | AH87: =AH70*AH73 -> 0 | AI87: =AI70*AI73 -> 0 | AJ87: =AJ70*AJ73 -> 0 | AK87: =AK70*AK73 -> 0 | AL87: =AL130 -> 0 | AM87: =AM70*AM73 -> 0 | AN87: =AN70*AN73 -> 0 | AO87: =AO70*AO73 -> 0 | AP87: =AP70*AP73 -> 0 | AQ87: =AQ130 -> 0 | AR87: =AR70*AR73 -> 0 | AS87: =AS70*AS73 -> 0 | AT87: =AT70*AT73 -> 0 | AU87: =AU70*AU73 -> 0 | AV87: =AV130 -> 0 | AW87: =AW70*AW73 -> -33.7 | AX87: =AX70*AX73 -> 0 | AY87: =AY70*AY73 -> 0 | AZ87: =AZ70*AZ73 -> 0 | BA87: =BA130 -> -33.7 | BB87: =BB70*BB73 -> 0 | BC87: =BC70*BC73 -> 0 | BD87: =BD70*BD73 -> 4.1 | BE87: =BE70*BE73 -> 0 | BF87: =BF130 -> 4.107 | BG87: =BG70*BG73 -> 4.4 | BH87: =BH70*BH73 -> 1.6 | BI87: =BI70*BI73 -> 3.8 | BJ87: =BJ70*BJ73 -> -0.922 | BK87: =BK130 -> 9.0684166 | BL87: =BL73*BL70 -> -13.066 | BM87: =BM73*BM70 -> -4.04 | BN87: =BN73*BN70 -> -16.372 | BO87: =BO73*BO70 -> -60.297 | BP87: =BP73*BP70 -> -93.776 | BQ87: =BQ73*BQ70 -> 0 | BR87: =BR73*BR70 -> 0 | BS87: =BS73*BS70 -> -5.163 | BT87: =BT73*BT70 -> -26.015 | BU87: =SUM(BQ87:BT87) -> -31.178 | BV87: =BV73*BV70 -> 0 | BW87: =BW73*BW70 -> 0 | BX87: =BX73*BX70 -> 0 | BY87: =BY73*BY70 -> 0 | BZ87: =SUM(BV87:BY87) -> 0 | CA87: =CA73*CA70 -> 0 | CB87: =CB73*CB70 -> -9.497 | CC87: =CC73*CC70 -> -7.635 | CD87: =CD73*CD70 -> -7.532 | CE87: =SUM(CA87:CD87) -> -24.664 | CF87: =CF73*CF70 -> -7.292 | CG87: =CG73*CG70 -> -7.709 | CH87: =CH73*CH70 -> -23.516 | CI87: =CI73*CI70 -> -1.46 | CJ87: =SUM(CF87:CI87) -> -39.977 | CK87: =CK73*CK70 -> 0 | CL87: =CL73*CL70 -> 8.519 | CM87: =CM73*CM70 -> 0 | CN87: =CN73*CN70 -> -442.67 | CO87: =SUM(CK87:CN87) -> -434.151 | CP87: =CP73*CP70 -> 0 | CQ87: =CQ73*CQ70 -> 0 | CR87: =CR73*CR70 -> -72.125 | CS87: =CS73*CS70 -> 0 | CT87: =SUM(CP87:CS87) -> -72.125 | CU87: =CU73*CU70 -> 0 | CV87: =CV73*CV70 -> 0 | CW87: =CW73*CW70 -> 0 | CX87: =CX73*CX70 -> 0 | CY87: =SUM(CU87:CX87) -> 0 | CZ87: =CZ73*CZ70 -> 0 | DA87: =DA73*DA70 -> 0 | DB87: =DB73*DB70 -> 0 | DC87: =DC73*DC70 -> 0 | DD87: =SUM(CZ87:DC87) -> 0 | DE87: =DE73*DE70 -> 0 | DF87: =DF73*DF70 -> 0 | DG87: =DG73*DG70 -> 0 | DH87: =DH73*DH70 -> 0 | DI87: =SUM(DE87:DH87) -> 0 | DJ87: =DJ73*DJ70 -> 0 | DK87: =DK73*DK70 -> 0 | DL87: =DL73*DL70 -> 0 | DM87: =DM73*DM70 -> 0 | DN87: =SUM(DJ87:DM87) -> 0 | DO87: =DO73*DO70 -> 0 | DP87: =DP73*DP70 -> 0 | DQ87: =DQ73*DQ70 -> 0 | DR87: =DR73*DR70 -> 0 | DS87: =SUM(DO87:DR87) -> 0
B89: GAAP Net Income | M89: =M132 -> 7.976377 | R89: =R132 -> 32.115881 | W89: =W132 -> 40.501592 | AB89: =AB132 -> 58.281 | AG89: =AG132 -> 122.197 | AH89: =AH87+AH86 -> 33.516 | AI89: =AI87+AI86 -> 38.618 | AJ89: =AJ87+AJ86 -> 38.941 | AK89: =AK87+AK86 -> 73.889 | AL89: =AL132 -> 184.964 | AM89: =AM87+AM86 -> 46.974 | AN89: =AN87+AN86 -> 57.702 | AO89: =AO87+AO86 -> 57.38 | AP89: =AP87+AP86 -> 109.375 | AQ89: =AQ132 -> 271.431 | AR89: =AR87+AR86 -> 47.279 | AS89: =AS87+AS86 -> 56.465 | AT89: =AT87+AT86 -> 66.111 | AU89: =AU87+AU86 -> 109.692 | AV89: =AV132 -> 279.547 | AW89: =AW87+AW86 -> 18.981 | AX89: =AX87+AX86 -> 48.767 | AY89: =AY87+AY86 -> 60.451 | AZ89: =AZ87+AZ86 -> 110.853 | BA89: =BA132 -> 239.033 | BB89: =BB87+BB86 -> 47.81 | BC89: =BC87+BC86 -> 47.668 | BD89: =BD87+BD86 -> 53.146 | BE89: =BE87+BE86 -> 117.416 | BF89: =BF132 -> 266.047 | BG89: =BG87+BG86 -> 45.336 | BH89: =BH87+BH86 -> 53.625 | BI89: =BI87+BI86 -> 68.285 | BJ89: =BJ87+BJ86 -> 136.13328 | BK89: =BK132 -> 303.5697 | BL89: =BL87+BL86 -> 31.246 | BM89: =BM87+BM86 -> 48.711 | BN89: =BN87+BN86 -> 58.96 | BO89: =BO87+BO86 -> 119.761 | BP89: =SUM(BP86:BP87) -> 258.661 | BQ89: =BQ87+BQ86 -> 75.153 | BR89: =BR87+BR86 -> 95.77 | BS89: =BS86+BS87 -> 94.413 | BT89: =BT87+BT86 -> 218.465 | BU89: =SUM(BU86:BU87) -> 483.801 | BV89: =BV87+BV86 -> 96.603 | BW89: =BW86+BW87 -> 124.99 | BX89: =BX86+BX87 -> 125.982 | BY89: =BY86+BY87 -> 298.021 | BZ89: =BZ86+BZ87 -> 645.596 | CA89: =CA87+CA86 -> 28.632 | CB89: =CB86+CB87 -> 86.801 | CC89: =CC86+CC87 -> 143.643 | CD89: =CD86+CD87 -> 329.839 | CE89: =CE86+CE87 -> 588.915 | CF89: =CF87+CF86 -> 144.956 | CG89: =CG86+CG87 -> 208.074 | CH89: =CH86+CH87 -> 187.788 | CI89: =CI86+CI87 -> 434.504 | CJ89: =CJ86+CJ87 -> 975.322 | CK89: =CK87+CK86 -> 189.998 | CL89: =CL86+CL87 -> 289.521 | CM89: =CM86+CM87 -> 255.47 | CN89: =CN86+CN87 -> 119.811 | CO89: =CO86+CO87 -> 854.8 | CP89: =CP87+CP86 -> 290.405 | CQ89: =CQ86+CQ87 -> 341.603 | CR89: =CR86+CR87 -> 248.714 | CS89: =CS86+CS87 -> 669.468 | CT89: =CT86+CT87 -> 1550.19 | CU89: =CU87+CU86 -> 321.421 | CV89: =CV86+CV87 -> 392.922 | CW89: =CW86+CW87 -> 351.87 | CX89: =CX86+CX87 -> 748.403 | CY89: =CY86+CY87 -> 1814.616 | CZ89: =CZ87+CZ86 -> 314.572 | DA89: =DA86+DA87 -> 370.905 | DB89: =DB86+DB87 -> 306.835 | DC89: =DC86+DC87 -> 586.871 | DD89: =DD86+DD87 -> 1579.183 | DE89: =DE87+DE86 -> 195.048 | DF89: =DF86+DF87 -> 329.223 | DG89: =DG86+DG87 -> 108.63248 | DH89: =DH86+DH87 -> 446.94434 | DI89: =DI86+DI87 -> 1079.8478 | DJ89: =DJ86+DJ87 -> 169.83149 | DK89: =DK86+DK87 -> 201.69822 | DL89: =DL86+DL87 -> 93.953427 | DM89: =DM86+DM87 -> 419.05011 | ... DS89: =DS86+DS87 -> 852.39768
B90: D&A | C90: 1.123 | D90: 0.6165745 | E90: 0.6165745 | F90: 0.6165745 | G90: 0.6165745 | H90: 2.466298 | I90: 0.893 | J90: 1 | K90: 1.2 | L90: 1.525512 | M90: =M133 -> 4.586646 | N90: 1.503738 | O90: 1.864801 | P90: 2.125247 | Q90: 2.797468 | R90: =R133 -> 8.291254 | S90: 3.38106 | T90: 3.817848 | U90: 3.903516 | V90: 4.720526 | W90: =W133 -> 15.82295 | X90: 4.278 | Y90: 5.274 | Z90: 5.684 | AA90: 5.596 | AB90: =AB133 -> 20.832 | AC90: 5.388 | AD90: 6.602 | AE90: 6.426 | AF90: 6.198 | AG90: =AG133 -> 24.614 | AH90: =AH133 -> 6.041 | AI90: =AI133-AH133 -> 7.52 | AJ90: =AJ133-AI133 -> 7.327 | AK90: =AK133-AJ133 -> 9.371 | AL90: =AL133 -> 30.259 | AM90: =AM133 -> 9.798 | AN90: =AN133-AM133 -> 9.681 | AO90: =AO133-AN133 -> 11.483 | AP90: =AP133-AO133 -> 12.038 | AQ90: =AQ133 -> 43 | AR90: =AR133 -> 11.729 | AS90: =AS133-AR133 -> 12.078 | AT90: =AT133-AS133 -> 12.916 | AU90: =AU133-AT133 -> 12.345 | AV90: =AV133 -> 49.068 | AW90: =AW133 -> 12.46 | AX90: =AX133-AW133 -> 13.637 | AY90: =AY133-AX133 -> 15.612 | AZ90: =AZ133-AY133 -> 16.655 | BA90: =BA133 -> 58.364 | BB90: =BB133 -> 16.096 | BC90: =BC133-BB133 -> 16.695 | BD90: =BD133-BC133 -> 19.707 | BE90: =BE133-BD133 -> 20.885 | BF90: =BF133 -> 73.383 | BG90: =BG133 -> 19.185 | BH90: =BH133-BG133 -> 20.498 | BI90: =BI133-BH133 -> 23.958 | BJ90: =BJ133-BI133 -> 24.056 | BK90: =BK133 -> 87.697 | BL90: =BL133 -> 23.163 | BM90: =BM133-BL133 -> 28.406 | BN90: =BN133-BM133 -> 28.56 | BO90: =BO133-BN133 -> 28.106 | BP90: =BP133 -> 108.235 | BQ90: =BQ133 -> 26.773 | BR90: =BR133-BQ133 -> 28.656 | BS90: =BS133-BR133 -> 31.686 | BT90: =BT133-BS133 -> 35.369 | BU90: =BU133 -> 122.484 | BV90: =BV133 -> 32.823 | BW90: =BW133-BV133 -> 37.599 | BX90: =BX133-BW133 -> 44.022 | BY90: =BY133-BX133 -> 47.489 | BZ90: =SUM(BV90:BY90) -> 161.933 | CA90: =CA133 -> 43.532 | CB90: =CB133-CA133 -> 40.644 | CC90: =CC133-CB133 -> 49.033 | CD90: =CD133-CC133 -> 52.269 | CE90: =SUM(CA90:CD90) -> 185.478 | CF90: =CF133 -> 50.485 | CG90: =CG133-CF133 -> 53.638 | CH90: =CH133-CG133 -> 57.963 | CI90: =CI133-CH133 -> 62.12 | CJ90: =SUM(CF90:CI90) -> 224.206 | CK90: =CK133 -> 64.47 | CL90: =CL133-CK133 -> 67.971 | CM90: =CM133-CL133 -> 79.188 | CN90: =CN133-CM133 -> 80.162 | CO90: =SUM(CK90:CN90) -> 291.791 | CP90: =CP133 -> 84.116 | CQ90: =CQ133-CP133 -> 94.009 | CR90: =CR133-CQ133 -> 97.969 | CS90: =CS133-CR133 -> 103.29 | CT90: =SUM(CP90:CS90) -> 379.384 | CU90: =CU133 -> 95.759 | CV90: =CV133-CU133 -> 103.573 | CW90: =CW133-CV133 -> 113.599 | CX90: =CX133-CW133 -> 133.593 | CY90: =SUM(CU90:CX90) -> 446.524 | CZ90: =CZ133 -> 114.529 | DA90: =DA133-CZ133 -> 119.715 | DB90: =DB133-DA133 -> 127.459 | DC90: =DC133-DB133 -> 134.525 | DD90: =SUM(CZ90:DC90) -> 496.228 | DE90: =DE133 -> 135.335 | DF90: =DF133-DE133 -> 142.332 | DG90: =DB90*(1+DG223) -> 150.40162 | DH90: =DC90*(1+DH223) -> 158.7395 | DI90: =SUM(DE90:DH90) -> 586.80812 | DJ90: =DE90*(1+DJ223) -> 159.6953 | DK90: =DF90*(1+DK223) -> 167.95176 | DL90: =DG90*(1+DL223) -> 177.47391 | DM90: =DH90*(1+DM223) -> 187.31261 | DN90: =SUM(DJ90:DM90) -> 692.43358 | DO90: =DJ90*(1+DO223) -> 188.44045 | DP90: =DK90*(1+DP223) -> 198.18308 | DQ90: =DL90*(1+DQ223) -> 209.41922 | DR90: =DM90*(1+DR223) -> 221.02888 | DS90: =SUM(DO90:DR90) -> 817.07163
B91: Share-Based Compensation | M91: =M134 -> 2.641564 | R91: =R134 -> 5.947097 | W91: =W134 -> 6.532308 | AB91: =AB134 -> 5.616 | AG91: =AG134 -> 7.273 | AH91: =AH134 -> 2.729 | AI91: =AI134-AH134 -> 2.337 | AJ91: =AJ134-AI134 -> 2.679 | AK91: =AK134-AJ134 -> 2.595 | AL91: =AL134 -> 10.34 | AM91: =AM134 -> 3.891 | AN91: =AN134-AM134 -> 4.149 | AO91: =AO134-AN134 -> 3.788 | AP91: =AP134-AO134 -> 3.809 | AQ91: =AQ134 -> 15.637 | AR91: =AR134 -> 0 | AS91: =AS134-AR134 -> 0 | AT91: =AT134-AS134 -> 12.453 | AU91: =AU134-AT134 -> -2.366 | AV91: =AV134 -> 10.087 | AW91: =AW134 -> 1.977 | AX91: =AX134-AW134 -> 1.392 | AY91: =AY134-AX134 -> 2.013 | AZ91: =AZ134-AY134 -> 2.887 | BA91: =BA134 -> 8.269 | BB91: =BB134 -> 2.068 | BC91: =BC134-BB134 -> 3.953 | BD91: =BD134-BC134 -> 0.618 | BE91: =BE134-BD134 -> 3.717 | BF91: =BF134 -> 10.356 | BG91: =BG134 -> 3.181 | BH91: =BH134-BG134 -> 4.945 | BI91: =BI134-BH134 -> 4.813 | BJ91: =BJ134-BI134 -> 3.883 | BK91: =BK134 -> 16.822 | BL91: =BL134 -> 2.73 | BM91: =BM134-BL134 -> 5.98 | BN91: =BN134-BM134 -> 4.338 | BO91: =BO134-BN134 -> 4.562 | BP91: =BP134 -> 17.61 | BQ91: =BQ134 -> 5.193 | BR91: =BR134-BQ134 -> 7.855 | BS91: =BS134-BR134 -> 5.568 | BT91: =BT134-BS134 -> 9.952 | BU91: =BU134 -> 28.568 | BV91: =BV134 -> 10.157 | BW91: =BW134-BV134 -> 11.848 | BX91: =BX134-BW134 -> 14.065 | BY91: =BY134-BX134 -> 9.523 | BZ91: =SUM(BV91:BY91) -> 45.593 | CA91: =CA134 -> 6.128 | CB91: =CB134-CA134 -> 15.784 | CC91: =CC134-CB134 -> 15.186 | CD91: =CD134-CC134 -> 13.699 | CE91: =SUM(CA91:CD91) -> 50.797 | CF91: =CF134 -> 14.932 | CG91: =CG134-CF134 -> 15.289 | CH91: =CH134-CG134 -> 21.657 | CI91: =CI134-CH134 -> 17.259 | CJ91: =SUM(CF91:CI91) -> 69.137 | CK91: =CK134 -> 18.358 | CL91: =CL134-CK134 -> 20.817 | CM91: =CM134-CL134 -> 20.312 | CN91: =CN134-CM134 -> 18.588 | CO91: =SUM(CK91:CN91) -> 78.075 | CP91: =CP134 -> 21.301 | CQ91: =CQ134-CP134 -> 24.283 | CR91: =CR134-CQ134 -> 24.573 | CS91: =CS134-CR134 -> 23.403 | CT91: =SUM(CP91:CS91) -> 93.56 | CU91: =CU134 -> 25.758 | CV91: =CV134-CU134 -> 21.567 | CW91: =CW134-CV134 -> 24.169 | CX91: =CX134-CW134 -> 18.517 | CY91: =SUM(CU91:CX91) -> 90.011 | CZ91: =CZ134 -> 23.091 | DA91: =DA134-CZ134 -> -1.844 | DB91: =DB134-DA134 -> 16.558 | DC91: =DC134-DB134 -> 24.398 | DD91: =SUM(CZ91:DC91) -> 62.203 | DE91: =DE134 -> 29.186 | DF91: =DF134-DE134 -> 21.089 | DG91: 6 | DH91: 6 | DI91: =SUM(DE91:DH91) -> 62.275 | DJ91: 6 | DK91: 6 | DL91: 6 | DM91: 6 | DN91: =SUM(DJ91:DM91) -> 24 | DO91: 6 | DP91: 6 | DQ91: 6 | DR91: 6 | DS91: =SUM(DO91:DR91) -> 24
B92: Deferred Income Tax | M92: =M135 -> 0 | R92: =R135 -> 0 | W92: =W135 -> 0 | AB92: =AB135 -> 0 | AG92: =AG135 -> 0 | AH92: =AH135 -> 0 | AI92: =AI135-AH135 -> 0 | AJ92: =AJ135-AI135 -> 0 | AK92: =AK135-AJ135 -> 0 | AL92: =AL135 -> 0 | AM92: =AM135 -> 0 | AN92: =AN135-AM135 -> 0 | AO92: =AO135-AN135 -> 0 | AP92: =AP135-AO135 -> -6.445 | AQ92: =AQ135 -> -6.445 | AR92: =AR135 -> 0 | AS92: =AS135-AR135 -> 0 | AT92: =AT135-AS135 -> 0 | AU92: =AU135-AT135 -> 0.82 | AV92: =AV135 -> 0.82 | AW92: =AW135 -> 30.946 | AX92: =AX135-AW135 -> -3.096 | AY92: =AY135-AX135 -> -6.9 | AZ92: =AZ135-AY135 -> -18.863 | BA92: =BA135 -> 2.087 | BB92: =BB135 -> 0 | BC92: =BC135-BB135 -> -0.011 | BD92: =BD135-BC135 -> 5.116 | BE92: =BE135-BD135 -> 6.037 | BF92: =BF135 -> 11.142 | BG92: =BG135 -> -0.3 | BH92: =BH135-BG135 -> 0.3 | BI92: =BI135-BH135 -> 0 | BJ92: =BJ135-BI135 -> -17.563 | BK92: =BK135 -> -17.563 | BL92: =BL135 -> 0 | BM92: =BM135-BL135 -> 0 | BN92: =BN135-BM135 -> -18.385 | BO92: =BO135-BN135 -> 6.969 | BP92: =BP135 -> -11.416 | BQ92: =BQ135 -> 0.4 | BR92: =BR135-BQ135 -> 2.064 | BS92: =BS135-BR135 -> -0.082 | BT92: =BT135-BS135 -> 14.404 | BU92: =BU135 -> 16.786 | BV92: =BV135 -> 0 | BW92: =BW135-BV135 -> 0 | BX92: =BX135-BW135 -> 0 | BY92: =BY135-BX135 -> 24.129 | BZ92: =SUM(BV92:BY92) -> 24.129 | CA92: =CA135 -> 0 | CB92: =CB135-CA135 -> 0 | CC92: =CC135-CB135 -> 0 | CD92: =CD135-CC135 -> 34.908 | CE92: =SUM(CA92:CD92) -> 34.908 | CF92: =CF135 -> 0 | CG92: =CG135-CF135 -> 0 | CH92: =CH135-CG135 -> 0 | CI92: =CI135-CH135 -> -5.18 | CJ92: =SUM(CF92:CI92) -> -5.18 | CK92: =CK135 -> 0 | CL92: =CL135-CK135 -> 0 | CM92: =CM135-CL135 -> 0 | CN92: =CN135-CM135 -> 3.042 | CO92: =SUM(CK92:CN92) -> 3.042 | CP92: =CP135 -> -0.721 | CQ92: =CQ135-CP135 -> 0.721 | CR92: =CR135-CQ135 -> 0 | CS92: =CS135-CR135 -> -28.383 | CT92: =SUM(CP92:CS92) -> -28.383 | CU92: =CU135 -> 0 | CV92: =CV135-CU135 -> 0 | CW92: =CW135-CV135 -> 0 | CX92: =CX135-CW135 -> 57.451 | CY92: =SUM(CU92:CX92) -> 57.451 | CZ92: =CZ135 -> 0 | DA92: =DA135-CZ135 -> 0 | DB92: =DB135-DA135 -> 0 | DC92: =DC135-DB135 -> -53.379 | DD92: =SUM(CZ92:DC92) -> -53.379 | DE92: =DE135 -> 0 | DF92: =DF135-DE135 -> 0 | DG92: 0 | DH92: 0 | DI92: =SUM(DE92:DH92) -> 0 | DJ92: 0 | DK92: 0 | DL92: 0 | DM92: 0 | DN92: =SUM(DJ92:DM92) -> 0 | DO92: 0 | DP92: 0 | DQ92: 0 | DR92: 0 | DS92: =SUM(DO92:DR92) -> 0
B94: Accounts Receivable | M94: =M137 -> -1.196101 | R94: =R137 -> 0.412848 | W94: =W137 -> -1.038881 | AB94: =AB137 -> -3.796 | AG94: =AG137 -> -0.541 | AH94: =AH137 -> -2.557 | AI94: =AI137-AH137 -> 2.557 | AJ94: =AJ137-AI137 -> 0 | AK94: =AK137-AJ137 -> 3.743 | AL94: =AL137 -> 3.743 | AM94: =AM137 -> 0 | AN94: =AN137-AM137 -> 0 | AO94: =AO137-AN137 -> 0 | AP94: =AP137-AO137 -> 0 | AQ94: =AQ137 -> 0 | AR94: =AR137 -> 0 | AS94: =AS137-AR137 -> 0 | AT94: =AT137-AS137 -> 0 | AU94: =AU137-AT137 -> 0 | AV94: =AV137 -> 0 | AW94: =AW137 -> 0 | AX94: =AX137-AW137 -> 0 | AY94: =AY137-AX137 -> 0 | AZ94: =AZ137-AY137 -> 0 | BA94: =BA137 -> 0 | BB94: =BB137 -> 0 | BC94: =BC137-BB137 -> 0 | BD94: =BD137-BC137 -> 0 | BE94: =BE137-BD137 -> 0 | BF94: =BF137 -> 0 | BG94: =BG137 -> 0 | BH94: =BH137-BG137 -> 0 | BI94: =BI137-BH137 -> 0 | BJ94: =BJ137-BI137 -> 0 | BK94: =BK137 -> 0 | BL94: =BL137 -> 0 | BM94: =BM137-BL137 -> 0 | BN94: =BN137-BM137 -> 0 | BO94: =BO137-BN137 -> 0 | BP94: =BP137 -> 0 | BQ94: =BQ137 -> 0 | BR94: =BR137-BQ137 -> 0 | BS94: =BS137-BR137 -> 0 | BT94: =BT137-BS137 -> 0 | BU94: =BU137 -> 0 | BV94: =BV137 -> 0 | BW94: =BW137-BV137 -> 0 | BX94: =BX137-BW137 -> 0 | BY94: =BY137-BX137 -> 0 | BZ94: =SUM(BV94:BY94) -> 0 | CA94: =CA137 -> 0 | CB94: =CB137-CA137 -> 0 | CC94: =CC137-CB137 -> 0 | CD94: =CD137-CC137 -> 0 | CE94: =SUM(CA94:CD94) -> 0 | CF94: =CF137 -> 0 | CG94: =CG137-CF137 -> 0 | CH94: =CH137-CG137 -> 0 | CI94: =CI137-CH137 -> 0 | CJ94: =SUM(CF94:CI94) -> 0 | CK94: =CK137 -> 0 | CL94: =CL137-CK137 -> 0 | CM94: =CM137-CL137 -> 0 | CN94: =CN137-CM137 -> 0 | CO94: =SUM(CK94:CN94) -> 0 | CP94: =CP137 -> 0 | CQ94: =CQ137-CP137 -> 0 | CR94: =CR137-CQ137 -> 0 | CS94: =CS137-CR137 -> 0 | CT94: =SUM(CP94:CS94) -> 0 | CU94: =CU137 -> 0 | CV94: =CV137-CU137 -> 0 | CW94: =CW137-CV137 -> 0 | CX94: =CX137-CW137 -> 1.626 | CY94: =SUM(CU94:CX94) -> 1.626 | CZ94: =CZ137 -> -18.504 | DA94: =DA137-CZ137 -> 2.575 | DB94: =DB137-DA137 -> -111.49 | DC94: =DC137-DB137 -> 61.664 | DD94: =SUM(CZ94:DC94) -> -65.755 | DE94: =DE137 -> 26.667 | DF94: =DF137-DE137 -> -6.297 | DG94: =DF174-DG174 -> -73.94848 | DH94: =DG174-DH174 -> 65.377007 | DI94: =SUM(DE94:DH94) -> 11.798527 | DJ94: =DI174-DJ174 -> 27.241784 | DK94: =DJ174-DK174 -> -5.9597489 | DL94: =DK174-DL174 -> -73.459353 | DM94: =DL174-DM174 -> 56.464872 | DN94: =SUM(DJ94:DM94) -> 4.2875544 | DO94: =DN174-DO174 -> 24.547335 | DP94: =DO174-DP174 -> -7.6189257 | DQ94: =DP174-DQ174 -> -74.549749 | DR94: =DQ174-DR174 -> 55.662618 | DS94: =SUM(DO94:DR94) -> -1.958722
B95: Inventories | M95: =M138 -> -5.751628 | R95: =R138 -> -11.217151 | W95: =W138 -> -19.782088 | AB95: =AB138 -> 11.296 | AG95: =AG138 -> -7.954 | AH95: =AH138 -> -5.552 | AI95: =AI138-AH138 -> -24.612 | AJ95: =AJ138-AI138 -> -40.831 | AK95: =AK138-AJ138 -> 24.923 | AL95: =AL138 -> -46.072 | AM95: =AM138 -> -2.749 | AN95: =AN138-AM138 -> -18.719 | AO95: =AO138-AN138 -> -39.07 | AP95: =AP138-AO138 -> 9.516 | AQ95: =AQ138 -> -51.022 | AR95: =AR138 -> -6.229 | AS95: =AS138-AR138 -> -19.912 | AT95: =AT138-AS138 -> 11.496 | AU95: =AU138-AT138 -> -22.762 | AV95: =AV138 -> -37.407 | AW95: =AW138 -> 11.241 | AX95: =AX138-AW138 -> -1.261 | AY95: =AY138-AX138 -> -54.132 | AZ95: =AZ138-AY138 -> 17.346 | BA95: =BA138 -> -26.806 | BB95: =BB138 -> -25.797 | BC95: =BC138-BB138 -> -48.213 | BD95: =BD138-BC138 -> -77.307 | BE95: =BE138-BD138 -> 68.031 | BF95: =BF138 -> -83.286 | BG95: =BG138 -> 12.912 | BH95: =BH138-BG138 -> 4.035 | BI95: =BI138-BH138 -> -90.607 | BJ95: =BJ138-BI138 -> 68.257 | BK95: =BK138 -> -5.403 | BL95: =BL138 -> -13.445 | BM95: =BM138-BL138 -> 3.404 | BN95: =BN138-BM138 -> -85.434 | BO95: =BO138-BN138 -> 74.297 | BP95: =BP138 -> -21.178 | BQ95: =BQ138 -> -50.77 | BR95: =BR138-BQ138 -> -22.295 | BS95: =BS138-BR138 -> -104.825 | BT95: =BT138-BS138 -> 91.948 | BU95: =BU138 -> -85.942 | BV95: =BV138 -> -42.856 | BW95: =BW138-BV138 -> -50.502 | BX95: =BX138-BW138 -> -131.766 | BY95: =BY138-BX138 -> 107.533 | BZ95: =SUM(BV95:BY95) -> -117.591 | CA95: =CA138 -> -122.81 | CB95: =CB138-CA138 -> -15.384 | CC95: =CC138-CB138 -> -95.96 | CD95: =CD138-CC138 -> 137.606 | CE95: =SUM(CA95:CD95) -> -96.548 | CF95: =CF138 -> -74.218 | CG95: =CG138-CF138 -> -63.146 | CH95: =CH138-CG138 -> -151.457 | CI95: =CI138-CH138 -> -34.788 | CJ95: =SUM(CF95:CI95) -> -323.609 | CK95: =CK138 -> -320.607 | CL95: =CL138-CK138 -> -189.96 | CM95: =CM138-CL138 -> -321.457 | CN95: =CN138-CM138 -> 321.514 | CO95: =SUM(CK95:CN95) -> -510.51 | CP95: =CP138 -> -155.174 | CQ95: =CQ138-CP138 -> -78.876 | CR95: =CR138-CQ138 -> -67.751 | CS95: =CS138-CR138 -> 368.385 | CT95: =SUM(CP95:CS95) -> 66.584 | CU95: =CU138 -> -36.425 | CV95: =CV138-CU138 -> -89.651 | CW95: =CW138-CV138 -> -351.606 | CX95: =CX138-CW138 -> 321.597 | CY95: =SUM(CU95:CX95) -> -156.085 | CZ95: =CZ138 -> -174.319 | DA95: =DA138-CZ138 -> -63.584 | DB95: =DB138-DA138 -> -279.581 | DC95: =DC138-DB138 -> 328.774 | DD95: =SUM(CZ95:DC95) -> -188.71 | DE95: =DE138 -> 23.642 | DF95: =DF138-DE138 -> -37.992 | DG95: =DF175-DG175 -> -329.78323 | DH95: =DG175-DH175 -> 261.9774 | DI95: =SUM(DE95:DH95) -> -82.155831 | DJ95: =DI175-DJ175 -> 128.02012 | DK95: =DJ175-DK175 -> -85.541414 | DL95: =DK175-DL175 -> -337.70634 | DM95: =DL175-DM175 -> 290.03399 | DN95: =SUM(DJ95:DM95) -> -5.1936371 | DO95: =DN175-DO175 -> 101.61915 | DP95: =DO175-DP175 -> -59.440826 | DQ95: =DP175-DQ175 -> -348.06971 | DR95: =DQ175-DR175 -> 281.93594 | DS95: =SUM(DO95:DR95) -> -23.955446
B96: Other Current Assets | M96: =M139 -> -0.733573 | R96: =R139 -> -2.329807 | W96: =W139 -> -0.901805 | AB96: =AB139 -> 0.272 | AG96: =AG139 -> -0.968 | AH96: =AH139 -> -4.286 | AI96: =AI139-AH139 -> -5.96 | AJ96: =AJ139-AI139 -> 10.957 | AK96: =AK139-AJ139 -> -0.206 | AL96: =AL139 -> 0.505 | AM96: =AM139 -> -8.011 | AN96: =AN139-AM139 -> -8.199 | AO96: =AO139-AN139 -> -0.07 | AP96: =AP139-AO139 -> -2.024 | AQ96: =AQ139 -> -18.304 | AR96: =AR139 -> -7.706 | AS96: =AS139-AR139 -> -9.992 | AT96: =AT139-AS139 -> 5.574 | AU96: =AU139-AT139 -> 0.783 | AV96: =AV139 -> -11.341 | AW96: =AW139 -> 5.847 | AX96: =AX139-AW139 -> -5.847 | AY96: =AY139-AX139 -> -24.108 | AZ96: =AZ139-AY139 -> 0.061 | BA96: =BA139 -> -24.047 | BB96: =BB139 -> -1.944 | BC96: =BC139-BB139 -> 1.944 | BD96: =BD139-BC139 -> -89.661 | BE96: =BE139-BD139 -> 33.735 | BF96: =BF139 -> -55.926 | BG96: =BG139 -> -0.568 | BH96: =BH139-BG139 -> -15.047 | BI96: =BI139-BH139 -> -28.436 | BJ96: =BJ139-BI139 -> 48.858 | BK96: =BK139 -> 4.807 | BL96: =BL139 -> -1.811 | BM96: =BM139-BL139 -> -0.662 | BN96: =BN139-BM139 -> -8.847 | BO96: =BO139-BN139 -> 26.613 | BP96: =BP139 -> 15.293 | BQ96: =BQ139 -> 3 | BR96: =BR139-BQ139 -> -23.979 | BS96: =BS139-BR139 -> -27.204 | BT96: =BT139-BS139 -> 17.093 | BU96: =BU139 -> -31.09 | BV96: =BV139 -> -48.98 | BW96: =BW139-BV139 -> -59.746 | BX96: =BX139-BW139 -> 31.396 | BY96: =BY139-BX139 -> -40.051 | BZ96: =SUM(BV96:BY96) -> -117.381 | CA96: =CA139 -> -57.515 | CB96: =CB139-CA139 -> -59.156 | CC96: =CC139-CB139 -> -33.22 | CD96: =CD139-CC139 -> 24.926 | CE96: =SUM(CA96:CD96) -> -124.965 | CF96: =CF139 -> -9.232 | CG96: =CG139-CF139 -> 17.171 | CH96: =CH139-CG139 -> -52.217 | CI96: =CI139-CH139 -> -18.018 | CJ96: =SUM(CF96:CI96) -> -62.296 | CK96: =CK139 -> 2.419 | CL96: =CL139-CK139 -> -63.357 | CM96: =CM139-CL139 -> -29.574 | CN96: =CN139-CM139 -> -90.022 | CO96: =SUM(CK96:CN96) -> -180.534 | CP96: =CP139 -> 30.76 | CQ96: =CQ139-CP139 -> -48.994 | CR96: =CR139-CQ139 -> -85.693 | CS96: =CS139-CR139 -> 99.722 | CT96: =SUM(CP96:CS96) -> -4.205 | CU96: =CU139 -> -32.636 | CV96: =CV139-CU139 -> -60.654 | CW96: =CW139-CV139 -> -93.198 | CX96: =CX139-CW139 -> 39.463 | CY96: =SUM(CU96:CX96) -> -147.025 | CZ96: =CZ139 -> -25.351 | DA96: =DA139-CZ139 -> -46.586 | DB96: =DB139-DA139 -> -170.841 | DC96: =DC139-DB139 -> 49.99 | DD96: =SUM(CZ96:DC96) -> -192.788 | DE96: =DE139 -> -63.174 | DF96: =DF139-DE139 -> -52.721 | DG96: =(DF176-DG176)+(DF189-DG189) -> 0 | DH96: =(DG176-DH176)+(DG189-DH189) -> 0 | DI96: =SUM(DE96:DH96) -> -115.895 | DJ96: =(DI176-DJ176)+(DI189-DJ189) -> 0 | DK96: =(DJ176-DK176)+(DJ189-DK189) -> 0 | DL96: =(DK176-DL176)+(DK189-DL189) -> 0 | DM96: =(DL176-DM176)+(DL189-DM189) -> 0 | DN96: =SUM(DJ96:DM96) -> 0 | DO96: =(DN176-DO176)+(DN189-DO189) -> 0 | DP96: =(DO176-DP176)+(DO189-DP189) -> 0 | DQ96: =(DP176-DQ176)+(DP189-DQ189) -> 0 | DR96: =(DQ176-DR176)+(DQ189-DR189) -> 0 | DS96: =SUM(DO96:DR96) -> 0
B97: Accounts Payable | M97: =M140 -> -1.099306 | R97: =R140 -> 0.540457 | W97: =W140 -> 0.831566 | AB97: =AB140 -> 6.025 | AG97: =AG140 -> -5.167 | AH97: =AH140 -> -3.104 | AI97: =AI140-AH140 -> 1.019 | AJ97: =AJ140-AI140 -> 1.465 | AK97: =AK140-AJ140 -> 8.481 | AL97: =AL140 -> 7.861 | AM97: =AM140 -> -10.225 | AN97: =AN140-AM140 -> 2.624 | AO97: =AO140-AN140 -> -0.357 | AP97: =AP140-AO140 -> 25.428 | AQ97: =AQ140 -> 17.47 | AR97: =AR140 -> 2.709 | AS97: =AS140-AR140 -> 8.958 | AT97: =AT140-AS140 -> -48.211 | AU97: =AU140-AT140 -> 13.096 | AV97: =AV140 -> -23.448 | AW97: =AW140 -> -5.805 | AX97: =AX140-AW140 -> 0.096 | AY97: =AY140-AX140 -> 2.729 | AZ97: =AZ140-AY140 -> 0.782 | BA97: =BA140 -> -2.198 | BB97: =BB140 -> -4.092 | BC97: =BC140-BB140 -> 2.283 | BD97: =BD140-BC140 -> -1.639 | BE97: =BE140-BD140 -> 4.695 | BF97: =BF140 -> 1.247 | BG97: =BG140 -> -4.532 | BH97: =BH140-BG140 -> 2.02 | BI97: =BI140-BH140 -> 0.954 | BJ97: =BJ140-BI140 -> 15.638 | BK97: =BK140 -> 14.08 | BL97: =BL140 -> -15.798 | BM97: =BM140-BL140 -> 9.014 | BN97: =BN140-BM140 -> -4.357 | BO97: =BO140-BN140 -> 9.59 | BP97: =BP140 -> -1.551 | BQ97: =BQ140 -> -7.676 | BR97: =BR140-BQ140 -> 94.561 | BS97: =BS140-BR140 -> 42.732 | BT97: =BT140-BS140 -> -57.655 | BU97: =BU140 -> 71.962 | BV97: =BV140 -> -5.42 | BW97: =BW140-BV140 -> 21.211 | BX97: =BX140-BW140 -> 5.294 | BY97: =BY140-BX140 -> -35.895 | BZ97: =SUM(BV97:BY97) -> -14.81 | CA97: =CA140 -> 2.222 | CB97: =CB140-CA140 -> 33.745 | CC97: =CC140-CB140 -> 37.629 | CD97: =CD140-CC140 -> 9.067 | CE97: =SUM(CA97:CD97) -> 82.663 | CF97: =CF140 -> 19.623 | CG97: =CG140-CF140 -> 8.609 | CH97: =CH140-CG140 -> 22.671 | CI97: =CI140-CH140 -> 66.752 | CJ97: =SUM(CF97:CI97) -> 117.655 | CK97: =CK140 -> 20.63 | CL97: =CL140-CK140 -> -48.879 | CM97: =CM140-CL140 -> 54.786 | CN97: =CN140-CM140 -> -133.817 | CO97: =SUM(CK97:CN97) -> -107.28 | CP97: =CP140 -> 116.935 | CQ97: =CQ140-CP140 -> 9.072 | CR97: =CR140-CQ140 -> 15.678 | CS97: =CS140-CR140 -> 35.682 | CT97: =SUM(CP97:CS97) -> 177.367 | CU97: =CU140 -> -82.366 | CV97: =CV140-CU140 -> 58.683 | CW97: =CW140-CV140 -> 69.262 | CX97: =CX140-CW140 -> -102.623 | CY97: =SUM(CU97:CX97) -> -57.044 | CZ97: =CZ140 -> 22.489 | DA97: =DA140-CZ140 -> 68.665 | DB97: =DB140-DA140 -> -18.344 | DC97: =DC140-DB140 -> -26.954 | DD97: =SUM(CZ97:DC97) -> 45.856 | DE97: =DE140 -> -37.691 | DF97: =DF140-DE140 -> 59.406 | DG97: =DG195-DF195 -> 21.580609 | DH97: =DH195-DG195 -> -48.739544 | DI97: =SUM(DE97:DH97) -> -5.4439351 | DJ97: =DJ195-DI195 -> -47.498681 | DK97: =DK195-DJ195 -> 60.844828 | DL97: =DL195-DK195 -> 24.526134 | DM97: =DM195-DL195 -> -36.939493 | DN97: =SUM(DJ97:DM97) -> 0.93278807 | DO97: =DO195-DN195 -> -43.225908 | DP97: =DP195-DO195 -> 56.692356 | DQ97: =DQ195-DP195 -> 26.205249 | DR97: =DR195-DQ195 -> -35.369249 | DS97: =SUM(DO97:DR97) -> 4.3024482
B98: Other Current Liabilities | M98: =M141 -> 14.197267 | R98: =R141 -> 6.328737 | W98: =W141 -> 20.154283 | AB98: =AB141 -> 16.993 | AG98: =AG141 -> 38.596 | AH98: =AH141 -> -18.639 | AI98: =AI141-AH141 -> 4.78 | AJ98: =AJ141-AI141 -> 14.643 | AK98: =AK141-AJ141 -> 19.449 | AL98: =AL141 -> 20.233 | AM98: =AM141 -> -19.57 | AN98: =AN141-AM141 -> 1.21 | AO98: =AO141-AN141 -> 19.049 | AP98: =AP141-AO141 -> 18.909 | AQ98: =AQ141 -> 19.598 | AR98: =AR141 -> -43.806 | AS98: =AS141-AR141 -> 1.128 | AT98: =AT141-AS141 -> 41.955 | AU98: =AU141-AT141 -> 22.847 | AV98: =AV141 -> 22.124 | AW98: =AW141 -> -2.938 | AX98: =AX141-AW141 -> -2.985 | AY98: =AY141-AX141 -> 48.312 | AZ98: =AZ141-AY141 -> 19.239 | BA98: =BA141 -> 61.628 | BB98: =BB141 -> -13.201 | BC98: =BC141-BB141 -> -12.449 | BD98: =BD141-BC141 -> 83.809 | BE98: =BE141-BD141 -> 20.063 | BF98: =BF141 -> 78.222 | BG98: =BG141 -> -35.48 | BH98: =BH141-BG141 -> 3.762 | BI98: =BI141-BH141 -> 5.82 | BJ98: =BJ141-BI141 -> 23.398 | BK98: =BK141 -> -2.5 | BL98: =BL141 -> -15.277 | BM98: =BM141-BL141 -> -9.432 | BN98: =BN141-BM141 -> 1.198 | BO98: =BO141-BN141 -> 47.303 | BP98: =BP141 -> 23.792 | BQ98: =BQ141 -> -18.836 | BR98: =BR141-BQ141 -> -18.536 | BS98: =BS141-BR141 -> 46.979 | BT98: =BT141-BS141 -> 113.787 | BU98: =BU141 -> 123.394 | BV98: =BV141 -> -109.557 | BW98: =BW141-BV141 -> 13.954 | BX98: =BX141-BW141 -> 0.557 | BY98: =BY141-BX141 -> 103.799 | BZ98: =SUM(BV98:BY98) -> 8.753 | CA98: =CA141 -> -66.05 | CB98: =CB141-CA141 -> 126.281 | CC98: =CC141-CB141 -> -54.078 | CD98: =CD141-CC141 -> 120.937 | CE98: =SUM(CA98:CD98) -> 127.09 | CF98: =CF141 -> 44.228 | CG98: =CG141-CF141 -> 24.353 | CH98: =CH141-CG141 -> 89.004 | CI98: =CI141-CH141 -> 243.858 | CJ98: =SUM(CF98:CI98) -> 401.443 | CK98: =CK141 -> -208.146 | CL98: =CL141-CK141 -> 29.382 | CM98: =CM141-CL141 -> 18.239 | CN98: =CN141-CM141 -> 374.47 | CO98: =SUM(CK98:CN98) -> 213.945 | CP98: =CP141 -> -200.89 | CQ98: =CQ141-CP141 -> -25.207 | CR98: =CR141-CQ141 -> 47.524 | CS98: =CS141-CR141 -> 100.515 | CT98: =SUM(CP98:CS98) -> -78.058 | CU98: =CU141 -> -190.151 | CV98: =CV141-CU141 -> 55.68 | CW98: =CW141-CV141 -> 193.392 | CX98: =CX141-CW141 -> 247.712 | CY98: =SUM(CU98:CX98) -> 306.633 | CZ98: =CZ141 -> -149.271 | DA98: =DA141-CZ141 -> -335.439 | DB98: =DB141-DA141 -> 385.444 | DC98: =DC141-DB141 -> 91.223 | DD98: =SUM(CZ98:DC98) -> -8.043 | DE98: =DE141 -> -104.442 | DF98: =DF141-DE141 -> -62.038 | DG98: =(DG197-DF197)+(DG199-DF199) -> -28.783988 | DH98: =(DH197-DG197)+(DH199-DG199) -> 49.960155 | DI98: =SUM(DE98:DH98) -> -145.30383 | DJ98: =(DJ197-DI197)+(DJ199-DI199) -> -24.551266 | DK98: =(DK197-DJ197)+(DK199-DJ199) -> -17.218411 | DL98: =(DL197-DK197)+(DL199-DK199) -> -21.574422 | DM98: =(DM197-DL197)+(DM199-DL199) -> 56.22358 | DN98: =SUM(DJ98:DM98) -> -7.1205197 | DO98: =(DO197-DN197)+(DO199-DN199) -> -20.292634 | DP98: =(DP197-DO197)+(DP199-DO199) -> -14.249475 | DQ98: =(DQ197-DP197)+(DQ199-DP199) -> -20.508859 | DR98: =(DR197-DQ197)+(DR199-DQ199) -> 58.303899 | DS98: =SUM(DO98:DR98) -> 3.2529309
B100: Working Captial | M100: =SUM(M94:M98) -> 5.416659 | R100: =SUM(R94:R98) -> -6.264916 | W100: =SUM(W94:W98) -> -0.736925 | AB100: =SUM(AB94:AB98) -> 30.79 | AG100: =SUM(AG94:AG98) -> 23.966 | AH100: =SUM(AH94:AH98) -> -34.138 | AI100: =SUM(AI94:AI98) -> -22.216 | AJ100: =SUM(AJ94:AJ98) -> -13.766 | AK100: =SUM(AK94:AK98) -> 56.39 | AL100: =SUM(AL94:AL98) -> -13.73 | AM100: =SUM(AM94:AM98) -> -40.555 | AN100: =SUM(AN94:AN98) -> -23.084 | ... DS100: =SUM(DS94:DS98) -> -18.358789
B101: Other Non-Current | M101: =M144 -> 4.2928711 | R101: =R144 -> -3.608779 | W101: =W144 -> -16.482151 | AB101: =AB144 -> 2.441 | AG101: =AG144 -> 1.945 | AH101: =AH144 -> -2.493 | AI101: =AI144-AH144 -> -12.385 | AJ101: =AJ144-AI144 -> -1.191 | AK101: =AK144-AJ144 -> 7.851 | AL101: =AL144 -> -8.218 | AM101: =AM144 -> -4.156 | AN101: =AN144-AM144 -> -0.88 | AO101: =AO144-AN144 -> -2.483 | AP101: =AP144-AO144 -> -3.733 | AQ101: =AQ144 -> -11.252 | AR101: =AR144 -> 21.159 | AS101: =AS144-AR144 -> -2.928 | AT101: =AT144-AS144 -> -78.42 | AU101: =AU144-AT144 -> 49.078 | AV101: =AV144 -> -11.111 | AW101: =AW144 -> -1.74 | AX101: =AX144-AW144 -> 2.293 | AY101: =AY144-AX144 -> -1.149 | AZ101: =AZ144-AY144 -> -1.285 | BA101: =BA144 -> -1.881 | BB101: =BB144 -> 0 | BC101: =BC144-BB144 -> -0.649 | BD101: =BD144-BC144 -> -0.017 | BE101: =BE144-BD144 -> -1.779 | BF101: =BF144 -> -2.445 | BG101: =BG144 -> 0 | BH101: =BH144-BG144 -> -13.884 | BI101: =BI144-BH144 -> 12.556 | BJ101: =BJ144-BI144 -> -14.864701 | BK101: =BK144 -> -16.390701 | BL101: =BL144 -> 8.592 | BM101: =BM144-BL144 -> -2.783 | BN101: =BN144-BM144 -> 53.254 | BO101: =BO144-BN144 -> 40.827 | BP101: =BP144 -> 99.89 | BQ101: =BQ144 -> 2.6 | BR101: =BR144-BQ144 -> 10.093 | BS101: =BS144-BR144 -> 17.583 | BT101: =BT144-BS144 -> -17.46 | BU101: =BU144 -> 12.816 | BV101: =BV144 -> 4.427 | BW101: =BW144-BV144 -> 13.491 | BX101: =BX144-BW144 -> -44.486 | BY101: =BY144-BX144 -> 59.662 | BZ101: =SUM(BV101:BY101) -> 33.094 | CA101: =CA144 -> 44.618 | CB101: =CB144-CA144 -> -47.41 | CC101: =CC144-CB144 -> -36.891 | CD101: =CD144-CC144 -> -5.319 | CE101: =SUM(CA101:CD101) -> -45.002 | CF101: =CF144 -> 23.335 | CG101: =CG144-CF144 -> 21.675 | CH101: =CH144-CG144 -> -17.057 | CI101: =CI144-CH144 -> -35.523 | CJ101: =SUM(CF101:CI101) -> -7.57 | CK101: =CK144 -> -10.378 | CL101: =CL144-CK144 -> -7.857 | CM101: =CM144-CL144 -> -11.147 | CN101: =CN144-CM144 -> 352.516 | CO101: =SUM(CK101:CN101) -> 323.134 | CP101: =CP144 -> -141.229 | CQ101: =CQ144-CP144 -> 160.099 | CR101: =CR144-CQ144 -> 108.839 | CS101: =CS144-CR144 -> 12.016 | CT101: =SUM(CP101:CS101) -> 139.725 | CU101: =CU144 -> 26.164 | CV101: =CV144-CU144 -> -38.98 | CW101: =CW144-CV144 -> -6.829 | CX101: =CX144-CW144 -> -64.349 | CY101: =SUM(CU101:CX101) -> -83.994 | CZ101: =CZ144 -> -226.19 | DA101: =DA144-CZ144 -> 214.269 | DB101: =DB144-DA144 -> -6.156 | DC101: =DC144-DB144 -> -54.241 | DD101: =SUM(CZ101:DC101) -> -72.318 | DE101: =DE144 -> 9.869 | DF101: =DF144-DE144 -> -18.164 | DG101: =(DF191-DG191)+(DG203-DF203) -> 0 | DH101: =(DG191-DH191)+(DH203-DG203) -> 0 | DI101: =SUM(DE101:DH101) -> -8.295 | DJ101: =(DI191-DJ191)+(DJ203-DI203) -> 0 | DK101: =(DJ191-DK191)+(DK203-DJ203) -> 0 | DL101: =(DK191-DL191)+(DL203-DK203) -> 0 | DM101: =(DL191-DM191)+(DM203-DL203) -> 0 | DN101: =SUM(DJ101:DM101) -> 0 | DO101: =(DN191-DO191)+(DO203-DN203) -> 0 | DP101: =(DO191-DP191)+(DP203-DO203) -> 0 | DQ101: =(DP191-DQ191)+(DQ203-DP203) -> 0 | DR101: =(DQ191-DR191)+(DR203-DQ203) -> 0 | DS101: =SUM(DO101:DR101) -> 0
B103: Cash From Operations | M103: =SUM(M89:M92,M100:M101) -> 24.914117 | R103: =SUM(R89:R92,R100:R101) -> 36.480537 | W103: =SUM(W89:W92,W100:W101) -> 45.637774 | AB103: =SUM(AB89:AB92,AB100:AB101) -> 117.96 | AG103: =SUM(AG89:AG92,AG100:AG101) -> 179.995 | AH103: =SUM(AH89:AH92,AH100:AH101) -> 5.655 | AI103: =SUM(AI89:AI92,AI100:AI101) -> 13.874 | AJ103: =SUM(AJ89:AJ92,AJ100:AJ101) -> 33.99 | AK103: =SUM(AK89:AK92,AK100:AK101) -> 150.096 | AL103: =SUM(AL89:AL92,AL100:AL101) -> 203.615 | AM103: =SUM(AM89:AM92,AM100:AM101) -> 15.952 | AN103: =SUM(AN89:AN92,AN100:AN101) -> 47.568 | ... DS103: =SUM(DS89:DS92,DS100:DS101) -> 1675.1105
B105: Capex | M105: =M148 -> -12.532013 | R105: =R148 -> -29.126067 | W105: =W148 -> -40.530459 | AB105: =AB148 -> -15.497 | AG105: =AG148 -> -30.357 | AH105: =AH148 -> -74.831 | AI105: =AI148-AH148 -> -12.493 | AJ105: =AJ148-AI148 -> -13.366 | AK105: =AK148-AJ148 -> -15.967 | AL105: =AL148 -> -116.657 | AM105: =AM148 -> -12.696 | AN105: =AN148-AM148 -> -26.35 | AO105: =AO148-AN148 -> -32.995 | AP105: =AP148-AO148 -> -21.188 | AQ105: =AQ148 -> -93.229 | AR105: =AR148 -> -20.976 | AS105: =AS148-AR148 -> -23.038 | AT105: =AT148-AS148 -> -27.931 | AU105: =AU148-AT148 -> -34.463 | AV105: =AV148 -> -106.408 | AW105: =AW148 -> -25.447 | AX105: =AX148-AW148 -> -26.655 | AY105: =AY148-AX148 -> -37.271 | AZ105: =AZ148-AY148 -> -30.36 | BA105: =BA148 -> -119.733 | BB105: =BB148 -> -27.936 | BC105: =BC148-BB148 -> -37.182 | BD105: =BD148-BC148 -> -42.943 | BE105: =BE148-BD148 -> -35.426 | BF105: =BF148 -> -143.487 | BG105: =BG148 -> -26.644 | BH105: =BH148-BG148 -> -44.617 | BI105: =BI148-BH148 -> -34.907 | BJ105: =BJ148-BI148 -> -43.343 | BK105: =BK148 -> -149.511 | BL105: =BL148 -> -19.879 | BM105: =BM148-BL148 -> -30.01 | BN105: =BN148-BM148 -> -57.239 | BO105: =BO148-BN148 -> -50.736 | BP105: =BP148 -> -157.864 | BQ105: =BQ148 -> -34.314 | BR105: =BR148-BQ148 -> -49.693 | BS105: =BS148-BR148 -> -72.739 | BT105: =BT148-BS148 -> -69.061 | BU105: =BU148 -> -225.807 | BV105: =BV148 -> -68.434 | BW105: =BW148-BV148 -> -67.33 | BX105: =BX148-BW148 -> -78.453 | BY105: =BY148-BX148 -> -68.831 | BZ105: =SUM(BV105:BY105) -> -283.048 | CA105: =CA148 -> -52.101 | CB105: =CB148-CA148 -> -52.622 | CC105: =CC148-CB148 -> -66.107 | CD105: =CD148-CC148 -> -58.396 | CE105: =SUM(CA105:CD105) -> -229.226 | CF105: =CF148 -> -64.225 | CG105: =CG148-CF148 -> -80.269 | CH105: =CH148-CG148 -> -122.497 | CI105: =CI148-CH148 -> -127.511 | CJ105: =SUM(CF105:CI105) -> -394.502 | CK105: =CK148 -> -111.352 | CL105: =CL148-CK148 -> -144.718 | CM105: =CM148-CL148 -> -175.607 | CN105: =CN148-CM148 -> -206.98 | CO105: =SUM(CK105:CN105) -> -638.657 | CP105: =CP148 -> -136.942 | CQ105: =CQ148-CP148 -> -145.511 | CR105: =CR148-CQ148 -> -162.9 | CS105: =CS148-CR148 -> -206.512 | CT105: =SUM(CP105:CS105) -> -651.865 | CU105: =CU148 -> -130.681 | CV105: =CV148-CU148 -> -145.086 | CW105: =CW148-CV148 -> -178.483 | CX105: =CX148-CW148 -> -234.982 | CY105: =SUM(CU105:CX105) -> -689.232 | CZ105: =CZ148 -> -152.263 | DA105: =DA148-CZ148 -> -177.898 | DB105: =DB148-DA148 -> -167.441 | DC105: =DC148-DB148 -> -183.2 | DD105: =SUM(CZ105:DC105) -> -680.802 | DE105: =DE148 -> -127.38 | DF105: =DF148-DE148 -> -149.676 | DG105: =-DG253 -> -197.58038 | DH105: =-DH253 -> -216.176 | DI105: =SUM(DE105:DH105) -> -690.81238 | DJ105: =-DJ253 -> -142.6656 | DK105: =-DK253 -> -167.63712 | DL105: =-DL253 -> -221.29003 | DM105: =-DM253 -> -242.11712 | DN105: =SUM(DJ105:DM105) -> -773.70987 | DO105: =-DO253 -> -159.78547 | DP105: =-DP253 -> -187.75357 | DQ105: =-DQ253 -> -247.84483 | DR105: =-DR253 -> -271.17117 | DS105: =SUM(DO105:DR105) -> -866.55505
B106: Acquisitions | M106: =M149 -> -0.51185 | R106: =R149 -> -5.559179 | W106: =W149 -> -3.401633 | AB106: =AB149 -> -0.81 | AG106: =AG149 -> -12.482 | AH106: =AH149 -> 0 | AI106: =AI149-AH149 -> 0 | AJ106: =AJ149-AI149 -> -5.654 | AK106: =AK149-AJ149 -> 0 | AL106: =AL149 -> -5.654 | AM106: =AM149 -> 0 | AN106: =AN149-AM149 -> 0 | AO106: =AO149-AN149 -> 0 | AP106: =AP149-AO149 -> 0 | AQ106: =AQ149 -> 0 | AR106: =AR149 -> 0 | AS106: =AS149-AR149 -> 0 | AT106: =AT149-AS149 -> 0 | AU106: =AU149-AT149 -> 0 | AV106: =AV149 -> 0 | AW106: =AW149 -> 0 | AX106: =AX149-AW149 -> 0 | AY106: =AY149-AX149 -> 0 | AZ106: =AZ149-AY149 -> 0 | BA106: =BA149 -> 0 | BB106: =BB149 -> 0 | BC106: =BC149-BB149 -> 0 | BD106: =BD149-BC149 -> 0 | BE106: =BE149-BD149 -> 0 | BF106: =BF149 -> 0 | BG106: =BG149 -> 0 | BH106: =BH149-BG149 -> 0 | BI106: =BI149-BH149 -> 0 | BJ106: =BJ149-BI149 -> 0 | BK106: =BK149 -> 0 | BL106: =BL149 -> 0 | BM106: =BM149-BL149 -> 0 | BN106: =BN149-BM149 -> 0 | BO106: =BO149-BN149 -> 0 | BP106: =BP149 -> 0 | BQ106: =BQ149 -> 0 | BR106: =BR149-BQ149 -> 0 | BS106: =BS149-BR149 -> 0 | BT106: =BT149-BS149 -> 0 | BU106: =BU149 -> 0 | BV106: =BV149 -> 0 | BW106: =BW149-BV149 -> 0 | BX106: =BX149-BW149 -> 0 | BY106: =BY149-BX149 -> 0 | BZ106: =SUM(BV106:BY106) -> 0 | CA106: =CA149 -> 0 | CB106: =CB149-CA149 -> -452.581 | CC106: =CC149-CB149 -> 0 | CD106: =CD149-CC149 -> 0 | CE106: =SUM(CA106:CD106) -> -452.581 | CF106: =CF149 -> 0 | CG106: =CG149-CF149 -> 0 | CH106: =CH149-CG149 -> 0 | CI106: =CI149-CH149 -> 0 | CJ106: =SUM(CF106:CI106) -> 0 | CK106: =CK149 -> 0 | CL106: =CL149-CK149 -> 0 | CM106: =CM149-CL149 -> 0 | CN106: =CN149-CM149 -> 0 | CO106: =SUM(CK106:CN106) -> 0 | CP106: =CP149 -> 0 | CQ106: =CQ149-CP149 -> 0 | CR106: =CR149-CQ149 -> 0 | CS106: =CS149-CR149 -> 0 | CT106: =SUM(CP106:CS106) -> 0 | CU106: =CU149 -> 0 | CV106: =CV149-CU149 -> 0 | CW106: =CW149-CV149 -> -130.996 | CX106: =CX149-CW149 -> -23.15 | CY106: =SUM(CU106:CX106) -> -154.146 | CZ106: =CZ149 -> 0 | DA106: =DA149-CZ149 -> 0 | DB106: =DB149-DA149 -> 0 | DC106: =DC149-DB149 -> 0 | DD106: =SUM(CZ106:DC106) -> 0 | DE106: =DE149 -> 0 | DF106: =DF149-DE149 -> 0 | DG106: 0 | DH106: 0 | DI106: =SUM(DE106:DH106) -> 0 | DJ106: 0 | DK106: 0 | DL106: 0 | DM106: 0 | DN106: =SUM(DJ106:DM106) -> 0 | DO106: 0 | DP106: 0 | DQ106: 0 | DR106: 0 | DS106: =SUM(DO106:DR106) -> 0
B107: Other | M107: =M150 -> -0.305807 | R107: =R150 -> -0.549873 | W107: =W150 -> -2.863353 | AB107: =AB150 -> 0 | AG107: =AG150 -> 0 | AH107: =AH150 -> 0 | AI107: =AI150-AH150 -> 0 | AJ107: =AJ150-AI150 -> 0 | AK107: =AK150-AJ150 -> 0 | AL107: =AL150 -> 0 | AM107: =AM150 -> 0 | AN107: =AN150-AM150 -> 0 | AO107: =AO150-AN150 -> 0 | AP107: =AP150-AO150 -> 0 | AQ107: =AQ150 -> 0 | AR107: =AR150 -> 0 | AS107: =AS150-AR150 -> 0 | AT107: =AT150-AS150 -> 0 | AU107: =AU150-AT150 -> 0 | AV107: =AV150 -> 0 | AW107: =AW150 -> 0 | AX107: =AX150-AW150 -> 0 | AY107: =AY150-AX150 -> 0 | AZ107: =AZ150-AY150 -> 0 | BA107: =BA150 -> 0 | BB107: =BB150 -> 0 | BC107: =BC150-BB150 -> 0 | BD107: =BD150-BC150 -> 0 | BE107: =BE150-BD150 -> 0 | BF107: =BF150 -> 0 | BG107: =BG150 -> 0 | BH107: =BH150-BG150 -> 0 | BI107: =BI150-BH150 -> 0 | BJ107: =BJ150-BI150 -> 0 | BK107: =BK150 -> 0 | BL107: =BL150 -> 0 | BM107: =BM150-BL150 -> 0 | BN107: =BN150-BM150 -> -12.923 | BO107: =BO150-BN150 -> -2.605 | BP107: =BP150 -> -15.528 | BQ107: =BQ150 -> 0 | BR107: =BR150-BQ150 -> -5.285 | BS107: =BS150-BR150 -> -3.883 | BT107: =BT150-BS150 -> -7.819 | BU107: =BU150 -> -16.987 | BV107: =BV150 -> 4.526 | BW107: =BW150-BV150 -> -0.731 | BX107: =BX150-BW150 -> -2.053 | BY107: =BY150-BX150 -> 2.898 | BZ107: =SUM(BV107:BY107) -> 4.64 | CA107: =CA150 -> 6.475 | CB107: =CB150-CA150 -> 5.506 | CC107: =CC150-CB150 -> -5.114 | CD107: =CD150-CC150 -> -20.592 | CE107: =SUM(CA107:CD107) -> -13.725 | CF107: =CF150 -> -21.239 | CG107: =CG150-CF150 -> -35.76 | CH107: =CH150-CG150 -> 10.552 | CI107: =CI150-CH150 -> 13.058 | CJ107: =SUM(CF107:CI107) -> -33.389 | CK107: =CK150 -> 10.024 | CL107: =CL150-CK150 -> 21.102 | CM107: =CM150-CL150 -> 13.689 | CN107: =CN150-CM150 -> 23.905 | CO107: =SUM(CK107:CN107) -> 68.72 | CP107: =CP150 -> -1.277 | CQ107: =CQ150-CP150 -> 0.07 | CR107: =CR150-CQ150 -> 1.235 | CS107: =CS150-CR150 -> -2.295 | CT107: =SUM(CP107:CS107) -> -2.267 | CU107: =CU150 -> -0.856 | CV107: =CV150-CU150 -> 9.998 | CW107: =CW150-CV150 -> 0.89 | CX107: =CX150-CW150 -> 35.172 | CY107: =SUM(CU107:CX107) -> 45.204 | CZ107: =CZ150 -> 45.421 | DA107: =DA150-CZ150 -> -35.22 | DB107: =DB150-DA150 -> -1.656 | DC107: =DC150-DB150 -> 10.139 | DD107: =SUM(CZ107:DC107) -> 18.684 | DE107: =DE150 -> -11.47 | DF107: =DF150-DE150 -> 6.724 | DG107: 0 | DH107: 0 | DI107: =SUM(DE107:DH107) -> -4.746 | DJ107: 0 | DK107: 0 | DL107: 0 | DM107: 0 | DN107: =SUM(DJ107:DM107) -> 0 | DO107: 0 | DP107: 0 | DQ107: 0 | DR107: 0 | DS107: =SUM(DO107:DR107) -> 0
B109: Cash From Investing | M109: =SUM(M105:M107) -> -13.34967 | R109: =SUM(R105:R107) -> -35.235119 | W109: =SUM(W105:W107) -> -46.795445 | AB109: =SUM(AB105:AB107) -> -16.307 | AG109: =SUM(AG105:AG107) -> -42.839 | AH109: =SUM(AH105:AH107) -> -74.831 | AI109: =SUM(AI105:AI107) -> -12.493 | AJ109: =SUM(AJ105:AJ107) -> -19.02 | AK109: =SUM(AK105:AK107) -> -15.967 | AL109: =SUM(AL105:AL107) -> -122.311 | AM109: =SUM(AM105:AM107) -> -12.696 | AN109: =SUM(AN105:AN107) -> -26.35 | ... DS109: =SUM(DS105:DS107) -> -866.55505
B111: Debt | M111: =M156 -> 0 | R111: =R156 -> 0 | W111: =W156 -> 0 | AB111: =AB156 -> 0 | AG111: =AG156 -> 0 | AH111: =AH156 -> 0 | AI111: =AI156-AH156 -> 0 | AJ111: =AJ156-AI156 -> 0 | AK111: =AK156-AJ156 -> 0 | AL111: =AL156 -> 0 | AM111: =AM156 -> 0 | AN111: =AN156-AM156 -> 0 | AO111: =AO156-AN156 -> 0 | AP111: =AP156-AO156 -> 0 | AQ111: =AQ156 -> 0 | AR111: =AR156 -> 0 | AS111: =AS156-AR156 -> 0 | AT111: =AT156-AS156 -> 0 | AU111: =AU156-AT156 -> 0 | AV111: =AV156 -> 0 | AW111: =AW156 -> 0 | AX111: =AX156-AW156 -> 0 | AY111: =AY156-AX156 -> 0 | AZ111: =AZ156-AY156 -> 0 | BA111: =BA156 -> 0 | BB111: =BB156 -> 0 | BC111: =BC156-BB156 -> 0 | BD111: =BD156-BC156 -> 0 | BE111: =BE156-BD156 -> 0 | BF111: =BF156 -> 0 | BG111: =BG156 -> 0 | BH111: =BH156-BG156 -> 0 | BI111: =BI156-BH156 -> 0 | BJ111: =BJ156-BI156 -> 0 | BK111: =BK156 -> 0 | BL111: =BL156 -> 0 | BM111: =BM156-BL156 -> 0 | BN111: =BN156-BM156 -> 0 | BO111: =BO156-BN156 -> 0 | BP111: =BP156 -> 0 | BQ111: =BQ156 -> 0 | BR111: =BR156-BQ156 -> 100 | BS111: =BS156-BR156 -> -100 | BT111: =BT156-BS156 -> 0 | BU111: =BU156 -> 0 | BV111: =BV156 -> 0 | BW111: =BW156-BV156 -> 0 | BX111: =BX156-BW156 -> 0 | BY111: =BY156-BX156 -> 0 | BZ111: =SUM(BV111:BY111) -> 0 | CA111: =CA156 -> 0 | CB111: =CB156-CA156 -> 0 | CC111: =CC156-CB156 -> 0 | CD111: =CD156-CC156 -> 0 | CE111: =SUM(CA111:CD111) -> 0 | CF111: =CF156 -> 0 | CG111: =CG156-CF156 -> 0 | CH111: =CH156-CG156 -> 0 | CI111: =CI156-CH156 -> 0 | CJ111: =SUM(CF111:CI111) -> 0 | CK111: =CK156 -> 0 | CL111: =CL156-CK156 -> 0 | CM111: =CM156-CL156 -> 0 | CN111: =CN156-CM156 -> 0 | CO111: =SUM(CK111:CN111) -> 0 | CP111: =CP156 -> 0 | CQ111: =CQ156-CP156 -> 0 | CR111: =CR156-CQ156 -> 0 | CS111: =CS156-CR156 -> 0 | CT111: =SUM(CP111:CS111) -> 0 | CU111: =CU156 -> 0 | CV111: =CV156-CU156 -> 0 | CW111: =CW156-CV156 -> 0 | CX111: =CX156-CW156 -> 0 | CY111: =SUM(CU111:CX111) -> 0 | CZ111: =CZ156 -> 0 | DA111: =DA156-CZ156 -> 0 | DB111: =DB156-DA156 -> 0 | DC111: =DC156-DB156 -> 0 | DD111: =SUM(CZ111:DC111) -> 0 | DE111: =DE156 -> 0 | DF111: =DF156-DE156 -> 0 | DG111: 0 | DH111: 0 | DI111: =SUM(DE111:DH111) -> 0 | DJ111: 0 | DK111: 0 | DL111: 0 | DM111: 0 | DN111: =SUM(DJ111:DM111) -> 0 | DO111: 0 | DP111: 0 | DQ111: 0 | DR111: 0 | DS111: =SUM(DO111:DR111) -> 0
B112: Stock Buybacks | M112: =M157 -> 0 | R112: =R157 -> 0 | W112: =W157 -> 0 | AB112: =AB157 -> 0 | AG112: =AG157 -> 0 | AH112: =AH157 -> 0 | AI112: =AI157-AH157 -> 0 | AJ112: =AJ157-AI157 -> 0 | AK112: =AK157-AJ157 -> 0 | AL112: =AL157 -> 0 | AM112: =AM157 -> 0 | AN112: =AN157-AM157 -> 0 | AO112: =AO157-AN157 -> 0 | AP112: =AP157-AO157 -> 0 | AQ112: =AQ157 -> 0 | AR112: =AR157 -> 0 | AS112: =AS157-AR157 -> 0 | AT112: =AT157-AS157 -> 0 | AU112: =AU157-AT157 -> 0 | AV112: =AV157 -> 0 | AW112: =AW157 -> 0 | AX112: =AX157-AW157 -> -55.804 | AY112: =AY157-AX157 -> -74.462 | AZ112: =AZ157-AY157 -> -17.165 | BA112: =BA157 -> -147.431 | BB112: =BB157 -> -18.815 | BC112: =BC157-BB157 -> -63.183 | BD112: =BD157-BC157 -> -87.976 | BE112: =BE157-BD157 -> -104.219 | BF112: =BF157 -> -274.193 | BG112: =BG157 -> -15.765 | BH112: =BH157-BG157 -> -12.791 | BI112: =BI157-BH157 -> 0 | BJ112: =BJ157-BI157 -> -0.771 | BK112: =BK157 -> -29.327 | BL112: =BL157 -> -12.804 | BM112: =BM157-BL157 -> -77.997 | BN112: =BN157-BM157 -> -8.468 | BO112: =BO157-BN157 -> -0.992 | BP112: =BP157 -> -100.261 | BQ112: -0.008 | BR112: =BR157-BQ157 -> -406.238 | BS112: =BS157-BR157 -> -8.089 | BT112: =BT157-BS157 -> -184.005 | BU112: =BU157 -> -598.34 | BV112: =BV157 -> -163.53 | BW112: =BW157-BV157 -> -1.569 | BX112: =BX157-BW157 -> -7.993 | BY112: =BY157-BX157 -> -0.307 | BZ112: =SUM(BV112:BY112) -> -173.399 | CA112: =CA157 -> -63.663 | CB112: =CB157-CA157 -> 0 | CC112: =CC157-CB157 -> 0 | CD112: =CD157-CC157 -> 0 | CE112: =SUM(CA112:CD112) -> -63.663 | CF112: =CF157 -> -83.831 | CG112: =CG157-CF157 -> -171.082 | CH112: =CH157-CG157 -> -236.423 | CI112: =CI157-CH157 -> -321.266 | CJ112: =SUM(CF112:CI112) -> -812.602 | CK112: =CK157 -> -232.644 | CL112: =CL157-CK157 -> -125.34 | CM112: =CM157-CL157 -> -16.992 | CN112: =CN157-CM157 -> -69.025 | CO112: =SUM(CK112:CN112) -> -444.001 | CP112: =CP157 -> -98.479 | CQ112: =CQ157-CP157 -> -193.538 | CR112: =CR157-CQ157 -> -212.626 | CS112: =CS157-CR157 -> -54.009 | CT112: =SUM(CP112:CS112) -> -558.652 | CU112: =CU157 -> -299.479 | CV112: =CV157-CU157 -> -589.456 | CW112: =CW157-CV157 -> -412.593 | CX112: =CX157-CW157 -> -335.351 | CY112: =SUM(CU112:CX112) -> -1636.879 | CZ112: =CZ157 -> -434.439 | DA112: =DA157-CZ157 -> -281.233 | DB112: =DB157-DA157 -> -190.908 | DC112: =DC157-DB157 -> -271.769 | DD112: =SUM(CZ112:DC112) -> -1178.349 | DE112: =DE157 -> -361.756 | DF112: =DF157-DE157 -> -333.349 | DG112: -275 | DH112: -275 | DI112: =SUM(DE112:DH112) -> -1245.105 | DJ112: -150 | DK112: -150 | DL112: -150 | DM112: -150 | DN112: =SUM(DJ112:DM112) -> -600 | DO112: -150 | DP112: -150 | DQ112: -150 | DR112: -150 | DS112: =SUM(DO112:DR112) -> -600
B113: Other Equity | M113: =M158 -> 0 | R113: =R158 -> 0.054649 | W113: =W158 -> 1.436471 | AB113: =AB158 -> 1.209 | AG113: =AG158 -> 5.836 | AH113: =AH158 -> 8.158 | AI113: =AI158-AH158 -> 3.937 | AJ113: =AJ158-AI158 -> 2.379 | AK113: =AK158-AJ158 -> -4.86 | AL113: =AL158 -> 9.614 | AM113: =AM158 -> 8.811 | AN113: =AN158-AM158 -> 1.659 | AO113: =AO158-AN158 -> 3.68 | AP113: =AP158-AO158 -> -40.163 | AQ113: =AQ158 -> -26.013 | AR113: =AR158 -> 0.163 | AS113: =AS158-AR158 -> 6.142 | AT113: =AT158-AS158 -> 0.148 | AU113: =AU158-AT158 -> -6.453 | AV113: =AV158 -> 0 | AW113: =AW158 -> 1.575 | AX113: =AX158-AW158 -> -2.938 | AY113: =AY158-AX158 -> -0.152 | AZ113: =AZ158-AY158 -> 4.428 | BA113: =BA158 -> 2.913 | BB113: =BB158 -> 2.802 | BC113: =BC158-BB158 -> 0.504 | BD113: =BD158-BC158 -> -0.639 | BE113: =BE158-BD158 -> 2.037 | BF113: =BF158 -> 4.704 | BG113: =BG158 -> 3.579 | BH113: =BH158-BG158 -> 1.1 | BI113: =BI158-BH158 -> -0.083 | BJ113: =BJ158-BI158 -> 2.311 | BK113: =BK158 -> 6.907 | BL113: =BL158 -> 0.278 | BM113: =BM158-BL158 -> -1.387 | BN113: =BN158-BM158 -> 2.757 | BO113: =BO158-BN158 -> 3.98 | BP113: =BP158 -> 5.628 | BQ113: =BQ158 -> 8.408 | BR113: =BR158-BQ158 -> 5.344 | BS113: =BS158-BR158 -> 3.505 | BT113: =BT158-BS158 -> 0.393 | BU113: =BU158 -> 17.65 | BV113: =BV158 -> 12.177 | BW113: =BW158-BV158 -> 1.337 | BX113: =BX158-BW158 -> 1.516 | BY113: =BY158-BX158 -> 3.14 | BZ113: =SUM(BV113:BY113) -> 18.17 | CA113: =CA158 -> 3.135 | CB113: =CB158-CA158 -> 9.328 | CC113: =CC158-CB158 -> 1.679 | CD113: =CD158-CC158 -> 1.121 | CE113: =SUM(CA113:CD113) -> 15.263 | CF113: =CF158 -> 4.495 | CG113: =CG158-CF158 -> 5.218 | CH113: =CH158-CG158 -> 7.907 | CI113: =CI158-CH158 -> 0.574 | CJ113: =SUM(CF113:CI113) -> 18.194 | CK113: =CK158 -> 5.143 | CL113: =CL158-CK158 -> 1.043 | CM113: =CM158-CL158 -> 4.057 | CN113: =CN158-CM158 -> 1.461 | CO113: =SUM(CK113:CN113) -> 11.704 | CP113: =CP158 -> 11.873 | CQ113: =CQ158-CP158 -> 4.228 | CR113: =CR158-CQ158 -> 8.836 | CS113: =CS158-CR158 -> 17.493 | CT113: =SUM(CP113:CS113) -> 42.43 | CU113: =CU158 -> 3.393 | CV113: =CV158-CU158 -> 2.37 | CW113: =CW158-CV158 -> 1.514 | CX113: =CX158-CW158 -> 12.536 | CY113: =SUM(CU113:CX113) -> 19.813 | CZ113: =CZ158 -> 0.221 | DA113: =DA158-CZ158 -> 5.257 | DB113: =DB158-DA158 -> 0.071 | DC113: =DC158-DB158 -> 2.828 | DD113: =SUM(CZ113:DC113) -> 8.377 | DE113: =DE158 -> 0 | DF113: =DF158-DE158 -> 0 | DG113: 0 | DH113: 0 | DI113: =SUM(DE113:DH113) -> 0 | DJ113: 0 | DK113: 0 | DL113: 0 | DM113: 0 | DN113: =SUM(DJ113:DM113) -> 0 | DO113: 0 | DP113: 0 | DQ113: 0 | DR113: 0 | DS113: =SUM(DO113:DR113) -> 0
B114: Dividends | M114: =M159 -> 0 | R114: =R159 -> 0 | W114: =W159 -> 0 | AB114: =AB159 -> 0 | AG114: =AG159 -> 0 | AH114: =AH159 -> 0 | AI114: =AI159-AH159 -> 0 | AJ114: =AJ159-AI159 -> 0 | AK114: =AK159-AJ159 -> 0 | AL114: =AL159 -> 0 | AM114: =AM159 -> 0 | AN114: =AN159-AM159 -> 0 | AO114: =AO159-AN159 -> 0 | AP114: =AP159-AO159 -> 0 | AQ114: =AQ159 -> 0 | AR114: =AR159 -> 0 | AS114: =AS159-AR159 -> 0 | AT114: =AT159-AS159 -> 0 | AU114: =AU159-AT159 -> 0 | AV114: =AV159 -> 0 | AW114: =AW159 -> 0 | AX114: =AX159-AW159 -> 0 | AY114: =AY159-AX159 -> 0 | AZ114: =AZ159-AY159 -> 0 | BA114: =BA159 -> 0 | BB114: =BB159 -> 0 | BC114: =BC159-BB159 -> 0 | BD114: =BD159-BC159 -> 0 | BE114: =BE159-BD159 -> 0 | BF114: =BF159 -> 0 | BG114: =BG159 -> 0 | BH114: =BH159-BG159 -> 0 | BI114: =BI159-BH159 -> 0 | BJ114: =BJ159-BI159 -> 0 | BK114: =BK159 -> 0 | BL114: =BL159 -> 0 | BM114: =BM159-BL159 -> 0 | BN114: =BN159-BM159 -> 0 | BO114: =BO159-BN159 -> 0 | BP114: =BP159 -> 0 | BQ114: =BQ159 -> 0 | BR114: =BR159-BQ159 -> 0 | BS114: =BS159-BR159 -> 0 | BT114: =BT159-BS159 -> 0 | BU114: =BU159 -> 0 | BV114: =BV159 -> 0 | BW114: =BW159-BV159 -> 0 | BX114: =BX159-BW159 -> 0 | BY114: =BY159-BX159 -> 0 | BZ114: =SUM(BV114:BY114) -> 0 | CA114: =CA159 -> 0 | CB114: =CB159-CA159 -> 0 | CC114: =CC159-CB159 -> 0 | CD114: =CD159-CC159 -> 0 | CE114: =SUM(CA114:CD114) -> 0 | CF114: =CF159 -> 0 | CG114: =CG159-CF159 -> 0 | CH114: =CH159-CG159 -> 0 | CI114: =CI159-CH159 -> 0 | CJ114: =SUM(CF114:CI114) -> 0 | CK114: =CK159 -> 0 | CL114: =CL159-CK159 -> 0 | CM114: =CM159-CL159 -> 0 | CN114: =CN159-CM159 -> 0 | CO114: =SUM(CK114:CN114) -> 0 | CP114: =CP159 -> 0 | CQ114: =CQ159-CP159 -> 0 | CR114: =CR159-CQ159 -> 0 | CS114: =CS159-CR159 -> 0 | CT114: =SUM(CP114:CS114) -> 0 | CU114: =CU159 -> 0 | CV114: =CV159-CU159 -> 0 | CW114: =CW159-CV159 -> 0 | CX114: =CX159-CW159 -> 0 | CY114: =SUM(CU114:CX114) -> 0 | CZ114: =CZ159 -> 0 | DA114: =DA159-CZ159 -> 0 | DB114: =DB159-DA159 -> 0 | DC114: =DC159-DB159 -> 0 | DD114: =SUM(CZ114:DC114) -> 0 | DE114: =DE159 -> 0 | DF114: =DF159-DE159 -> 0 | DG114: 0 | DH114: 0 | DI114: =SUM(DE114:DH114) -> 0 | DJ114: 0 | DK114: 0 | DL114: 0 | DM114: 0 | DN114: =SUM(DJ114:DM114) -> 0 | DO114: 0 | DP114: 0 | DQ114: 0 | DR114: 0 | DS114: =SUM(DO114:DR114) -> 0
B115: Other | M115: =M160 -> 0.668859 | R115: =R160 -> 31.357508 | W115: =W160 -> 12.024413 | AB115: =AB160 -> -3.858 | AG115: =AG160 -> 7.863 | AH115: =AH160 -> 0 | AI115: =AI160-AH160 -> 0 | AJ115: =AJ160-AI160 -> 0 | AK115: =AK160-AJ160 -> 5.75 | AL115: =AL160 -> 5.75 | AM115: =AM160 -> 0 | AN115: =AN160-AM160 -> 0 | AO115: =AO160-AN160 -> -26.013 | AP115: =AP160-AO160 -> 46.535 | AQ115: =AQ160 -> 20.522 | AR115: =AR160 -> -4.521 | AS115: =AS160-AR160 -> 4.521 | AT115: =AT160-AS160 -> 2.201 | AU115: =AU160-AT160 -> 6.706 | AV115: =AV160 -> 8.907 | AW115: =AW160 -> -3.224 | AX115: =AX160-AW160 -> 3.224 | AY115: =AY160-AX160 -> 0 | AZ115: =AZ160-AY160-0.067 -> -4.626 | BA115: =BA160 -> -4.559 | BB115: =BB160 -> -1.028 | BC115: =BC160-BB160 -> 0.883 | BD115: =BD160-BC160 -> 0 | BE115: =BE160-BD160 -> -4.059 | BF115: =BF160 -> -4.204 | BG115: =BG160 -> -1.143 | BH115: =BH160-BG160 -> 1.143 | BI115: =BI160-BH160 -> 0 | BJ115: =BJ160-BI160 -> -2.918 | BK115: =BK160 -> -2.918 | BL115: =BL160 -> -1.961 | BM115: =BM160-BL160 -> 1.961 | BN115: =BN160-BM160 -> -3.086 | BO115: =BO160-BN160 -> -0.143 | BP115: =BP160 -> -3.229 | BQ115: =BQ160 -> -6.5 | BR115: =BR160-BQ160 -> -1.245 | BS115: =BS160-BR160 -> -1.538 | BT115: =BT160-BS160 -> -0.241 | BU115: =BU160 -> -9.524 | BV115: =BV160 -> -18.939 | BW115: =BW160-BV160 -> -0.461 | BX115: =BX160-BW160 -> -2.093 | BY115: =BY160-BX160 -> -0.451 | BZ115: =SUM(BV115:BY115) -> -21.944 | CA115: =CA160 -> -30.059 | CB115: =CB160-CA160 -> -0.898 | CC115: =CC160-CB160 -> -0.926 | CD115: =CD160-CC160 -> -0.505 | CE115: =SUM(CA115:CD115) -> -32.388 | CF115: =CF160 -> -42.899 | CG115: =CG160-CF160 -> -2.668 | CH115: =CH160-CG160 -> -3.914 | CI115: =CI160-CH160 -> -1.098 | CJ115: =SUM(CF115:CI115) -> -50.579 | CK115: =CK160 -> -32.059 | CL115: =CL160-CK160 -> -0.719 | CM115: =CM160-CL160 -> -1.917 | CN115: =CN160-CM160 -> -0.495 | CO115: =SUM(CK115:CN115) -> -35.19 | CP115: =CP160 -> -28.793 | CQ115: =CQ160-CP160 -> -0.942 | CR115: =CR160-CQ160 -> -1.142 | CS115: =CS160-CR160 -> -1.729 | CT115: =SUM(CP115:CS115) -> -32.606 | CU115: =CU160 -> -32.542 | CV115: =CV160-CU160 -> -0.829 | CW115: =CW160-CV160 -> -0.888 | CX115: =CX160-CW160 -> -1.183 | CY115: =SUM(CU115:CX115) -> -35.442 | CZ115: =CZ160 -> -33.756 | DA115: =DA160-CZ160 -> -0.873 | DB115: =DB160-DA160 -> -3.366 | DC115: =DC160-DB160 -> -0.689 | DD115: =SUM(CZ115:DC115) -> -38.684 | DE115: =DE160 -> -16.769 | DF115: =DF160-DE160 -> -0.351 | DG115: 0 | DH115: 0 | DI115: =SUM(DE115:DH115) -> -17.12 | DJ115: 0 | DK115: 0 | DL115: 0 | DM115: 0 | DN115: =SUM(DJ115:DM115) -> 0 | DO115: 0 | DP115: 0 | DQ115: 0 | DR115: 0 | DS115: =SUM(DO115:DR115) -> 0
B117: Cash From Financing | M117: =SUM(M111:M115) -> 0.668859 | R117: =SUM(R111:R115) -> 31.412157 | W117: =SUM(W111:W115) -> 13.460884 | AB117: =SUM(AB111:AB115) -> -2.649 | AG117: =SUM(AG111:AG115) -> 13.699 | AH117: =SUM(AH111:AH115) -> 8.158 | AI117: =SUM(AI111:AI115) -> 3.937 | AJ117: =SUM(AJ111:AJ115) -> 2.379 | AK117: =SUM(AK111:AK115) -> 0.89 | AL117: =SUM(AL111:AL115) -> 15.364 | AM117: =SUM(AM111:AM115) -> 8.811 | AN117: =SUM(AN111:AN115) -> 1.659 | ... DS117: =SUM(DS111:DS115) -> -600
B118: Forex | M118: =M163 -> -0.616486 | R118: =R163 -> 4.653263 | W118: =W163 -> -8.851203 | AB118: =AB163 -> 3.772 | AG118: =AG163 -> 5.858 | AH118: =AH163 -> 5.603 | AI118: =AI163-AH163 -> -1.461 | AJ118: =AJ163-AI163 -> -5.132 | AK118: =AK163-AJ163 -> -2.527 | AL118: =AL163 -> -3.517 | AM118: =AM163 -> 2.826 | AN118: =AN163-AM163 -> -2.921 | AO118: =AO163-AN163 -> 0.745 | AP118: =AP163-AO163 -> -1.301 | AQ118: =AQ163 -> -0.651 | AR118: =AR163 -> -1.562 | AS118: =AS163-AR163 -> -11.566 | AT118: =AT163-AS163 -> -7.82 | AU118: =AU163-AT163 -> -51.42 | AV118: =AV163 -> -72.368 | AW118: =AW163 -> 9.437 | AX118: =AX163-AW163 -> 2.271 | AY118: =AY163-AX163 -> -22.462 | AZ118: =AZ163-AY163 -> -69.055 | BA118: =BA163 -> -79.809 | BB118: =BB163 -> 15.439 | BC118: =BC163-BB163 -> -26.862 | BD118: =BD163-BC163 -> -0.037 | BE118: =BE163-BD163 -> -33.097 | BF118: =BF163 -> -44.557 | BG118: =BG163 -> 48.803 | BH118: =BH163-BG163 -> -19.785 | BI118: =BI163-BH163 -> -17.317 | BJ118: =BJ163-BI163 -> 11.393 | BK118: =BK163 -> 23.094 | BL118: =BL163 -> -21.591 | BM118: =BM163-BL163 -> 47.718 | BN118: =BN163-BM163 -> -21.47 | BO118: =BO163-BN163 -> 32.915 | BP118: =BP163 -> 37.572 | BQ118: =BQ163 -> -27.353 | BR118: =BR163-BQ163 -> -5.802 | BS118: =BS163-BR163 -> 1.66 | BT118: =BT163-BS163 -> 12.543 | BU118: =BU163 -> -18.952 | BV118: =BV163 -> -8.076 | BW118: =BW163-BV163 -> 3.406 | BX118: =BX163-BW163 -> 6.427 | BY118: =BY163-BX163 -> -3.307 | BZ118: =SUM(BV118:BY118) -> -1.55 | CA118: =CA163 -> -13.043 | CB118: =CB163-CA163 -> 9.954 | CC118: =CC163-CB163 -> 3.709 | CD118: =CD163-CC163 -> 29.376 | CE118: =SUM(CA118:CD118) -> 29.996 | CF118: =CF163 -> 22.812 | CG118: =CG163-CF163 -> -10.8 | CH118: =CH163-CG163 -> 9.573 | CI118: =CI163-CH163 -> -28.461 | CJ118: =SUM(CF118:CI118) -> -6.876 | CK118: =CK163 -> -6.711 | CL118: =CL163-CK163 -> 0.809 | CM118: =CM163-CL163 -> -35.254 | CN118: =CN163-CM163 -> 7.113 | CO118: =SUM(CK118:CN118) -> -34.043 | CP118: =CP163 -> 3.855 | CQ118: =CQ163-CP163 -> 15.906 | CR118: =CR163-CQ163 -> -39.648 | CS118: =CS163-CR163 -> 15.787 | CT118: =SUM(CP118:CS118) -> -4.1 | CU118: =CU163 -> -10.658 | CV118: =CV163-CU163 -> -10.697 | CW118: =CW163-CV163 -> -1.796 | CX118: =CX163-CW163 -> -58.515 | CY118: =SUM(CU118:CX118) -> -81.666 | CZ118: =CZ163 -> 34.706 | DA118: =DA163-CZ163 -> -8.187 | DB118: =DB163-DA163 -> -6.546 | DC118: =DC163-DB163 -> 71.19 | DD118: =SUM(CZ118:DC118) -> 91.163 | DE118: =DE163 -> 10.462 | DF118: =DF163-DE163 -> -23.178 | DG118: 0 | DH118: 0 | DI118: =SUM(DE118:DH118) -> -12.716 | DJ118: 0 | DK118: 0 | DL118: 0 | DM118: 0 | DN118: =SUM(DJ118:DM118) -> 0 | DO118: 0 | DP118: 0 | DQ118: 0 | DR118: 0 | DS118: =SUM(DO118:DR118) -> 0
B120: Change in Cash | M120: =M118+M117+M109+M103 -> 11.61682 | R120: =R118+R117+R109+R103 -> 37.310838 | W120: =W118+W117+W109+W103 -> 3.45201 | AB120: =AB118+AB117+AB109+AB103 -> 102.776 | AG120: =AG118+AG117+AG109+AG103 -> 156.713 | AH120: =AH118+AH117+AH109+AH103 -> -55.415 | AI120: =AI118+AI117+AI109+AI103 -> 3.857 | AJ120: =AJ118+AJ117+AJ109+AJ103 -> 12.217 | AK120: =AK118+AK117+AK109+AK103 -> 132.492 | AL120: =AL118+AL117+AL109+AL103 -> 93.151 | AM120: =AM118+AM117+AM109+AM103 -> 14.893 | AN120: =AN118+AN117+AN109+AN103 -> 19.956 | ... DS120: =DS118+DS117+DS109+DS103 -> 208.55547
B122: Beginning Cash | M122: =M167 -> 3.8770179 | R122: =M173 -> 16.028534 | W122: =R173 -> 53.339326 | AB122: =W173 -> 56.797 | AG122: =AB173 -> 159.573 | AH122: =AG173 -> 316.286 | AI122: =AH173 -> 260.871 | AJ122: =AI173 -> 264.728 | AK122: =AJ173 -> 276.946 | AL122: =AG173 -> 316.286 | AM122: =AL173 -> 409.437 | AN122: =AM173 -> 424.33 | AO122: =AN173 -> 444.286 | AP122: =AO173 -> 439.423 | AQ122: =AL173 -> 409.437 | AR122: =AQ173 -> 590.179 | AS122: =AR173 -> 588.418 | AT122: =AS173 -> 610.273 | AU122: =AT173 -> 600.745 | AV122: =AQ173 -> 590.179 | AW122: =AV173 -> 698.649 | AX122: =AW173 -> 751.965 | AY122: =AX173 -> 725.073 | AZ122: =AY173 -> 633.582 | BA122: =AV173 -> 698.649 | BB122: =BA173 -> 664.479 | BC122: =BB173 -> 655.881 | BD122: =BC173 -> 541.262 | BE122: =BD173 -> 403.446 | BF122: =BA173 -> 664.479 | BG122: =BF173 -> 501.482 | BH122: =BG173 -> 550.046 | BI122: =BH173 -> 535.35 | BJ122: =BI173 -> 480.386 | BK122: =BF173 -> 501.482 | BL122: =BK173 -> 734.846 | BM122: =BL173 -> 698.289 | BN122: =BM173 -> 721.212 | BO122: =BN173 -> 650.054 | BP122: =BK173 -> 734.846 | BQ122: =BP173 -> 990.501 | BR122: =BQ173 -> 966.571 | BS122: =BR173 -> 777.841 | BT122: =BS173 -> 703.607 | BU122: =BP173 -> 990.501 | BV122: =BU173 -> 881.32 | BW122: =BV173 -> 576.241 | BX122: =BW173 -> 623.738 | BY122: =BX173 -> 586.153 | BZ122: =BU173 -> 881.32 | CA122: =BZ173 -> 1093.505 | CB122: =CA173 -> 823.006 | CC122: =CB173 -> 522.998 | CD122: =CC173 -> 481.581 | CE122: =BZ173 -> 1093.505 | CF122: =CE173 -> 1150.517 | CG122: =CF173 -> 1179.739 | CH122: =CG173 -> 1170.041 | CI122: =CH173 -> 993.591 | CJ122: =CE173 -> 1150.517 | CK122: =CJ173 -> 1259.871 | CL122: =CK173 -> 649.016 | CM122: =CL173 -> 498.831 | CN122: =CM173 -> 352.624 | CO122: =CJ173 -> 1259.871 | CP122: =CO173 -> 1154.867 | CQ122: =CP173 -> 950.607 | CR122: =CQ173 -> 1107.53 | CS122: =CR173 -> 1091.138 | CT122: =CO173 -> 1154.867 | CU122: =CT173 -> 2243.971 | CV122: =CU173 -> 1900.672 | CW122: =CV173 -> 1610.112 | CX122: =CW173 -> 1188.419 | CY122: =CT173 -> 2243.971 | CZ122: =CY173 -> 1984.336 | DA122: =CZ173 -> 1325.272 | DB122: =DA173 -> 1155.794 | DC122: =DB173 -> 1035.862 | DD122: =CY173 -> 1984.336 | DE122: =DD173 -> 1807.202 | DF122: =DE173 -> 1514.729 | DG122: =DF173 -> 1389.737 | DH122: =DG173 -> 771.25563 | DI122: =DD173 -> 1807.202 | DJ122: =DI173 -> 1220.3385 | DK122: =DJ173 -> 1346.4116 | DL122: =DK173 -> 1356.5497 | DM122: =DL173 -> 854.47308 | DN122: =DI173 -> 1220.3385 | DO122: =DN173 -> 1440.5016 | DP122: =DO173 -> 1550.4387 | DQ122: =DP173 -> 1587.0009 | DR122: =DQ173 -> 1073.9337 | DS122: =DN173 -> 1440.5016
B123: Ending Cash | M123: =M168 -> 16.028534 | R123: =R120+R122 -> 53.339372 | W123: =W120+W122 -> 56.791336 | AB123: =AB120+AB122 -> 159.573 | AG123: =AG120+AG122 -> 316.286 | AH123: =AH120+AH122 -> 260.871 | AI123: =AI120+AI122 -> 264.728 | AJ123: =AJ120+AJ122 -> 276.945 | AK123: =AK120+AK122 -> 409.438 | AL123: =AL120+AL122 -> 409.437 | AM123: =AM120+AM122 -> 424.33 | AN123: =AN120+AN122 -> 444.286 | ... DS123: =DS120+DS122 -> 1649.0571
B124: Check | M124: =M173-M123 -> 0 | R124: =R173-R123 -> -4.6e-05 | W124: =W173-W123 -> 0.005664 | AB124: =AB173-AB123 -> 0 | AG124: =AG173-AG123 -> 0 | AH124: =AH173-AH123 -> 0 | AI124: =AI173-AI123 -> 0 | AJ124: =AJ173-AJ123 -> 0.001 | AK124: =AK173-AK123 -> -0.001 | AL124: =AL173-AL123 -> 0 | AM124: =AM173-AM123 -> 0 | AN124: =AN173-AN123 -> 0 | ... DS124: =DS173-DS123 -> 0
B126: Free-Cash Flow | M126: =M103+M105 -> 12.382104 | R126: =R103+R105 -> 7.35447 | W126: =W103+W105 -> 5.107315 | AB126: =AB103+AB105 -> 102.463 | AG126: =AG103+AG105 -> 149.638 | AH126: =AH103+AH105 -> -69.176 | AI126: =AI103+AI105 -> 1.381 | AJ126: =AJ103+AJ105 -> 20.624 | AK126: =AK103+AK105 -> 134.129 | AL126: =AL103+AL105 -> 86.958 | AM126: =AM103+AM105 -> 3.256 | AN126: =AN103+AN105 -> 21.218 | ... DS126: =DS103+DS105 -> 808.55547
B128: Cash Flow Year to Date
B129: Net Income (Comparable) | M129: =M64 -> 11.014791 | R129: =R64 -> 30.842439 | W129: =W64 -> 42.121694 | AB129: =AB64 -> 58.415456 | AG129: =AG64 -> 122.197 | AH129: =AH64 -> 33.516 | AI129: =AI64+AH129 -> 72.134 | AJ129: =AJ64+AI129 -> 111.075 | AK129: =AK64+AJ129 -> 184.964 | AL129: =AL64 -> 184.964 | AM129: =AM64 -> 46.974 | AN129: =AN64+AM129 -> 104.676 | AO129: =AO64+AN129 -> 162.056 | AP129: =AP64+AO129 -> 271.431 | AQ129: =AQ64 -> 271.431 | AR129: =AR64 -> 47.279 | AS129: =AS64+AR129 -> 103.744 | AT129: =AT64+AS129 -> 169.855 | AU129: =AU64+AT129 -> 279.547 | AV129: =AV64 -> 279.547 | AW129: =AW64 -> 52.681 | AX129: =AX64+AW129 -> 101.448 | AY129: =AY64+AX129 -> 161.899 | AZ129: =BA129 -> 272.733 | BA129: =BA64 -> 272.733 | BB129: =BB64 -> 47.81 | BC129: =BC64+BB129 -> 95.478 | BD129: =BD64+BC129 -> 144.524 | BE129: =BE64+BD129 -> 261.94 | BF129: =BF64 -> 261.94 | BG129: =BG64 -> 40.936 | BH129: =BH64+BG129 -> 92.961 | BI129: =BI64+BH129 -> 157.446 | BJ129: =BJ64+BI129 -> 294.50128 | BK129: =BK64 -> 294.50128 | BL129: =BL64 -> 44.312 | BM129: =BM64+BL129 -> 97.063 | BN129: =BN64+BM129 -> 172.395 | BO129: =BO64+BN129 -> 352.453 | BP129: =BP86 -> 352.437 | BQ129: =BQ64 -> 75.153 | BR129: =BR64+BQ129 -> 170.923 | BS129: =BS64+BR129 -> 270.499 | BT129: =BT64+BS129 -> 514.979 | BU129: =BU86 -> 514.979 | BV129: =BV64 -> 96.603 | BW129: =BW64+BV129 -> 221.593 | BX129: =BX64+BW129 -> 347.575 | BY129: =BY64+BX129 -> 645.596 | BZ129: =BZ86 -> 645.596 | CA129: =CA64 -> 28.632 | CB129: =CB64+CA129 -> 124.93 | CC129: =CC64+CB129 -> 276.208 | CD129: =CD64+CC129 -> 613.579 | CE129: =CE86 -> 613.579 | CF129: =CF64 -> 152.248 | CG129: =CG64+CF129 -> 368.031 | CH129: =CH64+CG129 -> 579.335 | CI129: =CI64+CH129 -> 1015.299 | CJ129: =CJ86 -> 1015.299 | CK129: =CK64 -> 189.998 | CL129: =CL64+CK129 -> 471 | CM129: =CM64+CL129 -> 726.47 | CN129: =CN64+CM129 -> 1288.951 | CO129: =CO86 -> 1288.951 | CP129: =CP64 -> 290.405 | CQ129: =CQ64+CP129 -> 632.008 | CR129: =CR64+CQ129 -> 952.847 | CS129: =CS64+CR129 -> 1622.315 | CT129: =CT86 -> 1622.315 | CU129: =CU64 -> 321.421 | CV129: =CV64+CU129 -> 714.343 | CW129: =CW64+CV129 -> 1066.213 | CX129: =CX64+CW129 -> 1814.616 | CY129: =CY86 -> 1814.616 | CZ129: =CZ64 -> 314.572 | DA129: =DA64+CZ129 -> 685.477 | DB129: =DB64+DA129 -> 992.312 | DC129: =DC64+DB129 -> 1579.183 | DD129: =DD86 -> 1579.183 | DE129: =DE64 -> 195.048 | DF129: =DF64+DE129 -> 524.271
...

Sheet 3. Earnings Build
B1: Lululemon Athletica Inc. (LULU)
B2: Segment Build
B3: $ millions except per-share data, fiscal year ending January
C5: Jan | D5: Apr | E5: Jul | F5: Oct | G5: Jan | H5: Jan | I5: Apr | J5: Jul | K5: Oct | L5: Jan | M5: Jan | N5: Apr | O5: Jul | P5: Oct | Q5: Jan | R5: Jan | S5: Apr | T5: Jul | U5: Oct | V5: Jan | W5: Jan | X5: Apr | Y5: Jul | Z5: Oct | AA5: Jan | AB5: Jan | AC5: Apr | AD5: Jul | AE5: Oct | AF5: Jan | AG5: Jan | AH5: Apr | AI5: Jul | AJ5: Oct | AK5: Jan | AL5: Jan | AM5: Apr | AN5: Jul | AO5: Oct | AP5: Jan | AQ5: Jan | AR5: Apr | AS5: Jul | AT5: Oct | AU5: Jan | AV5: Jan | AW5: Apr | AX5: Jul | AY5: Oct | AZ5: Jan | BA5: Jan | BB5: Apr | BC5: Jul | BD5: Oct | BE5: Jan | BF5: Jan | BG5: Apr | BH5: Jul | BI5: Oct | BJ5: Jan | BK5: Jan | BL5: Apr | BM5: Jul | BN5: Oct | BO5: Jan | BP5: Jan | BQ5: Apr | BR5: Jul | BS5: Oct | BT5: Jan | BU5: Jan | BV5: Apr | BW5: Jul | BX5: Oct | BY5: Jan | BZ5: Jan | CA5: Apr | CB5: Jul | CC5: Oct | CD5: Jan | CE5: Jan | CF5: Apr | CG5: Jul | CH5: Oct | CI5: Jan | CJ5: Jan | CK5: Apr | CL5: Jul | CM5: Oct | CN5: Jan | CO5: Jan | CP5: Apr | CQ5: Jul | CR5: Oct | CS5: Jan | CT5: Jan | CU5: Apr | CV5: Jul | CW5: Oct | CX5: Jan | CY5: Jan | CZ5: Apr | DA5: Jul | DB5: Oct | DC5: Jan | DD5: Jan | DE5: Apr | DF5: Jul | DG5: Oct | DH5: Jan | DI5: Jan | DJ5: Apr | DK5: Jul | DL5: Oct | DM5: Jan | DN5: Jan | DO5: Apr | DP5: Jul | DQ5: Oct | DR5: Jan | DS5: Jan
C6: FY04 | D6: 1Q | E6: 2Q | F6: 3Q | G6: 4Q | H6: FY05 | I6: 1Q | J6: 2Q | K6: 3Q | L6: 4Q | M6: FY06 | N6: 1Q | O6: 2Q | P6: 3Q | Q6: 4Q | R6: FY07 | S6: 1Q | T6: 2Q | U6: 3Q | V6: 4Q | W6: FY08* | X6: 1Q | Y6: 2Q | Z6: 3Q | AA6: 4Q | AB6: FY09 | AC6: 1Q | AD6: 2Q | AE6: 3Q | AF6: 4Q | AG6: FY10 | AH6: 1Q | AI6: 2Q | AJ6: 3Q | AK6: 4Q | AL6: FY11 | AM6: 1Q | AN6: 2Q | AO6: 3Q | AP6: 4Q | AQ6: FY12 | AR6: 1Q | AS6: 2Q | AT6: 3Q | AU6: 4Q | AV6: FY13* | AW6: 1Q | AX6: 2Q | AY6: 3Q | AZ6: 4Q | BA6: FY14 | BB6: 1Q | BC6: 2Q | BD6: 3Q | BE6: 4Q | BF6: FY15 | BG6: 1Q | BH6: 2Q | BI6: 3Q | BJ6: 4Q | BK6: FY16 | BL6: 1Q | BM6: 2Q | BN6: 3Q | BO6: 4Q | BP6: FY17 | BQ6: 1Q | BR6: 2Q | BS6: 3Q | BT6: 4Q | BU6: FY18* | BV6: 1Q | BW6: 2Q | BX6: 3Q | BY6: 4Q | BZ6: FY19 | CA6: 1Q | CB6: 2Q | CC6: 3Q | CD6: 4Q | CE6: FY20 | CF6: 1Q | CG6: 2Q | CH6: 3Q | CI6: 4Q | CJ6: FY21 | CK6: 1Q | CL6: 2Q | CM6: 3Q | CN6: 4Q | CO6: FY22 | CP6: 1Q | CQ6: 2Q | CR6: 3Q | CS6: 4Q | CT6: FY23 | CU6: 1Q | CV6: 2Q | CW6: 3Q | CX6: 4Q | CY6: FY24 | CZ6: 1Q | DA6: 2Q | DB6: 3Q | DC6: 4Q | DD6: FY25 | DE6: 1Q | DF6: 2Q | DG6: 3QE | DH6: 4QE | DI6: FY26E | DJ6: 1QE | DK6: 2QE | DL6: 3QE | DM6: 4QE | DN6: FY27E | DO6: 1QE | DP6: 2QE | DQ6: 3QE | DR6: 4QE | DS6: FY28E
B7: Consolidated Summary
B8: Sales Summary
B10: Americas | CO10: =CO173 -> 6817.454 | CP10: =CP173 -> 1567.738 | CQ10: =CQ173 -> 1719.773 | CR10: =CR173 -> 1732.398 | CS10: =CS173 -> 2611.738 | CT10: =CT173 -> 7631.647 | CU10: =CU173 -> 1622.264 | CV10: =CV173 -> 1741.433 | ... DS10: =DS173 -> 6312.3848
B11: Mainland China | CO11: =CO236 -> 576.503 | CP11: =CP236 -> 210.068 | CQ11: =CQ236 -> 234.445 | CR11: =CR236 -> 228.595 | CS11: =CS236 -> 290.652 | CT11: =CT236 -> 963.76 | CU11: =CU236 -> 303.786 | CV11: =CV236 -> 314.189 | ... DS11: =DS236 -> 2185.8684
B12: Rest of World | CO12: =CO294 -> 716.561 | CP12: =CP294 -> 222.986 | CQ12: =CQ294 -> 254.947 | CR12: =CR294 -> 243.225 | CS12: =CS294 -> 302.713 | CT12: =CT294 -> 1023.871 | CU12: =CU294 -> 282.841 | CV12: =CV294 -> 315.456 | ... DS12: =DS294 -> 1832.7337
B13: Total sales | C13: =SUM(C28:C32) -> 40.749 | D13: =SUM(D28,D30,D32) -> 15.63 | E13: =SUM(E28,E30,E32) -> 17.126 | F13: =SUM(F28,F30,F32) -> 19.984 | G13: =SUM(G28,G30,G32) -> 31.389093 | H13: =SUM(H28,H30,H32) -> 84.129093 | I13: =SUM(I28,I30,I32) -> 28.184 | J13: =SUM(J28,J30,J32) -> 32.517437 | K13: =SUM(K28,K30,K32) -> 35.967615 | ... CN13: =SUM(CN28,CN30,CN32) -> 2771.838 | CO13: =SUM(CO10:CO12) -> 8110.518 | CP13: =SUM(CP10:CP12) -> 2000.792 | CQ13: =SUM(CQ10:CQ12) -> 2209.165 | CR13: =SUM(CR10:CR12) -> 2204.218 | CS13: =SUM(CS10:CS12) -> 3205.103 | CT13: =SUM(CT10:CT12) -> 9619.278 | CU13: =SUM(CU10:CU12) -> 2208.891 | CV13: =SUM(CV10:CV12) -> 2371.078 | ... DS13: =SUM(DS10:DS12) -> 10330.987
B14: % chg. Y/Y | H14: =H13/C13-1 -> 1.0645683 | I14: =I13/D13-1 -> 0.80319898 | J14: =J13/E13-1 -> 0.89871756 | K14: =K13/F13-1 -> 0.79982061 | L14: =L13/G13-1 -> 0.66350082 | M14: =M13/H13-1 -> 0.76971876 | N14: =N13/I13-1 -> 0.58918024 | O14: =O13/J13-1 -> 0.8045993 | ... DS14: =DS13/DN13-1 -> 0.011164122
B15: 2-yr CAGR | N15: =(N13/D13)^(1/2)-1 -> 0.69281074 | O15: =(O13/E13)^(1/2)-1 -> 0.85106034 | P15: =(P13/F13)^(1/2)-1 -> 0.8193851 | Q15: =(Q13/G13)^(1/2)-1 -> 0.82977119 | R15: =(R13/H13)^(1/2)-1 -> 0.80703582 | S15: =(S13/I13)^(1/2)-1 -> 0.665374 | T15: =(T13/J13)^(1/2)-1 -> 0.62138007 | U15: =(U13/K13)^(1/2)-1 -> 0.55568413 | ... DS15: =(DS13/DI13)^(1/2)-1 -> -0.0064996223
B16: % chg Y/Y, FX-Neutral | N16: =(1+N14)/(1+N17)-1 -> 0.53668153 | O16: =(1+O14)/(1+O17)-1 -> 0.74694139 | P16: =(1+P14)/(1+P17)-1 -> 0.72803168 | Q16: =(1+Q14)/(1+Q17)-1 -> 0.89463292 | R16: =(1+R14)/(1+R17)-1 -> 0.75550409 | S16: =(1+S14)/(1+S17)-1 -> 0.59245964 | T16: =(1+T14)/(1+T17)-1 -> 0.40068033 | U16: =(1+U14)/(1+U17)-1 -> 0.38843312 | ... BN16: =(1+BN14)/(1+BN17)-1 -> 0.12676361 | BO16: 0.16 | BP16: 0.12 | BQ16: 0.23 | BR16: =(1+BR14)/(1+BR17)-1 -> 0.2425465 | BS16: =(1+BS14)/(1+BS17)-1 -> 0.22039475 | BT16: =(1+BT14)/(1+BT17)-1 -> 0.27197347 | BU16: =(1+BU14)/(1+BU17)-1 -> 0.24512601 | BV16: 0.22 | BW16: 0.23 | BX16: 0.23 | BY16: 0.2 | BZ16: =(1+BZ14)/(1+BZ17)-1 -> 0.21924508 | CA16: -0.16 | CB16: 0.03 | CC16: 0.21 | CD16: 0.22 | CE16: =(1+CE14)/(1+CE17)-1 -> 0.10054642 | CF16: 0.83 | CG16: 0.56 | CH16: 0.28 | CI16: 0.23 | CJ16: =(1+CJ14)/(1+CJ17)-1 -> 0.39320819 | CK16: 0.32 | CL16: 0.31 | CM16: 0.31 | CN16: 0.33 | CO16: =(1+CO14)/(1+CO17)-1 -> 0.32520063 | CP16: 0.27 | CQ16: 0.2 | CR16: 0.19 | CS16: 0.16 | CT16: =(1+CT14)/(1+CT17)-1 -> 0.19870163 | CU16: 0.11 | CV16: 0.08 | CW16: 0.08 | CX16: 0.14 | CY16: =(1+CY14)/(1+CY17)-1 -> 0.10671457 | CZ16: 0.08 | DA16: 0.06 | DB16: 0.07 | DC16: 0 | DD16: =(1+DD14)/(1+DD17)-1 -> 0.044865736 | DE16: 0.02 | DF16: -0.05 | DG16: =(1+DG14)/(1+DG17)-1 -> -0.1074336 | DH16: =(1+DH14)/(1+DH17)-1 -> -0.10897737 | DI16: =(1+DI14)/(1+DI17)-1 -> -0.05540147 | DJ16: =(1+DJ14)/(1+DJ17)-1 -> -0.047900587 | DK16: =(1+DK14)/(1+DK17)-1 -> -0.037677383 | DL16: =(1+DL14)/(1+DL17)-1 -> -0.0045097354 | DM16: =(1+DM14)/(1+DM17)-1 -> -0.013100228 | DN16: =(1+DN14)/(1+DN17)-1 -> -0.025114061 | ... DS16: =(1+DS14)/(1+DS17)-1 -> 0.011164122
B17: FX impact | N17: =(N390*I28+N466*I30)/I13 -> 0.034163694 | O17: =(O390*J28+O466*J30)/J13 -> 0.033005061 | P17: =(P390*K28+P466*K30)/K13 -> 0.064310498 | Q17: =(Q390*L28+Q466*L30)/L13 -> 0.06229581 | R17: =SUMPRODUCT(N17:Q17,I13:L13)/M13 -> 0.051059796 | S17: =(S390*N28+S466*N30)/N13 -> 0.095927857 | T17: =(T390*O28+T466*O30)/O13 -> 0.040039532 | U17: =(U390*P28+U466*P30)/P13 -> -0.052241188 | V17: =(V390*Q28+V466*Q30)/Q13 -> -0.13393979 | W17: =SUMPRODUCT(S17:V17,N13:Q13)/R13 -> -0.039625825 | X17: =(X390*S28+X466*S30)/S13 -> -0.1276245 | Y17: =(Y390*T28+Y466*T30)/T13 -> -0.074772122 | Z17: =(Z390*U28+Z466*U30)/U13 -> 0.0081042822 | AA17: =(AA390*V28+AA466*V30)/V13 -> 0.086352225 | AB17: =SUMPRODUCT(X17:AA17,S13:V13)/W13 -> -0.018861492 | AC17: =(AC390*X28+AC466*X30)/X13 -> 0.10451772 | AD17: =(AD390*Y28+AD466*Y30)/Y13 -> 0.046533787 | AE17: =(AE390*Z28+AE466*Z30)/Z13 -> 0.020208833 | AF17: =(AF390*AA28+AF466*AA30)/AA13 -> 0.026909798 | AG17: =SUMPRODUCT(AC17:AF17,X13:AA13)/AB13 -> 0.043470287 | AH17: =(AH390*AC28+AH466*AC30)/AC13 -> 0.021617082 | AI17: =(AI390*AD28+AI466*AD30)/AD13 -> 0.035423018 | AJ17: =(AJ390*AE28+AJ466*AE30)/AE13 -> 0.014044172 | AK17: =(AK390*AF28+AK466*AF30)/AF13 -> -0.0065588035 | AL17: =SUMPRODUCT(AH17:AK17,AC13:AF13)/AG13 -> 0.012983889 | AM17: =(AM390*AH28+AM466*AH30)/AH13 -> -0.0067030731 | AN17: =(AN390*AI28+AN466*AI30)/AI13 -> -0.014598185 | AO17: =(AO390*AJ28+AO466*AJ30)/AJ13 -> 0 | AP17: =(AP390*AK28+AP466*AK30)/AK13 -> 0.0078722621 | AQ17: =SUMPRODUCT(AM17:AP17,AH13:AK13)/AL13 -> -0.0014256315 | AR17: =(AR390*AM28+AR466*AM30)/AM13 -> -0.0080080715 | AS17: =(AS390*AN28+AS466*AN30)/AN13 -> -0.0081842241 | AT17: =(AT390*AO28+AT466*AO30)/AO13 -> -0.023887824 | AU17: =(AU390*AP28+AU466*AP30)/AP13 -> -0.023358138 | AV17: =SUMPRODUCT(AR17:AU17,AM13:AP13)/AQ13 -> -0.017150812 | AW17: =(AW390*AR28+AW466*AR30)/AR13 -> -0.028051547 | AX17: =(AX390*AS28+AX466*AS30)/AS13 -> -0.017326487 | AY17: =(AY390*AT28+AY466*AT30)/AT13 -> -0.018563833 | AZ17: =(AZ390*AU28+AZ466*AU30)/AU13 -> -0.028387291 | BA17: =SUMPRODUCT(AW17:AZ17,AR13:AU13)/AV13 -> -0.023574147 | BB17: =(BB390*AW28+BB466*AW30)/AW13 -> -0.03682355 | BC17: =(BC390*AX28+BC466*AX30)/AX13 -> -0.045753173 | BD17: =(BD390*AY28+BD466*AY30)/AY13 -> -0.053555566 | BE17: =(BE390*AZ28+BE466*AZ30)/AZ13 -> -0.039782628 | BF17: =SUMPRODUCT(BB17:BE17,AW13:AZ13)/BA13 -> -0.043661447 | BG17: =(BG390*BB28+BG466*BB30)/BB13 -> -0.016806377 | BH17: =(BH390*BC28+BH466*BC30)/BC13 -> -0.009315865 | BI17: =(BI390*BD28+BI466*BD30)/BD13 -> 0 | BJ17: =(BJ390*BE28+BJ466*BE30)/BE13 -> 0 | BK17: =SUMPRODUCT(BG17:BJ17,BB13:BE13)/BF13 -> -0.0055026903 | BL17: =(BL390*BG28+BL466*BG30)/BG13 -> -0.0072389993 | BM17: =(BM390*BH28+BM466*BH30)/BH13 -> -0.0013589209 | BN17: =(BN390*BI28+BN466*BI30)/BI13 -> 0.0091385815 | BO17: =(1+BO14)/(1+BO16)-1 -> 0.013586366 | BP17: =(1+BP14)/(1+BP16)-1 -> 0.0089331568 | BQ17: =(1+BQ14)/(1+BQ16)-1 -> 0.015129264 | BR17: =(BR390*BM28+BR466*BM30)/BM13 -> 0.0020961391 | BS17: =(BS390*BN28+BS466*BN30)/BN13 -> -0.010339109 | BT17: =(BT390*BO28+BT466*BO30)/BO13 -> -0.01174853 | BU17: =SUMPRODUCT(BQ17:BT17,BL13:BO13)/BP13 -> -0.0031036939 | BV17: =BV14-BV16 -> -0.015808577 | BW17: -0.01 | BX17: =-6.8/BS13 -> -0.009095104 | BY17: =-0.3/BT13 -> -0.00025695843 | BZ17: =SUMPRODUCT(BV17:BY17,BQ13:BT13)/BU13 -> -0.0074826074 | CA17: -0.01 | CB17: -0.01 | CC17: 0.01 | CD17: 0.02 | CE17: =SUMPRODUCT(CA17:CD17,BV13:BY13)/BZ13 -> 0.0051402256 | CF17: 0.05 | CG17: 0.05 | CH17: 0.01 | CI17: 0 | CJ17: =SUMPRODUCT(CF17:CI17,CA13:CD13)/CE13 -> 0.020200308 | CK17: 0 | CL17: -0.02 | CM17: -0.03 | CN17: -0.03 | CO17: =SUMPRODUCT(CK17:CN17,CF13:CI13)/CJ13 -> -0.021800607 | CP17: -0.03 | CQ17: -0.02 | CR17: 0 | CS17: 0 | CT17: =SUMPRODUCT(CP17:CS17,CK13:CN13)/CO13 -> -0.010575212 | CU17: -0.01 | CV17: -0.01 | CW17: 0.01 | CX17: -0.01 | CY17: =SUMPRODUCT(CU17:CX17,CP13:CS13)/CT13 -> -0.0054170822 | CZ17: -0.01 | DA17: 0.01 | DB17: 0 | DC17: 0.01 | DD17: =SUMPRODUCT(CZ17:DC17,CU13:CX13)/CY13 -> 0.0035640717 | DE17: -0.02 | DF17: -0.01 | DG17: =(DG176*DB173+DG239*DB236+DG297*DB294)/DB13 -> 0.01106312 | DH17: =(DH176*DC173+DH239*DC236+DH297*DC294)/DC13 -> 0.0060853914 | DI17: =SUMPRODUCT(DE17:DH17,CZ13:DC13)/DD13 -> -0.0019925611 | DJ17: =(DJ176*DE173+DJ239*DE236+DJ297*DE294)/DE13 -> 0.0033334884 | DK17: =(DK176*DF173+DK239*DF236+DK297*DF294)/DF13 -> 0.0021860239 | DL17: =(DL176*DG173+DL239*DG236+DL297*DG294)/DG13 -> 0 | DM17: =(DM176*DH173+DM239*DH236+DM297*DH294)/DH13 -> 0 | DN17: =SUMPRODUCT(DJ17:DM17,DE13:DH13)/DI13 -> 0.0012916977 | DO17: =(DO176*DJ173+DO239*DJ236+DO297*DJ294)/DJ13 -> 0 | DP17: =(DP176*DK173+DP239*DK236+DP297*DK294)/DK13 -> 0 | DQ17: =(DQ176*DL173+DQ239*DL236+DQ297*DL294)/DL13 -> 0 | DR17: =(DR176*DM173+DR239*DM236+DR297*DM294)/DM13 -> 0 | DS17: =SUMPRODUCT(DO17:DR17,DJ13:DM13)/DN13 -> 0
B19: Comp Store Sales ex-FX | C19: =C388 -> 0.18 | D19: =D388 -> 0.22 | E19: =E388 -> 0.09 | F19: =F388 -> 0.21 | G19: =G388 -> 0.22 | H19: =H388 -> 0.19 | I19: =I388 -> 0.15 | J19: =J388 -> 0.32 | ... CT19: =CT388 -> 0.094906819
B20: Comp Direct Sales ex-FX | AW20: =AW465 -> 0.26029672 | AX20: =AX465 -> 0.29882987 | AY20: =AY465 -> 0.27156554 | AZ20: =AZ465 -> 0.20723718 | BA20: =BA465 -> 0.25046337 | BB20: =BB465 -> 0.32053284 | BC20: =BC465 -> 0.36326564 | BD20: =BD465 -> 0.2179783 | ... BS20: =BS465 -> 0.46 | BT20: 0.39 | BU20: =BU465 -> 0.4928278 | BV20: =BV465 -> 0.35 | BW20: =BW465 -> 0.31 | BX20: =BX465 -> 0.3 | BY20: =BY465 -> 0.34665269 | BZ20: =BZ465 -> 0.32983702 | CA20: =CA465 -> 0.7 | CB20: =CB465 -> 1.57 | ... CT20: =CT465 -> 0.17609752
B21: Americas Comp ex-FX | CS21: =CS179 -> 0.07 | CT21: =CT179 -> 0.09 | CU21: =CU179 -> 0 | CV21: =CV179 -> -0.02 | CW21: =CW179 -> -0.02 | CX21: =CX179 -> 0 | CY21: =CY179 -> -0.01 | CZ21: =CZ179 -> -0.01 | ... DS21: =DS179 -> -0.04
B22: Mainland China Comp ex-FX | CS22: =CS242 -> 0.6 | CT22: =CT242 -> 0.46 | CU22: =CU242 -> 0.33 | CV22: =CV242 -> 0.23 | CW22: =CW242 -> 0.24 | CX22: =CX242 -> 0.27 | CY22: =CY242 -> 0.27 | CZ22: =CZ242 -> 0.08 | ... DS22: =DS242 -> 0.04
B23: Rest of World Comp ex-FX | CS23: =CS300 -> 0.31 | CT23: =CT300 -> 0.33 | CU23: =CU300 -> 0.4 | CV23: =CV300 -> 0.2 | CW23: =CW300 -> 0.2 | CX23: =CX300 -> 0.17 | CY23: =CY300 -> 0.2 | CZ23: =CZ300 -> 0.07 | ... DS23: =DS300 -> 0.06
B24: Comp Sales ex-FX: Calced | C24: =C19 -> 0.18 | D24: =D19 -> 0.22 | E24: =E19 -> 0.09 | F24: =F19 -> 0.21 | G24: =G19 -> 0.22 | H24: =H19 -> 0.19 | I24: =I19 -> 0.15 | J24: =J19 -> 0.32 | ... AB24: =AB19 -> 0.08356852 | AC24: =(X28/(X28+X30))*AC19+(X30/(X30+X28))*AC462 -> 0.45911728 | AD24: =(Y28/(Y28+Y30))*AD19+(Y30/(Y30+Y28))*AD462 -> 0.37748578 | AE24: =(Z28/(Z28+Z30))*AE19+(Z30/(Z30+Z28))*AE462 -> 0.36802542 | AF24: =(AA28/(AA28+AA30))*AF19+(AA30/(AA30+AA28))*AF462 -> 0.37439673 | AG24: =(AC24*(X30+X28)+AD24*(Y30+Y28)+AE24*(Z30+Z28)+AF24*(AA30+AA28))/(AB30+AB28) -> 0.3885399 | AH24: =(AC28/(AC28+AC30))*AH19+(AC30/(AC30+AC28))*AH462 -> 0.18592485 | AI24: =(AD28/(AD28+AD30))*AI19+(AD30/(AD30+AD28))*AI462 -> 0.25093525 | AJ24: =(AE28/(AE28+AE30))*AJ19+(AE30/(AE30+AE28))*AJ462 -> 0.21335888 | AK24: =(AF28/(AF28+AF30))*AK19+(AF30/(AF30+AF28))*AK462 -> 0.33509235 | AL24: =(AH24*(AC30+AC28)+AI24*(AD30+AD28)+AJ24*(AE30+AE28)+AK24*(AF30+AF28))/(AG30+AG28) -> 0.2588776 | AM24: =(AH28/(AH28+AH30))*AM19+(AH30/(AH30+AH28))*AM462 -> 0.37429331 | AN24: =(AI28/(AI28+AI30))*AN19+(AI30/(AI30+AI28))*AN462 -> 0.22129248 | AO24: =(AJ28/(AJ28+AJ30))*AO19+(AJ30/(AJ30+AJ28))*AO462 -> 0.25909647 | AP24: =(AK28/(AK28+AK30))*AP19+(AK30/(AK30+AK28))*AP462 -> 0.16769414 | AQ24: =(AM24*(AH30+AH28)+AN24*(AI30+AI28)+AO24*(AJ30+AJ28)+AP24*(AK30+AK28))/(AL30+AL28) -> 0.23838269 | AR24: =(AM28/(AM28+AM30))*AR19+(AM30/(AM30+AM28))*AR462 -> 0.11800517 | AS24: =(AN28/(AN28+AN30))*AS19+(AN30/(AN30+AN28))*AS462 -> 0.11304803 | AT24: =(AO28/(AO28+AO30))*AT19+(AO30/(AO30+AO28))*AT462 -> 0.099049359 | AU24: =(AP28/(AP28+AP30))*AU19+(AP30/(AP30+AP28))*AU462 -> 0.026115547 | AV24: =(AR24*(AM30+AM28)+AS24*(AN30+AN28)+AT24*(AO30+AO28)+AU24*(AP30+AP28))/(AQ30+AQ28) -> 0.080033484 | AW24: =(AR28/(AR28+AR30))*AW19+(AR30/(AR30+AR28))*AW465 -> 0.010123446 | AX24: =(AS28/(AS28+AS30))*AX19+(AS30/(AS30+AS28))*AX465 -> 0.0033080846 | AY24: =(AT28/(AT28+AT30))*AY19+(AT30/(AT30+AT28))*AY465 -> 0.022983924 | AZ24: =(AU28/(AU28+AU30))*AZ19+(AU30/(AU30+AU28))*AZ465 -> 0.081186154 | BA24: =(AW24*(AR30+AR28)+AX24*(AS30+AS28)+AY24*(AT30+AT28)+AZ24*(AU30+AU28))/(AV30+AV28) -> 0.035165893 | BB24: =(AW28/(AW28+AW30))*BB19+(AW30/(AW30+AW28))*BB465 -> 0.055655803 | BC24: =(AX28/(AX28+AX30))*BC19+(AX30/(AX30+AX28))*BC465 -> 0.11386074 | BD24: =(AY28/(AY28+AY30))*BD19+(AY30/(AY30+AY28))*BD465 -> 0.091497581 | BE24: =(AZ28/(AZ28+AZ30))*BE19+(AZ30/(AZ30+AZ28))*BE465 -> 0.10923209 | BF24: =(BB24*(AW30+AW28)+BC24*(AX30+AX28)+BD24*(AY30+AY28)+BE24*(AZ30+AZ28))/(BA30+BA28) -> 0.094746543 | BG24: =(BB28/(BB28+BB30))*BG19+(BB30/(BB30+BB28))*BG465 -> 0.076987442 | BH24: =(BC28/(BC28+BC30))*BH19+(BC30/(BC30+BC28))*BH465 -> 0.04652403 | BI24: =(BD28/(BD28+BD30))*BI19+(BD30/(BD30+BD28))*BI465 -> 0.065093906 | BJ24: =(BE28/(BE28+BE30))*BJ19+(BE30/(BE30+BE28))*BJ465 -> 0.074052804 | BK24: =(BG24*(BB30+BB28)+BH24*(BC30+BC28)+BI24*(BD30+BD28)+BJ24*(BE30+BE28))/(BF30+BF28) -> 0.066535624 | BL24: =(BG28/(BG28+BG30))*BL19+(BG30/(BG30+BG28))*BL465 -> -0.0086134087 | BM24: =(BH28/(BH28+BH30))*BM19+(BH30/(BH30+BH28))*BM465 -> 0.072931614 | BN24: =(BI28/(BI28+BI30))*BN19+(BI30/(BI30+BI28))*BN465 -> 0.059905729 | BO24: =(BJ28/(BJ28+BJ30))*BO19+(BJ30/(BJ30+BJ28))*BO465 -> 0.10101447 | BP24: =(BL24*(BG30+BG28)+BM24*(BH30+BH28)+BN24*(BI30+BI28)+BO24*(BJ30+BJ28))/(BK30+BK28) -> 0.062251263 | BQ24: =(BL28/(BL28+BL30))*BQ19+(BL30/(BL30+BL28))*BQ465 -> 0.17022044 | BR24: =(BM28/(BM28+BM30))*BR19+(BM30/(BM30+BM28))*BR465 -> 0.17937132 | BS24: =(BN28/(BN28+BN30))*BS19+(BN30/(BN30+BN28))*BS465 -> 0.16196897 | BT24: =(BO28/(BO28+BO30))*BT19+(BO30/(BO30+BO28))*BT20 -> 0.15837575 | BU24: =(BQ24*(BL30+BL28)+BR24*(BM30+BM28)+BS24*(BN30+BN28)+BT24*(BO30+BO28))/(BP30+BP28) -> 0.16612236 | BV24: =(BQ28/(BQ28+BQ30))*BV19+(BQ30/(BQ30+BQ28))*BV465 -> 0.15210783 | BW24: =(BR28/(BR28+BR30))*BW19+(BR30/(BR30+BR28))*BW465 -> 0.16120832 | BX24: =(BS28/(BS28+BS30))*BX19+(BS30/(BS30+BS28))*BX465 -> 0.16400547 | BY24: =(BT28/(BT28+BT30))*BY19+(BT30/(BT30+BT28))*BY465 -> 0.17225032 | BZ24: =(BV24*(BQ30+BQ28)+BW24*(BR30+BR28)+BX24*(BS30+BS28)+BY24*(BT30+BT28))/(BU30+BU28) -> 0.16400455 | CA24: =(BV28/(BV28+BV30))*CA19+(BV30/(BV30+BV28))*CA465 -> -0.14235111 | CB24: =(BW28/(BW28+BW30))*CB19+(BW30/(BW30+BW28))*CB465 -> 0.045590332 | CC24: =(BX28/(BX28+BX30))*CC19+(BX30/(BX30+BX28))*CC465 -> 0.15144154 | CD24: =(BY28/(BY28+BY30))*CD19+(BY30/(BY30+BY28))*CD465 -> 0.14317066 | CE24: =(CA24*(BV30+BV28)+CB24*(BW30+BW28)+CC24*(BX30+BX28)+CD24*(BY30+BY28))/(BZ30+BZ28) -> 0.0673567 | CF24: =(CA28/(CA28+CA30))*CF19+(CA30/(CA30+CA28))*CF465 -> 0.69646137 | CG24: =(CB28/(CB28+CB30))*CG19+(CB30/(CB30+CB28))*CG465 -> 0.44784789 | CH24: =(CC28/(CC28+CC30))*CH19+(CC30/(CC30+CC28))*CH465 -> 0.26169153 | CI24: =(CD28/(CD28+CD30))*CI19+(CD30/(CD30+CD28))*CI465 -> 0.22401517 | CJ24: =(CF24*(CA30+CA28)+CG24*(CB30+CB28)+CH24*(CC30+CC28)+CI24*(CD30+CD28))/(CE30+CE28) -> 0.35457901 | CK24: =(CF28/(CF28+CF30))*CK19+(CF30/(CF30+CF28))*CK465 -> 0.28535428 | CL24: =(CG28/(CG28+CG30))*CL19+(CG30/(CG30+CG28))*CL465 -> 0.24470922 | CM24: =(CH28/(CH28+CH30))*CM19+(CH30/(CH30+CH28))*CM465 -> 0.24707382 | CN24: =(CI28/(CI28+CI30))*CN19+(CI30/(CI30+CI28))*CN465 -> 0.28946847 | CO24: =(CK24*(CF30+CF28)+CL24*(CG30+CG28)+CM24*(CH30+CH28)+CN24*(CI30+CI28))/(CJ30+CJ28) -> 0.26854692 | CP24: =(CK28/(CK28+CK30))*CP19+(CK30/(CK30+CK28))*CP465 -> 0.16992875 | CQ24: =(CL28/(CL28+CL30))*CQ19+(CL30/(CL30+CL28))*CQ465 -> 0.12695795 | CR24: =(CM28/(CM28+CM30))*CR19+(CM30/(CM30+CM28))*CR465 -> 0.13593786 | CS24: =(CN28/(CN28+CN30))*CS19+(CN30/(CN30+CN28))*CS465 -> 0.12202853 | CT24: =(CP24*(CK30+CK28)+CQ24*(CL30+CL28)+CR24*(CM30+CM28)+CS24*(CN30+CN28))/(CO30+CO28) -> 0.1357876 | CU24: =((CU21*CP10)+(CU22*CP11)+(CU23*CP12))/CP13 -> 0.079227046 | CV24: =((CV21*CQ10)+(CV22*CQ11)+(CV23*CQ12))/CQ13 -> 0.031919884 | CW24: =((CW21*CR10)+(CW22*CR11)+(CW23*CR12))/CR13 -> 0.031240032 | CX24: =((CX21*CS10)+(CX22*CS11)+(CX23*CS12))/CS13 -> 0.040540741 | CY24: =(SUMPRODUCT(CU21:CX21,CP10:CS10)+SUMPRODUCT(CU22:CX22,CP11:CS11)+SUMPRODUCT(CU23:CX23,CP12:CS12))/CT13 -> 0.044476334 | CZ24: =((CZ21*CU10)+(CZ22*CU11)+(CZ23*CU12))/CU13 -> 0.012621315 | DA24: =((DA21*CV10)+(DA22*CV11)+(DA23*CV12))/CV13 -> 0.01114189 | DB24: =((DB21*CW10)+(DB22*CW11)+(DB23*CW12))/CW13 -> 0.019399748 | DC24: =((DC21*CX10)+(DC22*CX11)+(DC23*CX12))/CX13 -> 0.020557819 | DD24: =(SUMPRODUCT(CZ21:DC21,CU10:CX10)+SUMPRODUCT(CZ22:DC22,CU11:CX11)+SUMPRODUCT(CZ23:DC23,CU12:CX12))/CY13 -> 0.016531396 | DE24: =((DE21*CZ10)+(DE22*CZ11)+(DE23*CZ12))/CZ13 -> -0.020812913 | DF24: =((DF21*DA10)+(DF22*DA11)+(DF23*DA12))/DA13 -> -0.10044317 | DG24: =((DG21*DB10)+(DG22*DB11)+(DG23*DB12))/DB13 -> -0.12896818 | DH24: =((DH21*DC10)+(DH22*DC11)+(DH23*DC12))/DC13 -> -0.12666379 | DI24: =(SUMPRODUCT(DE21:DH21,CZ10:DC10)+SUMPRODUCT(DE22:DH22,CZ11:DC11)+SUMPRODUCT(DE23:DH23,CZ12:DC12))/DD13 -> -0.098631045 | DJ24: =((DJ21*DE10)+(DJ22*DE11)+(DJ23*DE12))/DE13 -> -0.068120487 | DK24: =((DK21*DF10)+(DK22*DF11)+(DK23*DF12))/DF13 -> -0.055331833 | DL24: =((DL21*DG10)+(DL22*DG11)+(DL23*DG12))/DG13 -> -0.023942657 | DM24: =((DM21*DH10)+(DM22*DH11)+(DM23*DH12))/DH13 -> -0.02986078 | DN24: =(SUMPRODUCT(DJ21:DM21,DE10:DH10)+SUMPRODUCT(DJ22:DM22,DE11:DH11)+SUMPRODUCT(DJ23:DM23,DE12:DH12))/DI13 -> -0.043464766 | DO24: =((DO21*DJ10)+(DO22*DJ11)+(DO23*DJ12))/DJ13 -> -0.0068921198 | DP24: =((DP21*DK10)+(DP22*DK11)+(DP23*DK12))/DK13 -> -0.0077703764 | DQ24: =((DQ21*DL10)+(DQ22*DL11)+(DQ23*DL12))/DL13 -> -0.0046214173 | DR24: =((DR21*DM10)+(DR22*DM11)+(DR23*DM12))/DM13 -> -0.011105308 | DS24: =(SUMPRODUCT(DO21:DR21,DJ10:DM10)+SUMPRODUCT(DO22:DR22,DJ11:DM11)+SUMPRODUCT(DO23:DR23,DJ12:DM12))/DN13 -> -0.0079083291
B25: Comp Sales ex-FX: Reported | BB25: 0.06 | BC25: 0.11 | BD25: 0.09 | BE25: 0.11 | BF25: 0.1 | BG25: 0.08 | BH25: 0.05 | BI25: 0.07 | BJ25: 0.07 | BK25: 0.07 | BL25: -0.01 | BM25: 0.07 | BN25: 0.07 | BO25: 0.11 | BP25: 0.07 | BQ25: 0.19 | BR25: 0.19 | BS25: 0.18 | BT25: 0.17 | BU25: 0.18 | BV25: 0.16 | BW25: 0.17 | BX25: 0.17 | BY25: 0.2 | BZ25: 0.18 | CA25: -- | CB25: -- | CC25: 0.18 | CD25: 0.2 | CF25: -- | CG25: -- | CH25: 0.27 | CI25: 0.22 | CJ25: -- | CK25: 0.29 | CL25: 0.25 | CM25: 0.25 | CN25: 0.3 | CP25: 0.17 | CQ25: 0.13 | CR25: 0.14 | CS25: 0.12 | CU25: 0.07 | CV25: 0.03 | CW25: 0.03 | CX25: 0.04 | CZ25: 0.01 | DA25: 0.01 | DB25: 0.02 | DC25: 0.02 | DE25: -0.02 | DF25: -0.1
B27: Channel Sales:
B28: Stores | C28: =C383 -> 29.906 | D28: =D383 -> 11.052 | E28: =E383 -> 13.455 | F28: =F383 -> 15.62 | G28: =G383 -> 25.45 | H28: =SUM(D28:G28) -> 65.577 | I28: =I383 -> 22.146 | J28: =J383 -> 26.831 | K28: =K383 -> 29.145 | L28: =L383 -> 42.612 | M28: =SUM(I28:L28) -> 120.734 | N28: =N383 -> 38.008 | O28: =O383 -> 53.1 | P28: =P383 -> 59.9 | Q28: =Q383 -> 92.5 | R28: =SUM(N28:Q28) -> 243.508 | S28: =S383 -> 70.6 | T28: =T383 -> 78.3 | U28: =U383 -> 77.6 | V28: =V383 -> 89.047803 | W28: =SUM(S28:V28) -> 315.5478 | X28: =X383 -> 72.031 | Y28: =Y383 -> 85.1 | Z28: =Z383 -> 98.1 | AA28: =AA383 -> 138.3 | AB28: =SUM(X28:AA28) -> 393.531 | AC28: =AC383 -> 115.597 | AD28: =AD383 -> 129.4 | AE28: =AE383 -> 143.2 | AF28: =AF383 -> 202.8 | AG28: =SUM(AC28:AF28) -> 590.997 | AH28: =AH383 -> 156.5 | AI28: =AI383 -> 178.223 | AJ28: =AJ383 -> 190.016 | AK28: =AK383 -> 292.47028 | AL28: =SUM(AH28:AK28) -> 817.20928 | AM28: =AM383 -> 228.789 | AN28: =AN383 -> 231.314 | AO28: =AO383 -> 252.046 | AP28: =AP383 -> 378.032 | AQ28: =SUM(AM28:AP28) -> 1090.181 | AR28: =AR383 -> 269.357 | AS28: =AS383 -> 273.768 | AT28: =AT383 -> 290.666 | AU28: =AU383 -> 395.208 | AV28: =SUM(AR28:AU28) -> 1228.999 | AW28: =AW383 -> 288.101 | AX28: =AX383 -> 294.04 | AY28: =AY383 -> 310.014 | AZ28: =AZ383 -> 456.07 | BA28: =SUM(AW28:AZ28) -> 1348.225 | BB28: =BB383 -> 314.094 | BC28: =BC383 -> 339.779 | BD28: =BD383 -> 353.399 | BE28: =BE383 -> 509.051 | BF28: =SUM(BB28:BE28) -> 1516.323 | BG28: =BG383 -> 358.704 | BH28: =BH383 -> 381.389 | BI28: =BI383 -> 393.506 | BJ28: =BJ383 -> 570.758 | BK28: =SUM(BG28:BJ28) -> 1704.357 | BL28: =BL383 -> 379.099 | BM28: =BM383 -> 413.944 | BN28: =BN383 -> 425.1 | BO28: =BO383 -> 618.9 | BP28: =SUM(BL28:BO28) -> 1837.043 | BQ28: =BQ383 -> 433.12 | BR28: =BR383 -> 486.4 | BS28: =BS383 -> 476.877 | BT28: =BT383 -> 729.966 | BU28: =SUM(BQ28:BT28) -> 2126.363 | BV28: =BV383 -> 506.422 | BW28: =BW383 -> 583.756 | BX28: =BX383 -> 579.5 | BY28: =BY383 -> 831.4 | BZ28: =SUM(BV28:BY28) -> 2501.078 | CA28: =CA383 -> 259.97 | CB28: =CB383 -> 287.2 | CC28: =CC383 -> 511.756 | CD28: =CD383 -> 599.881 | CE28: =SUM(CA28:CD28) -> 1658.807 | CF28: =CF383 -> 536.584 | CG28: =CG383 -> 695.12 | CH28: =CH383 -> 707.16 | CI28: =CI383 -> 882.633 | CJ28: =SUM(CF28:CI28) -> 2821.497 | CK28: =CK383 -> 731.604 | CL28: =CL383 -> 903.077 | CM28: =CM383 -> 903.06 | CN28: =CN383 -> 1110.386 | CO28: =SUM(CK28:CN28) -> 3648.127 | CP28: =CP383 -> 958.087 | CQ28: =CQ383 -> 1096.939 | CR28: =CR383 -> 1073.973 | CS28: =CS383 -> 1281.957 | CT28: =SUM(CP28:CS28) -> 4410.956 | CU28: 1070.525 | CV28: 1215.613 | CW28: 1210.523 | CX28: 1511.211 | CY28: =SUM(CU28:CX28) -> 5007.872 | CZ28: 1153.107 | DA28: 1254.952 | DB28: 1206.558 | DC28: =DD28-CZ28-DA28-DB28 -> 1435.127 | DD28: 5049.744 | DE28: 1192.84 | DF28: 1173.747
B29: % chg. Y/Y | H29: =H28/C28-1 -> 1.1927707 | I29: =I28/D28-1 -> 1.0038002 | J29: =J28/E28-1 -> 0.99412858 | K29: =K28/F28-1 -> 0.86587708 | L29: =L28/G28-1 -> 0.67434185 | M29: =M28/H28-1 -> 0.84110283 | N29: =N28/I28-1 -> 0.71624673 | O29: =O28/J28-1 -> 0.97905408 | ... DF29: =DF28/DA28-1 -> -0.064707654
B30: Direct | C30: =C461 -> 0 | D30: =D461 -> 0 | E30: =E461 -> 0 | F30: =F461 -> 0 | G30: =G461 -> 0 | H30: =SUM(D30:G30) -> 0 | I30: =I461 -> 0 | J30: =J461 -> 0 | K30: =K461 -> 0 | L30: =L461 -> 0 | M30: =SUM(I30:L30) -> 0 | N30: =N461 -> 0 | O30: =O461 -> 0 | P30: =P461 -> 0 | Q30: =Q461 -> 0 | R30: =SUM(N30:Q30) -> 0 | S30: =S461 -> 0 | T30: =T461 -> 0 | U30: =U461 -> 0 | V30: =V461 -> 0 | W30: =SUM(S30:V30) -> 0 | X30: =X461 -> 0.869 | Y30: =Y461 -> 2.8 | Z30: =Z461 -> 4.2 | AA30: =AA461 -> 8.4 | AB30: =SUM(X30:AA30) -> 16.269 | AC30: =AC461 -> 9.1278 | AD30: =AD461 -> 9.6 | AE30: =AE461 -> 13.4 | AF30: =AF461 -> 24.6 | AG30: =SUM(AC30:AF30) -> 56.7278 | AH30: =AH461 -> 13.82172 | AI30: =AI461 -> 18.6 | AJ30: =AJ461 -> 23.9 | AK30: =AK461 -> 50.1 | AL30: =SUM(AH30:AK30) -> 106.42172 | AM30: =AM461 -> 38.447 | AN30: =AN461 -> 35.422 | AO30: =AO461 -> 45.122 | AP30: =AP461 -> 78.3 | AQ30: =SUM(AM30:AP30) -> 197.291 | AR30: =AR461 -> 53.967 | AS30: =AS461 -> 49.384 | AT30: =AT461 -> 61.954 | AU30: =AU461 -> 97.778 | AV30: =SUM(AR30:AU30) -> 263.083 | AW30: =AW461 -> 65.974 | AX30: =AX461 -> 63.5 | AY30: =AY461 -> 77.203 | AZ30: =AZ461 -> 114.5 | BA30: =SUM(AW30:AZ30) -> 321.177 | BB30: =BB461 -> 83.636 | BC30: =BC461 -> 82.239 | BD30: =BD461 -> 89.33 | BE30: =BE461 -> 146.32 | BF30: =SUM(BB30:BE30) -> 401.525 | BG30: =BG461 -> 97.566 | BH30: =BH461 -> 87.399 | BI30: =BI461 -> 104.013 | BJ30: =BJ461 -> 164.309 | BK30: =SUM(BG30:BJ30) -> 453.287 | BL30: =BL461 -> 97.223 | BM30: =BM461 -> 113.049 | BN30: =BN461 -> 131.181 | BO30: =BO461 -> 236.14 | BP30: =SUM(BL30:BO30) -> 577.593 | BQ30: =BQ461 -> 157.82 | BR30: =BR461 -> 167.4 | BS30: =BS461 -> 189.375 | BT30: =BT461 -> 344.261 | BU30: =SUM(BQ30:BT30) -> 858.856 | BV30: =BV461 -> 209.844 | BW30: =BW461 -> 217.636 | BX30: =BX461 -> 246.7 | BY30: =BY461 -> 463.6 | BZ30: =SUM(BV30:BY30) -> 1137.78 | CA30: =CA461 -> 352.039 | CB30: =CB461 -> 554.3 | CC30: =CC461 -> 478.263 | CD30: =CD461 -> 899.466 | CE30: =SUM(CA30:CD30) -> 2284.068 | CF30: =CF461 -> 545.1 | CG30: =CG461 -> 597.426 | CH30: =CH461 -> 586.525 | CI30: =CI461 -> 1048.893 | CJ30: =SUM(CF30:CI30) -> 2777.944 | CK30: =CK461 -> 721.253 | CL30: =CL461 -> 775.425 | CM30: =CM461 -> 767.351 | CN30: =CN461 -> 1435.762 | CO30: =SUM(CK30:CN30) -> 3699.791 | CP30: =CP461 -> 834.942 | CQ30: =CQ461 -> 893.673 | CR30: =CR461 -> 908.127 | CS30: =CS461 -> 1674.368 | CT30: =SUM(CP30:CS30) -> 4311.11 | CU30: 905.787 | CV30: 910.637 | CW30: 944.777 | CX30: 1809.245 | CY30: =SUM(CU30:CX30) -> 4570.446 | CZ30: 960.89 | DA30: 993.093 | DB30: 1066.75 | DC30: =DD30-CZ30-DA30-DB30 -> 1897.964 | DD30: 4918.697 | DE30: 997.442 | DF30: 934.63
B31: % chg. Y/Y | H31: =IFERROR(H30/C30-1,"--") -> -- | I31: =IFERROR(I30/D30-1,"--") -> -- | J31: =IFERROR(J30/E30-1,"--") -> -- | K31: =IFERROR(K30/F30-1,"--") -> -- | L31: =IFERROR(L30/G30-1,"--") -> -- | M31: =IFERROR(M30/H30-1,"--") -> -- | N31: =IFERROR(N30/I30-1,"--") -> -- | O31: =IFERROR(O30/J30-1,"--") -> -- | ... DF31: =IFERROR(DF30/DA30-1,"--") -> -0.058869612
B32: Other | C32: =C476 -> 10.843 | D32: =D476 -> 4.578 | E32: =E476 -> 3.671 | F32: =F476 -> 4.364 | G32: =G476 -> 5.939093 | H32: =SUM(D32:G32) -> 18.552093 | I32: =I476 -> 6.038 | J32: =J476 -> 5.686437 | K32: =K476 -> 6.822615 | L32: =L476 -> 9.603782 | M32: =SUM(I32:L32) -> 28.150834 | N32: =N476 -> 6.781456 | O32: =O476 -> 5.580944 | P32: =P476 -> 6.25028 | Q32: =Q476 -> 12.592648 | R32: =SUM(N32:Q32) -> 31.205328 | S32: =S476 -> 7.567494 | T32: =T476 -> 7.184223 | U32: =U476 -> 9.447135 | V32: =V476 -> 14.873197 | W32: =SUM(S32:V32) -> 39.072049 | X32: =X476 -> 8.78 | Y32: =Y476 -> 9.821 | Z32: =Z476 -> 10.591 | AA32: =AA476 -> 13.906 | AB32: =SUM(X32:AA32) -> 43.098 | AC32: =AC476 -> 13.5722 | AD32: =AD476 -> 13.208 | AE32: =AE476 -> 19.2 | AF32: =AF476 -> 17.999 | AG32: =SUM(AC32:AF32) -> 63.9792 | AH32: =AH476 -> 16.45828 | AI32: =AI476 -> 15.5 | AJ32: =AJ476 -> 16.3 | AK32: =AK476 -> 28.94972 | AL32: =SUM(AH32:AK32) -> 77.208 | AM32: =AM476 -> 18.462 | AN32: =AN476 -> 15.898 | AO32: =AO476 -> 19.369 | AP32: =AP476 -> 29.193 | AQ32: =SUM(AM32:AP32) -> 82.922 | AR32: =AR476 -> 22.458 | AS32: =AS476 -> 21.361 | AT32: =AT476 -> 27.28 | AU32: =AU476 -> 28.007 | AV32: =SUM(AR32:AU32) -> 99.106 | AW32: =AW476 -> 30.543 | AX32: =AX476 -> 33.187 | AY32: =AY476 -> 32.179 | AZ32: =AZ476 -> 31.899 | BA32: =SUM(AW32:AZ32) -> 127.808 | BB32: =BB476 -> 25.814 | BC32: =BC476 -> 30.992 | BD32: =BD476 -> 36.964 | BE32: =BE476 -> 48.905 | BF32: =SUM(BB32:BE32) -> 142.675 | BG32: =BG476 -> 39.246 | BH32: =BH476 -> 45.732 | BI32: =BI476 -> 46.897 | BJ32: =BJ476 -> 54.873 | BK32: =SUM(BG32:BJ32) -> 186.748 | BL32: =BL476 -> 43.985 | BM32: =BM476 -> 54.061 | BN32: =BN476 -> 62.753 | BO32: =BO476 -> 73.74 | BP32: =SUM(BL32:BO32) -> 234.539 | BQ32: =BQ476 -> 58.72 | BR32: =BR476 -> 69.7 | BS32: =BS476 -> 81.403 | BT32: =BT476 -> 93.277 | BU32: =SUM(BQ32:BT32) -> 303.1 | BV32: =BV476 -> 66.049 | BW32: =BW476 -> 81.96 | BX32: =BX476 -> 89.9 | BY32: =BY476 -> 102.5 | BZ32: =SUM(BV32:BY32) -> 340.409 | CA32: =CA476 -> 39.953 | CB32: =CB476 -> 61.439 | CC32: =CC476 -> 127.407 | CD32: =CD476 -> 230.205 | CE32: =SUM(CA32:CD32) -> 459.004 | CF32: =CF476 -> 144.792 | CG32: =CG476 -> 158.072 | CH32: =CH476 -> 156.736 | CI32: =CI476 -> 197.576 | CJ32: =SUM(CF32:CI32) -> 657.176 | CK32: =CK476 -> 160.606 | CL32: =CL476 -> 189.826 | CM32: =CM476 -> 186.478 | CN32: =CN476 -> 225.69 | CO32: =SUM(CK32:CN32) -> 762.6 | CP32: =CP476 -> 207.763 | CQ32: =CQ476 -> 218.553 | CR32: =CR476 -> 222.118 | CS32: =CS476 -> 248.778 | CT32: =SUM(CP32:CS32) -> 897.212 | CU32: 232.579 | CV32: 244.828 | CW32: 241.36 | CX32: 291.041 | CY32: =SUM(CU32:CX32) -> 1009.808 | CZ32: 256.663 | DA32: 277.174 | DB32: 292.612 | DC32: =DD32-CZ32-DA32-DB32 -> 307.71 | DD32: 1134.159 | DE32: 281.321 | DF32: 307.254
B33: % chg. Y/Y | H33: =H32/C32-1 -> 0.71097418 | I33: =I32/D32-1 -> 0.31891656 | J33: =J32/E32-1 -> 0.5490158 | K33: =K32/F32-1 -> 0.56338566 | L33: =L32/G32-1 -> 0.61704523 | M33: =M32/H32-1 -> 0.51739397 | N33: =N32/I32-1 -> 0.12312951 | O33: =O32/J32-1 -> -0.018551687 | ... DF33: =DF32/DA32-1 -> 0.10852389
B34: Total | C34: =C28+C30+C32 -> 40.749 | D34: =D28+D30+D32 -> 15.63 | E34: =E28+E30+E32 -> 17.126 | F34: =F28+F30+F32 -> 19.984 | G34: =G28+G30+G32 -> 31.389093 | H34: =H28+H30+H32 -> 84.129093 | I34: =I28+I30+I32 -> 28.184 | J34: =J28+J30+J32 -> 32.517437 | ... DF34: =DF28+DF30+DF32 -> 2415.631
B36: Category Sales:
B37: Women's | BP37: 1892.624 | BU37: 2352.788 | BV37: 562.983 | BW37: 616.197 | BX37: 650.269 | BY37: =BZ37-SUM(BV37:BX37) -> 961.548 | BZ37: 2790.997 | CA37: 480.313 | CB37: 649.31 | CC37: 791.946 | CD37: =CE37-SUM(CA37:CC37) -> 1128.337 | CE37: 3049.906 | CF37: 849.645 | CG37: 968.951 | CH37: 984.952 | CI37: =CJ37-SUM(CF37:CH37) -> 1368.214 | CJ37: 4171.762 | CK37: 1073.924 | CL37: 1205.636 | CM37: 1204.835 | CN37: =CO37-CM37-CL37-CK37 -> 1775.408 | CO37: 5259.803 | CP37: 1308.828 | CQ37: 1396.327 | CR37: 1433.927 | CS37: =CT37-SUM(CP37:CR37) -> 2008.29 | CT37: 6147.372 | CU37: 1435.241 | CV37: 1476.121 | CW37: 1555.686 | CX37: =CY37-CU37-CV37-CW37 -> 2225.582 | CY37: 6692.63 | CZ37: 1535.172 | DA37: 1547.321 | DB37: 1644.952 | DC37: =DD37-CZ37-DA37-DB37 -> 2267.92 | DD37: 6995.365 | DE37: 1602.985 | DF37: 1488.241
B38: % chg. Y/Y | BP38: -- | BU38: =BU37/BP37-1 -> 0.24313546 | BZ38: =BZ37/BU37-1 -> 0.18625095 | CA38: =CA37/BV37-1 -> -0.1468428 | CB38: =CB37/BW37-1 -> 0.053737685 | CC38: =CC37/BX37-1 -> 0.21787445 | CD38: =CD37/BY37-1 -> 0.17345884 | CE38: =CE37/BZ37-1 -> 0.092765775 | CF38: =CF37/CA37-1 -> 0.76894025 | CG38: =CG37/CB37-1 -> 0.49227796 | ... DF38: =DF37/DA37-1 -> -0.038182123
B39: Men's | BP39: 526.535 | BU39: 694.921 | BV39: 170.219 | BW39: 212.727 | BX39: 209.317 | BY39: =BZ39-SUM(BV39:BX39) -> 341.504 | BZ39: 933.767 | CA39: 129.129 | CB39: 191.019 | CC39: 239.496 | CD39: =CE39-SUM(CA39:CC39) -> 393.539 | CE39: 953.183 | CF39: 247.307 | CG39: 363.063 | CH39: 343.263 | CI39: =CJ39-SUM(CF39:CH39) -> 582.217 | CJ39: 1535.85 | CK39: 374.998 | CL39: 461.31 | CM39: 440.564 | CN39: =CO39-CM39-CL39-CK39 -> 679.73 | CO39: 1956.602 | CP39: 438.165 | CQ39: 530.723 | CR39: 504.828 | CS39: =CT39-SUM(CP39:CR39) -> 779.037 | CT39: 2252.753 | CU39: 505.698 | CV39: 587.525 | CW39: 551.43 | CX39: =CY39-CU39-CV39-CW39 -> 913.727 | CY39: 2558.38 | CZ39: 544.788 | DA39: 624.598 | DB39: 596.241 | DC39: =DD39-CZ39-DA39-DB39 -> 898.359 | DD39: 2663.986 | DE39: 581.878 | DF39: 621.38
B40: % chg. Y/Y | BP40: -- | BU40: =BU39/BP39-1 -> 0.3198002 | BZ40: =BZ39/BU39-1 -> 0.34370238 | CA40: =CA39/BV39-1 -> -0.24139491 | CB40: =CB39/BW39-1 -> -0.10204628 | CC40: =CC39/BX39-1 -> 0.14417845 | CD40: =CD39/BY39-1 -> 0.1523701 | CE40: =CE39/BZ39-1 -> 0.020793196 | CF40: =CF39/CA39-1 -> 0.91519333 | CG40: =CG39/CB39-1 -> 0.90066433 | ... DF40: =DF39/DA39-1 -> -0.0051521138
B41: Other | BP41: 230.022 | BU41: 240.61 | BV41: 49.113 | BW41: 54.428 | BX41: 56.498 | BY41: =BZ41-SUM(BV41:BX41) -> 94.493 | BZ41: 254.532 | CA41: 42.52 | CB41: 62.613 | CC41: 85.984 | CD41: =CE41-SUM(CA41:CC41) -> 207.673 | CE41: 398.79 | CF41: 102.513 | CG41: 118.604 | CH41: 122.206 | CI41: =CJ41-SUM(CF41:CH41) -> 205.682 | CJ41: 549.005 | CK41: 164.541 | CL41: 201.382 | CM41: 211.49 | CN41: =CO41-CM41-CL41-CK41 -> 316.7 | CO41: 894.113 | CP41: 253.799 | CQ41: 282.115 | CR41: 265.463 | CS41: =CT41-SUM(CP41:CR41) -> 417.776 | CT41: 1219.153 | CU41: 267.952 | CV41: 307.432 | CW41: 289.544 | CX41: =CY41-CU41-CV41-CW41 -> 472.188 | CY41: 1337.116 | CZ41: 290.7 | DA41: 353.3 | DB41: 324.727 | DC41: =DD41-CZ41-DA41-DB41 -> 474.522 | DD41: 1443.249 | DE41: 286.74 | DF41: 306.01
B42: % chg. Y/Y | BP42: -- | BU42: =BU41/BP41-1 -> 0.04603038 | BZ42: =BZ41/BU41-1 -> 0.057861269 | CA42: =CA41/BV41-1 -> -0.13424144 | CB42: =CB41/BW41-1 -> 0.15038216 | CC42: =CC41/BX41-1 -> 0.52189458 | CD42: =CD41/BY41-1 -> 1.1977607 | CE42: =CE41/BZ41-1 -> 0.56675781 | CF42: =CF41/CA41-1 -> 1.410936 | CG42: =CG41/CB41-1 -> 0.89423922 | ... DF42: =DF41/DA41-1 -> -0.13385225
B43: Total | BP43: =SUM(BP41,BP39,BP37) -> 2649.181 | BU43: =SUM(BU41,BU39,BU37) -> 3288.319 | BV43: =BV41+BV39+BV37 -> 782.315 | BW43: =BW41+BW39+BW37 -> 883.352 | BX43: =BX41+BX39+BX37 -> 916.084 | BY43: =BZ43-SUM(BV43:BX43) -> 1397.545 | BZ43: =SUM(BZ41,BZ39,BZ37) -> 3979.296 | CA43: =CA41+CA39+CA37 -> 651.962 | CB43: =CB41+CB39+CB37 -> 902.942 | CC43: =CC41+CC39+CC37 -> 1117.426 | CD43: =CD41+CD39+CD37 -> 1729.549 | CE43: =SUM(CE41,CE39,CE37) -> 4401.879 | CF43: =CF41+CF39+CF37 -> 1199.465 | CG43: =CG41+CG39+CG37 -> 1450.618 | CH43: =CH41+CH39+CH37 -> 1450.421 | CI43: =CI41+CI39+CI37 -> 2156.113 | CJ43: =SUM(CJ41,CJ39,CJ37) -> 6256.617 | CK43: =CK41+CK39+CK37 -> 1613.463 | CL43: =CL41+CL39+CL37 -> 1868.328 | CM43: =CM41+CM39+CM37 -> 1856.889 | CN43: =CN41+CN39+CN37 -> 2771.838 | CO43: =SUM(CO41,CO39,CO37) -> 8110.518 | CP43: =CP41+CP39+CP37 -> 2000.792 | CQ43: =CQ41+CQ39+CQ37 -> 2209.165 | CR43: =CR41+CR39+CR37 -> 2204.218 | CS43: =CS41+CS39+CS37 -> 3205.103 | CT43: =SUM(CT41,CT39,CT37) -> 9619.278 | CU43: =CU41+CU39+CU37 -> 2208.891 | CV43: =CV41+CV39+CV37 -> 2371.078 | CW43: =CW41+CW39+CW37 -> 2396.66 | CX43: =CX41+CX39+CX37 -> 3611.497 | CY43: =SUM(CY41,CY39,CY37) -> 10588.126 | CZ43: =CZ41+CZ39+CZ37 -> 2370.66 | DA43: =DA41+DA39+DA37 -> 2525.219 | DB43: =DB41+DB39+DB37 -> 2565.92 | DC43: =DC41+DC39+DC37 -> 3640.801 | DD43: =SUM(DD41,DD39,DD37) -> 11102.6 | DE43: =DE41+DE39+DE37 -> 2471.603 | DF43: =DF41+DF39+DF37 -> 2415.631
B45: Store Summary
B47: Americas Stores | Q47: =Q188 -> 67 | R47: =R188 -> 67 | S47: =S188 -> 70 | T47: =T188 -> 79 | U47: =U188 -> 98 | V47: =V188 -> 103 | W47: =W188 -> 103 | X47: =X188 -> 103 | ... DS47: =DS188 -> 498
B48: China Mainland Stores | Q48: =Q247 -> 0 | R48: =R247 -> 0 | S48: =S247 -> 0 | T48: =T247 -> 0 | U48: =U247 -> 0 | V48: =V247 -> 0 | W48: =W247 -> 0 | X48: =X247 -> 0 | ... DS48: =DS247 -> 223
B49: RoW Stores | Q49: =Q326 -> 4 | R49: =R326 -> 4 | S49: =S326 -> 4 | T49: =T326 -> 1 | U49: =U326 -> 0 | V49: =V326 -> 0 | W49: =W326 -> 0 | X49: =X326 -> 0 | ... DS49: =DS326 -> 187
B50: Total Stores | Q50: =Q47+Q48+Q49 -> 71 | R50: =R47+R48+R49 -> 71 | S50: =S47+S48+S49 -> 74 | T50: =T47+T48+T49 -> 80 | U50: =U47+U48+U49 -> 98 | V50: =V47+V48+V49 -> 103 | W50: =W47+W48+W49 -> 103 | X50: =X47+X48+X49 -> 103 | ... DS50: =DS47+DS48+DS49 -> 908
B51: Net additions/closures | Q51: -- | R51: -- | S51: =S50-R50 -> 3 | T51: =T50-S50 -> 6 | U51: =U50-T50 -> 18 | V51: =V50-U50 -> 5 | W51: =W50-R50 -> 32 | X51: =X50-W50 -> 0 | Y51: =Y50-X50 -> 1 | Z51: =Z50-Y50 -> 2 | AA51: =AA50-Z50 -> 4 | AB51: =AB50-W50 -> 7 | AC51: =AC50-AB50 -> 1 | AD51: =AD50-AC50 -> 12 | AE51: =AE50-AD50 -> 4 | AF51: =AF50-AE50 -> 4 | AG51: =AG50-AB50 -> 21 | AH51: =AH50-AG50 -> 4 | AI51: =AI50-AH50 -> 9 | AJ51: =AJ50-AI50 -> 18 | AK51: =AK50-AJ50 -> 7 | AL51: =AL50-AG50 -> 38 | AM51: =AM50-AL50 -> 4 | AN51: =AN50-AM50 -> 9 | AO51: =AO50-AN50 -> 12 | AP51: =AP50-AO50 -> 9 | AQ51: =AQ50-AL50 -> 34 | AR51: =AR50-AQ50 -> 7 | AS51: =AS50-AR50 -> 7 | AT51: =AT50-AS50 -> 19 | AU51: =AU50-AT50 -> 6 | AV51: =AV50-AQ50 -> 39 | AW51: =AW50-AV50 -> 5 | AX51: =AX50-AW50 -> 5 | AY51: =AY50-AX50 -> 16 | AZ51: =AZ50-AY50 -> 12 | BA51: =BA50-AV50 -> 38 | BB51: =BB50-BA50 -> 7 | BC51: =BC50-BB50 -> 14 | BD51: =BD50-BC50 -> 12 | BE51: =BE50-BD50 -> 7 | BF51: =BF50-BA50 -> 40 | BG51: =BG50-BF50 -> 4 | BH51: =BH50-BG50 -> 3 | BI51: =BI50-BH50 -> 8 | BJ51: =BJ50-BI50 -> 16 | BK51: =BK50-BF50 -> 31 | BL51: =BL50-BK50 -> 5 | BM51: =BM50-BL50 -> 10 | BN51: =BN50-BM50 -> 15 | BO51: =BO50-BN50 -> 16 | BP51: =BP50-BK50 -> 46 | BQ51: =BQ50-BP50 -> 7 | BR51: =BR50-BQ50 -> 4 | BS51: =BS50-BR50 -> 11 | BT51: =BT50-BS50 -> 14 | BU51: =BU50-BP50 -> 36 | BV51: =BV50-BU50 -> 15 | BW51: =BW50-BV50 -> 5 | BX51: =BX50-BW50 -> 20 | BY51: =BY50-BX50 -> 14 | BZ51: =BZ50-BU50 -> 54 | CA51: =CA50-BZ50 -> 2 | CB51: =CB50-CA50 -> 17 | CC51: =CC50-CB50 -> 9 | CD51: =CD50-CC50 -> 6 | CE51: =CE50-BZ50 -> 34 | CF51: =CF50-CE50 -> 2 | CG51: =CG50-CF50 -> 11 | CH51: =CH50-CG50 -> 18 | CI51: =CI50-CH50 -> 22 | CJ51: =CJ50-CE50 -> 53 | CK51: =CK50-CJ50 -> 5 | CL51: =CL50-CK50 -> 21 | CM51: =CM50-CL50 -> 23 | CN51: =CN50-CM50 -> 32 | CO51: =CO50-CJ50 -> 81 | CP51: =CP50-CO50 -> 7 | CQ51: =CQ50-CP50 -> 10 | CR51: =CR50-CQ50 -> 14 | CS51: =CS50-CR50 -> 25 | CT51: =CT50-CO50 -> 56 | CU51: =CU50-CT50 -> 0 | CV51: =CV50-CU50 -> 10 | CW51: =CW50-CV50 -> 28 | CX51: =CX50-CW50 -> 18 | CY51: =CY50-CT50 -> 56 | CZ51: =CZ50-CY50 -> 3 | DA51: =DA50-CZ50 -> 14 | DB51: =DB50-DA50 -> 12 | DC51: =DC50-DB50 -> 15 | DD51: =DD50-CY50 -> 44 | DE51: =DE50-DD50 -> 5 | DF51: =DF50-DE50 -> 9 | DG51: =DG50-DF50 -> 10 | DH51: =DH50-DG50 -> 11 | DI51: =DI50-DD50 -> 35 | DJ51: =DJ50-DI50 -> 1 | DK51: =DK50-DJ50 -> 9 | DL51: =DL50-DK50 -> 9 | DM51: =DM50-DL50 -> 12 | DN51: =DN50-DI50 -> 31 | DO51: =DO50-DN50 -> 1 | DP51: =DP50-DO50 -> 9 | DQ51: =DQ50-DP50 -> 9 | DR51: =DR50-DQ50 -> 12 | DS51: =DS50-DN50 -> 31
B52: Average Stores | Q52: -- | R52: -- | S52: =AVERAGE(R50:S50) -> 72.5 | T52: =AVERAGE(S50:T50) -> 77 | U52: =AVERAGE(T50:U50) -> 89 | V52: =AVERAGE(U50:V50) -> 100.5 | W52: =AVERAGE(S50:V50) -> 88.75 | X52: =AVERAGE(W50:X50) -> 103 | Y52: =AVERAGE(X50:Y50) -> 103.5 | Z52: =AVERAGE(Y50:Z50) -> 105 | AA52: =AVERAGE(Z50:AA50) -> 108 | AB52: =AVERAGE(X50:AA50) -> 105.75 | AC52: =AVERAGE(AB50:AC50) -> 110.5 | AD52: =AVERAGE(AC50:AD50) -> 117 | AE52: =AVERAGE(AD50:AE50) -> 125 | AF52: =AVERAGE(AE50:AF50) -> 129 | AG52: =AVERAGE(AC50:AF50) -> 123 | AH52: =AVERAGE(AG50:AH50) -> 133 | AI52: =AVERAGE(AH50:AI50) -> 139.5 | AJ52: =AVERAGE(AI50:AJ50) -> 153 | AK52: =AVERAGE(AJ50:AK50) -> 165.5 | AL52: =AVERAGE(AH50:AK50) -> 152.5 | AM52: =AVERAGE(AL50:AM50) -> 171 | AN52: =AVERAGE(AM50:AN50) -> 177.5 | AO52: =AVERAGE(AN50:AO50) -> 188 | AP52: =AVERAGE(AO50:AP50) -> 198.5 | AQ52: =AVERAGE(AM50:AP50) -> 188 | AR52: =AVERAGE(AQ50:AR50) -> 206.5 | AS52: =AVERAGE(AR50:AS50) -> 213.5 | AT52: =AVERAGE(AS50:AT50) -> 226.5 | AU52: =AVERAGE(AT50:AU50) -> 239 | AV52: =AVERAGE(AR50:AU50) -> 226.25 | AW52: =AVERAGE(AV50:AW50) -> 244.5 | AX52: =AVERAGE(AW50:AX50) -> 249.5 | AY52: =AVERAGE(AX50:AY50) -> 260 | AZ52: =AVERAGE(AY50:AZ50) -> 274 | BA52: =AVERAGE(AW50:AZ50) -> 261.75 | BB52: =AVERAGE(BA50:BB50) -> 283.5 | BC52: =AVERAGE(BB50:BC50) -> 294 | BD52: =AVERAGE(BC50:BD50) -> 307 | BE52: =AVERAGE(BD50:BE50) -> 316.5 | BF52: =AVERAGE(BB50:BE50) -> 305.25 | BG52: =AVERAGE(BF50:BG50) -> 322 | BH52: =AVERAGE(BG50:BH50) -> 325.5 | BI52: =AVERAGE(BH50:BI50) -> 331 | BJ52: =AVERAGE(BI50:BJ50) -> 343 | BK52: =AVERAGE(BG50:BJ50) -> 334.25 | BL52: =AVERAGE(BK50:BL50) -> 353.5 | BM52: =AVERAGE(BL50:BM50) -> 361 | BN52: =AVERAGE(BM50:BN50) -> 373.5 | BO52: =AVERAGE(BN50:BO50) -> 389 | BP52: =AVERAGE(BL50:BO50) -> 375 | BQ52: =AVERAGE(BP50:BQ50) -> 400.5 | BR52: =AVERAGE(BQ50:BR50) -> 406 | BS52: =AVERAGE(BR50:BS50) -> 413.5 | BT52: =AVERAGE(BS50:BT50) -> 426 | BU52: =AVERAGE(BQ50:BT50) -> 416 | BV52: =AVERAGE(BU50:BV50) -> 440.5 | BW52: =AVERAGE(BV50:BW50) -> 450.5 | BX52: =AVERAGE(BW50:BX50) -> 463 | BY52: =AVERAGE(BX50:BY50) -> 480 | BZ52: =AVERAGE(BV50:BY50) -> 465.25 | CA52: =AVERAGE(BZ50:CA50) -> 488 | CB52: =AVERAGE(CA50:CB50) -> 497.5 | CC52: =AVERAGE(CB50:CC50) -> 510.5 | CD52: =AVERAGE(CC50:CD50) -> 518 | CE52: =AVERAGE(CA50:CD50) -> 507.75 | CF52: =AVERAGE(CE50:CF50) -> 522 | CG52: =AVERAGE(CF50:CG50) -> 528.5 | CH52: =AVERAGE(CG50:CH50) -> 543 | CI52: =AVERAGE(CH50:CI50) -> 563 | CJ52: =AVERAGE(CF50:CI50) -> 545.75 | CK52: =AVERAGE(CJ50:CK50) -> 576.5 | CL52: =AVERAGE(CK50:CL50) -> 589.5 | CM52: =AVERAGE(CL50:CM50) -> 611.5 | CN52: =AVERAGE(CM50:CN50) -> 639 | CO52: =AVERAGE(CK50:CN50) -> 614.25 | CP52: =AVERAGE(CO50:CP50) -> 658.5 | CQ52: =AVERAGE(CP50:CQ50) -> 667 | CR52: =AVERAGE(CQ50:CR50) -> 679 | CS52: =AVERAGE(CR50:CS50) -> 698.5 | CT52: =AVERAGE(CP50:CS50) -> 682.75 | CU52: =AVERAGE(CT50:CU50) -> 711 | CV52: =AVERAGE(CU50:CV50) -> 716 | CW52: =AVERAGE(CV50:CW50) -> 735 | CX52: =AVERAGE(CW50:CX50) -> 758 | CY52: =AVERAGE(CU50:CX50) -> 737 | CZ52: =AVERAGE(CY50:CZ50) -> 768.5 | DA52: =AVERAGE(CZ50:DA50) -> 777 | DB52: =AVERAGE(DA50:DB50) -> 790 | DC52: =AVERAGE(DB50:DC50) -> 803.5 | DD52: =AVERAGE(CZ50:DC50) -> 790.25 | DE52: =AVERAGE(DD50:DE50) -> 813.5 | DF52: =AVERAGE(DE50:DF50) -> 820.5 | DG52: =AVERAGE(DF50:DG50) -> 830 | DH52: =AVERAGE(DG50:DH50) -> 840.5 | DI52: =AVERAGE(DE50:DH50) -> 830.5 | DJ52: =AVERAGE(DI50:DJ50) -> 846.5 | DK52: =AVERAGE(DJ50:DK50) -> 851.5 | DL52: =AVERAGE(DK50:DL50) -> 860.5 | DM52: =AVERAGE(DL50:DM50) -> 871 | DN52: =AVERAGE(DJ50:DM50) -> 861.25 | DO52: =AVERAGE(DN50:DO50) -> 877.5 | DP52: =AVERAGE(DO50:DP50) -> 882.5 | DQ52: =AVERAGE(DP50:DQ50) -> 891.5 | DR52: =AVERAGE(DQ50:DR50) -> 902 | DS52: =AVERAGE(DO50:DR50) -> 892.25
B53: % chg. Y/Y | Q53: -- | R53: -- | S53: -- | T53: -- | U53: -- | V53: -- | W53: -- | X53: =X52/S52-1 -> 0.42068966 | Y53: =Y52/T52-1 -> 0.34415584 | Z53: =Z52/U52-1 -> 0.17977528 | AA53: =AA52/V52-1 -> 0.074626866 | AB53: =AB52/W52-1 -> 0.1915493 | AC53: =AC52/X52-1 -> 0.072815534 | AD53: =AD52/Y52-1 -> 0.13043478 | AE53: =AE52/Z52-1 -> 0.19047619 | ... DS53: =DS52/DN52-1 -> 0.035994194
B55: Period-end Gross Sq Ft | C55: 0.035966 | D55: 0.044632 | E55: 0.04787 | F55: 0.054401 | G55: 0.071913 | H55: =G55 -> 0.071913 | I55: 0.083835 | J55: 0.090612 | K55: 0.103366 | L55: 0.11652 | M55: =L55 -> 0.11652 | N55: 0.13152 | O55: 0.15152 | P55: 0.16902 | Q55: 0.18652 | R55: =Q55 -> 0.18652 | S55: 0.20152 | T55: 0.23152 | U55: 0.27402 | V55: 0.27402 | W55: =V55 -> 0.27402 | X55: 0.27402 | Y55: 0.27682 | Z55: 0.28242 | AA55: 0.316 | AB55: =AA55 -> 0.316 | AC55: 0.325 | AD55: 0.35 | AE55: 0.364 | AF55: 0.374 | AG55: =AF55 -> 0.374 | AH55: 0.386 | AI55: 0.416 | AJ55: 0.47 | AK55: 0.494 | AL55: =AK55 -> 0.494 | AM55: 0.508 | AN55: 0.538 | AO55: 0.573 | AP55: 0.602 | AQ55: =AP55 -> 0.602 | AR55: 0.627 | AS55: 0.654 | AT55: 0.718 | AU55: 0.74 | AV55: =AU55 -> 0.74 | AW55: 0.764 | AX55: 0.787 | AY55: 0.848 | AZ55: 0.888 | BA55: =AZ55 -> 0.888 | BB55: 0.931 | BC55: 0.985 | BD55: 1.036 | BE55: 1.071 | BF55: =BE55 -> 1.071 | BG55: 1.095 | BH55: 1.117 | BI55: 1.144 | BJ55: 1.19 | BK55: =BJ55 -> 1.19 | BL55: 1.204 | BM55: 1.238 | BN55: 1.192 | BO55: 1.192 | BP55: =BO55 -> 1.192 | BQ55: 1.277 | BR55: 1.303 | BS55: 1.354 | BT55: 1.426 | BU55: =BT55 -> 1.426 | BV55: 1.466 | BW55: 1.522 | BX55: 1.604 | BY55: 1.68 | BZ55: =BY55 -> 1.68 | CA55: 1.692 | CB55: 1.757 | CC55: 1.808 | CD55: 1.858 | CE55: =CD55 -> 1.858 | CF55: 1.862 | CG55: 1.905 | CH55: 2.002 | CI55: 2.125 | CJ55: =CI55 -> 2.125 | CK55: 2.155 | CL55: 2.258 | CM55: 2.39 | CN55: 2.575 | CO55: =CN55 -> 2.575 | CP55: 2.632 | CQ55: 2.691 | CR55: 2.797 | CS55: 2.967 | CT55: =CS55 -> 2.967 | CU55: 2.988 | CV55: 3.075 | CW55: 3.231 | CX55: 3.372 | CY55: =CX55 -> 3.372 | CZ55: 3.415 | DA55: 3.511 | DB55: 3.63 | DC55: 3.736 | DD55: =DC55 -> 3.736 | DE55: 3.788 | DF55: 3.88 | DG55: =DG56*2-DF55 -> 3.9976981 | DH55: =DH56*2-DG55 -> 4.0927551 | DI55: =DH55 -> 4.0927551 | DJ55: =DJ56*2-DI55 -> 4.1279201 | DK55: =DK56*2-DJ55 -> 4.2276766 | DL55: =DL56*2-DK55 -> 4.3478622 | DM55: =DM56*2-DL55 -> 4.4553787 | DN55: =DM55 -> 4.4553787 | DO55: =DO56*2-DN55 -> 4.4924354 | DP55: =DP56*2-DO55 -> 4.6003477 | DQ55: =DQ56*2-DP55 -> 4.7283536 | DR55: =DR56*2-DQ55 -> 4.8440339 | DS55: =DR55 -> 4.8440339
B56: Average Gross Square Feet | C56: -- | D56: =AVERAGE(C55:D55) -> 0.040299 | E56: =AVERAGE(D55:E55) -> 0.046251 | F56: =AVERAGE(E55:F55) -> 0.0511355 | G56: =AVERAGE(F55:G55) -> 0.063157 | H56: =AVERAGE(D55:G55) -> 0.054704 | I56: =AVERAGE(H55:I55) -> 0.077874 | J56: =AVERAGE(I55:J55) -> 0.0872235 | K56: =AVERAGE(J55:K55) -> 0.096989 | L56: =AVERAGE(K55:L55) -> 0.109943 | M56: =AVERAGE(I55:L55) -> 0.09858325 | N56: =AVERAGE(M55:N55) -> 0.12402 | O56: =AVERAGE(N55:O55) -> 0.14152 | P56: =AVERAGE(O55:P55) -> 0.16027 | Q56: =AVERAGE(P55:Q55) -> 0.17777 | R56: =AVERAGE(N55:Q55) -> 0.159645 | S56: =AVERAGE(R55:S55) -> 0.19402 | T56: =AVERAGE(S55:T55) -> 0.21652 | U56: =AVERAGE(T55:U55) -> 0.25277 | V56: =AVERAGE(U55:V55) -> 0.27402 | W56: =AVERAGE(S55:V55) -> 0.24527 | X56: =AVERAGE(W55:X55) -> 0.27402 | Y56: =AVERAGE(X55:Y55) -> 0.27542 | Z56: =AVERAGE(Y55:Z55) -> 0.27962 | AA56: =AVERAGE(Z55:AA55) -> 0.29921 | AB56: =AVERAGE(X55:AA55) -> 0.287315 | AC56: =AVERAGE(AB55:AC55) -> 0.3205 | AD56: =AVERAGE(AC55:AD55) -> 0.3375 | AE56: =AVERAGE(AD55:AE55) -> 0.357 | AF56: =AVERAGE(AE55:AF55) -> 0.369 | AG56: =AVERAGE(AC55:AF55) -> 0.35325 | AH56: =AVERAGE(AG55:AH55) -> 0.38 | AI56: =AVERAGE(AH55:AI55) -> 0.401 | AJ56: =AVERAGE(AI55:AJ55) -> 0.443 | AK56: =AVERAGE(AJ55:AK55) -> 0.482 | AL56: =AVERAGE(AH55:AK55) -> 0.4415 | AM56: =AVERAGE(AL55:AM55) -> 0.501 | AN56: =AVERAGE(AM55:AN55) -> 0.523 | AO56: =AVERAGE(AN55:AO55) -> 0.5555 | AP56: =AVERAGE(AO55:AP55) -> 0.5875 | AQ56: =AVERAGE(AM55:AP55) -> 0.55525 | AR56: =AVERAGE(AQ55:AR55) -> 0.6145 | AS56: =AVERAGE(AR55:AS55) -> 0.6405 | AT56: =AVERAGE(AS55:AT55) -> 0.686 | AU56: =AVERAGE(AT55:AU55) -> 0.729 | AV56: =AVERAGE(AR55:AU55) -> 0.68475 | AW56: =AVERAGE(AV55:AW55) -> 0.752 | AX56: =AVERAGE(AW55:AX55) -> 0.7755 | AY56: =AVERAGE(AX55:AY55) -> 0.8175 | AZ56: =AVERAGE(AY55:AZ55) -> 0.868 | BA56: =AVERAGE(AW55:AZ55) -> 0.82175 | BB56: =AVERAGE(BA55:BB55) -> 0.9095 | BC56: =AVERAGE(BB55:BC55) -> 0.958 | BD56: =AVERAGE(BC55:BD55) -> 1.0105 | BE56: =AVERAGE(BD55:BE55) -> 1.0535 | BF56: =AVERAGE(BB55:BE55) -> 1.00575 | BG56: =AVERAGE(BF55:BG55) -> 1.083 | BH56: =AVERAGE(BG55:BH55) -> 1.106 | BI56: =AVERAGE(BH55:BI55) -> 1.1305 | BJ56: =AVERAGE(BI55:BJ55) -> 1.167 | BK56: =AVERAGE(BG55:BJ55) -> 1.1365 | BL56: =AVERAGE(BK55:BL55) -> 1.197 | BM56: =AVERAGE(BL55:BM55) -> 1.221 | BN56: =AVERAGE(BM55:BN55) -> 1.215 | BO56: =AVERAGE(BN55:BO55) -> 1.192 | BP56: =AVERAGE(BL55:BO55) -> 1.2065 | BQ56: =AVERAGE(BP55:BQ55) -> 1.2345 | BR56: =AVERAGE(BQ55:BR55) -> 1.29 | BS56: =AVERAGE(BR55:BS55) -> 1.3285 | BT56: =AVERAGE(BS55:BT55) -> 1.39 | BU56: =AVERAGE(BQ55:BT55) -> 1.34 | BV56: =AVERAGE(BU55:BV55) -> 1.446 | BW56: =AVERAGE(BV55:BW55) -> 1.494 | BX56: =AVERAGE(BW55:BX55) -> 1.563 | BY56: =AVERAGE(BX55:BY55) -> 1.642 | BZ56: =AVERAGE(BV55:BY55) -> 1.568 | CA56: =AVERAGE(BZ55:CA55) -> 1.686 | CB56: =AVERAGE(CA55:CB55) -> 1.7245 | CC56: =AVERAGE(CB55:CC55) -> 1.7825 | CD56: =AVERAGE(CC55:CD55) -> 1.833 | CE56: =AVERAGE(CA55:CD55) -> 1.77875 | CF56: =AVERAGE(CE55:CF55) -> 1.86 | CG56: =AVERAGE(CF55:CG55) -> 1.8835 | CH56: =AVERAGE(CG55:CH55) -> 1.9535 | CI56: =AVERAGE(CH55:CI55) -> 2.0635 | CJ56: =AVERAGE(CF55:CI55) -> 1.9735 | CK56: =AVERAGE(CJ55:CK55) -> 2.14 | CL56: =AVERAGE(CK55:CL55) -> 2.2065 | CM56: =AVERAGE(CL55:CM55) -> 2.324 | CN56: =AVERAGE(CM55:CN55) -> 2.4825 | CO56: =AVERAGE(CK55:CN55) -> 2.3445 | CP56: =AVERAGE(CO55:CP55) -> 2.6035 | CQ56: =AVERAGE(CP55:CQ55) -> 2.6615 | CR56: =AVERAGE(CQ55:CR55) -> 2.744 | CS56: =AVERAGE(CR55:CS55) -> 2.882 | CT56: =AVERAGE(CP55:CS55) -> 2.77175 | CU56: =AVERAGE(CT55:CU55) -> 2.9775 | CV56: =AVERAGE(CU55:CV55) -> 3.0315 | CW56: =AVERAGE(CV55:CW55) -> 3.153 | CX56: =AVERAGE(CW55:CX55) -> 3.3015 | CY56: =AVERAGE(CU55:CX55) -> 3.1665 | CZ56: =AVERAGE(CY55:CZ55) -> 3.3935 | DA56: =AVERAGE(CZ55:DA55) -> 3.463 | DB56: =AVERAGE(DA55:DB55) -> 3.5705 | DC56: =AVERAGE(DB55:DC55) -> 3.683 | DD56: =AVERAGE(CZ55:DC55) -> 3.573 | DE56: =AVERAGE(DD55:DE55) -> 3.762 | DF56: =AVERAGE(DE55:DF55) -> 3.834 | DG56: =DG58/1000*DG52 -> 3.9388491 | DH56: =DH58/1000*DH52 -> 4.0452266 | DI56: =AVERAGE(DE55:DH55) -> 3.9396133 | DJ56: =DJ58/1000*DJ52 -> 4.1103376 | DK56: =DK58/1000*DK52 -> 4.1777984 | DL56: =DL58/1000*DL52 -> 4.2877694 | DM56: =DM58/1000*DM52 -> 4.4016205 | DN56: =AVERAGE(DJ55:DM55) -> 4.2897094 | DO56: =DO58/1000*DO52 -> 4.4739071 | DP56: =DP58/1000*DP52 -> 4.5463915 | DQ56: =DQ58/1000*DQ52 -> 4.6643506 | DR56: =DR58/1000*DR52 -> 4.7861937 | DS56: =AVERAGE(DO55:DR55) -> 4.6662926
B57: % chg. Y/Y | C57: -- | D57: -- | E57: -- | F57: -- | G57: -- | H57: -- | I57: =I56/D56-1 -> 0.93240527 | J57: =J56/E56-1 -> 0.88587274 | K57: =K56/F56-1 -> 0.89670581 | L57: =L56/G56-1 -> 0.74078883 | M57: =M56/H56-1 -> 0.80212142 | N57: =N56/I56-1 -> 0.59257262 | O57: =O56/J56-1 -> 0.62249852 | P57: =P56/K56-1 -> 0.65245543 | ... DS57: =DS56/DN56-1 -> 0.087787585
B58: Avg. Square Feet per Store (000s) | Q58: -- | R58: -- | S58: =S56*1000/S52 -> 2.6761379 | T58: =T56*1000/T52 -> 2.8119481 | U58: =U56*1000/U52 -> 2.8401124 | V58: =V56*1000/V52 -> 2.7265672 | W58: =W56*1000/W52 -> 2.7636056 | X58: =X56*1000/X52 -> 2.6603883 | Y58: =Y56*1000/Y52 -> 2.6610628 | Z58: =Z56*1000/Z52 -> 2.6630476 | ... DF58: =DF56*1000/DF52 -> 4.6727605 | DG58: =DB58*(1+DG59) -> 4.7456013 | DH58: =DC58*(1+DH59) -> 4.8128811 | DI58: =DI56*1000/DI52 -> 4.7436644 | DJ58: =DE58*(1+DJ59) -> 4.8556853 | DK58: =DF58*(1+DK59) -> 4.9063985 | DL58: =DG58*(1+DL59) -> 4.9828813 | DM58: =DH58*(1+DM59) -> 5.0535252 | DN58: =DN56*1000/DN52 -> 4.9807947 | DO58: =DJ58*(1+DO59) -> 5.0984696 | DP58: =DK58*(1+DP59) -> 5.1517185 | DQ58: =DL58*(1+DQ59) -> 5.2320254 | DR58: =DM58*(1+DR59) -> 5.3062015 | DS58: =DS56*1000/DS52 -> 5.229804
B59: % chg. Y/Y | Q59: -- | R59: -- | S59: -- | T59: -- | U59: -- | V59: -- | W59: -- | X59: =X58/S58-1 -> -0.0058851905 | Y59: =Y58/T58-1 -> -0.053658619 | Z59: =Z58/U58-1 -> -0.062344273 | AA59: =AA58/V58-1 -> 0.016099291 | AB59: =AB58/W58-1 -> -0.016890586 | AC59: =AC58/X58-1 -> 0.090236502 | AD59: =AD58/Y58-1 -> 0.084008759 | AE59: =AE58/Z58-1 -> 0.072455475 | ... DF59: =DF58/DA58-1 -> 0.048436303 | DG59: 0.05 | DH59: 0.05 | DI59: =DI58/DD58-1 -> 0.049168992 | DJ59: 0.05 | DK59: 0.05 | DL59: 0.05 | DM59: 0.05 | DN59: =DN58/DI58-1 -> 0.049988832 | DO59: 0.05 | DP59: 0.05 | DQ59: 0.05 | DR59: 0.05 | DS59: =DS58/DN58-1 -> 0.0499939
