Workbook
Name \0: '[1]RANDSTAD (old 4)'!#REF!
Name \0: '[1]RANDSTAD (old 4)'!#REF!
Name \a: '[1]RANDSTAD (old 4)'!#REF!
Name \a: '[1]RANDSTAD (old 4)'!#REF!
Name \b: '[2]teo model'!#REF!
Name \b: '[2]teo model'!#REF!
Name \BS: #REF!
Name \BS: #REF!
Name \BS: #REF!
Name \c: '[2]teo model'!#REF!
Name \c: '[2]teo model'!#REF!
Name \d: #REF!
Name \d: #REF!
Name \d: #REF!
Name \e: [3]Geographic!#REF!
Name \e: [3]Geographic!#REF!
Name \EP1: #REF!
Name \EP1: #REF!
Name \EP1: #REF!
Name \EP2: #REF!
Name \EP2: #REF!
Name \EP2: #REF!
Name \f: #REF!
Name \f: #REF!
Name \f: #REF!
Name \g: [3]Geographic!#REF!
Name \g: [3]Geographic!#REF!
Name \h: '[2]teo model'!#REF!
Name \h: '[2]teo model'!#REF!
Name \i: '[1]RANDSTAD (old 4)'!#REF!
Name \i: '[1]RANDSTAD (old 4)'!#REF!
Name \j: [3]Geographic!#REF!
Name \j: #REF!
Name \j: #REF!
Name \k: [4]roysuna!#REF!
Name \k: [4]roysuna!#REF!
Name \l: '[2]teo model'!#REF!
Name \l: #REF!
Name \l: #REF!
Name \m: '[2]teo model'!#REF!
Name \m: #REF!
Name \m: #REF!
Name \o: #REF!
Name \o: #REF!
Name \o: #REF!
Name \p: #REF!
Name \P: #REF!
Name \P: #REF!
Name \PL: #REF!
Name \PL: #REF!
Name \PL: #REF!
Name \q: [5]VABQORF!#REF!
Name \q: [5]VABQORF!#REF!
Name \R: #REF!
Name \R: #REF!
Name \R: #REF!
Name \s: #REF!
Name \s: #REF!
Name \s: #REF!
Name \SF: #REF!

Sheet Cover Sheet
C4: Adidas Model
C5: European General Retail
B13: Team:
B16: Richard Edwards
B17: Managing Director
B18: Richard.Edwards@gs.com
B19: +44 (20) 7051-6016
B21: Ben Williams
B22: Analyst
B23: ben.williams@gs.com
B24: +44 (20) 7051-0661
B26: Hamish Bogdan
B27: Analyst
B28: hamish.bogdan@gs.com
B29: +44 (20) 7552-2214

Sheet Sheet2

Sheet Sheet1

Sheet Profit and Loss
A1: =TODAY() -> 46294 | B1: FY 95 | C1: FY 96 | D1: FY 97 | E1: FY 98 | F1: FY 99 | G1: FY 00 | H1: FY 01 | I1: FY 02 | J1: FY 03 | K1: FY 04 | L1: FY 05 | M1: FY 06 | N1: FY 07 | O1: FY 08 | P1: FY 09 | Q1: FY 10 | R1: FY 11 | S1: FY 12 | T1: FY 13 | U1: FY 14 | V1: FY 15 | W1: FY 16 | X1: FY 17 | Y1: FY 18 | Z1: FY 19 | AA1: FY 20 | AB1: FY 21 | AC1: FY 22 | AD1: FY 23 | AE1: FY 24 | AF1: FY 25 | AG1: FY 26E | AH1: FY 27E | AI1: FY 28E | AJ1: FY 29E | AK1: FY 30E
A2: adidas - Dec YE - in EUR mn | L2: IFRS | M2: IFRS | N2: IFRS | O2: IFRS | P2: IFRS | Q2: IFRS | R2: IFRS | S2: IFRS | T2: IFRS | U2: IFRS | V2: IFRS | W2: IFRS | X2: IFRS | Y2: IFRS | Z2: IFRS | AA2: IFRS | AB2: IFRS | AC2: IFRS | AD2: IFRS | AE2: IFRS | AF2: IFRS | AG2: IFRS | AH2: IFRS | AI2: IFRS | AJ2: IFRS | AK2: IFRS
A4: Sales by segment | T4: FY 13 | U4: FY 14 | V4: FY 15 | W4: FY 16 | X4: FY 17 | Y4: FY 18 | Z4: FY 19 | AA4: FY 20 | AB4: FY 21 | AC4: FY 22 | AD4: FY 23 | AE4: =AE1 -> FY 24 | AF4: =AF1 -> FY 25 | AG4: =AG1 -> FY 26E | AH4: =AH1 -> FY 27E | AI4: =AI1 -> FY 28E | AJ4: =AJ1 -> FY 29E | AK4: =AK1 -> FY 30E | AO4: FY 12 | AP4: FY 13 | AQ4: FY 14 | AR4: FY 15 | AS4: FY 16 | AT4: FY 17E | AU4: FY 18E | AV4: FY 19E | AW4: FY 20 | AX4: FY 21 | AY4: FY 22E | AZ4: FY 23E | BA4: FY 24E | BB4: FY 25E
A5: Wholesale | M5: =M9*M$32 -> 8571.4 | N5: =N9*N32 -> 8548.17 | O5: 7758 | P5: 7164 | Q5: 8181 | R5: 8971 | S5: =+Interim!EO5 -> 9533 | T5: =Interim!EW5 -> 9100 | U5: 9376 | V5: =V32-V27-V10 -> 11227 | W5: =W32-W27-W10 -> 12812 | X5: =X32-X27-X10 -> 14617 | Y5: =Y32-Y27-Y10 -> 14596 | Z5: =Z32-Z27-Z10 -> 15222 | AA5: =AA32-AA27-AA10 -> 11237 | AB5: =AB32-AB27-AB10 -> 12796.003 | AC5: =AC32-AC27-AC10 -> 13523 | ... AK5: =AK32-AK27-AK10 -> 20822.778 | AN5: Wholesale | AO5: =S5 -> 9533 | AP5: =T5 -> 9100 | AQ5: =U5 -> 9376 | AR5: =V5 -> 11227 | AS5: =W5 -> 12812 | AT5: =X5 -> 14617 | AU5: =Y5 -> 14596 | AV5: =Z5 -> 15222 | ... BB5: =AF5 -> 14808
A6: Growth | N6: =N5/M5-1 -> -0.0027101757 | O6: =O5/N5-1 -> -0.092437329 | P6: =P5/O5-1 -> -0.076566125 | Q6: =Q5/P5-1 -> 0.1419598 | R6: =R5/Q5-1 -> 0.096565212 | S6: =+S5/R5-1 -> 0.062646305 | T6: =T5/S5-1 -> -0.045421169 | U6: =U5/T5-1 -> 0.03032967 | V6: =V5/U5-1 -> 0.19741894 | W6: =W5/V5-1 -> 0.14117752 | X6: =X5/W5-1 -> 0.14088355 | Y6: =Y5/X5-1 -> -0.0014366833 | Z6: =Z5/Y5-1 -> 0.042888463 | AA6: =AA5/Z5-1 -> -0.26179214 | ... AE6: =AE5/AD5-1 -> 0.13967096 | AF6: =Interim!IO6 -> 0.07 | AG6: =AG5/AF5-1 -> 0.10568359 | AH6: =AH5/AG5-1 -> 0.074563685 | AI6: =AI5/AH5-1 -> 0.066841687 | AJ6: =AJ5/AI5-1 -> 0.053275387 | AK6: =AK5/AJ5-1 -> 0.053264224 | AN6: Retail | AO6: =S10 -> 3373 | AP6: =T10 -> 3446 | AQ6: =U10 -> 3820.5652 | AR6: =V10 -> 4221 | AS6: =W10 -> 5003 | AT6: =X10 -> 5860 | AU6: =Y10 -> 6488 | AV6: =Z10 -> 7814 | ... BB6: =AF10 -> 9931
A7: FX & Scope impact | P7: =P6-P8 -> 0.013433875 | Q7: =Q6-Q8 -> 0.066959799 | R7: =R6-R8 -> -0.013434788 | S7: =+S6-S8 -> 0.041739266 | T7: =T6-T8 -> -0.049224274 | U7: =U6-U8 -> -0.02967033 | V7: =V6-V8 -> 0.089049577 | W7: =W6-W8 -> -0.044691725 | X7: =X6-X8 -> -0.018181918 | Y7: =Y6-Y8 -> -0.063659848 | Z7: =Z6-Z8 -> 0.034761388 | AA7: =AA6-AA8 -> -0.026607596 | ... AK7: =AK6-AK8 -> 2.4286129e-16 | AN7: Other | AO7: =S27 -> 1977 | AP7: =T27 -> 1659 | AQ7: =U27 -> 1358 | AR7: =V27 -> 1467 | AS7: =W27 -> 1475 | AT7: =X27 -> 741 | AU7: =Y27 -> 831 | AV7: =Z27 -> 605 | ... BB7: =AF27 -> 72
A8: Currency neutral | P8: -0.09 | Q8: 0.075 | R8: =Interim!EG8 -> 0.11 | S8: =+Interim!EO8 -> 0.020907039 | T8: =Interim!EW8 -> 0.003803105 | U8: 0.06 | V8: =(U32*V35-U27*V30-U10*V13)/U5 -> 0.10836937 | W8: =(V32*W35-V27*W30-V10*W13)/V5 -> 0.18586924 | X8: =(W32*X35-W27*X30-W10*X13)/W5 -> 0.15906546 | Y8: =(X32*Y35-X27*Y30-X10*Y13)/X5 -> 0.062223165 | Z8: =(Y32*Z35-Y27*Z30-Y10*Z13)/Y5 -> 0.0081270748 | AA8: =(Z32*AA35-Z27*AA30-Z10*AA13)/Z5 -> -0.23518455 | AB8: =(AA32*AB35-AA27*AB30-AA10*AB13)/AA5 -> 0.23141875 | AC8: =(AB32*AC35-AB27*AC30-AB10*AC13)/AB5 -> 0.0050181236 | ... AE8: =(AD32*AE35-AD27*AE30-AD10*AE13)/AD5 -> 0.16830868 | AF8: =Interim!IO8 -> 0.12 | AG8: =(AF32*AG35-AF27*AG30-AF10*AG13)/AF5 -> 0.11754862 | AH8: =(AG32*AH35-AG27*AH30-AG10*AH13)/AG5 -> 0.066497018 | AI8: =(AH32*AI35-AH27*AI30-AH10*AI13)/AH5 -> 0.066841687 | AJ8: =(AI32*AJ35-AI27*AJ30-AI10*AJ13)/AI5 -> 0.053275387 | AK8: =(AJ32*AK35-AJ27*AK30-AJ10*AK13)/AJ5 -> 0.053264224 | AS8: =AS6/SUM(AS5:AS7) -> 0.25935718 | AT8: =AT6/SUM(AT5:AT7) -> 0.2761806 | AU8: =AU6/SUM(AU5:AU7) -> 0.29605293 | AV8: =AV6/SUM(AV5:AV7) -> 0.33052747 | AW8: =AW6/SUM(AW5:AW7) -> 0.40974602 | AX8: =AX6/SUM(AX5:AX7) -> 0.39059984 | AY8: =AY6/SUM(AY5:AY7) -> 0.39260806 | AZ8: =AZ6/SUM(AZ5:AZ7) -> 0.42010833 | ... BB8: =BB6/SUM(BB5:BB7) -> 0.40026601
A9: % of total | M9: 0.85 | N9: 0.83 | O9: =O5/O32 -> 0.7195993 | P9: =P5/P32 -> 0.69130561 | Q9: =Q5/Q32 -> 0.6823186 | R9: =R5/R32 -> 0.67334684 | S9: =S5/S32 -> 0.64052946 | T9: =T5/T32 -> 0.6406195 | U9: =U5/U32 -> 0.64510802 | V9: =V5/V32 -> 0.66373042 | ... AK9: =AK5/AK32 -> 0.5951685
A10: Retail | M10: =M32-M5-M27 -> 656.6 | N10: =N32-N5-N27 -> 946.83 | O10: 1738 | P10: 1906 | Q10: 2389 | R10: 2793 | S10: =+Interim!EO10 -> 3373 | T10: =Interim!EW10 -> 3446 | U10: =Interim!FE10 -> 3820.5652 | V10: =Interim!FM10 -> 4221 | W10: =Interim!FU10 -> 5003 | X10: =Interim!GC10 -> 5860 | Y10: =Interim!GK10 -> 6488 | Z10: =Y10*(1+Z11) -> 7814 | AA10: =Z10*(1+AA11) -> 8131 | AB10: =AA10*(1+AB11) -> 8293.997 | AC10: =AB10*(1+AC11) -> 8838 | AD10: =AC10*(1+AD11) -> 8687 | AE10: =AD10*(1+AE11) -> 9490 | AF10: =Interim!IO10 -> 9931 | AG10: =AF10*(1+AG11) -> 10608.219 | AH10: =AG10*(1+AH11) -> 11436.57 | AI10: =AH10*(1+AI11) -> 12237.13 | AJ10: =AI10*(1+AJ11) -> 13093.729 | AK10: =AJ10*(1+AK11) -> 14010.29
A11: Growth | N11: =N10/M10-1 -> 0.44201949 | O11: =O10/N10-1 -> 0.83559879 | P11: =P10/O10-1 -> 0.096662831 | Q11: =Q10/P10-1 -> 0.25341028 | R11: =+R10/Q10-1 -> 0.16910841 | S11: =+S10/R10-1 -> 0.20766201 | T11: =T10/S10-1 -> 0.021642455 | U11: =U10/T10-1 -> 0.10869564 | V11: =V10/U10-1 -> 0.10481036 | W11: =W10/V10-1 -> 0.18526416 | X11: =X10/W10-1 -> 0.17129722 | Y11: =Y10/X10-1 -> 0.10716724 | Z11: =Z12+Z13 -> 0.20437731 | AA11: =AA12+AA13 -> 0.040568211 | AB11: =AB12+AB13 -> 0.020046362 | AC11: =AC12+AC13 -> 0.065589973 | AD11: =AD12+AD13 -> -0.017085313 | AE11: =AE12+AE13 -> 0.092436975 | AF11: =AF12+AF13 -> 0.1 | AG11: =AG12+AG13 -> 0.068192381 | ... AK11: =AK12+AK13 -> 0.07
A12: FX & Scope impact | P12: =P11-P13 -> 0.026662831 | Q12: =Q11-Q13 -> 0.075410283 | R12: =+R11-R13 -> -0.030891586 | S12: =+S11-S13 -> 0.070154314 | T12: =T11-T13 -> -0.059504002 | U12: =U11-U13 -> -0.10030436 | V12: =V11-V13 -> -0.0051896415 | W12: =W11-W13 -> -0.044735845 | X12: =X11-X13 -> -0.00060163902 | Y12: =Y11-Y13 -> -0.042525597 | Z12: =Z$34 -> 0.01823927 | AA12: =AA$34 -> -0.02612586 | AB12: =AB$34 -> -0.089953638 | AC12: 0.045589973 | AD12: -0.047085313 | AE12: -0.017563025 | AF12: =Interim!IO12 -> -0.04 | AG12: =AG$34 -> -0.011807619 | AH12: =AH$34 -> 0.0080857898 | AI12: =AI$34 -> 0 | AJ12: =AJ$34 -> 1.5265567e-16 | AK12: =AK$34 -> 0
A13: Currency neutral | P13: 0.07 | Q13: 0.178 | R13: =Interim!EG13 -> 0.2 | S13: =+Interim!EO13 -> 0.1375077 | T13: =Interim!EW13 -> 0.081146457 | U13: 0.209 | V13: =Interim!FM13 -> 0.11 | W13: =Interim!FU13 -> 0.23 | X13: =Interim!GC13 -> 0.17189886 | Y13: =Interim!GK13 -> 0.14969283 | Z13: 0.18613804 | AA13: 0.066694071 | AB13: 0.11 | AC13: 0.02 | AD13: 0.03 | AE13: 0.11 | AF13: =Interim!IO13 -> 0.14 | AG13: 0.08 | AH13: 0.07 | AI13: =AH13 -> 0.07 | AJ13: =AI13 -> 0.07 | AK13: =AJ13 -> 0.07
A14: % of total | M14: =M10/M$32 -> 0.06511305 | N14: =N10/$N$32 -> 0.091934168 | O14: =O10/O32 -> 0.16120954 | P14: =P10/P32 -> 0.18392357 | Q14: =Q10/Q32 -> 0.19924937 | R14: =R10/R32 -> 0.20963747 | S14: =S10/S32 -> 0.22663442 | T14: =T10/T32 -> 0.24259064 | U14: =U10/U32 -> 0.26287087 | V14: =V10/V32 -> 0.24954183 | ... AK14: =AK10/AK32 -> 0.40045007
A15: of which stores | O15: =O10-O21 -> 1722.0031 | P15: =P10-P21 -> 1876.4142 | Q15: =Q10-Q21 -> 2334 | R15: =R10-R21 -> 2704 | S15: =S10-S21 -> 3215 | T15: =T10-T21 -> 3196 | U15: =U10-U21 -> 3398.5652 | V15: =V10-V21 -> 3593.2489 | ... AK15: =AK10-AK21 -> 7637.409
A16: Growth | P16: =P15/O15-1 -> 0.089669444 | Q16: =Q15/P15-1 -> 0.24386183 | R16: =R15/Q15-1 -> 0.15852614 | S16: =S15/R15-1 -> 0.18897929 | T16: =T15/S15-1 -> -0.0059097978 | U16: =U15/T15-1 -> 0.063380849 | V16: =V15/U15-1 -> 0.057284099 | W16: =W15/V15-1 -> 0.11389024 | ... AK16: =AK15/AJ15-1 -> 0.061796348
A17: FX & Scope impact | P17: =P16-P18 -> 0.026729603 | Q17: =Q16-Q18 -> 0.075488994 | R17: =R16-R18 -> -0.031175955 | S17: =S16-S18 -> 0.070708627 | T17: =T16-T18 -> -0.059591602 | U17: =U16-U18 -> -0.10564731 | V17: =V16-V18 -> -0.014223186 | W17: =W16-W18 -> -0.053216706 | ... AK17: =AK16-AK18 -> -1.4571677e-16
A18: Currency neutral | P18: =(O10*P13-O21*P24)/O15 -> 0.062939841 | Q18: =(P10*Q13-P21*Q24)/P15 -> 0.16837283 | R18: =(Q10*R13-Q21*R24)/Q15 -> 0.18970209 | S18: =(R10*S13-R21*S24)/R15 -> 0.11827066 | T18: =(S10*T13-S21*T24)/S15 -> 0.053681804 | U18: =(T10*U13-T21*U24)/T15 -> 0.16902816 | V18: =(U10*V13-U21*V24)/U15 -> 0.071507285 | W18: =(V10*W13-V21*W24)/V15 -> 0.16710695 | ... AC18: =(AB10*AC13-AB21*AC24)/AB15 -> 0.003020308 | AD18: 0.12 | AE18: 0.15 | AF18: =(AE10*AF13-AE21*AF24)/AE15 -> 0.1258956 | AG18: =(AF10*AG13-AF21*AG24)/AF15 -> 0.08 | AH18: =(AG10*AH13-AG21*AH24)/AG15 -> 0.062197304 | AI18: =(AH10*AI13-AH21*AI24)/AH15 -> 0.062067516 | AJ18: =(AI10*AJ13-AI21*AJ24)/AI15 -> 0.06193358 | AK18: =(AJ10*AK13-AJ21*AK24)/AJ15 -> 0.061796348
A19: % of total | P19: =P15/P$32 -> 0.18106863 | Q19: =Q15/Q$32 -> 0.19466222 | R19: =R15/R$32 -> 0.20295729 | S19: =S15/S$32 -> 0.21601828 | T19: =T15/T$32 -> 0.2249912 | U19: =U15/U$32 -> 0.2338355 | V19: =V15/V$32 -> 0.21242973 | W19: =W15/W$32 -> 0.20749015 | ... AK19: =AK15/AK$32 -> 0.21829677
A20: % of retail | P20: =P15/P$10 -> 0.98447755 | Q20: =Q15/Q$10 -> 0.97697781 | R20: =R15/R$10 -> 0.96813462 | S20: =S15/S$10 -> 0.95315743 | T20: =T15/T$10 -> 0.92745212 | U20: =U15/U$10 -> 0.88954514 | V20: =V15/V$10 -> 0.85127907 | W20: =W15/W$10 -> 0.80001698 | ... AK20: =AK15/AK$10 -> 0.54512856
A21: of which eCommerce | O21: =P21/(1+P22) -> 15.996863 | P21: =Q21/(1+Q22) -> 29.585799 | Q21: 55 | R21: 89 | S21: 158 | T21: 250 | U21: 422 | V21: =U21*(1+V22) -> 627.75106 | W21: =V21*(1+W22) -> 1000.5151 | X21: =W21*(1+X22) -> 1510.7281 | Y21: =X21*(1+Y22) -> 1977.0021 | Z21: =Y21*(1+Z22) -> 2665.4718 | AA21: =Z21*(1+AA22) -> 4008.5342 | AB21: =AA21*(1+AB22) -> 3808.2933 | AC21: =AB21*(1+AC22) -> 4149.913 | ... AK21: =AJ21*(1+AK22) -> 6372.8806
A22: Growth | P22: =P23+P24 -> 0.849475 | Q22: 0.859 | R22: =R21/Q21-1 -> 0.61818182 | S22: =S21/R21-1 -> 0.7752809 | T22: =T21/S21-1 -> 0.58227848 | U22: =U21/T21-1 -> 0.688 | V22: =V23+V24 -> 0.48756176 | W22: =W23+W24 -> 0.59380863 | X22: =X23+X24 -> 0.50995037 | Y22: =Y23+Y24 -> 0.30864191 | Z22: =Z23+Z24 -> 0.34823927 | AA22: =AA23+AA24 -> 0.50387414 | AB22: =AB23+AB24 -> -0.049953638 | AC22: =AC23+AC24 -> 0.089704154 | ... AK22: =AK23+AK24 -> 0.08
A23: FX & Scope impact | P23: =P$34 -> 0.019475002 | Q23: =Q$34 -> 0.070418219 | R23: =R$34 -> -0.01882402 | S23: =S$34 -> 0.053313188 | T23: =T22-T24 -> -0.057721519 | U23: =U22-U24 -> -0.032 | V23: =V145 -> 0.067561756 | W23: =W145+4.5% -> 0.0038086314 | X23: =X$34 -> -0.060049627 | Y23: =Y$34 -> -0.051358092 | Z23: =Z$34 -> 0.01823927 | AA23: =AA$34 -> -0.02612586 | AB23: =AB$34 -> -0.089953638 | AC23: =AC$34 -> 0.049704154 | AD23: =AD$34 -> -0.037426858 | AE23: =AE$34 -> -0.023656533 | ... AK23: =AK$34 -> 0
A24: Currency neutral | P24: 0.83 | Q24: =Q22-Q23 -> 0.78858178 | R24: =R22-R23 -> 0.63700584 | S24: =S22-S23 -> 0.72196771 | T24: 0.64 | U24: 0.72 | V24: =Interim!FM19 -> 0.42 | W24: =Interim!FU19 -> 0.59 | X24: 0.57 | Y24: 0.36 | Z24: 0.33 | AA24: 0.53 | AB24: 0.04 | AC24: 0.04 | AD24: -0.05 | AE24: 0.06 | AF24: =Interim!IO19 -> 0.16 | AG24: 0.08 | AH24: 0.08 | AI24: 0.08 | AJ24: 0.08 | AK24: 0.08
A25: % of total | P25: =P21/P32 -> 0.0028549454 | Q25: =Q21/Q32 -> 0.004587156 | R25: =R21/R32 -> 0.0066801771 | S25: =S21/S32 -> 0.010616139 | T25: =T21/T32 -> 0.017599437 | U25: =U21/U32 -> 0.029035365 | V25: =V21/V32 -> 0.037112093 | W25: =W21/W32 -> 0.051867033 | ... AK25: =AK21/AK32 -> 0.1821533
A26: % of retail | P26: =P21/P$10 -> 0.015522455 | Q26: =Q21/Q$10 -> 0.023022185 | R26: =R21/R$10 -> 0.031865378 | S26: =S21/S$10 -> 0.046842573 | T26: =T21/T$10 -> 0.072547882 | U26: =U21/U$10 -> 0.11045486 | V26: =V21/V$10 -> 0.14872093 | W26: =W21/W$10 -> 0.19998302 | ... AK26: =AK21/AK$10 -> 0.45487144
A27: Other Businesses | M27: =M31*M$32 -> 856 | N27: =N31*N$32 -> 804 | O27: 1285 | P27: 1293 | Q27: 1420 | R27: 1580 | S27: =+Interim!EO21 -> 1977 | T27: =T32-T5-T10 -> 1659 | U27: =U137 -> 1358 | V27: =V137 -> 1467 | W27: =W137 -> 1475 | X27: =X137 -> 741 | Y27: =Y137 -> 831 | Z27: =Z137 -> 605 | AA27: =AA137 -> 476 | AB27: =AB137 -> 144 | ... AK27: =AK137 -> 153.29012
A28: Growth | N28: =N27/M27-1 -> -0.060747664 | O28: =O27/N27-1 -> 0.59825871 | P28: =P27/O27-1 -> 0.0062256809 | Q28: =Q27/P27-1 -> 0.098221191 | R28: =+R27/Q27-1 -> 0.11267606 | S28: =+S27/R27-1 -> 0.25126582 | T28: =T27/S27-1 -> -0.16084977 | U28: =U27/T27-1 -> -0.1814346 | V28: =V27/U27-1 -> 0.080265096 | W28: =W27/V27-1 -> 0.0054533061 | X28: =X27/W27-1 -> -0.49762712 | Y28: =Y27/X27-1 -> 0.12145749 | Z28: =Z27/Y27-1 -> -0.27196149 | AA28: =AA27/Z27-1 -> -0.21322314 | ... AK28: =AK27/AJ27-1 -> 0
A29: FX & Scope impact | P29: =P28-P30 -> 0.046225681 | Q29: =Q28-Q30 -> 0.082221191 | R29: =+R28-R30 -> -0.017323944 | S29: =+S28-S30 -> 0.082856962 | T29: =T28-T30 -> -0.20956247 | U29: =U28-U30 -> 0.0095654008 | V29: =V28-V30 -> 0.10685714 | W29: =W28-W30 -> -0.004204499 | X29: =X28-X30 -> -0.62535632 | Y29: =Y28-Y30 -> 0.12145749 | Z29: =Z28-Z30 -> -0.27196149 | AA29: =AA28-AA30 -> -0.014005221 | ... AK29: =AK28-AK30 -> 0
A30: Currency neutral | P30: -0.04 | Q30: 0.016 | R30: =Interim!EG24 -> 0.13 | S30: =+Interim!EO24 -> 0.16840886 | T30: =Interim!EW24 -> 0.048712696 | U30: -0.191 | V30: =V140 -> -0.026592047 | W30: =W140 -> 0.009657805 | X30: =X140 -> 0.1277292 | Y30: =Y140 -> 0 | Z30: =Z140 -> 0 | AA30: =AA140 -> -0.19921792 | AB30: =AB140 -> -0.67189603 | AC30: =AC140 -> -0.059096276 | ... AK30: =AK140 -> 0
A31: % of total | M31: 0.08488695 | N31: 0.078065832 | O31: =O27/O32 -> 0.11919117 | P31: =P27/P32 -> 0.12477082 | Q31: =Q27/Q32 -> 0.11843203 | R31: =R27/R32 -> 0.11859191 | S31: =S27/S32 -> 0.13283612 | T31: =T27/T32 -> 0.11678986 | U31: =U27/U32 -> 0.093436081 | V31: =V27/V32 -> 0.086727756 | ... AK31: =AK27/AK32 -> 0.0043814255
A32: Total sales | K32: =K325 -> 5860 | L32: 6636 | M32: 10084 | N32: 10299 | O32: =SUM(O27,O10,O5) -> 10781 | P32: =SUM(P27,P10,P5) -> 10363 | Q32: =SUM(Q27,Q10,Q5) -> 11990 | R32: =Interim!EG26 -> 13323 | S32: =+Interim!EO26 -> 14883 | T32: =T325 -> 14205 | U32: =U325 -> 14534 | V32: =V143 -> 16915 | W32: =W143 -> 19290 | X32: =X143 -> 21218 | Y32: =Y143 -> 21915 | Z32: =Z143 -> 23641 | AA32: =AA143 -> 19844 | AB32: =AB143 -> 21234 | AC32: =AC143 -> 22511 | ... AK32: =AK143 -> 34986.358 | AM32: =((AF32/AB32)^0.25)-1 -> 0.039688198
A33: Growth | L33: =L32/K32-1 -> 0.13242321 | M33: 0.14 | N33: =N32/M32-1 -> 0.021320904 | O33: =O32/N32-1 -> 0.04680066 | P33: =P32/O32-1 -> -0.038771914 | Q33: =Q32/P32-1 -> 0.15700087 | R33: =R32/Q32-1 -> 0.11117598 | S33: =S32/R32-1 -> 0.11709075 | T33: =T32/S32-1 -> -0.045555332 | U33: =U32/T32-1 -> 0.023160859 | ... AK33: =AK32/AJ32-1 -> 0.05965397
A34: FX & Scope impact | P34: =P33-P35 -> 0.019475002 | Q34: =Q33-Q35 -> 0.070418219 | R34: =R33-R35 -> -0.01882402 | S34: =S33-S35 -> 0.053313188 | T34: =T33-T35 -> -0.0749744 | U34: =U33-U35 -> -0.04153104 | V34: =V33-V35 -> 0.067481675 | W34: =W149 -> -0.043378907 | X34: =X33-X35 -> -0.060049627 | Y34: =Y33-Y35 -> -0.051358092 | Z34: =Z33-Z35 -> 0.01823927 | AA34: =AA33-AA35 -> -0.02612586 | AB34: =AB33-AB35 -> -0.089953638 | AC34: =AC33-AC35 -> 0.049704154 | AD34: =AD33-AD35 -> -0.037426858 | AE34: =AE33-AE35 -> -0.023656533 | ... AK34: =AK33-AK35 -> 0
A35: Currency neutral | P35: =(P8*$O$5+P13*$O$10+P30*$O$27)/$O$32 -> -0.058246916 | Q35: =(Q8*$P$5+Q13*$P$10+Q30*$P$27)/$P$32 -> 0.08658265 | R35: =Interim!EG29 -> 0.13 | S35: =Interim!EO29 -> 0.063777558 | T35: =Interim!EW29 -> 0.029419069 | U35: =Interim!FE29 -> 0.064691899 | V35: =V146 -> 0.096341086 | W35: =W146 -> 0.18159929 | X35: =X146 -> 0.15999779 | Y35: =Y146 -> 0.08420756 | Z35: =Z146 -> 0.060519571 | AA35: =AA146 -> -0.13448494 | AB35: =AB146 -> 0.16 | AC35: =AC146 -> 0.010435245 | ... AK35: =AK146 -> 0.05965397
A36: Check | Y36: =(Y14-X14)*25% -> 0.0049680826 | Z36: =(Z14-Y14)*25% -> 0.0086186354 | AA36: =(AA14-Z14)*25% -> 0.019804636 | AB36: =(AB14-AA14)*25% -> -0.0047865452 | AC36: =(AC14-AB14)*25% -> 0.000502055 | AD36: =(AD14-AC14)*25% -> 0.0068750674 | AE36: =(AE14-AD14)*25% -> -0.0020226969 | AF36: =(AF14-AE14)*25% -> -0.0029378823 | ... AK36: =(AK14-AJ14)*25% -> 0.00096800661
A38: Gross profit by segment
A39: Wholesale | O39: 3387 | P39: 2978 | Q39: 3379 | R39: 3585 | S39: =Interim!EO33 -> 3840 | T39: 3884 | U39: 3911 | V39: =Interim!FM33 -> 5064.752 | W39: =W5*W40 -> 5736.9077 | X39: =X5*X40 -> 6691.3136 | Y39: =Y5*Y40 -> 6725.4883 | Z39: =Z5*Z40 -> 7090.0441 | AA39: =AA5*AA40 -> 5245.1633 | AB39: =AB5*AB40 -> 5985.6647 | AC39: =AC5*AC40 -> 6339.2595 | AD39: =AD5*AD40 -> 5539.6 | ... AK39: =AK5*AK40 -> 9927.8035
A40: Gross margin % | O40: =O39/O$5 -> 0.43658159 | P40: =P39/P$5 -> 0.41568956 | Q40: =Q39/Q5 -> 0.41303019 | R40: =Interim!EG35 -> 0.39888268 | S40: =+S39/S5 -> 0.40281129 | T40: =T39/T5 -> 0.42681319 | U40: =U39/U5 -> 0.41712884 | V40: =V39/V5 -> 0.45112247 | W40: 0.44777612 | X40: =W40+0.01 -> 0.45777612 | Y40: =X40+0.3% -> 0.46077612 | Z40: =Y40+0.5% -> 0.46577612 | AA40: =Z40+0.1% -> 0.46677612 | AB40: =AA40+0.1% -> 0.46777612 | AC40: =AB40+0.1% -> 0.46877612 | AD40: =AC40+0.1% -> 0.46977612 | AE40: =AD40+0.1% -> 0.47077612 | AF40: =AE40+0.1% -> 0.47177612 | AG40: =AF40+0.1% -> 0.47277612 | AH40: =AG40+0.1% -> 0.47377612 | ... AK40: =AJ40+0.1% -> 0.47677612
A41: Retail | O41: 1069 | P41: 1116 | Q41: 1476 | R41: 1749 | S41: =Interim!EO36 -> 2055 | T41: 2143 | U41: 2281 | V41: =Interim!FM36 -> 2606.248 | W41: =W10*W42 -> 3089.0923 | X41: =X10*X42 -> 3687.5357 | Y41: =Y10*Y42 -> 4092.9165 | Z41: =Z10*Z42 -> 4953.8988 | AA41: =AA10*AA42 -> 5163.4592 | AB41: =AB10*AB42 -> 5360.9949 | AC41: =AC10*AC42 -> 5712.6224 | AD41: =AD10*AD42 -> 5615.0205 | ... AK41: =AK10*AK42 -> 9055.8378
A42: Gross margin % | O42: =O41/O$10 -> 0.6150748 | P42: =P41/P$10 -> 0.58551941 | Q42: =Q41/Q10 -> 0.61783173 | R42: =Interim!EG38 -> 0.62620838 | S42: =+S41/S10 -> 0.60924993 | T42: =T41/T10 -> 0.62188044 | U42: =U41/U10 -> 0.59703208 | V42: =V41/V10 -> 0.617448 | W42: =V42 -> 0.617448 | X42: 0.6292723 | Y42: 0.63084409 | Z42: 0.63397733 | AA42: 0.63503373 | AB42: 0.64637049 | AC42: 0.64637049 | AD42: 0.64637049 | AE42: 0.64637049 | AF42: 0.64637049 | AG42: 0.64637049 | AH42: 0.64637049 | AI42: 0.64637049 | AJ42: 0.64637049 | AK42: 0.64637049
A43: Other Businesses | O43: 543 | P43: 509 | Q43: 618 | R43: 688 | S43: =Interim!EO42 -> 845 | T43: 799 | U43: 457 | V43: =Interim!FM42 -> 497 | W43: =W27*W44 -> 553 | X43: =X27*X44 -> 280.7762 | Y43: =Y27*Y44 -> 314.87858 | Z43: =Z27*Z44 -> 229.24373 | AA43: =AA27*AA44 -> 180.36366 | AB43: =AB27*AB44 -> 54.563797 | AC43: =AC27*AC44 -> 56.837288 | AD43: =AD27*AD44 -> 75.404136 | ... AK43: =AK27*AK44 -> 58.083965
A44: Gross margin % | O44: =O43/O$27 -> 0.42256809 | P44: =P43/P$27 -> 0.39365816 | Q44: =Q43/Q27 -> 0.43521127 | R44: =Interim!EG44 -> 0.43544304 | S44: =+S43/S27 -> 0.42741528 | T44: =T43/T27 -> 0.48161543 | U44: =U43/U27 -> 0.3365243 | V44: =V43/V27 -> 0.33878664 | W44: =W316 -> 0.37491525 | X44: =W44+0.4% -> 0.37891525 | Y44: =X44 -> 0.37891525 | Z44: =Y44 -> 0.37891525 | AA44: =Z44 -> 0.37891525 | AB44: =AA44 -> 0.37891525 | AC44: =AB44 -> 0.37891525 | AD44: =AC44 -> 0.37891525 | AE44: =AD44 -> 0.37891525 | AF44: =AE44 -> 0.37891525 | ... AK44: =AJ44 -> 0.37891525
A45: Total | O45: =SUM(O43,O41,O39,) -> 4999 | P45: =SUM(P43,P41,P39,) -> 4603 | Q45: =SUM(Q43,Q41,Q39)-Interim!DY49 -> 5728 | R45: =+R39+R41+R43-Interim!EG49 -> 6359 | S45: =Interim!EO395 -> 7104 | T45: =Interim!EW45 -> 7140 | U45: =U333 -> 6924 | V45: =SUM(V43,V41,V39) -> 8168 | W45: =SUM(W43,W41,W39) -> 9379 | X45: =SUM(X43,X41,X39) -> 10659.625 | Y45: =SUM(Y43,Y41,Y39) -> 11133.283 | Z45: =SUM(Z43,Z41,Z39) -> 12273.187 | AA45: =SUM(AA43,AA41,AA39) -> 10588.986 | AB45: =SUM(AB43,AB41,AB39) -> 11401.223 | AC45: =SUM(AC43,AC41,AC39) -> 12108.719 | ... AK45: =SUM(AK43,AK41,AK39) -> 19041.725
A46: Gross margin % | O46: =O45/O$32 -> 0.46368611 | P46: =P45/P$32 -> 0.4441764 | Q46: =Q45/Q$32 -> 0.47773144 | R46: =R45/R$32 -> 0.4772949 | S46: =S45/S32 -> 0.47732312 | T46: =T45/T$32 -> 0.50263992 | U46: =U45/U$32 -> 0.47640017 | V46: =V45/V$32 -> 0.48288501 | W46: =W45/W$32 -> 0.48621047 | X46: =X45/X$32 -> 0.50238597 | Y46: =Y45/Y$32 -> 0.50802114 | Z46: =Z45/Z$32 -> 0.51914837 | AA46: =AA45/AA$32 -> 0.53361148 | ... AK46: =AK45/AK$32 -> 0.54426143
A47: Growth | Q47: =Q45/P45-1 -> 0.24440582 | R47: =R45/Q45-1 -> 0.11016061 | S47: =S45/R45-1 -> 0.11715679 | T47: =T45/S45-1 -> 0.0050675676 | U47: =U45/T45-1 -> -0.030252101 | V47: =V45/U45-1 -> 0.17966493 | W47: =W45/V45-1 -> 0.14826151 | X47: =X45/W45-1 -> 0.13654179 | ... AK47: =AK45/AJ45-1 -> 0.062153968
O48: =O46/O335 -> 0.95269147 | P48: =P46/P335 -> 0.97856434 | Q48: =Q46/Q335 -> 0.99965096 | R48: =R46/R335 -> 1.0047401 | S48: =S46/S335 -> 1.0001408 | T48: =T46/T335 -> 1.0198543 | U48: =U46/U335 -> 1 | V48: =V46/V335 -> 1 | ... AK48: =AK46/AK335 -> 1.0366884
A49: Gross margins by brands | B49: FY 95 | C49: FY 96 | D49: FY 97 | E49: FY 98 | F49: FY 99 | G49: FY 00 | H49: FY 01 | I49: FY 02 | J49: FY 03 | K49: FY 04 | L49: FY 05 | M49: FY 06 | N49: FY 07 | O49: FY 08 | P49: FY 09 | Q49: FY 10 | R49: FY 11 | S49: FY 12E | T49: FY 13E | U49: FY 14E | V49: =V1 -> FY 15 | W49: =W1 -> FY 16 | X49: =X1 -> FY 17 | Y49: =Y1 -> FY 18 | Z49: =Z1 -> FY 19 | AA49: =AA1 -> FY 20 | AB49: =AB1 -> FY 21 | AC49: =AC1 -> FY 22 | ... AK49: =AK1 -> FY 30E | EE49: =EE$2 -> 0 | EF49: =EF$2 -> 0 | EG49: =EG$2 -> 0 | EH49: =EH$2 -> 0 | EI49: =EI$2 -> 0 | EJ49: =EJ$2 -> 0 | EK49: =EK$2 -> 0 | EL49: =EL$2 -> 0 | ... FB49: =FB$2 -> 0
A50: Wholesale
A51: adidas | O51: =Interim!DI58 -> 0.46 | P51: =Interim!DQ58 -> 0.444 | Q51: 0.437 | R51: =+Interim!EG58 -> 0.42 | S51: =+Interim!EO58 -> 0.421 | T51: 0.442 | U51: 0.433 | V51: =U51+((V40-U40)+0.1%) -> 0.46799363 | W51: =V51+((W40-V40)+0.1%) -> 0.46564728 | X51: =W51+((X40-W40)+0.1%) -> 0.47664728 | Y51: =X51+((Y40-X40)+0.1%) -> 0.48064728 | Z51: =Y51+((Z40-Y40)+0.1%) -> 0.48664728 | AA51: =Z51+((AA40-Z40)+0.1%) -> 0.48864728 | AB51: =AA51+((AB40-AA40)+0.1%) -> 0.49064728 | AC51: =AB51+((AC40-AB40)+0.1%) -> 0.49264728 | ... AK51: =AJ51+((AK40-AJ40)+0.1%) -> 0.50864728 | EE51: 0.475 | EF51: 0.454 | EH51: 0.474 | EJ51: 0.433 | EL51: 0.46 | EM51: 0.456 | EN51: 0.424 | EP51: 0.446 | ER51: 0.446 | ET51: 0.444
A52: change in GM (bps) | P52: =Interim!DQ59 -> -160 | Q52: =(Q51-P51)*10000 -> -70 | R52: =+Interim!EG59 -> -170 | S52: =+Interim!EO59 -> 10 | T52: =(T51-S51)*10000 -> 210 | U52: =(U51-T51)*10000 -> -90 | V52: =(V51-U51)*10000 -> 349.93633 | W52: =(W51-V51)*10000 -> -23.463514 | X52: =(X51-W51)*10000 -> 110 | Y52: =(Y51-X51)*10000 -> 40 | Z52: =(Z51-Y51)*10000 -> 60 | AA52: =(AA51-Z51)*10000 -> 20 | ... AK52: =(AK51-AJ51)*10000 -> 20 | EM52: =(EM51-EE51)*10000 -> -190 | EN52: =(EN51-EF51)*10000 -> -300 | EP52: =(EP51-EH51)*10000 -> -280 | ER52: =(ER51-EJ51)*10000 -> 130 | ET52: =(ET51-EL51)*10000 -> -160
A53: Reebok | O53: =Interim!DI60 -> 0.33 | P53: =Interim!DQ60 -> 0.284 | Q53: 0.307 | R53: =+Interim!EG60 -> 0.291 | S53: =+Interim!EO60 -> 0.262 | T53: 0.31 | U53: 0.286 | V53: =(V39-(('Sales & stores'!$O372+'Sales & stores'!$O373)*'Profit and Loss'!V5*'Profit and Loss'!V51))/(V$5*'Sales & stores'!$O374) -> 0.34153642 | W53: =(W39-(('Sales & stores'!$O372+'Sales & stores'!$O373)*'Profit and Loss'!W5*'Profit and Loss'!W51))/(W$5*'Sales & stores'!$O374) -> 0.33050094 | X53: =(X39-(('Sales & stores'!$O372+'Sales & stores'!$O373)*'Profit and Loss'!X5*'Profit and Loss'!X51))/(X$5*'Sales & stores'!$O374) -> 0.33334134 | Y53: =(Y39-(('Sales & stores'!$O372+'Sales & stores'!$O373)*'Profit and Loss'!Y5*'Profit and Loss'!Y51))/(Y$5*'Sales & stores'!$O374) -> 0.32890401 | Z53: =(Z39-(('Sales & stores'!$O372+'Sales & stores'!$O373)*'Profit and Loss'!Z5*'Profit and Loss'!Z51))/(Z$5*'Sales & stores'!$O374) -> 0.32654603 | AA53: =(AA39-(('Sales & stores'!$O372+'Sales & stores'!$O373)*'Profit and Loss'!AA5*'Profit and Loss'!AA51))/(AA$5*'Sales & stores'!$O374) -> 0.32002934 | AB53: =(AB39-(('Sales & stores'!$O372+'Sales & stores'!$O373)*'Profit and Loss'!AB5*'Profit and Loss'!AB51))/(AB$5*'Sales & stores'!$O374) -> 0.31351266 | AC53: =(AC39-(('Sales & stores'!$O372+'Sales & stores'!$O373)*'Profit and Loss'!AC5*'Profit and Loss'!AC51))/(AC$5*'Sales & stores'!$O374) -> 0.30699598 | ... AK53: =(AK39-(('Sales & stores'!$O372+'Sales & stores'!$O373)*'Profit and Loss'!AK5*'Profit and Loss'!AK51))/(AK$5*'Sales & stores'!$O374) -> 0.25486253 | EE53: 0.32 | EF53: 0.33 | EH53: 0.367 | EJ53: 0.293 | EL53: 0.33 | EM53: 0.27 | EN53: 0.254 | EP53: 0.309 | ER53: 0.292 | ET53: 0.284
A54: change in GM (bps) | P54: =Interim!DQ61 -> -460 | Q54: =(Q53-P53)*10000 -> 230 | R54: =+Interim!EG61 -> -160 | S54: =+Interim!EO61 -> -290 | T54: =(T53-S53)*10000 -> 480 | U54: =(U53-T53)*10000 -> -240 | V54: =(V53-U53)*10000 -> 555.36417 | W54: =(W53-V53)*10000 -> -110.35476 | X54: =(X53-W53)*10000 -> 28.403968 | Y54: =(Y53-X53)*10000 -> -44.373309 | Z54: =(Z53-Y53)*10000 -> -23.579802 | AA54: =(AA53-Z53)*10000 -> -65.166817 | ... AK54: =(AK53-AJ53)*10000 -> -65.166817 | EM54: =(EM53-EE53)*10000 -> -500 | EN54: =(EN53-EF53)*10000 -> -760 | EP54: =(EP53-EH53)*10000 -> -580 | ER54: =(ER53-EJ53)*10000 -> -10 | ET54: =(ET53-EL53)*10000 -> -460
A55: Wholesale check | P55: =(('Sales & stores'!L372+'Sales & stores'!L373)*'Profit and Loss'!P51)+('Sales & stores'!L374*'Profit and Loss'!P53) -> 0.4152 | Q55: =(('Sales & stores'!M372+'Sales & stores'!M373)*'Profit and Loss'!Q51)+('Sales & stores'!M374*'Profit and Loss'!Q53) -> 0.4136 | R55: =(('Sales & stores'!N372+'Sales & stores'!N373)*'Profit and Loss'!R51)+('Sales & stores'!N374*'Profit and Loss'!R53) -> 0.39813273 | S55: =(('Sales & stores'!$O372+'Sales & stores'!$O373)*'Profit and Loss'!S51)+('Sales & stores'!$O374*'Profit and Loss'!S53) -> 0.40055995 | T55: =(('Sales & stores'!$O372+'Sales & stores'!$O373)*'Profit and Loss'!T51)+('Sales & stores'!$O374*'Profit and Loss'!T53) -> 0.42460401 | U55: =(('Sales & stores'!$O372+'Sales & stores'!$O373)*'Profit and Loss'!U51)+('Sales & stores'!$O374*'Profit and Loss'!U53) -> 0.41390056 | V55: =(('Sales & stores'!$O372+'Sales & stores'!$O373)*'Profit and Loss'!V51)+('Sales & stores'!$O374*'Profit and Loss'!V53) -> 0.45112247 | W55: =(('Sales & stores'!$O372+'Sales & stores'!$O373)*'Profit and Loss'!W51)+('Sales & stores'!$O374*'Profit and Loss'!W53) -> 0.44777612 | X55: =(('Sales & stores'!$O372+'Sales & stores'!$O373)*'Profit and Loss'!X51)+('Sales & stores'!$O374*'Profit and Loss'!X53) -> 0.45777612 | Y55: =(('Sales & stores'!$O372+'Sales & stores'!$O373)*'Profit and Loss'!Y51)+('Sales & stores'!$O374*'Profit and Loss'!Y53) -> 0.46077612 | Z55: =(('Sales & stores'!$O372+'Sales & stores'!$O373)*'Profit and Loss'!Z51)+('Sales & stores'!$O374*'Profit and Loss'!Z53) -> 0.46577612 | ... AK55: =(('Sales & stores'!$O372+'Sales & stores'!$O373)*'Profit and Loss'!AK51)+('Sales & stores'!$O374*'Profit and Loss'!AK53) -> 0.47677612
A56: Retail | EE56: 0.61 | EF56: 0.65 | EH56: 0.643 | EJ56: 0.635 | EL56: 0.636 | EM56: 0.573 | EN56: 0.628 | EP56: 0.605 | ER56: 0.622 | ET56: 0.609
A57: adidas | O57: =Interim!DI63 -> 0.636 | P57: =Interim!DQ63 -> 0.609 | Q57: 0.632 | R57: =+Interim!EG63 -> 0.636 | S57: =+Interim!EO63 -> 0.621 | T57: 0.631 | U57: 0.603 | V57: =U57+((V42-U42)+0.25%) -> 0.62591591 | W57: =V57+((W42-V42)+0.25%) -> 0.62841591 | X57: =W57+((X42-W42)+0.25%) -> 0.64274022 | Y57: =X57+((Y42-X42)+0.25%) -> 0.64681201 | Z57: =Y57+((Z42-Y42)+0.25%) -> 0.65244524 | AA57: =Z57+((AA42-Z42)+0.25%) -> 0.65600164 | AB57: =AA57+((AB42-AA42)+0.25%) -> 0.66983841 | AC57: =AB57+((AC42-AB42)+0.25%) -> 0.67233841 | ... AK57: =AJ57+((AK42-AJ42)+0.25%) -> 0.69233841 | EM57: =(EM56-EE56)*10000 -> -370 | EN57: =(EN56-EF56)*10000 -> -220 | EP57: =(EP56-EH56)*10000 -> -380 | ER57: =(ER56-EJ56)*10000 -> -130 | ET57: =(ET56-EL56)*10000 -> -270
A58: change in GM (bps) | P58: =Interim!DQ64 -> -270 | Q58: =(Q57-P57)*10000 -> 230 | R58: =+Interim!EG64 -> 40 | S58: =+Interim!EO64 -> -150 | T58: =(T57-S57)*10000 -> 100 | U58: =(U57-T57)*10000 -> -280 | V58: =(V57-U57)*10000 -> 229.15914 | W58: =(W57-V57)*10000 -> 25 | X58: =(X57-W57)*10000 -> 143.24301 | Y58: =(Y57-X57)*10000 -> 40.717912 | Z58: =(Z57-Y57)*10000 -> 56.332377 | AA58: =(AA57-Z57)*10000 -> 35.563972 | ... AK58: =(AK57-AJ57)*10000 -> 25 | EE58: 0.477 | EF58: 0.532 | EH58: 0.533 | EJ58: 0.523 | EL58: 0.519 | EM58: 0.407 | EN58: 0.51 | EP58: 0.446 | ER58: 0.543 | ET58: 0.481
A59: Reebok | O59: =Interim!DI65 -> 0.519 | P59: =Interim!DQ65 -> 0.481 | Q59: 0.548 | R59: =+Interim!EG65 -> 0.578 | S59: =+Interim!EO65 -> 0.551 | T59: 0.574 | U59: 0.541 | V59: =(V41-(('Sales & stores'!$O388+'Sales & stores'!$O389)*'Profit and Loss'!V10*'Profit and Loss'!V57))/(V$10*'Sales & stores'!$O390) -> 0.58482445 | W59: =(W41-(('Sales & stores'!$O388+'Sales & stores'!$O389)*'Profit and Loss'!W10*'Profit and Loss'!W57))/(W$10*'Sales & stores'!$O390) -> 0.57225277 | X59: =(X41-(('Sales & stores'!$O388+'Sales & stores'!$O389)*'Profit and Loss'!X10*'Profit and Loss'!X57))/(X$10*'Sales & stores'!$O390) -> 0.5716961 | Y59: =(Y41-(('Sales & stores'!$O388+'Sales & stores'!$O389)*'Profit and Loss'!Y10*'Profit and Loss'!Y57))/(Y$10*'Sales & stores'!$O390) -> 0.56072156 | Z59: =(Z41-(('Sales & stores'!$O388+'Sales & stores'!$O389)*'Profit and Loss'!Z10*'Profit and Loss'!Z57))/(Z$10*'Sales & stores'!$O390) -> 0.55133364 | AA59: =(AA41-(('Sales & stores'!$O388+'Sales & stores'!$O389)*'Profit and Loss'!AA10*'Profit and Loss'!AA57))/(AA$10*'Sales & stores'!$O390) -> 0.5398354 | AB59: =(AB41-(('Sales & stores'!$O388+'Sales & stores'!$O389)*'Profit and Loss'!AB10*'Profit and Loss'!AB57))/(AB$10*'Sales & stores'!$O390) -> 0.53878333 | AC59: =(AC41-(('Sales & stores'!$O388+'Sales & stores'!$O389)*'Profit and Loss'!AC10*'Profit and Loss'!AC57))/(AC$10*'Sales & stores'!$O390) -> 0.52621165 | ... AK59: =(AK41-(('Sales & stores'!$O388+'Sales & stores'!$O389)*'Profit and Loss'!AK10*'Profit and Loss'!AK57))/(AK$10*'Sales & stores'!$O390) -> 0.42563817 | EM59: =(EM58-EE58)*10000 -> -700 | EN59: =(EN58-EF58)*10000 -> -220 | EP59: =(EP58-EH58)*10000 -> -870 | ER59: =(ER58-EJ58)*10000 -> 200 | ET59: =(ET58-EL58)*10000 -> -380
A60: change in GM (bps) | P60: =Interim!DQ66 -> -380 | Q60: =(Q59-P59)*10000 -> 670 | R60: =+Interim!EG66 -> 300 | S60: =+Interim!EO66 -> -270 | T60: =(T59-S59)*10000 -> 230 | U60: =(U59-T59)*10000 -> -330 | V60: =(V59-U59)*10000 -> 438.24451 | W60: =(W59-V59)*10000 -> -125.71685 | X60: =(X59-W59)*10000 -> -5.5666877 | Y60: =(Y59-X59)*10000 -> -109.74542 | Z60: =(Z59-Y59)*10000 -> -93.879108 | AA60: =(AA59-Z59)*10000 -> -114.98249 | ... AK60: =(AK59-AJ59)*10000 -> -125.71685
A61: Retail check
A64: Sales by brand
A65: adidas | O65: =O71+O74 -> 7743 | P65: =P71+P74 -> 7483 | Q65: =Q71+Q74 -> 8657 | R65: =R71+R74 -> 9802 | S65: =S71+S74 -> 11186 | T65: =T71+T74 -> 11021 | U65: =U71+U74 -> 11676 | V65: =V202 -> 13708 | W65: =W202 -> 16051 | X65: =X202 -> 18647 | Y65: =Y202 -> 19406 | Z65: =Z202 -> 21289 | AA65: =AA202 -> 17961
A66: Growth | P66: =P65/O65-1 -> -0.033578716 | Q66: =Q65/P65-1 -> 0.15688895 | R66: =R65/Q65-1 -> 0.13226291 | S66: =S65/R65-1 -> 0.14119567 | T66: =T65/S65-1 -> -0.014750581 | U66: =U65/T65-1 -> 0.059431993 | V66: =V65/U65-1 -> 0.1740322 | W66: =W65/V65-1 -> 0.17092209 | ... AA66: =AA65/Z65-1 -> -0.15632486
A67: as % of sales | O67: =O65/O$89 -> 0.72061424 | P67: =P65/P$89 -> 0.72160077 | Q67: =Q65/Q$89 -> 0.72201835 | R67: =R65/R$89 -> 0.73572018 | S67: =S65/S$89 -> 0.75159578 | T67: =T65/T$89 -> 0.77585357 | U67: =U65/U$89 -> 0.80335764 | V67: =V65/V$89 -> 0.81040497 | ... AA67: =AA65/AA$89 -> 0.90510986
A68: Reebok | O68: =O77+O83+O85 -> 2148 | P68: =P77+P83+P85 -> 2013 | Q68: =Q77+Q83+Q85 -> 2365 | R68: =R77+R83+R85 -> 2433 | S68: =S77+S83+S85 -> 2195 | T68: =T77+T83+T85 -> 2148 | U68: =U77+U83+U85 -> 1847 | V68: =V77+V83+V85 -> 2002.47 | ... AA68: =AA77+AA83+AA85 -> 2412.417
A69: Growth | P69: =P68/O68-1 -> -0.062849162 | Q69: =Q68/P68-1 -> 0.17486339 | R69: =R68/Q68-1 -> 0.028752643 | S69: =S68/R68-1 -> -0.097821619 | T69: =T68/S68-1 -> -0.021412301 | U69: =U68/T68-1 -> -0.14013035 | V69: =V68/U68-1 -> 0.084174337 | W69: =W68/V68-1 -> 0.067178984 | ... AA69: =AA68/Z68-1 -> 0.07
A70: as % of sales | O70: =O68/O$89 -> 0.19990693 | P70: =P68/P$89 -> 0.19411765 | Q70: =Q68/Q$89 -> 0.19724771 | R70: =R68/R$89 -> 0.18261653 | S70: =S68/S$89 -> 0.14748371 | T70: =T68/T$89 -> 0.15121436 | U70: =U68/U$89 -> 0.12708133 | V70: =V68/V$89 -> 0.11838427 | ... AA70: =AA68/AA$89 -> 0.12156909
A71: adidas Sport Performance | O71: 6246 | P71: 5838 | Q71: 6523 | R71: 7189 | S71: 8035 | T71: 7845 | U71: 8259 | V71: =V65-V74 -> 9312.6555 | W71: =W65-W74 -> 9787.6341 | X71: =X65-X74 -> 9897.9685 | Y71: =Y65-Y74 -> 10300.851 | Z71: =Z65-Z74 -> 11127.364 | AA71: =AA65-AA74 -> 7253.9371
A72: Growth | P72: =P71/O71-1 -> -0.065321806 | Q72: =Q71/P71-1 -> 0.1173347 | R72: =R71/Q71-1 -> 0.10210026 | S72: =S71/R71-1 -> 0.11767979 | T72: =T71/S71-1 -> -0.023646546 | U72: =U71/T71-1 -> 0.052772467 | V72: =V71/U71-1 -> 0.12757665 | W72: =W71/V71-1 -> 0.051003562 | ... AA72: =AA71/Z71-1 -> -0.34809925
A73: as % of adidas brand | O73: =O71/O$65 -> 0.80666408 | P73: =P71/P$65 -> 0.78016838 | Q73: =Q71/Q$65 -> 0.75349428 | R73: =R71/R$65 -> 0.73342175 | S73: =S71/S$65 -> 0.7183086 | T73: =T71/T$65 -> 0.71182288 | U73: =U71/U$65 -> 0.70734841 | V73: =V71/V$65 -> 0.67935917 | ... AA73: =AA71/AA$65 -> 0.40387156
A74: adidas Sport Style | O74: 1497 | P74: 1645 | Q74: 2134 | R74: 2613 | S74: 3151 | T74: 3176 | U74: 3417 | V74: =U74*(1+V75) -> 4395.3445 | W74: =V74*(1+W75) -> 6263.3659 | X74: =W74*(1+X75) -> 8749.0315 | Y74: =X74*(1+Y75) -> 9105.1485 | Z74: =Y74*(1+Z75) -> 10161.636 | AA74: =Z74*(1+AA75) -> 10707.063
A75: Growth | P75: =P74/O74-1 -> 0.098864395 | Q75: =Q74/P74-1 -> 0.29726444 | R75: =R74/Q74-1 -> 0.22446111 | S75: =S74/R74-1 -> 0.20589361 | T75: =T74/S74-1 -> 0.0079339892 | U75: =U74/T74-1 -> 0.075881612 | V75: =22.5%+(V203-V204) -> 0.28631679 | W75: 0.425 | X75: 0.3968578 | Y75: =9%+(Y203-Y204) -> 0.040703598 | Z75: =8.5%+(Z203-Z204) -> 0.11603185 | AA75: =8%+(AA203-AA204) -> 0.053675137
A76: as % of adidas brand | O76: =O74/O$65 -> 0.19333592 | P76: =P74/P$65 -> 0.21983162 | Q76: =Q74/Q$65 -> 0.24650572 | R76: =R74/R$65 -> 0.26657825 | S76: =S74/S$65 -> 0.2816914 | T76: =T74/T$65 -> 0.28817712 | U76: =U74/U$65 -> 0.29265159 | V76: =V74/V$65 -> 0.32064083 | ... AA76: =AA74/AA$65 -> 0.59612844
A77: Reebok | O77: 1717 | P77: 1604 | Q77: 1913 | R77: 1962 | S77: 1667 | T77: 1599 | U77: 1578 | V77: =U77*(1+V78) -> 1720.02 | W77: =V77*(1+W78) -> 1840.4214 | X77: =W77*(1+X78) -> 1969.2509 | Y77: =X77*(1+Y78) -> 2107.0985 | Z77: =Y77*(1+Z78) -> 2254.5954 | AA77: =Z77*(1+AA78) -> 2412.417
A78: Growth | P78: =P77/O77-1 -> -0.065812464 | Q78: =Q77/P77-1 -> 0.19264339 | R78: =R77/Q77-1 -> 0.025614219 | S78: =S77/R77-1 -> -0.15035678 | T78: =T77/S77-1 -> -0.040791842 | U78: =U77/T77-1 -> -0.013133208 | V78: 0.09 | W78: =V78-2% -> 0.07 | X78: =W78 -> 0.07 | Y78: =X78 -> 0.07 | Z78: =Y78 -> 0.07 | AA78: =Z78 -> 0.07
A79: Other brands | O79: 1285 | P79: 1283 | Q79: 1420 | R79: 1580 | S79: 1976 | T79: 1946 | U79: 1316 | V79: =V27 -> 1467 | W79: =W27 -> 1475 | X79: =X27 -> 741 | Y79: =Y27 -> 831 | Z79: =Z27 -> 605 | AA79: =AA27 -> 476
A80: Growth | P80: =P79/O79-1 -> -0.0015564202 | Q80: =Q79/P79-1 -> 0.10678098 | R80: =R79/Q79-1 -> 0.11267606 | S80: =S79/R79-1 -> 0.25063291 | T80: =T79/S79-1 -> -0.015182186 | U80: =U79/T79-1 -> -0.32374101 | V80: =V79/U79-1 -> 0.11474164 | W80: =W79/V79-1 -> 0.0054533061 | ... AA80: =AA79/Z79-1 -> -0.21322314
A81: TaylorMade-adidas Golf | O81: 812 | P81: 831 | Q81: 909 | R81: 1044 | S81: 1344 | T81: 1285 | U81: 913 | V81: =V79-V85-V87 -> 1030.45 | W81: =W79-W85-W87 -> 1008.9175
A82: Growth | P82: =P81/O81-1 -> 0.023399015 | Q82: =Q81/P81-1 -> 0.093862816 | R82: =R81/Q81-1 -> 0.14851485 | S82: =S81/R81-1 -> 0.28735632 | T82: =T81/S81-1 -> -0.04389881 | U82: =U81/T81-1 -> -0.28949416 | V82: =V81/U81-1 -> 0.12864184 | W82: =W81/V81-1 -> -0.02089621
A83: Rockport | O83: 243 | P83: 232 | Q83: 252 | R83: 261 | S83: 285 | T83: 289 | U83: 0 | V83: =U83*(1+V84) -> 0 | W83: =V83*(1+W84) -> 0
A84: Growth | P84: =P83/O83-1 -> -0.04526749 | Q84: =Q83/P83-1 -> 0.086206897 | R84: =R83/Q83-1 -> 0.035714286 | S84: =S83/R83-1 -> 0.091954023 | T84: =T83/S83-1 -> 0.014035088 | U84: =U83/T83-1 -> -1
A85: Reebok-CCM Hockey | O85: 188 | P85: 177 | Q85: 200 | R85: 210 | S85: 243 | T85: 260 | U85: 269 | V85: =U85*(1+V86) -> 282.45 | W85: =V85*(1+W86) -> 296.5725
A86: Growth | P86: =P85/O85-1 -> -0.058510638 | Q86: =Q85/P85-1 -> 0.1299435 | R86: =R85/Q85-1 -> 0.05 | S86: =S85/R85-1 -> 0.15714286 | T86: =T85/S85-1 -> 0.069958848 | U86: =U85/T85-1 -> 0.034615385 | V86: 0.05 | W86: =V86 -> 0.05
A87: Other centrally managed brands | O87: 42 | P87: 43 | Q87: 59 | R87: 65 | S87: 104 | T87: 112 | U87: 134 | V87: =U87*(1+V88) -> 154.1 | W87: =V87*(1+W88) -> 169.51 | X87: =W87*(1+X88) -> 177.9855 | Y87: =X87*(1+Y88) -> 186.88477 | Z87: =Y87*(1+Z88) -> 196.22901 | AA87: =Z87*(1+AA88) -> 206.04046
A88: Growth | P88: =P87/O87-1 -> 0.023809524 | Q88: =Q87/P87-1 -> 0.37209302 | R88: =R87/Q87-1 -> 0.10169492 | S88: =S87/R87-1 -> 0.6 | T88: =T87/S87-1 -> 0.076923077 | U88: =U87/T87-1 -> 0.19642857 | V88: 0.15 | W88: 0.1 | X88: 0.05 | Y88: =X88 -> 0.05 | Z88: =Y88 -> 0.05 | AA88: =Z88 -> 0.05
A89: Total sales | O89: =SUM(O87,O85,O83,O81,O77,O74,O71) -> 10745 | P89: =SUM(P87,P85,P83,P81,P77,P74,P71) -> 10370 | Q89: =Q32 -> 11990 | R89: =R32 -> 13323 | S89: =S32 -> 14883 | T89: =T32 -> 14205 | U89: =U32 -> 14534 | V89: =V32 -> 16915 | W89: =W32 -> 19290 | X89: =X32 -> 21218 | ... AA89: =AA32 -> 19844
A90: Growth | P90: =P89/O89-1 -> -0.034899953 | Q90: =Q89/P89-1 -> 0.15621986 | R90: =R89/Q89-1 -> 0.11117598 | S90: =S89/R89-1 -> 0.11709075 | T90: =T89/S89-1 -> -0.045555332 | U90: =U89/T89-1 -> 0.023160859 | V90: =V89/U89-1 -> 0.16382276 | W90: =W89/V89-1 -> 0.14040792 | ... AA90: =AA89/Z89-1 -> -0.1606108
A91: Check | Q91: =SUM(Q87,Q85,Q83,Q81,Q77,Q74,Q71,-Q89) -> 0 | R91: =SUM(R87,R85,R83,R81,R77,R74,R71,-R89) -> 21 | S91: =SUM(S87,S85,S83,S81,S77,S74,S71,-S89) -> -54 | T91: =SUM(T87,T85,T83,T81,T77,T74,T71,-T89) -> 361 | U91: =SUM(U87,U85,U83,U81,U77,U74,U71,-U89) -> 36 | V91: =SUM(V87,V85,V83,V81,V77,V74,V71,-V89) -> -19.98 | W91: =SUM(W87,W85,W83,W81,W77,W74,W71,-W89) -> 76.4214 | X91: =SUM(X87,X85,X83,X81,X77,X74,X71,-X89) -> -423.7636 | ... AA91: =SUM(AA87,AA85,AA83,AA81,AA77,AA74,AA71,-AA89) -> 735.45749
A93: Sales by brand analysis
G94: =5.5/100 -> 0.055 | H94: =4.6/100 -> 0.046 | I94: =3.5/100 -> 0.035 | J94: =2.9/100 -> 0.029 | K94: =4/100 -> 0.04 | L94: =3.7/100 -> 0.037 | M94: =5.4/100 -> 0.054 | N94: =5.6/100 -> 0.056 | O94: =2.4/100 -> 0.024 | P94: =-3.5/100 -> -0.035 | Q94: =2.7/100 -> 0.027 | R94: =2.7/100 -> 0.027 | S94: =0.4/100 -> 0.004 | T94: =1/100 -> 0.01 | U94: =1.8/100 -> 0.018 | V94: =2.8/100 -> 0.028
A95: NEW REPORTING STRUCTURE
A96: SALES BY REGION | S96: =S49 -> FY 12E | T96: =T49 -> FY 13E | U96: =U49 -> FY 14E | V96: =V49 -> FY 15 | W96: =W49 -> FY 16 | X96: =X49 -> FY 17 | Y96: =Y49 -> FY 18 | Z96: =Z49 -> FY 19 | ... AK96: =AK49 -> FY 30E
A97: Western Europe/EMEA from 2020/Europe from 2022 | U97: =Interim!FE169 -> 3793 | V97: =Interim!FM169 -> 4539 | W97: =Interim!FU169 -> 5291 | X97: =Interim!GC169 -> 5883 | Y97: =Interim!GK169 -> 5884 | Z97: =Interim!GS169 -> 6071.42 | AA97: =Interim!HA169 -> 5320 | AB97: =Interim!HI169 -> 7760 | AC97: =Interim!HQ169 -> 8550 | AD97: =Interim!HY169 -> 6114.5 | AE97: =Interim!IG169 -> 7389.004 | AF97: =Interim!IO169 -> 8136 | AG97: =Interim!IW169 -> 8563.68 | AH97: =AG97*(1+AH98) -> 9001.2937 | AI97: =AH97*(1+AI98) -> 9451.3584 | AJ97: =AI97*(1+AJ98) -> 9923.9263 | AK97: =AJ97*(1+AK98) -> 10420.123
A98: Growth | V98: =V97/U97-1 -> 0.19667809 | W98: =W97/V97-1 -> 0.16567526 | X98: =X97/W97-1 -> 0.11188811 | Y98: =Interim!GK170 -> 0.0001699813 | Z98: =Interim!GS170 -> 0.031852481 | AA98: =Interim!HA170 -> -0.12376347 | AB98: =Interim!HI170 -> 0.23018389 | AC98: =Interim!HQ170 -> 0.10180412 | AD98: =Interim!HY170 -> -0.057426901 | AE98: =Interim!IG170 -> 0.20843961 | AF98: =Interim!IO170 -> 0.10109563 | AG98: =Interim!IW170 -> 0.052566372 | AH98: =AH100+AH99 -> 0.05110113 | AI98: =AI100+AI99 -> 0.05 | AJ98: =AJ100+AJ99 -> 0.05 | AK98: =AK100+AK99 -> 0.05
A99: FX & Scope | V99: =V98-V100 -> 0.022897706 | W99: =W98-W100 -> -0.03090879 | X99: =X98-X100 -> -0.015600026 | Y99: =Interim!GK171 -> 0.0043694725 | Z99: =Interim!GS171 -> 0.0012890891 | AA99: =Interim!HA171 -> -0.0051393513 | AB99: =Interim!HI171 -> -0.0083625555 | AC99: =Interim!HQ171 -> 0.014021134 | AD99: =Interim!HY171 -> -0.019160585 | AE99: =Interim!IG171 -> 0.0069019544 | AF99: =Interim!IO171 -> -0.0025279929 | AG99: =Interim!IW171 -> -0.0018633235 | AH99: =20%*AH457 -> 0.0011011301 | AI99: =20%*AI457 -> 0 | AJ99: =20%*AJ457 -> 0 | AK99: =20%*AK457 -> 0
A100: Currency Neutral | V100: =Interim!FM172 -> 0.17378038 | W100: =Interim!FU172 -> 0.19658405 | X100: =Interim!GC172 -> 0.12748814 | Y100: =Interim!GK172 -> -0.0041994912 | Z100: =Interim!GS172 -> 0.030563392 | AA100: =Interim!HA172 -> -0.11862412 | AB100: =Interim!HI172 -> 0.23854645 | AC100: =Interim!HQ172 -> 0.08778299 | AD100: =Interim!HY172 -> -0.038266316 | AE100: =Interim!IG172 -> 0.20153766 | AF100: =Interim!IO172 -> 0.10362362 | AG100: =Interim!IW172 -> 0.054429695 | AH100: 0.05 | AI100: 0.05 | AJ100: 0.05 | AK100: 0.05
A101: % of total | U101: =U97/U$143 -> 0.26099222 | V101: =V97/V$143 -> 0.26834171 | W101: =W97/W$143 -> 0.2742872 | X101: =X97/X$143 -> 0.27726459 | Y101: =Y97/Y$143 -> 0.2684919 | Z101: =Z97/Z$143 -> 0.25681739 | AA101: =AA97/AA$143 -> 0.26809111 | AB101: =AB97/AB$143 -> 0.36545163 | ... AK101: =AK97/AK$143 -> 0.29783388
A102: North America | U102: =Interim!FE174 -> 2217 | V102: =Interim!FM174 -> 2754 | W102: =Interim!FU174 -> 3412 | X102: =Interim!GC174 -> 4275 | Y102: =Interim!GK174 -> 4688 | Z102: =Interim!GS174 -> 5313 | AA102: =Interim!HA174 -> 4762 | AB102: =Interim!HI174 -> 5105 | AC102: =Interim!HQ174 -> 6398 | AD102: =Interim!HY174 -> 4844 | AE102: =Interim!IG174 -> 4927.017 | AF102: =Interim!IO174 -> 5087 | AG102: =Interim!IW174 -> 5551.7334 | AH102: =AG102*(1+AH103) -> 5992.35 | AI102: =AH102*(1+AI103) -> 6411.8145 | AJ102: =AI102*(1+AJ103) -> 6796.5234 | AK102: =AJ102*(1+AK103) -> 7204.3148
A103: Growth | V103: =V102/U102-1 -> 0.24221922 | W103: =W102/V102-1 -> 0.2389252 | X103: =X102/W102-1 -> 0.25293083 | Y103: =Interim!GK175 -> 0.096608187 | Z103: =Interim!GS175 -> 0.13331911 | AA103: =Interim!HA175 -> -0.10370789 | AB103: =Interim!HI175 -> 0.12967471 | AC103: =Interim!HQ175 -> 0.2532811 | AD103: =Interim!HY175 -> -0.2428884 | AE103: =Interim!IG175 -> 0.017138109 | AF103: =Interim!IO175 -> 0.03247056 | AG103: =Interim!IW175 -> 0.09135706 | AH103: =AH105+AH104 -> 0.079365605 | AI103: =AI105+AI104 -> 0.07 | AJ103: =AJ105+AJ104 -> 0.06 | AK103: =AK105+AK104 -> 0.06
A104: FX & Scope | V104: =V103-V105 -> 0.18881146 | W104: =W103-W105 -> -0.0016499637 | X104: =X103-X105 -> -0.021656213 | Y104: =Interim!GK176 -> -0.055979883 | Z104: =Interim!GS176 -> 0.058222696 | AA104: =Interim!HA176 -> -0.018145071 | AB104: =Interim!HI176 -> -0.045319097 | AC104: =Interim!HQ176 -> 0.13447581 | AD104: =Interim!HY176 -> -0.039682713 | AE104: =Interim!IG176 -> -0.0010022709 | AF104: =Interim!IO176 -> -0.061837934 | AG104: =Interim!IW176 -> -0.023986711 | AH104: =AH450 -> 0.0093656047 | AI104: =AI450 -> 0 | AJ104: =AJ450 -> 0 | AK104: =AK450 -> 0
A105: Currency Neutral | V105: =Interim!FM177 -> 0.053407758 | W105: =Interim!FU177 -> 0.24057516 | X105: =Interim!GC177 -> 0.27458705 | Y105: =Interim!GK177 -> 0.15258807 | Z105: =Interim!GS177 -> 0.075096416 | AA105: =Interim!HA177 -> -0.085562816 | AB105: =Interim!HI177 -> 0.1749938 | AC105: =Interim!HQ177 -> 0.11880529 | AD105: =Interim!HY177 -> -0.20320569 | AE105: =Interim!IG177 -> 0.01814038 | AF105: =Interim!IO177 -> 0.094308493 | AG105: =Interim!IW177 -> 0.11561431 | AH105: 0.07 | AI105: 0.07 | AJ105: 0.06 | AK105: 0.06
...

Sheet Interim
A1: =TODAY() -> 46294 | B1: 1995 | J1: 1996 | R1: 1997 | Z1: 1998 | AH1: 1999 | AP1: 2000 | AX1: 2001 | BF1: 2002 | BN1: 2003 | BV1: 2004 | CD1: 2005 | CL1: 2006 | CT1: 2007 | DB1: 2008 | DJ1: 2009 | DR1: 2010 | DZ1: 2011 | EH1: 2012 | EP1: 2013 | EX1: 2014 | FF1: 2015 | FN1: 2016 | FV1: 2017 | GD1: 2018E | JD1: 2015 | JK1: 2016
A2: ADIDAS -in EURmn | B2: Q1 95 | C2: Q2 95 | D2: H1 95 | E2: Q3 95 | F2: 9M 95 | G2: Q4 95 | H2: H2 95 | I2: FY 95 | J2: Q1 96 | K2: Q2 96 | L2: H1 96 | M2: Q3 96 | N2: 9M 96 | O2: Q4 96 | P2: H2 96 | Q2: FY 96 | R2: Q1 97 | S2: Q2 97 | T2: H1 97 | U2: Q3 97 | V2: 9M 97 | W2: Q4 97 | X2: H2 97 | Y2: FY 97 | Z2: Q1 98 | AA2: Q2 98 | AB2: H1 98 | AC2: Q3 98 | AD2: 9M 97 | AE2: Q4 98 | AF2: H2 98 | AG2: FY 98 | AH2: Q1 99 | AI2: Q2 99 | AJ2: H1 99 | AK2: Q3 99 | AL2: 9M 99 | AM2: Q4 99 | AN2: H2 99 | AO2: FY 99 | AP2: Q1 00 | AQ2: Q2 00 | AR2: H1 00 | AS2: Q3 00 | AT2: 9M 00 | AU2: Q4 00 | AV2: H2 00 | AW2: FY 00 | AX2: Q1 01 | AY2: Q2 01 | AZ2: H1 01 | BA2: Q3 01 | BB2: 9M 01 | BC2: Q4 01 | BD2: H2 01 | BE2: FY 01 | BF2: Q1 02 | BG2: Q2 02 | BH2: H1 02 | BI2: Q3 02 | BJ2: 9M 02 | BK2: Q4 02 | BL2: H2 02 | BM2: FY 02 | BN2: Q1 03 | BO2: Q2 03 | BP2: H1 03 | BQ2: Q3 03 | BR2: 9M 03 | BS2: Q4 03 | BT2: H2 03 | BU2: FY 03 | BV2: Q1 04 | BW2: Q2 04 | BX2: H1 04 | BY2: Q3 04 | BZ2: 9M 04 | CA2: Q4 04 | CB2: H2 04 | CC2: FY 04 | CD2: Q1 05 | CE2: Q2 05 | CF2: H1 05 | CG2: Q3 05 | CH2: 9M 05 | CI2: Q4 05 | CJ2: H2 05 | CK2: FY 05 | CL2: Q1 06 | CM2: Q2 06 | CN2: H1 06 | CO2: Q3 06 | CP2: 9M 06 | CQ2: Q4 06 | CR2: H2 06 | CS2: FY 06 | CT2: Q1 07 | CU2: Q2 07 | CV2: H1 07 | CW2: Q3 07 | CX2: 9M 07 | CY2: Q4 07 | CZ2: H2 07 | DA2: FY 07 | DB2: Q1 08 | DC2: Q2 08 | DD2: H1 08 | DE2: Q3 08 | DF2: 9M 08 | DG2: Q4 08 | DH2: H2 08 | DI2: FY 08 | DJ2: Q1 09 | DK2: Q2 09 | DL2: H1 09 | DM2: Q3 09 | DN2: 9M 09 | DO2: Q4 09 | DP2: H2 09 | DQ2: FY 09 | DR2: Q1 10 | DS2: Q2 10 | DT2: H1 10 | DU2: Q3 10 | DV2: 9M 10 | DW2: Q4 10 | DX2: H2 10 | DY2: FY 10 | DZ2: Q1 11 | EA2: Q2 11 | EB2: H1 11 | EC2: Q3 11 | ED2: 9M 11 | EE2: Q4 11 | EF2: H2 11 | EG2: FY 11 | EH2: Q1 12 | EI2: Q2 12 | EJ2: H1 12 | EK2: Q3 12 | EL2: 9M 12 | EM2: Q4 12 | EN2: H2 12 | EO2: FY 12 | EP2: 1Q13 | EQ2: 2Q13 | ER2: 1H13 | ES2: 3Q13 | ET2: 9M13 | EU2: 4Q13 | EV2: 2H13 | EW2: FY13 | EX2: 1Q14 | EY2: 2Q14 | EZ2: 1H14 | FA2: 3Q14 | FB2: 9M14 | FC2: 4Q14 | FD2: 2H14 | FE2: FY14 | FF2: 1Q15 | FG2: 2Q15 | FH2: 1H15 | FI2: 3Q15 | FJ2: 9M15 | FK2: 4Q15 | FL2: 2H15 | FM2: FY15 | FN2: 1Q16 | FO2: 2Q16 | FP2: 1H16 | FQ2: 3Q16 | FR2: 9M16 | FS2: 4Q16 | FT2: 2H16 | FU2: FY16 | FV2: 1Q17 | FW2: 2Q17 | FX2: 1H17 | FY2: 3Q17 | FZ2: 9M17 | GA2: 4Q17 | GB2: 2H17 | GC2: FY17 | GD2: 1Q18 | GE2: 2Q18 | GF2: 1H18 | GG2: 3Q18 | GH2: 9M18 | GI2: 4Q18 | GJ2: 2H18 | GK2: FY18 | GL2: 1Q19 | GM2: 2Q19 | GN2: 1H19 | GO2: 3Q19 | GP2: 9M19 | GQ2: 4Q19 | GR2: 2H19 | GS2: FY19 | GT2: 1Q20 | GU2: 2Q20 | GV2: 1H20 | GW2: 3Q20 | GX2: 9M20 | GY2: 4Q20 | GZ2: 2H20 | HA2: FY20 | HB2: 1Q21 | HC2: 2Q21 | HD2: 1H21 | HE2: 3Q21 | HF2: 9M21 | HG2: 4Q21 | HH2: 2H21 | HI2: FY21 | HJ2: 1Q22 | HK2: 2Q22 | HL2: 1H22 | HM2: 3Q22 | HN2: 9M22E | HO2: 4Q22 | HP2: 2H22 | HQ2: FY22 | HR2: 1Q23 | HS2: 2Q23 | HT2: 1H23 | HU2: 3Q23 | HV2: 9M23E | HW2: 4Q23 | HX2: 2H23 | HY2: FY23 | HZ2: 1Q24 | IA2: 2Q24 | IB2: 1H24 | IC2: 3Q24 | ID2: 9M24E | IE2: 4Q24 | IF2: 2H24E | IG2: FY24 | IH2: 1Q25 | II2: 2Q25 | IJ2: 1H25 | IK2: 3Q25 | IL2: 9M25E | IM2: 4Q25 | IN2: 2H25E | IO2: FY25 | IP2: 1Q26 | IQ2: 2Q26 | IR2: 1H25E | IS2: 3Q26E | IT2: 9M25E | IU2: 4Q26E | IV2: 2H25E | IW2: FY26E | JB2: Q3 | JC2: Q4 | JD2: Q1 | JE2: Q2 | JF2: 1H | JG2: Q3 | JH2: 9M | JI2: Q4 | JJ2: 2H | JK2: Q1 | JL2: Q2 | JM2: 1H | JN2: Q3 | JO2: 9M | JP2: Q4
A3: Interim Results | AD3: adidas-Salomon | CE3: =CE2/2 -> #VALUE!
A4: Sales by segment | DB4: =DB$2 -> Q1 08 | DC4: =DC$2 -> Q2 08 | DD4: =DD$2 -> H1 08 | DE4: =DE$2 -> Q3 08 | DF4: =DF$2 -> 9M 08 | DG4: =DG$2 -> Q4 08 | DH4: =DH$2 -> H2 08 | DI4: =DI$2 -> FY 08 | ... GS4: =GS$2 -> FY19 | GT4: 1Q20 | GU4: 2Q20 | GV4: 1H20 | GW4: 3Q20 | GX4: 9M20 | GY4: 4Q20 | GZ4: 2H20 | HA4: FY20 | HB4: 1Q21 | HC4: 2Q21 | HD4: 1H21 | HE4: 3Q21 | HF4: 9M21 | HG4: 4Q21 | HH4: 2H21 | HI4: FY21 | HJ4: 1Q22 | HK4: 2Q22 | HL4: 1H22 | HM4: 3Q22 | HN4: 9M22E | HO4: 4Q22 | HP4: 2H22 | HQ4: FY22 | HR4: 1Q23 | HS4: 2Q23 | HT4: 1H23E | HU4: 3Q23 | HV4: 9M23E | HW4: 4Q23 | HX4: 2H23 | HY4: FY23 | HZ4: 1Q24 | IA4: 2Q24 | IB4: 1H23E | IC4: 3Q24 | ID4: 9M23E | IE4: 4Q24 | IF4: 2H23 | IG4: FY24 | IH4: =IH2 -> 1Q25 | II4: =II2 -> 2Q25 | IJ4: =IJ2 -> 1H25 | IK4: =IK2 -> 3Q25 | IL4: =IL2 -> 9M25E | IM4: =IM2 -> 4Q25 | IN4: =IN2 -> 2H25E | IO4: =IO2 -> FY25 | ... IQ4: =IQ2 -> 2Q26
A5: Wholesale | DB5: 1968 | DC5: 1755 | DD5: =DB5+DC5 -> 3723 | DE5: 2241 | DF5: =DD5+DE5 -> 5964 | DG5: 1794 | DH5: =DE5+DG5 -> 4035 | DI5: ='Profit and Loss'!O5 -> 7758 | DJ5: 1874 | DK5: 1605 | DL5: =DJ5+DK5 -> 3479 | DM5: 2036 | DN5: =DM5+DL5 -> 5515 | DO5: 1650 | DP5: =DO5+DM5 -> 3686 | DQ5: ='Profit and Loss'!P5 -> 7164 | DR5: 1898 | DS5: 1928 | DT5: =DR5+DS5 -> 3826 | DU5: 2421 | DV5: =DT5+DU5 -> 6247 | DW5: =DY5-DV5 -> 1934 | DX5: =DU5+DW5 -> 4355 | DY5: ='Profit and Loss'!Q5 -> 8181 | DZ5: 2320 | EA5: 1973 | EB5: =DZ5+EA5 -> 4293 | EC5: =ED5-EB5 -> 2576 | ED5: 6869 | EE5: 2081 | EF5: =+EG5-EB5 -> 4657 | EG5: =DZ5+EA5+EC5+EE5 -> 8950 | EH5: 2614 | EI5: =+EJ5-EH5 -> 2113 | EJ5: 4727 | EK5: =EL5-EJ5 -> 2743 | EL5: 7470 | EM5: 2063 | EN5: =EK5+EM5 -> 4806 | EO5: =EH5+EI5+EK5+EM5 -> 9533 | EP5: 2481 | EQ5: =ER5-EP5 -> 2014 | ER5: 4495 | ES5: 2553 | ET5: =ER5+ES5 -> 7048 | EU5: 2052 | EV5: =ES5+EU5 -> 4605 | EW5: =EP5+EQ5+ES5+EU5 -> 9100 | EX5: 2357 | EY5: 2085 | EZ5: =EX5+EY5 -> 4442 | FA5: 2717 | FB5: =EZ5+FA5 -> 7159 | FC5: =EU5*(1+FC6) -> 2038.2274 | FD5: =FA5+FC5 -> 4755.2274 | FE5: =EZ5+FD5 -> 9197.2274 | FF5: =FF26-FF21-FF10 -> 2811 | FG5: =FG26-FG21-FG10 -> 2485 | FH5: =FH26-FH21-FH10 -> 5296 | FI5: =FI26-FI21-FI10 -> 3311 | FJ5: =FJ26-FJ21-FJ10 -> 8607 | FK5: =FK26-FK21-FK10 -> 2620 | FL5: =FM5-FH5 -> 5931 | FM5: =FM26-FM21-FM10 -> 11227 | FN5: =FN26-FN21-FN10 -> 3339 | FO5: =FO26-FO21-FO10 -> 2869 | FP5: =FP26-FP21-FP10 -> 6208 | FQ5: =FQ26-FQ21-FQ10 -> 3716 | FR5: =FR26-FR21-FR10 -> 9924 | FS5: =FS26-FS21-FS10 -> 2888 | FT5: =FT26-FT21-FT10 -> 6604 | ... GH5: =GH26-GH21-GH10 -> 11473 | GI5: =GI26-GI10-GI21 -> 3125 | GJ5: =GJ26-GJ21-GJ10 -> 7070 | GK5: =GK26-GK10-GK21 -> 14598 | GL5: =GL26-GL21-GL10 -> 4093 | GM5: =GM26-GM21-GM10 -> 3512 | GN5: =GN26-GN21-GN10 -> 7605 | GO5: =GO26-GO21-GO10 -> 4288 | GP5: =GP26-GP21-GP10 -> 11893 | GQ5: =GQ26-GQ10-GQ21 -> 3329 | GR5: =GR26-GR21-GR10 -> 7617 | GS5: =GS26-GS10-GS21 -> 15222 | GT5: =GT26-GT21-GT10 -> 3002 | GU5: =GU26-GU21-GU10 -> 1675 | GV5: =GV26-GV21-GV10 -> 4677 | GW5: =GW26-GW21-GW10 -> 3707.232 | GY5: =HA5-GW5-GU5-GT5 -> 2852.768 | GZ5: =GZ26-GZ21-GZ10 -> 6560 | HA5: ='Profit and Loss'!AA5 -> 11237 | HB5: =HB26-HB21-HB10 -> 3420 | HC5: =HC26-HC21-HC10 -> 3139 | HD5: =HD26-HD21-HD10 -> 6559 | HE5: =HE26-HE21-HE10 -> 3694 | HG5: =HI5-HE5-HC5-HB5 -> 2543.003 | HH5: =HH26-HH21-HH10 -> 6359 | HI5: ='Profit and Loss'!AB5 -> 12796.003 | HJ5: =HJ26-HJ21-HJ10 -> 3361 | HK5: =HK26-HK21-HK10 -> 3451 | HM5: =HM26-HM21-HM10 -> 4050 | HO5: =HQ5-HM5-HK5-HJ5 -> 2661 | HP5: =HP26-HP21-HP10 -> 6828 | HQ5: ='Profit and Loss'!AC5 -> 13523 | HR5: =HR26-HR21-HR10 -> 3420 | HS5: =HS26-HS21-HS10 -> 2557 | HU5: =HU26-HU21-HU10 -> 3369 | HW5: =HY5-HU5-HS5-HR5 -> 2446 | HX5: =HX26-HX21-HX10 -> 5815 | HY5: ='Profit and Loss'!AD5 -> 11792 | HZ5: =HZ26-HZ21-HZ10 -> 3230 | IA5: =IA26-IA21-IA10 -> 3211 | IC5: =IC26-IC21-IC10 -> 3863 | IE5: =IE26-IE21-IE10 -> 3155 | IG5: =IG26-IG21-IG10 -> 13543 | IH5: =IH26-IH21-IH10 -> 3969 | II5: =II26-II21-II10 -> 3600 | IK5: =IK26-IK21-IK10 -> 4192 | IM5: =IM26-IM21-IM10 -> 3048 | IO5: =IO26-IO21-IO10 -> 14808 | IP5: =IP26-IP21-IP10 -> 4050 | IQ5: =IQ26-IQ21-IQ10 -> 3805
A6: Growth | DJ6: =DJ5/DB5-1 -> -0.047764228 | DK6: =DK5/DC5-1 -> -0.085470085 | DL6: =DL5/DD5-1 -> -0.065538544 | DM6: =DM5/DE5-1 -> -0.091477019 | DN6: =DN5/DF5-1 -> -0.075285044 | DO6: =DO5/DG5-1 -> -0.080267559 | DP6: =DP5/DH5-1 -> -0.086493185 | DQ6: =DQ5/DI5-1 -> -0.076566125 | ... FB6: =FB5/ET5-1 -> 0.015749149 | FC6: =FC7+FC8 -> -0.0067117918 | FD6: =FD5/EV5-1 -> 0.032622672 | FE6: =FE5/EW5-1 -> 0.01068433 | FF6: =FF5/EX5-1 -> 0.19261773 | FG6: =FG5/EY5-1 -> 0.19184652 | FH6: =FH5/EZ5-1 -> 0.19225574 | FI6: =FI5/FA5-1 -> 0.21862348 | FJ6: =FJ5/FB5-1 -> 0.20226289 | FK6: =FK5/FC5-1 -> 0.28543066 | ... GW6: =GW5/GO5-1 -> -0.1354403 | GY6: =GY5/GQ5-1 -> -0.14305557 | GZ6: =GZ5/GR5-1 -> -0.13876854 | HA6: =HA5/GS5-1 -> -0.26179214 | HB6: =HB5/2917-1 -> 0.17243744 | HC6: =HC5/GU5-1 -> 0.87402985 | HD6: =HD5/GV5-1 -> 0.4023947 | HE6: =HE5/GW5-1 -> -0.0035692398 | HG6: =HG5/GY5-1 -> -0.108584 | HH6: =HH5/GZ5-1 -> -0.030640244 | HI6: =HI5/HA5-1 -> 0.13873837 | HJ6: =HJ5/HB5-1 -> -0.017251462 | HK6: =HK5/HC5-1 -> 0.099394712 | HM6: =HM5/HE5-1 -> 0.096372496 | HO6: =HO5/HG5-1 -> 0.046400639 | HP6: =HP5/HH5-1 -> 0.073753735 | HQ6: =HQ5/HI5-1 -> 0.056814379 | HR6: =HR5/HJ5-1 -> 0.017554299 | HS6: =HS5/HK5-1 -> -0.25905535 | HU6: =HU5/HM5-1 -> -0.16814815 | HW6: =HW5/HO5-1 -> -0.080796693 | HX6: =HX5/HP5-1 -> -0.1483597 | HY6: =HY5/HQ5-1 -> -0.12800414 | HZ6: =HZ5/HR5-1 -> -0.055555556 | IA6: =IA5/HS5-1 -> 0.25576848 | IC6: =IC5/HU5-1 -> 0.14663105 | IH6: =IH5/HZ5-1 -> 0.22879257 | II6: =II5/IA5-1 -> 0.12114606 | IK6: =IK5/IC5-1 -> 0.085166969 | IM6: -0.06 | IO6: 0.07 | IP6: =IP5/IH5-1 -> 0.020408163 | IQ6: =IQ5/II5-1 -> 0.056944444
A7: FX & Scope impact | DJ7: =DJ6-DJ8 -> 0.032235772 | DK7: =DK6-DK8 -> 0.044529915 | DL7: =DL6-DL8 -> 0.038031158 | DM7: =DM6-DM8 -> -0.0014770192 | DN7: =DN6-DN8 -> 0.023185781 | DO7: =DO6-DO8 -> -0.040267559 | DP7: =DP6-DP8 -> -0.018723668 | DQ7: =DQ6-DQ8 -> 0.013433875 | ... DW7: =DW6-DW8 -> 0.096121212 | DX7: =((DW7*DO5)+(DU7*DM5))/DP5 -> 0.094450353 | DY7: ='Profit and Loss'!Q7 -> 0.066959799 | DZ7: =DZ6-DZ8 -> 0.042339305 | EA7: =EA6-EA8 -> -0.036659751 | EB7: =EB6-EB8 -> -0.0079404077 | EC7: =EC6-EC8 -> -0.035976869 | ED7: =ED6-ED8 -> -0.020432207 | EE7: =+EE6-EE8 -> -0.013991727 | EF7: =+EF6-EF8 -> -0.023083812 | EG7: =EG6-EG8 -> -0.016001711 | EH7: =+EH6-EH8 -> 0.026724138 | EI7: =+EI6-EI8 -> 0.060957932 | EJ7: =+EJ6-EJ8 -> 0.041094805 | EK7: =EK6-EK8 -> 0.060829193 | EL7: =EL6-EL8 -> 0.048494541 | EM7: =EM6-EM8 -> 0.027350312 | EN7: =+EN6-EN8 -> 0.045869014 | EO7: =+EO6-EO8 -> 0.044232626 | EP7: =EP6-EP8 -> -0.018879878 | EQ7: =EQ6-EQ8 -> -0.036852816 | ER7: =ER6-ER8 -> -0.027079755 | ES7: =ES6-ES8 -> -0.061267226 | ET7: =ET6-ET8 -> -0.039528514 | EU7: =EU6-EU8 -> -0.084332041 | EV7: =EV6-EV8 -> -0.071167915 | EW7: =EW6-EW8 -> -0.049224274 | ... FB7: =FB6-FB8 -> -0.046013763 | FC7: =((EU95*(0.1*FC492)+EU100*FC102+EU105*FC483+EU110*FC112+EU115*FC117+EU120*FC122)/EU127)-(FE842/EW5) -> -0.056711792 | FD7: =FD6-FD8 -> -0.036781237 | FE7: =FE6-FE8 -> -0.04842611 | FF7: =FF6-FF8 -> 0.10728978 | FG7: =FG6-FG8 -> 0.1217689 | FH7: =FH6-FH8 -> 0.11504369 | FI7: =FI6-FI8 -> 0.078377003 | FJ7: =FJ6-FJ8 -> 0.099814275 | FK7: =FK6-FK8 -> 0.14314646 | ... GH7: =GH6-GH8 -> -0.068441891 | GI7: =GI12 -> -0.010189798 | GJ7: =GJ6-GJ8 -> -0.035242553 | GK7: =GK12 -> -0.051358092 | GL7: =GL6-GL8 -> 0.014795133 | GM7: =GM6-GM8 -> 0.0050951157 | GN7: =GN6-GN8 -> 0.010567295 | GO7: =GO6-GO8 -> 0.027649937 | GP7: =GP6-GP8 -> 0.016441175 | GQ7: =GQ12 -> 0.02595339 | GR7: =GR6-GR8 -> 0.018627864 | GS7: =GS12 -> 0.01823927 | GT7: =GT6-GT8 -> -0.0013542634 | GU7: =GU6-GU8 -> -0.0018962642 | GV7: =GV6-GV8 -> -0.0016045602 | GW7: =GW6-GW8 -> -0.038094216 | GY7: =GY6-GY8 -> -0.047954575 | GZ7: =GZ6-GZ8 -> -0.042403673 | HA7: =HA6-HA8 -> -0.025149222 | HB7: =HB6-HB8 -> -0.26695235 | HC7: =HC6-HC8 -> -0.10308095 | HD7: =HD6-HD8 -> -0.2338473 | HE7: =HE6-HE8 -> -0.037240921 | HG7: =HG6-HG8 -> -0.059263094 | HH7: =HH6-HH8 -> -0.028220675 | HI7: =HI6-HI8 -> -0.062311503 | HJ7: =HJ6-HJ8 -> 0.032522358 | HK7: =HK6-HK8 -> 0.064249124 | HM7: =HM6-HM8 -> 0.060837033 | HO7: =HO6-HO8 -> 0.061403374 | HP7: =HP6-HP8 -> 0.059110552 | HQ7: =HQ6-HQ8 -> 0.052578603 | HR7: =HR6-HR8 -> 0.0072691432 | HS7: =HS6-HS8 -> -0.031002318 | HU7: =HU6-HU8 -> -0.01906929 | HW7: =HW6-HW8 -> 0.10403871 | HX7: =HX6-HX8 -> 0.012099645 | HY7: =HY6-HY8 -> 0.032619417 | HZ7: =HZ6-HZ8 -> -0.090091687 | IA7: =IA6-IA8 -> 0.067359406 | IC7: =IC6-IC8 -> 0.016841793 | IH7: =IH6-IH8 -> 0.033613136 | II7: =II6-II8 -> -0.066645905 | IK7: =IK6-IK8 -> -0.021878007 | IM7: =IM6-IM8 -> -0.08 | IO7: =IO6-IO8 -> -0.05 | IP7: =IP6-IP8 -> -0.059591837 | IQ7: =IQ6-IQ8 -> -0.0035027778 | JA7: 2 year | JB7: =(EK5*(1+ES8)*(1+FA8))/EK5-1 -> 0.07632 | JC7: =(EM5*(1+EU8)*(1+FC8))/EM5-1 -> 0.13295 | JD7: =(EP5*(1+EX8)*(1+FF8))/EP5-1 -> 0.091839927 | JE7: =(EQ5*(1+EY8)*(1+FG8))/EQ5-1 -> 0.17815546 | JF7: =(EJ5*(1+ER8)*(1+EZ8))/EJ5-1 -> 0.025496641 | JG7: =(ES5*(1+FA8)*(1+FI8))/ES5-1 -> 0.23716743 | JH7: =(EL5*(1+ET8)*(1+FB8))/EL5-1 -> 0.043751035 | JI7: =(EU5*(1+FC8)*(1+FK8))/EU5-1 -> 0.19939842 | JJ7: =(EN5*(1+EV8)*(1+FD8))/EN5-1 -> 0.10078577 | JK7: =(EX5*(1+FF8)*(1+FN8))/EX5-1 -> 0.33761671 | JL7: =(EY5*(1+FG8)*(1+FO8))/EY5-1 -> 0.31380125 | JM7: =(EZ5*(1+FH8)*(1+FP8))/EZ5-1 -> 0.32524297 | JN7: =(FA5*(1+FI8)*(1+FQ8))/FA5-1 -> 0.32360438 | JO7: =(FB5*(1+FJ8)*(1+FR8))/FB5-1 -> 0.32683795 | JP7: =(FC5*(1+FK8)*(1+FS8))/FC5-1 -> 0.28829995
A8: Currency neutral | DJ8: -0.08 | DK8: -0.13 | DL8: =(DJ8*DB5+DK8*DC5)/DD5 -> -0.1035697 | DM8: -0.09 | DN8: =(DJ8*DB5+DK8*DC5+DM8*DE5)/DF5 -> -0.098470825 | DO8: -0.04 | DP8: =(DM8*DE5+DO8*DG5)/DH5 -> -0.067769517 | DQ8: ='Profit and Loss'!P8 -> -0.09 | DR8: 0.01 | DS8: 0.121 | DT8: 0.06 | DU8: 0.096 | DV8: 0.075 | DW8: 0.076 | DX8: =DX6-DX7 -> 0.087047206 | DY8: =DY6-DY7 -> 0.075 | DZ8: 0.18 | EA8: 0.06 | EB8: 0.13 | EC8: 0.1 | ED8: 0.12 | EE8: 0.09 | EF8: =(-EB8*DT5+EG8*DY5)/DX5 -> 0.092429392 | EG8: 0.11 | EH8: 0.1 | EI8: 0.01 | EJ8: 0.06 | EK8: 0.004 | EL8: 0.039 | EM8: -0.036 | EN8: =+(EK8*EC5+EM8*EE5)/EF5 -> -0.013874168 | EO8: =(EH8*DZ5+EI8*EA5+EK8*EC5+EM8*EE5)/EG5 -> 0.020907039 | EP8: -0.032 | EQ8: -0.01 | ER8: -0.022 | ES8: -0.008 | ET8: =(EH5*EP8+EI5*EQ8+EK5*ES8)/EL5 -> -0.016964123 | EU8: 0.079 | EV8: =(EK5*ES8+EM5*EU8)/EN5 -> 0.029345194 | EW8: =(EH5*EP8+EI5*EQ8+EK5*ES8+EM5*EU8)/EO5 -> 0.003803105 | EX8: 0.006 | EY8: 0.101 | EZ8: =(EP5*EX8+EQ5*EY8)/ER5 -> 0.048565072 | FA8: 0.085 | FB8: =(EP5*EX8+EQ5*EY8+ES5*FA8)/ET5 -> 0.061762911 | FC8: 0.05 | FD8: =(ES5*FA8+EU5*FC8)/EV5 -> 0.069403909 | FE8: =(EP5*EX8+EQ5*EY8+ES5*FA8+EU5*FC8)/EW5 -> 0.05911044 | FF8: =(EX26*FF29-EX10*FF13-EX21*FF24)/EX5 -> 0.085327959 | FG8: =(EY26*FG29-EY10*FG13-EY21*FG24)/EY5 -> 0.070077618 | FH8: =(EZ26*FH29-EZ10*FH13-EZ21*FH24)/EZ5 -> 0.077212051 | FI8: =(FA26*FI29-FA10*FI13-FA21*FI24)/FA5 -> 0.14024648 | FJ8: =(FB26*FJ29-FB10*FJ13-FB21*FJ24)/FB5 -> 0.10244861 | FK8: =(FC26*FK29-FC10*FK13-FC21*FK24)/FC5 -> 0.14228421 | FL8: =(FE5*FM8-EZ5*FH8)/FD5 -> 0.14100559 | FM8: =(FE26*FM29-FE10*FM13-FE21*FM24)/FE5 -> 0.11019512 | FN8: =(FF26*FN29-FF21*FN24-FF10*FN13)/FF5 -> 0.23245393 | FO8: =(FG26*FO29-FG21*FO24-FG10*FO13)/FG5 -> 0.22776258 | FP8: =(FH26*FP29-FH21*FP24-FH10*FP13)/FH5 -> 0.23025264 | FQ8: =(FI26*FQ29-FI21*FQ24-FI10*FQ13)/FI5 -> 0.1608055 | FR8: =(FJ26*FR29-FJ21*FR24-FJ10*FR13)/FJ5 -> 0.20353724 | FS8: =(FK26*FS29-FK21*FS24-FK10*FS13)/FK5 -> 0.12782786 | FT8: =(FL26*FT29-FL21*FT24-FL10*FT13)/FL5 -> 0.14623773 | FU8: =(FM26*FU29-FM21*FU24-FM10*FU13)/FM5 -> 0.18586924 | ... GH8: =(FZ26*GH29-FZ21*GH24-FZ10*GH13)/FZ5 -> 0.074757127 | GI8: =GI6-GI7 -> -0.018106222 | GJ8: =(GB26*GJ29-GB21*GJ24-GB10*GJ13)/GB5 -> 0.0057298559 | GK8: =GK6-GK7 -> 0.050058236 | GL8: =(GD26*GL29-GD21*GL24-GD10*GL13)/GD5 -> 0.0015942389 | GM8: =(GE26*GM29-GE21*GM24-GE10*GM13)/GE5 -> -0.0019531562 | GN8: =(GF26*GN29-GF21*GN24-GF10*GN13)/GF5 -> -0.00033881509 | GO8: =(GG26*GO29-GG21*GO24-GG10*GO13)/GG5 -> 0.059295564 | GP8: =(GH26*GP29-GH21*GP24-GH10*GP13)/GH5 -> 0.020166513 | GQ8: =GQ6-GQ7 -> 0.03932661 | GR8: =(GJ26*GR29-GJ21*GR24-GJ10*GR13)/GJ5 -> 0.058741301 | GS8: =GS6-GS7 -> 0.024506312 | GT8: =(GL26*GT29-GL21*GT24-GL10*GT13)/GL5 -> -0.26519839 | GU8: =(GM26*GU29-GM21*GU24-GM10*GU13)/GM5 -> -0.52116752 | GV8: =(GN26*GV29-GN21*GV24-GN10*GV13)/GN5 -> -0.3834053 | GW8: =(GO26*GW29-GO21*GW24-GO10*GW13)/GO5 -> -0.097346082 | GY8: =(GQ26*GY29-GQ21*GY24-GQ10*GY13)/GQ5 -> -0.095100997 | GZ8: =(GR26*GZ29-GR21*GZ24-GR10*GZ13)/GR5 -> -0.096364871 | HA8: =(GS26*HA29-GS21*HA24-GS10*HA13)/GS5 -> -0.23664292 | HB8: =(4381*HB29-47*HB24-1464*HB13)/2917 -> 0.43938978 | HC8: =(GU26*HC29-GU21*HC24-GU10*HC13)/GU5 -> 0.9771108 | HD8: =(GV26*HD29-GV21*HD24-GV10*HD13)/GV5 -> 0.636242 | HE8: =(GW26*HE29-GW21*HE24-GW10*HE13)/GW5 -> 0.033671681 | HG8: =(GY26*HG29-GY21*HG24-GY10*HG13)/GY5 -> -0.049320908 | HH8: =(GZ26*HH29-GZ21*HH24-GZ10*HH13)/GZ5 -> -0.0024195694 | HI8: =(HA26*HI29-HA21*HI24-HA10*HI13)/HA5 -> 0.20104987 | HJ8: =(4381*HJ29-47*HJ24-1464*HJ13)/2917 -> -0.04977382 | HK8: =(HC26*HK29-HC21*HK24-HC10*HK13)/HC5 -> 0.035145588 | HM8: =(HE26*HM29-HE21*HM24-HE10*HM13)/HE5 -> 0.035535463 | HO8: =(HG26*HO29-HG21*HO24-HG10*HO13)/HG5 -> -0.015002735 | HP8: =(HH26*HP29-HH21*HP24-HH10*HP13)/HH5 -> 0.014643183 | HQ8: =(HI26*HQ29-HI21*HQ24-HI10*HQ13)/HI5 -> 0.0042357758 | HR8: =(4381*HR29-47*HR24-1464*HR13)/2917 -> 0.010285156 | HS8: =(HK26*HS29-HK21*HS24-HK10*HS13)/HK5 -> -0.22805303 | HU8: =(HM26*HU29-HM21*HU24-HM10*HU13)/HM5 -> -0.14907886 | HW8: =(HO26*HW29-HO21*HW24-HO10*HW13)/HO5 -> -0.1848354 | HX8: =(HP26*HX29-HP21*HX24-HP10*HX13)/HP5 -> -0.16045934 | HY8: =(HQ26*HY29-HQ21*HY24-HQ10*HY13)/HQ5 -> -0.16062356 | HZ8: =(4381*HZ29-47*HZ24-1464*HZ13)/2917 -> 0.034536131 | IA8: =(HS26*IA29-HS21*IA24-HS10*IA13)/HS5 -> 0.18840907 | IC8: =(HU26*IC29-HU21*IC24-HU10*IC13)/HU5 -> 0.12978925 | IH8: =(4381*IH29-47*IH24-1464*IH13)/2917 -> 0.19517943 | II8: =(IA26*II29-IA21*II24-IA10*II13)/IA5 -> 0.18779197 | IK8: =(IC26*IK29-IC21*IK24-IC10*IK13)/IC5 -> 0.10704498 | IM8: 0.02 | IO8: 0.12 | IP8: 0.08 | IQ8: =(II26*IQ29-II21*IQ24-II10*IQ13)/II5 -> 0.060447222 | JA8: 3 year | JB8: =(EC5*(1+EK8)*(1+ES8)*(1+FA8))/EC5-1 -> 0.08062528 | JC8: =(EE5*(1+EM8)*(1+EU8)*(1+FC8))/EE5-1 -> 0.0921638 | JD8: =(EH5*(1+EP8)*(1+EX8)*(1+FF8))/EH5-1 -> 0.056901049 | JE8: =(EI5*(1+EQ8)*(1+EY8)*(1+FG8))/EI5-1 -> 0.1663739 | JF8: =(EB5*(1+EJ8)*(1+ER8)*(1+EZ8))/EB5-1 -> 0.087026439 | JG8: =(EK5*(1+ES8)*(1+FA8)*(1+FI8))/EK5-1 -> 0.22727009 | JH8: =(ED5*(1+EL8)*(1+ET8)*(1+FB8))/ED5-1 -> 0.084457325 | JI8: =(EM5*(1+EU8)*(1+FC8)*(1+FK8))/EM5-1 -> 0.29415089 | JJ8: =(EF5*(1+EN8)*(1+EV8)*(1+FD8))/EF5-1 -> 0.085513287 | JK8: =(EP5*(1+EX8)*(1+FF8)*(1+FN8))/EP5-1 -> 0.34564241 | JL8: =(EQ5*(1+EY8)*(1+FG8)*(1+FO8))/EQ5-1 -> 0.44649518 | JM8: =(ER5*(1+EZ8)*(1+FH8)*(1+FP8))/ER5-1 -> 0.38960349 | JN8: =(ES5*(1+FA8)*(1+FI8)*(1+FQ8))/ES5-1 -> 0.43611075 | JO8: =(ET5*(1+FB8)*(1+FJ8)*(1+FR8))/ET5-1 -> 0.40878733 | JP8: =(EU5*(1+FC8)*(1+FK8)*(1+FS8))/EU5-1 -> 0.35271495
A9: % of total | DB9: =DB5/DB$26 -> 0.75315729 | DC9: =DC5/DC$26 -> 0.69809069 | DD9: =DD5/DD$26 -> 0.72615565 | DE9: =DE5/DE$26 -> 0.72783371 | DF9: =DF5/DF$26 -> 0.72678528 | DG9: =DG5/DG$26 -> 0.69642857 | DH9: =DH5/DH$26 -> 0.71352785 | DI9: =DI5/DI$26 -> 0.81560161 | ... GW9: =GW5/GW$26 -> 0.62156805 | GY9: =GY5/GY$26 -> 0.51419468 | GZ9: =GZ5/GZ$26 -> 0.56982269 | HA9: =HA5/HA$26 -> 0.56626688 | HB9: =HB5/HB$26 -> 0.64920273 | HC9: =HC5/HC$26 -> 0.61827851 | HD9: =HD5/HD$26 -> 0.6340261 | HE9: =HE5/HE$26 -> 0.6422114 | HG9: =HG5/HG$26 -> 0.4950366 | HH9: =HH5/HH$26 -> 0.58398384 | HI9: =HI5/HI$26 -> 0.60261858 | HJ9: =HJ5/HJ$26 -> 0.63391173 | HK9: =HK5/HK$26 -> 0.61658031 | HM9: =HM5/HM$26 -> 0.63202247 | HO9: =HO5/HO$26 -> 0.51133743 | HP9: =HP5/HP$26 -> 0.58214682 | HQ9: =HQ5/HQ$26 -> 0.60072853 | HR9: =HR5/HR$26 -> 0.64846416 | HS9: =HS5/HS$26 -> 0.51729719 | HU9: =HU5/HU$26 -> 0.59638874 | HW9: =HW5/HW$26 -> 0.50831255 | HX9: =HX5/HX$26 -> 0.5558742 | HY9: =HY5/HY$26 -> 0.57026792 | HZ9: =HZ5/HZ$26 -> 0.60851545 | IA9: =IA5/IA$26 -> 0.57114906 | IC9: =IC5/IC$26 -> 0.619269 | IH9: =IH5/IH$26 -> 0.64505119 | II9: =II5/II$26 -> 0.60483871 | IK9: =IK5/IK$26 -> 0.63227753 | IM9: =IM5/IM$26 -> 0.50164582 | IO9: =IO5/IO$26 -> 0.59683205 | IP9: =IP5/IP$26 -> 0.61438107 | IQ9: =IQ5/IQ$26 -> 0.56428889
A10: Retail | DB10: 360 | DC10: 423 | DD10: =DB10+DC10 -> 783 | DE10: 491 | DF10: =DD10+DE10 -> 1274 | DG10: 464 | DH10: =DE10+DG10 -> 955 | DI10: ='Profit and Loss'!O10 -> 1738 | DJ10: 400 | DK10: 486 | DL10: =DJ10+DK10 -> 886 | DM10: 524 | DN10: =DM10+DL10 -> 1410 | DO10: 497 | DP10: =DO10+DM10 -> 1021 | DQ10: ='Profit and Loss'!P10 -> 1906 | DR10: 459 | DS10: 602 | DT10: =DR10+DS10 -> 1061 | DU10: 665 | DV10: =DT10+DU10 -> 1726 | DW10: =DY10-DV10 -> 663 | DX10: =DU10+DW10 -> 1328 | DY10: ='Profit and Loss'!Q10 -> 2389 | DZ10: 577 | EA10: 681 | EB10: =DZ10+EA10 -> 1258 | EC10: =ED10-EB10 -> 757 | ED10: 2015 | EE10: =+EF10-EC10 -> 778 | EF10: =+EG10-EB10 -> 1535 | EG10: 2793 | EH10: 693 | EI10: =+EJ10-EH10 -> 854 | EJ10: 1547 | EK10: =EL10-EJ10 -> 944 | EL10: 2491 | EM10: 882 | EN10: =EK10+EM10 -> 1826 | EO10: =EH10+EI10+EK10+EM10 -> 3373 | EP10: 722 | EQ10: =ER10-EP10 -> 867 | ER10: 1589 | ES10: 923 | ET10: =ER10+ES10 -> 2512 | EU10: 934 | EV10: =ES10+EU10 -> 1857 | EW10: =EP10+EQ10+ES10+EU10 -> 3446 | EX10: 794 | EY10: 958 | EZ10: =EX10+EY10 -> 1752 | FA10: 1047 | FB10: =EZ10+FA10 -> 2799 | FC10: =EU10*(1+FC11) -> 1021.5652 | FD10: =FA10+FC10 -> 2068.5652 | FE10: =EZ10+FD10 -> 3820.5652 | FF10: 895 | FG10: =FH10-FF10 -> 1057 | FH10: 1952 | FI10: =FJ10-FH10 -> 1104 | FJ10: 3056 | FK10: =FM10-FJ10 -> 1165 | FL10: =FM10-FH10 -> 2269 | FM10: 4221 | FN10: 1034 | FO10: =FP10-FN10 -> 1177 | FP10: 2211 | FQ10: 1330 | FR10: =FN10+FO10+FQ10 -> 3541 | FS10: =FU10-FN10-FO10-FQ10 -> 1462 | FT10: =FQ10+FS10 -> 2792 | FU10: 5003 | FV10: 1290 | FW10: 1467 | FX10: =FV10+FW10 -> 2757 | FY10: 1417 | FZ10: =FV10+FW10+FY10 -> 4174 | GA10: =GC10-FV10-FW10-FY10 -> 1686 | GB10: =FY10+GA10 -> 3103 | GC10: 5860 | GD10: 1331 | GE10: 1571 | GF10: =GD10+GE10 -> 2902 | GG10: 1698 | GH10: =GD10+GE10+GG10 -> 4600 | GI10: =GK10-GD10-GE10-GG10 -> 1888 | GJ10: =GG10+GI10 -> 3586 | GK10: 6488 | GL10: 1595 | GM10: 1850 | GN10: =GL10+GM10 -> 3445 | GO10: 1960 | GP10: =GL10+GM10+GO10 -> 5405 | GQ10: =GS10-GL10-GM10-GO10 -> 2409 | GR10: =GO10+GQ10 -> 4369 | GS10: 7814 | GT10: 1595 | GU10: 1830 | GV10: =GT10+GU10 -> 3425 | GW10: 2104 | GY10: =HA10-GW10-GU10-GT10 -> 2602 | GZ10: =GW10+GY10 -> 4706 | HA10: ='Profit and Loss'!AA10 -> 8131 | HB10: 1809 | HC10: 1904 | HD10: =HB10+HC10 -> 3713 | HE10: 2014 | HG10: =HI10-HE10-HC10-HB10 -> 2445 | HH10: =HE10+HG10 -> 4459 | HI10: 8172 | HJ10: 1905 | HK10: 2117 | HM10: 2312 | HO10: =HQ10-HM10-HK10-HJ10 -> 2504 | HP10: =HM10+HO10 -> 4816 | HQ10: 8838 | HR10: 1774 | HS10: 2338 | HU10: 2242 | HW10: =HY10-HU10-HS10-HR10 -> 2333 | HX10: =HU10+HW10 -> 4575 | HY10: 8687 | HZ10: 2046 | IA10: 2388 | IC10: 2346 | IE10: =IG10-IC10-IA10-HZ10 -> 2710 | IG10: 9490 | IH10: 2163 | II10: 2338 | IK10: 2417 | IM10: 3012 | IO10: 9931 | IP10: 2480 | IQ10: 2909
A11: Growth | DJ11: =DJ10/DB10-1 -> 0.11111111 | DK11: =DK10/DC10-1 -> 0.14893617 | DL11: =DL10/DD10-1 -> 0.13154534 | DM11: =DM10/DE10-1 -> 0.067209776 | DN11: =DN10/DF10-1 -> 0.10675039 | DO11: =DO10/DG10-1 -> 0.07112069 | DP11: =DP10/DH10-1 -> 0.069109948 | DQ11: =DQ10/DI10-1 -> 0.096662831 | ... EG11: =EG10/DY10-1 -> 0.16910841 | EH11: =+EH10/DZ10-1 -> 0.20103986 | EI11: =EI10/EA10-1 -> 0.25403818 | EJ11: =EJ10/EB10-1 -> 0.22972973 | EK11: =EK10/EC10-1 -> 0.24702774 | EL11: =EL10/ED10-1 -> 0.23622829 | EM11: =EM10/EE10-1 -> 0.13367609 | EN11: =EN10/EF10-1 -> 0.18957655 | EO11: =EO10/EG10-1 -> 0.20766201 | EP11: =EP10/EH10-1 -> 0.041847042 | ... FB11: =FB10/ET10-1 -> 0.11425159 | FC11: =FC12+FC13 -> 0.093752883 | FD11: =FD10/EV10-1 -> 0.11392848 | FE11: =FE10/EW10-1 -> 0.10869564 | FF11: =FF10/EX10-1 -> 0.12720403 | FG11: =FG10/EY10-1 -> 0.10334029 | FH11: =FH10/EZ10-1 -> 0.11415525 | FI11: =FI10/FA10-1 -> 0.054441261 | FJ11: =FJ10/FB10-1 -> 0.091818507 | FK11: =FK10/FC10-1 -> 0.14040691 | ... GC11: =GC10/FU10-1 -> 0.17129722 | GD11: =GD10/1311-1 -> 0.01525553 | GE11: =GE10/1496-1 -> 0.05013369 | GF11: =GF10/(1496+1311)-1 -> 0.033843962 | GG11: =GG10/1444-1 -> 0.17590028 | GH11: =GH10/FZ10-1 -> 0.10206037 | GI11: =GI10/GA10-1 -> 0.1198102 | GJ11: =GJ10/GB10-1 -> 0.15565582 | GK11: =GK12+GK13 -> 0.098334741 | GL11: =GL10/GD10-1 -> 0.19834711 | GM11: =GM10/1496-1 -> 0.23663102 | GN11: =GN10/(1496+1311)-1 -> 0.22728892 | GO11: =GO10/1444-1 -> 0.35734072 | GP11: =GP10/GH10-1 -> 0.175 | GQ11: =GQ10/GI10-1 -> 0.27595339 | GR11: =GR10/GJ10-1 -> 0.21834914 | GS11: =GS12+GS13 -> 0.19510933 | GT11: =GT10/GL10-1 -> 0 | GU11: =GU10/1850-1 -> -0.010810811 | GV11: =GV10/(1595+1850)-1 -> -0.0058055152 | GW11: =GW10/1960-1 -> 0.073469388 | GY11: =GY10/2409-1 -> 0.080116231 | GZ11: =GZ10/GR10-1 -> 0.077134356 | HA11: =HA10/7814-1 -> 0.040568211 | HB11: =HB10/1464-1 -> 0.23565574 | HC11: =HC10/1683-1 -> 0.13131313 | HD11: =HD10/(1464+1683)-1 -> 0.17985383 | HE11: =HE10/1927-1 -> 0.045147898 | HG11: =HG10/2396-1 -> 0.020450751 | HH11: =HH10/GZ10-1 -> -0.052486188 | HI11: =HI10/7471-1 -> 0.093829474 | HJ11: =HJ10/HB10-1 -> 0.053067993 | HK11: =HK10/1683-1 -> 0.25787285 | HM11: =HM10/1927-1 -> 0.19979242 | HO11: =HO10/2396-1 -> 0.045075125 | HP11: =HP10/HH10-1 -> 0.080062794 | HQ11: =HQ10/7471-1 -> 0.18297417 | HR11: =HR10/HJ10-1 -> -0.068766404 | HS11: =HS10/1683-1 -> 0.38918598 | HU11: =HU10/1927-1 -> 0.16346653 | HW11: =HW10/2396-1 -> -0.026293823 | HX11: =HX10/HP10-1 -> -0.050041528 | HY11: =HY10/7471-1 -> 0.16276268 | HZ11: =HZ10/HR10-1 -> 0.15332582 | IA11: =IA10/1683-1 -> 0.41889483 | IC11: =IC10/1927-1 -> 0.21743643 | IH11: =IH10/HZ10-1 -> 0.057184751 | II11: =II10/IA10-1 -> -0.020938023 | IK11: =IK10/IC10-1 -> 0.03026428 | IM11: 0.12 | IO11: 0.1 | IP11: =IP10/IH10-1 -> 0.14655571 | IQ11: =IQ10/II10-1 -> 0.24422583
A12: FX & Scope impact | DJ12: =DJ11-DJ13 -> 0.071111111 | DK12: =DK11-DK13 -> 0.07893617 | DL12: =DL11-DL13 -> 0.075338442 | DM12: =DM11-DM13 -> 0.027209776 | DN12: =DN11-DN13 -> 0.056789639 | DO12: =DO11-DO13 -> -0.06887931 | DP12: =DP11-DP13 -> -0.01947644 | DQ12: =DQ11-DQ13 -> 0.026662831 | ... DW12: =DW11-DW13 -> 0.10800402 | DX12: =((DW12*DO10)+(DU12*DM10))/DP10 -> 0.11112439 | DY12: ='Profit and Loss'!Q12 -> 0.075410283 | DZ12: =DZ11-DZ13 -> 0.03708061 | EA12: =EA11-EA13 -> -0.068770764 | EB12: =EB11-EB13 -> -0.024326107 | EC12: =EC11-EC13 -> -0.071654135 | ED12: =ED11-ED13 -> -0.042560834 | EE12: =+EE11-EE13 -> -0.006546003 | EF12: =+EF11-EF13 -> -0.036137048 | EG12: =EG11-EG13 -> -0.030891586 | EH12: =+EH11-EH13 -> 0.041039861 | EI12: =+EI11-EI13 -> 0.093038179 | EJ12: =+EJ11-EJ13 -> 0.06772973 | EK12: =EK11-EK13 -> 0.10102774 | EL12: =EL11-EL13 -> 0.080228288 | EM12: =EM11-EM13 -> 0.041676093 | EN12: =+EN11-EN13 -> 0.070945928 | EO12: =+EO11-EO13 -> 0.070154314 | EP12: =EP11-EP13 -> -0.023152958 | EQ12: =EQ11-EQ13 -> -0.037777518 | ER12: =ER11-ER13 -> -0.030850679 | ES12: =ES11-ES13 -> -0.078245763 | ET12: =ET11-ET13 -> -0.049044962 | EU12: =EU11-EU13 -> -0.089043084 | EV12: =EV11-EV13 -> -0.083461117 | EW12: =EW11-EW13 -> -0.059504002 | ... FB12: =FB11-FB13 -> -0.096860271 | FC12: =((EU95*(0.1*FC492)+EU100*FC102+EU105*FC483+EU110*FC112+EU115*FC117+EU120*FC122)/EU127)*1.2 -> -0.031247117 | FD12: =FD11-FD13 -> -0.047355308 | FE12: =FE11-FE13 -> -0.079076555 | FF12: =FF11-FF13 -> -0.01279597 | FG12: =FG11-FG13 -> 0.018204593 | FH12: =FH11-FH13 -> 0.0041552511 | FI12: =FI11-FI13 -> -0.035558739 | FJ12: =FJ11-FJ13 -> -0.0081814934 | FK12: =FK11-FK13 -> 0.0030077731 | ... GJ12: =GJ11-GJ13 -> -0.024576217 | GK12: =GK218 -> -0.051358092 | GL12: =GL11-GL13 -> 0.018347107 | GM12: =GM11-GM13 -> 0.076631016 | GN12: =GN11-GN13 -> 0.058115936 | GO12: =GO11-GO13 -> 0.24734072 | GP12: =GP11-GP13 -> 0.027669565 | GQ12: =GQ11-GQ13 -> 0.02595339 | GR12: =GR11-GR13 -> 0.034640268 | GS12: =GS218 -> 0.01823927 | GT12: =GT11-GT13 -> 0.01 | GU12: =GU11-GU13 -> -0.020810811 | GV12: =GV11-GV13 -> -0.0065457184 | GW12: =GW11-GW13 -> -0.056530612 | GY12: =GY11-GY13 -> -0.059883769 | GZ12: =GZ11-GZ13 -> -0.058379492 | HA12: =HA11-HA13 -> -0.029431789 | HB12: =HB11-HB13 -> 0.30965574 | HC12: =HC11-HC13 -> -0.038686869 | HD12: =HD11-HD13 -> 0.12348303 | HE12: =HE11-HE13 -> -0.0048521017 | HG12: =HG11-HG13 -> 0.020450751 | HH12: =HH11-HH13 -> -0.074840629 | HI12: =HI11-HI13 -> -0.016170526 | HJ12: =HJ11-HJ13 -> 0.043067993 | HK12: =HK11-HK13 -> 0.21787285 | HM12: =HM11-HM13 -> 0.13979242 | HO12: =HO11-HO13 -> 0.055075125 | HP12: =HP11-HP13 -> 0.05844584 | HQ12: =HQ11-HQ13 -> 0.16297417 | HR12: =HR11-HR13 -> 0.0012335958 | HS12: =HS11-HS13 -> 0.19918598 | HU12: =HU11-HU13 -> 0.063466528 | HW12: =HW11-HW13 -> -0.11629382 | HX12: =HX11-HX13 -> -0.14484219 | HY12: =HY11-HY13 -> 0.042762682 | HZ12: =HZ11-HZ13 -> 0.043325817 | IA12: =IA11-IA13 -> 0.26889483 | IC12: =IC11-IC13 -> 0.04743643 | IH12: =IH11-IH13 -> -0.072815249 | II12: =II11-II13 -> -0.050938023 | IK12: =IK11-IK13 -> -0.10973572 | IM12: =IM11-IM13 -> -0.07 | IO12: =IO11-IO13 -> -0.04 | IP12: =IP11-IP13 -> -0.07344429 | IQ12: =IQ11-IQ13 -> -0.005774166 | JA12: 2 year | JB12: =(EK10*(1+ES13)*(1+FA13))/EK10-1 -> 0.265088 | JC12: =(EM10*(1+EU13)*(1+FC13))/EM10-1 -> 0.2915 | JD12: =(EP10*(1+EX13)*(1+FF13))/EP10-1 -> 0.38624 | JE12: =(EQ10*(1+EY13)*(1+FG13))/EQ10-1 -> 0.32495069 | JF12: =(EJ10*(1+ER13)*(1+EZ13))/EJ10-1 -> 0.28941436 | JG12: =(ES10*(1+FA13)*(1+FI13))/ES10-1 -> 0.30582 | JH12: =(EL10*(1+ET13)*(1+FB13))/EL10-1 -> 0.28072089 | JI12: =(EU10*(1+FC13)*(1+FK13))/EU10-1 -> 0.27957402 | JJ12: =(EN10*(1+EV13)*(1+FD13))/EN10-1 -> 0.27792095 | JK12: =(EX10*(1+FF13)*(1+FN13))/EX10-1 -> 0.3908 | JL12: =(EY10*(1+FG13)*(1+FO13))/EY10-1 -> 0.30382596 | JM12: =(EZ10*(1+FH13)*(1+FP13))/EZ10-1 -> 0.3431 | JN12: =(FA10*(1+FI13)*(1+FQ13))/FA10-1 -> 0.34907246 | JO12: =(FB10*(1+FJ13)*(1+FR13))/FB10-1 -> 0.342 | JP12: =(FC10*(1+FK13)*(1+FS13))/FC10-1 -> 0.42883691
A13: Currency neutral | DJ13: 0.04 | DK13: 0.07 | DL13: =(DJ13*DB10+DK13*DC10)/DD10 -> 0.056206897 | DM13: 0.04 | DN13: =(DJ13*DB10+DK13*DC10+DM13*DE10)/DF10 -> 0.049960754 | DO13: 0.14 | DP13: =(DM13*DE10+DO13*DG10)/DH10 -> 0.088586387 | DQ13: ='Profit and Loss'!P13 -> 0.07 | DR13: 0.16 | DS13: 0.167 | DT13: 0.16 | DU13: 0.155 | DV13: 0.161 | DW13: 0.226 | DX13: =DX11-DX12 -> 0.18956121 | DY13: =DY11-DY12 -> 0.178 | DZ13: 0.22 | EA13: 0.2 | EB13: 0.21 | EC13: 0.21 | ED13: 0.21 | EE13: 0.18 | EF13: =(-EB13*DT10+EG13*DY10)/DX10 -> 0.19201054 | EG13: 0.2 | EH13: 0.16 | EI13: 0.161 | EJ13: 0.162 | EK13: 0.146 | EL13: 0.156 | EM13: 0.092 | EN13: =+(EK13*EC10+EM13*EE10)/EF10 -> 0.11863062 | EO13: =(EH13*DZ10+EI13*EA10+EK13*EC10+EM13*EE10)/EG10 -> 0.1375077 | EP13: 0.065 | EQ13: 0.053 | ER13: 0.058 | ES13: 0.056 | ET13: =(EH10*EP13+EI10*EQ13+EK10*ES13)/EL10 -> 0.057475311 | EU13: 0.148 | EV13: =(EK10*ES13+EM10*EU13)/EN10 -> 0.10043812 | EW13: =(EH10*EP13+EI10*EQ13+EK10*ES13+EM10*EU13)/EO10 -> 0.081146457 | EX13: 0.216 | EY13: 0.221 | EZ13: =(EP10*EX13+EQ10*EY13)/ER10 -> 0.21872813 | FA13: 0.198 | FB13: =(EP10*EX13+EQ10*EY13+ES10*FA13)/ET10 -> 0.21111186 | FC13: 0.125 | FD13: =(ES10*FA13+EU10*FC13)/EV10 -> 0.16128379 | FE13: =(EP10*EX13+EQ10*EY13+ES10*FA13+EU10*FC13)/EW10 -> 0.1877722 | FF13: 0.14 | FG13: =(EZ10*FH13-EX10*FF13)/EY10 -> 0.085135699 | FH13: 0.11 | FI13: 0.09 | FJ13: 0.1 | FK13: =(FE10*FM13-FB10*FJ13)/FC10 -> 0.13739913 | FL13: =(FE10*FM13-EZ10*FH13)/FD10 -> 0.11 | FM13: 0.11 | FN13: 0.22 | FO13: =(FH10*FP13-FF10*FN13)/FG10 -> 0.20153264 | FP13: 0.21 | FQ13: =(FJ10*FR13-FH10*FP13)/FI10 -> 0.23768116 | FR13: 0.22 | FS13: =(FM10*FU13-FJ10*FR13)/FK10 -> 0.25623176 | FT13: =(FI10*FQ13+FK10*FS13)/FL10 -> 0.24720582 | FU13: 0.23 | FV13: 0.18 | FW13: 0.21 | FX13: =(FN10*FV13+FO10*FW13)/FP10 -> 0.19597015 | FY13: =(FR10*FZ13-FP10*FX13)/FQ10 -> 0.09 | FZ13: 0.15616775 | GA13: 0.21 | GB13: =(FQ10*FY13+FS10*GA13)/FT10 -> 0.15283668 | GC13: =(FN10*FV13+FO10*FW13+FQ10*FY13+FS10*GA13)/FU10 -> 0.17189886 | GD13: 0.11 | GE13: 0.12 | GF13: =(FV10*GD13+FW10*GE13)/FX10 -> 0.115321 | GG13: 0.24 | GH13: =(FX10*GF13+FY10*GG13)/FZ10 -> 0.15764734 | GI13: 0.13 | GJ13: =(FY10*GG13+GA10*GI13)/GB10 -> 0.18023203 | GK13: =((GJ13*$GB$10)+(GF13*$FX$10))/$GC$10 -> 0.14969283 | GL13: 0.18 | GM13: 0.16 | GN13: =(GD10*GL13+GE10*GM13)/GF10 -> 0.16917298 | GO13: 0.11 | GP13: =(GF10*GN13+GG10*GO13)/GH10 -> 0.14733043 | GQ13: 0.25 | GR13: =(GG10*GO13+GI10*GQ13)/GJ10 -> 0.18370887 | GS13: =((GR13*$GB$10)+(GN13*$FX$10))/$GC$10 -> 0.17687006 | GT13: -0.01 | GU13: 0.01 | GV13: =(GL10*GT13+GM10*GU13)/GN10 -> 0.00074020319 | GW13: 0.13 | GY13: 0.14 | GZ13: =(GO10*GW13+GQ10*GY13)/GR10 -> 0.13551385 | HA13: 0.07 | HB13: -0.074 | HC13: 0.17 | HD13: =(GT10*HB13+GU10*HC13)/GV10 -> 0.056370803 | HE13: 0.05 | HG13: 0 | HH13: =(GW10*HE13+GY10*HG13)/GZ10 -> 0.022354441 | HI13: 0.11 | HJ13: 0.01 | HK13: 0.04 | HM13: 0.06 | HO13: -0.01 | HP13: =(HE10*HM13+HG10*HO13)/HH10 -> 0.021616954 | HQ13: 0.02 | HR13: -0.07 | HS13: 0.19 | HU13: 0.1 | HW13: 0.09 | HX13: =(HM10*HU13+HO10*HW13)/HP10 -> 0.094800664 | HY13: 0.12 | HZ13: 0.11 | IA13: 0.15 | IC13: 0.17 | IH13: 0.13 | II13: 0.03 | IK13: 0.14 | IM13: 0.19 | IO13: 0.14 | IP13: 0.22 | IQ13: 0.25 | JA13: 3 year | JB13: =(EC10*(1+EK13)*(1+ES13)*(1+FA13))/EC10-1 -> 0.44979085 | JC13: =(EE10*(1+EM13)*(1+EU13)*(1+FC13))/EE10-1 -> 0.410318 | JD13: =(EH10*(1+EP13)*(1+EX13)*(1+FF13))/EH10-1 -> 0.4763456 | JE13: =(EI10*(1+EQ13)*(1+EY13)*(1+FG13))/EI10-1 -> 0.39517308 | JF13: =(EB10*(1+EJ13)*(1+ER13)*(1+EZ13))/EB10-1 -> 0.49829949 | JG13: =(EK10*(1+ES13)*(1+FA13)*(1+FI13))/EK10-1 -> 0.37894592 | JH13: =(ED10*(1+EL13)*(1+ET13)*(1+FB13))/ED10-1 -> 0.48051335 | JI13: =(EM10*(1+EU13)*(1+FC13)*(1+FK13))/EM10-1 -> 0.46895098 | JJ13: =(EF10*(1+EN13)*(1+EV13)*(1+FD13))/EF10-1 -> 0.4295215 | JK13: =(EP10*(1+EX13)*(1+FF13)*(1+FN13))/EP10-1 -> 0.6912128 | JL13: =(EQ10*(1+EY13)*(1+FG13)*(1+FO13))/EQ10-1 -> 0.5919715 | JM13: =(ER10*(1+EZ13)*(1+FH13)*(1+FP13))/ER10-1 -> 0.63687375 | JN13: =(ES10*(1+FA13)*(1+FI13)*(1+FQ13))/ES10-1 -> 0.61618881 | JO13: =(ET10*(1+FB13)*(1+FJ13)*(1+FR13))/ET10-1 -> 0.62531212 | JP13: =(EU10*(1+FC13)*(1+FK13)*(1+FS13))/EU10-1 -> 0.60744153
A14: Store contribution implied | DR14: =DR13-DR16-DR15 -> 0.09 | DS14: =DS13-DS16-DS15 -> 0.078769547 | DT14: =DT13-DT16-DT15 -> 0.08 | DU14: =DU13-DU16-DU15 -> 0.048091603 | DV14: =DV13-DV16-DV15 -> 0.071 | DW14: =DW13-DW16-DW15 -> 0.076 | DX14: =DX13-DX16-DX15 -> 0.053635651 | DY14: =DY13-DY16-DY15 -> 0.068 | ... GJ14: =GJ13-GJ16-GJ15 -> 0.040181487 | GK14: =((GJ14*$GB$10)+(GF14*$FX$10))/$GC$10 -> 0.019905945 | GL14: =GL13-GL16-GL15 -> -0.0018866884 | GM14: =GM13-GM16-GM15 -> -0.0027451868 | GN14: =GN13-GN16-GN15 -> -0.0023514372 | GO14: =GO13-GO16-GO15 -> 0.0073396591 | GP14: =GP13-GP16-GP15 -> -0.0099400392 | GQ14: =GQ13-GQ16-GQ15 -> 0.059830308 | GR14: =GR13-GR16-GR15 -> 0.034975561 | GS14: =((GR14*$GB$10)+(GN14*$FX$10))/$GC$10 -> 0.017414037 | GT14: =GT13-GT16-GT15 -> 0.19060978 | GU14: =GU13-GU16-GU15 -> -0.11723686 | GV14: =GV13-GV16-GV15 -> 0.049369165 | GW14: =GW13-GW16-GW15 -> 0.0960314 | GY14: =GY13-GY16-GY15 -> 0.043320592 | GZ14: =GZ13-GZ16-GZ15 -> 0.083924984 | HA14: =HA13-HA16-HA15 -> 0.099209102 | HB14: =HB13-HB16-HB15 -> -0.56598742 | HC14: =HC13-HC16-HC15 -> 0.40901916 | HD14: =HD13-HD16-HD15 -> -0.021416508 | HE14: =HE13-HE16-HE15 -> 0.01056048 | HG14: =HG13-HG16-HG15 -> 0.0098598799 | HH14: =HH13-HH16-HH15 -> 0.014825232 | HI14: =HI13-HI16-HI15 -> 0.09028024 | HJ14: =HJ13-HJ16-HJ15 -> 0.00081674775 | HK14: =HK13-HK16-HK15 -> -0.01969114 | HM14: =HM13-HM16-HM15 -> 0.02056048 | HO14: =HO13-HO16-HO15 -> 0.0097197599 | HP14: =HP13-HP16-HP15 -> 0.017289827 | HQ14: =HQ13-HQ16-HQ15 -> 0.00028024015 | HR14: =HR13-HR16-HR15 -> 0.035607401 | HS14: =HS13-HS16-HS15 -> 0.12571723 | HU14: =HU13-HU16-HU15 -> 0.09507006 | HW14: =HW13-HW16-HW15 -> 0.14915928 | HX14: =HX13-HX16-HX15 -> 0.11234972 | HY14: =HY13-HY16-HY15 -> 0.1446497 | HZ14: =HZ13-HZ16-HZ15 -> -0.046115288 | IA14: =IA13-IA16-IA15 -> 0.17754976 | IC14: =IC13-IC16-IC15 -> 0.18478982 | IH14: =IH13-IH16-IH15 -> 0.04735073 | II14: =II13-II16-II15 -> 0.043774878 | IK14: =IK13-IK16-IK15 -> 0.066050901 | IM14: =IM13-IM16-IM15 -> 0.086471261 | IO14: =IO13-IO16-IO15 -> 0.061120961 | IP14: =IP13-IP16-IP15 -> 0.10520935 | IQ14: =IQ13-IQ16-IQ15 -> 0.12602609
A15: eCommerce contribution implied | EP15: =EP19*'Profit and Loss'!$S26 -> 0.03185295 | EQ15: =EQ19*'Profit and Loss'!$S26 -> 0.037005633 | ER15: =ER19*'Profit and Loss'!$S26 -> 0.034663504 | ES15: =ES19*'Profit and Loss'!$S26 -> 0.026700267 | ET15: =ET19*'Profit and Loss'!$S26 -> 0.031384524 | EU15: =EU19*'Profit and Loss'!$S26 -> 0.026010375 | EV15: =EV19*'Profit and Loss'!$S26 -> 0.026367033 | EW15: =EW19*'Profit and Loss'!$S26 -> 0.029979247 | EX15: =EX19*'Profit and Loss'!$T26 -> 0.052234475 | EY15: =EY19*'Profit and Loss'!$T26 -> 0.04280325 | EZ15: =EZ19*'Profit and Loss'!$T26 -> 0.047156123 | FA15: =FA19*'Profit and Loss'!$T26 -> 0.072547882 | FB15: =FB19*'Profit and Loss'!$T26 -> 0.056587348 | FC15: =FC19*'Profit and Loss'!$T26 -> 0.044979687 | FD15: =FD19*'Profit and Loss'!$T26 -> 0 | FE15: =FE19*'Profit and Loss'!$T26 -> 0.052234475 | FF15: =FF19*'Profit and Loss'!$U26 -> 0.061854723 | FG15: =FG19*'Profit and Loss'!$U26 -> 0.06406382 | FH15: =FH19*'Profit and Loss'!$U26 -> 0.062959271 | FI15: =FI19*'Profit and Loss'!$U26 -> 0.024572251 | FJ15: =FJ19*'Profit and Loss'!$U26 -> 0.048600139 | FK15: =FK19*'Profit and Loss'!$U26 -> 0.040338307 | FL15: =FL19*'Profit and Loss'!$U26 -> 0.03235835 | FM15: =FM19*'Profit and Loss'!$U26 -> 0.046391042 | FN15: =FN19*'Profit and Loss'!$V26 -> 0.069898839 | FO15: =FO19*'Profit and Loss'!$V26 -> 0.075391805 | FP15: =FP19*'Profit and Loss'!$V26 -> 0.072873257 | FQ15: =FQ19*'Profit and Loss'!$V26 -> 0.081106793 | FR15: =FR19*'Profit and Loss'!$V26 -> 0.075847676 | FS15: =FS19*'Profit and Loss'!$V26 -> 0.11895505 | FT15: =FT19*'Profit and Loss'!$V26 -> 0.10053968 | FU15: =FU19*'Profit and Loss'!$V26 -> 0.087745351 | FV15: ='Profit and Loss'!$W26*Interim!FV19 -> 0.105991 | FW15: ='Profit and Loss'!$W26*Interim!FW19 -> 0.13198879 | FX15: ='Profit and Loss'!$W26*Interim!FX19 -> 0.11983062 | FY15: ='Profit and Loss'!$W26*Interim!FY19 -> 0.077993379 | FZ15: ='Profit and Loss'!$W26*Interim!FZ19 -> 0.10411655 | GA15: ='Profit and Loss'!$W26*Interim!GA19 -> 0.13790484 | GB15: ='Profit and Loss'!$W26*Interim!GB19 -> 0.10936536 | GC15: ='Profit and Loss'!$W26*Interim!GC19 -> 0.11399032 | GD15: ='Profit and Loss'!$X26*Interim!GD19 -> 0.069606926 | GE15: ='Profit and Loss'!$X26*Interim!GE19 -> 0.067028891 | GF15: ='Profit and Loss'!$X26*Interim!GF19 -> 0.068235153 | GG15: ='Profit and Loss'!$X26*Interim!GG19 -> 0.19593061 | GH15: ='Profit and Loss'!$W26*Interim!GH19 -> 0.13535219 | GI15: ='Profit and Loss'!$X26*Interim!GI19 -> 0.061872823 | GJ15: ='Profit and Loss'!$W26*Interim!GJ19 -> 0.095483998 | GK15: =((GJ15*$GB$10)+(GF15*$FX$10))/$GC$10 -> 0.082664021 | GL15: ='Profit and Loss'!$Y26*Interim!GL19 -> 0.12188669 | GM15: ='Profit and Loss'!$Y26*Interim!GM19 -> 0.11274519 | GN15: ='Profit and Loss'!$Y26*Interim!GN19 -> 0.11693793 | GO15: ='Profit and Loss'!$Y26*Interim!GO19 -> 0.042660341 | GP15: ='Profit and Loss'!$Y26*Interim!GP19 -> 0.10068569 | GQ15: ='Profit and Loss'!$Y26*Interim!GQ19 -> 0.14016969 | GR15: ='Profit and Loss'!$Y26*Interim!GR19 -> 0.093998226 | GS15: =((GR15*$GB$10)+(GN15*$FX$10))/$GC$10 -> 0.10479085 | GT15: ='Profit and Loss'!$Z26*Interim!GT19 -> 0.11939022 | GU15: ='Profit and Loss'!$Z26*Interim!GU19 -> 0.31723686 | GV15: ='Profit and Loss'!$Y26*Interim!GV19 -> 0.20155972 | GW15: ='Profit and Loss'!$Z26*Interim!GW19 -> 0.1739686 | GY15: ='Profit and Loss'!$Z26*Interim!GY19 -> 0.14667941 | GZ15: ='Profit and Loss'!$Y26*Interim!GZ19 -> 0.14196424 | HA15: ='Profit and Loss'!$Z26*Interim!HA19 -> 0.1807909 | HB15: ='Profit and Loss'!$AA26*Interim!HB19 -> 0.21198742 | HC15: ='Profit and Loss'!$AA26*Interim!HC19 -> -0.069019159 | HD15: ='Profit and Loss'!$Y26*Interim!HD19 -> 0.038225267 | HE15: ='Profit and Loss'!$AA26*Interim!HE19 -> 0.03943952 | HG15: ='Profit and Loss'!$AA26*Interim!HG19 -> -0.0098598799 | HH15: ='Profit and Loss'!$Y26*Interim!HH19 -> 0.0075292096 | HI15: ='Profit and Loss'!$AA26*Interim!HI19 -> 0.01971976 | HJ15: ='Profit and Loss'!$AB26*Interim!HJ19 -> 0.0091832523 | HK15: ='Profit and Loss'!$AB26*Interim!HK19 -> 0.05969114 | HM15: ='Profit and Loss'!$AA26*Interim!HM19 -> 0.03943952 | HO15: ='Profit and Loss'!$AA26*Interim!HO19 -> -0.01971976 | HP15: ='Profit and Loss'!$Y26*Interim!HP19 -> 0.0043271278 | HQ15: ='Profit and Loss'!$AA26*Interim!HQ19 -> 0.01971976 | HR15: ='Profit and Loss'!$AB26*Interim!HR19 -> -0.1056074 | HS15: ='Profit and Loss'!$AB26*Interim!HS19 -> 0.064282766 | HU15: ='Profit and Loss'!$AA26*Interim!HU19 -> 0.00492994 | HW15: ='Profit and Loss'!$AA26*Interim!HW19 -> -0.05915928 | HX15: ='Profit and Loss'!$Y26*Interim!HX19 -> -0.017549051 | HY15: ='Profit and Loss'!$AA26*Interim!HY19 -> -0.0246497 | HZ15: ='Profit and Loss'!$AB26*Interim!HZ19 -> 0.15611529 | IA15: ='Profit and Loss'!$AB26*Interim!IA19 -> -0.027549757 | IC15: ='Profit and Loss'!$AA26*Interim!IC19 -> -0.01478982 | IH15: ='Profit and Loss'!$AB26*Interim!IH19 -> 0.08264927 | II15: ='Profit and Loss'!$AB26*Interim!II19 -> -0.013774878 | IK15: ='Profit and Loss'!$AA26*Interim!IK19 -> 0.073949099 | IM15: ='Profit and Loss'!$AA26*Interim!IM19 -> 0.10352874 | IO15: ='Profit and Loss'!$AA26*Interim!IO19 -> 0.078879039 | IP15: ='Profit and Loss'!$AB26*Interim!IP19 -> 0.11479065 | IQ15: ='Profit and Loss'!$AB26*Interim!IQ19 -> 0.12397391
A16: Group LFL | DR16: 0.07 | DS16: =(DL$10*DT16-DJ$10*DR16)/DK$10 -> 0.088230453 | DT16: 0.08 | DU16: =(DN$10*DV16-DK$10*DS16-DJ$10*DR16)/DM$10 -> 0.1069084 | DV16: 0.09 | DW16: 0.15 | DX16: =(DQ$10*DY16-DL$10*DT16)/DP$10 -> 0.13592556 | DY16: 0.11 | DZ16: 0.17 | EA16: =(DT$10*EB16-DR$10*DZ16)/DS$10 -> 0.13475083 | EB16: 0.15 | EC16: =(DV$10*ED16-DS$10*EA16-DR$10*DZ16)/DU$10 -> 0.15 | ED16: 0.15 | EE16: 0.11 | EF16: =(DY$10*EG16-DT$10*EB16)/DX$10 -> 0.13201054 | EG16: 0.14 | EH16: 0.09 | EI16: 0.08 | EJ16: 0.09 | EK16: 0.09 | EL16: 0.09 | EM16: 0.01 | EN16: =(EG$10*EO16-EB$10*EJ16)/EF$10 -> 0.053609121 | EO16: 0.07 | EP16: -0.01 | EQ16: -0.02 | ER16: -0.01 | ES16: -0.03 | ET16: -0.02 | EU16: 0.03 | EV16: =(EO$10*EW16-EJ$10*ER16)/EN$10 -> -0.01 | EW16: -0.01 | EX16: 0.08 | EY16: 0.1 | EZ16: 0.09 | FA16: 0.06 | FB16: 0.08 | FC16: 0.09 | FD16: =(EW$10*FE16-ER$10*EZ16)/EV$10 -> 0.09 | FE16: 0.09 | FF16: 0.04 | FG16: -0.02 | FH16: 0.01 | FI16: 0.03 | FJ16: 0.02 | FK16: 0.05 | FL16: =(FE$10*FM16-EZ$10*FH16)/FD$10 -> 0.046939278 | FM16: 0.03 | FN16: 0.13 | FO16: =(FH10*FP16-FF10*FN16)/FG10 -> 0.13 | FP16: 0.13 | FQ16: 0.13 | FR16: 0.13 | FS16: =(FM10*FU16-FJ10*FR16)/FK10 -> 0.09376824 | FT16: =(FI10*FQ16+FK10*FS16)/FL10 -> 0.11139709 | FU16: 0.12 | FV16: 0.05 | FW16: 0.06 | FX16: =(FN10*FV16+FO10*FW16)/FP10 -> 0.055323383 | FY16: 0.02 | FZ16: =(FN10*FV16+FO10*FW16+FQ10*FY16)/FR10 -> 0.042055916 | GA16: =85%*7.5%+15%*-5% -> 0.05625 | GB16: =(FQ10*FY16+FS10*GA16)/FT10 -> 0.038981913 | GC16: =(FN10*FV16+FO10*FW16+FQ10*FY16+FS10*GA16)/FU10 -> 0.046203778 | GD16: 0.05 | GE16: 0.05 | GF16: =(FV10*GD16+FW10*GE16)/FX10 -> 0.05 | GG16: 0.05 | GH16: =(FV10*GD16+FW10*GE16+FY10*GG16)/FZ10 -> 0.05 | GI16: 0.04 | GJ16: =(FY10*GG16+GA10*GI16)/GB10 -> 0.044566549 | GK16: =((GJ16*$GB$10)+(GF16*$FX$10))/$GC$10 -> 0.047122867 | GL16: 0.06 | GM16: 0.05 | GN16: =(GD10*GL16+GE10*GM16)/GF10 -> 0.054586492 | GO16: 0.06 | GP16: =(GD10*GL16+GE10*GM16+GG10*GO16)/GH10 -> 0.056584783 | GQ16: 0.05 | GR16: =(GG10*GO16+GI10*GQ16)/GJ10 -> 0.054735081 | GS16: =((GR16*$GB$10)+(GN16*$FX$10))/$GC$10 -> 0.054665173 | GT16: -0.32 | GU16: -0.19 | GV16: =(GL10*GT16+GM10*GU16)/GN10 -> -0.25018868 | GW16: -0.14 | GY16: -0.05 | GZ16: =(GO10*GW16+GQ10*GY16)/GR10 -> -0.090375372 | HA16: -0.21 | HB16: 0.28 | HC16: -0.17 | HD16: =(GT10*HB16+GU10*HC16)/GV10 -> 0.039562044 | JB16: =(55%*(FF10/FM10))+(55%*(FG10/FM10))+(35%*(FI10/FM10))+(25%*(FK10/FM10)) -> 0.41488984
A17: adidas LFL | DR17: 0.05 | DS17: =(DL$10*DT17-DJ$10*DR17)/DK$10 -> 0.086460905 | DT17: 0.07 | DU17: =(DN$10*DV17-DK$10*DS17-DJ$10*DR17)/DM$10 -> 0.096908397 | DV17: 0.08 | DW17: 0.17 | DX17: =(DQ$10*DY17-DL$10*DT17)/DP$10 -> 0.14460333 | DY17: 0.11 | DZ17: 0.17 | EA17: =(DT$10*EB17-DR$10*DZ17)/DS$10 -> 0.13475083 | EB17: 0.15 | EC17: =(DV$10*ED17-DS$10*EA17-DR$10*DZ17)/DU$10 -> 0.15 | ED17: 0.15 | EE17: 0.12 | EF17: =(DY$10*EG17-DT$10*EB17)/DX$10 -> 0.13201054 | EG17: 0.14 | EH17: 0.09 | EI17: 0.08 | EJ17: 0.09 | EK17: 0.08 | EL17: 0.09 | EM17: 0.01 | EN17: =(EG$10*EO17-EB$10*EJ17)/EF$10 -> 0.053609121 | EO17: 0.07 | EP17: 0 | EQ17: -0.01 | ER17: -0.01 | ES17: -0.02 | ET17: -0.01 | EU17: 0.03 | EV17: =(EO$10*EW17-EJ$10*ER17)/EN$10 -> 0.0084720701 | EW17: 0 | EX17: 0.09 | EY17: 0.12 | EZ17: 0.1 | FA17: 0.08 | FB17: 0.1 | FC17: 0.1 | FD17: =(EW$10*FE17-ER$10*EZ17)/EV$10 -> 0.1 | FE17: 0.1 | FF17: 0.05 | FG17: -0.01 | FH17: 0.02 | FI17: 0.04 | FJ17: 0.03 | FK17: 0.05 | FL17: =(FE$10*FM17-EZ$10*FH17)/FD$10 -> 0.056939278 | FM17: 0.04 | FN17: 0.15 | FO17: =(FH10*FP17-FF10*FN17)/FG10 -> 0.11306528 | FP17: 0.13 | FQ17: 0.13 | FR17: =(FH10*FP17+FI10*FQ17)/FJ10 -> 0.13 | FS17: 0.12 | FT17: =(FM$10*FU17-FH$10*FP17)/FL$10 -> 0.13 | FU17: 0.13 | FV17: 0.05 | FW17: 0.06 | FX17: =(FN10*FV17+FO10*FW17)/FP10 -> 0.055323383 | FY17: 0.03 | FZ17: =(FP10*FX17+FQ10*FY17)/FR10 -> 0.045811918 | GA17: 0.06 | GB17: =(FU$10*GC17-FP$10*FX17)/FT$10 -> 0.063703438 | GC17: 0.06 | GD17: 0.05 | GE17: 0.05 | GF17: =(FV10*GD17+FW10*GE17)/FX10 -> 0.05 | GG17: 0.06 | GH17: =(FX10*GF17+FY10*GG17)/FZ10 -> 0.053394825 | GL17: 0.07 | GM17: 0.06 | GN17: =(GD10*GL17+GE10*GM17)/GF10 -> 0.064586492 | GO17: 0.06 | GP17: =(GF10*GN17+GG10*GO17)/GH10 -> 0.062893478 | GQ17: 0.05 | GT17: -0.32 | GU17: -0.2 | GV17: =(GL10*GT17+GM10*GU17)/GN10 -> -0.25555878 | GW17: -0.14 | GY17: -0.05 | HA17: -0.21
A18: Reebok LFL | DR18: 0.15 | DS18: =(DL$10*DT18-DJ$10*DR18)/DK$10 -> 0.15 | DT18: 0.15 | DU18: =(DN$10*DV18-DK$10*DS18-DJ$10*DR18)/DM$10 -> 0.069274809 | DV18: 0.12 | DW18: 0.1 | DX18: =(DQ$10*DY18-DL$10*DT18)/DP$10 -> 0.075181195 | DY18: 0.11 | DZ18: 0.15 | EA18: =(DT$10*EB18-DR$10*DZ18)/DS$10 -> 0.11475083 | EB18: 0.13 | EC18: =(DV$10*ED18-DS$10*EA18-DR$10*DZ18)/DU$10 -> 0.13 | ED18: 0.13 | EE18: 0.05 | EF18: =(DY$10*EG18-DT$10*EB18)/DX$10 -> 0.094021084 | EG18: 0.11 | EH18: 0.06 | EI18: 0.09 | EJ18: 0.08 | EK18: 0.11 | EL18: 0.09 | EM18: 0.01 | EN18: =(EG$10*EO18-EB$10*EJ18)/EF$10 -> 0.06180456 | EO18: 0.07 | EP18: -0.01 | EQ18: -0.03 | ER18: -0.01 | ES18: -0.07 | ET18: -0.04 | EU18: 0 | EV18: =(EO$10*EW18-EJ$10*ER18)/EN$10 -> -0.04694414 | EW18: -0.03 | EX18: 0.04 | EY18: 0 | EZ18: 0.02 | FA18: -0.02 | FB18: 0 | FC18: 0.01 | FD18: =(EW$10*FE18-ER$10*EZ18)/EV$10 -> 0.0014431879 | FE18: 0.01 | FF18: -0.02 | FG18: -0.09 | FH18: -0.06 | FI18: -0.04 | FJ18: -0.05 | FK18: 0.03 | FL18: =(FE$10*FM18-EZ$10*FH18)/FD$10 -> -0.0045910836 | FM18: -0.03 | FN18: 0.03 | FO18: =(FH10*FP18-FF10*FN18)/FG10 -> 0.085402081 | FP18: 0.06 | FQ18: 0.07 | FR18: =(FH10*FP18+FI10*FQ18)/FJ10 -> 0.063612565 | FS18: 0.04 | FT18: =(FM$10*FU18-FH$10*FP18)/FL$10 -> 0.041397091 | FU18: 0.05 | FV18: -0.01 | FW18: 0.01 | FX18: =(FN10*FV18+FO10*FW18)/FP10 -> 0.00064676617 | FY18: -0.03 | FZ18: =(FP10*FX18+FQ10*FY18)/FR10 -> -0.010864163 | GA18: 0.03 | GB18: =(FU$10*GC18-FP$10*FX18)/FT$10 -> -0.018431232 | GC18: -0.01 | GD18: -0.01 | GE18: 0.05 | GF18: =(FV10*GD18+FW10*GE18)/FX10 -> 0.021926007 | GG18: 0.01 | GH18: =(FX10*GF18+FY10*GG18)/FZ10 -> 0.017877336 | GL18: 0.05 | GM18: 0.01 | GN18: =(GD10*GL18+GE10*GM18)/GF10 -> 0.028345968 | GO18: 0.04 | GP18: =(GF10*GN18+GG10*GO18)/GH10 -> 0.032647826 | GQ18: 0.04 | GT18: -0.25 | GU18: 0.01 | GV18: =(GL10*GT18+GM10*GU18)/GN10 -> -0.11037736 | GW18: -0.26 | GY18: 0.03 | HA18: -0.12
A19: eCommerce growth (cFX) | EP19: 0.68 | EQ19: 0.79 | ER19: 0.74 | ES19: 0.57 | ET19: 0.67 | EU19: =(EO10*EW19-EL10*ET19)/EM10 -> 0.55527211 | EV19: =(EK10*ES19+EM10*EU19)/EN10 -> 0.56288609 | EW19: 0.64 | EX19: 0.72 | EY19: 0.59 | EZ19: 0.65 | FA19: 1 | FB19: 0.78 | FC19: 0.62 | FE19: ='Profit and Loss'!U24 -> 0.72 | FF19: 0.56 | FG19: 0.58 | FH19: 0.57 | FI19: =(FB10*FJ19-EZ10*FH19)/FA10 -> 0.22246418 | FJ19: 0.44 | FK19: =(FE10*FM19-FB10*FJ19)/FC10 -> 0.36520174 | FL19: =(FA10*FI19+FC10*FK19)/FD10 -> 0.29295542 | FM19: 0.42 | FN19: 0.47 | FO19: =(FH10*FP19-FF10*FN19)/FG10 -> 0.50693472 | FP19: 0.49 | FQ19: =(FJ10*FR19-FH10*FP19)/FI10 -> 0.54536232 | FR19: 0.51 | FS19: =(FM10*FU19-FJ10*FR19)/FK10 -> 0.79985408 | FT19: =(FI10*FQ19+FK10*FS19)/FL10 -> 0.67602909 | FU19: 0.59 | FV19: 0.53 | FW19: 0.66 | FX19: =(FN10*FV19+FO10*FW19)/FP10 -> 0.59920398 | FY19: 0.39 | FZ19: =(FN10*FV19+FO10*FW19+FQ10*FY19)/FR10 -> 0.52062694 | GA19: =(FU10*GC19-FR10*FZ19)/FS10 -> 0.68958276 | GB19: =(FQ10*FY19+FS10*GA19)/FT10 -> 0.54687321 | GC19: ='Profit and Loss'!X24 -> 0.57 | GD19: 0.27 | GE19: 0.26 | GF19: =(FV10*GD19+FW10*GE19)/FX10 -> 0.264679 | GG19: 0.76 | GH19: =(FV10*GD19+FW10*GE19+FX10*GG19)/FZ10 -> 0.6768184 | GI19: 0.24 | GJ19: =(FY10*GG19+GA10*GI19)/GB10 -> 0.47746052 | GK19: 0.36 | GL19: 0.4 | GM19: 0.37 | GN19: =(GD10*GL19+GE10*GM19)/GF10 -> 0.38375948 | GO19: 0.14 | GP19: =(GD10*GL19+GE10*GM19+GF10*GO19)/GH10 -> 0.33042391 | GQ19: 0.46 | GR19: =(GG10*GO19+GI10*GQ19)/GJ10 -> 0.30847741 | GS19: 0.34 | GT19: 0.35 | GU19: 0.93 | GV19: =(GL10*GT19+GM10*GU19)/GN10 -> 0.66146589 | GW19: 0.51 | GY19: 0.43 | GZ19: =(GO10*GW19+GQ10*GY19)/GR10 -> 0.46588922 | HA19: 0.53 | HB19: 0.43 | HC19: -0.14 | HD19: =(GT10*HB19+GU10*HC19)/GV10 -> 0.12544526 | HE19: 0.08 | HG19: -0.02 | HH19: =(GW10*HE19+GY10*HG19)/GZ10 -> 0.024708882 | HI19: 0.04 | HJ19: 0.02 | HK19: 0.13 | HM19: 0.08 | HO19: -0.04 | HP19: =(HE10*HM19+HG10*HO19)/HH10 -> 0.014200493 | HQ19: 0.04 | HR19: -0.23 | HS19: 0.14 | HU19: 0.01 | HW19: -0.12 | HX19: =(HM10*HU19+HO10*HW19)/HP10 -> -0.057591362 | HY19: -0.05 | HZ19: 0.34 | IA19: -0.06 | IC19: -0.03 | IH19: 0.18 | II19: -0.03 | IK19: 0.15 | IM19: 0.21 | IO19: 0.16 | IP19: 0.25 | IQ19: 0.27
A20: % of total | DB20: =DB10/DB$26 -> 0.13777268 | DC20: =DC10/DC$26 -> 0.16825776 | DD20: =DD10/DD$26 -> 0.15272089 | DE20: =DE10/DE$26 -> 0.15946736 | DF20: =DF10/DF$26 -> 0.15525225 | DG20: =DG10/DG$26 -> 0.18012422 | DH20: =DH10/DH$26 -> 0.1688771 | DI20: =DI10/DI$26 -> 0.18271663 | ... GW20: =GW10/GW$26 -> 0.35276432 | GY20: =GY10/GY$26 -> 0.46899522 | GZ20: =GZ10/GZ$26 -> 0.40877829 | HA20: =HA10/HA$26 -> 0.40974602 | HB20: =HB10/HB$26 -> 0.34339408 | HC20: =HC10/HC$26 -> 0.37502462 | HD20: =HD10/HD$26 -> 0.35891735 | HE20: =HE10/HE$26 -> 0.35013908 | HG20: =HG10/HG$26 -> 0.47595873 | HH20: =HH10/HH$26 -> 0.40949582 | HI20: =HI10/HI$26 -> 0.38485448 | HJ20: =HJ10/HJ$26 -> 0.35929838 | HK20: =HK10/HK$26 -> 0.37823834 | HM20: =HM10/HM$26 -> 0.360799 | HO20: =HO10/HO$26 -> 0.48116833 | HP20: =HP10/HP$26 -> 0.41060619 | HQ20: =HQ10/HQ$26 -> 0.39260806 | HR20: =HR10/HR$26 -> 0.33636708 | HS20: =HS10/HS$26 -> 0.47299211 | HU20: =HU10/HU$26 -> 0.3968844 | HW20: =HW10/HW$26 -> 0.48482959 | HX20: =HX10/HX$26 -> 0.43733869 | HY20: =HY10/HY$26 -> 0.42010833 | HZ20: =HZ10/HZ$26 -> 0.38545592 | IA20: =IA10/IA$26 -> 0.42475987 | IC20: =IC10/IC$26 -> 0.37608208 | IH20: =IH10/IH$26 -> 0.35153584 | II20: =II10/II$26 -> 0.39280914 | IK20: =IK10/IK$26 -> 0.36455505 | IM20: =IM10/IM$26 -> 0.49572087 | IO20: =IO10/IO$26 -> 0.40026601 | IP20: =IP10/IP$26 -> 0.37621359 | IQ20: =IQ10/IQ$26 -> 0.43141035
A21: Other Businesses | DB21: 285 | DC21: 336 | DD21: =DB21+DC21 -> 621 | DE21: 347 | DF21: =DD21+DE21 -> 968 | DG21: 318 | DH21: =DE21+DG21 -> 665 | DI21: ='Profit and Loss'!O21 -> 15.996863 | DJ21: 295 | DK21: 362 | DL21: =DJ21+DK21 -> 657 | DM21: 326 | DN21: =DM21+DL21 -> 983 | DO21: 308 | DP21: =DO21+DM21 -> 634 | DQ21: ='Profit and Loss'!P27 -> 1293 | DR21: 316 | DS21: 387 | DT21: =DR21+DS21 -> 703 | DU21: 382 | DV21: =DT21+DU21 -> 1085 | DW21: =DY21-DV21 -> 335 | DX21: =DU21+DW21 -> 717 | DY21: ='Profit and Loss'!Q27 -> 1420 | DZ21: 376 | EA21: 410 | EB21: =DZ21+EA21 -> 786 | EC21: =ED21-EB21 -> 411 | ED21: 1197 | EE21: 382 | EF21: =+EG21-EB21 -> 794 | EG21: 1580 | EH21: 517 | EI21: =+EJ21-EH21 -> 550 | EJ21: 1067 | EK21: =EL21-EJ21 -> 486 | EL21: 1553 | EM21: 424 | EN21: =EK21+EM21 -> 910 | EO21: =EH21+EI21+EK21+EM21 -> 1977 | EP21: 548 | EQ21: =ER21-EP21 -> 502 | ER21: 1050 | ES21: 403 | ET21: =ET26-ET5-ET10 -> 1453 | EU21: 493 | EV21: =EV26-EV5-EV10 -> 896 | EW21: =EW26-EW5-EW10 -> 1946 | EX21: 382 | EY21: 422 | EZ21: =EX21+EY21 -> 804 | FA21: 354 | FB21: =EZ21+FA21 -> 1158 | FC21: =FC209 -> 366 | FD21: =FA21+FC21 -> 720 | FE21: =EZ21+FD21 -> 1524 | FF21: =FF209 -> 377 | FG21: =FG209 -> 365 | FH21: =FH209 -> 742 | FI21: =FI209 -> 342 | FJ21: =FJ209 -> 1084 | FK21: =FM21-FJ21 -> 383 | FL21: =FM21-FH21 -> 725 | FM21: =FM209 -> 1467 | FN21: =FN209 -> 396 | FO21: =FO209 -> 377 | FP21: =FP209 -> 773 | FQ21: =FQ209 -> 366 | FR21: =FR209 -> 1139 | FS21: =FS209 -> 336 | FT21: =FT209 -> 702 | ... GE21: =GE209 -> 189 | GF21: =GE21+GD21 -> 379 | GG21: =GG209 -> 230 | GH21: =GG21+GF21 -> 609 | GI21: =GI209 -> 220 | GJ21: =GJ209 -> 450 | GK21: =GI21+GG21+GE21+GD21 -> 829 | GL21: =GL209 -> 195 | GM21: =GM209 -> 147 | GN21: =GM21+GL21 -> 342 | GO21: =GO209 -> 162 | GP21: =GO21+GN21 -> 504 | GQ21: =GQ209 -> 101 | GR21: =GR209 -> 263 | GS21: =GQ21+GO21+GM21+GL21 -> 605 | GT21: =GT209 -> 156 | GU21: =GU209 -> 73.647 | GV21: =GU21+GT21 -> 229.647 | GW21: =GW209 -> 153.09 | GY21: =GY209 -> 93.263 | GZ21: =GZ209 -> 246.353 | HA21: =HA209 -> 476 | HB21: =HB209 -> 39 | HC21: =HC209 -> 34 | HD21: =HC21+HB21 -> 73 | HE21: =HE209 -> 44 | HG21: =HG209 -> 27 | HH21: =HH209 -> 71 | HI21: =HI209 -> 144 | HJ21: =HJ209 -> 36 | HK21: =HK209 -> 29 | HM21: =HM209 -> 46 | HO21: =HO209 -> 39 | HP21: =HP209 -> 85 | HQ21: =HQ209 -> 150 | HR21: =HR209 -> 80 | HS21: =HS209 -> 48 | HU21: =HU209 -> 38 | HW21: =HW209 -> 33 | HX21: =HX209 -> 71 | HY21: =HY209 -> 199 | HZ21: =HZ209 -> 32 | IA21: =IA209 -> 23 | IC21: =IC209 -> 29 | IH21: =IH209 -> 21 | II21: =II209 -> 14 | IK21: =IK209 -> 21 | IM21: =IM209 -> 16 | IO21: =IO209 -> 72 | IP21: =IP209 -> 62 | IQ21: =IQ209 -> 29
A22: Growth | DJ22: =DJ21/DB21-1 -> 0.035087719 | DK22: =DK21/DC21-1 -> 0.077380952 | DL22: =DL21/DD21-1 -> 0.057971014 | DM22: =DM21/DE21-1 -> -0.060518732 | DN22: =DN21/DF21-1 -> 0.015495868 | DO22: =DO21/DG21-1 -> -0.031446541 | DP22: =DP21/DH21-1 -> -0.046616541 | DQ22: =DQ21/DI21-1 -> 79.828346 | ... EG22: =EG21/DY21-1 -> 0.11267606 | EH22: =+EH21/DZ21-1 -> 0.375 | EI22: =EI21/EA21-1 -> 0.34146341 | EJ22: =EJ21/EB21-1 -> 0.35750636 | EK22: =EK21/EC21-1 -> 0.18248175 | EL22: =EL21/ED21-1 -> 0.29741019 | EM22: =EM21/EE21-1 -> 0.10994764 | EN22: =EN21/EF21-1 -> 0.14609572 | EO22: =EO21/EG21-1 -> 0.25126582 | EP22: =EP21/EH21-1 -> 0.059961315 | ... GW22: =GW21/GO21-1 -> -0.055 | GY22: =GY21/GQ21-1 -> -0.07660396 | GZ22: =GZ21/GR21-1 -> -0.063296578 | HA22: =HA21/GS21-1 -> -0.21322314 | HB22: =HB21/GT21-1 -> -0.75 | HC22: =HC21/GU21-1 -> -0.53833829 | HD22: =HD21/GV21-1 -> -0.68212082 | HE22: =HE21/GW21-1 -> -0.71258737 | HG22: =HG21/GY21-1 -> -0.71049612 | HH22: =HH21/GZ21-1 -> -0.71179568 | HI22: =HI21/HA21-1 -> -0.69747899 | HJ22: =HJ21/HB21-1 -> -0.076923077 | HK22: =HK21/HC21-1 -> -0.14705882 | HM22: =HM21/HE21-1 -> 0.045454545 | HO22: =HO21/HG21-1 -> 0.44444444 | HP22: =HP21/HH21-1 -> 0.1971831 | HQ22: =HQ21/HI21-1 -> 0.041666667 | HR22: =HR21/HJ21-1 -> 1.2222222 | HS22: =HS21/HK21-1 -> 0.65517241 | HU22: =HU21/HM21-1 -> -0.17391304 | HW22: =HW21/HO21-1 -> -0.15384615 | HX22: =HX21/HP21-1 -> -0.16470588 | HY22: =HY21/HQ21-1 -> 0.32666667 | HZ22: =HZ21/HR21-1 -> -0.6 | IA22: =IA21/HS21-1 -> -0.52083333 | IC22: =IC21/HU21-1 -> -0.23684211 | IH22: =IH21/HZ21-1 -> -0.34375 | II22: =II21/IA21-1 -> -0.39130435 | IK22: =IK21/IC21-1 -> -0.27586207 | IM22: =IM21/IE21-1 -> #DIV/0! | IO22: =IO21/IG21-1 -> #DIV/0! | IP22: =IP21/IH21-1 -> 1.952381 | IQ22: =IQ21/II21-1 -> 1.0714286
A23: FX & Scope impact | DJ23: =DJ22-DJ24 -> 0.065087719 | DK23: =DK22-DK24 -> 0.087380952 | DL23: =DL22-DL24 -> 0.077149758 | DM23: =DM22-DM24 -> 0.049481268 | DN23: =DN22-DN24 -> 0.067231405 | DO23: =DO22-DO24 -> -0.051446541 | DP23: =DP22-DP24 -> 0.0012180451 | DQ23: =DQ22-DQ24 -> 78.998346 | ... DW23: =DW22-DW24 -> 0.11966234 | DX23: =((DW23*DO21)+(DU23*DM21))/DP21 -> 0.12794953 | DY23: ='Profit and Loss'!Q29 -> 0.082221191 | DZ23: =DZ22-DZ24 -> 0.049873418 | EA23: =EA22-EA24 -> -0.060568475 | EB23: =EB22-EB24 -> -0.011934566 | EC23: =EC22-EC24 -> -0.05408377 | ED23: =ED22-ED24 -> -0.026774194 | EE23: =+EE22-EE24 -> 0.020298507 | EF23: =+EF22-EF24 -> -0.022608089 | EG23: =EG22-EG24 -> -0.017323944 | EH23: =+EH22-EH24 -> 0.055 | EI23: =+EI22-EI24 -> 0.11946341 | EJ23: =+EJ22-EJ24 -> 0.087506361 | EK23: =EK22-EK24 -> 0.11248175 | EL23: =EL22-EL24 -> 0.099410192 | EM23: =EM22-EM24 -> 0.041947644 | EN23: =+EN22-EN24 -> 0.077146096 | EO23: =+EO22-EO24 -> 0.082856962 | EP23: =EP22-EP24 -> -0.027038685 | EQ23: =EQ22-EQ24 -> -0.042272727 | ER23: =ER22-ER24 -> -0.035932521 | ES23: =ES22-ES24 -> -0.084781893 | ET23: =ET22-ET24 -> -0.050504185 | EU23: =EU22-EU24 -> -0.11526415 | EV23: =EV22-EV24 -> -0.098984615 | EW23: =EW22-EW24 -> -0.06439302 | ... GW23: =GW22-GW24 -> -0.025 | GY23: =GY22-GY24 -> -0.02519802 | GZ23: =GZ22-GZ24 -> -0.025076046 | HA23: =HA22-HA24 -> -0.008 | HB23: =HB22-HB24 -> -0.589 | HC23: =HC22-HC24 -> -1.1773859 | HD23: =HD22-HD24 -> -1.0776757 | HE23: =HE22-HE24 -> -0.71258737 | HG23: =HG22-HG24 -> -0.75149612 | HH23: =HH22-HH24 -> -0.72731724 | HI23: =HI22-HI24 -> -0.74250548 | HJ23: =HJ22-HJ24 -> 0.001 | HK23: =HK22-HK24 -> 0.012941176 | HM23: =HM22-HM24 -> 0.018454545 | HO23: =HO22-HO24 -> 0.028444444 | HP23: =HP22-HP24 -> 0.022253521 | HQ23: =HQ22-HQ24 -> 0.014298611 | HR23: =HR22-HR24 -> 1.2222222 | HS23: =HS22-HS24 -> 0.65517241 | HU23: =HU22-HU24 -> -0.17391304 | HW23: =HW22-HW24 -> -0.15384615 | HX23: =HX22-HX24 -> -0.16470588 | HY23: =HY22-HY24 -> 0.32666667 | HZ23: =HZ22-HZ24 -> 0 | IA23: =IA22-IA24 -> -0.002 | IC23: =IC22-IC24 -> 0.041157895 | IH23: =IH22-IH24 -> 0.002 | II23: =II22-II24 -> -0.39130435 | IK23: =IK22-IK24 -> -0.27586207 | IM23: =IM22-IM24 -> #DIV/0! | IO23: =IO22-IO24 -> #DIV/0! | IP23: =IP22-IP24 -> 0 | IQ23: =IQ22-IQ24 -> 0 | JA23: 2 year | JB23: =(EK21*(1+ES24)*(1+FA24))/EK21-1 -> -0.196594 | JC23: =(EM21*(1+EU24)*(1+FC24))/EM21-1 -> 0.23586229 | JD23: =(EP21*(1+EX24)*(1+FF24))/EP21-1 -> -0.27433 | JE23: =(EQ21*(1+EY24)*(1+FG24))/EQ21-1 -> -0.241584 | JF23: =(EJ21*(1+ER24)*(1+EZ24))/EJ21-1 -> -0.17772846 | JG23: =(ES21*(1+FA24)*(1+FI24))/ES21-1 -> -0.030463 | JH23: =(EL21*(1+ET24)*(1+FB24))/EL21-1 -> -0.18512141 | JI23: =(EU21*(1+FC24)*(1+FK24))/EU21-1 -> -0.058018535 | JJ23: =(EN21*(1+EV24)*(1+FD24))/EN21-1 -> 0.0049688563 | JK23: =(EX21*(1+FF24)*(1+FN24))/EX21-1 -> 0.04445 | JL23: =(EY21*(1+FG24)*(1+FO24))/EY21-1 -> -0.091784 | JM23: =(EZ21*(1+FH24)*(1+FP24))/EZ21-1 -> -0.027145794 | JN23: =(FA21*(1+FI24)*(1+FQ24))/FA21-1 -> 0.178004 | JO23: =(FB21*(1+FJ24)*(1+FR24))/FB21-1 -> 0.032672583 | JP23: =(FC21*(1+FK24)*(1+FS24))/FC21-1 -> -0.1583784
A24: Currency neutral | DJ24: -0.03 | DK24: -0.01 | DL24: =(DJ24*DB21+DK24*DC21)/DD21 -> -0.019178744 | DM24: -0.11 | DN24: =(DJ24*DB21+DK24*DC21+DM24*DE21)/DF21 -> -0.051735537 | DO24: 0.02 | DP24: =(DM24*DE21+DO24*DG21)/DH21 -> -0.047834586 | DQ24: ='Profit and Loss'!P24 -> 0.83 | DR24: 0.08 | DS24: -0.008 | DT24: 0.03 | DU24: 0.036 | DV24: 0.031 | DW24: -0.032 | DX24: =DX22-DX23 -> 0.0029652997 | DY24: =DY22-DY23 -> 0.016 | DZ24: 0.14 | EA24: 0.12 | EB24: 0.13 | EC24: 0.13 | ED24: 0.13 | EE24: 0.12 | EF24: =(-EB24*DT21+EG24*DY21)/DX21 -> 0.13 | EG24: 0.13 | EH24: 0.32 | EI24: 0.222 | EJ24: 0.27 | EK24: 0.07 | EL24: 0.198 | EM24: 0.068 | EN24: =+(EK24*EC21+EM24*EE21)/EF21 -> 0.068949622 | EO24: =(EH24*DZ21+EI24*EA21+EK24*EC21+EM24*EE21)/EG21 -> 0.16840886 | EP24: 0.087 | EQ24: -0.045 | ER24: 0.02 | ES24: -0.086 | ET24: =(EH21*EP24+EI21*EQ24+EK21*ES24)/EL21 -> -0.013887315 | EU24: 0.278 | EV24: =(EK21*ES24+EM21*EU24)/EN21 -> 0.0836 | EW24: =(EH21*EP24+EI21*EQ24+EK21*ES24+EM21*EU24)/EO21 -> 0.048712696 | EX24: -0.267 | EY24: -0.114 | EZ24: =(EP21*EX24+EQ21*EY24)/ER21 -> -0.19385143 | FA24: -0.121 | FB24: =(EP21*EX24+EQ21*EY24+ES21*FA24)/ET21 -> -0.17364556 | FC24: =(EU26*FC29-EU5*FC8-EU10*FC13)/EU21 -> -0.032971602 | FD24: =(ES21*FA24+EU21*FC24)/EV21 -> -0.072564732 | FE24: =(EP21*EX24+EQ21*EY24+ES21*FA24+EU21*FC24)/EW21 -> -0.13800719 | FF24: =FF213 -> -0.01 | FG24: =FG213 -> -0.144 | FH24: =FH213 -> -0.080435897 | FI24: =FI213 -> 0.103 | FJ24: =FJ213 -> -0.026810484 | FK24: =(FE21*FM24-FB21*FJ24)/FC21 -> -0.025900928 | FL24: =(FE21*FM24-EZ21*FH24)/FD21 -> 0.033533586 | FM24: =FM213 -> -0.026592047 | FN24: =FN213 -> 0.055 | FO24: =FO213 -> 0.061 | FP24: =FP213 -> 0.057951482 | FQ24: =FQ213 -> 0.068 | FR24: =FR213 -> 0.061121771 | FS24: =FS213 -> -0.136 | FT24: =FT213 -> -0.039768276 | ... GH24: =GH213 -> 0.070425894 | GI24: 0.42 | GJ24: =GJ213 -> 0.29791908 | GK24: 0.15 | GL24: =GL213 -> 0 | GM24: =GM213 -> -0.236 | GN24: =GN213 -> -0.11768865 | GO24: =GO213 -> -0.306 | GP24: =GP213 -> -0.18880788 | GQ24: =GQ213 -> -0.55090909 | GR24: =GR213 -> -0.42573333 | GS24: =GS213 -> -0.28490229 | ... GW24: =GW213 -> -0.03 | GY24: =GY213 -> -0.051405941 | GZ24: =GZ213 -> -0.038220532 | HA24: =HA213 -> -0.20522314 | HB24: =HB213 -> -0.161 | HC24: =HC213 -> 0.63904762 | HD24: =HD213 -> 0.39555487 | HE24: =HE213 -> 0 | HG24: =HG213 -> 0.041 | HH24: =HH213 -> 0.015521561 | HI24: =HI213 -> 0.04502649 | HJ24: =HJ213 -> -0.077923077 | HK24: =HK213 -> -0.16 | HM24: =HM213 -> 0.027 | HO24: =HO213 -> 0.416 | HP24: =HP213 -> 0.17492958 | HQ24: =HQ213 -> 0.027368056 | HR24: =HR213 -> 0 | HS24: =HS213 -> 0 | HU24: =HU213 -> 0 | HW24: =HW213 -> 0 | HX24: =HX213 -> 0 | HY24: =HY213 -> 0 | HZ24: =HZ213 -> -0.6 | IA24: =IA213 -> -0.51883333 | IC24: =IC213 -> -0.278 | IH24: =IH213 -> -0.34575 | II24: =II213 -> 0 | IK24: =IK213 -> 0 | IM24: =IM213 -> 0 | IO24: =IO213 -> -0.10638462 | IP24: =IP213 -> 1.952381 | IQ24: =IQ213 -> 1.0714286 | JA24: 3 year | JB24: =(EC21*(1+EK24)*(1+ES24)*(1+FA24))/EC21-1 -> -0.14035558 | JC24: =(EE21*(1+EM24)*(1+EU24)*(1+FC24))/EE21-1 -> 0.31990093 | JD24: =(EH21*(1+EP24)*(1+EX24)*(1+FF24))/EH21-1 -> -0.21119671 | JE24: =(EI21*(1+EQ24)*(1+EY24)*(1+FG24))/EI21-1 -> -0.27571272 | JF24: =(EB21*(1+EJ24)*(1+ER24)*(1+EZ24))/EB21-1 -> 0.044284859 | JG24: =(EK21*(1+ES24)*(1+FA24)*(1+FI24))/EK21-1 -> -0.11384318 | JH24: =(ED21*(1+EL24)*(1+ET24)*(1+FB24))/ED21-1 -> -0.023775443 | JI24: =(EM21*(1+EU24)*(1+FC24)*(1+FK24))/EM21-1 -> 0.20385231 | JJ24: =(EF21*(1+EN24)*(1+EV24)*(1+FD24))/EF21-1 -> 0.074261079 | JK24: =(EP21*(1+EX24)*(1+FF24)*(1+FN24))/EP21-1 -> -0.23441815 | JL24: =(EQ21*(1+EY24)*(1+FG24)*(1+FO24))/EQ21-1 -> -0.19532062 | JM24: =(ER21*(1+EZ24)*(1+FH24)*(1+FP24))/ER21-1 -> -0.21573497 | JN24: =(ES21*(1+FA24)*(1+FI24)*(1+FQ24))/ES21-1 -> 0.035465516 | JO24: =(ET21*(1+FB24)*(1+FJ24)*(1+FR24))/ET21-1 -> -0.14664643 | JP24: =(EU21*(1+FC24)*(1+FK24)*(1+FS24))/EU21-1 -> -0.18612801
A25: % of total | DB25: =DB21/DB$26 -> 0.10907003 | DC25: =DC21/DC$26 -> 0.13365155 | DD25: =DD21/DD$26 -> 0.12112346 | DE25: =DE21/DE$26 -> 0.11269893 | DF25: =DF21/DF$26 -> 0.11796247 | DG25: =DG21/DG$26 -> 0.1234472 | DH25: =DH21/DH$26 -> 0.11759505 | DI25: =DI21/DI$26 -> 0.0016817566 | ... GW25: =GW21/GW$26 -> 0.025667628 | GY25: =GY21/GY$26 -> 0.016810108 | GZ25: =GZ21/GZ$26 -> 0.021399014 | HA25: =HA21/HA$26 -> 0.023987099 | HB25: =HB21/HB$26 -> 0.0074031891 | HC25: =HC21/HC$26 -> 0.0066968682 | HD25: =HD21/HD$26 -> 0.0070565491 | HE25: =HE21/HE$26 -> 0.0076495132 | HG25: =HG21/HG$26 -> 0.005255986 | HH25: =HH21/HH$26 -> 0.0065203416 | HI25: =HI21/HI$26 -> 0.0067815767 | HJ25: =HJ21/HJ$26 -> 0.0067898906 | HK25: =HK21/HK$26 -> 0.0051813472 | HM25: =HM21/HM$26 -> 0.0071785268 | HO25: =HO21/HO$26 -> 0.0074942352 | HP25: =HP21/HP$26 -> 0.0072469946 | HQ25: =HQ21/HQ$26 -> 0.006663409 | HR25: =HR21/HR$26 -> 0.015168752 | HS25: =HS21/HS$26 -> 0.009710702 | HU25: =HU21/HU$26 -> 0.0067268543 | HW25: =HW21/HW$26 -> 0.0068578554 | HX25: =HX21/HX$26 -> 0.006787114 | HY25: =HY21/HY$26 -> 0.0096237547 | HZ25: =HZ21/HZ$26 -> 0.006028636 | IA25: =IA21/IA$26 -> 0.0040910708 | IC25: =IC21/IC$26 -> 0.0046489259 | IH25: =IH21/IH$26 -> 0.0034129693 | II25: =II21/II$26 -> 0.0023521505 | IK25: =IK21/IK$26 -> 0.0031674208 | IM25: =IM21/IM$26 -> 0.0026333114 | IO25: =IO21/IO$26 -> 0.0029019387 | IP25: =IP21/IP$26 -> 0.0094053398 | IQ25: =IQ21/IQ$26 -> 0.0043007563
A26: Total sales | DB26: =SUM(DB21,DB10,DB5) -> 2613 | DC26: =SUM(DC21,DC10,DC5) -> 2514 | DD26: =SUM(DD21,DD10,DD5) -> 5127 | DE26: =SUM(DE21,DE10,DE5) -> 3079 | DF26: =SUM(DF21,DF10,DF5) -> 8206 | DG26: =SUM(DG21,DG10,DG5) -> 2576 | DH26: =SUM(DH21,DH10,DH5) -> 5655 | DI26: =SUM(DI21,DI10,DI5) -> 9511.9969 | DJ26: 2577 | DK26: 2457 | DL26: 5034 | DM26: 2888 | DN26: 7923 | DO26: 2458 | DP26: =SUM(DP21,DP10,DP5) -> 5341 | DQ26: =SUM(DQ21,DQ10,DQ5) -> 10363 | DR26: 2674 | DS26: 2917 | DT26: 5590 | DU26: =SUM(DU21,DU10,DU5) -> 3468 | DV26: =SUM(DV21,DV10,DV5) -> 9058 | DW26: =SUM(DW21,DW10,DW5) -> 2932 | DX26: =DY26-DT26 -> 6400 | DY26: ='Profit and Loss'!Q32 -> 11990 | DZ26: =DZ5+DZ10+DZ21 -> 3273 | EA26: =EA5+EA10+EA21 -> 3064 | EB26: =DZ26+EA26 -> 6337 | EC26: =EC5+EC10+EC21 -> 3744 | ED26: =EC26+EB26 -> 10081 | EE26: 3241 | EF26: =EC26+EE26 -> 6985 | EG26: =EG21+EG10+EG5 -> 13323 | EH26: =EH5+EH10+EH21 -> 3824 | EI26: =EI5+EI10+EI21 -> 3517 | EJ26: =EH26+EI26 -> 7341 | EK26: =EK5+EK10+EK21 -> 4173 | EL26: =EK26+EJ26 -> 11514 | EM26: =EM5+EM10+EM21 -> 3369 | EN26: =EN127 -> 7542 | EO26: =EO127 -> 14883 | EP26: =EP5+EP10+EP21 -> 3751 | EQ26: =EQ127 -> 3383 | ER26: =ER127 -> 7134 | ES26: =ES127 -> 3879 | ET26: =ET127 -> 11013 | EU26: =EU127 -> 3479 | EV26: =EV127 -> 7358 | EW26: =EW127 -> 14492 | EX26: =EX5+EX10+EX21 -> 3533 | EY26: =EY127 -> 3412 | EZ26: =EZ127 -> 6892 | FA26: =FA127 -> 4065 | FB26: =FB127 -> 10957 | FC26: =FC216 -> 3610 | FD26: =FD127 -> 7569.3844 | FE26: =FE127 -> 14461.384 | FF26: =FF216 -> 4083 | FG26: =FG216 -> 3907 | FH26: =FH216 -> 7990 | FI26: =FI216 -> 4757 | FJ26: =FJ216 -> 12747 | FK26: =FK216 -> 4168 | FL26: =FL216 -> 8925 | FM26: =FM216 -> 16915 | ... GH26: =GH216 -> 16682 | GI26: =GK26-GG26-GE26-GD26 -> 5233 | GJ26: =GJ216 -> 11106 | GK26: =GK216 -> 21915 | GL26: =GL216 -> 5883 | GM26: =GM216 -> 5509 | GN26: =GN216 -> 11392 | GO26: =GO216 -> 6410 | GP26: =GP216 -> 17802 | GQ26: =GS26-GO26-GM26-GL26 -> 5839 | GR26: =GR216 -> 12249 | GS26: =GS216 -> 23641 | GT26: =GT216 -> 4753 | GU26: =GU216 -> 3578.647 | GV26: =GV216 -> 8331.647 | GW26: =GW216 -> 5964.322 | GY26: =GY216 -> 5548.031 | GZ26: =GZ216 -> 11512.353 | HA26: =HA216 -> 19844 | HB26: =HB216 -> 5268 | HC26: =HC216 -> 5077 | HD26: =HD216 -> 10345 | HE26: =HE216 -> 5752 | HG26: =HG216 -> 5137 | HH26: =HH216 -> 10889 | HI26: =HI216 -> 21234 | HJ26: =HJ216 -> 5302 | HK26: =HK216 -> 5597 | HM26: =HM216 -> 6408 | HO26: =HO216 -> 5204 | HP26: =HP216 -> 11729 | HQ26: =HQ216 -> 22511 | HR26: =HR216 -> 5274 | HS26: =HS216 -> 4943 | HU26: =HU216 -> 5649 | HW26: =HW216 -> 4812 | HX26: =HX216 -> 10461 | HY26: =HY216 -> 20678 | HZ26: =HZ216 -> 5308 | IA26: =IA216 -> 5622 | IC26: =IC216 -> 6238 | IE26: =IE216 -> 5865 | IG26: =IG216 -> 23033 | IH26: =IH216 -> 6153 | II26: =II216 -> 5952 | IK26: =IK216 -> 6630 | IM26: =IM216 -> 6076 | IO26: =IO216 -> 24811 | IP26: =IP216 -> 6592 | IQ26: =IQ216 -> 6743
A27: Growth | DJ27: =DJ26/DB26-1 -> -0.013777268 | DK27: =DK26/DC26-1 -> -0.022673031 | DL27: =DL26/DD26-1 -> -0.018139263 | DM27: =DM26/DE26-1 -> -0.062033128 | DN27: =DN26/DF26-1 -> -0.034486961 | DO27: =DO26/DG26-1 -> -0.045807453 | DP27: =DP26/DH26-1 -> -0.055526083 | DQ27: =DQ26/DI26-1 -> 0.089466297 | ... EG27: =EG26/DY26-1 -> 0.11117598 | EH27: =+EH26/DZ26-1 -> 0.16834708 | EI27: =EI26/EA26-1 -> 0.14784595 | EJ27: =EJ26/EB26-1 -> 0.15843459 | EK27: =EK26/EC26-1 -> 0.11458333 | EL27: =EL26/ED26-1 -> 0.1421486 | EM27: =EM26/EE26-1 -> 0.039493983 | EN27: =EN26/EF26-1 -> 0.079742305 | EO27: =EO26/EG26-1 -> 0.11709075 | EP27: =EP26/EH26-1 -> -0.019089958 | ... GW27: =GW26/GO26-1 -> -0.069528549 | GY27: =GY26/GQ26-1 -> -0.049831992 | GZ27: =GZ26/GR26-1 -> -0.060139358 | HA27: =HA26/GS26-1 -> -0.1606108 | HB27: =HB26/4381-1 -> 0.20246519 | HC27: =HC26/GU26-1 -> 0.4186926 | HD27: =HD26/GV26-1 -> 0.24165126 | HE27: =HE217 -> 0.034346341 | HG27: =HG217 -> -0.00097238429 | HH27: =HH217 -> -0.054146446 | HI27: =HI217 -> 0.15183076 | HJ27: =HJ26/HB26-1 -> 0.0064540623 | HK27: =HK26/HC26-1 -> 0.10242269 | HM27: =HM217 -> 0.11404729 | HO27: =HO217 -> 0.013042632 | HP27: =HP217 -> 0.07714207 | HQ27: =HQ217 -> 0.060139399 | HR27: =HR26/HJ26-1 -> -0.005281026 | HS27: =HS26/HK26-1 -> -0.11684831 | HU27: =HU217 -> -0.11844569 | HW27: =HW217 -> -0.075326672 | HX27: =HX217 -> -0.10810811 | HY27: =HY217 -> -0.081426858 | HZ27: =HZ26/HR26-1 -> 0.0064467198 | IA27: =IA26/HS26-1 -> 0.13736597 | IC27: =IC217 -> 0.10426624 | IE27: =IE217 -> 0.21882793 | IG27: =IG217 -> 0.11388916 | IH27: =IH26/HZ26-1 -> 0.15919367 | II27: =II26/IA26-1 -> 0.058697972 | IK27: =IK26/IC26-1 -> 0.062840654 | IM27: =IM26/IE26-1 -> 0.03597613 | IO27: =IO217 -> 0.077193592 | IP27: =IP26/IH26-1 -> 0.07134731 | IQ27: =IQ26/II26-1 -> 0.13289651
A28: FX & Scope impact | DJ28: =DJ27-DJ29 -> 0.041624362 | DK28: =DK27-DK29 -> 0.049874792 | DL28: =DL27-DL29 -> 0.046048285 | DM28: =DM27-DM29 -> 0.0065749056 | DN28: =DN27-DN29 -> 0.031583716 | DO28: =DO27-DO29 -> -0.049770025 | DP28: =DP27-DP29 -> -0.020012347 | DQ28: =DQ27-DQ29 -> 0.035249371 | ... DY28: =DY27-DY29 -> 0.070418219 | DZ28: =+DZ27-DZ29 -> 0.041937173 | EA28: =EA27-EA29 -> -0.04645869 | EB28: =EB27-EB29 -> -0.0063685152 | EC28: =EC27-EC29 -> -0.044812572 | ED28: =ED27-ED29 -> -0.027061161 | EE28: =EE27-EE29 -> -0.0046111869 | EF28: =EF27-EF29 -> -0.025895313 | EG28: =EG27-EG29 -> -0.01882402 | EH28: =+EH27-EH29 -> 0.032496181 | EI28: =+EI27-EI29 -> 0.075176534 | EJ28: =+EJ27-EJ29 -> 0.053132539 | EK28: =EK27-EK29 -> 0.074627137 | EL28: =EL27-EL29 -> 0.062148596 | EM28: =EM27-EM29 -> 0.032509719 | EN28: =EN129 -> 0.051384585 | EO28: =EO129 -> 0.053313188 | EP28: =EP27-EP29 -> -0.020757322 | EQ28: =EQ27-EQ29 -> -0.037924936 | ER28: =ER27-ER29 -> -0.02916115 | ES28: =ES$129 -> -0.070509466 | ET28: =ET$129 -> -0.044895258 | EU28: =EU$129 -> -0.092585337 | EV28: =EV$129 -> -0.080370724 | EW28: =EW$129 -> -0.055690654 | EX28: =EX27-EX29 -> -0.064655292 | EY28: =EY27-EY29 -> -0.093078037 | EZ28: =EZ27-EZ29 -> -0.0874836 | FA28: =FA27-FA29 -> -0.042874968 | FB28: =FB27-FB29 -> -0.071771543 | FC28: =FC27-FC29 -> -0.020722909 | FD28: =FD27-FD29 -> -0.046754906 | FE28: =FE27-FE29 -> -0.066804485 | ... GW28: =GW27-GW29 -> -0.043400624 | GY28: =GY27-GY29 -> -0.052482579 | GZ28: =GZ27-GZ29 -> -0.047729919 | HA28: =HA27-HA29 -> -0.02612586 | HB28: =HB27-HB29 -> -0.063637754 | HC28: =HC27-HC29 -> -0.13873163 | HD28: =HD27-HD29 -> -0.14958133 | HE28: =HE27-HE29 -> -0.0042211167 | HG28: =HG27-HG29 -> 0.02369895 | HH28: =HH27-HH29 -> -0.062237877 | HI28: =HI27-HI29 -> -0.0081692433 | HJ28: =HJ27-HJ29 -> 0.037089218 | HK28: =HK27-HK29 -> 0.066763443 | HM28: =HM27-HM29 -> 0.070011127 | HO28: =HO27-HO29 -> 0.023042632 | HP28: =HP27-HP29 -> 0.058598035 | HQ28: =HQ27-HQ29 -> 0.049704154 | HR28: =HR27-HR29 -> 0.011262731 | HS28: =HS27-HS29 -> -0.04810059 | HU28: =HU27-HU29 -> -0.060304404 | HW28: =HW27-HW29 -> -0.024118563 | HX28: =HX27-HX29 -> -0.053622954 | HY28: =HY27-HY29 -> -0.032048671 | HZ28: =HZ27-HZ29 -> -0.046870307 | IA28: =IA27-IA29 -> -0.026008092 | IC28: =IC27-IC29 -> -0.038738892 | IE28: =IE27-IE29 -> 0.021984622 | IG28: =IG27-IG29 -> -0.023638553 | IH28: =IH218 -> -0.0089728784 | II28: =II218 -> -0.054733953 | IJ28: =IJ218 -> -0.039488476 | IK28: =IK218 -> -0.050137107 | IL28: =IL218 -> -0.04559882 | IM28: =IM218 -> -0.072072072 | IO28: =IO218 -> -0.045183475 | IP28: =IP218 -> -0.056218834 | IQ28: =IQ218 -> -0.0038572279
A29: Currency neutral | DJ29: =(DJ8*DJ5+DJ13*DJ10+DJ24*DJ21)/DJ26 -> -0.05540163 | DK29: =(DK8*DK5+DK13*DK10+DK24*DK21)/DK26 -> -0.072547823 | DL29: =(DL8*DL5+DL13*DL10+DL24*DL21)/DL26 -> -0.064187548 | DM29: =(DM8*DM5+DM13*DM10+DM24*DM21)/DM26 -> -0.068608033 | DN29: =(DN8*DN5+DN13*DN10+DN24*DN21)/DN26 -> -0.066070677 | DO29: =(DO8*DO5+DO13*DO10+DO24*DO21)/DO26 -> 0.0039625712 | DP29: =(DP8*DP5+DP13*DP10+DP24*DP21)/DP26 -> -0.035513736 | DQ29: =(DQ8*DQ5+DQ13*DQ10+DQ24*DQ21)/DQ26 -> 0.054216926 | DR29: 0.04 | DS29: 0.11 | DT29: 0.07 | DU29: =(DU8*DM5+DU13*DM10+DU24*DM21)/DM26 -> 0.099865651 | DV29: =(DV8*DN5+DV13*DN10+DV24*DN21)/DN26 -> 0.084703774 | DW29: =(DW8*DO5+DW13*DO10+DW24*DO21)/DO26 -> 0.092703824 | DX29: =(DX8*DP5+DX13*DP10+DX24*DP21)/DP26 -> 0.096663172 | DY29: =(DY8*DQ5+DY13*DQ10+DY24*DQ21)/DQ26 -> 0.08658265 | DZ29: =(DZ8*DR5+DZ13*DR10+DZ24*DR21)/DR26 -> 0.1820718 | EA29: =(DS5*EA8+DS10*EA13+DS21*EA24)/DS26 -> 0.096852931 | EB29: 0.14 | EC29: =(DU5*EC8+DU10*EC13+DU21*EC24)/DU26 -> 0.12439735 | ED29: 0.14 | EE29: 0.11 | EF29: =(DX5*EF8+DX10*EF13+DX21*EF24)/DX26 -> 0.11730156 | EG29: 0.13 | EH29: =(EH8*DZ5+EH13*DZ10+EH24*DZ21)/DZ26 -> 0.1358509 | EI29: =(EJ29*EB26-EH29*DZ26)/EA26 -> 0.072669419 | EJ29: =+EJ130 -> 0.10530205 | EK29: =(EC5*EK8+EC10*EK13+EC21*EK24)/EC26 -> 0.039956197 | EL29: 0.08 | EM29: =(EE5*EM8+EE10*EM13+EE21*EM24)/EE26 -> 0.0069842641 | EN29: =EN130 -> 0.02835772 | EO29: =EO130 -> 0.063777558 | EP29: =(EP8*EH5+EP13*EH10+EP24*EH21)/EH26 -> 0.001667364 | EQ29: =(EQ8*EI5+EQ13*EI10+EQ24*EI21)/EI26 -> -0.00017571794 | ER29: =(ER8*EJ5+ER13*EJ10+ER24*EJ21)/EJ26 -> 0.00096335649 | ES29: =ES27-ES28 -> 5.6554038e-05 | ET29: =ET27-ET28 -> 0.001383012 | EU29: =EU27-EU28 -> 0.12523598 | EV29: =EV27-EV28 -> 0.055974012 | EW29: =EW27-EW28 -> 0.029419069 | EX29: =(EX8*EP5+EX13*EP10+EX24*EP21)/EP26 -> 0.0065374567 | EY29: =EY130 -> 0.10165031 | EZ29: =EZ130 -> 0.053561536 | FA29: =FA130 -> 0.09082547 | FB29: =FB130 -> 0.066686643 | FC29: =FC130 -> 0.058377407 | FD29: =FD130 -> 0.075483419 | FE29: =FE130 -> 0.064691899 | FF29: =FF219 -> 0.08730767 | FG29: =FG219 -> 0.048916716 | FH29: =FH219 -> 0.0683438 | FI29: =FI219 -> 0.12588971 | FJ29: =FJ219 -> 0.089648906 | FK29: =FK219 -> 0.11659003 | FL29: =FL219 -> 0.12150353 | FM29: =FM219 -> 0.096341086 | ... GL29: =GL219 -> 0.044340303 | GM29: 0.038 | GN29: =GN219 -> 0.041057027 | GO29: =GO219 -> 0.059649413 | GP29: =GP219 -> 0.04760259 | GQ29: =GQ219 -> 0.10169692 | GR29: =GR219 -> 0.079461642 | GS29: =GS219 -> 0.060519571 | GT29: =GT219 -> -0.19414618 | GU29: =GU219 -> -0.34220245 | ... GW29: =GW219 -> -0.026127925 | GY29: =GY219 -> 0.0026505874 | GZ29: =GZ219 -> -0.012409439 | HA29: =HA219 -> -0.13448494 | HB29: =HB219 -> 0.26610294 | HC29: =HC219 -> 0.55742422 | HD29: =HD219 -> 0.39123259 | HE29: =HE219 -> 0.038567457 | HG29: =HG219 -> -0.024671334 | HH29: =HH219 -> 0.0080914308 | HI29: =HI219 -> 0.16 | HJ29: =HJ219 -> -0.030635156 | HK29: =HK219 -> 0.035659248 | HM29: =HM219 -> 0.044036161 | HO29: =HO219 -> -0.01 | HP29: =HP219 -> 0.018544035 | HQ29: =HQ219 -> 0.010435245 | HR29: =HR219 -> -0.016543757 | HS29: =HS219 -> -0.068747722 | HU29: =HU219 -> -0.058141288 | HW29: =HW219 -> -0.051208109 | HX29: =HX219 -> -0.054485154 | HY29: =HY219 -> -0.049378187 | HZ29: =HZ219 -> 0.053317027 | IA29: =IA219 -> 0.16337406 | IC29: =IC219 -> 0.14300513 | IE29: =IE219 -> 0.19684331 | IG29: =IG219 -> 0.13752771 | IH29: =IH219 -> 0.16968915 | II29: =II219 -> 0.12 | IK29: =IK219 -> 0.11894113 | IM29: =IM219 -> 0.11 | IO29: =IO219 -> 0.12816815 | IP29: =IP219 -> 0.13516496 | IQ29: =IQ219 -> 0.13728327
A30: Check | DZ30: =DZ26-SUM(DZ5,DZ10,DZ21) -> 0 | EH30: =EH26-SUM(EH5,EH10,EH21) -> 0
FW31: =FW20-FO20 -> 0.025078003
A32: Gross profit by segment | DB32: =DB$2 -> Q1 08 | DC32: =DC$2 -> Q2 08 | DD32: =DD$2 -> H1 08 | DE32: =DE$2 -> Q3 08 | DF32: =DF$2 -> 9M 08 | DG32: =DG$2 -> Q4 08 | DH32: =DH$2 -> H2 08 | DI32: =DI$2 -> FY 08 | ... FN32: =FN$2 -> 1Q16 | FO32: 2Q16 | FP32: 1H16 | FQ32: =FQ$2 -> 3Q16 | FR32: =FR$2 -> 9M16 | FS32: =FS$2 -> 4Q16 | FT32: 2H16 | FU32: FY16 | FV32: =FV$2 -> 1Q17 | FW32: =FW$2 -> 2Q17 | FX32: =FX$2 -> 1H17 | FY32: =FY$2 -> 3Q17 | FZ32: =FZ$2 -> 9M17 | GA32: =GA$2 -> 4Q17 | GB32: 2H16 | GC32: FY16 | GD32: =GD$2 -> 1Q18 | GE32: =GE$2 -> 2Q18 | GF32: =GF$2 -> 1H18 | GG32: =GG$2 -> 3Q18 | GH32: =GH$2 -> 9M18
A33: Wholesale | DB33: 885 | DC33: 761 | DD33: =DB33+DC33 -> 1646 | DE33: 1015 | DF33: =DD33+DE33 -> 2661 | DG33: 726 | DH33: =DE33+DG33 -> 1741 | DI33: ='Profit and Loss'!O39 -> 3387 | DJ33: 798 | DK33: 637 | DL33: =DJ33+DK33 -> 1435 | DM33: 859 | DN33: =DL33+DM33 -> 2294 | DO33: 686 | DP33: =DO33+DM33 -> 1545 | DQ33: ='Profit and Loss'!P39 -> 2978 | DR33: =DR$5*DR35 -> 818.038 | DS33: =DS$5*DS35 -> 790.48 | DT33: =DR33+DS33 -> 1608.518 | DU33: =DU$5*DU35 -> 1014.399 | DV33: =DT33+DU33 -> 2622.917 | DW33: =DY33-DV33 -> 756.083 | DX33: =DU33+DW33 -> 1770.482 | DY33: ='Profit and Loss'!Q39 -> 3379 | DZ33: =DZ$5*DZ35 -> 999.92 | EA33: =EB33-DZ33 -> 780.08 | EB33: 1780 | EC33: =+ED33-EB33 -> 1041 | ED33: 2821 | EE33: =+EF33-EC33 -> 749 | EF33: =+EG33-EB33 -> 1790 | EG33: 3570 | EH33: =EH$5*EH35 -> 1091.6064 | EI33: =+EJ33-EH33 -> 810.3936 | EJ33: 1902 | EK33: =EL33-EJ33 -> 1132 | EL33: 3034 | EM33: =EN33-EK33 -> 806 | EN33: =EO33-EJ33 -> 1938 | EO33: 3840 | EP33: =EP35*EP5 -> 1099.083 | EQ33: =ER33-EP33 -> 828.917 | ER33: 1928 | ES33: =ET33-ER33 -> 1121 | ET33: 3049 | EU33: =EU35*EU5 -> 831.06 | EV33: =ES33+EU33 -> 1952.06 | EW33: =ER33+EV33 -> 3880.06 | EX33: =EX35*EX5 -> 1032.366 | EY33: =EY35*EY5 -> 861.105 | EZ33: =EX33+EY33 -> 1893.471 | FA33: =FB33-EZ33 -> 1137.529 | FB33: 3031 | FC33: =FE33-FB33 -> 880 | FD33: =FA33+FC33 -> 2017.529 | FE33: ='Profit and Loss'!U39 -> 3911 | FF33: =FF45-FF42-FF36 -> 1348.795 | FG33: =FG45-FG42-FG36 -> 1083.453 | FH33: =FH45-FH36-FH42 -> 2432.248 | FI33: =FI45-FI36-FI42 -> 1508.144 | FJ33: =FJ45-FJ36-FJ42 -> 3940.392 | FK33: =FK45-FK36-FK42 -> 1124.36 | FL33: =FI33+FK33 -> 2632.504 | FM33: =FM45-FM36-FM42 -> 5064.752 | FN33: =FN45-FN42-FN36 -> 1579.192 | FO33: =FO45-FO42-FO36 -> 1289.676 | FP33: =FP45-FP42-FP36 -> 2868.868
A34: Growth | DJ34: =DJ33/DB33-1 -> -0.098305085 | DK34: =DK33/DC33-1 -> -0.1629435 | DL34: =DL33/DD33-1 -> -0.12818955 | DM34: =DM33/DE33-1 -> -0.15369458 | DN34: =DN33/DF33-1 -> -0.13791808 | DO34: =DO33/DG33-1 -> -0.055096419 | DP34: =DP33/DH33-1 -> -0.11257898 | DQ34: =DQ33/DI33-1 -> -0.12075583 | ... FP34: =FP33/FH33-1 -> 0.17951294
A35: Gross margin % | DB35: =DB33/DB5 -> 0.44969512 | DC35: =DC33/DC5 -> 0.43361823 | DD35: =DD33/DD5 -> 0.44211657 | DE35: =DE33/DE5 -> 0.4529228 | DF35: =DF33/DF5 -> 0.44617706 | DG35: =DG33/DG5 -> 0.40468227 | DH35: =DH33/DH5 -> 0.4314746 | DI35: =DI33/DI5 -> 0.43658159 | ... DQ35: =DQ33/DQ5 -> 0.41568956 | DR35: 0.431 | DS35: 0.41 | DT35: =DT33/DT5 -> 0.42041767 | DU35: 0.419 | DV35: =DV33/DV5 -> 0.41986826 | DW35: =DW33/DW5 -> 0.39094261 | DX35: =DX33/DX5 -> 0.40654007 | DY35: =DY33/DY5 -> 0.41303019 | DZ35: 0.431 | EA35: =EA33/EA5 -> 0.3953776 | EB35: =EB33/EB5 -> 0.41462846 | EC35: =EC33/EC5 -> 0.40411491 | ED35: =ED33/ED5 -> 0.41068569 | EE35: =EE33/EE5 -> 0.35992311 | EF35: =EF33/EF5 -> 0.38436762 | EG35: =EG33/EG5 -> 0.39888268 | EH35: 0.4176 | EI35: =EI33/EI5 -> 0.3835275 | EJ35: =EJ33/EJ5 -> 0.40236937 | EK35: =EK33/EK5 -> 0.41268684 | EL35: =EL33/EL5 -> 0.40615797 | EM35: =EM33/EM5 -> 0.39069317 | EN35: =EN33/EN5 -> 0.40324594 | EO35: =EO33/EO5 -> 0.40281129 | EP35: 0.443 | EQ35: =EQ33/EQ5 -> 0.41157746 | ER35: =ER33/ER5 -> 0.42892102 | ES35: =ES33/ES5 -> 0.43909127 | ET35: =ET33/ET5 -> 0.43260499 | EU35: 0.405 | EV35: =EV33/EV5 -> 0.42390011 | EW35: =EW33/EW5 -> 0.42638022 | EX35: 0.438 | EY35: 0.413 | EZ35: =EZ33/EZ5 -> 0.42626542 | FA35: =FA33/FA5 -> 0.41867096 | FB35: =FB33/FB5 -> 0.42338315 | FC35: =FC33/FC5 -> 0.4317477 | FD35: =FD33/FD5 -> 0.42427603 | FE35: =FE33/FE5 -> 0.42523685 | FF35: =FF33/FF$5 -> 0.47982746 | FG35: =FG33/FG$5 -> 0.43599718 | FH35: =FH33/FH$5 -> 0.45926133 | FI35: =FI33/FI$5 -> 0.45549502 | FJ35: =FJ33/FJ$5 -> 0.45781248 | FK35: =FK33/FK$5 -> 0.42914504 | FL35: =FL33/FL$5 -> 0.443855 | FM35: =FM33/FM$5 -> 0.45112247 | ... FP35: =FP33/FP$5 -> 0.46212436
A36: Retail | DB36: 212 | DC36: 266 | DD36: =DB36+DC36 -> 478 | DE36: 305 | DF36: =DD36+DE36 -> 783 | DG36: 285 | DH36: =DE36+DG36 -> 590 | DI36: ='Profit and Loss'!O41 -> 1069 | DJ36: 218 | DK36: 295 | DL36: =DJ36+DK36 -> 513 | DM36: 302 | DN36: =DL36+DM36 -> 815 | DO36: 302 | DP36: =DO36+DM36 -> 604 | DQ36: ='Profit and Loss'!P41 -> 1116 | DR36: =DR$10*DR38 -> 267.138 | DS36: =DS$10*DS38 -> 391.902 | DT36: =DR36+DS36 -> 659.04 | DU36: =DU$10*DU38 -> 404.985 | DV36: =DT36+DU36 -> 1064.025 | DW36: =DY36-DV36 -> 411.975 | DX36: =DU36+DW36 -> 816.96 | DY36: ='Profit and Loss'!Q41 -> 1476 | DZ36: =+DZ38*DZ10 -> 353.124 | EA36: =EB36-DZ36 -> 447.876 | EB36: 801 | EC36: =+ED36-EB36 -> 472 | ED36: 1273 | EE36: =+EF36-EC36 -> 476 | EF36: =+EG36-EB36 -> 948 | EG36: 1749 | EH36: =EH$10*EH38 -> 426.195 | EI36: =+EJ36-EH36 -> 536.039 | EJ36: =EJ$10*EJ38 -> 962.234 | EK36: =EL36-EJ36 -> 557.766 | EL36: 1520 | EM36: =EN36-EK36 -> 535 | EN36: =EO36-EJ36 -> 1092.766 | EO36: 2055 | EP36: =EP38*EP10 -> 438.254 | EQ36: =ER36-EP36 -> 566.746 | ER36: 1005 | ES36: =ET36-ER36 -> 568 | ET36: 1573 | EU36: =EU38*EU10 -> 581.882 | EV36: =ES36+EU36 -> 1149.882 | EW36: =ER36+EV36 -> 2154.882 | EX36: =EX38*EX10 -> 475.606 | EY36: =EY38*EY10 -> 579.59 | EZ36: =EX36+EY36 -> 1055.196 | FA36: =FB36-EZ36 -> 608.804 | FB36: 1664 | FC36: =FE36-FB36 -> 617 | FD36: =FA36+FC36 -> 1225.804 | FE36: ='Profit and Loss'!U41 -> 2281 | FF36: =FF38*FF10 -> 518.205 | FG36: =FH36-FF36 -> 692.547 | FH36: =FJ36-FI36 -> 1210.752 | FI36: =FI38*FI10 -> 677.856 | FJ36: =FJ38*FJ10 -> 1888.608 | FK36: =FK38*FK10 -> 717.64 | FL36: =FI36+FK36 -> 1395.496 | FM36: =FH36+FL36 -> 2606.248 | FN36: =FN38*FN10 -> 632.808 | FO36: =FO38*FO10 -> 720.324 | FP36: =FP38*FP10 -> 1353.132
A37: Growth | DJ37: =DJ36/DB36-1 -> 0.028301887 | DK37: =DK36/DC36-1 -> 0.10902256 | DL37: =DL36/DD36-1 -> 0.073221757 | DM37: =DM36/DE36-1 -> -0.0098360656 | DN37: =DN36/DF36-1 -> 0.040868455 | DO37: =DO36/DG36-1 -> 0.059649123 | DP37: =DP36/DH36-1 -> 0.023728814 | DQ37: =DQ36/DI36-1 -> 0.043966324 | ... FP37: =FP36/FH36-1 -> 0.11759634
A38: Gross margin % | DB38: =DB36/DB10 -> 0.58888889 | DC38: =DC36/DC10 -> 0.62884161 | DD38: =DD36/DD10 -> 0.61047254 | DE38: =DE36/DE10 -> 0.62118126 | DF38: =DF36/DF10 -> 0.61459969 | DG38: =DG36/DG10 -> 0.61422414 | DH38: =DH36/DH10 -> 0.61780105 | DI38: =DI36/DI10 -> 0.6150748 | ... DQ38: =DQ36/DQ10 -> 0.58551941 | DR38: 0.582 | DS38: 0.651 | DT38: =DT36/DT10 -> 0.62114986 | DU38: 0.609 | DV38: =DV36/DV10 -> 0.61646871 | DW38: =DW36/DW10 -> 0.62138009 | DX38: =DX36/DX10 -> 0.61518072 | DY38: =DY36/DY10 -> 0.61783173 | DZ38: 0.612 | EA38: =EA36/EA10 -> 0.65767401 | EB38: =EB36/EB10 -> 0.63672496 | EC38: =EC36/EC10 -> 0.62351387 | ED38: =ED36/ED10 -> 0.63176179 | EE38: =EE36/EE10 -> 0.61182519 | EF38: =EF36/EF10 -> 0.61758958 | EG38: =EG36/EG10 -> 0.62620838 | EH38: 0.615 | EI38: =EI36/EI10 -> 0.62768033 | EJ38: 0.622 | EK38: =EK36/EK10 -> 0.59085381 | EL38: =EL36/EL10 -> 0.61019671 | EM38: =EM36/EM10 -> 0.60657596 | EN38: =EN36/EN10 -> 0.59844797 | EO38: =EO36/EO10 -> 0.60924993 | EP38: 0.607 | EQ38: =EQ36/EQ10 -> 0.65368627 | ER38: =ER36/ER10 -> 0.63247325 | ES38: =ES36/ES10 -> 0.61538462 | ET38: =ET36/ET10 -> 0.62619427 | EU38: 0.623 | EV38: =EV36/EV10 -> 0.61921486 | EW38: =EW36/EW10 -> 0.6253285 | EX38: 0.599 | EY38: 0.605 | EZ38: =EZ36/EZ10 -> 0.60228082 | FA38: =FA36/FA10 -> 0.58147469 | FB38: =FB36/FB10 -> 0.59449804 | FC38: =FC36/FC10 -> 0.60397516 | FD38: =FD36/FD10 -> 0.59258659 | FE38: =FE36/FE10 -> 0.59703208 | FF38: =FN38-3.3% -> 0.579 | FG38: =FG36/FG10 -> 0.65520057 | FH38: =FH36/FH10 -> 0.6202623 | FI38: 0.614 | FJ38: 0.618 | FK38: 0.616 | FL38: =FL36/FL10 -> 0.61502688 | FM38: =FM36/FM10 -> 0.617448 | FN38: 0.612 | FO38: 0.612 | FP38: 0.612
A39: Retail & Wholesale gross margin | EX39: =EX45-EX42 -> 1563.02 | EY39: =EY45-EY42 -> 1510.53 | EZ39: =EZ45-EZ42 -> 3073.55 | FA39: =FA45-FA42 -> 1792.45 | FB39: =FB45-FB42 -> 4866 | FC39: =FC45-FC42 -> 1506 | FD39: =FD45-FD42 -> 3298.45 | FE39: =FE45-FE42 -> 6467 | ... GK39: =GK45-GK42 -> 10979
A40: Growth | FD40: =FD39/EV39-1 -> #DIV/0! | FE40: =FE39/EW39-1 -> #DIV/0! | FF40: =FF39/EX39-1 -> 0.19448248 | FG40: =FG39/EY39-1 -> 0.17574626 | FH40: =FH39/EZ39-1 -> 0.18527436 | FI40: =FI39/FA39-1 -> 0.21955982 | FJ40: =FJ39/FB39-1 -> 0.19790382 | FK40: =FK39/FC39-1 -> 0.22310757 | ... GK40: =GK39/GC39-1 -> 0.054152664
A41: Gross margin % | EX41: =EX39/(EX5+EX10) -> 0.49603935 | EY41: =EY39/(EY5+EY10) -> 0.496395 | EZ41: =EZ39/(EZ5+EZ10) -> 0.49621408 | FA41: =FA39/(FA5+FA10) -> 0.47620882 | FB41: =FB39/(FB5+FB10) -> 0.48865234 | FC41: =FC39/(FC5+FC10) -> 0.49219022 | FD41: =FD39/(FD5+FD10) -> 0.48337489 | FE41: =FE39/(FE5+FE10) -> 0.49678161 | ... GK41: =GK39/(GK5+GK10) -> 0.52067723
A42: Other Businesses | DB42: 130 | DC42: 143 | DD42: =DB42+DC42 -> 273 | DE42: 147 | DF42: =DD42+DE42 -> 420 | DG42: 123 | DH42: =DE42+DG42 -> 270 | DI42: ='Profit and Loss'!O43 -> 543 | DJ42: 116 | DK42: 138 | DL42: =DJ42+DK42 -> 254 | DM42: 123 | DN42: =DL42+DM42 -> 377 | DO42: 129 | DP42: =DO42+DM42 -> 252 | DQ42: ='Profit and Loss'!P43 -> 509 | DR42: =DR$21*DR44 -> 142.2 | DS42: =DS$21*DS44 -> 171.054 | DT42: =DR42+DS42 -> 313.254 | DU42: =DU$21*DU44 -> 173.046 | DV42: =DT42+DU42 -> 486.3 | DW42: =DY42-DV42 -> 131.7 | DX42: =DU42+DW42 -> 304.746 | DY42: ='Profit and Loss'!Q43 -> 618 | DZ42: =DZ$21*DZ44 -> 171.456 | EA42: =EB42-DZ42 -> 184.544 | EB42: 356 | EC42: =+ED42-EB42 -> 176 | ED42: 532 | EE42: =+EF42-EC42 -> 156 | EF42: =+EG42-EB42 -> 332 | EG42: 688 | EH42: =EH$21*EH44 -> 225.929 | EI42: =+EJ42-EH42 -> 248.886 | EJ42: =EJ$21*EJ44 -> 474.815 | EK42: =EL42-EJ42 -> 207.185 | EL42: 682 | EM42: =EN42-EK42 -> 163 | EN42: =EO42-EJ42 -> 370.185 | EO42: 845 | EP42: =EP44*EP21 -> 244.408 | EQ42: =ER42-EP42 -> 217.592 | ER42: 462 | ES42: =ET42-ER42 -> 143 | ET42: 605 | EU42: =EU44*EU21 -> 184.382 | EV42: =ES42+EU42 -> 327.382 | EW42: =ER42+EV42 -> 789.382 | EX42: =EX44*EX21 -> 148.98 | EY42: =EY44*EY21 -> 162.47 | EZ42: =EX42+EY42 -> 311.45 | FA42: =FB42-EZ42 -> 125.55 | FB42: 437 | FC42: =FC377 -> 115 | FD42: =FA42+FC42 -> 240.55 | FE42: ='Profit and Loss'!U43 -> 457 | FF42: =FF377 -> 141 | FG42: =FG377 -> 113 | FH42: =FH377 -> 254 | FI42: =FI377 -> 118 | FJ42: =FJ377 -> 372 | FK42: =FK377 -> 125 | FL42: =FI42+FK42 -> 243 | FM42: =FM377 -> 497 | FN42: =FN377 -> 146 | FO42: =FO377 -> 149 | FP42: =FP377 -> 295 | FQ42: =FQ377 -> 138 | FR42: =FR377 -> 433 | FS42: =FS377 -> 120 | FT42: =FT377 -> 258 | ... GK42: =GK377 -> 384
A43: Growth | DJ43: =DJ42/DB42-1 -> -0.10769231 | DK43: =DK42/DC42-1 -> -0.034965035 | DL43: =DL42/DD42-1 -> -0.06959707 | DM43: =DM42/DE42-1 -> -0.16326531 | DN43: =DN42/DF42-1 -> -0.10238095 | DO43: =DO42/DG42-1 -> 0.048780488 | DP43: =DP42/DH42-1 -> -0.066666667 | DQ43: =DQ42/DI42-1 -> -0.062615101 | ... GC43: =GC42/FU42-1 -> -0.47920434 | GD43: =GD378 -> -0.048780488 | GE43: =GE42/FW42-1 -> 0.12658228 | GF43: =GF42/FX42-1 -> 0.037267081 | GG43: =GG42/FY42-1 -> 0.92647059 | GH43: =GH42/FZ42-1 -> 0.30131004 | GI43: =GI42/GA42-1 -> 0.45762712 | GJ43: =GJ42/GB42-1 -> 0.70866142 | GK43: =GK42/GC42-1 -> 0.33333333
A44: Gross margin % | DB44: =DB42/DB21 -> 0.45614035 | DC44: =DC42/DC21 -> 0.42559524 | DD44: =DD42/DD21 -> 0.43961353 | DE44: =DE42/DE21 -> 0.42363112 | DF44: =DF42/DF21 -> 0.4338843 | DG44: =DG42/DG21 -> 0.38679245 | DH44: =DH42/DH21 -> 0.40601504 | DI44: =DI42/DI21 -> 33.944155 | ... DQ44: =DQ42/DQ21 -> 0.39365816 | DR44: 0.45 | DS44: 0.442 | DT44: =DT42/DT21 -> 0.44559602 | DU44: 0.453 | DV44: =DV42/DV21 -> 0.44820276 | DW44: =DW42/DW21 -> 0.39313433 | DX44: =DX42/DX21 -> 0.42502929 | DY44: =DY42/DY21 -> 0.43521127 | DZ44: 0.456 | EA44: =EA42/EA21 -> 0.45010732 | EB44: =EB42/EB21 -> 0.45292621 | EC44: =EC42/EC21 -> 0.42822384 | ED44: =ED42/ED21 -> 0.44444444 | EE44: =EE42/EE21 -> 0.40837696 | EF44: =EF42/EF21 -> 0.41813602 | EG44: =EG42/EG21 -> 0.43544304 | EH44: 0.437 | EI44: =EI42/EI21 -> 0.45252 | EJ44: 0.445 | EK44: =EK42/EK21 -> 0.42630658 | EL44: =EL42/EL21 -> 0.43915003 | EM44: =EM42/EM21 -> 0.38443396 | EN44: =EN42/EN21 -> 0.4067967 | EO44: =EO42/EO21 -> 0.42741528 | EP44: 0.446 | EQ44: =EQ42/EQ21 -> 0.4334502 | ER44: =ER42/ER21 -> 0.44 | ES44: =ES42/ES21 -> 0.35483871 | ET44: =ET42/ET21 -> 0.4163799 | EU44: 0.374 | EV44: =EV42/EV21 -> 0.3653817 | EW44: =EW42/EW21 -> 0.40564337 | EX44: 0.39 | EY44: 0.385 | EZ44: =EZ42/EZ21 -> 0.38737562 | FA44: =FA42/FA21 -> 0.35466102 | FB44: =FB42/FB21 -> 0.37737478 | FC44: =FC42/FC21 -> 0.31420765 | FD44: =FD42/FD21 -> 0.33409722 | FE44: =FE42/FE21 -> 0.29986877 | FF44: =FF42/FF$21 -> 0.37400531 | FG44: =FG42/FG$21 -> 0.30958904 | FH44: =FH42/FH$21 -> 0.34231806 | FI44: =FI42/FI$21 -> 0.34502924 | FJ44: =FJ42/FJ$21 -> 0.34317343 | FK44: =FK42/FK$21 -> 0.32637076 | FL44: =FL42/FL$21 -> 0.33517241 | FM44: =FM42/FM$21 -> 0.33878664 | ... GK44: =GK42/GK$21 -> 0.46320869
A45: Total | DB45: =SUM(DB42,DB36,DB33) -> 1227 | DC45: =SUM(DC42,DC36,DC33) -> 1170 | DD45: =SUM(DD42,DD36,DD33) -> 2397 | DE45: =SUM(DE42,DE36,DE33) -> 1467 | DF45: =SUM(DF42,DF36,DF33) -> 3864 | DG45: =SUM(DG42,DG36,DG33) -> 1134 | DH45: =SUM(DH42,DH36,DH33) -> 2601 | DI45: =SUM(DI42,DI36,DI33) -> 4999 | ... DQ45: =SUM(DQ42,DQ36,DQ33) -> 4603 | DR45: =DR395 -> 1299.564 | DS45: =DS395 -> 1426.413 | DT45: =DT395 -> 2727.92 | DU45: =DU395 -> 1640.364 | DV45: =DT45+DU45 -> 4368.284 | DW45: 1361 | DX45: =DU45+DW45 -> 3001.364 | DY45: 5728 | DZ45: =DZ395 -> 1587.405 | EA45: =EA395 -> 1506 | EB45: =EB395 -> 3093.405 | EC45: =EC395 -> 1762 | ED45: =EB45+EC45 -> 4855.405 | EE45: =EE395 -> 1478 | EF45: =EC45+EE45 -> 3240 | EG45: =EG395 -> 6344 | EH45: =EH395 -> 1826 | EI45: =EI395 -> 1697 | EJ45: =EJ395 -> 3523 | EK45: =EK395 -> 1978 | EL45: =EJ45+EK45 -> 5501 | EM45: =EN45-EK45 -> 1603 | EN45: =EO45-EJ45 -> 3581 | EO45: =EO395 -> 7104 | EP45: =EP395 -> 1881 | EQ45: =EQ395 -> 1694 | ER45: =ER395 -> 3575 | ES45: =ES395 -> 1913 | ET45: =ET395 -> 5488 | EU45: =EU395 -> 1652 | EV45: =EV395 -> 3565 | ... GK45: =GK395 -> 11363
A46: Growth | DJ46: =DJ45/DB45-1 -> -0.077424613 | DK46: =DK45/DC45-1 -> -0.085470085 | DL46: =DL45/DD45-1 -> -0.08135169 | DM46: =DM45/DE45-1 -> -0.12474438 | DN46: =DN45/DF45-1 -> -0.097826087 | DO46: =DO45/DG45-1 -> -0.014991182 | DP46: =DP45/DH45-1 -> -0.076893502 | DQ46: =DQ45/DI45-1 -> -0.079215843 | ... GK46: =GK45/GC45-1 -> 0.061664954
A47: Gross margin % | DB47: =DB45/DB26 -> 0.4695752 | DC47: =DC45/DC26 -> 0.46539379 | DD47: =DD45/DD26 -> 0.46752487 | DE47: =DE45/DE26 -> 0.47645339 | DF47: =DF45/DF26 -> 0.47087497 | DG47: =DG45/DG26 -> 0.44021739 | DH47: =DH45/DH26 -> 0.45994695 | DI47: =DI45/DI26 -> 0.52554685 | ... GK47: =GK45/GK26 -> 0.51850331
A48: yoy gross margin bp | DJ48: =(DJ47-DB47)*10000 -> -303.04731 | DK48: =(DK47-DC47)*10000 -> -299.03359 | DL48: =(DL47-DD47)*10000 -> -300.99362 | DM48: =(DM47-DE47)*10000 -> -318.55056 | DN48: =(DN47-DF47)*10000 -> -308.90115 | DO48: =(DO47-DG47)*10000 -> 142.17108 | DP48: =(DP47-DH47)*10000 -> -104.05665 | DQ48: =(DQ47-DI47)*10000 -> -813.70454 | ... GK48: =(GK47-GC47)*10000 -> 140.73107
DJ49: =DJ33+DJ36+DJ42-DJ45 -> 0 | DK49: =DK33+DK36+DK42-DK45 -> 0 | DL49: =DL33+DL36+DL42-DL45 -> 0 | DM49: =DM33+DM36+DM42-DM45 -> 0 | DN49: =DN33+DN36+DN42-DN45 -> 0 | DO49: =DO33+DO36+DO42-DO45 -> 0 | DP49: =DP33+DP36+DP42-DP45 -> 0 | DQ49: check | DR49: =DR33+DR36+DR42-DR45 -> -72.188 | DS49: =DS33+DS36+DS42-DS45 -> -72.977 | DT49: =DT33+DT36+DT42-DT45 -> -147.108 | DU49: =DU33+DU36+DU42-DU45 -> -47.934 | DV49: =DV33+DV36+DV42-DV45 -> -195.042 | DW49: =DW45*DV54 -> -60.768064 | DX49: =DW49+DU49 -> -108.70206 | DY49: =DY33+DY36+DY42-DY45 -> -255 | DZ49: =DZ33+DZ36+DZ42-DZ45 -> -62.905 | EA49: =EA33+EA36+EA42-EA45 -> -93.5 | EB49: =EB33+EB36+EB42-EB45 -> -156.405 | EC49: =EC33+EC36+EC42-EC45 -> -73 | ED49: =ED33+ED36+ED42-ED45 -> -229.405 | EE49: =EE33+EE36+EE42-EE45 -> -97 | EF49: =EE49+EC49 -> -170 | EG49: =EG33+EG36+EG42-EG45 -> -337 | EH49: =EH33+EH36+EH42-EH45 -> -82.2696 | EI49: =EI33+EI36+EI42-EI45 -> -101.6814 | EJ49: =EJ33+EJ36+EJ42-EJ45 -> -183.951 | EK49: =EK33+EK36+EK42-EK45 -> -81.049 | EL49: =EL33+EL36+EL42-EL45 -> -265 | EM49: =EM33+EM36+EM42-EM45 -> -99 | EN49: =EM49+EK49 -> -180.049 | EO49: =EO33+EO36+EO42-EO45 -> -364 | EP49: =EP33+EP36+EP42-EP45 -> -99.255 | EQ49: =EQ33+EQ36+EQ42-EQ45 -> -80.745 | ER49: =ER33+ER36+ER42-ER45 -> -180 | ES49: =ES33+ES36+ES42-ES45 -> -81 | ET49: =ET33+ET36+ET42-ET45 -> -261 | EU49: =EU33+EU36+EU42-EU45 -> -54.676 | EV49: =EV33+EV36+EV42-EV45 -> -135.676 | ... FE49: =FE33+FE36+FE42-FE45 -> -275
DR50: =DR45+DR49 -> 1227.376 | DS50: =DS45+DS49 -> 1353.436 | DU50: =DU45+DU49 -> 1592.43 | DW50: =DW45+DW49 -> 1300.2319 | DY50: =DY45+DY49 -> 5473 | DZ50: =DZ33+DZ36+DZ42 -> 1524.5 | EA50: =EA33+EA36+EA42 -> 1412.5 | EB50: =DZ50+EA50 -> 2937 | EC50: =EC33+EC36+EC42 -> 1689 | EE50: =EE33+EE36+EE42 -> 1381 | EF50: =EC50+EE50 -> 3070 | EG50: =EG33+EG36+EG42 -> 6007 | EH50: =EH33+EH36+EH42 -> 1743.7304 | EI50: =EI33+EI36+EI42 -> 1595.3186 | EJ50: =EH50+EI50 -> 3339.049 | EK50: =EK33+EK36+EK42 -> 1896.951 | EM50: =EM33+EM36+EM42 -> 1504 | EN50: =EK50+EM50 -> 3400.951 | EO50: =EO33+EO36+EO42 -> 6740
DR51: =DR50/DR26 -> 0.45900374 | DS51: =DS50/DS26 -> 0.46398217 | DU51: =DU50/DU26 -> 0.4591782 | DW51: =DW50/DW26 -> 0.44346246 | DY51: =DY50/DY26 -> 0.45646372 | DZ51: =DZ50/DZ26 -> 0.46578063 | EA51: =EA50/EA26 -> 0.46099869 | EC51: =EC50/EC26 -> 0.45112179 | EE51: =EE50/EE26 -> 0.42610305 | EG51: =EG50/EG26 -> 0.45087443 | EH51: =EH50/EH26 -> 0.45599644 | EI51: =EI50/EI26 -> 0.4536021 | EK51: =EK50/EK26 -> 0.45457728 | EM51: =EM50/EM26 -> 0.44642327 | EO51: =EO50/EO26 -> 0.45286569
DZ52: =DZ50-DZ49 -> 1587.405 | EA52: =EA50-EA49 -> 1506 | EB52: =DZ52+EA52 -> 3093.405 | EC52: =EC50-EC49 -> 1762 | EE52: =EE50-EE49 -> 1478 | EF52: =EC52+EE52 -> 3240 | EG52: =EG50-EG49 -> 6344 | EH52: =EH50-EH49 -> 1826 | EI52: =EI50-EI49 -> 1697 | EJ52: =EH52+EI52 -> 3523 | EK52: =EK50-EK49 -> 1978 | EM52: =EM50-EM49 -> 1603 | EN52: =EK52+EM52 -> 3581 | EO52: =EO50-EO49 -> 7104
DZ53: =DZ52/DZ26 -> 0.485 | EA53: =EA52/EA26 -> 0.49151436 | EC53: =EC52/EC26 -> 0.47061966 | EE53: =EE52/EE26 -> 0.45603209 | EG53: =EG52/EG26 -> 0.47616903 | EH53: =EH52/EH26 -> 0.47751046 | EI53: =EI52/EI26 -> 0.48251351 | EK53: =EK52/EK26 -> 0.47399952 | EM53: =EM52/EM26 -> 0.47580885 | EO53: =EO52/EO26 -> 0.47732312
DR54: =DR49/DR45 -> -0.055547861 | DS54: =DS49/DS45 -> -0.051161199 | DT54: =DT49/DT45 -> -0.053926801 | DU54: =DU49/DU45 -> -0.029221563 | DV54: =DV49/DV45 -> -0.044649569 | DW54: =DW49/DW45 -> -0.044649569 | DX54: =DX49/DX45 -> -0.036217554 | DY54: =DY49/DY45 -> -0.044518156 | ... EO54: =EO49/EO45 -> -0.051238739
DJ55: 1Q | DK55: 2Q | DM55: 3Q | DO55: 4Q
A56: Gross margins by brands | DB56: =DB$2 -> Q1 08 | DC56: =DC$2 -> Q2 08 | DD56: =DD$2 -> H1 08 | DE56: =DE$2 -> Q3 08 | DF56: =DF$2 -> 9M 08 | DG56: =DG$2 -> Q4 08 | DH56: =DH$2 -> H2 08 | DI56: =DI$2 -> FY 08 | ... FE56: =FE$2 -> FY14
A57: Wholesale
A58: adidas | DB58: 0.475 | DC58: 0.454 | DD58: =(DB58*DB5+DC58*DC5)/DD5 -> 0.46510073 | DE58: 0.474 | DF58: =(DD58*DD5+DE58*DE5)/DF5 -> 0.46844467 | DG58: 0.433 | DH58: =(DE58*DE5+DG58*DG5)/DH5 -> 0.455771 | DI58: 0.46 | DJ58: 0.456 | DK58: 0.424 | DL58: =(DJ58*DJ5+DK58*DK5)/DL5 -> 0.44123714 | DM58: 0.446 | DN58: =(DL58*DL5+DM58*DM5)/DN5 -> 0.44299547 | DO58: 0.446 | DP58: =(DM58*DM5+DO58*DO5)/DP5 -> 0.446 | DQ58: 0.444 | DR58: 0.45 | DS58: =((DT58*(DT807+DT810))-(DR58*(DR807+DR810)))/(DS807+DS810) -> 0.43996224 | DT58: 0.445 | DU58: =((DV58*(DV807+DV810))-(DT58*(DT807+DT810)))/(DU807+DU810) -> 0.43972821 | DV58: 0.443 | DW58: =((DY58*(DY807+DY810))-(DV58*(DV807+DV810)))/(DW807+DW810) -> #REF! | DX58: =((DY58*(DY807+DY810))-(DT58*(DT807+DT810)))/(DX807+DX810) -> #REF! | DY58: ='Profit and Loss'!Q51 -> 0.437 | DZ58: 0.452 | EA58: =((EB58*(EB807+EB810))-(DZ58*(DZ807+DZ810)))/(EA807+EA810) -> 0.41945317 | EB58: 0.437 | EC58: =((ED58*(ED807+ED810))-(EB58*(EB807+EB810)))/(EC807+EC810) -> 0.42087976 | ED58: 0.431 | EE58: =((EG58*(EG807+EG810))-(ED58*(ED807+ED810)))/(EE807+EE810) -> 0.38339732 | EF58: =((EG58*(EG807+EG810))-(EB58*(EB807+EB810)))/(EF807+EF810) -> 0.4041354 | EG58: 0.42 | EH58: 0.432 | EI58: =((EJ58*(EJ807+EJ810))-(EH58*(EH807+EH810)))/(EI807+EI810) -> 0.40781507 | EJ58: 0.421 | EK58: =((EL58*(EL807+EL810))-(EJ58*(EJ807+EJ810)))/(EK807+EK810) -> 0.43455123 | EL58: 0.426 | EM58: =((EO58*(EO807+EO810))-(EL58*(EL807+EL810)))/(EM807+EM810) -> 0.40228749 | EN58: =((EO58*(EO807+EO810))-(EJ58*(EJ807+EJ810)))/(EN807+EN810) -> 0.421 | EO58: 0.421 | EP58: 0.456 | EQ58: =((ER58*(ER807+ER810))-(EP58*(EP807+EP810)))/(EQ807+EQ810) -> 0.42915141 | ER58: 0.444 | ES58: =((ET58*(ET807+ET810))-(ER58*(ER807+ER810)))/(ES807+ES810) -> 0.45504014 | ET58: 0.448 | EU58: =((EW58*(EW807+EW810))-(ET58*(ET807+ET810)))/(EU807+EU810) -> 0.42027361 | EV58: =((EW58*(EW807+EW810))-(ER58*(ER807+ER810)))/(EV807+EV810) -> 0.44000248 | EW58: ='Profit and Loss'!T51 -> 0.442 | EX58: 0.45 | EY58: =((EZ58*(EZ807+EZ810))-(EX58*(EX807+EX810)))/(EY807+EY810) -> 0.42668674 | EZ58: 0.439 | FA58: =((FB58*(FB807+FB810))-(EZ58*(EZ807+EZ810)))/(FA807+FA810) -> 0.43106317 | FB58: 0.436
A59: change in GM (bps) | DJ59: =(DJ58-DB58)*10000 -> -190 | DK59: =(DK58-DC58)*10000 -> -300 | DL59: =(DL58-DD58)*10000 -> -238.63588 | DM59: =(DM58-DE58)*10000 -> -280 | DN59: =(DN58-DF58)*10000 -> -254.49201 | DO59: =(DO58-DG58)*10000 -> 130 | DP59: =(DP58-DH58)*10000 -> -97.710037 | DQ59: =(DQ58-DI58)*10000 -> -160 | ... FB59: =(FB58-ET58)*10000 -> -120
A60: Reebok | DB60: 0.32 | DC60: 0.33 | DD60: =(DB60*DB5+DC60*DC5)/DD5 -> 0.32471394 | DE60: 0.367 | DF60: =(DD60*DD5+DE60*DE5)/DF5 -> 0.34060312 | DG60: 0.293 | DH60: =(DE60*DE5+DG60*DG5)/DH5 -> 0.33409888 | DI60: 0.33 | DJ60: 0.27 | DK60: 0.254 | DL60: =(DJ60*DJ5+DK60*DK5)/DL5 -> 0.26261857 | DM60: 0.309 | DN60: =(DL60*DL5+DM60*DM5)/DN5 -> 0.27974143 | DO60: 0.292 | DP60: =(DM60*DM5+DO60*DO5)/DP5 -> 0.30139012 | DQ60: 0.284 | DR60: 0.327 | DS60: =((DT60*DT813)-(DR60*DR813))/DS813 -> 0.26628701 | DT60: 0.295 | DU60: =((DV60*DV813)-(DT60*DT813))/DU813 -> 0.33237872 | DV60: 0.311 | DW60: =((DY60*DY813)-(DV60*DV813))/DW813 -> #REF! | DX60: =((DY60*DY813)-(DT60*DT813))/DX813 -> #REF! | DY60: ='Profit and Loss'!Q53 -> 0.307 | DZ60: 0.325 | EA60: =((EB60*EB813)-(DZ60*DZ813))/EA813 -> 0.26658442 | EB60: 0.299 | EC60: =((ED60*ED813)-(EB60*EB813))/EC813 -> 0.31452294 | ED60: 0.305 | EE60: =((EG60*EG813)-(ED60*ED813))/EE813 -> 0.24562069 | EF60: =((EG60*EG813)-(EB60*EB813))/EF813 -> 0.28393878 | EG60: 0.291 | EH60: 0.325 | EI60: =((EJ60*EJ813)-(EH60*EH813))/EI813 -> 0.13388421 | EJ60: 0.257 | EK60: =((EL60*EL813)-(EJ60*EJ813))/EK813 -> 0.23125436 | EL60: 0.248 | EM60: =((EO60*EO813)-(EL60*EL813))/EM813 -> 0.30190972 | EN60: =((EO60*EO813)-(EJ60*EJ813))/EN813 -> 0.26664348 | EO60: 0.262 | EP60: 0.336 | EQ60: =((ER60*ER813)-(EP60*EP813))/EQ813 -> 0.26643192 | ER60: 0.305 | ES60: =((ET60*ET813)-(ER60*ER813))/ES813 -> 0.3182699 | ET60: 0.31 | EU60: =((EW60*EW813)-(ET60*ET813))/EU813 -> 0.31 | EV60: =((EW60*EW813)-(ER60*ER813))/EV813 -> 0.31417832 | EW60: ='Profit and Loss'!T53 -> 0.31 | EX60: 0.337 | EY60: =((EZ60*EZ813)-(EX60*EX813))/EY813 -> 0.27923558 | EZ60: 0.31 | FA60: =((FB60*FB813)-(EZ60*EZ813))/FA813 -> 0.30745486 | FB60: 0.309
A61: change in GM (bps) | DJ61: =(DJ60-DB60)*10000 -> -500 | DK61: =(DK60-DC60)*10000 -> -760 | DL61: =(DL60-DD60)*10000 -> -620.95372 | DM61: =(DM60-DE60)*10000 -> -580 | DN61: =(DN60-DF60)*10000 -> -608.61686 | DO61: =(DO60-DG60)*10000 -> -10 | DP61: =(DP60-DH60)*10000 -> -327.0876 | DQ61: =(DQ60-DI60)*10000 -> -460 | ... FB61: =(FB60-ET60)*10000 -> -10
A62: Retail
A63: adidas | DB63: 0.61 | DC63: 0.65 | DD63: =(DB63*DB10+DC63*DC10)/DD10 -> 0.6316092 | DE63: 0.643 | DF63: =(DD63*DD10+DE63*DE10)/DF10 -> 0.63599922 | DG63: 0.635 | DH63: =(DE63*DE10+DG63*DG10)/DH10 -> 0.63911309 | DI63: 0.636 | DJ63: 0.573 | DK63: 0.628 | DL63: =(DJ63*DJ10+DK63*DK10)/DL10 -> 0.6031693 | DM63: 0.605 | DN63: =(DL63*DL10+DM63*DM10)/DN10 -> 0.60384965 | DO63: 0.622 | DP63: =(DM63*DM10+DO63*DO10)/DP10 -> 0.61327522 | DQ63: 0.609 | DR63: 0.6 | DS63: =((DT63*(DT822+DT825))-(DR63*(DR822+DR825)))/(DS822+DS825) -> 0.66705433 | DT63: 0.638 | DU63: =((DV63*(DV822+DV825))-(DT63*(DT822+DT825)))/(DU822+DU825) -> 0.63019891 | DV63: 0.635 | DW63: =((DY63*(DY822+DY825))-(DV63*(DV822+DV825)))/(DW822+DW825) -> #REF! | DX63: =((DY63*(DY822+DY825))-(DT63*(DT822+DT825)))/(DX822+DX825) -> #REF! | DY63: ='Profit and Loss'!Q57 -> 0.632 | DZ63: 0.622 | EA63: =((EB63*(EB822+EB825))-(DZ63*(DZ822+DZ825)))/(EA822+EA825) -> 0.66853025 | EB63: 0.647 | EC63: =((ED63*(ED822+ED825))-(EB63*(EB822+EB825)))/(EC822+EC825) -> 0.63100637 | ED63: 0.641 | EE63: =((EG63*(EG822+EG825))-(ED63*(ED822+ED825)))/(EE822+EE825) -> 0.62320183 | EF63: =((EG63*(EG822+EG825))-(EB63*(EB822+EB825)))/(EF822+EF825) -> 0.62702496 | EG63: 0.636 | EH63: 0.628 | EI63: =((EJ63*(EJ822+EJ825))-(EH63*(EH822+EH825)))/(EI822+EI825) -> 0.64079037 | EJ63: 0.635 | EK63: =((EL63*(EL822+EL825))-(EJ63*(EJ822+EJ825)))/(EK822+EK825) -> 0.60038918 | EL63: 0.622 | EM63: =((EO63*(EO822+EO825))-(EL63*(EL822+EL825)))/(EM822+EM825) -> 0.61820811 | EN63: =((EO63*(EO822+EO825))-(EJ63*(EJ822+EJ825)))/(EN822+EN825) -> 0.60908707 | EO63: 0.621 | EP63: 0.622 | EQ63: =((ER63*(ER822+ER825))-(EP63*(EP822+EP825)))/(EQ822+EQ825) -> 0.66249584 | ER63: 0.644 | ES63: =((ET63*(ET822+ET825))-(ER63*(ER822+ER825)))/(ES822+ES825) -> 0.62228129 | ET63: 0.636 | EU63: =((EW63*(EW822+EW825))-(ET63*(ET822+ET825)))/(EU822+EU825) -> 0.61758163 | EV63: =((EW63*(EW822+EW825))-(ER63*(ER822+ER825)))/(EV822+EV825) -> 0.6199179 | EW63: ='Profit and Loss'!T57 -> 0.631 | EX63: 0.609 | EY63: =((EZ63*(EZ822+EZ825))-(EX63*(EX822+EX825)))/(EY822+EY825) -> 0.6163202 | EZ63: 0.613 | FA63: =((FB63*(FB822+FB825))-(EZ63*(EZ822+EZ825)))/(FA822+FA825) -> 0.59162767 | FB63: 0.605
A64: change in GM (bps) | DJ64: =(DJ63-DB63)*10000 -> -370 | DK64: =(DK63-DC63)*10000 -> -220 | DL64: =(DL63-DD63)*10000 -> -284.39895 | DM64: =(DM63-DE63)*10000 -> -380 | DN64: =(DN63-DF63)*10000 -> -321.4957 | DO64: =(DO63-DG63)*10000 -> -130 | DP64: =(DP63-DH63)*10000 -> -258.37869 | DQ64: =(DQ63-DI63)*10000 -> -270 | ... FB64: =(FB63-ET63)*10000 -> -310
A65: Reebok | DB65: 0.477 | DC65: 0.532 | DD65: =(DB65*DB10+DC65*DC10)/DD10 -> 0.50671264 | DE65: 0.533 | DF65: =(DD65*DD10+DE65*DE10)/DF10 -> 0.5168438 | DG65: 0.523 | DH65: =(DE65*DE10+DG65*DG10)/DH10 -> 0.52814136 | DI65: 0.519 | DJ65: 0.407 | DK65: 0.51 | DL65: =(DJ65*DJ10+DK65*DK10)/DL10 -> 0.46349887 | DM65: 0.446 | DN65: =(DL65*DL10+DM65*DM10)/DN10 -> 0.45699574 | DO65: 0.543 | DP65: =(DM65*DM10+DO65*DO10)/DP10 -> 0.49321743 | DQ65: 0.481 | DR65: 0.495 | DS65: =((DT65*DT828)-(DR65*DR828))/DS828 -> 0.58122115 | DT65: 0.544 | DU65: =((DV65*DV828)-(DT65*DT828))/DU828 -> 0.50772174 | DV65: 0.53 | DW65: =((DY65*DY828)-(DV65*DV828))/DW828 -> #REF! | DX65: =((DY65*DY828)-(DT65*DT828))/DX828 -> #REF! | DY65: ='Profit and Loss'!Q59 -> 0.548 | DZ65: 0.565 | EA65: =((EB65*EB828)-(DZ65*DZ828))/EA828 -> 0.60612712 | EB65: 0.588 | EC65: =((ED65*ED828)-(EB65*EB828))/EC828 -> 0.58535156 | ED65: 0.587 | EE65: =((EG65*EG828)-(ED65*ED828))/EE828 -> 0.55339516 | EF65: =((EG65*EG828)-(EB65*EB828))/EF828 -> 0.56962698 | EG65: 0.578 | EH65: 0.546 | EI65: =((EJ65*EJ828)-(EH65*EH828))/EI828 -> 0.56868276 | EJ65: 0.559 | EK65: =((EL65*EL828)-(EJ65*EJ828))/EK828 -> 0.53865854 | EL65: 0.551 | EM65: =((EO65*EO828)-(EL65*EL828))/EM828 -> 0.551 | EN65: =((EO65*EO828)-(EJ65*EJ828))/EN828 -> 0.54436393 | EO65: 0.551 | EP65: 0.528 | EQ65: =((ER65*ER828)-(EP65*EP828))/EQ828 -> 0.60342254 | ER65: 0.57 | ES65: =((ET65*ET828)-(ER65*ER828))/ES828 -> 0.5862 | ET65: 0.576 | EU65: =((EW65*EW828)-(ET65*ET828))/EU828 -> 0.568375 | EV65: =((EW65*EW828)-(ER65*ER828))/EV828 -> 0.57746939 | EW65: ='Profit and Loss'!T59 -> 0.574 | EX65: 0.545 | EY65: =((EZ65*EZ828)-(EX65*EX828))/EY828 -> 0.54134247 | EZ65: 0.543 | FA65: =((FB65*FB828)-(EZ65*EZ828))/FA828 -> 0.51610127 | FB65: 0.533
A66: change in GM (bps) | DJ66: =(DJ65-DB65)*10000 -> -700 | DK66: =(DK65-DC65)*10000 -> -220 | DL66: =(DL65-DD65)*10000 -> -432.13772 | DM66: =(DM65-DE65)*10000 -> -870 | DN66: =(DN65-DF65)*10000 -> -598.48054 | DO66: =(DO65-DG65)*10000 -> 200 | DP66: =(DP65-DH65)*10000 -> -349.23927 | DQ66: =(DQ65-DI65)*10000 -> -380 | ... FB66: =(FB65-ET65)*10000 -> -430
A67: Brand average
A68: adidas | DS68: 0.461 | DT68: 0.473 | DU68: 0.446 | DV68: 0.462 | EA68: 0.472 | EB68: 0.475 | EC68: 0.46 | ED68: 0.469 | EH68: 0.463 | EI68: 0.459 | EJ68: 0.461 | EK68: 0.467 | EL68: 0.463 | EP68: 0.481 | EQ68: 0.485 | ER68: 0.483
A69: change in GM (bps) | EA69: =(EA68-DS68)*10000 -> 110 | EB69: =(EB68-DT68)*10000 -> 20 | EC69: =(EC68-DU68)*10000 -> 140 | ED69: =(ED68-DV68)*10000 -> 70 | EH69: =(EH68-DZ68)*10000 -> 4630 | EI69: =(EI68-EA68)*10000 -> -130 | EJ69: =(EJ68-EB68)*10000 -> -140 | EK69: =(EK68-EC68)*10000 -> 70 | EL69: =(EL68-ED68)*10000 -> -60 | EP69: =(EP68-EH68)*10000 -> 180 | EQ69: =(EQ68-EI68)*10000 -> 260 | ER69: =(ER68-EJ68)*10000 -> 220
A70: Reebok | DS70: 0.342 | DT70: 0.351 | DU70: 0.368 | DV70: 0.358 | EA70: 0.362 | EB70: 0.367 | EC70: 0.375 | ED70: 0.37 | EH70: 0.376 | EI70: 0.321 | EJ70: 0.354 | EK70: 0.345 | EL70: 0.351 | EP70: 0.391 | EQ70: 0.397 | ER70: 0.394
A71: change in GM (bps) | EA71: =(EA70-DS70)*10000 -> 200 | EB71: =(EB70-DT70)*10000 -> 160 | EC71: =(EC70-DU70)*10000 -> 70 | ED71: =(ED70-DV70)*10000 -> 120 | EH71: =(EH70-DZ70)*10000 -> 3760 | EI71: =(EI70-EA70)*10000 -> -410 | EJ71: =(EJ70-EB70)*10000 -> -130 | EK71: =(EK70-EC70)*10000 -> -300 | EL71: =(EL70-ED70)*10000 -> -190 | EP71: =(EP70-EH70)*10000 -> 150 | EQ71: =(EQ70-EI70)*10000 -> 760 | ER71: =(ER70-EJ70)*10000 -> 400
A73: Sales by brand | DB73: =DB$2 -> Q1 08 | DC73: =DC$2 -> Q2 08 | DD73: =DD$2 -> H1 08 | DE73: =DE$2 -> Q3 08 | DF73: =DF$2 -> 9M 08 | DG73: =DG$2 -> Q4 08 | DH73: =DH$2 -> H2 08 | DI73: =DI$2 -> FY 08 | ... FM73: =FM$2 -> FY15 | GT73: 1Q20 | GU73: 2Q20 | GV73: 1H20 | GW73: 3Q20 | GX73: 9M20 | GY73: 4Q20 | GZ73: 2H20 | HA73: FY20 | HB73: 1Q21 | HC73: 2Q21 | HD73: 1H21 | HE73: 3Q21 | HF73: 9M21 | HG73: 4Q21 | HH73: 2H21 | HI73: FY21 | HJ73: 1Q22 | HK73: 2Q22 | HL73: 1H22 | HM73: 3Q22 | HN73: 9M22E | HO73: 4Q22 | HP73: 2H22 | HQ73: FY22 | HR73: =HR4 -> 1Q23 | HS73: 2Q23 | HT73: 1H23 | HU73: 3Q23 | HV73: 9M23E | HW73: 4Q23 | HX73: 2H23 | HY73: FY23 | HZ73: 1Q24 | IA73: 2Q24 | IB73: 1H24 | IC73: 3Q24 | ID73: 9M24E | IE73: 4Q24 | IF73: 2H24E | IG73: FY24 | IH73: 1Q25 | II73: 2Q25 | IJ73: 1H25E | IK73: 3Q25E | IL73: 9M25E | IM73: 4Q25E | IN73: 2H25E | IO73: FY25E | IP73: 1Q25 | IQ73: =IQ2 -> 2Q26
A74: adidas Sport Performance | DB74: =DB807+DB822 -> 1569 | DC74: =DC807+DC822 -> 1487 | DD74: =DB74+DC74 -> 3056 | DE74: =DE807+DE822 -> 1754 | DF74: =DD74+DE74 -> 4810 | DG74: =DG807+DG822 -> 1437 | DH74: =DE74+DG74 -> 3191 | DI74: ='Profit and Loss'!O71 -> 6246 | DJ74: =DJ807+DJ822 -> 1494 | DK74: =DK807+DK822 -> 1354 | DL74: =DJ74+DK74 -> 2848 | DM74: =DM807+DM822 -> 1634 | DN74: =DL74+DM74 -> 4482 | DO74: =DO807+DO822 -> 1357 | DP74: =DO74+DM74 -> 2991 | DQ74: ='Profit and Loss'!P71 -> 5838 | DR74: =DR807+DR822 -> 1461 | DS74: =DS807+DS822 -> 1622 | DT74: =DT807+DT822 -> 3083 | DU74: =DU807+DU822 -> 1885 | DV74: =DV807+DV822 -> 4968 | DW74: =DW807+DW822 -> #REF! | DX74: =DX807+DX822 -> #REF! | DY74: =DY807+DY822 -> #REF! | DZ74: =DZ807+DZ822+DZ816 -> 1743 | EA74: =EA807+EA822+EA816 -> 1628 | EB74: =EB807+EB822+EB816 -> 3371 | EC74: =EC807+EC822+EC816 -> 2056 | ED74: =ED807+ED822+ED816 -> 5427 | EE74: =EE807+EE822+EE816 -> 1762 | EF74: =EF807+EF822+EF816 -> 3818 | EG74: =EG807+EG822+EG816+EG831 -> 7191 | EH74: =EH807+EH822+EH816 -> 1995 | EI74: =EI807+EI822+EI816 -> 1973 | EJ74: =EJ807+EJ822+EJ816 -> 3968 | EK74: =EK807+EK822+EK816 -> 2302 | EL74: =EL807+EL822+EL816 -> 6270 | EM74: =EM807+EM822+EM816 -> 1809 | EN74: =EN807+EN822+EN816 -> 4111 | EO74: =EO807+EO822+EO816 -> 8079 | ... FB74: =FB807+FB822+FB816 -> 6249
A75: Growth | DJ75: =DJ74/DB74-1 -> -0.047801147 | DK75: =DK74/DC74-1 -> -0.089441829 | DL75: =DL74/DD74-1 -> -0.068062827 | DM75: =DM74/DE74-1 -> -0.068415051 | DN75: =DN74/DF74-1 -> -0.068191268 | DO75: =DO74/DG74-1 -> -0.055671538 | DP75: =DP74/DH74-1 -> -0.062676277 | DQ75: =DQ74/DI74-1 -> -0.065321806 | ... FB75: =FB74/ET74-1 -> 0.051489147
A76: adidas Sport Style | DB76: =DB810+DB825 -> 371 | DC76: =DC810+DC825 -> 317 | DD76: =DB76+DC76 -> 688 | DE76: =DE810+DE825 -> 436 | DF76: =DD76+DE76 -> 1124 | DG76: =DG810+DG825 -> 373 | DH76: =DE76+DG76 -> 809 | DI76: ='Profit and Loss'!O74 -> 1497 | DJ76: =DJ810+DJ825 -> 421 | DK76: =DK810+DK825 -> 376 | DL76: =DJ76+DK76 -> 797 | DM76: =DM810+DM825 -> 470 | DN76: =DL76+DM76 -> 1267 | DO76: =DO810+DO825 -> 377 | DP76: =DO76+DM76 -> 847 | DQ76: ='Profit and Loss'!P74 -> 1645 | DR76: =DR810+DR825 -> 520 | DS76: =DS810+DS825 -> 464 | DT76: =DT810+DT825 -> 984 | DU76: =DU810+DU825 -> 613 | DV76: =DV810+DV825 -> 1597 | DW76: =DW810+DW825 -> #REF! | DX76: =DX810+DX825 -> #REF! | DY76: =DY810+DY825 -> #REF! | ... FB76: =FB810+FB825 -> 2552
A77: Growth | DJ77: =DJ76/DB76-1 -> 0.13477089 | DK77: =DK76/DC76-1 -> 0.18611987 | DL77: =DL76/DD76-1 -> 0.15843023 | DM77: =DM76/DE76-1 -> 0.077981651 | DN77: =DN76/DF76-1 -> 0.1272242 | DO77: =DO76/DG76-1 -> 0.010723861 | DP77: =DP76/DH76-1 -> 0.04697157 | DQ77: =DQ76/DI76-1 -> 0.098864395 | ... FB77: =FB76/ET76-1 -> 0.045045045
A78: Reebok | DB78: =DB813+DB828 -> 375 | DC78: =DC813+DC828 -> 365 | DD78: =DB78+DC78 -> 740 | DE78: =DE813+DE828 -> 532 | DF78: =DD78+DE78 -> 1272 | DG78: =DG813+DG828 -> 445 | DH78: =DE78+DG78 -> 977 | DI78: ='Profit and Loss'!O77 -> 1717 | DJ78: =DJ813+DJ828 -> 373 | DK78: =DK813+DK828 -> 350 | DL78: =DJ78+DK78 -> 723 | DM78: =DM813+DM828 -> 469 | DN78: =DL78+DM78 -> 1192 | DO78: =DO813+DO828 -> 411 | DP78: =DO78+DM78 -> 880 | DQ78: ='Profit and Loss'!P77 -> 1604 | DR78: =DR813+DR828 -> 376 | DS78: =DS813+DS828 -> 435 | DT78: =DT813+DT828 -> 811 | DU78: =DU813+DU828 -> 585 | DV78: =DV813+DV828 -> 1396 | DW78: =DW813+DW828 -> #REF! | DX78: =DX813+DX828 -> #REF! | DY78: =DY813+DY828 -> #REF! | DZ78: =DZ813+DZ828 -> 477 | EA78: 427 | EB78: =EB813+EB828 -> 903 | EC78: =EC813+EC828 -> 564 | ED78: =ED813+ED828 -> 1467 | EE78: =EE813+EE828 -> 472 | EF78: =EF813+EF828 -> 1036 | EG78: =EG813+EG828 -> 1939 | EH78: =EH813+EH828 -> 452 | EI78: =EI813+EI828 -> 335 | ... FB78: =FB813+FB828 -> 1158
A79: Growth | DJ79: =DJ78/DB78-1 -> -0.0053333333 | DK79: =DK78/DC78-1 -> -0.04109589 | DL79: =DL78/DD78-1 -> -0.022972973 | DM79: =DM78/DE78-1 -> -0.11842105 | DN79: =DN78/DF78-1 -> -0.062893082 | DO79: =DO78/DG78-1 -> -0.076404494 | DP79: =DP78/DH78-1 -> -0.099283521 | DQ79: =DQ78/DI78-1 -> -0.065812464 | ... FB79: =FB78/ET78-1 -> -0.011945392
A80: Other brands | DB80: =DB851 -> 285 | DC80: =DC851 -> 336 | DD80: =DB80+DC80 -> 621 | DE80: =DE851 -> 347 | DF80: =DD80+DE80 -> 968 | DG80: =DG851 -> 317 | DH80: =DE80+DG80 -> 664 | DI80: ='Profit and Loss'!O79 -> 1285 | DJ80: =DJ851 -> 293 | DK80: =DK851 -> 360 | DL80: =DJ80+DK80 -> 653 | DM80: =DM851 -> 321 | DN80: =DL80+DM80 -> 974 | DO80: =DO851 -> 308 | DP80: =DO80+DM80 -> 629 | DQ80: ='Profit and Loss'!P79 -> 1283 | DR80: =DR851 -> 316 | DS80: =DS851 -> 387 | DT80: =DR80+DS80 -> 703 | DU80: =DU851 -> 383 | DV80: =DT80+DU80 -> 1086 | DW80: =DW851 -> #REF! | DX80: =DW80+DU80 -> #REF! | DY80: ='Profit and Loss'!Q79 -> 1420 | DZ80: =DZ851 -> 376 | EA80: =EA851 -> 410 | EB80: =EB851 -> 786 | EC80: =EC851 -> 411 | ED80: =ED851 -> 1197 | EE80: =EE851 -> 382 | EF80: =EF851 -> 794 | EG80: =EG851 -> 1580 | ... FB80: =FB851 -> 1158
A81: Growth | DJ81: =DJ80/DB80-1 -> 0.028070175 | DK81: =DK80/DC80-1 -> 0.071428571 | DL81: =DL80/DD80-1 -> 0.051529791 | DM81: =DM80/DE80-1 -> -0.074927954 | DN81: =DN80/DF80-1 -> 0.0061983471 | DO81: =DO80/DG80-1 -> -0.028391167 | DP81: =DP80/DH80-1 -> -0.052710843 | DQ81: =DQ80/DI80-1 -> -0.0015564202 | ... FB81: =FB80/ET80-1 -> -0.20302822
A82: TaylorMade-adidas Golf | DB82: =DB839 -> 191 | DC82: =DC839 -> 226 | DD82: =DB82+DC82 -> 417 | DE82: =DE839 -> 197 | DF82: =DD82+DE82 -> 614 | DG82: =DG839 -> 198 | DH82: =DE82+DG82 -> 395 | DI82: ='Profit and Loss'!O81 -> 812 | DJ82: =DJ839 -> 194 | DK82: =DK839 -> 255 | DL82: =DJ82+DK82 -> 449 | DM82: =DM839 -> 184 | DN82: =DL82+DM82 -> 633 | DO82: =DO839 -> 198 | DP82: =DO82+DM82 -> 382 | DQ82: ='Profit and Loss'!P81 -> 831 | DR82: =DR839 -> 223 | DS82: =DS839 -> 269 | DT82: =DT839 -> 492 | DU82: =DU839 -> 221 | DV82: =DV839 -> 713 | DW82: =DW839 -> #REF! | DX82: =DX839 -> #REF! | DY82: =DY839 -> #REF! | DZ82: =DZ839 -> 281 | EA82: 288 | EB82: =EB839 -> 570 | EC82: =EC839 -> 244 | ED82: =ED839 -> 814 | EE82: =EE839 -> 230 | EF82: =EF839 -> 474 | EG82: =EG839 -> 1044 | EH82: =EH839 -> 387 | EI82: =EI839 -> 401 | ... FB82: =FB839 -> 673
A83: Growth | DJ83: =DJ82/DB82-1 -> 0.015706806 | DK83: =DK82/DC82-1 -> 0.12831858 | DL83: =DL82/DD82-1 -> 0.076738609 | DM83: =DM82/DE82-1 -> -0.065989848 | DN83: =DN82/DF82-1 -> 0.030944625 | DO83: =DO82/DG82-1 -> 0 | DP83: =DP82/DH82-1 -> -0.032911392 | DQ83: =DQ82/DI82-1 -> 0.023399015 | ... FB83: =FB82/ET82-1 -> -0.31396534
A84: Rockport | DB84: =DB842 -> 57 | DC84: =DC842 -> 56 | DD84: =DB84+DC84 -> 113 | DE84: =DE842 -> 68 | DF84: =DD84+DE84 -> 181 | DG84: =DG842 -> 62 | DH84: =DE84+DG84 -> 130 | DI84: ='Profit and Loss'!O83 -> 243 | DJ84: =DJ842 -> 60 | DK84: =DK842 -> 55 | DL84: =DJ84+DK84 -> 115 | DM84: =DM842 -> 63 | DN84: =DL84+DM84 -> 178 | DO84: =DO842 -> 53 | DP84: =DO84+DM84 -> 116 | DQ84: ='Profit and Loss'!P83 -> 232 | DR84: =DR842 -> 56 | DS84: =DS842 -> 58 | DT84: =DT842 -> 114 | DU84: =DU842 -> 73 | DV84: =DV842 -> 187 | DW84: =DW842 -> #REF! | DX84: =DX842 -> #REF! | DY84: =DY842 -> #REF! | DZ84: =DZ842 -> 54 | EA84: 59 | EB84: =EB842 -> 114 | EC84: =EC842 -> 72 | ED84: =ED842 -> 186 | EE84: =EE842 -> 75 | EF84: =EF842 -> 147 | EG84: =EG842 -> 261 | EH84: =EH842 -> 60 | EI84: =EI842 -> 67 | ... FB84: =FB842 -> 192
A85: Growth | DJ85: =DJ84/DB84-1 -> 0.052631579 | DK85: =DK84/DC84-1 -> -0.017857143 | DL85: =DL84/DD84-1 -> 0.017699115 | DM85: =DM84/DE84-1 -> -0.073529412 | DN85: =DN84/DF84-1 -> -0.016574586 | DO85: =DO84/DG84-1 -> -0.14516129 | DP85: =DP84/DH84-1 -> -0.10769231 | DQ85: =DQ84/DI84-1 -> -0.04526749 | ... FB85: =FB84/ET84-1 -> -0.044776119
A86: Reebok-CCM Hockey | DB86: =DB845 -> 22 | DC86: =DC845 -> 49 | DD86: =DB86+DC86 -> 71 | DE86: =DE845 -> 64 | DF86: =DD86+DE86 -> 135 | DG86: =DG845 -> 53 | DH86: =DE86+DG86 -> 117 | DI86: ='Profit and Loss'!O85 -> 188 | DJ86: =DJ845 -> 24 | DK86: =DK845 -> 44 | DL86: =DJ86+DK86 -> 68 | DM86: =DM845 -> 59 | DN86: =DL86+DM86 -> 127 | DO86: =DO845 -> 50 | DP86: =DO86+DM86 -> 109 | DQ86: ='Profit and Loss'!P85 -> 177 | DR86: =DR845 -> 21 | DS86: =DS845 -> 52 | DT86: =DT845 -> 73 | DU86: =DU845 -> 65 | DV86: =DV845 -> 138 | DW86: =DW845 -> #REF! | DX86: =DX845 -> #REF! | DY86: =DY845 -> #REF! | DZ86: =DZ845 -> 22 | EA86: 56 | EB86: =EB845 -> 77 | EC86: =EC845 -> 71 | ED86: =ED845 -> 148 | EE86: =EE845 -> 62 | EF86: =EF845 -> 133 | EG86: =EG845 -> 210 | EH86: =EH845 -> 37 | EI86: =EI845 -> 65 | ... FB86: =FB845 -> 188
A87: Growth | DJ87: =DJ86/DB86-1 -> 0.090909091 | DK87: =DK86/DC86-1 -> -0.10204082 | DL87: =DL86/DD86-1 -> -0.042253521 | DM87: =DM86/DE86-1 -> -0.078125 | DN87: =DN86/DF86-1 -> -0.059259259 | DO87: =DO86/DG86-1 -> -0.056603774 | DP87: =DP86/DH86-1 -> -0.068376068 | DQ87: =DQ86/DI86-1 -> -0.058510638 | ... FB87: =FB86/ET86-1 -> 0.038674033
A88: Other centrally managed brands | DB88: =DB848 -> 15 | DC88: =DC848 -> 5 | DD88: =DB88+DC88 -> 20 | DE88: =DE848 -> 18 | DF88: =DD88+DE88 -> 38 | DG88: =DG848 -> 4 | DH88: =DE88+DG88 -> 22 | DI88: ='Profit and Loss'!O87 -> 42 | DJ88: =DJ848 -> 15 | DK88: =DK848 -> 6 | DL88: =DJ88+DK88 -> 21 | DM88: =DM848 -> 15 | DN88: =DL88+DM88 -> 36 | DO88: =DO848 -> 7 | DP88: =DO88+DM88 -> 22 | DQ88: ='Profit and Loss'!P87 -> 43 | DR88: =DR848 -> 16 | DS88: =DS848 -> 8 | DT88: =DT848 -> 24 | DU88: =DU848 -> 24 | DV88: =DV848 -> 48 | DW88: =DW848 -> #REF! | DX88: =DX848 -> #REF! | DY88: =DY848 -> #REF! | ... FB88: =FB848 -> 105
A89: Growth | DJ89: =DJ88/DB88-1 -> 0 | DK89: =DK88/DC88-1 -> 0.2 | DL89: =DL88/DD88-1 -> 0.05 | DM89: =DM88/DE88-1 -> -0.16666667 | DN89: =DN88/DF88-1 -> -0.052631579 | DO89: =DO88/DG88-1 -> 0.75 | DP89: =DP88/DH88-1 -> 0 | DQ89: =DQ88/DI88-1 -> 0.023809524 | ... FB89: =FB88/ET88-1 -> 0.16666667
A90: Total sales | DB90: =SUM(DB88,DB86,DB84,DB82,DB78,DB76,DB74) -> 2600 | DC90: =SUM(DC88,DC86,DC84,DC82,DC78,DC76,DC74) -> 2505 | DD90: =SUM(DD88,DD86,DD84,DD82,DD78,DD76,DD74) -> 5105 | DE90: =SUM(DE88,DE86,DE84,DE82,DE78,DE76,DE74) -> 3069 | DF90: =SUM(DF88,DF86,DF84,DF82,DF78,DF76,DF74) -> 8174 | DG90: =SUM(DG88,DG86,DG84,DG82,DG78,DG76,DG74) -> 2572 | DH90: =SUM(DH88,DH86,DH84,DH82,DH78,DH76,DH74) -> 5641 | DI90: =SUM(DI88,DI86,DI84,DI82,DI78,DI76,DI74) -> 10745 | ... DQ90: =SUM(DQ88,DQ86,DQ84,DQ82,DQ78,DQ76,DQ74) -> 10370 | DR90: =SUM(DR74,DR76,DR78,DR80) -> 2673 | DS90: =SUM(DS74,DS76,DS78,DS80) -> 2908 | DT90: =SUM(DT74,DT76,DT78,DT80) -> 5581 | DU90: =SUM(DU74,DU76,DU78,DU80) -> 3466 | DV90: =SUM(DV74,DV76,DV78,DV80) -> 9047 | DW90: =SUM(DW74,DW76,DW78,DW80) -> #REF! | DX90: =SUM(DX74,DX76,DX78,DX80) -> #REF! | DY90: =SUM(DY74,DY76,DY78,DY80) -> #REF! | ... FB90: =SUM(FB74,FB76,FB78,FB80) -> 11117
A91: Growth | DJ91: =DJ90/DB90-1 -> -0.0073076923 | DK91: =DK90/DC90-1 -> -0.025948104 | DL91: =DL90/DD90-1 -> -0.016454456 | DM91: =DM90/DE90-1 -> -0.057021831 | DN91: =DN90/DF90-1 -> -0.031685833 | DO91: =DO90/DG90-1 -> -0.046267496 | DP91: =DP90/DH90-1 -> -0.052118419 | DQ91: =DQ90/DI90-1 -> -0.034899953 | ... FB91: =FB90/ET90-1 -> 0.0097184378
A94: Sales by region | DR94: =DR2 -> Q1 10 | DS94: =DS2 -> Q2 10 | DT94: =DT2 -> H1 10 | DU94: =DU2 -> Q3 10 | DV94: =DV2 -> 9M 10 | DW94: =DW2 -> Q4 10 | DX94: =DX2 -> H2 10 | DY94: =DY2 -> FY 10 | ... EO94: =EO2 -> FY 12 | EP94: =EP$2 -> 1Q13 | EQ94: =EQ$2 -> 2Q13 | ER94: =ER$2 -> 1H13 | ES94: =ES$2 -> 3Q13 | ET94: =ET$2 -> 9M13 | EU94: =EU$2 -> 4Q13 | EV94: =EV$2 -> 2H13 | EW94: =EW$2 -> FY13 | ... FM94: =FM$2 -> FY15 | GT94: 1Q20 | GU94: 2Q20 | GV94: 1H20 | GW94: 3Q20 | GX94: 9M20 | GY94: 4Q20 | GZ94: 2H20 | HA94: FY20 | HB94: 1Q21 | HC94: 2Q21 | HD94: 1H21 | HE94: 3Q21 | HF94: 9M21 | HG94: 4Q21 | HH94: 2H21 | HI94: FY21 | HJ94: 1Q22 | HK94: 2Q22 | HL94: 1H22 | HM94: 3Q22 | HN94: 9M22E | HO94: 4Q22 | HP94: 2H22 | HQ94: FY22 | HR94: =HR73 -> 1Q23 | HS94: 2Q23 | HT94: 1H23 | HU94: 3Q23 | HV94: 9M23E | HW94: 4Q23 | HX94: 2H23 | HY94: FY23 | HZ94: 1Q24 | IA94: 2Q24 | IB94: 1H24 | IC94: 3Q24 | ID94: 9M24E | IE94: 4Q24 | IF94: 2H24E | IG94: FY24 | IH94: 1Q25 | II94: 2Q25 | IJ94: 1H25E | IK94: 3Q25 | IL94: 9M25E | IM94: 4Q25E | IN94: 2H25E | IO94: FY25E | IP94: 1Q25 | IQ94: =IQ2 -> 2Q26
A95: Western Europe | DB95: 980 | DC95: 846 | DD95: =DB95+DC95 -> 1826 | DE95: 1079 | DF95: =DE95+DD95 -> 2905 | DG95: 623 | DH95: =DE95+DG95 -> 1702 | DI95: =SUM(DB95,DC95,DE95,DG95) -> 3528 | DJ95: 899 | DK95: 719 | DL95: =DJ95+DK95 -> 1618 | DM95: 1008 | DN95: =DM95+DL95 -> 2626 | DO95: 636 | DP95: =DM95+DO95 -> 1644 | DQ95: =SUM(DJ95,DK95,DM95,DO95) -> 3262 | DR95: 945 | DS95: 827 | DT95: =DR95+DS95 -> 1772 | DU95: 1102 | DV95: =DU95+DT95 -> 2874 | DW95: =DY95-DV95 -> 669 | DX95: =DU95+DW95 -> 1771 | DY95: 3543 | DZ95: 1094 | EA95: 867 | EB95: =DZ95+EA95 -> 1961 | EC95: =ED95-EB95 -> 1211 | ED95: 3172 | EE95: =+EF95-EC95 -> 750 | EF95: =+EG95-EB95 -> 1961 | EG95: 3922 | EH95: 1174 | EI95: 924 | EJ95: =EH95+EI95 -> 2098 | EK95: =EL95-EJ95 -> 1244 | EL95: 3342 | EM95: 733 | EN95: =EK95+EM95 -> 1977 | EO95: =EH95+EI95+EK95+EM95 -> 4075 | EP95: 1096 | EQ95: =ER95-EP95 -> 811 | ER95: 1907 | ES95: 1145 | ET95: =ER95+ES95 -> 3052 | EU95: 747 | EV95: =ES95+EU95 -> 1892 | EW95: =EP95+EQ95+ES95+EU95 -> 3799 | EX95: =1098-(50%*EX842) -> 1071.5 | EY95: =919-(50%*EX842) -> 892.5 | EZ95: =EX95+EY95 -> 1964 | FA95: =1265-(50%*EX842) -> 1238.5 | FB95: =EZ95+FA95 -> 3202.5 | FC95: =EU95*(1+FC96) -> 776.75958 | FD95: =FA95+FC95 -> 2015.2596 | FE95: =EX95+EY95+FA95+FC95 -> 3979.2596 | FF95: =EX95*(1+FF96) -> 1189.5324 | FG95: =EY95*(1+FG96) -> 924.98676 | FH95: =FF95+FG95 -> 2114.5192 | FI95: =FA95*(1+FI96) -> 1312.2627 | FJ95: =FH95+FI95 -> 3426.7819 | FK95: =FM95-FJ95 -> 1198.2181 | FL95: =FI95+FK95 -> 2510.4808 | FM95: 4625
A96: Growth | DJ96: =DJ95/DB95-1 -> -0.082653061 | DK96: =DK95/DC95-1 -> -0.1501182 | DL96: =DL95/DD95-1 -> -0.11391019 | DM96: =DM95/DE95-1 -> -0.065801668 | DN96: =DN95/DF95-1 -> -0.096041308 | DO96: =DO95/DG95-1 -> 0.020866774 | DP96: =DP95/DH95-1 -> -0.034077556 | DQ96: =DQ95/DI95-1 -> -0.075396825 | ... DW96: =DW95/DO95-1 -> 0.051886792 | DX96: =DX97+DX98 -> 0.077678714 | DY96: =DY95/DQ95-1 -> 0.08614347 | DZ96: =DZ95/DR95-1 -> 0.15767196 | EA96: =EA95/DS95-1 -> 0.048367594 | EB96: =EB95/DT95-1 -> 0.10665914 | EC96: =EC95/DU95-1 -> 0.098911071 | ED96: =ED95/DV95-1 -> 0.10368824 | EE96: =EE95/DW95-1 -> 0.12107623 | EF96: =EF95/DX95-1 -> 0.10728402 | EG96: =EG95/DY95-1 -> 0.10697149 | EH96: =+EH95/DZ95-1 -> 0.073126143 | EI96: =EI95/EA95-1 -> 0.065743945 | EJ96: =EJ95/EB95-1 -> 0.069862315 | EK96: =EK95/EC95-1 -> 0.027250206 | EL96: =EL95/ED95-1 -> 0.053593947 | EM96: =EM95/EE95-1 -> -0.022666667 | EN96: =EN95/EF95-1 -> 0.0081591025 | EO96: =EO95/EG95-1 -> 0.039010709 | EP96: =EP95/EH95-1 -> -0.066439523 | ... FB96: =FB95/ET95-1 -> 0.049311927 | FC96: =FC97+FC98 -> 0.039838789 | FD96: =FD95/EV95-1 -> 0.065147767 | FE96: =FE95/EW95-1 -> 0.047449217 | FF96: =FF97+FF98 -> 0.11015623 | FG96: =FG97+FG98 -> 0.036399734 | FH96: =FH95/EZ95-1 -> 0.076639083 | FI96: =FI97+FI98 -> 0.059558122 | FJ96: =FJ95/FB95-1 -> 0.070033378 | FK96: =FK95/FC95-1 -> 0.54258556 | FL96: =FL95/FD95-1 -> 0.24573572 | FM96: =FM95/FE95-1 -> 0.16227653
A97: FX & Scope impact | DJ97: =DJ96-DJ98 -> -0.032653061 | DK97: =DK96-DK98 -> -0.030118203 | DL97: =DL96-DL98 -> -0.032803882 | DM97: =DM96-DM98 -> -0.025801668 | DN97: =DN96-DN98 -> -0.030713814 | DO97: =DO96-DO98 -> -0.0091332263 | DP97: =DP96-DP98 -> -0.021157848 | DQ97: =DQ96-DQ98 -> -0.025396825 | ... DW97: =DW96-DW98 -> 0.020886792 | DX97: =((DW97*DO95)+(DU97*DM95))/DP95 -> 0.01743309 | DY97: 0.017 | DZ97: =DZ96-DZ98 -> 0.017671958 | EA97: =EA96-EA98 -> 0.0013675937 | EB97: =EB96-EB98 -> 0.010062641 | EC97: =EC96-EC98 -> -0.0010889292 | ED97: =ED96-ED98 -> 0.0036882394 | EE97: =EE96-EE98 -> -0.0089237668 | EF97: =EF96-EF98 -> 0.0038785997 | EG97: =EG96-EG98 -> 0.0069714931 | EH97: 0 | EI97: =EI96-EI98 -> 0.014743945 | EJ97: =EJ96-EJ98 -> 0.0088623151 | EK97: =EK96-EK98 -> 0.016250206 | EL97: =EL96-EL98 -> 0.011593947 | EM97: =EM96-EM98 -> 0.018333333 | EN97: =+EN96-EN98 -> 0.017046915 | EO97: =EO96-EO98 -> 0.011782764 | EP97: =EP96-EP98 -> -0.002439523 | EQ97: =EQ96-EQ98 -> -0.010294372 | ER97: =ER96-ER98 -> -0.0060390848 | ES97: =ES96-ES98 -> -0.014581994 | ET97: =ET96-ET98 -> -0.0091310592 | EU97: =EU96-EU98 -> -0.014900409 | EV97: =EV96-EV98 -> -0.014700051 | ... FB97: =FB96-FB98 -> -0.021262779 | FC97: =0.1*FC492-((50%*FC842)/EU95) -> -0.060161211 | FD97: =FD96-FD98 -> -0.032431514 | FE97: =FE96-FE98 -> -0.028911404 | FF97: =10%*FF490 -> 0.010156227 | FG97: =10%*FG490 -> 0.011399734 | FH97: =FH96-FH98 -> 0.010721313 | FI97: =10%*FI490 -> 0.0095581218 | FJ97: =FJ96-FJ98 -> 0.010271473 | FK97: =FK96-FK98 -> 0.22545905 | FL97: =FL96-FL98 -> 0.092774754 | FM97: =FM96-FM98 -> 0.052276527
A98: Currency neutral | DJ98: -0.05 | DK98: -0.12 | DL98: =(DJ98*DJ95+DK98*DK95)/DL95 -> -0.081106304 | DM98: -0.04 | DN98: =(DL98*DL95+DM98*DM95)/DN95 -> -0.065327494 | DO98: 0.03 | DP98: =(DM98*DM95+DO98*DO95)/DP95 -> -0.012919708 | DQ98: -0.05 | DR98: 0.04 | DS98: 0.13 | DT98: 0.079 | DU98: 0.078 | DV98: =(DT98*DT95+DU98*DU95)/DV95 -> 0.078616562 | DW98: 0.031 | DX98: =(DU98*DU95+DW98*DW95)/DX95 -> 0.060245624 | DY98: =DY96-DY97 -> 0.06914347 | DZ98: 0.14 | EA98: 0.047 | EB98: =(DR95*DZ98+DS95*EA98)/DT95 -> 0.096596501 | EC98: 0.1 | ED98: 0.1 | EE98: 0.13 | EF98: =(-EB98*DT95+EG98*DY95)/DX95 -> 0.10340542 | EG98: 0.1 | EH98: =+EH96 -> 0.073126143 | EI98: 0.051 | EJ98: 0.061 | EK98: 0.011 | EL98: 0.042 | EM98: -0.041 | EN98: =(EC95*EK98+EE95*EM98)/EF95 -> -0.0088878123 | EO98: =(DZ95*EH98+EA95*EI98+EC95*EK98+EE95*EM98)/EG95 -> 0.027227945 | EP98: -0.064 | EQ98: -0.112 | ER98: -0.085 | ES98: -0.065 | ET98: =(EH95*EP98+EI95*EQ98+EK95*ES98)/EL95 -> -0.077643327 | EU98: 0.034 | EV98: =(EK95*ES98+EM95*EU98)/EN95 -> -0.028294385 | EW98: =(EH95*EP98+EI95*EQ98+EK95*ES98+EM95*EU98)/EO95 -> -0.057561227 | EX98: 0.003 | EY98: 0.126 | EZ98: =(EP95*EX98+EQ95*EY98)/ER95 -> 0.055308862 | FA98: 0.096 | FB98: =(EP95*EX98+EQ95*EY98+ES95*FA98)/ET95 -> 0.070574705 | FC98: 0.1 | FD98: =(ES95*FA98+EU95*FC98)/EV95 -> 0.097579281 | FE98: =(EP95*EX98+EQ95*EY98+ES95*FA98+EU95*FC98)/EW95 -> 0.076360621 | FF98: 0.1 | FG98: 0.025 | FH98: =(EX95*FF98+EY95*FG98)/EZ95 -> 0.06591777 | FI98: 0.05 | FJ98: =(EX95*FF98+EY95*FG98+FA95*FI98)/FB95 -> 0.059761905 | FK98: =(FE95*FM98-FB95*FJ98)/FC95 -> 0.31712651 | FL98: =(FA95*FI98+FC95*FK98)/FD95 -> 0.15296097 | FM98: 0.11
A99: % of total | DB99: =DB95/DB$127 -> 0.3740458 | DC99: =DC95/DC$127 -> 0.33558112 | DD99: =DD95/DD$127 -> 0.35518382 | DE99: =DE95/DE$127 -> 0.35009734 | DF99: =DF95/DF$127 -> 0.35327739 | DG99: =DG95/DG$127 -> 0.24184783 | DH99: =DH95/DH$127 -> 0.30081301 | DI99: =DI95/DI$127 -> 0.32669692 | ... FM99: =FM95/FM$127 -> 0.28724924
A100: European Ems | DB100: 284 | DC100: 262 | DD100: =DB100+DC100 -> 546 | DE100: 362 | DF100: =DE100+DD100 -> 908 | DG100: 271 | DH100: =DE100+DG100 -> 633 | DI100: =SUM(DB100,DC100,DE100,DG100) -> 1179 | DJ100: 293 | DK100: 256 | DL100: =DJ100+DK100 -> 549 | DM100: 311 | DN100: =DM100+DL100 -> 860 | DO100: 263 | DP100: =DM100+DO100 -> 574 | DQ100: =SUM(DJ100,DK100,DM100,DO100) -> 1123 | DR100: 290 | DS100: 343 | DT100: =DR100+DS100 -> 633 | DU100: 400 | DV100: =DU100+DT100 -> 1033 | DW100: =DY100-DV100 -> 352 | DX100: =DU100+DW100 -> 752 | DY100: 1385 | DZ100: 370 | EA100: 380 | EB100: =DZ100+EA100 -> 750 | EC100: =ED100-EB100 -> 439 | ED100: 1189 | EE100: =+EF100-EC100 -> 408 | EF100: =+EG100-EB100 -> 847 | EG100: 1597 | EH100: 430 | EI100: 487 | EJ100: =EH100+EI100 -> 917 | EK100: =EL100-EJ100 -> 569 | EL100: 1486 | EM100: 461 | EN100: =EK100+EM100 -> 1030 | EO100: =EH100+EI100+EK100+EM100 -> 1947 | EP100: 433 | EQ100: =ER100-EP100 -> 468 | ER100: 901 | ES100: 531 | ET100: =ER100+ES100 -> 1432 | EU100: 462 | EV100: =ES100+EU100 -> 993 | EW100: =EP100+EQ100+ES100+EU100 -> 1894 | EX100: 477 | EY100: 461 | EZ100: =EX100+EY100 -> 938 | FA100: 572 | FB100: =EZ100+FA100 -> 1510 | FC100: =EU100*(1+FC101) -> 344.96466 | FD100: =FA100+FC100 -> 916.96466 | FE100: =EX100+EY100+FA100+FC100 -> 1854.9647 | FF100: =EX100*(1+FF101) -> 201.97494 | FG100: =EY100*(1+FG101) -> 360.89041 | FH100: =FF100+FG100 -> 562.86535 | FI100: =FA100*(1+FI101) -> 322.06338 | FJ100: =FH100+FI100 -> 884.92873 | FK100: =FM100-FJ100 -> 307.07127 | FL100: =FI100+FK100 -> 629.13465 | FM100: 1192
A101: Growth | DJ101: =DJ100/DB100-1 -> 0.031690141 | DK101: =DK100/DC100-1 -> -0.022900763 | DL101: =DL100/DD100-1 -> 0.0054945055 | DM101: =DM100/DE100-1 -> -0.14088398 | DN101: =DN100/DF100-1 -> -0.052863436 | DO101: =DO100/DG100-1 -> -0.029520295 | DP101: =DP100/DH100-1 -> -0.093206951 | DQ101: =DQ100/DI100-1 -> -0.04749788 | ... DW101: =DW100/DO100-1 -> 0.33840304 | DX101: =DX102+DX103 -> 0.31063897 | DY101: =DY100/DQ100-1 -> 0.23330365 | DZ101: =DZ100/DR100-1 -> 0.27586207 | EA101: =EA100/DS100-1 -> 0.10787172 | EB101: =EB100/DT100-1 -> 0.18483412 | EC101: =EC100/DU100-1 -> 0.0975 | ED101: =ED100/DV100-1 -> 0.15101646 | EE101: =EE100/DW100-1 -> 0.15909091 | EF101: =EF100/DX100-1 -> 0.12632979 | EG101: =EG100/DY100-1 -> 0.15306859 | EH101: =+EH100/DZ100-1 -> 0.16216216 | EI101: =EI100/EA100-1 -> 0.28157895 | EJ101: =EJ100/EB100-1 -> 0.22266667 | EK101: =EK100/EC100-1 -> 0.29612756 | EL101: =EL100/ED100-1 -> 0.24978974 | EM101: =EM100/EE100-1 -> 0.12990196 | EN101: =EN100/EF100-1 -> 0.21605667 | EO101: =EO100/EG100-1 -> 0.21916093 | EP101: =EP100/EH100-1 -> 0.0069767442 | ... FB101: =FB100/ET100-1 -> 0.054469274 | FC101: =FC102+FC103 -> -0.25332324 | FD101: =FD100/EV100-1 -> -0.076571338 | FE101: =FE100/EW100-1 -> -0.020609999 | FF101: =FF102+FF103 -> -0.57657246 | FG101: =FG102+FG103 -> -0.21715745 | FH101: =FH100/EZ100-1 -> -0.39993033 | FI101: =FI102+FI103 -> -0.43695213 | FJ101: =FJ100/FB100-1 -> -0.41395448 | FK101: =FK100/FC100-1 -> -0.10984718 | FL101: =FL100/FD100-1 -> -0.31389434 | FM101: =FM100/FE100-1 -> -0.35740016
A102: FX & Scope impact | DJ102: =DJ101-DJ103 -> 0.071690141 | DK102: =DK101-DK103 -> 0.087099237 | DL102: =DL101-DL103 -> 0.078135671 | DM102: =DM101-DM103 -> 0.019116022 | DN102: =DN101-DN103 -> 0.051369122 | DO102: =DO101-DO103 -> -0.1095203 | DP102: =DP101-DP103 -> -0.043172108 | DQ102: =DQ101-DQ103 -> 0.02250212 | ... DW102: =DW101-DW103 -> 0.12340304 | DX102: =((DW102*DO100)+(DU102*DM100))/DP100 -> 0.12436237 | DY102: 0.075 | DZ102: =DZ101-DZ103 -> 0.015862069 | EA102: =EA101-EA103 -> -0.10112828 | EB102: =EB101-EB103 -> -0.047530806 | EC102: =EC101-EC103 -> -0.1225 | ED102: =ED101-ED103 -> -0.078983543 | EE102: =EE101-EE103 -> -0.040909091 | EF102: =EF101-EF103 -> -0.083261968 | EG102: =EG101-EG103 -> -0.066931408 | EH102: =+EH101-EH103 -> 0.012162162 | EI102: =EI101-EI103 -> 0.10057895 | EJ102: =EJ101-EJ103 -> 0.058666667 | EK102: =EK101-EK103 -> 0.11012756 | EL102: =EL101-EL103 -> 0.076789739 | EM102: =EM101-EM103 -> 0.042901961 | EN102: =EN484 -> 0.035016614 | EO102: =EO101-EO103 -> 0.067983719 | EP102: =EP101-EP103 -> -0.024023256 | EQ102: =EQ101-EQ103 -> -0.036014374 | ER102: =ER101-ER103 -> -0.030448201 | ES102: =ES101-ES103 -> -0.083783831 | ET102: =ET101-ET103 -> -0.050835801 | EU102: =EU101-EU103 -> -0.1048308 | EV102: =EV101-EV103 -> -0.093203883 | ... FB102: =FB101-FB103 -> -0.14471578 | FC102: =FC484*1 -> -0.35332324 | FD102: =FD101-FD103 -> -0.22255925 | FE102: =FE101-FE103 -> -0.19560102 | FF102: =FF484 -> -0.47657246 | FG102: =FG484 -> -0.21715745 | FH102: =FH101-FH103 -> -0.34907745 | FI102: =FI484 -> -0.46195213 | FJ102: =FJ101-FJ103 -> -0.39183528 | FK102: =FK101-FK103 -> 0.062194304 | FL102: =FL101-FL103 -> -0.26476678 | FM102: =FM101-FM103 -> -0.30740016
A103: Currency neutral | DJ103: -0.04 | DK103: -0.11 | DL103: =(DJ103*DJ100+DK103*DK100)/DL100 -> -0.072641166 | DM103: -0.16 | DN103: =(DL103*DL100+DM103*DM100)/DN100 -> -0.10423256 | DO103: 0.08 | DP103: =(DM103*DM100+DO103*DO100)/DP100 -> -0.050034843 | DQ103: -0.07 | DR103: 0.01 | DS103: 0.25 | DT103: 0.129 | DU103: 0.161 | DV103: 0.141 | DW103: 0.215 | DX103: =(DU103*DU100+DW103*DW100)/DX100 -> 0.1862766 | DY103: =DY101-DY102 -> 0.15830365 | DZ103: 0.26 | EA103: 0.209 | EB103: =(DR100*DZ103+DS100*EA103)/DT100 -> 0.23236493 | EC103: 0.22 | ED103: 0.23 | EE103: 0.2 | EF103: =(-EB103*DT100+EG103*DY100)/DX100 -> 0.20959176 | EG103: 0.22 | EH103: 0.15 | EI103: 0.181 | EJ103: 0.164 | EK103: 0.186 | EL103: 0.173 | EM103: 0.087 | EN103: =(EC100*EK103+EE100*EM103)/EF100 -> 0.13831169 | EO103: =(DZ100*EH103+EA100*EI103+EC100*EK103+EE100*EM103)/EG100 -> 0.15117721 | EP103: 0.031 | EQ103: -0.003 | ER103: 0.013 | ES103: 0.017 | ET103: =(EH100*EP103+EI100*EQ103+EK100*ES103)/EL100 -> 0.014496635 | EU103: 0.107 | EV103: =(EK100*ES103+EM100*EU103)/EN100 -> 0.057281553 | EW103: =(EH100*EP103+EI100*EQ103+EK100*ES103+EM100*EU103)/EO100 -> 0.036399076 | EX103: 0.275 | EY103: 0.144 | EZ103: =(EP100*EX103+EQ100*EY103)/ER100 -> 0.2069556 | FA103: 0.186 | FB103: =(EP100*EX103+EQ100*EY103+ES100*FA103)/ET100 -> 0.19918506 | FC103: 0.1 | FD103: =(ES100*FA103+EU100*FC103)/EV100 -> 0.14598792 | FE103: =(EP100*EX103+EQ100*EY103+ES100*FA103+EU100*FC103)/EW100 -> 0.17499102 | FF103: -0.1 | FG103: 0 | FH103: =(EX100*FF103+EY100*FG103)/EZ100 -> -0.050852878 | FI103: 0.025 | FJ103: =(EX100*FF103+EY100*FG103+FA100*FI103)/FB100 -> -0.022119205 | FK103: =(FE100*FM103-FB100*FJ103)/FC100 -> -0.17204149 | FL103: =(FA100*FI103+FC100*FK103)/FD100 -> -0.049127556 | FM103: -0.05
...

Sheet Worksheet
C2: Q1 08 | D2: Q2 08 | E2: H1 08 | F2: Q3 08 | G2: 9M 08 | H2: Q4 08 | I2: H2 08 | J2: FY 08 | K2: Q1 09 | L2: Q2 09 | M2: H1 09 | N2: Q3 09 | O2: 9M 09 | P2: Q4 09 | Q2: H2 09 | R2: FY 09 | S2: Q1 10 | T2: Q2 10 | U2: H1 10 | V2: Q3 10 | W2: 9M 10 | X2: Q4 10 | Y2: H2 10 | Z2: FY 10 | AA2: Q1 11 | AB2: Q2 11 | AC2: H1 11 | AD2: Q3 11 | AE2: 9M 11 | AF2: Q4 11 | AG2: H2 11 | AH2: FY 11 | AI2: Q1 12 | AJ2: Q2 12 | AK2: H1 12 | AL2: Q3 12 | AM2: 9M 12 | AN2: Q4 12 | AO2: H2 12 | AP2: FY 12 | AQ2: 1Q13 | AR2: 2Q13 | AS2: 1H13 | AT2: 3Q13 | AU2: 9M13 | AV2: 4Q13 | AW2: 2H13 | AX2: FY13 | AY2: 1Q14 | AZ2: 2Q14 | BA2: 1H14 | BB2: 3Q14 | BC2: 9M14 | BD2: 4Q14 | BE2: 2H14 | BF2: FY14 | BG2: 1Q15 | BH2: 2Q15 | BI2: 1H15 | BJ2: 3Q15 | BK2: 9M15 | BL2: 4Q15 | BM2: 2H15 | BN2: FY15 | BO2: 1Q16 | BP2: 2Q16 | BQ2: 1H16 | BR2: 3Q16 | BS2: 9M16 | BT2: 4Q16 | BU2: 2H16 | BV2: FY16 | BW2: 1Q17 | BX2: 2Q17 | BY2: 1H17 | BZ2: 3Q17 | CA2: 9M17 | CB2: 4Q17 | CC2: 2H17E | CD2: FY17E | CE2: 1Q18 | CF2: 2Q18 | CG2: 1H18 | CH2: 3Q18 | CI2: 4Q18 | CJ2: 1Q19 | CK2: 2Q19 | CL2: 3Q19 | CM2: 4Q19 | CN2: 1Q20E | CO2: 2Q20E | CP2: 3Q20E | CQ2: 4Q20E
B3: Wholesale | C3: =Interim!DB5 -> 1968 | D3: =Interim!DC5 -> 1755 | F3: =Interim!DE5 -> 2241 | H3: =Interim!DG5 -> 1794 | K3: =Interim!DJ5 -> 1874 | L3: =Interim!DK5 -> 1605 | N3: =Interim!DM5 -> 2036 | P3: =Interim!DO5 -> 1650 | S3: =Interim!DR5 -> 1898 | T3: =Interim!DS5 -> 1928 | V3: =Interim!DU5 -> 2421 | X3: =Interim!DW5 -> 1934 | AA3: =Interim!DZ5 -> 2320 | AB3: =Interim!EA5 -> 1973 | AD3: =Interim!EC5 -> 2576 | AF3: =Interim!EE5 -> 2081 | AI3: =Interim!EH5 -> 2614 | AJ3: =Interim!EI5 -> 2113 | AL3: =Interim!EK5 -> 2743 | AN3: =Interim!EM5 -> 2063 | AQ3: =Interim!EP5 -> 2481 | AR3: =Interim!EQ5 -> 2014 | AT3: =Interim!ES5 -> 2553 | AV3: =Interim!EU5 -> 2052 | AY3: =Interim!EX5 -> 2357 | AZ3: =Interim!EY5 -> 2085 | BB3: =Interim!FA5 -> 2717 | BD3: =Interim!FC5 -> 2038.2274 | BG3: =Interim!FF5 -> 2811 | BH3: =Interim!FG5 -> 2485 | BJ3: =Interim!FI5 -> 3311 | BL3: =Interim!FK5 -> 2620 | BO3: =Interim!FN5 -> 3339 | BP3: =Interim!FO5 -> 2869 | BR3: =Interim!FQ5 -> 3716 | BT3: =Interim!FS5 -> 2888 | BW3: =Interim!FV5 -> 3959 | BX3: =Interim!FW5 -> 3373 | BZ3: =Interim!FY5 -> 4069 | CB3: =Interim!GA5 -> 3216 | CE3: =Interim!GD5 -> 4027 | CF3: =Interim!GE5 -> 3501 | CH3: =Interim!GG5 -> 3945 | CI3: =Interim!GI5 -> 3125 | CJ3: =Interim!GL5 -> 4093 | CK3: =Interim!GM5 -> 3512 | CL3: =Interim!GO5 -> 4288 | CM3: =Interim!GQ5 -> 3329
B4: Retail | C4: =Interim!DB10 -> 360 | D4: =Interim!DC10 -> 423 | F4: =Interim!DE10 -> 491 | H4: =Interim!DG10 -> 464 | K4: =Interim!DJ10 -> 400 | L4: =Interim!DK10 -> 486 | N4: =Interim!DM10 -> 524 | P4: =Interim!DO10 -> 497 | S4: =Interim!DR10 -> 459 | T4: =Interim!DS10 -> 602 | V4: =Interim!DU10 -> 665 | X4: =Interim!DW10 -> 663 | AA4: =Interim!DZ10 -> 577 | AB4: =Interim!EA10 -> 681 | AD4: =Interim!EC10 -> 757 | AF4: =Interim!EE10 -> 778 | AI4: =Interim!EH10 -> 693 | AJ4: =Interim!EI10 -> 854 | AL4: =Interim!EK10 -> 944 | AN4: =Interim!EM10 -> 882 | AQ4: =Interim!EP10 -> 722 | AR4: =Interim!EQ10 -> 867 | AT4: =Interim!ES10 -> 923 | AV4: =Interim!EU10 -> 934 | AY4: =Interim!EX10 -> 794 | AZ4: =Interim!EY10 -> 958 | BB4: =Interim!FA10 -> 1047 | BD4: =Interim!FC10 -> 1021.5652 | BG4: =Interim!FF10 -> 895 | BH4: =Interim!FG10 -> 1057 | BJ4: =Interim!FI10 -> 1104 | BL4: =Interim!FK10 -> 1165 | BO4: =Interim!FN10 -> 1034 | BP4: =Interim!FO10 -> 1177 | BR4: =Interim!FQ10 -> 1330 | BT4: =Interim!FS10 -> 1462 | BW4: =Interim!FV10 -> 1290 | BX4: =Interim!FW10 -> 1467 | BZ4: =Interim!FY10 -> 1417 | CB4: =Interim!GA10 -> 1686 | CE4: =Interim!GD10 -> 1331 | CF4: =Interim!GE10 -> 1571 | CH4: =Interim!GG10 -> 1698 | CI4: =Interim!GI10 -> 1888 | CJ4: =Interim!GL10 -> 1595 | CK4: =Interim!GM10 -> 1850 | CL4: =Interim!GO10 -> 1960 | CM4: =Interim!GQ10 -> 2409
B5: Other | C5: =Interim!DB21 -> 285 | D5: =Interim!DC21 -> 336 | F5: =Interim!DE21 -> 347 | H5: =Interim!DG21 -> 318 | K5: =Interim!DJ21 -> 295 | L5: =Interim!DK21 -> 362 | N5: =Interim!DM21 -> 326 | P5: =Interim!DO21 -> 308 | S5: =Interim!DR21 -> 316 | T5: =Interim!DS21 -> 387 | V5: =Interim!DU21 -> 382 | X5: =Interim!DW21 -> 335 | AA5: =Interim!DZ21 -> 376 | AB5: =Interim!EA21 -> 410 | AD5: =Interim!EC21 -> 411 | AF5: =Interim!EE21 -> 382 | AI5: =Interim!EH21 -> 517 | AJ5: =Interim!EI21 -> 550 | AL5: =Interim!EK21 -> 486 | AN5: =Interim!EM21 -> 424 | AQ5: =Interim!EP21 -> 548 | AR5: =Interim!EQ21 -> 502 | AT5: =Interim!ES21 -> 403 | AV5: =Interim!EU21 -> 493 | AY5: =Interim!EX21 -> 382 | AZ5: =Interim!EY21 -> 422 | BB5: =Interim!FA21 -> 354 | BD5: =Interim!FC21 -> 366 | BG5: =Interim!FF21 -> 377 | BH5: =Interim!FG21 -> 365 | BJ5: =Interim!FI21 -> 342 | BL5: =Interim!FK21 -> 383 | BO5: =Interim!FN21 -> 396 | BP5: =Interim!FO21 -> 377 | BR5: =Interim!FQ21 -> 366 | BT5: =Interim!FS21 -> 336 | BW5: =Interim!FV21 -> 197 | BX5: =Interim!FW21 -> 198 | BZ5: =Interim!FY21 -> 192 | CB5: =Interim!GA21 -> 154 | CE5: =Interim!GD21 -> 190 | CF5: =Interim!GE21 -> 189 | CH5: =Interim!GG21 -> 230 | CI5: =Interim!GI21 -> 220 | CJ5: =Interim!GL21 -> 195 | CK5: =Interim!GM21 -> 147 | CL5: =Interim!GO21 -> 162 | CM5: =Interim!GQ21 -> 101
B6: Wholesale cFX growth | K6: =Interim!DJ8 -> -0.08 | L6: =Interim!DK8 -> -0.13 | N6: =Interim!DM8 -> -0.09 | P6: =Interim!DO8 -> -0.04 | S6: =Interim!DR8 -> 0.01 | T6: =Interim!DS8 -> 0.121 | V6: =Interim!DU8 -> 0.096 | X6: =Interim!DW8 -> 0.076 | AA6: =Interim!DZ8 -> 0.18 | AB6: =Interim!EA8 -> 0.06 | AD6: =Interim!EC8 -> 0.1 | AF6: =Interim!EE8 -> 0.09 | AI6: =Interim!EH8 -> 0.1 | AJ6: =Interim!EI8 -> 0.01 | AL6: =Interim!EK8 -> 0.004 | AN6: =Interim!EM8 -> -0.036 | AQ6: =Interim!EP8 -> -0.032 | AR6: =Interim!EQ8 -> -0.01 | AT6: =Interim!ES8 -> -0.008 | AV6: =Interim!EU8 -> 0.079 | AY6: =Interim!EX8 -> 0.006 | AZ6: =Interim!EY8 -> 0.101 | BB6: =Interim!FA8 -> 0.085 | BD6: =Interim!FC8 -> 0.05 | BG6: =Interim!FF8 -> 0.085327959 | BH6: =Interim!FG8 -> 0.070077618 | BJ6: =Interim!FI8 -> 0.14024648 | BL6: =Interim!FK8 -> 0.14228421 | BO6: =Interim!FN8 -> 0.23245393 | BP6: =Interim!FO8 -> 0.22776258 | BR6: =Interim!FQ8 -> 0.1608055 | BT6: =Interim!FS8 -> 0.12782786 | BW6: =Interim!FV8 -> 0.17402845 | BX6: =Interim!FW8 -> 0.17871244 | BZ6: =Interim!FY8 -> 0.13427603 | CB6: =Interim!GA8 -> 0.15414474 | CE6: =Interim!GD8 -> 0.1024198 | CF6: =Interim!GE8 -> 0.10562526 | CH6: =Interim!GG8 -> 0.022254116 | CI6: =Interim!GI8 -> -0.018106222 | CJ6: =Interim!GL8 -> 0.0015942389 | CK6: =Interim!GM8 -> -0.0019531562 | CL6: =Interim!GO8 -> 0.059295564 | CM6: =Interim!GP8 -> 0.020166513
B7: Retail cFX growth | K7: =Interim!DJ13 -> 0.04 | L7: =Interim!DK13 -> 0.07 | N7: =Interim!DM13 -> 0.04 | P7: =Interim!DO13 -> 0.14 | S7: =Interim!DR13 -> 0.16 | T7: =Interim!DS13 -> 0.167 | V7: =Interim!DU13 -> 0.155 | X7: =Interim!DW13 -> 0.226 | AA7: =Interim!DZ13 -> 0.22 | AB7: =Interim!EA13 -> 0.2 | AD7: =Interim!EC13 -> 0.21 | AF7: =Interim!EE13 -> 0.18 | AI7: =Interim!EH13 -> 0.16 | AJ7: =Interim!EI13 -> 0.161 | AL7: =Interim!EK13 -> 0.146 | AN7: =Interim!EM13 -> 0.092 | AQ7: =Interim!EP13 -> 0.065 | AR7: =Interim!EQ13 -> 0.053 | AT7: =Interim!ES13 -> 0.056 | AV7: =Interim!EU13 -> 0.148 | AY7: =Interim!EX13 -> 0.216 | AZ7: =Interim!EY13 -> 0.221 | BB7: =Interim!FA13 -> 0.198 | BD7: =Interim!FC13 -> 0.125 | BG7: =Interim!FF13 -> 0.14 | BH7: =Interim!FG13 -> 0.085135699 | BJ7: =Interim!FI13 -> 0.09 | BL7: =Interim!FK13 -> 0.13739913 | BO7: =Interim!FN13 -> 0.22 | BP7: =Interim!FO13 -> 0.20153264 | BR7: =Interim!FQ13 -> 0.23768116 | BT7: =Interim!FS13 -> 0.25623176 | BW7: =Interim!FV13 -> 0.18 | BX7: =Interim!FW13 -> 0.21 | BZ7: =Interim!FY13 -> 0.09 | CB7: =Interim!GA13 -> 0.21 | CE7: =Interim!GD13 -> 0.11 | CF7: =Interim!GE13 -> 0.12 | CH7: =Interim!GG13 -> 0.24 | CI7: =Interim!GI13 -> 0.13 | CJ7: =Interim!GL13 -> 0.18 | CK7: =Interim!GM13 -> 0.16 | CL7: =Interim!GO13 -> 0.11 | CM7: =Interim!GP13 -> 0.14733043
C9: Q1 08 | D9: Q2 08 | E9: H1 08 | F9: Q3 08 | G9: 9M 08 | H9: Q4 08 | I9: H2 08 | J9: FY 08 | K9: Q1 09 | L9: Q2 09 | M9: H1 09 | N9: Q3 09 | O9: 9M 09 | P9: Q4 09 | Q9: H2 09 | R9: FY 09 | S9: Q1 10 | T9: Q2 10 | U9: H1 10 | V9: Q3 10 | W9: 9M 10 | X9: Q4 10 | Y9: H2 10 | Z9: FY 10 | AA9: Q1 11 | AB9: Q2 11 | AC9: H1 11 | AD9: Q3 11 | AE9: 9M 11 | AF9: Q4 11 | AG9: H2 11 | AH9: FY 11 | AI9: Q1 12 | AJ9: Q2 12 | AK9: H1 12 | AL9: Q3 12 | AM9: 9M 12 | AN9: Q4 12 | AO9: H2 12 | AP9: FY 12 | AQ9: 1Q13 | AR9: 2Q13 | AS9: 1H13 | AT9: 3Q13 | AU9: 9M13 | AV9: 4Q13 | AW9: 2H13 | AX9: FY13 | AY9: 1Q14 | AZ9: 2Q14 | BA9: 1H14 | BB9: 3Q14 | BC9: 9M14 | BD9: 4Q14 | BE9: 2H14 | BF9: FY14 | BG9: 1Q15 | BH9: 2Q15 | BI9: 1H15 | BJ9: 3Q15 | BK9: 9M15 | BL9: 4Q15 | BM9: 2H15 | BN9: FY15 | BO9: 1Q16 | BP9: 2Q16 | BQ9: 1H16 | BR9: 3Q16 | BS9: 9M16 | BT9: 4Q16 | BU9: 2H16 | BV9: FY16 | BW9: 1Q17 | BX9: 2Q17 | BY9: 1H17 | BZ9: 3Q17 | CA9: 9M17 | CB9: 4Q17 | CC9: 2H17E | CD9: FY17E | CE9: 1Q18 | CF9: 2Q18 | CG9: 1H18 | CH9: 3Q18 | CI9: 4Q18 | CJ9: 1Q19 | CK9: 2Q19 | CL9: 3Q19 | CM9: 4Q19 | CN9: 1Q20E | CO9: 2Q20E | CP9: 3Q20E | CQ9: 4Q20E
B10: - online | AQ10: =Interim!EP15 -> 0.03185295 | AR10: =Interim!EQ15 -> 0.037005633 | AT10: =Interim!ES15 -> 0.026700267 | AV10: =Interim!EU15 -> 0.026010375 | AY10: =Interim!EX15 -> 0.052234475 | AZ10: =Interim!EY15 -> 0.04280325 | BB10: =Interim!FA15 -> 0.072547882 | BD10: =Interim!FC15 -> 0.044979687 | BG10: =Interim!FF15 -> 0.061854723 | BH10: =Interim!FG15 -> 0.06406382 | BJ10: =Interim!FI15 -> 0.024572251 | BL10: =Interim!FK15 -> 0.040338307 | BO10: =Interim!FN15 -> 0.069898839 | BP10: =Interim!FO15 -> 0.075391805 | BR10: =Interim!FQ15 -> 0.081106793 | BT10: =Interim!FS15 -> 0.11895505 | BW10: =Interim!FV15 -> 0.105991 | BX10: =Interim!FW15 -> 0.13198879 | BZ10: =Interim!FY15 -> 0.077993379 | CB10: =Interim!GA15 -> 0.13790484 | CE10: =Interim!GD15 -> 0.069606926 | CF10: =Interim!GE15 -> 0.067028891 | CH10: =Interim!GG15 -> 0.19593061 | CI10: =Interim!GI15 -> 0.061872823 | CJ10: =Interim!GL15 -> 0.12188669 | CK10: =Interim!GM15 -> 0.11274519 | CL10: =Interim!GO15 -> 0.042660341
B11: - store LFL | S11: =Interim!DR16 -> 0.07 | T11: =Interim!DS16 -> 0.088230453 | V11: =Interim!DU16 -> 0.1069084 | X11: =Interim!DW16 -> 0.15 | AA11: =Interim!DZ16 -> 0.17 | AB11: =Interim!EA16 -> 0.13475083 | AD11: =Interim!EC16 -> 0.15 | AF11: =Interim!EE16 -> 0.11 | AI11: =Interim!EH16 -> 0.09 | AJ11: =Interim!EI16 -> 0.08 | AL11: =Interim!EK16 -> 0.09 | AN11: =Interim!EM16 -> 0.01 | AQ11: =Interim!EP16 -> -0.01 | AR11: =Interim!EQ16 -> -0.02 | AT11: =Interim!ES16 -> -0.03 | AV11: =Interim!EU16 -> 0.03 | AY11: =Interim!EX16 -> 0.08 | AZ11: =Interim!EY16 -> 0.1 | BB11: =Interim!FA16 -> 0.06 | BD11: =Interim!FC16 -> 0.09 | BG11: =Interim!FF16 -> 0.04 | BH11: =Interim!FG16 -> -0.02 | BJ11: =Interim!FI16 -> 0.03 | BL11: =Interim!FK16 -> 0.05 | BO11: =Interim!FN16 -> 0.13 | BP11: =Interim!FO16 -> 0.13 | BR11: =Interim!FQ16 -> 0.13 | BT11: =Interim!FS16 -> 0.09376824 | BW11: =Interim!FV16 -> 0.05 | BX11: =Interim!FW16 -> 0.06 | BZ11: =Interim!FY16 -> 0.02 | CB11: =Interim!GA16 -> 0.05625 | CE11: =Interim!GD16 -> 0.05 | CF11: =Interim!GE16 -> 0.05 | CH11: =Interim!GG16 -> 0.05 | CI11: =Interim!GI16 -> 0.04 | CJ11: =Interim!GL16 -> 0.06 | CK11: =Interim!GM16 -> 0.05 | CL11: =Interim!GO16 -> 0.06
B12: - space | S12: =Interim!DR14 -> 0.09 | T12: =Interim!DS14 -> 0.078769547 | V12: =Interim!DU14 -> 0.048091603 | X12: =Interim!DW14 -> 0.076 | AA12: =Interim!DZ14 -> 0.05 | AB12: =Interim!EA14 -> 0.065249169 | AD12: =Interim!EC14 -> 0.06 | AF12: =Interim!EE14 -> 0.07 | AI12: =Interim!EH14 -> 0.07 | AJ12: =Interim!EI14 -> 0.081 | AL12: =Interim!EK14 -> 0.056 | AN12: =Interim!EM14 -> 0.082 | AQ12: =Interim!EP14 -> 0.04314705 | AR12: =Interim!EQ14 -> 0.035994367 | AT12: =Interim!ES14 -> 0.059299733 | AV12: =Interim!EU14 -> 0.091989625 | AY12: =Interim!EX14 -> 0.083765525 | AZ12: =Interim!EY14 -> 0.07819675 | BB12: =Interim!FA14 -> 0.065452118 | BD12: =Interim!FC14 -> -0.0099796866 | BG12: =Interim!FF14 -> 0.038145277 | BH12: =Interim!FG14 -> 0.04107188 | BJ12: =Interim!FI14 -> 0.035427749 | BL12: =Interim!FK14 -> 0.047060825 | BO12: =Interim!FN14 -> 0.020101161 | BP12: =Interim!FO14 -> -0.0038591655 | BR12: =Interim!FQ14 -> 0.026574366 | BT12: =Interim!FS14 -> 0.043508474 | BW12: =Interim!FV14 -> 0.024008998 | BX12: =Interim!FW14 -> 0.018011205 | BZ12: =Interim!FY14 -> -0.0079933786 | CB12: =Interim!GA14 -> 0.015845155 | CE12: =Interim!GD14 -> -0.0096069255 | CF12: =Interim!GE14 -> 0.0029711088 | CH12: =Interim!GG14 -> -0.0059306051 | CI12: =Interim!GI14 -> 0.028127177 | CJ12: =Interim!GL14 -> -0.0018866884 | CK12: =Interim!GM14 -> -0.0027451868 | CL12: =Interim!GO14 -> 0.0073396591
C14: Q1 08 | D14: Q2 08 | E14: H1 08 | F14: Q3 08 | G14: 9M 08 | H14: Q4 08 | I14: H2 08 | J14: FY 08 | K14: Q1 09 | L14: Q2 09 | M14: H1 09 | N14: Q3 09 | O14: 9M 09 | P14: Q4 09 | Q14: H2 09 | R14: FY 09 | S14: Q1 10 | T14: Q2 10 | U14: H1 10 | V14: Q3 10 | W14: 9M 10 | X14: Q4 10 | Y14: H2 10 | Z14: FY 10 | AA14: Q1 11 | AB14: Q2 11 | AC14: H1 11 | AD14: Q3 11 | AE14: 9M 11 | AF14: Q4 11 | AG14: H2 11 | AH14: FY 11 | AI14: Q1 12 | AJ14: Q2 12 | AK14: H1 12 | AL14: Q3 12 | AM14: 9M 12 | AN14: Q4 12 | AO14: H2 12 | AP14: FY 12 | AQ14: 1Q13 | AR14: 2Q13 | AS14: 1H13 | AT14: 3Q13 | AU14: 9M13 | AV14: 4Q13 | AW14: 2H13 | AX14: FY13 | AY14: 1Q14 | AZ14: 2Q14 | BA14: 1H14 | BB14: 3Q14 | BC14: 9M14 | BD14: 4Q14 | BE14: 2H14 | BF14: FY14 | BG14: 1Q15 | BH14: 2Q15 | BI14: 1H15 | BJ14: 3Q15 | BK14: 9M15 | BL14: 4Q15 | BM14: 2H15 | BN14: FY15 | BO14: 1Q16 | BP14: 2Q16 | BQ14: 1H16 | BR14: 3Q16 | BS14: 9M16 | BT14: 4Q16 | BU14: 2H16 | BV14: FY16 | BW14: 1Q17 | BX14: 2Q17 | BY14: 1H17 | BZ14: 3Q17 | CA14: 9M17 | CB14: 4Q17 | CE14: 1Q18 | CF14: 2Q18 | CG14: 2Q18 | CH14: 3Q18 | CI14: 4Q18 | CJ14: 1Q19 | CK14: 2Q19 | CL14: 3Q19 | CM14: 4Q19 | CN14: 1Q20E | CO14: 2Q20E | CP14: 3Q20E | CQ14: 4Q20E
B15: Wholesale | C15: =C3/SUM(C3:C5) -> 0.75315729 | D15: =D3/SUM(D3:D5) -> 0.69809069 | F15: =F3/SUM(F3:F5) -> 0.72783371 | H15: =H3/SUM(H3:H5) -> 0.69642857 | K15: =K3/SUM(K3:K5) -> 0.72946672 | L15: =L3/SUM(L3:L5) -> 0.65430086 | N15: =N3/SUM(N3:N5) -> 0.70547471 | P15: =P3/SUM(P3:P5) -> 0.67209776 | S15: =S3/SUM(S3:S5) -> 0.7100636 | T15: =T3/SUM(T3:T5) -> 0.66095303 | V15: =V3/SUM(V3:V5) -> 0.69809689 | X15: =X3/SUM(X3:X5) -> 0.65961801 | AA15: =AA3/SUM(AA3:AA5) -> 0.70882982 | AB15: =AB3/SUM(AB3:AB5) -> 0.6439295 | AD15: =AD3/SUM(AD3:AD5) -> 0.68803419 | AF15: =AF3/SUM(AF3:AF5) -> 0.64208578 | AI15: =AI3/SUM(AI3:AI5) -> 0.68357741 | AJ15: =AJ3/SUM(AJ3:AJ5) -> 0.60079613 | AL15: =AL3/SUM(AL3:AL5) -> 0.65732087 | AN15: =AN3/SUM(AN3:AN5) -> 0.61234788 | AQ15: =AQ3/SUM(AQ3:AQ5) -> 0.66142362 | AR15: =AR3/SUM(AR3:AR5) -> 0.59532959 | AT15: =AT3/SUM(AT3:AT5) -> 0.65815932 | AV15: =AV3/SUM(AV3:AV5) -> 0.58982466 | AY15: =AY3/SUM(AY3:AY5) -> 0.66713841 | AZ15: =AZ3/SUM(AZ3:AZ5) -> 0.6017316 | BB15: =BB3/SUM(BB3:BB5) -> 0.6597863 | BD15: =BD3/SUM(BD3:BD5) -> 0.59496521 | BG15: =BG3/SUM(BG3:BG5) -> 0.68846436 | BH15: =BH3/SUM(BH3:BH5) -> 0.63603788 | BJ15: =BJ3/SUM(BJ3:BJ5) -> 0.69602691 | BL15: =BL3/SUM(BL3:BL5) -> 0.62859885 | BO15: =BO3/SUM(BO3:BO5) -> 0.70014678 | BP15: =BP3/SUM(BP3:BP5) -> 0.64865476 | BR15: =BR3/SUM(BR3:BR5) -> 0.68662232 | BT15: =BT3/SUM(BT3:BT5) -> 0.61630388 | BW15: =BW3/SUM(BW3:BW5) -> 0.72695556 | BX15: =BX3/SUM(BX3:BX5) -> 0.66951171 | BZ15: =BZ3/SUM(BZ3:BZ5) -> 0.71662557 | CB15: =CB3/SUM(CB3:CB5) -> 0.63607595 | CE15: =CE3/SUM(CE3:CE5) -> 0.72584715 | CF15: =CF3/SUM(CF3:CF5) -> 0.66546284 | CH15: =CH3/SUM(CH3:CH5) -> 0.67171803 | CI15: =CI3/SUM(CI3:CI5) -> 0.59717179 | CJ15: =CJ3/SUM(CJ3:CJ5) -> 0.69573347 | CK15: =CK3/SUM(CK3:CK5) -> 0.63750227 | CL15: =CL3/SUM(CL3:CL5) -> 0.66895476
B16: Retail | C16: =C4/SUM(C3:C5) -> 0.13777268 | D16: =D4/SUM(D3:D5) -> 0.16825776 | F16: =F4/SUM(F3:F5) -> 0.15946736 | H16: =H4/SUM(H3:H5) -> 0.18012422 | K16: =K4/SUM(K3:K5) -> 0.15570261 | L16: =L4/SUM(L3:L5) -> 0.19812475 | N16: =N4/SUM(N3:N5) -> 0.18156618 | P16: =P4/SUM(P3:P5) -> 0.20244399 | S16: =S4/SUM(S3:S5) -> 0.17171717 | T16: =T4/SUM(T3:T5) -> 0.20637641 | V16: =V4/SUM(V3:V5) -> 0.19175317 | X16: =X4/SUM(X3:X5) -> 0.22612551 | AA16: =AA4/SUM(AA3:AA5) -> 0.17629086 | AB16: =AB4/SUM(AB3:AB5) -> 0.22225849 | AD16: =AD4/SUM(AD3:AD5) -> 0.20219017 | AF16: =AF4/SUM(AF3:AF5) -> 0.24004937 | AI16: =AI4/SUM(AI3:AI5) -> 0.18122385 | AJ16: =AJ4/SUM(AJ3:AJ5) -> 0.24282059 | AL16: =AL4/SUM(AL3:AL5) -> 0.22621615 | AN16: =AN4/SUM(AN3:AN5) -> 0.26179875 | AQ16: =AQ4/SUM(AQ3:AQ5) -> 0.192482 | AR16: =AR4/SUM(AR3:AR5) -> 0.25628141 | AT16: =AT4/SUM(AT3:AT5) -> 0.23794792 | AV16: =AV4/SUM(AV3:AV5) -> 0.26846795 | AY16: =AY4/SUM(AY3:AY5) -> 0.22473818 | AZ16: =AZ4/SUM(AZ3:AZ5) -> 0.27647908 | BB16: =BB4/SUM(BB3:BB5) -> 0.25424964 | BD16: =BD4/SUM(BD3:BD5) -> 0.2981982 | BG16: =BG4/SUM(BG3:BG5) -> 0.21920157 | BH16: =BH4/SUM(BH3:BH5) -> 0.27054006 | BJ16: =BJ4/SUM(BJ3:BJ5) -> 0.23207904 | BL16: =BL4/SUM(BL3:BL5) -> 0.27951056 | BO16: =BO4/SUM(BO3:BO5) -> 0.21681694 | BP16: =BP4/SUM(BP3:BP5) -> 0.26610898 | BR16: =BR4/SUM(BR3:BR5) -> 0.24575018 | BT16: =BT4/SUM(BT3:BT5) -> 0.31199317 | BW16: =BW4/SUM(BW3:BW5) -> 0.2368711 | BX16: =BX4/SUM(BX3:BX5) -> 0.29118698 | BZ16: =BZ4/SUM(BZ3:BZ5) -> 0.2495597 | CB16: =CB4/SUM(CB3:CB5) -> 0.33346519 | CE16: =CE4/SUM(CE3:CE5) -> 0.23990627 | CF16: =CF4/SUM(CF3:CF5) -> 0.29861243 | CH16: =CH4/SUM(CH3:CH5) -> 0.2891197 | CI16: =CI4/SUM(CI3:CI5) -> 0.36078731 | CJ16: =CJ4/SUM(CJ3:CJ5) -> 0.27112018 | CK16: =CK4/SUM(CK3:CK5) -> 0.33581412 | CL16: =CL4/SUM(CL3:CL5) -> 0.30577223
B17: Other | C17: =1-C16-C15 -> 0.10907003 | D17: =1-D16-D15 -> 0.13365155 | F17: =1-F16-F15 -> 0.11269893 | H17: =1-H16-H15 -> 0.1234472 | K17: =1-K16-K15 -> 0.11483067 | L17: =1-L16-L15 -> 0.1475744 | N17: =1-N16-N15 -> 0.11295911 | P17: =1-P16-P15 -> 0.12545825 | S17: =1-S16-S15 -> 0.11821923 | T17: =1-T16-T15 -> 0.13267055 | V17: =1-V16-V15 -> 0.11014994 | X17: =1-X16-X15 -> 0.11425648 | AA17: =1-AA16-AA15 -> 0.11487932 | AB17: =1-AB16-AB15 -> 0.13381201 | AD17: =1-AD16-AD15 -> 0.10977564 | AF17: =1-AF16-AF15 -> 0.11786486 | AI17: =1-AI16-AI15 -> 0.13519874 | AJ17: =1-AJ16-AJ15 -> 0.15638328 | AL17: =1-AL16-AL15 -> 0.11646298 | AN17: =1-AN16-AN15 -> 0.12585337 | AQ17: =1-AQ16-AQ15 -> 0.14609437 | AR17: =1-AR16-AR15 -> 0.148389 | AT17: =1-AT16-AT15 -> 0.10389276 | AV17: =1-AV16-AV15 -> 0.14170739 | AY17: =1-AY16-AY15 -> 0.10812341 | AZ17: =1-AZ16-AZ15 -> 0.12178932 | BB17: =1-BB16-BB15 -> 0.08596406 | BD17: =1-BD16-BD15 -> 0.10683659 | BG17: =1-BG16-BG15 -> 0.092334068 | BH17: =1-BH16-BH15 -> 0.093422063 | BJ17: =1-BJ16-BJ15 -> 0.071894051 | BL17: =1-BL16-BL15 -> 0.091890595 | BO17: =1-BO16-BO15 -> 0.083036276 | BP17: =1-BP16-BP15 -> 0.085236265 | BR17: =1-BR16-BR15 -> 0.067627494 | BT17: =1-BT16-BT15 -> 0.071702945 | BW17: =1-BW16-BW15 -> 0.036173338 | BX17: =1-BX16-BX15 -> 0.03930131 | BZ17: =1-BZ16-BZ15 -> 0.033814723 | CB17: =1-CB16-CB15 -> 0.030458861 | CE17: =1-CE16-CE15 -> 0.034246575 | CF17: =1-CF16-CF15 -> 0.035924729 | CH17: =1-CH16-CH15 -> 0.039162268 | CI17: =1-CI16-CI15 -> 0.042040894 | CJ17: =1-CJ16-CJ15 -> 0.033146354 | CK17: =1-CK16-CK15 -> 0.026683609 | CL17: =1-CL16-CL15 -> 0.025273011
A54: Sales | C54: 1Q 10 | D54: 2Q 10 | E54: H1 10 | F54: 3Q 10 | G54: 9M 10 | H54: 4Q 10 | I54: H2 10 | J54: FY 10 | K54: 1Q 11 | L54: 2Q 11 | M54: H1 11 | N54: 3Q 11 | O54: 9M 11 | P54: 4Q 11 | Q54: H2 11 | R54: FY 11 | S54: 1Q 12 | T54: 2Q 12 | U54: H1 12 | V54: 3Q 12 | W54: 9M 12 | X54: 4Q 12 | Y54: H2 12 | Z54: FY 12 | AA54: 1Q13 | AB54: 2Q13 | AC54: 1H13 | AD54: 3Q13 | AE54: 9M13 | AF54: 4Q13 | AG54: 2H13 | AH54: FY13 | AI54: 1Q14 | AJ54: 2Q14 | AK54: 1H14 | AL54: 3Q14 | AM54: 9M14 | AN54: 4Q14 | AO54: 2H14 | AP54: FY14 | AQ54: 1Q15 | AR54: 2Q15 | AS54: 1H15 | AT54: 3Q15 | AU54: 9M15 | AV54: 4Q15 | AW54: 2H15 | AX54: FY15 | AY54: 1Q16 | AZ54: 2Q16 | BA54: 1H16 | BB54: 3Q16 | BC54: 9M16 | BD54: 4Q16 | BE54: 2H16 | BF54: FY16 | BG54: 1Q17 | BH54: 2Q17 | BI54: 1H17 | BJ54: 3Q17 | BK54: 9M17 | BL54: 4Q17 | BO54: 1Q18 | BP54: 2Q18 | BR54: 3Q18 | BT54: 4Q18 | BW54: 1Q19 | BX54: 2Q19 | BZ54: 3Q19
B55: Footwear | C55: =Interim!DR147 -> 1272 | D55: =Interim!DS147 -> 1301 | E55: =Interim!DT147 -> 2573 | F55: =Interim!DU147 -> 1604 | G55: =Interim!DV147 -> 4177 | H55: =Interim!DW147 -> 1212 | I55: =Interim!DX147 -> 2816 | J55: =Interim!DY147 -> 5389 | ... BL55: =Interim!GA147 -> 2832 | BO55: =Interim!GD147 -> 3204 | BP55: =Interim!GE147 -> 3102 | BR55: =Interim!GG147 -> 3363 | BT55: =Interim!GI147 -> 3113 | BW55: =Interim!GL147 -> 3456 | BX55: =Interim!GM147 -> 3283 | BZ55: =Interim!GO147 -> 3490
B56: Apparel | C56: =Interim!DR152 -> 1130 | D56: =Interim!DS152 -> 1262 | E56: =Interim!DT152 -> 2392 | F56: =Interim!DU152 -> 1545 | G56: =Interim!DV152 -> 3937 | H56: =Interim!DW152 -> 1443 | I56: =Interim!DX152 -> 2988 | J56: =Interim!DY152 -> 5380 | ... BL56: =Interim!GA152 -> 1960 | BO56: =Interim!GD152 -> 2019 | BP56: =Interim!GE152 -> 1895 | BR56: =Interim!GG152 -> 2249 | BT56: =Interim!GI152 -> 2060 | BW56: =Interim!GL152 -> 2170 | BX56: =Interim!GM152 -> 1927 | BZ56: =Interim!GO152 -> 2625
