Workbook
Name A_ALL_KEYWORDS_TYPE_ScalarContributed_EQTY_200021488: #REF!,#REF!,#REF!
Name A_ALL_ONON: #REF!
Name A_ALL_SECTION_KEYWORDS_EQTY_200021488_13A: #REF!
Name A_ALL_YOUG.DE: [1]YOUG.DE_Annotation_Sheet!$A$1:$U$346
Name E_ALL_GFG.DE: [2]GFG.DE_Exchange_Sheet!$A$1:$U$346
Name E_ALL_ONON: #REF!
Name E_ALL_YOUG.DE: [1]YOUG.DE_Exchange_Sheet!$A$1:$U$346
Name IQ_CH: 110000
Name IQ_CQ: 5000
Name IQ_CY: 10000
Name IQ_DAILY: 500000
Name IQ_FH: 100000
Name IQ_FQ: 500
Name IQ_FY: 1000
Name IQ_LTM: 2000
Name IQ_MONTH: 15000
Name IQ_NTM: 6000
Name IQ_WEEK: 50000
Name IQ_YTD: 3000
Name L_ALL_GFG.DE: [2]GFG.DE_Live_Sheet!$A$1:$U$346
Name L_ALL_KEYWORDS_TYPE_ScalarContributed_EQTY_200021488: #REF!,#REF!,#REF!
Name L_ALL_ONON: #REF!
Name L_ALL_SECTION_KEYWORDS_EQTY_200021488_13A: #REF!
Name L_ALL_YOUG.DE: [1]YOUG.DE_Live_Sheet!$A$1:$U$346
Name V_ALL_GFG.DE: [2]GFG.DE_Validation_Sheet!$A$1:$U$346
Name V_ALL_KEYWORDS_TYPE_ScalarContributed_EQTY_200021488: #REF!,#REF!,#REF!
Name V_ALL_KEYWORDS_TYPE_ScalarContributed_ISSR_208001535: ITX.MC_Validation_Sheet!$9:$9,ITX.MC_Validation_Sheet!$42:$42
Name V_ALL_KEYWORDS_TYPE_ScalarReference_ISSR_208001535: ITX.MC_Validation_Sheet!$6:$7
Name V_ALL_ONON: #REF!
Name V_ALL_PERIODS_ITX.MC: ITX.MC_Validation_Sheet!$F$1:$DL$1
Name V_ALL_SECTION_KEYWORDS_EQTY_200021488_13A: #REF!
Name V_ALL_SECTION_KEYWORDS_ISSR_208001535_1314: ITX.MC_Validation_Sheet!$C$44:$C$73
Name V_ALL_SECTION_KEYWORDS_ISSR_208001535_13168: ITX.MC_Validation_Sheet!$C$131:$C$188
Name V_ALL_SECTION_KEYWORDS_ISSR_208001535_1316S: ITX.MC_Validation_Sheet!$C$190:$C$198
Name V_ALL_SECTION_KEYWORDS_ISSR_208001535_1316T: ITX.MC_Validation_Sheet!$C$200:$C$225
Name V_ALL_SECTION_KEYWORDS_ISSR_208001535_1319: ITX.MC_Validation_Sheet!$C$75:$C$92
Name V_ALL_SECTION_KEYWORDS_ISSR_208001535_131E: ITX.MC_Validation_Sheet!$C$94:$C$111
Name V_ALL_SECTION_KEYWORDS_ISSR_208001535_131J: ITX.MC_Validation_Sheet!$C$113:$C$125
Name V_ALL_SECTION_KEYWORDS_ISSR_208001535_131O: ITX.MC_Validation_Sheet!$C$127
Name V_ALL_SECTION_KEYWORDS_ISSR_208001535_131P: ITX.MC_Validation_Sheet!$C$129
Name V_ALL_SECTION_KEYWORDS_ISSR_208001535_13A: ITX.MC_Validation_Sheet!$C$9
Name V_ALL_SECTION_KEYWORDS_ISSR_208001535_13U: ITX.MC_Validation_Sheet!$C$11:$C$29
Name V_ALL_SECTION_KEYWORDS_ISSR_208001535_13V: ITX.MC_Validation_Sheet!$C$31:$C$42
Name V_ALL_SECTION_KEYWORDS_ISSR_208001535_Reference_Data: ITX.MC_Validation_Sheet!$C$6:$C$7
Name V_ALL_YOUG.DE: [1]YOUG.DE_Validation_Sheet!$A$1:$U$346
Name V_CURRENCY_ISSR_208001535_REP: ITX.MC_Validation_Sheet!$E$7
Name V_ENTITY_DATA_ISSR_208001535: ITX.MC_Validation_Sheet!$E$5:$DL$284
Name V_KEYWORD_ISSR_208001535_ACC_AMORT: ITX.MC_Validation_Sheet!$53:$53
Name V_KEYWORD_ISSR_208001535_ACC_DDA: ITX.MC_Validation_Sheet!$50:$50
Name V_KEYWORD_ISSR_208001535_ACC_END_DATE: ITX.MC_Validation_Sheet!$3:$3
Name V_KEYWORD_ISSR_208001535_ACC_PAY_GQ: ITX.MC_Validation_Sheet!$59:$59
Name V_KEYWORD_ISSR_208001535_ACQ: ITX.MC_Validation_Sheet!$100:$100
Name V_KEYWORD_ISSR_208001535_ADJ_UNF_PENS_GOOD: ITX.MC_Validation_Sheet!$88:$88
Name V_KEYWORD_ISSR_208001535_ASSOC_JV_ADDBK: ITX.MC_Validation_Sheet!$113:$113
Name V_KEYWORD_ISSR_208001535_ASSOCIATE: ITX.MC_Validation_Sheet!$26:$26
Name V_KEYWORD_ISSR_208001535_ASSOCIATE_OP: ITX.MC_Validation_Sheet!$37:$37
Name V_KEYWORD_ISSR_208001535_BAL_MINO_INT: ITX.MC_Validation_Sheet!$91:$91
Name V_KEYWORD_ISSR_208001535_CAP_LEASES: ITX.MC_Validation_Sheet!$80:$80
Name V_KEYWORD_ISSR_208001535_CAPEX: ITX.MC_Validation_Sheet!$99:$99
Name V_KEYWORD_ISSR_208001535_CAPEX_EXPANSION: ITX.MC_Validation_Sheet!$123:$123

Sheet Cover Sheet
D4: On Holding Model
D5: European General Retail
B13: Team:
B15: Richard Edwards
B16: Managing Director
B17: Richard.Edwards@gs.com
B18: +44 (20) 7051-6016
B20: Ben Williams
B21: Analyst
B22: ben.williams@gs.com
B23: +44 (20) 7051-0661
B25: Hamish Bogdan
B26: Analyst
B27: hamish.bogdan@gs.com
B28: +44 (20) 7552-2214

Sheet ITX.MC_Validation_Sheet

Sheet MODEL
AT1: =AT153/MODEL!AT153-1 -> 0 | AU1: =AU153/MODEL!AU153-1 -> 0 | AV1: =AV153/MODEL!AV153-1 -> 0 | AW1: =AW153/MODEL!AW153-1 -> 0 | AX1: =AX153/MODEL!AX153-1 -> 0 | AY1: =AY153/MODEL!AY153-1 -> 0
B2: Dec year end (CHFmn) | C2: 1Q19 | D2: 2Q19 | E2: 3Q19 | F2: 4Q19 | G2: 2019 | H2: 1Q20 | I2: 2Q20 | J2: 1H20 | K2: 3Q20 | L2: 4Q20 | M2: 2H20 | N2: 2020 | O2: 1Q21 | P2: 2Q21 | Q2: 1H21 | R2: 3Q21 | S2: 4Q21 | T2: 2H21 | U2: =Valuation!C48 -> 2021 | V2: 1Q22 | W2: 2Q22 | X2: 3Q22 | Y2: 4Q22 | Z2: =Valuation!D48 -> 2022 | AA2: 1Q23 | AB2: 2Q23 | AC2: 3Q23 | AD2: 4Q23 | AE2: =Valuation!E48 -> 2023 | AF2: 1Q24 | AG2: 2Q24 | AH2: 3Q24 | AI2: 4Q24 | AJ2: =Valuation!F48 -> 2024 | AK2: 1Q25 | AL2: 2Q25 | AM2: 3Q25 | AN2: 4Q25 | AO2: =Valuation!G48 -> 2025 | AP2: 1Q26 | AQ2: 2Q26 | AR2: 3Q26E | AS2: 4Q26E | AT2: =Valuation!H48 -> 2026E | AU2: =Valuation!I48 -> 2027E | AV2: =Valuation!J48 -> 2028E | AW2: =Valuation!K48 -> 2029E | AX2: =Valuation!L48 -> 2030E | AY2: =Valuation!M48 -> 2031E
B3: Sales by region
B4: Europe | C4: 24.409314 | D4: 36.582871 | E4: 32.461653 | F4: 34.890102 | G4: 128.34394 | H4: 33.749016 | I4: 47.995953 | J4: =I4+H4 -> 81.74497 | K4: 58.767857 | L4: 46.997419 | M4: =L4+K4 -> 105.76528 | N4: 187.51024 | O4: =H4*(1+O7) -> 57.1 | P4: =I4*(1+P7) -> 70.8 | Q4: =P4+O4 -> 127.9 | R4: =K4*(1+R7) -> 88.3 | S4: =L4*(1+S7) -> 44.2 | T4: =S4+R4 -> 132.5 | U4: =T4+Q4 -> 260.4 | V4: =O4*(1+V7) -> 74.9 | W4: =P4*(1+W7) -> 83.293 | X4: =R4*(1+X7) -> 116.468 | Y4: =S4*(1+Y7) -> 79.639 | Z4: =SUM(V4:Y4) -> 354.3 | AA4: =V4*(1+AA7) -> 118.9 | AB4: =W4*(1+AB7) -> 113.6 | AC4: =X4*(1+AC7) -> 144 | AD4: =AE4-SUM(AA4:AC4) -> 112.2 | AE4: =Z4*(1+AE7) -> 488.7 | AF4: =AA4*(1+AF7) -> 126.2 | AG4: =AB4*(1+AG7) -> 138.4 | AH4: =AC4*(1+AH7) -> 165.8 | AI4: 147.4 | AJ4: =AE4*(1+AJ7) -> 577.8 | AK4: =AF4*(1+AK7) -> 168.6032 | AL4: =AG4*(1+AL7) -> 197.7736 | AM4: =AH4*(1+AM7) -> 213.3 | AN4: =AO4-SUM(AK4:AM4) -> 183.0232 | AO4: =AJ4*(1+AO7) -> 762.7 | AP4: =AK4*(1+AP7) -> 207.1 | AQ4: =AL4*(1+AQ7) -> 228.2 | AR4: =AM4*(1+AR7) -> 240.75012 | AS4: =AT4-SUM(AP4:AR4) -> 221.22491 | AT4: =AO4*(1+AT7) -> 897.27503 | AU4: =AT4*(1+AU7) -> 1054.132 | AV4: =AU4*(1+AV7) -> 1191.1691 | AW4: =AV4*(1+AW7) -> 1334.1094 | AX4: =AW4*(1+AX7) -> 1467.5204 | AY4: =AX4*(1+AY7) -> 1584.922
B5: - cFX growth | O5: =((1+O7)/(1+O6))-1 -> 0.79553474 | P5: =((1+P7)/(1+P6))-1 -> 0.55104458 | Q5: =((1+Q7)/(1+Q6))-1 -> 0.65143558 | R5: =((1+R7)/(1+R6))-1 -> 0.5259871 | S5: =((1+S7)/(1+S6))-1 -> -0.10047028 | T5: =((1+T7)/(1+T6))-1 -> 0.23830651 | U5: =((1+U7)/(1+U6))-1 -> 0.41177435 | V5: =((1+V7)/(1+V6))-1 -> 0.24073235 | ... AB5: =((1+AB7)/(1+AB6))-1 -> 0.35788118 | AC5: 0.24 | AD5: =((1+AD7)/(1+AD6))-1 -> 0.26001273 | AE5: =((1+AE7)/(1+AE6))-1 -> 0.35032983 | AF5: =((1+AF7)/(1+AF6))-1 -> 0.10396081 | AG5: =((1+AG7)/(1+AG6))-1 -> 0.22197579 | AH5: =((1+AH7)/(1+AH6))-1 -> 0.15196487 | AI5: =((1+AI7)/(1+AI6))-1 -> 0.33105282 | AJ5: =((1+AJ7)/(1+AJ6))-1 -> 0.19939817 | AK5: =((1+AK7)/(1+AK6))-1 -> 0.33000156 | ... AO5: =((1+AO7)/(1+AO6))-1 -> 0.34728225 | AP5: 0.256 | AQ5: 0.205 | AR5: 0.13 | AS5: =((1+AS7)/(1+AS6))-1 -> 0.19489595 | AT5: 0.19 | AU5: 0.17 | AV5: 0.16 | AW5: 0.15 | AX5: 0.12 | AY5: 0.1
B6: - ccy/other | O6: =FX!M8*0.9 -> -0.057717391 | P6: =FX!N8*0.9 -> -0.0489478 | Q6: =((O6*H4)+(P6*I4))/J4 -> -0.052568391 | R6: =FX!O8*0.9 -> -0.015376966 | S6: =FX!P8*0.9 -> 0.045520972 | T6: =((R6*K4)+(S6*L4))/M4 -> 0.011683389 | U6: =((O6*H4)+(P6*I4)+(R6*K4)+(S6*L4))/N4 -> -0.016327133 | V6: =FX!R8*0.9 -> 0.057225434 | W6: =FX!S8*0.9 -> 0.061957157 | X6: =FX!T8*0.9 -> 0.068651489 | Y6: =FX!U8*0.9 -> 0.032566372 | Z6: =((V6*O4)+(W6*P4)+(X6*R4)+(Y6*S4))/U4 -> 0.058200841 | AA6: =FX!W8*0.9 -> 0.0342 | AB6: =FX!X8*0.9 -> 0.0044031311 | AC6: =(((1+0.199)-(1+AC5))) -> -0.041 | AD6: 0.11812956 | AE6: 0.021483425 | AF6: -0.038556333 | AG6: -0.003 | AH6: -0.0005 | AI6: -0.013017761 | AJ6: -0.014238579 | AK6: 0.0045100995 | AL6: -0.022169349 | AM6: -0.032696436 | AN6: -0.026 | AO6: -0.020244702 | AP6: -0.022031996 | AQ6: -0.042452616 | AR6: =FX!AN8 -> -0.0013074337 | AS6: =FX!AO8 -> 0.011574292 | AT6: =AVERAGE(AP6:AS6) -> -0.013554438 | AU6: =FX!AQ8/3 -> 0.00481478 | AV6: =FX!AR8/3 -> 0 | AW6: =FX!AS8/3 -> 0 | AX6: =FX!AT8/3 -> 0 | AY6: =FX!AU8/3 -> 0
B7: - total growth | H7: =H4/C4-1 -> 0.38262863 | I7: =I4/D4-1 -> 0.31197885 | K7: =K4/E4-1 -> 0.81037784 | L7: =L4/F4-1 -> 0.34701295 | N7: =N4/G4-1 -> 0.46099805 | O7: 0.69190116 | P7: 0.47512436 | Q7: =Q4/J4-1 -> 0.56462227 | R7: 0.50252205 | S7: -0.059522815 | T7: =T4/M4-1 -> 0.25277412 | U7: =U4/N4-1 -> 0.38872412 | V7: 0.3117338 | W7: 0.1764548 | X7: 0.3190034 | Y7: 0.80178733 | Z7: =Z4/U4-1 -> 0.36059908 | AA7: 0.58744993 | AB7: 0.36386011 | AC7: 0.23639111 | AD7: =AD4/Y4-1 -> 0.40885747 | AE7: 0.37933954 | AF7: 0.061396131 | AG7: 0.21830986 | AH7: 0.15138889 | AI7: =AI4/AD4-1 -> 0.31372549 | AJ7: 0.18232044 | AK7: 0.336 | AL7: 0.429 | AM7: 0.28648975 | AN7: =AN4/AI4-1 -> 0.24167707 | AO7: 0.32000692 | AP7: =((1+AP6)*(1+AP5))-1 -> 0.22832781 | AQ7: =((1+AQ6)*(1+AQ5))-1 -> 0.1538446 | AR7: =AR6+AR5 -> 0.12869257 | AS7: =AS4/AN4-1 -> 0.20872603 | AT7: =AT6+AT5 -> 0.17644556 | AU7: =AU6+AU5 -> 0.17481478 | AV7: 0.13 | AW7: 0.12 | AX7: 0.1 | AY7: 0.08
B8: Group sales mix | C8: =C4/C$31 -> 0.49241786 | D8: =D4/D$31 -> 0.52502893 | E8: =E4/E$31 -> 0.49886749 | F8: =F4/F$31 -> 0.42137244 | G8: =G4/G$31 -> 0.48047308 | H8: =H4/H$31 -> 0.47340569 | I8: =I4/I$31 -> 0.48175237 | J8: =J4/J$31 -> 0.47827097 | ... AY8: =AY4/AY$31 -> 0.22126781
B9: Europe DTC % | N9: =(N4-N94)/N4 -> 0.3258395 | U9: =(U4-U94)/U4 -> 0.31696742 | Z9: =(Z4-Z94)/Z4 -> 0.36746903 | AE9: =(AE4-AE94)/AE4 -> 0.47034559 | AJ9: =(AJ4-AJ94)/AJ4 -> 0.48938733 | AO9: =(AO4-AO94)/AO4 -> 0.55321626 | AT9: =(AT4-AT94)/AT4 -> 0.57753911 | AU9: =(AU4-AU94)/AU4 -> 0.59998334 | AV9: =(AV4-AV94)/AV4 -> 0.61715219 | AW9: =(AW4-AW94)/AW4 -> 0.63031259 | AX9: =(AX4-AX94)/AX4 -> 0.64345329 | AY9: =(AY4-AY94)/AY4 -> 0.64975889
B10: - total growth yo2y | O10: =(1*(1+H7)*(1+O7))-1 -> 1.339271 | P10: =(1*(1+I7)*(1+P7))-1 -> 0.93533197 | R10: =(1*(1+K7)*(1+R7))-1 -> 1.7201326 | S10: =(1*(1+L7)*(1+S7))-1 -> 0.26683494 | U10: =(1*(1+N7)*(1+U7))-1 -> 1.0289232 | V10: =(1*(1+O7)*(1+V7))-1 -> 1.2193239 | W10: =(1*(1+P7)*(1+W7))-1 -> 0.73541714 | X10: =(1*(1+R7)*(1+X7))-1 -> 0.98183168 | Y10: =(1*(1+S7)*(1+Y7))-1 -> 0.69453988 | Z10: =(1*(1+U7)*(1+Z7))-1 -> 0.88949676 | AA10: =(1*(1+T7)*(1+AA7))-1 -> 0.9887162 | AB10: =(1*(1+U7)*(1+AB7))-1 -> 0.89402543 | AC10: =(1*(1+W7)*(1+AC7))-1 -> 0.45455826 | AD10: =(1*(1+X7)*(1+AD7))-1 -> 0.85828779 | AE10: =(1*(1+Z7)*(1+AE7))-1 -> 0.87672811 | AF10: =(1*(1+Y7)*(1+AF7))-1 -> 0.9124101 | AG10: =(1*(1+Z7)*(1+AG7))-1 -> 0.65763127 | AH10: =(1*(1+AB7)*(1+AH7))-1 -> 0.57033337 | AI10: =(1*(1+AC7)*(1+AI7))-1 -> 0.62427852 | AJ10: =(1*(1+AE7)*(1+AJ7))-1 -> 0.63082134 | AK10: =(1*(1+AD7)*(1+AK7))-1 -> 0.88223358 | AL10: =(1*(1+AE7)*(1+AL7))-1 -> 0.97107621 | AM10: =(1*(1+AG7)*(1+AM7))-1 -> 0.56734314 | AN10: =(1*(1+AH7)*(1+AN7))-1 -> 0.42965318 | AO10: =(1*(1+AJ7)*(1+AO7))-1 -> 0.56067117 | AP10: =(1*(1+AI7)*(1+AP7))-1 -> 0.61368556 | AQ10: =(1*(1+AJ7)*(1+AQ7))-1 -> 0.36421406 | AR10: =(1*(1+AL7)*(1+AR7))-1 -> 0.61290168 | AS10: =(1*(1+AM7)*(1+AS7))-1 -> 0.55501364 | AT10: =(1*(1+AO7)*(1+AT7))-1 -> 0.55291629 | AU10: =(1*(1+AT7)*(1+AU7))-1 -> 0.38210563 | AV10: =(1*(1+AU7)*(1+AV7))-1 -> 0.3275407 | AW10: =(1*(1+AV7)*(1+AW7))-1 -> 0.2656 | AX10: =(1*(1+AW7)*(1+AX7))-1 -> 0.232 | AY10: =(1*(1+AX7)*(1+AY7))-1 -> 0.188
B11: North America/Americas (from FY22) | C11: ='[3]Net Sales Breakdown'!C28/1000000 -> 20.919437 | D11: ='[3]Net Sales Breakdown'!D28/1000000 -> 26.762032 | E11: ='[3]Net Sales Breakdown'!E28/1000000 -> 26.174527 | F11: ='[3]Net Sales Breakdown'!F28/1000000 -> 37.905004 | G11: =SUM(C11:F11) -> 111.761 | H11: ='[3]Net Sales Breakdown'!H28/1000000 -> 33.124064 | I11: ='[3]Net Sales Breakdown'!I28/1000000 -> 46.872629 | J11: =I11+H11 -> 79.996693 | K11: ='[3]Net Sales Breakdown'!J28/1000000 -> 61.427927 | L11: ='[3]Net Sales Breakdown'!K28/1000000 -> 66.66438 | M11: =L11+K11 -> 128.09231 | N11: =M11+J11 -> 208.089 | O11: =H11*(1+O14) -> 74.2 | P11: =I11*(1+P14) -> 89.7 | Q11: =P11+O11 -> 163.9 | R11: =K11*(1+R14) -> 112.2 | S11: =L11*(1+S14) -> 133.4 | T11: =S11+R11 -> 245.6 | U11: =T11+Q11 -> 409.5 | V11: =O11*(1+V14) -> 138.4 | W11: =P11*(1+W14) -> 181.673 | X11: =R11*(1+X14) -> 176.26 | Y11: =S11*(1+Y14) -> 242.167 | Z11: =SUM(V11:Y11) -> 738.5 | AA11: =V11*(1+AA14) -> 270.2 | AB11: =W11*(1+AB14) -> 296.6 | AC11: =X11*(1+AC14) -> 294.9 | AD11: =AE11-SUM(AA11:AC11) -> 300.6 | AE11: =Z11*(1+AE14) -> 1162.3 | AF11: =AA11*(1+AF14) -> 329.6 | AG11: =AB11*(1+AG14) -> 370.1 | AH11: =AC11*(1+AH14) -> 395.5 | AI11: 385.1 | AJ11: =AE11*(1+AJ14) -> 1480.3 | AK11: =AF11*(1+AK14) -> 437.3792 | AL11: =AG11*(1+AL14) -> 432.2768 | AM11: =AH11*(1+AM14) -> 436.2 | AN11: =AO11-SUM(AK11:AM11) -> 434.344 | AO11: =AJ11*(1+AO14)+0.1 -> 1740.2 | AP11: =AK11*(1+AP14) -> 450.8 | AQ11: =AL11*(1+AQ14) -> 451.6 | AR11: =AM11*(1+AR14) -> 451.71351 | AS11: =AT11-SUM(AP11:AR11) -> 473.99707 | AT11: =AO11*(1+AT14) -> 1828.1106 | AU11: =AT11*(1+AU14) -> 1999.9317 | AV11: =AU11*(1+AV14) -> 2159.9262 | AW11: =AV11*(1+AW14) -> 2332.7203 | AX11: =AW11*(1+AX14) -> 2519.3379 | AY11: =AX11*(1+AY14) -> 2670.4982
B12: - cFX growth | O12: =((1+O14)/(1+O13))-1 -> 1.3963821 | P12: =((1+P14)/(1+P13))-1 -> 1.0243151 | Q12: =((1+Q14)/(1+Q13))-1 -> 1.1773605 | R12: =((1+R14)/(1+R13))-1 -> 0.82955457 | S12: =((1+S14)/(1+S13))-1 -> 0.96058094 | T12: =((1+T14)/(1+T13))-1 -> 0.89846813 | U12: =((1+U14)/(1+U13))-1 -> 1.0010547 | V12: =((1+V14)/(1+V13))-1 -> 0.82658463 | ... AB12: =((1+AB14)/(1+AB13))-1 -> 0.75326886 | AC12: 0.75 | AD12: =((1+AD14)/(1+AD13))-1 -> 0.29038576 | AE12: =((1+AE14)/(1+AE13))-1 -> 0.61047066 | AF12: =((1+AF14)/(1+AF13))-1 -> 0.30369422 | AG12: =((1+AG14)/(1+AG13))-1 -> 0.25800184 | AH12: =((1+AH14)/(1+AH13))-1 -> 0.34516809 | AI12: =((1+AI14)/(1+AI13))-1 -> 0.33892697 | AJ12: =((1+AJ14)/(1+AJ13))-1 -> 0.31234783 | AK12: =((1+AK14)/(1+AK13))-1 -> 0.28684312 | ... AO12: =((1+AO14)/(1+AO13))-1 -> 0.23390534 | AP12: 0.171 | AQ12: 0.13 | AR12: 0.08 | AS12: =((1+AS14)/(1+AS13))-1 -> 0.089315885 | AT12: 0.11 | AU12: 0.09 | AV12: =((1+AV14)/(1+AV13))-1 -> 0.08 | AW12: =((1+AW14)/(1+AW13))-1 -> 0.08 | AX12: =((1+AX14)/(1+AX13))-1 -> 0.08 | AY12: =((1+AY14)/(1+AY13))-1 -> 0.06
B13: - ccy/other | O13: =FX!M9 -> -0.065231159 | P13: =FX!N9 -> -0.054644809 | Q13: =((O13*H11)+(P13*I11))/J11 -> -0.059028277 | R13: =FX!O9 -> -0.0016527408 | S13: =FX!P9 -> 0.020650871 | T13: =((R13*K11)+(S13*L11))/M11 -> 0.0099549544 | U13: =((O13*H11)+(P13*I11)+(R13*K11)+(S13*L11))/N11 -> -0.016564614 | V13: =FX!R9 -> 0.021156689 | W13: =FX!S9 -> 0.059436511 | X13: =FX!T9 -> 0.052880897 | Y13: =FX!U9 -> 0.043984601 | Z13: =((V13*O11)+(W13*P11)+(X13*R11)+(Y13*S11))/U11 -> 0.045670485 | AA13: =FX!W9 -> -0.00018474044 | AB13: =FX!X9 -> -0.068823001 | AC13: =(((1+0.605)-(1+AC12))) -> -0.145 | AD13: -0.038045674 | AE13: -0.022729201 | AF13: -0.064322647 | AG13: -0.0081028025 | AH13: -0.003 | AI13: -0.043185713 | AJ13: -0.029529042 | AK13: 0.031205727 | AL13: -0.054891334 | AM13: -0.087849468 | AN13: -0.070095643 | AO13: -0.047329704 | AP13: -0.11982529 | AQ13: -0.075485851 | AR13: =FX!AN9-(FX!$AM$9-MODEL!$AQ$13) -> -0.044434869 | AS13: =FX!AO9-(FX!$AM$9-MODEL!$AQ$13) -> 0.0018160639 | AT13: =AVERAGE(AP13:AS13) -> -0.059482486 | AU13: =FX!AQ9-(FX!$AM$9-MODEL!$AQ$13) -> 0.0039883579 | AV13: =FX!AR9 -> 0 | AW13: =FX!AS9 -> 0 | AX13: =FX!AT9 -> 0 | AY13: =FX!AU9 -> 0
B14: - total growth | H14: =H11/C11-1 -> 0.58341085 | I14: =I11/D11-1 -> 0.75146004 | K14: =K11/E11-1 -> 1.3468591 | L14: =L11/F11-1 -> 0.7587224 | N14: =N11/G11-1 -> 0.86191068 | O14: 1.2400633 | P14: 0.9136968 | Q14: =Q11/J11-1 -> 1.0488347 | R14: 0.82653079 | S14: 1.0010686 | T14: =T11/M11-1 -> 0.9173673 | U14: =U11/N11-1 -> 0.96790796 | V14: 0.86522911 | W14: 1.02534 | X14: 0.57094474 | Y14: 0.81534483 | Z14: =Z11/U11-1 -> 0.8034188 | AA14: 0.95231214 | AB14: 0.63260363 | AC14: 0.67309656 | AD14: =AD11/Y11-1 -> 0.24129217 | AE14: 0.57386594 | AF14: 0.21983716 | AG14: 0.2478085 | AH14: 0.34113259 | AI14: =AI11/AD11-1 -> 0.28110446 | AJ14: 0.27359546 | AK14: 0.327 | AL14: 0.168 | AM14: 0.10290771 | AN14: =AN11/AI11-1 -> 0.12787328 | AO14: 0.17550497 | AP14: =((1+AP13)*(1+AP12))-1 -> 0.030684587 | AQ14: =((1+AQ13)*(1+AQ12))-1 -> 0.044700988 | AR14: =AR13+AR12 -> 0.035565131 | AS14: =AS11/AN11-1 -> 0.091294152 | AT14: =AT13+AT12 -> 0.050517514 | AU14: =AU13+AU12 -> 0.093988358 | AV14: 0.08 | AW14: 0.08 | AX14: 0.08 | AY14: 0.06
B15: Group sales mix | C15: =C11/C$31 -> 0.42201532 | D15: =D11/D$31 -> 0.38408251 | E15: =E11/E$31 -> 0.40224756 | F15: =F11/F$31 -> 0.45778382 | G15: =G11/G$31 -> 0.41839258 | H15: =H11/H$31 -> 0.46463933 | I15: =I11/I$31 -> 0.47047717 | J15: =J11/J$31 -> 0.4680422 | ... AY15: =AY11/AY$31 -> 0.37282295
B16: North America DTC % | N16: =(N11-N99)/N11 -> 0.44595822 | U16: =(U11-U99)/U11 -> 0.39467139 | Z16: =(Z11-Z99)/Z11 -> 0.29878688 | AE16: =(AE11-AE99)/AE11 -> 0.30153199 | AJ16: =(AJ11-AJ99)/AJ11 -> 0.31457002 | AO16: =(AO11-AO99)/AO11 -> 0.23820069 | AT16: =(AT11-AT99)/AT11 -> 0.22257124 | AU16: =(AU11-AU99)/AU11 -> 0.18812305 | AV16: =(AV11-AV99)/AV11 -> 0.15684509 | AW16: =(AW11-AW99)/AW11 -> 0.12296712 | AX16: =(AX11-AX99)/AX11 -> 0.074206711 | AY16: =(AY11-AY99)/AY11 -> 0.037982343
B17: - total growth yo2y | O17: =(1*(1+H14)*(1+O14))-1 -> 2.5469405 | P17: =(1*(1+I14)*(1+P14))-1 -> 2.3517635 | R17: =(1*(1+K14)*(1+R14))-1 -> 3.2866104 | S17: =(1*(1+L14)*(1+S14))-1 -> 2.5193242 | U17: =(1*(1+N14)*(1+U14))-1 -> 2.6640689 | V17: =(1*(1+O14)*(1+V14))-1 -> 3.1782313 | W17: =(1*(1+P14)*(1+W14))-1 -> 2.8758867 | X17: =(1*(1+R14)*(1+X14))-1 -> 1.8693789 | Y17: =(1*(1+S14)*(1+Y14))-1 -> 2.6326296 | Z17: =(1*(1+U14)*(1+Z14))-1 -> 2.5489622 | AA17: =(1*(1+T14)*(1+AA14))-1 -> 2.7432994 | AB17: =(1*(1+U14)*(1+AB14))-1 -> 2.2128137 | AC17: =(1*(1+W14)*(1+AC14))-1 -> 2.3885894 | AD17: =(1*(1+X14)*(1+AD14))-1 -> 0.9500014 | AE17: =(1*(1+Z14)*(1+AE14))-1 -> 1.8383394 | AF17: =(1*(1+Y14)*(1+AF14))-1 -> 1.2144251 | AG17: =(1*(1+Z14)*(1+AG14))-1 -> 1.2503213 | AH17: =(1*(1+AB14)*(1+AH14))-1 -> 1.1895379 | AI17: =(1*(1+AC14)*(1+AI14))-1 -> 1.1434115 | AJ17: =(1*(1+AE14)*(1+AJ14))-1 -> 1.0044685 | AK17: =(1*(1+AD14)*(1+AK14))-1 -> 0.6471947 | AL17: =(1*(1+AE14)*(1+AL14))-1 -> 0.83827542 | AM17: =(1*(1+AG14)*(1+AM14))-1 -> 0.37621761 | AN17: =(1*(1+AH14)*(1+AN14))-1 -> 0.51262761 | AO17: =(1*(1+AJ14)*(1+AO14))-1 -> 0.49711778 | AP17: =(1*(1+AI14)*(1+AP14))-1 -> 0.32041462 | AQ17: =(1*(1+AJ14)*(1+AQ14))-1 -> 0.33052643 | AR17: =(1*(1+AL14)*(1+AR14))-1 -> 0.20954007 | AS17: =(1*(1+AM14)*(1+AS14))-1 -> 0.20359674 | AT17: =(1*(1+AO14)*(1+AT14))-1 -> 0.23488855 | AU17: =(1*(1+AT14)*(1+AU14))-1 -> 0.14925393 | AV17: =(1*(1+AU14)*(1+AV14))-1 -> 0.18150743 | AW17: =(1*(1+AV14)*(1+AW14))-1 -> 0.1664 | AX17: =(1*(1+AW14)*(1+AX14))-1 -> 0.1664 | AY17: =(1*(1+AX14)*(1+AY14))-1 -> 0.1448
B18: APAC | C18: 2.8521384 | D18: 4.164982 | E18: 4.3005595 | F18: 6.54932 | G18: 17.867 | H18: 3.3503464 | I18: 4.1559842 | J18: =I18+H18 -> 7.5063307 | K18: 7.6383264 | L18: 7.8543429 | M18: =L18+K18 -> 15.492669 | N18: 22.999 | O18: =H18*(1+O21) -> 7.3 | P18: =I18*(1+P21) -> 11.7 | Q18: =P18+O18 -> 19 | R18: =K18*(1+R21) -> 13.1 | S18: =L18*(1+S21) -> 10.6 | T18: =S18+R18 -> 23.7 | U18: =T18+Q18 -> 42.7 | V18: =O18*(1+V21) -> 16.4 | W18: =P18*(1+W21) -> 17.916 | X18: =R18*(1+X21) -> 24.246 | Y18: =S18*(1+Y21) -> 21.638 | Z18: =SUM(V18:Y18) -> 80.2 | AA18: =V18*(1+AA21) -> 31.1 | AB18: =W18*(1+AB21) -> 34.1 | AC18: =X18*(1+AC21) -> 41.6 | AD18: =AE18-SUM(AA18:AC18) -> 34.3 | AE18: =Z18*(1+AE21) -> 141.1 | AF18: =AA18*(1+AF21) -> 52.4 | AG18: =AB18*(1+AG21) -> 59.2 | AH18: =AC18*(1+AH21) -> 74.5 | AI18: 74.1 | AJ18: =AE18*(1+AJ21) -> 260.2 | AK18: =AF18*(1+AK21) -> 120.5724 | AL18: =AG18*(1+AL21) -> 119.1696 | AM18: =AH18*(1+AM21) -> 144.9 | AN18: =AO18-SUM(AK18:AM18) -> 126.458 | AO18: =AJ18*(1+AO21) -> 511.1 | AP18: =AK18*(1+AP21) -> 174 | AQ18: =AL18*(1+AQ21) -> 170.5 | AR18: =AM18*(1+AR21) -> 224.595 | AS18: =AT18-SUM(AP18:AR18) -> 207.64518 | AT18: =AO18*(1+AT21) -> 776.74018 | AU18: =AT18*(1+AU21) -> 1104.4606 | AV18: =AU18*(1+AV21) -> 1491.0218 | AW18: =AV18*(1+AW21) -> 1938.3283 | AX18: =AW18*(1+AX21) -> 2422.9104 | AY18: =AX18*(1+AY21) -> 2907.4925
B19: - cFX growth | O19: =((1+O21)/(1+O20))-1 -> 1.1589669 | P19: =((1+P21)/(1+P20))-1 -> 1.711177 | Q19: =((1+Q21)/(1+Q20))-1 -> 1.4685854 | R19: =((1+R21)/(1+R20))-1 -> 0.60670534 | S19: =((1+S21)/(1+S20))-1 -> 0.27957491 | T19: =((1+T21)/(1+T20))-1 -> 0.44183985 | U19: =((1+U21)/(1+U20))-1 -> 0.76928465 | V19: =((1+V21)/(1+V20))-1 -> 1.1594562 | ... AB19: =((1+AB21)/(1+AB20))-1 -> 1.1660207 | AC19: 0.96 | AD19: =((1+AD21)/(1+AD20))-1 -> 0.75997911 | AE19: =((1+AE21)/(1+AE20))-1 -> 0.95998543 | AF19: =((1+AF21)/(1+AF20))-1 -> 0.90698767 | AG19: =((1+AG21)/(1+AG20))-1 -> 0.84702112 | AH19: 0.857 | AI19: =((1+AI21)/(1+AI20))-1 -> 1.2459238 | AJ19: =((1+AJ21)/(1+AJ20))-1 -> 0.95473813 | AK19: =((1+AK21)/(1+AK20))-1 -> 1.2889435 | AL19: =((1+AL21)/(1+AL20))-1 -> 1.1088607 | AM19: =((1+AM21)/(1+AM20))-1 -> 1.0915192 | AN19: =((1+AN21)/(1+AN20))-1 -> 0.8505592 | AO19: =((1+AO21)/(1+AO20))-1 -> 1.0668113 | AP19: 0.614 | AQ19: 0.547 | AR19: 0.5 | AS19: =((1+AS21)/(1+AS20))-1 -> 0.56381814 | AT19: 0.54 | AU19: 0.4 | AV19: 0.35 | AW19: 0.3 | AX19: 0.25 | AY19: 0.2
B20: - ccy/other | O20: =FX!M10 -> 0.0092230296 | P20: =FX!N10 -> 0.038374718 | Q20: =((O20*H18)+(P20*I18))/J18 -> 0.025363267 | R20: =FX!O10 -> 0.067423705 | S20: =FX!P10 -> 0.05470327 | T20: =((R20*K18)+(S20*L18))/M18 -> 0.060974806 | U20: =((O20*H18)+(P20*I18)+(R20*K18)+(S20*L18))/N18 -> 0.04935204 | V20: =FX!R10 -> 0.040343098 | W20: =FX!S10 -> 0.032152842 | X20: =FX!T10 -> -0.0074389247 | Y20: =FX!U10 -> -0.061488498 | Z20: =((V20*O18)+(W20*P18)+(X20*R18)+(Y20*S18))/U18 -> -0.00183923 | AA20: =FX!W10 -> -0.07547043 | AB20: =FX!X10 -> -0.12127959 | AC20: =(((1+0.715)-(1+AC19))) -> -0.245 | AD20: -0.099322134 | AE20: -0.10236495 | AF20: -0.11646652 | AG20: -0.060070097 | AH20: -0.034549929 | AI20: -0.0381019 | AJ20: -0.056609076 | AK20: 0.0052672751 | AL20: -0.045456168 | AM20: -0.07007 | AN20: -0.0778 | AO20: -0.049618951 | AP20: -0.10587588 | AQ20: -0.075155777 | AR20: 0.05 | AS20: 0.05 | AT20: =AVERAGE(AP20:AS20) -> -0.020257913 | AU20: =FX!AQ10/2 -> 0.021917665 | AV20: =FX!AR10 -> 0 | AW20: =FX!AS10 -> 0 | AX20: =FX!AT10 -> 0 | AY20: =FX!AU10 -> 0
B21: - total growth | H21: =H18/C18-1 -> 0.17467876 | I21: =I18/D18-1 -> -0.0021603479 | K21: =K18/E18-1 -> 0.77612387 | L21: =L18/F18-1 -> 0.19926082 | N21: =N18/G18-1 -> 0.28723345 | O21: 1.1788791 | P21: 1.8152176 | Q21: =Q18/J18-1 -> 1.5311968 | R21: 0.71503537 | S21: 0.34957184 | T21: =T18/M18-1 -> 0.52975575 | U21: =U18/N18-1 -> 0.85660246 | V21: 1.2465753 | W21: 0.53128205 | X21: 0.85083969 | Y21: 1.0413208 | Z21: =Z18/U18-1 -> 0.87822014 | AA21: 0.89634146 | AB21: 0.90332664 | AC21: 0.71574693 | AD21: =AD18/Y18-1 -> 0.58517423 | AE21: 0.75935162 | AF21: 0.68488746 | AG21: 0.73607038 | AH21: 0.79086538 | AI21: =AI18/AD18-1 -> 1.1603499 | AJ21: 0.84408221 | AK21: 1.301 | AL21: 1.013 | AM21: 0.94496644 | AN21: =AN18/AI18-1 -> 0.7065857 | AO21: 0.96425826 | AP21: =((1+AP20)*(1+AP19))-1 -> 0.44311634 | AQ21: =((1+AQ20)*(1+AQ19))-1 -> 0.43073401 | AR21: =AR20+AR19 -> 0.55 | AS21: =AS18/AN18-1 -> 0.64200905 | AT21: =AT20+AT19 -> 0.51974209 | AU21: =AU20+AU19 -> 0.42191766 | AV21: =AV20+AV19 -> 0.35 | AW21: =AW20+AW19 -> 0.3 | AX21: =AX20+AX19 -> 0.25 | AY21: =AY20+AY19 -> 0.2
B22: Group sales mix | C22: =C18/C$31 -> 0.057537213 | D22: =D18/D$31 -> 0.059774862 | E22: =E18/E$31 -> 0.066090576 | F22: =F18/F$31 -> 0.079097016 | G22: =G18/G$31 -> 0.066887556 | H22: =H18/H$31 -> 0.046996127 | I22: =I18/I$31 -> 0.041715085 | J22: =J18/J$31 -> 0.04391781 | ... AD22: =AD18/AD$31 -> 0.076716618 | AE22: 0.05 | AF22: =AF18/AF$31 -> 0.10310901 | AG22: =AG18/AG$31 -> 0.10428043 | AH22: =AH18/AH$31 -> 0.11717521 | AI22: =AI18/AI$31 -> 0.12215628 | AJ22: =AJ18/AJ$31 -> 0.11223742 | AK22: =AK18/AK$31 -> 0.16595087 | AL22: =AL18/AL$31 -> 0.15905822 | AM22: =AM18/AM$31 -> 0.18240181 | ... AY22: =AY18/AY$31 -> 0.40590925
B23: APAC DTC % | N23: =(N18-N104)/N18 -> 0.3500587 | U23: =(U18-U104)/U18 -> 0.45301522 | Z23: =(Z18-Z104)/Z18 -> 0.56298767 | AE23: =(AE18-AE104)/AE18 -> 0.64827414 | AJ23: =(AJ18-AJ104)/AJ18 -> 0.74701768 | AO23: =(AO18-AO104)/AO18 -> 0.82967152 | AT23: =(AT18-AT104)/AT18 -> 0.85177787 | AU23: =(AU18-AU104)/AU18 -> 0.86813512 | AV23: =(AV18-AV104)/AV18 -> 0.87643773 | AW23: =(AW18-AW104)/AW18 -> 0.8797644 | AX23: =(AX18-AX104)/AX18 -> 0.88361194 | AY23: =(AY18-AY104)/AY18 -> 0.88264204
B24: - total growth yo2y | O24: =(1*(1+H21)*(1+O21))-1 -> 1.559483 | P24: =(1*(1+I21)*(1+P21))-1 -> 1.8091358 | R24: =(1*(1+K21)*(1+R21))-1 -> 2.0461153 | S24: =(1*(1+L21)*(1+S21))-1 -> 0.61848864 | U24: =(1*(1+N21)*(1+U21))-1 -> 1.3898808 | V24: =(1*(1+O21)*(1+V21))-1 -> 3.8950162 | W24: =(1*(1+P21)*(1+W21))-1 -> 3.3108922 | X24: =(1*(1+R21)*(1+X21))-1 -> 2.1742555 | Y24: =(1*(1+S21)*(1+Y21))-1 -> 1.754909 | Z24: =(1*(1+U21)*(1+Z21))-1 -> 2.4871081 | AA24: =(1*(1+T21)*(1+AA21))-1 -> 1.9009393 | AB24: =(1*(1+U21)*(1+AB21))-1 -> 2.5337209 | AC24: =(1*(1+W21)*(1+AC21))-1 -> 1.6272925 | AD24: =(1*(1+X21)*(1+AD21))-1 -> 1.9339034 | AE24: =(1*(1+Z21)*(1+AE21))-1 -> 2.3044496 | AJ24: =(1*(1+AE21)*(1+AJ21))-1 -> 2.244389 | AO24: =(1*(1+AJ21)*(1+AO21))-1 -> 2.6222537 | AT24: =(1*(1+AO21)*(1+AT21))-1 -> 1.985166 | AU24: =(1*(1+AT21)*(1+AU21))-1 -> 1.1609481 | AV24: =(1*(1+AU21)*(1+AV21))-1 -> 0.91958885 | AW24: =(1*(1+AV21)*(1+AW21))-1 -> 0.755 | AX24: =(1*(1+AW21)*(1+AX21))-1 -> 0.625 | AY24: =(1*(1+AX21)*(1+AY21))-1 -> 0.5
B25: Rest of the World | C25: 1.3894368 | D25: 2.1679348 | E25: 2.133953 | F25: 3.4566754 | G25: 9.148 | H25: 1.0664144 | I25: 0.6032842 | J25: =I25+H25 -> 1.6696986 | K25: 2.2432334 | L25: 2.784068 | M25: =L25+K25 -> 5.0273014 | N25: 6.697 | O25: =H25*(1+O28) -> 1.8 | P25: =I25*(1+P28) -> 2.9 | Q25: =P25+O25 -> 4.7 | R25: =K25*(1+R28) -> 4.4 | S25: =L25*(1+S28) -> 2.9 | T25: =S25+R25 -> 7.3 | U25: =T25+Q25 -> 12 | V25: =O25*(1+V28) -> 6 | W25: =P25*(1+W28) -> 8.78 | X25: =R25*(1+X28) -> 11.039 | Y25: =S25*(1+Y28) -> 23.281 | Z25: =SUM(V25:Y25) -> 49.1
B26: - cFX growth | AO26: =AO18-AJ18 -> 250.9 | AT26: =AT18-AO18 -> 265.64018 | AU26: =AU18-AT18 -> 327.7204 | AV26: =AV18-AU18 -> 386.5612 | AW26: =AW18-AV18 -> 447.30654 | AX26: =AX18-AW18 -> 484.58208 | AY26: =AY18-AX18 -> 484.58208
B27: - ccy
B28: - total growth | H28: =H25/C25-1 -> -0.23248439 | I28: =I25/D25-1 -> -0.72172402 | K28: =K25/E25-1 -> 0.051210313 | L28: =L25/F25-1 -> -0.19458217 | N28: =N25/G25-1 -> -0.26792742 | O28: 0.68789912 | P28: 3.8070213 | Q28: =Q25/J25-1 -> 1.8148792 | R28: 0.9614544 | S28: 0.041641232 | T28: =T25/M25-1 -> 0.45207129 | U28: =U25/N25-1 -> 0.7918471 | V28: 2.3333333 | W28: 2.0275862 | X28: 1.5088636 | Y28: 7.027931 | Z28: =Z25/U25-1 -> 3.0916667
B29: Sales mix | C29: =C25/C$31 -> 0.028029608 | D29: =D25/D$31 -> 0.031113701 | E29: =E25/E$31 -> 0.03279438 | F29: =F25/F$31 -> 0.041746732 | G29: =G25/G$31 -> 0.034246788 | H29: =H25/H$31 -> 0.014958856 | I29: =I25/I$31 -> 0.006055377 | J29: =J25/J$31 -> 0.0097690217 | ... Z29: =Z25/Z$31 -> 0.040176745
B30: - total growth yo2y | O30: =(1*(1+H28)*(1+O28))-1 -> 0.29548893 | P30: =(1*(1+I28)*(1+P28))-1 -> 0.33767858 | R30: =(1*(1+K28)*(1+R28))-1 -> 1.0619011 | S30: =(1*(1+L28)*(1+S28))-1 -> -0.16104358 | U30: =(1*(1+N28)*(1+U28))-1 -> 0.31176213 | V30: =(1*(1+O28)*(1+V28))-1 -> 4.6263304 | W30: =(1*(1+P28)*(1+W28))-1 -> 13.553671 | X30: =(1*(1+R28)*(1+X28))-1 -> 3.9210216 | Y30: =(1*(1+S28)*(1+Y28))-1 -> 7.362224 | Z30: =(1*(1+U28)*(1+Z28))-1 -> 6.331641
B31: Total | C31: =C25+C18+C11+C4 -> 49.570327 | D31: =D25+D18+D11+D4 -> 69.67782 | E31: =E25+E18+E11+E4 -> 65.070692 | F31: =F25+F18+F11+F4 -> 82.801101 | G31: =G25+G18+G11+G4 -> 267.11994 | H31: =H25+H18+H11+H4 -> 71.289841 | I31: =I25+I18+I11+I4 -> 99.627851 | J31: =I31+H31 -> 170.91769 | K31: =K25+K18+K11+K4 -> 130.07734 | L31: =L25+L18+L11+L4 -> 124.30021 | M31: =L31+K31 -> 254.37755 | N31: =N25+N18+N11+N4 -> 425.29524 | O31: =O25+O18+O11+O4 -> 140.4 | P31: =P25+P18+P11+P4 -> 175.1 | Q31: =P31+O31 -> 315.5 | R31: =R25+R18+R11+R4 -> 218 | S31: =S25+S18+S11+S4 -> 191.1 | T31: =S31+R31 -> 409.1 | U31: =U25+U18+U11+U4 -> 724.6 | V31: =V25+V18+V11+V4 -> 235.7 | W31: =W25+W18+W11+W4 -> 291.662 | X31: =X25+X18+X11+X4 -> 328.013 | Y31: =Y25+Y18+Y11+Y4 -> 366.725 | Z31: =Z25+Z18+Z11+Z4 -> 1222.1 | AA31: =AA25+AA18+AA11+AA4 -> 420.2 | AB31: =AB25+AB18+AB11+AB4 -> 444.3 | AC31: =AC25+AC18+AC11+AC4 -> 480.5 | AD31: =AE31-SUM(AA31:AC31) -> 447.1 | AE31: =AE25+AE18+AE11+AE4 -> 1792.1 | AF31: =AF25+AF18+AF11+AF4 -> 508.2 | AG31: =AG25+AG18+AG11+AG4 -> 567.7 | AH31: =AH25+AH18+AH11+AH4 -> 635.8 | AI31: =AJ31-SUM(AF31:AH31) -> 606.6 | AJ31: =AJ25+AJ18+AJ11+AJ4 -> 2318.3 | AK31: =AK25+AK18+AK11+AK4 -> 726.5548 | AL31: =AL25+AL18+AL11+AL4 -> 749.22 | AM31: =AM25+AM18+AM11+AM4 -> 794.4 | AN31: =AO31-SUM(AK31:AM31) -> 743.8252 | AO31: =AO25+AO18+AO11+AO4 -> 3014 | AP31: =AP25+AP18+AP11+AP4 -> 831.9 | AQ31: =AQ25+AQ18+AQ11+AQ4 -> 850.3 | AR31: =AR25+AR18+AR11+AR4 -> 917.05863 | AS31: =AT31-SUM(AP31:AR31) -> 902.86715 | AT31: =AT25+AT18+AT11+AT4 -> 3502.1258 | AU31: =AU25+AU18+AU11+AU4 -> 4158.5242 | AV31: =AV25+AV18+AV11+AV4 -> 4842.1171 | AW31: =AW25+AW18+AW11+AW4 -> 5605.1581 | AX31: =AX25+AX18+AX11+AX4 -> 6409.7687 | AY31: =AY25+AY18+AY11+AY4 -> 7162.9127
B32: - cFX growth | O32: =((1+O34)/(1+O33))-1 -> 1.0908354 | P32: =((1+P34)/(1+P33))-1 -> 0.84611658 | Q32: =((1+Q34)/(1+Q33))-1 -> 0.94755564 | R32: =((1+R34)/(1+R33))-1 -> 0.68237721 | S32: =((1+S34)/(1+S33))-1 -> 0.48905633 | T32: =((1+T34)/(1+T33))-1 -> 0.58618233 | U32: =((1+U34)/(1+U33))-1 -> 0.7259124 | V32: =((1+V34)/(1+V33))-1 -> 0.61883479 | ... AC32: =((1+AC34)/(1+AC33))-1 -> 0.65417808 | AD32: 0.31 | AE32: 0.55 | AF32: =((1+AF34)/(1+AF33))-1 -> 0.29170745 | AG32: =((1+AG34)/(1+AG33))-1 -> 0.29404278 | AH32: =((1+AH34)/(1+AH33))-1 -> 0.3317938 | AI32: =((1+AI34)/(1+AI33))-1 -> 0.40627971 | AJ32: 0.332 | AK32: =((1+AK34)/(1+AK33))-1 -> 0.40031831 | AL32: =((1+AL34)/(1+AL33))-1 -> 0.38204002 | AM32: =((1+AM34)/(1+AM33))-1 -> 0.34549598 | AN32: =((1+AN34)/(1+AN33))-1 -> 0.30493637 | AO32: =((1+AO34)/(1+AO33))-1 -> 0.35544157 | AP32: =((AP5*AK4)+(AP12*AK11)+(AP19*AK18))/(AK4+AK11+AK18) -> 0.26424121 | AQ32: =((AQ5*AL4)+(AQ12*AL11)+(AQ19*AL18))/(AL4+AL11+AL18) -> 0.21612523 | AR32: =((AR5*AM4)+(AR12*AM11)+(AR19*AM18))/(AM4+AM11+AM18) -> 0.17003399 | AS32: =((AS5*AN4)+(AS12*AN11)+(AS19*AN18))/(AN4+AN11+AN18) -> 0.19596488 | AT32: =((AT5*AO4)+(AT12*AO11)+(AT19*AO18))/(AO4+AO11+AO18) -> 0.20316158 | AU32: =((AU5*AT4)+(AU12*AT11)+(AU19*AT18))/(AT4+AT11+AT18) -> 0.17925192 | AV32: =((AV5*AU4)+(AV12*AU11)+(AV19*AU18))/(AU4+AU11+AU18) -> 0.17198814 | AW32: =((AW5*AV4)+(AW12*AV11)+(AW19*AV18))/(AV4+AV11+AV18) -> 0.1649642 | AX32: =((AX5*AW4)+(AX12*AW11)+(AX19*AW18))/(AW4+AW11+AW18) -> 0.14830855 | AY32: =((AY5*AX4)+(AY12*AX11)+(AY19*AX18))/(AX4+AX11+AX18) -> 0.12207841
B33: - ccy | O33: =((O6*H4)+(O13*H11)+(O20*H18))/(H4+H11+H18) -> -0.058067886 | P33: =((P6*I4)+(P13*I11)+(P20*I18))/(I4+I11+I18) -> -0.047979583 | Q33: =Q133 -> -0.052187419 | R33: =((R6*K4)+(R13*K11)+(R20*K18))/(K4+K11+K18) -> -0.0038345909 | S33: =((S6*L4)+(S13*L11)+(S20*L18))/(L4+L11+L18) -> 0.032470616 | T33: =T133 -> 0.013905751 | U33: =((U6*N4)+(U13*N11)+(U20*N18))/(N4+N11+N18) -> -0.012836583 | V33: =((V6*O4)+(V13*O11)+(V20*O18))/(O4+O11+O18) -> 0.037026718 | W33: =((W6*P4)+(W13*P11)+(W20*P18))/(P4+P11+P18) -> 0.058619106 | X33: =((X6*R4)+(X13*R11)+(X20*R18))/(R4+R11+R18) -> 0.055700904 | Y33: =((Y6*S4)+(Y13*S11)+(Y20*S18))/(S4+S11+S18) -> 0.035362387 | Z33: =((Z6*U4)+(Z13*U11)+(Z20*U18))/(U4+U11+U18) -> 0.047402509 | AA33: =((AA6*V4)+(AA13*V11)+(AA20*V18))/(V4+V11+V18) -> 0.0056521414 | AB33: =((AB6*W4)+(AB13*W11)+(AB20*W18))/(W4+W11+W18) -> -0.050584258 | AC33: =((AC6*X4)+(AC13*X11)+(AC20*X18))/(X4+X11+X18) -> -0.11443575 | AD33: =((AD34+1)/(1+AD32))-1 -> -0.069336124 | AE33: =((AE34+1)/(1+AE32))-1 -> -0.053928853 | AF33: -0.063701241 | AG33: -0.012598129 | AH33: -0.00644905 | AI33: =((AI6*AD4)+(AI13*AD11)+(AI20*AD18))/(AD4+AD11+AD18) -> -0.035225036 | AJ33: =((AJ34+1)/(1+AJ32))-1 -> -0.028812307 | AK33: 0.020955815 | AL33: -0.045073716 | AM33: =((AM6*AH4)+(AM13*AH11)+(AM20*AH18))/(AH4+AH11+AH18) -> -0.071383688 | AN33: =((AN6*AI4)+(AN13*AI11)+(AN20*AI18))/(AI4+AI11+AI18) -> -0.060321813 | AO33: =((AO6*AJ4)+(AO13*AJ11)+(AO20*AJ18))/(AJ4+AJ11+AJ18) -> -0.04083613 | AP33: =AP34-AP32 -> -0.11924843 | AQ33: =AQ34-AQ32 -> -0.081211584 | AR33: =AR34-AR32 -> -0.015629866 | AS33: =AS34-AS32 -> 0.017851424 | AT33: =AT34-AT32 -> -0.041208763 | AU33: =AU34-AU32 -> 0.0081766543 | AV33: =AV34-AV32 -> -0.007604611 | AW33: =AW34-AW32 -> -0.0073800515 | ... AY33: =AY34-AY32 -> -0.0045790119
B34: - total growth | H34: =H31/C31-1 -> 0.43815557 | I34: =I31/D31-1 -> 0.42983594 | K34: =K31/E31-1 -> 0.99901583 | L34: =L31/F31-1 -> 0.50119029 | N34: =N31/G31-1 -> 0.59215087 | O34: =O31/H31-1 -> 0.96942506 | P34: =P31/I31-1 -> 0.75754068 | Q34: =Q31/J31-1 -> 0.84591774 | R34: =R31/K31-1 -> 0.67592599 | S34: =S31/L31-1 -> 0.5374069 | T34: =T31/M31-1 -> 0.60823939 | U34: =U31/N31-1 -> 0.70375759 | ... W34: =W31/P31-1 -> 0.66568818 | X34: =X31/R31-1 -> 0.50464679 | Y34: =Y31/S31-1 -> 0.91902145 | Z34: =Z31/U31-1 -> 0.6865857 | AA34: =AA31/V31-1 -> 0.78277471 | AB34: =AB31/W31-1 -> 0.52333866 | AC34: =AC31/X31-1 -> 0.46488097 | AD34: =AD31/Y31-1 -> 0.21916968 | AE34: =AE31/Z31-1 -> 0.46641028 | AF34: =AF31/AA31-1 -> 0.20942408 | AG34: =AG31/AB31-1 -> 0.27774027 | ... AT34: =AT31/AO31-1 -> 0.16195282 | AU34: =AU31/AT31-1 -> 0.18742858 | AV34: =AV31/AU31-1 -> 0.16438353 | AW34: =AW31/AV31-1 -> 0.15758415 | AX34: =AX31/AW31-1 -> 0.14354825 | AY34: =AY31/AX31-1 -> 0.1174994
B35: - total growth yo2y | O35: =(1*(1+H34)*(1+O34))-1 -> 1.8323396 | P35: =(1*(1+I34)*(1+P34))-1 -> 1.5129948 | R35: =(1*(1+K34)*(1+R34))-1 -> 2.3502026 | S35: =(1*(1+L34)*(1+S34))-1 -> 1.3079403 | U35: =(1*(1+N34)*(1+U34))-1 -> 1.7126391 | V35: =(1*(1+O34)*(1+V34))-1 -> 2.3062214 | W35: =(1*(1+P34)*(1+W34))-1 -> 1.9275147 | X35: =(1*(1+R34)*(1+X34))-1 -> 1.5216767 | Y35: =(1*(1+S34)*(1+Y34))-1 -> 1.9503168 | Z35: =(1*(1+U34)*(1+Z34))-1 -> 1.8735332 | AA35: =(1*(1+T34)*(1+AA34))-1 -> 1.8671285 | AB35: =(1*(1+U34)*(1+AB34))-1 -> 1.5953998 | AC35: =(1*(1+W34)*(1+AC34))-1 -> 1.4400349 | AD35: =(1*(1+X34)*(1+AD34))-1 -> 0.83441974 | AE35: =(1*(1+Z34)*(1+AE34))-1 -> 1.4732266 | AJ35: =(1*(1+AE34)*(1+AJ34))-1 -> 0.89698061 | AO35: =(1*(1+AJ34)*(1+AO34))-1 -> 0.68182579 | AT35: =(1*(1+AO34)*(1+AT34))-1 -> 0.51064391 | AU35: =(1*(1+AT34)*(1+AU34))-1 -> 0.37973598 | AV35: =(1*(1+AU34)*(1+AV34))-1 -> 0.38262228 | AW35: =(1*(1+AV34)*(1+AW34))-1 -> 0.34787192 | AX35: =(1*(1+AW34)*(1+AX34))-1 -> 0.32375334 | AY35: =(1*(1+AX34)*(1+AY34))-1 -> 0.27791449
B37: Sales by Product
B38: Shoes | C38: 46.347513 | D38: 67.031732 | E38: 61.496701 | F38: 80.735853 | G38: 255.6118 | H38: 66.729297 | I38: 94.970091 | J38: =I38+H38 -> 161.69939 | K38: 124.07351 | L38: 120.6174 | M38: =L38+K38 -> 244.69091 | N38: 406.3903 | O38: =H38*(1+O41) -> 131.7 | P38: =P53-P43-P48 -> 165.3 | Q38: =P38+O38 -> 297 | R38: =K38*(1+R41) -> 205 | S38: =L38*(1+S41) -> 181.3 | T38: =S38+R38 -> 386.3 | U38: =T38+Q38 -> 683.3 | V38: =O38*(1+V41) -> 222.5 | W38: =P38*(1+W41) -> 280.621 | X38: =R38*(1+X41) -> 310.892 | Y38: =S38*(1+Y41) -> 353.487 | Z38: =SUM(V38:Y38) -> 1167.5 | AA38: =V38*(1+AA41) -> 400.5 | AB38: =W38*(1+AB41) -> 428.2 | AC38: =X38*(1+AC41) -> 456.9 | AD38: =Y38*(1+AD41) -> 425.8 | AE38: =SUM(AA38:AD38) -> 1711.4 | AF38: =AA38*(1+AF41) -> 484.7 | AG38: 542.5 | AH38: 603.7 | AI38: =AJ38-AH38-AG38-AF38 -> 568.7 | AJ38: =AE38*(1+AJ41) -> 2199.6 | AK38: 680.9 | AL38: 704.9 | AM38: 731.3 | AN38: =AO38-AM38-AL38-AK38 -> 687.3 | AO38: =AJ38*(1+AO41) -> 2804.4 | AP38: =AK38*(1+AP41) -> 763.7 | AQ38: =AL38*(1+AQ41) -> 781.6 | AR38: =AM38*(1+AR41) -> 871.04255 | AS38: =AT38-AR38-AQ38-AP38 -> 765.19116 | AT38: =AT42*AT31 -> 3181.5337 | AU38: =AU42*AU31 -> 3694.6736 | AV38: =AV42*AV31 -> 4205.1747 | AW38: =AW42*AW31 -> 4755.7404 | AX38: =AX42*AX31 -> 5310.2233 | AY38: =AY42*AY31 -> 5790.9131
B39: - cFX growth | AG39: 0.282 | AH39: 0.329 | AI39: 0.385 | AJ39: 0.323 | AK39: =((1+AK41)/(1+AK40))-1 -> 0.3753329 | AL39: =((1+AL41)/(1+AL40))-1 -> 0.36004126 | AM39: =((1+AM41)/(1+AM40))-1 -> 0.30440926 | AN39: 0.288 | AO39: 0.329 | AP39: 0.24 | AQ39: 0.189 | AR39: 0.21 | AS39: =AS41-AS55 -> 0.095477772
B40: - ccy | AG40: =AG41-AG39 -> -0.01506866 | AH40: =AH41-AH39 -> -0.0077043117 | AI40: =AI41-AI39 -> -0.04939643 | AJ40: =AJ41-AJ39 -> -0.037736473 | AK40: 0.02141559 | AL40: -0.044621014 | AM40: -0.071331909 | AN40: =AN41-AN39 -> -0.079454194 | AO40: =AO41-AO39 -> -0.054040917 | AP40: -0.095480839 | AQ40: -0.067443431 | AR40: =AR133 -> -0.015629866 | AS40: =AS41-AS39 -> 0.017851424
B41: - total growth | H41: =H38/C38-1 -> 0.43976003 | I41: =I38/D38-1 -> 0.41679304 | K41: =K38/E38-1 -> 1.0175636 | L41: =L38/F38-1 -> 0.4939757 | N41: =N38/G38-1 -> 0.58987299 | O41: 0.97364585 | P41: =P38/I38-1 -> 0.74054797 | Q41: =Q38/J38-1 -> 0.83674164 | R41: 0.65224637 | S41: 0.50309985 | T41: 0.445 | U41: =U38/N38-1 -> 0.68138857 | V41: 0.68944571 | W41: 0.6976467 | X41: 0.51654634 | Y41: 0.94973525 | Z41: =Z38/U38-1 -> 0.70861993 | AA41: 0.8 | AB41: 0.52590148 | AC41: 0.46964219 | AD41: 0.20457047 | AE41: =AE38/Z38-1 -> 0.46586724 | AF41: 0.2102372 | AG41: =AG38/AB38-1 -> 0.26693134 | AH41: =AH38/AC38-1 -> 0.32129569 | AI41: =AI38/AD38-1 -> 0.33560357 | AJ41: 0.28526353 | AK41: =AK38/AF38-1 -> 0.40478647 | AL41: =AL38/AG38-1 -> 0.29935484 | AM41: =AM38/AH38-1 -> 0.21136326 | AN41: =AN38/AI38-1 -> 0.20854581 | AO41: 0.27495908 | AP41: =((1+AP40)*(1+AP39))-1 -> 0.12160376 | AQ41: =((1+AQ40)*(1+AQ39))-1 -> 0.10880976 | AR41: =((1+AR40)*(1+AR39))-1 -> 0.19108786 | AS41: =AS38/AN38-1 -> 0.1133292 | AT41: =AT38/AO38-1 -> 0.13447929 | AU41: =AU38/AT38-1 -> 0.16128694 | AV41: =AV38/AU38-1 -> 0.13817219 | AW41: =AW38/AV38-1 -> 0.13092577 | AX41: =AX38/AW38-1 -> 0.11659233 | AY41: =AY38/AX38-1 -> 0.09052158
B42: Sales mix | C42: =C38/C$53 -> 0.93498503 | D42: =D38/D$53 -> 0.96202396 | E42: =E38/E$53 -> 0.94507526 | F42: =F38/F$53 -> 0.97505772 | G42: =G38/G$53 -> 0.9569177 | H42: =H38/H$53 -> 0.93602813 | I42: =I38/I$53 -> 0.95324842 | K42: =K38/K$53 -> 0.95384409 | L42: =L38/L$53 -> 0.97037168 | N42: =N38/N$53 -> 0.95554865 | O42: =O38/O$53 -> 0.93803419 | P42: =P38/P$53 -> 0.94403198 | Q42: =Q38/Q$53 -> 0.94136292 | R42: =R38/R$53 -> 0.94036697 | S42: =S38/S$53 -> 0.94871795 | T42: =T38/T$53 -> 0.94426791 | U42: =U38/U$53 -> 0.94300304 | ... AS42: =AS38/AS$53 -> 0.84751245 | AT42: =AO42-0.022 -> 0.90845786 | AU42: =AT42-0.02 -> 0.88845786 | AV42: =AU42-0.02 -> 0.86845786 | AW42: =AV42-0.02 -> 0.84845786 | AX42: =AW42-0.02 -> 0.82845786 | AY42: =AX42-0.02 -> 0.80845786
B43: Apparel | C43: 2.7473304 | D43: 2.1792266 | E43: 3.0092065 | F43: 1.6340035 | G43: 9.5697669 | H43: 3.8620094 | I43: 3.7889126 | J43: =I43+H43 -> 7.6509221 | K43: 4.9389167 | L43: 3.1602187 | M43: =L43+K43 -> 8.0991354 | N43: 15.750058 | O43: =H43*(1+O46) -> 7.8 | P43: =I43*(1+P46) -> 8.8 | Q43: =P43+O43 -> 16.6 | R43: =K43*(1+R46) -> 11.5 | S43: =L43*(1+S46) -> 8.2 | T43: =S43+R43 -> 19.7 | U43: =T43+Q43 -> 36.3 | V43: =O43*(1+V46) -> 11.4 | W43: =P43*(1+W46) -> 9.204 | X43: =R43*(1+X46) -> 15.234 | Y43: =S43*(1+Y46) -> 11.462 | Z43: =SUM(V43:Y43) -> 47.3 | AA43: =V43*(1+AA46) -> 16.9 | AB43: =W43*(1+AB46) -> 13.4 | AC43: =X43*(1+AC46) -> 20.1 | AD43: =Y43*(1+AD46) -> 18.5 | AE43: =SUM(AA43:AD43) -> 68.9 | AF43: =AA43*(1+AF46) -> 19.7 | AG43: 21.9 | AH43: 26.8 | AI43: =AJ43-AH43-AG43-AF43 -> 32.6 | AJ43: =AE43*(1+AJ46) -> 101 | AK43: =AF43*(1+AK46) -> 38.1 | AL43: 36.7 | AM43: 50.1 | AN43: =AO43-AM43-AL43-AK43 -> 45 | AO43: =AJ43*(1+AO46) -> 169.9 | AP43: =AK43*(1+AP46) -> 55.3 | AQ43: =AL43*(1+AQ46) -> 54.2 | AR43: =AM43*(1+AR46) -> 73.975416 | AS43: =AT43-AR43-AQ43-AP43 -> 59.481584 | AT43: =AO43*(1+AT46) -> 242.957 | AU43: =AU53-AU48-AU38 -> 400.75811 | AV43: =AV53-AV48-AV38 -> 558.63637 | AW43: =AW53-AW48-AW38 -> 753.16661 | AX43: =AX53-AX48-AX38 -> 983.06797 | AY43: =AY53-AY48-AY38 -> 1234.6732
B44: - cFX growth | AG44: 0.666 | AH44: 0.347 | AI44: 0.825 | AJ44: 0.514 | AK44: =((1+AK46)/(1+AK45))-1 -> 0.91002667 | AL44: =((1+AL46)/(1+AL45))-1 -> 0.75539095 | AM44: =((1+AM46)/(1+AM45))-1 -> 1.0022206 | AN44: 0.46 | AO44: 0.755 | AP44: 0.575 | AQ44: 0.562 | AR44: 0.5 | AS44: =AS46-AS55 -> 0.30396156
B45: - ccy | AG45: =AG46-AG44 -> -0.031671642 | AH45: =AH46-AH44 -> -0.013666667 | AI45: =AI46-AI44 -> -0.062837838 | AJ45: =AJ46-AJ44 -> -0.048107402 | AK45: 0.012556623 | AL45: -0.045796608 | AM45: -0.066335153 | AN45: =AN46-AN44 -> -0.079631902 | AO45: =AO46-AO44 -> -0.072821782 | AP45: -0.078448527 | AQ45: -0.054520335 | AR45: =AR40 -> -0.015629866 | AS45: =AS46-AS44 -> 0.017851424
B46: - total growth | H46: =H43/C43-1 -> 0.4057317 | I46: =I43/D43-1 -> 0.73865016 | K46: =K43/E43-1 -> 0.64126882 | L46: =L43/F43-1 -> 0.93403426 | N46: =N43/G43-1 -> 0.64581412 | O46: 1.019674 | P46: 1.3225661 | Q46: =Q43/J43-1 -> 1.1696731 | R46: 1.3284458 | S46: 1.5947571 | T46: =T43/M43-1 -> 1.4323584 | U46: =U43/N43-1 -> 1.3047535 | V46: 0.46153846 | W46: 0.045909091 | X46: 0.32469565 | Y46: 0.39780488 | Z46: =Z43/U43-1 -> 0.3030303 | AA46: 0.48245614 | AB46: 0.45588874 | AC46: 0.31941709 | AD46: 0.61402897 | AE46: =AE43/Z43-1 -> 0.45665962 | AF46: 0.16568047 | AG46: =AG43/AB43-1 -> 0.63432836 | AH46: =AH43/AC43-1 -> 0.33333333 | AI46: =AI43/AD43-1 -> 0.76216216 | AJ46: 0.4658926 | AK46: 0.93401015 | AL46: 0.675 | AM46: =AM43/AH43-1 -> 0.86940299 | AN46: =AN43/AI43-1 -> 0.3803681 | AO46: 0.68217822 | AP46: =((1+AP45)*(1+AP44))-1 -> 0.45144357 | AQ46: =((1+AQ45)*(1+AQ44))-1 -> 0.47683924 | AR46: =((1+AR45)*(1+AR44))-1 -> 0.4765552 | AS46: =AS43/AN43-1 -> 0.32181299 | AT46: 0.43 | AU46: =AU43/AT43-1 -> 0.64950223 | AV46: =AV43/AU43-1 -> 0.393949 | AW46: =AW43/AV43-1 -> 0.34822338 | AX46: =AX43/AW43-1 -> 0.30524635 | AY46: =AY43/AX43-1 -> 0.2559388
B47: Sales mix | C47: =C43/C$53 -> 0.055422883 | D47: =D43/D$53 -> 0.031275757 | E47: =E43/E$53 -> 0.046245189 | F47: =F43/F$53 -> 0.019734079 | G47: =G43/G$53 -> 0.03582573 | H47: =H43/H$53 -> 0.054173348 | I47: =I43/I$53 -> 0.038030657 | K47: =K43/K$53 -> 0.037969078 | L47: =L43/L$53 -> 0.025424082 | N47: =N43/N$53 -> 0.037033232 | O47: =O43/O$53 -> 0.055555556 | P47: =P43/P$53 -> 0.050256996 | Q47: =Q43/Q$53 -> 0.052614897 | R47: =R43/R$53 -> 0.052752294 | S47: =S43/S$53 -> 0.042909471 | T47: =T43/T$53 -> 0.048154485 | U47: =U43/U$53 -> 0.050096605 | ... AY47: =AY43/AY$53 -> 0.17237027
B48: Accessories | C48: 0.47548311 | D48: 0.46686093 | E48: 0.56478437 | F48: 0.43124487 | G48: 1.9383733 | H48: 0.69853505 | I48: 0.86884669 | J48: =I48+H48 -> 1.5673817 | K48: 1.0649208 | L48: 0.5225881 | M48: =L48+K48 -> 1.5875089 | N48: 3.1548906 | O48: =O53-O43-O38 -> 0.9 | P48: 1 | Q48: =P48+O48 -> 1.9 | R48: =R53-R43-R38 -> 1.5 | S48: =S53-S43-S38 -> 1.6 | T48: =S48+R48 -> 3.1 | U48: =U53-U43-U38 -> 5 | V48: =V53-V43-V38 -> 1.8 | W48: =W53-W43-W38 -> 1.837 | X48: =X53-X43-X38 -> 1.887 | Y48: =Y53-Y43-Y38 -> 1.776 | Z48: =Z53-Z43-Z38 -> 7.3 | AA48: =AA53-AA43-AA38 -> 2.8 | AB48: =AB53-AB43-AB38 -> 2.7 | ... AG48: =AG53-AG43-AG38 -> 3.3 | AH48: 5.3 | AI48: =AJ48-AH48-AG48-AF48 -> 5.3 | AJ48: =AJ53-AJ43-AJ38 -> 17.7 | AK48: =AK53-AK43-AK38 -> 7.5548 | AL48: 7.7 | AM48: 13 | AN48: =AO48-AM48-AL48-AK48 -> 11.4452 | AO48: =AO53-AO43-AO38 -> 39.7 | AP48: =AP53-AP43-AP38 -> 12.9 | AQ48: =AQ53-AQ43-AQ38 -> 14.5 | AR48: =AR53-AR43-AR38 -> -27.959335 | AS48: =AT48-AR48-AQ48-AP48 -> 78.194412 | AT48: =AT53-AT43-AT38 -> 77.635078 | AU48: =AU52*AU31 -> 63.092567 | AV48: =AV52*AV31 -> 78.306063 | AW48: =AW52*AW31 -> 96.251015 | AX48: =AX52*AX31 -> 116.47745 | AY48: =AY52*AY31 -> 137.32639
B49: - cFX growth | AG49: 0.263 | AH49: 0.562 | AI49: 0.856 | AJ49: 0.543 | AK49: =((1+AK51)/(1+AK50))-1 -> 0.97001244 | AL49: =((1+AL51)/(1+AL50))-1 -> 1.4321078 | AM49: =((1+AM51)/(1+AM50))-1 -> 1.6082676 | AN49: 1.313 | AO49: 1.351 | AP49: =((1+AP51)/(1+AP50))-1 -> 0.86579129 | AQ49: =((1+AQ51)/(1+AQ50))-1 -> 1.021408 | AR49: =((1+AR51)/(1+AR50))-1 -> -3.1848672 | AS49: =AS51-AS55 -> 5.814219
B50: - ccy | AG50: =AG51-AG49 -> -0.040777778 | AH50: =AH51-AH49 -> -0.047714286 | AI50: =AI51-AI49 -> 0.036857143 | AJ50: =AJ51-AJ49 -> -0.043 | AK50: 0.0091841153 | AL50: -0.0406127 | AM50: -0.059594127 | AN50: =AN51-AN49 -> -0.1535283 | AO50: =AO51-AO49 -> -0.10806215 | AP50: -0.084825992 | AQ50: -0.068413275 | AR50: =AR40 -> -0.015629866 | AS50: =AS51-AS49 -> 0.017851424
B51: - total growth | H51: =H48/C48-1 -> 0.46910592 | I51: =I48/D48-1 -> 0.86103962 | K51: =K48/E48-1 -> 0.8855352 | L51: =L48/F48-1 -> 0.21181291 | N51: =N48/G48-1 -> 0.62759706 | O51: =O48/H48-1 -> 0.28841065 | P51: =P48/I48-1 -> 0.15095104 | Q51: =Q48/J48-1 -> 0.21221267 | R51: 0.35 | S51: 2 | T51: =T48/M48-1 -> 0.95274495 | U51: =U48/N48-1 -> 0.58484098 | V51: 0.5 | W51: 0.4 | X51: 0.65 | Y51: 0.4 | Z51: =Z48/U48-1 -> 0.46 | AA51: =AA48/V48-1 -> 0.55555556 | AB51: =AB48/W48-1 -> 0.4697877 | AC51: =AC48/X48-1 -> 0.85479597 | AD51: =AD48/Y48-1 -> 0.57657658 | AE51: =AE48/Z48-1 -> 0.61643836 | AF51: =AF48/AA48-1 -> 0.35714286 | AG51: =AG48/AB48-1 -> 0.22222222 | ... AT51: =AT48/AO48-1 -> 0.95554352 | AU51: =AU48/AT48-1 -> -0.18731882 | AV51: =AV48/AU48-1 -> 0.24112977 | AW51: =AW48/AV48-1 -> 0.22916428 | AX51: =AX48/AW48-1 -> 0.21014255 | AY51: =AY48/AX48-1 -> 0.17899553
B52: Sales mix | C52: =C48/C$53 -> 0.0095920915 | D52: =D48/D$53 -> 0.0067002804 | E52: =E48/E$53 -> 0.0086795507 | F52: =F48/F$53 -> 0.0052082021 | G52: =G48/G$53 -> 0.0072565653 | H52: =H48/H$53 -> 0.0097985216 | I52: =I48/I$53 -> 0.0087209218 | K52: =K48/K$53 -> 0.0081868278 | L52: =L48/L$53 -> 0.0042042415 | N52: =N48/N$53 -> 0.0074181188 | O52: =O48/O$53 -> 0.0064102564 | P52: =P48/P$53 -> 0.0057110223 | Q52: =Q48/Q$53 -> 0.006022187 | R52: =R48/R$53 -> 0.0068807339 | S52: =S48/S$53 -> 0.0083725798 | T52: =T48/T$53 -> 0.0075776094 | U52: =U48/U$53 -> 0.0069003588 | ... AO52: =AO48/AO$53 -> 0.013171865 | AP52: =AK52+0.001 -> 0.011398114 | AQ52: =AL52+0.001 -> 0.011277355 | AR52: =AM52+0.001 -> 0.017364552 | AS52: =AS48/AS$53 -> 0.086606775 | AT52: =AO52+0.001 -> 0.014171865 | AU52: =AT52+0.001 -> 0.015171865 | AV52: =AU52+0.001 -> 0.016171865 | AW52: =AV52+0.001 -> 0.017171865 | AX52: =AW52+0.001 -> 0.018171865 | AY52: =AX52+0.001 -> 0.019171865
B53: Group | C53: =C48+C43+C38 -> 49.570327 | D53: =D48+D43+D38 -> 69.67782 | E53: =E48+E43+E38 -> 65.070692 | F53: =F48+F43+F38 -> 82.801101 | G53: =G48+G43+G38 -> 267.11994 | H53: =H48+H43+H38 -> 71.289841 | I53: =I48+I43+I38 -> 99.627851 | J53: =I53+H53 -> 170.91769 | K53: =K48+K43+K38 -> 130.07734 | L53: =L48+L43+L38 -> 124.30021 | M53: =L53+K53 -> 254.37755 | N53: =N48+N43+N38 -> 425.29524 | O53: =O31 -> 140.4 | P53: =P31 -> 175.1 | Q53: =P53+O53 -> 315.5 | R53: =R31 -> 218 | S53: =S31 -> 191.1 | T53: =S53+R53 -> 409.1 | U53: =U31 -> 724.6 | V53: =V31 -> 235.7 | W53: =W31 -> 291.662 | X53: =X31 -> 328.013 | Y53: =Y31 -> 366.725 | Z53: =Z31 -> 1222.1 | AA53: =AA31 -> 420.2 | AB53: =AB31 -> 444.3 | ... AY53: =AY31 -> 7162.9127
B54: - cFX growth | O54: =((1+O56)/(1+O55))-1 -> 1.0908354 | P54: =((1+P56)/(1+P55))-1 -> 0.84611658 | Q54: =((1+Q56)/(1+Q55))-1 -> 0.94755564 | R54: =((1+R56)/(1+R55))-1 -> 0.68237721 | S54: =((1+S56)/(1+S55))-1 -> 0.48905633 | T54: =((1+T56)/(1+T55))-1 -> 0.58618233 | U54: =((1+U56)/(1+U55))-1 -> 0.7259124 | V54: =((1+V56)/(1+V55))-1 -> 0.61883479 | ... AY54: =((1+AY56)/(1+AY55))-1 -> 0.12263998
B55: - ccy | O55: =O33 -> -0.058067886 | P55: =P33 -> -0.047979583 | Q55: =Q33 -> -0.052187419 | R55: =R33 -> -0.0038345909 | S55: =S33 -> 0.032470616 | T55: =T33 -> 0.013905751 | U55: =U33 -> -0.012836583 | V55: =V33 -> 0.037026718 | ... AY55: =AY33 -> -0.0045790119
B56: - total growth | H56: =H53/C53-1 -> 0.43815557 | I56: =I53/D53-1 -> 0.42983594 | K56: =K53/E53-1 -> 0.99901583 | L56: =L53/F53-1 -> 0.50119029 | N56: =N53/G53-1 -> 0.59215087 | O56: =O53/H53-1 -> 0.96942506 | P56: =P53/I53-1 -> 0.75754068 | Q56: =Q53/J53-1 -> 0.84591774 | R56: =R53/K53-1 -> 0.67592599 | S56: =S53/L53-1 -> 0.5374069 | T56: =T53/M53-1 -> 0.60823939 | U56: =U53/N53-1 -> 0.70375759 | ... W56: =W53/P53-1 -> 0.66568818 | X56: =X53/R53-1 -> 0.50464679 | Y56: =Y53/S53-1 -> 0.91902145 | Z56: =Z53/U53-1 -> 0.6865857 | AA56: =AA53/V53-1 -> 0.78277471 | AB56: =AB53/W53-1 -> 0.52333866 | AC56: =AC53/X53-1 -> 0.46488097 | AD56: =AD53/Y53-1 -> 0.21916968 | AE56: =AE53/Z53-1 -> 0.46641028 | AF56: =AF53/AA53-1 -> 0.20942408 | AG56: =AG53/AB53-1 -> 0.27774027 | ... AT56: =AT53/AO53-1 -> 0.16195282 | AU56: =AU53/AT53-1 -> 0.18742858 | AV56: =AV53/AU53-1 -> 0.16438353 | AW56: =AW53/AV53-1 -> 0.15758415 | AX56: =AX53/AW53-1 -> 0.14354825 | AY56: =AY53/AX53-1 -> 0.1174994
B58: Dec year end (CHFmn) | C58: =C2 -> 1Q19 | D58: =D2 -> 2Q19 | E58: =E2 -> 3Q19 | F58: =F2 -> 4Q19 | G58: =G2 -> 2019 | H58: =H2 -> 1Q20 | I58: =I2 -> 2Q20 | J58: =J2 -> 1H20 | ... AY58: =AY2 -> 2031E
B59: SALES BY CHANNEL
B60: DTC:
B61: Europe | N61: =N4-N94 -> 61.098245 | U61: =U4-U94 -> 82.538316 | Z61: =Z4-Z94 -> 130.19428 | AE61: =AE4-AE94 -> 229.85789 | AJ61: =AJ4-AJ94 -> 282.768 | AO61: =AO4-AO94 -> 421.93804 | AT61: =AT4-AT94 -> 518.21143 | AU61: =AU4-AU94 -> 632.46161 | AV61: =AV4-AV94 -> 735.13264 | AW61: =AW4-AW94 -> 840.90596 | AX61: =AX4-AX94 -> 944.28081 | AY61: =AY4-AY94 -> 1029.8171
B62: - cFX growth | U62: =((1+U64)/(1+U63))-1 -> 0.37333401 | Z62: =((1+Z64)/(1+Z63))-1 -> 0.49062428 | AE62: =((1+AE64)/(1+AE63))-1 -> 0.72836792 | AJ62: =((1+AJ64)/(1+AJ63))-1 -> 0.24795528 | AO62: =((1+AO64)/(1+AO63))-1 -> 0.52300315 | AT62: =((1+AT64)/(1+AT63))-1 -> 0.24504538 | AU62: =((1+AU64)/(1+AU63))-1 -> 0.21462208 | AV62: =((1+AV64)/(1+AV63))-1 -> 0.16233558 | AW62: =((1+AW64)/(1+AW63))-1 -> 0.14388332 | AX62: =((1+AX64)/(1+AX63))-1 -> 0.12293271 | AY62: =((1+AY64)/(1+AY63))-1 -> 0.090583584
B63: - ccy | U63: =U6 -> -0.016327133 | Z63: =Z6 -> 0.058200841 | AE63: =AE6 -> 0.021483425 | AJ63: =AJ6 -> -0.014238579 | AO63: =AO6 -> -0.020244702 | AT63: =AT6 -> -0.013554438 | AU63: =AU6 -> 0.00481478 | AV63: =AV6 -> 0 | AW63: =AW6 -> 0 | AX63: =AX6 -> 0 | AY63: =AY6 -> 0
B64: - total growth | U64: =U61/N61-1 -> 0.35091141 | Z64: =Z61/U61-1 -> 0.57737987 | AE64: =AE61/Z61-1 -> 0.76549918 | AJ64: =AJ61/AE61-1 -> 0.23018617 | AO64: =AO61/AJ61-1 -> 0.4921704 | AT64: =AT61/AO61-1 -> 0.22816949 | AU64: =AU61/AT61-1 -> 0.22047022 | AV64: =AV61/AU61-1 -> 0.16233558 | AW64: =AW61/AV61-1 -> 0.14388332 | AX64: =AX61/AW61-1 -> 0.12293271 | AY64: =AY61/AX61-1 -> 0.090583584
B65: North America | N65: =N11-N99 -> 92.799 | U65: =U11-U99 -> 161.61793 | Z65: =Z11-Z99 -> 220.65411 | AE65: =AE11-AE99 -> 350.47063 | AJ65: =AJ11-AJ99 -> 465.658 | AO65: =AO11-AO99 -> 414.51684 | AT65: =AT11-AT99 -> 406.88483 | AU65: =AU11-AU99 -> 376.23324 | AV65: =AV11-AV99 -> 338.77383 | AW65: =AW11-AW99 -> 286.8479 | AX65: =AX11-AX99 -> 186.95178 | AY65: =AY11-AY99 -> 101.43178
B66: - cFX growth | U66: =((1+U68)/(1+U67))-1 -> 0.77092604 | Z66: =((1+Z68)/(1+Z67))-1 -> 0.30565255 | AE66: =((1+AE68)/(1+AE67))-1 -> 0.62526686 | AJ66: =((1+AJ68)/(1+AJ67))-1 -> 0.36909284 | AO66: =((1+AO68)/(1+AO67))-1 -> -0.065600728 | AT66: =((1+AT68)/(1+AT67))-1 -> 0.043668151 | AU66: =((1+AU68)/(1+AU67))-1 -> -0.079005612 | AV66: =((1+AV68)/(1+AV67))-1 -> -0.099564325 | AW66: =((1+AW68)/(1+AW67))-1 -> -0.15327611 | AX66: =((1+AX68)/(1+AX67))-1 -> -0.34825464 | AY66: =((1+AY68)/(1+AY67))-1 -> -0.45744418
B67: - ccy | U67: =U13 -> -0.016564614 | Z67: =Z13 -> 0.045670485 | AE67: =AE13 -> -0.022729201 | AJ67: =AJ13 -> -0.029529042 | AO67: =AO13 -> -0.047329704 | AT67: =AT13 -> -0.059482486 | AU67: =AU13 -> 0.0039883579 | AV67: =AV13 -> 0 | AW67: =AW13 -> 0 | AX67: =AX13 -> 0 | AY67: =AY13 -> 0
B68: - total growth | U68: =U65/N65-1 -> 0.74159133 | Z68: =Z65/U65-1 -> 0.36528234 | AE68: =AE65/Z65-1 -> 0.58832585 | AJ68: =AJ65/AE65-1 -> 0.32866484 | AO68: =AO65/AJ65-1 -> -0.10982557 | AT68: =AT65/AO65-1 -> -0.018411825 | AU68: =AU65/AT65-1 -> -0.075332356 | AV68: =AV65/AU65-1 -> -0.099564325 | AW68: =AW65/AV65-1 -> -0.15327611 | AX68: =AX65/AW65-1 -> -0.34825464 | AY68: =AY65/AX65-1 -> -0.45744418
B69: APAC | N69: =N18-N104 -> 8.051 | U69: =U18-U104 -> 19.34375 | Z69: =Z18-Z104 -> 45.151611 | AE69: =AE18-AE104 -> 91.471482 | AJ69: =AJ18-AJ104 -> 194.374 | AO69: =AO18-AO104 -> 424.04512 | AT69: =AT18-AT104 -> 661.6101 | AU69: =AU18-AU104 -> 958.82103 | AV69: =AV18-AV104 -> 1306.7877 | AW69: =AW18-AW104 -> 1705.2723 | AX69: =AX18-AX104 -> 2140.9126 | AY69: =AY18-AY104 -> 2566.2751
B70: - cFX growth | U70: =((1+U72)/(1+U71))-1 -> 1.2896528 | Z70: =((1+Z72)/(1+Z71))-1 -> 1.3384715 | AE70: =((1+AE72)/(1+AE71))-1 -> 1.2569018 | AJ70: =((1+AJ72)/(1+AJ71))-1 -> 1.2524791 | AO70: =((1+AO72)/(1+AO71))-1 -> 1.2954938 | AT70: =((1+AT72)/(1+AT71))-1 -> 0.5924958 | AU70: =((1+AU72)/(1+AU71))-1 -> 0.41814135 | AV70: =((1+AV72)/(1+AV71))-1 -> 0.36291103 | AW70: =((1+AW72)/(1+AW71))-1 -> 0.30493438 | AX70: =((1+AX72)/(1+AX71))-1 -> 0.25546672 | AY70: =((1+AY72)/(1+AY71))-1 -> 0.19868281
B71: - ccy | U71: =U20 -> 0.04935204 | Z71: =Z20 -> -0.00183923 | AE71: =AE20 -> -0.10236495 | AJ71: =AJ20 -> -0.056609076 | AO71: =AO20 -> -0.049618951 | AT71: =AT20 -> -0.020257913 | AU71: =AU20 -> 0.021917665 | AV71: =AV20 -> 0 | AW71: =AW20 -> 0 | AX71: =AX20 -> 0 | AY71: =AY20 -> 0
B72: - total growth | U72: =U69/N69-1 -> 1.4026518 | Z72: =Z69/U69-1 -> 1.3341705 | AE72: =AE69/Z69-1 -> 1.0258741 | AJ72: =AJ69/AE69-1 -> 1.1249683 | AO72: =AO69/AJ69-1 -> 1.1815938 | AT72: =AT69/AO69-1 -> 0.56023515 | AU72: =AU69/AT69-1 -> 0.44922369 | AV72: =AV69/AU69-1 -> 0.36291103 | AW72: =AW69/AV69-1 -> 0.30493438 | AX72: =AX69/AW69-1 -> 0.25546672 | AY72: =AY69/AX69-1 -> 0.19868281
B73: Rest of the World | U73: =U25-U114 -> 12 | Z73: =Z25-Z114 -> 49.1 | AE73: =AE25-AE114 -> 0 | AJ73: =AJ25-AJ114 -> 0 | AO73: =AO25-AO114 -> 0 | AT73: =AT25-AT114 -> 0 | AU73: =AU25-AU114 -> 0 | AV73: =AV25-AV114 -> 0 | AW73: =AW25-AW114 -> 0 | AX73: =AX25-AX114 -> 0 | AY73: =AY25-AY114 -> 0
B74: - cFX growth
B75: - ccy
B76: - total growth | Z76: =Z73/U73-1 -> 3.0916667 | AE76: =AE73/Z73-1 -> -1 | AJ76: =AJ73/AE73-1 -> #DIV/0! | AO76: =AO73/AJ73-1 -> #DIV/0! | AT76: =AT73/AO73-1 -> #DIV/0! | AU76: =AU73/AT73-1 -> #DIV/0! | AV76: =AV73/AU73-1 -> #DIV/0! | AW76: =AW73/AV73-1 -> #DIV/0! | AX76: =AX73/AW73-1 -> #DIV/0! | AY76: =AY73/AX73-1 -> #DIV/0!
B78: DTC sales | C78: 10.966702 | D78: 16.203041 | E78: 17.539588 | F78: 21.694669 | G78: 66.404 | H78: 21.437375 | I78: 51.508072 | J78: =I78+H78 -> 72.945447 | K78: 39.493991 | L78: 48.036562 | M78: =L78+K78 -> 87.530553 | N78: 160.476 | O78: =H78*(1+O81) -> 49.7 | P78: =I78*(1+P81) -> 65.4 | Q78: =P78+O78 -> 115.1 | R78: =K78*(1+R81) -> 75.7 | S78: =L78*(1+S81) -> 84.7 | T78: =S78+R78 -> 160.4 | U78: =T78+Q78 -> 275.5 | V78: =O78*(1+V81) -> 83.4 | W78: =P78*(1+W81) -> 105.641 | X78: =R78*(1+X81) -> 106.576 | Y78: =S78*(1+Y81) -> 149.483 | Z78: =SUM(V78:Y78) -> 445.1 | AA78: 137 | AB78: 163.5 | AC78: 164.7 | AD78: =AE78-AC78-AB78-AA78 -> 206.6 | AE78: =Z78*(1+AE81) -> 671.8 | AF78: =AA78*(1+AF81) -> 190.5 | AG78: =AB78*(1+AG81) -> 209.4 | AH78: =AC78*(1+AH81) -> 246.7 | AI78: =AJ78-AH78-AG78-AF78 -> 296.2 | AJ78: =AE78*(1+AJ81) -> 942.8 | AK78: =AF78*(1+AK81) -> 276.9 | AL78: =AG78*(1+AL81) -> 308.3 | AM78: 314.7 | AN78: =AO78-AM78-AL78-AK78 -> 360.6 | AO78: =AJ78*(1+AO81) -> 1260.5 | AP78: =AK78*(1+AP81) -> 322.3 | AQ78: =AL78*(1+AQ81) -> 388.4 | AR78: =AM78*(1+AR81) -> 397.89728 | AS78: =AT78-AR78-AQ78-AP78 -> 478.10907 | AT78: =AO78*(1+AT81) -> 1586.7064 | AU78: =AT78*(1+AU81) -> 1967.5159 | AV78: =AU78*(1+AV81) -> 2380.6942 | AW78: =AV78*(1+AW81) -> 2833.0261 | AX78: =AW78*(1+AX81) -> 3272.1452 | AY78: =AX78*(1+AY81) -> 3697.524
B79: - cFX growth | O79: =((1+O81)/(1+O80))-1 -> 1.4613036 | P79: =((1+P81)/(1+P80))-1 -> 0.33369397 | R79: =((1+R81)/(1+R80))-1 -> 0.92412554 | S79: =((1+S81)/(1+S80))-1 -> 0.70778734 | U79: =((1+U81)/(1+U80))-1 -> 0.73909161 | V79: =((1+V81)/(1+V80))-1 -> 0.6181535 | W79: =((1+W81)/(1+W80))-1 -> 0.52586119 | X79: =((1+X81)/(1+X80))-1 -> 0.33359096 | Y79: =((1+Y81)/(1+Y80))-1 -> 0.70457459 | Z79: =((1+Z81)/(1+Z80))-1 -> 0.54249009 | AA79: =((1+AA81)/(1+AA80))-1 -> 0.63345334 | AB79: =((1+AB81)/(1+AB80))-1 -> 0.63015472 | ... AD79: =((1+AD81)/(1+AD80))-1 -> 0.48506566 | AE79: 0.6 | AF79: =((1+AF81)/(1+AF80))-1 -> 0.48664458 | AG79: =((1+AG81)/(1+AG80))-1 -> 0.30401751 | AH79: =((1+AH81)/(1+AH80))-1 -> 0.50696356 | AI79: 0.482 | AJ79: 0.446 | AK79: =((1+AK81)/(1+AK80))-1 -> 0.42430478 | AL79: =((1+AL81)/(1+AL80))-1 -> 0.5428956 | AM79: 0.375 | AN79: 0.3 | AO79: 0.399 | AP79: 0.287 | AQ79: 0.343 | AR79: 0.28 | AS79: =((1+AS81)/(1+AS80))-1 -> 0.3026174 | AT79: 0.3
B80: - ccy | O80: =O55 -> -0.058067886 | P80: =P55 -> -0.047979583 | R80: =R55 -> -0.0038345909 | S80: =S55 -> 0.032470616 | U80: =U55 -> -0.012836583 | V80: =V55 -> 0.037026718 | W80: =W55 -> 0.058619106 | X80: =X55 -> 0.055700904 | Y80: =Y55 -> 0.035362387 | Z80: =Z55 -> 0.047402509 | AA80: =AA55 -> 0.0056521414 | AB80: =AB55 -> -0.050584258 | ... AD80: =AD55 -> -0.069336124 | AE80: =((1+AE81)/(1+AE79))-1 -> -0.056672658 | AF80: -0.064664836 | AG80: -0.017855252 | AH80: -0.0060310944 | AI80: =AI81-AI79 -> -0.048311713 | AJ80: =AJ81-AJ79 -> -0.042606133 | AK80: 0.020528277 | AL80: -0.04575409 | AM80: =AM81-AM79 -> -0.099361573 | AN80: =AN81-AN79 -> -0.082579338 | AO80: =AO81-AO79 -> -0.062025032 | AP80: -0.095603646 | AQ80: -0.061942017 | AR80: =AR133 -> -0.015629866 | AS80: =AS133 -> 0.017851424 | AT80: =AT133 -> -0.041208763
B81: - total growth | H81: =H78/C78-1 -> 0.95476957 | I81: =I78/D78-1 -> 2.1789138 | K81: =K78/E78-1 -> 1.2517057 | L81: =L78/F78-1 -> 1.2142104 | N81: =N78/G78-1 -> 1.4166616 | O81: 1.3183809 | P81: 0.26970389 | Q81: =Q78/J78-1 -> 0.57789149 | R81: 0.91674731 | S81: 0.76324025 | T81: =T78/M78-1 -> 0.83250299 | U81: =U78/N78-1 -> 0.71676762 | V81: 0.67806841 | W81: 0.61530581 | X81: 0.40787318 | Y81: 0.76485242 | Z81: =Z78/U78-1 -> 0.61560799 | AA81: =AA78/V78-1 -> 0.64268585 | AB81: =AB78/W78-1 -> 0.54769455 | AC81: =AC78/X78-1 -> 0.54537607 | AD81: =AD78/Y78-1 -> 0.38209696 | AE81: 0.50932375 | AF81: 0.39051095 | AG81: 0.28073394 | AH81: 0.49787492 | AI81: =AI78/AD78-1 -> 0.43368829 | AJ81: 0.40339387 | AK81: 0.45354331 | AL81: 0.47230181 | AM81: =AM78/AH78-1 -> 0.27563843 | AN81: =AN78/AI78-1 -> 0.21742066 | AO81: 0.33697497 | AP81: =((1+AP80)*(1+AP79))-1 -> 0.16395811 | AQ81: =((1+AQ80)*(1+AQ79))-1 -> 0.25981187 | AR81: =AR80+AR79 -> 0.26437013 | AS81: =AS78/AN78-1 -> 0.32587097 | AT81: =AT80+AT79 -> 0.25879124 | AU81: 0.24 | AV81: 0.21 | AW81: 0.19 | AX81: 0.155 | AY81: 0.13
B82: Sales mix | C82: =C78/C131 -> 0.22123521 | D82: =D78/D131 -> 0.23254231 | E82: =E78/E131 -> 0.26954666 | F82: =F78/F131 -> 0.26200943 | G82: =G78/G131 -> 0.24859245 | H82: =H78/H131 -> 0.30070729 | I82: =I78/I131 -> 0.51700475 | J82: =J78/J131 -> 0.42678699 | ... AY82: =AY78/AY131 -> 0.51620398
B83: - total growth yo2y | O83: =(1*(1+H81)*(1+O81))-1 -> 3.5319004 | P83: =(1*(1+I81)*(1+P81))-1 -> 3.0362792 | R83: =(1*(1+K81)*(1+R81))-1 -> 3.3159509 | S83: =(1*(1+L81)*(1+S81))-1 -> 2.9041849 | U83: =(1*(1+N81)*(1+U81))-1 -> 3.1488465 | V83: =(1*(1+O81)*(1+V81))-1 -> 2.8904017 | W83: =(1*(1+P81)*(1+W81))-1 -> 1.0509601 | X83: =(1*(1+R81)*(1+X81))-1 -> 1.6985371 | Y83: =(1*(1+S81)*(1+Y81))-1 -> 2.1118588 | Z83: =(1*(1+U81)*(1+Z81))-1 -> 1.7736235 | AE83: =(1*(1+Z81)*(1+AE81))-1 -> 1.4384755 | AJ83: =(1*(1+AE81)*(1+AJ81))-1 -> 1.1181757 | AO83: =(1*(1+AJ81)*(1+AO81))-1 -> 0.87630247 | AT83: =(1*(1+AO81)*(1+AT81))-1 -> 0.68297237 | AU83: =(1*(1+AT81)*(1+AU81))-1 -> 0.56090113 | AV83: =(1*(1+AU81)*(1+AV81))-1 -> 0.5004 | AW83: =(1*(1+AV81)*(1+AW81))-1 -> 0.4399 | AX83: =(1*(1+AW81)*(1+AX81))-1 -> 0.37445 | AY83: =(1*(1+AX81)*(1+AY81))-1 -> 0.30515
B84: - Gross profit | N84: =N78*N85 -> 112.3332 | O84: =O78*O85 -> 36.026586 | P84: =P78*P85 -> 49.333331 | Q84: =P84+O84 -> 85.359917 | R84: =R78*R85 -> 56.275 | S84: =S78*S85 -> 63.178 | T84: =S84+R84 -> 119.453 | U84: =T84+Q84 -> 204.81292 | V84: =V78*V85 -> 55.322605 | W84: =W78*W85 -> 72.854083 | X84: =X78*X85 -> 77.180207 | Y84: =Y78*Y85 -> 111.36484 | Z84: =SUM(V84:Y84) -> 316.72173
B85: DTC gross margin | N85: 0.7 | O85: 0.724881 | P85: 0.75433228 | Q85: =Q84/Q78 -> 0.74161527 | R85: 0.74339498 | S85: 0.74590319 | T85: =T84/T78 -> 0.74471945 | U85: =U84/U78 -> 0.74342257 | V85: 0.66334059 | W85: 0.68963833 | X85: 0.72417999 | Y85: 0.745 | Z85: =Z84/Z78 -> 0.71157432
B86: SG&A pre overhead | N86: =N84-N89 -> 65.197028 | O86: =O84-O89 -> 18.550022 | P86: =P84-P89 -> 24.97172 | Q86: =Q84-Q89 -> 43.521742 | R86: =R84-R89 -> 26.190306 | S86: =S84-S89 -> 61.139043 | T86: =T84-T89 -> 87.329349 | U86: =U84-U89 -> 89.012917 | ... Z86: =Z84-Z89 -> 174.12373
B87: SG&A/Sales | N87: =N86/N78 -> 0.40627276 | O87: =O86/O78 -> 0.37323988 | P87: =P86/P78 -> 0.38183059 | Q87: =Q86/Q78 -> 0.37812113 | R87: =R86/R78 -> 0.34597498 | S87: =S86/S78 -> 0.7218305 | T87: =T86/T78 -> 0.54444731 | U87: =U86/U78 -> 0.32309589 | ... Z87: =Z86/Z78 -> 0.39120137
B88: - growth | Z88: =Z86/U86-1 -> 0.95616249
B89: - Contribution | N89: =N147-N126 -> 47.136172 | O89: =O147-O126 -> 17.476564 | P89: =P147-P126 -> 24.361611 | Q89: =P89+O89 -> 41.838175 | R89: =R147-R126 -> 30.084694 | S89: =U89-SUM(O89:R89) -> 2.0389567 | T89: =S89+R89 -> 32.123651 | U89: =U147-U126 -> 115.8 | V89: =V147-V126 -> 31.742 | W89: =W147-W126 -> 28.035254 | X89: =X147-X126 -> 43.409238 | Y89: =Y147-Y126 -> 39.411508 | Z89: =SUM(V89:Y89) -> 142.598
B90: DTC Contribution margin | N90: =N89/N78 -> 0.29372724 | O90: =O89/O78 -> 0.35164112 | P90: =P89/P78 -> 0.3725017 | Q90: =Q89/Q78 -> 0.36349413 | R90: =R89/R78 -> 0.39742 | S90: =S89/S78 -> 0.024072688 | T90: =T89/T78 -> 0.20027214 | U90: =U89/U78 -> 0.42032668 | ... Z90: =Z89/Z78 -> 0.32037295
B91: - growth | U91: =U89/N89-1 -> 1.456712 | V91: =V89/O89-1 -> 0.81626095 | W91: =W89/P89-1 -> 0.15079639 | X91: =X89/R89-1 -> 0.44290109 | Y91: =Y89/S89-1 -> 18.329252 | Z91: =Z89/U89-1 -> 0.23141623
B93: WHOLESALE:
B94: Europe - revenue (CHF mn) | N94: =N95*N97/1000000 -> 126.412 | U94: =U95*U97/1000000 -> 177.86168 | Z94: =Z95*Z97/1000000 -> 224.10572 | AE94: =AE95*AE97/1000000 -> 258.84211 | AJ94: =AJ95*AJ97/1000000 -> 295.032 | AO94: =AO95*AO97/1000000 -> 340.76196 | AT94: =AT95*AT97/1000000 -> 379.0636 | AU94: =AU95*AU97/1000000 -> 421.67035 | AV94: =AV95*AV97/1000000 -> 456.03649 | AW94: =AW95*AW97/1000000 -> 493.20346 | AX94: =AX95*AX97/1000000 -> 523.23955 | AY94: =AY95*AY97/1000000 -> 555.10484
B95: - doors | N95: 3740 | U95: =N95*(1+U96) -> 3927 | Z95: =U95*(1+Z96) -> 4123.35 | AE95: =Z95*(1+AE96) -> 4329.5175 | AJ95: 4560 | AO95: =AJ95*(1+AO96) -> 4788 | AT95: =AO95*(1+AT96) -> 4931.64 | AU95: =AT95*(1+AU96) -> 5079.5892 | AV95: =AU95*(1+AV96) -> 5231.9769 | AW95: =AV95*(1+AW96) -> 5388.9362 | AX95: =AW95*(1+AX96) -> 5550.6043 | AY95: =AX95*(1+AY96) -> 5717.1224
B96: - growth% | U96: 0.05 | Z96: 0.05 | AE96: 0.05 | AJ96: =AJ95/AE95-1 -> 0.053235147 | AO96: 0.05 | AT96: 0.03 | AU96: 0.03 | AV96: 0.03 | AW96: 0.03 | AX96: 0.03 | AY96: 0.03
B97: - revenue/door | N97: 33800 | U97: =N97*(1+U98) -> 45292 | Z97: =U97*(1+Z98) -> 54350.4 | AE97: =Z97*(1+AE98) -> 59785.44 | AJ97: 64700 | AO97: =AJ97*(1+AO98) -> 71170 | AT97: =AO97*(1+AT98) -> 76863.6 | AU97: =AT97*(1+AU98) -> 83012.688 | AV97: =AU97*(1+AV98) -> 87163.322 | AW97: =AV97*(1+AW98) -> 91521.489 | AX97: =AW97*(1+AX98) -> 94267.133 | AY97: =AX97*(1+AY98) -> 97095.147
B98: - growth% | U98: 0.34 | Z98: 0.2 | AE98: 0.1 | AJ98: =AJ97/AE97-1 -> 0.082203292 | AO98: 0.1 | AT98: 0.08 | AU98: 0.08 | AV98: 0.05 | AW98: 0.05 | AX98: 0.03 | AY98: 0.03
B99: North America - revenue (CHF mn) | N99: =N100*N102/1000000 -> 115.29 | U99: =U100*U102/1000000 -> 247.88207 | Z99: =Z100*Z102/1000000 -> 517.84589 | AE99: =AE100*AE102/1000000 -> 811.82937 | AJ99: =AJ100*AJ102/1000000 -> 1014.642 | AO99: =AO100*AO102/1000000 -> 1325.6832 | AT99: =AT100*AT102/1000000 -> 1421.2257 | AU99: =AU100*AU102/1000000 -> 1623.6984 | AV99: =AV100*AV102/1000000 -> 1821.1524 | AW99: =AW100*AW102/1000000 -> 2045.8724 | AX99: =AX100*AX102/1000000 -> 2332.3862 | AY99: =AY100*AY102/1000000 -> 2569.0664
B100: - doors | N100: 2700 | U100: =N100*(1+U101) -> 3186 | Z100: =U100*(1+Z101) -> 3663.9 | AE100: =Z100*(1+AE101) -> 4103.568 | AJ100: 4450 | AO100: =AJ100*(1+AO101) -> 4806 | AT100: =AO100*(1+AT101) -> 4950.18 | AU100: =AT100*(1+AU101) -> 5098.6854 | AV100: =AU100*(1+AV101) -> 5251.646 | AW100: =AV100*(1+AW101) -> 5409.1953 | AX100: =AW100*(1+AX101) -> 5571.4712 | AY100: =AX100*(1+AY101) -> 5738.6153
B101: - growth% | U101: 0.18 | Z101: 0.15 | AE101: 0.12 | AJ101: =AJ100/AE100-1 -> 0.084422142 | AO101: 0.08 | AT101: 0.03 | AU101: 0.03 | AV101: 0.03 | AW101: 0.03 | AX101: 0.03 | AY101: 0.03
B102: - revenue/door | N102: 42700 | U102: =(U115-U94-U104)/U100*1000000 -> 77803.536 | Z102: =(Z115-Z94-Z104)/Z100*1000000 -> 141337.34 | AE102: =(AE115-AE94-AE104)/AE100*1000000 -> 197835 | AJ102: =(AJ115-AJ94-AJ104)/AJ100*1000000 -> 228009.44 | AO102: =(AO115-AO94-AO104)/AO100*1000000 -> 275839.19 | AT102: =(AT115-AT94-AT104)/AT100*1000000 -> 287105.87 | AU102: =(AU115-AU94-AU104)/AU100*1000000 -> 318454.33 | AV102: =(AV115-AV94-AV104)/AV100*1000000 -> 346777.45 | AW102: =(AW115-AW94-AW104)/AW100*1000000 -> 378221.21 | AX102: =(AX115-AX94-AX104)/AX100*1000000 -> 418630.21 | AY102: =(AY115-AY94-AY104)/AY100*1000000 -> 447680.55
B103: - growth% | U103: =U102/N102-1 -> 0.82209686 | Z103: =Z102/U102-1 -> 0.81659279 | AE103: =AE102/Z102-1 -> 0.39973623 | AJ103: =AJ102/AE102-1 -> 0.15252326 | AO103: =AO102/AJ102-1 -> 0.20977094 | AT103: =AT102/AO102-1 -> 0.040845103 | AU103: =AU102/AT102-1 -> 0.1091878 | AV103: =AV102/AU102-1 -> 0.088939341 | AW103: =AW102/AV102-1 -> 0.090674189 | AX103: =AX102/AW102-1 -> 0.10683958 | AY103: =AY102/AX102-1 -> 0.069393785
B104: APAC - revenue (CHF mn) | N104: =N105*N107/1000000 -> 14.948 | U104: =U105*U107/1000000 -> 23.35625 | Z104: =Z105*Z107/1000000 -> 35.048389 | AE104: =AE105*AE107/1000000 -> 49.628518 | AJ104: =AJ105*AJ107/1000000 -> 65.826 | AO104: =AO105*AO107/1000000 -> 87.054885 | AT104: =AT105*AT107/1000000 -> 115.13009 | AU104: =AU105*AU107/1000000 -> 145.63956 | AV104: =AV105*AV107/1000000 -> 184.23404 | AW104: =AW105*AW107/1000000 -> 233.05606 | AX104: =AX105*AX107/1000000 -> 281.99783 | AY104: =AY105*AY107/1000000 -> 341.21738
...

Sheet GSe vs Cons
B2: Source: FactSet
B3: ONON | C3: VA Keyword | D3: 2Q25E | F3: GSe vs. Consensus
B4: CHF, mn | D4: GSe | E4: Consensus
B5: Net Sales | D5: =MODEL!$AL$131 -> 749.22 | E5: 703.1 | F5: =D5/E5-1 -> 0.065595221
B6: -∆ yoy % | D6: =MODEL!$AL$134 -> 0.31974634 | E6: =E5/MODEL!AG131-1 -> 0.23850625 | F6: =(D6-E6)*10000 -> 812.40092
B7: -∆ cFX yoy % | D7: =MODEL!$AL$132 -> 0.38204002
B8: By Channel
B9: -Wholesale | D9: =MODEL!$AL$118 -> 0.23058889 | E9: =428.5/MODEL!AG115-1 -> 0.1959252 | F9: =(D9-E9)*10000 -> 346.6369
B10: -DTC | D10: =MODEL!$AL$81 -> 0.47230181 | E10: =278.5/MODEL!AG78-1 -> 0.32999045 | F10: =(D10-E10)*10000 -> 1423.1137
B11: By Region
B12: -EMEA cFX | D12: =MODEL!$AL$5 -> 0.46139825
B13: -Americas cFX | D13: =MODEL!$AL$12 -> 0.23583673
B14: -APAC cFX | D14: =MODEL!$AL$19 -> 1.1088607
B15: Gross Margin | D15: =MODEL!$AL$136 -> 0.61503964 | E15: 0.599 | F15: =(D15-E15)*10000 -> 160.39641
B16: -∆ bps | D16: =MODEL!$AL$137 -> 157.21163 | E16: =(E15-MODEL!AG136)*10000 -> -3.1847851 | F16: -
B17: adj. EBITDA | D17: =MODEL!$AL$153 -> 136.1 | E17: 114.6 | F17: =D17/E17-1 -> 0.18760908
B18: adj. EBITDA margin | D18: =MODEL!$AL$155 -> 0.18165559 | E18: =E17/E5 -> 0.16299246 | F18: =(D18-E18)*10000 -> 186.63127
B20: Source: Visible Alpha
A21: Ticker | B21: ONON | C21: VA Keyword | D21: 3Q26E | F21: GSe vs. | G21: FY26E | I21: GSe vs. | J21: FY27E | L21: GSe vs. | M21: FY28E | O21: GSe vs. | P21: FY29E | R21: GSe vs.
B22: CHF, mn | D22: GSe | E22: Consensus | F22: Consensus | G22: GSe | H22: Consensus | I22: Consensus | J22: GSe | K22: Consensus | L22: Consensus | M22: GSe | N22: Consensus | O22: Consensus | P22: GSe | Q22: Consensus | R22: Consensus
A23: ONON_CH | B23: =B5 -> Net Sales | C23: Total Revenue | D23: =MODEL!$AR$131 -> 917.05863 | E23: =_xll.VisibleAlpha.UDF.VAData($A23,D$21,$C23,E$22,"CD") -> #NAME? | F23: =D23/E23-1 -> #NAME? | G23: =MODEL!$AT$131 -> 3502.1258 | H23: =_xll.VisibleAlpha.UDF.VAData($A23,G$21,$C23,H$22,"CD") -> #NAME? | I23: =G23/H23-1 -> #NAME? | J23: =MODEL!$AU$131 -> 4158.5242 | K23: =_xll.VisibleAlpha.UDF.VAData($A23,J$21,$C23,K$22,"CD") -> #NAME? | L23: =J23/K23-1 -> #NAME? | M23: =MODEL!$AV$131 -> 4842.1171 | N23: =_xll.VisibleAlpha.UDF.VAData($A23,M$21,$C23,N$22,"CD") -> #NAME? | O23: =M23/N23-1 -> #NAME? | P23: =MODEL!$AW$131 -> 5605.1581 | Q23: =_xll.VisibleAlpha.UDF.VAData($A23,P$21,$C23,Q$22,"CD") -> 5736.8116 | R23: =P23/Q23-1 -> -0.02294891
A24: ONON_CH | B24: =B6 -> -∆ yoy % | C24: Total Revenue | D24: =MODEL!$AR$134 -> 0.15440412 | E24: =_xll.VisibleAlpha.UDF.VAData($A24,D$21,$C24,E$22,"CD",,,"YoY%") -> #NAME? | F24: =(D24-E24)*10000 -> #NAME? | G24: =MODEL!$AT$134 -> 0.16195282 | H24: =_xll.VisibleAlpha.UDF.VAData($A24,G$21,$C24,H$22,"CD",,,"YoY%") -> #NAME? | I24: =(G24-H24)*10000 -> #NAME? | J24: =MODEL!$AU$134 -> 0.18742858 | K24: =_xll.VisibleAlpha.UDF.VAData($A24,J$21,$C24,K$22,"CD",,,"YoY%") -> #NAME? | L24: =(J24-K24)*10000 -> #NAME? | M24: =MODEL!$AV$134 -> 0.16438353 | N24: =_xll.VisibleAlpha.UDF.VAData($A24,M$21,$C24,N$22,"CD",,,"YoY%") -> #NAME? | O24: =(M24-N24)*10000 -> #NAME? | P24: =MODEL!$AW$134 -> 0.15758415 | Q24: =_xll.VisibleAlpha.UDF.VAData($A24,P$21,$C24,Q$22,"CD",,,"YoY%") -> 0.15150472 | R24: =(P24-Q24)*10000 -> 60.794343
A25: ONON_CH | B25: =B7 -> -∆ cFX yoy % | C25: Constant currency impact | D25: =MODEL!$AR$132 -> 0.17003399 | E25: =_xll.VisibleAlpha.UDF.VAData($A25,D$21,$C25,E$22,"CD")/100 -> #NAME? | F25: =(D25-E25)*10000 -> #NAME? | G25: =MODEL!$AT$132 -> 0.20316158 | H25: =_xll.VisibleAlpha.UDF.VAData($A25,G$21,$C25,H$22,"CD")/100 -> #NAME? | I25: =(G25-H25)*10000 -> #NAME? | J25: =MODEL!$AU$132 -> 0.17779813 | K25: =_xll.VisibleAlpha.UDF.VAData($A25,J$21,$C25,K$22,"CD")/100 -> #NAME? | L25: =(J25-K25)*10000 -> #NAME? | M25: =MODEL!$AV$132 -> 0.17330607 | N25: =_xll.VisibleAlpha.UDF.VAData($A25,M$21,$C25,N$22,"CD")/100 -> #NAME? | O25: =(M25-N25)*10000 -> #NAME? | P25: =MODEL!$AW$132 -> 0.1661907 | Q25: =_xll.VisibleAlpha.UDF.VAData($A25,P$21,$C25,Q$22,"CD")/100 -> 0.14635192 | R25: =(P25-Q25)*10000 -> 198.3878
A26: ONON_CH | B26: =B8 -> By Channel
A27: ONON_CH | B27: =B9 -> -Wholesale | C27: Total revenue - Wholesale | D27: =MODEL!$AR$118 -> 0.082262567 | E27: =_xll.VisibleAlpha.UDF.VAData($A27,D$21,$C27,E$22,"CD",,,"YoY%") -> #NAME? | F27: =(D27-E27)*10000 -> #NAME? | G27: =MODEL!$AT$118 -> 0.092340709 | H27: =_xll.VisibleAlpha.UDF.VAData($A27,G$21,$C27,H$22,"CD",,,"YoY%") -> #NAME? | I27: =(G27-H27)*10000 -> #NAME? | J27: =MODEL!$AU$118 -> 0.14387915 | K27: =_xll.VisibleAlpha.UDF.VAData($A27,J$21,$C27,K$22,"CD",,,"YoY%") -> #NAME? | L27: =(J27-K27)*10000 -> #NAME? | M27: =MODEL!$AV$118 -> 0.12342014 | N27: =_xll.VisibleAlpha.UDF.VAData($A27,M$21,$C27,N$22,"CD",,,"YoY%") -> #NAME? | O27: =(M27-N27)*10000 -> #NAME? | P27: =MODEL!$AW$118 -> 0.12623147 | Q27: =_xll.VisibleAlpha.UDF.VAData($A27,P$21,$C27,Q$22,"CD",,,"YoY%") -> 0.12521792 | R27: =(P27-Q27)*10000 -> 10.13543
A28: ONON_CH | B28: =B10 -> -DTC | C28: Total revenue - DTC | D28: =MODEL!$AR$81 -> 0.26437013 | E28: =_xll.VisibleAlpha.UDF.VAData($A28,D$21,$C28,E$22,"CD",,,"YoY%") -> #NAME? | F28: =(D28-E28)*10000 -> #NAME? | G28: =MODEL!$AT$81 -> 0.25879124 | H28: =_xll.VisibleAlpha.UDF.VAData($A28,G$21,$C28,H$22,"CD",,,"YoY%") -> #NAME? | I28: =(G28-H28)*10000 -> #NAME? | J28: =MODEL!$AU$81 -> 0.24 | K28: =_xll.VisibleAlpha.UDF.VAData($A28,J$21,$C28,K$22,"CD",,,"YoY%") -> #NAME? | L28: =(J28-K28)*10000 -> #NAME? | M28: =MODEL!$AV$81 -> 0.21 | N28: =_xll.VisibleAlpha.UDF.VAData($A28,M$21,$C28,N$22,"CD",,,"YoY%") -> #NAME? | O28: =(M28-N28)*10000 -> #NAME? | P28: =MODEL!$AW$81 -> 0.19 | Q28: =_xll.VisibleAlpha.UDF.VAData($A28,P$21,$C28,Q$22,"CD",,,"YoY%") -> 0.17993633 | R28: =(P28-Q28)*10000 -> 100.63669
A29: ONON_CH | B29: =B11 -> By Region
A30: ONON_CH | B30: =B12 -> -EMEA cFX | C30: EMEA - Constant currency impact | D30: =MODEL!$AR$5 -> 0.13 | E30: =_xll.VisibleAlpha.UDF.VAData($A30,D$21,$C30,E$22,"CD")/100 -> #NAME? | F30: =(D30-E30)*10000 -> #NAME? | G30: =MODEL!$AT$5 -> 0.19 | H30: =_xll.VisibleAlpha.UDF.VAData($A30,G$21,$C30,H$22,"CD")/100 -> #NAME? | I30: =(G30-H30)*10000 -> #NAME? | J30: =MODEL!$AU$5 -> 0.17 | K30: =_xll.VisibleAlpha.UDF.VAData($A30,J$21,$C30,K$22,"CD")/100 -> #NAME? | L30: =(J30-K30)*10000 -> #NAME? | M30: =MODEL!$AV$5 -> 0.16 | N30: =_xll.VisibleAlpha.UDF.VAData($A30,M$21,$C30,N$22,"CD")/100 -> #NAME? | O30: =(M30-N30)*10000 -> #NAME? | P30: =MODEL!$AW$5 -> 0.15 | Q30: =_xll.VisibleAlpha.UDF.VAData($A30,P$21,$C30,Q$22,"CD")/100 -> 0.14099101 | R30: =(P30-Q30)*10000 -> 90.089872
A31: ONON_CH | B31: =B13 -> -Americas cFX | C31: Americas - constant currency impact | D31: =MODEL!$AR$12 -> 0.08 | E31: =_xll.VisibleAlpha.UDF.VAData($A31,D$21,$C31,E$22,"CD")/100 -> #NAME? | F31: =(D31-E31)*10000 -> #NAME? | G31: =MODEL!$AT$12 -> 0.11 | H31: =_xll.VisibleAlpha.UDF.VAData($A31,G$21,$C31,H$22,"CD")/100 -> #NAME? | I31: =(G31-H31)*10000 -> #NAME? | J31: =MODEL!$AU$12 -> 0.09 | K31: =_xll.VisibleAlpha.UDF.VAData($A31,J$21,$C31,K$22,"CD")/100 -> #NAME? | L31: =(J31-K31)*10000 -> #NAME? | M31: =MODEL!$AV$12 -> 0.08 | N31: =_xll.VisibleAlpha.UDF.VAData($A31,M$21,$C31,N$22,"CD")/100 -> #NAME? | O31: =(M31-N31)*10000 -> #NAME? | P31: =MODEL!$AW$12 -> 0.08 | Q31: =_xll.VisibleAlpha.UDF.VAData($A31,P$21,$C31,Q$22,"CD")/100 -> 0.10711495 | R31: =(P31-Q31)*10000 -> -271.14954
A32: ONON_CH | B32: =B14 -> -APAC cFX | C32: Asia Pacific - constant currency impact | D32: =MODEL!$AR$19 -> 0.5 | E32: =_xll.VisibleAlpha.UDF.VAData($A32,D$21,$C32,E$22,"CD")/100 -> #NAME? | F32: =(D32-E32)*10000 -> #NAME? | G32: =MODEL!$AT$19 -> 0.54 | H32: =_xll.VisibleAlpha.UDF.VAData($A32,G$21,$C32,H$22,"CD")/100 -> #NAME? | I32: =(G32-H32)*10000 -> #NAME? | J32: =MODEL!$AU$19 -> 0.4 | K32: =_xll.VisibleAlpha.UDF.VAData($A32,J$21,$C32,K$22,"CD")/100 -> #NAME? | L32: =(J32-K32)*10000 -> #NAME? | M32: =MODEL!$AV$19 -> 0.35 | N32: =_xll.VisibleAlpha.UDF.VAData($A32,M$21,$C32,N$22,"CD")/100 -> #NAME? | O32: =(M32-N32)*10000 -> #NAME? | P32: =MODEL!$AW$19 -> 0.3 | Q32: =_xll.VisibleAlpha.UDF.VAData($A32,P$21,$C32,Q$22,"CD")/100 -> 0.22503711 | R32: =(P32-Q32)*10000 -> 749.62887
A33: ONON_CH | B33: =B15 -> Gross Margin | C33: Gross profit/(loss) | D33: =MODEL!$AR$136 -> 0.65 | E33: =_xll.VisibleAlpha.UDF.VAData($A33,D$21,$C33,E$22,"CD")/E23 -> #NAME? | F33: =(D33-E33)*10000 -> #NAME? | G33: =MODEL!$AT$136 -> 0.65 | H33: =_xll.VisibleAlpha.UDF.VAData($A33,G$21,$C33,H$22,"CD")/H23 -> #NAME? | I33: =(G33-H33)*10000 -> #NAME? | J33: =MODEL!$AU$136 -> 0.652 | K33: =_xll.VisibleAlpha.UDF.VAData($A33,J$21,$C33,K$22,"CD")/K23 -> #NAME? | L33: =(J33-K33)*10000 -> #NAME? | M33: =MODEL!$AV$136 -> 0.654 | N33: =_xll.VisibleAlpha.UDF.VAData($A33,M$21,$C33,N$22,"CD")/N23 -> #NAME? | O33: =(M33-N33)*10000 -> #NAME? | P33: =MODEL!$AW$136 -> 0.656 | Q33: =_xll.VisibleAlpha.UDF.VAData($A33,P$21,$C33,Q$22,"CD")/Q23 -> 0.65675047 | R33: =(P33-Q33)*10000 -> -7.5047277
A34: ONON_CH | B34: =B16 -> -∆ bps | D34: =MODEL!$AR$137 -> -73.514602 | E34: =(E33-MODEL!$AM$136)*10000 -> #NAME? | F34: - | G34: =(G33-MODEL!$AO$136)*10000 -> 217.31918 | H34: =(H33-MODEL!$AO$136)*10000 -> #NAME? | I34: - | J34: =(J33-G33)*10000 -> 20 | K34: =(K33-H33)*10000 -> #NAME? | L34: - | M34: =(M33-J33)*10000 -> 20 | N34: =(N33-K33)*10000 -> #NAME? | O34: - | P34: =(P33-M33)*10000 -> 20 | Q34: =(Q33-N33)*10000 -> #NAME? | R34: -
A35: ONON_CH | B35: =B17 -> adj. EBITDA | C35: EBITDA - Operating | D35: =MODEL!$AR$153 -> 197.52286 | E35: =_xll.VisibleAlpha.UDF.VAData($A35,D$21,$C35,E$22,"CD") -> #NAME? | F35: =D35/E35-1 -> #NAME? | G35: =MODEL!$AT$153 -> 699.98963 | H35: =_xll.VisibleAlpha.UDF.VAData($A35,G$21,$C35,H$22,"CD") -> #NAME? | I35: =G35/H35-1 -> #NAME? | J35: =MODEL!$AU$153 -> 855 | K35: =_xll.VisibleAlpha.UDF.VAData($A35,J$21,$C35,K$22,"CD") -> #NAME? | L35: =J35/K35-1 -> #NAME? | M35: =MODEL!$AV$153 -> 1030 | N35: =_xll.VisibleAlpha.UDF.VAData($A35,M$21,$C35,N$22,"CD") -> #NAME? | O35: =M35/N35-1 -> #NAME? | P35: =MODEL!$AW$153 -> 1233 | Q35: =_xll.VisibleAlpha.UDF.VAData($A35,P$21,$C35,Q$22,"CD") -> 1239.7723 | R35: =P35/Q35-1 -> -0.0054625058
A36: ONON_CH | B36: =B18 -> adj. EBITDA margin | D36: =MODEL!$AR$155 -> 0.21538738 | E36: =E35/E23 -> #NAME? | F36: =(D36-E36)*10000 -> #NAME? | G36: =MODEL!$AT$155 -> 0.19987564 | H36: =H35/H23 -> #NAME? | I36: =(G36-H36)*10000 -> #NAME? | J36: =MODEL!$AU$155 -> 0.20560178 | K36: =K35/K23 -> #NAME? | L36: =(J36-K36)*10000 -> #NAME? | M36: =MODEL!$AV$155 -> 0.21271687 | N36: =N35/N23 -> #NAME? | O36: =(M36-N36)*10000 -> #NAME? | P36: =MODEL!$AW$155 -> 0.21997596 | Q36: =Q35/Q23 -> 0.21610824 | R36: =(P36-Q36)*10000 -> 38.677159
P37: =P36*P34 -> 4.3995191
P38: =P37/H35-1 -> #NAME?
B42: ONON | C42: VA Keyword | D42: Beat/Miss | E42: 1Q26
B43: CHF, mn | E43: Actual | F43: GSe | G43: Consensus
B44: =B23 -> Net Sales | D44: =IF(E44>G44,"Beat", "Miss") -> #NAME? | F44: =D23 -> 917.05863 | G44: =E23 -> #NAME?
B45: =B24 -> -∆ yoy % | D45: =IF(E45>G45,"Beat", "Miss") -> #NAME? | F45: =D24 -> 0.15440412 | G45: =E24 -> #NAME?
B46: =B25 -> -∆ cFX yoy % | D46: =IF(E46>G46,"Beat", "Miss") -> #NAME? | F46: =D25 -> 0.17003399 | G46: =E25 -> #NAME?
B47: =B26 -> By Channel
B48: =B27 -> -Wholesale | D48: =IF(E48>G48,"Beat", "Miss") -> #NAME? | F48: =D27 -> 0.082262567 | G48: =E27 -> #NAME?
B49: =B28 -> -DTC | D49: =IF(E49>G49,"Beat", "Miss") -> #NAME? | F49: =D28 -> 0.26437013 | G49: =E28 -> #NAME?
B50: =B29 -> By Region
B51: =B30 -> -EMEA cFX | D51: =IF(E51>G51,"Beat", "Miss") -> #NAME? | F51: =D30 -> 0.13 | G51: =E30 -> #NAME?
B52: =B31 -> -Americas cFX | D52: =IF(E52>G52,"Beat", "Miss") -> #NAME? | F52: =D31 -> 0.08 | G52: =E31 -> #NAME?
B53: =B32 -> -APAC cFX | D53: =IF(E53>G53,"Beat", "Miss") -> #NAME? | F53: =D32 -> 0.5 | G53: =E32 -> #NAME?
B54: =B33 -> Gross Margin | D54: =IF(E54>G54,"Beat", "Miss") -> #NAME? | F54: =D33 -> 0.65 | G54: =E33 -> #NAME?
B55: =B34 -> -∆ bps | D55: =IF(E55>G55,"Beat", "Miss") -> #NAME? | F55: =D34 -> -73.514602 | G55: =E34 -> #NAME?
B56: =B35 -> adj. EBITDA | D56: =IF(E56>G56,"Beat", "Miss") -> #NAME? | F56: =D35 -> 197.52286 | G56: =E35 -> #NAME?
B57: =B36 -> adj. EBITDA margin | D57: =IF(E57>G57,"Beat", "Miss") -> #NAME? | F57: =D36 -> 0.21538738 | G57: =E36 -> #NAME?

Sheet FX
B2: Dec year end (CHFmn) | C2: 1Q19 | D2: 2Q19 | E2: 3Q19 | F2: 4Q19 | G2: FY19 | H2: 1Q20 | I2: 2Q20 | J2: 3Q20 | K2: 4Q20 | L2: FY20 | M2: 1Q21 | N2: 2Q21 | O2: 3Q21 | P2: 4Q21 | Q2: =Valuation!C48 -> 2021 | R2: 1Q22 | S2: 2Q22 | T2: 3Q22 | U2: 4Q22E | V2: =Valuation!D48 -> 2022 | W2: 1Q23 | X2: 2Q23 | Y2: 3Q23 | Z2: 4Q23E | AA2: =Valuation!E48 -> 2023 | AB2: 1Q24 | AC2: 2Q24 | AD2: 3Q24 | AE2: 4Q24 | AF2: =Valuation!F48 -> 2024 | AG2: 1Q25 | AH2: 2Q25 | AI2: 3Q25 | AJ2: 4Q25E | AK2: =Valuation!G48 -> 2025 | AL2: 1Q26 | AM2: 2Q26 | AN2: 3Q26E | AO2: 4Q26E | AP2: =Valuation!H48 -> 2026E | AQ2: =Valuation!I48 -> 2027E | AR2: =Valuation!J48 -> 2028E | AS2: =Valuation!K48 -> 2029E | AT2: =Valuation!L48 -> 2030E | AU2: =Valuation!M48 -> 2031E
B3: FX
B4: CHF/Euro | G4: 1.0065 | H4: 1.0332 | I4: 1.038 | J4: 1.0873 | K4: 1.1071 | L4: 1.0137 | M4: 1.104 | N4: 1.0977 | O4: 1.1062 | P4: 1.0538 | Q4: =AVERAGE(M4:P4) -> 1.090425 | R4: 1.038 | S4: 1.027 | T4: 1.0278 | U4: 1.017 | V4: =AVERAGE(R4:U4) -> 1.02745 | W4: 1 | X4: 1.022 | Y4: 1.045 | Z4: 1.03 | AA4: =AVERAGE(W4:Z4) -> 1.02425 | AB4: 1.027 | AC4: 1.055 | AD4: 1.051 | AE4: 1.0684 | AF4: =AVERAGE(AB4:AE4) -> 1.05035 | AG4: 1.061 | AH4: 1.068 | AI4: 1.0694 | AJ4: 1.075 | AK4: =AVERAGE(AG4:AJ4) -> 1.06835 | AL4: 1.0905 | AM4: 1.0882 | AN4: 1.0708 | AO4: 1.0627 | AP4: =AVERAGE(AL4:AO4) -> 1.07805 | AQ4: =AO4 -> 1.0627 | AR4: =AQ4 -> 1.0627 | AS4: =AR4 -> 1.0627 | AT4: =AS4 -> 1.0627 | AU4: =AT4 -> 1.0627
B5: US$/CHF | G5: 1.0065 | H5: 1.0332 | I5: 1.038 | J5: 1.0873 | K5: 1.1071 | L5: =AVERAGE(H5:K5) -> 1.0664 | M5: 1.1053 | N5: 1.098 | O5: 1.0891 | P5: 1.0847 | Q5: =AVERAGE(M5:P5) -> 1.094275 | R5: 1.0824 | S5: 1.0364 | T5: 1.0344 | U5: 1.039 | V5: =AVERAGE(R5:U5) -> 1.04805 | W5: 1.0826 | X5: 1.113 | Y5: 1.137 | Z5: 1.12 | AA5: =AVERAGE(W5:Z5) -> 1.11315 | AB5: 1.1058 | AC5: 1.15 | AD5: 1.1553 | AE5: 1.139 | AF5: =AVERAGE(AB5:AE5) -> 1.137525 | AG5: 1.115 | AH5: 1.212 | AI5: 1.25 | AJ5: 1.251 | AK5: =AVERAGE(AG5:AJ5) -> 1.207 | AL5: 1.277 | AM5: 1.2652 | AN5: 1.2639 | AO5: 1.2084 | AP5: =AVERAGE(AL5:AO5) -> 1.253625 | AQ5: =AO5 -> 1.2084 | AR5: =AQ5 -> 1.2084 | AS5: =AR5 -> 1.2084 | AT5: =AS5 -> 1.2084 | AU5: =AT5 -> 1.2084
B6: Yuan/CHF | G6: 6.76 | H6: 7.222 | I6: 7.36 | J6: 7.52 | K6: 7.315 | L6: =AVERAGE(H6:K6) -> 7.35425 | M6: 7.156 | N6: 7.088 | O6: 7.045 | P6: 6.9356 | Q6: =AVERAGE(M6:P6) -> 7.05615 | R6: 6.8785 | S6: 6.8672 | T6: 7.0978 | U6: 7.39 | V6: =AVERAGE(R6:U6) -> 7.058375 | W6: 7.44 | X6: 7.815 | Y6: 8.338 | Z6: 8.13 | AA6: =AVERAGE(W6:Z6) -> 7.93075 | AB6: 8.023 | AC6: 8.27 | AD6: 8.2727 | AE6: 8.188 | AF6: =AVERAGE(AB6:AE6) -> 8.188425 | AG6: 8.1237 | AH6: 8.764 | AI6: 8.946 | AJ6: 8.87 | AK6: =AVERAGE(AG6:AJ6) -> 8.675925 | AL6: 8.839 | AM6: 8.6138 | AN6: 8.317 | AO6: 8.1156 | AP6: =AVERAGE(AL6:AO6) -> 8.47135 | AQ6: =AO6 -> 8.1156 | AR6: =AQ6 -> 8.1156 | AS6: =AR6 -> 8.1156 | AT6: =AS6 -> 8.1156 | AU6: =AT6 -> 8.1156
AN7: \
B8: CHF/Euro growth | L8: =G4/L4-1 -> -0.0071026931 | M8: =H4/M4-1 -> -0.064130435 | N8: =I4/N4-1 -> -0.054386444 | O8: =J4/O4-1 -> -0.017085518 | P8: =K4/P4-1 -> 0.050578857 | Q8: =L4/Q4-1 -> -0.070362473 | R8: =M4/R4-1 -> 0.063583815 | S8: =N4/S4-1 -> 0.068841285 | ... AP8: =AK4/AP4-1 -> -0.0089977274 | AQ8: =AP4/AQ4-1 -> 0.01444434 | AR8: =AQ4/AR4-1 -> 0 | AS8: =AR4/AS4-1 -> 0 | AT8: =AS4/AT4-1 -> 0 | AU8: =AT4/AU4-1 -> 0
B9: US$/CHF growth | L9: =G5/L5-1 -> -0.056170293 | M9: =H5/M5-1 -> -0.065231159 | N9: =I5/N5-1 -> -0.054644809 | O9: =J5/O5-1 -> -0.0016527408 | P9: =K5/P5-1 -> 0.020650871 | Q9: =L5/Q5-1 -> -0.025473487 | R9: =M5/R5-1 -> 0.021156689 | S9: =N5/S5-1 -> 0.059436511 | ... AP9: =AK5/AP5-1 -> -0.037192143 | AQ9: =AP5/AQ5-1 -> 0.037425521 | AR9: =AQ5/AR5-1 -> 0 | AS9: =AR5/AS5-1 -> 0 | AT9: =AS5/AT5-1 -> 0 | AU9: =AT5/AU5-1 -> 0
B10: Yuan/CHF growth | L10: =G6/L6-1 -> -0.080803617 | M10: =H6/M6-1 -> 0.0092230296 | N10: =I6/N6-1 -> 0.038374718 | O10: =J6/O6-1 -> 0.067423705 | P10: =K6/P6-1 -> 0.05470327 | Q10: =L6/Q6-1 -> 0.042246834 | R10: =M6/R6-1 -> 0.040343098 | S10: =N6/S6-1 -> 0.032152842 | ... AP10: =AK6/AP6-1 -> 0.024149044 | AQ10: =AP6/AQ6-1 -> 0.043835329 | AR10: =AQ6/AR6-1 -> 0 | AS10: =AR6/AS6-1 -> 0 | AT10: =AS6/AT6-1 -> 0 | AU10: =AT6/AU6-1 -> 0

Sheet Worksheet
C5: DTC | D5: Wholesale
B6: Retail Price | C6: 140 | D6: 140
B7: Wholesale Price | D7: 70
B8: COGS | C8: =C6-C9 -> 56.629652 | D8: =C8 -> 56.629652
B9: Gross Profit | C9: =C6*C10 -> 83.370348 | D9: =D7*D10 -> 0
B10: GM | C10: =MODEL!AE136 -> 0.59550248 | D10: =MODEL!$AE$122 -> 0
B11: Selling and Dist | C11: =MODEL!$AE$87 -> 0 | D11: =MODEL!$AE$124 -> 0
B12: Admin and D&A | C12: =MODEL!$AE$152+MODEL!$AE$159 -> 0.15992411 | D12: =MODEL!$AE$152+MODEL!$AE$159 -> 0.15992411
C13: =C10-SUM(C11:C12) -> 0.43557837 | D13: =D10-SUM(D11:D12) -> -0.15992411
C16: DTC | D16: Wholesale
B17: =B6 -> Retail Price | C17: =C6 -> 140 | D17: =D6 -> 140
B18: Retailer Commision | D18: =D6-D7 -> 70
B19: COGS | C19: =C8 -> 56.629652 | D19: =D8 -> 56.629652
B20: Selling and Distribution | C20: =C11*C6 -> 0 | D20: =D11*D7 -> 0
B21: Admin and D&A | C21: =C12*C6 -> 22.389376 | D21: =D12*D7 -> 11.194688
B22: EBIT | C22: =C17-SUM(C18:C21) -> 60.980972 | D22: =D17-SUM(D18:D21) -> 2.1756598
B31: Gross Margins | C31: 2019 | D31: 2020 | E31: 2021 | F31: 2022E | G31: 2023E | H31: 2024E | I31: 2025E | J31: 2026E | K31: 2027E | L31: 2028E
B32: On | C32: =MODEL!G136 -> 0.53577889 | D32: =MODEL!N136 -> 0.54339968 | E32: =MODEL!U136 -> 0.59384488 | F32: =MODEL!Z136 -> 0.56042877 | G32: =MODEL!AE136 -> 0.59550248 | H32: =MODEL!AJ136 -> 0.60633821 | I32: =MODEL!AO136 -> 0.62826808 | J32: =MODEL!AT136 -> 0.65 | K32: =MODEL!AU136 -> 0.652 | L32: =MODEL!AV136 -> 0.654
B33: Puma | C33: =Comps!BA7 -> #DIV/0! | D33: =Comps!BB7 -> #DIV/0! | E33: =Comps!BC7 -> #DIV/0! | F33: =Comps!BD7 -> #DIV/0! | G33: =Comps!BE7 -> #DIV/0! | H33: =Comps!BF7 -> #DIV/0! | I33: =Comps!BG7 -> #DIV/0! | J33: =Comps!BH7 -> #DIV/0! | K33: =Comps!BI7 -> #DIV/0!
B34: Adidas | C34: =Comps!BA6 -> #DIV/0! | D34: =Comps!BB6 -> #DIV/0! | E34: =Comps!BC6 -> #DIV/0! | F34: =Comps!BD6 -> #DIV/0! | G34: =Comps!BE6 -> #DIV/0! | H34: =Comps!BF6 -> #DIV/0! | I34: =Comps!BG6 -> #DIV/0! | J34: =Comps!BH6 -> #DIV/0! | K34: =Comps!BI6 -> #DIV/0!
B35: Nike | C35: =Comps!BA4 -> #DIV/0! | D35: =Comps!BB4 -> #DIV/0! | E35: =Comps!BC4 -> #DIV/0! | F35: =Comps!BD4 -> #DIV/0! | G35: =Comps!BE4 -> #DIV/0! | H35: =Comps!BF4 -> #DIV/0! | I35: =Comps!BG4 -> #DIV/0!
B36: Lululemon | C36: =Comps!BA5 -> #DIV/0! | D36: =Comps!BB5 -> #DIV/0! | E36: =Comps!BC5 -> #DIV/0! | F36: =Comps!BD5 -> #DIV/0! | G36: =Comps!BE5 -> #DIV/0! | H36: =Comps!BF5 -> #DIV/0! | I36: =Comps!BG5 -> #DIV/0!
D46: N | E46: U | F46: Z | G46: AA
D47: 2020 | E47: 2021 | F47: 2022E | G47: 2023E | H47: 2024E | I47: 2025E | J47: 2026E | K47: 2027E | L47: 2028E
B48: Wholesale contribution margin | D48: =MODEL!N127 -> 0.195 | E48: =MODEL!U127 -> 0.14473391 | F48: =MODEL!Z127 -> 0.226 | G48: =MODEL!AE127 -> 0 | H48: =MODEL!AJ127 -> 0 | I48: =MODEL!AO127 -> 0 | J48: =MODEL!AT127 -> 0 | K48: =MODEL!AU127 -> 0 | L48: =MODEL!AV127 -> 0
B49: DTC contribution margin | D49: =MODEL!N90 -> 0.29372724 | E49: =MODEL!U90 -> 0.42032668 | F49: =MODEL!Z90 -> 0.32037295 | G49: =MODEL!AE90 -> 0 | H49: =MODEL!AJ90 -> 0 | I49: =MODEL!AO90 -> 0 | J49: =MODEL!AT90 -> 0 | K49: =MODEL!AU90 -> 0 | L49: =MODEL!AV90 -> 0
B50: contribution margin = EBITDA before central admin costs
C64: G | D64: N | E64: U | F64: Z
B65: Opex breakdown | C65: =C31 -> 2019 | D65: =D31 -> 2020 | E65: =E31 -> 2021 | F65: =F31 -> 2022E | G65: =G31 -> 2023E | H65: =H31 -> 2024E | I65: =I31 -> 2025E | J65: =J31 -> 2026E | ... L65: =L31 -> 2028E
B66: G&A | C66: =MODEL!G152 -> 0.12220892 | D66: =MODEL!N152 -> 0.11524261 | E66: =MODEL!U152 -> 0.11649738 | F66: =MODEL!Z152 -> 0.12511251 | G66: =MODEL!AE152 -> 0.12370961 | H66: =MODEL!AJ152 -> 0.12290243 | I66: =MODEL!AO152 -> 0.12179827 | J66: =MODEL!AT152 -> 0.12012436 | K66: =MODEL!AU152 -> 0.11839822 | L66: =MODEL!AV152 -> 0.11528313
B67: Marketing | C67: =MODEL!G146 -> 0.10689213 | D67: =MODEL!N146 -> 0.1072796 | E67: =MODEL!U146 -> 0.13869721 | F67: =MODEL!Z146 -> 0.10653793 | G67: =MODEL!AE146 -> 0.1092573 | H67: =MODEL!AJ146 -> 0.1193266 | I67: =MODEL!AO146 -> 0.12491705 | J67: =MODEL!AT146 -> 0.135 | K67: =MODEL!AU146 -> 0.134 | L67: =MODEL!AV146 -> 0.133
B68: Selling | C68: =MODEL!G143 -> 0.087926236 | D68: =MODEL!N143 -> 0.083740699 | E68: =MODEL!U143 -> 0.072591775 | F68: =MODEL!Z143 -> 0.069961542 | G68: =MODEL!AE143 -> 0.07438201 | H68: =MODEL!AJ143 -> 0.072551815 | I68: =MODEL!AO143 -> 0.086297279 | J68: =MODEL!AT143 -> 0.095 | K68: =MODEL!AU143 -> 0.097 | L68: =MODEL!AV143 -> 0.099
B69: Distribution | C69: =MODEL!G140 -> 0.10693217 | D69: =MODEL!N140 -> 0.12012678 | E69: =MODEL!U140 -> 0.13303892 | F69: =MODEL!Z155 -> 0.13525898 | G69: =MODEL!AE155 -> 0.15451147 | H69: =MODEL!AJ155 -> 0.16720131 | I69: =MODEL!AO155 -> 0.1881221 | J69: =MODEL!AT155 -> 0.19987564 | K69: =MODEL!AU155 -> 0.20560178 | L69: =MODEL!AV155 -> 0.21271687
C70: =SUM(C66:C69) -> 0.42395946 | D70: =SUM(D66:D69) -> 0.42638969 | E70: =SUM(E66:E69) -> 0.46082528 | F70: =SUM(F66:F69) -> 0.43687096 | G70: =SUM(G66:G69) -> 0.46186039 | H70: =SUM(H66:H69) -> 0.48198215 | I70: =SUM(I66:I69) -> 0.5211347 | J70: =SUM(J66:J69) -> 0.55 | ... L70: =SUM(L66:L69) -> 0.56
C89: 2021 | D89: 2022 | E89: 2023 | F89: 2024E
B90: DTC | C90: =MODEL!$U$82 -> 0.38020977 | D90: =MODEL!Z82 -> 0.36420915 | E90: =MODEL!AE82 -> 0.37486747 | F90: =MODEL!AJ82 -> 0.40667731
B91: Wholesale | C91: =1-C90 -> 0.61979023 | D91: =1-D90 -> 0.63579085 | E91: =1-E90 -> 0.62513253 | F91: =1-F90 -> 0.59332269
C93: =C89 -> 2021 | D93: =D89 -> 2022 | E93: =E89 -> 2023 | F93: =F89 -> 2024E
B94: Europe | C94: =MODEL!U8 -> 0.35937069
B95: North America | C95: =MODEL!U15 -> 0.56513939
B96: ROW | C96: =MODEL!U29 -> 0.016560861
B97: APAC | C97: =MODEL!U22 -> 0.058929064
B100: Shoes | C100: 0.97
B101: Apparel | C101: 0.02
B102: Accessories | C102: 0
B107: Channel growth trends
B108: cFX | C108: 1Q21 | D108: 2Q21 | E108: 3Q21 | F108: 4Q21 | G108: 1Q22 | H108: 2Q22 | I108: 3Q22 | J108: 4Q22 | K108: 1Q23 | L108: 2Q23 | M108: 3Q23 | N108: 4Q23 | O108: 1Q24 | P108: 2Q24 | Q108: 3Q24
B109: DTC | C109: =MODEL!O79 -> 1.4613036 | D109: =MODEL!P79 -> 0.33369397 | E109: =MODEL!R79 -> 0.92412554 | F109: =MODEL!S79 -> 0.70778734 | G109: =MODEL!V79 -> 0.6181535 | H109: =MODEL!W79 -> 0.52586119 | I109: =MODEL!X79 -> 0.33359096 | J109: =MODEL!Y79 -> 0.70457459 | K109: =MODEL!AA79 -> 0.63345334 | L109: =MODEL!AB79 -> 0.63015472 | M109: =MODEL!AC79 -> 0.74507504 | N109: =MODEL!AD79 -> 0.48506566 | O109: =MODEL!AF79 -> 0.48664458 | P109: =MODEL!AG79 -> 0.30401751 | Q109: =MODEL!AH79 -> 0.50696356
B110: Wholesale | C110: =MODEL!O116 -> 0.9315281 | D110: =MODEL!P116 -> 1.3946208 | E110: =MODEL!R116 -> 0.57697588 | F110: =MODEL!S116 -> 0.35128314 | G110: =MODEL!V116 -> 0.61920811 | H110: =MODEL!W116 -> 0.60182704 | I110: =MODEL!X116 -> 0.47402346 | J110: =MODEL!Y116 -> 0.97201303 | K110: =MODEL!AA116 -> 0.84903684 | L110: =MODEL!AB116 -> 0.58993255 | M110: =MODEL!AC116 -> 0.61043003 | N110: =MODEL!AD116 -> 0.1895383 | O110: =MODEL!AF116 -> 0.19788792 | P110: =MODEL!AG116 -> 0.28841191 | Q110: =MODEL!AH116 -> 0.24010644
B111: DTC mix (RHS) | C111: =MODEL!O82 -> 0.3539886 | D111: =MODEL!P82 -> 0.37350086 | E111: =MODEL!R82 -> 0.34724771 | F111: =MODEL!S82 -> 0.44322344 | G111: =MODEL!V82 -> 0.35383963 | H111: =MODEL!W82 -> 0.36220351 | I111: =MODEL!X82 -> 0.32491395 | J111: =MODEL!Y82 -> 0.40761606 | K111: =MODEL!AA82 -> 0.32603522 | L111: =MODEL!AB82 -> 0.3679946 | M111: =MODEL!AC82 -> 0.34276795 | N111: =MODEL!AD82 -> 0.46208902 | O111: =MODEL!AF82 -> 0.37485242 | P111: =MODEL!AG82 -> 0.36885679 | Q111: =MODEL!AH82 -> 0.3880151
B112: Average | C112: =AVERAGE(C109:P110) -> 0.62643638 | D112: =C112 -> 0.62643638 | E112: =D112 -> 0.62643638 | F112: =E112 -> 0.62643638 | G112: =F112 -> 0.62643638 | H112: =G112 -> 0.62643638 | I112: =H112 -> 0.62643638 | J112: =I112 -> 0.62643638 | K112: =J112 -> 0.62643638 | ... Q112: =P112 -> 0.62643638
B136: Gross margin mix shift
B138: Sales mix | C138: 2024E | D138: 2025E | E138: 2026E | F138: 2027E | G138: 2028E | H138: 2029E | I138: 2030E | J138: 2031E
B139: DTC | C139: =MODEL!AJ82 -> 0.40667731 | D139: =MODEL!AO82 -> 0.418215 | E139: =MODEL!AT82 -> 0.45306949 | F139: =MODEL!AU82 -> 0.47312839 | G139: =MODEL!AV82 -> 0.4916639 | H139: =MODEL!AW82 -> 0.50543198 | I139: =MODEL!AX82 -> 0.51049348 | J139: =MODEL!AY82 -> 0.51620398
B140: Wholesale | C140: =1-C139 -> 0.59332269 | D140: =1-D139 -> 0.581785 | E140: =1-E139 -> 0.54693051 | F140: =1-F139 -> 0.52687161 | G140: =1-G139 -> 0.5083361 | H140: =1-H139 -> 0.49456802 | I140: =1-I139 -> 0.48950652 | J140: =1-J139 -> 0.48379602
B142: GM%
B143: DTC | C143: 0.76 | D143: 0.76 | E143: 0.76 | F143: 0.76 | G143: 0.76 | H143: 0.76 | I143: 0.76 | J143: 0.76
B144: Wholesale | C144: 0.5 | D144: 0.5 | E144: 0.5 | F144: 0.5 | G144: 0.5 | H144: 0.5 | I144: 0.5 | J144: 0.5
B145: Group | C145: =(C143*C139)+(C144*C140) -> 0.6057361 | D145: =(D143*D139)+(D144*D140) -> 0.6087359 | E145: =(E143*E139)+(E144*E140) -> 0.61779807 | F145: =(F143*F139)+(F144*F140) -> 0.62301338 | G145: =(G143*G139)+(G144*G140) -> 0.62783262 | H145: =(H143*H139)+(H144*H140) -> 0.63141231 | I145: =(I143*I139)+(I144*I140) -> 0.63272831 | J145: =(J143*J139)+(J144*J140) -> 0.63421303
D146: =D145-C145 -> 0.0029997994 | E146: =E145-D145 -> 0.009062169 | F146: =F145-E145 -> 0.0052153134 | G146: =G145-F145 -> 0.0048192336 | H146: =H145-G145 -> 0.0035796987 | I146: =I145-H145 -> 0.0013159922 | J146: =J145-I145 -> 0.0014847286
B149: Graphic:
C150: 2024E | D150: 2025E | E150: 2026E | F150: 2027E | G150: 2028E | H150: 2029E | I150: 2030E | J150: 2031E
B151: DTC sales mix | C151: =C139 -> 0.40667731 | D151: =D139 -> 0.418215 | E151: =E139 -> 0.45306949 | F151: =F139 -> 0.47312839 | G151: =G139 -> 0.4916639 | H151: =H139 -> 0.50543198 | I151: =I139 -> 0.51049348 | J151: =J139 -> 0.51620398
B152: Group GM% (RHS) | C152: =C145 -> 0.6057361 | D152: =D145 -> 0.6087359 | E152: =E145 -> 0.61779807 | F152: =F145 -> 0.62301338 | G152: =G145 -> 0.62783262 | H152: =H145 -> 0.63141231 | I152: =I145 -> 0.63272831 | J152: =J145 -> 0.63421303
C172: 2024E | D172: 2025E | E172: 2026E | F172: 2027E | G172: 2028E | H172: 2029E | I172: 2030E | J172: 2031E
B173: DTC sales mix delta | C173: =MODEL!AJ82-MODEL!AE82 -> 0.031809833 | D173: =D151-C151 -> 0.01153769 | E173: =E151-D151 -> 0.034854496 | F173: =F151-E151 -> 0.020058898 | G173: =G151-F151 -> 0.018535514 | H173: =H151-G151 -> 0.013768072 | I173: =I151-H151 -> 0.0050615084 | J173: =J151-I151 -> 0.0057104945
B174: Group GM% delta (RHS) | C174: =MODEL!AJ136-MODEL!AE136 -> 0.010835725 | D174: =D152-C152 -> 0.0029997994 | E174: =E152-D152 -> 0.009062169 | F174: =F152-E152 -> 0.0052153134 | G174: =G152-F152 -> 0.0048192336 | H174: =H152-G152 -> 0.0035796987 | I174: =I152-H152 -> 0.0013159922 | J174: =J152-I152 -> 0.0014847286
C194: 2024E | D194: 2025E | E194: 2026E | F194: 2027E | G194: 2028E | H194: 2029E | I194: 2030E | J194: 2031E
B195: On opex/sales | C195: =E227-E229 -> 0.51449421 | D195: =F227-F229 -> 0.48365295 | E195: =G227-G229 -> 0.48019184 | F195: =H227-H229 -> 0.47868101 | G195: =I227-I229 -> 0.47538515 | H195: =J227-J229 -> 0.47170577 | I195: =K227-K229 -> 0.47021277 | J195: =L227-L229 -> 0.46831746
B196: Lulu opex/sales | C196: ='[4]2. Consolidated'!CY38-'[4]2. Consolidated'!CY53 -> 0.35188686 | D196: ='[4]2. Consolidated'!DD38-'[4]2. Consolidated'!DD53 -> 0.35228018 | E196: ='[4]2. Consolidated'!DI38-'[4]2. Consolidated'!DI53 -> 0.3507861
B197: Nike opex/sales | C197: ='[5]Income Statement'!CO61-'[5]Income Statement'!CO78 -> 0.33385575 | D197: ='[5]Income Statement'!CT61-'[5]Income Statement'!CT78 -> 0.33062817 | E197: ='[5]Income Statement'!CY61-'[5]Income Statement'!CY78 -> 0.32972819
B198: Puma opex/sales | C198: ='[6]P&L'!AF126-'[6]P&L'!AF162 -> 0.40329129 | D198: ='[6]P&L'!AG126-'[6]P&L'!AG162 -> 0.47220471 | E198: ='[6]P&L'!AH126-'[6]P&L'!AH162 -> 0.47574136 | F198: ='[6]P&L'!AI126-'[6]P&L'!AI162 -> 0.4449262 | G198: ='[6]P&L'!AJ126-'[6]P&L'!AJ162 -> 0.42662226
B199: Adidas opex/sales | C199: ='[7]Profit and Loss'!AE335-'[7]Profit and Loss'!AE370 -> 0.45563604 | D199: ='[7]Profit and Loss'!AF335-'[7]Profit and Loss'!AF370 -> 0.43618546 | E199: ='[7]Profit and Loss'!AG335-'[7]Profit and Loss'!AG370 -> 0.41531101 | F199: ='[7]Profit and Loss'!AH335-'[7]Profit and Loss'!AH370 -> 0.40930182 | G199: ='[7]Profit and Loss'!AI335-'[7]Profit and Loss'!AI370 -> 0.40525654
B202: Sales mix
C203: 2022 | D203: 2023 | E203: 2024E | F203: 2025E | G203: 2026E | H203: 2027E | I203: 2028E | J203: 2029E | K203: 2030E | L203: 2031E
B204: DTC | C204: =1-C205 -> 0.36420915 | D204: =1-D205 -> 0.37486747 | E204: =1-E205 -> 0.40667731 | F204: =1-F205 -> 0.418215 | G204: =1-G205 -> 0.45306949 | H204: =1-H205 -> 0.47312839 | I204: =1-I205 -> 0.4916639 | J204: =1-J205 -> 0.50543198 | ... L204: =1-L205 -> 0.51620398
B205: Wholesale | C205: =MODEL!Z119 -> 0.63579085 | D205: =MODEL!AE119 -> 0.62513253 | E205: =MODEL!AJ119 -> 0.59332269 | F205: =MODEL!AO119 -> 0.581785 | G205: =MODEL!AT119 -> 0.54693051 | H205: =MODEL!AU119 -> 0.52687161 | I205: =MODEL!AV119 -> 0.5083361 | J205: =MODEL!AW119 -> 0.49456802 | K205: =MODEL!AX119 -> 0.48950652 | L205: =MODEL!AY119 -> 0.48379602
B207: Contribution margin
C208: 2022 | D208: 2023 | E208: 2024E | F208: 2025E | G208: 2026E | H208: 2027E | I208: 2028E | J208: 2029E | K208: 2030E | L208: 2031E
B209: DTC | C209: =MODEL!Z90 -> 0.32037295 | D209: =C209+(MODEL!AE137/10000) -> 0.35544666 | E209: =D209 -> 0.35544666 | F209: =E209 -> 0.35544666 | G209: =F209 -> 0.35544666 | H209: =G209+0.002 -> 0.35744666 | I209: =H209+0.002 -> 0.35944666 | J209: =I209+0.002 -> 0.36144666 | K209: =J209+0.002 -> 0.36344666 | L209: =K209+0.002 -> 0.36544666 | M209: =L209-G209 -> 0.01
B210: Wholesale | C210: =MODEL!Z127 -> 0.226 | D210: =(D211-(D209*D204))/D205 -> 0.23191193 | E210: =(E211-(E209*E204))/E205 -> 0.24531616 | F210: =(F211-(F209*F204))/F205 -> 0.27719389 | G210: =(G211-(G209*G204))/G205 -> 0.29063649 | H210: =(H211-(H209*H204))/H205 -> 0.29396504 | I210: =(I211-(I209*I204))/I205 -> 0.29758471 | J210: =(J211-(J209*J204))/J205 -> 0.3019065 | K210: =(K211-(K209*K204))/K205 -> 0.30329085 | L210: =(L211-(L209*L204))/L205 -> 0.3045808 | M210: =L210-G210 -> 0.013944313
B211: Group | C211: =MODEL!Z149 -> 0.26037149 | D211: =MODEL!AE149 -> 0.27822108 | E211: =MODEL!AJ149 -> 0.29010374 | F211: =MODEL!AO149 -> 0.30992037 | G211: =MODEL!AT149 -> 0.32 | H211: =MODEL!AU149 -> 0.324 | I211: =MODEL!AV149 -> 0.328 | J211: =MODEL!AW149 -> 0.332 | K211: =MODEL!AX149 -> 0.334 | L211: =MODEL!AY149 -> 0.336 | M211: =L211-G211 -> 0.016
B213: Fixed costs
B214: Admin/sales | C214: =MODEL!Z152 -> 0.12511251 | D214: =MODEL!AE152 -> 0.12370961 | E214: =MODEL!AJ152 -> 0.12290243 | F214: =MODEL!AO152 -> 0.12179827 | G214: =MODEL!AT152 -> 0.12012436 | H214: =MODEL!AU152 -> 0.11839822 | I214: =MODEL!AV152 -> 0.11528313 | J214: =MODEL!AW152 -> 0.11202404 | K214: =MODEL!AX152 -> 0.11121505 | L214: =MODEL!AY152 -> 0.10983502 | M214: =L214-G214 -> -0.010289339
B215: Depreciation/sales | C215: =MODEL!Z159 -> 0.037967433 | D215: =MODEL!AE159 -> 0.036214497 | E215: =MODEL!AJ159 -> 0.04511843 | F215: =MODEL!AO159 -> 0.042269409 | G215: =MODEL!AT159 -> 0.042269409 | H215: =MODEL!AU159 -> 0.041269409 | I215: =MODEL!AV159 -> 0.040269409 | J215: =MODEL!AW159 -> 0.040269409 | K215: =MODEL!AX159 -> 0.040269409 | L215: =MODEL!AY159 -> 0.040269409 | M215: =L215-G215 -> -0.002
B216: SBC/sales | C216: =MODEL!Z162 -> 0.027657311 | D216: =MODEL!AE162 -> 0.017744546 | E216: =MODEL!AJ162 -> 0.030840992 | F216: =MODEL!AO162 -> 0.020769741 | G216: =MODEL!AT162 -> 0.02 | H216: =MODEL!AU162 -> 0.02 | I216: =MODEL!AV162 -> 0.02 | J216: =MODEL!AW162 -> 0.02 | K216: =MODEL!AX162 -> 0.02 | L216: =MODEL!AY162 -> 0.02
B217: adj EBIT margin | C217: =C211-C215-C214-C216 -> 0.069634236 | D217: =D211-D215-D214-D216 -> 0.10055242 | E217: =E211-E215-E214-E216 -> 0.091241887 | F217: =F211-F215-F214-F216 -> 0.12508295 | G217: =G211-G215-G214-G216 -> 0.13760623 | H217: =H211-H215-H214-H216 -> 0.14433237 | I217: =I211-I215-I214-I216 -> 0.15244746 | J217: =J211-J215-J214-J216 -> 0.15970655 | ... L217: =L211-L215-L214-L216 -> 0.16589557 | M217: =L217-G217 -> 0.028289339
D220: 2023 | E220: 2024E | F220: 2025E | G220: 2026E | H220: 2027E | I220: 2028E | J220: 2029E | K220: 2030E | L220: 2031E
B221: Change in Contribution margin | D221: =D211-C211 -> 0.01784959 | E221: =E211-D211 -> 0.011882657 | F221: =F211-E211 -> 0.019816633 | G221: =G211-F211 -> 0.010079628 | H221: =H211-G211 -> 0.004 | I221: =I211-H211 -> 0.004 | J221: =J211-I211 -> 0.004 | K221: =K211-J211 -> 0.002 | L221: =L211-K211 -> 0.002
B222: Change in Admin costs | D222: =D214-C214 -> -0.0014028968 | E222: =E214-D214 -> -0.00080718466 | F222: =F214-E214 -> -0.001104155 | G222: =G214-F214 -> -0.0016739148 | H222: =H214-G214 -> -0.0017261434 | I222: =I214-H214 -> -0.0031150864 | J222: =J214-I214 -> -0.0032590856 | K222: =K214-J214 -> -0.00080899432 | L222: =L214-K214 -> -0.0013800293
B223: Change in adj EBIT margin | D223: =D217-C217 -> 0.030918188 | E223: =E217-D217 -> -0.0093105372 | F223: =F217-E217 -> 0.033841059 | G223: =G217-F217 -> 0.012523284 | H223: =H217-G217 -> 0.0067261434 | I223: =I217-H217 -> 0.0081150864 | J223: =J217-I217 -> 0.0072590856 | K223: =K217-J217 -> 0.0028089943 | L223: =L217-K217 -> 0.0033800293
C226: 2022 | D226: 2023 | E226: 2024E | F226: 2025E | G226: 2026E | H226: 2027E | I226: 2028E | J226: 2029E | K226: 2030E | L226: 2031E
B227: Gross margin | C227: =MODEL!Z136 -> 0.56042877 | D227: =MODEL!AE136 -> 0.59550248 | E227: =C145 -> 0.6057361 | F227: =D145 -> 0.6087359 | G227: =E145 -> 0.61779807 | H227: =F145 -> 0.62301338 | I227: =G145 -> 0.62783262 | J227: =H145 -> 0.63141231 | K227: =I145 -> 0.63272831 | L227: =J145 -> 0.63421303
B228: Contribution margin | C228: =C211 -> 0.26037149 | D228: =D211 -> 0.27822108 | E228: =E211 -> 0.29010374 | F228: =F211 -> 0.30992037 | G228: =G211 -> 0.32 | H228: =H211 -> 0.324 | I228: =I211 -> 0.328 | J228: =J211 -> 0.332 | ... L228: =L211 -> 0.336
B229: EBIT margin (RHS) | C229: =C217 -> 0.069634236 | D229: =D217 -> 0.10055242 | E229: =E217 -> 0.091241887 | F229: =F217 -> 0.12508295 | G229: =G217 -> 0.13760623 | H229: =H217 -> 0.14433237 | I229: =I217 -> 0.15244746 | J229: =J217 -> 0.15970655 | ... L229: =L217 -> 0.16589557
B250: Margin drivers FY26E
C251: Puma | D251: Adidas | E251: On Holding | F251: On Holding long term
B252: GM% | C252: ='[6]P&L'!$AH$126 -> 0.47 | D252: ='[8]Profit and Loss'!$AG$335 -> 0.515 | E252: =G227 -> 0.61779807 | F252: =Valuation!T54 -> 0.66
B253: Opex/sales | C253: =C252-C254 -> 0.47574136 | D253: =D252-D254 -> 0.42034407 | E253: =E252-E254 -> 0.48019184 | F253: =F252-F254 -> 0.49010443
B254: EBIT margin | C254: ='[6]P&L'!$AH$162 -> -0.005741362 | D254: ='[8]Profit and Loss'!$AG$375 -> 0.094655931 | E254: =G229 -> 0.13760623 | F254: =Valuation!T56+(Valuation!T16/Valuation!T49) -> 0.16989557

Sheet Vs consensus
C1: 2021E | F1: 2022E | I1: 2023E | L1: 2024E
C2: GSe | D2: Guidance | E2: GSe/Guidance | F2: GSe | G2: Guidance | H2: GSe/Guidance | I2: GSe | J2: Guidance | K2: GSe/Guidance | L2: GSe | M2: Guidance | N2: GSe/Guidance | Q2: GSe vs VA Consensus | R2: 2022E | U2: 2023E | X2: 2024E | AA2: 2025E
B3: Sales | C3: =MODEL!U131 -> 724.6 | D3: ='[9]Income Statement'!$Q$13/1000000 -> 684.21326 | E3: =C3/D3-1 -> 0.059026539 | F3: =MODEL!Z131 -> 1222.1 | G3: ='[9]Income Statement'!$V$13/1000000 -> 906.93526 | H3: =F3/G3-1 -> 0.34750522 | I3: =MODEL!AE131 -> 1792.1 | J3: ='[9]Income Statement'!$W$13/1000000 -> 1301.0006 | K3: =I3/J3-1 -> 0.37747828 | L3: =MODEL!AJ131 -> 2318.3 | M3: ='[9]Income Statement'!$X$13/1000000 -> 1711.1554 | N3: =L3/M3-1 -> 0.35481562 | R3: GSe | S3: Cons | T3: % diff | U3: GSe | V3: Cons | W3: % diff | X3: GSe | Y3: Cons | Z3: % diff | AA3: GSe | AB3: Cons | AC3: % diff
B4: Gross profit | C4: =MODEL!U135 -> 430.3 | D4: ='[9]Income Statement'!$Q$19/1000000 -> 388.78328 | E4: =C4/D4-1 -> 0.10678627 | F4: =MODEL!Z135 -> 684.9 | G4: ='[9]Income Statement'!$V$19/1000000 -> 520.13771 | H4: =F4/G4-1 -> 0.31676668 | I4: =MODEL!AE135 -> 1067.2 | J4: ='[9]Income Statement'!$W$19/1000000 -> 761.15061 | K4: =I4/J4-1 -> 0.40208782 | L4: =MODEL!AJ135 -> 1405.6739 | M4: ='[9]Income Statement'!$X$19/1000000 -> 1004.8565 | N4: =L4/M4-1 -> 0.39888017 | P4: X | Q4: Sales | R4: =MODEL!$Z$131 -> 1222.1 | S4: 1130 | T4: =R4/S4-1 -> 0.081504425 | U4: =MODEL!AE131 -> 1792.1 | V4: 1549.6 | W4: =U4/V4-1 -> 0.156492 | X4: =MODEL!AJ131 -> 2318.3 | Y4: 2031.4 | Z4: =X4/Y4-1 -> 0.14123265 | AA4: =MODEL!AO131 -> 3014 | AB4: 2486 | AC4: =AA4/AB4-1 -> 0.21238938
B5: EBITDA | C5: =MODEL!U153 -> 96.386 | D5: ='[9]Income Statement'!$Q$68/1000000 -> 85.803851 | E5: =C5/D5-1 -> 0.12332953 | F5: =MODEL!Z153 -> 165.3 | G5: ='[9]Income Statement'!$V$68/1000000 -> 120.26466 | H5: =F5/G5-1 -> 0.3744686 | I5: =MODEL!AE153 -> 276.9 | J5: ='[9]Income Statement'!$W$68/1000000 -> 195.44336 | K5: =I5/J5-1 -> 0.41677879 | L5: =MODEL!AJ153 -> 387.62279 | M5: ='[9]Income Statement'!$X$68/1000000 -> 267.46207 | N5: =L5/M5-1 -> 0.44926269 | P5: X | Q5: Gross Margins | R5: =MODEL!Z136 -> 0.56042877 | S5: =S12/S4 -> 0.55955752 | T5: =(R5-S5)*10000 -> 8.7124803 | U5: =MODEL!AE136 -> 0.59550248 | V5: =V12/V4 -> 0.58066598 | W5: =(U5-V5)*10000 -> 148.36505 | X5: =MODEL!AJ136 -> 0.60633821 | Y5: =Y12/Y4 -> 0.58983952 | Z5: =(X5-Y5)*10000 -> 164.98688 | AA5: =MODEL!AO136 -> 0.62826808 | AB5: =AB12/AB4 -> 0.59782784 | AC5: =(AA5-AB5)*10000 -> 304.40246
B6: EBIT | C6: =MODEL!U163 -> -141.121 | D6: ='[9]Income Statement'!$Q$37/1000000 -> -98.359035 | E6: =C6/D6-1 -> 0.43475381 | F6: =MODEL!Z163 -> 85.1 | G6: ='[9]Income Statement'!$V$37/1000000 -> -26.830969 | H6: =F6/G6-1 -> -4.1717081 | I6: =MODEL!AE163 -> 180.2 | J6: ='[9]Income Statement'!$W$37/1000000 -> 96.476642 | K6: =I6/J6-1 -> 0.86780963 | L6: =MODEL!AJ163 -> 211.52607 | M6: ='[9]Income Statement'!$X$37/1000000 -> 144.7204 | N6: =L6/M6-1 -> 0.46161886 | P6: X | Q6: adj. EBITDA margin | R6: =MODEL!Z155 -> 0.13525898 | S6: =S7/S4 -> 0.13097345 | T6: =(R6-S6)*10000 -> 42.855291 | U6: =MODEL!AE155 -> 0.15451147 | V6: =V7/V4 -> 0.15326536 | W6: =(U6-V6)*10000 -> 12.461082 | X6: =MODEL!AJ155 -> 0.16720131 | Y6: =Y7/Y4 -> 0.16589544 | Z6: =(X6-Y6)*10000 -> 13.05867 | AA6: =MODEL!AO155 -> 0.1881221 | AB6: =AB7/AB4 -> 0.16556718 | AC6: =(AA6-AB6)*10000 -> 225.54921
B7: PBT | C7: =MODEL!U167 -> -159.621 | D7: ='[9]Income Statement'!$Q$42/1000000 -> -99.385355 | E7: =C7/D7-1 -> 0.60608171 | F7: =MODEL!Z167 -> 77.9 | G7: ='[9]Income Statement'!$V$42/1000000 -> -28.191371 | H7: =F7/G7-1 -> -3.7632568 | I7: =MODEL!AE167 -> 69.1 | J7: ='[9]Income Statement'!$W$42/1000000 -> 94.525141 | K7: =I7/J7-1 -> -0.26897755 | L7: =MODEL!AJ167 -> 279.62607 | M7: ='[9]Income Statement'!$X$42/1000000 -> 142.15367 | N7: =L7/M7-1 -> 0.96706896 | P7: X | Q7: adj. EBITDA | R7: =MODEL!$Z$153 -> 165.3 | S7: 148 | T7: =R7/S7-1 -> 0.11689189 | U7: =MODEL!AE153 -> 276.9 | V7: 237.5 | W7: =U7/V7-1 -> 0.16589474 | X7: =MODEL!AJ153 -> 387.62279 | Y7: 337 | Z7: =X7/Y7-1 -> 0.150216 | AA7: =MODEL!AO153 -> 567 | AB7: 411.6 | AC7: =AA7/AB7-1 -> 0.37755102
B8: PAT | C8: =MODEL!U170 -> -170.20514 | D8: ='[9]Income Statement'!$Q$47/1000000 -> -111.92104 | E8: =C8/D8-1 -> 0.52076079 | F8: =MODEL!Z170 -> 57.7 | G8: ='[9]Income Statement'!$V$47/1000000 -> -46.920217 | H8: =F8/G8-1 -> -2.2297471 | I8: =MODEL!AE170 -> 79.6 | J8: ='[9]Income Statement'!$W$47/1000000 -> 62.384915 | K8: =I8/J8-1 -> 0.27594948 | L8: =MODEL!AJ170 -> 242.29662 | M8: ='[9]Income Statement'!$X$47/1000000 -> 96.886316 | N8: =L8/M8-1 -> 1.5008343 | Q8: PBT | R8: =MODEL!$Z$167 -> 77.9 | S8: 139 | T8: =R8/S8-1 -> -0.43956835 | U8: =MODEL!AE167 -> 69.1 | W8: =U8/V8-1 -> #DIV/0! | X8: =MODEL!AJ167 -> 279.62607 | Z8: =X8/Y8-1 -> #DIV/0! | AA8: =MODEL!AO167 -> 205.2 | AC8: =AA8/AB8-1 -> #DIV/0!
B9: Capex | C9: =MODEL!U197 -> -24.64 | D9: ='[9]Cash Flow'!$Q$32/1000000 -> -50.7 | E9: =C9/D9-1 -> -0.51400394 | F9: =MODEL!Z201 -> -82.9 | G9: ='[9]Cash Flow'!$V$32/1000000 -> -39.5 | H9: =F9/G9-1 -> 1.0987342 | I9: =MODEL!AE201 -> -47.2 | J9: ='[9]Cash Flow'!$W$32/1000000 -> -51.96 | K9: =I9/J9-1 -> -0.09160893 | L9: =MODEL!AJ201 -> -64.9 | M9: ='[9]Cash Flow'!$X$32/1000000 -> -63.888 | N9: =L9/M9-1 -> 0.01584022 | P9: X | Q9: adj. EPS* | R9: =MODEL!$Z$179 -> 0.32489405 | S9: 0.35 | T9: =R9/S9-1 -> -0.071731292 | U9: =MODEL!AE179 -> 0.35 | V9: 0.45 | W9: =U9/V9-1 -> -0.22222222 | X9: =MODEL!AJ179 -> 0.98 | Y9: 0.65 | Z9: =X9/Y9-1 -> 0.50769231 | AA9: =MODEL!AO179 -> 0.81 | AB9: 0.67 | AC9: =AA9/AB9-1 -> 0.20895522
B10: Depreciation | C10: =MODEL!U185 -> 31.4 | D10: ='[3]Cash Flow'!$Q$18/1000000 -> 24.662886 | E10: =C10/D10-1 -> 0.27316812 | F10: =MODEL!Z185 -> 46.4 | G10: ='[3]Cash Flow'!$V$18/1000000 -> 36.00083 | H10: =F10/G10-1 -> 0.28885919 | I10: =MODEL!AE185 -> 64.9 | J10: ='[3]Cash Flow'!$W$18/1000000 -> 50.584677 | K10: =I10/J10-1 -> 0.28299722 | L10: =MODEL!AJ185 -> 104.59806 | M10: ='[3]Cash Flow'!$X$18/1000000 -> 63.896454 | N10: =L10/M10-1 -> 0.63699312 | Q10: Net cash | R10: =MODEL!$Z$212 -> 370.98 | S10: 601 | T10: =R10/S10-1 -> -0.38272879 | U10: =MODEL!AE212 -> 494.58 | V10: 621 | W10: =U10/V10-1 -> -0.20357488 | X10: =MODEL!AJ212 -> 924.30412 | Y10: 687.2 | Z10: =X10/Y10-1 -> 0.34502928 | AA10: =MODEL!AO212 -> 1019.9041 | AB10: 880 | AC10: =AA10/AB10-1 -> 0.15898196
B11: Net cash | C11: =MODEL!U212 -> 653.08 | D11: ='[9]Cash Flow'!$Q$54/1000000 -> 503.69823 | E11: =C11/D11-1 -> 0.29656996 | F11: =MODEL!Z212 -> 370.98 | G11: ='[9]Cash Flow'!$V$54/1000000 -> 479.53136 | H11: =F11/G11-1 -> -0.22636967 | I11: =MODEL!AE212 -> 494.58 | J11: ='[9]Cash Flow'!$W$54/1000000 -> 486.7676 | K11: =I11/J11-1 -> 0.016049556 | L11: =MODEL!AJ212 -> 924.30412 | M11: ='[9]Cash Flow'!$X$54/1000000 -> 521.69234 | N11: =L11/M11-1 -> 0.7717418
S12: 632.3 | V12: 899.8 | Y12: 1198.2 | AB12: 1486.2
J13: Long term guide
J14: Sales | L14: =MODEL!AJ132 -> 0.332 | M14: +20-25% pa
J15: Gross margin | L15: =MODEL!AJ136 -> 0.60633821 | M15: 60%+
J16: Adj EBITDA growth | L16: =MODEL!AJ154 -> 0.39986563 | M16: +25-30% pa
J17: Adj EBITDA margin | L17: =MODEL!AJ155 -> 0.16720131 | M17: High teens
C25: New vs Old Estimates
D26: New | G26: Old | J26: Change
D27: FY21 | E27: FY22 | F27: FY23 | G27: FY21 | H27: FY22 | I27: FY23 | J27: FY21 | K27: FY22 | L27: FY23
C28: Group Sales | D28: =MODEL!U31 -> 724.6 | E28: =MODEL!Z31 -> 1222.1 | F28: =MODEL!AE31 -> 1792.1 | G28: 683 | H28: 905.3 | I28: 1298 | J28: =D28/G28-1 -> 0.06090776 | K28: =E28/H28-1 -> 0.34993925 | L28: =F28/I28-1 -> 0.38066256
C29: Gross Margins | D29: =MODEL!U136 -> 0.59384488 | E29: =MODEL!Z136 -> 0.56042877 | F29: =MODEL!AE136 -> 0.59550248 | G29: 0.568 | H29: 0.574 | I29: 0.586 | J29: =(D29-G29)*100 -> 2.584488 | K29: =(E29-H29)*10000 -> -135.7123 | L29: =(F29-I29)*10000 -> 95.024831
C30: Adj EBITDA | D30: =MODEL!U153 -> 96.386 | E30: =MODEL!Z153 -> 165.3 | F30: =MODEL!AE153 -> 276.9 | G30: 86 | H30: 121 | I30: 194 | J30: =D30/G30-1 -> 0.12076744 | K30: =E30/H30-1 -> 0.3661157 | L30: =F30/I30-1 -> 0.42731959
C31: EBITDA Margin | D31: =D30/D28 -> 0.1330196 | E31: =E30/E28 -> 0.13525898 | F31: =F30/F28 -> 0.15451147 | G31: =G30/G28 -> 0.12591508 | H31: =H30/H28 -> 0.13365735 | I31: =I30/I28 -> 0.14946071 | J31: =(D31-G31)*100 -> 0.71045165 | K31: =(E31-H31)*10000 -> 16.016293 | L31: =(F31-I31)*10000 -> 50.507582

Sheet Stat Ab
A1: STAT AB | B1: PRICE | C1: =F1/Valuation!H37 -> 36.411784 | D1: CHF | F1: 44 | G1: US$
S2: OLD | T2: NEW
A3: Yr to Dec | B3: EBIT (CHFm) | C3: EBITDA (CHFm) | D3: EPS, CHF (New) | E3: EPS, CHF (Old) | F3: DPS, CHF | G3: P/E | H3: Div Yld (%) | I3: EV/NOPAT | J3: EV/EBIT | K3: EV/EBITDA | N3: Net cash(Debt) | O3: FCF | P3: NOPAT | Q3: Sales | R3: # shares | S3: Straight EBITDA | U3: Delta
A4: 2020A | N4: =MODEL!N212 -> 90.595753
A5: 2021A | N5: =MODEL!U212 -> 653.08 | O5: =Valuation!C23 -> -18.513 | P5: =SUM(Valuation!C15:C17,Valuation!C19) -> 41.226 | Q5: =Valuation!C49 -> 724.6 | R5: =MODEL!U174 -> 264.171 | S5: =MODEL!$U$153 -> 96.386 | T5: =MODEL!U153 -> 96.386 | U5: =T5/S5-1 -> 0
A6: 2022A | B6: =MODEL!Z163 -> 85.1 | C6: =Valuation!D15+Valuation!D18+Valuation!D19+Valuation!D16 -> 116.1 | D6: =MODEL!Z176 -> 0.18254678 | E6: 0.18254678 | L6: =D6/E6-1 -> 0 | N6: =MODEL!Z212 -> 370.98 | O6: =Valuation!D23 -> -308.84 | P6: =MODEL!Z163*(1-0.225) -> 65.9525 | Q6: =Valuation!D49 -> 1222.1 | R6: =MODEL!Z174 -> 281.63027 | S6: =MODEL!$Z$153 -> 165.3 | T6: =MODEL!Z153 -> 165.3 | U6: =T6/S6-1 -> 0
A7: 2023A | B7: =MODEL!AE163 -> 180.2 | C7: =Valuation!E15+Valuation!E18+Valuation!E19+Valuation!E16 -> 213.1 | D7: =MODEL!AE176 -> 0.24950011 | E7: 0.24950011 | G7: =$C$1/D7 -> 145.93895 | I7: =($D$15-N7)/(P7*0.891) -> 84.766228 | J7: =($D$15-N7)/(B7*0.891) -> 65.693827 | K7: =($D$15-N7)/(C7*0.891) -> 55.551514 | L7: =D7/E7-1 -> 0 | N7: =MODEL!AE212 -> 494.58 | O7: =Valuation!E23 -> 209.1 | P7: =MODEL!AE163*(1-0.225) -> 139.655 | Q7: =Valuation!E49 -> 1792.1 | R7: =MODEL!AE174 -> 284.2628 | S7: =MODEL!$AA$153 -> 61 | T7: =MODEL!AE153 -> 276.9 | U7: =T7/S7-1 -> 3.5393443
A8: 2024A | B8: =MODEL!AJ163 -> 211.52607 | C8: =Valuation!F15+Valuation!F18+Valuation!F19+Valuation!F16 -> 249.62412 | D8: =MODEL!AJ176 -> 0.74839585 | E8: 0.74839585 | G8: =$C$1/D8 -> 48.653108 | I8: =($D$15-N8)/(P8*0.891) -> 69.270702 | J8: =($D$15-N8)/(B8*0.891) -> 53.684794 | K8: =($D$15-N8)/(C8*0.891) -> 45.49133 | L8: =D8/E8-1 -> 0 | N8: =MODEL!AJ212 -> 924.30412 | O8: =Valuation!F23 -> 213.25541 | P8: =MODEL!AJ163*(1-0.225) -> 163.9327 | Q8: =Valuation!F49 -> 2318.3 | R8: =MODEL!AJ174 -> 288.46538 | S8: =MODEL!$AB$153 -> 62.7 | T8: =MODEL!AJ153 -> 387.62279 | U8: =T8/S8-1 -> 5.1821817
A9: 2025A | B9: =MODEL!AO163 -> 377 | C9: =Valuation!G15+Valuation!G18+Valuation!G19+Valuation!G16 -> 413 | D9: =MODEL!AO176 -> 0.61409639 | E9: 0.61409639 | G9: =$C$1/D9 -> 59.293272 | I9: =($D$15-N9)/(P9*0.891) -> 38.498976 | J9: =($D$15-N9)/(B9*0.891) -> 29.836706 | K9: =($D$15-N9)/(C9*0.891) -> 27.235928 | L9: =D9/E9-1 -> 0 | N9: =MODEL!AO212 -> 1019.9041 | O9: =Valuation!G23 -> 195.9985 | P9: =MODEL!AO163*(1-0.225) -> 292.175 | Q9: =Valuation!G49 -> 3014 | R9: =MODEL!AO174 -> 295.55 | S9: =MODEL!$AC$153 -> 81.410901 | T9: =MODEL!AO153 -> 567 | U9: =T9/S9-1 -> 5.9646692
A10: 2026E | B10: =MODEL!AT163 -> 481.91433 | C10: =Valuation!H15+Valuation!H18+Valuation!H19+Valuation!H16 -> 525.60002 | D10: =MODEL!AT176 -> 1.1334549 | E10: 1.1289162 | G10: =$C$1/D10 -> 32.124599 | I10: =($D$15-N10)/(P10*0.891) -> 27.903617 | J10: =($D$15-N10)/(B10*0.891) -> 22.60193 | K10: =($D$15-N10)/(C10*0.891) -> 20.723351 | L10: =D10/E10-1 -> 0.0040204231 | N10: =MODEL!AT212 -> 1337.3179 | O10: =Valuation!H23 -> 157.15222 | P10: =MODEL!AT163*(1-MODEL!AT168) -> 390.35061 | Q10: =Valuation!H49 -> 3502.1258 | R10: =MODEL!AT174 -> 299.98325
A11: 2027E | B11: =MODEL!AU163 -> 600.20968 | C11: =Valuation!I15+Valuation!I18+Valuation!I19+Valuation!I16 -> 650.32937 | D11: =MODEL!AU176 -> 1.3523822 | E11: 1.311882 | G11: =$C$1/D11 -> 26.924182 | I11: =(($C$1*R11)-N11)/(P11*0.891) -> 22.851034 | J11: =($D$15-N11)/(B11*0.891) -> 18.003425 | K11: =($D$15-N11)/(C11*0.891) -> 16.615934 | L11: =D11/E11-1 -> 0.030871799 | N11: =MODEL!AU212 -> 1414.268 | O11: =Valuation!I23 -> 242.69385 | P11: =MODEL!AU163*(1-MODEL!AU168) -> 465.1625 | Q11: =Valuation!I49 -> 4158.5242 | R11: =MODEL!AU174 -> 298.9445
A12: 2028E | B12: =MODEL!AV163 -> 738.16846 | C12: =Valuation!J15+Valuation!J18+Valuation!J19+Valuation!J16 -> 793.87666 | D12: =MODEL!AV176 -> 1.7102301 | E12: 1.5620454 | G12: =$C$1/D12 -> 21.290577 | I12: =(($C$1*R12)-N12)/(P12*0.891) -> 17.745339 | J12: =($D$15-N12)/(B12*0.891) -> 14.361178 | K12: =($D$15-N12)/(C12*0.891) -> 13.35342 | L12: =D12/E12-1 -> 0.094865806 | N12: =MODEL!AV212 -> 1596.7996 | O12: =Valuation!J23 -> 327.15889 | P12: =MODEL!AV163*(1-MODEL!AV168) -> 572.08056 | Q12: =Valuation!J49 -> 4842.1171 | R12: =MODEL!AV174 -> 292.26859
A13: 2029E | B13: =MODEL!AW163 -> 895.18043 | C13: =Valuation!K15+Valuation!K18+Valuation!K19+Valuation!K16 -> 962.00093 | D13: =MODEL!AW176 -> 2.1354565 | E13: =MODEL!$AW$174 -> 285.49254 | G13: =$C$1/D13 -> 17.051054 | I13: =(($C$1*R13)-N13)/(P13*0.891) -> 13.750067 | J13: =($D$15-N13)/(B13*0.891) -> 11.467442 | K13: =($D$15-N13)/(C13*0.891) -> 10.670915 | L13: =D13/E13-1 -> -0.9925201 | N13: =MODEL!AW212 -> 1895.7648 | O13: =Valuation!K23 -> 418.72969 | P13: =MODEL!AW163*(1-MODEL!AW168) -> 693.76484 | Q13: =Valuation!K49 -> 5605.1581 | R13: =MODEL!AW174 -> 285.49254
A14: Gearing | C14: Shares | D14: =MODEL!AT175 -> 303.26068
A15: EV (m) | B15: =D15-N5 -> 10389.183 | C15: MV (CHFm) | D15: =C1*D14 -> 11042.263
C16: MV $mn | D16: =D15*Valuation!H37 -> 13343.47
A18: Target price | C18: =Valuation!H40 -> 44 | F18: PE FY27E | H18: 27x
A19: Capital delta | C19: =C18/F1-1 -> 0 | F19: EV/NOPAT FY27E | H19: 23x
A20: DY | C20: 0 | F20: EV/EBITDA FY27E | H20: 16.5x
A21: TSR | C21: =C20+C19 -> 0
A22: Change to price target

Sheet Valuation
A1: Global sportswear market
A2: Europe | C2: =('[10]Market Size'!R11+'[10]Market Size'!R14)/1000 -> 80.0825 | D2: =('[10]Market Size'!S11+'[10]Market Size'!S14)/1000 -> 77.4972 | E2: =('[10]Market Size'!T11+'[10]Market Size'!T14)/1000 -> 82.5565 | F2: =('[10]Market Size'!U11+'[10]Market Size'!U14)/1000 -> 84.3427 | G2: =('[10]Market Size'!V11+'[10]Market Size'!V14)/1000 -> 87.8641 | H2: =('[10]Market Size'!W11+'[10]Market Size'!W14)/1000 -> 91.7052 | I2: =('[10]Market Size'!X11+'[10]Market Size'!X14)/1000 -> 95.5042 | J2: =('[10]Market Size'!Y11+'[10]Market Size'!Y14)/1000 -> 99.0445
A3: USA | C3: ='[10]Market Size'!R10/1000 -> 138.8329 | D3: ='[10]Market Size'!S10/1000 -> 146.6201 | E3: ='[10]Market Size'!T10/1000 -> 150.1679 | F3: ='[10]Market Size'!U10/1000 -> 158.1389 | G3: ='[10]Market Size'!V10/1000 -> 168.4535 | H3: ='[10]Market Size'!W10/1000 -> 178.0786 | I3: ='[10]Market Size'!X10/1000 -> 188.3644 | J3: ='[10]Market Size'!Y10/1000 -> 198.254
A4: APAC | C4: ='[10]Market Size'!R8/1000 -> 96.9807 | D4: ='[10]Market Size'!S8/1000 -> 92.6689 | E4: ='[10]Market Size'!T8/1000 -> 102.4079 | F4: ='[10]Market Size'!U8/1000 -> 115.9486 | G4: ='[10]Market Size'!V8/1000 -> 127.396 | H4: ='[10]Market Size'!W8/1000 -> 138.8136 | I4: ='[10]Market Size'!X8/1000 -> 150.5322 | J4: ='[10]Market Size'!Y8/1000 -> 163.2104
A5: LatAm | C5: ='[10]Market Size'!R15/1000 -> 17.3125 | D5: ='[10]Market Size'!S15/1000 -> 20.7585 | E5: ='[10]Market Size'!T15/1000 -> 25.371 | F5: ='[10]Market Size'!U15/1000 -> 25.3008 | G5: ='[10]Market Size'!V15/1000 -> 26.1208 | H5: ='[10]Market Size'!W15/1000 -> 27.6603 | I5: ='[10]Market Size'!X15/1000 -> 29.5651 | J5: ='[10]Market Size'!Y15/1000 -> 31.5308
A6: Other | C6: =C7-SUM(C2:C5) -> 32.1338 | D6: =D7-SUM(D2:D5) -> 34.6695 | E6: =E7-SUM(E2:E5) -> 35.0113 | F6: =F7-SUM(F2:F5) -> 38.151 | G6: =G7-SUM(G2:G5) -> 41.1958 | H6: =H7-SUM(H2:H5) -> 44.4354 | I6: =I7-SUM(I2:I5) -> 47.998 | J6: =J7-SUM(J2:J5) -> 51.9101
A7: Total (EUR bn) | C7: ='[10]Market Size'!R7/1000 -> 365.3424 | D7: ='[10]Market Size'!S7/1000 -> 372.2142 | E7: ='[10]Market Size'!T7/1000 -> 395.5146 | F7: ='[10]Market Size'!U7/1000 -> 421.882 | G7: ='[10]Market Size'!V7/1000 -> 451.0302 | H7: ='[10]Market Size'!W7/1000 -> 480.6931 | I7: ='[10]Market Size'!X7/1000 -> 511.9639 | J7: ='[10]Market Size'!Y7/1000 -> 543.9498 | K7: =J7*1.05 -> 571.14729 | L7: =K7*1.05 -> 599.70465 | M7: =L7*1.05 -> 629.68989 | N7: =M7*1.05 -> 661.17438 | O7: =N7*1.05 -> 694.2331 | P7: =O7*1.05 -> 728.94476 | Q7: =P7*1.05 -> 765.39199 | R7: =Q7*1.05 -> 803.66159 | ... T7: =S7*1.05 -> 886.03691
A8: On Holding brand sales, at retail (Eur mn) | C8: =MODEL!U78+(MODEL!U115*1.666) -> 1023.7006 | D8: =MODEL!Z78+(MODEL!Z115*1.666) -> 1739.582 | E8: =MODEL!AE78+(MODEL!AE115*1.666) -> 2538.2198 | F8: =MODEL!AJ78+(MODEL!AJ115*1.666) -> 3234.383 | G8: =MODEL!AO78+(MODEL!AO115*1.666) -> 4181.831 | H8: =MODEL!AT78+(MODEL!AT115*1.666) -> 4777.7951 | I8: =MODEL!AU78+(MODEL!AU115*1.666) -> 5617.7358 | J8: =MODEL!AV78+(MODEL!AV115*1.666) -> 6481.4248 | K8: =MODEL!AW78+(MODEL!AW115*1.666) -> 7451.3979 | L8: =MODEL!AX78+(MODEL!AX115*1.666) -> 8499.426 | M8: =MODEL!AY78+(MODEL!AY115*1.666) -> 9470.8615 | N8: =M8*(1+N50) -> 10417.948 | O8: =N8*(1+O50) -> 11459.742 | P8: =O8*(1+P50) -> 12491.119 | Q8: =P8*(1+Q50) -> 13615.32 | R8: =Q8*(1+R50) -> 14840.699 | S8: =R8*(1+S50) -> 16027.955 | T8: =S8*(1+T50) -> 16829.352
A9: On Holding market share | C9: =C8/(C7*1000) -> 0.0028020306 | D9: =D8/(D7*1000) -> 0.0046736046 | E9: =E8/(E7*1000) -> 0.0064175123 | F9: =F8/(F7*1000) -> 0.0076665584 | G9: =G8/(G7*1000) -> 0.0092717317 | H9: =H8/(H7*1000) -> 0.0099393878 | I9: =I8/(I7*1000) -> 0.010972914 | J9: =J8/(J7*1000) -> 0.011915483 | ... T9: =T8/(T7*1000) -> 0.018993963
A10: On Holding performance market share | C10: =C9*0.4 -> 0.0011208123 | D10: =D9*0.4 -> 0.0018694418 | E10: =E9*0.4 -> 0.0025670049 | F10: =F9*0.4 -> 0.0030666234 | G10: =G9*0.4 -> 0.0037086927 | H10: =H9*0.4 -> 0.0039757551 | I10: =I9*0.4 -> 0.0043891656 | J10: =J9*0.4 -> 0.0047661933 | ... T10: =T9*0.4 -> 0.0075975853
A12: On Holding | F12: 0 | G12: 0 | H12: 0 | I12: 0 | J12: =I12+1 -> 1 | K12: =J12+1 -> 2 | L12: =K12+1 -> 3 | M12: =L12+1 -> 4 | N12: =M12+1 -> 5 | O12: =N12+1 -> 6 | P12: =O12+1 -> 7 | Q12: =P12+1 -> 8 | ... T12: =S12+1 -> 11
A14: Dec y/end | B14: 2020 | C14: 2021 | D14: 2022 | E14: 2023 | F14: 2024 | G14: 2025 | H14: 2026E | I14: 2027E | J14: 2028E | K14: 2029E | L14: 2030E | M14: 2031E | N14: 2032E | O14: 2033E | P14: 2034E | Q14: 2035E | R14: 2036E | S14: 2037E | T14: 2038E
A15: adj EBIT | C15: =C55 -> 64.986 | D15: =D55 -> 118.9 | E15: =E55 -> 212 | F15: =F55 -> 283.02474 | G15: =G55 -> 439.6 | H15: =H55 -> 551.95684 | I15: =I55 -> 683.38016 | J15: =J55 -> 835.0108 | ... T15: =T55 -> 2480.6731
A16: SBC charge | C16: =-(MODEL!U161-MODEL!U183) -> -6.06 | D16: =-MODEL!Z161 -> -33.8 | E16: =-MODEL!AE161 -> -31.8 | F16: =-MODEL!AJ161 -> -71.498671 | G16: =-MODEL!AO161 -> -62.6 | H16: =-MODEL!AT161 -> -70.042516 | I16: =-MODEL!AU161 -> -83.170485 | J16: =-MODEL!AV161 -> -96.842343 | K16: =-MODEL!AW161 -> -112.10316 | L16: =-MODEL!AX161 -> -128.19537 | M16: =-MODEL!AY161 -> -143.25825 | N16: =(-0.025)*N49 -> -196.9801 | O16: =(-0.025)*O49 -> -216.67811 | P16: =(-0.025)*P49 -> -236.17914 | Q16: =(-0.025)*Q49 -> -257.43526 | R16: =(-0.025)*R49 -> -280.60443 | S16: =(-0.025)*S49 -> -303.05279 | T16: =(-0.025)*T49 -> -318.20543
A17: Tax | C17: =MODEL!U195 -> -4.4 | D17: =MODEL!Z195 -> -25.4 | E17: =MODEL!AE195 -> -17.6 | F17: =(F15+(F16*0.1))*-0.25 -> -68.968718 | G17: =(G15+(G16*0.1))*-0.225 -> -97.5015 | H17: =(H15+(H16*0.1))*-0.225 -> -122.61433 | I17: =(I15+(I16*0.1))*-0.225 -> -151.8892 | J17: =(J15+(J16*0.1))*-0.225 -> -185.69848 | K17: =(K15+(K16*0.1))*-0.225 -> -224.11649 | L17: =(L15+(L16*0.1))*-0.225 -> -260.33914 | M17: =(M15+(M16*0.1))*-0.225 -> -296.37628 | N17: =(N15+(N16*0.1))*-0.225 -> -332.21878 | ... T17: =(T15+(T16*0.1))*-0.225 -> -550.99183
A18: Depreciation | C18: =C58 -> 31.4 | D18: =D58 -> 46.4 | E18: =E58 -> 64.9 | F18: =F58 -> 104.59806 | G18: =G58 -> 127.4 | H18: =H58 -> 148.03279 | I18: =I58 -> 171.61984 | J18: =J58 -> 194.9892 | ... T18: =T58 -> 512.55779
A19: Rent | C19: =C63 -> -13.3 | D19: =D63 -> -15.4 | E19: =E63 -> -32 | F19: =F63 -> -66.5 | G19: =G63 -> -91.4 | H19: =H63 -> -104.34709 | I19: =I63 -> -121.50015 | J19: =J63 -> -139.28099 | ... T19: =T63 -> -327.90455
A20: Capex | C20: =C60 -> -24.64 | D20: =D60 -> -60.3 | E20: =E60 -> -42.8 | F20: =F60 -> -60.5 | G20: =G60 -> -72.9 | H20: =H60 -> -105.06377 | I20: =I60 -> -124.75573 | J20: =J60 -> -145.26351 | ... T20: =T60 -> -318.20543
A21: Change in other operating assets | C21: =MODEL!U194 -> 8.095 | D21: =MODEL!Z194 -> -67.6 | E21: =MODEL!AE194 -> 93.4 | F21: =MODEL!AJ194 -> 95.7 | G21: =MODEL!AO194 -> 25 | H21: =MODEL!AT194 -> 0 | I21: =MODEL!AU194 -> 0 | J21: =MODEL!AV194 -> 0 | K21: =MODEL!AW194 -> 0 | L21: =MODEL!AX194 -> 0 | M21: =MODEL!AY194 -> 0 | N21: 0 | O21: 0 | P21: 0 | Q21: 0 | R21: 0 | S21: 0 | T21: 0
A22: Delta Working Capital | C22: =B66-C66 -> -74.594 | D22: =C66-D66 -> -271.64 | E22: =D66-E66 -> -37 | F22: =E66-F66 -> -2.6 | G22: =F66-G66 -> -71.6 | H22: =G66-H66 -> -140.76969 | I22: =H66-I66 -> -130.99059 | J22: =I66-J66 -> -135.75578 | ... T22: =S66-T66 -> -121.40238
A23: Free Cashflow | C23: =SUM(C15:C22) -> -18.513 | D23: =SUM(D15:D22) -> -308.84 | E23: =SUM(E15:E22) -> 209.1 | F23: =SUM(F15:F22) -> 213.25541 | G23: =SUM(G15:G22) -> 195.9985 | H23: =SUM(H15:H22) -> 157.15222 | I23: =SUM(I15:I22) -> 242.69385 | J23: =SUM(J15:J22) -> 327.15889 | ... T23: =SUM(T15:T22) -> 1356.5213
A24: Free Cashflow/Sales | C24: =C23/C49 -> -0.025549269 | D24: =D23/D49 -> -0.25271254 | E24: =E23/E49 -> 0.11667876 | F24: =F23/F49 -> 0.091987838 | G24: =G23/G49 -> 0.065029363 | H24: =H23/H49 -> 0.044873381 | I24: =I23/I49 -> 0.058360571 | J24: =J23/J49 -> 0.067565257 | ... T24: =T23/T49 -> 0.10657591
A25: Residual Value | T25: =(T23)/($K$44-$K$45) -> 18257.353
A26: Total Free Cashflow | E26: =E23 -> 209.1 | F26: =F23+F25 -> 213.25541 | G26: =G23+G25 -> 195.9985 | H26: =H23+H25 -> 157.15222 | I26: =I23+I25 -> 242.69385 | J26: =J23+J25 -> 327.15889 | K26: =K23+K25 -> 418.72969 | L26: =L23+L25 -> 509.19767 | M26: =M23+M25 -> 619.31678 | ... T26: =T23+T25 -> 19613.874
A27: Discount Factor | I27: =1/((1+$K$44)^I12) -> 1 | J27: =1/((1+$K$44)^J12) -> 0.90522314 | K27: =1/((1+$K$44)^K12) -> 0.81942893 | L27: =1/((1+$K$44)^L12) -> 0.74176603 | M27: =1/((1+$K$44)^M12) -> 0.67146377 | N27: =1/((1+$K$44)^N12) -> 0.60782454 | O27: =1/((1+$K$44)^O12) -> 0.55021684 | P27: =1/((1+$K$44)^P12) -> 0.49806901 | ... T27: =1/((1+$K$44)^T12) -> 0.3344353
A28: Discounted Free Cashflow | F28: =F26 -> 213.25541 | I28: =I26*I27 -> 242.69385 | J28: =J26*J27 -> 296.1518 | K28: =K26*K27 -> 343.11922 | L28: =L26*L27 -> 377.70553 | M28: =M26*M27 -> 415.84878 | N28: =N26*N27 -> 426.37989 | O28: =O26*O27 -> 440.42209 | P28: =P26*P27 -> 459.12596 | ... T28: =T26*T27 -> 6559.5717
A30: On Holding - DCF Valuation Summary (CHF m)
A31: NPV A shares | H31: =SUM(H28:T28) -> 10919.34
A32: Cash (Debt) | H32: =MODEL!AT212 -> 1337.3179
A33: Valuation | H33: =H31+H32 -> 12256.658
A34: SBC dilution
A35: Total Valuation
A36: Implied PE (12/23)
A37: CHF/$ | H37: =FX!AO5 -> 1.2084
A38: Valuation US$ A shares | H38: =H33*H37*0.891 -> 13196.552
A39: # A shares | H39: =MODEL!AT174 -> 299.98325
A40: Target Price, US$ | H40: =MROUND(H38/H39,1) -> 44
A43: On DCF Assumptions | H43: Rf | I43: Rm | J43: Beta | K43: WACC
A44: Inputs | H44: 0.0417 | I44: 0.045 | J44: 1.4 | K44: =H44+(I44*J44) -> 0.1047
A45: Growth rate | K45: 0.0304
A48: Dec y/end | B48: 2020 | C48: =C14 -> 2021 | D48: =D14 -> 2022 | E48: =E14 -> 2023 | F48: =F14 -> 2024 | G48: =G14 -> 2025 | H48: =H14 -> 2026E | I48: =I14 -> 2027E | J48: =J14 -> 2028E | ... T48: =T14 -> 2038E
A49: On Sales | C49: =MODEL!U131 -> 724.6 | D49: =MODEL!Z131 -> 1222.1 | E49: =MODEL!AE131 -> 1792.1 | F49: =MODEL!AJ131 -> 2318.3 | G49: =MODEL!AO131 -> 3014 | H49: =MODEL!AT131 -> 3502.1258 | I49: =MODEL!AU131 -> 4158.5242 | J49: =MODEL!AV131 -> 4842.1171 | K49: =MODEL!AW131 -> 5605.1581 | L49: =MODEL!AX131 -> 6409.7687 | M49: =MODEL!AY131 -> 7162.9127 | N49: =M49*(1+N50) -> 7879.204 | O49: =N49*(1+O50) -> 8667.1244 | P49: =O49*(1+P50) -> 9447.1656 | Q49: =P49*(1+Q50) -> 10297.41 | R49: =Q49*(1+R50) -> 11224.177 | S49: =R49*(1+S50) -> 12122.112 | T49: =S49*(1+T50) -> 12728.217
A50: - growth yoy | C50: =MODEL!U134 -> 0.70375759 | D50: =D49/C49-1 -> 0.6865857 | E50: =E49/D49-1 -> 0.46641028 | F50: =F49/E49-1 -> 0.29362201 | G50: =G49/F49-1 -> 0.30009058 | H50: =H49/G49-1 -> 0.16195282 | I50: =I49/H49-1 -> 0.18742858 | J50: =J49/I49-1 -> 0.16438353 | K50: =K49/J49-1 -> 0.15758415 | ... M50: =M49/L49-1 -> 0.1174994 | N50: =N51 -> 0.1 | O50: =O51 -> 0.1 | P50: =P51 -> 0.09 | Q50: =Q51 -> 0.09 | R50: =R51 -> 0.09 | S50: =S51 -> 0.08 | T50: =T51 -> 0.05
A51: - cFX | C51: =MODEL!U132 -> 0.7259124 | D51: =MODEL!Z132 -> 0.61025555 | E51: =E50-E52 -> 0.52033913 | F51: =F50-F52 -> 0.32243431 | G51: =G50-G52 -> 0.34092671 | H51: =H50-H52 -> 0.20316158 | I51: =I50-I52 -> 0.18742858 | J51: =J50-J52 -> 0.16438353 | K51: =K50-K52 -> 0.15758415 | L51: =L50-L52 -> 0.14354825 | M51: =M50-M52 -> 0.1174994 | N51: 0.1 | O51: 0.1 | P51: 0.09 | Q51: 0.09 | R51: 0.09 | S51: 0.08 | T51: 0.05
A52: - Ccy | C52: =MODEL!U133 -> -0.012836583 | D52: =MODEL!Z133 -> 0.047402509 | E52: =MODEL!AE133 -> -0.053928853 | F52: =MODEL!AJ133 -> -0.028812307 | G52: =MODEL!AO133 -> -0.04083613 | H52: =MODEL!AT55 -> -0.041208763 | I52: 0 | J52: 0 | K52: 0 | L52: 0 | M52: 0 | N52: 0 | O52: 0 | P52: 0 | Q52: 0 | R52: 0 | S52: 0 | T52: 0
A53: COGS | C53: =MODEL!U251 -> 294.3 | D53: =MODEL!Z251 -> 537.2 | E53: =MODEL!AE251 -> 724.9 | F53: =MODEL!AJ251 -> 912.62613 | G53: =MODEL!AO251 -> 1120.4 | H53: =MODEL!AT251 -> 1225.744 | I53: =MODEL!AU251 -> 1447.1664 | J53: =MODEL!AV251 -> 1675.3725 | K53: =MODEL!AW251 -> 1928.1744 | L53: =MODEL!AX251 -> 2192.1409 | M53: =MODEL!AY251 -> 2435.3903 | N53: =N54*N49 -> 5200.2746 | O53: =O54*O49 -> 5720.3021 | P53: =P54*P49 -> 6235.1293 | Q53: =Q54*Q49 -> 6796.2909 | R53: =R54*R49 -> 7407.9571 | S53: =S54*S49 -> 8000.5936 | T53: =T54*T49 -> 8400.6233
A54: GM% | C54: =(C49-C53)/C49 -> 0.59384488 | D54: =(D49-D53)/D49 -> 0.56042877 | E54: =(E49-E53)/E49 -> 0.59550248 | F54: =(F49-F53)/F49 -> 0.60633821 | G54: =(G49-G53)/G49 -> 0.62826808 | H54: =(H49-H53)/H49 -> 0.65 | I54: =(I49-I53)/I49 -> 0.652 | J54: =(J49-J53)/J49 -> 0.654 | ... M54: =(M49-M53)/M49 -> 0.66 | N54: =M54 -> 0.66 | O54: =N54 -> 0.66 | P54: =O54 -> 0.66 | Q54: =P54 -> 0.66 | R54: =Q54 -> 0.66 | S54: =R54 -> 0.66 | T54: =S54 -> 0.66
A55: adj EBIT | C55: =MODEL!U163+MODEL!U161+MODEL!U160 -> 64.986 | D55: =MODEL!Z163+MODEL!Z161 -> 118.9 | E55: =MODEL!AE163+MODEL!AE161 -> 212 | F55: =MODEL!AJ163+MODEL!AJ161 -> 283.02474 | G55: =MODEL!AO163+MODEL!AO161 -> 439.6 | H55: =MODEL!AT163+MODEL!AT161 -> 551.95684 | I55: =MODEL!AU163+MODEL!AU161 -> 683.38016 | J55: =MODEL!AV163+MODEL!AV161 -> 835.0108 | K55: =MODEL!AW163+MODEL!AW161 -> 1007.2836 | L55: =MODEL!AX163+MODEL!AX161 -> 1169.8824 | M55: =MODEL!AY163+MODEL!AY161 -> 1331.5537 | N55: =N56*N49 -> 1496.2259 | O55: =O56*O49 -> 1671.8499 | P55: =P56*P49 -> 1841.2107 | Q55: =Q56*Q49 -> 2006.9197 | R55: =R56*R49 -> 2187.5424 | S55: =S56*S49 -> 2362.5458 | T55: =T56*T49 -> 2480.6731
A56: adj EBIT/Sales | C56: =C55/C49 -> 0.089685344 | D56: =D55/D49 -> 0.097291547 | E56: =E55/E49 -> 0.11829697 | F56: =F55/F49 -> 0.12208288 | G56: =G55/G49 -> 0.14585269 | H56: =H55/H49 -> 0.15760623 | I56: =I55/I49 -> 0.16433237 | J56: =J55/J49 -> 0.17244746 | ... M56: =M55/M49 -> 0.18589557 | N56: =M56+0.004 -> 0.18989557 | O56: =N56+0.003 -> 0.19289557 | P56: =O56+0.002 -> 0.19489557 | Q56: =P56 -> 0.19489557 | R56: =Q56 -> 0.19489557 | S56: =R56 -> 0.19489557 | T56: =S56 -> 0.19489557
A57: - growth | D57: =(D55/C55)-1 -> 0.82962484 | E57: =(E55/D55)-1 -> 0.78301093 | F57: =(F55/E55)-1 -> 0.33502235 | G57: =(G55/F55)-1 -> 0.55322112 | H57: =(H55/G55)-1 -> 0.25558882 | I57: =(I55/H55)-1 -> 0.23810433 | J57: =(J55/I55)-1 -> 0.2218833 | K57: =(K55/J55)-1 -> 0.20631205 | ... T57: =(T55/S55)-1 -> 0.05
A58: Depreciation | C58: =MODEL!U157 -> 31.4 | D58: =MODEL!Z157 -> 46.4 | E58: =MODEL!AE157 -> 64.9 | F58: =MODEL!AJ157 -> 104.59806 | G58: =MODEL!AO157 -> 127.4 | H58: =MODEL!AT157 -> 148.03279 | I58: =MODEL!AU157 -> 171.61984 | J58: =MODEL!AV157 -> 194.9892 | K58: =MODEL!AW157 -> 225.7164 | L58: =MODEL!AX157 -> 258.1176 | M58: =MODEL!AY157 -> 288.44626 | N58: =N59*N49 -> 317.29089 | O58: =O59*O49 -> 349.01998 | P58: =P59*P49 -> 380.43178 | Q58: =Q59*Q49 -> 414.67064 | R58: =R59*R49 -> 451.991 | S58: =S59*S49 -> 488.15027 | T58: =T59*T49 -> 512.55779
A59: - depn/sales | C59: =C58/C49 -> 0.043334253 | D59: =D58/D49 -> 0.037967433 | E59: =E58/E49 -> 0.036214497 | F59: =F58/F49 -> 0.04511843 | G59: =G58/G49 -> 0.042269409 | H59: =H58/H49 -> 0.042269409 | I59: =I58/I49 -> 0.041269409 | J59: =J58/J49 -> 0.040269409 | ... M59: =M58/M49 -> 0.040269409 | N59: =M59 -> 0.040269409 | O59: =N59 -> 0.040269409 | P59: =O59 -> 0.040269409 | Q59: =P59 -> 0.040269409 | R59: =Q59 -> 0.040269409 | S59: =R59 -> 0.040269409 | T59: =S59 -> 0.040269409
A60: Capex | C60: =MODEL!U197 -> -24.64 | D60: =MODEL!Z197 -> -60.3 | E60: =MODEL!AE197 -> -42.8 | F60: =MODEL!AJ197 -> -60.5 | G60: =MODEL!AO197 -> -72.9 | H60: =MODEL!AT197 -> -105.06377 | I60: =MODEL!AU197 -> -124.75573 | J60: =MODEL!AV197 -> -145.26351 | K60: =MODEL!AW197 -> -168.15474 | L60: =MODEL!AX197 -> -192.29306 | M60: =MODEL!AY197 -> -214.88738 | N60: =-N61*N49 -> -228.49692 | O60: =-O61*O49 -> -242.67948 | P60: =-P61*P49 -> -255.07347 | Q60: =-Q61*Q49 -> -267.73267 | R60: =-R61*R49 -> -291.82861 | S60: =-S61*S49 -> -315.1749 | T60: =-T61*T49 -> -318.20543
A61: - capex/sales | C61: =-C60/C49 -> 0.034004968 | D61: =-D60/D49 -> 0.049341298 | E61: =-E60/E49 -> 0.023882596 | F61: =-F60/F49 -> 0.026096709 | G61: =-G60/G49 -> 0.024187127 | H61: =-H60/H49 -> 0.03 | I61: =-I60/I49 -> 0.03 | J61: =-J60/J49 -> 0.03 | ... M61: =-M60/M49 -> 0.03 | N61: =M61-0.001 -> 0.029 | O61: =N61-0.001 -> 0.028 | P61: =O61-0.001 -> 0.027 | Q61: =P61-0.001 -> 0.026 | R61: =Q61 -> 0.026 | S61: =R61 -> 0.026 | T61: =S61-0.001 -> 0.025
A62: - growth | D62: =(D60/C60)-1 -> 1.4472403 | E62: =(E60/D60)-1 -> -0.29021559 | F62: =(F60/E60)-1 -> 0.4135514 | G62: =(G60/F60)-1 -> 0.20495868 | H62: =(H60/G60)-1 -> 0.44120403 | I62: =(I60/H60)-1 -> 0.18742858 | J62: =(J60/I60)-1 -> 0.16438353 | K62: =(K60/J60)-1 -> 0.15758415 | ... T62: =(T60/S60)-1 -> 0.0096153846
A63: Rent | C63: =MODEL!U204 -> -13.3 | D63: =MODEL!Z204 -> -15.4 | E63: =MODEL!AE204+MODEL!AE207 -> -32 | F63: =MODEL!AJ204+MODEL!AJ207 -> -66.5 | G63: =MODEL!AO204+MODEL!AO207 -> -91.4 | H63: =MODEL!AT204+MODEL!AT207 -> -104.34709 | I63: =MODEL!AU204+MODEL!AU207 -> -121.50015 | J63: =MODEL!AV204+MODEL!AV207 -> -139.28099 | K63: =MODEL!AW204+MODEL!AW207 -> -158.89591 | L63: =MODEL!AX204+MODEL!AX207 -> -179.47046 | M63: =MODEL!AY204+MODEL!AY207 -> -198.8569 | N63: =-N64*N49 -> -210.86339 | O63: =-O64*O49 -> -231.94973 | P63: =-P64*P49 -> -243.37804 | Q63: =-Q64*Q49 -> -265.28206 | R63: =-R64*R49 -> -289.15745 | S63: =-S64*S49 -> -312.29004 | T63: =-T64*T49 -> -327.90455
A64: - rent/sales | C64: =-C63/C49 -> 0.018354954 | D64: =-D63/D49 -> 0.01260126 | E64: =-E63/E49 -> 0.017856146 | F64: =-F63/F49 -> 0.028684812 | G64: =-G63/G49 -> 0.030325149 | H64: =-H63/H49 -> 0.029795359 | I64: =-I63/I49 -> 0.029217132 | J64: =-J63/J49 -> 0.028764483 | ... M64: =-M63/M49 -> 0.027762017 | N64: =M64-0.001 -> 0.026762017 | O64: =N64 -> 0.026762017 | P64: =O64-0.001 -> 0.025762017 | Q64: =P64 -> 0.025762017 | R64: =Q64 -> 0.025762017 | S64: =R64 -> 0.025762017 | T64: =S64 -> 0.025762017
A65: - growth | D65: =(D63/C63)-1 -> 0.15789474 | E65: =(E63/D63)-1 -> 1.0779221 | F65: =(F63/E63)-1 -> 1.078125 | G65: =(G63/F63)-1 -> 0.37443609 | H65: =(H63/G63)-1 -> 0.14165311 | I65: =(I63/H63)-1 -> 0.1643846 | J65: =(J63/I63)-1 -> 0.14634421 | K65: =(K63/J63)-1 -> 0.14082979 | ... T65: =(T63/S63)-1 -> 0.05
A66: Working Capital | B66: =MODEL!N219+MODEL!N220-MODEL!N230 -> 112.966 | C66: =MODEL!U219+MODEL!U220-MODEL!U230 -> 187.56 | D66: =MODEL!Z219+MODEL!Z220-MODEL!Z230 -> 459.2 | E66: =MODEL!AE219+MODEL!AE220-MODEL!AE230 -> 496.2 | F66: =MODEL!AJ219+MODEL!AJ220-MODEL!AJ230 -> 498.8 | G66: =MODEL!AO219+MODEL!AO220-MODEL!AO230 -> 570.4 | H66: =MODEL!AT219+MODEL!AT220-MODEL!AT230 -> 711.16969 | I66: =MODEL!AU219+MODEL!AU220-MODEL!AU230 -> 842.16028 | J66: =MODEL!AV219+MODEL!AV220-MODEL!AV230 -> 977.91606 | K66: =MODEL!AW219+MODEL!AW220-MODEL!AW230 -> 1128.9161 | L66: =MODEL!AX219+MODEL!AX220-MODEL!AX230 -> 1287.4204 | M66: =MODEL!AY219+MODEL!AY220-MODEL!AY230 -> 1434.7248 | N66: =N67*N49 -> 1578.1972 | O66: =O67*O49 -> 1736.017 | P66: =P67*P49 -> 1892.2585 | Q66: =Q67*Q49 -> 2062.5618 | R66: =R67*R49 -> 2248.1923 | S66: =S67*S49 -> 2428.0477 | T66: =T67*T49 -> 2549.4501
A67: - working capital/sales | C67: =C66/C49 -> 0.25884626 | D67: =D66/D49 -> 0.37574667 | E67: =E66/E49 -> 0.27688187 | F67: =F66/F49 -> 0.21515766 | G67: =G66/G49 -> 0.18925017 | H67: =H66/H49 -> 0.203068 | I67: =I66/I49 -> 0.20251422 | J67: =J66/J49 -> 0.20196043 | ... M67: =M66/M49 -> 0.20029907 | N67: =M67 -> 0.20029907 | O67: =N67 -> 0.20029907 | P67: =O67 -> 0.20029907 | Q67: =P67 -> 0.20029907 | R67: =Q67 -> 0.20029907 | S67: =R67 -> 0.20029907 | T67: =S67 -> 0.20029907
A68: Capex/depreciation | C68: =-C60/C58 -> 0.78471338 | D68: =-D60/D58 -> 1.299569 | E68: =-E60/E58 -> 0.65947612 | F68: =-F60/F58 -> 0.57840463 | G68: =-G60/G58 -> 0.5722135 | H68: =-H60/H58 -> 0.70973312 | I68: =-I60/I58 -> 0.72693068 | J68: =-J60/J58 -> 0.74498237 | ... T68: =-T60/T58 -> 0.62081864
A69: FCF growth | D69: =D23/C23-1 -> 15.682331 | E69: =E23/D23-1 -> -1.6770496 | F69: =F23/E23-1 -> 0.019872812 | G69: =G23/F23-1 -> -0.080921302 | H69: =H23/G23-1 -> -0.19819681 | I69: =I23/H23-1 -> 0.54432336 | J69: =J23/I23-1 -> 0.34803124 | K69: =K23/J23-1 -> 0.27989702 | ... T69: =T23/S23-1 -> 0.11595594
A70: adj EBITDA/sales | C70: =(C55+C58)/C49 -> 0.1330196 | D70: =(D55+D58)/D49 -> 0.13525898 | E70: =(E55+E58)/E49 -> 0.15451147 | F70: =(F55+F58)/F49 -> 0.16720131 | G70: =(G55+G58)/G49 -> 0.1881221 | H70: =(H55+H58)/H49 -> 0.19987564 | I70: =(I55+I58)/I49 -> 0.20560178 | J70: =(J55+J58)/J49 -> 0.21271687 | ... T70: =(T55+T58)/T49 -> 0.23516498
A71: adj EBITDA | C71: =C70*C49 -> 96.386 | D71: =D70*D49 -> 165.3 | E71: =E70*E49 -> 276.9 | F71: =F70*F49 -> 387.62279 | G71: =G70*G49 -> 567 | H71: =H70*H49 -> 699.98963 | I71: =I70*I49 -> 855 | J71: =J70*J49 -> 1030 | ... T71: =T70*T49 -> 2993.2309
U80: Market Cap US$mn | W80: Tg
V81: =H38 -> 13196.552 | W81: 0.0275 | X81: =W81+0.0025 -> 0.03 | Y81: =X81+0.0025 -> 0.0325
W82: -32690.563 | X82: -29327.869 | Y82: -26482.511
W83: 0 | X83: 0 | Y83: 0
U84: WACC | V84: 0.075 | W84: 0 | X84: 0 | Y84: 0
V85: =V84+(0.085-0.075)/3 -> 0.078333333 | W85: 0 | X85: 0 | Y85: 0
V86: =V85+(0.085-0.075)/3 -> 0.081666667 | W86: 0 | X86: 0 | Y86: 0
V87: =V86+(0.085-0.075)/3 -> 0.085 | W87: 9305.3083 | X87: 9563.335 | Y87: 9845.9358
W89: =W87/$H$37 -> 7700.5199 | X89: =((X86+X85)/2)/$H$37 -> 0 | Y89: =Y84/$H$37 -> 0

Sheet Mkt share
B2: Dec year end (CHFmn) | C2: 1Q19 | D2: 2Q19 | E2: 3Q19 | F2: 4Q19 | G2: 2019 | H2: 1Q20 | I2: 2Q20 | J2: 3Q20 | K2: 4Q20 | L2: 2020 | M2: 1Q21E | N2: 2Q21E | O2: 3Q21E | P2: 4Q21E | Q2: 2021E | R2: 1Q22E | S2: 2Q22E | T2: 3Q22E | U2: 4Q22E | V2: 2022E | W2: =Valuation!E14 -> 2023 | X2: =Valuation!F14 -> 2024 | Y2: =Valuation!G14 -> 2025 | Z2: =Valuation!H14 -> 2026E | AA2: =Valuation!I14 -> 2027E | AB2: =Valuation!J14 -> 2028E | AC2: =Valuation!K14 -> 2029E | AD2: =Valuation!L14 -> 2030E | AE2: =Valuation!M14 -> 2031E
B3: Global sportswear market size | G3: =[11]EM_sportswear2!$T$19 -> 345759.3 | L3: =[11]EM_sportswear2!$U$19 -> 321777.6 | Q3: =[11]EM_sportswear2!$V$19 -> 354658.3 | V3: =[11]EM_sportswear2!$W$19 -> 381561 | W3: =[11]EM_sportswear2!X19 -> 408009.3 | X3: =[11]EM_sportswear2!Y19 -> 435354.8 | Y3: =X3*1.06 -> 461476.09 | Z3: =Y3*1.06 -> 489164.65 | AA3: =Z3*1.06 -> 518514.53 | AB3: =AA3*1.06 -> 549625.4 | AC3: =AB3*1.06 -> 582602.93 | AD3: =AC3*1.06 -> 617559.1 | AE3: =AD3*1.06 -> 654612.65
B4: On market share | G4: =MODEL!G31/G3 -> 0.00077256039 | L4: =MODEL!N31/L3 -> 0.0013217056 | Q4: =MODEL!U31/Q3 -> 0.0020430933 | V4: =MODEL!Z31/V3 -> 0.0032028955 | W4: =MODEL!AE31/W3 -> 0.0043923018 | X4: =MODEL!AJ31/X3 -> 0.005325082 | Y4: =MODEL!AO31/Y3 -> 0.006531216 | Z4: =MODEL!AT31/Z3 -> 0.0071594008 | AA4: =MODEL!AU31/AA3 -> 0.0080200727 | AB4: =MODEL!AV31/AB3 -> 0.0088098496 | AC4: =MODEL!AW31/AC3 -> 0.0096208889 | AD4: =MODEL!AX31/AD3 -> 0.010379199 | AE4: =MODEL!AY31/AE3 -> 0.010942216
B5: US sportswear market size | G5: =[11]EM_sportswear2!$T$10 -> 126962 | L5: =[11]EM_sportswear2!$U$10 -> 115107.5 | Q5: =[11]EM_sportswear2!$V$10 -> 124076.9 | V5: =[11]EM_sportswear2!$W$10 -> 131625.3 | W5: =[11]EM_sportswear2!$X$10 -> 138634.2 | X5: =[11]EM_sportswear2!Y10 -> 145709.2 | Y5: =X5*(1.05) -> 152994.66 | Z5: =Y5*(1.05) -> 160644.39 | AA5: =Z5*(1.05) -> 168676.61 | AB5: =AA5*(1.05) -> 177110.44 | AC5: =AB5*(1.05) -> 185965.97 | AD5: =AC5*(1.05) -> 195264.26 | AE5: =AD5*(1.05) -> 205027.48
B6: W Europe sportswear market size | G6: =[11]EM_sportswear2!$T$13 -> 60661 | L6: =[11]EM_sportswear2!$U$13 -> 55785.8 | Q6: =[11]EM_sportswear2!$V$13 -> 60208.3 | V6: =[11]EM_sportswear2!$W$13 -> 63499.3 | W6: =[11]EM_sportswear2!$X$13 -> 66472.4 | X6: =[11]EM_sportswear2!Y13 -> 69695.3 | Y6: =X6*(1.04) -> 72483.112 | Z6: =Y6*(1.04) -> 75382.436 | AA6: =Z6*(1.04) -> 78397.734 | AB6: =AA6*(1.04) -> 81533.643 | AC6: =AB6*(1.04) -> 84794.989 | AD6: =AC6*(1.04) -> 88186.789 | AE6: =AD6*(1.04) -> 91714.26
B7: China sportswear market size | G7: =[11]EM_sportswear2!$T$7/6.46 -> 49008.653 | L7: =[11]EM_sportswear2!$U$7/6.46 -> 48827.105 | Q7: =[11]EM_sportswear2!$V$7/6.46 -> 60502.755 | V7: =[11]EM_sportswear2!$W$7/6.46 -> 68675.248 | W7: =[11]EM_sportswear2!$X$7/6.464 -> 76494.817 | X7: =[11]EM_sportswear2!Y7/6.46 -> 83993.096 | Y7: =X7*(1.1) -> 92392.406 | Z7: =Y7*(1.1) -> 101631.65 | AA7: =Z7*(1.1) -> 111794.81 | AB7: =AA7*(1.1) -> 122974.29 | AC7: =AB7*(1.1) -> 135271.72 | AD7: =AC7*(1.1) -> 148798.89 | AE7: =AD7*(1.1) -> 163678.78
B8: On market share - US | G8: =MODEL!G11/G5 -> 0.00088027126 | L8: =MODEL!N11/L5 -> 0.0018077797 | Q8: =MODEL!U11/Q5 -> 0.0033003726 | V8: =MODEL!Z11/V5 -> 0.0056106235 | W8: =MODEL!AE11/W5 -> 0.0083839341 | X8: =MODEL!AJ11/X5 -> 0.010159276 | Y8: =MODEL!AO11/Y5 -> 0.011374253 | Z8: =MODEL!AT11/Z5 -> 0.011379859 | AA8: =MODEL!AU11/AA5 -> 0.011856603 | AB8: =MODEL!AV11/AB5 -> 0.012195363 | AC8: =MODEL!AW11/AC5 -> 0.012543802 | AD8: =MODEL!AX11/AD5 -> 0.012902197 | AE8: =MODEL!AY11/AE5 -> 0.013025075
B9: On market share - W Europe | G9: =MODEL!G4/G6 -> 0.0021157571 | L9: =MODEL!N4/L6 -> 0.003361254 | Q9: =MODEL!U4/Q6 -> 0.0043249851 | V9: =MODEL!Z4/V6 -> 0.0055795891 | W9: =MODEL!AE4/W6 -> 0.0073519235 | X9: =MODEL!AJ4/X6 -> 0.0082903725 | Y9: =MODEL!AO4/Y6 -> 0.010522451 | Z9: =MODEL!AT4/Z6 -> 0.011902972 | AA9: =MODEL!AU4/AA6 -> 0.013445949 | AB9: =MODEL!AV4/AB6 -> 0.014609541 | AC9: =MODEL!AW4/AC6 -> 0.015733352 | AD9: =MODEL!AX4/AD6 -> 0.016641045 | AE9: =MODEL!AY4/AE6 -> 0.017281086
B10: On market share - China | G10: =MODEL!G18/G7 -> 0.00036456827 | L10: =MODEL!N18/L7 -> 0.00047102936 | Q10: =MODEL!U18/Q7 -> 0.00070575298 | V10: =MODEL!Z18/V7 -> 0.0011678152 | W10: =MODEL!AE18/W7 -> 0.0018445694 | X10: =MODEL!AJ18/X7 -> 0.0030978737 | Y10: =MODEL!AO18/Y7 -> 0.0055318399 | Z10: =MODEL!AT18/Z7 -> 0.0076427 | AA10: =MODEL!AU18/AA7 -> 0.0098793547 | AB10: =MODEL!AV18/AB7 -> 0.012124663 | AC10: =MODEL!AW18/AC7 -> 0.014329147 | AD10: =MODEL!AX18/AD7 -> 0.016283121 | AE10: =MODEL!AY18/AE7 -> 0.017763405
B11: Global sportswear & apparel market size | G11: =[11]EM_sportswear2!$T$18 -> 1774334.8 | L11: =[11]EM_sportswear2!$U$18 -> 1525494.8 | Q11: =[11]EM_sportswear2!$V$18 -> 1691361.9 | V11: =[11]EM_sportswear2!$W$18 -> 1806330.8 | W11: =[11]EM_sportswear2!$X$18 -> 1905625.5 | X11: =[11]EM_sportswear2!Y18 -> 2004738.3 | Y11: =X11*1.03 -> 2064880.4 | Z11: =Y11*1.03 -> 2126826.9 | AA11: =Z11*1.03 -> 2190631.7 | AB11: =AA11*1.03 -> 2256350.6 | AC11: =AB11*1.03 -> 2324041.1 | AD11: =AC11*1.03 -> 2393762.4 | AE11: =AD11*1.03 -> 2465575.2
B12: On market share | G12: =MODEL!G31/G11 -> 0.00015054653 | L12: =MODEL!N31/L11 -> 0.00027879167 | Q12: =MODEL!U31/Q11 -> 0.00042841216 | V12: =MODEL!Z31/V11 -> 0.00067656489 | W12: =MODEL!AE31/W11 -> 0.00094042612 | X12: =MODEL!AJ31/X11 -> 0.0011564103 | Y12: =MODEL!AO31/Y11 -> 0.0014596487 | Z12: =MODEL!AT31/Z11 -> 0.0016466436 | AA12: =MODEL!AU31/AA11 -> 0.001898322 | AB12: =MODEL!AV31/AB11 -> 0.002145995 | AC12: =MODEL!AW31/AC11 -> 0.0024118153 | AD12: =MODEL!AX31/AD11 -> 0.0026776963 | AE12: =MODEL!AY31/AE11 -> 0.002905169
B14: Global sportswaer/apparel and sportswear mkt | G14: =G3/G11 -> 0.194867 | L14: =L3/L11 -> 0.21093327 | Q14: =Q3/Q11 -> 0.209688 | V14: =V3/V11 -> 0.21123539 | W14: =W3/W11 -> 0.21410781 | X14: =X3/X11 -> 0.21716291 | Y14: =Y3/Y11 -> 0.22348804 | Z14: =Z3/Z11 -> 0.2299974 | AA14: =AA3/AA11 -> 0.23669636 | AB14: =AB3/AB11 -> 0.24359042 | AC14: =AC3/AC11 -> 0.25068529 | ... AE14: =AE3/AE11 -> 0.26550098

Sheet Sales growth comparative
A2: Sales context:
C4: 2011 | D4: =C4+1 -> 2012 | E4: =D4+1 -> 2013 | F4: =E4+1 -> 2014 | G4: =F4+1 -> 2015 | H4: =G4+1 -> 2016 | I4: =H4+1 -> 2017 | J4: =I4+1 -> 2018 | K4: =J4+1 -> 2019 | ... M4: =L4+1 -> 2021 | N4: 2022 | O4: 2023E | P4: 2024E | Q4: 2025E
B5: Lulu | C5: ='[12]2. Consolidated'!$AL$30 -> 1000.839 | D5: ='[12]2. Consolidated'!$AQ$30 -> 1370.358 | E5: ='[12]2. Consolidated'!$AV$30 -> 1591.188 | F5: ='[12]2. Consolidated'!$BA$30 -> 1797.213 | G5: ='[12]2. Consolidated'!$BF$30 -> 2060.523 | H5: ='[12]2. Consolidated'!$BK$30 -> 2344.392 | I5: ='[12]2. Consolidated'!$BP$30 -> 2649.181 | J5: ='[12]2. Consolidated'!$BU$30 -> 3288.319 | K5: ='[12]2. Consolidated'!$BZ$30 -> 3979.296 | L5: ='[12]2. Consolidated'!$CE$30 -> 4401.88 | M5: ='[12]2. Consolidated'!$CJ$30 -> 6256.617 | N5: 8110.5 | O5: 9494.3 | P5: 10891.2 | Q5: 12540.9
D6: =D5/C5-1 -> 0.36920923 | E6: =E5/D5-1 -> 0.16114767 | F6: =F5/E5-1 -> 0.12947873 | G6: =G5/F5-1 -> 0.14651018 | H6: =H5/G5-1 -> 0.13776551 | I6: =I5/H5-1 -> 0.13000769 | J6: =J5/I5-1 -> 0.24125871 | K6: =K5/J5-1 -> 0.21013077 | ... Q6: =Q5/P5-1 -> 0.15147091
C7: 2002 | D7: =C7+1 -> 2003 | E7: =D7+1 -> 2004 | F7: =E7+1 -> 2005 | G7: =F7+1 -> 2006 | H7: =G7+1 -> 2007 | I7: =H7+1 -> 2008 | J7: =I7+1 -> 2009 | K7: =J7+1 -> 2010 | ... V7: =U7+1 -> 2021 | W7: 2022E | X7: 2023E | Y7: 2024E | Z7: 2025E | AA7: 2026E
B8: Puma | C8: ='[13]P&L'!J118 -> 909.8 | D8: ='[13]P&L'!K118 -> 1273.9 | E8: ='[13]P&L'!L118 -> 1530.4 | F8: ='[13]P&L'!M118 -> 1777.6 | G8: ='[13]P&L'!N118 -> 2369.2 | H8: ='[13]P&L'!O118 -> 2373.5 | I8: ='[13]P&L'!P118 -> 2524.2 | J8: ='[13]P&L'!Q118 -> 2447.3 | ... AA8: ='[13]P&L'!AH118 -> 11776.708
D9: =D8/C8-1 -> 0.40019785 | E9: =E8/D8-1 -> 0.20135018 | F9: =F8/E8-1 -> 0.1615264 | G9: =G8/F8-1 -> 0.33280828 | H9: =H8/G8-1 -> 0.0018149586 | I9: =I8/H8-1 -> 0.063492732 | J9: =J8/I8-1 -> -0.030465098 | K9: =K8/J8-1 -> 0.10587178 | ... AA9: =AA8/Z8-1 -> 0.089631041
C10: 2022E | D10: 2023E | E10: 2024E | F10: 2025E | G10: 2026E | H10: 2027E | I10: 2028E | J10: 2029E | K10: 2030E | L10: 2031E | M10: 2032E | N10: 2033E | O10: 2034E | P10: 2035E | Q10: 2036E | R10: 2037E
B11: On Holding | C11: =MODEL!Z131 -> 1222.1 | D11: =MODEL!AE131 -> 1792.1 | E11: =MODEL!AJ131 -> 2318.3 | F11: =MODEL!AO131 -> 3014 | G11: =MODEL!AT131 -> 3502.1258 | H11: =MODEL!AU131 -> 4158.5242 | I11: =MODEL!AV131 -> 4842.1171 | J11: =MODEL!AW131 -> 5605.1581 | K11: =MODEL!AX131 -> 6409.7687 | L11: =MODEL!AY131 -> 7162.9127 | M11: =Valuation!N49 -> 7879.204 | N11: =Valuation!O49 -> 8667.1244 | O11: =Valuation!P49 -> 9447.1656 | P11: =Valuation!Q49 -> 10297.41 | Q11: =Valuation!R49 -> 11224.177 | R11: =Valuation!S49 -> 12122.112
D12: =D11/C11-1 -> 0.46641028 | E12: =E11/D11-1 -> 0.29362201 | F12: =F11/E11-1 -> 0.30009058 | G12: =G11/F11-1 -> 0.16195282 | H12: =H11/G11-1 -> 0.18742858 | I12: =I11/H11-1 -> 0.16438353 | J12: =J11/I11-1 -> 0.15758415 | K12: =K11/J11-1 -> 0.14354825 | ... R12: =R11/Q11-1 -> 0.08
C13: 1988 | D13: =C13+1 -> 1989 | E13: =D13+1 -> 1990 | F13: =E13+1 -> 1991 | G13: =F13+1 -> 1992 | H13: =G13+1 -> 1993 | I13: =H13+1 -> 1994 | J13: =I13+1 -> 1995 | K13: =J13+1 -> 1996 | ... AI13: =AH13+1 -> 2020
B14: Nike | C14: 1203 | D14: 1711 | E14: 2235 | F14: 3004 | G14: 3405 | H14: 3931 | I14: 3790 | J14: 4761 | K14: 6471 | L14: 9187 | M14: 9553 | N14: 8777 | O14: 8995 | P14: 9489 | Q14: 9893 | R14: 10697 | S14: 12253 | T14: 13740 | U14: 14955 | V14: 16326 | W14: 18627 | X14: 19176
B17: $mn | C17: 2022E | D17: 2023E | E17: 2024E | F17: 2025E | G17: 2026E | H17: 2027E | I17: 2028E | J17: 2029E | K17: 2030E | L17: 2031E | M17: 2032E | N17: 2033E | O17: 2034E | P17: 2035E | Q17: 2036E | R17: 2037E
B18: On Holding | C18: =C11*1.06 -> 1295.426 | D18: =D11*1.06 -> 1899.626 | E18: =E11*1.06 -> 2457.398 | F18: =F11*1.06 -> 3194.84 | G18: =G11*1.06 -> 3712.2533 | H18: =H11*1.06 -> 4408.0357 | I18: =I11*1.06 -> 5132.6442 | J18: =J11*1.06 -> 5941.4675 | ... R18: =R11*1.06 -> 12849.438
B19: Puma index to 2011 | C19: =L8*1.04 -> 3129.3226 | D19: =M8*1.04 -> 3401.5488 | E19: =N8*1.04 -> 3104.608 | F19: =O8*1.04 -> 3090.9008 | G19: =P8*1.04 -> 3522.896 | H19: =Q8*1.04 -> 3771.872 | I19: =R8*1.04 -> 4301.336 | J19: =S8*1.04 -> 4834.336 | ... R19: =AA8*1.04 -> 12247.777
B20: LuluLemon index to 2011 | C20: =C5 -> 1000.839 | D20: =D5 -> 1370.358 | E20: =E5 -> 1591.188 | F20: =F5 -> 1797.213 | G20: =G5 -> 2060.523 | H20: =H5 -> 2344.392 | I20: =I5 -> 2649.181 | J20: =J5 -> 3288.319 | ... P20: =P5 -> 10891.2
B21: Nike index to 1988 | C21: =C14 -> 1203 | D21: =D14 -> 1711 | E21: =E14 -> 2235 | F21: =F14 -> 3004 | G21: =G14 -> 3405 | H21: =H14 -> 3931 | I21: =I14 -> 3790 | J21: =J14 -> 4761 | ... X21: =X14 -> 19176
C39: 2022E | D39: 2023E | E39: 2024E
B40: On Holding | C40: =C18 -> 1295.426 | D40: =D18 -> 1899.626 | E40: =E18 -> 2457.398 | F40: =C40/C41 -> 0.15303139
B41: Puma | C41: =W8 -> 8465.1 | D41: =X8 -> 9100.023 | E41: =Y8 -> 9920.9626 | F41: =C40/C42 -> 0.15972209
B42: LuluLemon | C42: =N5 -> 8110.5 | D42: =O5 -> 9494.3 | E42: =P5 -> 10891.2

Sheet Comps
A2: Ticker | B2: Name | C2: Year end | D2: End Month | E2: Last close (in reporting ccy) | F2: Pricing Currency | G2: Reporting currency | H2: Diluted WASO, mns | I2: Market cap, local ccy | J2: Net Debt (Cash), local ccy | K2: EV, local ccy | L2: EBITDA - (lcl ccy mn) | Q2: EBITDA - (lcl ccy mn) | AG2: SALES | AH2: SALES | AI2: SALES | AJ2: SALES | AK2: SALES | AL2: SALES | AM2: SALES | AN2: SALES | AO2: SALES | AQ2: GROSS_PROFIT | AR2: GROSS_PROFIT | AS2: GROSS_PROFIT | AT2: GROSS_PROFIT | AU2: GROSS_PROFIT | AV2: GROSS_PROFIT | AW2: GROSS_PROFIT | AX2: GROSS_PROFIT | AY2: GROSS_PROFIT | BA2: GM | BB2: GM | BC2: GM | BD2: GM | BE2: GM | BF2: GM | BG2: GM | BH2: GM
H3: CY 2024 | I3: CY 2024 | J3: CY 2024 | K3: CY 2024 | L3: FY 2021 | M3: FY 2022 | N3: FY 2023 | O3: FY 2024 | P3: FY 2025 | Q3: CY 2021 | R3: CY 2022 | S3: CY 2023 | T3: CY 2024 | AG3: 2019 | AH3: =AG3+1 -> 2020 | AI3: =AH3+1 -> 2021 | AJ3: =AI3+1 -> 2022 | AK3: =AJ3+1 -> 2023 | AL3: =AK3+1 -> 2024 | AM3: =AL3+1 -> 2025 | AN3: =AM3+1 -> 2026 | AO3: =AN3+1 -> 2027 | AQ3: 2019 | AR3: =AQ3+1 -> 2020 | AS3: =AR3+1 -> 2021 | AT3: =AS3+1 -> 2022 | AU3: =AT3+1 -> 2023 | AV3: =AU3+1 -> 2024 | AW3: =AV3+1 -> 2025 | AX3: =AW3+1 -> 2026 | AY3: =AX3+1 -> 2027 | BA3: 2019 | BB3: =BA3+1 -> 2020 | BC3: =BB3+1 -> 2021 | BD3: =BC3+1 -> 2022 | BE3: =BD3+1 -> 2023 | BF3: =BE3+1 -> 2024 | BG3: =BF3+1 -> 2025 | BH3: =BG3+1 -> 2026 | BI3: =BH3+1 -> 2027
A4: NKE | B4: Nike | C4: 31-May-2023 | D4: 5 | E4: =_xll.QueryTool.Functions.GQPrice($A4, "", "", "Reporting") -> 0 | F4: $ | G4: $ | H4: =(5/12)*#REF!+(7/12)*#REF! -> #REF! | I4: =H4*E4 -> #REF! | J4: =(5/12)*#REF!+(7/12)*#REF! -> #REF! | K4: =I4+J4 -> #REF! | L4: =#REF! -> #REF! | M4: =#REF! -> #REF! | N4: =#REF! -> #REF! | O4: =#REF! -> #REF! | P4: =#REF! -> #REF! | Q4: =(($D4/12)*L4+(1-$D4/12)*M4) -> #REF! | R4: =(($D4/12)*M4+(1-$D4/12)*N4) -> #REF! | S4: =(($D4/12)*N4+(1-$D4/12)*O4) -> #REF! | T4: =(($D4/12)*O4+(1-$D4/12)*P4) -> #REF! | U4: Ref Model | V4: =_xll.QueryTool.Functions.GQ($A4, "LAST_UPDATE_DATE", "", "", "Analyst") -> 0 | AG4: =_xll.QueryTool.Functions.GQ($A4, AG$2,AG$3, "Default", "Analyst") -> 0 | AH4: =_xll.QueryTool.Functions.GQ($A4, AH$2,AH$3, "Default", "Analyst") -> 0 | AI4: =_xll.QueryTool.Functions.GQ($A4, AI$2,AI$3, "Default", "Analyst") -> 0 | AJ4: =_xll.QueryTool.Functions.GQ($A4, AJ$2,AJ$3, "Default", "Analyst") -> 0 | AK4: =_xll.QueryTool.Functions.GQ($A4, AK$2,AK$3, "Default", "Analyst") -> 0 | AL4: =_xll.QueryTool.Functions.GQ($A4, AL$2,AL$3, "Default", "Analyst") -> 0 | AM4: =_xll.QueryTool.Functions.GQ($A4, AM$2,AM$3, "Default", "Analyst") -> 0 | AN4: =_xll.QueryTool.Functions.GQ($A4, AN$2,AN$3, "Default", "Analyst") -> 0 | AO4: =_xll.QueryTool.Functions.GQ($A4, AO$2,AO$3, "Default", "Analyst") -> 0 | AQ4: =_xll.QueryTool.Functions.GQ($A4, AQ$2,AQ$3, "Default", "Analyst") -> 0 | AR4: =_xll.QueryTool.Functions.GQ($A4, AR$2,AR$3, "Default", "Analyst") -> 0 | AS4: =_xll.QueryTool.Functions.GQ($A4, AS$2,AS$3, "Default", "Analyst") -> 0 | AT4: =_xll.QueryTool.Functions.GQ($A4, AT$2,AT$3, "Default", "Analyst") -> 0 | AU4: =_xll.QueryTool.Functions.GQ($A4, AU$2,AU$3, "Default", "Analyst") -> 0 | AV4: =_xll.QueryTool.Functions.GQ($A4, AV$2,AV$3, "Default", "Analyst") -> 0 | AW4: =_xll.QueryTool.Functions.GQ($A4, AW$2,AW$3, "Default", "Analyst") -> 0 | AX4: =_xll.QueryTool.Functions.GQ($A4, AX$2,AX$3, "Default", "Analyst") -> 0 | AY4: =_xll.QueryTool.Functions.GQ($A4, AY$2,AY$3, "Default", "Analyst") -> 0 | BA4: =AQ4/AG4 -> #DIV/0! | BB4: =AR4/AH4 -> #DIV/0! | BC4: =AS4/AI4 -> #DIV/0! | BD4: =AT4/AJ4 -> #DIV/0! | BE4: =AU4/AK4 -> #DIV/0! | BF4: =AV4/AL4 -> #DIV/0! | BG4: =AW4/AM4 -> #DIV/0!
A5: LULU | B5: lululemon | C5: 31-Jan-2023 | D5: 1 | E5: =_xll.QueryTool.Functions.GQPrice($A5, "", "", "Reporting") -> 0 | F5: $ | G5: $ | H5: =(1/12)*'[14]4. Summary Model'!$BO$44+(11/12)*'[14]4. Summary Model'!$BT$44 -> 124.9433 | I5: =H5*E5 -> 0 | J5: =(1/12)*'[14]4. Summary Model'!$BO$56+(11/12)*'[14]4. Summary Model'!$BT$56 -> -1330.6343 | K5: =I5+J5 -> -1330.6343 | L5: ='[14]2. Consolidated'!$CJ$77 -> 1598.955 | M5: ='[14]2. Consolidated'!$CO$77 -> 2080.86 | N5: ='[14]2. Consolidated'!$CT$77 -> 2495.6905 | O5: ='[14]2. Consolidated'!$CY$77 -> 2895.6746 | R5: =(($D5/12)*L5+(1-$D5/12)*M5) -> 2040.7012 | S5: =(($D5/12)*M5+(1-$D5/12)*N5) -> 2461.1213 | T5: =(($D5/12)*N5+(1-$D5/12)*O5) -> 2862.3426 | U5: Ref Model | V5: =_xll.QueryTool.Functions.GQ($A5, "LAST_UPDATE_DATE", "", "", "Analyst") -> 0 | AG5: =_xll.QueryTool.Functions.GQ($A5, AG$2,AG$3, "Default", "Analyst") -> 0 | AH5: =_xll.QueryTool.Functions.GQ($A5, AH$2,AH$3, "Default", "Analyst") -> 0 | AI5: =_xll.QueryTool.Functions.GQ($A5, AI$2,AI$3, "Default", "Analyst") -> 0 | AJ5: =_xll.QueryTool.Functions.GQ($A5, AJ$2,AJ$3, "Default", "Analyst") -> 0 | AK5: =_xll.QueryTool.Functions.GQ($A5, AK$2,AK$3, "Default", "Analyst") -> 0 | AL5: =_xll.QueryTool.Functions.GQ($A5, AL$2,AL$3, "Default", "Analyst") -> 0 | AM5: =_xll.QueryTool.Functions.GQ($A5, AM$2,AM$3, "Default", "Analyst") -> 0 | AN5: =_xll.QueryTool.Functions.GQ($A5, AN$2,AN$3, "Default", "Analyst") -> 0 | AO5: =_xll.QueryTool.Functions.GQ($A5, AO$2,AO$3, "Default", "Analyst") -> 0 | AQ5: =_xll.QueryTool.Functions.GQ($A5, AQ$2,AQ$3, "Default", "Analyst") -> 0 | AR5: =_xll.QueryTool.Functions.GQ($A5, AR$2,AR$3, "Default", "Analyst") -> 0 | AS5: =_xll.QueryTool.Functions.GQ($A5, AS$2,AS$3, "Default", "Analyst") -> 0 | AT5: =_xll.QueryTool.Functions.GQ($A5, AT$2,AT$3, "Default", "Analyst") -> 0 | AU5: =_xll.QueryTool.Functions.GQ($A5, AU$2,AU$3, "Default", "Analyst") -> 0 | AV5: =_xll.QueryTool.Functions.GQ($A5, AV$2,AV$3, "Default", "Analyst") -> 0 | AW5: =_xll.QueryTool.Functions.GQ($A5, AW$2,AW$3, "Default", "Analyst") -> 0 | AX5: =_xll.QueryTool.Functions.GQ($A5, AX$2,AX$3, "Default", "Analyst") -> 0 | AY5: =_xll.QueryTool.Functions.GQ($A5, AY$2,AY$3, "Default", "Analyst") -> 0 | BA5: =AQ5/AG5 -> #DIV/0! | BB5: =AR5/AH5 -> #DIV/0! | BC5: =AS5/AI5 -> #DIV/0! | BD5: =AT5/AJ5 -> #DIV/0! | BE5: =AU5/AK5 -> #DIV/0! | BF5: =AV5/AL5 -> #DIV/0! | BG5: =AW5/AM5 -> #DIV/0!
A6: ADSGn.DE | B6: adidas | C6: 31-Dec-2022 | D6: 12 | E6: =_xll.QueryTool.Functions.GQPrice($A6, "", "", "Reporting") -> 0 | F6: € | G6: € | H6: ='[15]Profit and Loss'!$AE$407 -> 178.5 | I6: =H6*E6 -> 0 | J6: ='[15]Balance Sheet & Cash Flow'!$AF$137 -> 1407.4572 | K6: =I6+J6 -> 1407.4572 | L6: - | M6: - | N6: - | O6: - | P6: - | Q6: ='[15]Stat Ab'!$N$13 -> 2563 | R6: ='[15]Stat Ab'!$N$14 -> 1413 | S6: ='[15]Stat Ab'!$N$15 -> 434.00135 | T6: ='[15]Stat Ab'!$N$16 -> 1774.3078 | V6: =_xll.QueryTool.Functions.GQ($A6, "LAST_UPDATE_DATE", "", "", "Analyst") -> 0 | AG6: =_xll.QueryTool.Functions.GQ($A6, AG$2,AG$3, "Default", "Analyst") -> 0 | AH6: =_xll.QueryTool.Functions.GQ($A6, AH$2,AH$3, "Default", "Analyst") -> 0 | AI6: =_xll.QueryTool.Functions.GQ($A6, AI$2,AI$3, "Default", "Analyst") -> 0 | AJ6: =_xll.QueryTool.Functions.GQ($A6, AJ$2,AJ$3, "Default", "Analyst") -> 0 | AK6: =_xll.QueryTool.Functions.GQ($A6, AK$2,AK$3, "Default", "Analyst") -> 0 | AL6: =_xll.QueryTool.Functions.GQ($A6, AL$2,AL$3, "Default", "Analyst") -> 0 | AM6: =_xll.QueryTool.Functions.GQ($A6, AM$2,AM$3, "Default", "Analyst") -> 0 | AN6: =_xll.QueryTool.Functions.GQ($A6, AN$2,AN$3, "Default", "Analyst") -> 0 | AO6: =_xll.QueryTool.Functions.GQ($A6, AO$2,AO$3, "Default", "Analyst") -> 0 | AQ6: =_xll.QueryTool.Functions.GQ($A6, AQ$2,AQ$3, "Default", "Analyst") -> 0 | AR6: =_xll.QueryTool.Functions.GQ($A6, AR$2,AR$3, "Default", "Analyst") -> 0 | AS6: =_xll.QueryTool.Functions.GQ($A6, AS$2,AS$3, "Default", "Analyst") -> 0 | AT6: =_xll.QueryTool.Functions.GQ($A6, AT$2,AT$3, "Default", "Analyst") -> 0 | AU6: =_xll.QueryTool.Functions.GQ($A6, AU$2,AU$3, "Default", "Analyst") -> 0 | AV6: =_xll.QueryTool.Functions.GQ($A6, AV$2,AV$3, "Default", "Analyst") -> 0 | AW6: =_xll.QueryTool.Functions.GQ($A6, AW$2,AW$3, "Default", "Analyst") -> 0 | AX6: =_xll.QueryTool.Functions.GQ($A6, AX$2,AX$3, "Default", "Analyst") -> 0 | AY6: =_xll.QueryTool.Functions.GQ($A6, AY$2,AY$3, "Default", "Analyst") -> 0 | BA6: =AQ6/AG6 -> #DIV/0! | BB6: =AR6/AH6 -> #DIV/0! | BC6: =AS6/AI6 -> #DIV/0! | BD6: =AT6/AJ6 -> #DIV/0! | BE6: =AU6/AK6 -> #DIV/0! | BF6: =AV6/AL6 -> #DIV/0! | BG6: =AW6/AM6 -> #DIV/0! | BH6: =AX6/AN6 -> #DIV/0! | BI6: =AY6/AO6 -> #DIV/0!
A7: PUMG.DE | B7: Puma | C7: 31-Dec-2022 | D7: 12 | E7: =_xll.QueryTool.Functions.GQPrice($A7, "", "", "Reporting") -> 0 | F7: € | G7: € | H7: ='[13]P&L'!$AF$196 -> 149.61 | I7: =H7*E7 -> 0 | J7: ='[13]Balance Sheet & Cash Flow'!$AG$167 -> -874.87589 | K7: =I7+J7 -> -874.87589 | L7: - | M7: - | N7: - | O7: - | P7: - | Q7: ='[13]Stat Ab'!$N$13 -> 565.29421 | R7: ='[13]Stat Ab'!$N$14 -> 652.49484 | S7: ='[13]Stat Ab'!$N$15 -> 725.43209 | T7: ='[13]Stat Ab'!$N$16 -> 898.88864 | V7: =_xll.QueryTool.Functions.GQ($A7, "LAST_UPDATE_DATE", "", "", "Analyst") -> 0 | AG7: =_xll.QueryTool.Functions.GQ($A7, AG$2,AG$3, "Default", "Analyst") -> 0 | AH7: =_xll.QueryTool.Functions.GQ($A7, AH$2,AH$3, "Default", "Analyst") -> 0 | AI7: =_xll.QueryTool.Functions.GQ($A7, AI$2,AI$3, "Default", "Analyst") -> 0 | AJ7: =_xll.QueryTool.Functions.GQ($A7, AJ$2,AJ$3, "Default", "Analyst") -> 0 | AK7: =_xll.QueryTool.Functions.GQ($A7, AK$2,AK$3, "Default", "Analyst") -> 0 | AL7: =_xll.QueryTool.Functions.GQ($A7, AL$2,AL$3, "Default", "Analyst") -> 0 | AM7: =_xll.QueryTool.Functions.GQ($A7, AM$2,AM$3, "Default", "Analyst") -> 0 | AN7: =_xll.QueryTool.Functions.GQ($A7, AN$2,AN$3, "Default", "Analyst") -> 0 | AO7: =_xll.QueryTool.Functions.GQ($A7, AO$2,AO$3, "Default", "Analyst") -> 0 | AQ7: =_xll.QueryTool.Functions.GQ($A7, AQ$2,AQ$3, "Default", "Analyst") -> 0 | AR7: =_xll.QueryTool.Functions.GQ($A7, AR$2,AR$3, "Default", "Analyst") -> 0 | AS7: =_xll.QueryTool.Functions.GQ($A7, AS$2,AS$3, "Default", "Analyst") -> 0 | AT7: =_xll.QueryTool.Functions.GQ($A7, AT$2,AT$3, "Default", "Analyst") -> 0 | AU7: =_xll.QueryTool.Functions.GQ($A7, AU$2,AU$3, "Default", "Analyst") -> 0 | AV7: =_xll.QueryTool.Functions.GQ($A7, AV$2,AV$3, "Default", "Analyst") -> 0 | AW7: =_xll.QueryTool.Functions.GQ($A7, AW$2,AW$3, "Default", "Analyst") -> 0 | AX7: =_xll.QueryTool.Functions.GQ($A7, AX$2,AX$3, "Default", "Analyst") -> 0 | AY7: =_xll.QueryTool.Functions.GQ($A7, AY$2,AY$3, "Default", "Analyst") -> 0 | BA7: =AQ7/AG7 -> #DIV/0! | BB7: =AR7/AH7 -> #DIV/0! | BC7: =AS7/AI7 -> #DIV/0! | BD7: =AT7/AJ7 -> #DIV/0! | BE7: =AU7/AK7 -> #DIV/0! | BF7: =AV7/AL7 -> #DIV/0! | BG7: =AW7/AM7 -> #DIV/0! | BH7: =AX7/AN7 -> #DIV/0! | BI7: =AY7/AO7 -> #DIV/0!
A8: 2331.HK | B8: Li Ning Co. | C8: 31-Dec-2022 | D8: 12 | E8: =_xll.QueryTool.Functions.GQPrice($A8, "", "", "Reporting") -> 0 | F8: HKD | G8: RMb | H8: =[16]Model!$AG$67 -> 2633.9196 | I8: =H8*E8 -> 0 | J8: =[16]Model!$AG$218 -> -15410.295 | K8: =I8+J8 -> -15410.295 | L8: - | M8: - | N8: - | O8: - | P8: - | Q8: =[16]Model!AD$23 -> 5366.269 | R8: =[16]Model!AE$23 -> 4863.114 | S8: =[16]Model!AF$23 -> 6034.1247 | T8: =[16]Model!AG$23 -> 7657.849 | U8: Ref Model | V8: =_xll.QueryTool.Functions.GQ($A8, "LAST_UPDATE_DATE", "", "", "Analyst") -> 0 | AG8: =_xll.QueryTool.Functions.GQ($A8, AG$2,AG$3, "Default", "Analyst") -> 0 | AH8: =_xll.QueryTool.Functions.GQ($A8, AH$2,AH$3, "Default", "Analyst") -> 0 | AI8: =_xll.QueryTool.Functions.GQ($A8, AI$2,AI$3, "Default", "Analyst") -> 0 | AJ8: =_xll.QueryTool.Functions.GQ($A8, AJ$2,AJ$3, "Default", "Analyst") -> 0 | AK8: =_xll.QueryTool.Functions.GQ($A8, AK$2,AK$3, "Default", "Analyst") -> 0 | AL8: =_xll.QueryTool.Functions.GQ($A8, AL$2,AL$3, "Default", "Analyst") -> 0 | AM8: =_xll.QueryTool.Functions.GQ($A8, AM$2,AM$3, "Default", "Analyst") -> 0 | AN8: =_xll.QueryTool.Functions.GQ($A8, AN$2,AN$3, "Default", "Analyst") -> 0 | AO8: =_xll.QueryTool.Functions.GQ($A8, AO$2,AO$3, "Default", "Analyst") -> 0 | AQ8: =_xll.QueryTool.Functions.GQ($A8, AQ$2,AQ$3, "Default", "Analyst") -> 0 | AR8: =_xll.QueryTool.Functions.GQ($A8, AR$2,AR$3, "Default", "Analyst") -> 0 | AS8: =_xll.QueryTool.Functions.GQ($A8, AS$2,AS$3, "Default", "Analyst") -> 0 | AT8: =_xll.QueryTool.Functions.GQ($A8, AT$2,AT$3, "Default", "Analyst") -> 0 | AU8: =_xll.QueryTool.Functions.GQ($A8, AU$2,AU$3, "Default", "Analyst") -> 0 | AV8: =_xll.QueryTool.Functions.GQ($A8, AV$2,AV$3, "Default", "Analyst") -> 0 | AW8: =_xll.QueryTool.Functions.GQ($A8, AW$2,AW$3, "Default", "Analyst") -> 0 | AX8: =_xll.QueryTool.Functions.GQ($A8, AX$2,AX$3, "Default", "Analyst") -> 0 | AY8: =_xll.QueryTool.Functions.GQ($A8, AY$2,AY$3, "Default", "Analyst") -> 0 | BA8: =AQ8/AG8 -> #DIV/0! | BB8: =AR8/AH8 -> #DIV/0! | BC8: =AS8/AI8 -> #DIV/0! | BD8: =AT8/AJ8 -> #DIV/0! | BE8: =AU8/AK8 -> #DIV/0! | BF8: =AV8/AL8 -> #DIV/0! | BG8: =AW8/AM8 -> #DIV/0! | BH8: =AX8/AN8 -> #DIV/0! | BI8: =AY8/AO8 -> #DIV/0!
A9: 2020.HK | B9: Anta Sports | C9: 31-Dec-2022 | D9: 12 | E9: =_xll.QueryTool.Functions.GQPrice($A9, "", "", "Reporting") -> 0 | F9: HKD | G9: RMb | H9: =[17]Model!$AF$68 -> 2900.008 | I9: =H9*E9 -> 0 | J9: =[17]Model!$AF$225 -> 15.950691 | K9: =I9+J9 -> 15.950691 | L9: - | M9: - | N9: - | O9: - | P9: - | Q9: =[17]Model!AC$23 -> 12989 | R9: =[17]Model!AD$23 -> 13566 | S9: =[17]Model!AE$23 -> 17264.664 | T9: =[17]Model!AF$23 -> 19986.123 | U9: Ref Model | V9: =_xll.QueryTool.Functions.GQ($A9, "LAST_UPDATE_DATE", "", "", "Analyst") -> 0 | AG9: =_xll.QueryTool.Functions.GQ($A9, AG$2,AG$3, "Default", "Analyst") -> 0 | AH9: =_xll.QueryTool.Functions.GQ($A9, AH$2,AH$3, "Default", "Analyst") -> 0 | AI9: =_xll.QueryTool.Functions.GQ($A9, AI$2,AI$3, "Default", "Analyst") -> 0 | AJ9: =_xll.QueryTool.Functions.GQ($A9, AJ$2,AJ$3, "Default", "Analyst") -> 0 | AK9: =_xll.QueryTool.Functions.GQ($A9, AK$2,AK$3, "Default", "Analyst") -> 0 | AL9: =_xll.QueryTool.Functions.GQ($A9, AL$2,AL$3, "Default", "Analyst") -> 0 | AM9: =_xll.QueryTool.Functions.GQ($A9, AM$2,AM$3, "Default", "Analyst") -> 0 | AN9: =_xll.QueryTool.Functions.GQ($A9, AN$2,AN$3, "Default", "Analyst") -> 0 | AO9: =_xll.QueryTool.Functions.GQ($A9, AO$2,AO$3, "Default", "Analyst") -> 0 | AQ9: =_xll.QueryTool.Functions.GQ($A9, AQ$2,AQ$3, "Default", "Analyst") -> 0 | AR9: =_xll.QueryTool.Functions.GQ($A9, AR$2,AR$3, "Default", "Analyst") -> 0 | AS9: =_xll.QueryTool.Functions.GQ($A9, AS$2,AS$3, "Default", "Analyst") -> 0 | AT9: =_xll.QueryTool.Functions.GQ($A9, AT$2,AT$3, "Default", "Analyst") -> 0 | AU9: =_xll.QueryTool.Functions.GQ($A9, AU$2,AU$3, "Default", "Analyst") -> 0 | AV9: =_xll.QueryTool.Functions.GQ($A9, AV$2,AV$3, "Default", "Analyst") -> 0 | AW9: =_xll.QueryTool.Functions.GQ($A9, AW$2,AW$3, "Default", "Analyst") -> 0 | AX9: =_xll.QueryTool.Functions.GQ($A9, AX$2,AX$3, "Default", "Analyst") -> 0 | AY9: =_xll.QueryTool.Functions.GQ($A9, AY$2,AY$3, "Default", "Analyst") -> 0 | BA9: =AQ9/AG9 -> #DIV/0! | BB9: =AR9/AH9 -> #DIV/0! | BC9: =AS9/AI9 -> #DIV/0! | BD9: =AT9/AJ9 -> #DIV/0! | BE9: =AU9/AK9 -> #DIV/0! | BF9: =AV9/AL9 -> #DIV/0! | BG9: =AW9/AM9 -> #DIV/0! | BH9: =AX9/AN9 -> #DIV/0! | BI9: =AY9/AO9 -> #DIV/0!
A10: 7936.T | B10: Asics | C10: 31-Dec-2022 | D10: 12 | E10: =_xll.QueryTool.Functions.GQPrice($A10, "", "", "Reporting") -> 0 | F10: JPY | G10: JPY | H10: =[18]Model!$AF$68 -> 183.12155 | I10: =H10*E10 -> 0 | J10: =[18]Model!$AF$131 -> 5287.3322 | K10: =I10+J10 -> 5287.3322 | L10: - | M10: - | N10: - | O10: - | P10: - | Q10: =[18]Model!AC$27 -> 36146 | R10: =[18]Model!AD$27 -> 50501 | S10: =[18]Model!AE$27 -> 61400 | T10: =[18]Model!AF$27 -> 67000 | U10: Ref Model | V10: =_xll.QueryTool.Functions.GQ($A10, "LAST_UPDATE_DATE", "", "", "Analyst") -> 0 | AG10: =_xll.QueryTool.Functions.GQ($A10, AG$2,AG$3, "Default", "Analyst") -> 0 | AH10: =_xll.QueryTool.Functions.GQ($A10, AH$2,AH$3, "Default", "Analyst") -> 0 | AI10: =_xll.QueryTool.Functions.GQ($A10, AI$2,AI$3, "Default", "Analyst") -> 0 | AJ10: =_xll.QueryTool.Functions.GQ($A10, AJ$2,AJ$3, "Default", "Analyst") -> 0 | AK10: =_xll.QueryTool.Functions.GQ($A10, AK$2,AK$3, "Default", "Analyst") -> 0 | AL10: =_xll.QueryTool.Functions.GQ($A10, AL$2,AL$3, "Default", "Analyst") -> 0 | AM10: =_xll.QueryTool.Functions.GQ($A10, AM$2,AM$3, "Default", "Analyst") -> 0 | AN10: =_xll.QueryTool.Functions.GQ($A10, AN$2,AN$3, "Default", "Analyst") -> 0 | AO10: =_xll.QueryTool.Functions.GQ($A10, AO$2,AO$3, "Default", "Analyst") -> 0 | AQ10: =_xll.QueryTool.Functions.GQ($A10, AQ$2,AQ$3, "Default", "Analyst") -> 0 | AR10: =_xll.QueryTool.Functions.GQ($A10, AR$2,AR$3, "Default", "Analyst") -> 0 | AS10: =_xll.QueryTool.Functions.GQ($A10, AS$2,AS$3, "Default", "Analyst") -> 0 | AT10: =_xll.QueryTool.Functions.GQ($A10, AT$2,AT$3, "Default", "Analyst") -> 0 | AU10: =_xll.QueryTool.Functions.GQ($A10, AU$2,AU$3, "Default", "Analyst") -> 0 | AV10: =_xll.QueryTool.Functions.GQ($A10, AV$2,AV$3, "Default", "Analyst") -> 0 | AW10: =_xll.QueryTool.Functions.GQ($A10, AW$2,AW$3, "Default", "Analyst") -> 0 | AX10: =_xll.QueryTool.Functions.GQ($A10, AX$2,AX$3, "Default", "Analyst") -> 0 | AY10: =_xll.QueryTool.Functions.GQ($A10, AY$2,AY$3, "Default", "Analyst") -> 0 | BA10: =AQ10/AG10 -> #DIV/0! | BB10: =AR10/AH10 -> #DIV/0! | BC10: =AS10/AI10 -> #DIV/0! | BD10: =AT10/AJ10 -> #DIV/0! | BE10: =AU10/AK10 -> #DIV/0! | BF10: =AV10/AL10 -> #DIV/0!
A11: ONON | B11: ON Holding | C11: 31-Dec-2022 | D11: 12 | E11: =_xll.QueryTool.Functions.GQPrice($A11, "", "", "Reporting") -> 0 | F11: $ | G11: CHF | H11: =MODEL!Z174 -> 281.63027 | I11: =H11*E11 -> 0 | J11: =-MODEL!AJ212 -> -924.30412 | K11: =I11+J11 -> -924.30412 | L11: - | M11: - | N11: - | O11: - | P11: - | Q11: =MODEL!U153 -> 96.386 | R11: ='Stat Ab'!C6 -> 116.1 | S11: ='Stat Ab'!C7 -> 213.1 | T11: ='Stat Ab'!C8 -> 249.62412 | V11: =_xll.QueryTool.Functions.GQ($A11, "LAST_UPDATE_DATE", "", "", "Analyst") -> 0 | AG11: =_xll.QueryTool.Functions.GQ($A11, AG$2,AG$3, "Default", "Analyst") -> 0 | AH11: =_xll.QueryTool.Functions.GQ($A11, AH$2,AH$3, "Default", "Analyst") -> 0 | AI11: =_xll.QueryTool.Functions.GQ($A11, AI$2,AI$3, "Default", "Analyst") -> 0 | AJ11: =_xll.QueryTool.Functions.GQ($A11, AJ$2,AJ$3, "Default", "Analyst") -> 0 | AK11: =_xll.QueryTool.Functions.GQ($A11, AK$2,AK$3, "Default", "Analyst") -> 0 | AL11: =_xll.QueryTool.Functions.GQ($A11, AL$2,AL$3, "Default", "Analyst") -> 0 | AM11: =_xll.QueryTool.Functions.GQ($A11, AM$2,AM$3, "Default", "Analyst") -> 0 | AN11: =_xll.QueryTool.Functions.GQ($A11, AN$2,AN$3, "Default", "Analyst") -> 0 | AO11: =_xll.QueryTool.Functions.GQ($A11, AO$2,AO$3, "Default", "Analyst") -> 0 | AQ11: =_xll.QueryTool.Functions.GQ($A11, AQ$2,AQ$3, "Default", "Analyst") -> 0 | AR11: =_xll.QueryTool.Functions.GQ($A11, AR$2,AR$3, "Default", "Analyst") -> 0 | AS11: =_xll.QueryTool.Functions.GQ($A11, AS$2,AS$3, "Default", "Analyst") -> 0 | AT11: =_xll.QueryTool.Functions.GQ($A11, AT$2,AT$3, "Default", "Analyst") -> 0 | AU11: =_xll.QueryTool.Functions.GQ($A11, AU$2,AU$3, "Default", "Analyst") -> 0 | AV11: =_xll.QueryTool.Functions.GQ($A11, AV$2,AV$3, "Default", "Analyst") -> 0 | AW11: =_xll.QueryTool.Functions.GQ($A11, AW$2,AW$3, "Default", "Analyst") -> 0 | AX11: =_xll.QueryTool.Functions.GQ($A11, AX$2,AX$3, "Default", "Analyst") -> 0 | AY11: =_xll.QueryTool.Functions.GQ($A11, AY$2,AY$3, "Default", "Analyst") -> 0 | BA11: =AQ11/AG11 -> #DIV/0! | BB11: =AR11/AH11 -> #DIV/0! | BC11: =AS11/AI11 -> #DIV/0! | BD11: =AT11/AJ11 -> #DIV/0! | BE11: =AU11/AK11 -> #DIV/0! | BF11: =AV11/AL11 -> #DIV/0! | BG11: =AW11/AM11 -> #DIV/0! | BH11: =AX11/AN11 -> #DIV/0! | BI11: =AY11/AO11 -> #DIV/0!
A12: JD.L | B12: JD Sports | C12: 31-Jan-2023 | D12: 1 | E12: =_xll.QueryTool.Functions.GQPrice($A12, "", "", "Reporting") -> 0 | F12: p | H12: =[19]Valuation!$F$32 -> 0 | I12: =E12*H12/100 -> 0 | J12: =[19]Valuation!$F$29 -> 0 | K12: =I12+J12 -> 0 | L12: =[19]Model!$AH$204 -> 649.3 | M12: =[19]Model!$AK$204 -> 1250.1152 | N12: =[19]Model!$AN$204 -> 1296.4 | O12: =[19]Model!$AQ$204 -> 1238 | P12: =[19]Model!$AR$204 -> 0 | Q12: =(($D12/12)*L12+(1-$D12/12)*M12) -> 1200.0472 | R12: =(($D12/12)*M12+(1-$D12/12)*N12) -> 1292.5429 | S12: =(($D12/12)*N12+(1-$D12/12)*O12) -> 1242.8667 | T12: =(($D12/12)*O12+(1-$D12/12)*P12) -> 103.16667 | X12: Price | Y12: Price | Z12: Price | AA12: Price | AB12: Price
W14: ONON | X14: =_xll.QueryTool.Functions.GQPrice($W14, "", "", "Reporting") -> 0 | Y14: =_xll.QueryTool.Functions.GQPrice($W14, "", "", "CHF") -> 0 | Z14: =_xll.QueryTool.Functions.GQPrice($W14, "", "", "Default") -> 0 | AA14: =_xll.QueryTool.Functions.GQPrice($W14, "", "", "Pricing") -> 0 | AB14: =_xll.QueryTool.Functions.GQPrice($W14, "", "", "Publishing") -> 0
F21: EV/EBITDA | I21: EBITDA growth
F22: FY22E | G22: FY23E | H22: FY24E | J22: FY23E growth | K22: FY22-24 CAGR
E23: =B4 -> Nike | H23: =K4/T4 -> #REF! | J23: =T4/S4-1 -> #REF! | K23: =(T4/R4)^0.5-1 -> #REF!
E24: =B5 -> lululemon | H24: =K5/T5 -> -0.46487597 | J24: =T5/S5-1 -> 0.1630238 | K24: =(T5/R5)^0.5-1 -> 0.18432553
E25: =B6 -> adidas | H25: =K6/T6 -> 0.793243 | J25: =T6/S6-1 -> 3.088254 | K25: =(T6/R6)^0.5-1 -> 0.12058136
E26: =B7 -> Puma | H26: =K7/T7 -> -0.97328619 | J26: =T7/S7-1 -> 0.23910789 | K26: =(T7/R7)^0.5-1 -> 0.17371973
E27: =B8 -> Li Ning Co. | H27: =K8/T8 -> -2.012353 | J27: =T8/S8-1 -> 0.26909027 | K27: =(T8/R8)^0.5-1 -> 0.25486259
E28: =B9 -> Anta Sports | H28: =K9/T9 -> 0.00079808832 | J28: =T9/S9-1 -> 0.15763176 | K28: =(T9/R9)^0.5-1 -> 0.21377551
E29: =B10 -> Asics | H29: =K10/T10 -> 0.078915405 | J29: =T10/S10-1 -> 0.091205212 | K29: =(T10/R10)^0.5-1 -> 0.15182742
E30: On Holding | H30: =K11/T11 -> -3.7027837 | J30: =T11/S11-1 -> 0.17139429 | K30: =(T11/R11)^0.5-1 -> 0.46631462
E31: JD Sports | H31: =K12/T12 -> 0 | K31: =(T12/R12)^0.5-1 -> -0.71748129
E32: Peer Average | F32: =AVERAGE(F23:F29) -> #DIV/0! | G32: =AVERAGE(G23:G29) -> #DIV/0! | H32: =AVERAGE(H23:H29) -> #REF! | K32: =AVERAGE(K23:K29) -> #REF!
H34: 49.433633
C41: Notes:
C42: - Use datastream for exchange rates
C43: - Use Net Debt before leases
C44: - Use EBITDA ex SBC ie EBITDA which adds back SBC
C45: - Use EBITDA less rent for IFRS16 companies
C46: - For EU co's EBITDA is actally EBITDAR, so to make it comparable with US co's we must minus rent (from cashflow), making EBITDA lower
C50: Last refreshed: 08/11/2022
C51: =_xll.Thomson.Reuters.AFOSpreadSheetFormulas.DSGRID("EUDOLLR,BRECBSP,POEURSP,RCNYEUR,TSEURSP,JPEURSP,CHHKDSP"," ","Latest Value","","","RowHeader=true;ColHeader=true;DispSeriesDescription=true;DispDatatypeDescription=true","") -> Type | D51: X
C52: EUDOLLR | D52: 0.87708 | F52: 1 USD = X EUR
C53: BRECBSP | D53: 5.8564
C54: POEURSP | D54: 4.379 | F54: X PLN = 1 EUR
C55: RCNYEUR | D55: 0.13091 | F55: 1 CNY = X EUR
C56: TSEURSP | D56: 1.1634 | F56: 1 GBP = X EUR
C57: JPEURSP | D57: 180.38885 | F57: X YEN = 1 EUR
C58: CHHKDSP | D58: 0.8558 | F58: 1HKD = X CNY
C59: EURCHF | D59: 1.0382 | F59: 1EUR = X CHF
C60: Source: Thomson Reuters Datastream
F64: =670/550-1 -> 0.21818182 | G64: =550*4.33333 -> 2383.3315 | H64: =670*4.333333 -> 2903.3331
H65: =1258*(1+F64) -> 1532.4727
H66: =1533-1258 -> 275

Sheet GEOS
C2: 2022 | D2: 2023 | E2: 2024
B3: Americas | C3: 763.8 | D3: 1162.2 | E3: 1480.3
B4: yoy | D4: =D3/C3-1 -> 0.52160251 | E4: =E3/D3-1 -> 0.27370504
B5: United States | C5: 718.5 | D5: 1082.1 | E5: 1367.7
B6: yoy | D6: =D5/C5-1 -> 0.50605428 | E6: =E5/D5-1 -> 0.26393124
B7: EMEA | C7: 378.1 | D7: 488.7 | E7: 577.8
B8: Switzerland | C8: 51.5 | D8: 46 | E8: 38.7
B9: yoy | D9: =D8/C8-1 -> -0.10679612 | E9: =E8/D8-1 -> -0.15869565
B10: APAC | C10: 80.2 | D10: 141.1 | E10: 260.2
B11: yoy | D11: =D10/C10-1 -> 0.75935162 | E11: =E10/D10-1 -> 0.84408221
B12: Net Sales | C12: =C3+C7+C10 -> 1222.1 | D12: =D3+D7+D10 -> 1792 | E12: =E3+E7+E10 -> 2318.3
