Workbook
Name \q: #REF!
Name \S: #REF!
Name __eps96: #REF!
Name __inc90: #REF!
Name __int94: #REF!
Name __int95: #REF!
Name __int96: #REF!
Name __qtr1: #REF!
Name __qtr2: #REF!
Name __qtr4: #REF!
Name __sga87: #REF!
Name __sga88: #REF!
Name __sga89: #REF!
Name __sga90: #REF!
Name __sga91: #REF!
Name __sga93: #REF!
Name __sls87: #REF!
Name __sls88: #REF!
Name __sls89: #REF!
Name __sls93: #REF!
Name __sls95: #REF!
Name __sls96: #REF!
Name __tax91: #REF!
Name __tax92: #REF!
Name __tax94: #REF!
Name __tax95: #REF!
Name __tax96: #REF!
Name _107_._0Restructuring_char: #REF!
Name _108_._0Restructuring_char: #REF!
Name _116_._0SGA_gro: #REF!
Name _117_._0SGA_gro: #REF!
Name _125_._0Shares_repurchase_liabil: #REF!
Name _126_._0Shares_repurchase_liabil: #REF!
Name _134_0FAMERangeSheet: #REF!
Name _135_0FAMERangeSheet: #REF!
Name _143_0FAMERangeSheet: #REF!
Name _144_0FAMERangeSheet: #REF!
Name _152_0FAMERangeSheet: #REF!
Name _153_0FAMERangeSheet: #REF!
Name _161_0FAMERangeSheet: #REF!
Name _162_0FAMERangeSheet: #REF!
Name _17_0UniqueRang: #REF!
Name _170_0FAMERangeSheet: #REF!
Name _171_0FAMERangeSheet: #REF!
Name _179_0FAMERangeSheet: #REF!
Name _18_0UniqueRang: #REF!
Name _180_0FAMERangeSheet: #REF!
Name _188_0FAMERangeSheet: #REF!
Name _189_0FAMERangeSheet: #REF!
Name _197_0FAMERangeSheet: #REF!
Name _198_0FAMERangeSheet: #REF!
Name _206_0UniqueRang: #REF!
Name _207_0UniqueRang: #REF!
Name _215_0UniqueRang: #REF!
Name _216_0UniqueRang: #REF!
Name _224_0UniqueRang: #REF!
Name _225_0UniqueRang: #REF!
Name _233_0UniqueRange: #REF!
Name _234_0UniqueRange: #REF!
Name _242_0UniqueRange: #REF!

Sheet 1. Cover
F3: Nike Inc. (NKE)
F4: COMPANY MODEL
B9: Sources: Company data, Goldman Sachs Global Investment Research
B11: Date: October 1st, 2026
B13: Brooke Roach, CFA
B14: Managing Director
B15: tel: 212-357-2421
B16: brooke.roach@gs.com
B18: Mentesnot Adamu
B19: Analyst
B20: tel: 801-744-0630
B21: mentesnot.adamu@gs.com
B23: Carly Chasen
B24: Analyst
... B26: carly.chasen@gs.com

Sheet 2. Consolidated
B1: Nike (NKE)
B2: Consolidated Financial Results
B3: $ millions except per share data, FY ending May
C5: 35216 | D5: 35581 | E5: 35946 | F5: 36311 | G5: 36677 | H5: 37042 | I5: 37407 | J5: 37772 | K5: 38138 | L5: 38503 | M5: 38868 | N5: 39233 | O5: 39599 | P5: 39964 | Q5: 40329 | R5: 40421 | S5: 40512 | T5: 40602 | U5: 40694 | V5: 40694 | W5: 40786 | X5: 40877 | Y5: 40968 | Z5: 41060 | AA5: 41060 | AB5: 41060 | AC5: 41152 | AD5: 41243 | AE5: 41333 | AF5: 41425 | AG5: 41425 | AH5: 41517 | AI5: 41608 | AJ5: 41698 | AK5: 41790 | AL5: 41790 | AM5: 41882 | AN5: 41973 | AO5: 42063 | AP5: 42155 | AQ5: 42155 | AR5: 42247 | AS5: 42338 | AT5: 42429 | AU5: 42521 | AV5: 42521 | AW5: 42613 | AX5: 42704 | AY5: 42794 | AZ5: 42886 | BA5: 42886 | BB5: 42978 | BC5: 43069 | BD5: 43159 | BE5: 43251 | BF5: 43251 | BG5: 43343 | BH5: 43434 | BI5: 43524 | BJ5: 43616 | BK5: 43616 | BL5: 43708 | BM5: 43799 | BN5: 43890 | BO5: 43982 | BP5: 43982 | BQ5: 44074 | BR5: 44165 | BS5: 44255 | BT5: 44347 | BU5: 44347 | BV5: 44439 | BW5: 44530 | BX5: 44620 | BY5: 44712 | BZ5: 44712 | CA5: 44804 | CB5: 44895 | CC5: 44985 | CD5: 45077 | CE5: 45077 | CF5: 45169 | CG5: 45260 | CH5: 45350 | CI5: 45443 | CJ5: 45443 | CK5: 45535 | CL5: 45626 | CM5: 45716 | CN5: 45808 | CO5: 45808 | CP5: 45900 | CQ5: 45991 | CR5: 46081 | CS5: 46173 | CT5: 46173 | CU5: 46265 | CV5: 46356 | CW5: 46446 | CX5: 46538 | CY5: 46538 | CZ5: 46630 | DA5: 46721 | DB5: 46811 | DC5: 46904 | DD5: 46904 | DE5: =DD5+91 -> 46995 | DF5: =DE5+91 -> 47086 | DG5: =DF5+91 -> 47177 | DH5: =DG5+91 -> 47268 | DI5: 46904
C6: 1996 | D6: 1997 | E6: 1998 | F6: 1999 | G6: 2000 | H6: 2001 | I6: 2002 | J6: 2003 | K6: 2004 | L6: 2005 | M6: 2006 | N6: 2007 | O6: 2008 | P6: 2009 | Q6: 2010 | R6: 1Q | S6: 2Q | T6: 3Q | U6: 4Q | V6: 2011 | W6: 1Q | X6: 2Q | Y6: 3Q | Z6: 4Q | AA6: 2012 | AB6: 2012R | AC6: 1Q | AD6: 2Q | AE6: 3Q | AF6: 4Q | AG6: 2013 | AH6: 1Q | AI6: 2Q | AJ6: 3Q | AK6: 4Q | AL6: 2014 | AM6: 1Q | AN6: 2Q | AO6: 3Q | AP6: 4Q | AQ6: 2015 | AR6: 1Q | AS6: 2Q | AT6: 3Q | AU6: 4Q | AV6: 2016 | AW6: 1Q | AX6: 2Q | AY6: 3Q | AZ6: 4Q | BA6: 2017 | BB6: 1Q | BC6: 2Q | BD6: 3Q | BE6: 4Q | BF6: 2018 | BG6: 1Q | BH6: 2Q | BI6: 3Q | BJ6: 4Q | BK6: 2019 | BL6: 1Q | BM6: 2Q | BN6: 3Q | BO6: 4Q | BP6: 2020 | BQ6: 1Q | BR6: 2Q | BS6: 3Q | BT6: 4Q | BU6: 2021 | BV6: 1Q | BW6: 2Q | BX6: 3Q | BY6: 4Q | BZ6: 2022 | CA6: 1Q | CB6: 2Q | CC6: 3Q | CD6: 4Q | CE6: 2023 | CF6: 1Q | CG6: 2Q | CH6: 3Q | CI6: 4Q | CJ6: 2024 | CK6: 1Q | CL6: 2Q | CM6: 3Q | CN6: 4Q | CO6: 2025 | CP6: 1Q | CQ6: 2Q | CR6: 3Q | CS6: 4Q | CT6: 2026 | CU6: 1Q | CV6: 2QE | CW6: 3QE | CX6: 4QE | CY6: 2027E | CZ6: 1QE | DA6: 2QE | DB6: 3QE | DC6: 4QE | DD6: 2028E | DE6: 1QE | DF6: 2QE | DG6: 3QE | DH6: 4QE | DI6: 2029E
B7: DIVISIONAL SUMMARY
B8: Net Sales
B9: North America | C9: 3615.062 | D9: 5201.624 | E9: 5139.412 | F9: 4750.711 | G9: 4732.073 | H9: 4819 | I9: 4669.6 | J9: 4658.5 | K9: 4786.3 | L9: 5129.3 | M9: 5722.5 | N9: 6107.1 | O9: 6414.5 | P9: =P31 -> 6778.3 | Q9: =Q31 -> 6696 | R9: =+'3. Segment Analysis'!R9 -> 1903 | S9: =+'3. Segment Analysis'!S9 -> 1701 | T9: =+'3. Segment Analysis'!T9 -> 1836 | U9: =+'3. Segment Analysis'!U9 -> 2139 | V9: =+'3. Segment Analysis'!V9 -> 7579 | W9: =+'3. Segment Analysis'!W9 -> 2200 | X9: =+'3. Segment Analysis'!X9 -> 2066 | Y9: =+'3. Segment Analysis'!Y9 -> 2149 | ... AA9: =+'3. Segment Analysis'!AA9 -> 8839 | AB9: =AA9 -> 8839 | AC9: =+'3. Segment Analysis'!AC9 -> 2866 | AD9: =+'3. Segment Analysis'!AD9 -> 2564 | AE9: =+'3. Segment Analysis'!AE9 -> 2737 | AF9: =+'3. Segment Analysis'!AF9 -> 2991 | AG9: =+'3. Segment Analysis'!AG9 -> 11158 | AH9: =+'3. Segment Analysis'!AH9 -> 3135 | AI9: =+'3. Segment Analysis'!AI9 -> 2801 | AJ9: =+'3. Segment Analysis'!AJ9 -> 3069 | ... DI9: =+'3. Segment Analysis'!DI9 -> 18673.44
B10: EMEA | C10: -- | D10: -- | E10: -- | F10: -- | G10: -- | H10: -- | I10: -- | J10: -- | K10: -- | L10: -- | M10: -- | N10: -- | O10: -- | P10: =P32+P33 -> 5512.3 | Q10: =Q32+Q33 -> 5041.9 | R10: =+'3. Segment Analysis'!R10 -> 1335 | S10: =+'3. Segment Analysis'!S10 -> 1077 | T10: =+'3. Segment Analysis'!T10 -> 1175 | U10: =+'3. Segment Analysis'!U10 -> 1311 | V10: =+'3. Segment Analysis'!V10 -> 4898 | W10: =+'3. Segment Analysis'!W10 -> 1562 | X10: =+'3. Segment Analysis'!X10 -> 1176 | Y10: =+'3. Segment Analysis'!Y10 -> 1237 | ... AA10: =+'3. Segment Analysis'!AA10 -> 5344 | AB10: =AA10 -> 5344 | AC10: =+'3. Segment Analysis'!AC10 -> 1503 | AD10: =+'3. Segment Analysis'!AD10 -> 1160 | AE10: =+'3. Segment Analysis'!AE10 -> 1360 | AF10: =+'3. Segment Analysis'!AF10 -> 1399 | AG10: =+'3. Segment Analysis'!AG10 -> 5422 | AH10: =+'3. Segment Analysis'!AH10 -> 1667 | AI10: =+'3. Segment Analysis'!AI10 -> 1369 | AJ10: =+'3. Segment Analysis'!AJ10 -> 1648 | ... DI10: =+'3. Segment Analysis'!DI10 -> 11085.17
B11: Greater China | C11: -- | D11: -- | E11: -- | F11: -- | G11: -- | H11: -- | I11: -- | J11: -- | K11: -- | L11: -- | M11: -- | N11: =O11/1.5 -> 902.66667 | O11: 1354 | P11: =P34 -> 1743.3 | Q11: =Q34 -> 1741.8 | R11: =+'3. Segment Analysis'!R11 -> 460 | S11: =+'3. Segment Analysis'!S11 -> 482 | T11: =+'3. Segment Analysis'!T11 -> 554 | U11: =+'3. Segment Analysis'!U11 -> 564 | V11: =+'3. Segment Analysis'!V11 -> 2060 | W11: =+'3. Segment Analysis'!W11 -> 528 | X11: =+'3. Segment Analysis'!X11 -> 650 | Y11: =+'3. Segment Analysis'!Y11 -> 694 | ... AA11: =+'3. Segment Analysis'!AA11 -> 2539 | AB11: =AA11 -> 2539 | AC11: =+'3. Segment Analysis'!AC11 -> 577 | AD11: =+'3. Segment Analysis'!AD11 -> 582 | AE11: =+'3. Segment Analysis'!AE11 -> 641 | AF11: =+'3. Segment Analysis'!AF11 -> 678 | AG11: =+'3. Segment Analysis'!AG11 -> 2478 | AH11: =+'3. Segment Analysis'!AH11 -> 574 | AI11: =+'3. Segment Analysis'!AI11 -> 629 | AJ11: =+'3. Segment Analysis'!AJ11 -> 697 | ... DI11: =+'3. Segment Analysis'!DI11 -> 3624.0423
B12: APAC & Latam | C12: -- | D12: -- | E12: -- | F12: -- | G12: -- | H12: -- | I12: -- | J12: -- | K12: -- | L12: -- | M12: -- | N12: -- | O12: -- | P12: =P36+P35 -> 2627.9 | Q12: =Q36+Q35 -> 2923.6 | R12: =+'3. Segment Analysis'!R12 -> 754 | S12: =+'3. Segment Analysis'!S12 -> 947 | T12: =+'3. Segment Analysis'!T12 -> 838 | U12: =+'3. Segment Analysis'!U12 -> 963 | V12: =+'3. Segment Analysis'!V12 -> 3502 | W12: =+'3. Segment Analysis'!W12 -> 990 | X12: =+'3. Segment Analysis'!X12 -> 1145 | Y12: =+'3. Segment Analysis'!Y12 -> 994 | ... AA12: =+'3. Segment Analysis'!AA12 -> 4239 | AB12: =AA12 -> 4239 | AC12: =+'3. Segment Analysis'!AC12 -> 1094 | AD12: =+'3. Segment Analysis'!AD12 -> 1314 | AE12: =+'3. Segment Analysis'!AE12 -> 1062 | AF12: =+'3. Segment Analysis'!AF12 -> 1238 | AG12: =+'3. Segment Analysis'!AG12 -> 4708 | AH12: =+'3. Segment Analysis'!AH12 -> 1060 | AI12: =+'3. Segment Analysis'!AI12 -> 1240 | AJ12: =+'3. Segment Analysis'!AJ12 -> 1114 | ... DI12: =+'3. Segment Analysis'!DI12 -> 6214.6093
B13: Global Brand | C13: -- | D13: -- | E13: -- | F13: -- | G13: -- | H13: -- | I13: -- | J13: -- | K13: -- | L13: -- | M13: -- | N13: -- | O13: -- | P13: =+P37 -> 95.3 | Q13: =+Q37 -> 105.3 | R13: =+'3. Segment Analysis'!R13 -> 31 | S13: =+'3. Segment Analysis'!S13 -> 24 | T13: =+'3. Segment Analysis'!T13 -> 22 | U13: =+'3. Segment Analysis'!U13 -> 29 | V13: =+'3. Segment Analysis'!V13 -> 106 | W13: =+'3. Segment Analysis'!W13 -> 33 | X13: =+'3. Segment Analysis'!X13 -> 25 | Y13: =+'3. Segment Analysis'!Y13 -> 27 | ... AA13: =+'3. Segment Analysis'!AA13 -> 111 | AB13: =AA13 -> 111 | AC13: =+'3. Segment Analysis'!AC13 -> 27 | AD13: =+'3. Segment Analysis'!AD13 -> 28 | AE13: =+'3. Segment Analysis'!AE13 -> 29 | AF13: =+'3. Segment Analysis'!AF13 -> 31 | AG13: =+'3. Segment Analysis'!AG13 -> 115 | AH13: =+'3. Segment Analysis'!AH13 -> 32 | AI13: =+'3. Segment Analysis'!AI13 -> 31 | AJ13: =+'3. Segment Analysis'!AJ13 -> 26 | ... DI13: =+'3. Segment Analysis'!DI13 -> 46
B14: Total Nike Brand | C14: -- | D14: -- | E14: -- | F14: -- | G14: -- | H14: -- | I14: -- | J14: -- | K14: -- | L14: -- | M14: -- | N14: -- | O14: -- | P14: =SUM(P9:P13) -> 16757.1 | Q14: =SUM(Q9:Q13) -> 16508.6 | R14: =SUM(R9:R13) -> 4483 | S14: =SUM(S9:S13) -> 4231 | T14: =SUM(T9:T13) -> 4425 | U14: =SUM(U9:U13) -> 5006 | V14: =SUM(V9:V13) -> 18145 | W14: =SUM(W9:W13) -> 5313 | ... DI14: =SUM(DI9:DI13) -> 39643.261
B15: Converse | C15: -- | D15: -- | E15: -- | F15: -- | G15: -- | H15: -- | I15: -- | J15: -- | K15: -- | L15: -- | M15: -- | N15: -- | O15: -- | P15: =P39 -> 2419 | Q15: =Q39 -> 2529.5 | R15: =+'3. Segment Analysis'!R18 -> 694 | S15: =+'3. Segment Analysis'!S18 -> 639 | T15: =+'3. Segment Analysis'!T18 -> 680 | U15: =+'3. Segment Analysis'!U18 -> 773 | V15: =+'3. Segment Analysis'!V18 -> 2786 | W15: =+'3. Segment Analysis'!W18 -> 773 | X15: =+'3. Segment Analysis'!X18 -> 673 | Y15: =+'3. Segment Analysis'!Y18 -> 753 | ... AA15: =+'3. Segment Analysis'!AA18 -> 3095 | AB15: =+AA15 -> 3095 | AC15: =+'3. Segment Analysis'!AC18 -> 418 | AD15: =+'3. Segment Analysis'!AD18 -> 316 | AE15: =+'3. Segment Analysis'!AE18 -> 361 | AF15: =+'3. Segment Analysis'!AF18 -> 354 | AG15: =+'3. Segment Analysis'!AG18 -> 1449 | AH15: =+'3. Segment Analysis'!AH18 -> 494 | AI15: =+'3. Segment Analysis'!AI18 -> 360 | AJ15: =+'3. Segment Analysis'!AJ18 -> 420 | ... DI15: =+'3. Segment Analysis'!DI18 -> 861.872
B16: Corporate | C16: -- | D16: -- | E16: -- | F16: -- | G16: -- | H16: -- | I16: -- | J16: -- | K16: -- | L16: -- | M16: -- | N16: -- | O16: -- | P16: =P40 -> 0 | Q16: =Q40 -> -24.1 | R16: =+'3. Segment Analysis'!R19 -> -2 | S16: =+'3. Segment Analysis'!S19 -> -28 | T16: =+'3. Segment Analysis'!T19 -> -26 | U16: =+'3. Segment Analysis'!U19 -> -13 | V16: =+'3. Segment Analysis'!V19 -> -69 | W16: =+'3. Segment Analysis'!W19 -> -5 | X16: =+'3. Segment Analysis'!X19 -> -4 | Y16: =+'3. Segment Analysis'!Y19 -> -8 | ... AA16: =+'3. Segment Analysis'!AA19 -> -39 | AB16: =+AA16 -> -39 | AC16: =+'3. Segment Analysis'!AC19 -> -11 | AD16: =+'3. Segment Analysis'!AD19 -> -9 | AE16: =+'3. Segment Analysis'!AE19 -> -3 | AF16: =+'3. Segment Analysis'!AF19 -> 6 | AG16: =+'3. Segment Analysis'!AG19 -> -17 | AH16: =+'3. Segment Analysis'!AH19 -> 9 | AI16: =+'3. Segment Analysis'!AI19 -> 1 | AJ16: =+'3. Segment Analysis'!AJ19 -> -2 | ... DI16: =+'3. Segment Analysis'!DI19 -> 0
B17: Net Sales | C17: =C57 -> 6470.625 | D17: =D57 -> 9186.539 | E17: =E57 -> 9553.1 | F17: =F57 -> 8776.9 | G17: =G57 -> 8995.1 | H17: =H57 -> 9488.8 | I17: =I57 -> 9893 | J17: =J57 -> 10697 | ... O17: =O57 -> 18627 | P17: =+P14+P15+P16 -> 19176.1 | Q17: =+Q14+Q15+Q16 -> 19014 | R17: =+R14+R15+R16 -> 5175 | S17: =+S14+S15+S16 -> 4842 | T17: =+T14+T15+T16 -> 5079 | U17: =+U14+U15+U16 -> 5766 | V17: =+V14+V15+V16 -> 20862 | W17: =+W14+W15+W16 -> 6081 | ... DI17: =+DI14+DI15+DI16 -> 40505.133
B19: Operating Profit
B20: North America | C20: -- | D20: -- | E20: -- | F20: -- | G20: -- | H20: -- | I20: -- | J20: -- | K20: -- | L20: -- | M20: -- | N20: -- | O20: -- | P20: =P44 -> 1429.3 | Q20: =Q44 -> 1538.1 | R20: =+'3. Segment Analysis'!R163 -> 443 | S20: =+'3. Segment Analysis'!S163 -> 356 | T20: =+'3. Segment Analysis'!T163 -> 419 | U20: =+'3. Segment Analysis'!U163 -> 518 | V20: =+'3. Segment Analysis'!V163 -> 1736 | W20: =+'3. Segment Analysis'!W163 -> 534 | X20: =+'3. Segment Analysis'!X163 -> 418 | Y20: =+'3. Segment Analysis'!Y163 -> 496 | ... AA20: =+'3. Segment Analysis'!AA163 -> 2007 | AC20: =+'3. Segment Analysis'!AC163 -> 645 | AD20: =+'3. Segment Analysis'!AD163 -> 565 | AE20: =+'3. Segment Analysis'!AE163 -> 653 | AF20: =+'3. Segment Analysis'!AF163 -> 778 | AG20: =AG44 -> 2641 | AH20: =+'3. Segment Analysis'!AH163 -> 813 | AI20: =+'3. Segment Analysis'!AI163 -> 649 | AJ20: =+'3. Segment Analysis'!AJ163 -> 729 | AK20: =+'3. Segment Analysis'!AK163 -> 888 | AL20: =+'3. Segment Analysis'!AL163 -> 3079 | AM20: =+'3. Segment Analysis'!AM163 -> 970 | AN20: =+'3. Segment Analysis'!AN163 -> 785 | AO20: =+'3. Segment Analysis'!AO163 -> 830 | ... DI20: =+'3. Segment Analysis'!DI163 -> 5228.2873
B21: EMEA | C21: -- | D21: -- | E21: -- | F21: -- | G21: -- | H21: -- | I21: -- | J21: -- | K21: -- | L21: -- | M21: -- | N21: -- | O21: -- | P21: =P45+P46 -> 1354.2 | Q21: =Q45+Q46 -> 1136.9 | R21: =+'3. Segment Analysis'!R164 -> 353 | S21: =+'3. Segment Analysis'!S164 -> 190 | T21: =+'3. Segment Analysis'!T164 -> 222 | U21: =+'3. Segment Analysis'!U164 -> 209 | V21: =+'3. Segment Analysis'!V164 -> 974 | W21: =+'3. Segment Analysis'!W164 -> 293 | X21: =+'3. Segment Analysis'!X164 -> 125 | Y21: =+'3. Segment Analysis'!Y164 -> 209 | ... AA21: =+'3. Segment Analysis'!AA164 -> 831 | AC21: =+'3. Segment Analysis'!AC164 -> 266 | AD21: =+'3. Segment Analysis'!AD164 -> 147 | AE21: =+'3. Segment Analysis'!AE164 -> 243 | AF21: =+'3. Segment Analysis'!AF164 -> 221 | AG21: =AG45+AG46 -> 877 | AH21: =+'3. Segment Analysis'!AH164 -> 346 | AI21: =+'3. Segment Analysis'!AI164 -> 171 | AJ21: =+'3. Segment Analysis'!AJ164 -> 354 | AK21: =+'3. Segment Analysis'!AK164 -> 263 | AL21: =+'3. Segment Analysis'!AL164 -> 1134 | AM21: =+'3. Segment Analysis'!AM164 -> 472 | AN21: =+'3. Segment Analysis'!AN164 -> 318 | AO21: =+'3. Segment Analysis'!AO164 -> 385 | ... DI21: =+'3. Segment Analysis'!DI164 -> 2569.6072
B22: Greater China | C22: -- | D22: -- | E22: -- | F22: -- | G22: -- | H22: -- | I22: -- | J22: -- | K22: -- | L22: -- | M22: -- | N22: -- | O22: -- | P22: =P47 -> 575.2 | Q22: =Q47 -> 637.1 | R22: =+'3. Segment Analysis'!R165 -> 164 | S22: =+'3. Segment Analysis'!S165 -> 174 | T22: =+'3. Segment Analysis'!T165 -> 213 | U22: =+'3. Segment Analysis'!U165 -> 226 | V22: =+'3. Segment Analysis'!V165 -> 777 | W22: =+'3. Segment Analysis'!W165 -> 171 | X22: =+'3. Segment Analysis'!X165 -> 220 | Y22: =+'3. Segment Analysis'!Y165 -> 273 | ... AA22: =+'3. Segment Analysis'!AA165 -> 911 | AC22: =+'3. Segment Analysis'!AC165 -> 165 | AD22: =+'3. Segment Analysis'!AD165 -> 187 | AE22: =+'3. Segment Analysis'!AE165 -> 218 | AF22: =+'3. Segment Analysis'!AF165 -> 243 | AG22: =AG47 -> 813 | AH22: =+'3. Segment Analysis'!AH165 -> 170 | AI22: =+'3. Segment Analysis'!AI165 -> 197 | AJ22: =+'3. Segment Analysis'!AJ165 -> 234 | AK22: =+'3. Segment Analysis'!AK165 -> 223 | AL22: =+'3. Segment Analysis'!AL165 -> 824 | AM22: =+'3. Segment Analysis'!AM165 -> 218 | AN22: =+'3. Segment Analysis'!AN165 -> 258 | AO22: =+'3. Segment Analysis'!AO165 -> 251 | ... DI22: =+'3. Segment Analysis'!DI165 -> 906.40022
B23: APAC & Latam | C23: -- | D23: -- | E23: -- | F23: -- | G23: -- | H23: -- | I23: -- | J23: -- | K23: -- | L23: -- | M23: -- | N23: -- | O23: -- | P23: =P48+P49 -> 548 | Q23: =Q48+Q49 -> 672.9 | R23: =+'3. Segment Analysis'!R166 -> 151 | S23: =+'3. Segment Analysis'!S166 -> 230 | T23: =+'3. Segment Analysis'!T166 -> 204 | U23: =+'3. Segment Analysis'!U166 -> 217 | V23: =+'3. Segment Analysis'!V166 -> 802 | W23: =+'3. Segment Analysis'!W166 -> 224 | X23: =+'3. Segment Analysis'!X166 -> 282 | Y23: =+'3. Segment Analysis'!Y166 -> 239 | ... AA23: =+'3. Segment Analysis'!AA166 -> 989 | AC23: =+'3. Segment Analysis'!AC166 -> 244 | AD23: =+'3. Segment Analysis'!AD166 -> 343 | AE23: =+'3. Segment Analysis'!AE166 -> 240 | AF23: =+'3. Segment Analysis'!AF166 -> 300 | AG23: =AG48+AG49 -> 1127 | AH23: =+'3. Segment Analysis'!AH166 -> 234 | AI23: =+'3. Segment Analysis'!AI166 -> 290 | AJ23: =+'3. Segment Analysis'!AJ166 -> 249 | AK23: =+'3. Segment Analysis'!AK166 -> 310 | AL23: =+'3. Segment Analysis'!AL166 -> 1083 | AM23: =+'3. Segment Analysis'!AM166 -> 167 | AN23: =+'3. Segment Analysis'!AN166 -> 265 | AO23: =+'3. Segment Analysis'!AO166 -> 256 | ... DI23: =+'3. Segment Analysis'!DI166 -> 1680.3031
B24: Global Brand | C24: -- | D24: -- | E24: -- | F24: -- | G24: -- | H24: -- | I24: -- | J24: -- | K24: -- | L24: -- | M24: -- | N24: -- | O24: -- | P24: =P50 -> -811.5 | Q24: =Q50 -> -866.8 | R24: =+'3. Segment Analysis'!R167 -> -245 | S24: =+'3. Segment Analysis'!S167 -> -221 | T24: =+'3. Segment Analysis'!T167 -> -237 | U24: =+'3. Segment Analysis'!U167 -> -268 | V24: =+'3. Segment Analysis'!V167 -> -971 | W24: =+'3. Segment Analysis'!W167 -> -261 | X24: =+'3. Segment Analysis'!X167 -> -273 | Y24: =+'3. Segment Analysis'!Y167 -> -292 | ... AA24: =+'3. Segment Analysis'!AA167 -> -1177 | AC24: =+'3. Segment Analysis'!AC167 -> -456 | AD24: =+'3. Segment Analysis'!AD167 -> -410 | AE24: =+'3. Segment Analysis'!AE167 -> -414 | AF24: =+'3. Segment Analysis'!AF167 -> -466 | AG24: =AG50 -> -1746 | AH24: =+'3. Segment Analysis'!AH167 -> -466 | AI24: =+'3. Segment Analysis'!AI167 -> -462 | AJ24: =+'3. Segment Analysis'!AJ167 -> -528 | AK24: =+'3. Segment Analysis'!AK167 -> -549 | AL24: =+'3. Segment Analysis'!AL167 -> -2005 | AM24: =+'3. Segment Analysis'!AM167 -> -533 | AN24: =+'3. Segment Analysis'!AN167 -> -554 | AO24: =+'3. Segment Analysis'!AO167 -> -552 | ... DI24: =+'3. Segment Analysis'!DI167 -> -5047.1868
B25: Total Nike Brand | C25: -- | D25: -- | E25: -- | F25: -- | G25: -- | H25: -- | I25: -- | J25: -- | K25: -- | L25: -- | M25: -- | N25: -- | O25: -- | P25: =SUM(P20:P24) -> 3095.2 | Q25: =SUM(Q20:Q24) -> 3118.2 | R25: =SUM(R20:R24) -> 866 | S25: =SUM(S20:S24) -> 729 | T25: =SUM(T20:T24) -> 821 | U25: =SUM(U20:U24) -> 902 | V25: =SUM(V20:V24) -> 3318 | W25: =SUM(W20:W24) -> 961 | ... AA25: =SUM(AA20:AA24) -> 3561 | AC25: =SUM(AC20:AC24) -> 864 | AD25: =SUM(AD20:AD24) -> 832 | AE25: =SUM(AE20:AE24) -> 940 | AF25: =SUM(AF20:AF24) -> 1076 | AG25: =SUM(AG20:AG24) -> 3712 | AH25: =SUM(AH20:AH24) -> 1097 | AI25: =SUM(AI20:AI24) -> 845 | AJ25: =SUM(AJ20:AJ24) -> 1038 | ... DI25: =SUM(DI20:DI24) -> 5337.4111
B26: Converse | C26: -- | D26: -- | E26: -- | F26: -- | G26: -- | H26: -- | I26: -- | J26: -- | K26: -- | L26: -- | M26: -- | N26: -- | O26: -- | P26: =P52 -> 208.7 | Q26: =Q52 -> 299.4 | R26: =+'3. Segment Analysis'!R173 -> 109 | S26: =+'3. Segment Analysis'!S173 -> 59 | T26: =+'3. Segment Analysis'!T173 -> 85 | U26: =+'3. Segment Analysis'!U173 -> 82 | V26: =+'3. Segment Analysis'!V173 -> 335 | W26: =+'3. Segment Analysis'!W173 -> 86 | X26: =+'3. Segment Analysis'!X173 -> 57 | Y26: =+'3. Segment Analysis'!Y173 -> 87 | ... AA26: =+'3. Segment Analysis'!AA173 -> 341 | AC26: =+'3. Segment Analysis'!AC173 -> 124 | AD26: =+'3. Segment Analysis'!AD173 -> 91 | AE26: =+'3. Segment Analysis'!AE173 -> 121 | AF26: =+'3. Segment Analysis'!AF173 -> 89 | AG26: =AG52 -> 425 | AH26: =+'3. Segment Analysis'!AH173 -> 169 | AI26: =+'3. Segment Analysis'!AI173 -> 100 | AJ26: =+'3. Segment Analysis'!AJ173 -> 133 | AK26: =+'3. Segment Analysis'!AK173 -> 94 | AL26: =+'3. Segment Analysis'!AL173 -> 496 | AM26: =+'3. Segment Analysis'!AM173 -> 186 | AN26: =+'3. Segment Analysis'!AN173 -> 88 | AO26: =+'3. Segment Analysis'!AO173 -> 163 | ... DI26: =+'3. Segment Analysis'!DI173 -> 4.51189
B27: Corporate | C27: -- | D27: -- | E27: -- | F27: -- | G27: -- | H27: -- | I27: -- | J27: -- | K27: -- | L27: -- | M27: -- | N27: -- | O27: -- | P27: =P53 -> -760.6 | Q27: =Q53 -> -894.4 | R27: =+'3. Segment Analysis'!R174 -> -221 | S27: =+'3. Segment Analysis'!S174 -> -178 | T27: =+'3. Segment Analysis'!T174 -> -199 | U27: =+'3. Segment Analysis'!U174 -> -207 | V27: =+'3. Segment Analysis'!V174 -> -805 | W27: =+'3. Segment Analysis'!W174 -> -195 | X27: =+'3. Segment Analysis'!X174 -> -208 | Y27: =+'3. Segment Analysis'!Y174 -> -242 | ... AA27: =+'3. Segment Analysis'!AA174 -> -916 | AC27: =+'3. Segment Analysis'!AC174 -> -196 | AD27: =+'3. Segment Analysis'!AD174 -> -214 | AE27: =+'3. Segment Analysis'!AE174 -> -207 | AF27: =+'3. Segment Analysis'!AF174 -> -267 | AG27: =AG53 -> -884 | AH27: =+'3. Segment Analysis'!AH174 -> -218 | AI27: =+'3. Segment Analysis'!AI174 -> -220 | AJ27: =+'3. Segment Analysis'!AJ174 -> -282 | AK27: =+'3. Segment Analysis'!AK174 -> -301 | AL27: =+'3. Segment Analysis'!AL174 -> -1021 | AM27: =+'3. Segment Analysis'!AM174 -> -242 | AN27: =+'3. Segment Analysis'!AN174 -> -273 | AO27: =+'3. Segment Analysis'!AO174 -> -281 | ... DI27: =+'3. Segment Analysis'!DI174 -> -2852.9313
B28: EBIT | C28: -- | D28: -- | E28: -- | F28: -- | G28: -- | H28: -- | I28: -- | J28: -- | K28: -- | L28: -- | M28: -- | N28: -- | O28: -- | P28: =SUM(P25:P27) -> 2543.3 | Q28: =SUM(Q25:Q27) -> 2523.2 | R28: =+R25+R26+R27 -> 754 | S28: =+S25+S26+S27 -> 610 | T28: =+T25+T26+T27 -> 707 | U28: =+U25+U26+U27 -> 777 | V28: =+V25+V26+V27 -> 2848 | W28: =+W25+W26+W27 -> 852 | X28: =+X25+X26+X27 -> 621 | Y28: =+Y25+Y26+Y27 -> 770 | ... AA28: =+AA25+AA26+AA27 -> 2986 | AC28: =+AC25+AC26+AC27 -> 792 | AD28: =+AD25+AD26+AD27 -> 709 | AE28: =+AE25+AE26+AE27 -> 854 | AF28: =+AF25+AF26+AF27 -> 898 | AG28: =SUM(AG25:AG27) -> 3253 | AH28: =+AH25+AH26+AH27 -> 1048 | AI28: =+AI25+AI26+AI27 -> 725 | AJ28: =+AJ25+AJ26+AJ27 -> 889 | AK28: =+AK25+AK26+AK27 -> 928 | AL28: =+AL25+AL26+AL27 -> 3590 | AM28: =+AM25+AM26+AM27 -> 1238 | AN28: =+AN25+AN26+AN27 -> 887 | AO28: =+AO25+AO26+AO27 -> 1052 | ... DI28: =+DI25+DI26+DI27 -> 2488.9917
B30: Net Sales - OLD SEGMENTS
B31: North America | C31: 3615.062 | D31: 5201.624 | E31: 5139.412 | F31: 4750.711 | G31: 4732.073 | H31: 4819 | I31: 4669.6 | J31: 4658.5 | K31: 4786.3 | L31: 5129.3 | M31: 5722.5 | N31: 6107.1 | O31: 6414.5 | P31: 6778.3 | Q31: 6696 | R31: 1903 | S31: 1701 | T31: 1836 | U31: 2139 | V31: =SUM(R31:U31) -> 7579 | W31: 2200 | X31: 2066 | Y31: 2149 | Z31: 2424 | AA31: =SUM(W31:Z31) -> 8839 | AC31: 2866 | AD31: 2564 | AE31: 2737 | AF31: 2991 | AG31: =SUM(AC31:AF31) -> 11158 | AH31: 3135 | AI31: 2801 | AJ31: 3069 | AK31: 3294 | AL31: =SUM(AH31:AK31) -> 12299 | AM31: 3513 | AN31: 3241 | AO31: 3254 | AP31: 3732 | AQ31: =SUM(AM31:AP31) -> 13740 | AR31: 3799 | AS31: 3547 | AT31: 3683 | AU31: 3735 | AV31: =SUM(AR31:AU31) -> 14764 | AW31: 4031 | AX31: 3650 | AY31: 3782 | AZ31: 3753 | BA31: =SUM(AW31:AZ31) -> 15216 | BB31: -- | BC31: -- | BD31: -- | BE31: -- | BF31: -- | BG31: -- | BH31: -- | BI31: -- | BJ31: -- | BK31: -- | BL31: -- | BM31: -- | BN31: -- | BO31: -- | BP31: -- | BQ31: -- | BR31: -- | BS31: -- | BT31: -- | BU31: -- | BV31: -- | BW31: -- | BX31: -- | BY31: -- | BZ31: -- | CA31: -- | CB31: -- | CC31: -- | CD31: -- | CE31: -- | CF31: -- | CG31: -- | CH31: -- | CI31: -- | CJ31: -- | CK31: -- | CL31: -- | CM31: -- | CN31: -- | CO31: -- | CP31: -- | CQ31: -- | CR31: -- | CS31: -- | CT31: -- | CU31: -- | CV31: -- | CW31: -- | CX31: -- | CY31: -- | CZ31: -- | DA31: -- | DB31: -- | DC31: -- | DD31: -- | DE31: -- | DF31: -- | DG31: -- | DH31: -- | DI31: --
B32: Western Europe | C32: -- | D32: -- | E32: -- | F32: -- | G32: -- | H32: -- | I32: -- | J32: -- | K32: -- | L32: -- | M32: -- | N32: -- | O32: -- | P32: 4139.1 | Q32: 3892 | R32: 1066 | S32: 853 | T32: 922 | U32: 1017 | V32: =SUM(R32:U32) -> 3858 | W32: 1228 | X32: 915 | Y32: 962 | Z32: 1039 | AA32: =SUM(W32:Z32) -> 4144 | AC32: 1176 | AD32: 908 | AE32: 1057 | AF32: 1052 | AG32: =SUM(AC32:AF32) -> 4193 | AH32: 1301 | AI32: 1074 | AJ32: 1292 | AK32: 1312 | AL32: =SUM(AH32:AK32) -> 4979 | AM32: 1714 | AN32: 1312 | AO32: 1413 | AP32: 1267 | AQ32: =SUM(AM32:AP32) -> 5706 | AR32: 1641 | AS32: 1299 | AT32: 1442 | AU32: 1502 | AV32: =SUM(AR32:AU32) -> 5884 | AW32: 1763 | AX32: 1385 | AY32: 1499 | AZ32: 1564 | BA32: =SUM(AW32:AZ32) -> 6211 | BB32: -- | BC32: -- | BD32: -- | BE32: -- | BF32: -- | BG32: -- | BH32: -- | BI32: -- | BJ32: -- | BK32: -- | BL32: -- | BM32: -- | BN32: -- | BO32: -- | BP32: -- | BQ32: -- | BR32: -- | BS32: -- | BT32: -- | BU32: -- | BV32: -- | BW32: -- | BX32: -- | BY32: -- | BZ32: -- | CA32: -- | CB32: -- | CC32: -- | CD32: -- | CE32: -- | CF32: -- | CG32: -- | CH32: -- | CI32: -- | CJ32: -- | CK32: -- | CL32: -- | CM32: -- | CN32: -- | CO32: -- | CP32: -- | CQ32: -- | CR32: -- | CS32: -- | CT32: -- | CU32: -- | CV32: -- | CW32: -- | CX32: -- | CY32: -- | CZ32: -- | DA32: -- | DB32: -- | DC32: -- | DD32: -- | DE32: -- | DF32: -- | DG32: -- | DH32: -- | DI32: --
B33: Central & Eastern Europe | C33: -- | D33: -- | E33: -- | F33: -- | G33: -- | H33: -- | I33: -- | J33: -- | K33: -- | L33: -- | M33: -- | N33: -- | O33: -- | P33: 1373.2 | Q33: 1149.9 | R33: 269 | S33: 224 | T33: 253 | U33: 294 | V33: =SUM(R33:U33) -> 1040 | W33: 334 | X33: 261 | Y33: 275 | Z33: 330 | AA33: =SUM(W33:Z33) -> 1200 | AC33: 327 | AD33: 252 | AE33: 303 | AF33: 347 | AG33: =SUM(AC33:AF33) -> 1229 | AH33: 366 | AI33: 295 | AJ33: 356 | AK33: 370 | AL33: =SUM(AH33:AK33) -> 1387 | AM33: 392 | AN33: 347 | AO33: 321 | AP33: 360 | AQ33: =SUM(AM33:AP33) -> 1420 | AR33: 401 | AS33: 326 | AT33: 359 | AU33: 345 | AV33: =SUM(AR33:AU33) -> 1431 | AW33: 440 | AX33: 328 | AY33: 362 | AZ33: 357 | BA33: =SUM(AW33:AZ33) -> 1487 | BB33: -- | BC33: -- | BD33: -- | BE33: -- | BF33: -- | BG33: -- | BH33: -- | BI33: -- | BJ33: -- | BK33: -- | BL33: -- | BM33: -- | BN33: -- | BO33: -- | BP33: -- | BQ33: -- | BR33: -- | BS33: -- | BT33: -- | BU33: -- | BV33: -- | BW33: -- | BX33: -- | BY33: -- | BZ33: -- | CA33: -- | CB33: -- | CC33: -- | CD33: -- | CE33: -- | CF33: -- | CG33: -- | CH33: -- | CI33: -- | CJ33: -- | CK33: -- | CL33: -- | CM33: -- | CN33: -- | CO33: -- | CP33: -- | CQ33: -- | CR33: -- | CS33: -- | CT33: -- | CU33: -- | CV33: -- | CW33: -- | CX33: -- | CY33: -- | CZ33: -- | DA33: -- | DB33: -- | DC33: -- | DD33: -- | DE33: -- | DF33: -- | DG33: -- | DH33: -- | DI33: --
B34: Greater China | C34: -- | D34: -- | E34: -- | F34: -- | G34: -- | H34: -- | I34: -- | J34: -- | K34: -- | L34: -- | M34: -- | N34: =O34/1.5 -> 902.66667 | O34: 1354 | P34: 1743.3 | Q34: 1741.8 | R34: 460 | S34: 482 | T34: 554 | U34: 564 | V34: =SUM(R34:U34) -> 2060 | W34: 528 | X34: 650 | Y34: 694 | Z34: 667 | AA34: =SUM(W34:Z34) -> 2539 | AC34: 577 | AD34: 582 | AE34: 641 | AF34: 678 | AG34: =SUM(AC34:AF34) -> 2478 | AH34: 574 | AI34: 629 | AJ34: 697 | AK34: 702 | AL34: =SUM(AH34:AK34) -> 2602 | AM34: 679 | AN34: 758 | AO34: 801 | AP34: 829 | AQ34: =SUM(AM34:AP34) -> 3067 | AR34: 886 | AS34: 938 | AT34: 982 | AU34: 979 | AV34: =SUM(AR34:AU34) -> 3785 | AW34: 1020 | AX34: 1055 | AY34: 1075 | AZ34: 1087 | BA34: =SUM(AW34:AZ34) -> 4237 | BB34: -- | BC34: -- | BD34: -- | BE34: -- | BF34: -- | BG34: -- | BH34: -- | BI34: -- | BJ34: -- | BK34: -- | BL34: -- | BM34: -- | BN34: -- | BO34: -- | BP34: -- | BQ34: -- | BR34: -- | BS34: -- | BT34: -- | BU34: -- | BV34: -- | BW34: -- | BX34: -- | BY34: -- | BZ34: -- | CA34: -- | CB34: -- | CC34: -- | CD34: -- | CE34: -- | CF34: -- | CG34: -- | CH34: -- | CI34: -- | CJ34: -- | CK34: -- | CL34: -- | CM34: -- | CN34: -- | CO34: -- | CP34: -- | CQ34: -- | CR34: -- | CS34: -- | CT34: -- | CU34: -- | CV34: -- | CW34: -- | CX34: -- | CY34: -- | CZ34: -- | DA34: -- | DB34: -- | DC34: -- | DD34: -- | DE34: -- | DF34: -- | DG34: -- | DH34: -- | DI34: --
B35: Japan | C35: -- | D35: -- | E35: -- | F35: -- | G35: -- | H35: -- | I35: -- | J35: -- | K35: -- | L35: -- | M35: -- | N35: -- | O35: -- | P35: 925.9 | Q35: 882 | R35: 163 | S35: 192 | T35: 195 | U35: 216 | V35: =SUM(R35:U35) -> 766 | W35: 191 | X35: 197 | Y35: 201 | Z35: 240 | AA35: =SUM(W35:Z35) -> 829 | AC35: 197 | AD35: 240 | AE35: 195 | AF35: 244 | AG35: =SUM(AC35:AF35) -> 876 | AH35: 158 | AI35: 210 | AJ35: 177 | AK35: 226 | AL35: =SUM(AH35:AK35) -> 771 | AM35: 160 | AN35: 199 | AO35: 166 | AP35: 230 | AQ35: =SUM(AM35:AP35) -> 755 | AR35: 179 | AS35: 205 | AT35: 205 | AU35: 280 | AV35: =SUM(AR35:AU35) -> 869 | AW35: 245 | AX35: 238 | AY35: 236 | AZ35: 295 | BA35: =SUM(AW35:AZ35) -> 1014 | BB35: -- | BC35: -- | BD35: -- | BE35: -- | BF35: -- | BG35: -- | BH35: -- | BI35: -- | BJ35: -- | BK35: -- | BL35: -- | BM35: -- | BN35: -- | BO35: -- | BP35: -- | BQ35: -- | BR35: -- | BS35: -- | BT35: -- | BU35: -- | BV35: -- | BW35: -- | BX35: -- | BY35: -- | BZ35: -- | CA35: -- | CB35: -- | CC35: -- | CD35: -- | CE35: -- | CF35: -- | CG35: -- | CH35: -- | CI35: -- | CJ35: -- | CK35: -- | CL35: -- | CM35: -- | CN35: -- | CO35: -- | CP35: -- | CQ35: -- | CR35: -- | CS35: -- | CT35: -- | CU35: -- | CV35: -- | CW35: -- | CX35: -- | CY35: -- | CZ35: -- | DA35: -- | DB35: -- | DC35: -- | DD35: -- | DE35: -- | DF35: -- | DG35: -- | DH35: -- | DI35: --
B36: Emerging Markets | C36: -- | D36: -- | E36: -- | F36: -- | G36: -- | H36: -- | I36: -- | J36: -- | K36: -- | L36: -- | M36: -- | N36: -- | O36: -- | P36: 1702 | Q36: 2041.6 | R36: 591 | S36: 755 | T36: 643 | U36: 747 | V36: =SUM(R36:U36) -> 2736 | W36: 799 | X36: 948 | Y36: 793 | Z36: 870 | AA36: =SUM(W36:Z36) -> 3410 | AC36: 897 | AD36: 1074 | AE36: 867 | AF36: 994 | AG36: =SUM(AC36:AF36) -> 3832 | AH36: 902 | AI36: 1030 | AJ36: 937 | AK36: 1080 | AL36: =SUM(AH36:AK36) -> 3949 | AM36: 934 | AN36: 1075 | AO36: 955 | AP36: 934 | AQ36: =SUM(AM36:AP36) -> 3898 | AR36: 966 | AS36: 984 | AT36: 879 | AU36: 872 | AV36: =SUM(AR36:AU36) -> 3701 | AW36: 945 | AX36: 1047 | AY36: 950 | AZ36: 1053 | BA36: =SUM(AW36:AZ36) -> 3995 | BB36: -- | BC36: -- | BD36: -- | BE36: -- | BF36: -- | BG36: -- | BH36: -- | BI36: -- | BJ36: -- | BK36: -- | BL36: -- | BM36: -- | BN36: -- | BO36: -- | BP36: -- | BQ36: -- | BR36: -- | BS36: -- | BT36: -- | BU36: -- | BV36: -- | BW36: -- | BX36: -- | BY36: -- | BZ36: -- | CA36: -- | CB36: -- | CC36: -- | CD36: -- | CE36: -- | CF36: -- | CG36: -- | CH36: -- | CI36: -- | CJ36: -- | CK36: -- | CL36: -- | CM36: -- | CN36: -- | CO36: -- | CP36: -- | CQ36: -- | CR36: -- | CS36: -- | CT36: -- | CU36: -- | CV36: -- | CW36: -- | CX36: -- | CY36: -- | CZ36: -- | DA36: -- | DB36: -- | DC36: -- | DD36: -- | DE36: -- | DF36: -- | DG36: -- | DH36: -- | DI36: --
B37: Global Brands | C37: -- | D37: -- | E37: -- | F37: -- | G37: -- | H37: -- | I37: -- | J37: -- | K37: -- | L37: -- | M37: -- | N37: -- | O37: -- | P37: 95.3 | Q37: 105.3 | R37: 31 | S37: 24 | T37: 22 | U37: 29 | V37: =SUM(R37:U37) -> 106 | W37: 33 | X37: 25 | Y37: 27 | Z37: 26 | AA37: =SUM(W37:Z37) -> 111 | AC37: 27 | AD37: 28 | AE37: 29 | AF37: 31 | AG37: =SUM(AC37:AF37) -> 115 | AH37: 32 | AI37: 31 | AJ37: 26 | AK37: 36 | AL37: =SUM(AH37:AK37) -> 125 | AM37: 29 | AN37: 27 | AO37: 29 | AP37: 30 | AQ37: =SUM(AM37:AP37) -> 115 | AR37: 26 | AS37: 18 | AT37: 17 | AU37: 12 | AV37: =SUM(AR37:AU37) -> 73 | AW37: 15 | AX37: 21 | AY37: 19 | AZ37: 18 | BA37: =SUM(AW37:AZ37) -> 73 | BB37: -- | BC37: -- | BD37: -- | BE37: -- | BF37: -- | BG37: -- | BH37: -- | BI37: -- | BJ37: -- | BK37: -- | BL37: -- | BM37: -- | BN37: -- | BO37: -- | BP37: -- | BQ37: -- | BR37: -- | BS37: -- | BT37: -- | BU37: -- | BV37: -- | BW37: -- | BX37: -- | BY37: -- | BZ37: -- | CA37: -- | CB37: -- | CC37: -- | CD37: -- | CE37: -- | CF37: -- | CG37: -- | CH37: -- | CI37: -- | CJ37: -- | CK37: -- | CL37: -- | CM37: -- | CN37: -- | CO37: -- | CP37: -- | CQ37: -- | CR37: -- | CS37: -- | CT37: -- | CU37: -- | CV37: -- | CW37: -- | CX37: -- | CY37: -- | CZ37: -- | DA37: -- | DB37: -- | DC37: -- | DD37: -- | DE37: -- | DF37: -- | DG37: -- | DH37: -- | DI37: --
B38: Total Nike Brand | C38: -- | D38: -- | E38: -- | F38: -- | G38: -- | H38: -- | I38: -- | J38: -- | K38: -- | L38: -- | M38: -- | N38: -- | O38: -- | P38: =SUM(P31:P37) -> 16757.1 | Q38: =SUM(Q31:Q37) -> 16508.6 | R38: =SUM(R31:R37) -> 4483 | S38: =SUM(S31:S37) -> 4231 | T38: =SUM(T31:T37) -> 4425 | U38: =SUM(U31:U37) -> 5006 | V38: =SUM(R38:U38) -> 18145 | W38: =SUM(W31:W37) -> 5313 | X38: =SUM(X31:X37) -> 5062 | Y38: =SUM(Y31:Y37) -> 5101 | Z38: =SUM(Z31:Z37) -> 5596 | AA38: =SUM(W38:Z38) -> 21072 | AC38: =SUM(AC31:AC37) -> 6067 | AD38: =SUM(AD31:AD37) -> 5648 | AE38: =SUM(AE31:AE37) -> 5829 | AF38: =SUM(AF31:AF37) -> 6337 | AG38: =SUM(AC38:AF38) -> 23881 | AH38: =SUM(AH31:AH37) -> 6468 | AI38: =SUM(AI31:AI37) -> 6070 | AJ38: =SUM(AJ31:AJ37) -> 6554 | AK38: =SUM(AK31:AK37) -> 7020 | AL38: =SUM(AH38:AK38) -> 26112 | AM38: =SUM(AM31:AM37) -> 7421 | AN38: =SUM(AN31:AN37) -> 6959 | AO38: =SUM(AO31:AO37) -> 6939 | AP38: =SUM(AP31:AP37) -> 7382 | AQ38: =SUM(AM38:AP38) -> 28701 | AR38: =SUM(AR31:AR37) -> 7898 | AS38: =SUM(AS31:AS37) -> 7317 | AT38: =SUM(AT31:AT37) -> 7567 | AU38: =SUM(AU31:AU37) -> 7725 | AV38: =SUM(AR38:AU38) -> 30507 | AW38: =SUM(AW31:AW37) -> 8459 | AX38: =SUM(AX31:AX37) -> 7724 | AY38: =SUM(AY31:AY37) -> 7923 | AZ38: =SUM(AZ31:AZ37) -> 8127 | BA38: =SUM(AW38:AZ38) -> 32233 | BB38: -- | BC38: -- | BD38: -- | BE38: -- | BF38: -- | BG38: -- | BH38: -- | BI38: -- | BJ38: -- | BK38: -- | BL38: -- | BM38: -- | BN38: -- | BO38: -- | BP38: -- | BQ38: -- | BR38: -- | BS38: -- | BT38: -- | BU38: -- | BV38: -- | BW38: -- | BX38: -- | BY38: -- | BZ38: -- | CA38: -- | CB38: -- | CC38: -- | CD38: -- | CE38: -- | CF38: -- | CG38: -- | CH38: -- | CI38: -- | CJ38: -- | CK38: -- | CL38: -- | CM38: -- | CN38: -- | CO38: -- | CP38: -- | CQ38: -- | CR38: -- | CS38: -- | CT38: -- | CU38: -- | CV38: -- | CW38: -- | CX38: -- | CY38: -- | CZ38: -- | DA38: -- | DB38: -- | DC38: -- | DD38: -- | DE38: -- | DF38: -- | DG38: -- | DH38: -- | DI38: --
B39: Other Businesses | C39: -- | D39: -- | E39: -- | F39: -- | G39: -- | H39: -- | I39: -- | J39: -- | K39: -- | L39: -- | M39: -- | N39: -- | O39: -- | P39: 2419 | Q39: 2529.5 | R39: 694 | S39: 639 | T39: 680 | U39: 773 | V39: =SUM(R39:U39) -> 2786 | W39: =585+188 -> 773 | X39: 673 | Y39: 753 | Z39: 896 | AA39: =SUM(W39:Z39) -> 3095 | AC39: 418 | AD39: 316 | AE39: 361 | AF39: 354 | AG39: =SUM(AC39:AF39) -> 1449 | AH39: 494 | AI39: 360 | AJ39: 420 | AK39: 410 | AL39: =SUM(AH39:AK39) -> 1684 | AM39: 575 | AN39: 434 | AO39: 538 | AP39: 435 | AQ39: =SUM(AM39:AP39) -> 1982 | AR39: 555 | AS39: 398 | AT39: 489 | AU39: 513 | AV39: =SUM(AR39:AU39) -> 1955 | AW39: 574 | AX39: 416 | AY39: 498 | AZ39: 554 | BA39: =SUM(AW39:AZ39) -> 2042 | BB39: -- | BC39: -- | BD39: -- | BE39: -- | BF39: -- | BG39: -- | BH39: -- | BI39: -- | BJ39: -- | BK39: -- | BL39: -- | BM39: -- | BN39: -- | BO39: -- | BP39: -- | BQ39: -- | BR39: -- | BS39: -- | BT39: -- | BU39: -- | BV39: -- | BW39: -- | BX39: -- | BY39: -- | BZ39: -- | CA39: -- | CB39: -- | CC39: -- | CD39: -- | CE39: -- | CF39: -- | CG39: -- | CH39: -- | CI39: -- | CJ39: -- | CK39: -- | CL39: -- | CM39: -- | CN39: -- | CO39: -- | CP39: -- | CQ39: -- | CR39: -- | CS39: -- | CT39: -- | CU39: -- | CV39: -- | CW39: -- | CX39: -- | CY39: -- | CZ39: -- | DA39: -- | DB39: -- | DC39: -- | DD39: -- | DE39: -- | DF39: -- | DG39: -- | DH39: -- | DI39: --
B40: Corporate | C40: -- | D40: -- | E40: -- | F40: -- | G40: -- | H40: -- | I40: -- | J40: -- | K40: -- | L40: -- | M40: -- | N40: -- | O40: -- | P40: 0 | Q40: -24.1 | R40: -2 | S40: -28 | T40: -26 | U40: -13 | V40: =SUM(R40:U40) -> -69 | W40: -5 | X40: -4 | Y40: -8 | Z40: -22 | AA40: =SUM(W40:Z40) -> -39 | AC40: -11 | AD40: -9 | AE40: -3 | AF40: 6 | AG40: =SUM(AC40:AF40) -> -17 | AH40: 9 | AI40: 1 | AJ40: -2 | AK40: -5 | AL40: =SUM(AH40:AK40) -> 3 | AM40: -14 | AN40: -13 | AO40: -17 | AP40: -38 | AQ40: =SUM(AM40:AP40) -> -82 | AR40: -39 | AS40: -29 | AT40: -24 | AU40: 6 | AV40: =SUM(AR40:AU40) -> -86 | AW40: 28 | AX40: 40 | AY40: 11 | AZ40: -4 | BA40: =SUM(AW40:AZ40) -> 75 | BB40: -- | BC40: -- | BD40: -- | BE40: -- | BF40: -- | BG40: -- | BH40: -- | BI40: -- | BJ40: -- | BK40: -- | BL40: -- | BM40: -- | BN40: -- | BO40: -- | BP40: -- | BQ40: -- | BR40: -- | BS40: -- | BT40: -- | BU40: -- | BV40: -- | BW40: -- | BX40: -- | BY40: -- | BZ40: -- | CA40: -- | CB40: -- | CC40: -- | CD40: -- | CE40: -- | CF40: -- | CG40: -- | CH40: -- | CI40: -- | CJ40: -- | CK40: -- | CL40: -- | CM40: -- | CN40: -- | CO40: -- | CP40: -- | CQ40: -- | CR40: -- | CS40: -- | CT40: -- | CU40: -- | CV40: -- | CW40: -- | CX40: -- | CY40: -- | CZ40: -- | DA40: -- | DB40: -- | DC40: -- | DD40: -- | DE40: -- | DF40: -- | DG40: -- | DH40: -- | DI40: --
B41: Net Sales | C41: =C57 -> 6470.625 | D41: =D57 -> 9186.539 | E41: =E57 -> 9553.1 | F41: =F57 -> 8776.9 | G41: =G57 -> 8995.1 | H41: =H57 -> 9488.8 | I41: =I57 -> 9893 | J41: =J57 -> 10697 | ... O41: =O57 -> 18627 | P41: =SUM(P38:P40) -> 19176.1 | Q41: =SUM(Q38:Q40) -> 19014 | R41: =SUM(R38:R40) -> 5175 | S41: =SUM(S38:S40) -> 4842 | T41: =SUM(T38:T40) -> 5079 | U41: =SUM(U38:U40) -> 5766 | V41: =SUM(R41:U41) -> 20862 | W41: =SUM(W38:W40) -> 6081 | X41: =SUM(X38:X40) -> 5731 | Y41: =SUM(Y38:Y40) -> 5846 | Z41: =SUM(Z38:Z40) -> 6470 | AA41: =SUM(W41:Z41) -> 24128 | AC41: =SUM(AC38:AC40) -> 6474 | AD41: =SUM(AD38:AD40) -> 5955 | AE41: =SUM(AE38:AE40) -> 6187 | AF41: =SUM(AF38:AF40) -> 6697 | AG41: =SUM(AC41:AF41) -> 25313 | AH41: =SUM(AH38:AH40) -> 6971 | AI41: =SUM(AI38:AI40) -> 6431 | AJ41: =SUM(AJ38:AJ40) -> 6972 | AK41: =SUM(AK38:AK40) -> 7425 | AL41: =SUM(AH41:AK41) -> 27799 | AM41: =SUM(AM38:AM40) -> 7982 | AN41: =SUM(AN38:AN40) -> 7380 | AO41: =SUM(AO38:AO40) -> 7460 | AP41: =SUM(AP38:AP40) -> 7779 | AQ41: =SUM(AM41:AP41) -> 30601 | AR41: =SUM(AR38:AR40) -> 8414 | AS41: =SUM(AS38:AS40) -> 7686 | AT41: =SUM(AT38:AT40) -> 8032 | AU41: =SUM(AU38:AU40) -> 8244 | AV41: =SUM(AR41:AU41) -> 32376 | AW41: =SUM(AW38:AW40) -> 9061 | AX41: =SUM(AX38:AX40) -> 8180 | AY41: =SUM(AY38:AY40) -> 8432 | AZ41: =SUM(AZ38:AZ40) -> 8677 | BA41: =SUM(AW41:AZ41) -> 34350 | BB41: -- | BC41: -- | BD41: -- | BE41: -- | BF41: -- | BG41: -- | BH41: -- | BI41: -- | BJ41: -- | BK41: -- | BL41: -- | BM41: -- | BN41: -- | BO41: -- | BP41: -- | BQ41: -- | BR41: -- | BS41: -- | BT41: -- | BU41: -- | BV41: -- | BW41: -- | BX41: -- | BY41: -- | BZ41: -- | CA41: -- | CB41: -- | CC41: -- | CD41: -- | CE41: -- | CF41: -- | CG41: -- | CH41: -- | CI41: -- | CJ41: -- | CK41: -- | CL41: -- | CM41: -- | CN41: -- | CO41: -- | CP41: -- | CQ41: -- | CR41: -- | CS41: -- | CT41: -- | CU41: -- | CV41: -- | CW41: -- | CX41: -- | CY41: -- | CZ41: -- | DA41: -- | DB41: -- | DC41: -- | DD41: -- | DE41: -- | DF41: -- | DG41: -- | DH41: -- | DI41: --
B43: EBIT - OLD SEGMENTS
B44: North America | C44: -- | D44: -- | E44: -- | F44: -- | G44: -- | H44: -- | I44: -- | J44: -- | K44: -- | L44: -- | M44: -- | N44: -- | O44: -- | P44: 1429.3 | Q44: 1538.1 | R44: 443 | S44: 356 | T44: 419 | U44: 518 | V44: =SUM(R44:U44) -> 1736 | W44: 534 | X44: 418 | Y44: 496 | Z44: 559 | AA44: =SUM(W44:Z44) -> 2007 | AC44: 645 | AD44: 565 | AE44: 653 | AF44: 778 | AG44: =SUM(AC44:AF44) -> 2641 | AH44: 813 | AI44: 649 | AJ44: 729 | AK44: 888 | AL44: =SUM(AH44:AK44) -> 3079 | AM44: 970 | AN44: 785 | AO44: 830 | AP44: 1060 | AQ44: =SUM(AM44:AP44) -> 3645 | AR44: 1042 | AS44: 882 | AT44: 903 | AU44: 936 | AV44: =SUM(AR44:AU44) -> 3763 | AW44: 1004 | AX44: 912 | AY44: 980 | AZ44: 979 | BA44: =SUM(AW44:AZ44) -> 3875 | BB44: -- | BC44: -- | BD44: -- | BE44: -- | BF44: -- | BG44: -- | BH44: -- | BI44: -- | BJ44: -- | BK44: -- | BL44: -- | BM44: -- | BN44: -- | BO44: -- | BP44: -- | BQ44: -- | BR44: -- | BS44: -- | BT44: -- | BU44: -- | BV44: -- | BW44: -- | BX44: -- | BY44: -- | BZ44: -- | CA44: -- | CB44: -- | CC44: -- | CD44: -- | CE44: -- | CF44: -- | CG44: -- | CH44: -- | CI44: -- | CJ44: -- | CK44: -- | CL44: -- | CM44: -- | CN44: -- | CO44: -- | CP44: -- | CQ44: -- | CR44: -- | CS44: -- | CT44: -- | CU44: -- | CV44: -- | CW44: -- | CX44: -- | CY44: -- | CZ44: -- | DA44: -- | DB44: -- | DC44: -- | DD44: -- | DE44: -- | DF44: -- | DG44: -- | DH44: -- | DI44: --
B45: Western Europe | C45: -- | D45: -- | E45: -- | F45: -- | G45: -- | H45: -- | I45: -- | J45: -- | K45: -- | L45: -- | M45: -- | N45: -- | O45: -- | P45: 939.1 | Q45: 855.7 | R45: 283 | S45: 142 | T45: 163 | U45: 142 | V45: =SUM(R45:U45) -> 730 | W45: 223 | X45: 92 | Y45: 149 | Z45: 133 | AA45: =SUM(W45:Z45) -> 597 | AC45: 212 | AD45: 110 | AE45: 179 | AF45: 142 | AG45: =SUM(AC45:AF45) -> 643 | AH45: 265 | AI45: 123 | AJ45: 275 | AK45: 192 | AL45: =SUM(AH45:AK45) -> 855 | AM45: 404 | AN45: 261 | AO45: 333 | AP45: 277 | AQ45: =SUM(AM45:AP45) -> 1275 | AR45: 485 | AS45: 307 | AT45: 334 | AU45: 308 | AV45: =SUM(AR45:AU45) -> 1434 | AW45: 392 | AX45: 236 | AY45: 290 | AZ45: 285 | BA45: =SUM(AW45:AZ45) -> 1203 | BB45: -- | BC45: -- | BD45: -- | BE45: -- | BF45: -- | BG45: -- | BH45: -- | BI45: -- | BJ45: -- | BK45: -- | BL45: -- | BM45: -- | BN45: -- | BO45: -- | BP45: -- | BQ45: -- | BR45: -- | BS45: -- | BT45: -- | BU45: -- | BV45: -- | BW45: -- | BX45: -- | BY45: -- | BZ45: -- | CA45: -- | CB45: -- | CC45: -- | CD45: -- | CE45: -- | CF45: -- | CG45: -- | CH45: -- | CI45: -- | CJ45: -- | CK45: -- | CL45: -- | CM45: -- | CN45: -- | CO45: -- | CP45: -- | CQ45: -- | CR45: -- | CS45: -- | CT45: -- | CU45: -- | CV45: -- | CW45: -- | CX45: -- | CY45: -- | CZ45: -- | DA45: -- | DB45: -- | DC45: -- | DD45: -- | DE45: -- | DF45: -- | DG45: -- | DH45: -- | DI45: --
B46: Central & Eastern Europe | C46: -- | D46: -- | E46: -- | F46: -- | G46: -- | H46: -- | I46: -- | J46: -- | K46: -- | L46: -- | M46: -- | N46: -- | O46: -- | P46: 415.1 | Q46: 281.2 | R46: 70 | S46: 48 | T46: 59 | U46: 67 | V46: =SUM(R46:U46) -> 244 | W46: 70 | X46: 33 | Y46: 60 | Z46: 71 | AA46: =SUM(W46:Z46) -> 234 | AC46: 54 | AD46: 37 | AE46: 64 | AF46: 79 | AG46: =SUM(AC46:AF46) -> 234 | AH46: 81 | AI46: 48 | AJ46: 79 | AK46: 71 | AL46: =SUM(AH46:AK46) -> 279 | AM46: 68 | AN46: 57 | AO46: 52 | AP46: 71 | AQ46: =SUM(AM46:AP46) -> 248 | AR46: 98 | AS46: 76 | AT46: 69 | AU46: 46 | AV46: =SUM(AR46:AU46) -> 289 | AW46: 81 | AX46: 58 | AY46: 57 | AZ46: 48 | BA46: =SUM(AW46:AZ46) -> 244 | BB46: -- | BC46: -- | BD46: -- | BE46: -- | BF46: -- | BG46: -- | BH46: -- | BI46: -- | BJ46: -- | BK46: -- | BL46: -- | BM46: -- | BN46: -- | BO46: -- | BP46: -- | BQ46: -- | BR46: -- | BS46: -- | BT46: -- | BU46: -- | BV46: -- | BW46: -- | BX46: -- | BY46: -- | BZ46: -- | CA46: -- | CB46: -- | CC46: -- | CD46: -- | CE46: -- | CF46: -- | CG46: -- | CH46: -- | CI46: -- | CJ46: -- | CK46: -- | CL46: -- | CM46: -- | CN46: -- | CO46: -- | CP46: -- | CQ46: -- | CR46: -- | CS46: -- | CT46: -- | CU46: -- | CV46: -- | CW46: -- | CX46: -- | CY46: -- | CZ46: -- | DA46: -- | DB46: -- | DC46: -- | DD46: -- | DE46: -- | DF46: -- | DG46: -- | DH46: -- | DI46: --
B47: Greater China | C47: -- | D47: -- | E47: -- | F47: -- | G47: -- | H47: -- | I47: -- | J47: -- | K47: -- | L47: -- | M47: -- | N47: -- | O47: -- | P47: 575.2 | Q47: 637.1 | R47: 164 | S47: 174 | T47: 213 | U47: 226 | V47: =SUM(R47:U47) -> 777 | W47: 171 | X47: 220 | Y47: 273 | Z47: 247 | AA47: =SUM(W47:Z47) -> 911 | AC47: 165 | AD47: 187 | AE47: 218 | AF47: 243 | AG47: =SUM(AC47:AF47) -> 813 | AH47: 170 | AI47: 197 | AJ47: 234 | AK47: 215 | AL47: =SUM(AH47:AK47) -> 816 | AM47: 218 | AN47: 258 | AO47: 251 | AP47: 266 | AQ47: =SUM(AM47:AP47) -> 993 | AR47: 330 | AS47: 327 | AT47: 358 | AU47: 357 | AV47: =SUM(AR47:AU47) -> 1372 | AW47: 371 | AX47: 375 | AY47: 381 | AZ47: 380 | BA47: =SUM(AW47:AZ47) -> 1507 | BB47: -- | BC47: -- | BD47: -- | BE47: -- | BF47: -- | BG47: -- | BH47: -- | BI47: -- | BJ47: -- | BK47: -- | BL47: -- | BM47: -- | BN47: -- | BO47: -- | BP47: -- | BQ47: -- | BR47: -- | BS47: -- | BT47: -- | BU47: -- | BV47: -- | BW47: -- | BX47: -- | BY47: -- | BZ47: -- | CA47: -- | CB47: -- | CC47: -- | CD47: -- | CE47: -- | CF47: -- | CG47: -- | CH47: -- | CI47: -- | CJ47: -- | CK47: -- | CL47: -- | CM47: -- | CN47: -- | CO47: -- | CP47: -- | CQ47: -- | CR47: -- | CS47: -- | CT47: -- | CU47: -- | CV47: -- | CW47: -- | CX47: -- | CY47: -- | CZ47: -- | DA47: -- | DB47: -- | DC47: -- | DD47: -- | DE47: -- | DF47: -- | DG47: -- | DH47: -- | DI47: --
B48: Japan | C48: -- | D48: -- | E48: -- | F48: -- | G48: -- | H48: -- | I48: -- | J48: -- | K48: -- | L48: -- | M48: -- | N48: -- | O48: -- | P48: 205.4 | Q48: 180.3 | R48: 27 | S48: 36 | T48: 31 | U48: 20 | V48: =SUM(R48:U48) -> 114 | W48: 34 | X48: 35 | Y48: 24 | Z48: 43 | AA48: =SUM(W48:Z48) -> 136 | AC48: 23 | AD48: 45 | AE48: 24 | AF48: 47 | AG48: =SUM(AC48:AF48) -> 139 | AH48: 24 | AI48: 47 | AJ48: 21 | AK48: 39 | AL48: =SUM(AH48:AK48) -> 131 | AM48: 11 | AN48: 29 | AO48: 22 | AP48: 38 | AQ48: =SUM(AM48:AP48) -> 100 | AR48: 36 | AS48: 47 | AT48: 36 | AU48: 55 | AV48: =SUM(AR48:AU48) -> 174 | AW48: 50 | AX48: 48 | AY48: 49 | AZ48: 77 | BA48: =SUM(AW48:AZ48) -> 224 | BB48: -- | BC48: -- | BD48: -- | BE48: -- | BF48: -- | BG48: -- | BH48: -- | BI48: -- | BJ48: -- | BK48: -- | BL48: -- | BM48: -- | BN48: -- | BO48: -- | BP48: -- | BQ48: -- | BR48: -- | BS48: -- | BT48: -- | BU48: -- | BV48: -- | BW48: -- | BX48: -- | BY48: -- | BZ48: -- | CA48: -- | CB48: -- | CC48: -- | CD48: -- | CE48: -- | CF48: -- | CG48: -- | CH48: -- | CI48: -- | CJ48: -- | CK48: -- | CL48: -- | CM48: -- | CN48: -- | CO48: -- | CP48: -- | CQ48: -- | CR48: -- | CS48: -- | CT48: -- | CU48: -- | CV48: -- | CW48: -- | CX48: -- | CY48: -- | CZ48: -- | DA48: -- | DB48: -- | DC48: -- | DD48: -- | DE48: -- | DF48: -- | DG48: -- | DH48: -- | DI48: --
B49: Emerging Markets | C49: -- | D49: -- | E49: -- | F49: -- | G49: -- | H49: -- | I49: -- | J49: -- | K49: -- | L49: -- | M49: -- | N49: -- | O49: -- | P49: 342.6 | Q49: 492.6 | R49: 124 | S49: 194 | T49: 173 | U49: 197 | V49: =SUM(R49:U49) -> 688 | W49: 190 | X49: 247 | Y49: 215 | Z49: 201 | AA49: =SUM(W49:Z49) -> 853 | AC49: 221 | AD49: 298 | AE49: 216 | AF49: 253 | AG49: =SUM(AC49:AF49) -> 988 | AH49: 210 | AI49: 243 | AJ49: 228 | AK49: 271 | AL49: =SUM(AH49:AK49) -> 952 | AM49: 156 | AN49: 236 | AO49: 234 | AP49: 192 | AQ49: =SUM(AM49:AP49) -> 818 | AR49: 258 | AS49: 241 | AT49: 202 | AU49: 191 | AV49: =SUM(AR49:AU49) -> 892 | AW49: 171 | AX49: 237 | AY49: 193 | AZ49: 215 | BA49: =SUM(AW49:AZ49) -> 816 | BB49: -- | BC49: -- | BD49: -- | BE49: -- | BF49: -- | BG49: -- | BH49: -- | BI49: -- | BJ49: -- | BK49: -- | BL49: -- | BM49: -- | BN49: -- | BO49: -- | BP49: -- | BQ49: -- | BR49: -- | BS49: -- | BT49: -- | BU49: -- | BV49: -- | BW49: -- | BX49: -- | BY49: -- | BZ49: -- | CA49: -- | CB49: -- | CC49: -- | CD49: -- | CE49: -- | CF49: -- | CG49: -- | CH49: -- | CI49: -- | CJ49: -- | CK49: -- | CL49: -- | CM49: -- | CN49: -- | CO49: -- | CP49: -- | CQ49: -- | CR49: -- | CS49: -- | CT49: -- | CU49: -- | CV49: -- | CW49: -- | CX49: -- | CY49: -- | CZ49: -- | DA49: -- | DB49: -- | DC49: -- | DD49: -- | DE49: -- | DF49: -- | DG49: -- | DH49: -- | DI49: --
B50: Global Brands | C50: -- | D50: -- | E50: -- | F50: -- | G50: -- | H50: -- | I50: -- | J50: -- | K50: -- | L50: -- | M50: -- | N50: -- | O50: -- | P50: -811.5 | Q50: -866.8 | R50: -245 | S50: -221 | T50: -237 | U50: -268 | V50: =SUM(R50:U50) -> -971 | W50: -261 | X50: -273 | Y50: -292 | Z50: -351 | AA50: =SUM(W50:Z50) -> -1177 | AC50: -456 | AD50: -410 | AE50: -414 | AF50: -466 | AG50: =SUM(AC50:AF50) -> -1746 | AH50: -466 | AI50: -462 | AJ50: -528 | AK50: -549 | AL50: =SUM(AH50:AK50) -> -2005 | AM50: -533 | AN50: -554 | AO50: -552 | AP50: -627 | AQ50: =SUM(AM50:AP50) -> -2266 | AR50: -624 | AS50: -625 | AT50: -625 | AU50: -722 | AV50: =SUM(AR50:AU50) -> -2596 | AW50: -771 | AX50: -619 | AY50: -598 | AZ50: -689 | BA50: =SUM(AW50:AZ50) -> -2677 | BB50: -- | BC50: -- | BD50: -- | BE50: -- | BF50: -- | BG50: -- | BH50: -- | BI50: -- | BJ50: -- | BK50: -- | BL50: -- | BM50: -- | BN50: -- | BO50: -- | BP50: -- | BQ50: -- | BR50: -- | BS50: -- | BT50: -- | BU50: -- | BV50: -- | BW50: -- | BX50: -- | BY50: -- | BZ50: -- | CA50: -- | CB50: -- | CC50: -- | CD50: -- | CE50: -- | CF50: -- | CG50: -- | CH50: -- | CI50: -- | CJ50: -- | CK50: -- | CL50: -- | CM50: -- | CN50: -- | CO50: -- | CP50: -- | CQ50: -- | CR50: -- | CS50: -- | CT50: -- | CU50: -- | CV50: -- | CW50: -- | CX50: -- | CY50: -- | CZ50: -- | DA50: -- | DB50: -- | DC50: -- | DD50: -- | DE50: -- | DF50: -- | DG50: -- | DH50: -- | DI50: --
B51: Total Nike Brand | C51: -- | D51: -- | E51: -- | F51: -- | G51: -- | H51: -- | I51: -- | J51: -- | K51: -- | L51: -- | M51: -- | N51: -- | O51: -- | P51: =SUM(P44:P50) -> 3095.2 | Q51: =SUM(Q44:Q50) -> 3118.2 | R51: =SUM(R44:R50) -> 866 | S51: =SUM(S44:S50) -> 729 | T51: =SUM(T44:T50) -> 821 | U51: =SUM(U44:U50) -> 902 | V51: =SUM(R51:U51) -> 3318 | W51: =SUM(W44:W50) -> 961 | X51: =SUM(X44:X50) -> 772 | Y51: =SUM(Y44:Y50) -> 925 | Z51: =SUM(Z44:Z50) -> 903 | AA51: =SUM(W51:Z51) -> 3561 | AC51: =SUM(AC44:AC50) -> 864 | AD51: =SUM(AD44:AD50) -> 832 | AE51: =SUM(AE44:AE50) -> 940 | AF51: =SUM(AF44:AF50) -> 1076 | AG51: =SUM(AC51:AF51) -> 3712 | AH51: =SUM(AH44:AH50) -> 1097 | AI51: =SUM(AI44:AI50) -> 845 | AJ51: =SUM(AJ44:AJ50) -> 1038 | AK51: =SUM(AK44:AK50) -> 1127 | AL51: =SUM(AH51:AK51) -> 4107 | AM51: =SUM(AM44:AM50) -> 1294 | AN51: =SUM(AN44:AN50) -> 1072 | AO51: =SUM(AO44:AO50) -> 1170 | AP51: =SUM(AP44:AP50) -> 1277 | AQ51: =SUM(AM51:AP51) -> 4813 | AR51: =SUM(AR44:AR50) -> 1625 | AS51: =SUM(AS44:AS50) -> 1255 | AT51: =SUM(AT44:AT50) -> 1277 | AU51: =SUM(AU44:AU50) -> 1171 | AV51: =SUM(AR51:AU51) -> 5328 | AW51: =SUM(AW44:AW50) -> 1298 | AX51: =SUM(AX44:AX50) -> 1247 | AY51: =SUM(AY44:AY50) -> 1352 | AZ51: =SUM(AZ44:AZ50) -> 1295 | BA51: =SUM(AW51:AZ51) -> 5192 | BB51: -- | BC51: -- | BD51: -- | BE51: -- | BF51: -- | BG51: -- | BH51: -- | BI51: -- | BJ51: -- | BK51: -- | BL51: -- | BM51: -- | BN51: -- | BO51: -- | BP51: -- | BQ51: -- | BR51: -- | BS51: -- | BT51: -- | BU51: -- | BV51: -- | BW51: -- | BX51: -- | BY51: -- | BZ51: -- | CA51: -- | CB51: -- | CC51: -- | CD51: -- | CE51: -- | CF51: -- | CG51: -- | CH51: -- | CI51: -- | CJ51: -- | CK51: -- | CL51: -- | CM51: -- | CN51: -- | CO51: -- | CP51: -- | CQ51: -- | CR51: -- | CS51: -- | CT51: -- | CU51: -- | CV51: -- | CW51: -- | CX51: -- | CY51: -- | CZ51: -- | DA51: -- | DB51: -- | DC51: -- | DD51: -- | DE51: -- | DF51: -- | DG51: -- | DH51: -- | DI51: --
B52: Other Businesses | C52: -- | D52: -- | E52: -- | F52: -- | G52: -- | H52: -- | I52: -- | J52: -- | K52: -- | L52: -- | M52: -- | N52: -- | O52: -- | P52: =-192.6+199.3+202 -> 208.7 | Q52: 299.4 | R52: 109 | S52: 59 | T52: 85 | U52: 82 | V52: =SUM(R52:U52) -> 335 | W52: 86 | X52: 57 | Y52: 87 | Z52: 111 | AA52: =SUM(W52:Z52) -> 341 | AC52: 124 | AD52: 91 | AE52: 121 | AF52: 89 | AG52: =SUM(AC52:AF52) -> 425 | AH52: 169 | AI52: 100 | AJ52: 133 | AK52: 94 | AL52: =SUM(AH52:AK52) -> 496 | AM52: 186 | AN52: 88 | AO52: 163 | AP52: 80 | AQ52: =SUM(AM52:AP52) -> 517 | AR52: 147 | AS52: 85 | AT52: 127 | AU52: 128 | AV52: =SUM(AR52:AU52) -> 487 | AW52: 153 | AX52: 78 | AY52: 109 | AZ52: 137 | BA52: =SUM(AW52:AZ52) -> 477 | BB52: -- | BC52: -- | BD52: -- | BE52: -- | BF52: -- | BG52: -- | BH52: -- | BI52: -- | BJ52: -- | BK52: -- | BL52: -- | BM52: -- | BN52: -- | BO52: -- | BP52: -- | BQ52: -- | BR52: -- | BS52: -- | BT52: -- | BU52: -- | BV52: -- | BW52: -- | BX52: -- | BY52: -- | BZ52: -- | CA52: -- | CB52: -- | CC52: -- | CD52: -- | CE52: -- | CF52: -- | CG52: -- | CH52: -- | CI52: -- | CJ52: -- | CK52: -- | CL52: -- | CM52: -- | CN52: -- | CO52: -- | CP52: -- | CQ52: -- | CR52: -- | CS52: -- | CT52: -- | CU52: -- | CV52: -- | CW52: -- | CX52: -- | CY52: -- | CZ52: -- | DA52: -- | DB52: -- | DC52: -- | DD52: -- | DE52: -- | DF52: -- | DG52: -- | DH52: -- | DI52: --
B53: Corporate | C53: -- | D53: -- | E53: -- | F53: -- | G53: -- | H53: -- | I53: -- | J53: -- | K53: -- | L53: -- | M53: -- | N53: -- | O53: -- | P53: -760.6 | Q53: -894.4 | R53: -221 | S53: -178 | T53: -199 | U53: -207 | V53: =SUM(R53:U53) -> -805 | W53: -195 | X53: -208 | Y53: -242 | Z53: -271 | AA53: =SUM(W53:Z53) -> -916 | AC53: =+AC76-AC51-AC52 -> -196 | AD53: =+AD76-AD51-AD52 -> -214 | AE53: =+AE76-AE51-AE52 -> -207 | AF53: =+AF76-AF51-AF52 -> -267 | AG53: =SUM(AC53:AF53) -> -884 | AH53: -218 | AI53: -220 | AJ53: -282 | AK53: -301 | AL53: =SUM(AH53:AK53) -> -1021 | AM53: -242 | AN53: -273 | AO53: -281 | AP53: -301 | AQ53: =SUM(AM53:AP53) -> -1097 | AR53: -323 | AS53: -365 | AT53: -264 | AU53: -221 | AV53: =SUM(AR53:AU53) -> -1173 | AW53: -163 | AX53: -196 | AY53: -119 | AZ53: -246 | BA53: =SUM(AW53:AZ53) -> -724 | BB53: -- | BC53: -- | BD53: -- | BE53: -- | BF53: -- | BG53: -- | BH53: -- | BI53: -- | BJ53: -- | BK53: -- | BL53: -- | BM53: -- | BN53: -- | BO53: -- | BP53: -- | BQ53: -- | BR53: -- | BS53: -- | BT53: -- | BU53: -- | BV53: -- | BW53: -- | BX53: -- | BY53: -- | BZ53: -- | CA53: -- | CB53: -- | CC53: -- | CD53: -- | CE53: -- | CF53: -- | CG53: -- | CH53: -- | CI53: -- | CJ53: -- | CK53: -- | CL53: -- | CM53: -- | CN53: -- | CO53: -- | CP53: -- | CQ53: -- | CR53: -- | CS53: -- | CT53: -- | CU53: -- | CV53: -- | CW53: -- | CX53: -- | CY53: -- | CZ53: -- | DA53: -- | DB53: -- | DC53: -- | DD53: -- | DE53: -- | DF53: -- | DG53: -- | DH53: -- | DI53: --
B54: EBIT | C54: -- | D54: -- | E54: -- | F54: -- | G54: -- | H54: -- | I54: -- | J54: -- | K54: -- | L54: -- | M54: -- | N54: -- | O54: -- | P54: =SUM(P51:P53) -> 2543.3 | Q54: =SUM(Q51:Q53) -> 2523.2 | R54: =SUM(R51:R53) -> 754 | S54: =SUM(S51:S53) -> 610 | T54: =SUM(T51:T53) -> 707 | U54: =SUM(U51:U53) -> 777 | V54: =SUM(R54:U54) -> 2848 | W54: =SUM(W51:W53) -> 852 | X54: =SUM(X51:X53) -> 621 | Y54: =SUM(Y51:Y53) -> 770 | Z54: =SUM(Z51:Z53) -> 743 | AA54: =SUM(W54:Z54) -> 2986 | AC54: =SUM(AC51:AC53) -> 792 | AD54: =SUM(AD51:AD53) -> 709 | AE54: =SUM(AE51:AE53) -> 854 | AF54: =SUM(AF51:AF53) -> 898 | AG54: =SUM(AC54:AF54) -> 3253 | AH54: =SUM(AH51:AH53) -> 1048 | AI54: =SUM(AI51:AI53) -> 725 | AJ54: =SUM(AJ51:AJ53) -> 889 | AK54: =SUM(AK51:AK53) -> 920 | AL54: =SUM(AH54:AK54) -> 3582 | AM54: =SUM(AM51:AM53) -> 1238 | AN54: =SUM(AN51:AN53) -> 887 | AO54: =SUM(AO51:AO53) -> 1052 | AP54: =SUM(AP51:AP53) -> 1056 | AQ54: =SUM(AM54:AP54) -> 4233 | AR54: =SUM(AR51:AR53) -> 1449 | AS54: =SUM(AS51:AS53) -> 975 | AT54: =SUM(AT51:AT53) -> 1140 | AU54: =SUM(AU51:AU53) -> 1078 | AV54: =SUM(AR54:AU54) -> 4642 | AW54: =SUM(AW51:AW53) -> 1288 | AX54: =SUM(AX51:AX53) -> 1129 | AY54: =SUM(AY51:AY53) -> 1342 | AZ54: =SUM(AZ51:AZ53) -> 1186 | BA54: =SUM(AW54:AZ54) -> 4945 | BB54: -- | BC54: -- | BD54: -- | BE54: -- | BF54: -- | BG54: -- | BH54: -- | BI54: -- | BJ54: -- | BK54: -- | BL54: -- | BM54: -- | BN54: -- | BO54: -- | BP54: -- | BQ54: -- | BR54: -- | BS54: -- | BT54: -- | BU54: -- | BV54: -- | BW54: -- | BX54: -- | BY54: -- | BZ54: -- | CA54: -- | CB54: -- | CC54: -- | CD54: -- | CE54: -- | CF54: -- | CG54: -- | CH54: -- | CI54: -- | CJ54: -- | CK54: -- | CL54: -- | CM54: -- | CN54: -- | CO54: -- | CP54: -- | CQ54: -- | CR54: -- | CS54: -- | CT54: -- | CU54: -- | CV54: -- | CW54: -- | CX54: -- | CY54: -- | CZ54: -- | DA54: -- | DB54: -- | DC54: -- | DD54: -- | DE54: -- | DF54: -- | DG54: -- | DH54: -- | DI54: --
B56: CONSOLIDATED INCOME STATEMENT
B57: Net Revenues | C57: 6470.625 | D57: 9186.539 | E57: 9553.1 | F57: 8776.9 | G57: 8995.1 | H57: 9488.8 | I57: 9893 | J57: 10697 | K57: 12253.1 | L57: 13739.7 | M57: 14954.9 | N57: 16325.9 | O57: 18627 | P57: 19176.1 | Q57: 19014 | R57: 5175 | S57: 4842 | T57: 5079 | U57: 5766 | V57: 20862 | W57: 6081 | X57: 5731 | Y57: 5846 | Z57: 6470 | AA57: 24128 | AB57: 23331 | AC57: =12429-AD57 -> 6474 | AD57: 5955 | AE57: =+AE41 -> 6187 | AF57: =+AF41 -> 6697 | AG57: 25313 | AH57: =+AH17 -> 6971 | AI57: 6431 | AJ57: =+AJ41 -> 6972 | AK57: 7425 | AL57: 27799 | AM57: =+AM17 -> 7982 | AN57: 7380 | AO57: 7460 | AP57: 7779 | AQ57: 30601 | AR57: =+AR17 -> 8414 | AS57: 7686 | AT57: 8032 | AU57: 8244 | AV57: 32376 | AW57: 9061 | AX57: 8180 | AY57: 8432 | AZ57: 8677 | BA57: 34350 | BB57: 9070 | BC57: 8554 | BD57: 8984 | BE57: 9789 | BF57: =BF17 -> 36397 | BG57: 9948 | BH57: 9374 | BI57: 9611 | BJ57: 10184 | BK57: =BK17 -> 39117 | BL57: 10660 | BM57: 10326 | BN57: 10104 | BO57: 6313 | BP57: =BP17 -> 37403 | BQ57: 10594 | BR57: 11243 | BS57: 10357 | BT57: 12344 | BU57: =BU17 -> 44538 | BV57: 12248 | BW57: 11357 | BX57: 10871 | BY57: 12234 | BZ57: =BZ17 -> 46710 | CA57: 12687 | CB57: 13315 | CC57: 12390 | CD57: 12825 | CE57: =CE17 -> 51217 | CF57: 12939 | CG57: 13388 | CH57: 12429 | CI57: 12606 | CJ57: =CJ17 -> 51362 | CK57: 11589 | CL57: 12354 | CM57: 11269 | CN57: 11097 | CO57: =CO17 -> 46309 | CP57: 11720 | CQ57: 12427 | CR57: 11279 | CS57: 10972 | CT57: =CT17 -> 46398 | CU57: 11213 | CV57: =+CV17 -> 10878.098 | CW57: =+CW17 -> 10305.983 | CX57: =+CX17 -> 9881.3434 | CY57: =CY17 -> 42278.425 | CZ57: =+CZ17 -> 10328.233 | DA57: =+DA17 -> 10360.009 | DB57: =+DB17 -> 10025.647 | DC57: =+DC17 -> 9627.892 | DD57: =DD17 -> 40341.781 | DE57: =+DE17 -> 10334.054 | DF57: =+DF17 -> 10379.712 | DG57: =+DG17 -> 10094.693 | DH57: =+DH17 -> 9696.6733 | DI57: =DI17 -> 40505.133
B58: % chg Y/Y | C58: -- | D58: -- | E58: =+E57/D57-1 -> 0.03990197 | F58: =+F57/E57-1 -> -0.081251112 | G58: =+G57/F57-1 -> 0.024860714 | H58: =+H57/G57-1 -> 0.054885438 | I58: =+I57/H57-1 -> 0.042597589 | J58: =+J57/I57-1 -> 0.081269585 | K58: =+K57/J57-1 -> 0.14547069 | L58: =+L57/K57-1 -> 0.1213244 | ... Q58: =+Q57/P57-1 -> -0.0084532308 | R58: -- | S58: -- | T58: -- | U58: -- | V58: =+V57/Q57-1 -> 0.097191543 | W58: =+W57/R57-1 -> 0.17507246 | X58: =+X57/S57-1 -> 0.18360182 | Y58: =+Y57/T57-1 -> 0.15101398 | Z58: =+Z57/U57-1 -> 0.12209504 | AA58: =+AA57/V57-1 -> 0.15655258 | AC58: =+AC57/W57-1 -> 0.064627528 | AD58: =+AD57/X57-1 -> 0.039085674 | AE58: =+AE57/Y57-1 -> 0.058330482 | AF58: =+AF57/Z57-1 -> 0.035085008 | AG58: =+AG57/AA57-1 -> 0.049113064 | AH58: =+AH57/AC57-1 -> 0.076768613 | AI58: =+AI57/AD57-1 -> 0.07993283 | AJ58: =+AJ57/AE57-1 -> 0.12687894 | AK58: =+AK57/AF57-1 -> 0.10870539 | AL58: =+AL57/AG57-1 -> 0.098210406 | AM58: =+AM57/AH57-1 -> 0.14502941 | AN58: =+AN57/AI57-1 -> 0.14756647 | AO58: =+AO57/AJ57-1 -> 0.069994263 | ... DI58: =+DI57/DD57-1 -> 0.0040492115
B59: COGS | C59: -3906.746 | D59: -5502.993 | E59: -6065.4 | F59: -5493.5 | G59: -5403.8 | H59: -5784.9 | I59: -6004.7 | J59: -6313.6 | K59: -7001.4 | L59: -7624.3 | M59: -8367.9 | N59: -9165.4 | O59: -10239.6 | P59: -10571.7 | Q59: -10213.6 | R59: -2741 | S59: -2649 | T59: -2752 | U59: -3212 | V59: -11354 | W59: -3388 | X59: -3281 | Y59: -3285 | Z59: -3703 | AA59: -13657 | AB59: =+AB60-AB57 -> -13183 | AC59: -3646 | AD59: -3425 | AE59: -3451 | AF59: -3757 | AG59: -14279 | AH59: -3839 | AI59: -3605 | AJ59: -3869 | AK59: -4040 | AL59: -15353 | AM59: -4261 | AN59: -4053 | AO59: -4034 | AP59: -4186 | AQ59: -16534 | AR59: -4419 | AS59: -4185 | AT59: -4343 | AU59: -4458 | AV59: -17405 | AW59: -4938 | AX59: -4564 | AY59: -4682 | AZ59: -4854 | BA59: -19038 | BB59: -5108 | BC59: -4876 | BD59: -5046 | BE59: -5411 | BF59: =SUM(BB59:BE59) -> -20441 | BG59: -5551 | BH59: -5269 | BI59: -5272 | BJ59: -5551 | BK59: =SUM(BG59:BJ59) -> -21643 | BL59: -5789 | BM59: -5782 | BN59: -5631 | BO59: -3960 | BP59: =SUM(BL59:BO59) -> -21162 | BQ59: -5853 | BR59: -6396 | BS59: -5638 | BT59: -6689 | BU59: =SUM(BQ59:BT59) -> -24576 | BV59: -6552 | BW59: -6144 | BX59: -5804 | BY59: -6731 | BZ59: =SUM(BV59:BY59) -> -25231 | CA59: -7072 | CB59: -7604 | CC59: -7019 | CD59: -7230 | CE59: =SUM(CA59:CD59) -> -28925 | CF59: -7219 | CG59: -7417 | CH59: =-6867+(403-340) -> -6804 | CI59: =-6972+(64-(403-340)) -> -6971 | CJ59: =SUM(CF59:CI59) -> -28411 | CK59: -6332 | CL59: -6965 | CM59: -6594 | CN59: -6628 | CO59: =SUM(CK59:CN59) -> -26519 | CP59: -6777 | CQ59: -7382 | CR59: -6749 | CS59: -5579 | CT59: =SUM(CP59:CS59) -> -26487 | CU59: -6415 | CV59: =+CV60-CV57 -> -6445.5899 | CW59: =+CW60-CW57 -> -6218.3072 | CX59: =+CX60-CX57 -> -5913.7481 | CY59: =SUM(CU59:CX59) -> -24992.645 | CZ59: =+CZ60-CZ57 -> -5960.4625 | DA59: =+DA60-DA57 -> -6164.5073 | DB59: =+DB60-DB57 -> -6049.1611 | DC59: =+DC60-DC57 -> -5762.0635 | DD59: =SUM(CZ59:DC59) -> -23936.194 | DE59: =+DE60-DE57 -> -5927.653 | DF59: =+DF60-DF57 -> -6139.9022 | DG59: =+DG60-DG57 -> -6055.4901 | DH59: =+DH60-DH57 -> -5769.289 | DI59: =SUM(DE59:DH59) -> -23892.334
B60: Gross Profit | C60: =SUM(C57:C59) -> 2563.879 | D60: =SUM(D57,D59) -> 3683.546 | E60: =SUM(E57,E59) -> 3487.7 | F60: =SUM(F57,F59) -> 3283.4 | G60: =SUM(G57,G59) -> 3591.3 | H60: =SUM(H57,H59) -> 3703.9 | I60: =SUM(I57,I59) -> 3888.3 | J60: =SUM(J57,J59) -> 4383.4 | K60: =SUM(K57,K59) -> 5251.7 | ... Q60: =SUM(Q57,Q59) -> 8800.4 | R60: =+R57+R59 -> 2434 | S60: =+S57+S59 -> 2193 | T60: =+T57+T59 -> 2327 | U60: =+U57+U59 -> 2554 | V60: =V57+V59 -> 9508 | W60: =+W57+W59 -> 2693 | X60: =+X57+X59 -> 2450 | Y60: =+Y57+Y59 -> 2561 | Z60: =+Z57+Z59 -> 2767 | AA60: =AA57+AA59 -> 10471 | AB60: 10148 | AC60: =+AC57+AC59 -> 2828 | AD60: =+AD57+AD59 -> 2530 | AE60: =+AE57+AE59 -> 2736 | AF60: =+AF57+AF59 -> 2940 | AG60: =AG57+AG59 -> 11034 | AH60: =+AH57+AH59 -> 3132 | AI60: =+AI57+AI59 -> 2826 | AJ60: =+AJ57+AJ59 -> 3103 | AK60: =+AK57+AK59 -> 3385 | AL60: =+AL57+AL59 -> 12446 | AM60: =+AM57+AM59 -> 3721 | AN60: =+AN57+AN59 -> 3327 | AO60: =+AO57+AO59 -> 3426 | ... BE60: =+BE57+BE59 -> 4378 | BF60: =BF57+BF59 -> 15956 | BG60: =+BG57+BG59 -> 4397 | BH60: =+BH57+BH59 -> 4105 | BI60: =+BI57+BI59 -> 4339 | BJ60: =+BJ57+BJ59 -> 4633 | BK60: =BK57+BK59 -> 17474 | BL60: =+BL57+BL59 -> 4871 | BM60: =+BM57+BM59 -> 4544 | BN60: =+BN57+BN59 -> 4473 | BO60: =+BO57+BO59 -> 2353 | BP60: =BP57+BP59 -> 16241 | BQ60: =+BQ57+BQ59 -> 4741 | BR60: =+BR57+BR59 -> 4847 | BS60: =+BS57+BS59 -> 4719 | BT60: =+BT57+BT59 -> 5655 | BU60: =BU57+BU59 -> 19962 | BV60: =+BV57+BV59 -> 5696 | BW60: =+BW57+BW59 -> 5213 | BX60: =+BX57+BX59 -> 5067 | BY60: =+BY57+BY59 -> 5503 | BZ60: =BZ57+BZ59 -> 21479 | CA60: =+CA57+CA59 -> 5615 | CB60: =+CB57+CB59 -> 5711 | CC60: =+CC57+CC59 -> 5371 | CD60: =+CD57+CD59 -> 5595 | CE60: =CE57+CE59 -> 22292 | CF60: =+CF57+CF59 -> 5720 | CG60: =+CG57+CG59 -> 5971 | CH60: =+CH57+CH59 -> 5625 | CI60: =+CI57+CI59 -> 5635 | CJ60: =CJ57+CJ59 -> 22951 | CK60: =+CK57+CK59 -> 5257 | CL60: =+CL57+CL59 -> 5389 | CM60: =+CM57+CM59 -> 4675 | CN60: =+CN57+CN59 -> 4469 | CO60: =CO57+CO59 -> 19790 | CP60: =+CP57+CP59 -> 4943 | CQ60: =+CQ57+CQ59 -> 5045 | CR60: =+CR57+CR59 -> 4530 | CS60: =+CS57+CS59 -> 5393 | CT60: =CT57+CT59 -> 19911 | CU60: =+CU57+CU59 -> 4798 | CV60: =+CV57*CV61 -> 4432.508 | CW60: =+CW57*CW61 -> 4087.676 | CX60: =+CX57*CX61 -> 3967.5953 | CY60: =CY57+CY59 -> 17285.779 | CZ60: =+CZ57*CZ61 -> 4367.7703 | DA60: =+DA57*DA61 -> 4195.5019 | DB60: =+DB57*DB61 -> 3976.4859 | DC60: =+DC57*DC61 -> 3865.8285 | DD60: =DD57+DD59 -> 16405.587 | DE60: =+DE57*DE61 -> 4406.4014 | DF60: =+DF57*DF61 -> 4239.8101 | DG60: =+DG57*DG61 -> 4039.2033 | DH60: =+DH57*DH61 -> 3927.3842 | DI60: =DI57+DI59 -> 16612.799
B61: % of revenues | C61: =C60/C57 -> 0.39623359 | D61: =D60/D57 -> 0.40097212 | E61: =E60/E57 -> 0.36508568 | F61: =F60/F57 -> 0.37409564 | G61: =G60/G57 -> 0.3992507 | H61: =H60/H57 -> 0.39034441 | I61: =I60/I57 -> 0.39303548 | J61: =J60/J57 -> 0.40977844 | ... AA61: =AA60/AA57 -> 0.43397712 | AC61: =AC60/AC57 -> 0.43682422 | AD61: =AD60/AD57 -> 0.42485306 | AE61: =AE60/AE57 -> 0.44221755 | AF61: =AF60/AF57 -> 0.43900254 | AG61: =AG60/AG57 -> 0.4359025 | AH61: =AH60/AH57 -> 0.44928992 | AI61: =AI60/AI57 -> 0.43943399 | AJ61: =AJ60/AJ57 -> 0.44506598 | ... CU61: =CU60/CU57 -> 0.42789619 | CV61: =CQ61+CV62/10000 -> 0.40747087 | CW61: =CR61+CW62/10000 -> 0.39663135 | CX61: =CS61+CX62/10000 -> 0.40152388 | CY61: =CY60/CY57 -> 0.40885581 | CZ61: =CU61+CZ62/10000 -> 0.42289619 | DA61: =CV61+DA62/10000 -> 0.40497087 | DB61: =CW61+DB62/10000 -> 0.39663135 | DC61: =CX61+DC62/10000 -> 0.40152388 | DD61: =DD60/DD57 -> 0.40666491 | DE61: =CZ61+DE62/10000 -> 0.42639619 | DF61: =DA61+DF62/10000 -> 0.40847087 | DG61: =DB61+DG62/10000 -> 0.40013135 | DH61: =DC61+DH62/10000 -> 0.40502388 | DI61: =DI60/DI57 -> 0.41014058
B62: % of revenues chg (bp) | C62: -- | D62: =+(D61-C61)*100*100 -> 47.385239 | E62: =+(E61-D61)*100*100 -> -358.86439 | F62: =+(F61-E61)*100*100 -> 90.099584 | G62: =+(G61-F61)*100*100 -> 251.55066 | H62: =+(H61-G61)*100*100 -> -89.062971 | I62: =+(I61-H61)*100*100 -> 26.910736 | J62: =+(J61-I61)*100*100 -> 167.42963 | K62: =+(K61-J61)*100*100 -> 188.23299 | ... Q62: =+(Q61-P61)*100*100 -> 141.33532 | R62: -- | S62: -- | T62: -- | U62: -- | V62: =+(V61-Q61)*100*100 -> -70.810304 | W62: =+(W61-R61)*100*100 -> -274.83371 | X62: =+(X61-S61)*100*100 -> -254.12456 | Y62: =+(Y61-T61)*100*100 -> -200.83738 | Z62: =+(Z61-U61)*100*100 -> -152.75229 | AA62: =+(AA61-V61)*100*100 -> -217.79757 | AC62: =+(AC61-W61)*100*100 -> -60.305737 | AD62: =+(AD61-X61)*100*100 -> -26.464991 | AE62: =+(AE61-Y61)*100*100 -> 41.402351 | AF62: =+(AF61-Z61)*100*100 -> 113.36387 | AG62: =+(AG61-AA61)*100*100 -> 19.253787 | AH62: =+(AH61-AC61)*100*100 -> 124.65695 | AI62: =+(AI61-AD61)*100*100 -> 145.80927 | AJ62: =+(AJ61-AE61)*100*100 -> 28.484253 | AK62: =+(AK61-AF61)*100*100 -> 168.89717 | AL62: =+(AL61-AG61)*100*100 -> 118.11446 | AM62: =+(AM61-AH61)*100*100 -> 168.83976 | AN62: =+(AN61-AI61)*100*100 -> 113.79017 | AO62: =+(AO61-AJ61)*100*100 -> 141.83352 | ... CU62: =+(CU61-CP61)*100*100 -> 61.385127 | CV62: 15 | CW62: -50 | CX62: -900 | CY62: =+(CY61-CT61)*100*100 -> -202.79069 | CZ62: -50 | DA62: -25 | DB62: 0 | DC62: 0 | DD62: =+(DD61-CY61)*100*100 -> -21.908981 | DE62: 35 | DF62: 35 | DG62: 35 | DH62: 35 | DI62: =+(DI61-DD61)*100*100 -> 34.756753
B63: Demand Creation Expense | C63: -- | D63: -978.3 | E63: -1129.1 | F63: -978.6 | G63: -978.2 | H63: -998.2 | I63: -1027.9 | J63: -1166.8 | K63: -1377.9 | L63: -1600.7 | M63: -1740.2 | N63: -1912.4 | O63: -2308.3 | P63: -2351.4 | Q63: -2356 | R63: -679 | S63: -574 | T63: -578 | U63: -617 | V63: -2448 | W63: -692 | X63: -644 | Y63: -615 | Z63: -760 | AA63: -2711 | AB63: -- | AC63: =-1484+613 -> -871 | AD63: -613 | AE63: -619 | AF63: -642 | AG63: -2745 | AH63: -731 | AI63: -691 | AJ63: -733 | AK63: -876 | AL63: -3031 | AM63: -897 | AN63: -766 | AO63: -731 | AP63: -819 | AQ63: -3213 | AR63: -832 | AS63: -769 | AT63: -804 | AU63: -873 | AV63: -3278 | AW63: -1041 | AX63: -762 | AY63: -749 | AZ63: -789 | BA63: -3341 | BB63: -855 | BC63: -877 | BD63: -862 | BE63: -983 | BF63: =SUM(BB63:BE63) -> -3577 | BG63: -964 | BH63: -910 | BI63: -865 | BJ63: -1014 | BK63: =SUM(BG63:BJ63) -> -3753 | BL63: -1018 | BM63: -881 | BN63: -870 | BO63: -823 | BP63: =SUM(BL63:BO63) -> -3592 | BQ63: -677 | BR63: -729 | BS63: -711 | BT63: -997 | BU63: =SUM(BQ63:BT63) -> -3114 | BV63: -918 | BW63: -1017 | BX63: -854 | BY63: -1061 | BZ63: =SUM(BV63:BY63) -> -3850 | CA63: -943 | CB63: -1102 | CC63: -923 | CD63: -1092 | CE63: =SUM(CA63:CD63) -> -4060 | CF63: -1069 | CG63: -1114 | CH63: -1011 | CI63: =-1091 -> -1091 | CJ63: =SUM(CF63:CI63) -> -4285 | CK63: -1226 | CL63: -1122 | CM63: -1088 | CN63: -1253 | CO63: =SUM(CK63:CN63) -> -4689 | CP63: -1188 | CQ63: -1273 | CR63: -1090 | CS63: -1203 | CT63: =SUM(CP63:CS63) -> -4754 | CU63: -1252 | CV63: =+CV57*-CV65 -> -1168.7237 | CW63: =+CW57*-CW65 -> -995.96788 | CX63: =+CX57*-CX65 -> -1083.4174 | CY63: =SUM(CU63:CX63) -> -4500.109 | CZ63: =+CZ57*-CZ65 -> -1049.928 | DA63: =+DA57*-DA65 -> -1115.1331 | DB63: =+DB57*-DB65 -> -968.87626 | DC63: =+DC57*-DC65 -> -1055.6283 | DD63: =SUM(CZ63:DC63) -> -4189.5657 | DE63: =+DE57*-DE65 -> -1050.5198 | DF63: =+DF57*-DF65 -> -1117.254 | DG63: =+DG57*-DG65 -> -975.54889 | DH63: =+DH57*-DH65 -> -1063.1697 | DI63: =SUM(DE63:DH63) -> -4206.4924
B64: % chg Y/Y | C64: -- | D64: -- | E64: =+E63/D63-1 -> 0.15414495 | F64: =+F63/E63-1 -> -0.133292 | G64: =+G63/F63-1 -> -0.00040874719 | H64: =+H63/G63-1 -> 0.020445717 | I64: =+I63/H63-1 -> 0.029753556 | J64: =+J63/I63-1 -> 0.13512988 | K64: =+K63/J63-1 -> 0.18092218 | L64: =+L63/K63-1 -> 0.16169533 | ... Q64: =+Q63/P63-1 -> 0.0019562814 | R64: -- | S64: -- | T64: -- | U64: -- | V64: =+V63/Q63-1 -> 0.039049236 | W64: =+W63/R63-1 -> 0.019145803 | X64: =+X63/S63-1 -> 0.12195122 | Y64: =+Y63/T63-1 -> 0.064013841 | Z64: =+Z63/U63-1 -> 0.23176661 | AA64: =+AA63/V63-1 -> 0.10743464 | AC64: =+AC63/W63-1 -> 0.25867052 | AD64: =+AD63/X63-1 -> -0.048136646 | AE64: =+AE63/Y63-1 -> 0.006504065 | AF64: =+AF63/Z63-1 -> -0.15526316 | AG64: =+AG63/AA63-1 -> 0.012541498 | AH64: =+AH63/AC63-1 -> -0.16073479 | AI64: =+AI63/AD63-1 -> 0.12724307 | AJ64: =+AJ63/AE63-1 -> 0.18416801 | AK64: =+AK63/AF63-1 -> 0.36448598 | AL64: =+AL63/AG63-1 -> 0.10418944 | AM64: =+AM63/AH63-1 -> 0.22708618 | AN64: =+AN63/AI63-1 -> 0.10853835 | AO64: =+AO63/AJ63-1 -> -0.002728513 | ... BG64: =+BG63/BB63-1 -> 0.12748538 | BH64: =BH63/BC63-1 -> 0.037628278 | BI64: =BI63/BD63-1 -> 0.0034802784 | BJ64: =+BJ63/BE63-1 -> 0.031536114 | BK64: =+BK63/BF63-1 -> 0.049203243 | BL64: =BL63/BG63-1 -> 0.056016598 | BM64: =BM63/BH63-1 -> -0.031868132 | BN64: =BN63/BI63-1 -> 0.0057803468 | BO64: =BO63/BJ63-1 -> -0.18836292 | BP64: =+BP63/BK63-1 -> -0.042899014 | BQ64: =BQ63/BL63-1 -> -0.33497053 | BR64: =BR63/BM63-1 -> -0.17253121 | BS64: =BS63/BN63-1 -> -0.18275862 | BT64: =BT63/BO63-1 -> 0.21142163 | BU64: =+BU63/BP63-1 -> -0.1330735 | BV64: =BV63/BQ63-1 -> 0.35598227 | BW64: =BW63/BR63-1 -> 0.39506173 | BX64: =BX63/BS63-1 -> 0.20112518 | BY64: =BY63/BT63-1 -> 0.064192578 | BZ64: =+BZ63/BU63-1 -> 0.23635196 | CA64: =CA63/BV63-1 -> 0.027233115 | CB64: =CB63/BW63-1 -> 0.083579154 | CC64: =CC63/BX63-1 -> 0.080796253 | CD64: =CD63/BY63-1 -> 0.029217719 | CE64: =+CE63/BZ63-1 -> 0.054545455 | CF64: =CF63/CA63-1 -> 0.13361612 | CG64: =CG63/CB63-1 -> 0.010889292 | CH64: =CH63/CC63-1 -> 0.095341278 | CI64: =CI63/CD63-1 -> -0.00091575092 | CJ64: =+CJ63/CE63-1 -> 0.055418719 | CK64: =CK63/CF63-1 -> 0.14686623 | CL64: =CL63/CG63-1 -> 0.0071813285 | CM64: =CM63/CH63-1 -> 0.076162216 | CN64: =CN63/CI63-1 -> 0.14848763 | CO64: =+CO63/CJ63-1 -> 0.09428238 | CP64: =CP63/CK63-1 -> -0.030995106 | CQ64: =CQ63/CL63-1 -> 0.13458111 | CR64: =CR63/CM63-1 -> 0.0018382353 | CS64: =CS63/CN63-1 -> -0.03990423 | CT64: =+CT63/CO63-1 -> 0.013862231 | CU64: =CU63/CP63-1 -> 0.053872054 | CV64: =CV63/CQ63-1 -> -0.081913834 | CW64: =CW63/CR63-1 -> -0.086268002 | CX64: =CX63/CS63-1 -> -0.09940363 | CY64: =+CY63/CT63-1 -> -0.053405763 | CZ64: =CZ63/CU63-1 -> -0.16139936 | DA64: =DA63/CV63-1 -> -0.045853903 | DB64: =DB63/CW63-1 -> -0.0272013 | DC64: =DC63/CX63-1 -> -0.025649483 | DD64: =+DD63/CY63-1 -> -0.069007941 | DE64: =DE63/CZ63-1 -> 0.00056365691 | DF64: =DF63/DA63-1 -> 0.001901849 | DG64: =DG63/DB63-1 -> 0.0068869773 | DH64: =DH63/DC63-1 -> 0.0071439572 | DI64: =+DI63/DD63-1 -> 0.0040401816
B65: % of revenues | C65: -- | D65: =-D63/D57 -> 0.10649277 | E65: =-E63/E57 -> 0.118192 | F65: =-F63/F57 -> 0.11149723 | G65: =-G63/G57 -> 0.1087481 | H65: =-H63/H57 -> 0.10519771 | I65: =-I63/I57 -> 0.10390175 | J65: =-J63/J57 -> 0.10907731 | K65: =-K63/K57 -> 0.11245318 | ... AA65: =-AA63/AA57 -> 0.11235908 | AC65: =-AC63/AC57 -> 0.13453815 | AD65: =-AD63/AD57 -> 0.10293871 | AE65: =-AE63/AE57 -> 0.10004849 | AF65: =-AF63/AF57 -> 0.09586382 | AG65: =-AG63/AG57 -> 0.1084423 | AH65: =-AH63/AH57 -> 0.104863 | AI65: =-AI63/AI57 -> 0.1074483 | AJ65: =-AJ63/AJ57 -> 0.10513483 | ... CU65: =-CU63/CU57 -> 0.11165611 | CV65: =CQ65+CV66/10000 -> 0.10743824 | CW65: =CR65+CW66/10000 -> 0.096639773 | CX65: =CS65+CX66/10000 -> 0.10964273 | CY65: =-CY63/CY57 -> 0.10643985 | CZ65: =CU65+CZ66/10000 -> 0.10165611 | DA65: =CV65+DA66/10000 -> 0.10763824 | DB65: =CW65+DB66/10000 -> 0.096639773 | DC65: =CX65+DC66/10000 -> 0.10964273 | DD65: =-DD63/DD57 -> 0.10385178 | DE65: =CZ65+DE66/10000 -> 0.10165611 | DF65: =DA65+DF66/10000 -> 0.10763824 | DG65: =DB65+DG66/10000 -> 0.096639773 | DH65: =DC65+DH66/10000 -> 0.10964273 | DI65: =-DI63/DI57 -> 0.10385085
B66: margin change (bp) | C66: -- | D66: -- | E66: =+(E65-D65)*100*100 -> 116.99229 | F66: =+(F65-E65)*100*100 -> -66.947748 | G66: =+(G65-F65)*100*100 -> -27.491295 | H66: =+(H65-G65)*100*100 -> -35.503894 | I66: =+(I65-H65)*100*100 -> -12.959581 | J66: =+(J65-I65)*100*100 -> 51.755627 | K66: =+(K65-J65)*100*100 -> 33.758637 | L66: =+(L65-K65)*100*100 -> 40.486408 | ... Q66: =+(Q65-P65)*100*100 -> 12.873108 | R66: -- | S66: -- | T66: -- | U66: -- | V66: =+(V65-Q65)*100*100 -> -65.661622 | W66: =+(W65-R65)*100*100 -> -174.10657 | X66: =+(X65-S65)*100*100 -> -61.747414 | Y66: =+(Y65-T65)*100*100 -> -86.017927 | Z66: =+(Z65-U65)*100*100 -> 104.58634 | AA66: =+(AA65-V65)*100*100 -> -49.834518 | AC66: =+(AC65-W65)*100*100 -> 207.4108 | AD66: =+(AD65-X65)*100*100 -> -94.326069 | AE66: =+(AE65-Y65)*100*100 -> -51.516481 | AF66: =+(AF65-Z65)*100*100 -> -216.01404 | AG66: =+(AG65-AA65)*100*100 -> -39.167825 | AH66: =+(AH65-AC65)*100*100 -> -296.75149 | AI66: =+(AI65-AD65)*100*100 -> 45.095903 | AJ66: =+(AJ65-AE65)*100*100 -> 50.863362 | AK66: =+(AK65-AF65)*100*100 -> 221.15978 | AL66: =+(AL65-AG65)*100*100 -> 5.9039664 | AM66: =+(AM65-AH65)*100*100 -> 75.148463 | AN66: =+(AN65-AI65)*100*100 -> -36.542594 | AO66: =+(AO65-AJ65)*100*100 -> -71.455489 | ... CU66: =+(CU65-CP65)*100*100 -> 102.90926 | CV66: 50 | CW66: 0 | CX66: 0 | CY66: =+(CY65-CT65)*100*100 -> 39.785332 | CZ66: -100 | DA66: 2 | DB66: 0 | DC66: 0 | DD66: =+(DD65-CY65)*100*100 -> -25.880668 | DE66: 0 | DF66: 0 | DG66: 0 | DH66: 0 | DI66: =+(DI65-DD65)*100*100 -> -0.0093399174
B67: Operating Overhead Expense | C67: -- | D67: -1325.404 | E67: -1494.8 | F67: -1448 | G67: -1628.2 | H67: -1691.5 | I67: -1792.5 | J67: -1984 | K67: -2324.1 | L67: -2621 | M67: -2737.6 | N67: -3116.3 | O67: -3645.4 | P67: -3798.2 | Q67: -3970.4 | R67: -994 | S67: -1037 | T67: -1059 | U67: -1155 | V67: -4245 | W67: -1131 | X67: -1176 | Y67: -1187 | Z67: -1226 | AA67: -4720 | AB67: -- | AC67: =-2411+1223-5 -> -1193 | AD67: =-1223-2 -> -1225 | AE67: =-1244-2 -> -1246 | AF67: -1387 | AG67: -5051 | AH67: =-1325-2 -> -1327 | AI67: =-1397-3 -> -1400 | AJ67: =-1433-3 -> -1436 | AK67: -1572 | AL67: -5735 | AM67: -1583 | AN67: -1672 | AO67: -1648 | AP67: -1776 | AQ67: -6679 | AR67: -1745 | AS67: -1791 | AT67: -1762 | AU67: -1893 | AV67: -7191 | AW67: -1856 | AX67: -1743 | AY67: -1747 | AZ67: -1876 | BA67: -7222 | BB67: -2001 | BC67: -1891 | BD67: -1905 | BE67: -2137 | BF67: =SUM(BB67:BE67) -> -7934 | BG67: -2099 | BH67: -2232 | BI67: -2226 | BJ67: -2392 | BK67: =SUM(BG67:BJ67) -> -8949 | BL67: -2310 | BM67: -2443 | BN67: -2413 | BO67: -2368 | BP67: =SUM(BL67:BO67) -> -9534 | BQ67: -2298 | BR67: -2538 | BS67: -2330 | BT67: -2745 | BU67: =SUM(BQ67:BT67) -> -9911 | BV67: -2654 | BW67: -2742 | BX67: -2584 | BY67: -2974 | BZ67: =SUM(BV67:BY67) -> -10954 | CA67: -2977 | CB67: -3022 | CC67: -3036 | CD67: -3282 | CE67: =SUM(CA67:CD67) -> -12317 | CF67: -3047 | CG67: -3032 | CH67: =-3215+340 -> -2875 | CI67: =-2997+(379-340) -> -2958 | CJ67: =SUM(CF67:CI67) -> -11912 | CK67: -2822 | CL67: -2883 | CM67: -2799 | CN67: -2895 | CO67: =SUM(CK67:CN67) -> -11399 | CP67: -2828 | CQ67: -2766 | CR67: -2887 | CS67: -2879 | CT67: =SUM(CP67:CS67) -> -11360 | CU67: -2658 | CV67: =+CV57*-CV69 -> -2568.0999 | CW67: =+CW57*-CW69 -> -2560.6494 | CX67: =+CX57*-CX69 -> -2627.4017 | CY67: =SUM(CU67:CX67) -> -10414.151 | CZ67: =+CZ57*-CZ69 -> -2474.0898 | DA67: =+DA57*-DA69 -> -2471.6896 | DB67: =+DB57*-DB69 -> -2490.9964 | DC67: =+DC57*-DC69 -> -2560.0102 | DD67: =SUM(CZ67:DC67) -> -9996.786 | DE67: =+DE57*-DE69 -> -2454.8162 | DF67: =+DF57*-DF69 -> -2455.631 | DG67: =+DG57*-DG69 -> -2487.9625 | DH67: =+DH57*-DH69 -> -2558.9054 | DI67: =SUM(DE67:DH67) -> -9957.3151
B68: % chg Y/Y | C68: -- | D68: -- | E68: =+E67/D67-1 -> 0.12780707 | F68: =+F67/E67-1 -> -0.031308536 | G68: =+G67/F67-1 -> 0.12444751 | H68: =+H67/G67-1 -> 0.038877288 | I68: =+I67/H67-1 -> 0.059710316 | J68: =+J67/I67-1 -> 0.10683403 | K68: =+K67/J67-1 -> 0.17142137 | L68: =+L67/K67-1 -> 0.12774838 | ... Q68: =+Q67/P67-1 -> 0.045337265 | R68: -- | S68: -- | T68: -- | U68: -- | V68: =+V67/Q67-1 -> 0.069161797 | W68: =+W67/R67-1 -> 0.13782696 | X68: =+X67/S67-1 -> 0.1340405 | Y68: =+Y67/T67-1 -> 0.12086874 | Z68: =+Z67/U67-1 -> 0.061471861 | AA68: =+AA67/V67-1 -> 0.11189635 | AC68: =+AC67/W67-1 -> 0.054818744 | AD68: =+AD67/X67-1 -> 0.041666667 | AE68: =+AE67/Y67-1 -> 0.049705139 | AF68: =+AF67/Z67-1 -> 0.13132137 | AG68: =+AG67/AA67-1 -> 0.070127119 | AH68: =+AH67/AC67-1 -> 0.11232188 | AI68: =+AI67/AD67-1 -> 0.14285714 | AJ68: =+AJ67/AE67-1 -> 0.15248796 | AK68: =+AK67/AF67-1 -> 0.1333814 | AL68: =+AL67/AG67-1 -> 0.13541873 | AM68: =+AM67/AH67-1 -> 0.19291635 | AN68: =+AN67/AI67-1 -> 0.19428571 | AO68: =+AO67/AJ67-1 -> 0.14763231 | ... DI68: =+DI67/DD67-1 -> -0.00394836
B69: % of revenues | C69: -- | D69: =-D67/D57 -> 0.14427675 | E69: =-E67/E57 -> 0.15647277 | F69: =-F67/F57 -> 0.16497852 | G69: =-G67/G57 -> 0.18100966 | H69: =-H67/H57 -> 0.17826279 | I69: =-I67/I57 -> 0.18118872 | J69: =-J67/J57 -> 0.18547256 | K69: =-K67/K57 -> 0.18967445 | ... AA69: =-AA67/AA57 -> 0.19562334 | AC69: =-AC67/AC57 -> 0.18427556 | AD69: =-AD67/AD57 -> 0.20570949 | AE69: =-AE67/AE57 -> 0.20139001 | AF69: =-AF67/AF57 -> 0.20710766 | AG69: =-AG67/AG57 -> 0.19954174 | AH69: =-AH67/AH57 -> 0.19036006 | AI69: =-AI67/AI57 -> 0.21769554 | AJ69: =-AJ67/AJ57 -> 0.20596672 | ... CU69: =-CU67/CU57 -> 0.23704629 | CV69: =CQ69+CV70/10000 -> 0.23607987 | CW69: =CR69+CW70/10000 -> 0.24846241 | CX69: =CS69+CX70/10000 -> 0.26589519 | CY69: =-CY67/CY57 -> 0.24632306 | CZ69: =CU69+CZ70/10000 -> 0.23954629 | DA69: =CV69+DA70/10000 -> 0.23857987 | DB69: =CW69+DB70/10000 -> 0.24846241 | DC69: =CX69+DC70/10000 -> 0.26589519 | DD69: =-DD67/DD57 -> 0.2478023 | DE69: =CZ69+DE70/10000 -> 0.23754629 | DF69: =DA69+DF70/10000 -> 0.23657987 | DG69: =DB69+DG70/10000 -> 0.24646241 | DH69: =DC69+DH70/10000 -> 0.26389519 | DI69: =-DI67/DI57 -> 0.24582847
B70: margin change (bp) | C70: -- | D70: -- | E70: =+(E69-D69)*100*100 -> 121.96017 | F70: =+(F69-E69)*100*100 -> 85.057552 | G70: =+(G69-F69)*100*100 -> 160.31138 | H70: =+(H69-G69)*100*100 -> -27.468668 | I70: =+(I69-H69)*100*100 -> 29.259253 | J70: =+(J69-I69)*100*100 -> 42.838431 | K70: =+(K69-J69)*100*100 -> 42.018873 | L70: =+(L69-K69)*100*100 -> 10.866295 | ... Q70: =+(Q69-P69)*100*100 -> 107.45086 | R70: -- | S70: -- | T70: -- | U70: -- | V70: =+(V69-Q69)*100*100 -> -53.345462 | W70: =+(W69-R69)*100*100 -> -60.881482 | X70: =+(X69-S69)*100*100 -> -89.679087 | Y70: =+(Y69-T69)*100*100 -> -54.607944 | Z70: =+(Z69-U69)*100*100 -> -108.22221 | AA70: =+(AA69-V69)*100*100 -> -78.566693 | AC70: =+(AC69-W69)*100*100 -> -17.135827 | AD70: =+(AD69-X69)*100*100 -> 5.0969721 | AE70: =+(AE69-Y69)*100*100 -> -16.548057 | AF70: =+(AF69-Z69)*100*100 -> 176.17707 | AG70: =+(AG69-AA69)*100*100 -> 39.183953 | AH70: =+(AH69-AC69)*100*100 -> 60.844993 | AI70: =+(AI69-AD69)*100*100 -> 119.86049 | AJ70: =+(AJ69-AE69)*100*100 -> 45.767127 | AK70: =+(AK69-AF69)*100*100 -> 46.095116 | AL70: =+(AL69-AG69)*100*100 -> 67.606475 | AM70: =+(AM69-AH69)*100*100 -> 79.611596 | AN70: =+(AN69-AI69)*100*100 -> 88.627283 | AO70: =+(AO69-AJ69)*100*100 -> 149.44804 | ... CU70: =+(CU69-CP69)*100*100 -> -42.506428 | CV70: 135 | CW70: -75 | CX70: 35 | CY70: =+(CY69-CT69)*100*100 -> 14.84922 | CZ70: 25 | DA70: 25 | DB70: 0 | DC70: 0 | DD70: =+(DD69-CY69)*100*100 -> 14.792346 | DE70: -20 | DF70: -20 | DG70: -20 | DH70: -20 | DI70: =+(DI69-DD69)*100*100 -> -19.738242
B71: Total SG&A | C71: -1588.612 | D71: =SUM(D63+D67) -> -2303.704 | E71: =SUM(E63+E67) -> -2623.9 | F71: =SUM(F63+F67) -> -2426.6 | G71: =SUM(G63+G67) -> -2606.4 | H71: =SUM(H63+H67) -> -2689.7 | I71: =SUM(I63+I67) -> -2820.4 | J71: =SUM(J63+J67) -> -3150.8 | K71: =SUM(K63+K67) -> -3702 | ... AA71: =SUM(AA63+AA67) -> -7431 | AC71: =SUM(AC63+AC67) -> -2064 | AD71: =SUM(AD63+AD67) -> -1838 | AE71: =SUM(AE63+AE67) -> -1865 | AF71: =SUM(AF63+AF67) -> -2029 | AG71: =SUM(AG63+AG67) -> -7796 | AH71: =SUM(AH63+AH67) -> -2058 | AI71: =SUM(AI63+AI67) -> -2091 | AJ71: =SUM(AJ63+AJ67) -> -2169 | ... DI71: =SUM(DI63+DI67) -> -14163.807
B72: % chg Y/Y | C72: -- | D72: =+D71/C71-1 -> 0.45013635 | E72: =+E71/D71-1 -> 0.13899181 | F72: =+F71/E71-1 -> -0.075193414 | G72: =+G71/F71-1 -> 0.074095442 | H72: =+H71/G71-1 -> 0.031959791 | I72: =+I71/H71-1 -> 0.04859278 | J72: =+J71/I71-1 -> 0.1171465 | K72: =+K71/J71-1 -> 0.1749397 | ... Q72: =+Q71/P71-1 -> 0.028749837 | R72: -- | S72: -- | T72: -- | U72: -- | V72: =+V71/Q71-1 -> 0.057947648 | W72: =+W71/R71-1 -> 0.089659295 | X72: =+X71/S71-1 -> 0.12973309 | Y72: =+Y71/T71-1 -> 0.10079414 | Z72: =+Z71/U71-1 -> 0.12076749 | AA72: =+AA71/V71-1 -> 0.11026446 | AC72: =+AC71/W71-1 -> 0.13219967 | AD72: =+AD71/X71-1 -> 0.0098901099 | AE72: =+AE71/Y71-1 -> 0.034961154 | AF72: =+AF71/Z71-1 -> 0.021651561 | AG72: =+AG71/AA71-1 -> 0.049118557 | AH72: =+AH71/AC71-1 -> -0.0029069767 | AI72: =+AI71/AD71-1 -> 0.13764962 | AJ72: =+AJ71/AE71-1 -> 0.16300268 | AK72: =+AK71/AF71-1 -> 0.20650567 | AL72: =+AL71/AG71-1 -> 0.12442278 | AM72: =+AM71/AH71-1 -> 0.20505345 | AN72: =+AN71/AI71-1 -> 0.16594931 | AO72: =+AO71/AJ71-1 -> 0.096818811 | ... DI72: =+DI71/DD71-1 -> -0.0015891544
B73: % of revenues | C73: =+-C71/C57 -> 0.24551137 | D73: =+-D71/D57 -> 0.25076952 | E73: =+-E71/E57 -> 0.27466477 | F73: =+-F71/F57 -> 0.27647575 | G73: =+-G71/G57 -> 0.28975776 | H73: =+-H71/H57 -> 0.2834605 | I73: =+-I71/I57 -> 0.28509047 | J73: =+-J71/J57 -> 0.29454987 | ... AA73: =+-AA71/AA57 -> 0.30798243 | AC73: =+-AC71/AC57 -> 0.31881372 | AD73: =+-AD71/AD57 -> 0.30864819 | AE73: =+-AE71/AE57 -> 0.3014385 | AF73: =+-AF71/AF57 -> 0.30297148 | AG73: =+-AG71/AG57 -> 0.30798404 | AH73: =+-AH71/AH57 -> 0.29522307 | AI73: =+-AI71/AI57 -> 0.32514383 | AJ73: =+-AJ71/AJ57 -> 0.31110155 | ... DI73: =+-DI71/DI57 -> 0.34967932
B74: % of revenues chg (bp) | C74: -- | D74: =+(D73-C73)*100*100 -> 52.58154 | E74: =+(E73-D73)*100*100 -> 238.95246 | F74: =+(F73-E73)*100*100 -> 18.109803 | G74: =+(G73-F73)*100*100 -> 132.82008 | H74: =+(H73-G73)*100*100 -> -62.972562 | I74: =+(I73-H73)*100*100 -> 16.299672 | J74: =+(J73-I73)*100*100 -> 94.594058 | K74: =+(K73-J73)*100*100 -> 75.77751 | ... Q74: =+(Q73-P73)*100*100 -> 120.32397 | R74: -- | S74: -- | T74: -- | U74: -- | V74: =+(V73-Q73)*100*100 -> -119.00708 | W74: =+(W73-R73)*100*100 -> -234.98805 | X74: =+(X73-S73)*100*100 -> -151.4265 | Y74: =+(Y73-T73)*100*100 -> -140.62587 | Z74: =+(Z73-U73)*100*100 -> -3.6358743 | AA74: =+(AA73-V73)*100*100 -> -128.40121 | AC74: =+(AC73-W73)*100*100 -> 190.27497 | AD74: =+(AD73-X73)*100*100 -> -89.229097 | AE74: =+(AE73-Y73)*100*100 -> -68.064537 | AF74: =+(AF73-Z73)*100*100 -> -39.83698 | AG74: =+(AG73-AA73)*100*100 -> 0.016127657 | AH74: =+(AH73-AC73)*100*100 -> -235.90649 | AI74: =+(AI73-AD73)*100*100 -> 164.9564 | AJ74: =+(AJ73-AE73)*100*100 -> 96.63049 | AK74: =+(AK73-AF73)*100*100 -> 267.2549 | AL74: =+(AL73-AG73)*100*100 -> 73.510442 | AM74: =+(AM73-AH73)*100*100 -> 154.76006 | AN74: =+(AN73-AI73)*100*100 -> 52.08469 | AO74: =+(AO73-AJ73)*100*100 -> 77.992552 | ... DI74: =+(DI73-DD73)*100*100 -> -19.747582
B75: Other Income | C75: -- | D75: -- | E75: -- | F75: -- | G75: -- | H75: -- | I75: -- | J75: -- | K75: -- | L75: -- | M75: -- | N75: -- | O75: -- | P75: 88.5 | Q75: 49.2 | R75: -7 | S75: 28 | T75: 17 | U75: -5 | V75: 33 | W75: -18 | X75: -9 | Y75: 11 | Z75: -38 | AA75: -54 | AB75: -- | AC75: 28 | AD75: 17 | AE75: -17 | AF75: -13 | AG75: 15 | AH75: -28 | AI75: -13 | AJ75: -45 | AK75: -17 | AL75: -103 | AM75: -3 | AN75: -2 | AO75: 5 | AP75: 58 | AQ75: 58 | AR75: 31 | AS75: 34 | AT75: 17 | AU75: 58 | AV75: 140 | AW75: 62 | AX75: 18 | AY75: 88 | AZ75: 28 | BA75: 196 | BB75: -18 | BC75: -18 | BD75: 1 | BE75: -31 | BF75: =SUM(BB75:BE75) -> -66 | BG75: -53 | BH75: 48 | BI75: 55 | BJ75: 28 | BK75: =SUM(BG75:BJ75) -> 78 | BL75: 33 | BM75: 41 | BN75: =-297+400 -> 103 | BO75: 84 | BP75: =SUM(BL75:BO75) -> 261 | BQ75: 14 | BR75: -54 | BS75: 22 | BT75: 4 | BU75: =SUM(BQ75:BT75) -> -14 | BV75: 39 | BW75: 102 | BX75: 94 | BY75: -54 | BZ75: =SUM(BV75:BY75) -> 181 | CA75: 146 | CB75: 79 | CC75: 58 | CD75: -3 | CE75: =SUM(CA75:CD75) -> 280 | CF75: 10 | CG75: 75 | CH75: =16 -> 16 | CI75: 127 | CJ75: =SUM(CF75:CI75) -> 228 | CK75: 55 | CL75: 8 | CM75: 38 | CN75: -25 | CO75: =SUM(CK75:CN75) -> 76 | CP75: -23 | CQ75: -16 | CR75: 82 | CS75: 10 | CT75: =SUM(CP75:CS75) -> 53 | CU75: 19 | CV75: 15 | CW75: 15 | CX75: 15 | CY75: =SUM(CU75:CX75) -> 64 | CZ75: 10 | DA75: 10 | DB75: 10 | DC75: 10 | DD75: =SUM(CZ75:DC75) -> 40 | DE75: 10 | DF75: 10 | DG75: 10 | DH75: 10 | DI75: =SUM(DE75:DH75) -> 40
B76: EBIT | C76: =C60+C71 -> 975.267 | D76: =D60+D71 -> 1379.842 | E76: =E60+E71 -> 863.8 | F76: =F60+F71 -> 856.8 | G76: =G60+G71 -> 984.9 | H76: =H60+H71 -> 1014.2 | I76: =I60+I71 -> 1067.9 | J76: =J60+J71 -> 1232.6 | ... O76: =O60+O71 -> 2433.7 | P76: =+P60+P71+P75 -> 2543.3 | Q76: =+Q60+Q71+Q75 -> 2523.2 | R76: =+R60+R71+R75 -> 754 | S76: =+S60+S71+S75 -> 610 | T76: =+T60+T71+T75 -> 707 | U76: =+U60+U71+U75 -> 777 | V76: =+V60+V71+V75 -> 2848 | W76: =+W60+W71+W75 -> 852 | ... AA76: =+AA60+AA71+AA75 -> 2986 | AB76: -- | AC76: =+AC60+AC71+AC75 -> 792 | AD76: =+AD60+AD71+AD75 -> 709 | AE76: =+AE60+AE71+AE75 -> 854 | AF76: =+AF60+AF71+AF75 -> 898 | AG76: =+AG60+AG71+AG75 -> 3253 | AH76: =+AH60+AH71+AH75 -> 1046 | AI76: =+AI60+AI71+AI75 -> 722 | AJ76: =+AJ60+AJ71+AJ75 -> 889 | ... BE76: =+BE60+BE71+BE75 -> 1227 | BF76: =SUM(BB76:BE76) -> 4379 | BG76: =+BG60+BG71+BG75 -> 1281 | BH76: =+BH60+BH71+BH75 -> 1011 | BI76: =+BI60+BI71+BI75 -> 1303 | BJ76: =+BJ60+BJ71+BJ75 -> 1255 | BK76: =SUM(BG76:BJ76) -> 4850 | BL76: =+BL60+BL71+BL75 -> 1576 | BM76: =+BM60+BM71+BM75 -> 1261 | BN76: =+BN60+BN71+BN75 -> 1293 | BO76: =+BO60+BO71+BO75 -> -754 | BP76: =SUM(BL76:BO76) -> 3376 | BQ76: =+BQ60+BQ71+BQ75 -> 1780 | BR76: =+BR60+BR71+BR75 -> 1526 | BS76: =+BS60+BS71+BS75 -> 1700 | BT76: =+BT60+BT71+BT75 -> 1917 | BU76: =SUM(BQ76:BT76) -> 6923 | BV76: =+BV60+BV71+BV75 -> 2163 | BW76: =+BW60+BW71+BW75 -> 1556 | BX76: =+BX60+BX71+BX75 -> 1723 | BY76: =+BY60+BY71+BY75 -> 1414 | BZ76: =SUM(BV76:BY76) -> 6856 | CA76: =+CA60+CA71+CA75 -> 1841 | CB76: =+CB60+CB71+CB75 -> 1666 | CC76: =+CC60+CC71+CC75 -> 1470 | CD76: =+CD60+CD71+CD75 -> 1218 | CE76: =SUM(CA76:CD76) -> 6195 | CF76: =+CF60+CF71+CF75 -> 1614 | CG76: =+CG60+CG71+CG75 -> 1900 | CH76: =+CH60+CH71+CH75 -> 1755 | CI76: =+CI60+CI71+CI75 -> 1713 | CJ76: =SUM(CF76:CI76) -> 6982 | CK76: =+CK60+CK71+CK75 -> 1264 | CL76: =+CL60+CL71+CL75 -> 1392 | CM76: =+CM60+CM71+CM75 -> 826 | CN76: =+CN60+CN71+CN75 -> 296 | CO76: =SUM(CK76:CN76) -> 3778 | CP76: =+CP60+CP71+CP75 -> 904 | CQ76: =+CQ60+CQ71+CQ75 -> 990 | CR76: =+CR60+CR71+CR75 -> 635 | CS76: =+CS60+CS71+CS75 -> 1321 | CT76: =SUM(CP76:CS76) -> 3850 | CU76: =+CU60+CU71+CU75 -> 907 | CV76: =+CV60+CV71+CV75 -> 710.68443 | CW76: =+CW60+CW71+CW75 -> 546.05875 | CX76: =+CX60+CX71+CX75 -> 271.77624 | CY76: =SUM(CU76:CX76) -> 2435.5194 | CZ76: =+CZ60+CZ71+CZ75 -> 853.75251 | DA76: =+DA60+DA71+DA75 -> 618.67918 | DB76: =+DB60+DB71+DB75 -> 526.61326 | DC76: =+DC60+DC71+DC75 -> 260.19006 | DD76: =SUM(CZ76:DC76) -> 2259.235 | DE76: =+DE60+DE71+DE75 -> 911.0654 | DF76: =+DF60+DF71+DF75 -> 676.92521 | DG76: =+DG60+DG71+DG75 -> 585.69198 | DH76: =+DH60+DH71+DH75 -> 315.30911 | DI76: =SUM(DE76:DH76) -> 2488.9917
B77: % chg Y/Y | C77: -- | D77: =+D76/C76-1 -> 0.41483512 | E77: =+E76/D76-1 -> -0.3739863 | F77: =+F76/E76-1 -> -0.0081037277 | G77: =+G76/F76-1 -> 0.1495098 | H77: =+H76/G76-1 -> 0.029749213 | I77: =+I76/H76-1 -> 0.052948136 | J77: =+J76/I76-1 -> 0.15422792 | K77: =+K76/J76-1 -> 0.25726107 | ... Q77: =+Q76/P76-1 -> -0.007903118 | R77: -- | S77: -- | T77: -- | U77: -- | V77: =+V76/Q76-1 -> 0.12872543 | W77: =+W76/R76-1 -> 0.12997347 | X77: =+X76/S76-1 -> 0.018032787 | Y77: =+Y76/T76-1 -> 0.089108911 | Z77: =+Z76/U76-1 -> -0.043758044 | AA77: =+AA76/V76-1 -> 0.048455056 | AC77: =+AC76/W76-1 -> -0.070422535 | AD77: =+AD76/X76-1 -> 0.14170692 | AE77: =+AE76/Y76-1 -> 0.10909091 | AF77: =+AF76/Z76-1 -> 0.20861373 | AG77: =+AG76/AA76-1 -> 0.089417281 | AH77: =+AH76/AC76-1 -> 0.32070707 | AI77: =+AI76/AD76-1 -> 0.018335684 | AJ77: =+AJ76/AE76-1 -> 0.040983607 | AK77: =+AK76/AF76-1 -> 0.024498886 | AL77: =+AL76/AG76-1 -> 0.099600369 | AM77: =+AM76/AH76-1 -> 0.18355641 | AN77: =+AN76/AI76-1 -> 0.22853186 | AO77: =+AO76/AJ76-1 -> 0.18335208 | ... DI77: =+DI76/DD76-1 -> 0.10169667
B78: % margin | C78: =+C76/C57 -> 0.15072223 | D78: =+D76/D57 -> 0.1502026 | E78: =+E76/E57 -> 0.09042091 | F78: =+F76/F57 -> 0.097619889 | G78: =+G76/G57 -> 0.10949295 | H78: =+H76/H57 -> 0.10688391 | I78: =+I76/I57 -> 0.10794501 | J78: =+J76/J57 -> 0.11522857 | ... AA78: =+AA76/AA57 -> 0.12375663 | AB78: -- | AC78: =+AC76/AC57 -> 0.1223355 | AD78: =+AD76/AD57 -> 0.11905961 | AE78: =+AE76/AE57 -> 0.13803136 | AF78: =+AF76/AF57 -> 0.13408989 | AG78: =+AG76/AG57 -> 0.12851104 | AH78: =+AH76/AH57 -> 0.15005021 | AI78: =+AI76/AI57 -> 0.1122687 | AJ78: =+AJ76/AJ57 -> 0.12751004 | ... DI78: =+DI76/DI57 -> 0.061448796
B79: % of revenues chg (bp) | C79: -- | D79: =+(D78-C78)*100*100 -> -5.196301 | E79: =+(E78-D78)*100*100 -> -597.81685 | F79: =+(F78-E78)*100*100 -> 71.989781 | G79: =+(G78-F78)*100*100 -> 118.73058 | H79: =+(H78-G78)*100*100 -> -26.090409 | I79: =+(I78-H78)*100*100 -> 10.611064 | J79: =+(J78-I78)*100*100 -> 72.835571 | K79: =+(K78-J78)*100*100 -> 112.45548 | ... Q79: =+(Q78-P78)*100*100 -> 0.73582729 | R79: -- | S79: -- | T79: -- | U79: -- | V79: =+(V78-Q78)*100*100 -> 38.139344 | W79: =+(W78-R78)*100*100 -> -55.919483 | X79: =+(X78-S78)*100*100 -> -176.22947 | Y79: =+(Y78-T78)*100*100 -> -74.866376 | Z79: =+(Z78-U78)*100*100 -> -199.17751 | AA79: =+(AA78-V78)*100*100 -> -127.59522 | AC79: =+(AC78-W78)*100*100 -> -177.73039 | AD79: =+(AD78-X78)*100*100 -> 107.01561 | AE79: =+(AE78-Y78)*100*100 -> 63.173636 | AF79: =+(AF78-Z78)*100*100 -> 192.52178 | AG79: =+(AG78-AA78)*100*100 -> 47.544105 | AH79: =+(AH78-AC78)*100*100 -> 277.14712 | AI79: =+(AI78-AD78)*100*100 -> -67.909153 | AJ79: =+(AJ78-AE78)*100*100 -> -105.21316 | AK79: =+(AK78-AF78)*100*100 -> -101.84167 | AL79: =+(AL78-AG78)*100*100 -> 1.6265154 | AM79: =+(AM78-AH78)*100*100 -> 50.487647 | AN79: =+(AN78-AI78)*100*100 -> 79.210034 | AO79: =+(AO78-AJ78)*100*100 -> 135.08727 | ... DI79: =+(DI78-DD78)*100*100 -> 54.464348
C80: ---- | D80: ---- | E80: ---- | F80: ---- | G80: ---- | H80: ---- | I80: ---- | J80: ---- | K80: ---- | L80: ---- | M80: ---- | N80: ---- | O80: ---- | P80: ---- | Q80: ---- | R80: ---- | S80: ---- | T80: ---- | U80: ---- | V80: ---- | W80: ---- | X80: ---- | Y80: ---- | Z80: ---- | AA80: ---- | AB80: ---- | AC80: ---- | AD80: ---- | AE80: ---- | AF80: ---- | AG80: ---- | AH80: ---- | AI80: ---- | AJ80: ---- | AK80: ---- | AL80: ---- | AM80: ---- | AN80: ---- | AO80: ---- | AP80: ---- | AQ80: ---- | AR80: ---- | AS80: ---- | AT80: ---- | AU80: ---- | AV80: ---- | AW80: ---- | AX80: ---- | AY80: ---- | AZ80: ---- | BA80: ---- | BB80: ---- | BC80: ---- | BD80: ---- | BE80: ---- | BF80: ---- | BG80: ---- | BH80: ---- | BI80: ---- | BJ80: ---- | BK80: ---- | BL80: ---- | BM80: ---- | BN80: ---- | BO80: ---- | BP80: ---- | BQ80: ---- | BR80: ---- | BS80: ---- | BT80: ---- | BU80: ---- | BV80: ---- | BW80: ---- | BX80: ---- | BY80: ---- | BZ80: ---- | CA80: ---- | CB80: ---- | CC80: ---- | CD80: ---- | CE80: ---- | CF80: ---- | CG80: ---- | CH80: ---- | CI80: ---- | CJ80: ---- | CK80: ---- | CL80: ---- | CM80: ---- | CN80: ---- | CO80: ---- | CP80: ---- | CQ80: ---- | CR80: ---- | CS80: ---- | CT80: ---- | CU80: ---- | CV80: ---- | CW80: ---- | CX80: ---- | CY80: ---- | CZ80: ---- | DA80: ---- | DB80: ---- | DC80: ---- | DD80: ---- | DE80: ---- | DF80: ---- | DG80: ---- | DH80: ---- | DI80: ----
B81: Net Interest | C81: =-39.498-36.679 -> -76.177 | D81: -84.62 | E81: -80.8 | F81: -65.6 | G81: -68.2 | H81: -92.9 | I81: -50.6 | J81: -109.6 | K81: -99.7 | L81: -33.9 | M81: 32.4 | N81: 68.1 | O81: 40.2 | P81: 9.5 | Q81: -6.3 | R81: 1 | S81: -1 | T81: 0 | U81: -4 | V81: =SUM(R81:U81) -> -4 | W81: 0 | X81: -3 | Y81: 0 | Z81: 0 | AA81: =SUM(W81:Z81) -> -3 | AB81: -- | AC81: 3 | AD81: 1 | AE81: 2 | AF81: -3 | AG81: =SUM(AC81:AF81) -> 3 | AH81: -8 | AI81: -8 | AJ81: -9 | AK81: -8 | AL81: =SUM(AH81:AK81) -> -33 | AM81: -9 | AN81: -9 | AO81: -6 | AP81: -4 | AQ81: =SUM(AM81:AP81) -> -28 | AR81: -4 | AS81: -5 | AT81: -5 | AU81: -5 | AV81: =SUM(AR81:AU81) -> -19 | AW81: -7 | AX81: -15 | AY81: -19 | AZ81: -18 | BA81: =SUM(AW81:AZ81) -> -59 | BB81: -16 | BC81: -13 | BD81: -13 | BE81: -12 | BF81: =SUM(BB81:BE81) -> -54 | BG81: -11 | BH81: -14 | BI81: -12 | BJ81: -12 | BK81: =SUM(BG81:BJ81) -> -49 | BL81: -15 | BM81: -12 | BN81: -12 | BO81: -50 | BP81: =SUM(BL81:BO81) -> -89 | BQ81: -65 | BR81: -70 | BS81: -64 | BT81: -63 | BU81: =SUM(BQ81:BT81) -> -262 | BV81: -57 | BW81: -55 | BX81: -53 | BY81: -40 | BZ81: =SUM(BV81:BY81) -> -205 | CA81: -13 | CB81: -16 | CC81: 7 | CD81: 28 | CE81: =SUM(CA81:CD81) -> 6 | CF81: 34 | CG81: 22 | CH81: 52 | CI81: 53 | CJ81: =SUM(CF81:CI81) -> 161 | CK81: 43 | CL81: 24 | CM81: 18 | CN81: 22 | CO81: =SUM(CK81:CN81) -> 107 | CP81: 18 | CQ81: 9 | CR81: 15 | CS81: 8 | CT81: =SUM(CP81:CS81) -> 50 | CU81: 14 | CV81: =+'2. Consolidated'!CV295 -> 9.86625 | CW81: =+'2. Consolidated'!CW295 -> 9.86625 | CX81: =+'2. Consolidated'!CX295 -> 9.86625 | CY81: =SUM(CU81:CX81) -> 43.59875 | CZ81: =+'2. Consolidated'!CZ295 -> 9.86625 | DA81: =+'2. Consolidated'!DA295 -> 9.86625 | DB81: =+'2. Consolidated'!DB295 -> 9.86625 | DC81: =+'2. Consolidated'!DC295 -> 9.86625 | DD81: =SUM(CZ81:DC81) -> 39.465 | DE81: =+'2. Consolidated'!DE295 -> 9.86625 | DF81: =+'2. Consolidated'!DF295 -> 9.86625 | DG81: =+'2. Consolidated'!DG295 -> 9.86625 | DH81: =+'2. Consolidated'!DH295 -> 9.86625 | DI81: =SUM(DE81:DH81) -> 39.465
B82: Pre-Tax Income | C82: =+C76+C81 -> 899.09 | D82: =+D76+D81 -> 1295.222 | E82: =+E76+E81 -> 783 | F82: =+F76+F81 -> 791.2 | G82: =+G76+G81 -> 916.7 | H82: =+H76+H81 -> 921.3 | I82: =+I76+I81 -> 1017.3 | J82: =+J76+J81 -> 1123 | ... AA82: =+AA76+AA81 -> 2983 | AB82: -- | AC82: =+AC76+AC81 -> 795 | AD82: =+AD76+AD81 -> 710 | AE82: =+AE76+AE81 -> 856 | AF82: =+AF76+AF81 -> 895 | AG82: =+AG76+AG81 -> 3256 | AH82: =+AH76+AH81 -> 1038 | AI82: =+AI76+AI81 -> 714 | AJ82: =+AJ76+AJ81 -> 880 | ... DI82: =+DI76+DI81 -> 2528.4567
B83: Taxes | C83: -345.9 | D83: -499.4 | E83: -253.4 | F83: -294.7 | G83: -340.1 | H83: -331.7 | I83: -349 | J83: -382.9 | K83: -504.4 | L83: -648.2 | M83: -749.6 | N83: -708.4 | O83: -610.6 | P83: -680.90526 | Q83: -610.2 | R83: -196 | S83: -152 | T83: -184 | U83: -179 | V83: =SUM(R83:U83) -> -711 | W83: -207 | X83: -149 | Y83: -210 | Z83: -194 | AA83: =SUM(W83:Z83) -> -760 | AB83: -- | AC83: =-805-AD83-AE83-AF83 -> -213 | AD83: -191 | AE83: -196 | AF83: -205 | AG83: -805 | AH83: -259 | AI83: -180 | AJ83: -198 | AK83: -214 | AL83: -851 | AM83: -267 | AN83: -223 | AO83: -255 | AP83: -187 | AQ83: =SUM(AM83:AP83) -> -932 | AR83: -266 | AS83: -185 | AT83: -185 | AU83: -227 | AV83: =SUM(AR83:AU83) -> -863 | AW83: -32 | AX83: -272 | AY83: -182 | AZ83: -160 | BA83: =SUM(AW83:AZ83) -> -646 | BB83: -122 | BC83: -112 | BD83: =-2080+2030 -> -50 | BE83: -78 | BF83: =SUM(BB83:BE83) -> -362 | BG83: -178 | BH83: -150 | BI83: -190 | BJ83: -254 | BK83: =SUM(BG83:BJ83) -> -772 | BL83: -194 | BM83: -134 | BN83: -34 | BO83: 14 | BP83: =SUM(BL83:BO83) -> -348 | BQ83: -197 | BR83: -205 | BS83: -187 | BT83: -345 | BU83: =SUM(BQ83:BT83) -> -934 | BV83: -232 | BW83: -164 | BX83: -274 | BY83: 65 | BZ83: =SUM(BV83:BY83) -> -605 | CA83: -360 | CB83: -319 | CC83: -237 | CD83: -215 | CE83: =SUM(CA83:CD83) -> -1131 | CF83: -198 | CG83: -344 | CH83: =-232-ROUND(0.05*CH90,0) -> -308 | CI83: =-226-ROUND(0.01*CI90,0) -> -241 | CJ83: =SUM(CF83:CI83) -> -1091 | CK83: -256 | CL83: -253 | CM83: -50 | CN83: -107 | CO83: =SUM(CK83:CN83) -> -666 | CP83: -195 | CQ83: -207 | CR83: -130 | CS83: -260 | CT83: =SUM(CP83:CS83) -> -792 | CU83: -209 | CV83: =+CV82*-CV84 -> -190.94593 | CW83: =+CW82*-CW84 -> -147.32013 | CX83: =+CX82*-CX84 -> -74.635259 | CY83: =SUM(CU83:CX83) -> -621.90132 | CZ83: =+CZ82*-CZ84 -> -207.2685 | DA83: =+DA82*-DA84 -> -150.8509 | DB83: =+DB82*-DB84 -> -128.75508 | DC83: =+DC82*-DC84 -> -64.813514 | DD83: =SUM(CZ83:DC83) -> -551.688 | DE83: =+DE82*-DE84 -> -211.81428 | DF83: =+DF82*-DF84 -> -157.96204 | DG83: =+DG82*-DG84 -> -136.97839 | DH83: =+DH82*-DH84 -> -74.790332 | DI83: =SUM(DE83:DH83) -> -581.54504
B84: Tax rate | C84: =-C83/C82 -> 0.38472233 | D84: =-D83/D82 -> 0.38557097 | E84: =-E83/E82 -> 0.32362708 | F84: =-F83/F82 -> 0.37247219 | G84: =-G83/G82 -> 0.37100469 | H84: =-H83/H82 -> 0.36003473 | I84: =-I83/I82 -> 0.34306498 | J84: =-J83/J82 -> 0.34096171 | ... AA84: =-AA83/AA82 -> 0.25477707 | AB84: -- | AC84: =-AC83/AC82 -> 0.26792453 | AD84: =-AD83/AD82 -> 0.26901408 | AE84: =-AE83/AE82 -> 0.22897196 | AF84: =-AF83/AF82 -> 0.22905028 | AG84: =-AG83/AG82 -> 0.24723587 | AH84: =-AH83/AH82 -> 0.2495183 | AI84: =-AI83/AI82 -> 0.25210084 | AJ84: =-AJ83/AJ82 -> 0.225 | ... CU84: =-CU83/CU82 -> 0.22692725 | CV84: 0.265 | CW84: 0.265 | CX84: 0.265 | CY84: =-CY83/CY82 -> 0.25085586 | CZ84: 0.24 | DA84: 0.24 | DB84: 0.24 | DC84: 0.24 | DD84: =-DD83/DD82 -> 0.24 | DE84: 0.23 | DF84: 0.23 | DG84: 0.23 | DH84: 0.23 | DI84: =-DI83/DI82 -> 0.23
C85: ---- | D85: ---- | E85: ---- | F85: ---- | G85: ---- | H85: ---- | I85: ---- | J85: ---- | K85: ---- | L85: ---- | M85: ---- | N85: ---- | O85: ---- | P85: ---- | Q85: ---- | R85: ---- | S85: ---- | T85: ---- | U85: ---- | V85: ---- | W85: ---- | X85: ---- | Y85: ---- | Z85: ---- | AA85: ---- | AB85: ---- | AC85: ---- | AD85: ---- | AE85: ---- | AF85: ---- | AG85: ---- | AH85: ---- | AI85: ---- | AJ85: ---- | AK85: ---- | AL85: ---- | AM85: ---- | AN85: ---- | AO85: ---- | AP85: ---- | AQ85: ---- | AR85: ---- | AS85: ---- | AT85: ---- | AU85: ---- | AV85: ---- | AW85: ---- | AX85: ---- | AY85: ---- | AZ85: ---- | BA85: ---- | BB85: ---- | BC85: ---- | BD85: ---- | BE85: ---- | BF85: ---- | BG85: ---- | BH85: ---- | BI85: ---- | BJ85: ---- | BK85: ---- | BL85: ---- | BM85: ---- | BN85: ---- | BO85: ---- | BP85: ---- | BQ85: ---- | BR85: ---- | BS85: ---- | BT85: ---- | BU85: ---- | BV85: ---- | BW85: ---- | BX85: ---- | BY85: ---- | BZ85: ---- | CA85: ---- | CB85: ---- | CC85: ---- | CD85: ---- | CE85: ---- | CF85: ---- | CG85: ---- | CH85: ---- | CI85: ---- | CJ85: ---- | CK85: ---- | CL85: ---- | CM85: ---- | CN85: ---- | CO85: ---- | CP85: ---- | CQ85: ---- | CR85: ---- | CS85: ---- | CT85: ---- | CU85: ---- | CV85: ---- | CW85: ---- | CX85: ---- | CY85: ---- | CZ85: ---- | DA85: ---- | DB85: ---- | DC85: ---- | DD85: ---- | DE85: ---- | DF85: ---- | DG85: ---- | DH85: ---- | DI85: ----
B86: Net Income - Cont. Ops | C86: =SUM(C82:C83) -> 553.19 | D86: =SUM(D82:D83) -> 795.822 | E86: =SUM(E82:E83) -> 529.6 | F86: =SUM(F82:F83) -> 496.5 | G86: =SUM(G82:G83) -> 576.6 | H86: =SUM(H82:H83) -> 589.6 | I86: =SUM(I82:I83) -> 668.3 | J86: =SUM(J82:J83) -> 740.1 | ... AA86: =SUM(AA82:AA83) -> 2223 | AB86: 2257 | AC86: =+AC82+AC83 -> 582 | AD86: =SUM(AD82:AD83) -> 519 | AE86: =SUM(AE82:AE83) -> 660 | AF86: =SUM(AF82:AF83) -> 690 | AG86: =SUM(AG82:AG83) -> 2451 | AH86: =SUM(AH82:AH83) -> 779 | AI86: =SUM(AI82:AI83) -> 534 | AJ86: =SUM(AJ82:AJ83) -> 682 | AK86: =SUM(AK82:AK83) -> 698 | ... DI86: =SUM(DI82:DI83) -> 1946.9117
B88: Period-End Shares | Q88: 1936 | R88: 1911.6 | S88: 1914 | T88: 1896.4 | U88: 1872 | V88: 1872 | W88: 1856 | X88: 1836 | Y88: 1832 | Z88: 1836 | AA88: 1836 | AC88: 1804 | AD88: 1792 | AE88: 1788 | AF88: 1788 | AG88: 1788 | AH88: 1778 | AI88: 1776 | AJ88: 1788 | AK88: 1740 | AL88: 1740 | AM88: 1728 | AN88: 1728 | AO88: 1720 | AP88: 1710.7032 | AQ88: 1710.7032 | AR88: 1704.3875 | AS88: 1706.6 | AT88: 1737.3 | AU88: 1677.6186 | AV88: 1677.6186 | AW88: 1665.4342 | AX88: 1654.4771 | AY88: 1650.7666 | AZ88: 1643.1951 | BA88: 1643.1951 | BB88: =1302.2727+329.245752 -> 1631.5185 | BC88: 1626.9406 | BD88: =329.065752+1282.69364 -> 1611.7594 | BE88: 1600.5545 | BF88: =+BF348 -> 1600.5545 | BG88: 1588.1084 | BH88: 1573.7975 | BI88: =315.024752+1256.724839 -> 1571.7496 | BJ88: =315.024752+1251.863621 -> 1566.8884 | BK88: =+BK348 -> 1566.8884 | BL88: =315.024752+1246.027581 -> 1561.0523 | BM88: =315.017252+1242.355516 -> 1557.3728 | BN88: =315.017252+1240.017482 -> 1555.0347 | BO88: =315.017252+1244.871297 -> 1559.8885 | BP88: =+BP348 -> 1559.8885 | BQ88: =315.017252+1254.809281 -> 1569.8265 | BR88: =305.011252+1271.478759 -> 1576.49 | BS88: =305.011252+1274.955822 -> 1579.9671 | BT88: =305.011252+1276.789972 -> 1581.8012 | BU88: =+BU348 -> 1581.8012 | BV88: =1277.806465+305.011252 -> 1582.8177 | BW88: =1276.288021+305.007252 -> 1581.2953 | BX88: =1268.760217+305.007252 -> 1573.7675 | BY88: =1263.652653+304.903252 -> 1568.5559 | BZ88: =+BZ348 -> 1568.5559 | CA88: =1259.687689+304.903252 -> 1564.5909 | CB88: =1245.665731+304.897252 -> 1550.563 | CC88: =304.897252+1232.091564 -> 1536.9888 | CD88: =304.897252+1225.074356 -> 1529.9716 | CE88: =+CE348 -> 1529.9716 | CF88: =297.897252+1224.012873 -> 1521.9101 | CG88: =297.897252+1217.224816 -> 1515.1221 | CH88: =297.897252+1211.461555 -> 1509.3588 | CI88: =298+1205 -> 1503 | CJ88: =+CJ348 -> 1503 | CK88: =298+1193 -> 1491 | CL88: =298+1184 -> 1482 | CM88: =298+1179 -> 1477 | CN88: =290+1186 -> 1476 | CO88: =+CO348 -> 1476 | CP88: =289+1188 -> 1477 | CQ88: =289+1191 -> 1480 | CR88: =281+1199 -> 1480 | CS88: =290+1186 -> 1476 | CT88: =+CT348 -> 1476 | CU88: 1476 | CV88: =+CV348 -> 1476 | CW88: =+CW348 -> 1476 | CX88: =+CX348 -> 1476 | CY88: =+CY348 -> 1476 | CZ88: =+CZ348 -> 1476 | DA88: =+DA348 -> 1476 | DB88: =+DB348 -> 1476 | DC88: =+DC348 -> 1476 | ... DI88: =+DI348 -> 1456.4733
B89: Basic Average Shares | C89: 1146.5 | D89: 1154.35 | E89: 2311.7 | F89: 2264.8 | G89: 2198.2 | H89: 2159 | I89: 2142.4 | J89: 2123 | K89: 2105.8 | L89: 2100.4 | M89: 2071 | N89: 2015.2 | O89: 1982.3 | P89: 1940.0708 | Q89: 1938 | R89: 1918.4 | S89: 1911.6 | T89: 1901.2 | U89: 1877.2 | V89: 1902 | W89: 1860 | X89: 1837 | Y89: 1837 | Z89: 1832.4 | AA89: =(460*2)*2 -> 1840 | AC89: =(452.8*2)*2 -> 1811.2 | AD89: =(448.5*2)*2 -> 1794 | AE89: 1787.8 | AF89: 1785.2 | AG89: =2*897.3 -> 1794.6 | AH89: 1778.8 | AI89: 1760 | AJ89: 1764.6 | AK89: 1747.4 | AL89: =AVERAGE(AH89:AK89) -> 1762.7 | AM89: 1729.8 | AN89: 1726.2 | AO89: 1722.8 | AP89: 1715 | AQ89: 1723.5 | AR89: 1709 | AS89: 1706.6 | AT89: 1693.8 | AU89: 1682.4 | AV89: 1697.9 | AW89: 1672 | AX89: 1659.1 | AY89: 1653.1 | AZ89: 1646.9 | BA89: 1657.8 | BB89: 1639.1 | BC89: 1627 | BD89: 1623.5 | BE89: 1605.7 | BF89: =+BF349 -> 1623.825 | BG89: 1594 | BH89: 1581.4 | BI89: 1572.8 | BJ89: 1570.2 | BK89: =+BK349 -> 1579.6 | BL89: 1562.4 | BM89: 1560.6 | BN89: 1556.3 | BO89: 1555.7 | BP89: =+BP349 -> 1558.75 | BQ89: 1561.8 | BR89: 1573 | BS89: 1578 | BT89: 1579 | BU89: =+BU349 -> 1572.95 | BV89: 1581.9 | BW89: 1582.38 | BX89: 1579 | BY89: 1572 | BZ89: =+BZ349 -> 1578.82 | CA89: 1567.1 | CB89: 1559 | CC89: 1543.8 | CD89: 1536.5 | CE89: =+CE349 -> 1551.6 | CF89: 1528.4 | CG89: 1520.8 | CH89: 1513.2 | CI89: 1508 | CJ89: =+CJ349 -> 1517.6 | CK89: 1497.7 | CL89: 1486.8 | CM89: 1478.1 | CN89: 1476.7 | CO89: =+CO349 -> 1484.825 | CP89: 1476.6 | CQ89: 1479.5 | CR89: 1480.5 | CS89: 1482.6 | CT89: =+CT349 -> 1479.8 | CU89: 1483.6 | CV89: =+CV349 -> 1476 | CW89: =+CW349 -> 1476 | CX89: =+CX349 -> 1476 | CY89: =+CY349 -> 1477.9 | CZ89: =+CZ349 -> 1476 | DA89: =+DA349 -> 1476 | DB89: =+DB349 -> 1476 | DC89: =+DC349 -> 1476 | ... DI89: =+DI349 -> 1466.1158
B90: Diluted Average Shares | C90: 1175.35 | D90: 1188.1 | E90: 2349 | F90: 2306.4 | G90: 2235 | H90: 2186.2 | I90: 2177.2 | J90: 2134.6 | K90: 2157.2 | L90: 2161 | M90: 2114.2 | N90: 2040.4 | O90: 2016.1 | P90: 1962.5881 | Q90: 1975.6 | R90: 1954.4 | S90: 1950.4 | T90: 1942 | U90: 1914.8 | V90: 1942.8 | W90: 1897.2 | X90: 1873.8 | Y90: 1873.8 | Z90: 1872.4 | AA90: =(469.8*2)*2 -> 1879.2 | AB90: =(AA90) -> 1879.2 | AC90: =(464.4*2)*2 -> 1857.6 | AD90: =(456.6*2)*2 -> 1826.4 | AE90: 1823.4 | AF90: 1826.8 | AG90: 1832.84 | AH90: 1821.4 | AI90: 1821.2 | AJ90: 1809.6 | AK90: 1790.4 | AL90: =AVERAGE(AH90:AK90) -> 1810.65 | AM90: 1772.4 | AN90: 1769.6 | AO90: 1767.6 | AP90: 1759.6 | AQ90: 1768.8 | AR90: 1754.6 | AS90: 1751.4 | AT90: 1737.3 | AU90: 1723.1 | AV90: 1742.5 | AW90: 1708.9 | AX90: 1693.2 | AY90: 1686.3 | AZ90: 1678.6 | BA90: 1692 | BB90: 1676.9 | BC90: 1660.9 | BD90: 1623.5 | BE90: 1641.2 | BF90: =+BF350 -> 1650.625 | BG90: 1634.4 | BH90: 1620.7 | BI90: 1609.6 | BJ90: 1607.5 | BK90: =+BK350 -> 1618.05 | BL90: 1597.5 | BM90: 1594.4 | BN90: 1591.6 | BO90: 1555.7 | BP90: =+BP350 -> 1584.8 | BQ90: 1593.3 | BR90: 1609.5 | BS90: 1616.9 | BT90: 1614.9 | BU90: =+BU350 -> 1608.65 | BV90: 1619.6 | BW90: 1617.4 | BX90: 1610.7 | BY90: 1595 | BZ90: =+BZ350 -> 1610.675 | CA90: 1585.8 | CB90: 1572.4 | CC90: 1564.8 | CD90: 1556.3 | CE90: =+CE350 -> 1569.825 | CF90: 1543.3 | CG90: 1532.1 | CH90: 1526.5 | CI90: 1516.7 | CJ90: =+CJ350 -> 1529.65 | CK90: 1502 | CL90: 1490 | CM90: 1480.6 | CN90: 1477.7 | CO90: =+CO350 -> 1487.575 | CP90: 1479 | CQ90: 1481 | CR90: 1481.6 | CS90: 1482.9 | CT90: =+CT350 -> 1481.125 | CU90: 1484.2 | CV90: =+CV350 -> 1453.7028 | CW90: =+CW350 -> 1454.0577 | CX90: =+CX350 -> 1454.3467 | CY90: =+CY350 -> 1461.5768 | CZ90: =+CZ350 -> 1455.5713 | DA90: =+DA350 -> 1455.7326 | DB90: =+DB350 -> 1455.832 | DC90: =+DC350 -> 1456.8706 | ... DI90: =+DI350 -> 1447.2893
B92: Comparable EPS | C92: =C86/C90 -> 0.4706598 | D92: =D86/D90 -> 0.66982746 | E92: =E86/E90 -> 0.22545764 | F92: =F86/F90 -> 0.21527055 | G92: =G86/G90 -> 0.25798658 | H92: =H86/H90 -> 0.2696917 | I92: =I86/I90 -> 0.30695389 | J92: =J86/J90 -> 0.34671601 | ... DI92: =DI86/DI90 -> 1.3452125
B93: One-Time Items | C93: =0/C90 -> 0 | D93: =0/D90 -> 0 | E93: =-130/E90 -> -0.055342699 | F93: =-45.1/F90 -> -0.019554284 | G93: =2.5/G90 -> 0.0011185682 | H93: =0.1/H90 -> 4.5741469e-05 | I93: =-5/I90 -> -0.0022965277 | J93: =-266.1/J90 -> -0.12466036 | K93: =0/K90 -> 0 | L93: =0/L90 -> 0 | M93: =0/M90 -> 0 | N93: =0/N90 -> 0 | O93: =20.1/O90 -> 0.0099697436 | P93: =-385.19474/P90 -> -0.19626876 | Q93: 0 | R93: 0 | S93: 0 | T93: 0 | U93: 0 | V93: =(R93*R90+S93*S90+T93*T90+U93*U90)/V90 -> 0 | W93: 0 | X93: 0 | Y93: 0 | Z93: 0 | AA93: =(W93*W90+X93*X90+Y93*Y90+Z93*Z90)/AA90 -> 0 | AB93: 0 | AC93: =(564-AC86)/AC90 -> -0.0096899225 | AD93: =-137/AD90 -> -0.075010951 | AE93: =204/AE90 -> 0.11187891 | AF93: =-28/AF90 -> -0.015327348 | AG93: =(AC93*AC90+AD93*AD90+AE93*AE90+AF93*AF90)/AG90 -> 0.011457629 | AH93: 0 | AI93: 0 | AJ93: 0 | AK93: 0 | AL93: =(AH93*AH90+AI93*AI90+AJ93*AJ90+AK93*AK90)/AL90 -> 0 | AM93: 0 | AN93: 0 | AO93: 0 | AP93: 0 | AQ93: =(AM93*AM90+AN93*AN90+AO93*AO90+AP93*AP90)/AQ90 -> 0 | AR93: 0 | AS93: 0 | AT93: 0 | AU93: 0 | AV93: =(AR93*AR90+AS93*AS90+AT93*AT90+AU93*AU90)/AV90 -> 0 | AW93: 0 | AX93: 0 | AY93: 0 | AZ93: 0 | BA93: =(AW93*AW90+AX93*AX90+AY93*AY90+AZ93*AZ90)/BA90 -> 0 | BB93: 0 | BC93: 0 | BD93: =-(2030)/BD90 -> -1.250385 | BE93: 0 | BF93: =(BB93*BB90+BC93*BC90+BD93*BD90+BE93*BE90)/BF90 -> -1.2298372 | BG93: 0 | BH93: 0 | BI93: 0 | BJ93: 0 | BK93: =(BG93*BG90+BH93*BH90+BI93*BI90+BJ93*BJ90)/BK90 -> 0 | BL93: 0 | BM93: 0 | BN93: =-400/BN90 -> -0.25131943 | BO93: 0 | BP93: =(BL93*BL90+BM93*BM90+BN93*BN90+BO93*BO90)/BP90 -> -0.25239778 | BQ93: 0 | BR93: 0 | BS93: 0 | BT93: 0 | BU93: =(BQ93*BQ90+BR93*BR90+BS93*BS90+BT93*BT90)/BU90 -> 0 | BV93: 0 | BW93: 0 | BX93: 0 | BY93: 0 | BZ93: =(BV93*BV90+BW93*BW90+BX93*BX90+BY93*BY90)/BZ90 -> 0 | CA93: 0 | CB93: 0 | CC93: 0 | CD93: 0 | CE93: =(CA93*CA90+CB93*CB90+CC93*CC90+CD93*CD90)/CE90 -> 0 | CF93: 0 | CG93: 0 | CH93: =-(403-ROUND(0.05*CH90,0))/CH90 -> -0.21421553 | CI93: =-((64-(403-340))+(379-340)-ROUND(0.01*CI90,0))/CI90 -> -0.016483154 | CJ93: =(CF93*CF90+CG93*CG90+CH93*CH90+CI93*CI90)/CJ90 -> -0.230118 | CK93: 0 | CL93: 0 | CM93: 0 | CN93: 0 | CO93: =(CK93*CK90+CL93*CL90+CM93*CM90+CN93*CN90)/CO90 -> 0 | CP93: 0 | CQ93: 0 | CR93: 0 | CS93: 0 | CT93: =(CP93*CP90+CQ93*CQ90+CR93*CR90+CS93*CS90)/CT90 -> 0 | CU93: 0 | CV93: =-0.15/3 -> -0.05 | CW93: =-0.15/3 -> -0.05 | CX93: =-0.15/3 -> -0.05 | CY93: =(CU93*CU90+CV93*CV90+CW93*CW90+CX93*CX90)/CY90 -> -0.14922607 | CZ93: =-200/4*(1-0.25)/CZ90 -> -0.02576308 | DA93: =-200/4*(1-0.25)/DA90 -> -0.025760225 | DB93: =-200/4*(1-0.25)/DB90 -> -0.025758467 | DC93: =-200/4*(1-0.25)/DC90 -> -0.025740104 | DD93: =(CZ93*CZ90+DA93*DA90+DB93*DB90+DC93*DC90)/DD90 -> -0.10302186 | DE93: =-200/4*(1-0.25)/DE90 -> -0.025784967 | DF93: =-200/4*(1-0.25)/DF90 -> -0.025874952 | DG93: =-200/4*(1-0.25)/DG90 -> -0.025946877 | DH93: =-200/4*(1-0.25)/DH90 -> -0.026036553 | DI93: =(DE93*DE90+DF93*DF90+DG93*DG90+DH93*DH90)/DI90 -> -0.10364203
B94: GAAP EPS | C94: =SUM(C92:C93) -> 0.4706598 | D94: =SUM(D92:D93) -> 0.66982746 | E94: =SUM(E92:E93) -> 0.17011494 | F94: =SUM(F92:F93) -> 0.19571627 | G94: =SUM(G92:G93) -> 0.25910515 | H94: =SUM(H92:H93) -> 0.26973744 | I94: =SUM(I92:I93) -> 0.30465736 | J94: =SUM(J92:J93) -> 0.22205565 | ... DI94: =SUM(DI92:DI93) -> 1.2415705
B96: % chg Y/Y in Comparable EPS | C96: -- | D96: =+D92/C92-1 -> 0.4231669 | E96: =+E92/D92-1 -> -0.66340938 | F96: =+F92/E92-1 -> -0.045184053 | G96: =+G92/F92-1 -> 0.19842949 | H96: =+H92/G92-1 -> 0.045371063 | I96: =+I92/H92-1 -> 0.13816585 | J96: =+J92/I92-1 -> 0.12953779 | K96: =+K92/J92-1 -> 0.26427967 | ... Q96: =+Q92/P92-1 -> 0.011884834 | R96: -- | S96: -- | T96: -- | U96: -- | V96: =+V92/Q92-1 -> 0.13757336 | W96: =+W92/R92-1 -> 0.18863426 | X96: =+X92/S92-1 -> 0.068211124 | Y96: =+Y92/T92-1 -> 0.10971723 | Z96: =+Z92/U92-1 -> -0.054828352 | AA96: =+AA92/V92-1 -> 0.077466307 | AC96: =+AC92/W92-1 -> -0.078438796 | AD96: =+AD92/X92-1 -> 0.13532931 | AE96: =+AE92/Y92-1 -> 0.21114793 | AF96: =+AF92/Z92-1 -> 0.28820321 | AG96: =+AG92/AA92-1 -> 0.13045245 | AH96: =+AH92/AC92-1 -> 0.36509018 | AI96: =+AI92/AD92-1 -> 0.031839516 | AJ96: =+AJ92/AE92-1 -> 0.041213528 | AK96: =+AK92/AF92-1 -> 0.032160573 | AL96: =+AL92/AG92-1 -> 0.1122005 | AM96: =+AM92/AH92-1 -> 0.26905722 | AN96: =+AN92/AI92-1 -> 0.26235811 | AO96: =+AO92/AJ92-1 -> 0.18738266 | ... DI96: =+DI92/DD92-1 -> 0.12113229
B98: EBITDA | C98: =C76+'2. Consolidated'!C110 -> 1072.446 | D98: =D76+'2. Consolidated'!D110 -> 1517.88 | E98: =E76+'2. Consolidated'!E110 -> 1048.3 | F98: =F76+'2. Consolidated'!F110 -> 1055 | G98: =G76+'2. Consolidated'!G110 -> 1172.9 | H98: =H76+'2. Consolidated'!H110 -> 1211.6 | I98: =I76+'2. Consolidated'!I110 -> 1291.4 | J98: =J76+'2. Consolidated'!J110 -> 1471.9 | ... AA98: =AA76+'2. Consolidated'!AA110 -> 3359 | AC98: =AC76+'2. Consolidated'!AC110 -> 896 | AD98: =AD76+'2. Consolidated'!AD110 -> 816 | AE98: =AE76+'2. Consolidated'!AE110 -> 965 | AF98: =AF76+'2. Consolidated'!AF110 -> 1014 | AG98: =AG76+'2. Consolidated'!AG110 -> 3691 | AH98: =AH76+'2. Consolidated'!AH110 -> 1168 | AI98: =AI76+'2. Consolidated'!AI110 -> 846 | AJ98: =AJ76+'2. Consolidated'!AJ110 -> 1021 | ... DI98: =DI76+'2. Consolidated'!DI110 -> 3313.8253
B99: EBITDAR | K99: =K98-K100 -> 2011.9 | L99: =L98-L100 -> 2383.9 | M99: =M98-M100 -> 2643.2 | N99: =N98-N100 -> 2686.5 | O99: =O98-O100 -> 3081.3 | P99: =P98-P100 -> 3275.3 | Q99: =Q98-Q100 -> 3262.9 | R99: =R98-R100 -> 943.5 | ... AA99: =AA98-AA100 -> 3790 | AC99: =AC98-AC100 -> 1016.5 | AD99: =AD98-AD100 -> 936.5 | AE99: =AE98-AE100 -> 1085.5 | AF99: =AF98-AF100 -> 1134.5 | AG99: =AG98-AG100 -> 4173 | AH99: =AH98-AH100 -> 1301.25 | AI99: =AI98-AI100 -> 979.25 | AJ99: =AJ98-AJ100 -> 1154.25 | ... DI99: =DI98-DI100 -> 4839.1513
B100: Rent Expense | K100: -207 | L100: -233 | M100: -252 | N100: -285 | O100: -344 | P100: -397 | Q100: -416 | R100: =+V100/4 -> -111.5 | S100: =+V100/4 -> -111.5 | T100: =+V100/4 -> -111.5 | U100: =+V100/4 -> -111.5 | V100: -446 | W100: =+AA100/4 -> -107.75 | X100: =+AA100/4 -> -107.75 | Y100: =+AA100/4 -> -107.75 | Z100: =+AA100/4 -> -107.75 | AA100: -431 | AC100: =+AG100/4 -> -120.5 | AD100: =+AG100/4 -> -120.5 | AE100: =+AG100/4 -> -120.5 | AF100: =+AG100/4 -> -120.5 | AG100: -482 | AH100: =+AL100/4 -> -133.25 | AI100: =+AL100/4 -> -133.25 | AJ100: =+AL100/4 -> -133.25 | AK100: =+AL100/4 -> -133.25 | AL100: -533 | AM100: =+AQ100/4 -> -148.5 | AN100: =+AQ100/4 -> -148.5 | AO100: =+AQ100/4 -> -148.5 | AP100: =+AQ100/4 -> -148.5 | AQ100: -594 | AR100: =+AV100/4 -> -165.25 | AS100: =+AV100/4 -> -165.25 | AT100: =+AV100/4 -> -165.25 | AU100: =+AV100/4 -> -165.25 | AV100: -661 | AW100: =+BA100/4 -> -182.75 | AX100: =+BA100/4 -> -182.75 | AY100: =+BA100/4 -> -182.75 | AZ100: =+BA100/4 -> -182.75 | BA100: -731 | BB100: =+BF100/4 -> -205 | BC100: =+BF100/4 -> -205 | BD100: =+BF100/4 -> -205 | BE100: =+BF100/4 -> -205 | BF100: -820 | BG100: =+BK100/4 -> -207.25 | BH100: =+BK100/4 -> -207.25 | BI100: =+BK100/4 -> -207.25 | BJ100: =+BK100/4 -> -207.25 | BK100: -829 | BL100: =+BP100/4 -> -226.5 | BM100: =+BP100/4 -> -226.5 | BN100: =+BP100/4 -> -226.5 | BO100: =+BP100/4 -> -226.5 | BP100: =-569-337 -> -906 | BQ100: =+BU100/4 -> -234 | BR100: =+BU100/4 -> -234 | BS100: =+BU100/4 -> -234 | BT100: =+BU100/4 -> -234 | BU100: =-589-347 -> -936 | BV100: =+BZ100/4 -> -239.75 | BW100: =+BZ100/4 -> -239.75 | BX100: =+BZ100/4 -> -239.75 | BY100: =+BZ100/4 -> -239.75 | BZ100: =-593-366 -> -959 | CA100: =+CE100/4 -> -247 | CB100: =+CE100/4 -> -247 | CC100: =+CE100/4 -> -247 | CD100: =+CE100/4 -> -247 | CE100: =-585-403 -> -988 | CF100: =+CJ100/4 -> -262.75 | CG100: =+CJ100/4 -> -262.75 | CH100: =+CJ100/4 -> -262.75 | CI100: =+CJ100/4 -> -262.75 | CJ100: =-618-433 -> -1051 | CK100: =+CO100/4 -> -273.75 | CL100: =+CO100/4 -> -273.75 | CM100: =+CO100/4 -> -273.75 | CN100: =+CO100/4 -> -273.75 | CO100: =-663-432 -> -1095 | CP100: =+CT100/4 -> -286.5 | CQ100: =+CT100/4 -> -286.5 | CR100: =+CT100/4 -> -286.5 | CS100: =+CT100/4 -> -286.5 | CT100: =-693-453 -> -1146 | CU100: =+CY100/4 -> -315.15 | CV100: =+CY100/4 -> -315.15 | CW100: =+CY100/4 -> -315.15 | CX100: =+CY100/4 -> -315.15 | CY100: =CT100*1.1 -> -1260.6 | CZ100: =+DD100/4 -> -346.665 | DA100: =+DD100/4 -> -346.665 | DB100: =+DD100/4 -> -346.665 | DC100: =+DD100/4 -> -346.665 | DD100: =CY100*1.1 -> -1386.66 | DE100: =+DI100/4 -> -381.3315 | DF100: =+DI100/4 -> -381.3315 | DG100: =+DI100/4 -> -381.3315 | DH100: =+DI100/4 -> -381.3315 | DI100: =DD100*1.1 -> -1525.326
B101: PVOL | K101: =-K100*8 -> 1656 | L101: =-L100*8 -> 1864 | M101: =-M100*8 -> 2016 | N101: =-N100*8 -> 2280 | O101: =-O100*8 -> 2752 | P101: =-P100*8 -> 3176 | Q101: =-Q100*8 -> 3328 | V101: =-V100*8 -> 3568 | AA101: =-AA100*8 -> 3448 | AG101: =-AG100*8 -> 3856 | AL101: =-AL100*8 -> 4264 | AQ101: =-AQ100*8 -> 4752 | AV101: =-AV100*8 -> 5288 | BA101: =-BA100*8 -> 5848 | BF101: =-BF100*8 -> 6560 | BK101: =-BK100*8 -> 6632 | BP101: =-BP100*8 -> 7248 | BU101: =-BU100*8 -> 7488 | BZ101: =-BZ100*8 -> 7672 | CE101: =-CE100*8 -> 7904 | CJ101: =-CJ100*8 -> 8408 | CO101: =-CO100*8 -> 8760 | CT101: =-CT100*8 -> 9168 | CY101: =-CY100*8 -> 10084.8 | DD101: =-DD100*8 -> 11093.28 | DI101: =-DI100*8 -> 12202.608
B102: Dividends per share declared | C102: -- | D102: -- | E102: -- | F102: -- | G102: -- | H102: -- | I102: -- | J102: -- | K102: -- | L102: -- | M102: -- | N102: -- | O102: -- | P102: -- | Q102: =+Q340 -> 0.265 | R102: =+R340 -> 0.06 | S102: =+S340 -> 0.08 | T102: =+T340 -> 0.08 | U102: =+U340 -> 0.08 | V102: =+V340 -> 0.3 | W102: =+W340 -> 0.08 | X102: =+X340 -> 0.09 | ... AA102: =+AA340 -> 0.35 | AC102: =+AC340 -> 0.09 | AD102: =+AD340 -> 0.105 | AE102: =+AE340 -> 0.105 | AF102: =+AF340 -> 0.105 | AG102: =+AG340 -> 0.405 | AH102: =+AH340 -> 0.105 | AI102: =+AI340 -> 0.12 | AJ102: =+AJ340 -> 0.12 | ... DI102: =+DI340 -> 1.9415894
B103: Payout ratio | C103: -- | D103: -- | E103: -- | F103: -- | G103: -- | H103: -- | I103: -- | J103: -- | K103: -- | L103: -- | M103: -- | N103: -- | O103: -- | P103: -- | Q103: =+(Q102/Q92) -> 0.27457597 | R103: =+(R102/R92) -> 0.2097746 | S103: =+(S102/S92) -> 0.3414267 | T103: =+(T102/T92) -> 0.29705545 | U103: =+(U102/U92) -> 0.25788552 | V103: =+(V102/V92) -> 0.27324895 | W103: =+(W102/W92) -> 0.23531163 | X103: =+(X102/X92) -> 0.35957783 | ... AA103: =+(AA102/AA92) -> 0.29587045 | AC103: =+(AC102/AC92) -> 0.28725773 | AD103: =+(AD102/AD92) -> 0.36950289 | AE103: =+(AE102/AE92) -> 0.29008636 | AF103: =+(AF102/AF92) -> 0.2779913 | AG103: =+(AG102/AG92) -> 0.30285606 | AH103: =+(AH102/AH92) -> 0.24550321 | AI103: =+(AI102/AI92) -> 0.40925843 | AJ103: =+(AJ102/AJ92) -> 0.31840469 | ... DI103: =+(DI102/DI92) -> 1.4433329
B105: CASH FLOW STATEMENT
B107: Net Income (Comparable) | C107: ='2. Consolidated'!C86 -> 553.19 | D107: ='2. Consolidated'!D86 -> 795.822 | E107: ='2. Consolidated'!E86 -> 529.6 | F107: ='2. Consolidated'!F86 -> 496.5 | G107: ='2. Consolidated'!G86 -> 576.6 | H107: ='2. Consolidated'!H86 -> 589.6 | I107: ='2. Consolidated'!I86 -> 668.3 | J107: ='2. Consolidated'!J86 -> 740.1 | ... AA107: ='2. Consolidated'!AA86 -> 2223 | AC107: ='2. Consolidated'!AC86 -> 582 | AD107: ='2. Consolidated'!AD86 -> 519 | AE107: ='2. Consolidated'!AE86 -> 660 | AF107: ='2. Consolidated'!AF86 -> 690 | AG107: ='2. Consolidated'!AG86 -> 2451 | AH107: ='2. Consolidated'!AH86 -> 779 | AI107: ='2. Consolidated'!AI86 -> 534 | AJ107: ='2. Consolidated'!AJ86 -> 682 | ... DI107: ='2. Consolidated'!DI86 -> 1946.9117
B108: One-Timers | C108: ='2. Consolidated'!C93*'2. Consolidated'!C90 -> 0 | D108: ='2. Consolidated'!D93*'2. Consolidated'!D90 -> 0 | E108: ='2. Consolidated'!E93*'2. Consolidated'!E90 -> -130 | F108: ='2. Consolidated'!F93*'2. Consolidated'!F90 -> -45.1 | G108: ='2. Consolidated'!G93*'2. Consolidated'!G90 -> 2.5 | H108: ='2. Consolidated'!H93*'2. Consolidated'!H90 -> 0.1 | I108: ='2. Consolidated'!I93*'2. Consolidated'!I90 -> -5 | J108: ='2. Consolidated'!J93*'2. Consolidated'!J90 -> -266.1 | ... AA108: ='2. Consolidated'!AA93*'2. Consolidated'!AA90 -> 0 | AC108: ='2. Consolidated'!AC93*'2. Consolidated'!AC90 -> -18 | AD108: ='2. Consolidated'!AD93*'2. Consolidated'!AD90 -> -137 | AE108: ='2. Consolidated'!AE93*'2. Consolidated'!AE90 -> 204 | AF108: ='2. Consolidated'!AF93*'2. Consolidated'!AF90 -> -28 | AG108: ='2. Consolidated'!AG93*'2. Consolidated'!AG90 -> 21 | AH108: ='2. Consolidated'!AH93*'2. Consolidated'!AH90 -> 0 | AI108: ='2. Consolidated'!AI93*'2. Consolidated'!AI90 -> 0 | AJ108: ='2. Consolidated'!AJ93*'2. Consolidated'!AJ90 -> 0 | ... DI108: ='2. Consolidated'!DI93*'2. Consolidated'!DI90 -> -150
B109: GAAP Net Income | C109: =SUM(C107:C108) -> 553.19 | D109: =SUM(D107:D108) -> 795.822 | E109: =SUM(E107:E108) -> 399.6 | F109: =SUM(F107:F108) -> 451.4 | G109: =SUM(G107:G108) -> 579.1 | H109: =SUM(H107:H108) -> 589.7 | I109: =SUM(I107:I108) -> 663.3 | J109: =SUM(J107:J108) -> 474 | ... AA109: =SUM(AA107:AA108) -> 2223 | AC109: =SUM(AC107:AC108) -> 564 | AD109: =SUM(AD107:AD108) -> 382 | AE109: =SUM(AE107:AE108) -> 864 | AF109: =SUM(AF107:AF108) -> 662 | AG109: =SUM(AG107:AG108) -> 2472 | AH109: =SUM(AH107:AH108) -> 779 | AI109: =SUM(AI107:AI108) -> 534 | AJ109: =SUM(AJ107:AJ108) -> 682 | ... BE109: =SUM(BE107:BE108) -> 1137 | BF109: =SUM(BB109:BE109) -> 1933 | BG109: =SUM(BG107:BG108) -> 1092 | BH109: =SUM(BH107:BH108) -> 847 | BI109: =SUM(BI107:BI108) -> 1101 | BJ109: =SUM(BJ107:BJ108) -> 989 | BK109: =SUM(BG109:BJ109) -> 4029 | BL109: =SUM(BL107:BL108) -> 1367 | BM109: =SUM(BM107:BM108) -> 1115 | BN109: =SUM(BN107:BN108) -> 847 | BO109: =SUM(BO107:BO108) -> -790 | BP109: =SUM(BL109:BO109) -> 2539 | BQ109: =SUM(BQ107:BQ108) -> 1518 | BR109: =SUM(BR107:BR108) -> 1251 | BS109: =SUM(BS107:BS108) -> 1449 | BT109: =SUM(BT107:BT108) -> 1509 | BU109: =SUM(BQ109:BT109) -> 5727 | BV109: =SUM(BV107:BV108) -> 1874 | BW109: =SUM(BW107:BW108) -> 1337 | BX109: =SUM(BX107:BX108) -> 1396 | BY109: =SUM(BY107:BY108) -> 1439 | BZ109: =SUM(BV109:BY109) -> 6046 | CA109: =SUM(CA107:CA108) -> 1468 | CB109: =SUM(CB107:CB108) -> 1331 | CC109: =SUM(CC107:CC108) -> 1240 | CD109: =SUM(CD107:CD108) -> 1031 | CE109: =SUM(CA109:CD109) -> 5070 | CF109: =SUM(CF107:CF108) -> 1450 | CG109: =SUM(CG107:CG108) -> 1578 | CH109: =SUM(CH107:CH108) -> 1172 | CI109: =SUM(CI107:CI108) -> 1500 | CJ109: =SUM(CF109:CI109) -> 5700 | CK109: =SUM(CK107:CK108) -> 1051 | CL109: =SUM(CL107:CL108) -> 1163 | CM109: =SUM(CM107:CM108) -> 794 | CN109: =SUM(CN107:CN108) -> 211 | CO109: =SUM(CK109:CN109) -> 3219 | CP109: =SUM(CP107:CP108) -> 727 | CQ109: =SUM(CQ107:CQ108) -> 792 | CR109: =SUM(CR107:CR108) -> 520 | CS109: =SUM(CS107:CS108) -> 1069 | CT109: =SUM(CP109:CS109) -> 3108 | CU109: =SUM(CU107:CU108) -> 712 | CV109: =SUM(CV107:CV108) -> 456.91961 | CW109: =SUM(CW107:CW108) -> 335.90199 | CX109: =SUM(CX107:CX108) -> 134.28989 | CY109: =SUM(CU109:CX109) -> 1639.1115 | CZ109: =SUM(CZ107:CZ108) -> 618.85026 | DA109: =SUM(DA107:DA108) -> 440.19452 | DB109: =SUM(DB107:DB108) -> 370.22443 | DC109: =SUM(DC107:DC108) -> 167.74279 | DD109: =SUM(CZ109:DC109) -> 1597.012 | DE109: =SUM(DE107:DE108) -> 671.61737 | DF109: =SUM(DF107:DF108) -> 491.32942 | DG109: =SUM(DG107:DG108) -> 421.07984 | DH109: =SUM(DH107:DH108) -> 212.88503 | DI109: =SUM(DE109:DH109) -> 1796.9117
B110: D&A | C110: 97.179 | D110: 138.038 | E110: 184.5 | F110: 198.2 | G110: 188 | H110: 197.4 | I110: 223.5 | J110: 239.3 | K110: 255.2 | L110: 257.2 | M110: 282 | N110: 269.7 | O110: 303.6 | P110: 335 | Q110: 323.7 | R110: =+R149 -> 78 | S110: =+S149-R149 -> 83 | T110: =+T149-S149 -> 88 | U110: =+U149-T149 -> 86 | V110: 335 | W110: =+W149 -> 86 | X110: =+X149-W149 -> 92 | Y110: =+Y149-X149 -> 94 | Z110: =+Z149-Y149 -> 101 | AA110: 373 | AC110: =+AC149 -> 104 | AD110: =+AD149-AC149 -> 107 | AE110: =+AE149-AD149 -> 111 | AF110: =+AF149-AE149 -> 116 | AG110: 438 | AH110: =+AH149 -> 122 | AI110: =+AI149-AH149 -> 124 | AJ110: =+AJ149-AI149 -> 132 | AK110: =+AK149-AJ149 -> 140 | AL110: 518 | AM110: =+AM149 -> 147 | AN110: =+AN149-AM149 -> 100 | AO110: =+AO149-AN149 -> 234 | AP110: =+AP149-AO149 -> 168 | AQ110: =606+43 -> 649 | AR110: =+AR149 -> 165 | AS110: =+AS149-AR149 -> 157 | AT110: =+AT149-AS149 -> 159 | AU110: =+AU149-AT149 -> 181 | AV110: =649+13 -> 662 | AW110: =+AW149 -> 173 | AX110: =+AX149-AW149 -> 173 | AY110: =+AY149-AX149 -> 175 | AZ110: =+AZ149-AY149 -> 185 | BA110: 706 | BB110: =+BB149 -> 179 | BC110: =+BC149-BB149 -> 187 | BD110: =+BD149-BC149 -> 185 | BE110: =+BE149-BD149 -> 196 | BF110: 747 | BG110: =+BG149 -> 178 | BH110: =+BH149-BG149 -> 171 | BI110: =+BI149-BH149 -> 178 | BJ110: =+BJ149-BI149 -> 178 | BK110: =SUM(BG110:BJ110) -> 705 | BL110: =+BL149 -> 169 | BM110: =+BM149-BL149 -> 174 | BN110: =+BN149-BM149 -> 170 | BO110: =+BO149-BN149 -> 208 | BP110: =SUM(BL110:BO110) -> 721 | BQ110: =+BQ149 -> 176 | BR110: =+BR149-BQ149 -> 185 | BS110: =+BS149-BR149 -> 182 | BT110: =+BT149-BS149 -> 201 | BU110: =SUM(BQ110:BT110) -> 744 | BV110: =+BV149 -> 177 | BW110: =+BW149-BV149 -> 181 | BX110: =+BX149-BW149 -> 180 | BY110: =+BY149-BX149 -> 179 | BZ110: =SUM(BV110:BY110) -> 717 | CA110: =+CA149 -> 169 | CB110: =+CB149-CA149 -> 173 | CC110: =+CC149-CB149 -> 174 | CD110: =+CD149-CC149 -> 187 | CE110: =SUM(CA110:CD110) -> 703 | CF110: =+CF149 -> 191 | CG110: =+CG149-CF149 -> 191 | CH110: =+CH149-CG149 -> 207 | CI110: =+CI149-CH149 -> 207 | CJ110: =SUM(CF110:CI110) -> 796 | CK110: =+CK149 -> 188 | CL110: =+CL149-CK149 -> 190 | CM110: =+CM149-CL149 -> 198 | CN110: =+CN149-CM149 -> 199 | CO110: =SUM(CK110:CN110) -> 775 | CP110: =+CP149 -> 190 | CQ110: =+CQ149-CP149 -> 179 | CR110: =CM110*1.03 -> 203.94 | CS110: =+CS149-CR149 -> 193 | CT110: =SUM(CP110:CS110) -> 765.94 | CU110: =CP110*1.025 -> 194.75 | CV110: =CQ110*1.025 -> 183.475 | CW110: =CR110*1.025 -> 209.0385 | CX110: =CS110*1.025 -> 197.825 | CY110: =SUM(CU110:CX110) -> 785.0885 | CZ110: =CU110*1.025 -> 199.61875 | DA110: =CV110*1.025 -> 188.06187 | DB110: =CW110*1.025 -> 214.26446 | DC110: =CX110*1.025 -> 202.77062 | DD110: =SUM(CZ110:DC110) -> 804.71571 | DE110: =CZ110*1.025 -> 204.60922 | DF110: =DA110*1.025 -> 192.76342 | DG110: =DB110*1.025 -> 219.62107 | DH110: =DC110*1.025 -> 207.83989 | DI110: =SUM(DE110:DH110) -> 824.83361
B111: Share-Based Compensation | C111: 0 | D111: 0 | E111: 0 | F111: 0 | G111: 0 | H111: 32.4 | I111: 13.9 | J111: 12.5 | K111: 47.2 | L111: 63.1 | M111: 54.2 | N111: 147.7 | O111: 141 | P111: 170.6 | Q111: 159 | R111: =+R150 -> 21 | S111: =+S150-R150 -> 29 | T111: =+T150-S150 -> 28 | U111: =+U150-T150 -> 27 | V111: 105 | W111: =+W150 -> 25 | X111: =+X150-W150 -> 36 | Y111: =+Y150-X150 -> 34 | Z111: =+Z150-Y150 -> 35 | AA111: 130 | AC111: =+AC150 -> 37 | AD111: =+AD150-AC150 -> 46 | AE111: =+AE150-AD150 -> 45 | AF111: =+AF150-AE150 -> 46 | AG111: 174 | AH111: =+AH150 -> 42 | AI111: =+AI150-AH150 -> 46 | AJ111: =+AJ150-AI150 -> 43 | AK111: =+AK150-AJ150 -> 46 | AL111: 177 | AM111: =+AM150 -> 43 | AN111: =+AN150-AM150 -> 49 | AO111: =+AO150-AN150 -> 48 | AP111: =+AP150-AO150 -> 51 | AQ111: 191 | AR111: =+AR150 -> 54 | AS111: =+AS150-AR150 -> 62 | AT111: =+AT150-AS150 -> 60 | AU111: =+AU150-AT150 -> 60 | AV111: 236 | AW111: =+AW150 -> 57 | AX111: =+AX150-AW150 -> 54 | AY111: =+AY150-AX150 -> 51 | AZ111: =+AZ150-AY150 -> 53 | BA111: 215 | BB111: =+BB150 -> 50 | BC111: =+BC150-BB150 -> 53 | BD111: =+BD150-BC150 -> 55 | BE111: =+BE150-BD150 -> 60 | BF111: 218 | BG111: =+BG150 -> 41 | BH111: =+BH150-BG150 -> 92 | BI111: =+BI150-BH150 -> 93 | BJ111: =+BJ150-BI150 -> 99 | BK111: =SUM(BG111:BJ111) -> 325 | BL111: =+BL150 -> 80 | BM111: =+BM150-BL150 -> 110 | BN111: =+BN150-BM150 -> 113 | BO111: =+BO150-BN150 -> 126 | BP111: =SUM(BL111:BO111) -> 429 | BQ111: =+BQ150 -> 136 | BR111: =+BR150-BQ150 -> 189 | BS111: =+BS150-BR150 -> 142 | BT111: =+BT150-BS150 -> 144 | BU111: =SUM(BQ111:BT111) -> 611 | BV111: =+BV150 -> 136 | BW111: =+BW150-BV150 -> 170 | BX111: =+BX150-BW150 -> 161 | BY111: =+BY150-BX150 -> 171 | BZ111: =SUM(BV111:BY111) -> 638 | CA111: =+CA150 -> 170 | CB111: =+CB150-CA150 -> 194 | CC111: =+CC150-CB150 -> 192 | CD111: =+CD150-CC150 -> 199 | CE111: =SUM(CA111:CD111) -> 755 | CF111: =+CF150 -> 196 | CG111: =+CG150-CF150 -> 206 | CH111: =+CH150-CG150 -> 216 | CI111: =+CI150-CH150 -> 186 | CJ111: =SUM(CF111:CI111) -> 804 | CK111: =+CK150 -> 183 | CL111: =+CL150-CK150 -> 192 | CM111: =+CM150-CL150 -> 169 | CN111: =+CN150-CM150 -> 165 | CO111: =SUM(CK111:CN111) -> 709 | CP111: =+CP150 -> 185 | CQ111: =+CQ150-CP150 -> 176 | CR111: =CM111*(1+'2. Consolidated'!CR58) -> 169.14997 | CS111: =+CS150-CR150 -> 160 | CT111: =SUM(CP111:CS111) -> 690.14997 | CU111: =CP111*(1+'2. Consolidated'!CU58) -> 176.99701 | CV111: =CQ111*(1+'2. Consolidated'!CV58) -> 154.06335 | CW111: =CR111*(1+'2. Consolidated'!CW58) -> 154.55774 | CX111: =CS111*(1+'2. Consolidated'!CX58) -> 144.09542 | CY111: =SUM(CU111:CX111) -> 629.71352 | CZ111: =CU111*(1+'2. Consolidated'!CZ58) -> 163.03098 | DA111: =CV111*(1+'2. Consolidated'!DA58) -> 146.72581 | DB111: =CW111*(1+'2. Consolidated'!DB58) -> 150.35357 | DC111: =CX111*(1+'2. Consolidated'!DC58) -> 140.39945 | DD111: =SUM(CZ111:DC111) -> 600.5098 | DE111: =CZ111*(1+'2. Consolidated'!DE58) -> 163.12287 | DF111: =DA111*(1+'2. Consolidated'!DF58) -> 147.00486 | DG111: =DB111*(1+'2. Consolidated'!DG58) -> 151.38905 | DH111: =DC111*(1+'2. Consolidated'!DH58) -> 141.40245 | DI111: =SUM(DE111:DH111) -> 602.91923
...

Sheet 3. Segment Analysis
B1: Nike (NKE)
B2: Quarterly Segment Sales Build
B3: $ millions except per share data, FY ending May
C5: =+'2. Consolidated'!C5 -> 35216 | D5: =+'2. Consolidated'!D5 -> 35581 | E5: =+'2. Consolidated'!E5 -> 35946 | F5: =+'2. Consolidated'!F5 -> 36311 | G5: =+'2. Consolidated'!G5 -> 36677 | H5: =+'2. Consolidated'!H5 -> 37042 | I5: =+'2. Consolidated'!I5 -> 37407 | J5: =+'2. Consolidated'!J5 -> 37772 | ... DI5: =+'2. Consolidated'!DI5 -> 46904
C6: =+'2. Consolidated'!C6 -> 1996 | D6: =+'2. Consolidated'!D6 -> 1997 | E6: =+'2. Consolidated'!E6 -> 1998 | F6: =+'2. Consolidated'!F6 -> 1999 | G6: =+'2. Consolidated'!G6 -> 2000 | H6: =+'2. Consolidated'!H6 -> 2001 | I6: =+'2. Consolidated'!I6 -> 2002 | J6: =+'2. Consolidated'!J6 -> 2003 | ... DI6: =+'2. Consolidated'!DI6 -> 2029E
A7: =IF(ISBLANK(B7),"Scrap", " ") | B7: CONSOLIDATED SALES / EBIT SUMMARY
A8: =IF(ISBLANK(B8),"Scrap", " ") | B8: Total Nike Sales Model
A9: =IF(ISBLANK(B9),"Scrap", " ") | B9: North America | C9: =+'2. Consolidated'!C9 -> 3615.062 | D9: =+'2. Consolidated'!D9 -> 5201.624 | E9: =+'2. Consolidated'!E9 -> 5139.412 | F9: =+'2. Consolidated'!F9 -> 4750.711 | G9: =+'2. Consolidated'!G9 -> 4732.073 | H9: =+'2. Consolidated'!H9 -> 4819 | I9: =+'2. Consolidated'!I9 -> 4669.6 | J9: =+'2. Consolidated'!J9 -> 4658.5 | ... Q9: =+'2. Consolidated'!Q9 -> 6696 | R9: =+R182 -> 1903 | S9: =+S182 -> 1701 | T9: =+T182 -> 1836 | U9: =+U182 -> 2139 | V9: =SUM(R9:U9) -> 7579 | W9: =+W182 -> 2200 | X9: =+X182 -> 2066 | Y9: =+Y182 -> 2149 | Z9: =+Z182 -> 2424 | AA9: =SUM(W9:Z9) -> 8839 | AC9: =+AC182 -> 2866 | AD9: =+AD182 -> 2564 | AE9: =+AE182 -> 2737 | AF9: =+AF182 -> 2991 | AG9: =SUM(AC9:AF9) -> 11158 | AH9: =+AH182 -> 3135 | AI9: =+AI182 -> 2801 | AJ9: =+AJ182 -> 3069 | AK9: =+AK182 -> 3294 | AL9: =SUM(AH9:AK9) -> 12299 | AM9: =+AM182 -> 3513 | AN9: =+AN182 -> 3241 | AO9: =+AO182 -> 3254 | AP9: =+AP182 -> 3732 | AQ9: =SUM(AM9:AP9) -> 13740 | AR9: =+AR182 -> 3799 | AS9: =+AS182 -> 3547 | AT9: =+AT182 -> 3683 | AU9: =+AU182 -> 3735 | AV9: =SUM(AR9:AU9) -> 14764 | AW9: =+AW182 -> 4031 | AX9: =+AX182 -> 3650 | AY9: =+AY182 -> 3782 | AZ9: =+AZ182 -> 3753 | BA9: =SUM(AW9:AZ9) -> 15216 | BB9: =+BB182 -> 3924 | BC9: =+BC182 -> 3485 | BD9: =+BD182 -> 3571 | BE9: =+BE182 -> 3875 | BF9: =SUM(BB9:BE9) -> 14855 | BG9: =+BG182 -> 4145 | BH9: =+BH182 -> 3782 | BI9: =+BI182 -> 3810 | BJ9: =+BJ182 -> 4165 | BK9: =SUM(BG9:BJ9) -> 15902 | BL9: =+BL182 -> 4293 | BM9: =+BM182 -> 3982 | BN9: =+BN182 -> 3979 | BO9: =+BO182 -> 2230 | BP9: =SUM(BL9:BO9) -> 14484 | BQ9: =+BQ182 -> 4225 | BR9: =+BR182 -> 4006 | BS9: =+BS182 -> 3564 | BT9: =+BT182 -> 5384 | BU9: =SUM(BQ9:BT9) -> 17179 | BV9: =+BV182 -> 4879 | BW9: =+BW182 -> 4477 | BX9: =+BX182 -> 3882 | BY9: =+BY182 -> 5115 | BZ9: =SUM(BV9:BY9) -> 18353 | CA9: =+CA182 -> 5510 | CB9: =+CB182 -> 5830 | CC9: =+CC182 -> 4913 | CD9: =+CD182 -> 5355 | CE9: =SUM(CA9:CD9) -> 21608 | CF9: =+CF182 -> 5423 | CG9: =+CG182 -> 5625 | CH9: =+CH182 -> 5070 | CI9: =+CI182 -> 5278 | CJ9: =SUM(CF9:CI9) -> 21396 | CK9: =+CK182 -> 4826 | CL9: =+CL182 -> 5179 | CM9: =+CM182 -> 4864 | CN9: =+CN182 -> 4703 | CO9: =SUM(CK9:CN9) -> 19572 | CP9: =+CP182 -> 5020 | CQ9: =+CQ182 -> 5633 | CR9: =+CR182 -> 5026 | CS9: =+CS182 -> 4832 | CT9: =SUM(CP9:CS9) -> 20511 | CU9: =+CU182 -> 5127 | CV9: =+CV182 -> 5050.934 | CW9: =+CW182 -> 4799.0826 | CX9: =+CX182 -> 4509.5029 | CY9: =SUM(CU9:CX9) -> 19486.52 | CZ9: =+CZ182 -> 4775.4098 | DA9: =+DA182 -> 4837.1291 | DB9: =+DB182 -> 4671.5671 | DC9: =+DC182 -> 4389.3339 | DD9: =SUM(CZ9:DC9) -> 18673.44 | DE9: =+DE182 -> 4775.4098 | DF9: =+DF182 -> 4837.1291 | DG9: =+DG182 -> 4671.5671 | DH9: =+DH182 -> 4389.3339 | DI9: =SUM(DE9:DH9) -> 18673.44
A10: =IF(ISBLANK(B10),"Scrap", " ") | B10: EMEA | C10: =+'2. Consolidated'!C10 -> -- | D10: =+'2. Consolidated'!D10 -> -- | E10: =+'2. Consolidated'!E10 -> -- | F10: =+'2. Consolidated'!F10 -> -- | G10: =+'2. Consolidated'!G10 -> -- | H10: =+'2. Consolidated'!H10 -> -- | I10: =+'2. Consolidated'!I10 -> -- | J10: =+'2. Consolidated'!J10 -> -- | ... Q10: =+'2. Consolidated'!Q10 -> 5041.9 | R10: =+R251 -> 1335 | S10: =+S251 -> 1077 | T10: =+T251 -> 1175 | U10: =+U251 -> 1311 | V10: =SUM(R10:U10) -> 4898 | W10: =+W251 -> 1562 | X10: =+X251 -> 1176 | Y10: =+Y251 -> 1237 | Z10: =+Z251 -> 1369 | AA10: =SUM(W10:Z10) -> 5344 | AC10: =+AC251 -> 1503 | AD10: =+AD251 -> 1160 | AE10: =+AE251 -> 1360 | AF10: =+AF251 -> 1399 | AG10: =SUM(AC10:AF10) -> 5422 | AH10: =+AH251 -> 1667 | AI10: =+AI251 -> 1369 | AJ10: =+AJ251 -> 1648 | AK10: =+AK251 -> 1682 | AL10: =SUM(AH10:AK10) -> 6366 | AM10: =+AM251 -> 2106 | AN10: =+AN251 -> 1658 | AO10: =+AO251 -> 1735 | AP10: =+AP251 -> 1627 | AQ10: =SUM(AM10:AP10) -> 7126 | AR10: =+AR251 -> 2104 | AS10: =+AS251 -> 1707 | AT10: =+AT251 -> 1853 | AU10: =+AU251 -> 1904 | AV10: =SUM(AR10:AU10) -> 7568 | AW10: =+AW251 -> 2262 | AX10: =+AX251 -> 1792 | AY10: =+AY251 -> 1925 | AZ10: =+AZ251 -> 1991 | BA10: =SUM(AW10:AZ10) -> 7970 | BB10: =+BB251 -> 2344 | BC10: =+BC251 -> 2133 | BD10: =+BD251 -> 2299 | BE10: =+BE251 -> 2466 | BF10: =SUM(BB10:BE10) -> 9242 | BG10: =+BG251 -> 2607 | BH10: =+BH251 -> 2313 | BI10: =+BI251 -> 2435 | BJ10: =+BJ251 -> 2457 | BK10: =SUM(BG10:BJ10) -> 9812 | BL10: =+BL251 -> 2773 | BM10: =+BM251 -> 2537 | BN10: =+BN251 -> 2709 | BO10: =+BO251 -> 1328 | BP10: =SUM(BL10:BO10) -> 9347 | BQ10: =+BQ251 -> 2910 | BR10: =+BR251 -> 2958 | BS10: =+BS251 -> 2609 | BT10: =+BT251 -> 2979 | BU10: =SUM(BQ10:BT10) -> 11456 | BV10: =+BV251 -> 3307 | BW10: =+BW251 -> 3142 | BX10: =+BX251 -> 2779 | BY10: =+BY251 -> 3251 | BZ10: =SUM(BV10:BY10) -> 12479 | CA10: =+CA251 -> 3333 | CB10: =+CB251 -> 3489 | CC10: =+CC251 -> 3246 | CD10: =+CD251 -> 3350 | CE10: =SUM(CA10:CD10) -> 13418 | CF10: =+CF251 -> 3610 | CG10: =+CG251 -> 3567 | CH10: =+CH251 -> 3138 | CI10: =+CI251 -> 3292 | CJ10: =SUM(CF10:CI10) -> 13607 | CK10: =+CK251 -> 3143 | CL10: =+CL251 -> 3303 | CM10: =+CM251 -> 2811 | CN10: =+CN251 -> 3000 | CO10: =SUM(CK10:CN10) -> 12257 | CP10: =+CP251 -> 3331 | CQ10: =+CQ251 -> 3392 | CR10: =+CR251 -> 2874 | CS10: =+CS251 -> 2975 | CT10: =SUM(CP10:CS10) -> 12572 | CU10: =+CU251 -> 3176 | CV10: =+CV251 -> 2888.6764 | CW10: =+CW251 -> 2687.4199 | CX10: =+CX251 -> 2732.7586 | CY10: =SUM(CU10:CX10) -> 11484.855 | CZ10: =+CZ251 -> 2958.4672 | DA10: =+DA251 -> 2795.5104 | DB10: =+DB251 -> 2616.9429 | DC10: =+DC251 -> 2661.4653 | DD10: =SUM(CZ10:DC10) -> 11032.386 | DE10: =+DE251 -> 2958.4672 | DF10: =+DF251 -> 2795.5104 | DG10: =+DG251 -> 2643.1124 | DH10: =+DH251 -> 2688.0799 | DI10: =SUM(DE10:DH10) -> 11085.17
A11: =IF(ISBLANK(B11),"Scrap", " ") | B11: GC | C11: =+'2. Consolidated'!C11 -> -- | D11: =+'2. Consolidated'!D11 -> -- | E11: =+'2. Consolidated'!E11 -> -- | F11: =+'2. Consolidated'!F11 -> -- | G11: =+'2. Consolidated'!G11 -> -- | H11: =+'2. Consolidated'!H11 -> -- | I11: =+'2. Consolidated'!I11 -> -- | J11: =+'2. Consolidated'!J11 -> -- | ... Q11: =+'2. Consolidated'!Q11 -> 1741.8 | R11: =+R320 -> 460 | S11: =+S320 -> 482 | T11: =+T320 -> 554 | U11: =+U320 -> 564 | V11: =SUM(R11:U11) -> 2060 | W11: =+W320 -> 528 | X11: =+X320 -> 650 | Y11: =+Y320 -> 694 | Z11: =+Z320 -> 667 | AA11: =SUM(W11:Z11) -> 2539 | AC11: =+AC320 -> 577 | AD11: =+AD320 -> 582 | AE11: =+AE320 -> 641 | AF11: =+AF320 -> 678 | AG11: =SUM(AC11:AF11) -> 2478 | AH11: =+AH320 -> 574 | AI11: =+AI320 -> 629 | AJ11: =+AJ320 -> 697 | AK11: =+AK320 -> 702 | AL11: =SUM(AH11:AK11) -> 2602 | AM11: =+AM320 -> 679 | AN11: =+AN320 -> 758 | AO11: =+AO320 -> 801 | AP11: =+AP320 -> 829 | AQ11: =SUM(AM11:AP11) -> 3067 | AR11: =+AR320 -> 886 | AS11: =+AS320 -> 938 | AT11: =+AT320 -> 982 | AU11: =+AU320 -> 979 | AV11: =SUM(AR11:AU11) -> 3785 | AW11: =+AW320 -> 1020 | AX11: =+AX320 -> 1055 | AY11: =+AY320 -> 1075 | AZ11: =+AZ320 -> 1087 | BA11: =SUM(AW11:AZ11) -> 4237 | BB11: =+BB320 -> 1108 | BC11: =+BC320 -> 1222 | BD11: =+BD320 -> 1336 | BE11: =+BE320 -> 1468 | BF11: =SUM(BB11:BE11) -> 5134 | BG11: =+BG320 -> 1379 | BH11: =+BH320 -> 1544 | BI11: =+BI320 -> 1588 | BJ11: =+BJ320 -> 1697 | BK11: =SUM(BG11:BJ11) -> 6208 | BL11: =+BL320 -> 1679 | BM11: =+BM320 -> 1847 | BN11: =+BN320 -> 1506 | BO11: =+BO320 -> 1647 | BP11: =SUM(BL11:BO11) -> 6679 | BQ11: =+BQ320 -> 1780 | BR11: =+BR320 -> 2298 | BS11: =+BS320 -> 2279 | BT11: =+BT320 -> 1933 | BU11: =SUM(BQ11:BT11) -> 8290 | BV11: =+BV320 -> 1982 | BW11: =+BW320 -> 1844 | BX11: =+BX320 -> 2160 | BY11: =+BY320 -> 1561 | BZ11: =SUM(BV11:BY11) -> 7547 | CA11: =+CA320 -> 1656 | CB11: =+CB320 -> 1788 | CC11: =+CC320 -> 1994 | CD11: =+CD320 -> 1810 | CE11: =SUM(CA11:CD11) -> 7248 | CF11: =+CF320 -> 1735 | CG11: =+CG320 -> 1863 | CH11: =+CH320 -> 2084 | CI11: =+CI320 -> 1863 | CJ11: =SUM(CF11:CI11) -> 7545 | CK11: =+CK320 -> 1666 | CL11: =+CL320 -> 1711 | CM11: =+CM320 -> 1733 | CN11: =+CN320 -> 1476 | CO11: =SUM(CK11:CN11) -> 6586 | CP11: =+CP320 -> 1512 | CQ11: =+CQ320 -> 1423 | CR11: =+CR320 -> 1615 | CS11: =+CS320 -> 1297 | CT11: =SUM(CP11:CS11) -> 5847 | CU11: =+CU320 -> 1180 | CV11: =+CV320 -> 1077.7956 | CW11: =+CW320 -> 1150.708 | CX11: =+CX320 -> 907.55669 | CY11: =SUM(CU11:CX11) -> 4316.0603 | CZ11: =+CZ320 -> 892.965 | DA11: =+DA320 -> 862.2365 | DB11: =+DB320 -> 1058.6514 | DC11: =+DC320 -> 834.95215 | DD11: =SUM(CZ11:DC11) -> 3648.805 | DE11: =+DE320 -> 866.70577 | DF11: =+DF320 -> 845.16366 | DG11: =+DG320 -> 1069.0332 | DH11: =+DH320 -> 843.13964 | DI11: =SUM(DE11:DH11) -> 3624.0423
A12: =IF(ISBLANK(B12),"Scrap", " ") | B12: APLA | C12: =+'2. Consolidated'!C12 -> -- | D12: =+'2. Consolidated'!D12 -> -- | E12: =+'2. Consolidated'!E12 -> -- | F12: =+'2. Consolidated'!F12 -> -- | G12: =+'2. Consolidated'!G12 -> -- | H12: =+'2. Consolidated'!H12 -> -- | I12: =+'2. Consolidated'!I12 -> -- | J12: =+'2. Consolidated'!J12 -> -- | ... Q12: =+'2. Consolidated'!Q12 -> 2923.6 | R12: =+R389 -> 754 | S12: =+S389 -> 947 | T12: =+T389 -> 838 | U12: =+U389 -> 963 | V12: =SUM(R12:U12) -> 3502 | W12: =+W389 -> 990 | X12: =+X389 -> 1145 | Y12: =+Y389 -> 994 | Z12: =+Z389 -> 1110 | AA12: =SUM(W12:Z12) -> 4239 | AC12: =+AC389 -> 1094 | AD12: =+AD389 -> 1314 | AE12: =+AE389 -> 1062 | AF12: =+AF389 -> 1238 | AG12: =SUM(AC12:AF12) -> 4708 | AH12: =+AH389 -> 1060 | AI12: =+AI389 -> 1240 | AJ12: =+AJ389 -> 1114 | AK12: =+AK389 -> 1306 | AL12: =SUM(AH12:AK12) -> 4720 | AM12: =+AM389 -> 1094 | AN12: =+AN389 -> 1274 | AO12: =+AO389 -> 1121 | AP12: =+AP389 -> 1164 | AQ12: =SUM(AM12:AP12) -> 4653 | AR12: =+AR389 -> 1083 | AS12: =+AS389 -> 1107 | AT12: =+AT389 -> 1032 | AU12: =+AU389 -> 1095 | AV12: =SUM(AR12:AU12) -> 4317 | AW12: =+AW389 -> 1131 | AX12: =+AX389 -> 1206 | AY12: =+AY389 -> 1122 | AZ12: =+AZ389 -> 1278 | BA12: =SUM(AW12:AZ12) -> 4737 | BB12: =+BB389 -> 1189 | BC12: =+BC389 -> 1273 | BD12: =+BD389 -> 1268 | BE12: =+BE389 -> 1436 | BF12: =SUM(BB12:BE12) -> 5166 | BG12: =+BG389 -> 1270 | BH12: =+BH389 -> 1298 | BI12: =+BI389 -> 1307 | BJ12: =+BJ389 -> 1379 | BK12: =SUM(BG12:BJ12) -> 5254 | BL12: =+BL389 -> 1345 | BM12: =+BM389 -> 1468 | BN12: =+BN389 -> 1414 | BO12: =+BO389 -> 801 | BP12: =SUM(BL12:BO12) -> 5028 | BQ12: =+BQ389 -> 1099 | BR12: =+BR389 -> 1471 | BS12: =+BS389 -> 1315 | BT12: =+BT389 -> 1458 | BU12: =SUM(BQ12:BT12) -> 5343 | BV12: =+BV389 -> 1465 | BW12: =+BW389 -> 1347 | BX12: =+BX389 -> 1461 | BY12: =+BY389 -> 1682 | BZ12: =SUM(BV12:BY12) -> 5955 | CA12: =+CA389 -> 1535 | CB12: =+CB389 -> 1599 | CC12: =+CC389 -> 1601 | CD12: =+CD389 -> 1696 | CE12: =SUM(CA12:CD12) -> 6431 | CF12: =+CF389 -> 1572 | CG12: =+CG389 -> 1805 | CH12: =+CH389 -> 1647 | CI12: =+CI389 -> 1705 | CJ12: =SUM(CF12:CI12) -> 6729 | CK12: =+CK389 -> 1462 | CL12: =+CL389 -> 1744 | CM12: =+CM389 -> 1470 | CN12: =+CN389 -> 1575 | CO12: =SUM(CK12:CN12) -> 6251 | CP12: =+CP389 -> 1490 | CQ12: =+CQ389 -> 1667 | CR12: =+CR389 -> 1490 | CS12: =+CS389 -> 1596 | CT12: =SUM(CP12:CS12) -> 6243 | CU12: =+CU389 -> 1463 | CV12: =+CV389 -> 1626.6919 | CW12: =+CW389 -> 1450.5727 | CX12: =+CX389 -> 1512.3252 | CY12: =SUM(CU12:CX12) -> 6052.5898 | CZ12: =+CZ389 -> 1445.5408 | DA12: =+DA389 -> 1642.3831 | DB12: =+DB389 -> 1464.5096 | DC12: =+DC389 -> 1526.8446 | DD12: =SUM(CZ12:DC12) -> 6079.2782 | DE12: =+DE389 -> 1477.6216 | DF12: =+DF389 -> 1679.1591 | DG12: =+DG389 -> 1497.0047 | DH12: =+DH389 -> 1560.8238 | DI12: =SUM(DE12:DH12) -> 6214.6093
A13: =IF(ISBLANK(B13),"Scrap", " ") | B13: Global Brand | C13: =+'2. Consolidated'!C13 -> -- | D13: =+'2. Consolidated'!D13 -> -- | E13: =+'2. Consolidated'!E13 -> -- | F13: =+'2. Consolidated'!F13 -> -- | G13: =+'2. Consolidated'!G13 -> -- | H13: =+'2. Consolidated'!H13 -> -- | I13: =+'2. Consolidated'!I13 -> -- | J13: =+'2. Consolidated'!J13 -> -- | ... Q13: =+'2. Consolidated'!Q13 -> 105.3 | R13: =+R458 -> 31 | S13: =+S458 -> 24 | T13: =+T458 -> 22 | U13: =+U458 -> 29 | V13: =SUM(R13:U13) -> 106 | W13: =+W458 -> 33 | X13: =+X458 -> 25 | Y13: =+Y458 -> 27 | Z13: =+Z458 -> 26 | AA13: =SUM(W13:Z13) -> 111 | AC13: =+AC458 -> 27 | AD13: =+AD458 -> 28 | AE13: =+AE458 -> 29 | AF13: =+AF458 -> 31 | AG13: =SUM(AC13:AF13) -> 115 | AH13: =+AH458 -> 32 | AI13: =+AI458 -> 31 | AJ13: =+AJ458 -> 26 | AK13: =+AK458 -> 36 | AL13: =SUM(AH13:AK13) -> 125 | AM13: =+AM458 -> 29 | AN13: =+AN458 -> 28 | AO13: =+AO458 -> 28 | AP13: =+AP458 -> 30 | AQ13: =SUM(AM13:AP13) -> 115 | AR13: =+AR458 -> 26 | AS13: =+AS458 -> 18 | AT13: =+AT458 -> 17 | AU13: =+AU458 -> 12 | AV13: =SUM(AR13:AU13) -> 73 | AW13: =+AW458 -> 15 | AX13: =+AX458 -> 21 | AY13: =+AY458 -> 19 | AZ13: =+AZ458 -> 18 | BA13: =SUM(AW13:AZ13) -> 73 | BB13: =+BB458 -> 20 | BC13: =+BC458 -> 23 | BD13: =+BD458 -> 21 | BE13: =+BE458 -> 24 | BF13: =SUM(BB13:BE13) -> 88 | BG13: =+BG458 -> 16 | BH13: =+BH458 -> 9 | BI13: =+BI458 -> 8 | BJ13: =+BJ458 -> 9 | BK13: =SUM(BG13:BJ13) -> 42 | BL13: =+BL458 -> 6 | BM13: =+BM458 -> 10 | BN13: =+BN458 -> 8 | BO13: =+BO458 -> 6 | BP13: =SUM(BL13:BO13) -> 30 | BQ13: =+BQ458 -> 4 | BR13: =+BR458 -> 8 | BS13: =+BS458 -> 6 | BT13: =+BT458 -> 7 | BU13: =SUM(BQ13:BT13) -> 25 | BV13: =+BV458 -> 7 | BW13: =+BW458 -> 6 | BX13: =+BX458 -> 41 | BY13: =+BY458 -> 48 | BZ13: =SUM(BV13:BY13) -> 102 | CA13: =+CA458 -> 14 | CB13: =+CB458 -> 18 | CC13: =+CC458 -> 12 | CD13: =+CD458 -> 14 | CE13: =SUM(CA13:CD13) -> 58 | CF13: =+CF458 -> 13 | CG13: =+CG458 -> 12 | CH13: =+CH458 -> 9 | CI13: =+CI458 -> 11 | CJ13: =SUM(CF13:CI13) -> 45 | CK13: =+CK458 -> 14 | CL13: =+CL458 -> 13 | CM13: =+CM458 -> 12 | CN13: =+CN458 -> 9 | CO13: =SUM(CK13:CN13) -> 48 | CP13: =+CP458 -> 9 | CQ13: =+CQ458 -> 9 | CR13: =+CR458 -> 7 | CS13: =+CS458 -> 24 | CT13: =SUM(CP13:CS13) -> 49 | CU13: =+CU458 -> 6 | CV13: =+CV458 -> 9 | CW13: =+CW458 -> 7 | CX13: =+CX458 -> 24 | CY13: =SUM(CU13:CX13) -> 46 | CZ13: =+CZ458 -> 6 | DA13: =+DA458 -> 9 | DB13: =+DB458 -> 7 | DC13: =+DC458 -> 24 | DD13: =SUM(CZ13:DC13) -> 46 | DE13: =+DE458 -> 6 | DF13: =+DF458 -> 9 | DG13: =+DG458 -> 7 | DH13: =+DH458 -> 24 | DI13: =SUM(DE13:DH13) -> 46
A14: =IF(ISBLANK(B14),"Scrap", " ") | B14: Total Nike Brand | C14: =+'2. Consolidated'!C14 -> -- | D14: =+'2. Consolidated'!D14 -> -- | E14: =+'2. Consolidated'!E14 -> -- | F14: =+'2. Consolidated'!F14 -> -- | G14: =+'2. Consolidated'!G14 -> -- | H14: =+'2. Consolidated'!H14 -> -- | I14: =+'2. Consolidated'!I14 -> -- | J14: =+'2. Consolidated'!J14 -> -- | ... Q14: =+'2. Consolidated'!Q14 -> 16508.6 | R14: =SUM(R9:R13) -> 4483 | S14: =SUM(S9:S13) -> 4231 | T14: =SUM(T9:T13) -> 4425 | U14: =SUM(U9:U13) -> 5006 | V14: =SUM(R14:U14) -> 18145 | W14: =SUM(W9:W13) -> 5313 | X14: =SUM(X9:X13) -> 5062 | Y14: =SUM(Y9:Y13) -> 5101 | Z14: =SUM(Z9:Z13) -> 5596 | AA14: =SUM(W14:Z14) -> 21072 | AC14: =SUM(AC9:AC13) -> 6067 | AD14: =SUM(AD9:AD13) -> 5648 | AE14: =SUM(AE9:AE13) -> 5829 | AF14: =SUM(AF9:AF13) -> 6337 | AG14: =SUM(AC14:AF14) -> 23881 | AH14: =SUM(AH9:AH13) -> 6468 | AI14: =SUM(AI9:AI13) -> 6070 | AJ14: =SUM(AJ9:AJ13) -> 6554 | AK14: =SUM(AK9:AK13) -> 7020 | AL14: =SUM(AH14:AK14) -> 26112 | AM14: =SUM(AM9:AM13) -> 7421 | AN14: =SUM(AN9:AN13) -> 6959 | AO14: =SUM(AO9:AO13) -> 6939 | AP14: =SUM(AP9:AP13) -> 7382 | AQ14: =SUM(AM14:AP14) -> 28701 | AR14: =SUM(AR9:AR13) -> 7898 | AS14: =SUM(AS9:AS13) -> 7317 | AT14: =SUM(AT9:AT13) -> 7567 | AU14: =SUM(AU9:AU13) -> 7725 | AV14: =SUM(AR14:AU14) -> 30507 | AW14: =SUM(AW9:AW13) -> 8459 | AX14: =SUM(AX9:AX13) -> 7724 | AY14: =SUM(AY9:AY13) -> 7923 | AZ14: =SUM(AZ9:AZ13) -> 8127 | BA14: =SUM(AW14:AZ14) -> 32233 | BB14: =SUM(BB9:BB13) -> 8585 | BC14: =SUM(BC9:BC13) -> 8136 | BD14: =SUM(BD9:BD13) -> 8495 | BE14: =SUM(BE9:BE13) -> 9269 | BF14: =SUM(BB14:BE14) -> 34485 | BG14: =SUM(BG9:BG13) -> 9417 | BH14: =SUM(BH9:BH13) -> 8946 | BI14: =SUM(BI9:BI13) -> 9148 | BJ14: =SUM(BJ9:BJ13) -> 9707 | BK14: =SUM(BG14:BJ14) -> 37218 | BL14: =SUM(BL9:BL13) -> 10096 | BM14: =SUM(BM9:BM13) -> 9844 | BN14: =SUM(BN9:BN13) -> 9616 | BO14: =SUM(BO9:BO13) -> 6012 | BP14: =SUM(BL14:BO14) -> 35568 | BQ14: =SUM(BQ9:BQ13) -> 10018 | BR14: =SUM(BR9:BR13) -> 10741 | BS14: =SUM(BS9:BS13) -> 9773 | BT14: =SUM(BT9:BT13) -> 11761 | BU14: =SUM(BQ14:BT14) -> 42293 | BV14: =SUM(BV9:BV13) -> 11640 | BW14: =SUM(BW9:BW13) -> 10816 | BX14: =SUM(BX9:BX13) -> 10323 | BY14: =SUM(BY9:BY13) -> 11657 | BZ14: =SUM(BV14:BY14) -> 44436 | CA14: =SUM(CA9:CA13) -> 12048 | CB14: =SUM(CB9:CB13) -> 12724 | CC14: =SUM(CC9:CC13) -> 11766 | CD14: =SUM(CD9:CD13) -> 12225 | CE14: =SUM(CA14:CD14) -> 48763 | CF14: =SUM(CF9:CF13) -> 12353 | CG14: =SUM(CG9:CG13) -> 12872 | CH14: =SUM(CH9:CH13) -> 11948 | CI14: =SUM(CI9:CI13) -> 12149 | CJ14: =SUM(CF14:CI14) -> 49322 | CK14: =SUM(CK9:CK13) -> 11111 | CL14: =SUM(CL9:CL13) -> 11950 | CM14: =SUM(CM9:CM13) -> 10890 | CN14: =SUM(CN9:CN13) -> 10763 | CO14: =SUM(CK14:CN14) -> 44714 | CP14: =SUM(CP9:CP13) -> 11362 | CQ14: =SUM(CQ9:CQ13) -> 12124 | CR14: =SUM(CR9:CR13) -> 11012 | CS14: =SUM(CS9:CS13) -> 10724 | CT14: =SUM(CP14:CS14) -> 45222 | CU14: =SUM(CU9:CU13) -> 10952 | CV14: =SUM(CV9:CV13) -> 10653.098 | CW14: =SUM(CW9:CW13) -> 10094.783 | CX14: =SUM(CX9:CX13) -> 9686.1434 | CY14: =SUM(CU14:CX14) -> 41386.025 | CZ14: =SUM(CZ9:CZ13) -> 10078.383 | DA14: =SUM(DA9:DA13) -> 10146.259 | DB14: =SUM(DB9:DB13) -> 9818.6711 | DC14: =SUM(DC9:DC13) -> 9436.596 | DD14: =SUM(CZ14:DC14) -> 39479.909 | DE14: =SUM(DE9:DE13) -> 10084.204 | DF14: =SUM(DF9:DF13) -> 10165.962 | DG14: =SUM(DG9:DG13) -> 9887.7175 | DH14: =SUM(DH9:DH13) -> 9505.3773 | DI14: =SUM(DE14:DH14) -> 39643.261
A15: =IF(ISBLANK(B15),"Scrap", " ") | B15: % chg. Y/Y | C15: -- | D15: -- | E15: -- | F15: -- | G15: -- | H15: -- | I15: -- | J15: -- | K15: -- | L15: -- | M15: -- | N15: -- | O15: -- | P15: -- | Q15: -- | R15: -- | S15: -- | T15: -- | U15: -- | V15: -- | W15: =+W14/R14-1 -> 0.18514388 | X15: =+X14/S14-1 -> 0.19640747 | Y15: =+Y14/T14-1 -> 0.15276836 | Z15: =+Z14/U14-1 -> 0.11785857 | AA15: =+AA14/V14-1 -> 0.16131166 | AC15: =+AC14/W14-1 -> 0.14191605 | AD15: =+AD14/X14-1 -> 0.11576452 | AE15: =+AE14/Y14-1 -> 0.14271711 | AF15: =+AF14/Z14-1 -> 0.13241601 | AG15: =+AG14/AA14-1 -> 0.13330486 | AH15: =+AH14/AC14-1 -> 0.066095269 | AI15: =+AI14/AD14-1 -> 0.074716714 | AJ15: =+AJ14/AE14-1 -> 0.12437811 | AK15: =+AK14/AF14-1 -> 0.10777971 | AL15: =+AL14/AG14-1 -> 0.093421549 | AM15: =+AM14/AH14-1 -> 0.14734075 | AN15: =+AN14/AI14-1 -> 0.14645799 | AO15: =+AO14/AJ14-1 -> 0.058742753 | ... DI15: =+DI14/DD14-1 -> 0.0041376084
A16: =IF(ISBLANK(B16),"Scrap", " ") | B16: % chg Y/Y, FX neutral | C16: -- | D16: -- | E16: -- | F16: -- | G16: -- | H16: -- | I16: -- | J16: -- | K16: -- | L16: -- | M16: -- | N16: -- | O16: -- | P16: -- | Q16: -- | R16: -- | S16: -- | T16: -- | U16: -- | V16: -- | W16: -- | X16: -- | Y16: -- | Z16: -- | AA16: -- | AC16: -- | AD16: -- | AE16: -- | AF16: -- | AG16: -- | AH16: -- | AI16: -- | AJ16: -- | AK16: -- | AL16: -- | AM16: -- | AN16: -- | AO16: -- | AP16: -- | AQ16: 0.14 | AR16: 0.15 | AS16: 0.13 | AT16: 0.15 | AU16: 0.09 | AV16: 0.13 | AW16: 0.1 | AX16: 0.081200177 | AY16: 0.07 | AZ16: 0.07 | BA16: 0.08 | BB16: 0.02 | BC16: 0.04 | BD16: 0.04 | BE16: 0.09 | BF16: =(BA182*BF184+BA251*BF253+BA320*BF322+BA389*BF391+BA458*BF459)/BA14 -> 0.047904942 | BG16: 0.1 | BH16: 0.14 | BI16: 0.12 | BJ16: 0.1 | BK16: =(BF182*BK184+BF251*BK253+BF320*BK322+BF389*BK391+BF458*BK459)/BF14 -> 0.11537335 | BL16: 0.1 | BM16: 0.12 | BN16: 0.06 | BO16: -0.36 | BP16: =(BK182*BP184+BK251*BP253+BK320*BP322+BK389*BP391+BK458*BP459)/BK14 -> -0.022481864 | BQ16: 0 | BR16: 0.08 | BS16: -0.02 | BT16: 0.88 | BU16: =(BP182*BU184+BP251*BU253+BP320*BU322+BP389*BU391+BP458*BU459)/BP14 -> 0.16847672 | BV16: 0.12 | BW16: 0 | BX16: 0.08 | BY16: 0.03 | BZ16: =(BU182*BZ184+BU251*BZ253+BU320*BZ322+BU389*BZ391+BU458*BZ459)/BU14 -> 0.055277233 | CA16: 0.1 | CB16: 0.28 | CC16: 0.19 | CD16: 0.08 | CE16: =(BZ182*CE184+BZ251*CE253+BZ320*CE322+BZ389*CE391+BZ458*CE459)/BZ14 -> 0.15997097 | CF16: 0.03 | CG16: 0 | CH16: 0.02 | CI16: 0.01 | CJ16: =(CE182*CJ184+CE251*CJ253+CE320*CJ322+CE389*CJ391+CE458*CJ459)/CE14 -> 0.015908373 | CK16: -0.09 | CL16: -0.08 | CM16: -0.06 | CN16: -0.11 | CO16: =(CJ182*CO184+CJ251*CO253+CJ320*CO322+CJ389*CO391+CJ458*CO459)/CJ14 -> -0.086392279 | CP16: 0 | CQ16: 0.01 | CR16: -0.02 | CS16: -0.03 | CT16: =(CO182*CT184+CO251*CT253+CO320*CT322+CO389*CT391+CO458*CT459)/CO14 -> -0.0088580758 | CU16: -0.04 | CV16: =(CQ182*CV184+CQ251*CV253+CQ320*CV322+CQ389*CV391+CQ458*CV459)/CQ14 -> -0.1212067 | CW16: =(CR182*CW184+CR251*CW253+CR320*CW322+CR389*CW391+CR458*CW459)/CR14 -> -0.078757719 | CX16: =(CS182*CX184+CS251*CX253+CS320*CX322+CS389*CX391+CS458*CX459)/CS14 -> -0.090897986 | CY16: =(CT182*CY184+CT251*CY253+CT320*CY322+CT389*CY391+CT458*CY459)/CT14 -> -0.083451639 | CZ16: =(CU182*CZ184+CU251*CZ253+CU320*CZ322+CU389*CZ391+CU458*CZ459)/CU14 -> -0.077510044 | DA16: =(CV182*DA184+CV251*DA253+CV320*DA322+CV389*DA391+CV458*DA459)/CV14 -> -0.047576654 | DB16: =(CW182*DB184+CW251*DB253+CW320*DB322+CW389*DB391+CW458*DB459)/CW14 -> -0.027351963 | DC16: =(CX182*DC184+CX251*DC253+CX320*DC322+CX389*DC391+CX458*DC459)/CX14 -> -0.025763335 | ... DI16: =(DD182*DI184+DD251*DI253+DD320*DI322+DD389*DI391+DD458*DI459)/DD14 -> 0.0041376084
A17: =IF(ISBLANK(B17),"Scrap", " ") | B17: % FX impact | C17: -- | D17: -- | E17: -- | F17: -- | G17: -- | H17: -- | I17: -- | J17: -- | K17: -- | L17: -- | M17: -- | N17: -- | O17: -- | P17: -- | Q17: -- | R17: -- | S17: -- | T17: -- | U17: -- | V17: -- | W17: -- | X17: -- | Y17: -- | Z17: -- | AA17: -- | AC17: -- | AD17: -- | AE17: -- | AF17: -- | AG17: -- | AH17: -- | AI17: -- | AJ17: -- | AK17: -- | AL17: -- | AM17: -- | AN17: -- | AO17: -- | AP17: -- | AQ17: =(1+AQ15)/(1+AQ16)-1 -> -0.035833495 | AR17: =(1+AR15)/(1+AR16)-1 -> -0.074541694 | AS17: =(1+AS15)/(1+AS16)-1 -> -0.069518431 | AT17: =(1+AT15)/(1+AT16)-1 -> -0.051736561 | AU17: =(1+AU15)/(1+AU16)-1 -> -0.039940942 | AV17: =(1+AV15)/(1+AV16)-1 -> -0.059358729 | AW17: =(1+AW15)/(1+AW16)-1 -> -0.026335781 | AX17: =(1+AX15)/(1+AX16)-1 -> -0.023655459 | ... DI17: =(1+DI15)/(1+DI16)-1 -> 0
A18: =IF(ISBLANK(B18),"Scrap", " ") | B18: Converse | C18: =+'2. Consolidated'!C15 -> -- | D18: =+'2. Consolidated'!D15 -> -- | E18: =+'2. Consolidated'!E15 -> -- | F18: =+'2. Consolidated'!F15 -> -- | G18: =+'2. Consolidated'!G15 -> -- | H18: =+'2. Consolidated'!H15 -> -- | I18: =+'2. Consolidated'!I15 -> -- | J18: =+'2. Consolidated'!J15 -> -- | ... Q18: =+'2. Consolidated'!Q15 -> 2529.5 | R18: =R483 -> 694 | S18: =S483 -> 639 | T18: =T483 -> 680 | U18: =U483 -> 773 | V18: =SUM(R18:U18) -> 2786 | W18: =W483 -> 773 | X18: =X483 -> 673 | Y18: =Y483 -> 753 | Z18: =Z483 -> 896 | AA18: =SUM(W18:Z18) -> 3095 | AC18: =AC483 -> 418 | AD18: =AD483 -> 316 | AE18: =AE483 -> 361 | AF18: =AF483 -> 354 | AG18: =SUM(AC18:AF18) -> 1449 | AH18: =AH483 -> 494 | AI18: =AI483 -> 360 | AJ18: =AJ483 -> 420 | AK18: =AK483 -> 410 | AL18: =SUM(AH18:AK18) -> 1684 | AM18: =AM483 -> 575 | AN18: =AN483 -> 434 | AO18: =AO483 -> 538 | AP18: =AP483 -> 435 | AQ18: =SUM(AM18:AP18) -> 1982 | AR18: =AR483 -> 555 | AS18: =AS483 -> 398 | AT18: =AT483 -> 489 | AU18: =AU483 -> 513 | AV18: =SUM(AR18:AU18) -> 1955 | AW18: =AW483 -> 574 | AX18: =AX483 -> 416 | AY18: =AY483 -> 498 | AZ18: =AZ483 -> 554 | BA18: =SUM(AW18:AZ18) -> 2042 | BB18: =BB483 -> 483 | BC18: =BC483 -> 408 | BD18: =BD483 -> 483 | BE18: =BE483 -> 512 | BF18: =SUM(BB18:BE18) -> 1886 | BG18: =BG483 -> 527 | BH18: =BH483 -> 425 | BI18: =BI483 -> 463 | BJ18: =BJ483 -> 491 | BK18: =SUM(BG18:BJ18) -> 1906 | BL18: =BL483 -> 555 | BM18: =BM483 -> 480 | BN18: =BN483 -> 506 | BO18: =BO483 -> 305 | BP18: =SUM(BL18:BO18) -> 1846 | BQ18: =BQ483 -> 563 | BR18: =BR483 -> 476 | BS18: =BS483 -> 570 | BT18: =BT483 -> 596 | BU18: =SUM(BQ18:BT18) -> 2205 | BV18: =BV483 -> 629 | BW18: =BW483 -> 557 | BX18: =BX483 -> 567 | BY18: =BY483 -> 593 | BZ18: =SUM(BV18:BY18) -> 2346 | CA18: =CA483 -> 643 | CB18: =CB483 -> 586 | CC18: =CC483 -> 612 | CD18: =CD483 -> 586 | CE18: =SUM(CA18:CD18) -> 2427 | CF18: =CF483 -> 588 | CG18: =CG483 -> 519 | CH18: =CH483 -> 495 | CI18: =CI483 -> 480 | CJ18: =SUM(CF18:CI18) -> 2082 | CK18: =CK483 -> 501 | CL18: =CL483 -> 429 | CM18: =CM483 -> 405 | CN18: =CN483 -> 357 | CO18: =SUM(CK18:CN18) -> 1692 | CP18: =CP483 -> 366 | CQ18: =CQ483 -> 300 | CR18: =CR483 -> 264 | CS18: =CS483 -> 244 | CT18: =SUM(CP18:CS18) -> 1174 | CU18: =CU483 -> 263 | CV18: =CV483 -> 225 | CW18: =CW483 -> 211.2 | CX18: =CX483 -> 195.2 | CY18: =SUM(CU18:CX18) -> 894.4 | CZ18: =CZ483 -> 249.85 | DA18: =DA483 -> 213.75 | DB18: =DB483 -> 206.976 | DC18: =DC483 -> 191.296 | DD18: =SUM(CZ18:DC18) -> 861.872 | DE18: =DE483 -> 249.85 | DF18: =DF483 -> 213.75 | DG18: =DG483 -> 206.976 | DH18: =DH483 -> 191.296 | DI18: =SUM(DE18:DH18) -> 861.872
A19: =IF(ISBLANK(B19),"Scrap", " ") | B19: Corporate | C19: =+'2. Consolidated'!C16 -> -- | D19: =+'2. Consolidated'!D16 -> -- | E19: =+'2. Consolidated'!E16 -> -- | F19: =+'2. Consolidated'!F16 -> -- | G19: =+'2. Consolidated'!G16 -> -- | H19: =+'2. Consolidated'!H16 -> -- | I19: =+'2. Consolidated'!I16 -> -- | J19: =+'2. Consolidated'!J16 -> -- | ... Q19: =+'2. Consolidated'!Q16 -> -24.1 | R19: =R563 -> -2 | S19: =S563 -> -28 | T19: =T563 -> -26 | U19: =U563 -> -13 | V19: =SUM(R19:U19) -> -69 | W19: =W563 -> -5 | X19: =X563 -> -4 | Y19: =Y563 -> -8 | Z19: =Z563 -> -22 | AA19: =SUM(W19:Z19) -> -39 | AC19: =AC563 -> -11 | AD19: =AD563 -> -9 | AE19: =AE563 -> -3 | AF19: =AF563 -> 6 | AG19: =SUM(AC19:AF19) -> -17 | AH19: =AH563 -> 9 | AI19: =AI563 -> 1 | AJ19: =AJ563 -> -2 | AK19: =AK563 -> -5 | AL19: =SUM(AH19:AK19) -> 3 | AM19: =AM563 -> -14 | AN19: =AN563 -> -13 | AO19: =AO563 -> -17 | AP19: =AP563 -> -38 | AQ19: =SUM(AM19:AP19) -> -82 | AR19: =AR563 -> -39 | AS19: =AS563 -> -29 | AT19: =AT563 -> -24 | AU19: =AU563 -> 6 | AV19: =SUM(AR19:AU19) -> -86 | AW19: =AW563 -> 28 | AX19: =AX563 -> 40 | AY19: =AY563 -> 11 | AZ19: =AZ563 -> -4 | BA19: =SUM(AW19:AZ19) -> 75 | BB19: =BB563 -> 2 | BC19: =BC563 -> 10 | BD19: =BD563 -> 6 | BE19: =BE563 -> 8 | BF19: =SUM(BB19:BE19) -> 26 | BG19: =BG563 -> 4 | BH19: =BH563 -> 3 | BI19: =BI563 -> 0 | BJ19: =BJ563 -> -14 | BK19: =SUM(BG19:BJ19) -> -7 | BL19: =BL563 -> 9 | BM19: =BM563 -> 2 | BN19: =BN563 -> -18 | BO19: =BO563 -> -4 | BP19: =SUM(BL19:BO19) -> -11 | BQ19: =BQ563 -> 13 | BR19: =BR563 -> 26 | BS19: =BS563 -> 14 | BT19: =BT563 -> -13 | BU19: =SUM(BQ19:BT19) -> 40 | BV19: =BV563 -> -21 | BW19: =BW563 -> -16 | BX19: =BX563 -> -19 | BY19: =BY563 -> -16 | BZ19: =SUM(BV19:BY19) -> -72 | CA19: =CA563 -> -4 | CB19: =CB563 -> 5 | CC19: =CC563 -> 12 | CD19: =CD563 -> 14 | CE19: =SUM(CA19:CD19) -> 27 | CF19: =CF563 -> -2 | CG19: =CG563 -> -3 | CH19: =CH563 -> -14 | CI19: =CI563 -> -23 | CJ19: =SUM(CF19:CI19) -> -42 | CK19: =CK563 -> -23 | CL19: =CL563 -> -25 | CM19: =CM563 -> -26 | CN19: =CN563 -> -23 | CO19: =SUM(CK19:CN19) -> -97 | CP19: =CP563 -> -8 | CQ19: =CQ563 -> 3 | CR19: =CR563 -> 3 | CS19: =CS563 -> 4 | CT19: =SUM(CP19:CS19) -> 2 | CU19: =CU563 -> -2 | CV19: =CV563 -> 0 | CW19: =CW563 -> 0 | CX19: =CX563 -> 0 | CY19: =SUM(CU19:CX19) -> -2 | CZ19: =CZ563 -> 0 | DA19: =DA563 -> 0 | DB19: =DB563 -> 0 | DC19: =DC563 -> 0 | DD19: =SUM(CZ19:DC19) -> 0 | DE19: =DE563 -> 0 | DF19: =DF563 -> 0 | DG19: =DG563 -> 0 | DH19: =DH563 -> 0 | DI19: =SUM(DE19:DH19) -> 0
A20: =IF(ISBLANK(B20),"Scrap", " ") | B20: Total Nike Revenues | C20: =+'2. Consolidated'!C17 -> 6470.625 | D20: =+'2. Consolidated'!D17 -> 9186.539 | E20: =+'2. Consolidated'!E17 -> 9553.1 | F20: =+'2. Consolidated'!F17 -> 8776.9 | G20: =+'2. Consolidated'!G17 -> 8995.1 | H20: =+'2. Consolidated'!H17 -> 9488.8 | I20: =+'2. Consolidated'!I17 -> 9893 | J20: =+'2. Consolidated'!J17 -> 10697 | ... Q20: =+'2. Consolidated'!Q17 -> 19014 | R20: =R18+R19+R14 -> 5175 | S20: =S18+S19+S14 -> 4842 | T20: =T18+T19+T14 -> 5079 | U20: =U18+U19+U14 -> 5766 | V20: =SUM(R20:U20) -> 20862 | W20: =W18+W19+W14 -> 6081 | X20: =X18+X19+X14 -> 5731 | Y20: =Y18+Y19+Y14 -> 5846 | Z20: =Z18+Z19+Z14 -> 6470 | AA20: =SUM(W20:Z20) -> 24128 | AB20: 23331 | AC20: =AC18+AC19+AC14 -> 6474 | AD20: =AD18+AD19+AD14 -> 5955 | AE20: =AE18+AE19+AE14 -> 6187 | AF20: =AF18+AF19+AF14 -> 6697 | AG20: =SUM(AC20:AF20) -> 25313 | AH20: =AH18+AH19+AH14 -> 6971 | AI20: =AI18+AI19+AI14 -> 6431 | AJ20: =AJ18+AJ19+AJ14 -> 6972 | AK20: =AK18+AK19+AK14 -> 7425 | AL20: =SUM(AH20:AK20) -> 27799 | AM20: =AM18+AM19+AM14 -> 7982 | AN20: =AN18+AN19+AN14 -> 7380 | AO20: =AO18+AO19+AO14 -> 7460 | AP20: =AP18+AP19+AP14 -> 7779 | AQ20: =SUM(AM20:AP20) -> 30601 | AR20: =AR18+AR19+AR14 -> 8414 | AS20: =AS18+AS19+AS14 -> 7686 | AT20: =AT18+AT19+AT14 -> 8032 | AU20: =AU18+AU19+AU14 -> 8244 | AV20: =SUM(AR20:AU20) -> 32376 | AW20: =AW18+AW19+AW14 -> 9061 | AX20: =AX18+AX19+AX14 -> 8180 | AY20: =AY18+AY19+AY14 -> 8432 | AZ20: =AZ18+AZ19+AZ14 -> 8677 | BA20: =SUM(AW20:AZ20) -> 34350 | BB20: =BB18+BB19+BB14 -> 9070 | BC20: =BC18+BC19+BC14 -> 8554 | BD20: =BD18+BD19+BD14 -> 8984 | BE20: =BE18+BE19+BE14 -> 9789 | BF20: =SUM(BB20:BE20) -> 36397 | BG20: =BG18+BG19+BG14 -> 9948 | BH20: =BH18+BH19+BH14 -> 9374 | BI20: =BI18+BI19+BI14 -> 9611 | BJ20: =BJ18+BJ19+BJ14 -> 10184 | BK20: =SUM(BG20:BJ20) -> 39117 | BL20: =BL18+BL19+BL14 -> 10660 | BM20: =BM18+BM19+BM14 -> 10326 | BN20: =BN18+BN19+BN14 -> 10104 | BO20: =BO18+BO19+BO14 -> 6313 | BP20: =SUM(BL20:BO20) -> 37403 | BQ20: =BQ18+BQ19+BQ14 -> 10594 | BR20: =BR18+BR19+BR14 -> 11243 | BS20: =BS18+BS19+BS14 -> 10357 | BT20: =BT18+BT19+BT14 -> 12344 | BU20: =SUM(BQ20:BT20) -> 44538 | BV20: =BV18+BV19+BV14 -> 12248 | BW20: =BW18+BW19+BW14 -> 11357 | BX20: =BX18+BX19+BX14 -> 10871 | BY20: =BY18+BY19+BY14 -> 12234 | BZ20: =SUM(BV20:BY20) -> 46710 | CA20: =CA18+CA19+CA14 -> 12687 | CB20: =CB18+CB19+CB14 -> 13315 | CC20: =CC18+CC19+CC14 -> 12390 | CD20: =CD18+CD19+CD14 -> 12825 | CE20: =SUM(CA20:CD20) -> 51217 | CF20: =CF18+CF19+CF14 -> 12939 | CG20: =CG18+CG19+CG14 -> 13388 | CH20: =CH18+CH19+CH14 -> 12429 | CI20: =CI18+CI19+CI14 -> 12606 | CJ20: =SUM(CF20:CI20) -> 51362 | CK20: =CK18+CK19+CK14 -> 11589 | CL20: =CL18+CL19+CL14 -> 12354 | CM20: =CM18+CM19+CM14 -> 11269 | CN20: =CN18+CN19+CN14 -> 11097 | CO20: =SUM(CK20:CN20) -> 46309 | CP20: =CP18+CP19+CP14 -> 11720 | CQ20: =CQ18+CQ19+CQ14 -> 12427 | CR20: =CR18+CR19+CR14 -> 11279 | CS20: =CS18+CS19+CS14 -> 10972 | CT20: =SUM(CP20:CS20) -> 46398 | CU20: =CU18+CU19+CU14 -> 11213 | CV20: =CV18+CV19+CV14 -> 10878.098 | CW20: =CW18+CW19+CW14 -> 10305.983 | CX20: =CX18+CX19+CX14 -> 9881.3434 | CY20: =SUM(CU20:CX20) -> 42278.425 | CZ20: =CZ18+CZ19+CZ14 -> 10328.233 | DA20: =DA18+DA19+DA14 -> 10360.009 | DB20: =DB18+DB19+DB14 -> 10025.647 | DC20: =DC18+DC19+DC14 -> 9627.892 | DD20: =SUM(CZ20:DC20) -> 40341.781 | DE20: =DE18+DE19+DE14 -> 10334.054 | DF20: =DF18+DF19+DF14 -> 10379.712 | DG20: =DG18+DG19+DG14 -> 10094.693 | DH20: =DH18+DH19+DH14 -> 9696.6733 | DI20: =SUM(DE20:DH20) -> 40505.133
A21: =IF(ISBLANK(B21),"Scrap", " ") | B21: % chg. Y/Y | C21: -- | D21: -- | E21: -- | F21: -- | G21: -- | H21: -- | I21: -- | J21: -- | K21: -- | L21: -- | M21: -- | N21: -- | O21: -- | P21: -- | Q21: -- | R21: -- | S21: -- | T21: -- | U21: -- | V21: -- | W21: =+W20/R20-1 -> 0.17507246 | X21: =+X20/S20-1 -> 0.18360182 | Y21: =+Y20/T20-1 -> 0.15101398 | Z21: =+Z20/U20-1 -> 0.12209504 | AA21: =+AA20/V20-1 -> 0.15655258 | AC21: =+AC20/W20-1 -> 0.064627528 | AD21: =+AD20/X20-1 -> 0.039085674 | AE21: =+AE20/Y20-1 -> 0.058330482 | AF21: =+AF20/Z20-1 -> 0.035085008 | AG21: =+AG20/AA20-1 -> 0.049113064 | AH21: =+AH20/AC20-1 -> 0.076768613 | AI21: =+AI20/AD20-1 -> 0.07993283 | AJ21: =+AJ20/AE20-1 -> 0.12687894 | AK21: =+AK20/AF20-1 -> 0.10870539 | AL21: =+AL20/AG20-1 -> 0.098210406 | AM21: =+AM20/AH20-1 -> 0.14502941 | AN21: =+AN20/AI20-1 -> 0.14756647 | AO21: =+AO20/AJ20-1 -> 0.069994263 | ... DI21: =+DI20/DD20-1 -> 0.0040492115
A22: =IF(ISBLANK(B22),"Scrap", " ") | B22: % chg Y/Y, FX neutral (disclosed) | AM22: 0.15 | AN22: 0.18 | AO22: 0.13 | AP22: 0.13 | AQ22: =SUMPRODUCT(AM22:AP22,AH20:AK20)/AL20 -> 0.14658225 | AR22: 0.14 | AS22: 0.12 | AT22: 0.14 | AU22: 0.09 | AV22: =SUMPRODUCT(AR22:AU22,AM20:AP20)/AQ20 -> 0.12246626 | AW22: 0.1 | AX22: 0.08 | AY22: 0.07 | AZ22: 0.07 | BA22: =SUMPRODUCT(AW22:AZ22,AR20:AU20)/AV20 -> 0.080170497 | BB22: 0 | BC22: 0.03 | BD22: 0.03 | BE22: 0.08 | BF22: =SUMPRODUCT(BB22:BE22,AW20:AZ20)/BA20 -> 0.034716739 | BG22: 0.09 | BH22: 0.14 | BI22: 0.11 | BJ22: 0.1 | BK22: =SUMPRODUCT(BG22:BJ22,BB20:BE20)/BF20 -> 0.10937715 | BL22: 0.1 | BM22: 0.13 | BN22: 0.07 | BO22: -0.36 | BP22: =SUMPRODUCT(BL22:BO22,BG20:BJ20)/BK20 -> -0.019941458 | BQ22: 0 | BR22: 0.07 | BS22: -0.01 | BT22: 0.88 | BU22: =SUMPRODUCT(BQ22:BT22,BL20:BO20)/BP20 -> 0.16515306 | BV22: 0.12 | BW22: 0 | BX22: 0.08 | BY22: 0.03 | BZ22: =SUMPRODUCT(BV22:BY22,BQ20:BT20)/BU20 -> 0.055461853 | CA22: 0.1 | CB22: 0.27 | CC22: 0.19 | CD22: 0.08 | CE22: =SUMPRODUCT(CA22:CD22,BV20:BY20)/BZ20 -> 0.15704132 | CF22: 0.02 | CG22: -0.01 | CH22: 0 | CI22: 0 | CJ22: =SUMPRODUCT(CF22:CI22,CA20:CD20)/CE20 -> 0.0023544917 | CK22: -0.09 | CL22: -0.09 | CM22: -0.07 | CN22: -0.11 | CO22: =SUMPRODUCT(CK22:CN22,CF20:CI20)/CJ20 -> -0.090068923 | CP22: -0.01 | CQ22: 0 | CR22: -0.03 | CS22: -0.04 | CT22: =SUMPRODUCT(CP22:CS22,CK20:CN20)/CO20 -> -0.019388024 | CU22: -0.05 | CV22: =IFERROR((CQ182*CV184+CQ251*CV253+CQ320*CV322+CQ389*CV391+CQ458*CV459+CQ483*CV485+CQ563*CV564)/CQ20,(CQ182*CV184+CQ251*CV253+CQ320*CV322+CQ389*CV391+CQ458*CV459+CQ483*CV485)/CQ20) -> -0.12452804 | CW22: =IFERROR((CR182*CW184+CR251*CW253+CR320*CW322+CR389*CW391+CR458*CW459+CR483*CW485+CR563*CW564)/CR20,(CR182*CW184+CR251*CW253+CR320*CW322+CR389*CW391+CR458*CW459+CR483*CW485)/CR20) -> -0.081840589 | CX22: =IFERROR((CS182*CX184+CS251*CX253+CS320*CX322+CS389*CX391+CS458*CX459+CS483*CX485+CS563*CX564)/CS20,(CS182*CX184+CS251*CX253+CS320*CX322+CS389*CX391+CS458*CX459+CS483*CX485)/CS20) -> -0.093655669 | CY22: =SUMPRODUCT(CU22:CX22,CP20:CS20)/CT20 -> -0.088024915 | CZ22: =IFERROR((CU182*CZ184+CU251*CZ253+CU320*CZ322+CU389*CZ391+CU458*CZ459+CU483*CZ485+CU563*CZ564)/CU20,(CU182*CZ184+CU251*CZ253+CU320*CZ322+CU389*CZ391+CU458*CZ459+CU483*CZ485)/CU20) -> -0.076700259 | DA22: =IFERROR((CV182*DA184+CV251*DA253+CV320*DA322+CV389*DA391+CV458*DA459+CV483*DA485+CV563*DA564)/CV20,(CV182*DA184+CV251*DA253+CV320*DA322+CV389*DA391+CV458*DA459+CV483*DA485)/CV20) -> -0.047626778 | DB22: =IFERROR((CW182*DB184+CW251*DB253+CW320*DB322+CW389*DB391+CW458*DB459+CW483*DB485+CW563*DB564)/CW20,(CW182*DB184+CW251*DB253+CW320*DB322+CW389*DB391+CW458*DB459+CW483*DB485)/CW20) -> -0.0272013 | DC22: =IFERROR((CX182*DC184+CX251*DC253+CX320*DC322+CX389*DC391+CX458*DC459+CX483*DC485+CX563*DC564)/CX20,(CX182*DC184+CX251*DC253+CX320*DC322+CX389*DC391+CX458*DC459+CX483*DC485)/CX20) -> -0.025649483 | DD22: =SUMPRODUCT(CZ22:DC22,CU20:CX20)/CY20 -> -0.045222032 | DE22: =IFERROR((CZ182*DE184+CZ251*DE253+CZ320*DE322+CZ389*DE391+CZ458*DE459+CZ483*DE485+CZ563*DE564)/CZ20,(CZ182*DE184+CZ251*DE253+CZ320*DE322+CZ389*DE391+CZ458*DE459+CZ483*DE485)/CZ20) -> 0.00056365691 | DF22: =IFERROR((DA182*DF184+DA251*DF253+DA320*DF322+DA389*DF391+DA458*DF459+DA483*DF485+DA563*DF564)/DA20,(DA182*DF184+DA251*DF253+DA320*DF322+DA389*DF391+DA458*DF459+DA483*DF485)/DA20) -> 0.001901849 | DG22: =IFERROR((DB182*DG184+DB251*DG253+DB320*DG322+DB389*DG391+DB458*DG459+DB483*DG485+DB563*DG564)/DB20,(DB182*DG184+DB251*DG253+DB320*DG322+DB389*DG391+DB458*DG459+DB483*DG485)/DB20) -> 0.0068869773 | DH22: =IFERROR((DC182*DH184+DC251*DH253+DC320*DH322+DC389*DH391+DC458*DH459+DC483*DH485+DC563*DH564)/DC20,(DC182*DH184+DC251*DH253+DC320*DH322+DC389*DH391+DC458*DH459+DC483*DH485)/DC20) -> 0.0071439572 | DI22: =SUMPRODUCT(DE22:DH22,CZ20:DC20)/DD20 -> 0.0040492115
A23: =IF(ISBLANK(B23),"Scrap", " ") | B23: % FX impact | AM23: =(1+AM21)/(1+AM22)-1 -> -0.0043222543 | AN23: =(1+AN21)/(1+AN22)-1 -> -0.027486038 | AO23: =(1+AO21)/(1+AO22)-1 -> -0.053102422 | AP23: =(1+AP21)/(1+AP22)-1 -> -0.072852418 | AQ23: =(1+AQ21)/(1+AQ22)-1 -> -0.039933689 | AR23: =(1+AR21)/(1+AR22)-1 -> -0.075331777 | AS23: =(1+AS21)/(1+AS22)-1 -> -0.070121951 | AT23: =(1+AT21)/(1+AT22)-1 -> -0.055547716 | ... DI23: =(1+DI21)/(1+DI22)-1 -> 0
A25: =IF(ISBLANK(B25),"Scrap", " ") | B25: NIKE BRAND REVENUES - Additional Disclosure
A26: =IF(ISBLANK(B26),"Scrap", " ") | B26: Footwear | R26: -- | S26: -- | T26: -- | U26: -- | V26: -- | W26: -- | X26: -- | Y26: -- | Z26: -- | AA26: -- | AC26: -- | AD26: -- | AE26: -- | AF26: -- | AG26: -- | AH26: 3979 | AI26: 3611 | AJ26: 4216 | AK26: 4402 | AL26: =SUM(AH26:AK26) -> 16208 | AM26: 4701 | AN26: 4266 | AO26: 4570 | AP26: 4781 | AQ26: =SUM(AM26:AP26) -> 18318 | AR26: 5123 | AS26: 4592 | AT26: 5074 | AU26: 5082 | AV26: =SUM(AR26:AU26) -> 19871 | AW26: 5472 | AX26: 4822 | AY26: 5314 | AZ26: 5473 | BA26: =SUM(AW26:AZ26) -> 21081 | BB26: 5493 | BC26: 5026 | BD26: 5605 | BE26: 6144 | BF26: =SUM(BB26:BE26) -> 22268 | BG26: 6036 | BH26: 5565 | BI26: 6122 | BJ26: 6499 | BK26: =SUM(BG26:BJ26) -> 24222 | BL26: 6521 | BM26: 6206 | BN26: 6377 | BO26: 4201 | BP26: =SUM(BL26:BO26) -> 23305 | BQ26: 6768 | BR26: 6801 | BS26: 6505 | BT26: 7947 | BU26: =SUM(BQ26:BT26) -> 28021 | BV26: 7718 | BW26: 6780 | BX26: 6660 | BY26: 7985 | BZ26: =SUM(BV26:BY26) -> 29143 | CA26: 8114 | CB26: 8504 | CC26: 7970 | CD26: 8547 | CE26: =SUM(CA26:CD26) -> 33135 | CF26: 8421 | CG26: 8607 | CH26: 8162 | CI26: 8237 | CJ26: =SUM(CF26:CI26) -> 33427 | CK26: 7462 | CL26: 7655 | CM26: 7208 | CN26: 7185 | CO26: =SUM(CK26:CN26) -> 29510 | CP26: 7410 | CQ26: 7659 | CR26: 7353 | CS26: 7103 | CT26: =SUM(CP26:CS26) -> 29525 | CU26: 6951 | CV26: =+CV187+CV256+CV325+CV394 -> 6646.1922 | CW26: =+CW187+CW256+CW325+CW394 -> 6685.7437 | CX26: =+CX187+CX256+CX325+CX394 -> 6364.2868 | CY26: =SUM(CU26:CX26) -> 26647.223 | CZ26: =+CZ187+CZ256+CZ325+CZ394 -> 6357.0788 | DA26: =+DA187+DA256+DA325+DA394 -> 6290.3793 | DB26: =+DB187+DB256+DB325+DB394 -> 6484.0014 | DC26: =+DC187+DC256+DC325+DC394 -> 6182.8504 | DD26: =SUM(CZ26:DC26) -> 25314.31 | DE26: =+DE187+DE256+DE325+DE394 -> 6357.6009 | DF26: =+DF187+DF256+DF325+DF394 -> 6301.5688 | DG26: =+DG187+DG256+DG325+DG394 -> 6528.5562 | DH26: =+DH187+DH256+DH325+DH394 -> 6226.2179 | DI26: =SUM(DE26:DH26) -> 25413.944
A27: =IF(ISBLANK(B27),"Scrap", " ") | B27: % chg. Y/Y | R27: -- | S27: -- | T27: -- | U27: -- | V27: -- | W27: -- | X27: -- | Y27: -- | Z27: -- | AA27: -- | AC27: -- | AD27: -- | AE27: -- | AF27: -- | AG27: -- | AH27: -- | AI27: -- | AJ27: -- | AK27: -- | AL27: -- | AM27: =+AM26/AH26-1 -> 0.18145263 | AN27: =+AN26/AI26-1 -> 0.1813902 | AO27: =+AO26/AJ26-1 -> 0.083965844 | AP27: =+AP26/AK26-1 -> 0.086097229 | AQ27: =+AQ26/AL26-1 -> 0.13018263 | AR27: =+AR26/AM26-1 -> 0.089768134 | AS27: =+AS26/AN26-1 -> 0.07641819 | AT27: =+AT26/AO26-1 -> 0.11028446 | ... DI27: =+DI26/DD26-1 -> 0.0039358776
A28: =IF(ISBLANK(B28),"Scrap", " ") | B28: % chg., FX neutral | R28: -- | S28: -- | T28: -- | U28: -- | V28: -- | W28: -- | X28: -- | Y28: -- | Z28: -- | AA28: -- | AC28: -- | AD28: -- | AE28: -- | AF28: -- | AG28: -- | AH28: -- | AI28: -- | AJ28: -- | AK28: -- | AL28: -- | AM28: -- | AN28: -- | AO28: -- | AP28: -- | AQ28: 0.17 | AR28: 0.18 | AS28: 0.16 | AT28: 0.18 | AU28: 0.09 | AV28: 0.15 | AW28: 0.1 | AX28: 0.07 | AY28: 0.07 | AZ28: 0.1 | BA28: 0.08 | BB28: 0.01 | BC28: 0.03 | BD28: 0.02 | BE28: 0.08 | BF28: =SUMPRODUCT(BB28:BE28,AW26:AZ26)/BA26 -> 0.035268725 | BG28: 0.1 | BH28: 0.15 | BI28: 0.13 | BJ28: 0.12 | BK28: =SUMPRODUCT(BG28:BJ28,BB26:BE26)/BF26 -> 0.12435468 | BL28: 0.11 | BM28: 0.14 | BN28: 0.05 | BO28: -0.34 | BP28: =SUMPRODUCT(BL28:BO28,BG26:BJ26)/BK26 -> -0.019011642 | BQ28: 0.05 | BR28: 0.08 | BS28: -0.01 | BT28: 0.83 | BU28: =SUMPRODUCT(BQ28:BT28,BL26:BO26)/BP26 -> 0.18217507 | BV28: 0.1 | BW28: -0.01 | BX28: 0.05 | BY28: 0.04 | BZ28: =SUMPRODUCT(BV28:BY28,BQ26:BT26)/BU26 -> 0.04467792 | CA28: 0.12 | CB28: 0.36 | CC28: 0.25 | CD28: 0.1 | CE28: =SUMPRODUCT(CA28:CD28,BV26:BY26)/BZ26 -> 0.20006382 | CF28: 0.04 | CG28: 0 | CH28: 0.03 | CI28: -0.02 | CJ28: =SUMPRODUCT(CF28:CI28,CA26:CD26)/CE26 -> 0.01185212 | CK28: -0.1 | CL28: -0.12 | CM28: -0.09 | CN28: -0.12 | CO28: =SUMPRODUCT(CK28:CN28,CF26:CI26)/CJ26 -> -0.10763634 | CP28: -0.02 | CQ28: -0.01 | CR28: -0.01 | CS28: -0.04 | CT28: =SUMPRODUCT(CP28:CS28,CK26:CN26)/CO26 -> -0.019832938 | CU28: -0.06 | CV28: =(CQ187*CV189+CQ256*CV258+CQ325*CV327+CQ394*CV396)/CQ26 -> -0.13290377 | CW28: =(CR187*CW189+CR256*CW258+CR325*CW327+CR394*CW396)/CR26 -> -0.087290902 | CX28: =(CS187*CX189+CS256*CX258+CS325*CX327+CS394*CX396)/CS26 -> -0.098882162 | CY28: =SUMPRODUCT(CU28:CX28,CP26:CS26)/CT26 -> -0.095062489 | CZ28: =(CU187*CZ189+CU256*CZ258+CU325*CZ327+CU394*CZ396)/CU26 -> -0.083923177 | DA28: =(CV187*DA189+CV256*DA258+CV325*DA327+CV394*DA396)/CV26 -> -0.053536357 | DB28: =(CW187*DB189+CW256*DB258+CW325*DB327+CW394*DB396)/CW26 -> -0.030174996 | DC28: =(CX187*DC189+CX256*DC258+CX325*DC327+CX394*DC396)/CX26 -> -0.028508519 | DD28: =SUMPRODUCT(CZ28:DC28,CU26:CX26)/CY26 -> -0.049623993 | DE28: =(CZ187*DE189+CZ256*DE258+CZ325*DE327+CZ394*DE396)/CZ26 -> 8.2137318e-05 | DF28: =(DA187*DF189+DA256*DF258+DA325*DF327+DA394*DF396)/DA26 -> 0.0017788254 | DG28: =(DB187*DG189+DB256*DG258+DB325*DG327+DB394*DG396)/DB26 -> 0.0068714997 | DH28: =(DC187*DH189+DC256*DH258+DC325*DH327+DC394*DH396)/DC26 -> 0.0070141711 | DI28: =SUMPRODUCT(DE28:DH28,CZ26:DC26)/DD26 -> 0.0039358776
A29: =IF(ISBLANK(B29),"Scrap", " ") | B29: Unit growth | R29: -- | S29: -- | T29: -- | U29: -- | V29: -- | W29: -- | X29: -- | Y29: -- | Z29: -- | AA29: -- | AC29: -- | AD29: -- | AE29: -- | AF29: -- | AG29: -- | AH29: -- | AI29: -- | AJ29: -- | AK29: -- | AL29: -- | AM29: -- | AN29: -- | AO29: -- | AP29: -- | AQ29: 0.09 | AR29: 0.1 | AS29: 0.11 | AT29: 0.12 | AU29: =((AV29*SUM(AM26:AP26))-AR29*AM26-AS29*AN26-AT29*AO26)/AP26 -> 0.033645681 | AV29: 0.09 | AW29: 0.06 | AX29: 0.04 | AY29: 0.06 | AZ29: =((BA29*SUM(AR26:AU26))-AW29*AR26-AX29*AS26-AY29*AT26)/AU26 -> 0.11717237 | BA29: 0.07 | BB29: 0.03 | BC29: 0 | BD29: 0.01 | BE29: =((BF29*SUM(AW26:AZ26))-BB29*AW26-BC29*AX26-BD29*AY26)/AZ26 -> 0.037332359 | BF29: 0.02 | BG29: 0.08 | BH29: 0.12 | BI29: 0.06 | BJ29: =((BK29*SUM(BB26:BE26))-BG29*BB26-BH29*BC26-BI29*BD26)/BE26 -> 0.065524089 | BK29: 0.08 | BL29: 0.03 | BM29: 0.08 | BN29: 0.01 | BO29: =((BP29*SUM(BG26:BJ26))-BL29*BG26-BM29*BH26-BN29*BI26)/BJ26 -> -0.4039483 | BP29: -0.08 | BQ29: 0 | BR29: 0.04 | BS29: -0.12 | BT29: =((BU29*SUM(BL26:BO26))-BQ29*BL26-BR29*BM26-BS29*BN26)/BO26 -> 0.73328969 | BU29: 0.11 | BV29: 0.05 | BW29: -0.07 | BX29: -0.03 | BY29: =((BZ29*SUM(BQ26:BT26))-BV29*BQ26-BW29*BR26-BX29*BS26)/BT26 -> -0.063899585 | BZ29: -0.03 | CA29: 0.03 | CB29: 0.28 | CC29: 0.19 | CD29: =((CE29*SUM(BV26:BY26))-CA29*BV26-CB29*BW26-CC29*BX26)/BY26 -> 0.049248591 | CE29: 0.13 | CF29: -0.01 | CG29: -0.06 | CH29: 0.02 | CI29: =((CJ29*SUM(CA26:CD26))-CF29*CA26-CG29*CB26-CH29*CC26)/CD26 -> -0.026994267 | CJ29: -0.02 | CK29: -0.1 | CL29: -0.07 | CM29: -0.08 | CN29: =((CO29*SUM(CF26:CI26))-CK29*CF26-CL29*CG26-CM29*CH26)/CI26 -> -0.070002428 | CO29: -0.08 | CP29: 0.02 | CQ29: 0 | CR29: -0.02 | CS29: =((CT29*SUM(CK26:CN26))-CP29*CK26-CQ29*CL26-CR29*CM26)/CN26 -> -0.041778706 | CT29: -0.01
A30: =IF(ISBLANK(B30),"Scrap", " ") | B30: Price growth | R30: -- | S30: -- | T30: -- | U30: -- | V30: -- | W30: -- | X30: -- | Y30: -- | Z30: -- | AA30: -- | AC30: -- | AD30: -- | AE30: -- | AF30: -- | AG30: -- | AH30: -- | AI30: -- | AJ30: -- | AK30: -- | AL30: -- | AM30: -- | AN30: -- | AO30: -- | AP30: -- | AQ30: 0.08 | AR30: 0.08 | AS30: 0.05 | AT30: 0.06 | AU30: =((AV30*SUM(AM26:AP26))-AR30*AM26-AS30*AN26-AT30*AO26)/AP26 -> 0.049257478 | AV30: 0.06 | AW30: 0.04 | AX30: 0.03 | AY30: 0.01 | AZ30: =((BA30*SUM(AR26:AU26))-AW30*AR26-AX30*AS26-AY30*AT26)/AU26 -> -0.038313656 | BA30: 0.01 | BB30: -0.02 | BC30: 0.03 | BD30: 0.01 | BE30: =((BF30*SUM(AW26:AZ26))-BB30*AW26-BC30*AX26-BD30*AY26)/AZ26 -> 0.06089165 | BF30: 0.02 | BG30: 0.02 | BH30: 0.03 | BI30: 0.07 | BJ30: =((BK30*SUM(BB26:BE26))-BG30*BB26-BH30*BC26-BI30*BD26)/BE26 -> 0.038693034 | BK30: 0.04 | BL30: 0.08 | BM30: 0.06 | BN30: 0.04 | BO30: =((BP30*SUM(BG26:BJ26))-BL30*BG26-BM30*BH26-BN30*BI26)/BJ26 -> 0.060264656 | BP30: 0.06 | BQ30: 0.05 | BR30: 0.04 | BS30: 0.11 | BT30: =((BU30*SUM(BL26:BO26))-BQ30*BL26-BR30*BM26-BS30*BN26)/BO26 -> 0.084644132 | BU30: 0.07 | BV30: 0.05 | BW30: 0.06 | BX30: 0.08 | BY30: =((BZ30*SUM(BQ26:BT26))-BV30*BQ26-BW30*BR26-BX30*BS26)/BT26 -> 0.08740531 | BZ30: 0.07 | CA30: 0.09 | CB30: 0.08 | CC30: 0.06 | CD30: =((CE30*SUM(BV26:BY26))-CA30*BV26-CB30*BW26-CC30*BX26)/BY26 -> 0.050518472 | CE30: 0.07 | CF30: 0.05 | CG30: 0.06 | CH30: 0.01 | CI30: =((CJ30*SUM(CA26:CD26))-CF30*CA26-CG30*CB26-CH30*CC26)/CD26 -> -0.00018603019 | CJ30: 0.03 | CK30: 0 | CL30: -0.05 | CM30: -0.01 | CN30: =((CO30*SUM(CF26:CI26))-CK30*CF26-CL30*CG26-CM30*CH26)/CI26 -> -0.059589656 | CO30: -0.03 | CP30: -0.04 | CQ30: -0.01 | CR30: 0.01 | CS30: =((CT30*SUM(CK26:CN26))-CP30*CK26-CQ30*CL26-CR30*CM26)/CN26 -> 0.0010925539 | CT30: -0.01
A31: =IF(ISBLANK(B31),"Scrap", " ") | B31: % FX impact | R31: -- | S31: -- | T31: -- | U31: -- | V31: -- | W31: -- | X31: -- | Y31: -- | Z31: -- | AA31: -- | AC31: -- | AD31: -- | AE31: -- | AF31: -- | AG31: -- | AH31: -- | AI31: -- | AJ31: -- | AK31: -- | AL31: -- | AM31: -- | AN31: -- | AO31: -- | AP31: -- | AQ31: =(1+AQ27)/(1+AQ28)-1 -> -0.034031944 | AR31: =(1+AR27)/(1+AR28)-1 -> -0.076467683 | AS31: =(1+AS27)/(1+AS28)-1 -> -0.072053284 | AT31: =(1+AT27)/(1+AT28)-1 -> -0.059080963 | AU31: =(1+AU27)/(1+AU28)-1 -> -0.024809596 | AV31: =(1+AV27)/(1+AV28)-1 -> -0.056713045 | AW31: =(1+AW27)/(1+AW28)-1 -> -0.028978049 | AX31: =(1+AX27)/(1+AX28)-1 -> -0.018610179 | ... DI31: =(1+DI27)/(1+DI28)-1 -> 0
A33: =IF(ISBLANK(B33),"Scrap", " ") | B33: Apparel | R33: -- | S33: -- | T33: -- | U33: -- | V33: -- | W33: -- | X33: -- | Y33: -- | Z33: -- | AA33: -- | AC33: -- | AD33: -- | AE33: -- | AF33: -- | AG33: -- | AH33: 2023 | AI33: 2058 | AJ33: 1893 | AK33: 2135 | AL33: =SUM(AH33:AK33) -> 8109 | AM33: 2236 | AN33: 2285 | AO33: 1959 | AP33: 2236 | AQ33: =SUM(AM33:AP33) -> 8716 | AR33: 2341 | AS33: 2362 | AT33: 2124 | AU33: 2240 | AV33: =SUM(AR33:AU33) -> 9067 | AW33: 2549 | AX33: 2535 | AY33: 2269 | AZ33: 2301 | BA33: =SUM(AW33:AZ33) -> 9654 | BB33: 2652 | BC33: 2761 | BD33: 2555 | BE33: 2765 | BF33: =SUM(BB33:BE33) -> 10733 | BG33: 2949 | BH33: 3049 | BI33: 2707 | BJ33: 2845 | BK33: =SUM(BG33:BJ33) -> 11550 | BL33: 3121 | BM33: 3287 | BN33: 2905 | BO33: 1640 | BP33: =SUM(BL33:BO33) -> 10953 | BQ33: 2875 | BR33: 3585 | BS33: 2966 | BT33: 3439 | BU33: =SUM(BQ33:BT33) -> 12865 | BV33: 3450 | BW33: 3648 | BX33: 3232 | BY33: 3237 | BZ33: =SUM(BV33:BY33) -> 13567 | CA33: 3434 | CB33: 3794 | CC33: 3381 | CD33: 3234 | CE33: =SUM(CA33:CD33) -> 13843 | CF33: 3388 | CG33: 3774 | CH33: 3290 | CI33: 3323 | CJ33: =SUM(CF33:CI33) -> 13775 | CK33: 3032 | CL33: 3738 | CM33: 3193 | CN33: 3002 | CO33: =SUM(CK33:CN33) -> 12965 | CP33: 3313 | CQ33: 3906 | CR33: 3184 | CS33: 3046 | CT33: =SUM(CP33:CS33) -> 13449 | CU33: 3384 | CV33: =+CV194+CV263+CV332+CV401 -> 3506.106 | CW33: =+CW194+CW263+CW332+CW401 -> 2961.2641 | CX33: =+CX194+CX263+CX332+CX401 -> 2775.0218 | CY33: =SUM(CU33:CX33) -> 12626.392 | CZ33: =+CZ194+CZ263+CZ332+CZ401 -> 3131.041 | DA33: =+DA194+DA263+DA332+DA401 -> 3371.7595 | DB33: =+DB194+DB263+DB332+DB401 -> 2895.907 | DC33: =+DC194+DC263+DC332+DC401 -> 2717.2167 | DD33: =SUM(CZ33:DC33) -> 12115.924 | DE33: =+DE194+DE263+DE332+DE401 -> 3136.0082 | DF33: =+DF194+DF263+DF332+DF401 -> 3379.8693 | DG33: =+DG194+DG263+DG332+DG401 -> 2918.3727 | DH33: =+DH194+DH263+DH332+DH401 -> 2740.4373 | DI33: =SUM(DE33:DH33) -> 12174.688
A34: =IF(ISBLANK(B34),"Scrap", " ") | B34: % chg. Y/Y | R34: -- | S34: -- | T34: -- | U34: -- | V34: -- | W34: -- | X34: -- | Y34: -- | Z34: -- | AA34: -- | AC34: -- | AD34: -- | AE34: -- | AF34: -- | AG34: -- | AH34: -- | AI34: -- | AJ34: -- | AK34: -- | AL34: -- | AM34: =+AM33/AH33-1 -> 0.10528917 | AN34: =+AN33/AI33-1 -> 0.11030126 | AO34: =+AO33/AJ33-1 -> 0.034865293 | AP34: =+AP33/AK33-1 -> 0.047306792 | AQ34: =+AQ33/AL33-1 -> 0.074855099 | AR34: =+AR33/AM33-1 -> 0.046958855 | AS34: =+AS33/AN33-1 -> 0.033698031 | AT34: =+AT33/AO33-1 -> 0.084226646 | ... DI34: =+DI33/DD33-1 -> 0.0048500985
A35: =IF(ISBLANK(B35),"Scrap", " ") | B35: % chg., FX neutral | R35: -- | S35: -- | T35: -- | U35: -- | V35: -- | W35: -- | X35: -- | Y35: -- | Z35: -- | AA35: -- | AC35: -- | AD35: -- | AE35: -- | AF35: -- | AG35: -- | AH35: -- | AI35: -- | AJ35: -- | AK35: -- | AL35: -- | AM35: -- | AN35: -- | AO35: -- | AP35: -- | AQ35: 0.1 | AR35: 0.12 | AS35: 0.1 | AT35: 0.14 | AU35: 0.07 | AV35: 0.11 | AW35: 0.12 | AX35: 0.09 | AY35: 0.09 | AZ35: 0.04 | BA35: 0.09 | BB35: 0.05 | BC35: 0.08 | BD35: 0.09 | BE35: 0.15 | BF35: =SUMPRODUCT(BB35:BE35,AW33:AZ33)/BA33 -> 0.091113528 | BG35: 0.11 | BH35: 0.14 | BI35: 0.1 | BJ35: 0.08 | BK35: =SUMPRODUCT(BG35:BJ35,BB33:BE33)/BF33 -> 0.10760831 | BL35: 0.09 | BM35: 0.1 | BN35: 0.09 | BO35: -0.41 | BP35: =SUMPRODUCT(BL35:BO35,BG33:BJ33)/BK33 -> -0.030520346 | BQ35: -0.07 | BR35: 0.07 | BS35: -0.01 | BT35: 1.01 | BU35: =SUMPRODUCT(BQ35:BT35,BL33:BO33)/BP33 -> 0.14963663 | BV35: 0.16 | BW35: 0.01 | BX35: 0.12 | BY35: -0.02 | BZ35: =SUMPRODUCT(BV35:BY35,BQ33:BT33)/BU33 -> 0.060862029 | CA35: 0.07 | CB35: 0.14 | CC35: 0.1 | CD35: 0.03 | CE35: =SUMPRODUCT(CA35:CD35,BV33:BY33)/BZ33 -> 0.086425149 | CF35: -0.01 | CG35: -0.02 | CH35: -0.03 | CI35: 0.04 | CJ35: =SUMPRODUCT(CF35:CI35,CA33:CD33)/CE33 -> -0.0059445207 | CK35: -0.09 | CL35: -0.02 | CM35: -0.01 | CN35: -0.09 | CO35: =SUMPRODUCT(CK35:CN35,CF33:CI33)/CJ33 -> -0.051714701 | CP35: 0.07 | CQ35: 0.04 | CR35: -0.04 | CS35: -0.01 | CT35: =SUMPRODUCT(CP35:CS35,CK33:CN33)/CO33 -> 0.015736213 | CU35: 0.02 | CV35: =(CQ194*CV196+CQ263*CV265+CQ332*CV334+CQ401*CV403)/CQ33 -> -0.10133129 | CW35: =(CR194*CW196+CR263*CW265+CR332*CW334+CR401*CW403)/CR33 -> -0.063665201 | CX35: =(CS194*CX196+CS263*CX265+CS332*CX334+CS401*CX403)/CS33 -> -0.081713723 | CY35: =SUMPRODUCT(CU35:CX35,CP33:CS33)/CT33 -> -0.058082385 | CZ35: =(CU194*CZ196+CU263*CZ265+CU332*CZ334+CU401*CZ403)/CU33 -> -0.071300236 | DA35: =(CV194*DA196+CV263*DA265+CV332*DA334+CV401*DA403)/CV33 -> -0.038317883 | DB35: =(CW194*DB196+CW263*DB265+CW332*DB334+CW401*DB403)/CW33 -> -0.022070704 | DC35: =(CX194*DC196+CX263*DC265+CX332*DC334+CX401*DC403)/CX33 -> -0.020830519 | DD35: =SUMPRODUCT(CZ35:DC35,CU33:CX33)/CY33 -> -0.039503675 | DE35: =(CZ194*DE196+CZ263*DE265+CZ332*DE334+CZ401*DE403)/CZ33 -> 0.0015864401 | DF35: =(DA194*DF196+DA263*DF265+DA332*DF334+DA401*DF403)/DA33 -> 0.0024052234 | DG35: =(DB194*DG196+DB263*DG265+DB332*DG334+DB401*DG403)/DB33 -> 0.007757763 | DH35: =(DC194*DH196+DC263*DH265+DC332*DH334+DC401*DH403)/DC33 -> 0.0085457378 | DI35: =SUMPRODUCT(DE35:DH35,CZ33:DC33)/DD33 -> 0.0048500985
A36: =IF(ISBLANK(B36),"Scrap", " ") | B36: Unit growth | R36: -- | S36: -- | T36: -- | U36: -- | V36: -- | W36: -- | X36: -- | Y36: -- | Z36: -- | AA36: -- | AC36: -- | AD36: -- | AE36: -- | AF36: -- | AG36: -- | AH36: -- | AI36: -- | AJ36: -- | AK36: -- | AL36: -- | AM36: -- | AN36: -- | AO36: -- | AP36: -- | AQ36: 0.08 | AR36: 0.09 | AS36: 0.08 | AT36: 0.12 | AU36: =((AV36*SUM(AM33:AP33))-AR36*AM33-AS36*AN33-AT36*AO33)/AP33 -> -0.0040250447 | AV36: 0.07 | AW36: 0.09 | AX36: 0.05 | AY36: 0.06 | AZ36: =((BA36*SUM(AR33:AU33))-AW36*AR33-AX36*AS33-AY36*AT33)/AU33 -> 0.039191964 | BA36: 0.06 | BB36: 0.03 | BC36: 0.03 | BD36: 0.02 | BE36: =((BF36*SUM(AW33:AZ33))-BB36*AW33-BC36*AX33-BD36*AY33)/AZ33 -> 0.081816601 | BF36: 0.04 | BG36: 0.07 | BH36: 0.08 | BI36: 0.02 | BJ36: =((BK36*SUM(BB33:BE33))-BG36*BB33-BH36*BC33-BI36*BD33)/BE33 -> 0.067399638 | BK36: 0.06 | BL36: 0.05 | BM36: 0.07 | BN36: 0.08 | BO36: =((BP36*SUM(BG33:BJ33))-BL36*BG33-BM36*BH33-BN36*BI33)/BJ33 -> -0.52774692 | BP36: -0.08 | BQ36: -0.06 | BR36: 0.09 | BS36: -0.11 | BT36: =((BU36*SUM(BL33:BO33))-BQ36*BL33-BR36*BM33-BS36*BN33)/BO33 -> 1.0636585 | BU36: 0.14 | BV36: 0.08 | BW36: -0.06 | BX36: 0.05 | BY36: =((BZ36*SUM(BQ33:BT33))-BV36*BQ33-BW36*BR33-BX36*BS33)/BT33 -> -0.047455656 | BZ36: 0 | CA36: 0.05 | CB36: 0.1 | CC36: 0.05 | CD36: =((CE36*SUM(BV33:BY33))-CA36*BV33-CB36*BW33-CC36*BX33)/BY33 -> -0.048260735 | CE36: 0.04 | CF36: -0.12 | CG36: -0.15 | CH36: -0.08 | CI36: =((CJ36*SUM(CA33:CD33))-CF36*CA33-CG36*CB33-CH36*CC33)/CD33 -> 0.0017903525 | CJ36: -0.09 | CK36: -0.12 | CL36: 0 | CM36: 0 | CN36: =((CO36*SUM(CF33:CI33))-CK36*CF33-CL36*CG33-CM36*CH33)/CI33 -> -0.084920253 | CO36: -0.05 | CP36: 0.1 | CQ36: 0.04 | CR36: -0.03 | CS36: =((CT36*SUM(CK33:CN33))-CP36*CK33-CQ36*CL33-CR36*CM33)/CN33 -> -0.075709527 | CT36: 0.01
A37: =IF(ISBLANK(B37),"Scrap", " ") | B37: Price growth | R37: -- | S37: -- | T37: -- | U37: -- | V37: -- | W37: -- | X37: -- | Y37: -- | Z37: -- | AA37: -- | AC37: -- | AD37: -- | AE37: -- | AF37: -- | AG37: -- | AH37: -- | AI37: -- | AJ37: -- | AK37: -- | AL37: -- | AM37: -- | AN37: -- | AO37: -- | AP37: -- | AQ37: 0.02 | AR37: 0.03 | AS37: 0.02 | AT37: 0.02 | AU37: =((AV37*SUM(AM33:AP33))-AR37*AM33-AS37*AN33-AT37*AO33)/AP33 -> 0.087960644 | AV37: 0.04 | AW37: 0.03 | AX37: 0.04 | AY37: 0.03 | AZ37: =((BA37*SUM(AR33:AU33))-AW37*AR33-AX37*AS33-AY37*AT33)/AU33 -> 0.019455357 | BA37: 0.03 | BB37: 0.02 | BC37: 0.05 | BD37: 0.07 | BE37: =((BF37*SUM(AW33:AZ33))-BB37*AW33-BC37*AX33-BD37*AY33)/AZ33 -> 0.063511517 | BF37: 0.05 | BG37: 0.04 | BH37: 0.06 | BI37: 0.08 | BJ37: =((BK37*SUM(BB33:BE33))-BG37*BB33-BH37*BC33-BI37*BD33)/BE33 -> 0.021884268 | BK37: 0.05 | BL37: 0.04 | BM37: 0.03 | BN37: 0.01 | BO37: =((BP37*SUM(BG33:BJ33))-BL37*BG33-BM37*BH33-BN37*BI33)/BJ33 -> 0.1198594 | BP37: 0.05 | BQ37: -0.01 | BR37: -0.02 | BS37: 0.1 | BT37: =((BU37*SUM(BL33:BO33))-BQ37*BL33-BR37*BM33-BS37*BN33)/BO33 -> -0.051231707 | BU37: 0.01 | BV37: 0.08 | BW37: 0.07 | BX37: 0.07 | BY37: =((BZ37*SUM(BQ33:BT33))-BV37*BQ33-BW37*BR33-BX37*BS33)/BT33 -> 0.024230881 | BZ37: 0.06 | CA37: 0.02 | CB37: 0.04 | CC37: 0.05 | CD37: =((CE37*SUM(BV33:BY33))-CA37*BV33-CB37*BW33-CC37*BX33)/BY33 -> 0.05133148 | CE37: 0.04 | CF37: 0.11 | CG37: 0.13 | CH37: 0.05 | CI37: =((CJ37*SUM(CA33:CD33))-CF37*CA33-CG37*CB33-CH37*CC33)/CD33 -> 0.063654917 | CJ37: 0.09 | CK37: 0.03 | CL37: -0.02 | CM37: -0.01 | CN37: =((CO37*SUM(CF33:CI33))-CK37*CF33-CL37*CG33-CM37*CH33)/CI33 -> 0.0020282877 | CO37: 0 | CP37: -0.03 | CQ37: 0 | CR37: -0.01 | CS37: =((CT37*SUM(CK33:CN33))-CP37*CK33-CQ37*CL33-CR37*CM33)/CN33 -> 0.084123917 | CT37: 0.01
A38: =IF(ISBLANK(B38),"Scrap", " ") | B38: % FX impact | R38: -- | S38: -- | T38: -- | U38: -- | V38: -- | W38: -- | X38: -- | Y38: -- | Z38: -- | AA38: -- | AC38: -- | AD38: -- | AE38: -- | AF38: -- | AG38: -- | AH38: -- | AI38: -- | AJ38: -- | AK38: -- | AL38: -- | AM38: -- | AN38: -- | AO38: -- | AP38: -- | AQ38: =(1+AQ34)/(1+AQ35)-1 -> -0.022859001 | AR38: =(1+AR34)/(1+AR35)-1 -> -0.065215308 | AS38: =(1+AS34)/(1+AS35)-1 -> -0.060274518 | AT38: =(1+AT34)/(1+AT35)-1 -> -0.048923995 | AU38: =(1+AU34)/(1+AU35)-1 -> -0.063748683 | AV38: =(1+AV34)/(1+AV35)-1 -> -0.062819129 | AW38: =(1+AW34)/(1+AW35)-1 -> -0.02781168 | AX38: =(1+AX34)/(1+AX35)-1 -> -0.015373381 | ... DI38: =(1+DI34)/(1+DI35)-1 -> 0
A40: =IF(ISBLANK(B40),"Scrap", " ") | B40: Equipment | R40: -- | S40: -- | T40: -- | U40: -- | V40: -- | W40: -- | X40: -- | Y40: -- | Z40: -- | AA40: -- | AC40: -- | AD40: -- | AE40: -- | AF40: -- | AG40: -- | AH40: 434 | AI40: 370 | AJ40: 419 | AK40: 447 | AL40: =SUM(AH40:AK40) -> 1670 | AM40: 455 | AN40: 380 | AO40: 382 | AP40: 415 | AQ40: =SUM(AM40:AP40) -> 1632 | AR40: 408 | AS40: 345 | AT40: 352 | AU40: 391 | AV40: =SUM(AR40:AU40) -> 1496 | AW40: 423 | AX40: 346 | AY40: 321 | AZ40: 335 | BA40: =SUM(AW40:AZ40) -> 1425 | BB40: 420 | BC40: 326 | BD40: 314 | BE40: 336 | BF40: =SUM(BB40:BE40) -> 1396 | BG40: 416 | BH40: 323 | BI40: 311 | BJ40: 354 | BK40: =SUM(BG40:BJ40) -> 1404 | BL40: 448 | BM40: 341 | BN40: 326 | BO40: 165 | BP40: =SUM(BL40:BO40) -> 1280 | BQ40: 371 | BR40: 347 | BS40: 296 | BT40: 368 | BU40: =SUM(BQ40:BT40) -> 1382 | BV40: 465 | BW40: 382 | BX40: 390 | BY40: 387 | BZ40: =SUM(BV40:BY40) -> 1624 | CA40: 486 | CB40: 408 | CC40: 403 | CD40: 430 | CE40: =SUM(CA40:CD40) -> 1727 | CF40: 531 | CG40: 479 | CH40: 487 | CI40: 578 | CJ40: =SUM(CF40:CI40) -> 2075 | CK40: 603 | CL40: 544 | CM40: 477 | CN40: 567 | CO40: =SUM(CK40:CN40) -> 2191 | CP40: 630 | CQ40: 550 | CR40: 468 | CS40: 551 | CT40: =SUM(CP40:CS40) -> 2199 | CU40: 611 | CV40: =+CV201+CV270+CV339+CV408 -> 491.79967 | CW40: =+CW201+CW270+CW339+CW408 -> 440.77538 | CX40: =+CX201+CX270+CX339+CX408 -> 522.83481 | CY40: =SUM(CU40:CX40) -> 2066.4099 | CZ40: =+CZ201+CZ270+CZ339+CZ408 -> 584.26306 | DA40: =+DA201+DA270+DA339+DA408 -> 475.12039 | DB40: =+DB201+DB270+DB339+DB408 -> 431.76271 | DC40: =+DC201+DC270+DC339+DC408 -> 512.52899 | DD40: =SUM(CZ40:DC40) -> 2003.6752 | DE40: =+DE201+DE270+DE339+DE408 -> 584.59528 | DF40: =+DF201+DF270+DF339+DF408 -> 475.52424 | DG40: =+DG201+DG270+DG339+DG408 -> 433.78854 | DH40: =+DH201+DH270+DH339+DH408 -> 514.72205 | DI40: =SUM(DE40:DH40) -> 2008.6301
A41: =IF(ISBLANK(B41),"Scrap", " ") | B41: % chg. Y/Y | R41: -- | S41: -- | T41: -- | U41: -- | V41: -- | W41: -- | X41: -- | Y41: -- | Z41: -- | AA41: -- | AC41: -- | AD41: -- | AE41: -- | AF41: -- | AG41: -- | AH41: -- | AI41: -- | AJ41: -- | AK41: -- | AL41: -- | AM41: =+AM40/AH40-1 -> 0.048387097 | AN41: =+AN40/AI40-1 -> 0.027027027 | AO41: =+AO40/AJ40-1 -> -0.088305489 | AP41: =+AP40/AK40-1 -> -0.071588367 | AQ41: =+AQ40/AL40-1 -> -0.022754491 | AR41: =+AR40/AM40-1 -> -0.1032967 | AS41: =+AS40/AN40-1 -> -0.092105263 | AT41: =+AT40/AO40-1 -> -0.078534031 | ... DI41: =+DI40/DD40-1 -> 0.0024729339
A42: =IF(ISBLANK(B42),"Scrap", " ") | B42: % chg., FX neutral | R42: -- | S42: -- | T42: -- | U42: -- | V42: -- | W42: -- | X42: -- | Y42: -- | Z42: -- | AA42: -- | AC42: -- | AD42: -- | AE42: -- | AF42: -- | AG42: -- | AH42: -- | AI42: -- | AJ42: -- | AK42: -- | AL42: -- | AM42: -- | AN42: -- | AO42: -- | AP42: -- | AQ42: 0.01 | AR42: -0.03 | AS42: -0.01 | AT42: -0.02 | AU42: -0.03 | AV42: -0.02 | AW42: 0.06 | AX42: 0.02 | AY42: -0.07 | AZ42: -0.14 | BA42: -0.03 | BB42: 0 | BC42: -0.07 | BD42: -0.06 | BE42: -0.03 | BF42: =SUMPRODUCT(BB42:BE42,AW40:AZ40)/BA40 -> -0.037564912 | BG42: -0.01 | BH42: 0.04 | BI42: 0.04 | BJ42: 0.11 | BK42: =SUMPRODUCT(BG42:BJ42,BB40:BE40)/BF40 -> 0.041805158 | BL42: 0.11 | BM42: 0.08 | BN42: 0.06 | BO42: -0.51 | BP42: =SUMPRODUCT(BL42:BO42,BG40:BJ40)/BK40 -> -0.064301994 | BQ42: -0.16 | BR42: 0.01 | BS42: -0.11 | BT42: 1.13 | BU42: =SUMPRODUCT(BQ42:BT42,BL40:BO40)/BP40 -> 0.0643125 | BV42: 0.22 | BW42: 0.09 | BX42: 0.36 | BY42: 0.1 | BZ42: =SUMPRODUCT(BV42:BY42,BQ40:BT40)/BU40 -> 0.18539074 | CA42: 0.12 | CB42: 0.17 | CC42: 0.08 | CD42: 0.14 | CE42: =SUMPRODUCT(CA42:CD42,BV40:BY40)/BZ40 -> 0.12692118 | CF42: 0.09 | CG42: 0.15 | CH42: 0.2 | CI42: 0.35 | CJ42: =SUMPRODUCT(CF42:CI42,CA40:CD40)/CE40 -> 0.1945802 | CK42: 0.15 | CL42: 0.12 | CM42: 0 | CN42: -0.01 | CO42: =SUMPRODUCT(CK42:CN42,CF40:CI40)/CJ40 -> 0.063301205 | CP42: 0.03 | CQ42: 0 | CR42: -0.06 | CS42: -0.05 | CT42: =SUMPRODUCT(CP42:CS42,CK40:CN40)/CO40 -> -0.017745322 | CU42: -0.03 | CV42: =(CQ201*CV203+CQ270*CV272+CQ339*CV341+CQ408*CV410)/CQ40 -> -0.10145455 | CW42: =(CR201*CW203+CR270*CW272+CR339*CW341+CR408*CW410)/CR40 -> -0.048547009 | CX42: =(CS201*CX203+CS270*CX272+CS339*CX341+CS408*CX410)/CS40 -> -0.042704174 | CY42: =SUMPRODUCT(CU42:CX42,CP40:CS40)/CT40 -> -0.055002274 | CZ42: =(CU201*CZ203+CU270*CZ272+CU339*CZ341+CU408*CZ410)/CU40 -> -0.039705401 | DA42: =(CV201*DA203+CV270*DA272+CV339*DA341+CV408*DA410)/CV40 -> -0.033914787 | DB42: =(CW201*DB203+CW270*DB272+CW339*DB341+CW408*DB410)/CW40 -> -0.0204473 | DC42: =(CX201*DC203+CX270*DC272+CX339*DC341+CX408*DC410)/CX40 -> -0.019711427 | DD42: =SUMPRODUCT(CZ42:DC42,CU40:CX40)/CY40 -> -0.029160608 | DE42: =(CZ201*DE203+CZ270*DE272+CZ339*DE341+CZ408*DE410)/CZ40 -> 0.00056860945 | DF42: =(DA201*DF203+DA270*DF272+DA339*DF341+DA408*DF410)/DA40 -> 0.00084999888 | DG42: =(DB201*DG203+DB270*DG272+DB339*DG341+DB408*DG410)/DB40 -> 0.0046919991 | DH42: =(DC201*DH203+DC270*DH272+DC339*DH341+DC408*DH410)/DC40 -> 0.004278893 | DI42: =SUMPRODUCT(DE42:DH42,CZ40:DC40)/DD40 -> 0.0024729339
A43: =IF(ISBLANK(B43),"Scrap", " ") | B43: % FX impact | R43: -- | S43: -- | T43: -- | U43: -- | V43: -- | W43: -- | X43: -- | Y43: -- | Z43: -- | AA43: -- | AC43: -- | AD43: -- | AE43: -- | AF43: -- | AG43: -- | AH43: -- | AI43: -- | AJ43: -- | AK43: -- | AL43: -- | AM43: -- | AN43: -- | AO43: -- | AP43: -- | AQ43: =(1+AQ41)/(1+AQ42)-1 -> -0.032430189 | AR43: =(1+AR41)/(1+AR42)-1 -> -0.075563612 | AS43: =(1+AS41)/(1+AS42)-1 -> -0.082934609 | AT43: =(1+AT41)/(1+AT42)-1 -> -0.059728603 | AU43: =(1+AU41)/(1+AU42)-1 -> -0.028692088 | AV43: =(1+AV41)/(1+AV42)-1 -> -0.06462585 | AW43: =(1+AW41)/(1+AW42)-1 -> -0.021920089 | AX43: =(1+AX41)/(1+AX42)-1 -> -0.016766127 | ... DI43: =(1+DI41)/(1+DI42)-1 -> 0
A45: =IF(ISBLANK(B45),"Scrap", " ") | B45: DTC sales | R45: -- | S45: -- | T45: -- | U45: -- | V45: -- | W45: -- | X45: -- | Y45: -- | Z45: -- | AA45: -- | AC45: -- | AD45: -- | AE45: -- | AF45: -- | AG45: -- | AH45: 1301 | AI45: 1157 | AJ45: 1359 | AK45: 1487 | AL45: =SUM(AH45:AK45) -> 5304 | AM45: 1703 | AN45: 1480 | AO45: 1684 | AP45: 1767 | AQ45: =SUM(AM45:AP45) -> 6634 | AR45: 1932 | AS45: 1741 | AT45: 2057 | AU45: 2127 | AV45: =SUM(AR45:AU45) -> 7857 | AW45: 2305 | AX45: 2144 | AY45: 2286 | AZ45: 2347 | BA45: =SUM(AW45:AZ45) -> 9082 | BB45: 2535 | BC45: 2484 | BD45: 2611 | BE45: =BF45-SUM(BB45:BD45) -> 2798 | BF45: 10428 | BG45: 2851 | BH45: 2831 | BI45: 2966 | BJ45: =BK45-SUM(BG45:BI45) -> 3105 | BK45: 11753 | BL45: 3248 | BM45: 3256 | BN45: 3297 | BO45: =12382-BN45-BM45-BL45 -> 2581 | BP45: =SUM(BL45:BO45) -> 12382 | BQ45: 3650 | BR45: 4310 | BS45: 3953 | BT45: =16370-BS45-BR45-BQ45 -> 4457 | BU45: =SUM(BQ45:BT45) -> 16370 | BV45: 4690 | BW45: 4691 | BX45: 4554 | BY45: =18726-BX45-BW45-BV45 -> 4791 | BZ45: =SUM(BV45:BY45) -> 18726 | CA45: 5051 | CB45: 5419 | CC45: 5331 | CD45: =21308-CA45-CB45-CC45 -> 5507 | CE45: =SUM(CA45:CD45) -> 21308 | CF45: 5357 | CG45: 5742 | CH45: 5351 | CI45: =21519-CH45-CG45-CF45 -> 5069 | CJ45: =SUM(CF45:CI45) -> 21519 | CK45: 4687 | CL45: 5017 | CM45: 4723 | CN45: =18783-CK45-CL45-CM45 -> 4356 | CO45: =SUM(CK45:CN45) -> 18783 | CP45: 4514 | CQ45: 4616 | CR45: 4539 | CS45: =17720-CR45-CQ45-CP45 -> 4051 | CT45: =CP45+CQ45+CR45+CS45 -> 17720 | CU45: 4142
A46: =IF(ISBLANK(B46),"Scrap", " ") | B46: % chg. Y/Y | R46: -- | S46: -- | T46: -- | U46: -- | V46: -- | W46: -- | X46: -- | Y46: -- | Z46: -- | AA46: -- | AC46: -- | AD46: -- | AE46: -- | AF46: -- | AG46: -- | AH46: -- | AI46: -- | AJ46: -- | AK46: -- | AL46: -- | AM46: =+AM45/AH45-1 -> 0.30899308 | AN46: =+AN45/AI45-1 -> 0.27917027 | AO46: =+AO45/AJ45-1 -> 0.23914643 | AP46: =+AP45/AK45-1 -> 0.18829859 | AQ46: =+AQ45/AL45-1 -> 0.25075415 | AR46: =+AR45/AM45-1 -> 0.13446858 | AS46: =+AS45/AN45-1 -> 0.17635135 | AT46: =+AT45/AO45-1 -> 0.22149644 | ... CS46: =+CS45/CN45-1 -> -0.070018365 | CT46: =CT45/CO45-1 -> -0.056593728 | CU46: =+CU45/CP45-1 -> -0.082410279
A47: =IF(ISBLANK(B47),"Scrap", " ") | B47: % chg., FX neutral | R47: -- | S47: -- | T47: -- | U47: -- | V47: -- | W47: -- | X47: -- | Y47: -- | Z47: -- | AA47: -- | AC47: -- | AD47: -- | AE47: -- | AF47: -- | AG47: -- | AH47: -- | AI47: -- | AJ47: -- | AK47: -- | AL47: -- | AM47: -- | AN47: -- | AO47: -- | AP47: -- | AQ47: 0.29 | AR47: 0.21 | AS47: 0.26 | AT47: 0.29 | AU47: 0.25 | AV47: 0.25 | AW47: 0.22 | AX47: 0.25 | AY47: 0.13 | AZ47: 0.12343206 | BA47: 0.18 | BB47: 0.11 | BC47: 0.15 | BD47: 0.1 | BE47: =(1+BE46)/(1+BE48)-1 -> 0.12221015 | BF47: 0.12 | BG47: 0.12 | BH47: 0.18 | BI47: 0.17 | BJ47: =(1+BJ46)/(1+BJ48)-1 -> 0.17074139 | BK47: 0.16 | BL47: 0.17 | BM47: 0.17 | BN47: 0.13 | BO47: =(1+BO46)/(1+BO48)-1 -> -0.13625237 | BP47: 0.08 | BQ47: 0.13 | BR47: 0.3 | BS47: 0.16 | BT47: =(1+BT46)/(1+BT48)-1 -> 0.6888487 | BU47: 0.3 | BV47: 0.25 | BW47: 0.08 | BX47: 0.17 | BY47: =(1+BY46)/(1+BY48)-1 -> 0.1153138 | BZ47: 0.15 | CA47: 0.14 | CB47: 0.25 | CC47: 0.22 | CD47: 0.18 | CE47: 0.2 | CF47: 0.06 | CG47: 0.04 | CH47: 0 | CI47: -0.07 | CJ47: 0.01 | CK47: -0.12 | CL47: -0.14 | CM47: -0.1 | CN47: -0.14 | CO47: -0.12 | CP47: -0.05 | CQ47: -0.09 | CR47: -0.07 | CS47: -0.09 | CT47: -0.08 | CU47: -0.09
A48: =IF(ISBLANK(B48),"Scrap", " ") | B48: % FX impact | R48: -- | S48: -- | T48: -- | U48: -- | V48: -- | W48: -- | X48: -- | Y48: -- | Z48: -- | AA48: -- | AC48: -- | AD48: -- | AE48: -- | AF48: -- | AG48: -- | AH48: -- | AI48: -- | AJ48: -- | AK48: -- | AL48: -- | AM48: -- | AN48: -- | AO48: -- | AP48: -- | AQ48: =(1+AQ46)/(1+AQ47)-1 -> -0.030423141 | AR48: =(1+AR46)/(1+AR47)-1 -> -0.062422657 | AS48: =(1+AS46)/(1+AS47)-1 -> -0.066387816 | AT48: =(1+AT46)/(1+AT47)-1 -> -0.053103537 | AU48: =(1+AU46)/(1+AU47)-1 -> -0.037011885 | AV48: =(1+AV46)/(1+AV47)-1 -> -0.052517335 | AW48: =(1+AW46)/(1+AW47)-1 -> -0.022078539 | AX48: =(1+AX46)/(1+AX47)-1 -> -0.01481907 | ... BD48: =(1+BD46)/(1+BD47)-1 -> 0.038336117 | BE48: =((BF48*SUM(AW45:AZ45))-BB48*AW45-BC48*AX45-BD48*AY45)/AZ45 -> 0.062332398 | BF48: =(1+BF46)/(1+BF47)-1 -> 0.025183251 | BG48: =(1+BG46)/(1+BG47)-1 -> 0.0041561003 | BH48: =(1+BH46)/(1+BH47)-1 -> -0.034157592 | BI48: =(1+BI46)/(1+BI47)-1 -> -0.029091254 | BJ48: =((BK48*SUM(BB45:BE45))-BG48*BB45-BH48*BC45-BI48*BD45)/BE45 -> -0.052120958 | BK48: =(1+BK46)/(1+BK47)-1 -> -0.028395037 | BL48: =(1+BL46)/(1+BL47)-1 -> -0.026282576 | BM48: =(1+BM46)/(1+BM47)-1 -> -0.016988349 | BN48: =(1+BN46)/(1+BN47)-1 -> -0.016284857 | BO48: =((BP48*SUM(BG45:BJ45))-BL48*BG45-BM48*BH45-BN48*BI45)/BJ45 -> -0.037635639 | BP48: =(1+BP46)/(1+BP47)-1 -> -0.024520138 | BQ48: =(1+BQ46)/(1+BQ47)-1 -> -0.0055146257 | BR48: =(1+BR46)/(1+BR47)-1 -> 0.018238518 | BS48: =(1+BS46)/(1+BS47)-1 -> 0.033593758 | BT48: =((BU48*SUM(BL45:BO45))-BQ48*BL45-BR48*BM45-BS48*BN45)/BO45 -> 0.022501341 | BU48: =(1+BU46)/(1+BU47)-1 -> 0.016984953 | BV48: =(1+BV46)/(1+BV47)-1 -> 0.027945205 | BW48: =(1+BW46)/(1+BW47)-1 -> 0.0077769184 | BX48: =(1+BX46)/(1+BX47)-1 -> -0.01535348 | BY48: =((BZ48*SUM(BQ45:BT45))-BV48*BQ45-BW48*BR45-BX48*BS45)/BT45 -> -0.036201021 | BZ48: =(1+BZ46)/(1+BZ47)-1 -> -0.0052853842 | CA48: =(1+CA46)/(1+CA47)-1 -> -0.055287472 | CB48: =(1+CB46)/(1+CB47)-1 -> -0.075847367 | CC48: =(1+CC46)/(1+CC47)-1 -> -0.040476036 | CD48: =(1+CD46)/(1+CD47)-1 -> -0.025892475 | CE48: =(1+CE46)/(1+CE47)-1 -> -0.051764036 | CF48: =(1+CF46)/(1+CF47)-1 -> 0.000549116 | CG48: =(1+CG46)/(1+CG47)-1 -> 0.018851051 | ... CU48: =(1+CU46)/(1+CU47)-1 -> 0.0083403526
A49: =IF(ISBLANK(B49),"Scrap", " ") | B49: Direct % of total NKE Brand | AH49: =AH45/AH14 -> 0.20114409 | AI49: =AI45/AI14 -> 0.19060956 | AJ49: =AJ45/AJ14 -> 0.20735429 | AK49: =AK45/AK14 -> 0.21182336 | AL49: =AL45/AL14 -> 0.203125 | AM49: =AM45/AM14 -> 0.2294839 | AN49: =AN45/AN14 -> 0.21267423 | AO49: =AO45/AO14 -> 0.24268627 | ... CU49: =CU45/CU14 -> 0.37819576
A51: =IF(ISBLANK(B51),"Scrap", " ") | B51: Wholesale sales | R51: -- | S51: -- | T51: -- | U51: -- | V51: -- | W51: -- | X51: -- | Y51: -- | Z51: -- | AA51: -- | AC51: -- | AD51: -- | AE51: -- | AF51: -- | AG51: -- | AH51: 5135 | AI51: 4882 | AJ51: 5169 | AK51: 5497 | AL51: =SUM(AH51:AK51) -> 20683 | AM51: 5689 | AN51: 5451 | AO51: 5227 | AP51: =21952-AO51-AN51-AM51 -> 5585 | AQ51: =SUM(AM51:AP51) -> 21952 | AR51: 5940 | AS51: 5558 | AT51: 5493 | AU51: 5586 | AV51: =SUM(AR51:AU51) -> 22577 | AW51: 6139 | AX51: 5559 | AY51: 5618 | AZ51: 5762 | BA51: =SUM(AW51:AZ51) -> 23078 | BB51: 6030 | BC51: 5629 | BD51: 5863 | BE51: =BF51-SUM(BB51:BD51) -> 6447 | BF51: 23969 | BG51: 6550 | BH51: 6106 | BI51: 6174 | BJ51: =BK51-SUM(BG51:BI51) -> 6593 | BK51: 25423 | BL51: 6842 | BM51: 6578 | BN51: 6311 | BO51: =23156-BN51-BM51-BL51 -> 3425 | BP51: =SUM(BL51:BO51) -> 23156 | BQ51: 6364 | BR51: 6423 | BS51: 5814 | BT51: =25898-BS51-BR51-BQ51 -> 7297 | BU51: =SUM(BQ51:BT51) -> 25898 | BV51: 6943 | BW51: 6119 | BX51: 5728 | BY51: =25608-BX51-BW51-BV51 -> 6818 | BZ51: =SUM(BV51:BY51) -> 25608 | CA51: 6983 | CB51: 7287 | CC51: 6423 | CD51: =27397-CA51-CB51-CC51 -> 6704 | CE51: =SUM(CA51:CD51) -> 27397 | CF51: 6983 | CG51: 7118 | CH51: 6588 | CI51: =27758-CH51-CG51-CF51 -> 7069 | CJ51: =SUM(CF51:CI51) -> 27758 | CK51: 6410 | CL51: 6920 | CM51: 6155 | CN51: =25883-CK51-CL51-CM51 -> 6398 | CO51: =SUM(CK51:CN51) -> 25883 | CP51: 6839 | CQ51: 7499 | CR51: 6466 | CS51: =27453-CR51-CQ51-CP51 -> 6649 | CT51: =CP51+CQ51+CR51+CS51 -> 27453 | CU51: 6804
A52: =IF(ISBLANK(B52),"Scrap", " ") | B52: % chg. Y/Y | R52: -- | S52: -- | T52: -- | U52: -- | V52: -- | W52: -- | X52: -- | Y52: -- | Z52: -- | AA52: -- | AC52: -- | AD52: -- | AE52: -- | AF52: -- | AG52: -- | AH52: -- | AI52: -- | AJ52: -- | AK52: -- | AL52: -- | AM52: =+AM51/AH51-1 -> 0.10788705 | AN52: =+AN51/AI51-1 -> 0.11655059 | AO52: =+AO51/AJ51-1 -> 0.011220739 | AP52: =+AP51/AK51-1 -> 0.016008732 | AQ52: =+AQ51/AL51-1 -> 0.061354736 | AR52: =+AR51/AM51-1 -> 0.044120232 | AS52: =+AS51/AN51-1 -> 0.019629426 | AT52: =+AT51/AO51-1 -> 0.050889612 | ... CS52: =+CS51/CN51-1 -> 0.03923101 | CT52: =CT51/CO51-1 -> 0.060657574 | CU52: =+CU51/CP51-1 -> -0.0051177073
A53: =IF(ISBLANK(B53),"Scrap", " ") | B53: % chg., FX neutral | R53: -- | S53: -- | T53: -- | U53: -- | V53: -- | W53: -- | X53: -- | Y53: -- | Z53: -- | AA53: -- | AC53: -- | AD53: -- | AE53: -- | AF53: -- | AG53: -- | AH53: -- | AI53: -- | AJ53: -- | AK53: -- | AL53: -- | AM53: -- | AN53: -- | AO53: -- | AP53: -- | AQ53: 0.1 | AR53: 0.13 | AS53: 0.09 | AT53: 0.11 | AU53: 0.09 | AV53: 0.09 | AW53: 0.06 | AX53: 0.02 | AY53: 0.05 | AZ53: 0.05150734 | BA53: 0.05 | BB53: -0.01 | BC53: 0 | BD53: 0.01 | BE53: =(1+BE52)/(1+BE54)-1 -> 0.079147525 | BF53: 0.02 | BG53: 0.09 | BH53: 0.13 | BI53: 0.1 | BJ53: =(1+BJ52)/(1+BJ54)-1 -> 0.083238887 | BK53: 0.1 | BL53: 0.08 | BM53: 0.1 | BN53: 0.04 | BO53: =(1+BO52)/(1+BO54)-1 -> -0.47432805 | BP53: -0.07 | BQ53: -0.06 | BR53: -0.04 | BS53: -0.11 | BT53: =(1+BT52)/(1+BT54)-1 -> 1.0553689 | BU53: 0.1 | BV53: 0.05 | BW53: -0.06 | BX53: 0.01 | BY53: =(1+BY52)/(1+BY54)-1 -> -0.036110392 | BZ53: -0.01 | CA53: 0.08 | CB53: 0.3 | CC53: 0.18 | CD53: 0.02 | CE53: 0.14 | CF53: 0.01 | CG53: -0.03 | CH53: 0.03 | CI53: 0.08 | CJ53: 0.02 | CK53: -0.07 | CL53: -0.04 | CM53: -0.04 | CN53: -0.09 | CO53: -0.06 | CP53: 0.05 | CQ53: 0.08 | CR53: 0.01 | CS53: 0.01 | CT53: 0.04 | CU53: -0.01
